Workbook
Name RiskAutoStopPercChange: 1.5
Name RiskCollectDistributionSamples: 2
Name RiskExcelReportsGoInNewWorkbook: TRUE
Name RiskExcelReportsToGenerate: 0
Name RiskFixedSeed: 1
Name RiskGenerateExcelReportsAtEndOfSimulation: FALSE
Name RiskHasSettings: TRUE
Name RiskMinimizeOnStart: FALSE
Name RiskMonitorConvergence: FALSE
Name RiskNumIterations: 1000
Name RiskNumSimulations: 1
Name RiskPauseOnError: FALSE
Name RiskRealTimeResults: FALSE
Name RiskReportGraphFormat: 0
Name RiskResultsUpdateFreq: 100
Name RiskRunAfterRecalcMacro: FALSE
Name RiskRunAfterSimMacro: FALSE
Name RiskRunBeforeRecalcMacro: FALSE
Name RiskRunBeforeSimMacro: FALSE
Name RiskSamplingType: 3
Name RiskShowRiskWindowAtEndOfSimulation: TRUE
Name RiskStandardRecalc: 1
Name RiskTemplateSheetName: "myTemplate"
Name RiskUpdateDisplay: FALSE
Name RiskUseDifferentSeedForEachSim: FALSE
Name RiskUseFixedSeed: FALSE
Name RiskUseMultipleCPUs: FALSE

Sheet __FDSCACHE__
B1: This sheet contains FactSet XML data for use with this workbook's =FDS codes. Modifying the worksheet's contents may damage the workbook's =FDS functionality.

Sheet JEF DISCLAIMER
B1: This material was prepared by personnel who are associated with Jefferies (Jefferies International Limited, Jefferies Hong Kong Limited, Jefferies Singapore Limited, Jefferies (Japan) Limited, Tokyo Branch, Jefferies India Private Limited, Jefferies (Australia) Pty Ltd); or by personnel who are associated with both Jefferies LLC and Jefferies Research Services LLC (“JRS”). Jefferies LLC is a US registered broker-dealer and is affiliated with JRS, which is a US registered investment adviser. JRS does not create tailored or personalized research and all research provided by JRS is impersonal. If you are paying separately for this research, it is being provided to you by JRS. Otherwise, it is being provided by Jefferies LLC. Jefferies LLC, JRS, and their affiliates are collectively referred to below as “Jefferies”. The information upon which this material is based was obtained from sources believed to be reliable, but has not been independently verified, therefore, we do not guarantee its accuracy. Additional and supporting information is available upon request. This is not an offer or solicitation of an offer to buy or sell any security or investment. Any opinion or estimates constitute our best judgment as of this date, and are subject to change without notice. Members of Jefferies and their respective directors, officers and employees may buy or sell securities mentioned herein as agent or principal for their own account. Upon request members of Jefferies may provide specialized research products or services to certain customers focusing on the prospects for individual covered stocks as compared to other covered stocks over varying time horizons or under differing market conditions. While the views expressed in these situations may not always be directionally consistent with the long-term views expressed in the analyst's published research, the analyst has a reasonable basis and any inconsistencies can be reasonably explained. In Australia, this report may contain general advice. Where this report refers to a particular financial product, you should obtain a copy of the relevant product disclosure statement or offer document before making any decision in relation to the product. This report may contain forward looking statements that may be affected by inaccurate assumptions or by known or unknown risks, uncertainties and other important factors. As a result, the actual results, events, performance or achievements of the financial product may be materially different from those expressed or implied in such statements. Past performance is not indicative of future performance. This report/model may contain information obtained from third parties, including ratings from credit ratings agencies such as Standard & Poor’s. Reproduction and distribution of third party content in any form is prohibited except with the prior written permission of the applicable third party. Third party content providers do not guarantee the accuracy, completeness, timeliness or availability of any information, including ratings, and are not responsible for any errors or omissions (negligent or otherwise), regardless of the cause, or for the results obtained from the use of such content. Third party content providers do not provide any express or implied warranties, including, but not limited to, any warranties of merchantability or fitness for a particular purpose or use. Third party content providers are not liable for any direct, indirect, incidental, exemplary, compensatory, punitive, special or consequential damages, costs, expenses, legal fees, or losses (including lost income or profits and opportunity costs) in connection with any use of their content, including ratings. Credit ratings are statements of opinions and are not statements of fact or recommendations to purchase, hold or sell securities. Such credit ratings do not address the suitability of securities or the suitability of securities for investment purposes, and should not be relied on as investment advice. This report/model or any portion hereof may not be reprinted, sold or redistributed without the written consent of Jefferies or its affiliates. Neither Jefferies or its affiliates nor any officer nor employee of Jefferies or its affiliates accepts any liability whatsoever for any direct, indirect or consequential damages or losses of any kind arising from any use of this report/model or its contents. For Important Disclosure information, please visit our website at https://javatar.bluematrix.com/sellside/Disclosures.action or call 1.888.JEFFERIES.

Sheet IS
A3: Valvoline Inc. (VVV)
A4: FYE: Sept.
A5: Earnings Model
A6: ($M's, except per share)
B7: 1Q16 | C7: 2Q16 | D7: 3Q16 | E7: 4Q16 | F7: FY16 | G7: 1Q17 | H7: 2Q17 | I7: 3Q17 | J7: 4Q17 | K7: FY17 | L7: 1Q18 | M7: 2Q18 | N7: 3Q18 | O7: 4Q18 | P7: FY18 | Q7: 1Q19 | R7: 2Q19 | S7: 3Q19 | T7: 4Q19 | U7: FY19 | V7: 1Q20 | W7: 2Q20 | X7: 3Q20 | Y7: 4Q20 | Z7: FY20 | AA7: 1Q21 | AB7: 2Q21 | AC7: 3Q21 | AD7: 4Q21 | AE7: FY21 | AF7: 1Q22 | AG7: 2Q22 | AH7: 3Q22 | AI7: 4Q22 | AJ7: FY22 | AK7: 1Q23 | AL7: 2Q23 | AM7: 3Q23 | AN7: 4Q23 | AO7: FY23 | AP7: 1Q24 | AQ7: 2Q24 | AR7: 3Q24 | AS7: 4Q24 | AT7: FY24 | AU7: 1Q25 | AV7: 2Q25 | AW7: 3Q25 | AX7: 4Q25 | AY7: FY25 | AZ7: 1Q26 | BA7: 2Q26E | BB7: 3Q26E | BC7: 4Q26E | BD7: FY26E | BE7: 1Q27E | BF7: 2Q27E | BG7: 3Q27E | BH7: 4Q27E | BI7: FY27E
A9: Global Products
A11: Sales Analysis: | B11: =SUM(B12:B13) -> 356 | C11: =SUM(C12:C13) -> 367 | D11: =SUM(D12:D13) -> 380 | E11: =SUM(E12:E13) -> 369 | F11: =SUM(B11:E11) -> 1472 | G11: =SUM(G12:G13) -> 362 | H11: =SUM(H12:H13) -> 386 | I11: =SUM(I12:I13) -> 395 | J11: =SUM(J12:J13) -> 400 | K11: =SUM(G11:J11) -> 1543 | L11: =SUM(L12:L13) -> 391 | M11: =SUM(M12:M13) -> 411 | N11: =SUM(N12:N13) -> 410 | O11: =SUM(O12:O13) -> 413 | P11: =SUM(L11:O11) -> 1625 | Q11: =SUM(Q12:Q13) -> 368 | R11: =SUM(R12:R13) -> 391 | S11: =SUM(S12:S13) -> 402 | T11: =SUM(T12:T13) -> 407 | U11: =SUM(Q11:T11) -> 1568 | V11: =SUM(V12:V13) -> 389 | W11: =SUM(W12:W13) -> 366 | X11: =SUM(X12:X13) -> 317 | Y11: =SUM(Y12:Y13) -> 398 | Z11: =SUM(V11:Y11) -> 1470 | AA11: =SUM(AA12:AA13) -> 399 | AB11: =SUM(AB12:AB13) -> 416 | AC11: 462 | AD11: 483 | AE11: =SUM(AA11:AD11) -> 1760 | AF11: 512 | AG11: 536 | AH11: 573 | AJ11: =SUM(AF11:AI11) -> 1621
A12: Core NA | B12: 241 | C12: 248 | D12: 251 | E12: 239 | F12: =SUM(B12:E12) -> 979 | G12: 237 | H12: 253 | I12: 258 | J12: 256 | K12: =SUM(G12:J12) -> 1004 | L12: 251 | M12: 258 | N12: 264 | O12: 262 | P12: =SUM(L12:O12) -> 1035 | Q12: 232 | R12: 243 | S12: 260 | T12: 259 | U12: =SUM(Q12:T12) -> 994 | V12: 248 | W12: 238 | X12: 207 | Y12: 252 | Z12: =SUM(V12:Y12) -> 945 | AA12: 235 | AB12: 242 | AE12: =SUM(AA12:AD12) -> 477
A13: International | B13: 115 | C13: 119 | D13: 129 | E13: 130 | F13: =SUM(B13:E13) -> 493 | G13: 125 | H13: 133 | I13: 137 | J13: 144 | K13: =SUM(G13:J13) -> 539 | L13: 140 | M13: 153 | N13: 146 | O13: 151 | P13: =SUM(L13:O13) -> 590 | Q13: 136 | R13: 148 | S13: 142 | T13: 148 | U13: =SUM(Q13:T13) -> 574 | V13: 141 | W13: 128 | X13: 110 | Y13: 146 | Z13: =SUM(V13:Y13) -> 525 | AA13: 164 | AB13: 174 | AE13: =SUM(AA13:AD13) -> 338
A15: Y/Y % growth
A16: Core NA | G16: =G12/B12-1 -> -0.01659751 | H16: =H12/C12-1 -> 0.02016129 | I16: =I12/D12-1 -> 0.027888446 | J16: =J12/E12-1 -> 0.071129707 | K16: =K12/F12-1 -> 0.025536261 | L16: =L12/G12-1 -> 0.05907173 | M16: =M12/H12-1 -> 0.019762846 | N16: =N12/I12-1 -> 0.023255814 | ... AB16: =AB12/W12-1 -> 0.016806723
A17: International | G17: =G13/B13-1 -> 0.086956522 | H17: =H13/C13-1 -> 0.11764706 | I17: =I13/D13-1 -> 0.062015504 | J17: =J13/E13-1 -> 0.10769231 | K17: =K13/F13-1 -> 0.093306288 | L17: =L13/G13-1 -> 0.12 | M17: =M13/H13-1 -> 0.15037594 | N17: =N13/I13-1 -> 0.065693431 | ... AB17: =AB13/W13-1 -> 0.359375
A18: Global Products Total | G18: =G11/B11-1 -> 0.016853933 | H18: =H11/C11-1 -> 0.051771117 | I18: =I11/D11-1 -> 0.039473684 | J18: =J11/E11-1 -> 0.08401084 | K18: =K11/F11-1 -> 0.048233696 | L18: =L11/G11-1 -> 0.080110497 | M18: =M11/H11-1 -> 0.064766839 | N18: =N11/I11-1 -> 0.037974684 | ... AH18: =AH11/AC11-1 -> 0.24025974 | AJ18: =AJ11/AE11-1 -> -0.078977273
A20: Operating Margin Analysis: | E20: =SUM(E21:E22) -> 63 | F20: =SUM(F21:F22) -> 286 | G20: =SUM(G21:G22) -> 71 | H20: =SUM(H21:H22) -> 75 | I20: =SUM(I21:I22) -> 66 | J20: =SUM(J21:J22) -> 63 | K20: =SUM(G20:J20) -> 275 | L20: =SUM(L21:L22) -> 62 | M20: =SUM(M21:M22) -> 70 | N20: =SUM(N21:N22) -> 61 | O20: =SUM(O21:O22) -> 63 | P20: =SUM(L20:O20) -> 256 | Q20: =SUM(Q21:Q22) -> 49 | R20: =SUM(R21:R22) -> 63 | S20: =SUM(S21:S22) -> 58 | T20: =SUM(T21:T22) -> 67 | U20: =SUM(Q20:T20) -> 237 | V20: =SUM(V21:V22) -> 66 | W20: =SUM(W21:W22) -> 65 | X20: =SUM(X21:X22) -> 63 | Y20: =SUM(Y21:Y22) -> 81 | Z20: =SUM(V20:Y20) -> 275 | AA20: =SUM(AA21:AA22) -> 81 | AB20: =SUM(AB21:AB22) -> 66 | AC20: 72 | AD20: 65 | AE20: =SUM(AA20:AD20) -> 284 | AF20: 70 | AG20: 74 | AH20: 80
A21: Core NA | E21: 42 | F21: 212 | G21: 51 | H21: 57 | I21: 48 | J21: 43 | K21: =SUM(G21:J21) -> 199 | L21: 43 | M21: 46 | N21: 41 | O21: 42 | P21: =SUM(L21:O21) -> 172 | Q21: 31 | R21: 40 | S21: 38 | T21: 43 | U21: =SUM(Q21:T21) -> 152 | V21: 46 | W21: 47 | X21: 51 | Y21: 58 | Z21: =SUM(V21:Y21) -> 202 | AA21: 47 | AB21: 38
A22: International | E22: 21 | F22: 74 | G22: 20 | H22: 18 | I22: 18 | J22: 20 | K22: =SUM(G22:J22) -> 76 | L22: 19 | M22: 24 | N22: 20 | O22: 21 | P22: =SUM(L22:O22) -> 84 | Q22: 18 | R22: 23 | S22: 20 | T22: 24 | U22: =SUM(Q22:T22) -> 85 | V22: 20 | W22: 18 | X22: 12 | Y22: 23 | Z22: =SUM(V22:Y22) -> 73 | AA22: 34 | AB22: 28
A24: Operating Margin % | E24: =E20/E11 -> 0.17073171 | F24: =F20/F11 -> 0.19429348 | G24: =G20/G11 -> 0.1961326 | H24: =H20/H11 -> 0.19430052 | I24: =I20/I11 -> 0.16708861 | J24: =J20/J11 -> 0.1575 | K24: =K20/K11 -> 0.17822424 | L24: =L20/L11 -> 0.15856777 | ... AH24: =AH20/AH11 -> 0.13961606 | AJ24: =AJ20/AJ11 -> 0
A26: Depreciation and Amortization | E26: =4+5 -> 9 | F26: 21 | G26: 4 | H26: 4 | I26: 6 | J26: 6 | K26: =SUM(G26:J26) -> 20 | L26: 5 | M26: 6 | N26: 7 | O26: 6 | P26: =SUM(L26:O26) -> 24 | Q26: 6 | R26: 5 | S26: 6 | T26: 8 | U26: =SUM(Q26:T26) -> 25 | V26: 6 | W26: 5 | X26: 6 | Y26: 6 | Z26: =SUM(V26:Y26) -> 23 | AA26: 6 | AB26: 7 | AC26: 9 | AD26: 7 | AF26: 7 | AG26: 7 | AH26: 7
A27: Other Ajustments | E27: 0 | F27: 0 | G27: 0 | H27: 0 | I27: 0 | J27: 0 | K27: =SUM(G27:J27) -> 0 | L27: 0 | M27: 0 | N27: 0 | O27: 0 | P27: =SUM(L27:O27) -> 0 | Q27: 0 | R27: 0 | S27: 0 | T27: 0 | U27: =SUM(Q27:T27) -> 0 | V27: 0 | W27: 0 | X27: 0 | Y27: 0 | Z27: =SUM(V27:Y27) -> 0 | AA27: 0 | AB27: 0 | AC27: 0 | AD27: 0 | AF27: 0 | AG27: 0 | AH27: 0
A29: EBITDA Analysis:
A30: EBITDA | E30: =E20+SUM(E26:E27) -> 72 | F30: =F20+SUM(F26:F27) -> 307 | G30: =G20+SUM(G26:G27) -> 75 | H30: =H20+SUM(H26:H27) -> 79 | I30: =I20+SUM(I26:I27) -> 72 | J30: =J20+SUM(J26:J27) -> 69 | K30: =SUM(G30:J30) -> 295 | L30: =L20+SUM(L26:L27) -> 67 | M30: =M20+SUM(M26:M27) -> 76 | N30: =N20+SUM(N26:N27) -> 68 | O30: =O20+SUM(O26:O27) -> 69 | P30: =SUM(L30:O30) -> 280 | Q30: =Q20+SUM(Q26:Q27) -> 55 | R30: =R20+SUM(R26:R27) -> 68 | S30: =S20+SUM(S26:S27) -> 64 | T30: =T20+SUM(T26:T27) -> 75 | U30: =SUM(Q30:T30) -> 262 | V30: =V20+SUM(V26:V27) -> 72 | W30: =W20+SUM(W26:W27) -> 70 | X30: =X20+SUM(X26:X27) -> 69 | Y30: =Y20+SUM(Y26:Y27) -> 87 | Z30: =SUM(V30:Y30) -> 298 | AA30: =AA20+SUM(AA26:AA27) -> 87 | AB30: =AB20+SUM(AB26:AB27) -> 73 | AC30: =AC20+SUM(AC26:AC27) -> 81 | AD30: =AD20+SUM(AD26:AD27) -> 72 | AE30: =SUM(AA30:AD30) -> 313 | AF30: =AF20+SUM(AF26:AF27) -> 77 | AG30: =AG20+SUM(AG26:AG27) -> 81 | AH30: =AH20+SUM(AH26:AH27) -> 87 | AJ30: =SUM(AF30:AI30) -> 245
A31: EBITDA Margin | E31: =E30/E11 -> 0.19512195 | F31: =F30/F11 -> 0.20855978 | G31: =G30/G11 -> 0.20718232 | H31: =H30/H11 -> 0.20466321 | I31: =I30/I11 -> 0.18227848 | J31: =J30/J11 -> 0.1725 | K31: =K30/K11 -> 0.191186 | L31: =L30/L11 -> 0.1713555 | ... AH31: =AH30/AH11 -> 0.15183246 | AJ31: =AJ30/AJ11 -> 0.15114127
A35: Retail Services
A37: Retail Stores
A38: Company Operated
A39: Opened | C39: 1 | D39: 0 | E39: 2 | F39: =SUM(B39:E39) -> 3 | G39: 0 | H39: 0 | I39: 1 | J39: 2 | K39: =SUM(G39:J39) -> 3 | L39: 2 | M39: 0 | N39: 4 | O39: 11 | P39: =SUM(L39:O39) -> 17 | Q39: 5 | R39: 7 | S39: 4 | T39: 12 | U39: =SUM(Q39:T39) -> 28 | V39: 2 | W39: 7 | X39: 5 | Y39: 22 | Z39: =SUM(V39:Y39) -> 36 | AA39: 18 | AB39: 11 | AC39: 17 | AD39: 21 | AE39: =SUM(AA39:AD39) -> 67 | AF39: 7 | AG39: 10 | AH39: 5 | AI39: 12 | AJ39: =SUM(AF39:AI39) -> 34 | AK39: 17 | AL39: 13 | AM39: 12 | AN39: 14 | AO39: =SUM(AK39:AN39) -> 56 | AP39: 14 | AQ39: 14 | AR39: 12 | AS39: 26 | AT39: =SUM(AP39:AS39) -> 66 | AU39: 15 | AV39: 12 | AW39: 19 | AX39: 26 | AY39: =SUM(AU39:AX39) -> 72 | AZ39: 26 | BA39: 23 | BB39: 23 | BC39: 28 | BD39: =SUM(AZ39:BC39) -> 100 | BE39: 20 | BF39: 20 | BG39: 23 | BH39: 28 | BI39: =SUM(BE39:BH39) -> 91
A40: Acquired | C40: 47 | D40: 1 | E40: 0 | F40: =SUM(B40:E40) -> 48 | G40: 0 | H40: 28 | I40: 0 | J40: 1 | K40: =SUM(G40:J40) -> 29 | L40: 0 | M40: 2 | N40: 1 | O40: 0 | P40: =SUM(L40:O40) -> 3 | Q40: 0 | R40: 5 | S40: 13 | T40: 6 | U40: =SUM(Q40:T40) -> 24 | V40: 7 | W40: 1 | X40: 2 | Y40: 2 | Z40: =SUM(V40:Y40) -> 12 | AA40: 54 | AB40: 0 | AC40: 5 | AD40: 3 | AE40: =SUM(AA40:AD40) -> 62 | AF40: 12 | AG40: 9 | AH40: 9 | AI40: 3 | AJ40: =SUM(AF40:AI40) -> 33 | AK40: 5 | AL40: 6 | AM40: 8 | AN40: 8 | AO40: =SUM(AK40:AN40) -> 27 | AP40: 5 | AQ40: 10 | AR40: 6 | AS40: 10 | AT40: =SUM(AP40:AS40) -> 31 | AU40: 6 | AV40: 6 | AW40: 8 | AX40: 8 | AY40: =SUM(AU40:AX40) -> 28 | AZ40: 210 | BA40: 0 | BB40: 0 | BC40: 0 | BD40: =SUM(AZ40:BC40) -> 210 | BE40: 0 | BF40: 0 | BG40: 0 | BH40: 0 | BI40: =SUM(BE40:BH40) -> 0
A41: Net Conversions | C41: 1 | D41: 1 | E41: 7 | F41: =SUM(B41:E41) -> 9 | G41: 5 | H41: 0 | I41: 9 | J41: 0 | K41: =SUM(G41:J41) -> 14 | L41: 56 | M41: 1 | N41: 1 | O41: 0 | P41: =SUM(L41:O41) -> 58 | Q41: 4 | R41: 0 | S41: 1 | T41: 0 | U41: =SUM(Q41:T41) -> 5 | V41: -4 | W41: 4 | X41: 5 | Y41: 12 | Z41: =SUM(V41:Y41) -> 17 | AA41: 7 | AB41: 0 | AC41: 3 | AD41: 0 | AE41: =SUM(AA41:AD41) -> 10 | AF41: 0 | AG41: 0 | AH41: 1 | AI41: 3 | AJ41: =SUM(AF41:AI41) -> 4 | AK41: 2 | AL41: 0 | AM41: 2 | AN41: 0 | AO41: =SUM(AK41:AN41) -> 4 | AP41: 0 | AQ41: 0 | AR41: 0 | AS41: -23 | AT41: =SUM(AP41:AS41) -> -23 | AU41: -39 | AV41: 0 | AW41: 6 | AX41: 0 | AY41: =SUM(AU41:AX41) -> -33 | AZ41: -10 | BA41: 0 | BB41: 0 | BC41: 0 | BD41: =SUM(AZ41:BC41) -> -10 | BE41: 0 | BF41: 0 | BG41: 0 | BH41: 0 | BI41: =SUM(BE41:BH41) -> 0
A42: Closed | C42: 0 | D42: 0 | E42: 0 | F42: =SUM(B42:E42) -> 0 | G42: 0 | H42: -1 | I42: -1 | J42: -2 | K42: =SUM(G42:J42) -> -4 | L42: 0 | M42: 0 | N42: 0 | O42: 0 | P42: =SUM(L42:O42) -> 0 | Q42: 0 | R42: 0 | S42: 0 | T42: 0 | U42: =SUM(Q42:T42) -> 0 | V42: 0 | W42: 0 | X42: 0 | Y42: 0 | Z42: =SUM(V42:Y42) -> 0 | AA42: 0 | AB42: -1 | AC42: 0 | AD42: -3 | AE42: =SUM(AA42:AD42) -> -4 | AF42: 0 | AG42: 0 | AH42: 0 | AI42: 0 | AJ42: =SUM(AF42:AI42) -> 0 | AK42: -1 | AL42: 0 | AM42: 0 | AN42: 0 | AO42: =SUM(AK42:AN42) -> -1 | AP42: 0 | AQ42: 0 | AR42: 0 | AS42: 0 | AT42: =SUM(AP42:AS42) -> 0 | AU42: 0 | AV42: 0 | AW42: 0 | AX42: -1 | AY42: =SUM(AU42:AX42) -> -1 | AZ42: =-45-1 -> -46 | BA42: 0 | BB42: 0 | BC42: 0 | BD42: =SUM(AZ42:BC42) -> -46 | BE42: 0 | BF42: 0 | BG42: 0 | BH42: 0 | BI42: =SUM(BE42:BH42) -> 0
A43: End of Period | B43: 282 | C43: =B43+SUM(C39:C42) -> 331 | D43: =C43+SUM(D39:D42) -> 333 | E43: =D43+SUM(E39:E42) -> 342 | F43: =E43 -> 342 | G43: =F43+SUM(G39:G42) -> 347 | H43: =G43+SUM(H39:H42) -> 374 | I43: =H43+SUM(I39:I42) -> 383 | J43: =I43+SUM(J39:J42) -> 384 | K43: =J43 -> 384 | L43: =K43+SUM(L39:L42) -> 442 | M43: =L43+SUM(M39:M42) -> 445 | N43: =M43+SUM(N39:N42) -> 451 | O43: =N43+SUM(O39:O42) -> 462 | P43: =O43 -> 462 | Q43: =P43+SUM(Q39:Q42) -> 471 | R43: =Q43+SUM(R39:R42) -> 483 | S43: =R43+SUM(S39:S42) -> 501 | T43: =S43+SUM(T39:T42) -> 519 | U43: =T43 -> 519 | V43: =U43+SUM(V39:V42) -> 524 | W43: =V43+SUM(W39:W42) -> 536 | X43: =W43+SUM(X39:X42) -> 548 | Y43: =X43+SUM(Y39:Y42) -> 584 | Z43: =Y43 -> 584 | AA43: =Z43+SUM(AA39:AA42) -> 663 | AB43: =AA43+SUM(AB39:AB42) -> 673 | AC43: =AB43+SUM(AC39:AC42) -> 698 | AD43: =AC43+SUM(AD39:AD42) -> 719 | AE43: =AD43 -> 719 | AF43: 738 | AG43: =AF43+AG39+AG40+AG41+AG42 -> 757 | AH43: =AG43+AH39+AH40+AH41+AH42 -> 772 | AI43: =AH43+AI39+AI40+AI41+AI42 -> 790 | AJ43: =AI43 -> 790 | AK43: =AJ43+AK39+AK40+AK41+AK42 -> 813 | AL43: =AK43+AL39+AL40+AL41+AL42 -> 832 | AM43: =AL43+AM39+AM40+AM41+AM42 -> 854 | AN43: =AM43+AN39+AN40+AN41+AN42 -> 876 | AO43: =AN43 -> 876 | AP43: =AO43+AP39+AP40+AP41+AP42 -> 895 | AQ43: =AP43+AQ39+AQ40+AQ41+AQ42 -> 919 | AR43: =AQ43+AR39+AR40+AR41+AR42 -> 937 | AS43: =AR43+AS39+AS40+AS41+AS42 -> 950 | AT43: =AS43 -> 950 | AU43: =AT43+AU39+AU40+AU41+AU42 -> 932 | AV43: =AU43+AV39+AV40+AV41+AV42 -> 950 | AW43: =AV43+AW39+AW40+AW41+AW42 -> 983 | AX43: =AW43+AX39+AX40+AX41+AX42 -> 1016 | AY43: =AX43 -> 1016 | AZ43: =AY43+AZ39+AZ40+AZ41+AZ42 -> 1196 | BA43: =AZ43+BA39+BA40+BA41+BA42 -> 1219 | BB43: =BA43+BB39+BB40+BB41+BB42 -> 1242 | BC43: =BB43+BC39+BC40+BC41+BC42 -> 1270 | BD43: =BC43 -> 1270 | BE43: =BD43+BE39+BE40+BE41+BE42 -> 1290 | BF43: =BE43+BF39+BF40+BF41+BF42 -> 1310 | BG43: =BF43+BG39+BG40+BG41+BG42 -> 1333 | BH43: =BG43+BH39+BH40+BH41+BH42 -> 1361 | BI43: =BH43 -> 1361
A45: Franchised
A46: Opened | C46: 6 | D46: 4 | E46: 12 | F46: =SUM(B46:E46) -> 22 | G46: 10 | H46: 7 | I46: 6 | J46: 15 | K46: =SUM(G46:J46) -> 38 | L46: 11 | M46: 2 | N46: 10 | O46: 5 | P46: =SUM(L46:O46) -> 28 | Q46: 24 | R46: 15 | S46: 11 | T46: 15 | U46: =SUM(Q46:T46) -> 65 | V46: 13 | W46: 8 | X46: 8 | Y46: 7 | Z46: =SUM(V46:Y46) -> 36 | AA46: 0 | AB46: 2 | AC46: 0 | AD46: 0 | AE46: =SUM(AA46:AD46) -> 2 | AF46: 25 | AG46: 9 | AH46: 16 | AI46: 10 | AJ46: =SUM(AF46:AI46) -> 60 | AK46: 11 | AL46: 16 | AM46: 3 | AN46: 26 | AO46: =SUM(AK46:AN46) -> 56 | AP46: 19 | AQ46: 15 | AR46: 15 | AS46: 13 | AT46: =SUM(AP46:AS46) -> 62 | AU46: 14 | AV46: 17 | AW46: 19 | AX46: 24 | AY46: =SUM(AU46:AX46) -> 74 | AZ46: 13 | BA46: 20 | BB46: 24 | BC46: 30 | BD46: =SUM(AZ46:BC46) -> 87 | BE46: 25 | BF46: 25 | BG46: 30 | BH46: 30 | BI46: =SUM(BE46:BH46) -> 110
A47: Acquired | C47: 42 | D47: 0 | E47: 0 | F47: =SUM(B47:E47) -> 42 | G47: 0 | H47: 0 | I47: 0 | J47: 0 | K47: =SUM(G47:J47) -> 0 | L47: 0 | M47: 0 | N47: 0 | O47: 73 | P47: =SUM(L47:O47) -> 73 | Q47: 31 | R47: 0 | S47: 0 | T47: 0 | U47: =SUM(Q47:T47) -> 31 | V47: 4 | W47: 0 | X47: 0 | Y47: 0 | Z47: =SUM(V47:Y47) -> 4 | AA47: 0 | AB47: 3 | AC47: 0 | AD47: 4 | AE47: =SUM(AA47:AD47) -> 7 | AF47: 0 | AG47: 0 | AH47: 0 | AI47: 0 | AJ47: =SUM(AF47:AI47) -> 0 | AK47: 0 | AL47: 0 | AM47: 0 | AN47: 0 | AO47: =SUM(AK47:AN47) -> 0 | AP47: 0 | AQ47: 0 | AR47: 0 | AS47: 0 | AT47: =SUM(AP47:AS47) -> 0 | AU47: 0 | AV47: 0 | AW47: 0 | AX47: 0 | AY47: =SUM(AU47:AX47) -> 0 | AZ47: 0 | BA47: 0 | BB47: 0 | BC47: 0 | BD47: =SUM(AZ47:BC47) -> 0 | BE47: 0 | BF47: 0 | BG47: 0 | BH47: 0 | BI47: =SUM(BE47:BH47) -> 0
A48: Net Conversions | C48: -1 | D48: -1 | E48: -7 | F48: =SUM(B48:E48) -> -9 | G48: -5 | I48: -9 | K48: =SUM(G48:J48) -> -14 | L48: -56 | M48: -1 | N48: -1 | O48: 0 | P48: =SUM(L48:O48) -> -58 | Q48: -4 | R48: 0 | S48: -1 | T48: 0 | U48: =SUM(Q48:T48) -> -5 | V48: 0 | W48: -4 | X48: -5 | Y48: -12 | Z48: =SUM(V48:Y48) -> -21 | AA48: -7 | AB48: 0 | AC48: -3 | AD48: 0 | AE48: =SUM(AA48:AD48) -> -10 | AF48: 0 | AG48: 0 | AH48: -1 | AI48: -3 | AJ48: =SUM(AF48:AI48) -> -4 | AK48: -2 | AL48: 0 | AM48: -2 | AN48: 0 | AO48: =SUM(AK48:AN48) -> -4 | AP48: 0 | AQ48: 0 | AR48: 0 | AS48: 23 | AT48: =SUM(AP48:AS48) -> 23 | AU48: 39 | AV48: 0 | AW48: -6 | AX48: 0 | AY48: =SUM(AU48:AX48) -> 33 | AZ48: 10 | BA48: 0 | BB48: 0 | BC48: 0 | BD48: =SUM(AZ48:BC48) -> 10 | BE48: 0 | BF48: 0 | BG48: 0 | BH48: 0 | BI48: =SUM(BE48:BH48) -> 0
A49: Closed | C49: 0 | D49: -2 | E49: -1 | F49: =SUM(B49:E49) -> -3 | G49: -2 | H49: -2 | I49: -1 | J49: -2 | K49: =SUM(G49:J49) -> -7 | L49: -1 | M49: -2 | N49: -2 | O49: -1 | P49: =SUM(L49:O49) -> -6 | Q49: -1 | R49: -1 | S49: -3 | T49: 0 | U49: =SUM(Q49:T49) -> -5 | V49: 0 | W49: -4 | X49: -2 | Y49: -1 | Z49: =SUM(V49:Y49) -> -7 | AA49: -1 | AB49: 0 | AC49: -1 | AD49: 0 | AE49: =SUM(AA49:AD49) -> -2 | AF49: -3 | AG49: -2 | AH49: -1 | AI49: 0 | AJ49: =SUM(AF49:AI49) -> -6 | AK49: -1 | AL49: 0 | AM49: 0 | AN49: 0 | AO49: =SUM(AK49:AN49) -> -1 | AP49: 0 | AQ49: -1 | AR49: 0 | AS49: 0 | AT49: =SUM(AP49:AS49) -> -1 | AU49: 0 | AV49: -2 | AW49: 0 | AX49: -1 | AY49: =SUM(AU49:AX49) -> -3 | AZ49: -3 | BA49: 0 | BB49: 0 | BC49: 0 | BD49: =SUM(AZ49:BC49) -> -3 | BE49: 0 | BF49: 0 | BG49: 0 | BH49: 0 | BI49: =SUM(BE49:BH49) -> 0
A50: End of Period | B50: 674 | C50: =B50+SUM(C46:C49) -> 721 | D50: =C50+SUM(D46:D49) -> 722 | E50: =D50+SUM(E46:E49) -> 726 | F50: =E50 -> 726 | G50: =F50+SUM(G46:G49) -> 729 | H50: =G50+SUM(H46:H49) -> 734 | I50: =H50+SUM(I46:I49) -> 730 | J50: =I50+SUM(J46:J49) -> 743 | K50: =J50 -> 743 | L50: =K50+SUM(L46:L49) -> 697 | M50: =L50+SUM(M46:M49) -> 696 | N50: =M50+SUM(N46:N49) -> 703 | O50: =N50+SUM(O46:O49) -> 780 | P50: =O50 -> 780 | Q50: =P50+SUM(Q46:Q49) -> 830 | R50: =Q50+SUM(R46:R49) -> 844 | S50: =R50+SUM(S46:S49) -> 851 | T50: =S50+SUM(T46:T49) -> 866 | U50: =T50 -> 866 | V50: =U50+SUM(V46:V49) -> 883 | W50: =V50+SUM(W46:W49) -> 883 | X50: =W50+SUM(X46:X49) -> 884 | Y50: =X50+SUM(Y46:Y49) -> 878 | Z50: =Y50 -> 878 | AA50: =Z50+SUM(AA46:AA49) -> 870 | AB50: =AA50+SUM(AB46:AB49) -> 875 | AC50: =AB50+SUM(AC46:AC49) -> 871 | AD50: =AC50+SUM(AD46:AD49) -> 875 | AE50: =AD50 -> 875 | AF50: 897 | AG50: =AF50+AG46+AG47+AG48+AG49 -> 904 | AH50: =AG50+AH46+AH47+AH48+AH49 -> 918 | AI50: =AH50+AI46+AI47+AI48+AI49 -> 925 | AJ50: =AI50 -> 925 | AK50: =AJ50+AK46+AK47+AK48+AK49 -> 933 | AL50: =AK50+AL46+AL47+AL48+AL49 -> 949 | AM50: =AL50+AM46+AM47+AM48+AM49 -> 950 | AN50: =AM50+AN46+AN47+AN48+AN49 -> 976 | AO50: =AN50 -> 976 | AP50: =AO50+AP46+AP47+AP48+AP49 -> 995 | AQ50: =AP50+AQ46+AQ47+AQ48+AQ49 -> 1009 | AR50: =AQ50+AR46+AR47+AR48+AR49 -> 1024 | AS50: =AR50+AS46+AS47+AS48+AS49 -> 1060 | AT50: =AS50 -> 1060 | AU50: =AT50+AU46+AU47+AU48+AU49 -> 1113 | AV50: =AU50+AV46+AV47+AV48+AV49 -> 1128 | AW50: =AV50+AW46+AW47+AW48+AW49 -> 1141 | AX50: =AW50+AX46+AX47+AX48+AX49 -> 1164 | AY50: =AX50 -> 1164 | AZ50: =AY50+AZ46+AZ47+AZ48+AZ49 -> 1184 | BA50: =AZ50+BA46+BA47+BA48+BA49 -> 1204 | BB50: =BA50+BB46+BB47+BB48+BB49 -> 1228 | BC50: =BB50+BC46+BC47+BC48+BC49 -> 1258 | BD50: =BC50 -> 1258 | BE50: =BD50+BE46+BE47+BE48+BE49 -> 1283 | BF50: =BE50+BF46+BF47+BF48+BF49 -> 1308 | BG50: =BF50+BG46+BG47+BG48+BG49 -> 1338 | BH50: =BG50+BH46+BH47+BH48+BH49 -> 1368 | BI50: =BH50 -> 1368
A52: System-Wide Stores | B52: =B43+B50 -> 956 | C52: =C43+C50 -> 1052 | D52: =D43+D50 -> 1055 | E52: =E43+E50 -> 1068 | F52: =F50+F43 -> 1068 | G52: =G43+G50 -> 1076 | H52: =H43+H50 -> 1108 | I52: =I43+I50 -> 1113 | J52: =J43+J50 -> 1127 | K52: =K50+K43 -> 1127 | L52: =L43+L50 -> 1139 | M52: =M43+M50 -> 1141 | N52: =N43+N50 -> 1154 | O52: =O43+O50 -> 1242 | P52: =P50+P43 -> 1242 | Q52: =Q43+Q50 -> 1301 | R52: =R43+R50 -> 1327 | S52: =S43+S50 -> 1352 | T52: =T43+T50 -> 1385 | U52: =U50+U43 -> 1385 | V52: =V43+V50 -> 1407 | W52: =W43+W50 -> 1419 | X52: =X43+X50 -> 1432 | Y52: =Y43+Y50 -> 1462 | Z52: =Z50+Z43 -> 1462 | AA52: =AA43+AA50 -> 1533 | AB52: =AB43+AB50 -> 1548 | AC52: =AC43+AC50 -> 1569 | AD52: =AD43+AD50 -> 1594 | AE52: =AE50+AE43 -> 1594 | AF52: =AF50+AF43 -> 1635 | AG52: =AG50+AG43 -> 1661 | AH52: =AH50+AH43 -> 1690 | AI52: =AI50+AI43 -> 1715 | AJ52: =AJ50+AJ43 -> 1715 | AK52: =AK50+AK43 -> 1746 | AL52: =AL50+AL43 -> 1781 | ... BI52: =BI50+BI43 -> 2729
A54: Sales Analysis:
A55: SSS Contribution | AF55: =AA59*(1+(AF83/100)) -> 524.987 | AG55: =AB59*(1+(AG83/100)) -> 529.308 | AH55: =AC59*(1+(AH83/100)) -> 578.074 | AI55: =AD59*(1+(AI83/100)) -> 605.7324 | AK55: =AF59*(1+(AK83/100)) -> 616.4571 | AL55: =AG59*(1+(AL83/100)) -> 632.195 | AM55: =AH59*(1+(AM83/100)) -> 686.7 | AN55: =AI59*(1+(AN83/100)) -> 706.09 | AP55: =AK59*(1+(AP83/100)) -> 689.724 | AQ55: =AL59*(1+(AQ83/100)) -> 710.7123 | AR55: =AM59*(1+(AR83/100)) -> 766.374 | AS55: =AN59*(1+(AS83/100)) -> 778.1682 | AU55: =AP59*(1+(AU83/100)) -> 780.60403 | AV55: =AQ59*(1+(AV83/100)) -> 789.20289 | AW55: =AR59*(1+(AW83/100)) -> 847.84258 | AX55: =AS59*(1+(AX83/100)) -> 876.30332 | AZ55: =AU59*(1+(AZ83/100)) -> 867.8774 | BA55: =AV59*(1+(BA83/100)) -> 869.66681 | BB55: =AW59*(1+(BB83/100)) -> 940.76461 | BC55: =AX59*(1+(BC83/100)) -> 964.7901 | BE55: =AZ59*(1+(BE83/100)) -> 956.39408 | BF55: =BA59*(1+(BF83/100)) -> 986.49364 | BG55: =BB59*(1+(BG83/100)) -> 1056.2241 | BH55: =BC59*(1+(BH83/100)) -> 1095.8242
A56: Net New Store Contribution | AF56: =AF59-AF55 -> 25.913 | AG56: =AG59-AG55 -> 27.692 | AH56: =AH59-AH55 -> 32.326 | AI56: =AI59-AI55 -> 36.1676 | AK56: =AK59-AK55 -> 27.5429 | AL56: =AL59-AL55 -> 27.705 | AM56: =AM59-AM55 -> 32.9 | AN56: =AN59-AN55 -> 32.21 | AP56: =AP59-AP55 -> 33.176 | AQ56: =AQ59-AQ55 -> 35.3877 | AR56: =AR59-AR55 -> 42.126 | AS56: =AS59-AS55 -> 48.6318 | AU56: =AU59-AU55 -> 39.695966 | AV56: =AV59-AV55 -> 36.297106 | AW56: =AW59-AW55 -> 41.757416 | AX56: =AX59-AX55 -> 42.096677 | AZ56: =AZ59-AZ55 -> 55.7226 | BA56: =(BA57*(BA39+BA40+BA41+BA46+BA47+AZ39+AZ40+AZ41+AZ46+AZ47+AX39+AX40+AX41+AX46+AX47+AW39+AW40+AW41+AW46+AW47))+(BA57*(BA42+AZ42+AX42+AW42+BA49+AZ49+AX49+AW49)) -> 78.43 | BB56: =(BB57*(BB39+BB40+BB41+BB46+BB47+BA39+BA40+BA41+BA46+BA47+AZ39+AZ40+AZ41+AZ46+AZ47+AX39+AX40+AX41+AX46+AX47))+(BB57*(BB42+BA42+AZ42+AX42+BB49+BA49+AZ49+AX49)) -> 77.28 | BC56: =(BC57*(BC39+BC40+BC41+BC46+BC47+BB39+BB40+BB41+BB46+BB47+BA39+BA40+BA41+BA46+BA47+AZ39+AZ40+AZ41+AZ46+AZ47))+(BC57*(BC42+BB42+BA42+AZ42+BC49+BB49+BA49+AZ49)) -> 87.88 | BE56: =(BE57*(BE39+BE40+BE41+BE46+BE47+BC39+BC40+BC41+BC46+BC47+BB39+BB40+BB41+BB46+BB47+BA39+BA40+BA41+BA46+BA47))+(BE57*(BE42+BC42+BB42+BA42+BE49+BC49+BB49+BA49)) -> 46.32 | BF56: =(BF57*(BF39+BF40+BF41+BF46+BF47+BE39+BE40+BE41+BE46+BE47+BC39+BC40+BC41+BC46+BC47+BB39+BB40+BB41+BB46+BB47))+(BF57*(BF42+BE42+BC42+BB42+BF49+BE49+BC49+BB49)) -> 48.75 | BG56: =(BG57*(BG39+BG40+BG41+BG46+BG47+BF39+BF40+BF41+BF46+BF47+BE39+BE40+BE41+BE46+BE47+BC39+BC40+BC41+BC46+BC47))+(BG57*(BG42+BF42+BE42+BC42+BG49+BF49+BE49+BC49)) -> 56.28 | BH56: =(BH57*(BH39+BH40+BH41+BH46+BH47+BG39+BG40+BG41+BG46+BG47+BF39+BF40+BF41+BF46+BF47+BE39+BE40+BE41+BE46+BE47))+(BH57*(BH42+BG42+BF42+BE42+BH49+BG49+BF49+BE49)) -> 44.22
A57: Sales Per Net New Store | AF57: =AF56/((AF39+AF40+AF41+AD41+AD40+AD39+AC39+AC40+AC41+AB41+AB40+AB39+AF46+AD46+AC46+AB46+AF47+AD47+AC47+AB47)+(AF42+AD42+AC42+AB42+AF49+AD49+AC49+AB49)) -> 0.24679048 | AG57: =AG56/((AG39+AG40+AG41+AF41+AF40+AF39+AD39+AD40+AD41+AC41+AC40+AC39+AG46+AF46+AD46+AC46+AG47+AF47+AD47+AC47)+(AG42+AF42+AD42+AC42+AG49+AF49+AD49+AC49)) -> 0.23872414 | AH57: =AH56/((AH39+AH40+AH41+AG41+AG40+AG39+AF39+AF40+AF41+AD41+AD40+AD39+AH46+AG46+AF46+AD46+AH47+AG47+AF47+AD47)+(AH42+AG42+AF42+AD42+AH49+AG49+AF49+AD49)) -> 0.26496721 | AI57: =AI56/((AI39+AI40+AI41+AH41+AH40+AH39+AG39+AG40+AG41+AF41+AF40+AF39+AI46+AH46+AG46+AF46+AI47+AH47+AG47+AF47)+(AI42+AH42+AG42+AF42+AI49+AH49+AG49+AF49)) -> 0.2893408 | AK57: =AK56/((AK39+AK40+AK41+AI41+AI40+AI39+AH39+AH40+AH41+AG41+AG40+AG39+AK46+AI46+AH46+AG46+AK47+AI47+AH47+AG47)+(AK42+AI42+AH42+AG42+AK49+AI49+AH49+AG49)) -> 0.2354094 | AL57: =AL56/((AL39+AL40+AL41+AK41+AK40+AK39+AI39+AI40+AI41+AH41+AH40+AH39+AL46+AK46+AI46+AH46+AL47+AK47+AI47+AH47)+(AL42+AK42+AI42+AH42+AL49+AK49+AI49+AH49)) -> 0.21988095 | AM57: =AM56/((AM39+AM40+AM41+AL41+AL40+AL39+AK39+AK40+AK41+AI41+AI40+AI39+AM46+AL46+AK46+AI46+AM47+AL47+AK47+AI47)+(AM42+AL42+AK42+AI42+AM49+AL49+AK49+AI49)) -> 0.27190083 | AN57: =AN56/((AN39+AN40+AN41+AM41+AM40+AM39+AL39+AL40+AL41+AK41+AK40+AK39+AN46+AM46+AL46+AK46+AN47+AM47+AL47+AK47)+(AN42+AM42+AL42+AK42+AN49+AM49+AL49+AK49)) -> 0.22843972 | AP57: =AP56/((AP39+AP40+AP41+AN41+AN40+AN39+AM39+AM40+AM41+AL41+AL40+AL39+AP46+AN46+AM46+AL46+AP47+AN47+AM47+AL47)+(AP42+AN42+AM42+AL42+AP49+AN49+AM49+AL49)) -> 0.22723288 | AQ57: =AQ56/((AQ39+AQ40+AQ41+AP41+AP40+AP39+AN39+AN40+AN41+AM41+AM40+AM39+AQ46+AP46+AN46+AM46+AQ47+AP47+AN47+AM47)+(AQ42+AP42+AN42+AM42+AQ49+AP49+AN49+AM49)) -> 0.23750134 | AR57: =AR56/((AR39+AR40+AR41+AQ41+AQ40+AQ39+AP39+AP40+AP41+AN41+AN40+AN39+AR46+AQ46+AP46+AN46+AR47+AQ47+AP47+AN47)+(AR42+AQ42+AP42+AN42+AR49+AQ49+AP49+AN49)) -> 0.26831847 | AS57: =AS56/((AS39+AS40+AS41+AR41+AR40+AR39+AQ39+AQ40+AQ41+AO41+AO40+AO39+AS46+AR46+AQ46+AO46+AS47+AR47+AQ47+AO47)+(AS42+AR42+AQ42+AO42+AS49+AR49+AQ49+AO49)) -> 0.20433529 | AU57: =AU56/((AU39+AU40+AU41+AS41+AS40+AS39+AR39+AR40+AR41+AQ41+AQ40+AQ39+AU46+AS46+AR46+AQ46+AU47+AS47+AR47+AQ47)+(AU42+AS42+AR42+AQ42+AU49+AS49+AR49+AQ49)) -> 0.42683834 | AV57: =AV56/((AV39+AV40+AV41+AT41+AT40+AT39+AS39+AS40+AS41+AR41+AR40+AR39+AV46+AT46+AS46+AR46+AV47+AT47+AS47+AR47)+(AV42+AT42+AS42+AR42+AV49+AT49+AS49+AR49)) -> 0.15989915 | AW57: =AW56/((AW39+AW40+AW41+AU41+AU40+AU39+AT39+AT40+AT41+AS41+AS40+AS39+AW46+AU46+AT46+AS46+AW47+AU47+AT47+AS47)+(AW42+AU42+AT42+AS42+AW49+AU49+AT49+AS49)) -> 0.19979625 | AX57: =AX56/((AX39+AX40+AX41+AV41+AV40+AV39+AU39+AU40+AU41+AT41+AT40+AT39+AX46+AV46+AU46+AT46+AX47+AV47+AU47+AT47)+(AX42+AV42+AU42+AT42+AX49+AV49+AU49+AT49)) -> 0.19134853 | AZ57: =AZ56/((AZ39+AZ40+AZ41+AX41+AX40+AX39+AW39+AW40+AW41+AV41+AV40+AV39+AZ46+AX46+AW46+AV46+AZ47+AX47+AW47+AV47)+(AZ42+AX42+AW42+AV42+AZ49+AX49+AW49+AV49)) -> 0.16834622 | BA57: 0.23 | BB57: 0.23 | BC57: 0.26 | BE57: 0.24 | BF57: 0.25 | BG57: 0.28 | BH57: 0.22
A59: System-Wide store sales | F59: 880 | K59: 1024 | P59: 1161 | U59: 1419 | Z59: 1520 | AA59: 421 | AB59: 468 | AC59: 526 | AD59: 554.7 | AE59: =SUM(AA59:AD59) -> 1969.7 | AF59: 550.9 | AG59: 557 | AH59: 610.4 | AI59: 641.9 | AJ59: =SUM(AF59:AI59) -> 2360.2 | AK59: 644 | AL59: 659.9 | AM59: 719.6 | AN59: 738.3 | AO59: =SUM(AK59:AN59) -> 2761.8 | AP59: 722.9 | AQ59: 746.1 | AR59: 808.5 | AS59: 826.8 | AT59: =SUM(AP59:AS59) -> 3104.3 | AU59: 820.3 | AV59: 825.5 | AW59: 889.6 | AX59: 918.4 | AY59: =SUM(AU59:AX59) -> 3453.8 | AZ59: 923.6 | BA59: =BA56+BA55 -> 948.09681 | BB59: =BB56+BB55 -> 1018.0446 | BC59: =BC56+BC55 -> 1052.6701 | BD59: =SUM(AZ59:BC59) -> 3942.4115 | BE59: =BE56+BE55 -> 1002.7141 | BF59: =BF56+BF55 -> 1035.2436 | BG59: =BG56+BG55 -> 1112.5041 | BH59: =BH56+BH55 -> 1140.0442 | BI59: =SUM(BE59:BH59) -> 4290.506
A60: y/y growth | K60: =K59/F59-1 -> 0.16363636 | P60: =P59/K59-1 -> 0.13378906 | U60: =U59/P59-1 -> 0.22222222 | Z60: =Z59/U59-1 -> 0.071176885 | AE60: =AE59/Z59-1 -> 0.29585526 | AF60: =AF59/AA59-1 -> 0.30855107 | AG60: =AG59/AB59-1 -> 0.19017094 | AH60: =AH59/AC59-1 -> 0.16045627 | AI60: =AI59/AD59-1 -> 0.15720209 | AJ60: =AJ59/AE59-1 -> 0.19825354 | AK60: =AK59/AF59-1 -> 0.16899619 | AL60: =AL59/AG59-1 -> 0.18473968 | ... BI60: =BI59/BD59-1 -> 0.088294822
A61: Sales per store | F61: =F59/F52 -> 0.82397004 | K61: =K59/K52 -> 0.90860692 | P61: =P59/P52 -> 0.93478261 | U61: =U59/U52 -> 1.0245487 | Z61: =Z59/Z52 -> 1.0396717 | AA61: =AA59/AA52 -> 0.27462492 | AB61: =AB59/AB52 -> 0.30232558 | AC61: =AC59/AC52 -> 0.33524538 | AD61: =AD59/AD52 -> 0.34799247 | AE61: =AE59/AE52 -> 1.2356964 | AF61: =AF59/AF52 -> 0.3369419 | AG61: =AG59/AG52 -> 0.33534016 | ... BI61: =BI59/BI52 -> 1.5721898
A63: Estimated Company Owned Store Sales/Revenue | AA63: =AA61*AA43 -> 182.07632 | AB63: =AB61*AB43 -> 203.46512 | AC63: =AC61*AC43 -> 234.00127 | AD63: =AD61*AD43 -> 250.20659 | AF63: =AF61*AF43 -> 248.66312 | AG63: =AG61*AG43 -> 253.8525 | AH63: =AH61*AH43 -> 278.83361 | AI63: =AI61*AI43 -> 295.68571 | AJ63: =SUM(AF63:AI63) -> 1077.0349 | AK63: =AK61*AK43 -> 299.86942 | AL63: =AL61*AL43 -> 308.27445 | AM63: =AM61*AM43 -> 340.65322 | AN63: =AN61*AN43 -> 349.21749 | AO63: =SUM(AK63:AN63) -> 1298.0146 | AP63: =AP61*AP43 -> 342.32566 | AQ63: =AQ61*AQ43 -> 355.63584 | AR63: =AR61*AR43 -> 386.3154 | AS63: =AS61*AS43 -> 390.77612 | AT63: =SUM(AP63:AS63) -> 1475.053 | AU63: =AU61*AU43 -> 373.84822 | AV63: =AV61*AV43 -> 377.39413 | AW63: =AW61*AW43 -> 411.71224 | AX63: =AX61*AX43 -> 428.02495 | AY63: =SUM(AU63:AX63) -> 1590.9795 | AZ63: =AZ61*AZ43 -> 464.1284 | BA63: =BA61*BA43 -> 476.98308 | BB63: =BB61*BB43 -> 511.90745 | BC63: =BC61*BC43 -> 528.83348 | BD63: =SUM(AZ63:BC63) -> 1981.8524 | BE63: =BE61*BE43 -> 502.72101 | BF63: =BF61*BF43 -> 518.01725 | BG63: =BG61*BG43 -> 555.21079 | BH63: =BH61*BH43 -> 568.55996 | BI63: =SUM(BE63:BH63) -> 2144.509
A64: Franchised Store Sales | AA64: =AA61*AA50 -> 238.92368 | AB64: =AB61*AB50 -> 264.53488 | AC64: =AC61*AC50 -> 291.99873 | AD64: =AD61*AD50 -> 304.49341 | AF64: =AF61*AF50 -> 302.23688 | AG64: =AG61*AG50 -> 303.1475 | AH64: =AH61*AH50 -> 331.56639 | AI64: =AI61*AI50 -> 346.21429 | AJ64: =SUM(AF64:AI64) -> 1283.1651 | AK64: =AK61*AK50 -> 344.13058 | AL64: =AL61*AL50 -> 351.62555 | AM64: =AM61*AM50 -> 378.94678 | AN64: =AN61*AN50 -> 389.08251 | AO64: =SUM(AK64:AN64) -> 1463.7854 | AP64: =AP61*AP50 -> 380.57434 | AQ64: =AQ61*AQ50 -> 390.46416 | AR64: =AR61*AR50 -> 422.1846 | AS64: =AS61*AS50 -> 436.02388 | AT64: =SUM(AP64:AS64) -> 1629.247 | AU64: =AU61*AU50 -> 446.45178 | AV64: =AV61*AV50 -> 448.10587 | AW64: =AW61*AW50 -> 477.88776 | AX64: =AX61*AX50 -> 490.37505 | AY64: =SUM(AU64:AX64) -> 1862.8205 | AZ64: =AZ61*AZ50 -> 459.4716 | BA64: =BA61*BA50 -> 471.11372 | BB64: =BB61*BB50 -> 506.13716 | BC64: =BC61*BC50 -> 523.83662 | BD64: =SUM(AZ64:BC64) -> 1960.5591 | BE64: =BE61*BE50 -> 499.99307 | BF64: =BF61*BF50 -> 517.22639 | BG64: =BG61*BG50 -> 557.29335 | BH64: =BH61*BH50 -> 571.48422 | BI64: =SUM(BE64:BH64) -> 2145.997
A65: Franchised Store Contribution % | AA65: =(AA67-AA63)/AA64 -> 0.30103203 | AB65: =(AB67-AB63)/AB64 -> 0.30821978 | AC65: =(AC67-AC63)/AC64 -> 0.32876419 | AD65: =(AD67-AD63)/AD64 -> 0.33430415 | AF65: =(AF67-AF63)/AF64 -> 0.12783642 | AG65: =(AG67-AG63)/AG64 -> 0.13903298 | AH65: =(AH67-AH63)/AH64 -> 0.11631574 | AI65: =(AI67-AI63)/AI64 -> 0.11471013 | AJ65: =(AJ67-AJ63)/AJ64 -> 0.12396305 | AK65: =(AK67-AK63)/AK64 -> 0.095692117 | AL65: =(AL67-AL63)/AL64 -> 0.10302308 | AM65: =(AM67-AM63)/AM64 -> 0.09380416 | ... AZ65: =(AZ67-AZ63)/AZ64 -> -0.0050675676 | BA65: 0.061 | BB65: 0.059 | BC65: 0.06 | BD65: =(BD67-BD63)/BD64 -> 0.044733068 | BE65: 0.065 | BF65: 0.065 | BG65: 0.062 | BH65: 0.063 | BI65: =(BI67-BI63)/BI64 -> 0.063688326
A66: Estimated Franchised Store Revenue | AA66: =AA64*AA65 -> 71.923679 | AB66: =AB64*AB65 -> 81.534884 | AC66: =AC64*AC65 -> 95.998725 | AD66: =AD64*AD65 -> 101.79341 | AF66: =AF64*AF65 -> 38.636881 | AG66: =AG64*AG65 -> 42.147502 | AH66: =AH64*AH65 -> 38.566391 | AI66: =AI64*AI65 -> 39.714286 | AJ66: =SUM(AF66:AI66) -> 159.06506 | AK66: =AK64*AK65 -> 32.930584 | AL66: =AL64*AL65 -> 36.225547 | AM66: =AM64*AM65 -> 35.546785 | AN66: =AN64*AN65 -> 40.782505 | AO66: =SUM(AK66:AN66) -> 145.48542 | AP66: =AP64*AP65 -> 31.074339 | AQ66: =AQ64*AQ65 -> 33.06416 | AR66: =AR64*AR65 -> 35.0846 | AS66: =AS64*AS65 -> 44.723881 | AT66: =SUM(AP66:AS66) -> 143.94698 | AU66: =AU64*AU65 -> 40.451785 | AV66: =AV64*AV65 -> 25.805871 | AW66: =AW64*AW65 -> 27.287759 | AX66: =AX64*AX65 -> 25.775046 | AY66: =SUM(AU66:AX66) -> 119.32046 | AZ66: =AZ64*AZ65 -> -2.3284034 | BA66: =BA64*BA65 -> 28.737937 | BB66: =BB64*BB65 -> 29.862092 | BC66: =BC64*BC65 -> 31.430197 | BD66: =SUM(AZ66:BC66) -> 87.701823 | BE66: =BE64*BE65 -> 32.499549 | BF66: =BF64*BF65 -> 33.619715 | BG66: =BG64*BG65 -> 34.552188 | BH66: =BH64*BH65 -> 36.003506 | BI66: =SUM(BE66:BH66) -> 136.67496
A67: Retail Services Revenue | AA67: 254 | AB67: 285 | AC67: 330 | AD67: 352 | AF67: =AF86 -> 287.3 | AG67: =AG86 -> 296 | AH67: =AH86 -> 317.4 | AI67: =AI86 -> 335.4 | AJ67: =SUM(AF67:AI67) -> 1236.1 | AK67: =AK86 -> 332.8 | AL67: =AL86 -> 344.5 | AM67: =AM86 -> 376.2 | AN67: =AN86 -> 390 | AO67: =SUM(AK67:AN67) -> 1443.5 | AP67: =AP86 -> 373.4 | AQ67: =AQ86 -> 388.7 | AR67: =AR86 -> 421.4 | AS67: =AS86 -> 435.5 | AT67: =SUM(AP67:AS67) -> 1619 | AU67: =AU86 -> 414.3 | AV67: =AV86 -> 403.2 | AW67: =AW86 -> 439 | AX67: =AX86 -> 453.8 | AY67: =SUM(AU67:AX67) -> 1710.3 | AZ67: =AZ86 -> 461.8 | BA67: =BA63+(BA65*BA64) -> 505.72102 | BB67: =BB63+(BB65*BB64) -> 541.76954 | BC67: =BC63+(BC65*BC64) -> 560.26367 | BD67: =SUM(AZ67:BC67) -> 2069.5542 | BE67: =BE63+(BE65*BE64) -> 535.22056 | BF67: =BF63+(BF65*BF64) -> 551.63697 | BG67: =BG63+(BG65*BG64) -> 589.76298 | BH67: =BH63+(BH65*BH64) -> 604.56346 | BI67: =SUM(BE67:BH67) -> 2281.184
A69: Gross Margin Analysis:
A70: Estimated Company Owned Gross Profit | AA70: =AA88-AA72 -> 156.07632 | AB70: =AB88-AB72 -> 165.46512 | AC70: =AC88-AC72 -> 163.00127 | AD70: =AD88-AD72 -> 144.20659 | AF70: =AF88-AF72 -> 73.563119 | AG70: =AG88-AG72 -> 65.152498 | AH70: =AH88-AH72 -> 89.233609 | AI70: =AI88-AI72 -> 89.385714 | AJ70: =SUM(AF70:AI70) -> 317.33494 | AK70: =AK88-AK72 -> 85.869416 | AL70: =AL88-AL72 -> 90.474453 | AM70: =AM88-AM72 -> 115.15322 | AN70: =AN88-AN72 -> 107.51749 | AO70: =SUM(AK70:AN70) -> 399.01458 | AP70: =AP88-AP72 -> 103.72566 | AQ70: =AQ88-AQ72 -> 113.13584 | AR70: =AR88-AR72 -> 132.4154 | AS70: =AS88-AS72 -> 125.57612 | AT70: =SUM(AP70:AS70) -> 474.85302 | AU70: =AU88-AU72 -> 112.44822 | AV70: =AV88-AV72 -> 124.69413 | AW70: =AW88-AW72 -> 150.31224 | AX70: =AX88-AX72 -> 151.72495 | AY70: =SUM(AU70:AX70) -> 539.17954 | AZ70: =AZ88-AZ72 -> 174.8284 | BA70: =BA71*BA63 -> 162.17425 | BB70: =BB71*BB63 -> 185.3105 | BC70: =BC71*BC63 -> 186.14938 | BD70: =SUM(AZ70:BC70) -> 708.46253 | BE70: =BE71*BE63 -> 166.40066 | BF70: =BF71*BF63 -> 174.57181 | BG70: =BG71*BG63 -> 203.20715 | BH70: =BH71*BH63 -> 205.25014 | BI70: =SUM(BE70:BH70) -> 749.42976
A71: Company Owned GM% | AA71: =AA70/AA63 -> 0.85720274 | AB71: =AB70/AB63 -> 0.8132358 | AC71: =AC70/AC63 -> 0.69658285 | AD71: =AD70/AD63 -> 0.57635008 | AF71: =AF70/AF63 -> 0.29583446 | AG71: =AG70/AG63 -> 0.25665494 | AH71: =AH70/AH63 -> 0.32002458 | AI71: =AI70/AI63 -> 0.30229974 | AJ71: =AJ70/AJ63 -> 0.29463755 | AK71: =AK70/AK63 -> 0.28635603 | AL71: =AL70/AL63 -> 0.2934867 | AM71: =AM70/AM63 -> 0.33803648 | ... AZ71: =AZ70/AZ63 -> 0.37668111 | BA71: 0.34 | BB71: 0.362 | BC71: 0.352 | BD71: =BD70/BD63 -> 0.35747492 | BE71: 0.331 | BF71: 0.337 | BG71: 0.366 | BH71: 0.361 | BI71: =BI70/BI63 -> 0.3494645
A72: Estimated Franchised Gross Profit | AA72: =AA66 -> 71.923679 | AB72: =AB66 -> 81.534884 | AC72: =AC66 -> 95.998725 | AD72: =AD66 -> 101.79341 | AF72: =AF66 -> 38.636881 | AG72: =AG66 -> 42.147502 | AH72: =AH66 -> 38.566391 | AI72: =AI66 -> 39.714286 | AJ72: =SUM(AF72:AI72) -> 159.06506 | AK72: =AK66 -> 32.930584 | AL72: =AL66 -> 36.225547 | AM72: =AM66 -> 35.546785 | AN72: =AN66 -> 40.782505 | AO72: =SUM(AK72:AN72) -> 145.48542 | AP72: =AP66 -> 31.074339 | AQ72: =AQ66 -> 33.06416 | AR72: =AR66 -> 35.0846 | AS72: =AS66 -> 44.723881 | AT72: =SUM(AP72:AS72) -> 143.94698 | AU72: =AU66 -> 40.451785 | AV72: =AV66 -> 25.805871 | AW72: =AW66 -> 27.287759 | AX72: =AX66 -> 25.775046 | AY72: =SUM(AU72:AX72) -> 119.32046 | AZ72: =AZ66 -> -2.3284034 | BA72: =BA66 -> 28.737937 | BB72: =BB66 -> 29.862092 | BC72: =BC66 -> 31.430197 | BD72: =SUM(AZ72:BC72) -> 87.701823 | BE72: =BE66 -> 32.499549 | BF72: =BF66 -> 33.619715 | BG72: =BG66 -> 34.552188 | BH72: =BH66 -> 36.003506 | BI72: =SUM(BE72:BH72) -> 136.67496
A73: Total Gross Profit | AA73: =AA72+AA70 -> 228 | AB73: =AB72+AB70 -> 247 | AC73: =AC72+AC70 -> 259 | AD73: =AD72+AD70 -> 246 | AF73: =AF72+AF70 -> 112.2 | AG73: =AG72+AG70 -> 107.3 | AH73: =AH72+AH70 -> 127.8 | AI73: =AI72+AI70 -> 129.1 | AJ73: =SUM(AF73:AI73) -> 476.4 | AK73: =AK72+AK70 -> 118.8 | AL73: =AL72+AL70 -> 126.7 | AM73: =AM72+AM70 -> 150.7 | AN73: =AN72+AN70 -> 148.3 | AO73: =SUM(AK73:AN73) -> 544.5 | AP73: =AP72+AP70 -> 134.8 | AQ73: =AQ72+AQ70 -> 146.2 | AR73: =AR72+AR70 -> 167.5 | AS73: =AS72+AS70 -> 170.3 | AT73: =SUM(AP73:AS73) -> 618.8 | AU73: =AU72+AU70 -> 152.9 | AV73: =AV72+AV70 -> 150.5 | AW73: =AW72+AW70 -> 177.6 | AX73: =AX72+AX70 -> 177.5 | AY73: =SUM(AU73:AX73) -> 658.5 | AZ73: =AZ72+AZ70 -> 172.5 | BA73: =BA72+BA70 -> 190.91218 | BB73: =BB72+BB70 -> 215.17259 | BC73: =BC72+BC70 -> 217.57958 | BD73: =SUM(AZ73:BC73) -> 796.16435 | BE73: =BE72+BE70 -> 198.9002 | BF73: =BF72+BF70 -> 208.19153 | BG73: =BG72+BG70 -> 237.75934 | BH73: =BH72+BH70 -> 241.25365 | BI73: =SUM(BE73:BH73) -> 886.10472
A74: Total GM% | AA74: =AA73/AA86 -> 0.34915773 | AB74: =AB73/AB86 -> 0.35235378 | AC74: =AC73/AC86 -> 0.3270202 | AD74: =AD73/AD86 -> 0.29461078 | AF74: =AF73/AF86 -> 0.39053254 | AG74: =AG73/AG86 -> 0.3625 | AH74: =AH73/AH86 -> 0.4026465 | AI74: =AI73/AI86 -> 0.38491354 | AJ74: =AJ73/AJ86 -> 0.38540571 | AK74: =AK73/AK86 -> 0.35697115 | AL74: =AL73/AL86 -> 0.36777939 | AM74: =AM73/AM86 -> 0.4005848 | ... BI74: =BI73/BI86 -> 0.38844071
A76: SG&A Analysis:
A77: SG&A per store ($ thousands) | AF77: =(AF89/AF43)*1000 -> 81.571816 | AG77: =(AG89/AG43)*1000 -> 83.48745 | AH77: =(AH89/AH43)*1000 -> 76.683938 | AI77: =(AI89/AI43)*1000 -> 78.607595 | AJ77: =SUM(AF77:AI77) -> 320.3508 | AK77: =(AK89/AK43)*1000 -> 81.180812 | AL77: =(AL89/AL43)*1000 -> 75.240385 | AM77: =(AM89/AM43)*1000 -> 76.814988 | AN77: =(AN89/AN43)*1000 -> 80.251142 | AO77: =SUM(AK77:AN77) -> 313.48733 | AP77: =(AP89/AP43)*1000 -> 83.240223 | AQ77: =(AQ89/AQ43)*1000 -> 78.67247 | AR77: =(AR89/AR43)*1000 -> 82.390608 | AS77: =(AS89/AS43)*1000 -> 85.368421 | AT77: =SUM(AP77:AS77) -> 329.67172 | AU77: =(AU89/AU43)*1000 -> 88.841202 | AV77: =(AV89/AV43)*1000 -> 90.842105 | AW77: =(AW89/AW43)*1000 -> 86.978637 | AX77: =(AX89/AX43)*1000 -> 93.799213 | AY77: =SUM(AU77:AX77) -> 360.46116 | AZ77: =(AZ89/AZ43)*1000 -> 89.297659 | BA77: =(BA89/BA43)*1000 -> 87.536616 | BB77: =(BB89/BB43)*1000 -> 87.241472 | BC77: =(BC89/BC43)*1000 -> 86.024737 | BD77: =SUM(AZ77:BC77) -> 350.10048 | BE77: =(BE89/BE43)*1000 -> 86.299129 | BF77: =(BF89/BF43)*1000 -> 86.324869 | BG77: =(BG89/BG43)*1000 -> 85.389538 | BH77: =(BH89/BH43)*1000 -> 84.843219 | BI77: =SUM(BE77:BH77) -> 342.85676
A78: y/y growth | AK78: =AK77/AF77-1 -> -0.0047933702 | AL78: =AL77/AG77-1 -> -0.098782102 | AM78: =AM77/AH77-1 -> 0.0017089689 | AN78: =AN77/AI77-1 -> 0.020908242 | AO78: =AO77/AJ77-1 -> -0.021424865 | AP78: =AP77/AK77-1 -> 0.025368207 | AQ78: =AQ77/AL77-1 -> 0.045614938 | AR78: =AR77/AM77-1 -> 0.072585053 | ... BI78: =BI77/BD77-1 -> -0.020690427
A81: Company Operated SSS% | B81: 5.6 | C81: 7.1 | D81: 6.8 | E81: 5.4 | F81: 6.2 | G81: 9.5 | H81: 2.1 | I81: 6.9 | J81: 9.8 | K81: 7 | L81: 8.2 | M81: 11.2 | N81: 8.7 | O81: 6.9 | P81: 8.7 | Q81: 9.9 | R81: 10.2 | S81: 9.2 | T81: 9.5 | U81: 9.7 | V81: 6.2 | W81: 0.5 | X81: -5 | Y81: 8.9 | Z81: 2.6 | AA81: 6.1 | AB81: 19.8 | AC81: 36.1 | AD81: 17.3 | AE81: 19.6 | AF81: 22.1 | AG81: 10 | AH81: 7.1 | AI81: 8.5 | AJ81: 11.4 | AK81: 12.7 | AL81: 14.2 | AM81: 12.1 | AN81: 9.1 | AO81: =AK86/AO86*AK81+AL86/AO86*AL81+AM86/AO86*AM81+AN86/AO86*AN81 -> 11.928978 | AP81: 6.1 | AQ81: 7.4 | AR81: 6.7 | AS81: 5.9 | AT81: =AP86/AT86*AP81+AQ86/AT86*AQ81+AR86/AT86*AR81+AS86/AT86*AS81 -> 6.5144842 | AU81: 8.2 | AV81: 4.8 | AW81: 4.2 | AX81: 5.4 | AY81: =AU86/AY86*AU81+AV86/AY86*AV81+AW86/AY86*AW81+AX86/AY86*AX81 -> 5.628802 | AZ81: 5.6 | BA81: 5.4 | BB81: 6 | BC81: 5.3 | BD81: =AZ86/BD86*AZ81+BA86/BD86*BA81+BB86/BD86*BB81+BC86/BD86*BC81 -> 5.5746247 | BE81: 3.8 | BF81: 3.9 | BG81: 3.6 | BH81: 4.3 | BI81: =BE86/BI86*BE81+BF86/BI86*BF81+BG86/BI86*BG81+BH86/BI86*BH81 -> 3.9049862
A82: Franchised SSS% | B82: 7.8 | C82: 8.4 | D82: 8.5 | E82: 7.4 | F82: 8 | G82: 8.9 | H82: 4.7 | I82: 8.3 | J82: 8.1 | K82: 7.5 | L82: 7.7 | M82: 8.5 | N82: 7.4 | O82: 8.1 | P82: 8 | Q82: 9.8 | R82: 11.2 | S82: 10 | T82: 10.4 | U82: 10.4 | V82: 9.8 | W82: 0.8 | X82: -10 | Y82: 7.9 | Z82: 2.1 | AA82: 6 | AB82: 20.4 | AC82: 43.9 | AD82: 22.1 | AE82: 22.4 | AF82: 26.8 | AG82: 15.5 | AH82: 12.1 | AI82: 9.8 | AJ82: 15.5 | AK82: 11.2 | AL82: 12.9 | AM82: 12.8 | AN82: 10.8 | AO82: =AK86/AO86*AK82+AL86/AO86*AL82+AM86/AO86*AM82+AN86/AO86*AN82 -> 11.914631 | AP82: 8 | AQ82: 8 | AR82: 6.4 | AS82: 5.1 | AT82: =AP86/AT86*AP82+AQ86/AT86*AQ82+AR86/AT86*AR82+AS86/AT86*AS82 -> 6.8034651 | AU82: 7.8 | AV82: 6.6 | AW82: 5.44 | AX82: 6.5 | AY82: =AU86/AY86*AU82+AV86/AY86*AV82+AW86/AY86*AW82+AX86/AY86*AX82 -> 6.5664036 | AZ82: 6.1 | BA82: 5.3 | BB82: 5.5 | BC82: 4.8 | BD82: =AZ86/BD86*AZ82+BA86/BD86*BA82+BB86/BD86*BB82+BC86/BD86*BC82 -> 5.3955095 | BE82: 3.3 | BF82: 4.2 | BG82: 3.9 | BH82: 3.9 | BI82: =BE86/BI86*BE82+BF86/BI86*BF82+BG86/BI86*BG82+BH86/BI86*BH82 -> 3.8317717
A83: System-wide SSS% | G83: 9 | H83: 3.9 | I83: 7.9 | J83: 8.6 | K83: 7.4 | L83: 7.9 | M83: 9.6 | N83: 7.9 | O83: 7.6 | P83: 8.3 | Q83: 9.8 | R83: 10.8 | S83: 9.7 | T83: 10 | U83: 10.1 | V83: 8.3 | W83: 0.7 | X83: -8 | Y83: 8.3 | Z83: 2.3 | AA83: 6 | AB83: 20.2 | AC83: 40.5 | AD83: 20.1 | AE83: 21.2 | AF83: 24.7 | AG83: 13.1 | AH83: 9.9 | AI83: 9.2 | AJ83: 13.7 | AK83: 11.9 | AL83: 13.5 | AM83: 12.5 | AN83: 10 | AO83: =AK86/AO86*AK83+AL86/AO86*AL83+AM86/AO86*AM83+AN86/AO86*AN83 -> 11.924884 | AP83: 7.1 | AQ83: 7.7 | AR83: 6.5 | AS83: 5.4 | AT83: =AP86/AT86*AP83+AQ86/AT86*AQ83+AR86/AT86*AR83+AS86/AT86*AS83 -> 6.630593 | AU83: =((AU43/AU52)*AU81)+((AU50/AU52)*AU82) -> 7.9822983 | AV83: =((AV43/AV52)*AV81)+((AV50/AV52)*AV82) -> 5.7770934 | AW83: =((AW43/AW52)*AW81)+((AW50/AW52)*AW82) -> 4.8661205 | AX83: =((AX43/AX52)*AX81)+((AX50/AX52)*AX82) -> 5.9873394 | AY83: =AU86/AY86*AU83+AV86/AY86*AV83+AW86/AY86*AW83+AX86/AY86*AX83 -> 6.133235 | AZ83: 5.8 | BA83: =((BA43/BA52)*BA81)+((BA50/BA52)*BA82) -> 5.3503095 | BB83: =((BB43/BB52)*BB81)+((BB50/BB52)*BB82) -> 5.751417 | BC83: =((BC43/BC52)*BC81)+((BC50/BC52)*BC82) -> 5.0511867 | BD83: =AZ86/BD86*AZ83+BA86/BD86*BA83+BB86/BD86*BB83+BC86/BD86*BC83 -> 5.474678 | BE83: =((BE43/BE52)*BE81)+((BE50/BE52)*BE82) -> 3.5506801 | BF83: =((BF43/BF52)*BF81)+((BF50/BF52)*BF82) -> 4.0498854 | BG83: =((BG43/BG52)*BG81)+((BG50/BG52)*BG82) -> 3.7502808 | BH83: =((BH43/BH52)*BH81)+((BH50/BH52)*BH82) -> 4.099487 | BI83: =BE86/BI86*BE83+BF86/BI86*BF83+BG86/BI86*BG83+BH86/BI86*BH83 -> 3.8684475
A85: INCOME STATEMENT
A86: Sales | B86: 456 | C86: 480 | D86: 499 | E86: 494 | F86: =SUM(B86:E86) -> 1929 | G86: 489 | H86: 514 | I86: 534 | J86: 547 | K86: =SUM(G86:J86) -> 2084 | L86: 545 | M86: 569 | N86: 577 | O86: 594 | P86: =SUM(L86:O86) -> 2285 | Q86: 557 | R86: 591 | S86: 613 | T86: 629 | U86: =SUM(Q86:T86) -> 2390 | V86: 607 | W86: 578 | X86: 516 | Y86: 652 | Z86: =SUM(V86:Y86) -> 2353 | AA86: 653 | AB86: 701 | AC86: 792 | AD86: 835 | AE86: =SUM(AA86:AD86) -> 2981 | AF86: 287.3 | AG86: 296 | AH86: 317.4 | AI86: 335.4 | AJ86: =SUM(AF86:AI86) -> 1236.1 | AK86: 332.8 | AL86: 344.5 | AM86: 376.2 | AN86: 390 | AO86: =SUM(AK86:AN86) -> 1443.5 | AP86: 373.4 | AQ86: 388.7 | AR86: 421.4 | AS86: 435.5 | AT86: =SUM(AP86:AS86) -> 1619 | AU86: 414.3 | AV86: 403.2 | AW86: 439 | AX86: 453.8 | AY86: =SUM(AU86:AX86) -> 1710.3 | AZ86: 461.8 | BA86: =BA67 -> 505.72102 | BB86: =BB67 -> 541.76954 | BC86: =BC67 -> 560.26367 | BD86: =SUM(AZ86:BC86) -> 2069.5542 | BE86: =BE67 -> 535.22056 | BF86: =BF67 -> 551.63697 | BG86: =BG67 -> 589.76298 | BH86: =BH67 -> 604.56346 | BI86: =SUM(BE86:BH86) -> 2281.184
A87: Cost of Sales | B87: 280 | C87: 288 | D87: 300 | E87: 300 | F87: =SUM(B87:E87) -> 1168 | G87: 304 | H87: 316 | I87: 337 | J87: 349 | K87: =SUM(G87:J87) -> 1306 | L87: 350 | M87: 362 | N87: 376 | O87: 391 | P87: =SUM(L87:O87) -> 1479 | Q87: 374 | R87: 388 | S87: 406 | T87: 412 | U87: =SUM(Q87:T87) -> 1580 | V87: 396 | W87: 371 | X87: 329 | Y87: 394 | Z87: =SUM(V87:Y87) -> 1490 | AA87: 425 | AB87: 454 | AC87: 533 | AD87: 589 | AE87: =SUM(AA87:AD87) -> 2001 | AF87: 175.1 | AG87: 188.7 | AH87: 189.6 | AI87: 206.3 | AJ87: =SUM(AF87:AI87) -> 759.7 | AK87: 214 | AL87: 217.8 | AM87: 225.5 | AN87: 241.7 | AO87: =SUM(AK87:AN87) -> 899 | AP87: 238.6 | AQ87: 242.5 | AR87: 253.9 | AS87: 265.2 | AT87: =SUM(AP87:AS87) -> 1000.2 | AU87: 261.4 | AV87: 252.7 | AW87: 261.4 | AX87: 276.3 | AY87: =SUM(AU87:AX87) -> 1051.8 | AZ87: 289.3 | BA87: =BA86-BA88 -> 314.80883 | BB87: =BB86-BB88 -> 326.59695 | BC87: =BC86-BC88 -> 342.68409 | BD87: =SUM(AZ87:BC87) -> 1273.3899 | BE87: =BE86-BE88 -> 336.32036 | BF87: =BF86-BF88 -> 343.44544 | BG87: =BG86-BG88 -> 352.00364 | BH87: =BH86-BH88 -> 363.30981 | BI87: =SUM(BE87:BH87) -> 1395.0792
A88: Gross Profit | B88: =B86-B87 -> 176 | C88: =C86-C87 -> 192 | D88: =D86-D87 -> 199 | E88: =E86-E87 -> 194 | F88: =F86-F87 -> 761 | G88: =G86-G87 -> 185 | H88: =H86-H87 -> 198 | I88: =I86-I87 -> 197 | ... AZ88: =AZ86-AZ87 -> 172.5 | BA88: =BA73 -> 190.91218 | BB88: =BB73 -> 215.17259 | BC88: =BC73 -> 217.57958 | BD88: =BD86-BD87 -> 796.16435 | BE88: =BE73 -> 198.9002 | BF88: =BF73 -> 208.19153 | BG88: =BG73 -> 237.75934 | BH88: =BH73 -> 241.25365 | BI88: =BI86-BI87 -> 886.10472
A89: SG&A Expenses | B89: 87 | C89: 93 | D89: 93 | E89: 92 | F89: =SUM(B89:E89) -> 365 | G89: 95 | H89: 97 | I89: 100 | J89: 83 | K89: =SUM(G89:J89) -> 375 | L89: 107 | M89: 111 | N89: 110 | O89: 102 | P89: =SUM(L89:O89) -> 430 | Q89: 105 | R89: 113 | S89: 116 | T89: 115 | U89: =SUM(Q89:T89) -> 449 | V89: 117 | W89: 96 | X89: 106 | Y89: 123 | Z89: =SUM(V89:Y89) -> 442 | AA89: 117 | AB89: 129 | AC89: 136 | AD89: 138 | AE89: =SUM(AA89:AD89) -> 520 | AF89: 60.2 | AG89: 63.2 | AH89: 59.2 | AI89: 62.1 | AJ89: =SUM(AF89:AI89) -> 244.7 | AK89: 66 | AL89: 62.6 | AM89: 65.6 | AN89: 70.3 | AO89: =SUM(AK89:AN89) -> 264.5 | AP89: 74.5 | AQ89: 72.3 | AR89: 77.2 | AS89: 81.1 | AT89: =SUM(AP89:AS89) -> 305.1 | AU89: 82.8 | AV89: 86.3 | AW89: 85.5 | AX89: 95.3 | AY89: =SUM(AU89:AX89) -> 349.9 | AZ89: 106.8 | BA89: =BA86*(BA136/100) -> 106.70713 | BB89: =BB86*(BB136/100) -> 108.35391 | BC89: =BC86*(BC136/100) -> 109.25142 | BD89: =SUM(AZ89:BC89) -> 431.11246 | BE89: =BE86*(BE136/100) -> 111.32588 | BF89: =BF86*(BF136/100) -> 113.08558 | BG89: =BG86*(BG136/100) -> 113.82425 | BH89: =BH86*(BH136/100) -> 115.47162 | BI89: =SUM(BE89:BH89) -> 453.70733
A90: Other Expenses (Income) | B90: =-5 -> -5 | C90: =-6+1 -> -5 | D90: -5 | E90: =6-3 -> 3 | F90: =SUM(B90:E90) -> -12 | G90: =6-10 -> -4 | H90: =6-5 -> 1 | I90: =15-5 -> 10 | J90: =5-5 -> 0 | K90: =SUM(G90:J90) -> 7 | L90: =9-9 -> 0 | M90: =8-12 -> -4 | N90: =-3-8 -> -11 | O90: -4 | P90: =SUM(L90:O90) -> -19 | Q90: -9 | R90: =3-9 -> -6 | S90: -11 | T90: -11 | U90: =SUM(Q90:T90) -> -37 | V90: =-1-9 -> -10 | W90: -6 | X90: =1-8 -> -7 | Y90: =-30-11 -> -41 | Z90: =SUM(V90:Y90) -> -64 | AA90: =1-14 -> -13 | AB90: -13 | AC90: =1-9 -> -8 | AD90: =-26-8 -> -34 | AE90: =SUM(AA90:AD90) -> -68 | AF90: =2.8-2.8 -> 0 | AG90: =6.2-2.1 -> 4.1 | AH90: 7.5 | AI90: =1.6-1.8 -> -0.2 | AJ90: =SUM(AF90:AI90) -> 11.4 | AK90: =25.4-1.9 -> 23.5 | AL90: =3.8-0.9 -> 2.9 | AM90: =1.6-3 -> -1.4 | AN90: =5.8+2 -> 7.8 | AO90: =SUM(AK90:AN90) -> 32.8 | AP90: =0.1-2.6 -> -2.5 | AQ90: =0-2.5 -> -2.5 | AR90: =0.1-3.2 -> -3.1 | AS90: =-0.9-44.5 -> -45.4 | AT90: =SUM(AP90:AS90) -> -53.5 | AU90: =0.4-74.1 -> -73.7 | AV90: =0.8-3.5 -> -2.7 | AW90: =-3+0.4 -> -2.6 | AX90: =-2.1-0.2 -> -2.3 | AY90: =SUM(AU90:AX90) -> -81.3 | AZ90: =5.2+42.2 -> 47.4 | BA90: -5 | BB90: -5 | BC90: -5 | BD90: =SUM(AZ90:BC90) -> 32.4 | BE90: -5 | BF90: -5 | BG90: -5 | BH90: -5 | BI90: =SUM(BE90:BH90) -> -20
A91: Operating Income | B91: =B88-(B89+B90) -> 94 | C91: =C88-(C89+C90) -> 104 | D91: =D88-(D89+D90) -> 111 | E91: =E88-(E89+E90) -> 99 | F91: =F88-SUM(F89:F90) -> 408 | G91: =G88-(G89+G90) -> 94 | H91: =H88-(H89+H90) -> 100 | I91: =I88-(I89+I90) -> 87 | J91: =J88-(J89+J90) -> 115 | K91: =K88-SUM(K89:K90) -> 396 | L91: =L88-(L89+L90) -> 88 | M91: =M88-(M89+M90) -> 100 | N91: =N88-(N89+N90) -> 102 | O91: =O88-(O89+O90) -> 105 | P91: =P88-SUM(P89:P90) -> 395 | Q91: =Q88-(Q89+Q90) -> 87 | R91: =R88-(R89+R90) -> 96 | S91: =S88-(S89+S90) -> 102 | T91: =T88-(T89+T90) -> 113 | U91: =U88-SUM(U89:U90) -> 398 | V91: =V88-(V89+V90) -> 104 | W91: =W88-(W89+W90) -> 117 | X91: =X88-(X89+X90) -> 88 | Y91: =Y88-(Y89+Y90) -> 176 | Z91: =Z88-SUM(Z89:Z90) -> 485 | AA91: =AA88-(AA89+AA90) -> 124 | AB91: =AB88-(AB89+AB90) -> 131 | AC91: =AC88-(AC89+AC90) -> 131 | AD91: =AD88-(AD89+AD90) -> 142 | AE91: =AE88-SUM(AE89:AE90) -> 528 | AF91: =AF88-(AF89+AF90) -> 52 | AG91: =AG88-(AG89+AG90) -> 40 | AH91: =AH88-(AH89+AH90) -> 61.1 | AI91: =AI88-(AI89+AI90) -> 67.2 | AJ91: =AJ88-SUM(AJ89:AJ90) -> 220.3 | AK91: =AK88-(AK89+AK90) -> 29.3 | AL91: =AL88-(AL89+AL90) -> 61.2 | AM91: =AM88-(AM89+AM90) -> 86.5 | AN91: =AN88-(AN89+AN90) -> 70.2 | AO91: =AO88-SUM(AO89:AO90) -> 247.2 | AP91: =AP88-(AP89+AP90) -> 62.8 | AQ91: =AQ88-(AQ89+AQ90) -> 76.4 | AR91: =AR88-(AR89+AR90) -> 93.4 | AS91: =AS88-(AS89+AS90) -> 134.6 | AT91: =AT88-SUM(AT89:AT90) -> 367.2 | AU91: =AU88-(AU89+AU90) -> 143.8 | AV91: =AV88-(AV89+AV90) -> 66.9 | AW91: =AW88-(AW89+AW90) -> 94.7 | AX91: =AX88-(AX89+AX90) -> 84.5 | AY91: =AY88-SUM(AY89:AY90) -> 389.9 | AZ91: =AZ88-(AZ89+AZ90) -> 18.3 | BA91: =BA88-(BA89+BA90) -> 89.20505 | BB91: =BB88-(BB89+BB90) -> 111.81868 | BC91: =BC88-(BC89+BC90) -> 113.32816 | BD91: =BD88-SUM(BD89:BD90) -> 332.6519 | BE91: =BE88-(BE89+BE90) -> 92.574328 | BF91: =BF88-(BF89+BF90) -> 100.10595 | BG91: =BG88-(BG89+BG90) -> 128.93508 | BH91: =BH88-(BH89+BH90) -> 130.78203 | BI91: =BI88-SUM(BI89:BI90) -> 452.39739
A92: Net Pension Expense (Income) | B92: -2 | C92: 1 | D92: -2 | E92: -19 | F92: =SUM(B92:E92) -> -22 | G92: -26 | H92: -17 | I92: -17 | J92: -76 | K92: =SUM(G92:J92) -> -136 | L92: -10 | M92: -10 | N92: -10 | O92: 30 | P92: =SUM(L92:O92) -> 0 | Q92: -2 | R92: -3 | S92: -2 | T92: 67 | U92: =SUM(Q92:T92) -> 60 | V92: -9 | W92: -9 | X92: -9 | Y92: -32 | Z92: =SUM(V92:Y92) -> -59 | AA92: -13 | AB92: -14 | AC92: -14 | AD92: -85 | AE92: =SUM(AA92:AD92) -> -126 | AF92: -9.3 | AG92: -9.2 | AH92: -9.2 | AI92: 34.6 | AJ92: =SUM(AF92:AI92) -> 6.9 | AK92: 3.7 | AL92: 3.6 | AM92: 3.7 | AN92: -38.6 | AO92: =SUM(AK92:AN92) -> -27.6 | AP92: 3.4 | AQ92: 3.6 | AR92: 3.4 | AS92: 1.3 | AT92: =SUM(AP92:AS92) -> 11.7 | AU92: -0.9 | AV92: -0.9 | AW92: -0.9 | AX92: 26.3 | AY92: =SUM(AU92:AX92) -> 23.6 | AZ92: -1.2 | BA92: 3 | BB92: 3 | BC92: 3 | BD92: =SUM(AZ92:BC92) -> 7.8 | BE92: 3 | BF92: 3 | BG92: 3 | BH92: 3 | BI92: =SUM(BE92:BH92) -> 12
A93: Interest Expense | B93: 0 | C93: 0 | D93: 0 | E93: 9 | F93: =SUM(B93:E93) -> 9 | G93: 10 | H93: 8 | I93: 10 | J93: 14 | K93: =SUM(G93:J93) -> 42 | L93: 14 | M93: 16 | N93: 15 | O93: 18 | P93: =SUM(L93:O93) -> 63 | Q93: 17 | R93: 19 | S93: 19 | T93: 18 | U93: =SUM(Q93:T93) -> 73 | V93: 16 | W93: 38 | X93: 19 | Y93: 20 | Z93: =SUM(V93:Y93) -> 93 | AA93: 20 | AB93: 55 | AC93: 17 | AD93: 19 | AE93: =SUM(AA93:AD93) -> 111 | AF93: 17 | AG93: 16.9 | AH93: 17.3 | AI93: 18.1 | AJ93: =SUM(AF93:AI93) -> 69.3 | AK93: 18.7 | AL93: 13.3 | AM93: -4.6 | AN93: 10.9 | AO93: =SUM(AK93:AN93) -> 38.3 | AP93: 13.6 | AQ93: 15.5 | AR93: 24.8 | AS93: 18 | AT93: =SUM(AP93:AS93) -> 71.9 | AU93: 17.5 | AV93: 16.9 | AW93: 18.6 | AX93: 21 | AY93: =SUM(AU93:AX93) -> 74 | AZ93: 25.5 | BA93: 33 | BB93: 33 | BC93: 33 | BD93: =SUM(AZ93:BC93) -> 124.5 | BE93: 33 | BF93: 33 | BG93: 32 | BH93: 32 | BI93: =SUM(BE93:BH93) -> 130
A94: EBT | B94: =B91-(B92+B93) -> 96 | C94: =C91-(C92+C93) -> 103 | D94: =D91-(D92+D93) -> 113 | E94: =E91-(E92+E93) -> 109 | F94: =F91-SUM(F92:F93) -> 421 | G94: =G91-(G92+G93) -> 110 | H94: =H91-(H92+H93) -> 109 | I94: =I91-(I92+I93) -> 94 | J94: =J91-(J92+J93) -> 177 | K94: =K91-SUM(K92:K93) -> 490 | L94: =L91-(L92+L93) -> 84 | M94: =M91-(M92+M93) -> 94 | N94: =N91-(N92+N93) -> 97 | O94: =O91-(O92+O93) -> 57 | P94: =P91-SUM(P92:P93) -> 332 | Q94: =Q91-(Q92+Q93) -> 72 | R94: =R91-(R92+R93) -> 80 | S94: =S91-(S92+S93) -> 85 | T94: =T91-(T92+T93) -> 28 | U94: =U91-SUM(U92:U93) -> 265 | V94: =V91-(V92+V93) -> 97 | W94: =W91-(W92+W93) -> 88 | X94: =X91-(X92+X93) -> 78 | Y94: =Y91-(Y92+Y93) -> 188 | Z94: =Z91-SUM(Z92:Z93) -> 451 | AA94: =AA91-(AA92+AA93) -> 117 | AB94: =AB91-(AB92+AB93) -> 90 | AC94: =AC91-(AC92+AC93) -> 128 | AD94: =AD91-(AD92+AD93) -> 208 | AE94: =AE91-SUM(AE92:AE93) -> 543 | AF94: =AF91-(AF92+AF93) -> 44.3 | AG94: =AG91-(AG92+AG93) -> 32.3 | AH94: =AH91-(AH92+AH93) -> 53 | AI94: =AI91-(AI92+AI93) -> 14.5 | AJ94: =AJ91-SUM(AJ92:AJ93) -> 144.1 | AK94: =AK91-(AK92+AK93) -> 6.9 | AL94: =AL91-(AL92+AL93) -> 44.3 | AM94: =AM91-(AM92+AM93) -> 87.4 | AN94: =AN91-(AN92+AN93) -> 97.9 | AO94: =AO91-SUM(AO92:AO93) -> 236.5 | AP94: =AP91-(AP92+AP93) -> 45.8 | AQ94: =AQ91-(AQ92+AQ93) -> 57.3 | AR94: =AR91-(AR92+AR93) -> 65.2 | AS94: =AS91-(AS92+AS93) -> 115.3 | AT94: =AT91-SUM(AT92:AT93) -> 283.6 | AU94: =AU91-(AU92+AU93) -> 127.2 | AV94: =AV91-(AV92+AV93) -> 50.9 | AW94: =AW91-(AW92+AW93) -> 77 | AX94: =AX91-(AX92+AX93) -> 37.2 | AY94: =AY91-SUM(AY92:AY93) -> 292.3 | AZ94: =AZ91-(AZ92+AZ93) -> -6 | BA94: =BA91-(BA92+BA93) -> 53.20505 | BB94: =BB91-(BB92+BB93) -> 75.818681 | BC94: =BC91-(BC92+BC93) -> 77.328165 | BD94: =BD91-SUM(BD92:BD93) -> 200.3519 | BE94: =BE91-(BE92+BE93) -> 56.574328 | BF94: =BF91-(BF92+BF93) -> 64.105951 | BG94: =BG91-(BG92+BG93) -> 93.935082 | BH94: =BH91-(BH92+BH93) -> 95.782029 | BI94: =BI91-SUM(BI92:BI93) -> 310.39739
A95: Income Tax Expense | B95: 31 | C95: 35 | D95: 38 | E95: 44 | F95: =SUM(B95:E95) -> 148 | G95: 38 | H95: 38 | I95: 38 | J95: 72 | K95: =SUM(G95:J95) -> 186 | L95: 94 | M95: 27 | N95: 33 | O95: 12 | P95: =SUM(L95:O95) -> 166 | Q95: 19 | R95: 17 | S95: 20 | T95: 1 | U95: =SUM(Q95:T95) -> 57 | V95: 24 | W95: 25 | X95: 19 | Y95: 66 | Z95: =SUM(V95:Y95) -> 134 | AA95: 30 | AB95: 22 | AC95: 31 | AD95: 40 | AE95: =SUM(AA95:AD95) -> 123 | AF95: 10.1 | AG95: 9.3 | AH95: 13.2 | AI95: 2.1 | AJ95: =SUM(AF95:AI95) -> 34.7 | AK95: -20.1 | AL95: 11.4 | AM95: 22.9 | AN95: 22.9 | AO95: =SUM(AK95:AN95) -> 37.1 | AP95: 11.9 | AQ95: 14 | AR95: 17 | AS95: 26.2 | AT95: =SUM(AP95:AS95) -> 69.1 | AU95: 33.3 | AV95: 12.6 | AW95: 20 | AX95: 11.6 | AY95: =SUM(AU95:AX95) -> 77.5 | AZ95: 26.2 | BA95: =BA94*(BA143/100) -> 12.769212 | BB95: =BB94*(BB143/100) -> 18.196483 | BC95: =BC94*(BC143/100) -> 18.558759 | BD95: =SUM(AZ95:BC95) -> 75.724455 | BE95: =BE94*(BE143/100) -> 13.577839 | BF95: =BF94*(BF143/100) -> 15.385428 | BG95: =BG94*(BG143/100) -> 22.54442 | BH95: =BH94*(BH143/100) -> 22.987687 | BI95: =SUM(BE95:BH95) -> 74.495373
A96: Net Income from continuing operations | B96: =B94-B95 -> 65 | C96: =C94-C95 -> 68 | D96: =D94-D95 -> 75 | E96: =E94-E95 -> 65 | F96: =F94-F95 -> 273 | G96: =G94-G95 -> 72 | H96: =H94-H95 -> 71 | I96: =I94-I95 -> 56 | ... BI96: =BI94-BI95 -> 235.90202
A97: Net Income from discontinued operations | B97: 0 | C97: 0 | D97: 0 | E97: 0 | F97: =SUM(B97:E97) -> 0 | G97: 0 | H97: 0 | I97: 0 | J97: 0 | K97: =SUM(G97:J97) -> 0 | L97: 0 | M97: 0 | N97: 0 | O97: 0 | P97: =SUM(L97:O97) -> 0 | Q97: 0 | R97: 0 | S97: 0 | T97: 0 | U97: =SUM(Q97:T97) -> 0 | V97: 0 | W97: 0 | X97: 0 | Y97: 0 | Z97: =SUM(V97:Y97) -> 0 | AA97: 0 | AB97: 0 | AC97: 0 | AD97: 0 | AE97: =SUM(AA97:AD97) -> 0 | AF97: 52.8 | AG97: 58.4 | AH97: 58.4 | AI97: 145.3 | AJ97: =SUM(AF97:AI97) -> 314.9 | AK97: 54.9 | AL97: 1194.4 | AM97: -2.9 | AN97: -29.8 | AO97: =SUM(AK97:AN97) -> 1216.6 | AP97: -2 | AQ97: -1.9 | AR97: -2.3 | AS97: 3.2 | AT97: =SUM(AP97:AS97) -> -3 | AU97: -2.3 | AV97: -0.7 | AW97: -0.5 | AX97: -0.6 | AY97: =SUM(AU97:AX97) -> -4.1 | AZ97: -0.6 | BA97: 0 | BB97: 0 | BC97: 0 | BD97: =SUM(AZ97:BC97) -> -0.6 | BE97: 0 | BF97: 0 | BG97: 0 | BH97: 0 | BI97: =SUM(BE97:BH97) -> 0
A98: Total Net Income | B98: =SUM(B96:B97) -> 65 | C98: =SUM(C96:C97) -> 68 | D98: =SUM(D96:D97) -> 75 | E98: =SUM(E96:E97) -> 65 | F98: =SUM(B98:E98) -> 273 | G98: =SUM(G96:G97) -> 72 | H98: =SUM(H96:H97) -> 71 | I98: =SUM(I96:I97) -> 56 | J98: =SUM(J96:J97) -> 105 | K98: =SUM(G98:J98) -> 304 | L98: =SUM(L96:L97) -> -10 | M98: =SUM(M96:M97) -> 67 | N98: =SUM(N96:N97) -> 64 | O98: =SUM(O96:O97) -> 45 | P98: =SUM(L98:O98) -> 166 | Q98: =SUM(Q96:Q97) -> 53 | R98: =SUM(R96:R97) -> 63 | S98: =SUM(S96:S97) -> 65 | T98: =SUM(T96:T97) -> 27 | U98: =SUM(Q98:T98) -> 208 | V98: =SUM(V96:V97) -> 73 | W98: =SUM(W96:W97) -> 63 | X98: =SUM(X96:X97) -> 59 | Y98: =SUM(Y96:Y97) -> 122 | Z98: =SUM(V98:Y98) -> 317 | AA98: =SUM(AA96:AA97) -> 87 | AB98: =SUM(AB96:AB97) -> 68 | AC98: =SUM(AC96:AC97) -> 97 | AD98: =SUM(AD96:AD97) -> 168 | AE98: =SUM(AA98:AD98) -> 420 | AF98: =SUM(AF96:AF97) -> 87 | AG98: =SUM(AG96:AG97) -> 81.4 | AH98: =SUM(AH96:AH97) -> 98.2 | AI98: =SUM(AI96:AI97) -> 157.7 | AJ98: =SUM(AF98:AI98) -> 424.3 | AK98: =SUM(AK96:AK97) -> 81.9 | AL98: =SUM(AL96:AL97) -> 1227.3 | AM98: =SUM(AM96:AM97) -> 61.6 | AN98: =SUM(AN96:AN97) -> 45.2 | AO98: =SUM(AK98:AN98) -> 1416 | AP98: =SUM(AP96:AP97) -> 31.9 | AQ98: =SUM(AQ96:AQ97) -> 41.4 | AR98: =SUM(AR96:AR97) -> 45.9 | AS98: =SUM(AS96:AS97) -> 92.3 | AT98: =SUM(AP98:AS98) -> 211.5 | AU98: =SUM(AU96:AU97) -> 91.6 | AV98: =SUM(AV96:AV97) -> 37.6 | AW98: =SUM(AW96:AW97) -> 56.5 | AX98: =SUM(AX96:AX97) -> 25 | AY98: =SUM(AU98:AX98) -> 210.7 | AZ98: =SUM(AZ96:AZ97) -> -32.8 | BA98: =SUM(BA96:BA97) -> 40.435838 | BB98: =SUM(BB96:BB97) -> 57.622197 | BC98: =SUM(BC96:BC97) -> 58.769405 | BD98: =SUM(AZ98:BC98) -> 124.02744 | BE98: =SUM(BE96:BE97) -> 42.996489 | BF98: =SUM(BF96:BF97) -> 48.720523 | BG98: =SUM(BG96:BG97) -> 71.390662 | BH98: =SUM(BH96:BH97) -> 72.794342 | BI98: =SUM(BE98:BH98) -> 235.90202
A100: Net Pension Expenses (Income) | B100: 0 | C100: 5 | D100: 0 | E100: -23 | F100: =SUM(B100:E100) -> -18 | G100: 0 | H100: 0 | I100: 0 | J100: -60 | K100: =SUM(G100:J100) -> -60 | L100: =L92 -> -10 | M100: =M92 -> -10 | N100: =N92 -> -10 | O100: =O92 -> 30 | P100: =SUM(L100:O100) -> 0 | Q100: =Q92 -> -2 | R100: =R92 -> -3 | S100: =S92 -> -2 | T100: =T92 -> 67 | U100: =SUM(Q100:T100) -> 60 | V100: =V92 -> -9 | W100: =W92 -> -9 | X100: =X92 -> -9 | Y100: =Y92 -> -32 | Z100: =SUM(V100:Y100) -> -59 | AA100: =AA92 -> -13 | AB100: =AB92 -> -14 | AC100: =AC92 -> -14 | AD100: =AD92 -> -85 | AE100: =SUM(AA100:AD100) -> -126 | AF100: -9.3 | AG100: -9.2 | AH100: -9.2 | AI100: 34.6 | AJ100: =SUM(AF100:AI100) -> 6.9 | AK100: 3.7 | AL100: =AL92 -> 3.6 | AM100: =AM92 -> 3.7 | AN100: =AN92 -> -38.6 | AO100: =SUM(AK100:AN100) -> -27.6 | AP100: =AP92 -> 3.4 | AQ100: =AQ92 -> 3.6 | AR100: =AR92 -> 3.4 | AS100: =AS92 -> 1.3 | AT100: =SUM(AP100:AS100) -> 11.7 | AU100: =AU92 -> -0.9 | AV100: =AV92 -> -0.9 | AW100: =AW92 -> -0.9 | AX100: =AX92 -> 26.3 | AY100: =SUM(AU100:AX100) -> 23.6 | AZ100: =AZ92 -> -1.2 | BA100: =BA92 -> 3 | BB100: =BB92 -> 3 | BC100: =BC92 -> 3 | BD100: =SUM(AZ100:BC100) -> 7.8 | BE100: =BE92 -> 3 | BF100: =BF92 -> 3 | BG100: =BG92 -> 3 | BH100: =BH92 -> 3 | BI100: =SUM(BE100:BH100) -> 12
A101: Net Legacy and Seperation Related Expenses | B101: 0 | C101: 0 | D101: 0 | E101: 6 | F101: =SUM(B101:E101) -> 6 | G101: 0 | H101: -6 | I101: 15 | J101: 5 | K101: =SUM(G101:J101) -> 14 | L101: 9 | M101: 8 | N101: -3 | O101: 0 | P101: =SUM(L101:O101) -> 14 | Q101: 0 | R101: 3 | S101: 0 | T101: 0 | U101: =SUM(Q101:T101) -> 3 | V101: -1 | W101: 0 | X101: 1 | Y101: -30 | Z101: =SUM(V101:Y101) -> -30 | AA101: 1 | AB101: 0 | AC101: 1 | AD101: -26 | AE101: =SUM(AA101:AD101) -> -24 | AF101: 2.8 | AG101: 6.2 | AH101: 9.9 | AI101: 1.6 | AJ101: =SUM(AF101:AI101) -> 20.5 | AK101: 25.4 | AL101: 3.8 | AM101: 1.6 | AN101: 2 | AO101: =SUM(AK101:AN101) -> 32.8 | AP101: 0.1 | AQ101: 0 | AR101: 0.1 | AS101: -0.9 | AT101: =SUM(AP101:AS101) -> -0.7 | AU101: 0.4 | AV101: 0.8 | AW101: 0.4 | AX101: -0.2 | AY101: =SUM(AU101:AX101) -> 1.4 | AZ101: 5.2 | BA101: 0 | BB101: 0 | BC101: 0 | BD101: =SUM(AZ101:BC101) -> 5.2 | BE101: 0 | BF101: 0 | BG101: 0 | BH101: 0 | BI101: =SUM(BE101:BH101) -> 0
A102: Information Technology Transition Costs | B102: 0 | C102: 0 | D102: 0 | E102: 0 | F102: =SUM(B102:E102) -> 0 | G102: 0 | H102: 0 | I102: 0 | J102: 0 | K102: =SUM(G102:J102) -> 0 | L102: 0 | M102: 0 | N102: 0 | O102: 0 | P102: =SUM(L102:O102) -> 0 | Q102: 0 | R102: 0 | S102: 0 | T102: 0 | U102: =SUM(Q102:T102) -> 0 | V102: 0 | W102: 0 | X102: 0 | Y102: 0 | Z102: =SUM(V102:Y102) -> 0 | AA102: 0 | AB102: 0 | AC102: 0 | AD102: 0 | AE102: =SUM(AA102:AD102) -> 0 | AF102: 1 | AG102: 1.6 | AH102: 0 | AI102: 0 | AJ102: =SUM(AF102:AI102) -> 2.6 | AK102: -0.2 | AL102: 0.4 | AM102: 1.1 | AN102: 1.2 | AO102: =SUM(AK102:AN102) -> 2.5 | AP102: 2.7 | AQ102: 3.1 | AR102: 1.9 | AS102: 2.7 | AT102: =SUM(AP102:AS102) -> 10.4 | AU102: 1.5 | AV102: 4.9 | AW102: 2.1 | AX102: 3 | AY102: =SUM(AU102:AX102) -> 11.5 | AZ102: 3.1 | BA102: 0 | BB102: 0 | BC102: 0 | BD102: =SUM(AZ102:BC102) -> 3.1 | BE102: 0 | BF102: 0 | BG102: 0 | BH102: 0 | BI102: =SUM(BE102:BH102) -> 0
A103: Suspended Operations | B103: 0 | C103: 0 | D103: 0 | E103: 0 | F103: =SUM(B103:E103) -> 0 | G103: 0 | H103: 0 | I103: 0 | J103: 0 | K103: =SUM(G103:J103) -> 0 | L103: 0 | M103: 0 | N103: 0 | O103: 0 | P103: =SUM(L103:O103) -> 0 | Q103: 0 | R103: 0 | S103: 0 | T103: 0 | U103: =SUM(Q103:T103) -> 0 | V103: 0 | W103: 0 | X103: 0 | Y103: 0 | Z103: =SUM(V103:Y103) -> 0 | AA103: 0 | AB103: 0 | AC103: 0 | AD103: 0 | AE103: =SUM(AA103:AD103) -> 0 | AF103: -0.3 | AG103: 4 | AH103: -2.2 | AI103: -0.6 | AJ103: =SUM(AF103:AI103) -> 0.9 | AK103: 0.3 | AL103: 0.1 | AM103: -0.4 | AN103: 7.6 | AO103: =SUM(AK103:AN103) -> 7.6 | AP103: 0 | AQ103: 0 | AR103: 0 | AS103: 0 | AT103: =SUM(AP103:AS103) -> 0 | AU103: 0 | AV103: 0 | AW103: 0 | AX103: 0 | AY103: =SUM(AU103:AX103) -> 0 | AZ103: 0 | BA103: 0 | BB103: 0 | BC103: 0 | BD103: =SUM(AZ103:BC103) -> 0 | BE103: 0 | BF103: 0 | BG103: 0 | BH103: 0 | BI103: =SUM(BE103:BH103) -> 0
A104: Restructuring Related Adjustments | B104: 0 | C104: 0 | D104: 0 | E104: 0 | F104: =SUM(B104:E104) -> 0 | G104: 0 | H104: 0 | I104: 0 | J104: 0 | K104: =SUM(G104:J104) -> 0 | L104: 0 | M104: 0 | N104: 0 | O104: 0 | P104: =SUM(L104:O104) -> 0 | Q104: 0 | R104: 8 | S104: 4 | T104: 2 | U104: =SUM(Q104:T104) -> 14 | V104: 1 | W104: 0 | X104: 0 | Y104: -1 | Z104: =SUM(V104:Y104) -> 0 | AA104: 0 | AB104: 0 | AC104: 0 | AD104: 0 | AE104: =SUM(AA104:AD104) -> 0 | AF104: 0 | AG104: 0 | AI104: 0 | AJ104: =SUM(AF104:AI104) -> 0 | AK104: 0 | AL104: 0 | AM104: 0 | AN104: 0 | AO104: =SUM(AK104:AN104) -> 0 | AP104: 0 | AQ104: 0 | AR104: 0 | AS104: 0 | AT104: =SUM(AP104:AS104) -> 0 | AU104: 0 | AV104: 0 | AW104: 0 | AX104: 0 | AY104: =SUM(AU104:AX104) -> 0 | AZ104: 0 | BA104: 0 | BB104: 0 | BC104: 0 | BD104: =SUM(AZ104:BC104) -> 0 | BE104: 0 | BF104: 0 | BG104: 0 | BH104: 0 | BI104: =SUM(BE104:BH104) -> 0
A105: LIFO Charge | B105: 0 | C105: 0 | D105: 0 | E105: 0 | F105: =SUM(B105:E105) -> 0 | G105: 0 | H105: 0 | I105: 0 | J105: 0 | K105: =SUM(G105:J105) -> 0 | L105: 0 | M105: 0 | N105: 0 | O105: 0 | P105: =SUM(L105:O105) -> 0 | Q105: 0 | R105: 0 | S105: 0 | T105: 0 | U105: =SUM(Q105:T105) -> 0 | V105: 0 | W105: 0 | X105: 0 | Y105: 0 | Z105: =SUM(V105:Y105) -> 0 | AA105: 0 | AB105: 0 | AC105: 17 | AD105: 15 | AE105: =SUM(AA105:AD105) -> 32 | AF105: 0 | AG105: 0 | AH105: 0 | AI105: 0 | AJ105: =SUM(AF105:AI105) -> 0 | AK105: 0 | AL105: 0 | AM105: 0 | AN105: 0 | AO105: =SUM(AK105:AN105) -> 0 | AP105: 0 | AQ105: 0 | AR105: 0 | AS105: 0 | AT105: =SUM(AP105:AS105) -> 0 | AU105: 0 | AV105: 0 | AW105: 0 | AX105: 0 | AY105: =SUM(AU105:AX105) -> 0 | AZ105: 0 | BA105: 0 | BB105: 0 | BC105: 0 | BD105: =SUM(AZ105:BC105) -> 0 | BE105: 0 | BF105: 0 | BG105: 0 | BH105: 0 | BI105: =SUM(BE105:BH105) -> 0
A106: Business Interruption Losses (Recoveries) | B106: 0 | C106: 0 | D106: 0 | E106: 0 | F106: =SUM(B106:E106) -> 0 | G106: 0 | H106: 0 | I106: 0 | J106: 0 | K106: =SUM(G106:J106) -> 0 | L106: 0 | M106: 0 | N106: 0 | O106: 0 | P106: =SUM(L106:O106) -> 0 | Q106: 0 | R106: 1 | S106: 5 | T106: 0 | U106: =SUM(Q106:T106) -> 6 | V106: 0 | W106: 0 | X106: 0 | Y106: -2 | Z106: =SUM(V106:Y106) -> -2 | AA106: -1 | AB106: -2 | AC106: 0 | AD106: 0 | AE106: =SUM(AA106:AD106) -> -3 | AF106: 0 | AG106: 0 | AH106: 0 | AI106: 0 | AJ106: =SUM(AF106:AI106) -> 0 | AK106: 0 | AL106: 0 | AM106: 0 | AN106: 0 | AO106: =SUM(AK106:AN106) -> 0 | AP106: 0 | AQ106: 0 | AR106: 0 | AS106: 0 | AT106: =SUM(AP106:AS106) -> 0 | AU106: 0 | AV106: 0 | AW106: 0 | AX106: 0 | AY106: =SUM(AU106:AX106) -> 0 | AZ106: 0 | BA106: 0 | BB106: 0 | BC106: 0 | BD106: =SUM(AZ106:BC106) -> 0 | BE106: 0 | BF106: 0 | BG106: 0 | BH106: 0 | BI106: =SUM(BE106:BH106) -> 0
A107: Debt Extinguishment and Modification Costs | B107: 0 | C107: 0 | D107: 0 | E107: 0 | F107: =SUM(B107:E107) -> 0 | G107: 0 | H107: 0 | I107: 0 | J107: 0 | K107: =SUM(G107:J107) -> 0 | L107: 0 | M107: 0 | N107: 0 | O107: 0 | P107: =SUM(L107:O107) -> 0 | Q107: 0 | R107: 0 | S107: 0 | T107: 0 | U107: =SUM(Q107:T107) -> 0 | V107: 0 | W107: 19 | X107: 0 | Y107: 0 | Z107: =SUM(V107:Y107) -> 19 | AA107: 0 | AB107: 36 | AC107: 0 | AD107: 0 | AE107: =SUM(AA107:AD107) -> 36 | AF107: 0 | AG107: 0 | AH107: 0 | AI107: 0 | AJ107: =SUM(AF107:AI107) -> 0 | AK107: 0 | AL107: 0.9 | AM107: 0.1 | AN107: 0.1 | AO107: =SUM(AK107:AN107) -> 1.1 | AP107: 0 | AQ107: 0 | AR107: 7.3 | AS107: 0 | AT107: =SUM(AP107:AS107) -> 7.3 | AU107: 0 | AV107: 0 | AW107: 0 | AX107: 0 | AY107: =SUM(AU107:AX107) -> 0 | AZ107: 0 | BA107: 0 | BB107: 0 | BC107: 0 | BD107: =SUM(AZ107:BC107) -> 0 | BE107: 0 | BF107: 0 | BG107: 0 | BH107: 0 | BI107: =SUM(BE107:BH107) -> 0
A108: Other | B108: 0 | C108: -1 | D108: 0 | E108: 4 | F108: =SUM(B108:E108) -> 3 | G108: 0 | H108: 8 | I108: 0 | J108: =-14-5 -> -19 | K108: =SUM(G108:J108) -> -11 | L108: 0 | M108: 0 | N108: 2 | O108: 1 | P108: =SUM(L108:O108) -> 3 | Q108: 0 | R108: 0 | S108: 0 | T108: -4 | U108: =SUM(Q108:T108) -> -4 | V108: 0 | W108: 2 | X108: 0 | Y108: -11 | Z108: =SUM(V108:Y108) -> -9 | AA108: 0 | AB108: 0 | AC108: 0 | AD108: 0 | AE108: =SUM(AA108:AD108) -> 0 | AF108: 0 | AG108: 0 | AH108: 0 | AI108: 0 | AJ108: =SUM(AF108:AI108) -> 0 | AK108: 0 | AL108: 1 | AM108: 0 | AN108: 0.1 | AO108: =SUM(AK108:AN108) -> 1.1 | AP108: 0 | AQ108: 0 | AR108: 0.9 | AS108: -41.1 | AT108: =SUM(AP108:AS108) -> -40.2 | AU108: -70.9 | AV108: 3.4 | AW108: 3.5 | AX108: 13.8 | AY108: =SUM(AU108:AX108) -> -50.2 | AZ108: 62.2 | BA108: 1 | BB108: 1 | BC108: 1 | BD108: =SUM(AZ108:BC108) -> 65.2 | BE108: 1 | BF108: 1 | BG108: 1 | BH108: 1 | BI108: =SUM(BE108:BH108) -> 4
A109: Tax Impact of Adjustments | B109: 0 | C109: -2 | D109: 0 | E109: 7 | F109: =SUM(B109:E109) -> 5 | G109: 0 | H109: -2 | I109: -2 | J109: =34+3 -> 37 | K109: =SUM(G109:J109) -> 33 | L109: =71-1 -> 70 | M109: =1+2 -> 3 | N109: =6+3 -> 9 | O109: =-13+2 -> -11 | P109: =SUM(L109:O109) -> 71 | Q109: 0 | R109: =-3-2 -> -5 | S109: -2 | T109: -17 | U109: =SUM(Q109:T109) -> -24 | V109: 2 | W109: =-3+2 -> -1 | X109: 2 | Y109: =41-2 -> 39 | Z109: =SUM(V109:Y109) -> 42 | AA109: 3 | AB109: -5 | AC109: -1 | AD109: 18 | AE109: =SUM(AA109:AD109) -> 15 | AF109: 1.5 | AG109: 0.4 | AH109: -0.1 | AI109: -10.3 | AJ109: =SUM(AF109:AI109) -> -8.5 | AK109: -27.8 | AL109: -2.5 | AM109: -1.5 | AN109: 6.2 | AO109: =SUM(AK109:AN109) -> -25.6 | AP109: -1.6 | AQ109: -1.7 | AR109: -3.5 | AS109: 9.4 | AT109: =SUM(AP109:AS109) -> 2.6 | AU109: 17.9 | AV109: -2.3 | AW109: -1.3 | AX109: -10.5 | AY109: =SUM(AU109:AX109) -> 3.8 | AZ109: =6+4.5 -> 10.5 | BA109: 0 | BB109: 0 | BC109: 0 | BD109: =SUM(AZ109:BC109) -> 10.5 | BE109: 0 | BF109: 0 | BG109: 0 | BH109: 0 | BI109: =SUM(BE109:BH109) -> 0
A110: Total Adjustments | B110: =SUM(B100:B109) -> 0 | C110: =SUM(C100:C109) -> 2 | D110: =SUM(D100:D109) -> 0 | E110: =SUM(E100:E109) -> -6 | F110: =SUM(B110:E110) -> -4 | G110: =SUM(G100:G109) -> 0 | H110: =SUM(H100:H109) -> 0 | I110: =SUM(I100:I109) -> 13 | J110: =SUM(J100:J109) -> -37 | K110: =SUM(G110:J110) -> -24 | L110: =SUM(L100:L109) -> 69 | M110: =SUM(M100:M109) -> 1 | N110: =SUM(N100:N109) -> -2 | O110: =SUM(O100:O109) -> 20 | P110: =SUM(L110:O110) -> 88 | Q110: =SUM(Q100:Q109) -> -2 | R110: =SUM(R100:R109) -> 4 | S110: =SUM(S100:S109) -> 5 | T110: =SUM(T100:T109) -> 48 | U110: =SUM(Q110:T110) -> 55 | V110: =SUM(V100:V109) -> -7 | W110: =SUM(W100:W109) -> 11 | X110: =SUM(X100:X109) -> -6 | Y110: =SUM(Y100:Y109) -> -37 | Z110: =SUM(V110:Y110) -> -39 | AA110: =SUM(AA100:AA109) -> -10 | AB110: =SUM(AB100:AB109) -> 15 | AC110: =SUM(AC100:AC109) -> 3 | AD110: =SUM(AD100:AD109) -> -78 | AE110: =SUM(AA110:AD110) -> -70 | AF110: =SUM(AF100:AF109) -> -4.3 | AG110: =SUM(AG100:AG109) -> 3 | AH110: =SUM(AH100:AH109) -> -1.6 | AI110: =SUM(AI100:AI109) -> 25.3 | AJ110: =SUM(AF110:AI110) -> 22.4 | AK110: =SUM(AK100:AK109) -> 1.4 | AL110: =SUM(AL100:AL109) -> 7.3 | AM110: =SUM(AM100:AM109) -> 4.6 | AN110: =SUM(AN100:AN109) -> -21.4 | AO110: =SUM(AK110:AN110) -> -8.1 | AP110: =SUM(AP100:AP109) -> 4.6 | AQ110: =SUM(AQ100:AQ109) -> 5 | AR110: =SUM(AR100:AR109) -> 10.1 | AS110: =SUM(AS100:AS109) -> -28.6 | AT110: =SUM(AP110:AS110) -> -8.9 | AU110: =SUM(AU100:AU109) -> -52 | AV110: =SUM(AV100:AV109) -> 5.9 | AW110: =SUM(AW100:AW109) -> 3.8 | AX110: =SUM(AX100:AX109) -> 32.4 | AY110: =SUM(AU110:AX110) -> -9.9 | AZ110: =SUM(AZ100:AZ109) -> 79.8 | BA110: =SUM(BA100:BA109) -> 4 | BB110: =SUM(BB100:BB109) -> 4 | BC110: =SUM(BC100:BC109) -> 4 | BD110: =SUM(AZ110:BC110) -> 91.8 | BE110: =SUM(BE100:BE109) -> 4 | BF110: =SUM(BF100:BF109) -> 4 | BG110: =SUM(BG100:BG109) -> 4 | BH110: =SUM(BH100:BH109) -> 4 | BI110: =SUM(BE110:BH110) -> 16
A111: Adjusted Net Income | B111: =B96+B110 -> 65 | C111: =C96+C110 -> 70 | D111: =D96+D110 -> 75 | E111: =E96+E110 -> 59 | F111: =F96+F110 -> 269 | G111: =G96+G110 -> 72 | H111: =H96+H110 -> 71 | I111: =I96+I110 -> 69 | ... BI111: =BI96+BI110 -> 251.90202
A113: Diluted Shares Outstanding | B113: 205 | C113: 205 | D113: 170 | E113: 171 | F113: =AVERAGE(B113:E113) -> 187.75 | G113: 205 | H113: 205 | I113: 204 | J113: 203 | K113: =AVERAGE(G113:J113) -> 204.25 | L113: 202 | M113: 200 | N113: 196 | O113: 191 | P113: =AVERAGE(L113:O113) -> 197.25 | Q113: 189 | R113: 189 | S113: 189 | T113: 189 | U113: =AVERAGE(Q113:T113) -> 189 | V113: 189 | W113: 188 | X113: 186 | Y113: 186 | Z113: =AVERAGE(V113:Y113) -> 187.25 | AA113: 186 | AB113: 183 | AC113: 183 | AD113: 182 | AE113: =AVERAGE(AA113:AD113) -> 183.5 | AF113: 182 | AG113: 181 | AH113: 179 | AI113: 178.6 | AJ113: =AVERAGE(AF113:AI113) -> 180.15 | AK113: 176.3 | AL113: 172.7 | AM113: 162.5 | AN113: 139.2 | AO113: =AVERAGE(AK113:AN113) -> 162.675 | AP113: 132.7 | AQ113: 130.7 | AR113: 130.2 | AS113: 130.3 | AT113: =AVERAGE(AP113:AS113) -> 130.975 | AU113: 129.5 | AV113: 128.2 | AW113: 128.2 | AX113: 128.4 | AY113: =AVERAGE(AU113:AX113) -> 128.575 | AZ113: 128.2 | BA113: =+(1+BA158/100)*AV113 -> 128.2 | BB113: =+(1+BB158/100)*AW113 -> 128.2 | BC113: =+(1+BC158/100)*AX113 -> 128.24392 | BD113: =AVERAGE(AZ113:BC113) -> 128.21098 | BE113: =+AZ113*(1+BE158) -> 128.2 | BF113: =+BA113*(1+BF158) -> 128.2 | BG113: =+BB113*(1+BG158) -> 128.2 | BH113: =+BC113*(1+BH158) -> 128.24392 | BI113: =AVERAGE(BE113:BH113) -> 128.21098
A114: Diluted Adj. EPS | B114: =B111/B113 -> 0.31707317 | C114: =C111/C113+0.01 -> 0.35146341 | D114: =D111/D113 -> 0.44117647 | E114: =E111/E113 -> 0.34502924 | F114: =SUM(B114:E114) -> 1.4547423 | G114: =G111/G113 -> 0.35121951 | H114: =H111/H113+0.02 -> 0.36634146 | I114: =I111/I113 -> 0.33823529 | J114: =J111/J113 -> 0.33497537 | K114: =SUM(G114:J114) -> 1.3907716 | L114: =L111/L113 -> 0.29207921 | M114: =M111/M113 -> 0.34 | N114: =N111/N113 -> 0.31632653 | O114: =O111/O113 -> 0.34031414 | P114: =SUM(L114:O114) -> 1.2887199 | Q114: =Q111/Q113 -> 0.26984127 | R114: =R111/R113 -> 0.35449735 | S114: =S111/S113 -> 0.37037037 | T114: =T111/T113 -> 0.3968254 | U114: =SUM(Q114:T114) -> 1.3915344 | V114: =V111/V113 -> 0.34920635 | W114: =W111/W113 -> 0.39361702 | X114: =X111/X113 -> 0.28494624 | Y114: =Y111/Y113 -> 0.45698925 | Z114: =SUM(V114:Y114) -> 1.4847589 | AA114: =AA111/AA113 -> 0.41397849 | AB114: =AB111/AB113+0.01 -> 0.46355191 | AC114: =AC111/AC113 -> 0.54644809 | AD114: =AD111/AD113+0.01 -> 0.50450549 | AE114: =SUM(AA114:AD114) -> 1.928484 | AF114: =AF111/AF113 -> 0.16428571 | AG114: =AG111/AG113 -> 0.14364641 | AH114: =AH111/AH113 -> 0.21340782 | AI114: =AI111/AI113 -> 0.21108623 | AJ114: =SUM(AF114:AI114) -> 0.73242617 | AK114: =AK111/AK113 -> 0.16108905 | AL114: =AL111/AL113 -> 0.2327736 | AM114: =AM111/AM113 -> 0.42523077 | AN114: =AN111/AN113 -> 0.38505747 | AO114: =AO111/AO113 -> 1.1759643 | AP114: =AP111/AP113 -> 0.29012811 | AQ114: =AQ111/AQ113 -> 0.36954858 | AR114: =AR111/AR113 -> 0.44777266 | ... BI114: =BI111/BI113 -> 1.964746
A116: EBITDA Analysis: | AZ116: =+AZ90-AU90 -> 121.1 | BA116: =+AZ116/AZ86 -> 0.26223473
A117: EBITDA | F117: =F94+F93+CF!F9 -> 468 | K117: =K94+K93+CF!K9 -> 574 | P117: =P94+P93+CF!P9 -> 449 | U117: =U94+U93+CF!U9 -> 399 | V117: =V94+V93+CF!V9 -> 129 | W117: =W94+W93+CF!W9 -> 141 | X117: =X94+X93+CF!X9 -> 114 | Y117: =Y94+Y93+CF!Y9 -> 226 | Z117: =SUM(V117:Y117) -> 610 | AA117: =AA94+AA93+CF!AA9 -> 158 | AB117: =AB94+AB93+CF!AB9 -> 168 | AC117: =AC94+AC93+CF!AC9 -> 169 | AD117: =AD94+AD93+CF!AD9 -> 251 | AE117: =SUM(AA117:AD117) -> 746 | AF117: =AF94+AF93+CF!AF9 -> 78.2 | AG117: =AG94+AG93+CF!AG9 -> 66.8 | AH117: =AH94+AH93+CF!AH9 -> 87.9 | AI117: =AI94+AI93+CF!AI9 -> 51.9 | AJ117: =SUM(AF117:AI117) -> 284.8 | AK117: =AK94+AK93+CF!AK9 -> 44.1 | AL117: =AL94+AL93+CF!AL9 -> 78.2 | AM117: =AM94+AM93+CF!AM9 -> 104.4 | AN117: =AN94+AN93+CF!AN9 -> 136.9 | AO117: =SUM(AK117:AN117) -> 363.6 | AP117: =AP94+AP93+CF!AP9 -> 84 | AQ117: =AQ94+AQ93+CF!AQ9 -> 98.4 | AR117: =AR94+AR93+CF!AR9 -> 116.9 | AS117: =AS94+AS93+CF!AS9 -> 162.1 | AT117: =SUM(AP117:AS117) -> 461.4 | AU117: =AU94+AU93+CF!AU9 -> 172.7 | AV117: =AV94+AV93+CF!AV9 -> 96.2 | AW117: =AW94+AW93+CF!AW9 -> 125.8 | AX117: =AX94+AX93+CF!AX9 -> 91 | AY117: =SUM(AU117:AX117) -> 485.7 | AZ117: =AZ94+AZ93+CF!AZ9 -> 53 | BA117: =BA94+BA93+CF!BA9 -> 122.9275 | BB117: =BB94+BB93+CF!BB9 -> 147.07097 | BC117: =BC94+BC93+CF!BC9 -> 150.2005 | BD117: =SUM(AZ117:BC117) -> 473.19897 | BE117: =BE94+BE93+CF!BE9 -> 130.97433 | BF117: =BF94+BF93+CF!BF9 -> 139.90595 | BG117: =BG94+BG93+CF!BG9 -> 170.43508 | BH117: =BH94+BH93+CF!BH9 -> 173.96716 | BI117: =SUM(BE117:BH117) -> 615.28252
A118: Total Adjustments: | F118: =SUM(F119:F127) -> -28 | K118: =SUM(K119:K127) -> -127 | P118: =SUM(P119:P127) -> 17 | U118: =SUM(U119:U127) -> 79 | V118: =SUM(V119:V127) -> -9 | W118: =SUM(W119:W127) -> -7 | X118: =SUM(X119:X127) -> -15 | Y118: =SUM(Y119:Y127) -> -76 | Z118: =SUM(V118:Y118) -> -107 | AA118: =SUM(AA119:AA127) -> -13 | AB118: =SUM(AB119:AB127) -> -16 | AC118: =SUM(AC119:AC127) -> 4 | AD118: =SUM(AD119:AD127) -> -96 | AE118: =SUM(AA118:AD118) -> -121 | AF118: =SUM(AF119:AF127) -> -5.8 | AG118: =SUM(AG119:AG127) -> 2.6 | AH118: =SUM(AH119:AH127) -> -1.5 | AI118: =SUM(AI119:AI127) -> 35.6 | AJ118: =SUM(AF118:AI118) -> 30.9 | AK118: =SUM(AK119:AK127) -> 29.2 | AL118: =SUM(AL119:AL127) -> 8.9 | AM118: =SUM(AM119:AM127) -> 6 | AN118: =SUM(AN119:AN127) -> -27.7 | AO118: =SUM(AK118:AN118) -> 16.4 | AP118: =SUM(AP119:AP127) -> 6.2 | AQ118: =SUM(AQ119:AQ127) -> 6.7 | AR118: =SUM(AR119:AR127) -> 6.3 | AS118: =SUM(AS119:AS127) -> -38 | AT118: =SUM(AP118:AS118) -> -18.8 | AU118: =SUM(AU119:AU127) -> -69.9 | AV118: =SUM(AV119:AV127) -> 8.2 | AW118: =SUM(AW119:AW127) -> 3.7 | AX118: =SUM(AX119:AX127) -> 39.1 | AY118: =SUM(AU118:AX118) -> -18.9 | AZ118: =SUM(AZ119:AZ127) -> 64.4 | BA118: =SUM(BA119:BA127) -> 4 | BB118: =SUM(BB119:BB127) -> 4 | BC118: =SUM(BC119:BC127) -> 4 | BD118: =SUM(AZ118:BC118) -> 76.4 | BE118: =SUM(BE119:BE127) -> 4 | BF118: =SUM(BF119:BF127) -> 4 | BG118: =SUM(BG119:BG127) -> 4 | BH118: =SUM(BH119:BH127) -> 4 | BI118: =SUM(BE118:BH118) -> 16
A119: Net Pension Expenses (Income) | F119: -35 | K119: -138 | P119: 0 | U119: 60 | V119: -9 | W119: -9 | X119: -9 | Y119: -32 | Z119: =SUM(V119:Y119) -> -59 | AA119: -13 | AB119: -14 | AC119: -14 | AD119: -85 | AE119: =SUM(AA119:AD119) -> -126 | AF119: =AF92 -> -9.3 | AG119: =AG92 -> -9.2 | AH119: =AH92 -> -9.2 | AI119: =AI92 -> 34.6 | AJ119: =SUM(AF119:AI119) -> 6.9 | AK119: =AK92 -> 3.7 | AL119: =AL92 -> 3.6 | AM119: =AM92 -> 3.7 | AN119: =AN92 -> -38.6 | AO119: =SUM(AK119:AN119) -> -27.6 | AP119: =AP92 -> 3.4 | AQ119: =AQ92 -> 3.6 | AR119: =AR92 -> 3.4 | AS119: =AS92 -> 1.3 | AT119: =SUM(AP119:AS119) -> 11.7 | AU119: =AU92 -> -0.9 | AV119: =AV92 -> -0.9 | AW119: =AW92 -> -0.9 | AX119: =AX92 -> 26.3 | AY119: =SUM(AU119:AX119) -> 23.6 | AZ119: =AZ92 -> -1.2 | BA119: =BA92 -> 3 | BB119: =BB92 -> 3 | BC119: =BC92 -> 3 | BD119: =SUM(AZ119:BC119) -> 7.8 | BE119: =BE92 -> 3 | BF119: =BF92 -> 3 | BG119: =BG92 -> 3 | BH119: =BH92 -> 3 | BI119: =SUM(BE119:BH119) -> 12
A120: Net Legacy and Seperation Related Expenses | F120: 6 | K120: 11 | P120: 14 | U120: 3 | V120: -1 | W120: 0 | X120: 1 | Y120: -30 | Z120: =SUM(V120:Y120) -> -30 | AA120: 1 | AB120: 0 | AC120: 1 | AD120: -26 | AE120: =SUM(AA120:AD120) -> -24 | AF120: 2.8 | AG120: 6.2 | AH120: 9.9 | AI120: 1.6 | AJ120: =SUM(AF120:AI120) -> 20.5 | AK120: 25.4 | AL120: 3.8 | AM120: =AM101 -> 1.6 | AN120: =AN101 -> 2 | AO120: =SUM(AK120:AN120) -> 32.8 | AP120: =AP101 -> 0.1 | AQ120: =AQ101 -> 0 | AR120: =AR101 -> 0.1 | AS120: =AS101 -> -0.9 | AT120: =SUM(AP120:AS120) -> -0.7 | AU120: =AU101 -> 0.4 | AV120: =AV101 -> 0.8 | AW120: =AW101 -> 0.4 | AX120: =AX101 -> -0.2 | AY120: =SUM(AU120:AX120) -> 1.4 | AZ120: =AZ101 -> 5.2 | BA120: =BA101 -> 0 | BB120: =BB101 -> 0 | BC120: =BC101 -> 0 | BD120: =SUM(AZ120:BC120) -> 5.2 | BE120: =BE101 -> 0 | BF120: =BF101 -> 0 | BG120: =BG101 -> 0 | BH120: =BH101 -> 0 | BI120: =SUM(BE120:BH120) -> 0
A121: Information Technology Transition Costs | F121: =SUM(B121:E121) -> 0 | K121: =SUM(G121:J121) -> 0 | P121: =SUM(L121:O121) -> 0 | U121: 0 | V121: 0 | W121: 0 | X121: 0 | Y121: 0 | Z121: =SUM(V121:Y121) -> 0 | AA121: 0 | AB121: 0 | AC121: 0 | AD121: 0 | AE121: =SUM(AA121:AD121) -> 0 | AF121: 1 | AG121: 1.6 | AH121: 0 | AI121: 0 | AJ121: =SUM(AF121:AI121) -> 2.6 | AK121: 0.3 | AL121: 0.4 | AM121: =AM102 -> 1.1 | AN121: =AN102 -> 1.2 | AO121: =SUM(AK121:AN121) -> 3 | AP121: =AP102 -> 2.7 | AQ121: =AQ102 -> 3.1 | AR121: =AR102 -> 1.9 | AS121: =AS102 -> 2.7 | AT121: =SUM(AP121:AS121) -> 10.4 | AU121: =AU102 -> 1.5 | AV121: =AV102 -> 4.9 | AW121: =AW102 -> 2.1 | AX121: =AX102 -> 3 | AY121: =SUM(AU121:AX121) -> 11.5 | AZ121: =AZ102 -> 3.1 | BA121: =BA102 -> 0 | BB121: =BB102 -> 0 | BC121: =BC102 -> 0 | BD121: =SUM(AZ121:BC121) -> 3.1 | BE121: =BE102 -> 0 | BF121: =BF102 -> 0 | BG121: =BG102 -> 0 | BH121: =BH102 -> 0 | BI121: =SUM(BE121:BH121) -> 0
A122: Suspended Operations | F122: =SUM(B122:E122) -> 0 | K122: =SUM(G122:J122) -> 0 | P122: =SUM(L122:O122) -> 0 | U122: 0 | V122: 0 | W122: 0 | X122: 0 | Y122: 0 | Z122: =SUM(V122:Y122) -> 0 | AA122: 0 | AB122: 0 | AC122: 0 | AD122: 0 | AE122: =SUM(AA122:AD122) -> 0 | AF122: -0.3 | AG122: 4 | AH122: -2.2 | AI122: -0.6 | AJ122: =SUM(AF122:AI122) -> 0.9 | AK122: -0.2 | AL122: 0.1 | AM122: =AM103 -> -0.4 | AN122: =AN103 -> 7.6 | AO122: =SUM(AK122:AN122) -> 7.1 | AP122: =AP103 -> 0 | AQ122: =AQ103 -> 0 | AR122: =AR103 -> 0 | AS122: =AS103 -> 0 | AT122: =SUM(AP122:AS122) -> 0 | AU122: =AU103 -> 0 | AV122: =AV103 -> 0 | AW122: =AW103 -> 0 | AX122: =AX103 -> 0 | AY122: =SUM(AU122:AX122) -> 0 | AZ122: =AZ103 -> 0 | BA122: =BA103 -> 0 | BB122: =BB103 -> 0 | BC122: =BC103 -> 0 | BD122: =SUM(AZ122:BC122) -> 0 | BE122: =BE103 -> 0 | BF122: =BF103 -> 0 | BG122: =BG103 -> 0 | BH122: =BH103 -> 0 | BI122: =SUM(BE122:BH122) -> 0
A123: Restructuring Related Adjustments | F123: =SUM(B123:E123) -> 0 | K123: =SUM(G123:J123) -> 0 | P123: =SUM(L123:O123) -> 0 | U123: 14 | V123: 1 | W123: 2 | X123: 0 | Y123: -1 | Z123: =SUM(V123:Y123) -> 2 | AA123: 0 | AB123: 0 | AC123: 0 | AD123: 0 | AE123: =SUM(AA123:AD123) -> 0 | AF123: 0 | AG123: 0 | AH123: 0 | AI123: 0 | AJ123: =SUM(AF123:AI123) -> 0 | AK123: 0 | AL123: 0 | AM123: 0 | AN123: 0 | AO123: =SUM(AK123:AN123) -> 0 | AP123: 0 | AQ123: 0 | AR123: 0 | AS123: 0 | AT123: =SUM(AP123:AS123) -> 0 | AU123: 0 | AV123: 0 | AW123: 0 | AX123: 0 | AY123: =SUM(AU123:AX123) -> 0 | AZ123: 0 | BA123: 0 | BB123: 0 | BC123: 0 | BD123: =SUM(AZ123:BC123) -> 0 | BE123: 0 | BF123: 0 | BG123: 0 | BH123: 0 | BI123: =SUM(BE123:BH123) -> 0
A124: LIFO Charge | F124: =SUM(B124:E124) -> 0 | K124: =SUM(G124:J124) -> 0 | P124: =SUM(L124:O124) -> 0 | U124: 0 | V124: 0 | W124: 0 | X124: -7 | Y124: 0 | Z124: =SUM(V124:Y124) -> -7 | AA124: 0 | AB124: 0 | AC124: 17 | AD124: 15 | AE124: =SUM(AA124:AD124) -> 32 | AF124: 0 | AG124: 0 | AH124: 0 | AI124: 0 | AJ124: =SUM(AF124:AI124) -> 0 | AK124: 0 | AL124: 0 | AM124: 0 | AN124: 0 | AO124: =SUM(AK124:AN124) -> 0 | AP124: 0 | AQ124: 0 | AR124: 0 | AS124: 0 | AT124: =SUM(AP124:AS124) -> 0 | AU124: 0 | AV124: 0 | AW124: 0 | AX124: 0 | AY124: =SUM(AU124:AX124) -> 0 | AZ124: 0 | BA124: 0 | BB124: 0 | BC124: 0 | BD124: =SUM(AZ124:BC124) -> 0 | BE124: 0 | BF124: 0 | BG124: 0 | BH124: 0 | BI124: =SUM(BE124:BH124) -> 0
A125: Business Interruption Losses (Recoveries) | F125: =SUM(B125:E125) -> 0 | K125: =SUM(G125:J125) -> 0 | P125: =SUM(L125:O125) -> 0 | U125: 6 | V125: 0 | W125: 0 | X125: 0 | Y125: -2 | Z125: =SUM(V125:Y125) -> -2 | AA125: -1 | AB125: -2 | AC125: 0 | AD125: 0 | AE125: =SUM(AA125:AD125) -> -3 | AF125: 0 | AG125: 0 | AH125: 0 | AI125: 0 | AJ125: =SUM(AF125:AI125) -> 0 | AK125: 0 | AL125: 0 | AM125: 0 | AN125: 0 | AO125: =SUM(AK125:AN125) -> 0 | AP125: 0 | AQ125: 0 | AR125: 0 | AS125: 0 | AT125: =SUM(AP125:AS125) -> 0 | AU125: 0 | AV125: 0 | AW125: 0 | AX125: 0 | AY125: =SUM(AU125:AX125) -> 0 | AZ125: 0 | BA125: 0 | BB125: 0 | BC125: 0 | BD125: =SUM(AZ125:BC125) -> 0 | BE125: 0 | BF125: 0 | BG125: 0 | BH125: 0 | BI125: =SUM(BE125:BH125) -> 0
A126: Debt Extinguishment and Modification Costs | F126: =SUM(B126:E126) -> 0 | K126: =SUM(G126:J126) -> 0 | P126: =SUM(L126:O126) -> 0 | U126: 0 | V126: 0 | W126: 0 | X126: 0 | Y126: 0 | Z126: =SUM(V126:Y126) -> 0 | AA126: 0 | AB126: 0 | AC126: 0 | AD126: 0 | AE126: =SUM(AA126:AD126) -> 0 | AF126: 0 | AG126: 0 | AH126: 0 | AI126: 0 | AJ126: =SUM(AF126:AI126) -> 0 | AK126: 0 | AL126: 0 | AM126: 0 | AN126: 0 | AO126: =SUM(AK126:AN126) -> 0 | AP126: 0 | AQ126: 0 | AR126: 0 | AS126: 0 | AT126: =SUM(AP126:AS126) -> 0 | AU126: 0 | AV126: 0 | AW126: 0 | AX126: 0 | AY126: =SUM(AU126:AX126) -> 0 | AZ126: 0 | BA126: 0 | BB126: 0 | BC126: 0 | BD126: =SUM(AZ126:BC126) -> 0 | BE126: 0 | BF126: 0 | BG126: 0 | BH126: 0 | BI126: =SUM(BE126:BH126) -> 0
...

Sheet BS
A5: Valvoline Inc. (VVV)
A6: Consolidated Balance Sheet
A7: ($M's, except per share) | B7: =IS!B7 -> 1Q16 | C7: =IS!C7 -> 2Q16 | D7: =IS!D7 -> 3Q16 | E7: =IS!E7 -> 4Q16 | F7: =IS!F7 -> FY16 | G7: =IS!G7 -> 1Q17 | H7: =IS!H7 -> 2Q17 | I7: =IS!I7 -> 3Q17 | ... BI7: =IS!BI7 -> FY27E
A9: Assets
A10: Current assets:
A11: Cash and equivalents | E11: 172 | F11: =E11 -> 172 | G11: 236 | H11: 135 | I11: 132 | J11: 201 | K11: =J11 -> 201 | L11: 115 | M11: 127 | N11: 107 | O11: 96 | P11: =O11 -> 96 | Q11: 99 | R11: 114 | S11: 126 | T11: 159 | U11: =T11 -> 159 | V11: 162 | W11: 774 | X11: 751 | Y11: 760 | Z11: =Y11 -> 760 | AA11: 527 | AB11: 247 | AC11: 226 | AD11: 230 | AE11: =AD11 -> 230 | AF11: 152 | AG11: 118 | AH11: 98 | AI11: 23.4 | AJ11: =AI11 -> 23.4 | AK11: 21 | AL11: 2334.5 | AM11: 526.7 | AN11: 409.1 | AO11: =AN11 -> 409.1 | AP11: 420.7 | AQ11: 494.5 | AR11: 65.7 | AS11: 68.3 | AT11: =AS11 -> 68.3 | AU11: 60 | AV11: 61.9 | AW11: 68.3 | AX11: 51.6 | AY11: =AX11 -> 51.6 | AZ11: 69.9 | BA11: =CF!BA42 -> 71.058486 | BB11: =CF!BB42 -> 74.260016 | BC11: =CF!BC42 -> 76.878199 | BD11: =BC11 -> 76.878199 | BE11: =CF!BE42 -> 79.015504 | BF11: =CF!BF42 -> 81.348377 | BG11: =CF!BG42 -> 84.509122 | BH11: =CF!BH42 -> 88.150574 | BI11: =BH11 -> 88.150574
A12: Receivables | E12: 363 | F12: =E12 -> 363 | G12: 353 | H12: 405 | I12: 403 | J12: 385 | K12: =J12 -> 385 | L12: 418 | M12: 435 | N12: 461 | O12: 409 | P12: =O12 -> 409 | Q12: 331 | R12: 368 | S12: 423 | T12: 401 | U12: =T12 -> 401 | V12: 395 | W12: 352 | X12: 396 | Y12: 433 | Z12: =Y12 -> 433 | AA12: 430 | AB12: 448 | AC12: 490 | AD12: 496 | AE12: =AD12 -> 496 | AF12: 530 | AG12: 563 | AH12: 583 | AI12: 66.1 | AJ12: =AI12 -> 66.1 | AK12: 56.9 | AL12: 61.1 | AM12: 71.9 | AN12: 81.3 | AO12: =AN12 -> 81.3 | AP12: 83.5 | AQ12: 109.6 | AR12: 97.5 | AS12: 86.4 | AT12: =AS12 -> 86.4 | AU12: 84.7 | AV12: 86.1 | AW12: 89.8 | AX12: 89.6 | AY12: =AX12 -> 89.6 | AZ12: 98.5 | BA12: =2*(BA70/BA79)-AZ12 -> 99.821968 | BB12: =2*(BB70/BB79)-BA12 -> 104.23436 | BC12: =2*(BC70/BC79)-BB12 -> 107.1859 | BD12: =BC12 -> 107.1859 | BE12: =2*(BE70/BE79)-BD12 -> 111.27148 | BF12: =2*(BF70/BF79)-BE12 -> 116.20769 | BG12: =2*(BG70/BG79)-BF12 -> 121.36048 | BH12: =2*(BH70/BH79)-BG12 -> 126.9202 | BI12: =BH12 -> 126.9202
A13: Inventories | E13: 139 | F13: =E13 -> 139 | G13: 141 | H13: 156 | I13: 181 | J13: 175 | K13: =J13 -> 175 | L13: 170 | M13: 194 | N13: 196 | O13: 176 | P13: =O13 -> 176 | Q13: 200 | R13: 192 | S13: 200 | T13: 194 | U13: =T13 -> 194 | V13: 194 | W13: 209 | X13: 189 | Y13: 199 | Z13: =Y13 -> 199 | AA13: 213 | AB13: 218 | AC13: 247 | AD13: 258 | AE13: =AD13 -> 258 | AF13: 264 | AG13: 276 | AH13: 306 | AI13: 29.4 | AJ13: =AI13 -> 29.4 | AK13: 31.2 | AL13: 33.5 | AM13: 34.1 | AN13: 33.3 | AO13: =AN13 -> 33.3 | AP13: 31.5 | AQ13: 37.5 | AR13: 40.2 | AS13: 39.7 | AT13: =AS13 -> 39.7 | AU13: 38 | AV13: 41.5 | AW13: 41.3 | AX13: 42.6 | AY13: =AX13 -> 42.6 | AZ13: 48.5 | BA13: =2*(BA71/BA78)-AZ13 -> 48.66322 | BB13: =2*(BB71/BB78)-BA13 -> 50.60637 | BC13: =2*(BC71/BC78)-BB13 -> 52.456515 | BD13: =BC13 -> 52.456515 | BE13: =2*(BE71/BE78)-BD13 -> 54.311853 | BF13: =2*(BF71/BF78)-BE13 -> 55.590687 | BG13: =2*(BG71/BG78)-BF13 -> 57.593763 | BH13: =2*(BH71/BH78)-BG13 -> 60.363968 | BI13: =BH13 -> 60.363968
A14: Prepaid expenses and other current assets | E14: 56 | F14: =E14 -> 56 | G14: 29 | H14: 36 | I14: 32 | J14: 29 | K14: =J14 -> 29 | L14: 32 | M14: 39 | N14: 26 | O14: 44 | P14: =O14 -> 44 | Q14: 38 | R14: 59 | S14: 52 | T14: 43 | U14: =T14 -> 43 | V14: 43 | W14: 49 | X14: 43 | Y14: 46 | Z14: =Y14 -> 46 | AA14: 44 | AB14: 55 | AC14: 53 | AD14: 53 | AE14: =AD14 -> 53 | AF14: 55 | AG14: 59 | AH14: 64 | AI14: 38 | AJ14: =AI14 -> 38 | AK14: 38.7 | AL14: 29 | AM14: =30.3+424.1 -> 454.4 | AN14: =65.5+347.5 -> 413 | AO14: =AN14 -> 413 | AP14: =55.2+119.7 -> 174.9 | AQ14: 59.8 | AR14: 53 | AS14: 61 | AT14: =AS14 -> 61 | AU14: 30 | AV14: 40.5 | AW14: 39.6 | AX14: 59.9 | AY14: =AX14 -> 59.9 | AZ14: 38.3 | BA14: =AZ14 -> 38.3 | BB14: =BA14 -> 38.3 | BC14: =BB14 -> 38.3 | BD14: =BC14 -> 38.3 | BE14: =BD14 -> 38.3 | BF14: =BE14 -> 38.3 | BG14: =BF14 -> 38.3 | BH14: =BG14 -> 38.3 | BI14: =BH14 -> 38.3
A15: Current assets of discontinued operations | E15: 0 | F15: =E15 -> 0 | G15: 0 | H15: 0 | I15: 0 | J15: 0 | K15: =J15 -> 0 | L15: 0 | M15: 0 | N15: 0 | O15: 0 | P15: =O15 -> 0 | Q15: 0 | R15: 0 | S15: 0 | T15: 0 | U15: =T15 -> 0 | V15: 0 | W15: 0 | X15: 0 | Y15: 0 | Z15: =Y15 -> 0 | AA15: 0 | AB15: 0 | AC15: 0 | AD15: 0 | AE15: =AD15 -> 0 | AF15: 0 | AG15: 0 | AH15: 0 | AI15: 1464.2 | AJ15: =AI15 -> 1464.2 | AK15: 1553.6 | AL15: 0 | AM15: =AL15 -> 0 | AN15: =AM15 -> 0 | AO15: =AN15 -> 0 | AP15: =AO15 -> 0 | AQ15: =AP15 -> 0 | AR15: 0 | AS15: =AR15 -> 0 | AT15: =AS15 -> 0 | AU15: =AT15 -> 0 | AV15: =AU15 -> 0 | AW15: =AV15 -> 0 | AX15: =AW15 -> 0 | AY15: =AX15 -> 0 | AZ15: =AY15 -> 0 | ... BI15: =BH15 -> 0
A16: Total current assets | E16: =SUM(E11:E15) -> 730 | F16: =SUM(F11:F15) -> 730 | G16: =SUM(G11:G15) -> 759 | H16: =SUM(H11:H15) -> 732 | I16: =SUM(I11:I15) -> 748 | J16: =SUM(J11:J15) -> 790 | K16: =SUM(K11:K15) -> 790 | L16: =SUM(L11:L15) -> 735 | ... BI16: =SUM(BI11:BI15) -> 313.73474
A18: Property, Plant and Equipment | E18: 324 | F18: =E18 -> 324 | G18: 331 | H18: 349 | I18: 369 | J18: 391 | K18: =J18 -> 391 | L18: 384 | M18: 390 | N18: 399 | O18: 420 | P18: =O18 -> 420 | Q18: 428 | R18: 441 | S18: 455 | T18: 498 | U18: =T18 -> 498 | V18: 479 | W18: 509 | X18: 559 | Y18: 613 | Z18: =Y18 -> 613 | AA18: 713 | AB18: 741 | AC18: 773 | AD18: 817 | AE18: =AD18 -> 817 | AF18: 824 | AG18: 843 | AH18: 874 | AI18: 668.6 | AJ18: =AI18 -> 668.6 | AK18: 693.3 | AL18: 722.5 | AM18: 761.6 | AN18: 818.3 | AO18: =AN18 -> 818.3 | AP18: 841.5 | AQ18: 877.9 | AR18: 927.2 | AS18: 958.7 | AT18: =AS18 -> 958.7 | AU18: 934.14 | AV18: 995.5 | AW18: 1050.5 | AX18: 1134.6 | AY18: =AX18 -> 1134.6 | AZ18: 1217.3 | BA18: =AZ18 -> 1217.3 | BB18: =BA18 -> 1217.3 | BC18: =BB18 -> 1217.3 | BD18: =BC18 -> 1217.3 | BE18: =BD18 -> 1217.3 | BF18: =BE18 -> 1217.3 | BG18: =BF18 -> 1217.3 | BH18: =BG18 -> 1217.3 | BI18: =BH18 -> 1217.3
A19: Operating lease assets | E19: 0 | F19: =E19 -> 0 | G19: 0 | H19: 0 | I19: 0 | J19: 0 | K19: =J19 -> 0 | L19: 0 | M19: 0 | N19: 0 | O19: 0 | P19: =O19 -> 0 | Q19: 0 | R19: 0 | S19: 0 | T19: 0 | U19: =T19 -> 0 | V19: 253 | W19: 254 | X19: 261 | Y19: 261 | Z19: =Y19 -> 261 | AA19: 293 | AB19: 299 | AC19: 311 | AD19: 307 | AE19: =AD19 -> 307 | AF19: 309 | AG19: 313 | AH19: 321 | AI19: 248.1 | AJ19: =AI19 -> 248.1 | AK19: 253.5 | AL19: 258.7 | AM19: 264.3 | AN19: 266.5 | AO19: =AN19 -> 266.5 | AP19: 273.1 | AQ19: 288.1 | AR19: 289.3 | AS19: 298.6 | AT19: =AS19 -> 298.6 | AU19: 290.7 | AV19: 313.2 | AW19: 329.3 | AX19: 331.8 | AY19: =AX19 -> 331.8 | AZ19: 403.3 | BA19: =AZ19 -> 403.3 | BB19: =BA19 -> 403.3 | BC19: =BB19 -> 403.3 | BD19: =BC19 -> 403.3 | BE19: =BD19 -> 403.3 | BF19: =BE19 -> 403.3 | BG19: =BF19 -> 403.3 | BH19: =BG19 -> 403.3 | BI19: =BH19 -> 403.3
A20: Goodwill and Intangibles | E20: 267 | F20: =E20 -> 267 | G20: 270 | H20: 317 | I20: 334 | J20: 335 | K20: =J20 -> 335 | L20: 393 | M20: 396 | N20: 398 | O20: 448 | P20: =O20 -> 448 | Q20: 473 | R20: 478 | S20: 490 | T20: 504 | U20: =T20 -> 504 | V20: 507 | W20: 503 | X20: 510 | Y20: 529 | Z20: =Y20 -> 529 | AA20: 739 | AB20: 732 | AC20: 773 | AD20: 775 | AE20: =AD20 -> 775 | AF20: 782 | AG20: 788 | AH20: 804 | AI20: 663.1 | AJ20: =AI20 -> 663.1 | AK20: 668.2 | AL20: 673.1 | AM20: 678 | AN20: 680.6 | AO20: =AN20 -> 680.6 | AP20: 685.6 | AQ20: 692.3 | AR20: 693.7 | AS20: 705.6 | AT20: =AS20 -> 705.6 | AU20: 689.5 | AV20: 690.8 | AW20: 713.1 | AX20: 740.5 | AY20: =AX20 -> 740.5 | AZ20: 1304.9 | BA20: =AZ20 -> 1304.9 | BB20: =BA20 -> 1304.9 | BC20: =BB20 -> 1304.9 | BD20: =BC20 -> 1304.9 | BE20: =BD20 -> 1304.9 | BF20: =BE20 -> 1304.9 | BG20: =BF20 -> 1304.9 | BH20: =BG20 -> 1304.9 | BI20: =BH20 -> 1304.9
A21: Deferred Tax Assets | E21: 389 | F21: =E21 -> 389 | G21: 386 | H21: 393 | I21: 394 | J21: 281 | K21: =J21 -> 281 | L21: 196 | M21: 171 | N21: 147 | O21: 138 | P21: =O21 -> 138 | Q21: 134 | R21: 125 | S21: 113 | T21: 123 | U21: =T21 -> 123 | V21: 116 | W21: 99 | X21: 82 | Y21: 34 | Z21: =Y21 -> 34 | AA21: 28 | AB21: 19 | AC21: 10 | AD21: 14 | AE21: =AD21 -> 14 | AF21: 13 | AG21: 13 | AH21: 0 | AI21: 61.6 | AJ21: =AI21 -> 61.6 | AK21: 82.2 | AL21: 0 | AM21: =AL21 -> 0 | AN21: =AM21 -> 0 | AO21: =AN21 -> 0 | AP21: =AO21 -> 0 | AQ21: 0 | AR21: 0 | AS21: =AR21 -> 0 | AT21: =AS21 -> 0 | AU21: =AT21 -> 0 | AV21: =AU21 -> 0 | AW21: =AV21 -> 0 | AX21: =AW21 -> 0 | AY21: =AX21 -> 0 | AZ21: =AY21 -> 0 | ... BI21: =BH21 -> 0
A22: Other assets | E22: =26+89 -> 115 | F22: =E22 -> 115 | G22: 89 | H22: =86+30 -> 116 | I22: =86+29 -> 115 | J22: =88+30 -> 118 | K22: =J22 -> 118 | L22: =33+86 -> 119 | M22: =34+83 -> 117 | N22: =33+82 -> 115 | O22: =92+31 -> 123 | P22: =O22 -> 123 | Q22: =97+32 -> 129 | R22: =103+34 -> 137 | S22: =106+35 -> 141 | T22: =108+34 -> 142 | U22: =T22 -> 142 | V22: =109+39 -> 148 | W22: =131+37 -> 168 | X22: =133+39 -> 172 | Y22: =132+44 -> 176 | Z22: =Y22 -> 176 | AA22: =123+46 -> 169 | AB22: =117+45 -> 162 | AC22: =119+47 -> 166 | AD22: =194+47 -> 241 | AE22: =AD22 -> 241 | AF22: =204+50 -> 254 | AG22: =222+53 -> 275 | AH22: =250+48 -> 298 | AI22: 154.3 | AJ22: =AI22 -> 154.3 | AK22: 152.9 | AL22: 168 | AM22: 194.5 | AN22: 187.8 | AO22: =AN22 -> 187.8 | AP22: 198.5 | AQ22: 203.3 | AR22: 209 | AS22: 220.4 | AT22: =AS22 -> 220.4 | AU22: 222.8 | AV22: 223.1 | AW22: 229.7 | AX22: 219.8 | AY22: =AX22 -> 219.8 | AZ22: 221.4 | BA22: =AZ22 -> 221.4 | BB22: =BA22 -> 221.4 | BC22: =BB22 -> 221.4 | BD22: =BC22 -> 221.4 | BE22: =BD22 -> 221.4 | BF22: =BE22 -> 221.4 | BG22: =BF22 -> 221.4 | BH22: =BG22 -> 221.4 | BI22: =BH22 -> 221.4
A23: Total assets | E23: =E16+SUM(E18:E22) -> 1825 | F23: =E23 -> 1825 | G23: =G16+SUM(G18:G22) -> 1835 | H23: =H16+SUM(H18:H22) -> 1907 | I23: =I16+SUM(I18:I22) -> 1960 | J23: =J16+SUM(J18:J22) -> 1915 | K23: =J23 -> 1915 | L23: =L16+SUM(L18:L22) -> 1827 | M23: =M16+SUM(M18:M22) -> 1869 | N23: =N16+SUM(N18:N22) -> 1849 | O23: =O16+SUM(O18:O22) -> 1854 | P23: =O23 -> 1854 | Q23: =Q16+SUM(Q18:Q22) -> 1832 | R23: =R16+SUM(R18:R22) -> 1914 | S23: =S16+SUM(S18:S22) -> 2000 | T23: =T16+SUM(T18:T22) -> 2064 | U23: =T23 -> 2064 | V23: =V16+SUM(V18:V22) -> 2297 | W23: =W16+SUM(W18:W22) -> 2917 | X23: =X16+SUM(X18:X22) -> 2963 | Y23: =Y16+SUM(Y18:Y22) -> 3051 | Z23: =Y23 -> 3051 | AA23: =AA16+SUM(AA18:AA22) -> 3156 | AB23: =AB16+SUM(AB18:AB22) -> 2921 | AC23: =AC16+SUM(AC18:AC22) -> 3049 | AD23: =AD16+SUM(AD18:AD22) -> 3191 | AE23: =AD23 -> 3191 | AF23: =AF16+SUM(AF18:AF22) -> 3183 | AG23: =AG16+SUM(AG18:AG22) -> 3248 | AH23: =AH16+SUM(AH18:AH22) -> 3348 | AI23: =AI16+SUM(AI18:AI22) -> 3416.8 | AJ23: =AI23 -> 3416.8 | AK23: =AK16+SUM(AK18:AK22) -> 3551.5 | AL23: =AL16+SUM(AL18:AL22) -> 4280.4 | AM23: =AM16+SUM(AM18:AM22) -> 2985.5 | AN23: =AN16+SUM(AN18:AN22) -> 2889.9 | AO23: =AN23 -> 2889.9 | AP23: =AP16+SUM(AP18:AP22) -> 2709.3 | AQ23: =AQ16+SUM(AQ18:AQ22) -> 2763 | AR23: =AR16+SUM(AR18:AR22) -> 2375.6 | AS23: =AS16+SUM(AS18:AS22) -> 2438.7 | AT23: =AS23 -> 2438.7 | AU23: =AU16+SUM(AU18:AU22) -> 2349.84 | AV23: =AV16+SUM(AV18:AV22) -> 2452.6 | AW23: =AW16+SUM(AW18:AW22) -> 2561.6 | AX23: =AX16+SUM(AX18:AX22) -> 2670.4 | AY23: =AX23 -> 2670.4 | AZ23: =AZ16+SUM(AZ18:AZ22) -> 3402.1 | BA23: =BA16+SUM(BA18:BA22) -> 3404.7437 | BB23: =BB16+SUM(BB18:BB22) -> 3414.3007 | BC23: =BC16+SUM(BC18:BC22) -> 3421.7206 | BD23: =BC23 -> 3421.7206 | BE23: =BE16+SUM(BE18:BE22) -> 3429.7988 | BF23: =BF16+SUM(BF18:BF22) -> 3438.3468 | BG23: =BG16+SUM(BG18:BG22) -> 3448.6634 | BH23: =BH16+SUM(BH18:BH22) -> 3460.6347 | BI23: =BH23 -> 3460.6347
A25: Liabilities and Shareholders' Equity
A26: Current liabilities:
A27: Current portion of LT debt | E27: 19 | F27: =E27 -> 19 | G27: =15+75 -> 90 | H27: =75+16 -> 91 | I27: =75+15 -> 90 | J27: 90 | K27: =J27 -> 90 | L27: 19 | M27: 23 | N27: 26 | O27: 30 | P27: =O27 -> 30 | Q27: 30 | R27: 30 | S27: 7 | T27: 15 | U27: =T27 -> 15 | V27: 32 | W27: 0 | X27: 0 | Y27: 0 | Z27: =Y27 -> 0 | AA27: 88 | AB27: 1 | AC27: 2 | AD27: 17 | AE27: =AD27 -> 17 | AF27: 32 | AG27: 47 | AH27: 61 | AI27: 162.5 | AJ27: =AI27 -> 162.5 | AK27: 224.5 | AL27: 23.8 | AM27: 23.7 | AN27: 23.8 | AO27: =AN27 -> 23.8 | AP27: 23.8 | AQ27: 623.8 | AR27: 23.8 | AS27: 23.8 | AT27: =AS27 -> 23.8 | AU27: 23.8 | AV27: 23.8 | AW27: 23.8 | AX27: 23.8 | AY27: =AX27 -> 23.8 | AZ27: 31.2 | BA27: =AZ27 -> 31.2 | BB27: =BA27 -> 31.2 | BC27: =BB27 -> 31.2 | BD27: =BC27 -> 31.2 | BE27: =BD27 -> 31.2 | BF27: =BE27 -> 31.2 | BG27: =BF27 -> 31.2 | BH27: =BG27 -> 31.2 | BI27: =BH27 -> 31.2
A28: Trade accounts payable | E28: 177 | F28: =E28 -> 177 | G28: 146 | H28: 170 | I28: 196 | J28: 192 | K28: =J28 -> 192 | L28: 141 | M28: 194 | N28: 176 | O28: 178 | P28: =O28 -> 178 | Q28: 152 | R28: 154 | S28: 163 | T28: 171 | U28: =T28 -> 171 | V28: 218 | W28: 186 | X28: 178 | Y28: 189 | Z28: =Y28 -> 189 | AA28: 158 | AB28: 180 | AC28: 216 | AD28: 246 | AE28: =AD28 -> 246 | AF28: 218 | AG28: 238 | AH28: 265 | AI28: 45 | AJ28: =AI28 -> 45 | AK28: 46.6 | AL28: 85.8 | AM28: 96.4 | AN28: 118.7 | AO28: =AN28 -> 118.7 | AP28: 77.2 | AQ28: 118.8 | AR28: 107.7 | AS28: 117.4 | AT28: =AS28 -> 117.4 | AU28: 88.3 | AV28: 102.5 | AW28: 100.8 | AX28: 118.9 | AY28: =AX28 -> 118.9 | AZ28: 113.4 | BA28: =2*(BA71/BA80)-AZ28 -> 115.88538 | BB28: =2*(BB71/BB80)-BA28 -> 116.56796 | BC28: =2*(BC71/BC80)-BB28 -> 117.34609 | BD28: =BC28 -> 117.34609 | BE28: =2*(BE71/BE80)-BD28 -> 122.02783 | BF28: =2*(BF71/BF80)-BE28 -> 125.05522 | BG28: =2*(BG71/BG80)-BF28 -> 125.48118 | BH28: =2*(BH71/BH80)-BG28 -> 129.47308 | BI28: =BH28 -> 129.47308
A29: Federal and state income taxes payable | E29: 0 | F29: =E29 -> 0 | G29: 0 | H29: 0 | I29: 0 | J29: 0 | K29: =J29 -> 0 | L29: 0 | M29: 0 | N29: 0 | O29: 0 | P29: =O29 -> 0 | Q29: 0 | R29: 0 | S29: 0 | T29: 0 | U29: =T29 -> 0 | V29: 0 | W29: 0 | X29: 0 | Y29: 0 | Z29: =Y29 -> 0 | AA29: 0 | AB29: 0 | AC29: 0 | AD29: 0 | AE29: =AD29 -> 0 | AF29: 0 | AG29: 0 | AH29: 0 | AI29: 0 | AJ29: =AI29 -> 0 | AK29: 0 | AL29: 0 | AM29: =AL29 -> 0 | AN29: =AM29 -> 0 | AO29: =AN29 -> 0 | AP29: =AO29 -> 0 | AQ29: 0 | AR29: 0 | AS29: =AR29 -> 0 | AT29: =AS29 -> 0 | AU29: =AT29 -> 0 | AV29: =AU29 -> 0 | AW29: =AV29 -> 0 | AX29: =AW29 -> 0 | AY29: =AX29 -> 0 | AZ29: =AY29 -> 0 | ... BI29: =BH29 -> 0
A30: Current liabilities held for sale | E30: 0 | F30: =E30 -> 0 | G30: 0 | H30: 0 | I30: 0 | J30: 0 | K30: =J30 -> 0 | L30: 0 | M30: 0 | N30: 0 | O30: 0 | P30: =O30 -> 0 | Q30: 0 | R30: 0 | S30: 0 | T30: 0 | U30: =T30 -> 0 | V30: 0 | W30: 0 | X30: 0 | Y30: 0 | Z30: =Y30 -> 0 | AA30: 0 | AB30: 0 | AC30: 0 | AD30: 0 | AE30: =AD30 -> 0 | AF30: 0 | AG30: 0 | AH30: 0 | AI30: 539.3 | AJ30: =AI30 -> 539.3 | AK30: 478.1 | AL30: 0 | AM30: =AL30 -> 0 | AN30: =AM30 -> 0 | AO30: =AN30 -> 0 | AP30: =AO30 -> 0 | AQ30: 0 | AR30: 0 | AS30: =AR30 -> 0 | AT30: =AS30 -> 0 | AU30: =AT30 -> 0 | AV30: =AU30 -> 0 | AW30: =AV30 -> 0 | AX30: =AW30 -> 0 | AY30: =AX30 -> 0 | AZ30: =AY30 -> 0 | ... BI30: =BH30 -> 0
A31: Accrued expenses and other liabilities | E31: 204 | F31: =E31 -> 204 | G31: 257 | H31: 210 | I31: 235 | J31: 196 | K31: =J31 -> 196 | L31: 208 | M31: 198 | N31: 223 | O31: 203 | P31: =O31 -> 203 | Q31: 198 | R31: 206 | S31: 242 | T31: 237 | U31: =T31 -> 237 | V31: 291 | W31: 215 | X31: 254 | Y31: 255 | Z31: =Y31 -> 255 | AA31: 260 | AB31: 267 | AC31: 289 | AD31: 306 | AE31: =AD31 -> 306 | AF31: 291 | AG31: 300 | AH31: 315 | AI31: 172.6 | AJ31: =AI31 -> 172.6 | AK31: 175.2 | AL31: 512 | AM31: 285.8 | AN31: =215.9+3.9 -> 219.8 | AO31: =AN31 -> 219.8 | AP31: 216.4 | AQ31: 221.1 | AR31: 219.9 | AS31: 212.7 | AT31: =AS31 -> 212.7 | AU31: 191.5 | AV31: 189.3 | AW31: 202.9 | AX31: 204.7 | AY31: =AX31 -> 204.7 | AZ31: 219.2 | BA31: =AZ31 -> 219.2 | BB31: =BA31 -> 219.2 | BC31: =BB31 -> 219.2 | BD31: =BC31 -> 219.2 | BE31: =BD31 -> 219.2 | BF31: =BE31 -> 219.2 | BG31: =BF31 -> 219.2 | BH31: =BG31 -> 219.2 | BI31: =BH31 -> 219.2
A32: Total current liabilities | E32: =SUM(E27:E31) -> 400 | F32: =E32 -> 400 | G32: =SUM(G27:G31) -> 493 | H32: =SUM(H27:H31) -> 471 | I32: =SUM(I27:I31) -> 521 | J32: =SUM(J27:J31) -> 478 | K32: =J32 -> 478 | L32: =SUM(L27:L31) -> 368 | M32: =SUM(M27:M31) -> 415 | N32: =SUM(N27:N31) -> 425 | O32: =SUM(O27:O31) -> 411 | P32: =O32 -> 411 | Q32: =SUM(Q27:Q31) -> 380 | R32: =SUM(R27:R31) -> 390 | S32: =SUM(S27:S31) -> 412 | T32: =SUM(T27:T31) -> 423 | U32: =T32 -> 423 | V32: =SUM(V27:V31) -> 541 | W32: =SUM(W27:W31) -> 401 | X32: =SUM(X27:X31) -> 432 | Y32: =SUM(Y27:Y31) -> 444 | Z32: =Y32 -> 444 | AA32: =SUM(AA27:AA31) -> 506 | AB32: =SUM(AB27:AB31) -> 448 | AC32: =SUM(AC27:AC31) -> 507 | AD32: =SUM(AD27:AD31) -> 569 | AE32: =AD32 -> 569 | AF32: =SUM(AF27:AF31) -> 541 | AG32: =SUM(AG27:AG31) -> 585 | AH32: =SUM(AH27:AH31) -> 641 | AI32: =SUM(AI27:AI31) -> 919.4 | AJ32: =AI32 -> 919.4 | AK32: =SUM(AK27:AK31) -> 924.4 | AL32: =SUM(AL27:AL31) -> 621.6 | AM32: =SUM(AM27:AM31) -> 405.9 | AN32: =SUM(AN27:AN31) -> 362.3 | AO32: =AN32 -> 362.3 | AP32: =SUM(AP27:AP31) -> 317.4 | AQ32: =SUM(AQ27:AQ31) -> 963.7 | AR32: =SUM(AR27:AR31) -> 351.4 | AS32: =SUM(AS27:AS31) -> 353.9 | AT32: =AS32 -> 353.9 | AU32: =SUM(AU27:AU31) -> 303.6 | AV32: =SUM(AV27:AV31) -> 315.6 | AW32: =SUM(AW27:AW31) -> 327.5 | AX32: =SUM(AX27:AX31) -> 347.4 | AY32: =AX32 -> 347.4 | AZ32: =SUM(AZ27:AZ31) -> 363.8 | BA32: =SUM(BA27:BA31) -> 366.28538 | BB32: =SUM(BB27:BB31) -> 366.96796 | BC32: =SUM(BC27:BC31) -> 367.74609 | BD32: =BC32 -> 367.74609 | BE32: =SUM(BE27:BE31) -> 372.42783 | BF32: =SUM(BF27:BF31) -> 375.45522 | BG32: =SUM(BG27:BG31) -> 375.88118 | BH32: =SUM(BH27:BH31) -> 379.87308 | BI32: =BH32 -> 379.87308
A34: Long term debt | E34: 724 | F34: =E34 -> 724 | G34: 650 | H34: 646 | I34: 643 | J34: 1034 | K34: =J34 -> 1034 | L34: 1147 | M34: 1183 | N34: 1231 | O34: 1292 | P34: =O34 -> 1292 | Q34: 1291 | R34: 1318 | S34: 1334 | T34: 1327 | U34: =T34 -> 1327 | V34: 1320 | W34: 2003 | X34: 1953 | Y34: 1962 | Z34: =Y34 -> 1962 | AA34: 1887 | AB34: 1719 | AC34: 1691 | AD34: 1677 | AE34: =AD34 -> 1677 | AF34: 1662 | AG34: 1648 | AH34: 1639 | AI34: 1525.1 | AJ34: =AI34 -> 1525.1 | AK34: 1656.1 | AL34: 1573.4 | AM34: 1567.8 | AN34: 1562.3 | AO34: =AN34 -> 1562.3 | AP34: 1556.8 | AQ34: 951.3 | AR34: 1125.7 | AS34: 1070 | AT34: =AS34 -> 1070 | AU34: 1009.3 | AV34: 1051.9 | AW34: 1055.9 | AX34: 1050.2 | AY34: =AX34 -> 1050.2 | AZ34: 1633.6 | BA34: =AZ34+CF!BA30+CF!BA29 -> 1623.6 | BB34: =BA34+CF!BB30+CF!BB29 -> 1613.6 | BC34: =BB34+CF!BC30+CF!BC29 -> 1603.6 | BD34: =BC34 -> 1603.6 | BE34: =BD34+CF!BE30+CF!BE29 -> 1588.6 | BF34: =BE34+CF!BF30+CF!BF29 -> 1573.6 | BG34: =BF34+CF!BG30+CF!BG29 -> 1558.6 | BH34: =BG34+CF!BH30+CF!BH29 -> 1543.6 | BI34: =BH34 -> 1543.6
A35: Employee benefit obligations | E35: 886 | F35: =E35 -> 886 | G35: 854 | H35: 833 | I35: 811 | J35: 342 | K35: =J35 -> 342 | L35: 331 | M35: 316 | N35: 303 | O35: 333 | P35: =O35 -> 333 | Q35: 330 | R35: 325 | S35: 322 | T35: 387 | U35: =T35 -> 387 | V35: 376 | W35: 361 | X35: 350 | Y35: 317 | Z35: =Y35 -> 317 | AA35: 303 | AB35: 286 | AC35: 272 | AD35: 258 | AE35: =AD35 -> 258 | AF35: 248 | AG35: 237 | AH35: 229 | AI35: 199.4 | AJ35: =AI35 -> 199.4 | AK35: 200.5 | AL35: 201 | AM35: 202.1 | AN35: 168 | AO35: =AN35 -> 168 | AP35: 169.9 | AQ35: 170.2 | AR35: 167.8 | AS35: 176.2 | AT35: =AS35 -> 176.2 | AU35: 174.5 | AV35: 171.5 | AW35: 170.4 | AX35: 187.5 | AY35: =AX35 -> 187.5 | AZ35: 186.1 | BA35: =AZ35 -> 186.1 | BB35: =BA35 -> 186.1 | BC35: =BB35 -> 186.1 | BD35: =BC35 -> 186.1 | BE35: =BD35 -> 186.1 | BF35: =BE35 -> 186.1 | BG35: =BF35 -> 186.1 | BH35: =BG35 -> 186.1 | BI35: =BH35 -> 186.1
A36: Operating lease liabilities | E36: 0 | F36: =E36 -> 0 | G36: 0 | H36: 0 | I36: 0 | J36: 0 | K36: =J36 -> 0 | L36: 0 | M36: 0 | N36: 0 | O36: 0 | P36: =O36 -> 0 | Q36: 0 | R36: 0 | S36: 0 | T36: 0 | U36: =T36 -> 0 | V36: 224 | W36: 226 | X36: 231 | Y36: 231 | Z36: =Y36 -> 231 | AA36: 260 | AB36: 286 | AC36: 276 | AD36: 274 | AE36: =AD36 -> 274 | AF36: 276 | AG36: 280 | AH36: 288 | AI36: 229.4 | AJ36: =AI36 -> 229.4 | AK36: 234.5 | AL36: 239.6 | AM36: 245 | AN36: 247.3 | AO36: =AN36 -> 247.3 | AP36: 253.9 | AQ36: 269 | AR36: 270.3 | AS36: 279.7 | AT36: =AS36 -> 279.7 | AU36: 273.1 | AV36: 295.2 | AW36: 312.2 | AX36: 315.3 | AY36: =AX36 -> 315.3 | AZ36: 376 | BA36: =AZ36 -> 376 | BB36: =BA36 -> 376 | BC36: =BB36 -> 376 | BD36: =BC36 -> 376 | BE36: =BD36 -> 376 | BF36: =BE36 -> 376 | BG36: =BF36 -> 376 | BH36: =BG36 -> 376 | BI36: =BH36 -> 376
A37: Other long-term liabilities | E37: =143+2 -> 145 | F37: =E37 -> 145 | G37: 154 | H37: =2+173 -> 175 | I37: =2+186 -> 188 | J37: 178 | K37: =J37 -> 178 | L37: 175 | M37: 181 | N37: 178 | O37: 176 | P37: =O37 -> 176 | Q37: 174 | R37: 179 | S37: 184 | T37: 185 | U37: =T37 -> 185 | V37: 152 | W37: 163 | X37: 185 | Y37: 173 | Z37: =Y37 -> 173 | AA37: 255 | AB37: 259 | AC37: 280 | AD37: =252+26 -> 278 | AE37: =AD37 -> 278 | AF37: =255+34 -> 289 | AG37: =256+42 -> 298 | AH37: =267+58 -> 325 | AI37: 237.1 | AJ37: =AI37 -> 237.1 | AK37: 246.7 | AL37: 272.4 | AM37: 279.3 | AN37: 346.8 | AO37: =AN37 -> 346.8 | AP37: 346.5 | AQ37: 348.7 | AR37: 353.9 | AS37: 373.3 | AT37: =AS37 -> 373.3 | AU37: 359.5 | AV37: 369.7 | AW37: 382 | AX37: 431.5 | AY37: =AX37 -> 431.5 | AZ37: 535 | BA37: =AZ37 -> 535 | BB37: =BA37 -> 535 | BC37: =BB37 -> 535 | BD37: =BC37 -> 535 | BE37: =BD37 -> 535 | BF37: =BE37 -> 535 | BG37: =BF37 -> 535 | BH37: =BG37 -> 535 | BI37: =BH37 -> 535
A38: Total liabilities | E38: =SUM(E34:E37)+E32 -> 2155 | F38: =E38 -> 2155 | G38: =SUM(G34:G37)+G32 -> 2151 | H38: =SUM(H34:H37)+H32 -> 2125 | I38: =SUM(I34:I37)+I32 -> 2163 | J38: =SUM(J34:J37)+J32 -> 2032 | K38: =J38 -> 2032 | L38: =SUM(L34:L37)+L32 -> 2021 | M38: =SUM(M34:M37)+M32 -> 2095 | N38: =SUM(N34:N37)+N32 -> 2137 | O38: =SUM(O34:O37)+O32 -> 2212 | P38: =O38 -> 2212 | Q38: =SUM(Q34:Q37)+Q32 -> 2175 | R38: =SUM(R34:R37)+R32 -> 2212 | S38: =SUM(S34:S37)+S32 -> 2252 | T38: =SUM(T34:T37)+T32 -> 2322 | U38: =T38 -> 2322 | V38: =SUM(V34:V37)+V32 -> 2613 | W38: =SUM(W34:W37)+W32 -> 3154 | X38: =SUM(X34:X37)+X32 -> 3151 | Y38: =SUM(Y34:Y37)+Y32 -> 3127 | Z38: =Y38 -> 3127 | AA38: =SUM(AA34:AA37)+AA32 -> 3211 | AB38: =SUM(AB34:AB37)+AB32 -> 2998 | AC38: =SUM(AC34:AC37)+AC32 -> 3026 | AD38: =SUM(AD34:AD37)+AD32 -> 3056 | AE38: =AD38 -> 3056 | AF38: =SUM(AF34:AF37)+AF32 -> 3016 | AG38: =SUM(AG34:AG37)+AG32 -> 3048 | AH38: =SUM(AH34:AH37)+AH32 -> 3122 | AI38: =SUM(AI34:AI37)+AI32 -> 3110.4 | AJ38: =AI38 -> 3110.4 | AK38: =SUM(AK34:AK37)+AK32 -> 3262.2 | AL38: =SUM(AL34:AL37)+AL32 -> 2908 | AM38: =SUM(AM34:AM37)+AM32 -> 2700.1 | AN38: =SUM(AN34:AN37)+AN32 -> 2686.7 | AO38: =AN38 -> 2686.7 | AP38: =SUM(AP34:AP37)+AP32 -> 2644.5 | AQ38: =SUM(AQ34:AQ37)+AQ32 -> 2702.9 | AR38: =SUM(AR34:AR37)+AR32 -> 2269.1 | AS38: =SUM(AS34:AS37)+AS32 -> 2253.1 | AT38: =AS38 -> 2253.1 | AU38: =SUM(AU34:AU37)+AU32 -> 2120 | AV38: =SUM(AV34:AV37)+AV32 -> 2203.9 | AW38: =SUM(AW34:AW37)+AW32 -> 2248 | AX38: =SUM(AX34:AX37)+AX32 -> 2331.9 | AY38: =AX38 -> 2331.9 | AZ38: =SUM(AZ34:AZ37)+AZ32 -> 3094.5 | BA38: =SUM(BA34:BA37)+BA32 -> 3086.9854 | BB38: =SUM(BB34:BB37)+BB32 -> 3077.668 | BC38: =SUM(BC34:BC37)+BC32 -> 3068.4461 | BD38: =BC38 -> 3068.4461 | BE38: =SUM(BE34:BE37)+BE32 -> 3058.1278 | BF38: =SUM(BF34:BF37)+BF32 -> 3046.1552 | BG38: =SUM(BG34:BG37)+BG32 -> 3031.5812 | BH38: =SUM(BH34:BH37)+BH32 -> 3020.5731 | BI38: =BH38 -> 3020.5731
A40: Shareholders' equity
A41: Preferred stock, no par value | Q41: 0 | R41: 0 | S41: 0 | T41: 0 | U41: =T41 -> 0 | V41: 0 | W41: 0 | X41: 0 | Y41: 0 | Z41: =Y41 -> 0 | AA41: 0 | AB41: 0 | AC41: 0 | AD41: 0 | AE41: =AD41 -> 0 | AF41: 0 | AG41: 0 | AH41: 0 | AI41: 0 | AJ41: =AI41 -> 0 | AK41: 0 | AL41: 0 | AM41: 0 | AN41: 0 | AO41: =AN41 -> 0 | AT41: =AS41 -> 0
A42: Common Stock | Q42: 2 | R42: 2 | S42: 2 | T42: 2 | U42: =T42 -> 2 | V42: 2 | W42: 2 | X42: 2 | Y42: 2 | Z42: =Y42 -> 2 | AA42: 2 | AB42: 2 | AC42: 2 | AD42: 2 | AE42: =AD42 -> 2 | AF42: 2 | AG42: 2 | AH42: 2 | AI42: 1.8 | AJ42: =AI42 -> 1.8 | AK42: 1.7 | AL42: 1.7 | AM42: 1.4 | AN42: 1.3 | AO42: =AN42 -> 1.3 | AP42: 1.3 | AQ42: 1.3 | AR42: 1.3 | AS42: 1.3 | AT42: =AS42 -> 1.3 | AU42: 1.3 | AV42: 1.3 | AW42: 1.3
A43: Paid-in capital | Q43: 8 | R43: 10 | S43: 13 | T43: 13 | U43: =T43 -> 13 | V43: 16 | W43: 16 | X43: 20 | Y43: 24 | Z43: =Y43 -> 24 | AA43: 25 | AB43: 29 | AC43: 32 | AD43: 35 | AE43: =AD43 -> 35 | AF43: 33 | AG43: 36 | AH43: 41 | AI43: 44.1 | AJ43: =AI43 -> 44.1 | AK43: 40.8 | AL43: 42.6 | AM43: 44.8 | AN43: 48 | AO43: =AN43 -> 48 | AP43: 46.3 | AQ43: 45.3 | AR43: 48.9 | AS43: 51.2 | AT43: =AS43 -> 51.2 | AU43: 50.3 | AV43: 52.8 | AW43: 55.5
A44: Retained earnings | Q44: -379 | R44: -336 | S44: -291 | T44: -284 | U44: =T44 -> -284 | V44: -231 | W44: -249 | X44: -211 | Y44: -110 | Z44: =Y44 -> -110 | AA44: -106 | AB44: -103 | AC44: -29 | AD44: 90 | AE44: =AD44 -> 90 | AF44: 123 | AG44: 147 | AH44: 186 | AI44: 282 | AJ44: =AI44 -> 282 | AK44: 254.6 | AL44: 1310.2 | AM44: 222.2 | AN44: 140.7 | AO44: =AN44 -> 140.7 | AP44: -0.2 | AQ44: 0.4 | AR44: 46.3 | AS44: 123.2 | AT44: =AS44 -> 123.2 | AU44: 175.2 | AV44: 192.1 | AW44: 248.6
A45: Accumulated other comprehensive loss | Q45: 26 | R45: 26 | S45: 24 | T45: 11 | U45: =T45 -> 11 | V45: 17 | W45: -6 | X45: 1 | Y45: 8 | Z45: =Y45 -> 8 | AA45: 24 | AB45: 16 | AC45: 18 | AD45: 8 | AE45: =AD45 -> 8 | AF45: 9 | AG45: 15 | AH45: -3 | AI45: -21.3 | AJ45: =AI45 -> -21.3 | AK45: -7.8 | AL45: 17.9 | AM45: 17 | AN45: 13.2 | AO45: =AN45 -> 13.2 | AP45: 17.4 | AQ45: 13.1 | AR45: 10 | AS45: 9.9 | AT45: =AS45 -> 9.9 | AU45: 3 | AV45: 2.5 | AW45: 8.2
A46: Total shareholders' equity | E46: =E23-E38 -> -330 | F46: =F23-F38 -> -330 | G46: -286 | H46: -218 | I46: -203 | J46: =J23-J38 -> -117 | K46: =K23-K38 -> -117 | L46: =L23-L38 -> -194 | M46: =M23-M38 -> -226 | N46: =N23-N38 -> -288 | O46: =O23-O38 -> -358 | P46: =P23-P38 -> -358 | Q46: =SUM(Q41:Q45) -> -343 | R46: =SUM(R41:R45) -> -298 | S46: =SUM(S41:S45) -> -252 | T46: =SUM(T41:T45) -> -258 | U46: =T46 -> -258 | V46: =SUM(V41:V45) -> -196 | W46: =SUM(W41:W45) -> -237 | X46: =SUM(X41:X45) -> -188 | Y46: =SUM(Y41:Y45) -> -76 | Z46: =Y46 -> -76 | AA46: =SUM(AA41:AA45) -> -55 | AB46: =SUM(AB41:AB45) -> -56 | AC46: =SUM(AC41:AC45) -> 23 | AD46: =SUM(AD41:AD45) -> 135 | AE46: =AD46 -> 135 | AF46: =SUM(AF41:AF45) -> 167 | AG46: =SUM(AG41:AG45) -> 200 | AH46: =SUM(AH41:AH45) -> 226 | AI46: =SUM(AI41:AI45) -> 306.6 | AJ46: =AI46 -> 306.6 | AK46: =SUM(AK41:AK45) -> 289.3 | AL46: =SUM(AL41:AL45) -> 1372.4 | AM46: =SUM(AM41:AM45) -> 285.4 | AN46: =SUM(AN41:AN45) -> 203.2 | AO46: =AN46 -> 203.2 | AP46: =SUM(AP42:AP45) -> 64.8 | AQ46: =SUM(AQ42:AQ45) -> 60.1 | AR46: =SUM(AR42:AR45) -> 106.5 | AS46: =SUM(AS42:AS45) -> 185.6 | AT46: =AS46 -> 185.6 | AU46: =SUM(AU42:AU45) -> 229.8 | AV46: =SUM(AV42:AV45) -> 248.7 | AW46: =SUM(AW42:AW45) -> 313.6 | AX46: =AX23-AX38 -> 338.5 | AY46: =AX46 -> 338.5 | AZ46: 307.6 | BA46: =BA23-BA38 -> 317.75829 | BB46: =BB23-BB38 -> 336.63278 | BC46: =BC23-BC38 -> 353.27452 | BD46: =BC46 -> 353.27452 | BE46: =BE23-BE38 -> 371.67101 | BF46: =BF23-BF38 -> 392.19153 | BG46: =BG23-BG38 -> 417.08219 | BH46: =BH23-BH38 -> 440.06167 | BI46: =BH46 -> 440.06167
A47: Total liabilities and shareholders' equity | E47: =E46+E38 -> 1825 | F47: =F46+F38 -> 1825 | G47: =G46+G38 -> 1865 | H47: =H46+H38 -> 1907 | I47: =I46+I38 -> 1960 | J47: =J46+J38 -> 1915 | K47: =K46+K38 -> 1915 | L47: =L46+L38 -> 1827 | ... O47: =O46+O38 -> 1854 | Q47: =Q46+Q38 -> 1832 | R47: =R46+R38 -> 1914 | S47: =S46+S38 -> 2000 | T47: =T46+T38 -> 2064 | U47: =U46+U38 -> 2064 | V47: =V46+V38 -> 2417 | W47: =W46+W38 -> 2917 | X47: =X46+X38 -> 2963 | ... BI47: =BI46+BI38 -> 3460.6347
AD48: =AD47-AD23 -> 0
A49: BALANCE SHEET ANALYSIS
A50: Cash | F50: =F11 -> 172 | G50: =G11 -> 236 | H50: =H11 -> 135 | I50: =I11 -> 132 | J50: =J11 -> 201 | K50: =K11 -> 201 | L50: =L11 -> 115 | M50: =M11 -> 127 | ... BI50: =BI11 -> 88.150574
A51: Debt | F51: =F34+F27 -> 743 | G51: =G34+G27 -> 740 | H51: =H34+H27 -> 737 | I51: =I34+I27 -> 733 | J51: =J34+J27 -> 1124 | K51: =K34+K27 -> 1124 | L51: =L34+L27 -> 1166 | M51: =M34+M27 -> 1206 | ... BI51: =BI34+BI27 -> 1574.8
A52: Net Debt | F52: =F51-F50 -> 571 | G52: =G51-G50 -> 504 | H52: =H51-H50 -> 602 | I52: =I51-I50 -> 601 | J52: =J51-J50 -> 923 | K52: =K51-K50 -> 923 | L52: =L51-L50 -> 1051 | M52: =M51-M50 -> 1079 | ... BI52: =BI51-BI50 -> 1486.6494
A53: Capital | F53: =F51+F46 -> 413 | G53: =G51+G46 -> 454 | H53: =H51+H46 -> 519 | I53: =I51+I46 -> 530 | J53: =J51+J46 -> 1007 | K53: =K51+K46 -> 1007 | L53: =L51+L46 -> 972 | M53: =M51+M46 -> 980 | ... BI53: =BI51+BI46 -> 2014.8617
A54: Book Value | F54: =F46 -> -330 | G54: =G46 -> -286 | H54: =H46 -> -218 | I54: =I46 -> -203 | J54: =J46 -> -117 | K54: =K46 -> -117 | L54: =L46 -> -194 | M54: =M46 -> -226 | ... BI54: =BI46 -> 440.06167
A55: Tangible book value | F55: =F46-F20 -> -597 | G55: =G46-G20 -> -556 | H55: =H46-H20 -> -535 | I55: =I46-I20 -> -537 | J55: =J46-J20 -> -452 | K55: =K46-K20 -> -452 | L55: =L46-L20 -> -587 | M55: =M46-M20 -> -622 | ... BI55: =BI46-BI20 -> -864.83833
A56: Working capital | F56: =F16-F32 -> 330 | G56: =G16-G32 -> 266 | H56: =H16-H32 -> 261 | I56: =I16-I32 -> 227 | J56: =J16-J32 -> 312 | K56: =K16-K32 -> 312 | L56: =L16-L32 -> 367 | M56: =M16-M32 -> 380 | ... BI56: =BI16-BI32 -> -66.138334
A57: Average equity (LTM) | F57: =AVERAGE(E46,D46,C46,B46) -> -330 | G57: =AVERAGE(G46,E46,D46,C46) -> -308 | H57: =AVERAGE(H46,G46,E46,D46) -> -278 | I57: =AVERAGE(I46,H46,G46,E46) -> -259.25 | J57: =AVERAGE(J46,I46,H46,G46) -> -206 | K57: =AVERAGE(J46,I46,H46,G46) -> -206 | L57: =AVERAGE(L46,J46,I46,H46) -> -183 | M57: =AVERAGE(M46,L46,J46,I46) -> -185 | N57: =AVERAGE(N46,M46,L46,J46) -> -206.25 | O57: =AVERAGE(O46,N46,M46,L46) -> -266.5 | P57: =AVERAGE(O46,N46,M46,L46) -> -266.5 | Q57: =AVERAGE(Q46,O46,N46,M46) -> -303.75 | R57: =AVERAGE(R46,Q46,O46,N46) -> -321.75 | S57: =AVERAGE(S46,R46,Q46,O46) -> -312.75 | T57: =AVERAGE(T46,S46,R46,Q46) -> -287.75 | U57: =AVERAGE(T46,S46,R46,Q46) -> -287.75 | V57: =AVERAGE(V46,T46,S46,R46) -> -251 | W57: =AVERAGE(W46,V46,T46,S46) -> -235.75 | X57: =AVERAGE(X46,W46,V46,T46) -> -219.75 | Y57: =AVERAGE(Y46,X46,W46,V46) -> -174.25 | Z57: =AVERAGE(Y46,X46,W46,V46) -> -174.25 | AA57: =AVERAGE(AA46,Y46,X46,W46) -> -139 | AB57: =AVERAGE(AB46,AA46,Y46,X46) -> -93.75 | AC57: =AVERAGE(AC46,AB46,AA46,Y46) -> -41 | AD57: =AVERAGE(AD46,AC46,AB46,AA46) -> 11.75 | AE57: =AVERAGE(AD46,AC46,AB46,AA46) -> 11.75 | AF57: =AVERAGE(AF46,AD46,AC46,AB46) -> 67.25 | AG57: =AVERAGE(AG46,AF46,AD46,AC46) -> 131.25 | AH57: =AVERAGE(AH46,AG46,AF46,AD46) -> 182 | AI57: =AVERAGE(AI46,AH46,AG46,AF46) -> 224.9 | AJ57: =AVERAGE(AI46,AH46,AG46,AF46) -> 224.9 | AK57: =AVERAGE(AK46,AI46,AH46,AG46) -> 255.475 | AL57: =AVERAGE(AL46,AK46,AI46,AH46) -> 548.575 | AM57: =AVERAGE(AM46,AL46,AK46,AI46) -> 563.425 | AN57: =AVERAGE(AN46,AM46,AL46,AK46) -> 537.575 | AO57: =AVERAGE(AN46,AM46,AL46,AK46) -> 537.575 | AP57: =AVERAGE(AP46,AN46,AM46,AL46) -> 481.45 | AQ57: =AVERAGE(AQ46,AP46,AN46,AM46) -> 153.375 | AR57: =AVERAGE(AR46,AQ46,AP46,AN46) -> 108.65 | AS57: =AVERAGE(AS46,AR46,AQ46,AP46) -> 104.25 | AT57: =AVERAGE(AS46,AR46,AQ46,AP46) -> 104.25 | AU57: =AVERAGE(AU46,AS46,AR46,AQ46) -> 145.5 | AV57: =AVERAGE(AV46,AU46,AS46,AR46) -> 192.65 | AW57: =AVERAGE(AW46,AV46,AU46,AS46) -> 244.425 | AX57: =AVERAGE(AX46,AW46,AV46,AU46) -> 282.65 | AY57: =AVERAGE(AX46,AW46,AV46,AU46) -> 282.65 | AZ57: =AVERAGE(AZ46,AX46,AW46,AV46) -> 302.1 | BA57: =AVERAGE(BA46,AZ46,AX46,AW46) -> 319.36457 | BB57: =AVERAGE(BB46,BA46,AZ46,AX46) -> 325.12277 | BC57: =AVERAGE(BC46,BB46,BA46,AZ46) -> 328.8164 | BD57: =AVERAGE(BC46,BB46,BA46,AZ46) -> 328.8164 | BE57: =AVERAGE(BE46,BC46,BB46,BA46) -> 344.83415 | BF57: =AVERAGE(BF46,BE46,BC46,BB46) -> 363.44246 | BG57: =AVERAGE(BG46,BF46,BE46,BC46) -> 383.55481 | BH57: =AVERAGE(BH46,BG46,BF46,BE46) -> 405.2516 | BI57: =AVERAGE(BH46,BG46,BF46,BE46) -> 405.2516
A58: Shares Outstanding | F58: =IS!F113 -> 187.75 | G58: =IS!G113 -> 205 | H58: =IS!H113 -> 205 | I58: =IS!I113 -> 204 | J58: =IS!J113 -> 203 | K58: =IS!K113 -> 204.25 | L58: =IS!L113 -> 202 | M58: =IS!M113 -> 200 | ... BI58: =IS!BI113 -> 128.21098
A59: # of Stores | F59: =IS!F52 -> 1068 | G59: =IS!G52 -> 1076 | H59: =IS!H52 -> 1108 | I59: =IS!I52 -> 1113 | J59: =IS!J52 -> 1127 | K59: =IS!K52 -> 1127 | L59: =IS!L52 -> 1139 | M59: =IS!M52 -> 1141 | ... BI59: =IS!BI52 -> 2729
A60: Inventory/store | F60: =F13/F59 -> 0.13014981 | G60: =G13/G59 -> 0.13104089 | H60: =H13/H59 -> 0.14079422 | I60: =I13/I59 -> 0.16262354 | J60: =J13/J59 -> 0.1552795 | K60: =K13/K59 -> 0.1552795 | L60: =L13/L59 -> 0.14925373 | M60: =M13/M59 -> 0.17002629 | ... BI60: =BI13/BI59 -> 0.022119446
A62: Financial Ratios
A63: Book Value/Share | F63: =F54/IS!F113 -> -1.7576565 | G63: =G54/IS!G113 -> -1.395122 | H63: =H54/IS!H113 -> -1.0634146 | I63: =I54/IS!I113 -> -0.99509804 | J63: =J54/IS!J113 -> -0.57635468 | K63: =K54/IS!K113 -> -0.57282742 | L63: =L54/IS!L113 -> -0.96039604 | M63: =M54/IS!M113 -> -1.13 | ... BI63: =BI54/IS!BI113 -> 3.4323243
A64: Tangible book value/share | F64: =F55/F58 -> -3.1797603 | G64: =G55/G58 -> -2.7121951 | H64: =H55/H58 -> -2.6097561 | I64: =I55/I58 -> -2.6323529 | J64: =J55/J58 -> -2.226601 | K64: =K55/K58 -> -2.2129743 | L64: =L55/L58 -> -2.9059406 | M64: =M55/M58 -> -3.11 | ... BI64: =BI55/BI58 -> -6.7454311
A65: Cash/share | F65: =F50/F58 -> 0.91611185 | G65: =G50/G58 -> 1.1512195 | H65: =H50/H58 -> 0.65853659 | I65: =I50/I58 -> 0.64705882 | J65: =J50/J58 -> 0.99014778 | K65: =K50/K58 -> 0.98408813 | L65: =L50/L58 -> 0.56930693 | M65: =M50/M58 -> 0.635 | ... BI65: =BI50/BI58 -> 0.6875431
A66: Debt/Capital | F66: =F51/F53 -> 1.7990315 | G66: =G51/G53 -> 1.6299559 | H66: =H51/H53 -> 1.4200385 | I66: =I51/I53 -> 1.3830189 | J66: =J51/J53 -> 1.1161867 | K66: =K51/K53 -> 1.1161867 | L66: =L51/L53 -> 1.1995885 | M66: =M51/M53 -> 1.2306122 | ... BI66: =BI51/BI53 -> 0.78159212
A67: Net Debt/Capital | F67: =F52/F53 -> 1.3825666 | G67: =G52/G53 -> 1.1101322 | H67: =H52/H53 -> 1.1599229 | I67: =I52/I53 -> 1.1339623 | J67: =J52/J53 -> 0.91658391 | K67: =K52/K53 -> 0.91658391 | L67: =L52/L53 -> 1.0812757 | M67: =M52/M53 -> 1.1010204 | ... BI67: =BI52/BI53 -> 0.73784193
A68: Net Income | F68: =IS!F96 -> 273 | G68: =IS!G96 -> 72 | H68: =IS!H96 -> 71 | I68: =IS!I96 -> 56 | J68: =IS!J96 -> 105 | K68: =IS!K96 -> 304 | L68: =IS!L96 -> -10 | M68: =IS!M96 -> 67 | ... BI68: =IS!BI96 -> 235.90202
A69: Adj. EBITDA | F69: =IS!F128 -> 440 | G69: =IS!G128 -> 0 | H69: =IS!H128 -> 0 | I69: =IS!I128 -> 0 | J69: =IS!J128 -> 0 | K69: =IS!K128 -> 447 | L69: =IS!L128 -> 0 | M69: =IS!M128 -> 0 | ... BI69: =IS!BI128 -> 631.28252
A70: Sales | F70: =IS!F86 -> 1929 | G70: =IS!G86 -> 489 | H70: =IS!H86 -> 514 | I70: =IS!I86 -> 534 | J70: =IS!J86 -> 547 | K70: =IS!K86 -> 2084 | L70: =IS!L86 -> 545 | M70: =IS!M86 -> 569 | ... BI70: =IS!BI86 -> 2281.184
A71: COGS | F71: =IS!F87 -> 1168 | G71: =IS!G87 -> 304 | H71: =IS!H87 -> 316 | I71: =IS!I87 -> 337 | J71: =IS!J87 -> 349 | K71: =IS!K87 -> 1306 | L71: =IS!L87 -> 350 | M71: =IS!M87 -> 362 | ... BI71: =IS!BI87 -> 1395.0792
A72: TTM ROE | F72: =(F68+E68+D68+C68)/AVERAGE(F46,E46,D46,C46) -> -0.82727273 | G72: =(G68+F68+E68+D68)/AVERAGE(G46,F46,E46,D46) -> -1.0940803 | H72: =(H68+G68+F68+E68)/AVERAGE(H46,G46,F46,E46) -> -1.4295533 | I72: =(I68+H68+G68+F68)/AVERAGE(I46,H46,G46,F46) -> -1.8206365 | J72: =(J68+I68+H68+G68)/AVERAGE(J46,I46,H46,G46) -> -1.4757282 | K72: =(J68+I68+H68+G68)/AVERAGE(J46,I46,H46,G46) -> -1.4757282 | L72: =(L68+J68+I68+H68)/AVERAGE(L46,J46,I46,H46) -> -1.2131148 | M72: =(M68+L68+J68+I68)/AVERAGE(M46,L46,J46,I46) -> -1.1783784 | N72: =(N68+M68+L68+J68)/AVERAGE(N46,M46,L46,J46) -> -1.0957576 | O72: =(O68+N68+M68+L68)/AVERAGE(O46,N46,M46,L46) -> -0.62288931 | P72: =(O68+N68+M68+L68)/AVERAGE(O46,N46,M46,L46) -> -0.62288931 | Q72: =(Q68+O68+N68+M68)/AVERAGE(Q46,O46,N46,M46) -> -0.75390947 | R72: =(R68+Q68+O68+N68)/AVERAGE(R46,Q46,O46,N46) -> -0.6993007 | S72: =(S68+R68+Q68+O68)/AVERAGE(S46,R46,Q46,O46) -> -0.7226219 | T72: =(T68+S68+R68+Q68)/AVERAGE(T46,S46,R46,Q46) -> -0.7228497 | U72: =(T68+S68+R68+Q68)/AVERAGE(T46,S46,R46,Q46) -> -0.7228497 | V72: =(V68+T68+S68+R68)/AVERAGE(V46,T46,S46,R46) -> -0.90836653 | W72: =(W68+V68+T68+S68)/AVERAGE(W46,V46,T46,S46) -> -0.96712619 | X72: =(X68+W68+V68+T68)/AVERAGE(X46,W46,V46,T46) -> -1.0102389 | Y72: =(Y68+X68+W68+V68)/AVERAGE(Y46,X46,W46,V46) -> -1.8192253 | Z72: =(Y68+X68+W68+V68)/AVERAGE(Y46,X46,W46,V46) -> -1.8192253 | AA72: =(AA68+Y68+X68+W68)/AVERAGE(AA46,Y46,X46,W46) -> -2.381295 | AB72: =(AB68+AA68+Y68+X68)/AVERAGE(AB46,AA46,Y46,X46) -> -3.584 | AC72: =(AC68+AB68+AA68+Y68)/AVERAGE(AC46,AB46,AA46,Y46) -> -9.1219512 | AD72: =(AD68+AC68+AB68+AA68)/AVERAGE(AD46,AC46,AB46,AA46) -> 35.744681 | AE72: =(AD68+AC68+AB68+AA68)/AVERAGE(AD46,AC46,AB46,AA46) -> 35.744681 | AF72: =(AF68+AD68+AC68+AB68)/AVERAGE(AF46,AD46,AC46,AB46) -> 5.460223 | AG72: =(AG68+AF68+AD68+AC68)/AVERAGE(AG46,AF46,AD46,AC46) -> 2.4548571 | AH72: =(AH68+AG68+AF68+AD68)/AVERAGE(AH46,AG46,AF46,AD46) -> 1.456044 | AI72: =(AI68+AH68+AG68+AF68)/AVERAGE(AI46,AH46,AG46,AF46) -> 0.48643842 | AJ72: =(AI68+AH68+AG68+AF68)/AVERAGE(AI46,AH46,AG46,AF46) -> 0.48643842 | AK72: =(AK68+AI68+AH68+AG68)/AVERAGE(AK46,AI46,AH46,AG46) -> 0.40003914 | AL72: =(AL68+AK68+AI68+AH68)/AVERAGE(AL46,AK46,AI46,AH46) -> 0.20434763 | AM72: =(AM68+AL68+AK68+AI68)/AVERAGE(AM46,AL46,AK46,AI46) -> 0.24280073 | AN72: =(AN68+AM68+AL68+AK68)/AVERAGE(AN46,AM46,AL46,AK46) -> 0.37092499 | AO72: =(AN68+AM68+AL68+AK68)/AVERAGE(AN46,AM46,AL46,AK46) -> 0.37092499 | AP72: =(AP68+AN68+AM68+AL68)/AVERAGE(AP46,AN46,AM46,AL46) -> 0.42849725 | AQ72: =(AQ68+AP68+AN68+AM68)/AVERAGE(AQ46,AP46,AN46,AM46) -> 1.4128769 | AR72: =(AR68+AQ68+AP68+AN68)/AVERAGE(AR46,AQ46,AP46,AN46) -> 1.8444547 | AS72: =(AS68+AR68+AQ68+AP68)/AVERAGE(AS46,AR46,AQ46,AP46) -> 2.057554 | AT72: =(AS68+AR68+AQ68+AP68)/AVERAGE(AS46,AR46,AQ46,AP46) -> 2.057554 | AU72: =(AU68+AS68+AR68+AQ68)/AVERAGE(AU46,AS46,AR46,AQ46) -> 1.8865979 | AV72: =(AV68+AU68+AS68+AR68)/AVERAGE(AV46,AU46,AS46,AR46) -> 1.3989099 | AW72: =(AW68+AV68+AU68+AS68)/AVERAGE(AW46,AV46,AU46,AS46) -> 1.1385906 | AX72: =(AX68+AW68+AV68+AU68)/AVERAGE(AX46,AW46,AV46,AU46) -> 0.75995047 | AY72: =(AX68+AW68+AV68+AU68)/AVERAGE(AX46,AW46,AV46,AU46) -> 0.75995047 | AZ72: =(AZ68+AX68+AW68+AV68)/AVERAGE(AZ46,AX46,AW46,AV46) -> 0.29361139 | BA72: =(BA68+AZ68+AX68+AW68)/AVERAGE(BA46,AZ46,AX46,AW46) -> 0.28442678 | BB72: =(BB68+BA68+AZ68+AX68)/AVERAGE(BB46,BA46,AZ46,AX46) -> 0.28130308 | BC72: =(BC68+BB68+BA68+AZ68)/AVERAGE(BC46,BB46,BA46,AZ46) -> 0.37901833 | BD72: =(BC68+BB68+BA68+AZ68)/AVERAGE(BC46,BB46,BA46,AZ46) -> 0.37901833 | BE72: =(BE68+BC68+BB68+BA68)/AVERAGE(BE46,BC46,BB46,BA46) -> 0.57947837 | BF72: =(BF68+BE68+BC68+BB68)/AVERAGE(BF46,BE46,BC46,BB46) -> 0.57260402 | BG72: =(BG68+BF68+BE68+BC68)/AVERAGE(BG46,BF46,BE46,BC46) -> 0.57847555 | BH72: =(BH68+BG68+BF68+BE68)/AVERAGE(BH46,BG46,BF46,BE46) -> 0.58211249 | BI72: =(BH68+BG68+BF68+BE68)/AVERAGE(BH46,BG46,BF46,BE46) -> 0.58211249
A73: TTM ROA | F73: =(E68+D68+C68+B68)/AVERAGE(E23,D23,C23,B23) -> 0 | G73: =(G68+E68+D68+C68)/AVERAGE(G23,E23,D23,C23) -> 0.039344262 | H73: =(G68+F68+E68+C68)/AVERAGE(G23,F23,E23,D23) -> 0.18869644 | I73: =(I68+H68+G68+E68)/AVERAGE(I23,H23,G23,E23) -> 0.10575262 | J73: =(J68+I68+H68+G68)/AVERAGE(J23,I23,H23,G23) -> 0.1596429 | K73: =(J68+I68+H68+G68)/AVERAGE(J23,I23,H23,G23) -> 0.1596429 | L73: =(L68+J68+I68+H68)/AVERAGE(L23,J23,I23,H23) -> 0.1167039 | M73: =(L68+K68+J68+H68)/AVERAGE(L23,K23,J23,I23) -> 0.24681633 | N73: =(N68+M68+L68+J68)/AVERAGE(N23,M23,L23,J23) -> 0.12117962 | O73: =(O68+N68+M68+L68)/AVERAGE(O23,N23,M23,L23) -> 0.089741857 | P73: =(O68+N68+M68+L68)/AVERAGE(O23,N23,M23,L23) -> 0.089741857 | Q73: =(Q68+O68+N68+M68)/AVERAGE(Q23,O23,N23,M23) -> 0.12371691 | R73: =(Q68+P68+O68+M68)/AVERAGE(Q23,P23,O23,N23) -> 0.17918528 | S73: =(S68+R68+Q68+O68)/AVERAGE(S23,R23,Q23,O23) -> 0.11894737 | T73: =(T68+S68+R68+Q68)/AVERAGE(T23,S23,R23,Q23) -> 0.10653009 | U73: =(T68+S68+R68+Q68)/AVERAGE(T23,S23,R23,Q23) -> 0.10653009 | V73: =(V68+T68+S68+R68)/AVERAGE(V23,T23,S23,R23) -> 0.11021148 | W73: =(V68+U68+T68+R68)/AVERAGE(V23,U23,T23,S23) -> 0.17614243 | X73: =(X68+W68+V68+T68)/AVERAGE(X23,W23,V23,T23) -> 0.086710282 | Y73: =(Y68+X68+W68+V68)/AVERAGE(Y23,X23,W23,V23) -> 0.11293196 | Z73: =(Y68+X68+W68+V68)/AVERAGE(Y23,X23,W23,V23) -> 0.11293196 | AA73: =(AA68+Y68+X68+W68)/AVERAGE(AA23,Y23,X23,W23) -> 0.10953917 | AB73: =(AA68+Z68+Y68+W68)/AVERAGE(AA23,Z23,Y23,X23) -> 0.19278291 | AC73: =(AC68+AB68+AA68+Y68)/AVERAGE(AC23,AB23,AA23,Y23) -> 0.12285456 | AD73: =(AD68+AC68+AB68+AA68)/AVERAGE(AD23,AC23,AB23,AA23) -> 0.13639685 | AE73: =(AD68+AC68+AB68+AA68)/AVERAGE(AD23,AC23,AB23,AA23) -> 0.13639685 | AF73: =(AF68+AD68+AC68+AB68)/AVERAGE(AF23,AD23,AC23,AB23) -> 0.11898898 | AG73: =(AF68+AE68+AD68+AB68)/AVERAGE(AF23,AE23,AD23,AC23) -> 0.21886792 | AH73: =(AH68+AG68+AF68+AD68)/AVERAGE(AH23,AG23,AF23,AD23) -> 0.081727062 | AI73: =(AI68+AH68+AG68+AF68)/AVERAGE(AI23,AH23,AG23,AF23) -> 0.033162067 | AJ73: =(AI68+AH68+AG68+AF68)/AVERAGE(AI23,AH23,AG23,AF23) -> 0.033162067 | AK73: =(AK68+AI68+AH68+AG68)/AVERAGE(AK23,AI23,AH23,AG23) -> 0.030137936 | AL73: =(AK68+AJ68+AI68+AG68)/AVERAGE(AK23,AJ23,AI23,AH23) -> 0.050039685 | AM73: =(AM68+AL68+AK68+AI68)/AVERAGE(AM23,AL23,AK23,AI23) -> 0.038442624 | AN73: =(AN68+AM68+AL68+AK68)/AVERAGE(AN23,AM23,AL23,AK23) -> 0.058187973 | AO73: =(AN68+AM68+AL68+AK68)/AVERAGE(AN23,AM23,AL23,AK23) -> 0.058187973 | AP73: =(AP68+AN68+AM68+AL68)/AVERAGE(AP23,AN23,AM23,AL23) -> 0.064142525 | AQ73: =(AP68+AO68+AN68+AL68)/AVERAGE(AP23,AO23,AN23,AM23) -> 0.11894097 | AR73: =(AR68+AQ68+AP68+AN68)/AVERAGE(AR23,AQ23,AP23,AN23) -> 0.074652163 | AS73: =(AS68+AR68+AQ68+AP68)/AVERAGE(AS23,AR23,AQ23,AP23) -> 0.083409484 | AT73: =(AS68+AR68+AQ68+AP68)/AVERAGE(AS23,AR23,AQ23,AP23) -> 0.083409484 | AU73: =(AU68+AS68+AR68+AQ68)/AVERAGE(AU23,AS23,AR23,AQ23) -> 0.11060587 | AV73: =(AU68+AS68+AR68+AQ68)/AVERAGE(AU23,AT23,AS23,AR23) -> 0.11434117 | AW73: =(AW68+AV68+AU68+AS68)/AVERAGE(AW23,AV23,AU23,AS23) -> 0.11356009 | AX73: =(AX68+AW68+AV68+AU68)/AVERAGE(AX23,AW23,AV23,AU23) -> 0.085625107 | AY73: =(AX68+AW68+AV68+AU68)/AVERAGE(AX23,AW23,AV23,AU23) -> 0.085625107 | AZ73: =(AZ68+AX68+AW68+AV68)/AVERAGE(AZ23,AX23,AW23,AV23) -> 0.032002309 | BA73: =(AZ68+AX68+AW68+AV68)/AVERAGE(AZ23,AY23,AX23,AW23) -> 0.031385731 | BB73: =(BB68+BA68+AZ68+AX68)/AVERAGE(BB23,BA23,AZ23,AX23) -> 0.028377681 | BC73: =(BC68+BB68+BA68+AZ68)/AVERAGE(BC23,BB23,BA23,AZ23) -> 0.036539961 | BD73: =(BC68+BB68+BA68+AZ68)/AVERAGE(BC23,BB23,BA23,AZ23) -> 0.036539961 | BE73: =(BE68+BC68+BB68+BA68)/AVERAGE(BE23,BC23,BB23,BA23) -> 0.05846838 | BF73: =(BE68+BC68+BB68+BA68)/AVERAGE(BE23,BD23,BC23,BB23) -> 0.05839586 | BG73: =(BG68+BF68+BE68+BC68)/AVERAGE(BG23,BF23,BE23,BC23) -> 0.064599949 | BH73: =(BH68+BG68+BF68+BE68)/AVERAGE(BH23,BG23,BF23,BE23) -> 0.068489343 | BI73: =(BH68+BG68+BF68+BE68)/AVERAGE(BH23,BG23,BF23,BE23) -> 0.068489343
A74: TTM ROIC | G74: =(G68+E68+D68+C68)/AVERAGE(G53,E53,D53,C53) -> 0.15859031 | H74: =(H68+G68+E68+D68)/AVERAGE(H53,G53,E53,D53) -> 0.29393628 | I74: =(I68+H68+G68+E68)/AVERAGE(I53,H53,G53,E53) -> 0.39720559 | J74: =(J68+I68+H68+G68)/AVERAGE(J53,I53,H53,G53) -> 0.48446215 | K74: =(J68+I68+H68+G68)/AVERAGE(J53,I53,H53,G53) -> 0.48446215 | L74: =(L68+J68+I68+H68)/AVERAGE(L53,J53,I53,H53) -> 0.29326288 | M74: =(M68+L68+J68+I68)/AVERAGE(M53,L53,J53,I53) -> 0.24992835 | N74: =(N68+M68+L68+J68)/AVERAGE(N53,M53,L53,J53) -> 0.23014257 | O74: =(O68+N68+M68+L68)/AVERAGE(O53,N53,M53,L53) -> 0.17091377 | P74: =(O68+N68+M68+L68)/AVERAGE(O53,N53,M53,L53) -> 0.17091377 | Q74: =(Q68+O68+N68+M68)/AVERAGE(Q53,O53,N53,M53) -> 0.23541506 | R74: =(R68+Q68+O68+N68)/AVERAGE(R53,Q53,O53,N53) -> 0.22721535 | S74: =(S68+R68+Q68+O68)/AVERAGE(S53,R53,Q53,O53) -> 0.22151433 | T74: =(T68+S68+R68+Q68)/AVERAGE(T53,S53,R53,Q53) -> 0.19804808 | U74: =(T68+S68+R68+Q68)/AVERAGE(T53,S53,R53,Q53) -> 0.19804808 | V74: =(V68+T68+S68+R68)/AVERAGE(V53,T53,S53,R53) -> 0.20826673 | W74: =(W68+V68+T68+S68)/AVERAGE(W53,V53,T53,S53) -> 0.17899902 | X74: =(X68+W68+V68+T68)/AVERAGE(X53,W53,V53,T53) -> 0.15387281 | Y74: =(Y68+X68+W68+V68)/AVERAGE(Y53,X53,W53,V53) -> 0.19291039 | Z74: =(Y68+X68+W68+V68)/AVERAGE(Y53,X53,W53,V53) -> 0.19291039 | AA74: =(AA68+Y68+X68+W68)/AVERAGE(AA53,Y53,X53,W53) -> 0.18045523 | AB74: =(AB68+AA68+Y68+X68)/AVERAGE(AB53,AA53,Y53,X53) -> 0.18576365 | AC74: =(AC68+AB68+AA68+Y68)/AVERAGE(AC53,AB53,AA53,Y53) -> 0.20818258 | AD74: =(AD68+AC68+AB68+AA68)/AVERAGE(AD53,AC53,AB53,AA53) -> 0.23565717 | AE74: =(AD68+AC68+AB68+AA68)/AVERAGE(AD53,AC53,AB53,AA53) -> 0.23565717 | AF74: =(AF68+AD68+AC68+AB68)/AVERAGE(AF53,AD53,AC53,AB53) -> 0.20775106 | AG74: =(AG68+AF68+AD68+AC68)/AVERAGE(AG53,AF53,AD53,AC53) -> 0.17652376 | AH74: =(AH68+AG68+AF68+AD68)/AVERAGE(AH53,AG53,AF53,AD53) -> 0.14112635 | AI74: =(AI68+AH68+AG68+AF68)/AVERAGE(AI53,AH53,AG53,AF53) -> 0.057007373 | AJ74: =(AI68+AH68+AG68+AF68)/AVERAGE(AI53,AH53,AG53,AF53) -> 0.057007373 | AK74: =(AK68+AI68+AH68+AG68)/AVERAGE(AK53,AI53,AH53,AG53) -> 0.051195351 | AL74: =(AL68+AK68+AI68+AH68)/AVERAGE(AL53,AK53,AI53,AH53) -> 0.049493913 | AM74: =(AM68+AL68+AK68+AI68)/AVERAGE(AM53,AL53,AK53,AI53) -> 0.060728475 | AN74: =(AN68+AM68+AL68+AK68)/AVERAGE(AN53,AM53,AL53,AK53) -> 0.090577694 | AO74: =(AN68+AM68+AL68+AK68)/AVERAGE(AN53,AM53,AL53,AK53) -> 0.090577694 | AP74: =(AP68+AN68+AM68+AL68)/AVERAGE(AP53,AN53,AM53,AL53) -> 0.099647394 | AQ74: =(AQ68+AP68+AN68+AM68)/AVERAGE(AQ53,AP53,AN53,AM53) -> 0.12477688 | AR74: =(AR68+AQ68+AP68+AN68)/AVERAGE(AR53,AQ53,AP53,AN53) -> 0.12671715 | AS74: =(AS68+AR68+AQ68+AP68)/AVERAGE(AS53,AR53,AQ53,AP53) -> 0.14752407 | AT74: =(AS68+AR68+AQ68+AP68)/AVERAGE(AS53,AR53,AQ53,AP53) -> 0.14752407 | AU74: =(AU68+AS68+AR68+AQ68)/AVERAGE(AU53,AS53,AR53,AQ53) -> 0.20207969 | AV74: =(AV68+AU68+AS68+AR68)/AVERAGE(AV53,AU53,AS53,AR53) -> 0.2104359 | AW74: =(AW68+AV68+AU68+AS68)/AVERAGE(AW53,AV53,AU53,AS53) -> 0.21163498 | AX74: =(AX68+AW68+AV68+AU68)/AVERAGE(AX53,AW53,AV53,AU53) -> 0.15931468 | AY74: =(AX68+AW68+AV68+AU68)/AVERAGE(AX53,AW53,AV53,AU53) -> 0.15931468 | AZ74: =(AZ68+AX68+AW68+AV68)/AVERAGE(AZ53,AX53,AW53,AV53) -> 0.058139154 | BA74: =(BA68+AZ68+AX68+AW68)/AVERAGE(BA53,AZ53,AX53,AW53) -> 0.053822598 | BB74: =(BB68+BA68+AZ68+AX68)/AVERAGE(BB53,BA53,AZ53,AX53) -> 0.049848422 | BC74: =(BC68+BB68+BA68+AZ68)/AVERAGE(BC53,BB53,BA53,AZ53) -> 0.062987166 | BD74: =(BC68+BB68+BA68+AZ68)/AVERAGE(BC53,BB53,BA53,AZ53) -> 0.062987166 | BE74: =(BE68+BC68+BB68+BA68)/AVERAGE(BE53,BC53,BB53,BA53) -> 0.10074898 | BF74: =(BF68+BE68+BC68+BB68)/AVERAGE(BF53,BE53,BC53,BB53) -> 0.10460387 | BG74: =(BG68+BF68+BE68+BC68)/AVERAGE(BG53,BF53,BE53,BC53) -> 0.11116895 | BH74: =(BH68+BG68+BF68+BE68)/AVERAGE(BH53,BG53,BF53,BE53) -> 0.11780072 | BI74: =(BH68+BG68+BF68+BE68)/AVERAGE(BH53,BG53,BF53,BE53) -> 0.11780072
A75: Net Debt/TTM Adj EBITDA | V75: =V52/(V69+T69+S69+R69) -> 9.9166667 | W75: =W52/(W69+V69+T69+S69) -> 4.8385827 | X75: =X52/(X69+W69+V69+T69) -> 3.4050992 | Y75: =Y52/(Y69+X69+W69+V69) -> 2.389662 | Z75: =Z52/(Y69+X69+W69+V69) -> 2.389662 | AA75: =AA52/(AA69+Y69+X69+W69) -> 2.7424242 | AB75: =AB52/(AB69+AA69+Y69+X69) -> 2.6978022 | AC75: =AC52/(AC69+AB69+AA69+Y69) -> 2.366129 | AD75: =AD52/(AD69+AC69+AB69+AA69) -> 2.3424 | AE75: =AE52/(AD69+AC69+AB69+AA69) -> 2.3424 | AF75: =AF52/(AF69+AD69+AC69+AB69) -> 2.7914555 | AG75: =AG52/(AG69+AF69+AD69+AC69) -> 3.3567476 | AH75: =AH52/(AH69+AG69+AF69+AD69) -> 4.1805846 | AI75: =AI52/(AI69+AH69+AG69+AF69) -> 5.2714602 | AJ75: =AJ52/(AI69+AH69+AG69+AF69) -> 5.2714602 | AK75: =AK52/(AK69+AI69+AH69+AG69) -> 5.8736576 | AL75: =AL52/(AL69+AK69+AI69+AH69) -> -2.205504 | AM75: =AM52/(AM69+AL69+AK69+AI69) -> 2.9718113 | AN75: =AN52/(AN69+AM69+AL69+AK69) -> 3.0973684 | AO75: =AO52/(AN69+AM69+AL69+AK69) -> 3.0973684 | AP75: =AP52/(AP69+AN69+AM69+AL69) -> 2.9223986 | AQ75: =AQ52/(AQ69+AP69+AN69+AM69) -> 2.604483 | AR75: =AR52/(AR69+AQ69+AP69+AN69) -> 2.5340192 | AS75: =AS52/(AS69+AR69+AQ69+AP69) -> 2.3169905 | AT75: =AT52/(AS69+AR69+AQ69+AP69) -> 2.3169905 | AU75: =AU52/(AU69+AS69+AR69+AQ69) -> 2.1377417 | AV75: =AV52/(AV69+AU69+AS69+AR69) -> 2.2305831 | AW75: =AW52/(AW69+AV69+AU69+AS69) -> 2.1948785 | AX75: =AX52/(AX69+AW69+AV69+AU69) -> 2.1902314 | AY75: =AY52/(AX69+AW69+AV69+AU69) -> 2.1902314 | AZ75: =AZ52/(AZ69+AX69+AW69+AV69) -> 3.3130453 | BA75: =BA52/(BA69+AZ69+AX69+AW69) -> 3.1427964 | BB75: =BB52/(BB69+BA69+AZ69+AX69) -> 2.9886671 | BC75: =BC52/(BC69+BB69+BA69+AZ69) -> 2.834652 | BD75: =BD52/(BC69+BB69+BA69+AZ69) -> 2.834652 | BE75: =BE52/(BE69+BC69+BB69+BA69) -> 2.7166027 | BF75: =BF52/(BF69+BE69+BC69+BB69) -> 2.6079724 | BG75: =BG52/(BG69+BF69+BE69+BC69) -> 2.4777804 | BH75: =BH52/(BH69+BG69+BF69+BE69) -> 2.3549669 | BI75: =BI52/(BH69+BG69+BF69+BE69) -> 2.3549669
A77: Operating Cycle - Current Quarter
A78: Inventory Turns | E78: =E71/AVERAGE(E13,D13) -> 0 | G78: =G71/AVERAGE(G13,F13) -> 2.1714286 | H78: =H71/AVERAGE(H13,G13) -> 2.1279461 | I78: =I71/AVERAGE(I13,H13) -> 2 | J78: =J71/AVERAGE(J13,I13) -> 1.9606742 | L78: =L71/AVERAGE(L13,K13) -> 2.0289855 | M78: =M71/AVERAGE(M13,L13) -> 1.989011 | N78: =N71/AVERAGE(N13,M13) -> 1.9282051 | O78: =O71/AVERAGE(O13,N13) -> 2.1021505 | Q78: =Q71/AVERAGE(Q13,P13) -> 1.9893617 | R78: =R71/AVERAGE(R13,Q13) -> 1.9795918 | S78: =S71/AVERAGE(S13,R13) -> 2.0714286 | T78: =T71/AVERAGE(T13,S13) -> 2.0913706 | V78: =V71/AVERAGE(V13,U13) -> 2.0412371 | W78: =W71/AVERAGE(W13,V13) -> 1.8411911 | X78: =X71/AVERAGE(X13,W13) -> 1.6532663 | Y78: =Y71/AVERAGE(Y13,X13) -> 2.0309278 | AA78: =AA71/AVERAGE(AA13,Z13) -> 2.0631068 | AB78: =AB71/AVERAGE(AB13,AA13) -> 2.1067285 | AC78: =AC71/AVERAGE(AC13,AB13) -> 2.2924731 | AD78: =AD71/AVERAGE(AD13,AC13) -> 2.3326733 | AF78: =AF71/AVERAGE(AF13,AE13) -> 0.67088123 | AG78: =AG71/AVERAGE(AG13,AF13) -> 0.69888889 | AH78: =AH71/AVERAGE(AH13,AG13) -> 0.65154639 | AI78: =AI71/AVERAGE(AI13,AH13) -> 1.2301729 | AK78: =AK71/AVERAGE(AK13,AJ13) -> 7.0627063 | AL78: =AL71/AVERAGE(AL13,AK13) -> 6.7326121 | AM78: =AM71/AVERAGE(AM13,AL13) -> 6.6715976 | AN78: =AN71/AVERAGE(AN13,AM13) -> 7.1721068 | AP78: =AP71/AVERAGE(AP13,AO13) -> 7.3641975 | AQ78: =AQ71/AVERAGE(AQ13,AP13) -> 7.0289855 | AR78: =AR71/AVERAGE(AR13,AQ13) -> 6.5353925 | AS78: =AS71/AVERAGE(AS13,AR13) -> 6.6382979 | AU78: =AU71/AVERAGE(AU13,AT13) -> 6.7284427 | AV78: =AV71/AVERAGE(AV13,AU13) -> 6.3572327 | AW78: =AW71/AVERAGE(AW13,AV13) -> 6.3140097 | AX78: =AX71/AVERAGE(AX13,AW13) -> 6.5864124 | AZ78: =AZ71/AVERAGE(AZ13,AY13) -> 6.3512623 | BA78: 6.48 | BB78: 6.58 | BC78: 6.65 | BE78: 6.3 | BF78: 6.25 | BG78: 6.22 | BH78: 6.16
A79: Receivable Turns | E79: =E70/AVERAGE(E12,D12) -> 0 | G79: =G70/AVERAGE(G12,F12) -> 1.3659218 | H79: =H70/AVERAGE(H12,G12) -> 1.3562005 | I79: =I70/AVERAGE(I12,H12) -> 1.3217822 | J79: =J70/AVERAGE(J12,I12) -> 1.3883249 | L79: =L70/AVERAGE(L12,K12) -> 1.3574097 | M79: =M70/AVERAGE(M12,L12) -> 1.3341149 | N79: =N70/AVERAGE(N12,M12) -> 1.2879464 | O79: =O70/AVERAGE(O12,N12) -> 1.3655172 | Q79: =Q70/AVERAGE(Q12,P12) -> 1.5054054 | R79: =R70/AVERAGE(R12,Q12) -> 1.6909871 | S79: =S70/AVERAGE(S12,R12) -> 1.5499368 | T79: =T70/AVERAGE(T12,S12) -> 1.526699 | V79: =V70/AVERAGE(V12,U12) -> 1.5251256 | W79: =W70/AVERAGE(W12,V12) -> 1.5475234 | X79: =X70/AVERAGE(X12,W12) -> 1.3796791 | Y79: =Y70/AVERAGE(Y12,X12) -> 1.5729795 | AA79: =AA70/AVERAGE(AA12,Z12) -> 1.5133256 | AB79: =AB70/AVERAGE(AB12,AA12) -> 1.5968109 | AC79: =AC70/AVERAGE(AC12,AB12) -> 1.6886994 | AD79: =AD70/AVERAGE(AD12,AC12) -> 1.693712 | AF79: =AF70/AVERAGE(AF12,AE12) -> 0.56003899 | AG79: =AG70/AVERAGE(AG12,AF12) -> 0.54162855 | AH79: =AH70/AVERAGE(AH12,AG12) -> 0.5539267 | AI79: =AI70/AVERAGE(AI12,AH12) -> 1.0334309 | AK79: =AK70/AVERAGE(AK12,AJ12) -> 5.4113821 | AL79: =AL70/AVERAGE(AL12,AK12) -> 5.8389831 | AM79: =AM70/AVERAGE(AM12,AL12) -> 5.6571429 | AN79: =AN70/AVERAGE(AN12,AM12) -> 5.0913838 | AP79: =AP70/AVERAGE(AP12,AO12) -> 4.5315534 | AQ79: =AQ70/AVERAGE(AQ12,AP12) -> 4.0258933 | AR79: =AR70/AVERAGE(AR12,AQ12) -> 4.0695316 | AS79: =AS70/AVERAGE(AS12,AR12) -> 4.7362697 | AU79: =AU70/AVERAGE(AU12,AT12) -> 4.842782 | AV79: =AV70/AVERAGE(AV12,AU12) -> 4.7213115 | AW79: =AW70/AVERAGE(AW12,AV12) -> 4.9914724 | AX79: =AX70/AVERAGE(AX12,AW12) -> 5.0590858 | AZ79: =AZ70/AVERAGE(AZ12,AY12) -> 4.9101542 | BA79: 5.1 | BB79: 5.31 | BC79: 5.3 | BE79: 4.9 | BF79: 4.85 | BG79: 4.965 | BH79: 4.87
A80: Payable Turns | E80: =E71/AVERAGE(E28,D28) -> 0 | G80: =G71/AVERAGE(G28,F28) -> 1.8823529 | H80: =H71/AVERAGE(H28,G28) -> 2 | I80: =I71/AVERAGE(I28,H28) -> 1.8415301 | J80: =J71/AVERAGE(J28,I28) -> 1.7989691 | L80: =L71/AVERAGE(L28,K28) -> 2.1021021 | M80: =M71/AVERAGE(M28,L28) -> 2.161194 | N80: =N71/AVERAGE(N28,M28) -> 2.0324324 | O80: =O71/AVERAGE(O28,N28) -> 2.2090395 | Q80: =Q71/AVERAGE(Q28,P28) -> 2.2666667 | R80: =R71/AVERAGE(R28,Q28) -> 2.5359477 | S80: =S71/AVERAGE(S28,R28) -> 2.5615142 | T80: =T71/AVERAGE(T28,S28) -> 2.4670659 | V80: =V71/AVERAGE(V28,U28) -> 2.0359897 | W80: =W71/AVERAGE(W28,V28) -> 1.8366337 | X80: =X71/AVERAGE(X28,W28) -> 1.8076923 | Y80: =Y71/AVERAGE(Y28,X28) -> 2.147139 | AA80: =AA71/AVERAGE(AA28,Z28) -> 2.4495677 | AB80: =AB71/AVERAGE(AB28,AA28) -> 2.6863905 | AC80: =AC71/AVERAGE(AC28,AB28) -> 2.6919192 | AD80: =AD71/AVERAGE(AD28,AC28) -> 2.5497835 | AF80: =AF71/AVERAGE(AF28,AE28) -> 0.75474138 | AG80: =AG71/AVERAGE(AG28,AF28) -> 0.82763158 | AH80: =AH71/AVERAGE(AH28,AG28) -> 0.75387674 | AI80: =AI71/AVERAGE(AI28,AH28) -> 1.3309677 | AK80: =AK71/AVERAGE(AK28,AJ28) -> 4.6724891 | AL80: =AL71/AVERAGE(AL28,AK28) -> 3.2900302 | AM80: =AM71/AVERAGE(AM28,AL28) -> 2.4753019 | AN80: =AN71/AVERAGE(AN28,AM28) -> 2.2473268 | AP80: =AP71/AVERAGE(AP28,AO28) -> 2.4359367 | AQ80: =AQ71/AVERAGE(AQ28,AP28) -> 2.4744898 | AR80: =AR71/AVERAGE(AR28,AQ28) -> 2.2419426 | AS80: =AS71/AVERAGE(AS28,AR28) -> 2.3562861 | AU80: =AU71/AVERAGE(AU28,AT28) -> 2.5415654 | AV80: =AV71/AVERAGE(AV28,AU28) -> 2.648847 | AW80: =AW71/AVERAGE(AW28,AV28) -> 2.5715691 | AX80: =AX71/AVERAGE(AX28,AW28) -> 2.5152481 | AZ80: =AZ71/AVERAGE(AZ28,AY28) -> 2.4907447 | BA80: 2.746 | BB80: 2.81 | BC80: 2.93 | BE80: 2.81 | BF80: 2.78 | BG80: 2.81 | BH80: 2.85
A81: Inventory Processing Period | G81: =90/G78 -> 41.447368 | H81: =90/H78 -> 42.294304 | I81: =90/I78 -> 45 | J81: =90/J78 -> 45.902579 | L81: 12.742991 | M81: 13.367769 | N81: 13.367769 | O81: 13.367769 | Q81: =90/Q78 -> 45.240642 | R81: =90/R78 -> 45.463918 | S81: =90/S78 -> 43.448276 | T81: =90/T78 -> 43.033981 | V81: =90/V78 -> 44.090909 | W81: =90/W78 -> 48.881402 | X81: =90/X78 -> 54.43769 | Y81: =90/Y78 -> 44.314721 | AA81: =90/AA78 -> 43.623529 | AB81: =90/AB78 -> 42.720264 | AC81: =90/AC78 -> 39.258912 | AD81: =90/AD78 -> 38.582343 | AF81: =90/AF78 -> 134.15191 | AG81: =90/AG78 -> 128.77583 | AH81: =90/AH78 -> 138.13291 | AI81: =90/AI78 -> 73.160446 | AK81: =90/AK78 -> 12.742991 | AL81: =90/AL78 -> 13.367769 | AM81: =90/AM78 -> 13.490022 | AN81: =90/AN78 -> 12.548614 | AP81: =90/AP78 -> 12.221291 | AQ81: =90/AQ78 -> 12.804124 | AR81: =90/AR78 -> 13.77117 | AS81: =90/AS78 -> 13.557692 | AU81: =90/AU78 -> 13.376052 | AV81: =90/AV78 -> 14.157103 | AW81: =90/AW78 -> 14.254017 | AX81: =90/AX78 -> 13.664495 | AZ81: =90/AZ78 -> 14.170411 | BA81: =90/BA78 -> 13.888889 | BB81: =90/BB78 -> 13.677812 | BC81: =90/BC78 -> 13.533835 | BE81: =90/BE78 -> 14.285714 | BF81: =90/BF78 -> 14.4 | BG81: =90/BG78 -> 14.469453 | BH81: =90/BH78 -> 14.61039
A82: Receivable Processing Period | G82: =90/G79 -> 65.889571 | H82: =90/H79 -> 66.361868 | I82: =90/I79 -> 68.089888 | J82: =90/J79 -> 64.826325 | L82: =90/L79 -> 66.302752 | M82: =90/M79 -> 67.460457 | N82: =90/N79 -> 69.878683 | O82: =90/O79 -> 65.909091 | Q82: =90/Q79 -> 59.78456 | R82: =90/R79 -> 53.22335 | S82: =90/S79 -> 58.066884 | T82: =90/T79 -> 58.950715 | V82: =90/V79 -> 59.011532 | W82: =90/W79 -> 58.157439 | X82: =90/X79 -> 65.232558 | Y82: =90/Y79 -> 57.216258 | AA82: =90/AA79 -> 59.471669 | AB82: =90/AB79 -> 56.36234 | AC82: =90/AC79 -> 53.295455 | AD82: =90/AD79 -> 53.137725 | AF82: =90/AF79 -> 160.7031 | AG82: =90/AG79 -> 166.16554 | AH82: =90/AH79 -> 162.47637 | AI82: =90/AI79 -> 87.088551 | AK82: =90/AK79 -> 16.631611 | AL82: =90/AL79 -> 15.413643 | AM82: =90/AM79 -> 15.909091 | AN82: =90/AN79 -> 17.676923 | AP82: =90/AP79 -> 19.860739 | AQ82: =90/AQ79 -> 22.355287 | AR82: =90/AR79 -> 22.115567 | AS82: =90/AS79 -> 19.002296 | AU82: =90/AU79 -> 18.584359 | AV82: =90/AV79 -> 19.0625 | AW82: =90/AW79 -> 18.030752 | AX82: =90/AX79 -> 17.789775 | AZ82: =90/AZ79 -> 18.329363 | BA82: =90/BA79 -> 17.647059 | BB82: =90/BB79 -> 16.949153 | BC82: =90/BC79 -> 16.981132 | BE82: =90/BE79 -> 18.367347 | BF82: =90/BF79 -> 18.556701 | BG82: =90/BG79 -> 18.126888 | BH82: =90/BH79 -> 18.480493
A83: Payable Payment Period | G83: =90/G80 -> 47.8125 | H83: =90/H80 -> 45 | I83: =90/I80 -> 48.872404 | J83: =90/J80 -> 50.028653 | L83: =90/L80 -> 42.814286 | M83: =90/M80 -> 41.643646 | N83: =90/N80 -> 44.281915 | O83: =90/O80 -> 40.741688 | Q83: =90/Q80 -> 39.705882 | R83: =90/R80 -> 35.489691 | S83: =90/S80 -> 35.135468 | T83: =90/T80 -> 36.480583 | V83: =90/V80 -> 44.204545 | W83: =90/W80 -> 49.002695 | X83: =90/X80 -> 49.787234 | Y83: =90/Y80 -> 41.916244 | AA83: =90/AA80 -> 36.741176 | AB83: =90/AB80 -> 33.502203 | AC83: =90/AC80 -> 33.433396 | AD83: =90/AD80 -> 35.297114 | AF83: =90/AF80 -> 119.24615 | AG83: =90/AG80 -> 108.74404 | AH83: =90/AH80 -> 119.38291 | AI83: =90/AI80 -> 67.619971 | AK83: =90/AK80 -> 19.261682 | AL83: =90/AL80 -> 27.355372 | AM83: =90/AM80 -> 36.359202 | AN83: =90/AN80 -> 40.04758 | AP83: =90/AP80 -> 36.946773 | AQ83: =90/AQ80 -> 36.371134 | AR83: =90/AR80 -> 40.143757 | AS83: =90/AS80 -> 38.195701 | AU83: =90/AU80 -> 35.411247 | AV83: =90/AV80 -> 33.977048 | AW83: =90/AW80 -> 34.998087 | AX83: =90/AX80 -> 35.781759 | AZ83: =90/AZ80 -> 36.133771 | BA83: =90/BA80 -> 32.774945 | BB83: =90/BB80 -> 32.02847 | BC83: =90/BC80 -> 30.716724 | BE83: =90/BE80 -> 32.02847 | BF83: =90/BF80 -> 32.374101 | BG83: =90/BG80 -> 32.02847 | BH83: =90/BH80 -> 31.578947
A84: Cash Conversion Cycle | G84: =G81+G82-G83 -> 59.524439 | H84: =H81+H82-H83 -> 63.656172 | I84: =I81+I82-I83 -> 64.217484 | J84: =J81+J82-J83 -> 60.700251 | L84: =L81+L82-L83 -> 36.231457 | M84: =M81+M82-M83 -> 39.184579 | N84: =N81+N82-N83 -> 38.964537 | O84: =O81+O82-O83 -> 38.535172 | Q84: =Q81+Q82-Q83 -> 65.31932 | R84: =R81+R82-R83 -> 63.197577 | S84: =S81+S82-S83 -> 66.379692 | T84: =T81+T82-T83 -> 65.504113 | V84: =V81+V82-V83 -> 58.897896 | W84: =W81+W82-W83 -> 58.036146 | X84: =X81+X82-X83 -> 69.883014 | Y84: =Y81+Y82-Y83 -> 59.614735 | AA84: =AA81+AA82-AA83 -> 66.354022 | AB84: =AB81+AB82-AB83 -> 65.580401 | AC84: =AC81+AC82-AC83 -> 59.12097 | AD84: =AD81+AD82-AD83 -> 56.422954 | AF84: =AF81+AF82-AF83 -> 175.60887 | AG84: =AG81+AG82-AG83 -> 186.19734 | AH84: =AH81+AH82-AH83 -> 181.22637 | AI84: =AI81+AI82-AI83 -> 92.629026 | AK84: =AK81+AK82-AK83 -> 10.112919 | AL84: =AL81+AL82-AL83 -> 1.4260397 | AM84: =AM81+AM82-AM83 -> -6.9600887 | AN84: =AN81+AN82-AN83 -> -9.8220426 | AP84: =AP81+AP82-AP83 -> -4.8647428 | AQ84: =AQ81+AQ82-AQ83 -> -1.2117235 | AR84: =AR81+AR82-AR83 -> -4.2570205 | AS84: =AS81+AS82-AS83 -> -5.6357128 | AU84: =AU81+AU82-AU83 -> -3.4508359 | AV84: =AV81+AV82-AV83 -> -0.7574446 | AW84: =AW81+AW82-AW83 -> -2.7133187 | AX84: =AX81+AX82-AX83 -> -4.3274886 | AZ84: =AZ81+AZ82-AZ83 -> -3.6339965 | BA84: =BA81+BA82-BA83 -> -1.2389977 | BB84: =BB81+BB82-BB83 -> -1.4015057 | BC84: =BC81+BC82-BC83 -> -0.20175689 | BE84: =BE81+BE82-BE83 -> 0.62459147 | BF84: =BF81+BF82-BF83 -> 0.58260031 | BG84: =BG81+BG82-BG83 -> 0.56787184 | BH84: =BH81+BH82-BH83 -> 1.5119351

Sheet CF
A3: Valvoline Inc. (VVV)
A4: Cash Flow Statement
A5: ($M's, except per share) | B5: =IS!B7 -> 1Q16 | C5: =IS!C7 -> 2Q16 | D5: =IS!D7 -> 3Q16 | E5: =IS!E7 -> 4Q16 | F5: =IS!F7 -> FY16 | G5: =IS!G7 -> 1Q17 | H5: =IS!H7 -> 2Q17 | I5: =IS!I7 -> 3Q17 | ... BI5: =IS!BI7 -> FY27E
A8: Net income | E8: 65 | F8: 273 | G8: 72 | H8: =143-G8 -> 71 | I8: =199-SUM(G8:H8) -> 56 | J8: =K8-SUM(G8:I8) -> 105 | K8: 304 | L8: -10 | M8: 67 | N8: =121-SUM(L8:M8) -> 64 | O8: =P8-SUM(L8:N8) -> 45 | P8: 166 | Q8: 53 | R8: 63 | S8: 65 | T8: =U8-SUM(Q8:S8) -> 27 | U8: 208 | V8: 73 | W8: =136-V8 -> 63 | X8: =195-SUM(V8:W8) -> 59 | Y8: =Z8-SUM(V8:X8) -> 122 | Z8: 317 | AA8: 87 | AB8: =155-AA8 -> 68 | AC8: =252-SUM(AA8:AB8) -> 97 | AD8: =AE8-SUM(AA8:AC8) -> 168 | AE8: 420 | AF8: 87 | AG8: =168.4-AF8 -> 81.4 | AH8: =267-SUM(AF8:AG8) -> 98.6 | AI8: =AJ8-SUM(AF8:AH8) -> 157.3 | AJ8: 424.3 | AK8: 81.9 | AL8: =1309.2-AK8 -> 1227.3 | AM8: =1370.8-SUM(AK8:AL8) -> 61.6 | AN8: =AO8-SUM(AK8:AM8) -> 48.9 | AO8: 1419.7 | AP8: 31.9 | AQ8: =73.3-AP8 -> 41.4 | AR8: =119.2-SUM(AP8:AQ8) -> 45.9 | AS8: =+AT8-SUM(AP8:AR8) -> 92.3 | AT8: 211.5 | AU8: 91.6 | AV8: =129.2-AU8 -> 37.6 | AW8: =185.7-SUM(AU8:AV8) -> 56.5 | AX8: =+AY8-SUM(AU8:AW8) -> 25 | AY8: 210.7 | AZ8: -32.8 | BA8: =IS!BA96 -> 40.435838 | BB8: =IS!BB96 -> 57.622197 | BC8: =IS!BC96 -> 58.769405 | BD8: =SUM(AZ8:BC8) -> 124.02744 | BE8: =IS!BE96 -> 42.996489 | BF8: =IS!BF96 -> 48.720523 | BG8: =IS!BG96 -> 71.390662 | BH8: =IS!BH96 -> 72.794342 | BI8: =SUM(BE8:BH8) -> 235.90202
A9: Depreciation and amortization | E9: 10 | F9: 38 | G9: 9 | H9: =18-G9 -> 9 | I9: =30-SUM(G9:H9) -> 12 | J9: =K9-SUM(G9:I9) -> 12 | K9: 42 | L9: 11 | M9: 14 | N9: 14 | O9: =P9-SUM(L9:N9) -> 15 | P9: 54 | Q9: 14 | R9: 14 | S9: 15 | T9: =U9-SUM(Q9:S9) -> 18 | U9: 61 | V9: 16 | W9: =31-V9 -> 15 | X9: =48-SUM(V9:W9) -> 17 | Y9: =Z9-SUM(V9:X9) -> 18 | Z9: 66 | AA9: 21 | AB9: =44-AA9 -> 23 | AC9: =68-SUM(AA9:AB9) -> 24 | AD9: =AE9-SUM(AA9:AC9) -> 24 | AE9: 92 | AF9: 16.9 | AG9: =34.5-AF9 -> 17.6 | AH9: 17.6 | AI9: =AJ9-SUM(AF9:AH9) -> 19.3 | AJ9: 71.4 | AK9: 18.5 | AL9: =39.1-AK9 -> 20.6 | AM9: =60.7-SUM(AK9:AL9) -> 21.6 | AN9: =AO9-SUM(AK9:AM9) -> 28.1 | AO9: 88.8 | AP9: 24.6 | AQ9: =50.2-AP9 -> 25.6 | AR9: =77.1-AQ9-AP9 -> 26.9 | AS9: =+AT9-SUM(AP9:AR9) -> 28.8 | AT9: 105.9 | AU9: 28 | AV9: 28.4 | AW9: 30.2 | AX9: =+AY9-SUM(AU9:AW9) -> 32.8 | AY9: 119.4 | AZ9: 33.5 | BA9: =+BA58*IS!BA86 -> 36.722451 | BB9: =+BB58*IS!BB86 -> 38.252294 | BC9: =+BC58*IS!BC86 -> 39.872331 | BD9: =SUM(AZ9:BC9) -> 148.34708 | BE9: =+BE58*IS!BE86 -> 41.4 | BF9: =+BF58*IS!BF86 -> 42.8 | BG9: =+BG58*IS!BG86 -> 44.5 | BH9: =+BH58*IS!BH86 -> 46.185134 | BI9: =SUM(BE9:BH9) -> 174.88513
A10: Stock-based compensation expense | E10: 0 | G10: 1 | H10: =3-G10 -> 2 | I10: =6-SUM(G10:H10) -> 3 | J10: =K10-SUM(G10:I10) -> 3 | K10: 9 | L10: 4 | M10: 3 | N10: 3 | O10: =P10-SUM(L10:N10) -> 2 | P10: 12 | Q10: 3 | R10: 2 | S10: -5 | T10: =U10-SUM(Q10:S10) -> 9 | U10: 9 | V10: 4 | W10: =3-V10 -> -1 | X10: =8-SUM(V10:W10) -> 5 | Y10: =Z10-SUM(V10:X10) -> 4 | Z10: 12 | AA10: 3 | AB10: =6-AA10 -> 3 | AC10: =10-SUM(AA10:AB10) -> 4 | AD10: =AE10-SUM(AA10:AC10) -> 4 | AE10: 14 | AF10: 3.2 | AG10: =7.2-AF10 -> 4 | AH10: =11-SUM(AF10:AG10) -> 3.8 | AI10: =AJ10-SUM(AF10:AH10) -> 3.4 | AJ10: 14.4 | AK10: 2.9 | AL10: =5.4-AK10 -> 2.5 | AM10: =8.8-SUM(AK10:AL10) -> 3.4 | AN10: =AO10-SUM(AK10:AM10) -> 3.4 | AO10: 12.2 | AP10: 2.4 | AQ10: =4.9-AP10 -> 2.5 | AR10: =9.4-SUM(AP10:AQ10) -> 4.5 | AS10: =+AT10-SUM(AP10:AR10) -> 2.6 | AT10: 12 | AU10: 2 | AV10: =4.6-AU10 -> 2.6 | AW10: =7.4-SUM(AU10:AV10) -> 2.8 | AX10: =+AY10-SUM(AU10:AW10) -> 3.1 | AY10: 10.5 | AZ10: 2.4 | BA10: 3 | BB10: 3 | BC10: 3 | BD10: =SUM(AZ10:BC10) -> 11.4 | BE10: 4 | BF10: 4 | BG10: 4 | BH10: 4 | BI10: =SUM(BE10:BH10) -> 16
A11: Deferred income taxes | E11: 13 | F11: 13 | G11: 0 | H11: 0 | I11: 0 | J11: =K11-SUM(G11:I11) -> 117 | K11: 117 | L11: 85 | M11: -20 | N11: 6 | O11: =P11-SUM(L11:N11) -> 74 | P11: 145 | Q11: 0 | R11: 0 | S11: 0 | T11: =U11-SUM(Q11:S11) -> 0 | V11: 0 | W11: 0 | X11: 0 | Y11: =Z11-SUM(V11:X11) -> 92 | Z11: 92 | AA11: 0 | AB11: 0 | AC11: =24-SUM(AA11:AB11) -> 24 | AD11: =AE11-SUM(AA11:AC11) -> 24 | AE11: 48 | AF11: 7.5 | AG11: =13.5-AF11 -> 6 | AH11: =30-SUM(AF11:AG11) -> 16.5 | AI11: =AJ11-SUM(AF11:AH11) -> -12 | AJ11: 18 | AK11: -26.5 | AL11: =-26.6-AK11 -> -0.1 | AM11: =-26.6-SUM(AK11:AL11) -> 0 | AN11: =AO11-SUM(AK11:AM11) -> 60.2 | AO11: 33.6 | AP11: 0 | AQ11: 0 | AR11: 0 | AS11: =+AT11-SUM(AP11:AR11) -> 23.5 | AT11: 23.5 | AU11: 0 | AV11: 0 | AW11: 0 | AX11: =+AY11-SUM(AU11:AW11) -> 38.3 | AY11: 38.3 | AZ11: 0 | BA11: 0 | BB11: 0 | BC11: 0 | BD11: =SUM(AZ11:BC11) -> 0 | BE11: 0 | BF11: 0 | BG11: 0 | BH11: 0 | BI11: =SUM(BE11:BH11) -> 0
A12: Loss on extinguishment of debt | E12: 0 | G12: 0 | H12: 0 | I12: 0 | J12: =K12-SUM(G12:I12) -> 0 | K12: 0 | L12: 0 | M12: 0 | N12: 0 | O12: =P12-SUM(L12:N12) -> 0 | P12: 0 | Q12: 0 | R12: 0 | S12: 0 | T12: =U12-SUM(Q12:S12) -> 0 | V12: 0 | W12: =19-V12 -> 19 | X12: =19-SUM(V12:W12) -> 0 | Y12: =Z12-SUM(V12:X12) -> 0 | Z12: 19 | AA12: 0 | AB12: =36-AA12 -> 36 | AC12: =36-SUM(AA12:AB12) -> 0 | AD12: =AE12-SUM(AA12:AC12) -> 0 | AE12: 36 | AF12: 0 | AG12: 0 | AH12: 0 | AI12: =AJ12-SUM(AF12:AH12) -> 0 | AJ12: 0 | AK12: 0 | AL12: 0 | AM12: 0 | AN12: =AO12-SUM(AK12:AM12) -> 0 | AO12: 0 | AP12: 0 | AQ12: 0 | AR12: 5.1 | AS12: =+AT12-SUM(AP12:AR12) -> 0 | AT12: 5.1 | AU12: 0 | AV12: 0 | AW12: 0 | AX12: =+AY12-SUM(AU12:AW12) -> 0 | AY12: 0 | AZ12: 0 | BA12: 0 | BB12: 0 | BC12: 0 | BD12: =SUM(AZ12:BC12) -> 0 | BE12: 0 | BF12: 0 | BG12: 0 | BH12: 0 | BI12: =SUM(BE12:BH12) -> 0
A13: Loss (gain) on pension remeasurements | E13: =-2-42 -> -44 | F13: -44 | G13: -11 | H13: =-18-G13 -> -7 | I13: =-16-8-SUM(G13:H13) -> -6 | J13: =K13-SUM(G13:I13) -> -456 | K13: =-412-68 -> -480 | L13: -3 | M13: -6 | N13: -4 | O13: =P13-SUM(L13:N13) -> 35 | P13: =38-16 -> 22 | Q13: -2 | R13: 0 | S13: -5 | T13: =U13-SUM(Q13:S13) -> -3 | U13: -10 | V13: -4 | W13: =-5-V13 -> -1 | X13: =-9-SUM(V13:W13) -> -4 | Y13: =Z13-SUM(V13:X13) -> -24 | Z13: =-11-22 -> -33 | AA13: -1 | AB13: =-4-AA13 -> -3 | AC13: =-4-SUM(AA13:AB13) -> 0 | AD13: =AE13-SUM(AA13:AC13) -> -73 | AE13: =-5-72 -> -77 | AF13: 0 | AG13: 0 | AH13: =0-SUM(AF13:AG13) -> 0 | AI13: =AJ13-SUM(AF13:AH13) -> 43.9 | AJ13: 43.9 | AK13: 0 | AL13: 0 | AM13: 0 | AN13: =AO13-SUM(AK13:AM13) -> -41.6 | AO13: -41.6 | AP13: 0 | AQ13: 0 | AR13: 0 | AS13: =+AT13-SUM(AP13:AR13) -> -2.4 | AT13: -2.4 | AU13: 0 | AV13: 0 | AW13: 0 | AX13: =+AY13-SUM(AU13:AW13) -> 26.6 | AY13: 26.6 | AZ13: 0 | BA13: 0 | BB13: 0 | BC13: 0 | BD13: =SUM(AZ13:BC13) -> 0 | BE13: 0 | BF13: 0 | BG13: 0 | BH13: 0 | BI13: =SUM(BE13:BH13) -> 0
A14: Equity Income from affiliates | E14: =-1+5 -> 4 | F14: =-12+16 -> 4 | G14: -4 | H14: =-7-G14 -> -3 | I14: =-10-SUM(G14:H14) -> -3 | J14: =K14-SUM(G14:I14) -> -2 | K14: -12 | L14: -2 | M14: -2 | N14: 0 | O14: =P14-SUM(L14:N14) -> 0 | P14: -4 | Q14: 0 | R14: -2 | S14: -2 | T14: =U14-SUM(Q14:S14) -> 1 | U14: -3 | V14: -2 | W14: =-1-V14 -> 1 | X14: =-3-SUM(V14:W14) -> -2 | Y14: =Z14-SUM(V14:X14) -> -4 | Z14: -7 | AA14: 0 | AB14: 0 | AC14: 0 | AD14: =AE14-SUM(AA14:AC14) -> 0 | AE14: 0 | AF14: 0 | AG14: 0 | AH14: 0 | AI14: =AJ14-SUM(AF14:AH14) -> 0 | AJ14: 0 | AK14: 0 | AL14: 0 | AM14: 0 | AN14: =AO14-SUM(AK14:AM14) -> 0 | AO14: 0 | AP14: 0 | AQ14: 0 | AR14: 0 | AS14: =+AT14-SUM(AP14:AR14) -> 0 | AT14: 0 | AU14: 0 | AV14: 0 | AW14: 0 | AX14: =+AY14-SUM(AU14:AW14) -> 0 | AY14: 0 | AZ14: 0 | BA14: 0 | BB14: 0 | BC14: 0 | BD14: =SUM(AZ14:BC14) -> 0 | BE14: 0 | BF14: 0 | BG14: 0 | BH14: 0 | BI14: =SUM(BE14:BH14) -> 0
A15: Other, net | E15: 4 | F15: =4+1 -> 5 | G15: 1 | H15: =2+3-G15 -> 4 | I15: =2+7-SUM(G15:H15) -> 4 | J15: =K15-SUM(G15:I15) -> 2 | K15: =8+3 -> 11 | L15: 1 | M15: -3 | N15: 3 | O15: =P15-SUM(L15:N15) -> 3 | P15: 4 | Q15: 6 | R15: =1-8 -> -7 | S15: =9+18 -> 27 | T15: =U15-SUM(Q15:S15) -> 64 | U15: 90 | V15: 2 | W15: =3-V15 -> 1 | X15: =4-SUM(V15:W15) -> 1 | Y15: =Z15-SUM(V15:X15) -> -2 | Z15: 2 | AA15: 0 | AB15: =2-AA15 -> 2 | AC15: =1-SUM(AA15:AB15) -> -1 | AD15: =AE15-SUM(AA15:AC15) -> 3 | AE15: 4 | AF15: 0.6 | AG15: =1.7-AF15 -> 1.1 | AH15: =-2-SUM(AF15:AG15) -> -3.7 | AI15: =AJ15-SUM(AF15:AH15) -> 6.2 | AJ15: 4.2 | AK15: 0.6 | AL15: =2.3-AK15 -> 1.7 | AM15: =2.1-SUM(AK15:AL15) -> -0.2 | AN15: =AO15-SUM(AK15:AM15) -> 9.8 | AO15: 11.9 | AP15: 1 | AQ15: =1.4-AP15 -> 0.4 | AR15: =1.6-AQ15-AP15 -> 0.2 | AS15: =+AT15-SUM(AP15:AR15) -> -43.5 | AT15: =-41.8-0.1 -> -41.9 | AU15: =-71.2+0.2 -> -71 | AV15: =-71.7+1-AU15 -> 0.3 | AW15: =-71.6+1.5-SUM(AU15:AV15) -> 0.6 | AX15: =+AY15-SUM(AU15:AW15) -> 2.6 | AY15: =-71.1+3.6 -> -67.5 | AZ15: =43.1+1.2 -> 44.3 | BA15: 0 | BB15: 0 | BC15: 0 | BD15: =SUM(AZ15:BC15) -> 44.3 | BE15: 0 | BF15: 0 | BG15: 0 | BH15: 0 | BI15: =SUM(BE15:BH15) -> 0
A16: Change in net working capital | E16: 73 | F16: 22 | G16: 20 | H16: =-74-G16 -> -94 | I16: =-53-SUM(G16:H16) -> 21 | J16: =K16-SUM(G16:I16) -> -68 | K16: -121 | L16: -66 | M16: 35 | N16: -13 | O16: =-79-SUM(L16:N16) -> -35 | P16: =SUM(L16:O16) -> -79 | Q16: 11 | R16: -21 | S16: -15 | T16: =U16-SUM(Q16:S16) -> -5 | U16: -30 | V16: =7+4-47+6 -> -30 | W16: =44-20-40-16-V16 -> -2 | X16: =13+3-10+3-SUM(V16:W16) -> 41 | Y16: =Z16-SUM(V16:X16) -> -105 | Z16: =-11-1-3-81 -> -96 | AA16: =7+6-40-4 -> -31 | AB16: =-14-13-26+4-AA16 -> -18 | AC16: =-55-39+59-56-SUM(AA16:AB16) -> -42 | AD16: =AE16-SUM(AA16:AC16) -> -42 | AE16: =-65-53+95-110 -> -133 | AF16: =-4.7+3.1-22.3-0.8 -> -24.7 | AG16: =-7.4-21.4-38.5-AF16 -> -42.6 | AH16: =-104-59+56-83-SUM(AF16:AG16) -> -122.7 | AI16: =AJ16-SUM(AF16:AH16) -> 63.1 | AJ16: =-17.5-5.4+24.5-128.5 -> -126.9 | AK16: 26 | AL16: =4.8-3.7+68.5+23.8-AK16 -> 67.4 | AM16: =80.5-SUM(AK16:AL16) -> -12.9 | AN16: =AO16-SUM(AK16:AM16) -> -31.8 | AO16: =26.4-3.3+111.3-85.7 -> 48.7 | AP16: -40 | AQ16: =-41.6-AP16 -> -1.6 | AR16: =-48.6-AQ16-AP16 -> -7 | AS16: =+AT16-SUM(AP16:AR16) -> 14.8 | AT16: -33.8 | AU16: -11.5 | AV16: =-2.5-4-22.6-0.2-AU16 -> -17.8 | AW16: =-0.7-3.8-28.4-0.2-SUM(AU16:AV16) -> -3.8 | AX16: =+AY16-SUM(AU16:AW16) -> -1.9 | AY16: -35 | AZ16: 16.8 | BA16: =-(BS!BA12-BS!AZ12)-(BS!BA13-BS!AZ13)+(BS!BA28-BS!AZ28) -> 1.0001968 | BB16: =-(BS!BB12-BS!BA12)-(BS!BB13-BS!BA13)+(BS!BB28-BS!BA28) -> -5.6729614 | BC16: =-(BS!BC12-BS!BB12)-(BS!BC13-BS!BB13)+(BS!BC28-BS!BB28) -> -4.0235534 | BD16: =SUM(AZ16:BC16) -> 8.103682 | BE16: =-(BS!BE12-BS!BD12)-(BS!BE13-BS!BD13)+(BS!BE28-BS!BD28) -> -1.2591838 | BF16: =-(BS!BF12-BS!BE12)-(BS!BF13-BS!BE13)+(BS!BF28-BS!BE28) -> -3.1876494 | BG16: =-(BS!BG12-BS!BF12)-(BS!BG13-BS!BF13)+(BS!BG28-BS!BF28) -> -6.7299168 | BH16: =-(BS!BH12-BS!BG12)-(BS!BH13-BS!BG13)+(BS!BH28-BS!BG28) -> -4.3380236 | BI16: =SUM(BE16:BH16) -> -15.514774
A17: Income from Discontinued Operations | E17: 0 | F17: 0 | G17: 0 | H17: 0 | I17: 0 | J17: =K17-SUM(G17:I17) -> 0 | K17: 0 | L17: 0 | M17: 0 | N17: 0 | O17: =P17-SUM(L17:N17) -> 0 | P17: 0 | Q17: 0 | R17: 0 | S17: 0 | T17: =U17-SUM(Q17:S17) -> 0 | U17: 0 | V17: 0 | W17: 0 | X17: 0 | Y17: =Z17-SUM(V17:X17) -> 0 | Z17: 0 | AA17: 0 | AB17: 0 | AC17: 0 | AD17: =AE17-SUM(AA17:AC17) -> 0 | AE17: 0 | AF17: -52.8 | AG17: =-111.2-AF17 -> -58.4 | AH17: 0 | AI17: =AJ17-SUM(AF17:AH17) -> -203.7 | AJ17: -314.9 | AK17: -54.9 | AL17: =-1249.3-AK17 -> -1194.4 | AM17: =-1246.4-SUM(AK17:AL17) -> 2.9 | AN17: =AO17-SUM(AK17:AM17) -> 26.1 | AO17: -1220.3 | AP17: =-IS!AP97 -> 2 | AQ17: =3.9-AP17 -> 1.9 | AR17: =6.2-SUM(AP17:AQ17) -> 2.3 | AS17: =+AT17-SUM(AP17:AR17) -> -3.2 | AT17: 3 | AU17: =-IS!AU97 -> 2.3 | AV17: =3-AU17 -> 0.7 | AW17: =3.5-SUM(AU17:AV17) -> 0.5 | AX17: =+AY17-SUM(AU17:AW17) -> 0.6 | AY17: 4.1 | AZ17: =-IS!AZ97 -> 0.6 | BA17: =-IS!BA97 -> 0 | BB17: =-IS!BB97 -> 0 | BC17: =-IS!BC97 -> 0 | BD17: =SUM(AZ17:BC17) -> 0.6 | BE17: =-IS!BE97 -> 0 | BF17: =-IS!BF97 -> 0 | BG17: =-IS!BG97 -> 0 | BH17: =-IS!BH97 -> 0 | BI17: =SUM(BE17:BH17) -> 0
A18: Net cash provided by operating activities - continuing operations | E18: =SUM(E8:E17) -> 125 | F18: =SUM(F8:F17) -> 311 | G18: =SUM(G8:G16) -> 88 | H18: =SUM(H8:H16) -> -18 | I18: =SUM(I8:I16) -> 87 | J18: =SUM(J8:J16) -> -287 | K18: =SUM(K8:K17) -> -130 | L18: =SUM(L8:L16) -> 20 | M18: =SUM(M8:M16) -> 88 | N18: =SUM(N8:N16) -> 73 | O18: =SUM(O8:O16) -> 139 | P18: =SUM(P8:P17) -> 320 | Q18: =SUM(Q8:Q16) -> 85 | R18: =SUM(R8:R16) -> 49 | S18: =SUM(S8:S16) -> 80 | T18: =SUM(T8:T16) -> 111 | U18: =SUM(U8:U17) -> 325 | V18: =SUM(V8:V16) -> 59 | W18: =SUM(W8:W16) -> 95 | X18: =SUM(X8:X16) -> 117 | Y18: =SUM(Y8:Y16) -> 101 | Z18: =SUM(Z8:Z17) -> 372 | AA18: =SUM(AA8:AA16) -> 79 | AB18: =SUM(AB8:AB16) -> 111 | AC18: =SUM(AC8:AC16) -> 106 | AD18: =SUM(AD8:AD16) -> 108 | AE18: =SUM(AE8:AE17) -> 404 | AF18: =SUM(AF8:AF17) -> 37.7 | AG18: =SUM(AG8:AG17) -> 9.1 | AH18: =SUM(AH8:AH17) -> 10.1 | AI18: =SUM(AI8:AI17) -> 77.5 | AJ18: =SUM(AJ8:AJ17) -> 134.4 | AK18: =SUM(AK8:AK17) -> 48.5 | AL18: =SUM(AL8:AL17) -> 125 | ... BI18: =SUM(BI8:BI17) -> 411.27238
A19: Net cash provided by operating activities - discontinued operations | L19: 0 | M19: 0 | N19: 0 | O19: 0 | P19: =SUM(L19:O19) -> 0 | Q19: 0 | R19: 0 | S19: 0 | T19: 0 | U19: =SUM(Q19:T19) -> 0 | V19: 0 | W19: 0 | X19: 0 | Y19: 0 | Z19: 0 | AA19: 0 | AB19: 0 | AC19: 0 | AD19: 0 | AE19: 0 | AF19: -5.9 | AG19: =49-AF19 -> 54.9 | AH19: 0 | AI19: =AJ19-SUM(AF19:AH19) -> 100.8 | AJ19: 149.8 | AK19: -57.2 | AL19: =-63.4-AK19 -> -6.2 | AM19: =-298.3-SUM(AK19:AL19) -> -234.9 | AN19: =AO19-SUM(AK19:AM19) -> -95.5 | AO19: -393.8 | AP19: -2 | AQ19: =-3.9-AP19 -> -1.9 | AR19: =-6.2-AQ19-AP19 -> -2.3 | AS19: =+AT19-SUM(AP19:AR19) -> -11.6 | AT19: -17.8 | AU19: -0.2 | AV19: =-4.8-AU19 -> -4.6 | AW19: =-4.7-SUM(AU19:AV19) -> 0.1 | AX19: =+AY19-SUM(AU19:AW19) -> -5.2 | AY19: -9.9 | AZ19: 0 | BA19: 0 | BB19: 0 | BC19: 0 | BD19: =SUM(AZ19:BC19) -> 0 | BE19: 0 | BF19: 0 | BG19: 0 | BH19: 0 | BI19: =SUM(BE19:BH19) -> 0
A21: Additions to PP&E | E21: -34 | F21: -66 | G21: -9 | H21: =-27-G21 -> -18 | I21: =-43-SUM(G21:H21) -> -16 | J21: =K21-SUM(G21:I21) -> -25 | K21: =-68 -> -68 | L21: -14 | M21: -16 | N21: -21 | O21: =P21-SUM(L21:N21) -> -42 | P21: -93 | Q21: -27 | R21: -21 | S21: -25 | T21: =U21-SUM(Q21:S21) -> -35 | U21: -108 | V21: -28 | W21: =-57-V21 -> -29 | X21: =-94-SUM(V21:W21) -> -37 | Y21: =Z21-SUM(V21:X21) -> -57 | Z21: -151 | AA21: -35 | AB21: =-74-AA21 -> -39 | AC21: =-106-SUM(AA21:AB21) -> -32 | AD21: =AE21-SUM(AA21:AC21) -> -38 | AE21: =-144 -> -144 | AF21: -32 | AG21: =-57.7-AF21 -> -25.7 | AH21: =-102-SUM(AF21:AG21) -> -44.3 | AI21: =AJ21-SUM(AF21:AH21) -> -30 | AJ21: -132 | AK21: -39.9 | AL21: =-79.4-AK21 -> -39.5 | AM21: =-125.9-SUM(AK21:AL21) -> -46.5 | AN21: =AO21-SUM(AK21:AM21) -> -54.6 | AO21: -180.5 | AP21: -42.3 | AQ21: =-87.2-AP21 -> -44.9 | AR21: =-153-AQ21-AP21 -> -65.8 | AS21: =+AT21-SUM(AP21:AR21) -> -71.4 | AT21: -224.4 | AU21: -53.6 | AV21: =-105.4-AU21 -> -51.8 | AW21: =-160.3-SUM(AU21:AV21) -> -54.9 | AX21: =+AY21-SUM(AU21:AW21) -> -98.9 | AY21: -259.2 | AZ21: -57.4 | BA21: -60 | BB21: -70 | BC21: -75 | BD21: =SUM(AZ21:BC21) -> -262.4 | BE21: -60 | BF21: -65 | BG21: -85 | BH21: -90 | BI21: =SUM(BE21:BH21) -> -300
A22: Notes Receivable, net of repayments | E22: 0 | F22: 0 | G22: 0 | H22: 0 | I22: 0 | J22: =K22-SUM(G22:I22) -> 0 | K22: 0 | L22: 0 | M22: 0 | N22: 0 | O22: =P22-SUM(L22:N22) -> 0 | P22: 0 | Q22: 0 | R22: 0 | S22: 0 | T22: =U22-SUM(Q22:S22) -> 0 | U22: 0 | V22: 0 | W22: 0 | X22: =-31-SUM(V22:W22) -> -31 | Y22: =Z22-SUM(V22:X22) -> 0 | Z22: -31 | AA22: 9 | AB22: =12-AA22 -> 3 | AC22: =14-SUM(AA22:AB22) -> 2 | AD22: =AE22-SUM(AA22:AC22) -> 3 | AE22: 17 | AF22: 3 | AG22: =0-AF22 -> -3 | AH22: =9-SUM(AF22:AG22) -> 9 | AI22: =AJ22-SUM(AF22:AH22) -> 2.2 | AJ22: 11.2 | AK22: -0.5 | AL22: =0-AK22 -> 0.5 | AM22: =0-SUM(AK22:AL22) -> 0 | AN22: =AO22-SUM(AK22:AM22) -> 0 | AO22: 0 | AP22: 0 | AQ22: 0 | AR22: 0 | AS22: =+AT22-SUM(AP22:AR22) -> 0 | AT22: 0 | AU22: 0 | AV22: 0 | AW22: 0 | AX22: =+AY22-SUM(AU22:AW22) -> 0 | AY22: 0 | AZ22: 0 | BA22: 0 | BB22: 0 | BC22: 0 | BD22: =SUM(AZ22:BC22) -> 0 | BE22: 0 | BF22: 0 | BG22: 0 | BH22: 0 | BI22: =SUM(BE22:BH22) -> 0
A23: Acquisitions, net of cash acquired | E23: -13 | F23: -83 | G23: 0 | H23: =-48-G23 -> -48 | I23: =-66-SUM(G23:H23) -> -18 | J23: =K23-SUM(G23:I23) -> -2 | K23: -68 | L23: -60 | M23: -7 | N23: -4 | O23: =P23-SUM(L23:N23) -> -54 | P23: -125 | Q23: -30 | R23: -5 | S23: -15 | T23: =U23-SUM(Q23:S23) -> -28 | U23: -78 | V23: -6 | W23: =-11-V23 -> -5 | X23: =-18-SUM(V23:W23) -> -7 | Y23: =Z23-SUM(V23:X23) -> -22 | Z23: -40 | AA23: -218 | AB23: =-223-AA23 -> -5 | AC23: =-267-SUM(AA23:AB23) -> -44 | AD23: =AE23-SUM(AA23:AC23) -> -15 | AE23: -282 | AF23: -13.6 | AG23: =-23.4-AF23 -> -9.8 | AH23: =-50-SUM(AF23:AG23) -> -26.6 | AI23: =AJ23-SUM(AF23:AH23) -> -0.7 | AJ23: -50.7 | AK23: -9.6 | AL23: =-18.9-AK23 -> -9.3 | AM23: =-27.8-SUM(AK23:AL23) -> -8.9 | AN23: =AO23-SUM(AK23:AM23) -> -8.5 | AO23: -36.3 | AP23: -8.3 | AQ23: =-21.3-AP23 -> -13 | AR23: =-27.9-AQ23-AP23 -> -6.6 | AS23: =+AT23-SUM(AP23:AR23) -> -24.8 | AT23: -52.7 | AU23: -4.4 | AV23: =-9.6-AU23 -> -5.2 | AW23: =-32.1-SUM(AU23:AV23) -> -22.5 | AX23: =+AY23-SUM(AU23:AW23) -> -32.9 | AY23: -65 | AZ23: -635.6 | BA23: -10 | BB23: -10 | BC23: -10 | BD23: =SUM(AZ23:BC23) -> -665.6 | BE23: -10 | BF23: -10 | BG23: -10 | BH23: -10 | BI23: =SUM(BE23:BH23) -> -40
A24: Proceeds from the disposal of businesses | E24: 0 | F24: 1 | G24: 0 | H24: 0 | I24: =1-SUM(G24:H24) -> 1 | J24: =K24-SUM(G24:I24) -> 0 | K24: 1 | L24: 0 | M24: 5 | N24: 0 | O24: =P24-SUM(L24:N24) -> -5 | P24: 0 | Q24: 0 | R24: 0 | S24: 0 | T24: =U24-SUM(Q24:S24) -> 0 | U24: 0 | V24: 0 | W24: 0 | X24: 0 | Y24: =Z24-SUM(V24:X24) -> 0 | Z24: 0 | AA24: 0 | AB24: 0 | AC24: 0 | AD24: =AE24-SUM(AA24:AC24) -> 0 | AE24: 0 | AF24: 0 | AG24: 0 | AH24: 0 | AI24: =AJ24-SUM(AF24:AH24) -> 0 | AJ24: 0 | AK24: 0 | AL24: 0 | AM24: 0 | AN24: =AO24-SUM(AK24:AM24) -> 0 | AO24: 0 | AP24: 0 | AQ24: 0 | AR24: 0 | AS24: =+AT24-SUM(AP24:AR24) -> 71.5 | AT24: 71.5 | AU24: 121 | AV24: =121-AU24 -> 0 | AW24: =121-SUM(AU24:AV24) -> 0 | AX24: =+AY24-SUM(AU24:AW24) -> 0 | AY24: 121 | AZ24: 63.6 | BA24: 0 | BB24: 0 | BC24: 0 | BD24: =SUM(AZ24:BC24) -> 63.6 | BE24: 0 | BF24: 0 | BG24: 0 | BH24: 0 | BI24: =SUM(BE24:BH24) -> 0
A25: Other | E25: 0 | F25: 0 | G25: -1 | H25: =-1-G25 -> 0 | I25: =-1-SUM(G25:H25) -> 0 | J25: =K25-SUM(G25:I25) -> 1 | K25: 0 | L25: 0 | M25: 1 | N25: -1 | O25: =P25-SUM(L25:N25) -> 5 | P25: 5 | Q25: 1 | R25: -3 | S25: 1 | T25: =U25-SUM(Q25:S25) -> -1 | U25: -2 | V25: -1 | W25: =-3-V25 -> -2 | X25: =0-SUM(V25:W25) -> 3 | Y25: =Z25-SUM(V25:X25) -> 0 | Z25: 0 | AA25: -1 | AB25: =9-AA25 -> 10 | AC25: =8-SUM(AA25:AB25) -> -1 | AD25: =AE25-SUM(AA25:AC25) -> 1 | AE25: 9 | AF25: -0.1 | AG25: =6.1-AF25 -> 6.2 | AH25: =0-SUM(AF25:AG25) -> -6.1 | AI25: =AJ25-SUM(AF25:AH25) -> 0.6 | AJ25: 0.6 | AK25: 1.6 | AL25: =2-AK25 -> 0.4 | AM25: =-440.4-0.8-SUM(AK25:AL25) -> -443.2 | AN25: =AO25-SUM(AK25:AM25) -> 80.8 | AO25: =-440.4+80 -> -360.4 | AP25: =230-7.1 -> 222.9 | AQ25: =350-10.9-AP25 -> 116.2 | AR25: =348-5.7-AQ25-AP25 -> 3.2 | AS25: =+AT25-SUM(AP25:AR25) -> 0.1 | AT25: =-3.5+350-4.1 -> 342.4 | AU25: 1 | AV25: =6-1.7-AU25 -> 3.3 | AW25: =-5.6+6-0.9-SUM(AU25:AV25) -> -4.8 | AX25: =+AY25-SUM(AU25:AW25) -> 2.6 | AY25: =-24.2+21.2-4.5+6+3.6 -> 2.1 | AZ25: -2 | BA25: 0 | BB25: 0 | BC25: 0 | BD25: =SUM(AZ25:BC25) -> -2 | BE25: 0 | BF25: 0 | BG25: 0 | BH25: 0 | BI25: =SUM(BE25:BH25) -> 0
A26: Net cash used for investing activities - continuing operations | E26: =SUM(E21:E25) -> -47 | F26: =SUM(F21:F25) -> -148 | G26: =SUM(G21:G25) -> -10 | H26: =SUM(H21:H25) -> -66 | I26: =SUM(I21:I25) -> -33 | J26: =SUM(J21:J25) -> -26 | K26: =SUM(K21:K25) -> -135 | L26: =SUM(L21:L25) -> -74 | ... BI26: =SUM(BI21:BI25) -> -340
A27: Net cash used in investing activities - discontinued operations | L27: 0 | M27: 0 | Q27: 0 | R27: 0 | S27: 0 | T27: 0 | U27: =SUM(Q27:T27) -> 0 | V27: 0 | W27: 0 | X27: 0 | Y27: 0 | Z27: 0 | AA27: 0 | AB27: 0 | AC27: 0 | AD27: 0 | AE27: 0 | AF27: -3.1 | AG27: =-9.2-AF27 -> -6.1 | AH27: 0 | AI27: =AJ27-SUM(AF27:AH27) -> -27.5 | AJ27: -36.7 | AK27: -8.4 | AL27: =2623.2-AK27 -> 2631.6 | AM27: =2621-SUM(AK27:AL27) -> -2.2 | AN27: =AO27-SUM(AK27:AM27) -> -0.1 | AO27: 2620.9 | AP27: 0 | AQ27: =0-AP27 -> 0 | AR27: 0 | AS27: 0 | AT27: =SUM(AP27:AS27) -> 0 | AU27: 0 | AV27: 0 | AW27: 0 | AX27: 0 | AY27: =SUM(AU27:AX27) -> 0 | AZ27: 0 | BA27: 0 | BB27: 0 | BC27: 0 | BD27: =SUM(AZ27:BC27) -> 0 | BE27: 0 | BF27: 0 | BG27: 0 | BH27: 0 | BI27: =SUM(BE27:BH27) -> 0
A29: Proceeds from borrowings, net of issuance cost | E29: 1372 | F29: 1372 | G29: 75 | H29: =75-G29 -> 0 | I29: =75-SUM(G29:H29) -> 0 | J29: =K29-SUM(G29:I29) -> 395 | K29: 470 | L29: 44 | M29: =95-L29 -> 51 | N29: =170-SUM(L29:M29) -> 75 | O29: =P29-SUM(L29:N29) -> 134 | P29: 304 | Q29: 100 | R29: =162-Q29 -> 62 | S29: =743-SUM(Q29:R29) -> 581 | T29: =U29-SUM(Q29:S29) -> 7 | U29: 750 | V29: 0 | W29: =1132-V29 -> 1132 | X29: =1547-SUM(V29:W29) -> 415 | Y29: =Z29-SUM(V29:X29) -> 11 | Z29: 1558 | AA29: 11 | AB29: =546-AA29 -> 535 | AC29: =555-SUM(AA29:AB29) -> 9 | AD29: =AE29-SUM(AA29:AC29) -> 0 | AE29: 555 | AF29: 0 | AG29: 0 | AH29: =414-SUM(AF29:AG29) -> 414 | AI29: =AJ29-SUM(AF29:AH29) -> -391 | AJ29: 23 | AK29: 250 | AL29: =920.9-AK29 -> 670.9 | AM29: =920.9-SUM(AK29:AL29) -> 0 | AN29: =AO29-SUM(AK29:AM29) -> 0.1 | AO29: 921 | AP29: 0 | AQ29: =0-AP29 -> 0 | AR29: =200-AQ29-AP29 -> 200 | AS29: =+AT29-SUM(AP29:AR29) -> 0 | AT29: 200 | AU29: 25 | AV29: =75-AU29 -> 50 | AW29: =85-SUM(AU29:AV29) -> 10 | AX29: =+AY29-SUM(AU29:AW29) -> 0 | AY29: 85 | AZ29: =740-13.7 -> 726.3 | BA29: 0 | BB29: 0 | BC29: 0 | BD29: =SUM(AZ29:BC29) -> 726.3 | BE29: 0 | BF29: 0 | BG29: 0 | BH29: 0 | BI29: =SUM(BE29:BH29) -> 0
A30: Repayments on borrowings | E30: -637 | F30: -637 | G30: -79 | H30: =-83-G30 -> -4 | I30: =-87-SUM(G30:H30) -> -4 | J30: =K30-SUM(G30:I30) -> -3 | K30: -90 | L30: -4 | M30: =-15-L30 -> -11 | N30: =-39-SUM(L30:M30) -> -24 | O30: =P30-SUM(L30:N30) -> -69 | P30: -108 | Q30: -101 | R30: =-137-Q30 -> -36 | S30: =-727-SUM(Q30:R30) -> -590 | T30: =U30-SUM(Q30:S30) -> -7 | U30: -734 | V30: 0 | W30: =-475-15-V30 -> -490 | X30: =-16-925-15-SUM(V30:W30) -> -466 | Y30: =Z30-SUM(V30:X30) -> -4 | Z30: =-16-929-15 -> -960 | AA30: 0 | AB30: =-800-26-AA30 -> -826 | AC30: =-7-829-26-SUM(AA30:AB30) -> -36 | AD30: =AE30-SUM(AA30:AC30) -> 0 | AE30: =-7-829-26 -> -862 | AF30: 0 | AG30: 0 | AH30: =-407-SUM(AF30:AG30) -> -407 | AI30: =AJ30-SUM(AF30:AH30) -> 368.9 | AJ30: -38.1 | AK30: -119.4 | AL30: =-909-AK30 -> -789.6 | AM30: =-915-SUM(AK30:AL30) -> -6 | AN30: =AO30-SUM(AK30:AM30) -> -5.9 | AO30: -920.9 | AP30: -5.9 | AQ30: =-11.8-AP30 -> -5.9 | AR30: =-642.8-AQ30-AP30 -> -631 | AS30: =+AT30-SUM(AP30:AR30) -> -56 | AT30: -698.8 | AU30: -85.9 | AV30: =-91.9-AU30 -> -6 | AW30: =-97.8-SUM(AU30:AV30) -> -5.9 | AX30: =+AY30-SUM(AU30:AW30) -> -6 | AY30: -103.8 | AZ30: -135.9 | BA30: -10 | BB30: -10 | BC30: -10 | BD30: =SUM(AZ30:BC30) -> -165.9 | BE30: -15 | BF30: -15 | BG30: -15 | BH30: -15 | BI30: =SUM(BE30:BH30) -> -60
A31: Purchases of common stock | E31: 0 | F31: 0 | G31: 0 | H31: 0 | I31: =-50-SUM(G31:H31) -> -50 | J31: =K31-SUM(G31:I31) -> 0 | K31: -50 | L31: =-37 -> -37 | M31: =-123-L31 -> -86 | N31: =-220-SUM(L31:M31) -> -97 | O31: =P31-SUM(L31:N31) -> -105 | P31: -325 | Q31: -1 | R31: 1 | S31: 0 | T31: =U31-SUM(Q31:S31) -> 0 | U31: 0 | V31: 0 | W31: =-60-V31 -> -60 | X31: =-60-SUM(V31:W31) -> 0 | Y31: =Z31-SUM(V31:X31) -> 0 | Z31: -60 | AA31: -58 | AB31: =-100-AA31 -> -42 | AC31: =-100-SUM(AA31:AB31) -> 0 | AD31: =AE31-SUM(AA31:AC31) -> -27 | AE31: -127 | AF31: -31.5 | AG31: =-66.3-AF31 -> -34.8 | AH31: =-104-SUM(AF31:AG31) -> -37.7 | AI31: =AJ31-SUM(AF31:AH31) -> -38.6 | AJ31: -142.6 | AK31: -87.4 | AL31: =-257.4-AK31 -> -170 | AM31: =-1395.5-SUM(AK31:AL31) -> -1138.1 | AN31: =AO31-SUM(AK31:AM31) -> -129.3 | AO31: -1524.8 | AP31: -171.7 | AQ31: =-212.2-AP31 -> -40.5 | AR31: =-212.2-AQ31-AP31 -> 0 | AS31: =+AT31-SUM(AP31:AR31) -> -14.6 | AT31: -226.8 | AU31: -45.7 | AV31: =-76.8-AU31 -> -31.1 | AW31: =-76.8-SUM(AU31:AV31) -> 0 | AX31: =+AY31-SUM(AU31:AW31) -> 0 | AY31: -76.8 | BD31: =SUM(AZ31:BC31) -> 0 | BI31: =SUM(BE31:BH31) -> 0
A32: Cash dividends paid | E32: 0 | F32: 0 | G32: -10 | H32: =-20-G32 -> -10 | I32: =-30-SUM(G32:H32) -> -10 | J32: =K32-SUM(G32:I32) -> -10 | K32: -40 | L32: -15 | M32: -15 | N32: -15 | O32: =P32-SUM(L32:N32) -> -13 | P32: -58 | Q32: -20 | R32: -20 | S32: -20 | T32: =U32-SUM(Q32:S32) -> -20 | U32: -80 | V32: -21 | W32: =-42-V32 -> -21 | X32: =-63-SUM(V32:W32) -> -21 | Y32: =Z32-SUM(V32:X32) -> -21 | Z32: -84 | AA32: -23 | AB32: =-46-AA32 -> -23 | AC32: =-69-SUM(AA32:AB32) -> -23 | AD32: =AE32-SUM(AA32:AC32) -> -22 | AE32: -91 | AF32: -22.5 | AG32: =-45-AF32 -> -22.5 | AH32: =-67-SUM(AF32:AG32) -> -22 | AI32: =AJ32-SUM(AF32:AH32) -> -22.2 | AJ32: -89.2 | AK32: -21.8 | AL32: =-21.8-AK32 -> 0 | AM32: =-21.8-SUM(AK32:AL32) -> 0 | AN32: =AO32-SUM(AK32:AM32) -> 0 | AO32: -21.8 | AP32: 0 | AQ32: 0 | AR32: 0 | AS32: =+AT32-SUM(AP32:AR32) -> 0 | AT32: 0 | AU32: 0 | AV32: 0 | AW32: 0 | AX32: =+AY32-SUM(AU32:AW32) -> 0 | AY32: 0 | AZ32: 0 | BA32: 0 | BB32: 0 | BC32: 0 | BD32: =SUM(AZ32:BC32) -> 0 | BE32: 0 | BF32: 0 | BG32: 0 | BH32: 0 | BI32: =SUM(BE32:BH32) -> 0
A33: Other | E33: =60+719-1419 -> -640 | F33: =60+719-1504 -> -725 | G33: -2 | H33: =-2-G33 -> 0 | I33: =5-SUM(G33:H33) -> 7 | J33: =K33-SUM(G33:I33) -> 0 | K33: 5 | L33: =-19 -> -19 | M33: =-1 -> -1 | N33: -1 | O33: =P33-SUM(L33:N33) -> -1 | P33: =-15-7 -> -22 | Q33: -3 | R33: -2 | S33: 0 | T33: =U33-SUM(Q33:S33) -> -2 | U33: -7 | V33: -2 | W33: =-3-V33 -> -1 | X33: =-3-SUM(V33:W33) -> 0 | Y33: =Z33-SUM(V33:X33) -> -1 | Z33: -4 | AA33: -3 | AB33: =-5-AA33 -> -2 | AC33: =-7-SUM(AA33:AB33) -> -2 | AD33: =AE33-SUM(AA33:AC33) -> -4 | AE33: -11 | AF33: -8.9 | AG33: =-11.2-AF33 -> -2.3 | AH33: =-14-SUM(AF33:AG33) -> -2.8 | AI33: =AJ33-SUM(AF33:AH33) -> -2 | AJ33: -16 | AK33: -8.9 | AL33: =-12.1-AK33 -> -3.2 | AM33: =-16-SUM(AK33:AL33) -> -3.9 | AN33: =AO33-SUM(AK33:AM33) -> -3 | AO33: -19 | AP33: -7.1 | AQ33: =-13.6-AP33 -> -6.5 | AR33: =-17.4-AQ33-AP33 -> -3.8 | AS33: =+AT33-SUM(AP33:AR33) -> -3.3 | AT33: -20.7 | AU33: -6.1 | AV33: =-10.7-AU33 -> -4.6 | AW33: =-14-SUM(AU33:AV33) -> -3.3 | AX33: =+AY33-SUM(AU33:AW33) -> -3.3 | AY33: =-12.2-5.1 -> -17.3 | AZ33: -5.7 | BA33: 0 | BB33: 0 | BC33: 0 | BD33: =SUM(AZ33:BC33) -> -5.7 | BE33: 0 | BF33: 0 | BG33: 0 | BH33: 0 | BI33: =SUM(BE33:BH33) -> 0
A34: Net cash used for financing activities - continuing operations | E34: =SUM(E29:E33) -> 95 | F34: =SUM(F29:F33) -> 10 | G34: =SUM(G29:G33) -> -16 | H34: =SUM(H29:H33) -> -14 | I34: =SUM(I29:I33) -> -57 | J34: =SUM(J29:J33) -> 382 | K34: =SUM(K29:K33) -> 295 | L34: =SUM(L29:L33) -> -31 | ... BI34: =SUM(BI29:BI33) -> -60
A35: Net cash used for financing activities - discontinued operations operations | Q35: 0 | R35: 0 | S35: 0 | T35: 0 | U35: =SUM(Q35:T35) -> 0 | V35: 0 | W35: 0 | X35: 0 | Y35: 0 | Z35: 0 | AA35: 0 | AB35: 0 | AC35: 0 | AD35: 0 | AE35: 0 | AF35: -0.9 | AG35: =-1-AF35 -> -0.1 | AH35: 0 | AI35: =AJ35-SUM(AF35:AH35) -> 45 | AJ35: 44 | AK35: 60 | AL35: =-108.1-AK35 -> -168.1 | AM35: =-108.1-SUM(AK35:AL35) -> 0 | AN35: =AO35-SUM(AK35:AM35) -> 0 | AO35: -108.1 | AP35: 0 | AQ35: =0-AP35 -> 0 | AR35: 0 | AS35: 0 | AT35: =SUM(AP35:AS35) -> 0 | AU35: 0 | AV35: 0 | AW35: 0 | AX35: 0 | AY35: =SUM(AU35:AX35) -> 0 | AZ35: 0 | BA35: 0 | BB35: 0 | BC35: 0 | BD35: =SUM(AZ35:BC35) -> 0 | BE35: 0 | BF35: 0 | BG35: 0 | BH35: 0 | BI35: =SUM(BE35:BH35) -> 0
A37: Effect of currency exchange rate changes on cash | E37: -1 | F37: -1 | G37: 2 | H37: =-1-G37 -> -3 | I37: =-1-SUM(G37:H37) -> 0 | J37: =K37-SUM(G37:I37) -> 0 | K37: -1 | L37: -1 | M37: =2-L37 -> 3 | N37: =-3-SUM(L37:M37) -> -5 | O37: =P37-SUM(L37:N37) -> 0 | P37: -3 | Q37: -1 | R37: =0-Q37 -> 1 | S37: 0 | T37: =U37-SUM(Q37:S37) -> -3 | U37: -3 | V37: 3 | W37: =-4-V37 -> -7 | X37: =-1-SUM(V37:W37) -> 3 | Y37: =Z37-SUM(V37:X37) -> 3 | Z37: 2 | AA37: 6 | AB37: =4-AA37 -> -2 | AC37: =5-SUM(AA37:AB37) -> 1 | AD37: =AE37-SUM(AA37:AC37) -> -3 | AE37: 2 | AF37: 0.1 | AG37: =0.7-AF37 -> 0.6 | AH37: =-1-SUM(AF37:AG37) -> -1.7 | AI37: =AJ37-SUM(AF37:AH37) -> -4.2 | AJ37: -5.2 | AK37: 2.1 | AL37: =1.1-AK37 -> -1 | AM37: =0.6-SUM(AK37:AL37) -> -0.5 | AN37: =AO37-SUM(AK37:AM37) -> -0.7 | AO37: -0.1 | AP37: 0.1 | AQ37: =0.2-AP37 -> 0.1 | AR37: =0.1-AQ37-AP37 -> -0.1 | AS37: =+AT37-SUM(AP37:AR37) -> -0.1 | AT37: 0 | AU37: -0.8 | AV37: =-0.7-AU37 -> 0.1 | AW37: =-0.2-SUM(AU37:AV37) -> 0.5 | AX37: =+AY37-SUM(AU37:AW37) -> -0.1 | AY37: -0.3 | AZ37: 0.2 | BA37: 0 | BB37: 0 | BC37: 0 | BD37: =SUM(AZ37:BC37) -> 0.2 | BE37: 0 | BF37: 0 | BG37: 0 | BH37: 0 | BI37: =SUM(BE37:BH37) -> 0
A39: (Decrease) increase in cash | E39: =SUM(E18,E26,E34,E19,E27,E35,E37) -> 172 | F39: =SUM(F18,F26,F34,F19,F27,F35,F37) -> 172 | G39: =SUM(G18,G26,G34,G19,G27,G35,G37) -> 64 | H39: =SUM(H18,H26,H34,H19,H27,H35,H37) -> -101 | I39: =SUM(I18,I26,I34,I19,I27,I35,I37) -> -3 | J39: =SUM(J18,J26,J34,J19,J27,J35,J37) -> 69 | K39: =SUM(K18,K26,K34,K19,K27,K35,K37) -> 29 | L39: =SUM(L18,L26,L34,L19,L27,L35,L37) -> -86 | ... AR39: =SUM(AR18,AR26,AR34,AR19,AR27,AR35,AR37) -> -428.5 | AS39: =+AT39-SUM(AP39:AR39) -> 2.7 | AT39: =SUM(AT18,AT26,AT34,AT19,AT27,AT35,AT37) -> -344.4 | AU39: =SUM(AU18,AU26,AU34,AU19,AU27,AU35,AU37) -> -8.3 | AV39: =SUM(AV18,AV26,AV34,AV19,AV27,AV35,AV37) -> 1.9 | AW39: =SUM(AW18,AW26,AW34,AW19,AW27,AW35,AW37) -> 6 | AX39: =SUM(AX18,AX26,AX34,AX19,AX27,AX35,AX37) -> -16.7 | AY39: =SUM(AY18,AY26,AY34,AY19,AY27,AY35,AY37) -> -17.1 | AZ39: =SUM(AZ18,AZ26,AZ34,AZ19,AZ27,AZ35,AZ37) -> 18.3 | BA39: =SUM(BA18,BA26,BA34,BA19,BA27,BA35,BA37) -> 1.1584858 | ... BI39: =SUM(BI18,BI26,BI34,BI19,BI27,BI35,BI37) -> 11.272376
A41: Cash at BOP | E41: 0 | G41: =F42 -> 172 | H41: =G42 -> 236 | I41: =H42 -> 135 | J41: =I42 -> 132 | K41: =F42 -> 172 | L41: =K42 -> 201 | M41: =L42 -> 115 | N41: =M42 -> 127 | O41: =N42 -> 107 | P41: =K42 -> 201 | Q41: =P42 -> 96 | R41: =Q42 -> 99 | S41: =R42 -> 125 | T41: =S42 -> 137 | U41: =P42 -> 96 | V41: =U42 -> 159 | W41: =V42 -> 163 | X41: =W42 -> 775 | Y41: =X42 -> 751 | Z41: =U42 -> 159 | AA41: =Z42 -> 761 | AB41: =AA42 -> 528 | AC41: =AB42 -> 248 | AD41: =AC42 -> 228 | AE41: =Z42 -> 761 | AF41: =AE42 -> 231.4 | AG41: =AF42 -> 153.7 | AH41: =AG42 -> 120.2 | AI41: =AH42 -> 5.1 | AJ41: =AE42 -> 231.4 | AK41: =AJ42 -> 83.9 | AL41: =AK42 -> 93 | AM41: =AL42 -> 2334.5 | AN41: =AM42 -> 526.7 | AO41: =AJ42 -> 83.9 | AP41: =AO42 -> 413.1 | AQ41: =AP42 -> 420.7 | AR41: =AQ42 -> 494.5 | AS41: =AR42 -> 66 | AT41: =AO42 -> 413.1 | AU41: =AT42 -> 68.7 | AV41: =AU42 -> 60.4 | AW41: =AV42 -> 62.3 | AX41: =AW42 -> 68.3 | AY41: =AT42 -> 68.7 | AZ41: =AY42 -> 51.6 | BA41: =AZ42 -> 69.9 | BB41: =BA42 -> 71.058486 | BC41: =BB42 -> 74.260016 | BD41: =AY42 -> 51.6 | BE41: =BD42 -> 76.878199 | BF41: =BE42 -> 79.015504 | BG41: =BF42 -> 81.348377 | BH41: =BG42 -> 84.509122 | BI41: =BD42 -> 76.878199
A42: Cash at EOP | E42: =E41+E39 -> 172 | F42: =E42 -> 172 | G42: =G41+G39 -> 236 | H42: =H41+H39 -> 135 | I42: =I41+I39 -> 132 | J42: =J41+J39 -> 201 | K42: =J42 -> 201 | L42: =L41+L39 -> 115 | M42: =M41+M39 -> 127 | N42: =N41+N39 -> 107 | O42: =O41+O39 -> 96 | P42: =O42 -> 96 | Q42: =Q41+Q39 -> 99 | R42: =R41+R39 -> 125 | S42: =S41+S39 -> 137 | T42: =T41+T39 -> 159 | U42: =T42 -> 159 | V42: =V41+V39 -> 163 | W42: =W41+W39 -> 775 | X42: =X41+X39 -> 751 | Y42: =Y41+Y39 -> 761 | Z42: =Y42 -> 761 | AA42: =AA41+AA39 -> 528 | AB42: =AB41+AB39 -> 248 | AC42: =AC41+AC39 -> 228 | AD42: =AD41+AD39 -> 231 | AE42: 231.4 | AF42: =AF41+AF39 -> 153.7 | AG42: =AG41+AG39 -> 120.2 | AH42: =AH41+AH39 -> 5.1 | AI42: =AI41+AI39 -> 83.9 | AJ42: =AI42 -> 83.9 | AK42: =AK41+AK39 -> 93 | AL42: =AL41+AL39 -> 2334.5 | AM42: =AM41+AM39 -> 526.7 | AN42: =AN41+AN39 -> 413.1 | AO42: =AN42 -> 413.1 | AP42: =AP41+AP39 -> 420.7 | AQ42: =AQ41+AQ39 -> 494.5 | AR42: =AR41+AR39 -> 66 | AS42: =AS41+AS39 -> 68.7 | AT42: =AS42 -> 68.7 | AU42: =AU41+AU39 -> 60.4 | AV42: =AV41+AV39 -> 62.3 | AW42: =AW41+AW39 -> 68.3 | AX42: =AX41+AX39 -> 51.6 | AY42: =AX42 -> 51.6 | AZ42: =AZ41+AZ39 -> 69.9 | BA42: =BA41+BA39 -> 71.058486 | BB42: =BB41+BB39 -> 74.260016 | BC42: =BC41+BC39 -> 76.878199 | BD42: =BC42 -> 76.878199 | BE42: =BE41+BE39 -> 79.015504 | BF42: =BF41+BF39 -> 81.348377 | BG42: =BG41+BG39 -> 84.509122 | BH42: =BH41+BH39 -> 88.150574 | BI42: =BH42 -> 88.150574
A44: FREE CASH FLOW
A45: Cash flow from operations | B45: =B18 -> 0 | C45: =C18 -> 0 | D45: =D18 -> 0 | E45: =E18 -> 125 | F45: =F18 -> 311 | G45: =G18 -> 88 | H45: =H18 -> -18 | I45: =I18 -> 87 | ... BI45: =BI18 -> 411.27238
A46: -Capital Expenditures | B46: =B21 -> 0 | C46: =C21 -> 0 | D46: =D21 -> 0 | E46: =E21 -> -34 | F46: =F21 -> -66 | G46: =G21 -> -9 | H46: =H21 -> -18 | I46: =I21 -> -16 | ... BI46: =BI21 -> -300
A47: Free cash flow | B47: =SUM(B45:B46) -> 0 | C47: =SUM(C45:C46) -> 0 | D47: =SUM(D45:D46) -> 0 | E47: =SUM(E45:E46) -> 91 | F47: =SUM(F45:F46) -> 245 | G47: =SUM(G45:G46) -> 79 | H47: =SUM(H45:H46) -> -36 | I47: =SUM(I45:I46) -> 71 | ... BI47: =SUM(BI45:BI46) -> 111.27238
A48: y/y growth | B48: 0 | C48: 0 | D48: 0 | E48: 0 | F48: 0 | G48: =IFERROR(G47/B47-1,"NM") -> NM | H48: =IFERROR(H47/C47-1,"NM") -> NM | I48: =IFERROR(I47/D47-1,"NM") -> NM | J48: =IFERROR(J47/E47-1,"NM") -> -4.4285714 | K48: =IFERROR(K47/F47-1,"NM") -> -1.8081633 | L48: =L47/G47-1 -> -0.92405063 | M48: =M47/H47-1 -> -3 | N48: =N47/I47-1 -> -0.26760563 | O48: =O47/J47-1 -> -1.3108974 | P48: =P47/K47-1 -> -2.1464646 | Q48: =Q47/L47-1 -> 8.6666667 | R48: =R47/M47-1 -> -0.61111111 | S48: =S47/N47-1 -> 0.057692308 | ... BI48: =BI47/BD47-1 -> 0.49603483
A50: FCF/share | B50: =B47/IS!B113 -> 0 | C50: =C47/IS!C113 -> 0 | D50: =D47/IS!D113 -> 0 | E50: =E47/IS!E113 -> 0.53216374 | F50: =F47/IS!F113 -> 1.3049268 | G50: =G47/IS!G113 -> 0.38536585 | H50: =H47/IS!H113 -> -0.17560976 | I50: =I47/IS!I113 -> 0.34803922 | ... BI50: =BI47/IS!BI113 -> 0.86788492
A51: y/y growth | B51: 0 | C51: 0 | D51: 0 | E51: 0 | F51: 0 | G51: =IFERROR(G50/B50-1,"NM") -> NM | H51: =IFERROR(H50/C50-1,"NM") -> NM | I51: =IFERROR(I50/D50-1,"NM") -> NM | J51: =IFERROR(J50/E50-1,"NM") -> -3.888107 | K51: =IFERROR(K50/F50-1,"NM") -> -1.7428771 | L51: =L50/G50-1 -> -0.92292267 | M51: =M50/H50-1 -> -3.05 | N51: =N50/I50-1 -> -0.23771199 | O51: =O50/J50-1 -> -1.3304303 | P51: =P50/K50-1 -> -2.1871503 | Q51: =Q50/L50-1 -> 9.3315697 | R51: =R50/M50-1 -> -0.58847737 | S51: =S50/N50-1 -> 0.096866097 | ... BI51: =BI50/BD50-1 -> 0.49603483
A52: Assumed Share Price | AF52: 32 | AG52: 32 | AH52: 32 | AI52: 32 | AK52: 34 | AL52: 37 | AM52: 38 | AN52: 32 | AP52: 34 | AQ52: 40 | AR52: 40 | AS52: 45 | AU52: =AS52 -> 45 | AV52: =AU52 -> 45 | AW52: =AU52 -> 45 | AX52: =AV52 -> 45 | AZ52: =AX52 -> 45 | BA52: =AZ52 -> 45 | BB52: =AZ52 -> 45 | BC52: =BA52 -> 45 | BE52: =BC52 -> 45 | BF52: =BE52 -> 45 | BG52: =BE52 -> 45 | BH52: =BF52 -> 45
A53: FCF Yield | AF53: =(AF50+AD50+AC50+AB50)/AF52 -> 0.037929634 | AG53: =(AG50+AF50+AD50+AC50)/AG52 -> 0.022768529 | AH53: =(AH50+AG50+AF50+AD50)/AH52 -> 0.0041612471 | AI53: =(AI50+AH50+AG50+AF50)/AI52 -> 0.00045318651 | AK53: =(AK50+AI50+AH50+AG50)/AK52 -> 0.00094011103 | AL53: =(AL50+AK50+AI50+AH50)/AL52 -> 0.016723099 | AM53: =(AM50+AL50+AK50+AI50)/AM52 -> 0.026153055 | AN53: =(AN50+AM50+AL50+AK50)/AN52 -> 0.033633694 | AP53: =(AP50+AN50+AM50+AL50)/AP52 -> 0.025699044 | AQ53: =(AQ50+AP50+AN50+AM50)/AQ52 -> 0.01430656 | AR53: =(AR50+AQ50+AP50+AN50)/AR52 -> 0.012029908 | AS53: =(AS50+AR50+AQ50+AP50)/AS52 -> 0.010028279 | AU53: =(AU50+AS50+AR50+AQ50)/AU52 -> 0.011350984 | AV53: =(AV50+AU50+AS50+AR50)/AV52 -> 0.0070493607 | AW53: =(AW50+AV50+AU50+AS50)/AW52 -> 0.010513716 | AX53: =(AX50+AW50+AV50+AU50)/AX52 -> 0.0083166139 | AZ53: =(AZ50+AX50+AW50+AV50)/AZ52 -> 0.011692854 | BA53: =(BA50+AZ50+AX50+AW50)/BA52 -> 0.015360472 | BB53: =(BB50+BA50+AZ50+AX50)/BB52 -> 0.013852676 | BC53: =(BC50+BB50+BA50+AZ50)/BC52 -> 0.012891394 | BE53: =(BE50+BC50+BB50+BA50)/BE52 -> 0.016312664 | BF53: =(BF50+BE50+BC50+BB50)/BF52 -> 0.017382934 | BG53: =(BG50+BF50+BE50+BC50)/BG52 -> 0.018242566 | BH53: =(BH50+BG50+BF50+BE50)/BH52 -> 0.019286283
A55: Forecast Drivers
A56: CapEx as a % of Revs | B56: 0 | C56: 0 | D56: 0 | E56: =-(E21/IS!E86) -> 0.068825911 | F56: =-(F21/IS!F86) -> 0.034214619 | G56: =-(G21/IS!G86) -> 0.018404908 | H56: =-(H21/IS!H86) -> 0.035019455 | I56: =-(I21/IS!I86) -> 0.029962547 | J56: =-(J21/IS!J86) -> 0.045703839 | K56: =-(K21/IS!K86) -> 0.032629559 | L56: =-(L21/IS!L86) -> 0.025688073 | ... BI56: =-(BI21/IS!BI86) -> 0.13151066
A57: Depreciation as a % of net PPE | B57: 0 | C57: 0 | D57: 0 | E57: =E9/BS!E18 -> 0.030864198 | F57: =F9/BS!F18 -> 0.11728395 | G57: =G9/BS!G18 -> 0.027190332 | H57: =H9/BS!H18 -> 0.025787966 | I57: =I9/BS!I18 -> 0.032520325 | J57: =J9/BS!J18 -> 0.030690537 | K57: =K9/BS!K18 -> 0.10741688 | L57: =L9/BS!L18 -> 0.028645833 | ... BI57: =BI9/BS!BI18 -> 0.14366642
A58: Depreciation as a % of revenue | B58: 0 | C58: 0 | D58: 0 | E58: =E9/IS!E86 -> 0.020242915 | F58: =F9/IS!F86 -> 0.019699326 | G58: =G9/IS!G86 -> 0.018404908 | H58: =H9/IS!H86 -> 0.017509728 | I58: =I9/IS!I86 -> 0.02247191 | J58: =J9/IS!J86 -> 0.021937843 | K58: =K9/IS!K86 -> 0.020153551 | L58: =L9/IS!L86 -> 0.020183486 | ... AX58: =AX9/IS!AX86 -> 0.072278537 | AY58: 0.073945354 | AZ58: =AZ9/IS!AZ86 -> 0.072542226 | BA58: 0.07261405 | BB58: 0.07060621 | BC58: 0.071167083 | BD58: 0.076846949 | BE58: 0.077351288 | BF58: 0.077587258 | BG58: 0.075454041 | BH58: 0.076394187 | BI58: 0.076846949
