Workbook
Name blank: #REF!
Name Current_Q: #REF!
Name export: #REF!
Name FY_92: #REF!
Name FY_93: #REF!
Name FY_94: #REF!
Name N_A: #REF!
Name N_M: #REF!
Name Next_Actual_Period_Range: '[1]Income Statement'!$D$3:$BE$6
Name NM_T: #REF!
Name Prior_Q: #REF!
Name Same_Q_Last_Yr: #REF!
Name source: #REF!
Name WIZARD_3YRATCF: #REF!
Name WIZARD_3YREBITDA: #REF!
Name WIZARD_3YRSECGROWTH: #REF!
Name WIZARD_AVGTRADINGVOLUME: #REF!
Name WIZARD_BKVALSHR: #REF!
Name WIZARD_BURNRATE: #REF!
Name WIZARD_CASH: #REF!
Name WIZARD_DIVYIELD: #REF!
Name WIZARD_EARNINGS: #REF!
Name WIZARD_EBITDABYSHROO: #REF!
Name WIZARD_EVBYEBITDAOO: #REF!
Name WIZARD_EVINVCAP: #REF!
Name WIZARD_LTDEBT: #REF!
Name WIZARD_MARKETCAP: #REF!
Name WIZARD_NETDEBTCAP: #REF!
Name WIZARD_OPERMARGIN: #REF!
Name WIZARD_PRICEESTNAV: #REF!
Name WIZARD_REVENUES: #REF!
Name WIZARD_ROAA: #REF!
Name WIZARD_ROAE: #REF!
Name WIZARD_ROE: #REF!
Name WIZARD_ROIC: #REF!
Name WIZARD_SHARESOUT: #REF!
Name WIZARD_STATIONREV: #REF!
Name WIZARD_TICKER: #REF!
Name WIZARD_TOTDEBTCAP: #REF!
Name WIZARD_Y1CAPREVR: [2]AMAT_FC!#REF!
Name WIZARD_Y1CAPREVS2: #REF!
Name WIZARD_Y1CASHCYEPSS1: #REF!
Name WIZARD_Y1CASHCYPES1: #REF!
Name WIZARD_Y1CYE: [2]AMAT_FC!#REF!
Name WIZARD_Y1CYPEE: [2]AMAT_FC!#REF!
Name WIZARD_Y1CYPES1: #REF!
Name WIZARD_Y1CYREVS2: #REF!
Name WIZARD_Y1CYS1: #REF!
Name WIZARD_Y1E: [2]AMAT_FC!#REF!
Name WIZARD_Y1EBITDAYRS2: #REF!
Name WIZARD_Y1EMVBYREV: #REF!
Name WIZARD_Y1EVEBITDAS2: #REF!
Name WIZARD_Y1PEE: [2]AMAT_FC!#REF!
Name WIZARD_Y1PES1: #REF!
Name WIZARD_Y1Q1E: [2]AMAT_FC!#REF!
Name WIZARD_Y1Q1R: [2]AMAT_FC!#REF!
Name WIZARD_Y1Q1S1: #REF!
Name WIZARD_Y1Q1S2: #REF!
Name WIZARD_Y1Q2E: [2]AMAT_FC!#REF!
Name WIZARD_Y1Q2R: [2]AMAT_FC!#REF!

Sheet Comparison
B2: Tempus Labs
D3: Y/Y Change | G3: Q/Q Change | J3: Estimate vs Actual
B4: Variance Analysis | D4: 4Q24 | E4: =K4 -> 4Q25 | F4: % Change | G4: 3Q25 | H4: =K4 -> 4Q25 | I4: % Change | J4: 4Q25E | K4: 4Q25 | L4: % Change
B5: Total Revenues | D5: =IS!AF15 -> 200.68 | E5: =K5 -> 367.211 | F5: =E5/D5-1 -> 0.82983357 | G5: 334.206 | H5: =K5 -> 367.211 | I5: =H5/G5-1 -> 0.098756456 | J5: 360.44908 | K5: =IS!AK15 -> 367.211 | L5: =K5/J5-1 -> 0.018759708
B6: Genomics Revenue | D6: =IS!AF9 -> 120.434 | E6: =K6 -> 266.856 | F6: =E6/D6-1 -> 1.2157862 | G6: 252.878 | H6: =K6 -> 266.856 | I6: =H6/G6-1 -> 0.055275667 | J6: 258.65224 | K6: =IS!AK9 -> 266.856 | L6: =K6/J6-1 -> 0.03171734
B7: Data & Other Revenue | D7: =IS!AF12 -> 80.246 | E7: =K7 -> 100.355 | F7: =E7/D7-1 -> 0.25059193 | G7: 81.328 | H7: =K7 -> 100.355 | I7: =H7/G7-1 -> 0.23395387 | J7: 101.79684 | K7: =IS!AK12 -> 100.355 | L7: =K7/J7-1 -> -0.014163911
B9: Cost of revenue | D9: =IS!AF23 -> 76.521 | E9: =K9 -> 126.384 | F9: =E9/D9-1 -> 0.65162504 | G9: 121.641 | H9: =K9 -> 126.384 | I9: =H9/G9-1 -> 0.038991787 | J9: 128.65 | K9: =IS!AK23 -> 126.384 | L9: =K9/J9-1 -> -0.017613648
B10: Non-GAAP Gross Profit | D10: =IS!AF25 -> 124.159 | E10: =K10 -> 240.827 | F10: =E10/D10-1 -> 0.93966607 | G10: 212.565 | H10: =K10 -> 240.827 | I10: =H10/G10-1 -> 0.13295698 | J10: 231.79908 | K10: =IS!AK25 -> 240.827 | L10: =K10/J10-1 -> 0.038947157
C11: Gross Margin | D11: =IS!AF26 -> 0.61869145 | E11: =K11 -> 0.6558273 | F11: =E11/D11-1 -> 0.060023223 | G11: 0.63602987 | H11: =K11 -> 0.6558273 | I11: =H11/G11-1 -> 0.031126572 | J11: 0.64308413 | K11: =IS!AK26 -> 0.6558273 | L11: =K11/J11-1 -> 0.019815712
B13: Operating Expenses
B14: Technology | D14: =IS!AF29 -> 26.448 | E14: =H14 -> 32.966 | F14: =E14/D14-1 -> 0.24644586 | G14: 32.346 | H14: =K14 -> 32.966 | I14: =H14/G14-1 -> 0.019167749 | J14: 32.260193 | K14: =IS!AK29 -> 32.966 | L14: =K14/J14-1 -> 0.021878583
B15: Research & Development | D15: =IS!AF31 -> 26.005 | E15: =K15 -> 45.302 | F15: =E15/D15-1 -> 0.74204961 | G15: 41.537 | H15: =K15 -> 45.302 | I15: =H15/G15-1 -> 0.090642078 | J15: 41.451644 | K15: =IS!AK31 -> 45.302 | L15: =K15/J15-1 -> 0.092887889
B16: General & Administrative | D16: =IS!AF33 -> 90.039 | E16: =K16 -> 158.278 | F16: =E16/D16-1 -> 0.7578827 | G16: 147.344 | H16: =K16 -> 158.278 | I16: =H16/G16-1 -> 0.074207297 | J16: 147.42367 | K16: =IS!AK33 -> 158.278 | L16: =K16/J16-1 -> 0.073626751
B17: Total Operating Expense | D17: =IS!AF35 -> 142.492 | E17: =K17 -> 236.546 | F17: =E17/D17-1 -> 0.66006513 | G17: 221.227 | H17: =K17 -> 236.546 | I17: =H17/G17-1 -> 0.069245616 | J17: 221.13551 | K17: =IS!AK35 -> 236.546 | L17: =K17/J17-1 -> 0.069687989 | M17: =K17-J17 -> 15.410489
B19: Non-GAAP Operating Income | D19: =IS!AF37 -> -18.333 | E19: =K19 -> 4.281 | F19: =E19/D19-1 -> -1.2335133 | G19: -8.662 | H19: =K19 -> 4.281 | I19: =H19/G19-1 -> -1.4942277 | J19: 10.663574 | K19: =IS!AK37 -> 4.281 | L19: =K19/J19-1 -> -0.59853984
C20: Operating Margins | D20: =IS!AF38 -> -0.091354395 | E20: =K20 -> 0.011658147 | F20: =E20/D20-1 -> -1.1276145 | G20: -0.025918146 | H20: =K20 -> 0.011658147 | I20: =H20/G20-1 -> -1.4498064 | J20: 0.029584134 | K20: =IS!AK38 -> 0.011658147 | L20: =K20/J20-1 -> -0.60593244
B22: GAAP & Non-Cash Charges | D22: =IS!AF53 -> 34.903 | E22: =K22 -> 65.326 | F22: =E22/D22-1 -> 0.87164427 | G22: 52.334 | H22: =K22 -> 65.326 | I22: =H22/G22-1 -> 0.24825161 | J22: 52.5 | K22: =IS!AK53 -> 65.326 | L22: =K22/J22-1 -> 0.24430476
B24: GAAP Operating Income | D24: =IS!AF55 -> -53.236 | E24: =K24 -> -61.045 | F24: =E24/D24-1 -> 0.14668645 | G24: -60.996 | H24: =K24 -> -61.045 | I24: =H24/G24-1 -> 0.00080333137 | J24: -41.836426 | K24: =IS!AK55 -> -61.045 | L24: =K24/J24-1 -> 0.45913515
C25: Operating Margins | D25: =IS!AF56 -> -0.26527805 | E25: =K25 -> -0.16623957 | F25: =E25/D25-1 -> -0.37333839 | G25: -0.18251019 | H25: =K25 -> -0.16623957 | I25: =H25/G25-1 -> -0.089149077 | J25: -0.11606751 | K25: =IS!AK56 -> -0.16623957 | L25: =K25/J25-1 -> 0.43226625
B27: Adjusted EBITDA | D27: =IS!AF63 -> -7.7515803 | E27: =K27 -> 12.893 | F27: =E27/D27-1 -> -2.6632738 | G27: 1.476 | H27: =K27 -> 12.893 | I27: =H27/G27-1 -> 7.7350949 | J27: 20.038574 | K27: =IS!AK63 -> 12.893 | L27: =K27/J27-1 -> -0.35659094
C28: Adjusted EBITDA Margin | D28: =IS!AF64 -> -0.038626571 | E28: =K28 -> 0.035110604 | F28: =E28/D28-1 -> -1.9089754 | G28: 0.0044164378 | H28: =K28 -> 0.035110604 | I28: =H28/G28-1 -> 6.9499827 | J28: 0.055593355 | K28: =IS!AK64 -> 0.035110604 | L28: =K28/J28-1 -> -0.36843884
B30: Other income (expense) | D30: =IS!AF61 -> 40.34442 | E30: =K30 -> 4.404 | F30: =E30/D30-1 -> -0.89083992 | G30: -20.228 | H30: =K30 -> 4.404 | I30: =H30/G30-1 -> -1.217718 | J30: -11.4 | K30: =IS!AK61 -> 4.404 | L30: =K30/J30-1 -> -1.3863158
B32: Non-GAAP Income Before Taxes | D32: =IS!AF66 -> -29.576 | E32: =K32 -> 8.685 | F32: =E32/D32-1 -> -1.2936503 | G32: -28.89 | H32: =K32 -> 8.685 | I32: =H32/G32-1 -> -1.3006231 | J32: -0.73642619 | K32: =IS!AK66 -> 8.685 | L32: =K32/J32-1 -> -12.793443
B33: Non-GAAP Income Tax | D33: =IS!AF67 -> -0.122 | E33: =K33 -> 5.992 | F33: =E33/D33-1 -> -50.114754 | G33: -0.276 | H33: =K33 -> 5.992 | I33: =H33/G33-1 -> -22.710145 | J33: 0 | K33: =IS!AK67 -> 5.992 | L33: =K33/J33-1 -> #DIV/0!
B34: Non-GAAP Net Income | D34: =IS!AF74 -> -13.01358 | E34: =K34 -> -54.166 | F34: =E34/D34-1 -> 3.1622673 | G34: -79.982 | H34: =K34 -> -54.166 | I34: =H34/G34-1 -> -0.32277262 | J34: -53.236426 | K34: =IS!AK74 -> -54.166 | L34: =K34/J34-1 -> 0.017461236
B36: GAAP Income Before Taxes | D36: =IS!AF71 -> -12.89158 | E36: =K36 -> -56.641 | F36: =E36/D36-1 -> 3.3936429 | G36: -81.224 | H36: =K36 -> -56.641 | I36: =H36/G36-1 -> -0.30265685 | J36: -53.236426 | K36: =IS!AK71 -> -56.641 | L36: =K36/J36-1 -> 0.06395196
B37: GAAP Income Tax | D37: =IS!AF72 -> -0.122 | E37: =K37 -> 5.992 | F37: =IFERROR(E37/D37-1, 0) -> -50.114754 | G37: -0.276 | H37: =K37 -> 5.992 | I37: =H37/G37-1 -> -22.710145 | J37: 0 | K37: =IS!AK72 -> 5.992 | L37: =K37/J37-1 -> #DIV/0!
B38: GAAP Net Income | D38: =IS!AF74 -> -13.01358 | E38: =K38 -> -54.166 | F38: =E38/D38-1 -> 3.1622673 | G38: -79.982 | H38: =K38 -> -54.166 | I38: =H38/G38-1 -> -0.32277262 | J38: -53.236426 | K38: =IS!AK74 -> -54.166 | L38: =K38/J38-1 -> 0.017461236
B40: GAAP EPS | D40: =IS!AF82 -> -0.18715117 | E40: =K40 -> -0.30414446 | F40: =IFERROR(E40/D40-1, 0) -> 0.62512724 | G40: -0.45718369 | H40: =K40 -> -0.30414446 | I40: =H40/G40-1 -> -0.3347434 | J40: -0.30351171 | K40: =IS!AK82 -> -0.30414446 | L40: =K40/J40-1 -> 0.0020847702
B42: Fully Diluted Shares Outstanding | D42: =IS!AF84 -> 166.398 | E42: =K42 -> 178.093 | F42: =IFERROR(E42/D42-1, 0) -> 0.070283297 | G42: 174.945 | H42: =K42 -> 178.093 | I42: =H42/G42-1 -> 0.017994227 | J42: 175.40156 | K42: =IS!AK84 -> 178.093 | L42: =K42/J42-1 -> 0.015344476
B43: Source: Company reports and Needham & Company, LLC, estimates

Sheet IS
C2: Tempus Labs (NASDAQ: TEM)
AL3: =+Diagnostics!AL13 -> 362.78
AL4: =+AL3/AG15 -> 0.52319156
AL5: =+AL16-AL4 -> 0.31094832
C8: Income Statement | D8: 1Q19 | E8: 2Q19 | F8: 3Q19 | G8: 4Q19 | H8: FY19 | I8: 1Q20 | J8: 2Q20 | K8: 3Q20 | L8: 4Q20 | M8: FY20 | N8: 1Q21 | O8: 2Q21 | P8: 3Q21 | Q8: 4Q21 | R8: FY21 | S8: 1Q22 | T8: 2Q22 | U8: 3Q22 | V8: 4Q22 | W8: FY22 | X8: 1Q23 | Y8: 2Q23 | Z8: 3Q23 | AA8: 4Q23 | AB8: FY23 | AC8: 1Q24 | AD8: 2Q24 | AE8: 3Q24 | AF8: 4Q24 | AG8: FY24 | AH8: 1Q25 | AI8: 2Q25 | AJ8: 3Q25 | AK8: 4Q25 | AL8: FY25 | AM8: 1Q26E | AN8: 2Q26E | AO8: 3Q26E | AP8: 4Q26E | AQ8: FY26E
C9: Diagnostics Revenue | D9: =Diagnostics!D4 -> 4.4874457 | E9: =Diagnostics!E4 -> 5.8740361 | F9: =Diagnostics!F4 -> 8.7568856 | G9: =Diagnostics!G4 -> 8.7716656 | H9: =SUM(D9:G9) -> 27.890033 | I9: =Diagnostics!I4 -> 13.645173 | J9: =Diagnostics!J4 -> 12.499903 | K9: =Diagnostics!K4 -> 47.078495 | L9: =Diagnostics!L4 -> 78.687212 | M9: =SUM(I9:L9) -> 151.91078 | N9: =Diagnostics!N4 -> 59.830029 | O9: =Diagnostics!O4 -> 53.070446 | P9: =Diagnostics!P4 -> 41.613709 | Q9: =Diagnostics!Q4 -> 40.498048 | R9: =SUM(N9:Q9) -> 195.01223 | S9: =Diagnostics!S4 -> 37.901848 | T9: =Diagnostics!T4 -> 47.421609 | U9: =Diagnostics!U4 -> 54.73176 | V9: =Diagnostics!V4 -> 57.929274 | W9: =SUM(S9:V9) -> 197.98449 | X9: =Diagnostics!X4 -> 82.058168 | Y9: =Diagnostics!Y4 -> 91.923548 | Z9: =Diagnostics!Z4 -> 96.784312 | AA9: =Diagnostics!AA4 -> 92.191474 | AB9: =SUM(X9:AA9) -> 362.9575 | AC9: =Diagnostics!AC4 -> 102.56942 | AD9: =Diagnostics!AD4 -> 112.324 | AE9: =Diagnostics!AE4 -> 116.422 | AF9: =Diagnostics!AF4 -> 120.434 | AG9: =SUM(AC9:AF9) -> 451.74942 | AH9: =Diagnostics!AH4 -> 193.804 | AI9: =Diagnostics!AI4 -> 241.843 | AJ9: =Diagnostics!AJ4 -> 252.878 | AK9: =Diagnostics!AK4 -> 266.856 | AL9: =SUM(AH9:AK9) -> 955.381 | AM9: =Diagnostics!AM4 -> 258.2497 | AN9: =Diagnostics!AN4 -> 298.36928 | AO9: =Diagnostics!AO4 -> 307.97813 | AP9: =Diagnostics!AP4 -> 314.34736 | AQ9: =SUM(AM9:AP9) -> 1178.9445
C10: Y/y Growth | I10: =I9/D9-1 -> 2.040744 | J10: =J9/E9-1 -> 1.1279922 | K10: =K9/F9-1 -> 4.3761688 | L10: =L9/G9-1 -> 7.9706124 | M10: =M9/H9-1 -> 4.4467768 | N10: =N9/I9-1 -> 3.3847027 | O10: =O9/J9-1 -> 3.2456685 | P10: =P9/K9-1 -> -0.11607818 | ... AQ10: =AQ9/AL9-1 -> 0.23400452
C11: Q/q Growth | E11: =E9/D9-1 -> 0.30899324 | F11: =F9/E9-1 -> 0.49077832 | G11: =G9/F9-1 -> 0.0016878123 | I11: =I9/G9-1 -> 0.55559662 | J11: =J9/I9-1 -> -0.083932257 | K11: =K9/J9-1 -> 2.7663088 | L11: =L9/K9-1 -> 0.67140458 | N11: =N9/L9-1 -> -0.23964737 | O11: =O9/N9-1 -> -0.11297977 | P11: =P9/O9-1 -> -0.21587791 | Q11: =Q9/P9-1 -> -0.026809928 | S11: =S9/Q9-1 -> -0.064106792 | T11: =T9/S9-1 -> 0.25116876 | U11: =U9/T9-1 -> 0.15415233 | V11: =V9/U9-1 -> 0.058421545 | X11: =X9/V9-1 -> 0.41652332 | Y11: =Y9/X9-1 -> 0.12022423 | Z11: =Z9/Y9-1 -> 0.052878335 | AA11: =AA9/Z9-1 -> -0.047454359 | AC11: =AC9/AA9-1 -> 0.11256946 | AD11: =AD9/AC9-1 -> 0.095102237 | AE11: =AE9/AD9-1 -> 0.036483743 | AF11: =AF9/AE9-1 -> 0.034460841 | AH11: =AH9/AF9-1 -> 0.60921335 | AI11: =AI9/AH9-1 -> 0.24787414 | AJ11: =AJ9/AI9-1 -> 0.045628776 | AK11: =AK9/AJ9-1 -> 0.055275667 | AM11: =AM9/AK9-1 -> -0.032250727 | AN11: =AN9/AM9-1 -> 0.15535189 | AO11: =AO9/AN9-1 -> 0.032204555 | AP11: =AP9/AO9-1 -> 0.020680787
C12: Data and Other Revenue | D12: ='Data & Other'!D7 -> 3.1913215 | E12: ='Data & Other'!E7 -> 4.7110225 | F12: ='Data & Other'!F7 -> 6.5473935 | G12: ='Data & Other'!G7 -> 19.717319 | H12: =SUM(D12:G12) -> 34.167057 | I12: ='Data & Other'!I7 -> 4.5969503 | J12: ='Data & Other'!J7 -> 5.6771733 | K12: ='Data & Other'!K7 -> 3.654138 | L12: ='Data & Other'!L7 -> 22.164383 | M12: =SUM(I12:L12) -> 36.092645 | N12: ='Data & Other'!N7 -> 10.280028 | O12: ='Data & Other'!O7 -> 8.9152628 | P12: ='Data & Other'!P7 -> 10.833945 | Q12: ='Data & Other'!Q7 -> 32.811488 | R12: =SUM(N12:Q12) -> 62.840725 | S12: ='Data & Other'!S7 -> 22.84992 | T12: ='Data & Other'!T7 -> 26.297225 | U12: ='Data & Other'!U7 -> 30.839768 | V12: ='Data & Other'!V7 -> 42.697508 | W12: =SUM(S12:V12) -> 122.68442 | X12: ='Data & Other'!X7 -> 33.56625 | Y12: ='Data & Other'!Y7 -> 40.492787 | Z12: ='Data & Other'!Z7 -> 39.241917 | AA12: ='Data & Other'!AA7 -> 55.498725 | AB12: =SUM(X12:AA12) -> 168.79968 | AC12: ='Data & Other'!AC7 -> 43.250622 | AD12: ='Data & Other'!AD7 -> 53.645 | AE12: ='Data & Other'!AE7 -> 64.507 | AF12: ='Data & Other'!AF7 -> 80.246 | AG12: =SUM(AC12:AF12) -> 241.64862 | AH12: ='Data & Other'!AH7 -> 61.933 | AI12: ='Data & Other'!AI7 -> 72.792 | AJ12: ='Data & Other'!AJ7 -> 81.328 | AK12: ='Data & Other'!AK7 -> 100.355 | AL12: =SUM(AH12:AK12) -> 316.408 | AM12: ='Data & Other'!AM7 -> 86.708248 | AN12: ='Data & Other'!AN7 -> 96.613063 | AO12: ='Data & Other'!AO7 -> 107.18766 | AP12: ='Data & Other'!AP7 -> 120.53203 | AQ12: =SUM(AM12:AP12) -> 411.041
C13: Y/y Growth | I13: =I12/D12-1 -> 0.44045351 | J13: =J12/E12-1 -> 0.20508302 | K13: =K12/F12-1 -> -0.44189425 | L13: =L12/G12-1 -> 0.12410735 | M13: =M12/H12-1 -> 0.056358031 | N13: =N12/I12-1 -> 1.2362714 | O13: =O12/J12-1 -> 0.57037004 | P13: =P12/K12-1 -> 1.9648429 | ... AQ13: =AQ12/AL12-1 -> 0.29908536
C14: Q/q Growth | E14: =E12/D12-1 -> 0.47619802 | F14: =F12/E12-1 -> 0.38980306 | G14: =G12/F12-1 -> 2.0114761 | I14: =I12/G12-1 -> -0.76685723 | J14: =J12/I12-1 -> 0.23498687 | K14: =K12/J12-1 -> -0.35634553 | L14: =L12/K12-1 -> 5.0655573 | N14: =N12/L12-1 -> -0.53619154 | O14: =O12/N12-1 -> -0.13275893 | P14: =P12/O12-1 -> 0.21521321 | Q14: =Q12/P12-1 -> 2.0285817 | S14: =S12/Q12-1 -> -0.30360003 | T14: =T12/S12-1 -> 0.15086727 | U14: =U12/T12-1 -> 0.17273852 | V14: =V12/U12-1 -> 0.38449511 | X14: =X12/V12-1 -> -0.21385928 | Y14: =Y12/X12-1 -> 0.20635422 | Z14: =Z12/Y12-1 -> -0.030891185 | AA14: =AA12/Z12-1 -> 0.41427151 | AC14: =AC12/AA12-1 -> -0.2206916 | AD14: =AD12/AC12-1 -> 0.24032897 | AE14: =AE12/AD12-1 -> 0.20247926 | AF14: =AF12/AE12-1 -> 0.24398902 | AH14: =AH12/AF12-1 -> -0.22821075 | AI14: =AI12/AH12-1 -> 0.17533464 | AJ14: =AJ12/AI12-1 -> 0.11726563 | AK14: =AK12/AJ12-1 -> 0.23395387 | AM14: =AM12/AK12-1 -> -0.13598477 | AN14: =AN12/AM12-1 -> 0.11423152 | AO14: =AO12/AN12-1 -> 0.10945308 | AP14: =AP12/AO12-1 -> 0.12449536
C15: Total Revenues | D15: =D12+D9 -> 7.6787672 | E15: =E12+E9 -> 10.585059 | F15: =F12+F9 -> 15.304279 | G15: =G12+G9 -> 28.488985 | H15: =SUM(D15:G15) -> 62.05709 | I15: =I12+I9 -> 18.242124 | J15: =J12+J9 -> 18.177076 | K15: =K12+K9 -> 50.732633 | L15: =L12+L9 -> 100.8516 | M15: =SUM(I15:L15) -> 188.00343 | N15: =N12+N9 -> 70.110057 | O15: =O12+O9 -> 61.985708 | P15: =P12+P9 -> 52.447654 | Q15: =Q12+Q9 -> 73.309537 | R15: =SUM(N15:Q15) -> 257.85296 | S15: =S12+S9 -> 60.751768 | T15: =T12+T9 -> 73.718833 | U15: =U12+U9 -> 85.571528 | V15: =V12+V9 -> 100.62678 | W15: =SUM(S15:V15) -> 320.66891 | X15: =X12+X9 -> 115.62442 | Y15: =Y12+Y9 -> 132.41633 | Z15: =Z12+Z9 -> 136.02623 | AA15: =AA12+AA9 -> 147.6902 | AB15: =SUM(X15:AA15) -> 531.75718 | AC15: =AC12+AC9 -> 145.82004 | AD15: =AD12+AD9 -> 165.969 | AE15: =AE12+AE9 -> 180.929 | AF15: =AF12+AF9 -> 200.68 | AG15: =SUM(AC15:AF15) -> 693.39804 | AH15: =AH12+AH9 -> 255.737 | AI15: =AI12+AI9 -> 314.635 | AJ15: =AJ12+AJ9 -> 334.206 | AK15: =AK12+AK9 -> 367.211 | AL15: =SUM(AH15:AK15) -> 1271.789 | AM15: =AM12+AM9 -> 344.95795 | AN15: =AN12+AN9 -> 394.98234 | AO15: =AO12+AO9 -> 415.16579 | AP15: =AP12+AP9 -> 434.87939 | AQ15: =SUM(AM15:AP15) -> 1589.9855
C16: Y/y Growth | I16: =I15/D15-1 -> 1.3756579 | J16: =J15/E15-1 -> 0.71723909 | K16: =K15/F15-1 -> 2.3149312 | L16: =L15/G15-1 -> 2.5400207 | M16: =M15/H15-1 -> 2.0295238 | N16: =N15/I15-1 -> 2.8433056 | O16: =O15/J15-1 -> 2.4101033 | P16: =P15/K15-1 -> 0.033805086 | ... AQ16: =AQ15/AL15-1 -> 0.25019596
C17: Q/q Growth | E17: =E15/D15-1 -> 0.37848411 | F17: =F15/E15-1 -> 0.44583792 | G17: =G15/F15-1 -> 0.86150451 | I17: =I15/G15-1 -> -0.359678 | J17: =J15/I15-1 -> -0.0035657721 | K17: =K15/J15-1 -> 1.7910227 | L17: =L15/K15-1 -> 0.98790383 | N17: =N15/L15-1 -> -0.30481956 | O17: =O15/N15-1 -> -0.11587993 | P17: =P15/O15-1 -> -0.15387506 | Q17: =Q15/P15-1 -> 0.39776579 | S17: =S15/Q15-1 -> -0.17129789 | T17: =T15/S15-1 -> 0.21344342 | U17: =U15/T15-1 -> 0.16078246 | V17: =V15/U15-1 -> 0.17593766 | X17: =X15/V15-1 -> 0.14904218 | Y17: =Y15/X15-1 -> 0.14522812 | Z17: =Z15/Y15-1 -> 0.027261697 | AA17: =AA15/Z15-1 -> 0.085747953 | AC17: =AC15/AA15-1 -> -0.01266271 | AD17: =AD15/AC15-1 -> 0.13817688 | AE17: =AE15/AD15-1 -> 0.090137315 | AF17: =AF15/AE15-1 -> 0.10916437 | AH17: =AH15/AF15-1 -> 0.2743522 | AI17: =AI15/AH15-1 -> 0.23030692 | AJ17: =AJ15/AI15-1 -> 0.062202234 | AK17: =AK15/AJ15-1 -> 0.098756456 | AM17: =AM15/AK15-1 -> -0.060600178 | AN17: =AN15/AM15-1 -> 0.14501592 | AO17: =AO15/AN15-1 -> 0.051099619 | AP17: =AP15/AO15-1 -> 0.047483671
C19: Diagnostics Cost of Revenue | D19: =Diagnostics!D26 -> 6.1617353 | E19: =Diagnostics!E26 -> 8.8999742 | F19: =Diagnostics!F26 -> 10.816278 | G19: =Diagnostics!G26 -> 13.807414 | H19: =SUM(D19:G19) -> 39.685401 | I19: =Diagnostics!I26 -> 16.832318 | J19: =Diagnostics!J26 -> 17.227103 | K19: =Diagnostics!K26 -> 46.356053 | L19: =Diagnostics!L26 -> 71.782609 | M19: =SUM(I19:L19) -> 152.19808 | N19: =Diagnostics!N26 -> 58.1521 | O19: =Diagnostics!O26 -> 39.350144 | P19: =Diagnostics!P26 -> 31.780714 | Q19: =Diagnostics!Q26 -> 32.992517 | R19: =SUM(N19:Q19) -> 162.27547 | S19: =Diagnostics!S26 -> 39.083505 | T19: =Diagnostics!T26 -> 34.266354 | U19: =Diagnostics!U26 -> 35.401601 | V19: =Diagnostics!V26 -> 41.503107 | W19: =SUM(S19:V19) -> 150.25457 | X19: =Diagnostics!X26 -> 45.280278 | Y19: =Diagnostics!Y26 -> 46.96103 | Z19: =Diagnostics!Z26 -> 46.540149 | AA19: =Diagnostics!AA26 -> 50.336734 | AB19: =SUM(X19:AA19) -> 189.11819 | AC19: =Diagnostics!AC26 -> 52.834757 | AD19: =Diagnostics!AD26-11.327-0.136 -> 56.861 | AE19: =Diagnostics!AE26-1.083-0.026 -> 59.017 | AF19: =Diagnostics!AF26-1.215-0.293 -> 60.674 | AG19: =SUM(AC19:AF19) -> 229.38676 | AH19: =Diagnostics!AH26 -> 83.7 | AI19: =Diagnostics!AI26 -> 98.082 | AJ19: =Diagnostics!AJ26 -> 96.976 | AK19: =Diagnostics!AK26 -> 100.747 | AL19: =SUM(AH19:AK19) -> 379.505 | AM19: =Diagnostics!AM26 -> 101.80962 | AN19: =Diagnostics!AN26 -> 118.83941 | AO19: =Diagnostics!AO26 -> 120.29982 | AP19: =Diagnostics!AP26 -> 118.2509 | AQ19: =SUM(AM19:AP19) -> 459.19975
C21: Data & Other Cost of Revenue | D21: ='Data & Other'!D19 -> 1.8783008 | E21: ='Data & Other'!E19 -> 1.7794325 | F21: ='Data & Other'!F19 -> 1.2114378 | G21: ='Data & Other'!G19 -> 1.4606137 | H21: =SUM(D21:G21) -> 6.3297848 | I21: ='Data & Other'!I19 -> 1.411472 | J21: ='Data & Other'!J19 -> 1.477868 | K21: ='Data & Other'!K19 -> 2.1382459 | L21: ='Data & Other'!L19 -> 2.0641284 | M21: =SUM(I21:L21) -> 7.0917143 | N21: ='Data & Other'!N19 -> 2.249488 | O21: ='Data & Other'!O19 -> 2.6678312 | P21: ='Data & Other'!P19 -> 3.0303307 | Q21: ='Data & Other'!Q19 -> 3.9851527 | R21: =SUM(N21:Q21) -> 11.932803 | S21: ='Data & Other'!S19 -> 7.7879838 | T21: ='Data & Other'!T19 -> 10.613211 | U21: ='Data & Other'!U19 -> 11.101333 | V21: ='Data & Other'!V19 -> 10.724351 | W21: =SUM(S21:V21) -> 40.226879 | X21: ='Data & Other'!X19 -> 11.392877 | Y21: ='Data & Other'!Y19 -> 13.806998 | Z21: ='Data & Other'!Z19 -> 15.489291 | AA21: ='Data & Other'!AA19 -> 15.79287 | AB21: =SUM(X21:AA21) -> 56.482036 | AC21: ='Data & Other'!AC19 -> 15.288271 | AD21: ='Data & Other'!AD19-7.229-0.119 -> 14.784 | AE21: ='Data & Other'!AE19-0.916-0.043 -> 14.005 | AF21: ='Data & Other'!AF19-0.385-0.202 -> 15.847 | AG21: =SUM(AC21:AF21) -> 59.924271 | AH21: ='Data & Other'!AH19 -> 15.096 | AI21: ='Data & Other'!AI19 -> 19.033 | AJ21: ='Data & Other'!AJ19 -> 24.665 | AK21: ='Data & Other'!AK19 -> 25.637 | AL21: =SUM(AH21:AK21) -> 84.431 | AM21: ='Data & Other'!AM19 -> 21.112614 | AN21: ='Data & Other'!AN19 -> 23.097934 | AO21: ='Data & Other'!AO19 -> 23.672625 | AP21: ='Data & Other'!AP19 -> 25.339939 | AQ21: =SUM(AM21:AP21) -> 93.223113
C23: Total Cost of Revenue | D23: =D19+D21 -> 8.0400362 | E23: =E19+E21 -> 10.679407 | F23: =F19+F21 -> 12.027716 | G23: =G19+G21 -> 15.268027 | H23: =SUM(D23:G23) -> 46.015186 | I23: =I19+I21 -> 18.24379 | J23: =J19+J21 -> 18.704971 | K23: =K19+K21 -> 48.494299 | L23: =L19+L21 -> 73.846737 | M23: =SUM(I23:L23) -> 159.2898 | N23: =N19+N21 -> 60.401588 | O23: =O19+O21 -> 42.017975 | P23: =P19+P21 -> 34.811044 | Q23: =Q19+Q21 -> 36.97767 | R23: =SUM(N23:Q23) -> 174.20828 | S23: =S19+S21 -> 46.871489 | T23: =T19+T21 -> 44.879565 | U23: =U19+U21 -> 46.502934 | V23: =V19+V21 -> 52.227458 | W23: =SUM(S23:V23) -> 190.48145 | X23: =X19+X21 -> 56.673155 | Y23: =Y19+Y21 -> 60.768028 | Z23: =Z19+Z21 -> 62.02944 | AA23: =AA19+AA21 -> 66.129604 | AB23: =SUM(X23:AA23) -> 245.60023 | AC23: =AC19+AC21 -> 68.123028 | AD23: =AD19+AD21 -> 71.645 | AE23: =AE19+AE21 -> 73.022 | AF23: =AF19+AF21 -> 76.521 | AG23: =SUM(AC23:AF23) -> 289.31103 | AH23: =AH19+AH21 -> 98.796 | AI23: =AI19+AI21 -> 117.115 | AJ23: =AJ19+AJ21 -> 121.641 | AK23: =AK19+AK21 -> 126.384 | AL23: =SUM(AH23:AK23) -> 463.936 | AM23: =AM19+AM21 -> 122.92223 | AN23: =AN19+AN21 -> 141.93735 | AO23: =AO19+AO21 -> 143.97244 | AP23: =AP19+AP21 -> 143.59084 | AQ23: =SUM(AM23:AP23) -> 552.42286
C25: Gross Profit | D25: =D15-D23 -> -0.36126895 | E25: =E15-E23 -> -0.094348017 | F25: =F15-F23 -> 3.2765634 | G25: =G15-G23 -> 13.220957 | H25: =SUM(D25:G25) -> 16.041904 | I25: =I15-I23 -> -0.001666383 | J25: =J15-J23 -> -0.52789494 | K25: =K15-K23 -> 2.2383338 | L25: =L15-L23 -> 27.004859 | M25: =SUM(I25:L25) -> 28.713631 | N25: =N15-N23 -> 9.7084692 | O25: =O15-O23 -> 19.967733 | P25: =P15-P23 -> 17.63661 | Q25: =Q15-Q23 -> 36.331867 | R25: =SUM(N25:Q25) -> 83.64468 | S25: =S15-S23 -> 13.880279 | T25: =T15-T23 -> 28.839268 | U25: =U15-U23 -> 39.068595 | V25: =V15-V23 -> 48.399324 | W25: =SUM(S25:V25) -> 130.18747 | X25: =X15-X23 -> 58.951262 | Y25: =Y15-Y23 -> 71.648307 | Z25: =Z15-Z23 -> 73.996789 | AA25: =AA15-AA23 -> 81.560595 | AB25: =SUM(X25:AA25) -> 286.15695 | AC25: =AC15-AC23 -> 77.697013 | AD25: =AD15-AD23 -> 94.324 | AE25: =AE15-AE23 -> 107.907 | AF25: =AF15-AF23 -> 124.159 | AG25: =SUM(AC25:AF25) -> 404.08701 | AH25: =AH15-AH23 -> 156.941 | AI25: =AI15-AI23 -> 197.52 | AJ25: =AJ15-AJ23 -> 212.565 | AK25: =AK15-AK23 -> 240.827 | AL25: =SUM(AH25:AK25) -> 807.853 | AM25: =AM15-AM23 -> 222.03572 | AN25: =AN15-AN23 -> 253.045 | AO25: =AO15-AO23 -> 271.19335 | AP25: =AP15-AP23 -> 291.28854 | AQ25: =SUM(AM25:AP25) -> 1037.5626
C26: Gross Margin | D26: =D25/D15 -> -0.04704778 | E26: =E25/E15 -> -0.0089133202 | F26: =F25/F15 -> 0.21409459 | G26: =G25/G15 -> 0.46407261 | H26: =H25/H15 -> 0.25850236 | I26: =I25/I15 -> -9.1348081e-05 | J26: =J25/J15 -> -0.029041796 | K26: =K25/K15 -> 0.044120199 | ... AQ26: =AQ25/AQ15 -> 0.65256106
C28: Operating Expenses
C29: Technology | D29: 4.7624656 | E29: 6.0944848 | F29: 6.911936 | G29: 7.8389731 | H29: 25.607859 | I29: 9.508666 | J29: 11.386503 | K29: 11.904752 | L29: 13.061494 | M29: 45.861414 | N29: 15.568639 | O29: 16.724552 | P29: 17.249761 | Q29: 17.647216 | R29: 67.190168 | S29: 18.376445 | T29: 19.492077 | U29: 20.389383 | V29: 20.822457 | W29: 79.08036 | X29: 22.902143 | Y29: 23.417789 | Z29: 24.156428 | AA29: 24.669381 | AB29: 95.556287 | AC29: 27.05099 | AD29: =77.908-50.434-1.248 -> 26.226 | AE29: =30.68-3.929-0.192 -> 26.559 | AF29: =31.864-4.11-1.306 -> 26.448 | AG29: =SUM(AC29:AF29) -> 106.28399 | AH29: =33.391-3.319-0.261 -> 29.811 | AI29: =34.482-3.285-0.495 -> 30.702 | AJ29: =38.087-5.463-0.278 -> 32.346 | AK29: =40.147-6.995-0.186 -> 32.966 | AL29: =SUM(AH29:AK29) -> 125.825 | AM29: =AM15*AM30 -> 37.945374 | AN29: =AN15*AN30 -> 39.498234 | AO29: =AO15*AO30 -> 41.516579 | AP29: =AP15*AP30 -> 43.487939 | AQ29: =SUM(AM29:AP29) -> 162.44813
C30: % of Revenue | D30: =D29/D15 -> 0.62021226 | E30: =E29/E15 -> 0.57576297 | F30: =F29/F15 -> 0.4516342 | G30: =G29/G15 -> 0.27515804 | H30: =H29/H15 -> 0.41265002 | I30: =I29/I15 -> 0.52124776 | J30: =J29/J15 -> 0.62642101 | K30: =K29/K15 -> 0.23465669 | ... AL30: =AL29/AL15 -> 0.098935437 | AM30: 0.11 | AN30: 0.1 | AO30: 0.1 | AP30: 0.1 | AQ30: =AQ29/AQ15 -> 0.10216957
C31: Research & Development | D31: 6.7716534 | E31: 7.6130874 | F31: 8.3112565 | G31: 8.5567344 | H31: 31.252732 | I31: 9.4118219 | J31: 11.211381 | K31: 11.685697 | L31: 13.105903 | M31: 45.414803 | N31: 14.028102 | O31: 13.762828 | P31: 14.734902 | Q31: 18.635596 | R31: 61.161428 | S31: 17.961027 | T31: 20.609998 | U31: 22.980849 | V31: 21.605942 | W31: 83.157816 | X31: 20.86253 | Y31: 22.171365 | Z31: 23.234179 | AA31: 24.075411 | AB31: 90.025956 | AC31: 24.339652 | AD31: =68.025-42.233-0.676 -> 25.116 | AE31: =27.348-2.554-0.134 -> 24.66 | AF31: =29.612-2.851-0.756 -> 26.005 | AG31: =SUM(AC31:AF31) -> 100.12065 | AH31: =35.874-1.982-0.176 -> 33.716 | AI31: =41.619-2.335-0.235 -> 39.049 | AJ31: =44.96-3.301-0.122 -> 41.537 | AK31: =50.471-5.07-0.099 -> 45.302 | AL31: =SUM(AH31:AK31) -> 159.604 | AM31: =AM15*AM32 -> 53.123524 | AN31: =AN15*AN32 -> 59.247352 | AO31: =AO15*AO32 -> 62.274869 | AP31: =AP15*AP32 -> 63.057511 | AQ31: =SUM(AM31:AP31) -> 237.70326
C32: % of Revenue | D32: =D31/D15 -> 0.88186726 | E32: =E31/E15 -> 0.71922959 | F32: =F31/F15 -> 0.54306749 | G32: =G31/G15 -> 0.30035238 | H32: =H31/H15 -> 0.50361259 | I32: =I31/I15 -> 0.51593894 | J32: =J31/J15 -> 0.61678683 | K32: =K31/K15 -> 0.23033887 | ... AL32: =AL31/AL15 -> 0.12549566 | AM32: 0.154 | AN32: 0.15 | AO32: 0.15 | AP32: 0.145 | AQ32: =AQ31/AQ15 -> 0.14950027
C33: General & Administrative | D33: 13.395203 | E33: 17.570622 | F33: 23.223093 | G33: 24.773481 | H33: 78.962398 | I33: 28.752381 | J33: 28.305386 | K33: 30.94784 | L33: 42.886876 | M33: 130.89248 | N33: 41.545114 | O33: 52.353458 | P33: 50.259131 | Q33: 54.845885 | R33: 199.00359 | S33: 54.635154 | T33: 55.292462 | U33: 58.876205 | V33: 64.585736 | W33: 233.38956 | X33: 69.046574 | Y33: 71.198037 | Z33: 71.426542 | AA33: =81.347648493+3.75 -> 85.097648 | AB33: 284.3657 | AC33: 79.580613 | AD33: =463.072-377.09-2.582 -> 83.4 | AE33: =101.427-12.556-0.806 -> 88.065 | AF33: =111.288-16.226-5.023 -> 90.039 | AG33: =SUM(AC33:AF33) -> 341.08461 | AH33: =154.627-16.027-4.725-3.529-11.156 -> 119.19 | AI33: =180.712-14.722-0.774-1.992-16.771-1.647 -> 144.806 | AJ33: =187.891-22.69-0.541-0.552-16.764 -> 147.344 | AK33: =208.508-30.243-3.006-0.143-16.838 -> 158.278 | AL33: =SUM(AH33:AK33) -> 569.618 | AM33: =AM15*AM34 -> 173.85881 | AN33: =AN15*AN34 -> 181.69188 | AO33: =AO15*AO34 -> 182.67295 | AP33: =AP15*AP34 -> 185.91094 | AQ33: =SUM(AM33:AP33) -> 724.13457
C34: % of Revenue | D34: =D33/D15 -> 1.744447 | E34: =E33/E15 -> 1.6599456 | F34: =F33/F15 -> 1.5174248 | G34: =G33/G15 -> 0.86958102 | H34: =H33/H15 -> 1.2724154 | I34: =I33/I15 -> 1.5761532 | J34: =J33/J15 -> 1.5572024 | K34: =K33/K15 -> 0.61001842 | ... AL34: =AL33/AL15 -> 0.44788719 | AM34: 0.504 | AN34: 0.46 | AO34: 0.44 | AP34: 0.4275 | AQ34: =AQ33/AQ15 -> 0.45543471
C35: Total Operating Expenses | D35: =D29+D31+D33 -> 24.929322 | E35: =E29+E31+E33 -> 31.278194 | F35: =F29+F31+F33 -> 38.446285 | G35: =G29+G31+G33 -> 41.169188 | H35: =SUM(D35:G35) -> 135.82299 | I35: =I29+I31+I33 -> 47.672869 | J35: =J29+J31+J33 -> 50.90327 | K35: =K29+K31+K33 -> 54.538289 | L35: =L29+L31+L33 -> 69.054273 | M35: =SUM(I35:L35) -> 222.1687 | N35: =N29+N31+N33 -> 71.141855 | O35: =O29+O31+O33 -> 82.840837 | P35: =P29+P31+P33 -> 82.243794 | Q35: =Q29+Q31+Q33 -> 91.128697 | R35: =SUM(N35:Q35) -> 327.35518 | S35: =S29+S31+S33 -> 90.972625 | T35: =T29+T31+T33 -> 95.394536 | U35: =U29+U31+U33 -> 102.24644 | V35: =V29+V31+V33 -> 107.01413 | W35: =SUM(S35:V35) -> 395.62773 | X35: =X29+X31+X33 -> 112.81125 | Y35: =Y29+Y31+Y33 -> 116.78719 | Z35: =Z29+Z31+Z33 -> 118.81715 | AA35: =AA29+AA31+AA33 -> 133.84244 | AB35: =SUM(X35:AA35) -> 482.25803 | AC35: =AC29+AC31+AC33 -> 130.97126 | AD35: =AD29+AD31+AD33 -> 134.742 | AE35: =AE29+AE31+AE33 -> 139.284 | AF35: =AF29+AF31+AF33 -> 142.492 | AG35: =SUM(AC35:AF35) -> 547.48926 | AH35: =AH29+AH31+AH33 -> 182.717 | AI35: =AI29+AI31+AI33 -> 214.557 | AJ35: =AJ29+AJ31+AJ33 -> 221.227 | AK35: =AK29+AK31+AK33 -> 236.546 | AL35: =SUM(AH35:AK35) -> 855.047 | AM35: =AM29+AM31+AM33 -> 264.9277 | AN35: =AN29+AN31+AN33 -> 280.43746 | AO35: =AO29+AO31+AO33 -> 286.4644 | AP35: =AP29+AP31+AP33 -> 292.45639 | AQ35: =SUM(AM35:AP35) -> 1124.286
C37: Non-GAAP Operating Income | D37: =D25-D35 -> -25.290591 | E37: =E25-E35 -> -31.372542 | F37: =F25-F35 -> -35.169722 | G37: =G25-G35 -> -27.948231 | H37: =SUM(D37:G37) -> -119.78109 | I37: =I25-I35 -> -47.674535 | J37: =J25-J35 -> -51.431165 | K37: =K25-K35 -> -52.299956 | L37: =L25-L35 -> -42.049414 | M37: =SUM(I37:L37) -> -193.45507 | N37: =N25-N35 -> -61.433386 | O37: =O25-O35 -> -62.873104 | P37: =P25-P35 -> -64.607184 | Q37: =Q25-Q35 -> -54.79683 | R37: =SUM(N37:Q37) -> -243.7105 | S37: =S25-S35 -> -77.092346 | T37: =T25-T35 -> -66.555268 | U37: =U25-U35 -> -63.177842 | V37: =V25-V35 -> -58.61481 | W37: =SUM(S37:V37) -> -265.44027 | X37: =X25-X35 -> -53.859984 | Y37: =Y25-Y35 -> -45.138884 | Z37: =Z25-Z35 -> -44.820361 | AA37: =AA25-AA35 -> -52.281845 | AB37: =SUM(X37:AA37) -> -196.10107 | AC37: =AC25-AC35 -> -53.274242 | AD37: =AD25-AD35 -> -40.418 | AE37: =AE25-AE35 -> -31.377 | AF37: =AF25-AF35 -> -18.333 | AG37: =SUM(AC37:AF37) -> -143.40224 | AH37: =AH25-AH35 -> -25.776 | AI37: =AI25-AI35 -> -17.037 | AJ37: =AJ25-AJ35 -> -8.662 | AK37: =AK25-AK35 -> 4.281 | AL37: =SUM(AH37:AK37) -> -47.194 | AM37: =AM25-AM35 -> -42.891988 | AN37: =AN25-AN35 -> -27.392466 | AO37: =AO25-AO35 -> -15.271045 | AP37: =AP25-AP35 -> -1.1678442 | AQ37: =SUM(AM37:AP37) -> -86.723343
C38: Non-GAAP Operating Margin | D38: =D37/D15 -> -3.2935743 | E38: =E37/E15 -> -2.9638515 | F38: =F37/F15 -> -2.2980319 | G38: =G37/G15 -> -0.98101883 | H38: =H37/H15 -> -1.9301757 | I38: =I37/I15 -> -2.6134312 | J38: =J37/J15 -> -2.829452 | K38: =K37/K15 -> -1.0308938 | ... AQ38: =AQ37/AQ15 -> -0.054543482
C40: GAAP Adjustments:
C41: Change in fair value of warrant | D41: 0 | E41: 0 | F41: 0 | G41: 0 | H41: =SUM(D41:G41) -> 0 | I41: 0 | J41: 0 | K41: 0 | L41: 0 | M41: =SUM(I41:L41) -> 0 | N41: 0 | O41: 0 | P41: 0 | Q41: 0 | R41: =SUM(N41:Q41) -> 0 | S41: -0.2 | T41: 3.2 | U41: 1.2 | V41: 0.5 | W41: =SUM(S41:V41) -> 4.7 | X41: -6.4 | Y41: 0.7 | Z41: -2.3 | AA41: -4.1 | AB41: =SUM(X41:AA41) -> -12.1 | AC41: 5.5 | AD41: 4.87 | AE41: 15.605 | AF41: -47.753 | AG41: =SUM(AC41:AF41) -> -21.778 | AH41: 31.85 | AI41: -37.546 | AJ41: 1.255 | AK41: -13.366 | AL41: =SUM(AH41:AK41) -> -17.807 | AM41: 0 | AN41: 0 | AO41: 0 | AP41: 0 | AQ41: =SUM(AM41:AP41) -> 0
C42: Stock-based compensation expense | D42: 0.13238493 | E42: 0.13238493 | F42: 3.0243849 | G42: 0.13202261 | H42: =SUM(D42:G42) -> 3.4211774 | I42: 0.09965667 | J42: 0.09965667 | K42: 0.09965667 | L42: 0.09965667 | M42: =SUM(I42:L42) -> 0.39862668 | N42: 0 | O42: 0.558749 | P42: 0 | Q42: 0 | R42: =SUM(N42:Q42) -> 0.558749 | S42: 0 | T42: 0 | U42: 0 | V42: 0 | W42: =SUM(S42:V42) -> 0 | X42: 0 | Y42: 0 | Z42: 0 | AA42: 0 | AB42: =SUM(X42:AA42) -> 0 | AC42: 0 | AD42: 488.313 | AE42: 21.038 | AF42: 24.787 | AG42: =SUM(AC42:AF42) -> 534.138 | AH42: 21.328 | AI42: 22.455 | AJ42: 33.979 | AK42: 45.339 | AL42: =SUM(AH42:AK42) -> 123.101 | AM42: 55 | AN42: 48.33 | AO42: 48.33 | AP42: 48.33 | AQ42: =SUM(AM42:AP42) -> 199.99
C43: Change in fair value of contingent consideration | D43: 0 | E43: 0 | F43: 0 | G43: 0 | H43: =SUM(D43:G43) -> 0 | I43: 0 | J43: 0 | K43: 0 | L43: 6.891 | M43: =SUM(I43:L43) -> 6.891 | N43: 0 | O43: 4.1488117 | P43: 0.445 | Q43: 0.64017596 | R43: =SUM(N43:Q43) -> 5.2339876 | S43: -2.2343574 | T43: -1.6117633 | U43: -0.03491184 | V43: 0.18039239 | W43: =SUM(S43:V43) -> -3.7006401 | X43: 0 | Y43: 0.04300932 | Z43: -0.39807103 | AA43: 0.16396916 | AB43: =SUM(X43:AA43) -> -0.19109255 | AC43: 0.15597065 | AD43: 0 | AE43: 0 | AF43: 0 | AG43: =SUM(AC43:AF43) -> 0.15597065 | AH43: 0 | AI43: 0 | AJ43: 0 | AK43: 0 | AL43: =SUM(AH43:AK43) -> 0 | AM43: 0 | AN43: 0 | AO43: 0 | AP43: 0 | AQ43: =SUM(AM43:AP43) -> 0
C44: Unrealized Gain/Loss on Stock | D44: 0 | E44: 0 | F44: 0 | G44: 0 | H44: =SUM(D44:G44) -> 0 | I44: 0 | J44: 0 | K44: 0 | L44: 0 | M44: =SUM(I44:L44) -> 0 | N44: 0 | O44: 0 | P44: 0 | Q44: 0 | R44: =SUM(N44:Q44) -> 0 | S44: 0 | T44: 0 | U44: 0 | V44: 0 | W44: =SUM(S44:V44) -> 0 | X44: 0 | Y44: 0 | Z44: 0 | AA44: -9.8073937 | AB44: =SUM(X44:AA44) -> -9.8073937 | AC44: -0.165 | AD44: 0 | AE44: 0 | AF44: 0 | AG44: =SUM(AC44:AF44) -> -0.165 | AH44: 1.6 | AI44: 0 | AJ44: 0 | AK44: 0 | AL44: =SUM(AH44:AK44) -> 1.6 | AM44: 0 | AN44: 0 | AO44: 0 | AP44: 0 | AQ44: =SUM(AM44:AP44) -> 0
C45: Loss on debt extinguishment | AK45: 0
C46: Amortization of intangibles | AH46: 11.156 | AI46: 16.771 | AJ46: 16.764 | AK46: 16.838 | AL46: =SUM(AH46:AK46) -> 61.529
C47: Settlement Costs | D47: 0 | E47: 0 | F47: 0 | G47: 0 | H47: =SUM(D47:G47) -> 0 | I47: 0 | J47: 0 | K47: 0 | L47: 0 | M47: =SUM(I47:L47) -> 0 | N47: 0 | O47: 0 | P47: 0 | Q47: 0 | R47: =SUM(N47:Q47) -> 0 | S47: 0 | T47: 0 | U47: 0 | V47: 0 | W47: =SUM(S47:V47) -> 0 | X47: 0 | Y47: 0 | Z47: 0 | AA47: 8.625 | AB47: =SUM(X47:AA47) -> 8.625 | AC47: -6.0798898 | AD47: 0 | AE47: 0 | AF47: 0 | AG47: =SUM(AC47:AF47) -> -6.0798898 | AH47: 0 | AI47: 1.647 | AJ47: 0 | AK47: 0 | AL47: =SUM(AH47:AK47) -> 1.647 | AM47: 0 | AN47: 0 | AO47: 0 | AP47: 0 | AQ47: =SUM(AM47:AP47) -> 0
C48: Transaction Costs | D48: 0 | E48: 0 | F48: 0 | G48: 0 | H48: =SUM(D48:G48) -> 0 | I48: 0 | J48: 0 | K48: 0 | L48: 0 | M48: =SUM(I48:L48) -> 0 | N48: 0 | O48: 0 | P48: 0 | Q48: 0.194091 | R48: =SUM(N48:Q48) -> 0.194091 | S48: 0.0066863 | T48: 0 | U48: 0.475 | V48: 0 | W48: =SUM(S48:V48) -> 0.4816863 | X48: 0 | Y48: 0 | Z48: 0.671906 | AA48: -0.0145796 | AB48: =SUM(X48:AA48) -> 0.6573264 | AC48: 0 | AD48: 0 | AE48: 0 | AF48: 2.536 | AG48: =SUM(AC48:AF48) -> 2.536 | AH48: 3.529 | AI48: =1.992+1.647 -> 3.639 | AJ48: 0.552 | AK48: 3.149 | AL48: =SUM(AH48:AK48) -> 10.869 | AM48: 0 | AN48: 0 | AO48: 0 | AP48: 0 | AQ48: =SUM(AM48:AP48) -> 0
C49: Employer payroll tax related to SBC | AD49: 4.762 | AE49: 1.201 | AF49: 7.58 | AH49: 5.162 | AI49: 1.873 | AJ49: 1.039 | AK49: 3.374 | AL49: =SUM(AH49:AK49) -> 11.448
C50: G-4 Special Payment | AD50: 2.25 | AE50: 0 | AF50: 0 | AI50: 0 | AK50: 0 | AL50: =SUM(AH50:AK50) -> 0
C51: Depreciation | AD51: 6.415 | AE51: 6.788 | AF51: 6.884 | AH51: 7.883 | AI51: 8.341 | AK51: 7.704 | AL51: =SUM(AH51:AK51) -> 23.928
C52: Amortization | D52: 0 | E52: 0 | F52: 0 | G52: 0 | H52: =SUM(D52:G52) -> 0 | I52: 0.61785714 | J52: 0.61785714 | K52: 0.61785714 | L52: 21.592695 | M52: =SUM(I52:L52) -> 23.446266 | N52: 2.4935756 | O52: 2.4935756 | P52: 2.4935756 | Q52: 2.6410054 | R52: =SUM(N52:Q52) -> 10.121732 | S52: 3.1598593 | T52: 3.249212 | U52: 3.4565433 | V52: 3.4688393 | W52: =SUM(S52:V52) -> 13.334454 | X52: 2.8879792 | Y52: 3.0444669 | Z52: 2.9194669 | AA52: 2.9194669 | AB52: =SUM(X52:AA52) -> 11.77138 | AC52: 2.9194669 | AD52: 2.744 | AE52: =2.652+-3.989 -> -1.337 | AF52: =2.573-3.988 -> -1.415 | AG52: =SUM(AC52:AF52) -> 2.9114669 | AH52: =12.47-3.989 -> 8.481 | AI52: =19.685-3.988 -> 15.697 | AJ52: -3.989 | AK52: =19.204-3.989 -> 15.215 | AL52: =SUM(AH52:AK52) -> 35.404 | AM52: 2.925 | AN52: 2.925 | AO52: 2.925 | AP52: 2.925 | AQ52: =SUM(AM52:AP52) -> 11.7
C53: Total GAAP and non-cash adjustments | D53: =SUM(D41:D52) -> 0.13238493 | E53: =SUM(E41:E52) -> 0.13238493 | F53: =SUM(F41:F52) -> 3.0243849 | G53: =SUM(G41:G52) -> 0.13202261 | H53: =SUM(D53:G53) -> 3.4211774 | I53: =SUM(I41:I52) -> 0.71751381 | J53: =SUM(J41:J52) -> 0.71751381 | K53: =SUM(K41:K52) -> 0.71751381 | L53: =SUM(L41:L52) -> 28.583351 | M53: =SUM(I53:L53) -> 30.735893 | N53: =SUM(N41:N52) -> 2.4935756 | O53: =SUM(O41:O52) -> 7.2011363 | P53: =SUM(P41:P52) -> 2.9385756 | Q53: =SUM(Q41:Q52) -> 3.4752724 | R53: =SUM(N53:Q53) -> 16.10856 | S53: =SUM(S41:S52) -> 0.73218821 | T53: =SUM(T41:T52) -> 4.8374487 | U53: =SUM(U41:U52) -> 5.0966314 | V53: =SUM(V41:V52) -> 4.1492317 | W53: =SUM(S53:V53) -> 14.8155 | X53: =SUM(X41:X52) -> -3.5120208 | Y53: =SUM(Y41:Y52) -> 3.7874762 | Z53: =SUM(Z41:Z52) -> 0.89330189 | AA53: =SUM(AA41:AA52) -> -2.2135372 | AB53: =SUM(X53:AA53) -> -1.0447799 | AC53: =SUM(AC41:AC52) -> 2.3305478 | AD53: =SUM(AD41:AD48) -> 493.183 | AE53: =SUM(AE42:AE49) -> 22.239 | AF53: =SUM(AF42:AF49) -> 34.903 | AG53: =SUM(AC53:AF53) -> 552.65555 | AH53: =SUM(AH42:AH49) -> 42.775 | AI53: =SUM(AI42:AI48) -> 44.512 | AJ53: =SUM(AJ42:AJ49) -> 52.334 | AK53: =SUM(AK42:AK48) -> 65.326 | AL53: =SUM(AH53:AK53) -> 204.947 | AM53: =SUM(AM42:AM48) -> 55 | AN53: =SUM(AN42:AN48) -> 48.33 | AO53: =SUM(AO42:AO48) -> 48.33 | AP53: =SUM(AP42:AP48) -> 48.33 | AQ53: =SUM(AM53:AP53) -> 199.99
C55: GAAP Operating Income | D55: =D37-D42 -> -25.422975 | E55: =E37-E42 -> -31.504927 | F55: =F37-F42 -> -38.194107 | G55: =G37-G42 -> -28.080253 | H55: =SUM(D55:G55) -> -123.20226 | I55: =I37-I42 -> -47.774192 | J55: =J37-J42 -> -51.530822 | K55: =K37-K42 -> -52.399612 | L55: =L37-L42 -> -42.149071 | M55: =SUM(I55:L55) -> -193.8537 | N55: =N37-N42 -> -61.433386 | O55: =O37-O42 -> -63.431853 | P55: =P37-P42 -> -64.607184 | Q55: =Q37-Q42 -> -54.79683 | R55: =SUM(N55:Q55) -> -244.26925 | S55: =S37-S42 -> -77.092346 | T55: =T37-T42 -> -66.555268 | U55: =U37-U42 -> -63.177842 | V55: =V37-V42 -> -58.61481 | W55: =SUM(S55:V55) -> -265.44027 | X55: =X37-X42 -> -53.859984 | Y55: =Y37-Y42 -> -45.138884 | Z55: =Z37-Z42 -> -44.820361 | AA55: =AA37-AA42 -> -52.281845 | AB55: =SUM(X55:AA55) -> -196.10107 | AC55: =AC37-AC42 -> -53.274242 | AD55: =AD37-AD53 -> -533.601 | AE55: =AE37-AE53 -> -53.616 | AF55: =AF37-AF53 -> -53.236 | AG55: =SUM(AC55:AF55) -> -693.72724 | AH55: =AH37-AH53 -> -68.551 | AI55: =AI37-AI53-0.225 -> -61.774 | AJ55: =AJ37-AJ53 -> -60.996 | AK55: =AK37-AK53 -> -61.045 | AL55: =SUM(AH55:AK55) -> -252.366 | AM55: =AM37-AM53 -> -97.891988 | AN55: =AN37-AN53 -> -75.722466 | AO55: =AO37-AO53 -> -63.601045 | AP55: =AP37-AP53 -> -49.497844 | AQ55: =SUM(AM55:AP55) -> -286.71334
C56: GAAP Operating Margins | D56: =D55/D15 -> -3.3108147 | E56: =E55/E15 -> -2.9763583 | F56: =F55/F15 -> -2.4956489 | G56: =G55/G15 -> -0.985653 | H56: =H55/H15 -> -1.9853052 | I56: =I55/I15 -> -2.6188942 | J56: =J55/J15 -> -2.8349345 | K56: =K55/K15 -> -1.0328581 | ... AQ56: =AQ55/AQ15 -> -0.18032451
C58: Interest Income | D58: 0.90721491 | E58: 1.17676 | F58: 1.6207179 | G58: 1.1552621 | H58: =SUM(D58:G58) -> 4.8599549 | I58: 0.73021818 | J58: 0.18887579 | K58: 0.30532132 | L58: 0.27049953 | M58: =SUM(I58:L58) -> 1.4949148 | N58: 0.19284473 | O58: 0.16318166 | P58: 0.15381932 | Q58: 0.11269541 | R58: =SUM(N58:Q58) -> 0.62254112 | S58: 0.07445231 | T58: 0.14660336 | U58: 0.66837598 | V58: 2.1424723 | W58: =SUM(S58:V58) -> 3.031904 | X58: 2.4242114 | Y58: 1.9568569 | Z58: 1.4825416 | AA58: 1.7373733 | AB58: =SUM(X58:AA58) -> 7.6009833 | AC58: 1.0312549 | AD58: 1.718 | AE58: 4.789 | AF58: 3.546 | AG58: =SUM(AC58:AF58) -> 11.084255 | AH58: 1.813 | AI58: 1.093 | AJ58: 4.6 | AK58: =AL58-AJ58-AI58-AH58 -> 5.122 | AL58: 12.628 | AM58: 3.4 | AN58: 3.4 | AO58: 3.3 | AP58: 3.3 | AQ58: =SUM(AM58:AP58) -> 13.4
C59: Interest Expense | D59: -0.01021187 | E59: -0.00760304 | F59: -0.0057988 | G59: -0.00481166 | H59: =SUM(D59:G59) -> -0.02842537 | I59: -0.14312638 | J59: 0.13652574 | K59: -5.5213461 | L59: -13.400725 | M59: =SUM(I59:L59) -> -18.928672 | N59: -3.7722974 | O59: -3.789743 | P59: -3.7892903 | Q59: -3.8321984 | R59: =SUM(N59:Q59) -> -15.183529 | S59: -4.2903923 | T59: -3.8553121 | U59: -4.5259343 | V59: -9.2220987 | W59: =SUM(S59:V59) -> -21.893737 | X59: -9.1909411 | Y59: -11.711687 | Z59: -12.342422 | AA59: -13.623889 | AB59: =SUM(X59:AA59) -> -46.868938 | AC59: -13.238359 | AD59: -13.295 | AE59: -13.761 | AF59: -13.359 | AG59: =SUM(AC59:AF59) -> -53.653359 | AH59: -18.003 | AI59: -21.579 | AJ59: -15.399 | AK59: =AL59-AJ59-AI59-AH59 -> -15.286 | AL59: =-70.267 -> -70.267 | AM59: -15 | AN59: -15 | AO59: -15 | AP59: -15 | AQ59: =SUM(AM59:AP59) -> -60
C60: Other Income (expense), net | D60: 0.000221695 | E60: -0.001562408 | F60: -0.005983689 | G60: 0.005552299 | H60: =SUM(D60:G60) -> -0.001772103 | I60: -0.015472958 | J60: 0.007150844 | K60: 0.006581178 | L60: -0.46387823 | M60: =SUM(I60:L60) -> -0.46561917 | N60: -0.007270918 | O60: 0.000229895 | P60: 0.005759931 | Q60: -0.31440046 | R60: =SUM(N60:Q60) -> -0.31568155 | S60: 0.18349747 | T60: -3.2613014 | U60: -1.3755354 | V60: -0.4581871 | W60: =SUM(S60:V60) -> -4.9115265 | X60: 6.3824136 | Y60: -0.76983404 | Z60: 2.287576 | AA60: 13.912101 | AB60: =SUM(X60:AA60) -> 21.812256 | AC60: 0.74858026 | AD60: -7.048 | AE60: -11.522 | AF60: =32.336-AE60-AD60-AC60 -> 50.15742 | AG60: =SUM(AC60:AF60) -> 32.336 | AH60: -27.455 | AI60: 41.729 | AJ60: =-12.034+2.605 -> -9.429 | AK60: =AL60-AJ60-AI60-AH60 -> 14.568 | AL60: =31.447-12.034 -> 19.413 | AM60: 0 | AN60: 0 | AO60: 0 | AP60: 0 | AQ60: =SUM(AM60:AP60) -> 0
C61: Total Other Income (expense) | D61: =SUM(D58:D60) -> 0.89722474 | E61: =SUM(E58:E60) -> 1.1675946 | F61: =SUM(F58:F60) -> 1.6089354 | G61: =SUM(G58:G60) -> 1.1560028 | H61: =SUM(D61:G61) -> 4.8297575 | I61: =SUM(I58:I60) -> 0.57161884 | J61: =SUM(J58:J60) -> 0.33255237 | K61: =SUM(K58:K60) -> -5.2094436 | L61: =SUM(L58:L60) -> -13.594104 | M61: =SUM(I61:L61) -> -17.899376 | N61: =SUM(N58:N60) -> -3.5867236 | O61: =SUM(O58:O60) -> -3.6263314 | P61: =SUM(P58:P60) -> -3.6297111 | Q61: =SUM(Q58:Q60) -> -4.0339035 | R61: =SUM(N61:Q61) -> -14.87667 | S61: =SUM(S58:S60) -> -4.0324425 | T61: =SUM(T58:T60) -> -6.9700102 | U61: =SUM(U58:U60) -> -5.2330937 | V61: =SUM(V58:V60) -> -7.5378135 | W61: =SUM(S61:V61) -> -23.77336 | X61: =SUM(X58:X60) -> -0.38431607 | Y61: =SUM(Y58:Y60) -> -10.524664 | Z61: =SUM(Z58:Z60) -> -8.572304 | AA61: =SUM(AA58:AA60) -> 2.0255854 | AB61: =SUM(X61:AA61) -> -17.455699 | AC61: =SUM(AC58:AC60) -> -11.458524 | AD61: =SUM(AD58:AD60) -> -18.625 | AE61: =SUM(AE58:AE60) -> -20.494 | AF61: =SUM(AF58:AF60) -> 40.34442 | AG61: =SUM(AC61:AF61) -> -10.233104 | AH61: =SUM(AH58:AH60) -> -43.645 | AI61: =SUM(AI58:AI60) -> 21.243 | AJ61: =SUM(AJ58:AJ60) -> -20.228 | AK61: =SUM(AK58:AK60) -> 4.404 | AL61: =SUM(AH61:AK61) -> -38.226 | AM61: =SUM(AM58:AM60) -> -11.6 | AN61: =SUM(AN58:AN60) -> -11.6 | AO61: =SUM(AO58:AO60) -> -11.7 | AP61: =SUM(AP58:AP60) -> -11.7 | AQ61: =SUM(AM61:AP61) -> -46.6
C63: Adjusted EBITDA | D63: =D74-D58-D59-D72+CF!D9+D53 -> -23.497644 | E63: =E74-E58-E59-E72+CF!E9+E53 -> -29.471326 | F63: =F74-F58-F59-F72+CF!F9+F53 -> -33.237773 | G63: =G74-G58-G59-G72+CF!G9+G53 -> -25.492394 | H63: =SUM(D63:G63) -> -111.69914 | I63: =I74-I58-I59-I72+CF!I9+I53 -> -43.749327 | J63: =J74-J58-J59-J72+CF!J9+J53 -> -47.842139 | K63: =K74-K58-K59-K72+CF!K9+K53 -> -48.403612 | L63: =L74-L58-L59-L72+CF!L9+L53 -> -10.509205 | M63: =SUM(I63:L63) -> -150.50428 | N63: =N74-N58-N59-N72+CF!N9+N53 -> -55.352262 | O63: =O74-O58-O59-O72+CF!O9+O53 -> -52.633937 | P63: =P74-P58-P59-P72+CF!P9+P53 -> -58.184305 | Q63: =Q74-Q58-Q59-Q72+CF!Q9+Q53 -> -48.547111 | R63: =SUM(N63:Q63) -> -214.71761 | S63: =S74-S58-S59-S72+CF!S9+S53 -> -73.77206 | T63: =T74-T58-T59-T72+CF!T9+T53 -> -61.088753 | U63: =U74-U58-U59-U72+CF!U9+U53 -> -54.930241 | V63: =V74-V58-V59-V72+CF!V9+V53 -> -50.14346 | W63: =SUM(S63:V63) -> -239.93451 | X63: =X74-X58-X59-X72+CF!X9+X53 -> -45.930335 | Y63: =Y74-Y58-Y59-Y72+CF!Y9+Y53 -> -36.927259 | Z63: =Z74-Z58-Z59-Z72+CF!Z9+Z53 -> -36.235085 | AA63: =AA74-AA58-AA59-AA72+CF!AA9+AA53 -> -35.445743 | AB63: =SUM(X63:AA63) -> -154.53842 | AC63: =AC74-AC58-AC59-AC72+CF!AC9+AC53 -> -43.925489 | AD63: =AD74-AD58-AD59+AD51+AD52-AD67+AD49+AD50+AD41+AD42 -> -31.295 | AE63: =AE74-AE58-AE59+AE51+AE52-AE67+AE49+AE50+AE41+AE42 -> -21.843 | AF63: =AF74-AF58-AF59+AF51+AF52-AF67+AF49+AF50+AF41+AF42+5.244 -> -7.7515803 | AG63: =SUM(AC63:AF63) -> -104.81507 | AH63: =AH74-AH58-AH59+AH51+AH52-AH72-AH77+AH41+AH42+AH49+AH48+0.091+1.646 -> -16.153 | AI63: =AI74-AI58-AI59+AI51+AI52-AI72-AI77+AI41+AI42+AI49+AI48 -> -5.586 | AJ63: =AJ74-AJ58-AJ59+CF!AJ9-IS!AJ67-IS!AJ77+IS!AJ41+IS!AJ42+IS!AJ49+IS!AJ48+IS!AJ52+12.034 -> 1.476 | AK63: =AK74-AK58-AK59+AK51+19.204-AK67-AK77+AK41+AK42+AK49-0.136-3.989+1.608 -> 12.893 | AL63: =SUM(AH63:AK63) -> -7.37 | AM63: =AM74-AM58-AM59+CF!AM9-IS!AM67-IS!AM77+IS!AM41+IS!AM42+IS!AM49+IS!AM48+IS!AM52 -> -4.966988 | AN63: =AN74-AN58-AN59+CF!AN9-IS!AN67-IS!AN77+IS!AN41+IS!AN42+IS!AN49+IS!AN48+IS!AN52 -> 10.532534 | AO63: =AO74-AO58-AO59+CF!AO9-IS!AO67-IS!AO77+IS!AO41+IS!AO42+IS!AO49+IS!AO48+IS!AO52 -> 22.653955 | AP63: =AP74-AP58-AP59+CF!AP9-IS!AP67-IS!AP77+IS!AP41+IS!AP42+IS!AP49+IS!AP48+IS!AP52 -> 36.757156 | AQ63: =SUM(AM63:AP63) -> 64.976657
C64: EBITDA Margins | D64: =D63/D15 -> -3.0600802 | E64: =E63/E15 -> -2.7842384 | F64: =F63/F15 -> -2.171796 | G64: =G63/G15 -> -0.89481583 | H64: =H63/H15 -> -1.7999416 | I64: =I63/I15 -> -2.3982584 | J64: =J63/J15 -> -2.6320041 | K64: =K63/K15 -> -0.95409226 | ... AQ64: =AQ63/AQ15 -> 0.040866195
C66: Non-GAAP Pre-Tax Income | D66: =D37+D61 -> -24.393366 | E66: =E37+E61 -> -30.204948 | F66: =F37+F61 -> -33.560787 | G66: =G37+G61 -> -26.792228 | H66: =SUM(D66:G66) -> -114.95133 | I66: =I37+I61 -> -47.102917 | J66: =J37+J61 -> -51.098613 | K66: =K37+K61 -> -57.509399 | L66: =L37+L61 -> -55.643518 | M66: =SUM(I66:L66) -> -211.35445 | N66: =N37+N61 -> -65.020109 | O66: =O37+O61 -> -66.499435 | P66: =P37+P61 -> -68.236895 | Q66: =Q37+Q61 -> -58.830734 | R66: =SUM(N66:Q66) -> -258.58717 | S66: =S37+S61 -> -81.124788 | T66: =T37+T61 -> -73.525278 | U66: =U37+U61 -> -68.410936 | V66: =V37+V61 -> -66.152623 | W66: =SUM(S66:V66) -> -289.21363 | X66: =X37+X61 -> -54.2443 | Y66: =Y37+Y61 -> -55.663548 | Z66: =Z37+Z61 -> -53.392665 | AA66: =AA37+AA61 -> -50.25626 | AB66: =SUM(X66:AA66) -> -213.55677 | AC66: =AC37+AC61 -> -64.732766 | AD66: =AD37+AD61 -> -59.043 | AE66: =AE37+AE61 -> -51.871 | AF66: =AF37+AF58+AF59-3.988+2.708-0.15 -> -29.576 | AG66: =SUM(AC66:AF66) -> -205.22277 | AH66: =AH37+AH61-3.989+3.529 -> -69.881 | AI66: =AI37+AI61-3.988+1.992 -> 2.21 | AJ66: =AJ37+AJ61 -> -28.89 | AK66: =AK37+AK61 -> 8.685 | AL66: =SUM(AH66:AK66) -> -87.876 | AM66: =AM37+AM61 -> -54.491988 | AN66: =AN37+AN61 -> -38.992466 | AO66: =AO37+AO61 -> -26.971045 | AP66: =AP37+AP61 -> -12.867844 | AQ66: =SUM(AM66:AP66) -> -133.32334
C67: Income Tax | D67: =D72 -> 0 | E67: =E72 -> 0 | F67: =F72 -> 0 | G67: =G72 -> 0 | H67: =SUM(D67:G67) -> 0 | I67: =I72 -> 0.001890819 | J67: =J72 -> 0 | K67: =K72 -> 0 | L67: =L72 -> 0.002365363 | M67: =SUM(I67:L67) -> 0.004256182 | N67: =N72 -> 0 | O67: =O72 -> 0 | P67: =P72 -> 0 | Q67: =Q72 -> 0 | R67: =SUM(N67:Q67) -> 0 | S67: =S72 -> -0.000484875 | T67: =T72 -> 5.474e-05 | U67: =U72 -> -0.000467806 | V67: =V72 -> -0.071677389 | W67: =SUM(S67:V67) -> -0.07257533 | X67: =X72 -> -0.005599457 | Y67: =Y72 -> -0.0036866 | Z67: =Z72 -> -0.064770125 | AA67: =AA72 -> -0.21415508 | AB67: =SUM(X67:AA67) -> -0.28821126 | AC67: =AC72 -> -0.011289509 | AD67: -0.095 | AE67: -0.038 | AF67: =AF72 -> -0.122 | AG67: =SUM(AC67:AF67) -> -0.26628951 | AH67: 46.18 | AI67: -0.212 | AJ67: =-0.276 -> -0.276 | AK67: =AK72 -> 5.992 | AL67: =SUM(AH67:AK67) -> 51.684 | AM67: =AM72 -> 0 | AN67: =AN72 -> 0 | AO67: =AO72 -> 0 | AP67: =AP72 -> 0 | AQ67: =SUM(AM67:AP67) -> 0
C68: Tax Rate % | D68: =D67/D66 -> 0 | E68: =E67/E66 -> 0 | F68: =F67/F66 -> 0 | G68: =G67/G66 -> 0 | I68: =I67/I66 -> -4.0142291e-05 | J68: =J67/J66 -> 0 | K68: =K67/K66 -> 0 | L68: =L67/L66 -> -4.2509228e-05 | N68: =N67/N66 -> 0 | O68: =O67/O66 -> 0 | P68: =P67/P66 -> 0 | Q68: =Q67/Q66 -> 0 | S68: =S67/S66 -> 5.9769031e-06 | T68: =T67/T66 -> -7.4450586e-07 | U68: =U67/U66 -> 6.8381757e-06 | V68: =V67/V66 -> 0.0010835154 | X68: =X67/X66 -> 0.00010322664 | Y68: =Y67/Y66 -> 6.6230058e-05 | Z68: =Z67/Z66 -> 0.0012130903 | AA68: =AA67/AA66 -> 0.0042612618 | AC68: =AC67/AC66 -> 0.00017440177 | AD68: =AD67/AD66 -> 0.0016089968 | AE68: =AE67/AE66 -> 0.00073258661 | AF68: =AF67/AF66 -> 0.0041249662 | AH68: =AH67/AH66 -> -0.66083771 | AI68: =AI67/AI66 -> -0.095927602 | AJ68: =AJ67/AJ66 -> 0.0095534787 | AK68: =AK67/AK66 -> 0.68992516 | AM68: 0 | AN68: 0 | AO68: 0 | AP68: 0
C69: Non-GAAP Net Income (loss) | D69: =D66+D67 -> -24.393366 | E69: =E66+E67 -> -30.204948 | F69: =F66+F67 -> -33.560787 | G69: =G66+G67 -> -26.792228 | H69: =SUM(D69:G69) -> -114.95133 | I69: =I66+I67 -> -47.101026 | J69: =J66+J67 -> -51.098613 | K69: =K66+K67 -> -57.509399 | L69: =L66+L67 -> -55.641153 | M69: =SUM(I69:L69) -> -211.35019 | N69: =N66+N67 -> -65.020109 | O69: =O66+O67 -> -66.499435 | P69: =P66+P67 -> -68.236895 | Q69: =Q66+Q67 -> -58.830734 | R69: =SUM(N69:Q69) -> -258.58717 | S69: =S66+S67 -> -81.125273 | T69: =T66+T67 -> -73.525223 | U69: =U66+U67 -> -68.411404 | V69: =V66+V67 -> -66.224301 | W69: =SUM(S69:V69) -> -289.2862 | X69: =X66+X67 -> -54.2499 | Y69: =Y66+Y67 -> -55.667235 | Z69: =Z66+Z67 -> -53.457435 | AA69: =AA66+AA67 -> -50.470415 | AB69: =SUM(X69:AA69) -> -213.84498 | AC69: =AC66+AC67 -> -64.744056 | AD69: =AD74+AD41+AD42+AD49+AD50 -> -52.126 | AE69: =AE66+AE67 -> -51.909 | AF69: =AF66+AF67 -> -29.698 | AG69: =SUM(AC69:AF69) -> -198.47706 | AH69: =AH74+AH41+AH42+AH49+AH48+AH46-AH77-AH67-3.989+0.091+1.646 -> -41.54 | AI69: =AI74+AI41+AI42+AI49+AI48+AI46-AI77-AI67-3.988 -> -37.327 | AJ69: =AJ74+AJ41+AJ42+AJ49+AJ48+AJ46-AJ77-AJ67+AJ52+12.034 -> -19.59 | AK69: =AK74+AK41+AK42+AK49-0.136+AK46-AK77-AK72+1.608-3.989 -> -7.341 | AL69: =SUM(AH69:AK69) -> -105.798 | AM69: =AM66+AM67 -> -54.491988 | AN69: =AN66+AN67 -> -38.992466 | AO69: =AO66+AO67 -> -26.971045 | AP69: =AP66+AP67 -> -12.867844 | AQ69: =SUM(AM69:AP69) -> -133.32334
P70: =P69/P10 -> 587.8529 | Q70: =Q69/Q10 -> 121.21832 | R70: =R69/R10 -> -911.38889 | S70: =S69/S10 -> 221.34657 | T70: =T69/T10 -> 690.76456 | U70: =U69/U10 -> -217.01793 | V70: =V69/V10 -> -153.85923 | W70: =W69/W10 -> -18980.288 | ... AQ70: =AQ69/AQ10 -> -569.74688
C71: GAAP Pre-Tax Income | D71: =D55+D61 -> -24.525751 | E71: =E55+E61 -> -30.337332 | F71: =F55+F61 -> -36.585171 | G71: =G55+G61 -> -26.92425 | H71: =SUM(D71:G71) -> -118.37251 | I71: =I55+I61 -> -47.202573 | J71: =J55+J61 -> -51.198269 | K71: =K55+K61 -> -57.609056 | L71: =L55+L61 -> -55.743175 | M71: =SUM(I71:L71) -> -211.75307 | N71: =N55+N61 -> -65.020109 | O71: =O55+O61 -> -67.058184 | P71: =P55+P61 -> -68.236895 | Q71: =Q55+Q61 -> -58.830734 | R71: =SUM(N71:Q71) -> -259.14592 | S71: =S55+S61 -> -81.124788 | T71: =T55+T61 -> -73.525278 | U71: =U55+U61 -> -68.410936 | V71: =V55+V61 -> -66.152623 | W71: =SUM(S71:V71) -> -289.21363 | X71: =X55+X61 -> -54.2443 | Y71: =Y55+Y61 -> -55.663548 | Z71: =Z55+Z61 -> -53.392665 | AA71: =AA55+AA61 -> -50.25626 | AB71: =SUM(X71:AA71) -> -213.55677 | AC71: =AC55+AC61 -> -64.732766 | AD71: =AD55+AD61 -> -552.226 | AE71: =AE55+AE61 -> -74.11 | AF71: =AF55+AF61 -> -12.89158 | AG71: =SUM(AC71:AF71) -> -703.96035 | AH71: =AH55+AH61 -> -112.196 | AI71: =AI55+AI61 -> -40.531 | AJ71: =AJ55+AJ61 -> -81.224 | AK71: =AK55+AK61 -> -56.641 | AL71: =SUM(AH71:AK71) -> -290.592 | AM71: =AM55+AM61 -> -109.49199 | AN71: =AN55+AN61 -> -87.322466 | AO71: =AO55+AO61 -> -75.301045 | AP71: =AP55+AP61 -> -61.197844 | AQ71: =SUM(AM71:AP71) -> -333.31334
C72: Income Tax | D72: 0 | E72: 0 | F72: 0 | G72: 0 | H72: =SUM(D72:G72) -> 0 | I72: 0.001890819 | J72: 0 | K72: 0 | L72: 0.002365363 | M72: =SUM(I72:L72) -> 0.004256182 | N72: 0 | O72: 0 | P72: 0 | Q72: 0 | R72: =SUM(N72:Q72) -> 0 | S72: -0.000484875 | T72: 5.474e-05 | U72: -0.000467806 | V72: -0.071677389 | W72: =SUM(S72:V72) -> -0.07257533 | X72: -0.005599457 | Y72: -0.0036866 | Z72: -0.064770125 | AA72: -0.21415508 | AB72: =SUM(X72:AA72) -> -0.28821126 | AC72: -0.011289509 | AD72: -0.095 | AE72: -0.038 | AF72: -0.122 | AG72: =SUM(AC72:AF72) -> -0.26628951 | AH72: 46.18 | AI72: -0.212 | AJ72: =-0.276 -> -0.276 | AK72: =AL72-AJ72-AI72-AH72 -> 5.992 | AL72: 51.684 | AM72: 0 | AN72: 0 | AO72: 0 | AP72: =AP71*AP73 -> 0 | AQ72: =SUM(AM72:AP72) -> 0
C73: Tax Rate % | D73: =D72/D71 -> 0 | E73: =E72/E71 -> 0 | F73: =F72/F71 -> 0 | G73: =G72/G71 -> 0 | I73: =I72/I71 -> -4.0057541e-05 | J73: =J72/J71 -> 0 | K73: =K72/K71 -> 0 | L73: =L72/L71 -> -4.2433231e-05 | N73: =N72/N71 -> 0 | O73: =O72/O71 -> 0 | P73: =P72/P71 -> 0 | Q73: =Q72/Q71 -> 0 | S73: =S72/S71 -> 5.9769031e-06 | T73: =T72/T71 -> -7.4450586e-07 | U73: =U72/U71 -> 6.8381757e-06 | V73: =V72/V71 -> 0.0010835154 | X73: =X72/X71 -> 0.00010322664 | Y73: =Y72/Y71 -> 6.6230058e-05 | Z73: =Z72/Z71 -> 0.0012130903 | AA73: =AA72/AA71 -> 0.0042612618 | AC73: =AC72/AC71 -> 0.00017440177 | AD73: =AD72/AD71 -> 0.00017203102 | AE73: =AE72/AE71 -> 0.00051275132 | AF73: =AF72/AF71 -> 0.0094635411 | AH73: =AH72/AH71 -> -0.41160113 | AI73: =AI72/AI71 -> 0.0052305643 | AJ73: =AJ72/AJ71 -> 0.0033980104 | AK73: =AK72/AK71 -> -0.10578909 | AM73: 0 | AN73: 0 | AO73: 0 | AP73: 0
C74: GAAP Net Income (loss) | D74: =D71+D72 -> -24.525751 | E74: =E71+E72 -> -30.337332 | F74: =F71+F72 -> -36.585171 | G74: =G71+G72 -> -26.92425 | H74: =SUM(D74:G74) -> -118.37251 | I74: =I71+I72 -> -47.200682 | J74: =J71+J72 -> -51.198269 | K74: =K71+K72 -> -57.609056 | L74: =L71+L72 -> -55.740809 | M74: =SUM(I74:L74) -> -211.74882 | N74: =N71+N72 -> -65.020109 | O74: =O71+O72 -> -67.058184 | P74: =P71+P72 -> -68.236895 | Q74: =Q71+Q72 -> -58.830734 | R74: =SUM(N74:Q74) -> -259.14592 | S74: =S71+S72 -> -81.125273 | T74: =T71+T72 -> -73.525223 | U74: =U71+U72 -> -68.411404 | V74: =V71+V72 -> -66.224301 | W74: =SUM(S74:V74) -> -289.2862 | X74: =X71+X72 -> -54.2499 | Y74: =Y71+Y72 -> -55.667235 | Z74: =Z71+Z72 -> -53.457435 | AA74: =AA71+AA72 -> -50.470415 | AB74: =SUM(X74:AA74) -> -213.84498 | AC74: =AC71+AC72 -> -64.744056 | AD74: =AD71+AD72 -> -552.321 | AE74: =AE71+AE72 -> -74.148 | AF74: =AF71+AF72 -> -13.01358 | AG74: =SUM(AC74:AF74) -> -704.22664 | AH74: =AH71+AH72-2 -> -68.016 | AI74: =AI71+AI72+AI77 -> -42.843 | AJ74: =AJ71+AJ72+AJ77 -> -79.982 | AK74: =AK71+AK72+AK77-0.368 -> -54.166 | AL74: =SUM(AH74:AK74) -> -245.007 | AM74: =AM71+AM72 -> -109.49199 | AN74: =AN71+AN72 -> -87.322466 | AO74: =AO71+AO72 -> -75.301045 | AP74: =AP71+AP72 -> -61.197844 | AQ74: =SUM(AM74:AP74) -> -333.31334
C75: GAAP Net margin | K75: =K74/K15 -> -1.1355424 | L75: =L74/L15 -> -0.55270131 | M75: =M74/M15 -> -1.126303 | N75: =N74/N15 -> -0.92740061 | O75: =O74/O15 -> -1.081833 | P75: =P74/P15 -> -1.3010476 | Q75: =Q74/Q15 -> -0.80249769 | R75: =R74/R15 -> -1.0050144 | ... AQ75: =AQ74/AQ15 -> -0.20963295
C77: Earnings from Equity Method Investments | D77: 0 | E77: 0 | F77: 0 | G77: 0 | H77: 0 | I77: 0 | J77: 0 | K77: 0 | L77: 1.5 | M77: 1.5 | N77: 0 | O77: -0.34763518 | P77: -0.1059884 | Q77: -0.150299 | R77: -0.60392258 | S77: -0.164533 | T77: -0.165779 | U77: -0.133929 | V77: -0.131189 | W77: -0.59543 | X77: -0.130974 | Y77: -0.16967342 | Z77: 0 | AA77: 0 | AB77: -0.30064742 | AC77: 0 | AD77: =11.54+0.668 -> 12.208 | AE77: 1.692 | AF77: =-4.228-AE77-AD77-AC77 -> -18.128 | AH77: -1.883 | AI77: -2.1 | AJ77: 1.518 | AK77: =AL77-AJ77-AI77-AH77 -> -3.149 | AL77: -5.614 | AM77: -5 | AN77: -5 | AO77: -5 | AP77: -5 | AQ77: =SUM(AM77:AP77) -> -20
C78: Net Income (loss) Attributable to Tempus Labs | D78: =D74-SUM(D77:D77) -> -24.525751 | E78: =E74-SUM(E77:E77) -> -30.337332 | F78: =F74-SUM(F77:F77) -> -36.585171 | G78: =G74-SUM(G77:G77) -> -26.92425 | H78: =SUM(D78:G78) -> -118.37251 | I78: =I74+SUM(I77:I77) -> -47.200682 | J78: =J74+SUM(J77:J77) -> -51.198269 | K78: =K74+SUM(K77:K77) -> -57.609056 | L78: =L74+SUM(L77:L77) -> -54.240809 | M78: =M74-SUM(M77:M77) -> -213.24882 | N78: =N74+SUM(N77:N77) -> -65.020109 | O78: =O74-SUM(O77:O77) -> -66.710549 | P78: =P74+SUM(P77:P77) -> -68.342884 | Q78: =Q74+SUM(Q77:Q77) -> -58.981033 | R78: =R74-SUM(R77:R77) -> -258.542 | S78: =S74+SUM(S77:S77) -> -81.289806 | T78: =T74+SUM(T77:T77) -> -73.691002 | U78: =U74+SUM(U77:U77) -> -68.545333 | V78: =V74+SUM(V77:V77) -> -66.35549 | W78: =W74-SUM(W77:W77) -> -288.69077 | X78: =X74+SUM(X77:X77) -> -54.380874 | Y78: =Y74+SUM(Y77:Y77) -> -55.836908 | Z78: =Z74+SUM(Z77:Z77) -> -53.457435 | AA78: =AA74+SUM(AA77:AA77) -> -50.470415 | AB78: =AB74-SUM(AB77:AB77) -> -213.54434 | AC78: -93.056 | AD78: =AD74-SUM(AD77:AD77) -> -564.529 | AE78: =AE74-SUM(AE77:AE77) -> -75.84 | AF78: =AF74+AF77 -> -31.14158 | AG78: =AG74-SUM(AG77:AG77) -> -704.22664 | AH78: =AH74-SUM(AH77:AH77) -> -66.133 | AI78: =AI74-SUM(AI77:AI77) -> -40.743 | AJ78: =AJ74-SUM(AJ77:AJ77) -> -81.5 | AK78: =AK74-SUM(AK77:AK77) -> -51.017 | AL78: =AL74-SUM(AL77:AL77) -> -239.393 | AM78: =AM74-SUM(AM77:AM77) -> -104.49199 | AN78: =AN74-SUM(AN77:AN77) -> -82.322466 | ... AQ78: =AQ74-SUM(AQ77:AQ77) -> -313.31334
C80: Non-GAAP EPS | D80: =D76/D82 -> #DIV/0! | E80: =E76/E82 -> #DIV/0! | F80: =F76/F82 -> #DIV/0! | G80: =G76/G82 -> #DIV/0! | I80: =I76/I82 -> #DIV/0! | J80: =J76/J82 -> #DIV/0! | K80: =K76/K82 -> #DIV/0! | L80: =L76/L82 -> #DIV/0! | N80: =N76/N82 -> #DIV/0! | O80: =O76/O82 -> #DIV/0! | P80: =P76/P82 -> #DIV/0! | Q80: =Q76/Q82 -> #DIV/0! | R80: =SUM(N80:Q80) -> #DIV/0! | S80: =S76/S82 -> #DIV/0! | T80: =T76/T82 -> #DIV/0! | U80: =U76/U82 -> #DIV/0! | V80: =V76/V82 -> #DIV/0! | W80: =SUM(S80:V80) -> #DIV/0! | X80: =X76/X82 -> #DIV/0! | Y80: =Y76/Y82 -> #DIV/0! | Z80: =Z76/Z82 -> #DIV/0! | AA80: =AA76/AA82 -> #DIV/0! | AB80: =SUM(X80:AA80) -> #DIV/0! | AC80: =-1.61-AD80 -> -0.9768266 | AD80: =AD69/AD84 -> -0.6331734 | AE80: =AE69/AE84 -> -0.31393707 | AF80: =AF69/AF84 -> -0.1784757 | AG80: =SUM(AC80:AF80) -> -2.1024128 | AH80: =AH69/AH84 -> -0.24362779 | AI80: =AI69/AI84 -> -0.21528887 | AJ80: =AJ69/AJ84 -> -0.11197805 | AK80: =AK69/AK84 -> -0.041220037 | AL80: =SUM(AH80:AK80) -> -0.61211475 | AM80: =AM69/AM84 -> -0.30523814 | AN80: =AN69/AN84 -> -0.21789254 | AO80: =AO69/AO84 -> -0.15035486 | AP80: =AP69/AP84 -> -0.071562579 | AQ80: =SUM(AM80:AP80) -> -0.74504811
C81: Y/Y Growth % | I81: =I80/D80-1 -> #DIV/0! | J81: =J80/E80-1 -> #DIV/0! | K81: =K80/F80-1 -> #DIV/0! | L81: =L80/G80-1 -> #DIV/0! | N81: =N80/I80-1 -> #DIV/0! | O81: =O80/J80-1 -> #DIV/0! | P81: =P80/K80-1 -> #DIV/0! | Q81: =Q80/L80-1 -> #DIV/0! | S81: =S80/N80-1 -> #DIV/0! | T81: =T80/O80-1 -> #DIV/0! | U81: =U80/P80-1 -> #DIV/0! | V81: =V80/Q80-1 -> #DIV/0! | X81: =X80/S80-1 -> #DIV/0! | Y81: =Y80/T80-1 -> #DIV/0! | Z81: =Z80/U80-1 -> #DIV/0! | AA81: =AA80/V80-1 -> #DIV/0! | AC81: =AC80/X80-1 -> #DIV/0! | AD81: =AD80/Y80-1 -> #DIV/0! | AE81: =AE80/Z80-1 -> #DIV/0! | AF81: =AF80/AA80-1 -> #DIV/0! | AH81: =AH80/AC80-1 -> -0.75059259 | AI81: =AI80/AD80-1 -> -0.65998434 | AJ81: =AJ80/AE80-1 -> -0.64331052 | AK81: =AK80/AF80-1 -> -0.76904399 | AM81: =AM80/AH80-1 -> 0.2528872 | AN81: =AN80/AI80-1 -> 0.012093822 | AO81: =AO80/AJ80-1 -> 0.34271721 | AP81: =AP80/AK80-1 -> 0.73611147
C82: GAAP EPS | D82: =D78/D84 -> #DIV/0! | E82: =E78/E84 -> #DIV/0! | F82: =F78/F84 -> #DIV/0! | G82: =G78/G84 -> #DIV/0! | I82: =I78/I84 -> #DIV/0! | J82: =J78/J84 -> #DIV/0! | K82: =K78/K84 -> #DIV/0! | L82: =L78/L84 -> #DIV/0! | N82: =N78/N84 -> #DIV/0! | O82: =O78/O84 -> #DIV/0! | P82: =P78/P84 -> #DIV/0! | Q82: =Q78/Q84 -> #DIV/0! | R82: =SUM(N82:Q82) -> #DIV/0! | S82: =S78/S84 -> #DIV/0! | T82: =T78/T84 -> #DIV/0! | U82: =U78/U84 -> #DIV/0! | V82: =V78/V84 -> #DIV/0! | W82: =SUM(S82:V82) -> #DIV/0! | X82: =X78/X84 -> #DIV/0! | Y82: =Y78/Y84 -> #DIV/0! | Z82: =Z78/Z84 -> #DIV/0! | AA82: =AA78/AA84 -> #DIV/0! | AB82: =SUM(X82:AA82) -> #DIV/0! | AC82: =AC78/AC84 -> -2.1600241 | AD82: =AD78/AD84 -> -6.8573216 | AE82: =AE78/AE84 -> -0.45866781 | AF82: =AF78/AF84 -> -0.18715117 | AG82: =SUM(AC82:AF82) -> -9.6631647 | AH82: =AH74/AH84 -> -0.39890678 | AI82: =AI74/AI84 -> -0.2471032 | AJ82: =AJ74/AJ84 -> -0.45718369 | AK82: =AK74/AK84 -> -0.30414446 | AL82: =SUM(AH82:AK82) -> -1.4073381 | AM82: =AM74/AM84 -> -0.61332192 | AN82: =AN74/AN84 -> -0.48796385 | AO82: =AO74/AO84 -> -0.41977897 | AP82: =AP74/AP84 -> -0.3403426 | AQ82: =SUM(AM82:AP82) -> -1.8614073
C83: Y/Y Growth % | I83: =I82/D82-1 -> #DIV/0! | J83: =J82/E82-1 -> #DIV/0! | K83: =K82/F82-1 -> #DIV/0! | L83: =L82/G82-1 -> #DIV/0! | N83: =N82/I82-1 -> #DIV/0! | O83: =O82/J82-1 -> #DIV/0! | P83: =P82/K82-1 -> #DIV/0! | Q83: =Q82/L82-1 -> #DIV/0! | S83: =S82/N82-1 -> #DIV/0! | T83: =T82/O82-1 -> #DIV/0! | U83: =U82/P82-1 -> #DIV/0! | V83: =V82/Q82-1 -> #DIV/0! | X83: =X82/S82-1 -> #DIV/0! | Y83: =Y82/T82-1 -> #DIV/0! | Z83: =Z82/U82-1 -> #DIV/0! | AA83: =AA82/V82-1 -> #DIV/0! | AC83: =AC82/X82-1 -> #DIV/0! | AD83: =AD82/Y82-1 -> #DIV/0! | AE83: =AE82/Z82-1 -> #DIV/0! | AF83: =AF82/AA82-1 -> #DIV/0! | AH83: =AH82/AC82-1 -> -0.815323 | AI83: =AI82/AD82-1 -> -0.96396506 | AJ83: =AJ82/AE82-1 -> -0.003235727 | AK83: =AK82/AF82-1 -> 0.62512724 | AM83: =AM82/AH82-1 -> 0.53750687 | AN83: =AN82/AI82-1 -> 0.97473706 | AO83: =AO82/AJ82-1 -> -0.081815501 | AP83: =AP82/AK82-1 -> 0.11901626
C84: Fully Diluted Shares Outstanding | AC84: 43.081 | AD84: 82.325 | AE84: 165.34842 | AF84: 166.398 | AG84: =AF84 -> 166.398 | AH84: 170.506 | AI84: 173.381 | AJ84: 174.945 | AK84: 178.093 | AL84: =AK84 -> 178.093 | AM84: =AL84+0.429868 -> 178.52287 | AN84: =AM84+0.429868 -> 178.95274 | AO84: =AN84+0.429868 -> 179.3826 | AP84: =AO84+0.429868 -> 179.81247 | AQ84: =AP84 -> 179.81247

Sheet BS
C2: Tempus Labs (NASDAQ: TEM)
B5: Balance Sheet | D5: 1Q19 | E5: 2Q19 | F5: 3Q19 | G5: 4Q19 | H5: FY19 | I5: 1Q20 | J5: 2Q20 | K5: 3Q20 | L5: 4Q20 | M5: FY20 | N5: 1Q21 | O5: 2Q21 | P5: 3Q21 | Q5: 4Q21 | R5: FY21 | S5: 1Q22 | T5: 2Q22 | U5: 3Q22 | V5: 4Q22 | W5: FY22 | X5: 1Q23 | Y5: 2Q23 | Z5: 3Q23 | AA5: 4Q23 | AB5: FY23 | AC5: 1Q24 | AD5: 2Q24 | AE5: 3Q24 | AF5: 4Q24 | AG5: FY24 | AH5: 1Q25 | AI5: 2Q25 | AJ5: 3Q25 | AK5: 4Q25 | AL5: FY25 | AM5: 1Q26E | AN5: 2Q26E | AO5: 3Q26E | AP5: 4Q26E | AQ5: FY26E
B6: Assets:
C7: Cash | D7: 162.63119 | E7: 322.80265 | F7: 296.20918 | G7: 228.1001 | H7: =G7 -> 228.1001 | I7: 268.0867 | J7: 532.96034 | K7: 465.50434 | L7: 514.216 | M7: =L7 -> 514.216 | N7: 471.931 | O7: 423.178 | P7: 345.725 | Q7: 278.466 | R7: =Q7 -> 278.466 | S7: 178.44295 | T7: 197.90377 | U7: 369.80596 | V7: 303.73118 | W7: =V7 -> 303.73118 | X7: 224.55794 | Y7: 203.07741 | Z7: 133.52737 | AA7: 166.60703 | AB7: =AA7 -> 166.60703 | AC7: 80.7923 | AD7: 478.811 | AE7: 388.006 | AF7: 340.954 | AG7: =AF7 -> 340.954 | AH7: 151.603 | AI7: 186.31 | AJ7: 655.918 | AK7: 604.787 | AL7: =AK7 -> 604.787 | AM7: =AK7+CF!AM80 -> 662.2392 | AN7: =AM7+CF!AN80 -> 658.89784 | AO7: =AN7+CF!AO80 -> 640.95473 | AP7: =AO7+CF!AP80 -> 659.00933 | AQ7: =AP7 -> 659.00933
C8: Marketable equity securities | D8: 0 | E8: 0 | F8: 0 | G8: 0 | H8: =G8 -> 0 | I8: 0 | J8: 0 | K8: 0 | L8: 0 | M8: =L8 -> 0 | N8: 0 | O8: 0 | P8: 0 | Q8: 0 | R8: =Q8 -> 0 | S8: 0 | T8: 0 | U8: 0 | V8: 0 | W8: =V8 -> 0 | X8: 0 | Y8: 0 | Z8: 0 | AA8: 31.807394 | AB8: =AA8 -> 31.807394 | AC8: 14.956498 | AD8: 11.255 | AE8: 78.317 | AF8: 107.309 | AG8: =AF8 -> 107.309 | AH8: 67.183 | AI8: 104.996 | AJ8: 103.72 | AK8: 150.211 | AL8: =AK8 -> 150.211 | AM8: =AK8 -> 150.211 | AN8: =AM8 -> 150.211 | AO8: =AN8 -> 150.211 | AP8: =AO8 -> 150.211 | AQ8: =AP8 -> 150.211
C9: Accounts receivable/ pre-paid expenses | D9: 16.203311 | E9: 20.730174 | F9: 22.028856 | G9: 39.82562 | H9: =G9 -> 39.82562 | I9: 27.820868 | J9: 32.032857 | K9: 63.333 | L9: 98.737 | M9: =L9 -> 98.737 | N9: 78.198 | O9: 9.263 | P9: 85.623 | Q9: 99.535 | R9: =Q9 -> 99.535 | S9: 99.751542 | T9: 95.903162 | U9: 97.190442 | V9: 113.40836 | W9: =V9 -> 113.40836 | X9: 123.60367 | Y9: 120.26196 | Z9: 140.99741 | AA9: 128.84206 | AB9: =AA9 -> 128.84206 | AC9: 144.33614 | AD9: =118.106+29.704 -> 147.81 | AE9: =31.335+145.616 -> 176.951 | AF9: =154.819+26.135 -> 180.954 | AG9: =AF9 -> 180.954 | AH9: =262.613+42.086 -> 304.699 | AI9: =266.284+36.476 -> 302.76 | AJ9: =283.626+42.611 -> 326.237 | AK9: =311.17+40.498 -> 351.668 | AL9: =AK9 -> 351.668 | AM9: =AM55*IS!AM15 -> 275.96636 | AN9: =AN55*IS!AN15 -> 296.23676 | AO9: =AO55*IS!AO15 -> 269.85776 | AP9: =AP55*IS!AP15 -> 239.61854 | AQ9: =AP9 -> 239.61854
C10: Warrant asset | AD10: 0.8 | AE10: 0 | AF10: 0 | AG10: =AF10 -> 0 | AH10: 0 | AI10: 2.535 | AJ10: 5.66 | AK10: 8.785 | AL10: =AK10 -> 8.785
C11: Inventory | D11: 5.4685583 | E11: 6.8028628 | F11: 6.494006 | G11: 8.2786812 | H11: =G11 -> 8.2786812 | I11: 8.369762 | J11: 25.423183 | K11: 32.601 | L11: 37.557 | M11: =L11 -> 37.557 | N11: 30.732 | O11: 27.704 | P11: 21.998 | Q11: 22.908 | R11: =Q11 -> 22.908 | S11: 17.299143 | T11: 20.64646 | U11: 21.028572 | V11: 22.281781 | W11: =V11 -> 22.281781 | X11: 25.211479 | Y11: 27.382672 | Z11: 27.157111 | AA11: 28.845248 | AB11: =AA11 -> 28.845248 | AC11: 30.129189 | AD11: 32.69 | AE11: 36.138 | AF11: 38.386 | AG11: =AF11 -> 38.386 | AH11: 50.485 | AI11: 47.6 | AJ11: 54.976 | AK11: 51.724 | AL11: =AK11 -> 51.724 | AM11: =AM56*IS!AM15 -> 50.018902 | AN11: =AN56*IS!AN15 -> 53.322616 | AO11: =AO56*IS!AO15 -> 51.895724 | AP11: =AP56*IS!AP15 -> 52.402966 | AQ11: =AP11 -> 52.402966
B12: Total Current Assets | D12: =SUM(D7:D11) -> 184.30306 | E12: =SUM(E7:E11) -> 350.33569 | F12: =SUM(F7:F11) -> 324.73204 | G12: =SUM(G7:G11) -> 276.2044 | H12: =G12 -> 276.2044 | I12: =SUM(I7:I11) -> 304.27733 | J12: =SUM(J7:J11) -> 590.41638 | K12: =SUM(K7:K11) -> 561.43834 | L12: =SUM(L7:L11) -> 650.51 | M12: =L12 -> 650.51 | N12: =SUM(N7:N11) -> 580.861 | O12: =SUM(O7:O11) -> 460.145 | P12: =SUM(P7:P11) -> 453.346 | Q12: =SUM(Q7:Q11) -> 400.909 | R12: =Q12 -> 400.909 | S12: =SUM(S7:S11) -> 295.49363 | T12: =SUM(T7:T11) -> 314.45339 | U12: =SUM(U7:U11) -> 488.02497 | V12: =SUM(V7:V11) -> 439.42132 | W12: =V12 -> 439.42132 | X12: =SUM(X7:X11) -> 373.37309 | Y12: =SUM(Y7:Y11) -> 350.72204 | Z12: =SUM(Z7:Z11) -> 301.68189 | AA12: =SUM(AA7:AA11) -> 356.10173 | AB12: =AA12 -> 356.10173 | AC12: =SUM(AC7:AC11) -> 270.21413 | AD12: =SUM(AD7:AD11) -> 671.366 | AE12: =SUM(AE7:AE11) -> 679.412 | AF12: =SUM(AF7:AF11) -> 667.603 | AG12: =AF12 -> 667.603 | AH12: =SUM(AH7:AH11) -> 573.97 | AI12: =SUM(AI7:AI11) -> 644.201 | AJ12: =SUM(AJ7:AJ11) -> 1146.511 | AK12: =SUM(AK7:AK11) -> 1167.175 | AL12: =AK12 -> 1167.175 | AM12: =SUM(AM7:AM11) -> 1138.4355 | AN12: =SUM(AN7:AN11) -> 1158.6682 | AO12: =SUM(AO7:AO11) -> 1112.9192 | AP12: =SUM(AP7:AP11) -> 1101.2418 | AQ12: =AP12 -> 1101.2418
C13: PP&E | D13: 20.596058 | E13: 23.187417 | F13: 25.607426 | G13: 36.065028 | H13: =G13 -> 36.065028 | I13: 34.408 | J13: 36.98096 | K13: 36.86 | L13: 38.435 | M13: =L13 -> 38.435 | N13: 36.3 | O13: 35.215 | P13: 35.999 | Q13: 35.395 | R13: =Q13 -> 35.395 | S13: 39.460915 | T13: 46.01009 | U13: 45.205557 | V13: 44.105478 | W13: =V13 -> 44.105478 | X13: 45.203759 | Y13: 50.451767 | Z13: 63.138071 | AA13: 61.680691 | AB13: =AA13 -> 61.680691 | AC13: 59.217122 | AD13: 60.539 | AE13: 59.362 | AF13: 58.056 | AG13: =AF13 -> 58.056 | AH13: 93.536 | AI13: 92.563 | AJ13: 90.71 | AK13: 89.156 | AL13: =AK13 -> 89.156 | AM13: =AK13-CF!AM9-CF!AM50 -> 61.656 | AN13: =AM13-CF!AN9-CF!AN50 -> 34.156 | AO13: =AN13-CF!AO9-CF!AO50 -> 6.656 | AP13: =AO13-CF!AP9-CF!AP50 -> -20.844 | AQ13: =AP13 -> -20.844
C14: Goodwill | AD14: 73.345 | AE14: 73.365 | AF14: 73.343 | AG14: =AF14 -> 73.343 | AH14: 325.774 | AI14: 325.793 | AJ14: 465.14 | AK14: 470.211 | AL14: =AK14 -> 470.211
C15: Warrant asset, less current portion | AD15: 1.5 | AE15: 0 | AF15: 0 | AG15: =AF15 -> 0 | AH15: 0 | AI15: 0 | AJ15: 0 | AK15: 0 | AL15: =AK15 -> 0
C16: Intangible assets, net | AD16: 16.252 | AE16: 14.289 | AF16: 11.716 | AG16: =AF16 -> 11.716 | AH16: 399.544 | AI16: 387.564 | AJ16: 372.876 | AK16: 355.253 | AL16: =AK16 -> 355.253
C17: Investments and other assets | D17: 27.056283 | E17: 25.422761 | F17: 28.424601 | G17: 57.9018 | H17: =G17 -> 57.9018 | I17: 68.945168 | J17: 66.463479 | K17: 64.407 | L17: 62.973 | M17: =L17 -> 62.973 | N17: 59.976 | O17: 108.826 | P17: 62.002 | Q17: 95.05 | R17: =Q17 -> 95.05 | S17: 149.50383 | T17: 145.34536 | U17: 139.73293 | V17: 147.83799 | W17: =V17 -> 147.83799 | X17: 150.52989 | Y17: 144.86559 | Z17: 139.24962 | AA17: 146.26981 | AB17: =AA17 -> 146.26981 | AC17: 139.84196 | AD17: 7.677 | AE17: =8.692+103.699 -> 112.391 | AF17: =8.305+91.45 -> 99.755 | AG17: =AF17 -> 99.755 | AH17: =14.811+94.153 -> 108.964 | AI17: =16.669+95.718 -> 112.387 | AJ17: =20.948+94.367 -> 115.315 | AK17: =86.557+21.111 -> 107.668 | AL17: =AK17 -> 107.668 | AM17: =AM58*IS!AM15 -> 189.72687 | AN17: =AN58*IS!AN15 -> 177.74205 | AO17: =AO58*IS!AO15 -> 145.30803 | AP17: =AP58*IS!AP15 -> 107.41521 | AQ17: =AP17 -> 107.41521
C18: Warrant contract asset, less current portion | AD18: 19.077 | AE18: 17.866 | AF18: 0 | AH18: 0 | AI18: 22.465 | AJ18: 19.34 | AK18: 16.215 | AL18: =AK18 -> 16.215
C19: Operating lease right-of-use assets | AD19: 13.994 | AE19: 14.141 | AF19: 14.762 | AH19: 39.626 | AI19: 38.651 | AJ19: 66.901 | AK19: 64.496 | AL19: =AK19 -> 64.496
C20: Restricted cash | AD20: 0.861 | AE20: 0.872 | AF20: 0.881 | AH20: 1.723 | AI20: 1.741 | AJ20: 4.631 | AK20: 4.664 | AL20: =AK20 -> 4.664
C21: Acquisition | D21: 0 | E21: 0 | F21: 0 | G21: 0 | H21: =G21 -> 0 | I21: 0 | J21: 0 | K21: 0 | L21: 0 | M21: =L21 -> 0 | N21: 0 | O21: 0 | P21: 0 | Q21: 0 | R21: =Q21 -> 0 | S21: 0 | T21: 0 | U21: 0 | V21: 0 | W21: =V21 -> 0 | X21: 0 | Y21: 0 | Z21: 0 | AA21: 0 | AB21: =AA21 -> 0 | AC21: 0 | AD21: 0 | AE21: 0 | AF21: 0 | AG21: =AF21 -> 0 | AH21: 0 | AI21: 0 | AJ21: 0 | AK21: 0 | AL21: =AK21 -> 0 | AM21: =AM59*IS!AM15 -> 0 | AN21: =AN59*IS!AN15 -> 0 | AO21: =AO59*IS!AO15 -> 0 | AP21: =AP59*IS!AP15 -> 0 | AQ21: =AP21 -> 0
B22: Total Assets | D22: =SUM(D12:D21) -> 231.9554 | E22: =SUM(E12:E21) -> 398.94587 | F22: =SUM(F12:F21) -> 378.76407 | G22: =SUM(G12:G21) -> 370.17123 | H22: =G22 -> 370.17123 | I22: =SUM(I12:I21) -> 407.63049 | J22: =SUM(J12:J21) -> 693.86082 | K22: =SUM(K12:K21) -> 662.70534 | L22: =SUM(L12:L21) -> 751.918 | M22: =L22 -> 751.918 | N22: =SUM(N12:N21) -> 677.137 | O22: =SUM(O12:O21) -> 604.186 | P22: =SUM(P12:P21) -> 551.347 | Q22: =SUM(Q12:Q21) -> 531.354 | R22: =Q22 -> 531.354 | S22: =SUM(S12:S21) -> 484.45838 | T22: =SUM(T12:T21) -> 505.80884 | U22: =SUM(U12:U21) -> 672.96346 | V22: =SUM(V12:V21) -> 631.36479 | W22: =V22 -> 631.36479 | X22: =SUM(X12:X21) -> 569.10673 | Y22: =SUM(Y12:Y21) -> 546.0394 | Z22: =SUM(Z12:Z21) -> 504.06958 | AA22: =SUM(AA12:AA21) -> 564.05223 | AB22: =AA22 -> 564.05223 | AC22: =SUM(AC12:AC21) -> 469.27321 | AD22: =SUM(AD12:AD21) -> 864.611 | AE22: =SUM(AE12:AE21) -> 971.698 | AF22: =SUM(AF12:AF21) -> 926.116 | AG22: =AF22 -> 926.116 | AH22: =SUM(AH12:AH21) -> 1543.137 | AI22: =SUM(AI12:AI21) -> 1625.365 | AJ22: =SUM(AJ12:AJ21) -> 2281.424 | AK22: =SUM(AK12:AK21) -> 2274.838 | AL22: =AK22 -> 2274.838 | AM22: =SUM(AM12:AM21) -> 1389.8183 | AN22: =SUM(AN12:AN21) -> 1370.5663 | AO22: =SUM(AO12:AO21) -> 1264.8832 | AP22: =SUM(AP12:AP21) -> 1187.813 | AQ22: =AP22 -> 1187.813
R23: =Q23 -> 0 | W23: =V23 -> 0 | AB23: =AA23 -> 0 | AG23: =AF23 -> 0 | AL23: =AK23 -> 0 | AQ23: =AP23 -> 0
B24: Liabilities: | R24: =Q24 -> 0 | W24: =V24 -> 0 | AB24: =AA24 -> 0 | AG24: =AF24 -> 0 | AL24: =AK24 -> 0 | AQ24: =AP24 -> 0
C25: Accounts payable/ accrued expenses | D25: 13.352296 | E25: 15.746838 | F25: 14.896405 | G25: 21.365342 | H25: =G25 -> 21.365342 | I25: 26.627932 | J25: 24.180251 | K25: 52.010728 | L25: 73.749 | M25: =L25 -> 73.749 | N25: 63.233 | O25: 59.033 | P25: 72.502 | Q25: 74.447 | R25: =Q25 -> 74.447 | S25: 82.930425 | T25: 85.8265 | U25: 91.386372 | V25: 106.19237 | W25: =V25 -> 106.19237 | X25: 105.82693 | Y25: 115.28837 | Z25: 128.23074 | AA25: 132.42166 | AB25: =AA25 -> 132.42166 | AC25: 117.42412 | AD25: =28.646+85.185 -> 113.831 | AE25: =49.027+101.985 -> 151.012 | AF25: =53.804+130.407 -> 184.211 | AG25: =AF25 -> 184.211 | AH25: =88.732+129.238 -> 217.97 | AI25: =79.323+165.903+25 -> 270.226 | AJ25: =59.553+160.773 -> 220.326 | AK25: =81.994+155.37 -> 237.364 | AL25: =AK25 -> 237.364 | AM25: =IS!AM15*BS!AM62 -> 241.47056 | AN25: =IS!AN15*BS!AN62 -> 256.73852 | AO25: =IS!AO15*BS!AO62 -> 249.09947 | AP25: =IS!AP15*BS!AP62 -> 247.22893 | AQ25: =AP25 -> 247.22893
C26: Deferred revenue | D26: 1.9963714 | E26: 5.2181112 | F26: 4.8041793 | G26: 5.5704542 | H26: =G26 -> 5.5704542 | I26: 4.3301905 | J26: 4.5862765 | K26: 4.1793549 | L26: 6.965 | M26: =L26 -> 6.965 | N26: 5.845 | O26: 5.917 | P26: 15.416 | Q26: 16.454 | R26: =Q26 -> 16.454 | S26: 17.344228 | T26: 12.146248 | U26: 82.148637 | V26: 85.27815 | W26: =V26 -> 85.27815 | X26: 82.208317 | Y26: 66.065964 | Z26: 69.396068 | AA26: 81.627424 | AB26: =AA26 -> 81.627424 | AC26: 65.655672 | AD26: 50.905 | AE26: =67.604+15.955 -> 83.559 | AF26: 75.981 | AG26: =AF26 -> 75.981 | AH26: 73.431 | AI26: 100.477 | AJ26: 84.719 | AK26: 92.673 | AL26: =AK26 -> 92.673 | AM26: =IS!AM15*BS!AM63 -> 155.23108 | AN26: =IS!AN15*BS!AN63 -> 157.99294 | AO26: =IS!AO15*BS!AO63 -> 145.30803 | AP26: =IS!AP15*BS!AP63 -> 139.68326 | AQ26: =AP26 -> 139.68326
C27: Deferred other income | AH27: 15.955 | AI27: 15.955 | AJ27: 15.955 | AK27: 15.955 | AL27: =AK27 -> 15.955
C28: Other current liabilities | AD28: 7.273 | AE28: =9.913 -> 9.913 | AF28: 6.964 | AH28: 18.194 | AI28: 16.554 | AJ28: 11.819 | AK28: 8.68 | AL28: =AK28 -> 8.68
C29: Operating lease liabilities | AD29: 5.828 | AE29: =5.894 -> 5.894 | AF29: 6.459 | AH29: 9.42 | AI29: 9.381 | AJ29: 12.417 | AK29: 13.355 | AL29: =AK29 -> 13.355
C30: Accrued data licensing fees | AD30: 3.727 | AE30: =2.242 -> 2.242 | AF30: 1.5 | AH30: 1.5 | AI30: 5.567 | AJ30: 4.792 | AK30: 4.361 | AL30: =AK30 -> 4.361
C31: Accrued dividends | AD31: 0 | AE31: 0 | AF31: 0 | AH31: 0 | AI31: 0 | AJ31: 0 | AK31: 0 | AL31: =AK31 -> 0
C32: Operating lease liabilities, less current portion | AD32: 27.238 | AE32: 26.664 | AF32: 26.199 | AH32: 47.567 | AI32: 45.866 | AJ32: 77.723 | AK32: 74.272 | AL32: =AK32 -> 74.272
C33: Convertible promissory note | D33: 0 | E33: 0 | F33: 0 | G33: 0 | H33: =G33 -> 0 | I33: 0 | J33: 330 | K33: 330 | L33: 250 | M33: =L33 -> 250 | N33: 249.058 | O33: 246.581 | P33: 243.42 | Q33: 238.236 | R33: =Q33 -> 238.236 | S33: 235.05403 | T33: 231.7628 | U33: 228.01513 | V33: 221.09384 | W33: =V33 -> 221.09384 | X33: 216.03447 | Y33: 207.16753 | Z33: 198.87366 | AA33: 193.12379 | AB33: =AA33 -> 193.12379 | AC33: 186.73266 | AD33: 180.648 | AE33: 174.46 | AF33: 168.192 | AG33: =AF33 -> 168.192 | AH33: 233.62 | AI33: 226.342 | AJ33: 217.959 | AK33: 208.672 | AL33: =AK33 -> 208.672 | AM33: =AK33-8.9 -> 199.772 | AN33: =AM33-8.9 -> 190.872 | AO33: =AN33-8.9 -> 181.972 | AP33: =AO33-8.9 -> 173.072 | AQ33: =AP33 -> 173.072
C34: Warrant liability | AD34: 33.6 | AE34: 76.9 | AF34: 0 | AH34: 0 | AI34: 0 | AJ34: 0 | AK34: 0 | AL34: =AK34 -> 0
C35: Interest payable | AD35: 62.608 | AE35: 66.529 | AF35: 70.45 | AH35: 1.47 | AI35: 5.084 | AJ35: 8.739 | AK35: 12.393 | AL35: =AK35 -> 12.393
C36: Revolving credit facility | AH36: 100 | AI36: 100 | AJ36: 100 | AK36: 100 | AL36: =AK36 -> 100
C37: Term loan debt | D37: 0 | E37: 0 | F37: 0 | G37: 0 | H37: =G37 -> 0 | I37: 0 | J37: 0 | K37: 0 | L37: 0 | M37: =L37 -> 0 | N37: 0 | O37: 0 | P37: 0 | Q37: 0 | R37: =Q37 -> 0 | S37: 0 | T37: -0.015 | U37: 168.07475 | V37: 168.45179 | W37: =V37 -> 168.45179 | X37: 168.79806 | Y37: 218.24333 | Z37: 220.4845 | AA37: 256.54135 | AB37: =AA37 -> 256.54135 | AC37: 259.1965 | AD37: 261.853 | AE37: 264.527 | AF37: 267.244 | AG37: =AF37 -> 267.244 | AH37: 467.144 | AI37: 471.663 | AJ37: 200.859 | AK37: 202.753 | AL37: =AK37 -> 202.753 | AM37: =AK37 -> 202.753 | AN37: =AM37 -> 202.753 | AO37: =AN37 -> 202.753 | AP37: =AO37 -> 202.753 | AQ37: =AP37 -> 202.753
C38: Convertible senior notes | AJ38: 726.863 | AK38: 728.078 | AL38: =AK38 -> 728.078
C39: Deferred revenue, less current portion | AD39: 2.059 | AE39: =12.976+27.921 -> 40.897 | AF39: =6.71+23.932+15.955 -> 46.597 | AH39: 1.058 | AI39: 23.225 | AJ39: 20.691 | AK39: 20.379 | AL39: =AK39 -> 20.379
C40: Deferred other income, less current portion | AH40: 19.944 | AI40: 15.955 | AJ40: 11.966 | AK40: 7.977 | AL40: =AK40 -> 7.977
C41: Other long-term liabilities | D41: 45.750416 | E41: 50.383916 | F41: 61.395561 | G41: 81.378557 | H41: =G41 -> 81.378557 | I41: 63.527681 | J41: 59.356797 | K41: 59.695985 | L41: 75.032 | M41: =L41 -> 75.032 | N41: 70.349 | O41: 71.699 | P41: 68.351 | Q41: 111.417 | R41: =Q41 -> 111.417 | S41: 140.74676 | T41: 150.56595 | U41: 147.71515 | V41: 153.23251 | W41: =V41 -> 153.23251 | X41: 154.47764 | Y41: 156.4313 | Z41: 160.14372 | AA41: 176.9576 | AB41: =AA41 -> 176.9576 | AC41: 179.88672 | AD41: 16.79 | AE41: 15.403 | AF41: 15.98 | AG41: =AF41 -> 15.98 | AH41: 9.67 | AI41: 9.508 | AJ41: 58.772 | AK41: 56.6 | AL41: =AK41 -> 56.6 | AM41: =IS!AM15*BS!AM66 -> 310.46215 | AN41: =IS!AN15*BS!AN66 -> 315.98587 | AO41: =IS!AO15*BS!AO66 -> 290.61605 | AP41: =IS!AP15*BS!AP66 -> 249.44682 | AQ41: =AP41 -> 249.44682
B42: Total Liabilities | D42: =SUM(D25:D41) -> 61.099084 | E42: =SUM(E25:E41) -> 71.348865 | F42: =SUM(F25:F41) -> 81.096145 | G42: =SUM(G25:G41) -> 108.31435 | H42: =G42 -> 108.31435 | I42: =SUM(I25:I41) -> 94.485804 | J42: =SUM(J25:J41) -> 418.12332 | K42: =SUM(K25:K41) -> 445.88607 | L42: =SUM(L25:L41) -> 405.746 | M42: =L42 -> 405.746 | N42: =SUM(N25:N41) -> 388.485 | O42: =SUM(O25:O41) -> 383.23 | P42: =SUM(P25:P41) -> 399.689 | Q42: =SUM(Q25:Q41) -> 440.554 | R42: =Q42 -> 440.554 | S42: =SUM(S25:S41) -> 476.07545 | T42: =SUM(T25:T41) -> 480.28649 | U42: =SUM(U25:U41) -> 717.34004 | V42: =SUM(V25:V41) -> 734.24866 | W42: =V42 -> 734.24866 | X42: =SUM(X25:X41) -> 727.34542 | Y42: =SUM(Y25:Y41) -> 763.19649 | Z42: =SUM(Z25:Z41) -> 777.12869 | AA42: =SUM(AA25:AA41) -> 840.67183 | AB42: =AA42 -> 840.67183 | AC42: =SUM(AC25:AC41) -> 808.89567 | AD42: =SUM(AD25:AD41) -> 766.36 | AE42: =SUM(AE25:AE41) -> 918 | AF42: =SUM(AF25:AF41) -> 869.777 | AG42: =AF42 -> 869.777 | AH42: =SUM(AH25:AH41) -> 1216.943 | AI42: =SUM(AI25:AI41) -> 1315.803 | AJ42: =SUM(AJ25:AJ41) -> 1773.6 | AK42: =SUM(AK25:AK41) -> 1783.512 | AL42: =AK42 -> 1783.512 | AM42: =SUM(AM25:AM41) -> 1109.6888 | AN42: =SUM(AN25:AN41) -> 1124.3423 | AO42: =SUM(AO25:AO41) -> 1069.7486 | AP42: =SUM(AP25:AP41) -> 1012.184 | AQ42: =AP42 -> 1012.184
M43: =L43 -> 0 | R43: =Q43 -> 0 | W43: =V43 -> 0 | AB43: =AA43 -> 0 | AG43: =AF43 -> 0 | AL43: =AK43 -> 0 | AQ43: =AP43 -> 0
B44: Shareholders Equity: | M44: =L44 -> 0 | R44: =Q44 -> 0 | W44: =V44 -> 0 | AB44: =AA44 -> 0 | AG44: =AF44 -> 0 | AL44: =AK44 -> 0 | AQ44: =AP44 -> 0
C45: Total Shareholder Equity | D45: =D22-D42 -> 170.85632 | E45: =E22-E42 -> 327.597 | F45: =F22-F42 -> 297.66793 | G45: =G22-G42 -> 261.85688 | H45: =G45 -> 261.85688 | I45: =I22-I42 -> 313.14469 | J45: =J22-J42 -> 275.73749 | K45: =K22-K42 -> 216.81927 | L45: =L22-L42 -> 346.172 | M45: =L45 -> 346.172 | N45: =N22-N42 -> 288.652 | O45: =O22-O42 -> 220.956 | P45: =P22-P42 -> 151.658 | Q45: =Q22-Q42 -> 90.8 | R45: =Q45 -> 90.8 | S45: =S22-S42 -> 8.382935 | T45: =T22-T42 -> 25.522348 | U45: =U22-U42 -> -44.376585 | V45: =V22-V42 -> -102.88387 | W45: =V45 -> -102.88387 | X45: =X22-X42 -> -158.23869 | Y45: =Y22-Y42 -> -217.15709 | Z45: =Z22-Z42 -> -273.05911 | AA45: =AA22-AA42 -> -276.6196 | AB45: =AA45 -> -276.6196 | AC45: =AC22-AC42 -> -339.62246 | AD45: =AD22-AD42 -> 98.251 | AE45: =AE22-AE42 -> 53.698 | AF45: =AF22-AF42 -> 56.339 | AG45: =AF45 -> 56.339 | AH45: =AH22-AH42 -> 326.194 | AI45: =AI22-AI42 -> 309.562 | AJ45: =AJ22-AJ42 -> 507.824 | AK45: =AK22-AK42 -> 491.326 | AL45: =AK45 -> 491.326 | AM45: =AM22-AM42 -> 280.12954 | AN45: =AN22-AN42 -> 246.22394 | AO45: =AO22-AO42 -> 195.13469 | AP45: =AP22-AP42 -> 175.62904 | AQ45: =AP45 -> 175.62904
B46: Total Liabilities & Shareholders Equity | D46: =D45+D42 -> 231.9554 | E46: =E45+E42 -> 398.94587 | F46: =F45+F42 -> 378.76407 | G46: =G45+G42 -> 370.17123 | H46: =G46 -> 370.17123 | I46: =I45+I42 -> 407.63049 | J46: =J45+J42 -> 693.86082 | K46: =K45+K42 -> 662.70534 | L46: =L45+L42 -> 751.918 | M46: =L46 -> 751.918 | N46: =N45+N42 -> 677.137 | O46: =O45+O42 -> 604.186 | P46: =P45+P42 -> 551.347 | Q46: =Q45+Q42 -> 531.354 | R46: =Q46 -> 531.354 | S46: =S45+S42 -> 484.45838 | T46: =T45+T42 -> 505.80884 | U46: =U45+U42 -> 672.96346 | V46: =V45+V42 -> 631.36479 | W46: =V46 -> 631.36479 | X46: =X45+X42 -> 569.10673 | Y46: =Y45+Y42 -> 546.0394 | Z46: =Z45+Z42 -> 504.06958 | AA46: =AA45+AA42 -> 564.05223 | AB46: =AA46 -> 564.05223 | AC46: =AC45+AC42 -> 469.27321 | AD46: =AD45+AD42 -> 864.611 | AE46: =AE45+AE42 -> 971.698 | AF46: =AF45+AF42 -> 926.116 | AG46: =AF46 -> 926.116 | AH46: =AH45+AH42 -> 1543.137 | AI46: =AI45+AI42 -> 1625.365 | AJ46: =AJ45+AJ42 -> 2281.424 | AK46: =AK45+AK42 -> 2274.838 | AL46: =AK46 -> 2274.838 | AM46: =AM45+AM42 -> 1389.8183 | AN46: =AN45+AN42 -> 1370.5663 | AO46: =AO45+AO42 -> 1264.8832 | AP46: =AP45+AP42 -> 1187.813 | AQ46: =AP46 -> 1187.813
B48: check | D48: =D46=D22 -> TRUE | E48: =E46=E22 -> TRUE | F48: =F46=F22 -> TRUE | G48: =G46=G22 -> TRUE | I48: =I46=I22 -> TRUE | J48: =J46=J22 -> TRUE | K48: =K46=K22 -> TRUE | L48: =L46=L22 -> TRUE | N48: =N46=N22 -> TRUE | O48: =O46=O22 -> TRUE | P48: =P46=P22 -> TRUE | Q48: =Q46=Q22 -> TRUE | S48: =S46=S22 -> TRUE | T48: =T46=T22 -> TRUE | U48: =U46=U22 -> TRUE | V48: =V46=V22 -> TRUE | X48: =X46=X22 -> TRUE | Y48: =Y46=Y22 -> TRUE | Z48: =Z46=Z22 -> TRUE | AA48: =AA46=AA22 -> TRUE | AC48: =AC46=AC22 -> TRUE | AD48: =AD46=AD22 -> TRUE | AE48: =AE46=AE22 -> TRUE | AF48: =AF46=AF22 -> TRUE | AH48: =AH46=AH22 -> TRUE | AI48: =AI46=AI22 -> TRUE | AJ48: =AJ46=AJ22 -> TRUE | AK48: =AK46=AK22 -> TRUE | AM48: =AM46=AM22 -> TRUE | AN48: =AN46=AN22 -> TRUE | AO48: =AO46=AO22 -> TRUE | AP48: =AP46=AP22 -> TRUE
C50: DSO | D50: =((D9+B9)/2)/IS!D15*91 -> 96.011593 | E50: =((E9+D9)/2)/IS!E15*91 -> 158.75902 | F50: =((F9+E9)/2)/IS!F15*91 -> 127.12365 | G50: =((G9+F9)/2)/IS!G15*91 -> 98.78831 | I50: =((I9+G9)/2)/IS!I15*91 -> 168.72571 | J50: =((J9+I9)/2)/IS!J15*91 -> 149.82302 | K50: =((K9+J9)/2)/IS!K15*91 -> 85.529693 | L50: =((L9+K9)/2)/IS!L15*91 -> 73.11917 | N50: =((N9+L9)/2)/IS!N15*91 -> 114.82721 | O50: =((O9+N9)/2)/IS!O15*91 -> 64.199887 | P50: =((P9+O9)/2)/IS!P15*91 -> 82.316608 | Q50: =((Q9+P9)/2)/IS!Q15*91 -> 114.91941 | S50: =((S9+Q9)/2)/IS!S15*91 -> 149.25554 | T50: =((T9+S9)/2)/IS!T15*91 -> 120.76004 | U50: =((U9+T9)/2)/IS!U15*91 -> 102.67152 | V50: =((V9+U9)/2)/IS!V15*91 -> 95.225596 | X50: =((X9+V9)/2)/IS!X15*91 -> 93.267905 | Y50: =((Y9+X9)/2)/IS!Y15*91 -> 83.795447 | Z50: =((Z9+Y9)/2)/IS!Z15*91 -> 87.389773 | AA50: =((AA9+Z9)/2)/IS!AA15*91 -> 83.131419 | AC50: =((AC9+AA9)/2)/IS!AC15*91 -> 85.239368 | AD50: =((AD9+AC9)/2)/IS!AD15*91 -> 80.091158 | AE50: =((AE9+AD9)/2)/IS!AE15*91 -> 81.670852 | AF50: =((AF9+AE9)/2)/IS!AF15*91 -> 81.147486 | AH50: =((AH9+AF9)/2)/IS!AH15*91 -> 86.406001 | AI50: =((AI9+AH9)/2)/IS!AI15*91 -> 87.845867 | AJ50: =((AJ9+AI9)/2)/IS!AJ15*91 -> 85.633901 | AK50: =((AK9+AJ9)/2)/IS!AK15*91 -> 83.99715 | AM50: =((AM9+AK9)/2)/IS!AM15*91 -> 82.785057 | AN50: =((AN9+AM9)/2)/IS!AN15*91 -> 65.914951 | AO50: =((AO9+AN9)/2)/IS!AO15*91 -> 62.041 | AP50: =((AP9+AO9)/2)/IS!AP15*91 -> 53.30483
C52: Deferred Revenues
B54: Drivers of Revenue % - Assets
C55: Accounts receivable/ pre-paid expenses | D55: =D9/IS!D15 -> 2.1101449 | E55: =E9/IS!E15 -> 1.9584373 | F55: =F9/IS!F15 -> 1.4393919 | G55: =G9/IS!G15 -> 1.3979305 | I55: =I9/IS!I15 -> 1.5250893 | J55: =J9/IS!J15 -> 1.7622667 | K55: =K9/IS!K15 -> 1.2483681 | L55: =L9/IS!L15 -> 0.9790326 | N55: =N9/IS!N15 -> 1.1153607 | O55: =O9/IS!O15 -> 0.14943767 | P55: =P9/IS!P15 -> 1.632542 | Q55: =Q9/IS!Q15 -> 1.357736 | S55: =S9/IS!S15 -> 1.6419529 | T55: =T9/IS!T15 -> 1.3009316 | U55: =U9/IS!U15 -> 1.1357801 | V55: =V9/IS!V15 -> 1.1270196 | X55: =X9/IS!X15 -> 1.0690101 | Y55: =Y9/IS!Y15 -> 0.9082109 | Z55: =Z9/IS!Z15 -> 1.0365458 | AA55: =AA9/IS!AA15 -> 0.87238056 | AC55: =AC9/IS!AC15 -> 0.98982376 | AD55: =AD9/IS!AD15 -> 0.890588 | AE55: =AE9/IS!AE15 -> 0.97801347 | AF55: =AF9/IS!AF15 -> 0.90170421 | AH55: =AH9/IS!AH15 -> 1.1914545 | AI55: =AI9/IS!AI15 -> 0.96225785 | AJ55: =AJ9/IS!AJ15 -> 0.97615543 | AK55: =AK9/IS!AK15 -> 0.95767284 | AM55: 0.8 | AN55: 0.75 | AO55: 0.65 | AP55: 0.551
C56: Inventory | D56: =D11/IS!D15 -> 0.71216618 | E56: =E11/IS!E15 -> 0.64268541 | F56: =F11/IS!F15 -> 0.42432616 | G56: =G11/IS!G15 -> 0.29059236 | I56: =I11/IS!I15 -> 0.45881511 | J56: =J11/IS!J15 -> 1.3986398 | K56: =K11/IS!K15 -> 0.64260414 | L56: =L11/IS!L15 -> 0.37239867 | N56: =N11/IS!N15 -> 0.4383394 | O56: =O11/IS!O15 -> 0.44694173 | P56: =P11/IS!P15 -> 0.41942772 | Q56: =Q11/IS!Q15 -> 0.31248322 | S56: =S11/IS!S15 -> 0.28475126 | T56: =T11/IS!T15 -> 0.28007035 | U56: =U11/IS!U15 -> 0.24574262 | V56: =V11/IS!V15 -> 0.22142993 | X56: =X11/IS!X15 -> 0.21804632 | Y56: =Y11/IS!Y15 -> 0.20679225 | Z56: =Z11/IS!Z15 -> 0.19964613 | AA56: =AA11/IS!AA15 -> 0.19530916 | AC56: =AC11/IS!AC15 -> 0.20661898 | AD56: =AD11/IS!AD15 -> 0.19696449 | AE56: =AE11/IS!AE15 -> 0.19973581 | AF56: =AF11/IS!AF15 -> 0.19127965 | AH56: =AH11/IS!AH15 -> 0.19740984 | AI56: =AI11/IS!AI15 -> 0.15128641 | AJ56: =AJ11/IS!AJ15 -> 0.16449735 | AK56: =AK11/IS!AK15 -> 0.14085635 | AM56: 0.145 | AN56: 0.135 | AO56: 0.125 | AP56: 0.1205
C57: PP&E | D57: =D13/IS!D15 -> 2.6822089 | E57: =E13/IS!E15 -> 2.19058 | F57: =F13/IS!F15 -> 1.67322 | G57: =G13/IS!G15 -> 1.2659288 | I57: =I13/IS!I15 -> 1.8861839 | J57: =J13/IS!J15 -> 2.0344834 | K57: =K13/IS!K15 -> 0.72655405 | L57: =L13/IS!L15 -> 0.38110453 | N57: =N13/IS!N15 -> 0.51775739 | O57: =O13/IS!O15 -> 0.56811483 | P57: =P13/IS!P15 -> 0.6863796 | Q57: =Q13/IS!Q15 -> 0.48281576 | S57: =S13/IS!S15 -> 0.64954348 | T57: =T13/IS!T15 -> 0.62412938 | U57: =U13/IS!U15 -> 0.52827801 | V57: =V13/IS!V15 -> 0.43830755 | X57: =X13/IS!X15 -> 0.3909534 | Y57: =Y13/IS!Y15 -> 0.38100864 | Z57: =Z13/IS!Z15 -> 0.464161 | AA57: =AA13/IS!AA15 -> 0.41763564 | AC57: =AC13/IS!AC15 -> 0.40609728 | AD57: =AD13/IS!AD15 -> 0.36476089 | AE57: =AE13/IS!AE15 -> 0.32809555 | AF57: =AF13/IS!AF15 -> 0.28929639 | AH57: =AH13/IS!AH15 -> 0.36575075 | AI57: =AI13/IS!AI15 -> 0.29419168 | AJ57: =AJ13/IS!AJ15 -> 0.27141942 | AK57: =AK13/IS!AK15 -> 0.24279229 | AM57: =AM13/IS!AM15 -> 0.17873483 | AN57: =AN13/IS!AN15 -> 0.086474751 | AO57: =AO13/IS!AO15 -> 0.016032149 | AP57: =AP13/IS!AP15 -> -0.047930531
C58: Other assets | D58: =D17/IS!D15 -> 3.523519 | E58: =E17/IS!E15 -> 2.4017591 | F58: =F17/IS!F15 -> 1.8572976 | G58: =G17/IS!G15 -> 2.0324276 | I58: =I17/IS!I15 -> 3.7794485 | J58: =J17/IS!J15 -> 3.6564449 | K58: =K17/IS!K15 -> 1.2695379 | L58: =L17/IS!L15 -> 0.62441253 | N58: =N17/IS!N15 -> 0.85545502 | O58: =O17/IS!O15 -> 1.7556628 | P58: =P17/IS!P15 -> 1.1821692 | Q58: =Q17/IS!Q15 -> 1.2965571 | S58: =S17/IS!S15 -> 2.4608968 | T58: =T17/IS!T15 -> 1.9716178 | U58: =U17/IS!U15 -> 1.6329372 | V58: =V17/IS!V15 -> 1.4691714 | X58: =X17/IS!X15 -> 1.3018867 | Y58: =Y17/IS!Y15 -> 1.094016 | Z58: =Z17/IS!Z15 -> 1.0236968 | AA58: =AA17/IS!AA15 -> 0.99038266 | AC58: =AC17/IS!AC15 -> 0.95900373 | AD58: =AD17/IS!AD15 -> 0.046255626 | AE58: =AE17/IS!AE15 -> 0.62118842 | AF58: =AF17/IS!AF15 -> 0.49708491 | AH58: =AH17/IS!AH15 -> 0.42607835 | AI58: =AI17/IS!AI15 -> 0.35719802 | AJ58: =AJ17/IS!AJ15 -> 0.34504168 | AK58: =AK17/IS!AK15 -> 0.29320472 | AM58: 0.55 | AN58: 0.45 | AO58: 0.35 | AP58: 0.247
C59: Acquisition | D59: =D21/IS!D15 -> 0 | E59: =E21/IS!E15 -> 0 | F59: =F21/IS!F15 -> 0 | G59: =G21/IS!G15 -> 0 | I59: =I21/IS!I15 -> 0 | J59: =J21/IS!J15 -> 0 | K59: =K21/IS!K15 -> 0 | L59: =L21/IS!L15 -> 0 | N59: =N21/IS!N15 -> 0 | O59: =O21/IS!O15 -> 0 | P59: =P21/IS!P15 -> 0 | Q59: =Q21/IS!Q15 -> 0 | S59: =S21/IS!S15 -> 0 | T59: =T21/IS!T15 -> 0 | U59: =U21/IS!U15 -> 0 | V59: =V21/IS!V15 -> 0 | X59: =X21/IS!X15 -> 0 | Y59: =Y21/IS!Y15 -> 0 | Z59: =Z21/IS!Z15 -> 0 | AA59: =AA21/IS!AA15 -> 0 | AC59: =AC21/IS!AC15 -> 0 | AD59: =AD21/IS!AD15 -> 0 | AE59: =AE21/IS!AE15 -> 0 | AF59: =AF21/IS!AF15 -> 0 | AH59: =AH21/IS!AH15 -> 0 | AI59: =AI21/IS!AI15 -> 0 | AJ59: =AJ21/IS!AJ15 -> 0 | AK59: =AK21/IS!AK15 -> 0 | AM59: 0 | AN59: 0 | AO59: 0 | AP59: 0
B61: Drivers of Revenue % - Liabilities
C62: Accounts payable/ accrued expenses | D62: =D25/IS!D15 -> 1.7388593 | E62: =E25/IS!E15 -> 1.4876477 | F62: =F25/IS!F15 -> 0.97334899 | G62: =G25/IS!G15 -> 0.74995099 | I62: =I25/IS!I15 -> 1.4596947 | J62: =J25/IS!J15 -> 1.3302607 | K62: =K25/IS!K15 -> 1.0251928 | L62: =L25/IS!L15 -> 0.7312626 | N62: =N25/IS!N15 -> 0.90191055 | O62: =O25/IS!O15 -> 0.95236469 | P62: =P25/IS!P15 -> 1.3823688 | Q62: =Q25/IS!Q15 -> 1.0155159 | S62: =S25/IS!S15 -> 1.3650702 | T62: =T25/IS!T15 -> 1.1642412 | U62: =U25/IS!U15 -> 1.067953 | V62: =V25/IS!V15 -> 1.0553092 | X62: =X25/IS!X15 -> 0.91526451 | Y62: =Y25/IS!Y15 -> 0.87065067 | Z62: =Z25/IS!Z15 -> 0.94269128 | AA62: =AA25/IS!AA15 -> 0.8966178 | AC62: =AC25/IS!AC15 -> 0.80526736 | AD62: =AD25/IS!AD15 -> 0.685857 | AE62: =AE25/IS!AE15 -> 0.83464785 | AF62: =AF25/IS!AF15 -> 0.91793402 | AH62: =AH25/IS!AH15 -> 0.85232094 | AI62: =AI25/IS!AI15 -> 0.8588555 | AJ62: =AJ25/IS!AJ15 -> 0.65925208 | AK62: =AK25/IS!AK15 -> 0.64639676 | AM62: 0.7 | AN62: 0.65 | AO62: 0.6 | AP62: 0.5685
C63: Deferred revenue | D63: =D26/IS!D15 -> 0.25998592 | E63: =E26/IS!E15 -> 0.49296952 | F63: =F26/IS!F15 -> 0.31391085 | G63: =G26/IS!G15 -> 0.19553011 | I63: =I26/IS!I15 -> 0.23737316 | J63: =J26/IS!J15 -> 0.25231101 | K63: =K26/IS!K15 -> 0.082380012 | L63: =L26/IS!L15 -> 0.069061872 | N63: =N26/IS!N15 -> 0.083368924 | O63: =O26/IS!O15 -> 0.095457488 | P63: =P26/IS!P15 -> 0.29393116 | Q63: =Q26/IS!Q15 -> 0.22444556 | S63: =S26/IS!S15 -> 0.28549338 | T63: =T26/IS!T15 -> 0.16476452 | U63: =U26/IS!U15 -> 0.95999965 | V63: =V26/IS!V15 -> 0.8474697 | X63: =X26/IS!X15 -> 0.71099443 | Y63: =Y26/IS!Y15 -> 0.49892609 | Z63: =Z26/IS!Z15 -> 0.51016682 | AA63: =AA26/IS!AA15 -> 0.55269357 | AC63: =AC26/IS!AC15 -> 0.45025136 | AD63: =AD26/IS!AD15 -> 0.3067139 | AE63: =AE26/IS!AE15 -> 0.46183309 | AF63: =AF26/IS!AF15 -> 0.3786177 | AH63: =AH26/IS!AH15 -> 0.28713483 | AI63: =AI26/IS!AI15 -> 0.31934464 | AJ63: =AJ26/IS!AJ15 -> 0.25349335 | AK63: =AK26/IS!AK15 -> 0.25236989 | AM63: 0.45 | AN63: 0.4 | AO63: 0.35 | AP63: 0.3212
C64: Convertible promissory note | D64: =D33/IS!D15 -> 0 | E64: =E33/IS!E15 -> 0 | F64: =F33/IS!F15 -> 0 | G64: =G33/IS!G15 -> 0 | I64: =I33/IS!I15 -> 0 | J64: =J33/IS!J15 -> 18.154735 | K64: =K33/IS!K15 -> 6.504689 | L64: =L33/IS!L15 -> 2.4788899 | N64: =N33/IS!N15 -> 3.5523862 | O64: =O33/IS!O15 -> 3.9780299 | P64: =P33/IS!P15 -> 4.641199 | Q64: =Q33/IS!Q15 -> 3.2497273 | S64: =S33/IS!S15 -> 3.8690896 | T64: =T33/IS!T15 -> 3.143875 | U64: =U33/IS!U15 -> 2.6646145 | V64: =V33/IS!V15 -> 2.197167 | X64: =X33/IS!X15 -> 1.8684157 | Y64: =Y33/IS!Y15 -> 1.5645164 | Z64: =Z33/IS!Z15 -> 1.4620243 | AA64: =AA33/IS!AA15 -> 1.3076277 | AC64: =AC33/IS!AC15 -> 1.2805692 | AD64: =AD33/IS!AD15 -> 1.0884442 | AE64: =AE33/IS!AE15 -> 0.96424564 | AF64: =AF33/IS!AF15 -> 0.83811042 | AH64: =AH33/IS!AH15 -> 0.91351662 | AI64: =AI33/IS!AI15 -> 0.7193796 | AJ64: =AJ33/IS!AJ15 -> 0.65216962 | AK64: =AK33/IS!AK15 -> 0.56826184 | AM64: =AM33/IS!AM15 -> 0.57911986 | AN64: =AN33/IS!AN15 -> 0.48324185 | AO64: =AO33/IS!AO15 -> 0.43831164 | AP64: =AP33/IS!AP15 -> 0.39797701
C65: Term loan debt | D65: =D37/IS!D15 -> 0 | E65: =E37/IS!E15 -> 0 | F65: =F37/IS!F15 -> 0 | G65: =G37/IS!G15 -> 0 | I65: =I37/IS!I15 -> 0 | J65: =J37/IS!J15 -> 0 | K65: =K37/IS!K15 -> 0 | L65: =L37/IS!L15 -> 0 | N65: =N37/IS!N15 -> 0 | O65: =O37/IS!O15 -> 0 | P65: =P37/IS!P15 -> 0 | Q65: =Q37/IS!Q15 -> 0 | S65: =S37/IS!S15 -> 0 | T65: =T37/IS!T15 -> -0.00020347582 | U65: =U37/IS!U15 -> 1.9641434 | V65: =V37/IS!V15 -> 1.6740254 | X65: =X37/IS!X15 -> 1.4598824 | Y65: =Y37/IS!Y15 -> 1.6481602 | Z65: =Z37/IS!Z15 -> 1.620897 | AA65: =AA37/IS!AA15 -> 1.7370235 | AC65: =AC37/IS!AC15 -> 1.7775094 | AD65: =AD37/IS!AD15 -> 1.5777223 | AE65: =AE37/IS!AE15 -> 1.4620486 | AF65: =AF37/IS!AF15 -> 1.3316922 | AH65: =AH37/IS!AH15 -> 1.8266579 | AI65: =AI37/IS!AI15 -> 1.4990799 | AJ65: =AJ37/IS!AJ15 -> 0.60100357 | AK65: =AK37/IS!AK15 -> 0.55214305 | AM65: =AM37/IS!AM15 -> 0.5877615 | AN65: =AN37/IS!AN15 -> 0.51332168 | AO65: =AO37/IS!AO15 -> 0.48836635 | AP65: =AP37/IS!AP15 -> 0.46622812
C66: Other liabilities | D66: =D41/IS!D15 -> 5.9580418 | E66: =E41/IS!E15 -> 4.759909 | F66: =F41/IS!F15 -> 4.0116597 | G66: =G41/IS!G15 -> 2.856492 | I66: =I41/IS!I15 -> 3.4824718 | J66: =J41/IS!J15 -> 3.2654754 | K66: =K41/IS!K15 -> 1.1766782 | L66: =L41/IS!L15 -> 0.74398426 | N66: =N41/IS!N15 -> 1.0034081 | O66: =O41/IS!O15 -> 1.1567021 | P66: =P41/IS!P15 -> 1.3032232 | Q66: =Q41/IS!Q15 -> 1.5198159 | S66: =S41/IS!S15 -> 2.3167517 | T66: =T41/IS!T15 -> 2.0424353 | U66: =U41/IS!U15 -> 1.7262185 | V66: =V41/IS!V15 -> 1.5227806 | X66: =X41/IS!X15 -> 1.3360296 | Y66: =Y41/IS!Y15 -> 1.1813595 | Z66: =Z41/IS!Z15 -> 1.1773003 | AA66: =AA41/IS!AA15 -> 1.1981675 | AC66: =AC41/IS!AC15 -> 1.2336214 | AD66: =AD41/IS!AD15 -> 0.10116347 | AE66: =AE41/IS!AE15 -> 0.085132842 | AF66: =AF41/IS!AF15 -> 0.079629261 | AH66: =AH41/IS!AH15 -> 0.037812284 | AI66: =AI41/IS!AI15 -> 0.030219143 | AJ66: =AJ41/IS!AJ15 -> 0.17585561 | AK66: =AK41/IS!AK15 -> 0.15413482 | AM66: 0.9 | AN66: 0.8 | AO66: 0.7 | AP66: 0.5736

Sheet CF
C2: Tempus Labs (NASDAQ: TEM)
B4: Statement of Cash Flows | D4: 1Q19 | E4: 2Q19 | F4: 3Q19 | G4: 4Q19 | H4: FY19 | I4: 1Q20 | J4: 2Q20 | K4: 3Q20 | L4: 4Q20 | M4: FY20 | N4: 1Q21 | O4: 2Q21 | P4: 3Q21 | Q4: 4Q21 | R4: FY21 | S4: 1Q22 | T4: 2Q22 | U4: 3Q22 | V4: 4Q22 | W4: FY22 | X4: 1Q23 | Y4: 2Q23 | Z4: 3Q23 | AA4: 4Q23 | AB4: FY23 | AC4: 1Q24 | AD4: 2Q24 | AE4: 3Q24 | AF4: 4Q24 | AG4: FY24 | AH4: 1Q25 | AI4: 2Q25 | AJ4: 3Q25 | AK4: 4Q25 | AL4: FY25 | AM4: 1Q26E | AN4: 2Q26E | AO4: 3Q26E | AP4: 4Q26E | AQ4: FY26E
B6: Net Income | D6: -24.393366 | E6: -30.204948 | F6: -33.560787 | G6: -26.792228 | H6: =SUM(D6:G6) -> -114.95133 | I6: -47.102917 | J6: -51.098613 | K6: -57.509399 | L6: -54.143518 | M6: =SUM(I6:L6) -> -209.85445 | N6: -65.020109 | O6: -66.84707 | P6: -68.342884 | Q6: -58.981033 | R6: =SUM(N6:Q6) -> -259.1911 | S6: -81.289321 | T6: -73.691057 | U6: -68.544865 | V6: -66.283812 | W6: =SUM(S6:V6) -> -289.80906 | X6: -54.375274 | Y6: -55.833222 | Z6: -53.425996 | AA6: -50.484901 | AB6: =SUM(X6:AA6) -> -214.11939 | AC6: -64.744056 | AD6: =-616.955-AC6 -> -552.21094 | AE6: =-692.795-AD6-AC6 -> -75.84 | AF6: =AG6-AE6-AD6-AC6 -> -13.014 | AG6: -705.809 | AH6: -68.037 | AI6: =-110.88-AH6 -> -42.843 | AJ6: =-190.862-AI6-AH6 -> -79.982 | AK6: =IS!AK78 -> -51.017 | AL6: -245.028 | AM6: =IS!AM78 -> -104.49199 | AN6: =IS!AN78 -> -82.322466 | AO6: =IS!AO78 -> -70.301045 | AP6: =IS!AP78 -> -56.197844 | AQ6: =SUM(AM6:AP6) -> -313.31334
B8: Operating Activities
C9: Depreciation | D9: 1.7927251 | E9: 1.9027783 | F9: 1.9379328 | G9: 2.4502838 | H9: =SUM(D9:G9) -> 8.08372 | I9: 3.3228243 | J9: 2.9640176 | K9: 3.2719049 | L9: 3.5203932 | M9: =SUM(I9:L9) -> 13.07914 | N9: 3.5948192 | O9: 3.5965499 | P9: 3.478544 | Q9: 3.0888472 | R9: =SUM(N9:Q9) -> 13.75876 | S9: 2.4045999 | T9: 3.8903675 | U9: 4.5265056 | V9: 4.7803052 | W9: =SUM(S9:V9) -> 15.601778 | X9: 5.0592569 | Y9: 5.1939829 | Z9: 5.4043979 | AA9: 5.137539 | AB9: =SUM(X9:AA9) -> 20.795177 | AC9: 6.2696247 | AD9: =18.348-AC9 -> 12.078375 | AE9: =27.788-AD9-AC9 -> 9.44 | AF9: =AG9-AE9-AD9-AC9 -> 9.457 | AG9: =37.245 -> 37.245 | AH9: 20.353 | AI9: =48.385-AH9 -> 28.032 | AJ9: =75.416-AI9-AH9 -> 27.031 | AK9: =AL9-AJ9-AI9-AH9 -> 26.908 | AL9: 102.324 | AM9: 30 | AN9: 30 | AO9: 30 | AP9: 30 | AQ9: =SUM(AM9:AP9) -> 120
C10: Change in fair value of warrant liability | AD10: =-0.9-AC10 -> -0.9 | AE10: =42.4-AD10 -> 43.3 | AF10: =AG10-AE10-AD10-AC10 -> 1.4432899e-15 | AG10: 42.4 | AH10: 0 | AI10: 0 | AJ10: 0 | AK10: =AL10-AJ10-AI10-AH10 -> 0 | AL10: 0
C11: Gain on warrant exercise | AD11: =-0.173-AC11 -> -0.173 | AE11: =-0.173-AD11 -> 0 | AF11: =AG11-AE11-AD11-AC11 -> -39.1 | AG11: =-39.1-0.173 -> -39.273 | AH11: 0 | AI11: 0 | AJ11: 0 | AK11: =AL11-AJ11-AI11-AH11 -> 0 | AL11: 0
C12: Gain on marketable securities | AD12: =-2.541-AC12 -> -2.541 | AE12: =-5.119-AD12 -> -2.578 | AF12: =AG12-AE12-AD12-AC12 -> -6.991 | AG12: -12.11 | AH12: 31.805 | AI12: =-6.007-AH12 -> -37.812 | AJ12: =-4.731-AI12-AH12 -> 1.276 | AK12: =AL12-AJ12-AI12-AH12 -> -11.74 | AL12: -16.471
C13: Loss on disposal of property and equipment | AK13: =AL13-AJ13-AI13-AH13 -> 0.415 | AL13: 0.415
C14: Loss on debt extinguishment | AH14: 0 | AI14: 0 | AJ14: =12.034-AI14-AH14 -> 12.034 | AK14: =AL14-AJ14-AI14-AH14 -> 0 | AL14: 12.034
C15: Deferred income taxes | AH15: -46.216 | AI15: =-46.216-AH15 -> 0 | AJ15: =-46.216-AI15-AH15 -> 0 | AK15: =AL15-AJ15-AI15-AH15 -> -6.449 | AL15: =-52.665 -> -52.665
C16: Amortization of original issue discount | AD16: =0.691-AC16 -> 0.691 | AE16: =1.036-AD16 -> 0.345 | AF16: =AG16-AE16-AD16-AC16 -> 0.346 | AG16: 1.382 | AH16: 0.56 | AI16: =1.169-AH16 -> 0.609 | AJ16: =2.615-AI16-AH16 -> 1.446 | AK16: =AL16-AJ16-AI16-AH16 -> 1.473 | AL16: =4.088 -> 4.088
C17: Amortization of deferred financing fees | AD17: =0.255-AC17 -> 0.255 | AE17: =0.383-AD17 -> 0.128 | AF17: =AG17-AE17-AD17-AC17 -> 0.127 | AG17: 0.51 | AH17: 0.157 | AI17: =0.332-AH17 -> 0.175 | AJ17: =0.398-AI17-AH17 -> 0.066 | AK17: =AL17-AJ17-AI17-AH17 -> 0.086 | AL17: 0.484
C18: Change in fair value of contingent consideration | AD18: =0.165-AC18 -> 0.165 | AE18: =0.165-AD18 -> 0 | AF18: =AG18-AE18-AD18-AC18 -> -0.093 | AG18: =0.072 -> 0.072 | AH18: 0 | AI18: 0 | AJ18: 0 | AK18: =AL18-AJ18-AI18-AH18 -> 0 | AL18: 0
C19: Change in fair value of holdback liability | AH19: 0.046 | AI19: =0.312-AH19 -> 0.266 | AJ19: =0.291-AI19-AH19 -> -0.021 | AK19: =AL19-AJ19-AI19-AH19 -> -1.628 | AL19: -1.337
C20: Amortization of warrant contract asset | AD20: =2.422-AC20 -> 2.422 | AE20: =3.633-AD20 -> 1.211 | AF20: =AG20-AE20-AD20-AC20 -> -15.091 | AG20: =-16.301+4.843 -> -11.458 | AH20: 0 | AI20: 0 | AJ20: 0 | AK20: =AL20-AJ20-AI20-AH20 -> 0 | AL20: 0
C21: Provision for bad debt expense | AD21: =0.327-AC21 -> 0.327 | AE21: =0.545-AD21 -> 0.218 | AF21: =AG21-AE21-AD21-AC21 -> 0.135 | AG21: =0.68 -> 0.68 | AH21: 0.316 | AI21: =0.625-AH21 -> 0.309 | AJ21: =0.767-AI21-AH21 -> 0.142 | AK21: =AL21-AJ21-AI21-AH21 -> 1.791 | AL21: 2.558
C22: Provision for obsolete inventory | AH22: 0 | AI22: 0 | AJ22: =1.135-AI22-AH22 -> 1.135 | AK22: =AL22-AJ22-AI22-AH22 -> 0.2 | AL22: 1.335
C23: Change in fair value of warrant asset | AD23: =7.7-AC23 -> 7.7 | AE23: =-18.302-AD23 -> -26.002 | AF23: =AG23-AE23-AD23-AC23 -> -8.8817842e-16 | AG23: -18.302 | AH23: 0 | AI23: 0 | AJ23: 0 | AK23: =AL23-AJ23-AI23-AH23 -> 0 | AL23: 0
C24: Loss from equity-method investments | AD24: 0 | AE24: =1.692-AD24 -> 1.692 | AF24: =AG24-AE24-AD24-AC24 -> 2.536 | AG24: =4.228 -> 4.228 | AH24: 1.883 | AI24: =3.983-AH24 -> 2.1 | AJ24: =2.465-AI24-AH24 -> -1.518 | AK24: =AL24-AJ24-AI24-AH24 -> 3.149 | AL24: 5.614
C25: Amortization of finance right-of-use lease assets | AD25: 0 | AE25: =0-AD25 -> 0 | AF25: =AG25-AE25-AD25-AC25 -> 0 | AG25: 0 | AH25: 0 | AI25: 0 | AJ25: 0 | AK25: =AL25-AJ25-AI25-AH25 -> 0 | AL25: 0
C26: Non-cash operating lease costs | AD26: =3.252-AC26 -> 3.252 | AE26: =4.67-AD26 -> 1.418 | AF26: =AG26-AE26-AD26-AC26 -> 1.377 | AG26: 6.047 | AH26: 2.089 | AI26: =4.573-AH26 -> 2.484 | AJ26: =7.866-AI26-AH26 -> 3.293 | AK26: =AL26-AJ26-AI26-AH26 -> 3.688 | AL26: 11.554
C27: Minimum accretion expense | AD27: =0.092-AC27 -> 0.092 | AE27: =0.085-AD27 -> -0.007 | AF27: =AG27-AE27-AD27-AC27 -> 0.112 | AG27: 0.197 | AH27: 0.248 | AI27: =0.108-AH27 -> -0.14 | AJ27: =0.109-AI27-AH27 -> 0.001 | AK27: =AL27-AJ27-AI27-AH27 -> 0.159 | AL27: 0.268
C28: Impairment of intangible assets | AD28: 0 | AE28: =0-AD28 -> 0 | AF28: =AG28-AE28-AD28-AC28 -> 0 | AG28: 0 | AH28: 0 | AI28: 0 | AJ28: 0 | AK28: =AL28-AJ28-AI28-AH28 -> 0 | AL28: 0
C29: PIK interest added to principal | AD29: =4.366-AC29 -> 4.366 | AE29: =6.567-AD29 -> 2.201 | AF29: =AG29-AE29-AD29-AC29 -> 2.244 | AG29: 8.811 | AH29: 3.274 | AI29: =7.157-AH29 -> 3.883 | AJ29: =8.839-AI29-AH29 -> 1.682 | AK29: =AL29-AJ29-AI29-AH29 -> 1.698 | AL29: 10.537
C30: Interest payable - Google | D30: 0.01021187 | E30: 0.00760304 | F30: 0.0057988 | G30: 0.00481166 | H30: =SUM(D30:G30) -> 0.02842537 | I30: 0.14312638 | J30: -0.13652574 | K30: 5.5213461 | L30: 13.400725 | M30: =SUM(I30:L30) -> 18.928672 | N30: 3.7722974 | O30: 3.789743 | P30: 3.7892903 | Q30: 3.8321984 | R30: =SUM(N30:Q30) -> 15.183529 | S30: 4.2903923 | T30: 3.8553121 | U30: 4.5259343 | V30: 4.131687 | W30: =SUM(S30:V30) -> 16.803326 | X30: 3.7847314 | Y30: 3.8267839 | Z30: 4.1122515 | AA30: 4.1122515 | AB30: =SUM(X30:AA30) -> 15.836018 | AC30: 3.6433407 | AD30: =0-AC30 -> -3.6433407 | AE30: =0-AD30-AC30 -> 0 | AF30: =AG30-AE30-AD30-AC30 -> 0 | AG30: 0 | AH30: 0 | AI30: 0 | AJ30: 0 | AK30: =AL30-AJ30-AI30-AH30 -> 0 | AL30: 0 | AM30: 3.275 | AN30: 3.275 | AO30: 3.275 | AP30: 3.275 | AQ30: =SUM(AM30:AP30) -> 13.1
C31: Interest payable - Ares | D31: 0 | E31: 0 | F31: 0 | G31: 0 | H31: =SUM(D31:G31) -> 0 | I31: 0 | J31: 0 | K31: 0 | L31: 0 | M31: =SUM(I31:L31) -> 0 | N31: 0 | O31: 0 | P31: 0 | Q31: 0 | R31: =SUM(N31:Q31) -> 0 | S31: 0 | T31: 0 | U31: 0 | V31: 5.0904116 | W31: =SUM(S31:V31) -> 5.0904116 | X31: 4.4438623 | Y31: 1.6144167 | Z31: -0.61172439 | AA31: 2.9575013 | AB31: =SUM(X31:AA31) -> 8.4040559 | AC31: -0.04111035 | AD31: =0-AC31 -> 0.04111035 | AE31: =0-AD31-AC31 -> 0 | AF31: =AG31-AE31-AD31-AC31 -> 0 | AG31: 0 | AH31: 0 | AI31: 0 | AJ31: 0 | AK31: =AL31-AJ31-AI31-AH31 -> 0 | AL31: 0 | AM31: 2.3 | AN31: 2.3 | AO31: 2.3 | AP31: 2.3 | AQ31: =SUM(AM31:AP31) -> 9.2
C32: Convertible promissory note | D32: 0 | E32: 0 | F32: 0 | G32: 0 | H32: =SUM(D32:G32) -> 0 | I32: 0 | J32: 330 | K32: 0 | L32: -80 | M32: =SUM(I32:L32) -> 250 | N32: -0.942 | O32: -2.477 | P32: -3.161 | Q32: -5.184 | R32: =SUM(N32:Q32) -> -11.764 | S32: -3.181968 | T32: -3.291235 | U32: -3.7476644 | V32: -6.9212894 | W32: =SUM(S32:V32) -> -17.142157 | X32: -5.05937 | Y32: -8.866948 | Z32: -8.2938695 | AA32: -5.7498614 | AB32: =SUM(X32:AA32) -> -27.970049 | AC32: -6.3911336 | AD32: =0-AC32 -> 6.3911336 | AE32: =0-AD32-AC32 -> 0 | AF32: =AG32-AE32-AD32-AC32 -> 0 | AG32: 0 | AH32: 0 | AI32: 0 | AJ32: 0 | AK32: =AL32-AJ32-AI32-AH32 -> 0 | AL32: 0 | AM32: =BS!AM33-BS!AK33 -> -8.9 | AN32: =BS!AN33-BS!AM33 -> -8.9 | AO32: =BS!AO33-BS!AN33 -> -8.9 | AP32: =BS!AP33-BS!AO33 -> -8.9 | AQ32: =SUM(AM32:AP32) -> -35.6
C33: Accounts receivable | D33: 3.2635307 | E33: -4.5268622 | F33: -1.2986825 | G33: -17.796764 | H33: =SUM(D33:G33) -> -20.358778 | I33: 12.533398 | J33: -4.2119896 | K33: -31.300143 | L33: -35.404 | M33: =SUM(I33:L33) -> -58.382734 | N33: 20.539 | O33: 68.935 | P33: -76.36 | Q33: -13.912 | R33: =SUM(N33:Q33) -> -0.798 | S33: -0.21654218 | T33: 3.84838 | U33: -1.2872801 | V33: -16.217915 | W33: =SUM(S33:V33) -> -13.873357 | X33: -10.19531 | Y33: 3.3417096 | Z33: -20.735451 | AA33: -19.652043 | AB33: =SUM(X33:AA33) -> -47.241095 | AC33: -15.494083 | AD33: =-23.971-AC33 -> -8.476917 | AE33: =-51.699-AD33-AC33 -> -27.728 | AF33: =AG33-AE33-AD33-AC33 -> -9.338 | AG33: -61.037 | AH33: -45.175 | AI33: =-49.155-AH33 -> -3.98 | AJ33: =-63.199-AI33-AH33 -> -14.044 | AK33: =AL33-AJ33-AI33-AH33 -> -27.203 | AL33: -90.402 | AM33: 10.649452 | AN33: -12 | AO33: -5 | AP33: 6 | AQ33: =SUM(AM33:AP33) -> -0.35054771
C34: Inventory | D34: -1.164397 | E34: -1.3343044 | F34: 0.30885676 | G34: -1.7846752 | H34: =SUM(D34:G34) -> -3.9745198 | I34: -0.09108083 | J34: -17.053421 | K34: -7.1778166 | L34: -4.956 | M34: =SUM(I34:L34) -> -29.278319 | N34: 6.825 | O34: 3.028 | P34: 5.706 | Q34: -0.91 | R34: =SUM(N34:Q34) -> 14.649 | S34: 5.6088573 | T34: -3.3473171 | U34: -0.38211219 | V34: -1.2532092 | W34: =SUM(S34:V34) -> 0.62621892 | X34: -2.9296982 | Y34: -2.1711925 | Z34: 0.22556123 | AA34: -1.6881379 | AB34: =SUM(X34:AA34) -> -6.5634673 | AC34: -1.2839401 | AD34: =-3.845-AC34 -> -2.5610599 | AE34: =-7.293-AD34-AC34 -> -3.448 | AF34: =AG34-AE34-AD34-AC34 -> -2.248 | AG34: -9.541 | AH34: -0.911 | AI34: =1.974-AH34 -> 2.885 | AJ34: =-6.537-AI34-AH34 -> -8.511 | AK34: =AL34-AJ34-AI34-AH34 -> 3.168 | AL34: -3.369 | AM34: =-(BS!AM11-BS!AK11) -> 1.7050975 | AN34: =-(BS!AN11-BS!AM11) -> -3.3037139 | AO34: =-(BS!AO11-BS!AN11) -> 1.4268925 | AP34: =-(BS!AP11-BS!AO11) -> -0.50724226 | AQ34: =SUM(AM34:AP34) -> -0.67896611
C35: Prepaid expenses and other current assets | AD35: =-12.409-AC35 -> -12.409 | AE35: =-14.04-AD35 -> -1.631 | AF35: =AG35-AE35-AD35-AC35 -> 0.357 | AG35: -13.683 | AH35: -5.798 | AI35: =-0.188-AH35 -> 5.61 | AJ35: =-3.991-AI35-AH35 -> -3.803 | AK35: =AL35-AJ35-AI35-AH35 -> 2.292 | AL35: -1.699
C36: Investments and other assets | AD36: =1.294-AC36 -> 1.294 | AE36: =-0.41-AD36 -> -1.704 | AF36: =AG36-AE36-AD36-AC36 -> -0.341 | AG36: -0.751 | AH36: -3.358 | AI36: =-11.073-AH36 -> -7.715 | AJ36: =-16.7-AI36-AH36 -> -5.627 | AK36: =AL36-AJ36-AI36-AH36 -> -0.601 | AL36: -17.301
C37: Accounts payable | D37: -0.66146186 | E37: 2.3945419 | F37: -0.85043316 | G37: 6.4689377 | H37: =SUM(D37:G37) -> 7.3515846 | I37: 5.5093697 | J37: -2.447681 | K37: 27.830477 | L37: 21.738272 | M37: =SUM(I37:L37) -> 52.630438 | N37: -10.516 | O37: -4.2 | P37: 13.469 | Q37: 1.945 | R37: =SUM(N37:Q37) -> 0.698 | S37: 8.4834254 | T37: 2.8960742 | U37: 5.559872 | V37: 14.805994 | W37: =SUM(S37:V37) -> 31.745366 | X37: -0.36543962 | Y37: 9.461445 | Z37: 12.942369 | AA37: 4.1909225 | AB37: =SUM(X37:AA37) -> 26.229296 | AC37: -10.663084 | AD37: =-33.371-AC37 -> -22.707916 | AE37: =-24.776-AD37-AC37 -> 8.595 | AF37: =AG37-AE37-AD37-AC37 -> 0.924 | AG37: -23.852 | AH37: 23.572 | AI37: =7.025-AH37 -> -16.547 | AJ37: =-18.528-AI37-AH37 -> -25.553 | AK37: =AL37-AJ37-AI37-AH37 -> 11.287 | AL37: -7.241 | AM37: =BS!AM25-BS!AK25 -> 4.1065637 | AN37: =BS!AN25-BS!AM25 -> 15.26796 | AO37: =BS!AO25-BS!AN25 -> -7.6390488 | AP37: =BS!AP25-BS!AO25 -> -1.8705431 | AQ37: =SUM(AM37:AP37) -> 9.8649314
C38: Related party asset | AJ38: =-25-AI38-AH38 -> -25 | AK38: =AL38-AJ38-AI38-AH38 -> 0 | AL38: -25
C39: Deferred revenue | D39: -0.096789224 | E39: 3.2217398 | F39: -0.4139319 | G39: 0.76627485 | H39: =SUM(D39:G39) -> 3.4772936 | I39: -1.2402637 | J39: 0.25608599 | K39: -0.4069216 | L39: 2.7856451 | M39: =SUM(I39:L39) -> 1.3945458 | N39: -1.12 | O39: 0.072 | P39: 9.499 | Q39: 1.038 | R39: =SUM(N39:Q39) -> 9.489 | S39: 0.89022763 | T39: -5.1979798 | U39: 70.00239 | V39: 3.1295121 | W39: =SUM(S39:V39) -> 68.82415 | X39: -3.0698329 | Y39: -16.142353 | Z39: 3.3301045 | AA39: 12.231355 | AB39: =SUM(X39:AA39) -> -3.6507259 | AC39: -15.971751 | AD39: =-28.669-AC39 -> -12.697249 | AE39: =43.876-1.52-AD39-AC39 -> 71.025 | AF39: =AG39-AE39-AD39-AC39 -> -63.298 | AG39: =-20.942 -> -20.942 | AH39: -12.377 | AI39: =36.836-AH39 -> 49.213 | AJ39: =17.398-AI39-AH39 -> -19.438 | AK39: =AL39-AJ39-AI39-AH39 -> -24.358 | AL39: -6.96 | AM39: =BS!AM26-BS!AK26 -> 62.558077 | AN39: =BS!AN26-BS!AM26 -> 2.7618607 | AO39: =BS!AO26-BS!AN26 -> -12.684911 | AP39: =BS!AP26-BS!AO26 -> -5.6247677 | AQ39: =SUM(AM39:AP39) -> 47.010259
C40: Accrued data licensing fees | AD40: =-2.749-AC40 -> -2.749 | AE40: =-4.25-AD40 -> -1.501 | AF40: =AG40-AE40-AD40-AC40 -> -0.75 | AG40: -5 | AH40: -0.25 | AI40: =3.957-AH40 -> 4.207 | AJ40: =3.73-AI40-AH40 -> -0.227 | AK40: =AL40-AJ40-AI40-AH40 -> -0.764 | AL40: 2.966
C41: Accrued expenses & other | AD41: =-2.805-AC41 -> -2.805 | AE41: =23.371-AD41 -> 26.176 | AF41: =AG41-AE41-AD41-AC41 -> 27.169 | AG41: 50.54 | AH41: -27.606 | AI41: =6.991-AH41 -> 34.597 | AJ41: =-5.179-AI41-AH41 -> -12.17 | AK41: =AL41-AJ41-AI41-AH41 -> -7.665 | AL41: -12.844
C42: Interest payable | AD42: =7.287-AC42 -> 7.287 | AE42: =11.208-AD42 -> 3.921 | AF42: =AG42-AE42-AD42-AC42 -> 3.921 | AG42: 15.129 | AH42: 3.508 | AI42: =7.122-AH42 -> 3.614 | AJ42: =10.288-AI42-AH42 -> 3.166 | AK42: =AL42-AJ42-AI42-AH42 -> 3.918 | AL42: 14.206
C43: Operating lease liabilities | AD43: =-4.582-AC43 -> -4.582 | AE43: =-6.655-AD43 -> -2.073 | AF43: =AG43-AE43-AD43-AC43 -> -1.898 | AG43: -8.553 | AH43: -2.693 | AI43: =-5.942-AH43 -> -3.249 | AJ43: =-11.152-AI43-AH43 -> -5.21 | AK43: =AL43-AJ43-AI43-AH43 -> -3.796 | AL43: -14.948
C44: Stock compensation | D44: 0 | E44: 0 | F44: 0 | G44: 0 | H44: =SUM(D44:G44) -> 0 | I44: 0 | J44: 0 | K44: 0 | L44: 0 | M44: =SUM(I44:L44) -> 0 | N44: 0 | O44: 0 | P44: 0 | Q44: 0 | R44: =SUM(N44:Q44) -> 0 | S44: 0 | T44: 0 | U44: 0 | V44: 0 | W44: =SUM(S44:V44) -> 0 | X44: 0 | Y44: 0 | Z44: 0 | AA44: 0 | AB44: =SUM(X44:AA44) -> 0 | AC44: 0 | AD44: =488.313-AC44 -> 488.313 | AE44: =509.351-AD44-AC44 -> 21.038 | AF44: =AG44-AE44-AD44-AC44 -> 24.787 | AG44: 534.138 | AH44: 22.974 | AI44: =45.429-AH44 -> 22.455 | AJ44: =79.408-AI44-AH44 -> 33.979 | AK44: =AL44-AJ44-AI44-AH44 -> 45.339 | AL44: 124.747 | AM44: =IS!AM42 -> 55 | AN44: =IS!AN42 -> 48.33 | AO44: =IS!AO42 -> 48.33 | AP44: =IS!AP42 -> 48.33 | AQ44: =SUM(AM44:AP44) -> 199.99
C45: Other | D45: -0.9726151 | E45: 0.7296157 | F45: 11.706681 | G45: 5.2545634 | H45: =SUM(D45:G45) -> 16.718245 | I45: -2.9180535 | J45: -4.2767572 | K45: -4.2498361 | L45: 2.4424015 | M45: =SUM(I45:L45) -> -9.0022453 | N45: -1.0437201 | O45: -42.554656 | P45: 43.61357 | Q45: 4.8658772 | R45: =SUM(N45:Q45) -> 4.8810711 | S45: 5.0941561 | T45: 4.1648376 | U45: 2.7963181 | V45: 1.8915348 | W45: =SUM(S45:V45) -> 13.946847 | X45: -3.7300851 | Y45: 5.6473662 | Z45: 2.3487995 | AA45: 9.655207 | AB45: =SUM(X45:AA45) -> 13.921288 | AC45: 3.2508186 | AD45: =0-AC45 -> -3.2508186 | AE45: =0.468-AD45-AC45 -> 0.468 | AF45: =AG45-AE45-AD45-AC45 -> 39.419 | AG45: =39.887 -> 39.887 | AH45: -3.988 | AI45: =-7.977-AH45 -> -3.989 | AJ45: =-11.966-AI45-AH45 -> -3.989 | AK45: =AL45-AJ45-AI45-AH45 -> -3.989 | AL45: -15.955 | AM45: 3.75 | AN45: 3.75 | AO45: 3.75 | AP45: 3.75 | AQ45: =SUM(AM45:AP45) -> 15
B46: Cash Flow from Operating Activites | D46: =SUM(D6:D45) -> -22.222161 | E46: =SUM(E6:E45) -> -27.809835 | F46: =SUM(F6:F45) -> -22.164565 | G46: =SUM(G6:G45) -> -31.428795 | H46: =SUM(D46:G46) -> -103.62536 | I46: =SUM(I6:I45) -> -29.843596 | J46: =SUM(J6:J45) -> 253.99512 | K46: =SUM(K6:K45) -> -64.020388 | L46: =SUM(L6:L45) -> -130.61608 | M46: =SUM(I46:L46) -> 29.51505 | N46: =SUM(N6:N45) -> -43.910713 | O46: =SUM(O6:O45) -> -36.657434 | P46: =SUM(P6:P45) -> -68.308479 | Q46: =SUM(Q6:Q45) -> -64.21711 | R46: =SUM(N46:Q46) -> -213.09374 | S46: =SUM(S6:S45) -> -57.916173 | T46: =SUM(T6:T45) -> -66.872617 | U46: =SUM(U6:U45) -> 13.449098 | V46: =SUM(V6:V45) -> -56.846781 | W46: =SUM(S46:V46) -> -168.18647 | X46: =SUM(X6:X45) -> -66.43716 | Y46: =SUM(Y6:Y45) -> -53.92801 | Z46: =SUM(Z6:Z45) -> -54.703558 | AA46: =SUM(AA6:AA45) -> -39.290167 | AB46: =SUM(X46:AA46) -> -214.3589 | AC46: =SUM(AC6:AC45) -> -101.42537 | AD46: =SUM(AD6:AD45) -> -97.032626 | AE46: =SUM(AE6:AE45) -> 48.664 | AF46: =SUM(AF6:AF45) -> -39.251 | AG46: =SUM(AC46:AF46) -> -189.045 | AH46: =SUM(AH6:AH45) -> -105.624 | AI46: =SUM(AI6:AI45) -> 44.164 | AJ46: =SUM(AJ6:AJ45) -> -119.842 | AK46: =SUM(AK6:AK45)-6.67 -> -40.309 | AL46: =SUM(AH46:AK46) -> -221.611 | AM46: =SUM(AM6:AM45) -> 59.952202 | AN46: =SUM(AN6:AN45) -> -0.84135939 | AO46: =SUM(AO6:AO45) -> -15.443112 | AP46: =SUM(AP6:AP45) -> 20.554603 | AQ46: =SUM(AM46:AP46) -> 64.222333
C47: OCF Margins | D47: =D46/IS!D15 -> -2.8939751 | E47: =E46/IS!E15 -> -2.6272727 | F47: =F46/IS!F15 -> -1.4482593 | G47: =G46/IS!G15 -> -1.1031911 | H47: =H46/IS!H15 -> -1.6698391 | I47: =I46/IS!I15 -> -1.6359716 | J47: =J46/IS!J15 -> 13.973376 | K47: =K46/IS!K15 -> -1.2619173 | ... AQ47: =AQ46/IS!AQ15 -> 0.040391774
B49: Investing Activites
C50: Fixed asset purchase | D50: -1.0797036 | E50: -4.4941376 | F50: -4.3579415 | G50: -12.907885 | H50: =SUM(D50:G50) -> -22.839668 | I50: -1.6657968 | J50: -5.5369776 | K50: -3.1509449 | L50: -5.0953932 | M50: =SUM(I50:L50) -> -15.449112 | N50: -1.4598192 | O50: -2.5115499 | P50: -4.262544 | Q50: -2.4848472 | R50: =SUM(N50:Q50) -> -10.71876 | S50: -6.4705145 | T50: -4.5042866 | U50: -3.7219726 | V50: -3.6802263 | W50: =SUM(S50:V50) -> -18.377 | X50: -6.1575376 | Y50: -10.441991 | Z50: -14.328312 | AA50: -3.6801594 | AB50: =SUM(X50:AA50) -> -34.608 | AC50: -6.1097552 | AD50: =-14.116-AC50 -> -8.0062448 | AE50: =-14.159-AD50-AC50 -> -0.043 | AF50: =AG50-AE50-AD50-AC50 -> -7.962 | AG50: -22.121 | AH50: -2.074 | AI50: =-9.588-AH50 -> -7.514 | AJ50: =-16.294-AI50-AH50 -> -6.706 | AK50: =AL50-AH50-AI50-AJ50 -> -4.755 | AL50: -21.049 | AM50: -2.5 | AN50: -2.5 | AO50: -2.5 | AP50: -2.5 | AQ50: =SUM(AM50:AP50) -> -10
C51: Proceeds from sale of marketable equity securities | AH51: 8.316 | AI51: =8.316-AH51 -> 0 | AJ51: =8.316-AI51-AH51 -> 0 | AK51: =AL51-AH51-AI51-AJ51 -> 0 | AL51: 8.316
C52: Business combinations, net of cash acquired | AH52: -380.762 | AI52: =-380.762-AH52 -> 0 | AJ52: =-375.025-AI52-AH52 -> 5.737 | AK52: =AL52-AH52-AI52-AJ52 -> -1.641 | AL52: =-376.666 -> -376.666
C53: Purchases of capitalized software | AH53: -1.298 | AI53: =-3.295-AH53 -> -1.997 | AJ53: =-4.635-AI53-AH53 -> -1.34 | AK53: =AL53-AH53-AI53-AJ53 -> -1.581 | AL53: -6.216
C54: Investments & other | D54: 0 | E54: 0 | F54: 0 | G54: -25.994 | H54: =SUM(D54:G54) -> -25.994 | I54: 0 | J54: 0 | K54: 0 | L54: 0 | M54: =SUM(I54:L54) -> 0 | N54: 0 | O54: -5.9566456 | P54: -4 | Q54: 0 | R54: =SUM(N54:Q54) -> -9.9566456 | S54: -35.049 | T54: 0 | U54: -0.5 | V54: -4.013 | W54: =SUM(S54:V54) -> -39.562 | X54: -2.869 | Y54: 0 | Z54: 0 | AA54: -2.836 | AB54: =SUM(X54:AA54) -> -5.705 | AC54: 22.285331 | AD54: =23.098-AC54 -> 0.8126686 | AE54: =23.098+-95.186-36.183-AD54-AC54 -> -131.369 | AF54: =AG54-AE54-AD54-AC54 -> 0 | AG54: =23.098-36.183-95.186 -> -108.271 | AH54: 0 | AI54: 0 | AJ54: 0 | AK54: =AL54-AH54-AI54-AJ54 -> -2.74 | AL54: =-2.74 -> -2.74 | AM54: 0 | AN54: 0 | AO54: 0 | AP54: 0 | AQ54: =SUM(AM54:AP54) -> 0
B55: Cash Used in Investing Activites | D55: =SUM(D50:D54) -> -1.0797036 | E55: =SUM(E50:E54) -> -4.4941376 | F55: =SUM(F50:F54) -> -4.3579415 | G55: =SUM(G50:G54) -> -38.901885 | H55: =SUM(D55:G55) -> -48.833668 | I55: =SUM(I50:I54) -> -1.6657968 | J55: =SUM(J50:J54) -> -5.5369776 | K55: =SUM(K50:K54) -> -3.1509449 | L55: =SUM(L50:L54) -> -5.0953932 | M55: =SUM(I55:L55) -> -15.449112 | N55: =SUM(N50:N54) -> -1.4598192 | O55: =SUM(O50:O54) -> -8.4681956 | P55: =SUM(P50:P54) -> -8.262544 | Q55: =SUM(Q50:Q54) -> -2.4848472 | R55: =SUM(N55:Q55) -> -20.675406 | S55: =SUM(S50:S54) -> -41.519514 | T55: =SUM(T50:T54) -> -4.5042866 | U55: =SUM(U50:U54) -> -4.2219726 | V55: =SUM(V50:V54) -> -7.6932263 | W55: =SUM(S55:V55) -> -57.939 | X55: =SUM(X50:X54) -> -9.0265376 | Y55: =SUM(Y50:Y54) -> -10.441991 | Z55: =SUM(Z50:Z54) -> -14.328312 | AA55: =SUM(AA50:AA54) -> -6.5161594 | AB55: =SUM(X55:AA55) -> -40.313 | AC55: =SUM(AC50:AC54) -> 16.175576 | AD55: =SUM(AD50:AD54) -> -7.1935762 | AE55: =SUM(AE50:AE54) -> -131.412 | AF55: =SUM(AF50:AF54) -> -7.962 | AG55: =SUM(AC55:AF55) -> -130.392 | AH55: =SUM(AH50:AH54) -> -375.818 | AI55: =SUM(AI50:AI54) -> -9.511 | AJ55: =SUM(AJ50:AJ54) -> -2.309 | AK55: =SUM(AK50:AK54) -> -10.717 | AL55: =SUM(AH55:AK55) -> -398.355 | AM55: =SUM(AM50:AM54) -> -2.5 | AN55: =SUM(AN50:AN54) -> -2.5 | AO55: =SUM(AO50:AO54) -> -2.5 | AP55: =SUM(AP50:AP54) -> -2.5 | AQ55: =SUM(AM55:AP55) -> -10
B57: Free Cash Flow | D57: =D46+D50 -> -23.301865 | E57: =E46+E50 -> -32.303973 | F57: =F46+F50 -> -26.522507 | G57: =G46+G50 -> -44.336681 | H57: =H46+H50 -> -126.46503 | I57: =I46+I50 -> -31.509393 | J57: =J46+J50 -> 248.45814 | K57: =K46+K50 -> -67.171333 | ... Q57: =Q46+Q50 -> -66.701957 | R57: =SUM(N57:Q57) -> -223.8125 | S57: =S46+S50 -> -64.386687 | T57: =T46+T50 -> -71.376904 | U57: =U46+U50 -> 9.7271251 | V57: =V46+V50 -> -60.527007 | W57: =SUM(S57:V57) -> -186.56347 | X57: =X46+X50 -> -72.594698 | Y57: =Y46+Y50 -> -64.370002 | Z57: =Z46+Z50 -> -69.03187 | AA57: =AA46+AA50 -> -42.970326 | AB57: =SUM(X57:AA57) -> -248.9669 | AC57: =AC46+AC50 -> -107.53513 | AD57: =AD46+AD50 -> -105.03887 | AE57: =AE46+AE50 -> 48.621 | AF57: =AF46+AF50 -> -47.213 | AG57: =SUM(AC57:AF57) -> -211.166 | AH57: =AH46+AH50 -> -107.698 | AI57: =AI46+AI50 -> 36.65 | AJ57: =AJ46+AJ50 -> -126.548 | AK57: =AK46+AK50 -> -45.064 | AL57: =SUM(AH57:AK57) -> -242.66 | AM57: =AM46+AM50 -> 57.452202 | AN57: =AN46+AN50 -> -3.3413594 | AO57: =AO46+AO50 -> -17.943112 | AP57: =AP46+AP50 -> 18.054603 | AQ57: =SUM(AM57:AP57) -> 54.222333
C58: FCF Margin | D58: =D57/IS!D15 -> -3.0345841 | E58: =E57/IS!E15 -> -3.0518464 | F58: =F57/IS!F15 -> -1.7330125 | G58: =G57/IS!G15 -> -1.5562745 | H58: =H57/IS!H15 -> -2.037882 | I58: =I57/IS!I15 -> -1.7272875 | J58: =J57/IS!J15 -> 13.668762 | K58: =K57/IS!K15 -> -1.3240261 | ... AQ58: =AQ57/IS!AQ15 -> 0.034102408
B60: Financing Activities
C61: Proceeds from issuance of common stock in connection with IPO, net of underwriting discounts and commissions | AD61: =381.951-AC61 -> 381.951 | AE61: =381.951-AD61 -> 0 | AF61: =AG61-AE61-AD61-AC61 -> 0 | AG61: 381.951
C62: Tax withholding related to net share settlement of RSUs | AD62: =-69.918-AC62 -> -69.918 | AE62: =-69.918-AD62 -> 0 | AF62: =AG62-AE62-AD62-AC62 -> 0 | AG62: -69.918
C63: Issuance of Series G-5 Preferred Stock | AD63: =199.75-AC63 -> 199.75 | AE63: =199.75-AD63 -> 0 | AF63: =AG63-AE63-AD63-AC63 -> 0 | AG63: 199.75
C64: Principal payments on finance lease liabilities | AD64: 0 | AE64: =0-AD64 -> 0 | AF64: =AG64-AE64-AD64-AC64 -> 0 | AG64: 0
C65: Purchase of treasury stock | AD65: 0 | AE65: =0-AD65 -> 0 | AF65: =AG65-AE65-AD65-AC65 -> 0 | AG65: 0 | AK65: =AL65-AH65-AI65-AJ65 -> -3.04 | AL65: -3.04
C66: Payment of deferred offering costs | AD66: =-2.714-AC66 -> -2.714 | AE66: =-8.587-AD66 -> -5.873 | AF66: =AG66-AE66-AD66-AC66 -> -0.179 | AG66: -8.766 | AH66: 0 | AI66: 0 | AJ66: =-0.501-AI66-AH66 -> -0.501 | AK66: =AL66-AJ66-AI66-AH66 -> -0.305 | AL66: -0.806
C67: Proceeds from revolving credit facility | AH67: 98 | AI67: =98-AH67 -> 0 | AJ67: =98-AI67-AH67 -> 0 | AK67: =AL67-AJ67-AI67-AH67 -> 0 | AL67: 98
C68: Dividends paid | AD68: =-5.625-AC68 -> -5.625 | AE68: =-5.625-AD68 -> 0 | AF68: =AG68-AE68-AD68-AC68 -> 0 | AG68: -5.625 | AI68: 0 | AJ68: 0 | AK68: =AL68-AJ68-AI68-AH68 -> 0 | AL68: 0
C69: Proceeds from long-term debt, net of original issue discount | AD69: 0 | AE69: =0-AD69 -> 0 | AF69: =AG69-AE69-AD69-AC69 -> 0 | AG69: 0 | AH69: 196 | AI69: =196-AH69 -> 0 | AJ69: =196-AI69-AH69 -> 0 | AK69: =AL69-AJ69-AI69-AH69 -> -196 | AL69: 0
C70: Proceeds from convertible senior notes | AJ70: =726.497-AI70-AH70 -> 726.497 | AK70: =AL70-AJ70-AI70-AH70 -> 196 | AL70: =726.497+196 -> 922.497
C71: Payment of deferred financing fees | AH71: -0.958 | AI71: =-0.958-AH71 -> 0 | AJ71: =-1.255-AI71-AH71 -> -0.297 | AK71: =AL71-AJ71-AI71-AH71 -> -0.264 | AL71: -1.519
C72: Principal payments on long-term debt | AJ72: =-276.892-AI72-AH72 -> -276.892 | AK72: =AL72-AJ72-AI72-AH72 -> 0 | AL72: -276.892
C73: Prepayment premium on long-term debt | AJ73: =-7.841-AI73-AH73 -> -7.841 | AK73: =AL73-AJ73-AI73-AH73 -> 0 | AL73: -7.841
C74: Purchase of capped call | AJ74: =-41.775-AI74-AH74 -> -41.775 | AK74: =AL74-AJ74-AI74-AH74 -> 0 | AL74: -41.775
C75: Proceeds from issuance of common stock in connection with ATM | AJ75: =195.499-AI75-AH75 -> 195.499 | AK75: =AL75-AJ75-AI75-AH75 -> 0 | AL75: 195.499
C76: Payment of indemnity holdback related to acquisition | AD76: =-0.813-AC76 -> -0.813 | AE76: =-2.25-0.813-AD76 -> -2.25 | AF76: =AG76-AE76-AD76-AC76 -> 2.220446e-16 | AG76: =-0.813-2.25 -> -3.063 | AH76: 0 | AI76: 0 | AJ76: 0 | AK76: =AL76-AJ76-AI76-AH76 -> 0 | AL76: 0
B77: Cash used in Financing Activites | D77: -5.6227196 | E77: 192.47543 | F77: -0.07096218 | G77: 2.2215995 | H77: =SUM(D77:G77) -> 189.00335 | I77: 71.495989 | J77: 16.415503 | K77: -0.28466846 | L77: 184.42314 | M77: =SUM(I77:L77) -> 272.04996 | N77: 3.085532 | O77: -3.6273707 | P77: -0.88197668 | Q77: -0.55704305 | R77: =SUM(N77:Q77) -> -1.9808585 | S77: -0.58736449 | T77: 90.837724 | U77: 162.67506 | V77: -1.534769 | W77: =SUM(S77:V77) -> 251.39065 | X77: -3.7095445 | Y77: 42.889478 | Z77: -0.51817105 | AA77: 78.885979 | AB77: =SUM(X77:AA77) -> 117.54774 | AC77: -0.564928 | AD77: =SUM(AD61:AD76)-AC77 -> 503.19593 | AE77: =SUM(AE61:AE76) -> -8.123 | AF77: =SUM(AF61:AF76) -> -0.179 | AG77: =SUM(AC77:AF77) -> 494.329 | AH77: =SUM(AH61:AH76) -> 293.042 | AI77: =SUM(AI61:AI76) -> 0 | AJ77: =SUM(AJ61:AJ76) -> 594.69 | AK77: =SUM(AK61:AK76) -> -3.609 | AL77: =SUM(AH77:AK77) -> 884.123 | AM77: =SUM(AM61:AM76) -> 0 | AN77: =SUM(AN61:AN76) -> 0 | AO77: =SUM(AO61:AO76) -> 0 | AP77: =SUM(AP61:AP76) -> 0 | AQ77: =SUM(AM77:AP77) -> 0
C79: Effects of foreign exchange rates on cash | AD79: =-0.09-AC79 -> -0.09 | AE79: =-0.013-AD79 -> 0.077 | AF79: =AG79-AE79-AD79-AC79 -> 0.349 | AG79: 0.336 | AH79: 0.109 | AI79: =-0.037-AH79 -> -0.146 | AJ79: =-0.078-AI79-AH79 -> -0.041 | AK79: =AL79-AJ79-AI79-AH79 -> 0.016 | AL79: -0.062
B80: Net change in cash & cash equivalents | D80: =D77+D55+D46 -> -28.924585 | E80: =E77+E55+E46 -> 160.17146 | F80: =F77+F55+F46 -> -26.593469 | G80: =G77+G55+G46 -> -68.109081 | H80: =SUM(D80:G80) -> 36.544326 | I80: =I77+I55+I46 -> 39.986596 | J80: =J77+J55+J46 -> 264.87364 | K80: =K77+K55+K46 -> -67.456001 | L80: =L77+L55+L46 -> 48.711663 | M80: =SUM(I80:L80) -> 286.1159 | N80: =N77+N55+N46 -> -42.285 | O80: =O77+O55+O46 -> -48.753 | P80: =P77+P55+P46 -> -77.453 | Q80: =Q77+Q55+Q46 -> -67.259 | R80: =SUM(N80:Q80) -> -235.75 | S80: =S77+S55+S46 -> -100.02305 | T80: =T77+T55+T46 -> 19.46082 | U80: =U77+U55+U46 -> 171.90219 | V80: =V77+V55+V46 -> -66.074776 | W80: =SUM(S80:V80) -> 25.26518 | X80: =X77+X55+X46 -> -79.173242 | Y80: =Y77+Y55+Y46 -> -21.480524 | Z80: =Z77+Z55+Z46 -> -69.550041 | AA80: =AA77+AA55+AA46 -> 33.079653 | AB80: =SUM(X80:AA80) -> -137.12415 | AC80: =AC77+AC55+AC46 -> -85.814726 | AD80: =AD77+AD55+AD46+AD79 -> 398.87973 | AE80: =AE77+AE55+AE46+AE79 -> -90.794 | AF80: =AF77+AF55+AF46+AF79 -> -47.043 | AG80: =SUM(AC80:AF80) -> 175.228 | AH80: =AH77+AH55+AH46 -> -188.4 | AI80: =AI77+AI55+AI46 -> 34.653 | AJ80: =AJ77+AJ55+AJ46 -> 472.539 | AK80: =AK77+AK55+AK46 -> -54.635 | AL80: =SUM(AH80:AK80) -> 264.157 | AM80: =AM77+AM55+AM46 -> 57.452202 | AN80: =AN77+AN55+AN46 -> -3.3413594 | AO80: =AO77+AO55+AO46 -> -17.943112 | AP80: =AP77+AP55+AP46 -> 18.054603 | AQ80: =SUM(AM80:AP80) -> 54.222333
B82: Beginning cash & cash equivalents | D82: 191.55577 | E82: =D83 -> 162.63119 | F82: =E83 -> 322.80265 | G82: =F83 -> 296.20918 | H82: =D82 -> 191.55577 | I82: =G83 -> 228.1001 | J82: =I83 -> 268.0867 | K82: =J83 -> 532.96034 | L82: =K83 -> 465.50434 | M82: =I82 -> 228.1001 | N82: =L83 -> 514.216 | O82: =N83 -> 471.931 | P82: =O83 -> 423.178 | Q82: =P83 -> 345.725 | R82: =N82 -> 514.216 | S82: =Q83 -> 278.466 | T82: =S83 -> 178.44295 | U82: =T83 -> 197.90377 | V82: =U83 -> 369.80596 | W82: =S82 -> 278.466 | X82: =V83 -> 303.73118 | Y82: =X83 -> 224.55794 | Z82: =Y83 -> 203.07741 | AA82: =Z83 -> 133.52737 | AB82: =X82 -> 303.73118 | AC82: =AA83 -> 166.60703 | AD82: =AC83 -> 80.7923 | AE82: =AD83 -> 479.67203 | AF82: =AE83 -> 388.87803 | AG82: =AC82 -> 166.60703 | AH82: 341.835 | AI82: =AH83 -> 153.435 | AJ82: =AI83 -> 188.088 | AK82: =AJ83 -> 660.627 | AL82: =AH82 -> 341.835 | AM82: =AK83 -> 605.992 | AN82: =AM83 -> 663.4442 | AO82: =AN83 -> 660.10284 | AP82: =AO83 -> 642.15973 | AQ82: =AM82 -> 605.992
B83: Total Cash and ST Investments, Ending | D83: =D82+D80 -> 162.63119 | E83: =E82+E80 -> 322.80265 | F83: =F82+F80 -> 296.20918 | G83: =G82+G80 -> 228.1001 | H83: =H80+H82 -> 228.1001 | I83: =I82+I80 -> 268.0867 | J83: =J82+J80 -> 532.96034 | K83: =K82+K80 -> 465.50434 | L83: =L82+L80 -> 514.216 | M83: =M80+M82 -> 514.216 | N83: =N82+N80 -> 471.931 | O83: =O82+O80 -> 423.178 | P83: =P82+P80 -> 345.725 | Q83: =Q82+Q80 -> 278.466 | R83: =R80+R82 -> 278.466 | S83: =S82+S80 -> 178.44295 | T83: =T82+T80 -> 197.90377 | U83: =U82+U80 -> 369.80596 | V83: =V82+V80 -> 303.73118 | W83: =W80+W82 -> 303.73118 | X83: =X82+X80 -> 224.55794 | Y83: =Y82+Y80 -> 203.07741 | Z83: =Z82+Z80 -> 133.52737 | AA83: =AA82+AA80 -> 166.60703 | AB83: =AB80+AB82 -> 166.60703 | AC83: =AC82+AC80 -> 80.7923 | AD83: =AD82+AD80 -> 479.67203 | AE83: =AE82+AE80 -> 388.87803 | AF83: =AF82+AF80 -> 341.83503 | AG83: =AG80+AG82 -> 341.83503 | AH83: =AH82+AH80 -> 153.435 | AI83: =AI82+AI80 -> 188.088 | AJ83: =AJ82+AJ80 -> 660.627 | AK83: =AK82+AK80 -> 605.992 | AL83: =AL80+AL82 -> 605.992 | AM83: =AM82+AM80 -> 663.4442 | AN83: =AN82+AN80 -> 660.10284 | AO83: =AO82+AO80 -> 642.15973 | AP83: =AP82+AP80 -> 660.21433 | AQ83: =AQ80+AQ82 -> 660.21433

Sheet Diagnostics
C2: Diagnostics Segment | D2: 1Q19 | E2: 2Q19 | F2: 3Q19 | G2: 4Q19 | H2: FY19 | I2: 1Q20 | J2: 2Q20 | K2: 3Q20 | L2: 4Q20 | M2: FY20 | N2: 1Q21 | O2: 2Q21 | P2: 3Q21 | Q2: 4Q21 | R2: FY21 | S2: 1Q22 | T2: 2Q22 | U2: 3Q22 | V2: 4Q22 | W2: FY22 | X2: 1Q23 | Y2: 2Q23 | Z2: 3Q23 | AA2: 4Q23 | AB2: FY23 | AC2: 1Q24 | AD2: 2Q24 | AE2: 3Q24 | AF2: 4Q24 | AG2: FY24 | AH2: 1Q25 | AI2: 2Q25 | AJ2: 3Q25 | AK2: 4Q25 | AL2: FY25E | AM2: 1Q26E | AN2: 2Q26E | AO2: 3Q26E | AP2: 4Q26E | AQ2: FY26E
AK3: =+AK13/IS!AK15 -> 0.27068906 | AL3: =+AL6/IS!AL15 -> 0.43951473
C4: Total Diagnostics Revenue | D4: =D6+D18+D23 -> 4.4874457 | E4: =E6+E18+E23 -> 5.8740361 | F4: =F6+F18+F23 -> 8.7568856 | G4: =G6+G18+G23 -> 8.7716656 | H4: =H6+H18+H23 -> 27.890033 | I4: =I6+I18+I23 -> 13.645173 | J4: =J6+J18+J23 -> 12.499903 | K4: =K6+K18+K23 -> 47.078495 | ... AC4: =AC6+AC18+AC23 -> 102.56942 | AD4: 112.324 | AE4: 116.422 | AF4: 120.434 | AG4: =AG6+AG18+AG23 -> 451.61836 | AH4: 193.804 | AI4: 241.843 | AJ4: 252.878 | AK4: 266.856 | AL4: =AL6+AL18+AL23 -> 592.601 | AM4: =AM6+AM13+AM23 -> 258.2497 | AN4: =AN6+AN13+AN23 -> 298.36928 | AO4: =AO6+AO13+AO23 -> 307.97813 | AP4: =AP6+AP13+AP23 -> 314.34736 | AQ4: =AQ6+AQ18+AQ23 -> 758.90147
C5: YoY Growth (%) | I5: =IFERROR((I4/D4)-1,"") -> 2.040744 | J5: =IFERROR((J4/E4)-1,"") -> 1.1279922 | K5: =IFERROR((K4/F4)-1,"") -> 4.3761688 | L5: =IFERROR((L4/G4)-1,"") -> 7.9706124 | M5: =IFERROR((M4/H4)-1,"") -> 4.4467768 | N5: =IFERROR((N4/I4)-1,"") -> 3.3847027 | O5: =IFERROR((O4/J4)-1,"") -> 3.2456685 | P5: =IFERROR((P4/K4)-1,"") -> -0.11607818 | ... AQ5: =IFERROR((AQ4/AL4)-1,"") -> 0.28062806
C6: Clinical Oncology Revenue | D6: =(D8*D10)/1000000 -> 4.2726457 | E6: =(E8*E10)/1000000 -> 5.7144361 | F6: =(F8*F10)/1000000 -> 7.843159 | G6: =(G8*G10)/1000000 -> 7.8686055 | H6: =SUM(D6:G6) -> 25.698846 | I6: =(I8*I10)/1000000 -> 10.335529 | J6: =(J8*J10)/1000000 -> 9.410869 | K6: =(K8*K10)/1000000 -> 13.223688 | L6: =(L8*L10)/1000000 -> 14.301035 | M6: =SUM(I6:L6) -> 47.271122 | N6: =(N8*N10)/1000000 -> 14.186112 | O6: =(O8*O10)/1000000 -> 15.209976 | P6: =(P8*P10)/1000000 -> 18.785738 | Q6: =(Q8*Q10)/1000000 -> 21.106912 | R6: =SUM(N6:Q6) -> 69.288738 | S6: =(S8*S10)/1000000 -> 20.367999 | T6: =(T8*T10)/1000000 -> 34.41437 | U6: =(U8*U10)/1000000 -> 38.989696 | V6: =(V8*V10)/1000000 -> 41.792016 | W6: =SUM(S6:V6) -> 135.56408 | X6: =(X8*X10)/1000000 -> 69.088166 | Y6: =(Y8*Y10)/1000000 -> 80.188975 | Z6: =(Z8*Z10)/1000000 -> 86.188424 | AA6: =(AA8*AA10)/1000000 -> 82.098982 | AB6: =SUM(X6:AA6) -> 317.56455 | AC6: =(AC8*AC10)/1000000 -> 90.777101 | AD6: =(AD8*AD10)/1000000 -> 99.75 | AE6: =(AE8*AE10)/1000000 -> 105.6419 | AF6: =(AF8*AF10)/1000000 -> 111.03244 | AG6: =SUM(AC6:AF6) -> 407.20144 | AH6: =(AH8*AH10)/1000000 -> 119.25 | AI6: =(AI8*AI10)/1000000 -> 132.72 | AJ6: 139.5 | AK6: 167.5 | AL6: =SUM(AH6:AK6) -> 558.97 | AM6: =(AM8*AM10)/1000000 -> 158.4 | AN6: =(AN8*AN10)/1000000 -> 176.4 | AO6: =(AO8*AO10)/1000000 -> 187.03125 | AP6: =(AP8*AP10)/1000000 -> 203.79576 | AQ6: =SUM(AM6:AP6) -> 725.62701
C7: YoY Growth (%) | I7: =IFERROR((I6/D6)-1,"") -> 1.4189997 | J7: =IFERROR((J6/E6)-1,"") -> 0.64685873 | K7: =IFERROR((K6/F6)-1,"") -> 0.68601559 | L7: =IFERROR((L6/G6)-1,"") -> 0.81748028 | M7: =IFERROR((M6/H6)-1,"") -> 0.83942582 | N7: =IFERROR((N6/I6)-1,"") -> 0.37255791 | O7: =IFERROR((O6/J6)-1,"") -> 0.61621381 | P7: =IFERROR((P6/K6)-1,"") -> 0.42061255 | ... AQ7: =IFERROR((AQ6/AL6)-1,"") -> 0.29815019
C8: Volume | D8: 7003 | E8: 9198 | F8: 11102 | G8: 13265 | H8: =SUM(D8:G8) -> 40568 | I8: 14066 | J8: 12201 | K8: 17052 | L8: 20931 | M8: =SUM(I8:L8) -> 64250 | N8: 15894 | O8: 25669 | P8: 26867 | Q8: 28566 | R8: =SUM(N8:Q8) -> 96996 | S8: 30561 | T8: 35545 | U8: 37661 | V8: 44199 | W8: =SUM(S8:V8) -> 147966 | X8: 48419.9 | Y8: 55300 | Z8: 55728 | AA8: 59241 | AB8: =SUM(X8:AA8) -> 218688.9 | AC8: 62718 | AD8: 66500 | AE8: =Z8*(1+AE9) -> 69046.992 | AF8: =AA8*(1+AF9) -> 72570.225 | AG8: =SUM(AC8:AF8) -> 270835.22 | AH8: 75000 | AI8: 84000 | AJ8: 87500 | AK8: 94000 | AL8: =SUM(AH8:AK8) -> 340500 | AM8: =AH8*(1+AM9) -> 96000 | AN8: =AI8*(1+AN9) -> 105000 | AO8: =AJ8*(1+AO9) -> 109375 | AP8: =AK8*(1+AP9) -> 117124 | AQ8: =SUM(AM8:AP8) -> 427499
C9: YoY Growth (%) | I9: =IFERROR((I8/D8)-1,"") -> 1.0085678 | J9: =IFERROR((J8/E8)-1,"") -> 0.32648402 | K9: =IFERROR((K8/F8)-1,"") -> 0.53593947 | L9: =IFERROR((L8/G8)-1,"") -> 0.5779118 | M9: =IFERROR((M8/H8)-1,"") -> 0.5837606 | N9: =IFERROR((N8/I8)-1,"") -> 0.12995877 | O9: =IFERROR((O8/J8)-1,"") -> 1.1038439 | P9: =IFERROR((P8/K8)-1,"") -> 0.57559231 | ... AD9: =IFERROR((AD8/Y8)-1,"") -> 0.20253165 | AE9: 0.239 | AF9: 0.225 | AG9: =IFERROR((AG8/AB8)-1,"") -> 0.23844977 | AH9: =IFERROR((AH8/AC8)-1,"") -> 0.19582895 | AI9: =IFERROR((AI8/AD8)-1,"") -> 0.26315789 | AJ9: =IFERROR((AJ8/AE8)-1,"") -> 0.26725289 | AK9: 0.29 | AL9: =IFERROR((AL8/AG8)-1,"") -> 0.25722203 | AM9: 0.28 | AN9: 0.25 | AO9: 0.25 | AP9: 0.246 | AQ9: =IFERROR((AQ8/AL8)-1,"") -> 0.25550367
C10: Average Revenue Per Test | D10: 610.11648 | E10: 621.26942 | F10: 706.46361 | G10: 593.18549 | H10: =(H6*1000000)/H8 -> 633.4758 | I10: 734.78806 | J10: 771.31948 | K10: 775.49193 | L10: 683.24664 | M10: =(M6*1000000)/M8 -> 735.7373 | N10: 892.5451 | O10: 592.54262 | P10: 699.21233 | Q10: 738.8823 | R10: =(R6*1000000)/R8 -> 714.34634 | S10: 666.47032 | T10: 968.19159 | U10: 1035.2804 | V10: 945.54211 | W10: =(W6*1000000)/W8 -> 916.18399 | X10: 1426.8548 | Y10: 1450.0719 | Z10: 1546.591 | AA10: 1385.8473 | AB10: =(AB6*1000000)/AB8 -> 1452.1292 | AC10: 1447.3851 | AD10: 1500 | AE10: 1530 | AF10: 1530 | AG10: =(AG6*1000000)/AG8 -> 1503.5026 | AH10: 1590 | AI10: 1580 | AJ10: 1600 | AK10: 1640 | AL10: =(AL6*1000000)/AL8 -> 1641.6153 | AM10: 1650 | AN10: 1680 | AO10: 1710 | AP10: 1740 | AQ10: =(AQ6*1000000)/AQ8 -> 1697.3771
C11: YoY Growth (%) | M11: =IFERROR((M10/H10)-1,"") -> 0.16142921 | N11: =IFERROR((N10/I10)-1,"") -> 0.21469734 | O11: =IFERROR((O10/J10)-1,"") -> -0.23178056 | P11: =IFERROR((P10/K10)-1,"") -> -0.098362852 | Q11: =IFERROR((Q10/L10)-1,"") -> 0.081428378 | R11: =IFERROR((R10/M10)-1,"") -> -0.029074179 | S11: =IFERROR((S10/N10)-1,"") -> -0.25329228 | T11: =IFERROR((T10/O10)-1,"") -> 0.63396111 | ... AQ11: =IFERROR((AQ10/AL10)-1,"") -> 0.033967655
C13: Hereditary | AC13: 51.64 | AD13: 72.8 | AE13: 77.25 | AF13: 86.2 | AG13: =(AG15*AG16)/1000000 -> 0 | AH13: 63.5 | AI13: =(AI15*AI16)/1000000 -> 97.28 | AJ13: 102.6 | AK13: 99.4 | AL13: =SUM(AH13:AK13) -> 362.78 | AM13: =(AM15*AM16)/1000000 -> 88.243 | AN13: =(AN15*AN16)/1000000 -> 110.6 | AO13: =(AO15*AO16)/1000000 -> 110.6 | AP13: =(AP15*AP16)/1000000 -> 110.6 | AQ13: =SUM(AM13:AP13) -> 420.043
C14: YoY Growth (%) | AG14: =IFERROR((AG13/AB13)-1,"") | AH14: =IFERROR((AH13/AC13)-1,"") -> 0.22966692 | AI14: =IFERROR((AI13/AD13)-1,"") -> 0.33626374 | AJ14: =IFERROR((AJ13/AE13)-1,"") -> 0.32815534 | AK14: =IFERROR((AK13/AF13)-1,"") -> 0.15313225 | AL14: =IFERROR((AL13/AG13)-1,"") | AM14: =IFERROR((AM13/AH13)-1,"") -> 0.38965354 | AN14: =IFERROR((AN13/AI13)-1,"") -> 0.13692434 | ... AQ14: =IFERROR((AQ13/AL13)-1,"") -> 0.15784497
C15: Volume | AC15: 63500 | AD15: 97000 | AE15: 94500 | AF15: 101500 | AG15: 0 | AH15: 78000 | AI15: 128000 | AJ15: 129500 | AK15: 125000 | AL15: 0 | AM15: 111700 | AN15: 140000 | AO15: 140000 | AP15: 140000 | AQ15: 0
C16: Average Revenue Per Test | AC16: =(AC13*1000000)/AC15 -> 813.22835 | AD16: =(AD13*1000000)/AD15 -> 750.51546 | AE16: =(AE13*1000000)/AE15 -> 817.46032 | AF16: =(AF13*1000000)/AF15 -> 849.26108 | AG16: 0 | AH16: 770 | AI16: 760 | AJ16: 790 | AK16: 800 | AL16: 0 | AM16: 790 | AN16: 790 | AO16: 790 | AP16: 790 | AQ16: 0
AN17: =AN15/AI15-1 -> 0.09375 | AO17: =AO15/AJ15-1 -> 0.081081081 | AP17: =AP15/AK15-1 -> 0.12
C18: Infectious Disease Revenue | D18: =(D20*D21)/1000000 -> 0 | E18: =(E20*E21)/1000000 -> 0 | F18: =(F20*F21)/1000000 -> 0 | G18: =(G20*G21)/1000000 -> 0 | H18: =SUM(D18:G18) -> 0 | I18: =(I20*I21)/1000000 -> 0 | J18: =(J20*J21)/1000000 -> 0.24076 | K18: =(K20*K21)/1000000 -> 29.489336 | L18: =(L20*L21)/1000000 -> 60.015142 | M18: =SUM(I18:L18) -> 89.745238 | N18: =(N20*N21)/1000000 -> 38.88664 | O18: =(O20*O21)/1000000 -> 32.679646 | P18: =(P20*P21)/1000000 -> 13.372756 | Q18: =(Q20*Q21)/1000000 -> 9.7834072 | R18: =SUM(N18:Q18) -> 94.722449 | S18: =(S20*S21)/1000000 -> 8.9822822 | T18: =(T20*T21)/1000000 -> 3.6182245 | U18: =(U20*U21)/1000000 -> 4.8911434 | V18: =(V20*V21)/1000000 -> 4.6742693 | W18: =SUM(S18:V18) -> 22.165919 | X18: =(X20*X21)/1000000 -> 2.6384504 | Y18: 0.07304822 | Z18: =(Z20*Z21)/1000000 -> 0 | AA18: =(AA20*AA21)/1000000 -> 0 | AB18: =SUM(X18:AA18) -> 2.7114986 | AC18: 0.13105811 | AD18: =(AD20*AD21)/1000000 -> 0 | AE18: =(AE20*AE21)/1000000 -> 0 | AF18: =(AF20*AF21)/1000000 -> 0 | AG18: =(AG20*AG21)/1000000 -> 0 | AH18: =(AH20*AH21)/1000000 -> 0 | AI18: =(AI20*AI21)/1000000 -> 0 | AJ18: =(AJ20*AJ21)/1000000 -> 0 | AK18: =(AK20*AK21)/1000000 -> 0 | ... AQ18: =(AQ20*AQ21)/1000000 -> 0
C19: YoY Growth (%) | I19: =IFERROR((I18/D18)-1,"") | J19: =IFERROR((J18/E18)-1,"") | K19: =IFERROR((K18/F18)-1,"") | L19: =IFERROR((L18/G18)-1,"") | M19: =IFERROR((M18/H18)-1,"") | N19: =IFERROR((N18/I18)-1,"") | O19: =IFERROR((O18/J18)-1,"") -> 134.73536 | P19: =IFERROR((P18/K18)-1,"") -> -0.54652232 | ... X19: =IFERROR((X18/S18)-1,"") -> -0.70626057 | Y19: =IFERROR((Y18/M18)-1,"") -> -0.99918605 | Z19: =IFERROR((Z18/U18)-1,"") -> -1 | AA19: =IFERROR((AA18/V18)-1,"") -> -1 | AB19: =IFERROR((AB18/W18)-1,"") -> -0.87767263 | AC19: =IFERROR((AC18/X18)-1,"") -> -0.95032762 | AE19: =IFERROR((AE18/Z18)-1,"") | AF19: =IFERROR((AF18/AA18)-1,"") | AG19: =IFERROR((AG18/AB18)-1,"") -> -1 | AH19: =IFERROR((AH18/AC18)-1,"") -> -1 | AJ19: =IFERROR((AJ18/AE18)-1,"") | AK19: =IFERROR((AK18/AF18)-1,"") | AL19: =IFERROR((AL18/AG18)-1,"") | AM19: =IFERROR((AM18/AH18)-1,"") | AO19: =IFERROR((AO18/AJ18)-1,"") | AP19: =IFERROR((AP18/AK18)-1,"") | AQ19: =IFERROR((AQ18/AL18)-1,"")
C20: Volume | D20: 0 | E20: 0 | F20: 0 | G20: 0 | H20: =SUM(D20:G20) -> 0 | I20: 0 | J20: 3999 | K20: 438918 | L20: 898253 | M20: =SUM(I20:L20) -> 1341170 | N20: 557953 | O20: 257861 | P20: 70396 | Q20: 86497 | R20: =SUM(N20:Q20) -> 972707 | S20: 143694 | T20: 87155 | U20: 104614 | V20: 101768 | W20: =SUM(S20:V20) -> 437231 | X20: 59856 | Y20: 0 | Z20: 0 | AA20: 0 | AB20: =SUM(X20:AA20) -> 59856 | AC20: 0 | AD20: 0 | AE20: 0 | AF20: 0 | AG20: 0 | AH20: 0 | AI20: 0 | AJ20: 0 | AK20: 0 | AL20: 0 | AM20: 0 | AN20: 0 | AO20: 0 | AP20: 0 | AQ20: 0
C21: Average Revenue Per Test | D21: 0 | E21: 0 | F21: 0 | G21: 0 | H21: 0 | I21: 0 | J21: 60.205051 | K21: 67.186436 | L21: 66.813183 | M21: =(M18*1000000)/M20 -> 66.915632 | N21: 69.695189 | O21: 126.73358 | P21: 189.96471 | Q21: 113.1069 | R21: =(R18*1000000)/R20 -> 97.380249 | S21: 62.509793 | T21: 41.514824 | U21: 46.754195 | V21: 45.930639 | W21: =(W18*1000000)/W20 -> 50.69613 | X21: 44.079966 | Y21: NA | Z21: 0 | AA21: 0 | AB21: =IFERROR((AB18*1000000)/AB20,0) -> 45.300365 | AC21: 0 | AD21: 0 | AE21: 0 | AF21: 0 | AG21: 0 | AH21: 0 | AI21: 0 | AJ21: 0 | AK21: 0 | AL21: 0 | AM21: 0 | AN21: 0 | AO21: 0 | AP21: 0 | AQ21: 0
C23: Other Genomics Revenue (Life Sci Research + Neuro) | D23: 0.2148 | E23: 0.1596 | F23: 0.91372667 | G23: 0.90306009 | H23: =SUM(D23:G23) -> 2.1911868 | I23: 3.3096446 | J23: 2.8482742 | K23: 4.3654707 | L23: 4.3710351 | M23: =SUM(I23:L23) -> 14.894425 | N23: 6.7572768 | O23: 5.1808228 | P23: 9.4552156 | Q23: 9.6077293 | R23: =SUM(N23:Q23) -> 31.001044 | S23: 8.5515669 | T23: 9.3890141 | U23: 10.850921 | V23: 11.462989 | W23: =SUM(S23:V23) -> 40.254491 | X23: 10.331552 | Y23: 11.661525 | Z23: 10.595888 | AA23: 10.092492 | AB23: =SUM(X23:AA23) -> 42.681457 | AC23: 11.661259 | AD23: =AD4-AD6 -> 12.574 | AE23: =AE4-AE6 -> 10.780102 | AF23: =AF4-AF6 -> 9.4015557 | AG23: =SUM(AC23:AF23) -> 44.416917 | AH23: =AH4-AH6-AH13 -> 11.054 | AI23: =AI4-AI6-AI13 -> 11.843 | AJ23: =AJ4-AJ6-AJ13 -> 10.778 | AK23: =AK4-AK6-AK13 -> -0.044 | AL23: =SUM(AH23:AK23) -> 33.631 | AM23: =AH23*(1+AM24) -> 11.6067 | AN23: =AI23*(1+AN24) -> 11.36928 | AO23: =AJ23*(1+AO24) -> 10.34688 | AP23: =AK23*(1+AP24) -> -0.0484 | AQ23: =SUM(AM23:AP23) -> 33.27446
C24: YoY Growth (%) | I24: =IFERROR((I23/D23)-1,"") -> 14.408029 | J24: =IFERROR((J23/E23)-1,"") -> 16.84633 | K24: =IFERROR((K23/F23)-1,"") -> 3.7776549 | L24: =IFERROR((L23/G23)-1,"") -> 3.8402483 | M24: =IFERROR((M23/H23)-1,"") -> 5.7974236 | N24: =IFERROR((N23/I23)-1,"") -> 1.0416926 | O24: =IFERROR((O23/J23)-1,"") -> 0.81893397 | P24: =IFERROR((P23/K23)-1,"") -> 1.1659097 | ... AL24: =IFERROR((AL23/AG23)-1,"") -> -0.24283354 | AM24: 0.05 | AN24: -0.04 | AO24: -0.04 | AP24: 0.1 | AQ24: =IFERROR((AQ23/AL23)-1,"") -> -0.010601528
C26: Total Genomics Cost of Revenue | D26: =D29+D37+D44 -> 6.1617353 | E26: =E29+E37+E44 -> 8.8999742 | F26: =F29+F37+F44 -> 10.816278 | G26: =G29+G37+G44 -> 13.807414 | H26: =H29+H37+H44 -> 39.685401 | I26: =I29+I37+I44 -> 16.832318 | J26: =J29+J37+J44 -> 17.227103 | K26: =K29+K37+K44 -> 46.356053 | ... AC26: =AC29+AC37+AC44 -> 52.834757 | AD26: 68.324 | AE26: 60.126 | AF26: 62.182 | AG26: =AG29+AG37+AG44 -> 227.00109 | AH26: =84.783-1.035-0.048 -> 83.7 | AI26: =99.756-1.42-0.254 -> 98.082 | AJ26: =98.643-1.631-0.036 -> 96.976 | AK26: =102.92-2.138-0.035 -> 100.747 | AL26: =AL29+AL37+AL44 -> 447.5147 | AM26: =AM29+AM37+AM44 -> 101.80962 | AN26: =AN29+AN37+AN44 -> 118.83941 | AO26: =AO29+AO37+AO44 -> 120.29982 | AP26: =AP29+AP37+AP44 -> 118.2509 | AQ26: =AQ29+AQ37+AQ44 -> 488.03208
C27: Margin (%) | D27: =IFERROR(1-(D26/D4),"") -> -0.37310527 | E27: =IFERROR(1-(E26/E4),"") -> -0.5151378 | F27: =IFERROR(1-(F26/F4),"") -> -0.23517405 | G27: =IFERROR(1-(G26/G4),"") -> -0.57409257 | H27: =IFERROR(1-(H26/H4),"") -> -0.42292413 | I27: =IFERROR(1-(I26/I4),"") -> -0.23357305 | J27: =IFERROR(1-(J26/J4),"") -> -0.37817894 | K27: =IFERROR(1-(K26/K4),"") -> 0.015345474 | ... AQ27: =IFERROR(1-(AQ26/AQ4),"") -> 0.35692301
C29: Clinical Oncology Cost of Revenue | D29: =(D32*D34)/1000000 -> 5.5885261 | E29: =(E32*E34)/1000000 -> 7.9259288 | F29: =(F32*F34)/1000000 -> 10.018053 | G29: =(G32*G34)/1000000 -> 12.147459 | H29: =SUM(D29:G29) -> 35.679967 | I29: =(I32*I34)/1000000 -> 13.215356 | J29: =(J32*J34)/1000000 -> 12.475363 | K29: =(K32*K34)/1000000 -> 15.369851 | L29: =(L32*L34)/1000000 -> 17.044644 | M29: =SUM(I29:L29) -> 58.105214 | N29: =(N32*N34)/1000000 -> 16.638107 | O29: =(O32*O34)/1000000 -> 16.507632 | P29: =(P32*P34)/1000000 -> 18.761066 | Q29: =(Q32*Q34)/1000000 -> 21.025492 | R29: =SUM(N29:Q29) -> 72.932297 | S29: =(S32*S34)/1000000 -> 21.609242 | T29: =(T32*T34)/1000000 -> 22.892285 | U29: =(U32*U34)/1000000 -> 25.149735 | V29: =(V32*V34)/1000000 -> 30.514611 | W29: =SUM(S29:V29) -> 100.16587 | X29: =(X32*X34)/1000000 -> 35.67523 | Y29: =(Y32*Y34)/1000000 -> 39.101813 | Z29: =(Z32*Z34)/1000000 -> 39.83609 | AA29: =(AA32*AA34)/1000000 -> 44.609081 | AB29: =SUM(X29:AA29) -> 159.22221 | AC29: =(AC32*AC34)/1000000 -> 45.487882 | AD29: =(AD32*AD34)/1000000 -> 48.8775 | AE29: =(AE32*AE34)/1000000 -> 51.785244 | AF29: =(AF32*AF34)/1000000 -> 54.79052 | AG29: =SUM(AC29:AF29) -> 200.94115 | AH29: =(AH32*AH34)/1000000 -> 112.302 | AI29: =(AI32*AI34)/1000000 -> 97.52 | AJ29: =(AJ32*AJ34)/1000000 -> 99.82 | AK29: =(AK32*AK34)/1000000 -> 100.74 | AL29: =SUM(AH29:AK29) -> 410.382 | AM29: =(AM32*AM34)/1000000 -> 95.542 | AN29: =(AN32*AN34)/1000000 -> 112.7 | AO29: =(AO32*AO34)/1000000 -> 114.7125 | AP29: =(AP32*AP34)/1000000 -> 118.27704 | AQ29: =SUM(AM29:AP29) -> 441.23154
C30: Margin (%) | D30: =IFERROR(1-(D29/D6),"") -> -0.30797789 | E30: =IFERROR(1-(E29/E6),"") -> -0.38700103 | F30: =IFERROR(1-(F29/F6),"") -> -0.2772982 | G30: =IFERROR(1-(G29/G6),"") -> -0.54378803 | H30: =IFERROR(1-(H29/H6),"") -> -0.38838788 | I30: =IFERROR(1-(I29/I6),"") -> -0.27863375 | J30: =IFERROR(1-(J29/J6),"") -> -0.32563349 | K30: =IFERROR(1-(K29/K6),"") -> -0.16229682 | ... AQ30: =IFERROR(1-(AQ29/AQ6),"") -> 0.39193066
C32: Volume | D32: =D8 -> 7003 | E32: =E8 -> 9198 | F32: =F8 -> 11102 | G32: =G8 -> 13265 | H32: =H8 -> 40568 | I32: =I8 -> 14066 | J32: =J8 -> 12201 | K32: =K8 -> 17052 | ... AF32: =AF8 -> 72570.225 | AG32: =SUM(AC32:AF32) -> 270835.22 | AH32: =AH8+AH15 -> 153000 | AI32: =AI8+AI15 -> 212000 | AJ32: =AJ8+AJ15 -> 217000 | AK32: =AK8+AK15 -> 219000 | AL32: =SUM(AH32:AK32) -> 801000 | AM32: =AM8+AM15 -> 207700 | AN32: =AN8+AN15 -> 245000 | AO32: =AO8+AO15 -> 249375 | AP32: =AP8+AP15 -> 257124 | AQ32: =SUM(AM32:AP32) -> 959199
C34: Cost Per Test | D34: 798.01887 | E34: 861.70132 | F34: 902.36469 | G34: 915.75266 | H34: =(H29*1000000)/H32 -> 879.51012 | I34: 939.52482 | J34: 1022.4869 | K34: 901.3518 | L34: 814.32535 | M34: =(M29*1000000)/M32 -> 904.36131 | N34: 1046.8169 | O34: 643.09601 | P34: 698.29406 | Q34: 736.03205 | R34: =(R29*1000000)/R32 -> 751.91036 | S34: 707.08556 | T34: 644.03671 | U34: 667.79255 | V34: 690.39143 | W34: =(W29*1000000)/W32 -> 676.95195 | X34: 736.7886 | Y34: 707.08522 | Z34: 714.83079 | AA34: 753.01026 | AB34: =(AB29*1000000)/AB32 -> 728.07634 | AC34: 725.27634 | AD34: 735 | AE34: 750 | AF34: 755 | AG34: =(AG29*1000000)/AG32 -> 741.93138 | AH34: 734 | AI34: 460 | AJ34: 460 | AK34: 460 | AL34: =(AL29*1000000)/AL32 -> 512.33708 | AM34: 460 | AN34: 460 | AO34: 460 | AP34: 460 | AQ34: =(AQ29*1000000)/AQ32 -> 460
C37: Infectious Disease Cost of Revenue | D37: 0 | E37: 0 | F37: 0 | G37: 0 | H37: =SUM(D37:G37) -> 0 | I37: 0 | J37: =(J40*J42)/1000000 -> 0.17917546 | K37: =(K40*K42)/1000000 -> 26.187444 | L37: =(L40*L42)/1000000 -> 50.119842 | M37: =SUM(I37:L37) -> 76.486461 | N37: =(N40*N42)/1000000 -> 36.094652 | O37: =(O40*O42)/1000000 -> 17.771925 | P37: =(P40*P42)/1000000 -> 6.498019 | Q37: =(Q40*Q42)/1000000 -> 5.3292812 | R37: =SUM(N37:Q37) -> 65.693878 | S37: =(S40*S42)/1000000 -> 10.008739 | T37: =(T40*T42)/1000000 -> 3.9620969 | U37: =(U40*U42)/1000000 -> 2.8131078 | V37: =(V40*V42)/1000000 -> 2.1694887 | W37: =SUM(S37:V37) -> 18.953433 | X37: =(X40*X42)/1000000 -> 1.4438402 | Y37: -0.03796402 | Z37: 0.03014089 | AA37: =(AA40*AA42)/1000000 -> 0 | AB37: =SUM(X37:AA37) -> 1.4360171 | AC37: =(AC40*AC42)/1000000 -> 0 | AD37: =(AD40*AD42)/1000000 -> 0 | AE37: =(AE40*AE42)/1000000 -> 0 | AF37: =(AF40*AF42)/1000000 -> 0 | AG37: =SUM(AC37:AF37) -> 0 | AH37: =(AH40*AH42)/1000000 -> 0 | AI37: =(AI40*AI42)/1000000 -> 0 | AJ37: =(AJ40*AJ42)/1000000 -> 0 | AK37: =(AK40*AK42)/1000000 -> 0 | AL37: =SUM(AH37:AK37) -> 0 | AM37: =(AM40*AM42)/1000000 -> 0 | AN37: =(AN40*AN42)/1000000 -> 0 | AO37: =(AO40*AO42)/1000000 -> 0 | AP37: =(AP40*AP42)/1000000 -> 0 | AQ37: =SUM(AM37:AP37) -> 0
C38: Margin (%) | D38: =IFERROR(1-(D37/D18),"") | E38: =IFERROR(1-(E37/E18),"") | F38: =IFERROR(1-(F37/F18),"") | G38: =IFERROR(1-(G37/G18),"") | H38: =IFERROR(1-(H37/H18),"") | I38: =IFERROR(1-(I37/I18),"") | J38: =IFERROR(1-(J37/J18),"") -> 0.25579224 | K38: =IFERROR(1-(K37/K18),"") -> 0.111969 | ... AB38: =IFERROR(1-(AB37/AB18),"") -> 0.47039728 | AE38: =IFERROR(1-(AE37/AE18),"") | AF38: =IFERROR(1-(AF37/AF18),"") | AG38: =IFERROR(1-(AG37/AG18),"") | AH38: =IFERROR(1-(AH37/AH18),"") | AJ38: =IFERROR(1-(AJ37/AJ18),"") | AK38: =IFERROR(1-(AK37/AK18),"") | AL38: =IFERROR(1-(AL37/AL18),"") | AM38: =IFERROR(1-(AM37/AM18),"") | AO38: =IFERROR(1-(AO37/AO18),"") | AP38: =IFERROR(1-(AP37/AP18),"") | AQ38: =IFERROR(1-(AQ37/AQ18),"")
C40: Volume | D40: =D20 -> 0 | E40: =E20 -> 0 | F40: =F20 -> 0 | G40: =G20 -> 0 | H40: =H20 -> 0 | I40: =I20 -> 0 | J40: =J20 -> 3999 | K40: =K20 -> 438918 | ... AQ40: =AQ20 -> 0
C42: Cost Per Test | D42: 0 | E42: 0 | F42: 0 | G42: 0 | H42: 0 | I42: 0 | J42: 44.805066 | K42: 59.663638 | L42: 55.797021 | M42: =(M37*1000000)/M40 -> 57.029654 | N42: 64.691206 | O42: 68.920563 | P42: 92.306651 | Q42: 61.612324 | R42: =(R37*1000000)/R40 -> 67.53717 | S42: 69.653148 | T42: 45.460351 | U42: 26.890357 | V42: 21.317985 | W42: =(W37*1000000)/W40 -> 43.348786 | X42: 24.121896 | Y42: 0 | Z42: 0 | AA42: 0 | AB42: =IFERROR((AB37*1000000)/AB40,0) -> 23.991197 | AC42: 0 | AD42: 0 | AE42: 0 | AF42: 0 | AG42: 0 | AH42: 0 | AI42: 0 | AJ42: 0 | AK42: 0 | AL42: 0 | AM42: 0 | AN42: 0 | AO42: 0 | AP42: 0 | AQ42: 0
C44: Other Genomics Cost of Revenue | D44: 0.57320921 | E44: 0.97404538 | F44: 0.79822513 | G44: 1.6599546 | H44: =SUM(D44:G44) -> 4.0054344 | I44: 3.6169621 | J44: 4.5725648 | K44: 4.7987579 | L44: 4.6181233 | M44: =SUM(I44:L44) -> 17.606408 | N44: 5.4193401 | O44: 5.070587 | P44: 6.5216282 | Q44: 6.6377442 | R44: =SUM(N44:Q44) -> 23.649299 | S44: 7.4655239 | T44: 7.4119719 | U44: 7.4387575 | V44: 8.8190076 | W44: =SUM(S44:V44) -> 31.135261 | X44: 8.1612075 | Y44: 7.8971809 | Z44: 6.673918 | AA44: 5.7276531 | AB44: =SUM(X44:AA44) -> 28.459959 | AC44: 7.3468754 | AD44: =AD23*(1-AD45) -> 8.29884 | AE44: =AE23*(1-AE45) -> 5.7134542 | AF44: =AF23*(1-AF45) -> 4.7007779 | AG44: =SUM(AC44:AF44) -> 26.059947 | AH44: =AH23*(1-AH45) -> 5.96916 | AI44: =AI23*(1-AI45) -> 6.39522 | AJ44: =AJ23*(1-AJ45) -> 5.82012 | AK44: =AK23*(1-AK45) -> -0.02376 | AL44: 37.132703 | AM44: =AM23*(1-AM45) -> 6.267618 | AN44: =AN23*(1-AN45) -> 6.1394112 | AO44: =AO23*(1-AO45) -> 5.5873152 | AP44: =AP23*(1-AP45) -> -0.026136 | AQ44: 46.800535
C45: Margin (%) | D45: =IFERROR(1-(D44/D23),"") -> -1.6685717 | E45: =IFERROR(1-(E44/E23),"") -> -5.1030413 | F45: =IFERROR(1-(F44/F23),"") -> 0.1264071 | G45: =IFERROR(1-(G44/G23),"") -> -0.83814418 | H45: =IFERROR(1-(H44/H23),"") -> -0.82797489 | I45: =IFERROR(1-(I44/I23),"") -> -0.092855138 | J45: =IFERROR(1-(J44/J23),"") -> -0.6053808 | K45: =IFERROR(1-(K44/K23),"") -> -0.099253257 | ... AC45: =IFERROR(1-(AC44/AC23),"") -> 0.36997581 | AD45: 0.34 | AE45: 0.47 | AF45: 0.5 | AG45: =IFERROR(1-(AG44/AG23),"") -> 0.41328779 | AH45: 0.46 | AI45: 0.46 | AJ45: 0.46 | AK45: 0.46 | AL45: =IFERROR(1-(AL44/AL23),"") -> -0.10412128 | AM45: 0.46 | AN45: 0.46 | AO45: 0.46 | AP45: 0.46 | AQ45: =IFERROR(1-(AQ44/AQ23),"") -> -0.40650021
C47: Genomics Gross Profit | D47: =D4-D26 -> -1.6742896 | E47: =E4-E26 -> -3.025938 | F47: =F4-F26 -> -2.0593923 | G47: =G4-G26 -> -5.0357481 | H47: =SUM(D47:G47) -> -11.795368 | I47: =I4-I26 -> -3.1871447 | J47: =J4-J26 -> -4.7272002 | K47: =K4-K26 -> 0.7224418 | L47: =L4-L26 -> 6.9046037 | M47: =SUM(I47:L47) -> -0.2872994 | N47: =N4-N26 -> 1.6779288 | O47: =O4-O26 -> 13.720302 | P47: =P4-P26 -> 9.8329954 | Q47: =Q4-Q26 -> 7.5055316 | R47: =SUM(N47:Q47) -> 32.736758 | S47: =S4-S26 -> -1.1816568 | T47: =T4-T26 -> 13.155255 | U47: =U4-U26 -> 19.330159 | V47: =V4-V26 -> 16.426167 | W47: =SUM(S47:V47) -> 47.729925 | X47: =X4-X26 -> 36.77789 | Y47: =Y4-Y26 -> 44.962518 | Z47: =Z4-Z26 -> 50.244163 | AA47: =AA4-AA26 -> 41.854741 | AB47: =SUM(X47:AA47) -> 173.83931 | AC47: =AC4-AC26 -> 49.734662 | AD47: =AD4-AD26+11.327+0.136 -> 55.463 | AE47: =AE4-AE26+1.083+0.026 -> 57.405 | AF47: =AF4-AF26+1.215+0.293 -> 59.76 | AG47: =AG4-AG26 -> 224.61727 | AH47: =AH4-AH26 -> 110.104 | AI47: =AI4-AI26 -> 143.761 | AJ47: =AJ4-AJ26 -> 155.902 | AK47: =AK4-AK26 -> 166.109 | AL47: =AL4-AL26 -> 145.0863 | AM47: =AM4-AM26 -> 156.44008 | AN47: =AN4-AN26 -> 179.52987 | ... AQ47: =AQ4-AQ26 -> 270.86939
C48: Margin (%) | D48: =D27 -> -0.37310527 | E48: =E27 -> -0.5151378 | F48: =F27 -> -0.23517405 | G48: =G27 -> -0.57409257 | H48: =H27 -> -0.42292413 | I48: =I27 -> -0.23357305 | J48: =J27 -> -0.37817894 | K48: =K27 -> 0.015345474 | ... AC48: =AC27 -> 0.48488782 | AD48: =AD47/AD4 -> 0.49377693 | AE48: =AE27 -> 0.48355122 | AF48: =AF27 -> 0.48368401 | AG48: =AG27 -> 0.4973608 | AH48: =AH27 -> 0.56812037 | AI48: =AI27 -> 0.59443937 | AJ48: =AJ27 -> 0.61651073 | AK48: =AK27 -> 0.6224668 | AL48: =AL27 -> 0.24482965 | ... AQ48: =AQ27 -> 0.35692301

Sheet Data & Other
C5: Data & Other Segment | D5: 1Q19 | E5: 2Q19 | F5: 3Q19 | G5: 4Q19 | H5: FY19 | I5: 1Q20 | J5: 2Q20 | K5: 3Q20 | L5: 4Q20 | M5: FY20 | N5: 1Q21 | O5: 2Q21 | P5: 3Q21 | Q5: 4Q21 | R5: FY21 | S5: 1Q22 | T5: 2Q22 | U5: 3Q22 | V5: 4Q22 | W5: FY22 | X5: 1Q23 | Y5: 2Q23 | Z5: 3Q23 | AA5: 4Q23 | AB5: FY23 | AC5: 1Q24 | AD5: 2Q24 | AE5: 3Q24 | AF5: 4Q24 | AG5: FY24 | AH5: 1Q25 | AI5: 2Q25 | AJ5: 3Q25 | AK5: 4Q25 | AL5: FY25E | AM5: 1Q26E | AN5: 2Q26E | AO5: 3Q26E | AP5: 4Q26E | AQ5: FY26E
C7: Total Data & Other Revenue | D7: =SUM(D10,D13,D16) -> 3.1913215 | E7: =SUM(E10,E13,E16) -> 4.7110225 | F7: =SUM(F10,F13,F16) -> 6.5473935 | G7: =SUM(G10,G13,G16) -> 19.717319 | H7: =SUM(D7:G7) -> 34.167057 | I7: =SUM(I10,I13,I16) -> 4.5969503 | J7: =SUM(J10,J13,J16) -> 5.6771733 | K7: =SUM(K10,K13,K16) -> 3.654138 | L7: =SUM(L10,L13,L16) -> 22.164383 | M7: =SUM(I7:L7) -> 36.092645 | N7: =SUM(N10,N13,N16) -> 10.280028 | O7: =SUM(O10,O13,O16) -> 8.9152628 | P7: =SUM(P10,P13,P16) -> 10.833945 | Q7: =SUM(Q10,Q13,Q16) -> 32.811488 | R7: =SUM(N7:Q7) -> 62.840725 | S7: =SUM(S10,S13,S16) -> 22.84992 | T7: =SUM(T10,T13,T16) -> 26.297225 | U7: =SUM(U10,U13,U16) -> 30.839768 | V7: =SUM(V10,V13,V16) -> 42.697508 | W7: =SUM(S7:V7) -> 122.68442 | X7: =SUM(X10,X13,X16) -> 33.56625 | Y7: =SUM(Y10,Y13,Y16) -> 40.492787 | Z7: =SUM(Z10,Z13,Z16) -> 39.241917 | AA7: =SUM(AA10,AA13,AA16) -> 55.498725 | AB7: =SUM(X7:AA7) -> 168.79968 | AC7: =SUM(AC10,AC13,AC16) -> 43.250622 | AD7: 53.645 | AE7: 64.507 | AF7: 80.246 | AG7: =SUM(AG10,AG13,AG16) -> 241.64862 | AH7: 61.933 | AI7: 72.792 | AJ7: 81.328 | AK7: 100.355 | AL7: =SUM(AL10,AL13,AL16) -> 316.57152 | AM7: =SUM(AM10,AM13,AM16) -> 86.708248 | AN7: =SUM(AN10,AN13,AN16) -> 96.613063 | AO7: =SUM(AO10,AO13,AO16) -> 107.18766 | AP7: =SUM(AP10,AP13,AP16) -> 120.53203 | AQ7: =SUM(AQ10,AQ13,AQ16) -> 411.041
C8: YoY Growth (%) | I8: =IFERROR((I7/D7)-1,"") -> 0.44045351 | J8: =IFERROR((J7/E7)-1,"") -> 0.20508302 | K8: =IFERROR((K7/F7)-1,"") -> -0.44189425 | L8: =IFERROR((L7/G7)-1,"") -> 0.12410735 | M8: =IFERROR((M7/H7)-1,"") -> 0.056358031 | N8: =IFERROR((N7/I7)-1,"") -> 1.2362714 | O8: =IFERROR((O7/J7)-1,"") -> 0.57037004 | P8: =IFERROR((P7/K7)-1,"") -> 1.9648429 | ... AQ8: =IFERROR((AQ7/AL7)-1,"") -> 0.29841433
C10: Insights Revenue | D10: 3.1913215 | E10: 4.7110225 | F10: 6.3311435 | G10: 18.813569 | H10: =SUM(D10:G10) -> 33.047057 | I10: 3.8914503 | J10: 5.2916732 | K10: 2.838823 | L10: 21.127998 | M10: =SUM(I10:L10) -> 33.149945 | N10: 9.0434284 | O10: 6.7683624 | P10: 9.2409262 | Q10: 30.989684 | R10: =SUM(N10:Q10) -> 56.042401 | S10: 16.080187 | T10: 17.650796 | U10: 22.013176 | V10: 32.622384 | W10: =SUM(S10:V10) -> 88.366543 | X10: 22.753743 | Y10: 29.103125 | Z10: 26.865776 | AA10: 38.914232 | AB10: =SUM(X10:AA10) -> 117.63688 | AC10: 31.332667 | AD10: 40.7 | AE10: 50.1 | AF10: =64.7 -> 64.7 | AG10: =SUM(AC10:AF10) -> 186.83267 | AH10: =AC10*(1+AH11) -> 49.505615 | AI10: =AD10*(1+AI11) -> 57.2649 | AJ10: =AE10*(1+AJ11) -> 68.9376 | AK10: 82 | AL10: =SUM(AH10:AK10) -> 257.70811 | AM10: =AH10*(1+AM11) -> 73.763366 | AN10: =AI10*(1+AN11) -> 82.461456 | AO10: =AJ10*(1+AO11) -> 86.172 | AP10: =AK10*(1+AP11) -> 102.5 | AQ10: =SUM(AM10:AP10) -> 344.89682
C11: YoY Growth (%) | I11: =IFERROR((I10/D10)-1,"") -> 0.21938522 | J11: =IFERROR((J10/E10)-1,"") -> 0.12325365 | K11: =IFERROR((K10/F10)-1,"") -> -0.55160976 | L11: =IFERROR((L10/G10)-1,"") -> 0.12301914 | M11: =IFERROR((M10/H10)-1,"") -> 0.0031133804 | N11: =IFERROR((N10/I10)-1,"") -> 1.3239224 | O11: =IFERROR((O10/J10)-1,"") -> 0.27905902 | P11: =IFERROR((P10/K10)-1,"") -> 2.2551964 | ... AG11: =IFERROR((AG10/AB10)-1,"") -> 0.58821514 | AH11: 0.58 | AI11: 0.407 | AJ11: 0.376 | AK11: 0.376 | AL11: =IFERROR((AL10/AG10)-1,"") -> 0.37935254 | AM11: 0.49 | AN11: 0.44 | AO11: 0.25 | AP11: 0.25 | AQ11: =IFERROR((AQ10/AL10)-1,"") -> 0.33832348
C13: Trials Revenue | D13: 0 | E13: 0 | F13: 0.21625 | G13: 0.90375 | H13: =SUM(D13:G13) -> 1.12 | I13: 0.7055 | J13: 0.3855 | K13: 0.815315 | L13: 1.036385 | M13: =SUM(I13:L13) -> 2.9427 | N13: 1.2366 | O13: 1.7166 | P13: 1.42935 | Q13: 1.5955 | R13: =SUM(N13:Q13) -> 5.97805 | S13: 6.4831499 | T13: 7.908544 | U13: 7.479657 | V13: 9.3793606 | W13: =SUM(S13:V13) -> 31.250712 | X13: 10.2828 | Y13: 10.636964 | Z13: 10.609873 | AA13: 14.099472 | AB13: =SUM(X13:AA13) -> 45.629109 | AC13: 11.250035 | AD13: 10.5 | AE13: 10.1 | AF13: =AG13-AE13-AD13-AC13 -> 10.549965 | AG13: 42.4 | AH13: =AC13*(1+AH14) -> 11.250035 | AI13: =AD13*(1+AI14) -> 10.5 | AJ13: =AE13*(1+AJ14) -> 10.1 | AK13: =AF13*(1+AK14) -> 10.549965 | AL13: =SUM(AH13:AK13) -> 42.4 | AM13: =AH13*(1+AM14) -> 11.250035 | AN13: =AI13*(1+AN14) -> 10.5 | AO13: =AJ13*(1+AO14) -> 10.1 | AP13: =AK13*(1+AP14) -> 10.549965 | AQ13: =SUM(AM13:AP13) -> 42.4
C14: YoY Growth (%) | I14: =IFERROR((I13/D13)-1,"") | J14: =IFERROR((J13/E13)-1,"") | K14: =IFERROR((K13/F13)-1,"") -> 2.7702428 | L14: =IFERROR((L13/G13)-1,"") -> 0.14676072 | M14: =IFERROR((M13/H13)-1,"") -> 1.6274107 | N14: =IFERROR((N13/I13)-1,"") -> 0.75279943 | O14: =IFERROR((O13/J13)-1,"") -> 3.4529183 | P14: =IFERROR((P13/K13)-1,"") -> 0.75312609 | ... AG14: =IFERROR((AG13/AB13)-1,"") -> -0.070768613 | AH14: 0 | AI14: 0 | AJ14: 0 | AK14: 0 | AL14: =IFERROR((AL13/AG13)-1,"") -> 0 | AM14: 0 | AN14: 0 | AO14: 0 | AP14: 0 | AQ14: =IFERROR((AQ13/AL13)-1,"") -> 0
C16: AI Application Revenue | D16: 0 | E16: 0 | F16: 0 | G16: 0 | H16: =SUM(D16:G16) -> 0 | I16: 0 | J16: 0 | K16: 0 | L16: 0 | M16: =SUM(I16:L16) -> 0 | N16: 0 | O16: 0.43030042 | P16: 0.16366888 | Q16: 0.22630469 | R16: =SUM(N16:Q16) -> 0.82027399 | S16: 0.28658304 | T16: 0.7378844 | U16: 1.3469351 | V16: 0.69576383 | W16: =SUM(S16:V16) -> 3.0671664 | X16: 0.52970687 | Y16: 0.75269833 | Z16: 1.766268 | AA16: 2.4850204 | AB16: =SUM(X16:AA16) -> 5.5336936 | AC16: 0.66792032 | AD16: =AD7-AD10-AD13 -> 2.445 | AE16: =AE7-AE10-AE13 -> 4.307 | AF16: =AF7-AF10-AF13 -> 4.9960346 | AG16: =SUM(AC16:AF16) -> 12.415955 | AH16: =AC16*(1+AH17) -> 1.1688606 | AI16: =AD16*(1+AI17) -> 2.51835 | AJ16: =AE16*(1+AJ17) -> 7.58032 | AK16: =AF16*(1+AK17) -> 5.195876 | AL16: =SUM(AH16:AK16) -> 16.463407 | AM16: =AH16*(1+AM17) -> 1.6948478 | AN16: =AI16*(1+AN17) -> 3.6516075 | AO16: =AJ16*(1+AO17) -> 10.915661 | AP16: =AK16*(1+AP17) -> 7.4820614 | AQ16: =SUM(AM16:AP16) -> 23.744177
C17: YoY Growth (%) | I17: =IFERROR((I16/D16)-1,"") | J17: =IFERROR((J16/E16)-1,"") | K17: =IFERROR((K16/F16)-1,"") | L17: =IFERROR((L16/G16)-1,"") | M17: =IFERROR((M16/H16)-1,"") | N17: =IFERROR((N16/I16)-1,"") | O17: =IFERROR((O16/J16)-1,"") | P17: =IFERROR((P16/K16)-1,"") | ... AG17: =IFERROR((AG16/AB16)-1,"") -> 1.2437012 | AH17: 0.75 | AI17: 0.03 | AJ17: 0.76 | AK17: 0.04 | AL17: =IFERROR((AL16/AG16)-1,"") -> 0.32598794 | AM17: 0.45 | AN17: 0.45 | AO17: 0.44 | AP17: 0.44 | AQ17: =IFERROR((AQ16/AL16)-1,"") -> 0.44223964
C19: Total Data & Other Cost of Revenue | D19: =D22+D25+D28 -> 1.8783008 | E19: =E22+E25+E28 -> 1.7794325 | F19: =F22+F25+F28 -> 1.2114378 | G19: =G22+G25+G28 -> 1.4606137 | H19: =SUM(D19:G19) -> 6.3297848 | I19: =I22+I25+I28 -> 1.411472 | J19: =J22+J25+J28 -> 1.477868 | K19: =K22+K25+K28 -> 2.1382459 | L19: =L22+L25+L28 -> 2.0641284 | M19: =SUM(I19:L19) -> 7.0917143 | N19: =N22+N25+N28 -> 2.249488 | O19: =O22+O25+O28 -> 2.6678312 | P19: =P22+P25+P28 -> 3.0303307 | Q19: =Q22+Q25+Q28 -> 3.9851527 | R19: =SUM(N19:Q19) -> 11.932803 | S19: =S22+S25+S28 -> 7.7879838 | T19: =T22+T25+T28 -> 10.613211 | U19: =U22+U25+U28 -> 11.101333 | V19: =V22+V25+V28 -> 10.724351 | W19: =SUM(S19:V19) -> 40.226879 | X19: =X22+X25+X28 -> 11.392877 | Y19: =Y22+Y25+Y28 -> 13.806998 | Z19: =Z22+Z25+Z28 -> 15.489291 | AA19: =AA22+AA25+AA28 -> 15.79287 | AB19: =SUM(X19:AA19) -> 56.482036 | AC19: =AC22+AC25+AC28 -> 15.288271 | AD19: 22.132 | AE19: 14.964 | AF19: 16.434 | AG19: =SUM(AG22,AG25,AG28) -> 65.020288 | AH19: =15.751-0.611-0.044 -> 15.096 | AI19: =19.84-0.693-0.114 -> 19.033 | AJ19: =25.621-0.894-0.062 -> 24.665 | AK19: =26.578-0.893-0.048 -> 25.637 | AL19: =SUM(AL22,AL25,AL28) -> 75.009328 | AM19: =AM22+AM25+AM28 -> 21.112614 | AN19: =AN22+AN25+AN28 -> 23.097934 | AO19: =AO22+AO25+AO28 -> 23.672625 | AP19: =AP22+AP25+AP28 -> 25.339939 | AQ19: =SUM(AQ22,AQ25,AQ28) -> 93.223113
C20: Margin (%) | D20: =IFERROR(1-(D19/D7),"") -> 0.41143478 | E20: =IFERROR(1-(E19/E7),"") -> 0.62228317 | F20: =IFERROR(1-(F19/F7),"") -> 0.81497404 | G20: =IFERROR(1-(G19/G7),"") -> 0.9259223 | H20: =IFERROR(1-(H19/H7),"") -> 0.81474012 | I20: =IFERROR(1-(I19/I7),"") -> 0.6929547 | J20: =IFERROR(1-(J19/J7),"") -> 0.73968241 | K20: =IFERROR(1-(K19/K7),"") -> 0.41484259 | ... AQ20: =IFERROR(1-(AQ19/AQ7),"") -> 0.7732024
C22: Insights Cost of Revenue | D22: 1.8783008 | E22: 1.7794325 | F22: 1.2114378 | G22: 1.4606137 | H22: =SUM(D22:G22) -> 6.3297848 | I22: 1.411472 | J22: 0.97366293 | K22: 1.1370944 | L22: 1.0574782 | M22: =SUM(I22:L22) -> 4.5797075 | N22: 1.1669592 | O22: 1.2438754 | P22: 1.6484946 | Q22: 5.4515581 | R22: =SUM(N22:Q22) -> 9.5108874 | S22: 3.8355033 | T22: 5.2305151 | U22: 5.7684513 | V22: 5.1225322 | W22: =SUM(S22:V22) -> 19.957002 | X22: 5.0183346 | Y22: 6.6254355 | Z22: 8.0227723 | AA22: 8.3604932 | AB22: =SUM(X22:AA22) -> 28.027036 | AC22: 8.497387 | AD22: =AD10*(1-AD23) -> 9.361 | AE22: =AE10*(1-AE23) -> 10.02 | AF22: =AF10*(1-AF23) -> 10.999 | AG22: =SUM(AC22:AF22) -> 38.877387 | AH22: =AH10*(1-AH23) -> 8.8119994 | AI22: =AI10*(1-AI23) -> 10.880331 | AJ22: =AJ10*(1-AJ23) -> 13.098144 | AK22: =AK10*(1-AK23) -> 14.76 | AL22: =SUM(AH22:AK22) -> 47.550474 | AM22: =AM10*(1-AM23) -> 14.752673 | AN22: =AN10*(1-AN23) -> 16.492291 | AO22: =AO10*(1-AO23) -> 16.37268 | AP22: =AP10*(1-AP23) -> 19.475 | AQ22: =SUM(AM22:AP22) -> 67.092644
C23: Margin (%) | D23: =(D10-D22)/D10 -> 0.41143478 | E23: =(E10-E22)/E10 -> 0.62228317 | F23: =(F10-F22)/F10 -> 0.80865419 | G23: =(G10-G22)/G10 -> 0.92236382 | H23: =(H10-H22)/H10 -> 0.80846147 | I23: =(I10-I22)/I10 -> 0.63728896 | J23: =(J10-J22)/J10 -> 0.81600094 | K23: =(K10-K22)/K10 -> 0.59944865 | ... AC23: =(AC10-AC22)/AC10 -> 0.72880103 | AD23: 0.77 | AE23: 0.8 | AF23: 0.83 | AG23: =(AG10-AG22)/AG10 -> 0.79191333 | AH23: 0.822 | AI23: 0.81 | AJ23: 0.81 | AK23: 0.82 | AL23: =(AL10-AL22)/AL10 -> 0.81548709 | AM23: 0.8 | AN23: 0.8 | AO23: 0.81 | AP23: 0.81 | AQ23: =(AQ10-AQ22)/AQ10 -> 0.80547039
C25: Trials Cost of Revenue | D25: 0 | E25: 0 | F25: 0 | G25: 0 | H25: =SUM(D25:G25) -> 0 | I25: 0 | J25: 0.34762784 | K25: 0.56694555 | L25: 0.62389248 | M25: =SUM(I25:L25) -> 1.5384659 | N25: 0.8545793 | O25: 0.84599396 | P25: 0.88857845 | Q25: -0.49069355 | R25: =SUM(N25:Q25) -> 2.0984582 | S25: 3.9971131 | T25: 5.3092387 | U25: 5.2758345 | V25: 5.1756208 | W25: =SUM(S25:V25) -> 19.757807 | X25: 6.0751708 | Y25: 6.554954 | Z25: 7.0009332 | AA25: 6.8666059 | AB25: =SUM(X25:AA25) -> 26.497664 | AC25: 6.3616324 | AD25: =AD13*(1-AD26) -> 6.195 | AE25: =AE13*(1-AE26) -> 5.757 | AF25: =AF13*(1-AF26) -> 5.1694831 | AG25: =SUM(AC25:AF25) -> 23.483115 | AH25: =AH13*(1-AH26) -> 7.6500235 | AI25: =AI13*(1-AI26) -> 5.25 | AJ25: =AJ13*(1-AJ26) -> 5.05 | AK25: =AK13*(1-AK26) -> 5.2749827 | AL25: =SUM(AH25:AK25) -> 23.225006 | AM25: =AM13*(1-AM26) -> 5.5125169 | AN25: =AN13*(1-AN26) -> 5.145 | AO25: =AO13*(1-AO26) -> 4.8985 | AP25: =AP13*(1-AP26) -> 5.1167332 | AQ25: =SUM(AM25:AP25) -> 20.67275
C26: Margin (%) | F26: =(F13-F25)/F13 -> 1 | G26: =(G13-G25)/G13 -> 1 | H26: =(H13-H25)/H13 -> 1 | I26: =(I13-I25)/I13 -> 1 | J26: =(J13-J25)/J13 -> 0.09824166 | K26: =(K13-K25)/K13 -> 0.30463005 | L26: =(L13-L25)/L13 -> 0.39801089 | M26: =(M13-M25)/M13 -> 0.47719242 | ... AC26: =(AC13-AC25)/AC13 -> 0.4345233 | AD26: 0.41 | AE26: 0.43 | AF26: 0.51 | AG26: =(AG13-AG25)/AG13 -> 0.44615294 | AH26: 0.32 | AI26: 0.5 | AJ26: 0.5 | AK26: 0.5 | AL26: =(AL13-AL25)/AL13 -> 0.45224042 | AM26: 0.51 | AN26: 0.51 | AO26: 0.515 | AP26: 0.515 | AQ26: =(AQ13-AQ25)/AQ13 -> 0.51243514
C28: AI Application Cost of Revenue | D28: 0 | E28: 0 | F28: 0 | G28: 0 | H28: =SUM(D28:G28) -> 0 | I28: 0 | J28: 0.15657727 | K28: 0.43420599 | L28: 0.38275766 | M28: =SUM(I28:L28) -> 0.97354092 | N28: 0.22794948 | O28: 0.57796181 | P28: 0.49325765 | Q28: -0.97571182 | R28: =SUM(N28:Q28) -> 0.32345712 | S28: -0.04463252 | T28: 0.0734575 | U28: 0.05704728 | V28: 0.4261978 | W28: =SUM(S28:V28) -> 0.51207006 | X28: 0.29937181 | Y28: 0.62660894 | Z28: 0.46558509 | AA28: 0.56577117 | AB28: =SUM(X28:AA28) -> 1.957337 | AC28: 0.42925187 | AD28: =AD16*(1-AD29) -> 0.85575 | AE28: =AE16*(1-AE29) -> 0.77526 | AF28: =AF16*(1-AF29) -> 0.59952415 | AG28: =SUM(AC28:AF28) -> 2.659786 | AH28: =AH16*(1-AH29) -> 0.58443028 | AI28: =AI16*(1-AI29) -> 1.00734 | AJ28: =AJ16*(1-AJ29) -> 2.1224896 | AK28: =AK16*(1-AK29) -> 0.5195876 | AL28: =SUM(AH28:AK28) -> 4.2338475 | AM28: =AM16*(1-AM29) -> 0.8474239 | AN28: =AN16*(1-AN29) -> 1.460643 | AO28: =AO16*(1-AO29) -> 2.4014454 | AP28: =AP16*(1-AP29) -> 0.74820614 | AQ28: =SUM(AM28:AP28) -> 5.4577184
C29: Margin (%) | D29: =IFERROR(1-(D28/#REF!),"") | E29: =IFERROR(1-(E28/#REF!),"") | F29: =IFERROR(1-(F28/#REF!),"") | G29: =IFERROR(1-(G28/#REF!),"") | H29: =IFERROR(1-(H28/#REF!),"") | O29: =(O16-O28)/O16 -> -0.34315883 | P29: =(P16-P28)/P16 -> -2.0137534 | Q29: =(Q16-Q28)/Q16 -> 5.3114962 | R29: =(R16-R28)/R16 -> 0.60567186 | S29: =(S16-S28)/S16 -> 1.1557403 | T29: =(T16-T28)/T16 -> 0.9004485 | U29: =(U16-U28)/U16 -> 0.9576466 | V29: =(V16-V28)/V16 -> 0.38743897 | ... AC29: =(AC16-AC28)/AC16 -> 0.35733072 | AD29: 0.65 | AE29: 0.82 | AF29: 0.88 | AG29: =(AG16-AG28)/AG16 -> 0.78577677 | AH29: 0.5 | AI29: 0.6 | AJ29: 0.72 | AK29: 0.9 | AL29: =(AL16-AL28)/AL16 -> 0.74283284 | AM29: 0.5 | AN29: 0.6 | AO29: 0.78 | AP29: 0.9 | AQ29: =(AQ16-AQ28)/AQ16 -> 0.77014498
C31: Data & Other Gross Profit | D31: =D7-D19 -> 1.3130207 | E31: =E7-E19 -> 2.93159 | F31: =F7-F19 -> 5.3359557 | G31: =G7-G19 -> 18.256705 | H31: =SUM(D31:G31) -> 27.837272 | I31: =I7-I19 -> 3.1854783 | J31: =J7-J19 -> 4.1993052 | K31: =K7-K19 -> 1.5158921 | L31: =L7-L19 -> 20.100255 | M31: =SUM(I31:L31) -> 29.00093 | N31: =N7-N19 -> 8.0305404 | O31: =O7-O19 -> 6.2474316 | P31: =P7-P19 -> 7.8036144 | Q31: =Q7-Q19 -> 28.826336 | R31: =SUM(N31:Q31) -> 50.907922 | S31: =S7-S19 -> 15.061936 | T31: =T7-T19 -> 15.684013 | U31: =U7-U19 -> 19.738435 | V31: =V7-V19 -> 31.973158 | W31: =SUM(S31:V31) -> 82.457542 | X31: =X7-X19 -> 22.173373 | Y31: =Y7-Y19 -> 26.685789 | Z31: =Z7-Z19 -> 23.752626 | AA31: =AA7-AA19 -> 39.705855 | AB31: =SUM(X31:AA31) -> 112.31764 | AC31: =AC7-AC19 -> 27.962351 | AD31: =AD7-AD19+7.229+0.119 -> 38.861 | AE31: =AE7-AE19+0.916+0.043 -> 50.502 | AF31: =AF7-AF19+0.385+0.202 -> 64.399 | AG31: =AG7-AG19 -> 176.62833 | AH31: =AH7-AH19 -> 46.837 | AI31: =AI7-AI19 -> 53.759 | AJ31: =AJ7-AJ19 -> 56.663 | AK31: =AK7-AK19 -> 74.718 | AL31: =AL7-AL19 -> 241.56219 | AM31: =AM7-AM19 -> 65.595634 | AN31: =AN7-AN19 -> 73.515129 | ... AQ31: =AQ7-AQ19 -> 317.81789
C32: Margin (%) | D32: =D20 -> 0.41143478 | E32: =E20 -> 0.62228317 | F32: =F20 -> 0.81497404 | G32: =G20 -> 0.9259223 | H32: =H20 -> 0.81474012 | I32: =I20 -> 0.6929547 | J32: =J20 -> 0.73968241 | K32: =K20 -> 0.41484259 | ... AC32: =AC20 -> 0.64651905 | AD32: =AD31/AD7 -> 0.72441048 | AE32: =AE20 -> 0.76802518 | AF32: =AF20 -> 0.79520475 | AG32: =AG20 -> 0.73093044 | AH32: =AH20 -> 0.75625272 | AI32: =AI20 -> 0.73852896 | AJ32: =AJ20 -> 0.69672192 | AK32: =AK20 -> 0.74453689 | AL32: =AL20 -> 0.76305725 | ... AQ32: =AQ20 -> 0.7732024

Sheet Valuation
B3: Tempus | I3: Current Level | K3: Upside Scenario | M3: Base case (Target Price) | O3: Downside Scenario
B4: Current Price | D4: 86.66 | G4: 1 | K4: 1 | O4: 1
B5: Price Target | D5: 100 | E5: =D5/D4-1 -> 0.15393492 | F5: Price | I5: =D4 -> 86.66 | K5: =D6 -> 100 | M5: =D5 -> 100 | O5: =D7 -> 30
B6: Upside Scenario | D6: 100 | E6: =$D$4 -> 86.66 | F6: Variance From Current Price | I6: NA | K6: =K5/$I$5-1 -> 0.15393492 | M6: =M5/$I$5-1 -> 0.15393492 | O6: =O5/$I$5-1 -> -0.65381952
B7: Downside Scenario | D7: 30 | E7: =$D$4 -> 86.66 | F7: Sales | I7: =C14 -> 1589.9855 | K7: =C14 -> 1589.9855 | M7: =C14 -> 1589.9855 | O7: =C14 -> 1589.9855
F8: FY2020 EV/S | I8: =(I5*C12+C15-C16)/I7 -> 9.8089839 | K8: =(K5*C12+C15-C16)/K7 -> 11.342511 | M8: =(M5*C12+C15-C16)/M7 -> 11.342511 | O8: =(O5*C12+C15-C16)/O7 -> 3.2955188
B9: Period | F9: FY2020 P/E | I9: =I5/$C$17 -> -46.556172 | K9: =K5/$C$17 -> -53.722792 | M9: =M5/$C$17 -> -53.722792 | O9: =O5/$C$17 -> -16.116838
B10: Column | F10: FY2020 EV/FCF | I10: =(I5*C12+C15-C16)/C18 -> 287.63317 | K10: =(K5*C12+C15-C16)/C18 -> 332.60146 | M10: =(M5*C12+C15-C16)/C18 -> 332.60146 | O10: =(O5*C12+C15-C16)/C18 -> 96.635956
B12: Shares | C12: 182.78
B13: Mkt Cap | C13: =C12*D4 -> 15839.715
B14: FY25 Sales | C14: =IS!AQ15 -> 1589.9855
B15: Debt | C15: =BS!AK33+BS!AK37+BS!AK36 -> 511.425
B16: Cash | C16: =BS!AK7+BS!AK8 -> 754.998 | D16: =C16-C15 -> 243.573 | E16: net debt
B17: FY24 Earnings | C17: =IS!AQ82 -> -1.8614073
B18: FY24 FCF | C18: =CF!AQ57 -> 54.222333

Sheet DCF
T2: WACC calculation
E4: Key Assumptions | H4: Implied Equity Value | T4: 2023 Cost of debt | U4: 0.104
E5: Terminal Growth Rate | F5: 0.05 | H5: Terminal Value | K5: =Q63*(1+F5)/(F6-F5) -> 27071.054 | T5: 2024 Cost of debt | U5: 0.127
E6: WACC | F6: 0.127 | H6: PV Terminal Value | K6: =K5/((1+F6)^R18) -> 8189.6624 | T6: 2023 debt | U6: =BS!AB33+BS!AB37 -> 449.66515
T7: 2024 debt | U7: =BS!AG37+BS!AG33 -> 435.436
E8: Projection Period Assumptions | H8: PV of FCFs | K8: =SUM(H65:Q65) -> 2066.6813
E9: S&M % of Revenue | F9: =R29 -> 0.1 | H9: Enterprise Value | K9: =K8+K6 -> 10256.344
E10: R&D % of Revenue | F10: =R31 -> 0.1 | H10: Less Debt | K10: =Valuation!C15 -> 511.425
E11: G&A % of Revenue | F11: =R33 -> 0.15 | H11: Plus Cash | K11: =Valuation!C16 -> 754.998
E12: D&A % of Revenue | F12: 0.03 | H12: Equity Value | K12: =K9-K10+K11 -> 10499.917
E13: SBC % of Revenue | F13: 0.11 | H13: Diluted Shares | K13: 172.11 | M13: *based on factset share count
E14: Tax Rate | F14: 0 | H14: Implied Price/Share | K14: =ROUNDUP(K12/K13,0) -> 62
H16: Current Price | K16: 27.26
H17: Upside to Current Price | K17: =K14/K16-1 -> 1.2743947
I18: 1 | J18: 2 | K18: 3 | L18: 4 | M18: 5 | N18: 6 | O18: 7 | P18: 8 | Q18: 9 | R18: 10 | S18: 11
F19: W | G19: AB | H19: AG | I19: AL | J19: AQ
F20: Historical Period | H20: Model Period | K20: Projection Period
F21: 2022A | G21: 2023A | H21: 2024E | I21: 2025E | J21: 2026E | K21: 2027E | L21: 2028E | M21: 2029E | N21: 2030E | O21: 2031E | P21: 2032E | Q21: 2033E | R21: 2034E
E23: Revenue | F23: =IS!W15 -> 320.66891 | G23: =IS!AB15 -> 531.75718 | H23: =IS!AG15 -> 693.39804 | I23: =IS!AL15 -> 1271.789 | J23: =IS!AQ15 -> 1589.9855 | K23: =J23*(1+K24) -> 2066.9811 | L23: =K23*(1+L24) -> 2645.7358 | M23: =L23*(1+M24) -> 3333.6271 | N23: =M23*(1+N24) -> 4133.6976 | O23: =N23*(1+O24) -> 5043.1111 | P23: =O23*(1+P24) -> 6051.7334 | Q23: =P23*(1+Q24) -> 7141.0454 | R23: =Q23*(1+R24) -> 8283.6126
E24: Y/Y Growth | F24: =IS!W16 -> 0.24361154 | G24: =G23/F23-1 -> 0.65827481 | H24: =H23/G23-1 -> 0.30397495 | I24: =I23/H23-1 -> 0.83413988 | J24: =J23/I23-1 -> 0.25019596 | K24: 0.3 | L24: 0.28 | M24: 0.26 | N24: 0.24 | O24: 0.22 | P24: 0.2 | Q24: 0.18 | R24: 0.16
E25: Operating COGS | F25: =IS!W23 -> 190.48145 | G25: =IS!AB23 -> 245.60023 | H25: =IS!AG23 -> 289.31103 | I25: =IS!AL23 -> 463.936 | J25: =IS!AQ23 -> 552.42286 | K25: =(1-K27)*K23 -> 826.79244 | L25: =(1-L27)*L23 -> 1018.6083 | M25: =(1-M27)*M23 -> 1233.442 | N25: =(1-N27)*N23 -> 1467.4627 | O25: =(1-O27)*O23 -> 1714.6578 | P25: =(1-P27)*P23 -> 1966.8133 | Q25: =(1-Q27)*Q23 -> 2213.7241 | R25: =(1-R27)*R23 -> 2485.0838
E26: Gross Profit | F26: =IS!W25 -> 130.18747 | G26: =IS!AB25 -> 286.15695 | H26: =IS!AG25 -> 404.08701 | I26: =IS!AL25 -> 807.853 | J26: =IS!AQ25 -> 1037.5626 | K26: =K23-K25 -> 1240.1887 | L26: =L23-L25 -> 1627.1275 | M26: =M23-M25 -> 2100.1851 | N26: =N23-N25 -> 2666.235 | O26: =O23-O25 -> 3328.4533 | P26: =P23-P25 -> 4084.92 | Q26: =Q23-Q25 -> 4927.3213 | R26: =R23-R25 -> 5798.5288
E27: Gross Margin | F27: =F26/F23 -> 0.40598718 | G27: =G26/G23 -> 0.53813463 | H27: =H26/H23 -> 0.58276342 | I27: =I26/I23 -> 0.63520993 | J27: =J26/J23 -> 0.65256106 | K27: 0.6 | L27: 0.615 | M27: 0.63 | N27: 0.645 | O27: 0.66 | P27: 0.675 | Q27: 0.69 | R27: 0.7
E28: Technology | F28: =IS!W29 -> 79.08036 | G28: =IS!AB29 -> 95.556287 | H28: =IS!AG29 -> 106.28399 | I28: =IS!AL29 -> 125.825 | J28: =IS!AQ29 -> 162.44813 | K28: =K23*K$29 -> 227.36792 | L28: =L23*L$29 -> 285.73947 | M28: =M23*M$29 -> 353.36448 | N28: =N23*N$29 -> 429.90456 | O28: =O23*O$29 -> 514.39734 | P28: =P23*P$29 -> 605.17334 | Q28: =Q23*Q$29 -> 714.10454 | R28: =R23*R$29 -> 828.36126
E29: % of Revenue | F29: =F28/F23 -> 0.24661062 | G29: =G28/G23 -> 0.1796991 | H29: =H28/H23 -> 0.15327991 | I29: =I28/I23 -> 0.098935437 | J29: =J28/J23 -> 0.10216957 | K29: 0.11 | L29: 0.108 | M29: 0.106 | N29: 0.104 | O29: 0.102 | P29: 0.1 | Q29: 0.1 | R29: 0.1
E30: R&D | F30: =IS!W31 -> 83.157816 | G30: =IS!AB31 -> 90.025956 | H30: =IS!AG31 -> 100.12065 | I30: =IS!AL31 -> 159.604 | J30: =IS!AQ31 -> 237.70326 | K30: =K31*K23 -> 225.30094 | L30: =L31*L23 -> 285.73947 | M30: =M31*M23 -> 356.6981 | N30: =N31*N23 -> 438.17195 | O30: =O31*O23 -> 529.52667 | P30: =P31*P23 -> 629.38027 | Q30: =Q31*Q23 -> 728.38663 | R30: =R31*R23 -> 828.36126
E31: % of Revenue | F31: =F30/F23 -> 0.25932609 | G31: =G30/G23 -> 0.16929899 | H31: =H30/H23 -> 0.14439131 | I31: =I30/I23 -> 0.12549566 | J31: =J30/J23 -> 0.14950027 | K31: 0.109 | L31: 0.108 | M31: 0.107 | N31: 0.106 | O31: 0.105 | P31: 0.104 | Q31: 0.102 | R31: 0.1
E32: G&A | F32: =IS!W33 -> 233.38956 | G32: =IS!AB33 -> 284.3657 | H32: =IS!AG33 -> 341.08461 | I32: =IS!AL33 -> 569.618 | J32: =IS!AQ33 -> 724.13457 | K32: =K33*K23 -> 620.09433 | L32: =L33*L23 -> 740.80603 | M32: =M33*M23 -> 866.74305 | N32: =N33*N23 -> 992.08744 | O32: =O33*O23 -> 1109.4844 | P32: =P33*P23 -> 1210.3467 | Q32: =Q33*Q23 -> 1285.3882 | R32: =R33*R23 -> 1242.5419
E33: % of Revenue | F33: =F32/F23 -> 0.72782096 | G33: =G32/G23 -> 0.53476607 | H33: =H32/H23 -> 0.49190305 | I33: =I32/I23 -> 0.44788719 | J33: =J32/J23 -> 0.45543471 | K33: 0.3 | L33: 0.28 | M33: 0.26 | N33: 0.24 | O33: 0.22 | P33: 0.2 | Q33: 0.18 | R33: 0.15
E34: Operating Income | F34: =F26-F28-F30-F32 -> -265.44027 | G34: =G26-G28-G30-G32 -> -183.79099 | H34: =H26-H28-H30-H32 -> -143.40224 | I34: =I26-I28-I30-I32 -> -47.194 | J34: =J26-J28-J30-J32 -> -86.723343 | K34: =K26-K28-K30-K32 -> 167.42547 | L34: =L26-L28-L30-L32 -> 314.84256 | M34: =M26-M28-M30-M32 -> 523.37946 | ... R34: =R26-R28-R30-R32 -> 2899.2644
E35: Operating Margin | F35: =F34/F23 -> -0.8277705 | G35: =G34/G23 -> -0.34562954 | H35: =H34/H23 -> -0.20681086 | I35: =I34/I23 -> -0.037108357 | J35: =J34/J23 -> -0.054543482 | K35: =K34/K23 -> 0.081 | L35: =L34/L23 -> 0.119 | M35: =M34/M23 -> 0.157 | ... R35: =R34/R23 -> 0.35
E37: Less D&A | F37: =CF!W9+IS!W52 -> 28.936232 | G37: =CF!AB9+IS!AB52 -> 32.566557 | H37: =CF!AG9+IS!AG52 -> 40.156467 | I37: =CF!AL9+IS!AL52 -> 137.728 | J37: =CF!AQ9+IS!AQ52 -> 131.7 | K37: =K38*K23 -> 62.009433 | L37: =L38*L23 -> 79.372075 | M37: =M38*M23 -> 100.00881 | N37: =N38*N23 -> 124.01093 | O37: =O38*O23 -> 151.29333 | P37: =P38*P23 -> 181.552 | Q37: =Q38*Q23 -> 214.23136 | R37: =R38*R23 -> 248.50838
E38: % of Revenue | F38: =F37/F23 -> 0.090237098 | G38: =G37/G23 -> 0.061243285 | H38: =H37/H23 -> 0.057912576 | I38: =I37/I23 -> 0.10829469 | J38: =J37/J23 -> 0.082830946 | K38: =F12 -> 0.03 | L38: =K38 -> 0.03 | M38: =L38 -> 0.03 | N38: =M38 -> 0.03 | O38: =N38 -> 0.03 | P38: =O38 -> 0.03 | Q38: =P38 -> 0.03 | R38: =Q38 -> 0.03
E40: Less SBC | F40: =IS!W42 -> 0 | G40: =IS!AB42 -> 0 | H40: =IS!AG42 -> 534.138 | I40: =IS!AL42 -> 123.101 | J40: =IS!AQ42 -> 199.99 | K40: =K41*K23 -> 227.36792 | L40: =L41*L23 -> 291.03094 | M40: =M41*M23 -> 366.69898 | N40: =N41*N23 -> 454.70674 | O40: =O41*O23 -> 554.74222 | P40: =P41*P23 -> 665.69067 | Q40: =Q41*Q23 -> 785.51499 | R40: =R41*R23 -> 911.19739
E41: % of Revenue | F41: =F40/F23 -> 0 | G41: =G40/G23 -> 0 | H41: =H40/H23 -> 0.77031945 | I41: =I40/I23 -> 0.096793572 | J41: =J40/J23 -> 0.12578102 | K41: =F13 -> 0.11 | L41: =K41 -> 0.11 | M41: =L41 -> 0.11 | N41: =M41 -> 0.11 | O41: =N41 -> 0.11 | P41: =O41 -> 0.11 | Q41: =P41 -> 0.11 | R41: =Q41 -> 0.11
E43: GAAP Operating Income | F43: =F34-F37-F40 -> -294.3765 | G43: =G34-G37-G40 -> -216.35754 | H43: =H34-H37-H40 -> -717.69671 | I43: =I34-I37-I40 -> -308.023 | J43: =J34-J37-J40 -> -418.41334 | K43: =K34-K37-K40 -> -121.95189 | L43: =L34-L37-L40 -> -55.560452 | M43: =M34-M37-M40 -> 56.671661 | ... R43: =R34-R37-R40 -> 1739.5586
E44: GAAP Operating Margin | F44: =F43/F23 -> -0.9180076 | G44: =G43/G23 -> -0.40687282 | H44: =H43/H23 -> -1.0350429 | I44: =I43/I23 -> -0.24219662 | J44: =J43/J23 -> -0.26315545 | K44: =K43/K23 -> -0.059 | L44: =L43/L23 -> -0.021 | M44: =M43/M23 -> 0.017 | ... R44: =R43/R23 -> 0.21
E46: Less Taxes | F46: =IS!W72 -> -0.07257533 | G46: =IS!AB72 -> -0.28821126 | H46: =IS!AG72 -> -0.26628951 | I46: =IS!AL72 -> 51.684 | J46: =IS!AQ72 -> 0 | K46: =K43*K47 -> 0 | L46: =L43*L47 -> 0 | M46: =M43*M47 -> 0 | N46: =N43*N47 -> 0 | O46: =O43*O47 -> 0 | P46: =P43*P47 -> 0 | Q46: =Q43*Q47 -> 0 | R46: =R43*R47 -> 0
E47: Tax Rate | F47: =F46/F43 -> 0.00024653914 | G47: =G46/G43 -> 0.0013321064 | H47: =H46/H43 -> 0.00037103348 | I47: =I46/I43 -> -0.16779266 | J47: =J46/J43 -> 0 | K47: =F14 -> 0 | L47: =K47 -> 0 | M47: =L47 -> 0 | N47: =M47 -> 0 | O47: =N47 -> 0 | P47: =O47 -> 0 | Q47: =P47 -> 0 | R47: 0
E49: NOPAT | F49: =F43-F46 -> -294.30392 | G49: =G43-G46 -> -216.06933 | H49: =H43-H46 -> -717.43042 | I49: =I43-I46 -> -359.707 | J49: =J43-J46 -> -418.41334 | K49: =K43-K46 -> -121.95189 | L49: =L43-L46 -> -55.560452 | M49: =M43-M46 -> 56.671661 | ... R49: =R43-R46 -> 1739.5586
E51: + D&A | F51: =F37 -> 28.936232 | G51: =G37 -> 32.566557 | H51: =H37 -> 40.156467 | I51: =I37 -> 137.728 | J51: =J37 -> 131.7 | K51: =K37 -> 62.009433 | L51: =L37 -> 79.372075 | M51: =M37 -> 100.00881 | ... R51: =R37 -> 248.50838
E52: % of Revenue | F52: =F38 -> 0.090237098 | G52: =G38 -> 0.061243285 | H52: =H38 -> 0.057912576 | I52: =I38 -> 0.10829469 | J52: =J38 -> 0.082830946 | K52: =K38 -> 0.03 | L52: =L38 -> 0.03 | M52: =M38 -> 0.03 | ... R52: =R38 -> 0.03
E54: + SBC | F54: =F40 -> 0 | G54: =G40 -> 0 | H54: =H40 -> 534.138 | I54: =I40 -> 123.101 | J54: =J40 -> 199.99 | K54: =K40 -> 227.36792 | L54: =L40 -> 291.03094 | M54: =M40 -> 366.69898 | ... R54: =R40 -> 911.19739
E55: % of Revenue | F55: =F41 -> 0 | G55: =G41 -> 0 | H55: =H41 -> 0.77031945 | I55: =I41 -> 0.096793572 | J55: =J41 -> 0.12578102 | K55: =K41 -> 0.11 | L55: =L41 -> 0.11 | M55: =M41 -> 0.11 | ... R55: =R41 -> 0.11
E57: Change in NWC | F57: =SUM(CF!W33:W39,CF!W45) -> 101.26922 | G57: =SUM(CF!X33:AB39,CF!AB45) -> -48.530696 | H57: =SUM(CF!Y33:AC39,CF!AG45) -> -49.417561 | I57: =SUM(CF!Z33:AD39,CF!AL45) -> -157.30731 | J57: =SUM(CF!AA33:AE39,CF!AQ45) -> -77.005895 | K57: =-K58*K23 -> -41.339622 | L57: =-L58*L23 -> -52.914716 | M57: =-M58*M23 -> -66.672543 | N57: =-N58*N23 -> -82.673953 | O57: =-O58*O23 -> -100.86222 | P57: =-P58*P23 -> -121.03467 | Q57: =-Q58*Q23 -> -142.82091 | R57: =-R58*R23 -> -165.67225
E58: % of Revenue | F58: =-F57/F23 -> -0.31580618 | G58: =-G57/G23 -> 0.091264769 | H58: =-H57/H23 -> 0.071268677 | I58: =-I57/I23 -> 0.12368979 | J58: =-J57/J23 -> 0.048431823 | K58: 0.02 | L58: 0.02 | M58: 0.02 | N58: 0.02 | O58: 0.02 | P58: 0.02 | Q58: 0.02 | R58: 0.02
E60: CapEx | F60: =CF!W50 -> -18.377 | G60: =CF!AB50 -> -34.608 | H60: =CF!AG50 -> -22.121 | I60: =CF!AL50 -> -21.049 | J60: =CF!AQ50 -> -10 | K60: =-K61*K23 -> -20.669811 | L60: =-L61*L23 -> -26.457358 | M60: =-M61*M23 -> -33.336271 | N60: =-N61*N23 -> -41.336976 | O60: =-O61*O23 -> -50.431111 | P60: =-P61*P23 -> -60.517334 | Q60: =-Q61*Q23 -> -71.410454 | R60: =-R61*R23 -> -82.836126
E61: % of Revenue | F61: =-F60/F23 -> 0.05730833 | G61: =-G60/G23 -> 0.065082337 | H61: =-H60/H23 -> 0.031902311 | I61: =-I60/I23 -> 0.016550701 | J61: =-J60/J23 -> 0.0062893657 | K61: 0.01 | L61: 0.01 | M61: 0.01 | N61: 0.01 | O61: 0.01 | P61: 0.01 | Q61: 0.01 | R61: 0.01
E63: Unlevered Free Cash Flow | F63: =F49+F51+F54+F57+F60 -> -182.47547 | G63: =G49+G51+G54+G57+G60 -> -266.64147 | H63: =H49+H51+H54+H57+H60 -> -214.67451 | I63: =I49+I51+I54+I57+I60 -> -277.23431 | J63: =J49+J51+J54+J57+J60 -> -173.72924 | K63: =K49+K51+K54+K57+K60 -> 105.41604 | L63: =L49+L51+L54+L57+L60 -> 235.47049 | M63: =M49+M51+M54+M57+M60 -> 423.37065 | ... R63: =R49+R51+R54+R57+R60 -> 2650.756
E64: Discount Factor | J64: =1/(1+$F$6)^K18 -> 0.69859947 | K64: =1/(1+$F$6)^L18 -> 0.61987531 | L64: =1/(1+$F$6)^M18 -> 0.55002245 | M64: =1/(1+$F$6)^N18 -> 0.48804122 | N64: =1/(1+$F$6)^O18 -> 0.43304456 | O64: =1/(1+$F$6)^P18 -> 0.3842454 | P64: =1/(1+$F$6)^Q18 -> 0.34094534 | Q64: =1/(1+$F$6)^R18 -> 0.3025247 | R64: =1/(1+$F$6)^S18 -> 0.26843363
E65: PV of Free Cash Flow | J65: =J63*J64 -> -121.36715 | K65: =K63*K64 -> 65.344798 | L65: =L63*L64 -> 129.51406 | M65: =M63*M64 -> 206.62233 | N65: =N63*N64 -> 295.36242 | O65: =O63*O64 -> 393.37182 | P65: =P63*P64 -> 497.25778 | Q65: =Q63*Q64 -> 600.57524 | R65: =R63*R64 -> 711.55206
E66: FCF Margins | F66: =F63/F23 -> -0.56904633 | G66: =G63/G23 -> -0.50143464 | H66: =H63/H23 -> -0.30959781 | I66: =I63/I23 -> -0.21798766 | J66: =J63/J23 -> -0.10926467 | K66: =K63/K23 -> 0.051 | L66: =L63/L23 -> 0.089 | M66: =M63/M23 -> 0.127 | ... R66: =R63/R23 -> 0.32

Sheet Comps
B3: Genomics | H3: Tech
B4: Ticker | C4: Growth | D4: GM | E4: multiple | H4: Ticker | I4: Growth | J4: GM | K4: Multiple
B5: GH | C5: 0.177 | D5: 0.595 | E5: 3.44 | H5: RVTY | I5: 0.024 | J5: 0.616 | K5: 5.45
B6: MYGN | C6: 0.097 | D6: 0.704 | E6: 2.35 | H6: SDGR | I6: -0.01 | J6: 0.624 | K6: 6.56
B7: NTRA | C7: 0.237 | D7: 0.516 | E7: 8.92 | H7: DH | I7: 0.059 | J7: 0.84 | K7: 4.77
B8: VCYT | C8: 0.103 | D8: 0.685 | E8: 3.99 | H8: DOCS | I8: 0.131 | J8: 0.906 | K8: 9.59
B9: NEO | C9: 0.106 | D9: 0.431 | E9: 3.06 | H9: PLTR | I9: 0.201 | J9: 0.825 | K9: 21.15
D10: Rev | E10: 9.2 | F10: =E10*IS!AG9 -> 4156.0947 | H10: SNOW | I10: 0.224 | J10: 0.732 | K10: 16.19
D11: GP | E11: 8.1 | F11: =Diagnostics!AG47*E11 -> 1819.3999 | H11: ZETA | I11: 0.2 | J11: 0.62 | K11: 2.84
H12: IQV | I12: 0.036 | J12: 0.354 | K12: 3.81
H13: DDOG | I13: 0.21 | J13: 0.821 | K13: 16.28
H14: DUOL | I14: 0.37 | J14: 0.732 | K14: 14.34 | M14: was trading around 9x when growing fast at breakeven
H15: GLBE | I15: 0.318 | J15: 0.422 | K15: 7.92
H16: MNDY | I16: 0.281 | J16: 0.89 | K16: 11.35
H17: KYVO | I17: 0.28 | J17: 0.765 | K17: 7.92
H18: BRZE | I18: 0.31 | J18: 0.697 | K18: 11.08 | P18: =11.08+14.34+16.19 -> 41.61
H19: SPT | I19: 0.276 | J19: 0.783 | K19: 7.84 | P19: =P18/3 -> 13.87 | Q19: =P19*IS!AG12 -> 3351.6664
H20: CLVT | I20: 0 | J20: 0.659 | K20: 3.7 | Q20: =Q19+F10 -> 7507.761
J21: Rev | K21: 9.8 | L21: =K21*IS!AG12 -> 2368.1565 | Q21: =Q20/IS!AG15 -> 10.827491 | R21: bull case SOTP comp valuation multiple
J22: GP | K22: 13.7 | L22: ='Data & Other'!AG31*K22 -> 2419.8082
G24: Total AV | H24: =F10+L21 -> 6524.2512
H25: =H24/IS!AG15 -> 9.4090995 | I25: base case SOTP comp valuation multiple
