Workbook
Name _1994: #REF!
Name _1994: #REF!
Name _1995: #REF!
Name _1995: #REF!
Name _1996: #REF!
Name _1996: #REF!
Name _1997: #REF!
Name _1997: #REF!
Name _1998: #REF!
Name _1998: #REF!
Name _1999: #REF!
Name _1999: #REF!
Name _1Q94: #REF!
Name _1Q94: #REF!
Name _1Q95: #REF!
Name _1Q95: #REF!
Name _2007: #REF!
Name _2007: #REF!
Name _2008: #REF!
Name _2008: #REF!
Name _2Q94: #REF!
Name _2Q94: #REF!
Name _2Q95: #REF!
Name _2Q95: #REF!
Name _3Q94: #REF!
Name _3Q94: #REF!
Name _3Q95: #REF!
Name _3Q95: #REF!
Name _4Q94: #REF!
Name _4Q94: #REF!
Name _4Q95: #REF!
Name _4Q95: #REF!
Name _Key1: #REF!
Name _Key1: #REF!
Name _marketsource: #REF!
Name _Order1: 0
Name _Sort: #REF!
Name _Sort: #REF!
Name _strtyr: #REF!
Name a: #REF!
Name a: #REF!
Name Acc_payable: #REF!
Name Acc_payable: #REF!
Name Acc_payable_growth_fore: #REF!
Name Acc_payable_growth_fore: #REF!
Name Acc_Rec: #REF!
Name Acc_Rec: #REF!
Name Acc_Rec_growth_fore: #REF!
Name Acc_Rec_growth_fore: #REF!
Name Acc_Rec_turns: #REF!
Name Acc_Rec_turns: #REF!
Name Accel_Ratio: #REF!
Name Accel_Ratio: #REF!
Name Accrued_compensation: #REF!
Name Accrued_compensation: #REF!
Name Accrued_compensation_growth_fore: #REF!
Name Accrued_compensation_growth_fore: #REF!
Name Accrued_expenses: #REF!
Name Accrued_expenses: #REF!
Name Accrued_expenses_growth_fore: #REF!

Sheet __FDSCACHE__
B1: This sheet contains FactSet XML data for use with this workbook's =FDS codes. Modifying the worksheet's contents may damage the workbook's =FDS functionality.

Sheet Disclaimer
C5: Equity Research
C7: Financial Model
C8: Life Science Tools & Diagnostics
C9: 46073
C12: Guardant Health (GH)
C19: Brandon Couillard | E19: Evan Stampler, PhD, CFA | G19: Chris Mercado, CFA
C20: Senior Analyst | E20: Vice President | G20: Vice President
C21: 212.214.5053 | E21: 212.214.5312 | G21: 212.214.8092
C22: brandon.couillard@wellsfargo.com | E22: evan.stampler@wellsfargo.com | G22: chistopher.mercado2@wellsfargo.com
C26: Important Disclaimers:
BP437: 33.6
BP438: 16.1
BP443: 0
BQ513: 40 | BY513: 30
BP514: =0.9 -> 0.9 | BQ514: 1 | BT514: =+BR514 -> 0

Sheet IS
A1: Guardant Health, Inc. (NASDAQ: GH) | AT1: 1280
A2: Income Statement | AT2: =+AT1/AT7-1 -> 0.30343445 | AY2: =+AY7/AT7-1 -> 0.32372802
A3: $ millions except per share data, FY ending Dec
B5: Mar | C5: Jun | D5: Sep | E5: Dec | F5: 43070 | G5: Mar | H5: Jun | I5: Sep | J5: Dec | K5: =+DATE(YEAR(F5)+1,MONTH(F5),DAY(F5)) -> 43435 | L5: Mar | M5: Jun | N5: Sep | O5: Dec | P5: =+DATE(YEAR(K5)+1,MONTH(K5),DAY(K5)) -> 43800 | Q5: Mar | R5: Jun | S5: Sep | T5: Dec | U5: =+DATE(YEAR(P5)+1,MONTH(P5),DAY(P5)) -> 44166 | V5: Mar | W5: Jun | X5: Sep | Y5: Dec | Z5: =+DATE(YEAR(U5)+1,MONTH(U5),DAY(U5)) -> 44531 | AA5: Mar | AB5: Jun | AC5: Sep | AD5: Dec | AE5: =+DATE(YEAR(Z5)+1,MONTH(Z5),DAY(Z5)) -> 44896 | AF5: Mar | AG5: Jun | AH5: Sep | AI5: Dec | AJ5: =+DATE(YEAR(AE5)+1,MONTH(AE5),DAY(AE5)) -> 45261 | AK5: Mar | AL5: Jun | AM5: Sep | AN5: Dec | AO5: =+DATE(YEAR(AJ5)+1,MONTH(AJ5),DAY(AJ5)) -> 45627 | AP5: Mar | AQ5: Jun | AR5: Sep | AS5: Dec | AT5: =+DATE(YEAR(AO5)+1,MONTH(AO5),DAY(AO5)) -> 45992 | AU5: Mar | AV5: Jun | AW5: Sep | AX5: Dec | AY5: =+DATE(YEAR(AT5)+1,MONTH(AT5),DAY(AT5)) -> 46357 | AZ5: Mar | BA5: Jun | BB5: Sep | BC5: Dec | BD5: =+DATE(YEAR(AY5)+1,MONTH(AY5),DAY(AY5)) -> 46722 | BE5: Mar | BF5: Jun | BG5: Sep | BH5: Dec | BI5: =+DATE(YEAR(BD5)+1,MONTH(BD5),DAY(BD5)) -> 47088 | BJ5: Mar | BK5: Jun | BL5: Sep | BM5: Dec | BN5: =+DATE(YEAR(BI5)+1,MONTH(BI5),DAY(BI5)) -> 47453 | BO5: Mar | BP5: Jun | BQ5: Sep | BR5: Dec | BS5: =+DATE(YEAR(BN5)+1,MONTH(BN5),DAY(BN5)) -> 47818 | BT5: Mar | BU5: Jun | BV5: Sep | BW5: Dec | BX5: =+DATE(YEAR(BS5)+1,MONTH(BS5),DAY(BS5)) -> 48183 | BY5: Mar | BZ5: Jun | CA5: Sep | CB5: Dec | CC5: =+DATE(YEAR(BX5)+1,MONTH(BX5),DAY(BX5)) -> 48549 | CD5: Mar | CE5: Jun | CF5: Sep | CG5: Dec | CH5: =+DATE(YEAR(CC5)+1,MONTH(CC5),DAY(CC5)) -> 48914 | CI5: Mar | CJ5: Jun | CK5: Sep | CL5: Dec | CM5: =+DATE(YEAR(CH5)+1,MONTH(CH5),DAY(CH5)) -> 49279 | CO5: CAGRs
B6: 1Q17A | C6: 2Q17A | D6: 3Q17A | E6: 4Q17A | F6: FY17A | G6: 1Q18A | H6: 2Q18A | I6: 3Q18A | J6: 4Q18A | K6: FY18A | L6: 1Q19A | M6: 2Q19A | N6: 3Q19A | O6: 4Q19A | P6: FY19A | Q6: 1Q20A | R6: 2Q20A | S6: 3Q20A | T6: 4Q20A | U6: FY20A | V6: 1Q21A | W6: 2Q21A | X6: 3Q21A | Y6: 4Q21A | Z6: FY21A | AA6: 1Q22A | AB6: 2Q22A | AC6: 3Q22A | AD6: 4Q22A | AE6: FY22A | AF6: 1Q23A | AG6: 2Q23A | AH6: 3Q23A | AI6: 4Q23A | AJ6: FY23A | AK6: 1Q24A | AL6: 2Q24A | AM6: 3Q24A | AN6: 4Q24A | AO6: FY24A | AP6: 1Q25A | AQ6: 2Q25A | AR6: 3Q25A | AS6: 4Q25A | AT6: FY25A | AU6: 1Q26E | AV6: 2Q26E | AW6: 3Q26E | AX6: 4Q26E | AY6: FY26E | AZ6: 1Q27E | BA6: 2Q27E | BB6: 3Q27E | BC6: 4Q27E | BD6: FY27E | BE6: 1Q28E | BF6: 2Q28E | BG6: 3Q28E | BH6: 4Q28E | BI6: FY28E | BJ6: 1Q29E | BK6: 2Q29E | BL6: 3Q29E | BM6: 4Q29E | BN6: FY29E | BO6: 1Q30E | BP6: 2Q30E | BQ6: 3Q30E | BR6: 4Q30E | BS6: FY30E | BT6: 1Q31E | BU6: 2Q31E | BV6: 3Q31E | BW6: 4Q31E | BX6: FY31E | BY6: 1Q32E | BZ6: 2Q32E | CA6: 3Q32E | CB6: 4Q32E | CC6: FY32E | CD6: 1Q33E | CE6: 2Q33E | CF6: 3Q33E | CG6: 4Q33E | CH6: FY33E | CI6: 1Q34E | CJ6: 2Q34E | CK6: 3Q34E | CL6: 4Q34E | CM6: FY34E | CO6: 3YR | CP6: 5YR
A7: Net sales | B7: 8.512 | C7: 10.196 | D7: 11.132 | E7: 20.002 | F7: =+B7+C7+D7+E7 -> 49.842 | G7: 16.692 | H7: 19.382 | I7: 21.692 | J7: 32.873 | K7: =+G7+H7+I7+J7 -> 90.639 | L7: 36.655 | M7: 53.975 | N7: 60.848 | O7: 62.897 | P7: =+L7+M7+N7+O7 -> 214.375 | Q7: 67.51 | R7: 66.335 | S7: 74.569 | T7: 78.316 | U7: =+Q7+R7+S7+T7 -> 286.73 | V7: 78.665 | W7: 92.101 | X7: 94.779 | Y7: 108.108 | Z7: =+V7+W7+X7+Y7 -> 373.653 | AA7: 96.099 | AB7: 109.144 | AC7: 117.404 | AD7: 126.891 | AE7: =SUM(AA7:AD7) -> 449.538 | AF7: 128.714 | AG7: 137.15 | AH7: 143.03 | AI7: 155.054 | AJ7: =SUM(AF7:AI7) -> 563.948 | AK7: =168.491 -> 168.491 | AL7: 177.235 | AM7: 191.476 | AN7: 201.814 | AO7: =+AK7+AL7+AM7+AN7 -> 739.016 | AP7: 203.471 | AQ7: 232.088 | AR7: 265.196 | AS7: 281.266 | AT7: =SUM(AP7:AS7) -> 982.021 | AU7: =+Rev!AU36 -> 281.60532 | AV7: =+Rev!AV36 -> 311.50646 | AW7: =+Rev!AW36 -> 342.59686 | AX7: =+Rev!AX36 -> 364.22008 | AY7: =SUM(AU7:AX7) -> 1299.9287 | AZ7: =+Rev!AZ36 -> 413.59501 | BA7: =+Rev!BA36 -> 448.77172 | BB7: =+Rev!BB36 -> 470.63164 | BC7: =+Rev!BC36 -> 499.07065 | BD7: =SUM(AZ7:BC7) -> 1832.069 | BE7: =+Rev!BE36 -> 553.16834 | BF7: =+Rev!BF36 -> 592.87406 | BG7: =+Rev!BG36 -> 621.18652 | BH7: =+Rev!BH36 -> 651.68819 | BI7: =SUM(BE7:BH7) -> 2418.9171 | BJ7: =+Rev!BJ36 -> 688.0392 | BK7: =+Rev!BK36 -> 719.8563 | BL7: =+Rev!BL36 -> 752.57812 | BM7: =+Rev!BM36 -> 777.10023 | BN7: =SUM(BJ7:BM7) -> 2937.5738 | BO7: =+Rev!BO36 -> 818.64399 | BP7: =+Rev!BP36 -> 861.85048 | BQ7: =+Rev!BQ36 -> 888.40657 | BR7: =+Rev!BR36 -> 913.78389 | BS7: =SUM(BO7:BR7) -> 3482.6849 | BT7: =+Rev!BT36 -> 941.23611 | BU7: =+Rev!BU36 -> 978.11363 | BV7: =+Rev!BV36 -> 1001.4567 | BW7: =+Rev!BW36 -> 1023.3963 | BX7: =SUM(BT7:BW7) -> 3944.2028 | BY7: =+Rev!BY36 -> 1038.2503 | BZ7: =+Rev!BZ36 -> 1070.7141 | CA7: =+Rev!CA36 -> 1097.9244 | CB7: =+Rev!CB36 -> 1117.9568 | CC7: =SUM(BY7:CB7) -> 4324.8456 | CD7: =+Rev!CD36 -> 1134.0506 | CE7: =+Rev!CE36 -> 1172.2424 | CF7: =+Rev!CF36 -> 1190.4939 | CG7: =+Rev!CG36 -> 1207.8366 | CH7: =SUM(CD7:CG7) -> 4704.6235 | CI7: =+Rev!CI36 -> 1215.2078 | CJ7: =+Rev!CJ36 -> 1247.7237 | CK7: =+Rev!CK36 -> 1262.1706 | CL7: =+Rev!CL36 -> 1276.2324 | CM7: =SUM(CI7:CL7) -> 5001.3344 | CO7: =(BI7/AT7)^(1/3)-1 -> 0.35051705 | CP7: =(BS7/AT7)^(1/5)-1 -> 0.288127
A8: Cost of precision oncology testing | B8: =6.371-0.129/2 -> 6.3065 | C8: =6.954-0.129/2 -> 6.8895 | D8: =7.603-0.112 -> 7.491 | E8: =7.955-0.058 -> 7.897 | F8: =+B8+C8+D8+E8 -> 28.584 | G8: =8.045-0.063 -> 7.982 | H8: =9.506-0.079 -> 9.427 | I8: =9.671-0.112 -> 9.559 | J8: =12.624-0.258 -> 12.366 | K8: =+G8+H8+I8+J8 -> 39.334 | L8: =11.023-0.17 -> 10.853 | M8: =14.65-0.126 -> 14.524 | N8: =16.578-0.266 -> 16.312 | O8: =20.004-0.301 -> 19.703 | P8: =+L8+M8+N8+O8 -> 61.392 | Q8: =18.191-0.322 -> 17.869 | R8: =17.809-0.141-0.394 -> 17.274 | S8: =16.699-0.45 -> 16.249 | T8: =22.07-0.301-0.727 -> 21.042 | U8: =+Q8+R8+S8+T8 -> 72.434 | V8: =23.59-0.148-0.799 -> 22.643 | W8: =24.887-0.149-0.888 -> 23.85 | X8: =29.665-0.152-0.762 -> 28.751 | Y8: =32.254-0.152-1.174 -> 30.928 | Z8: =+V8+W8+X8+Y8 -> 106.172 | AA8: =30.684-0.148-1.176 -> 29.36 | AB8: =34.375-0.149-1.229 -> 32.997 | AC8: =39.434-0.285-1.377 -> 37.772 | AD8: =43.706-0.351-1.793 -> 41.562 | AE8: =SUM(AA8:AD8) -> 141.691 | AF8: =45.106-0.148-1.218 -> 43.74 | AG8: =49.357-0.149-1.225 -> 47.983 | AH8: =53.648-0.151-1.12 -> 52.377 | AI8: =57.417-0.151-1.164 -> 56.102 | AJ8: =SUM(AF8:AI8) -> 200.202 | AK8: =59.306-0.149-1.278 -> 57.879 | AL8: =65.715-0.15-1.309 -> 64.256 | AM8: =66.095-0.151-1.505 -> 64.439 | AN8: =69.465-0.151-1.337 -> 67.977 | AO8: =+AK8+AL8+AM8+AN8 -> 254.551
A9: Cost of development services | B9: 0.003 | C9: 0.481 | D9: 1.058 | E9: 1.193 | F9: =+B9+C9+D9+E9 -> 2.735 | G9: 1.208 | H9: 0.453 | I9: 0.38 | J9: 1.323 | K9: =+G9+H9+I9+J9 -> 3.364 | L9: 2.512 | M9: 2.183 | N9: 1.936 | O9: 1.834 | P9: =+L9+M9+N9+O9 -> 8.465 | Q9: 2.315 | R9: 4.626 | S9: 4.488 | T9: 6.337 | U9: =+Q9+R9+S9+T9 -> 17.766 | V9: 5.157 | W9: =5.04 -> 5.04 | X9: 1.151 | Y9: 1.168 | Z9: =+V9+W9+X9+Y9 -> 12.516 | AA9: 1.297 | AB9: 2.352 | AC9: 1.062 | AD9: 3.415 | AE9: =SUM(AA9:AD9) -> 8.126 | AF9: =7.967-0.201-0.476 -> 7.29 | AG9: =4.491-0.201-0.478 -> 3.812 | AH9: =3.966-0.201-0.437 -> 3.328 | AI9: =5.1-0.201-0.466 -> 4.433 | AJ9: =SUM(AF9:AI9) -> 18.863 | AK9: =5.99-0.2-0.499 -> 5.291 | AL9: =6.706-0.067-0.498 -> 6.141 | AM9: =8.394-2.412 -> 5.982 | AN9: =8.128-0.656 -> 7.472 | AO9: =+AK9+AL9+AM9+AN9 -> 24.886
A10: COGS | B10: =+B8+B9 -> 6.3095 | C10: =+C8+C9 -> 7.3705 | D10: =+D8+D9 -> 8.549 | E10: =+E8+E9 -> 9.09 | F10: =+F8+F9 -> 31.319 | G10: =+G8+G9 -> 9.19 | H10: =+H8+H9 -> 9.88 | I10: =+I8+I9 -> 9.939 | ... AO10: =+AO8+AO9 -> 279.437 | AP10: =74.723-0.148-2.39 -> 72.185 | AQ10: =81.205-0.15-2.759 -> 78.296 | AR10: 90.872 | AS10: 95.842 | AT10: =+AP10+AQ10+AR10+AS10 -> 337.195 | AU10: =+AU7-AU11 -> 102.1574 | AV10: =+AV7-AV11 -> 109.76079 | AW10: =+AW7-AW11 -> 120.13494 | AX10: =+AX7-AX11 -> 127.02254 | AY10: =+AU10+AV10+AW10+AX10 -> 459.07567 | AZ10: =+AZ7-AZ11 -> 147.97106 | BA10: =+BA7-BA11 -> 155.88301 | BB10: =+BB7-BB11 -> 162.67842 | BC10: =+BC7-BC11 -> 171.55662 | BD10: =+AZ10+BA10+BB10+BC10 -> 638.08912 | BE10: =+BE7-BE11 -> 195.14009 | BF10: =+BF7-BF11 -> 202.97328 | BG10: =+BG7-BG11 -> 211.61326 | BH10: =+BH7-BH11 -> 220.76079 | BI10: =+BE10+BF10+BG10+BH10 -> 830.48741 | BJ10: =+BJ7-BJ11 -> 239.27802 | BK10: =+BK7-BK11 -> 242.84697 | BL10: =+BL7-BL11 -> 252.6102 | BM10: =+BM7-BM11 -> 259.35889 | BN10: =+BJ10+BK10+BL10+BM10 -> 994.09408 | BO10: =+BO7-BO11 -> 280.60496 | BP10: =+BP7-BP11 -> 286.44014 | BQ10: =+BQ7-BQ11 -> 293.76031 | BR10: =+BR7-BR11 -> 300.40844 | BS10: =+BO10+BP10+BQ10+BR10 -> 1161.2139 | BT10: =+BT7-BT11 -> 317.91944 | BU10: =+BU7-BU11 -> 320.19019 | BV10: =+BV7-BV11 -> 326.13417 | BW10: =+BW7-BW11 -> 331.32679 | BX10: =+BT10+BU10+BV10+BW10 -> 1295.5706 | BY10: =+BY7-BY11 -> 345.49646 | BZ10: =+BZ7-BZ11 -> 345.14984 | CA10: =+CA7-CA11 -> 352.06017 | CB10: =+CB7-CB11 -> 356.35117 | CC10: =+BY10+BZ10+CA10+CB10 -> 1399.0576 | CD10: =+CD7-CD11 -> 371.70551 | CE10: =+CE7-CE11 -> 372.01676 | CF10: =+CF7-CF11 -> 375.79103 | CG10: =+CG7-CG11 -> 378.96134 | CH10: =+CD10+CE10+CF10+CG10 -> 1498.4746 | CI10: =+CI7-CI11 -> 392.23018 | CJ10: =+CJ7-CJ11 -> 389.73247 | CK10: =+CK7-CK11 -> 392.10563 | CL10: =+CL7-CL11 -> 394.03952 | CM10: =+CI10+CJ10+CK10+CL10 -> 1568.1078
A11: Gross profit | B11: =+B7-B10 -> 2.2025 | C11: =+C7-C10 -> 2.8255 | D11: =+D7-D10 -> 2.583 | E11: =+E7-E10 -> 10.912 | F11: =+F7-F10 -> 18.523 | G11: =+G7-G10 -> 7.502 | H11: =+H7-H10 -> 9.502 | I11: =+I7-I10 -> 11.753 | ... AK11: =+AK7-AK10 -> 105.321 | AL11: =AL7-AL10 -> 106.838 | AM11: =AM7-AM10 -> 121.055 | AN11: =AN7-AN10 -> 126.365 | AO11: =AO7-AO10 -> 459.579 | AP11: =AP7-AP10 -> 131.286 | AQ11: =AQ7-AQ10 -> 153.792 | AR11: =AR7-AR10 -> 174.324 | AS11: =AS7-AS10 -> 185.424 | AT11: =AT7-AT10 -> 644.826 | AU11: =+AU7*AU60 -> 179.44792 | AV11: =+AV7*AV60 -> 201.74566 | AW11: =+AW7*AW60 -> 222.46192 | AX11: =+AX7*AX60 -> 237.19754 | AY11: =AY7-AY10 -> 840.85304 | AZ11: =+AZ7*AZ60 -> 265.62395 | BA11: =+BA7*BA60 -> 292.88871 | BB11: =+BB7*BB60 -> 307.95322 | BC11: =+BC7*BC60 -> 327.51403 | BD11: =BD7-BD10 -> 1193.9799 | BE11: =+BE7*BE60 -> 358.02825 | BF11: =+BF7*BF60 -> 389.90078 | BG11: =+BG7*BG60 -> 409.57327 | BH11: =+BH7*BH60 -> 430.9274 | BI11: =BI7-BI10 -> 1588.4297 | BJ11: =+BJ7*BJ60 -> 448.76118 | BK11: =+BK7*BK60 -> 477.00932 | BL11: =+BL7*BL60 -> 499.96792 | BM11: =+BM7*BM60 -> 517.74134 | BN11: =BN7-BN10 -> 1943.4798 | BO11: =+BO7*BO60 -> 538.03903 | BP11: =+BP7*BP60 -> 575.41034 | BQ11: =+BQ7*BQ60 -> 594.64626 | BR11: =+BR7*BR60 -> 613.37545 | BS11: =BS7-BS10 -> 2321.4711 | BT11: =+BT7*BT60 -> 623.31667 | BU11: =+BU7*BU60 -> 657.92344 | BV11: =+BV7*BV60 -> 675.32256 | BW11: =+BW7*BW60 -> 692.06956 | BX11: =BX7-BX10 -> 2648.6322 | BY11: =+BY7*BY60 -> 692.75379 | BZ11: =+BZ7*BZ60 -> 725.5643 | CA11: =+CA7*CA60 -> 745.86419 | CB11: =+CB7*CB60 -> 761.60568 | CC11: =CC7-CC10 -> 2925.788 | CD11: =+CD7*CD60 -> 762.34512 | CE11: =+CE7*CE60 -> 800.22568 | CF11: =+CF7*CF60 -> 814.70287 | CG11: =+CG7*CG60 -> 828.87521 | CH11: =CH7-CH10 -> 3206.1489 | CI11: =+CI7*CI60 -> 822.97758 | CJ11: =+CJ7*CJ60 -> 857.99119 | CK11: =+CK7*CK60 -> 870.06497 | CL11: =+CL7*CL60 -> 882.19287 | CM11: =CM7-CM10 -> 3433.2266
A12: Gross profit (ex-screening) | AF12: 81.072 | AG12: 87.642 | AH12: 89.679 | AI12: 97.305 | AJ12: =+AF12+AG12+AH12+AI12 -> 355.698 | AK12: 107.951 | AL12: 109.732 | AM12: 123.963 | AN12: 126.29 | AO12: =+AK12+AL12+AM12+AN12 -> 467.936
A13: R&D expense | B13: =4.702-0.29/2 -> 4.557 | C13: =5.494-0.29/2 -> 5.349 | D13: =7.246-0.617 -> 6.629 | E13: =8.12-0.2 -> 7.92 | F13: =+B13+C13+D13+E13 -> 24.455 | G13: =8.255-0.204 -> 8.051 | H13: =11.554-0.214 -> 11.34 | I13: =14.253-0.617 -> 13.636 | J13: =16.652-0.649 -> 16.003 | K13: =+G13+H13+I13+J13 -> 49.03 | L13: =16.316-1.21 -> 15.106 | M13: =19.532-1.428 -> 18.104 | N13: =24.569-2.066 -> 22.503 | O13: =25.875-1.203 -> 24.672 | P13: =+L13+M13+N13+O13 -> 80.385 | Q13: =37.016-2.472-8.5 -> 26.044 | R13: =36.319-0.043-2.557 -> 33.719 | S13: =36.245-2.474 -> 33.771 | T13: =40.282-2.716 -> 37.566 | U13: =+Q13+R13+S13+T13 -> 131.1 | V13: =55.508-4.391 -> 51.117 | W13: =63.724-4.659 -> 59.065 | X13: =70.968-4.624 -> 66.344 | Y13: =73.021-5.696 -> 67.325 | Z13: =+V13+W13+X13+Y13 -> 243.851 | AA13: =81.757-5.41-2.12 -> 74.227 | AB13: =85.455-6.191-0.177 -> 79.087 | AC13: =100.017-7.256-0.355 -> 92.406 | AD13: =106.578-8.071-2.577 -> 95.93 | AE13: =SUM(AA13:AD13) -> 341.65 | AF13: =93.128-8.748-0.57 -> 83.81 | AG13: =90.359-8.518-0.531 -> 81.31 | AH13: =93.851-8.611-0.531 -> 84.709 | AI13: =89.856-9.409-0.45 -> 79.997 | AJ13: =SUM(AF13:AI13) -> 329.826 | AK13: =83.802-10.064-0.375 -> 73.363 | AL13: =83.102-10.001-0.11 -> 72.991 | AM13: =87.306-18.75-0.19 -> 68.366 | AN13: =93.543-12.397 -> 81.146 | AO13: =+AK13+AL13+AM13+AN13 -> 295.866 | AP13: =88.521-13.09-0.534 -> 74.897 | AQ13: =87.449-14.255-0.647 -> 72.547 | AR13: 75.79 | AS13: 85.944 | AT13: =+AP13+AQ13+AR13+AS13 -> 309.178 | AU13: =+AP13*(1+AU48) -> 78.791644 | AV13: =+AQ13*(1+AV48) -> 76.319444 | AW13: =+AR13*(1+AW48) -> 79.73108 | AX13: =+AS13*(1+AX48) -> 90.413088 | AY13: =+AU13+AV13+AW13+AX13 -> 325.25526 | AZ13: =+AU13*(1+AZ48) -> 82.731226 | BA13: =+AV13*(1+BA48) -> 80.135416 | BB13: =+AW13*(1+BB48) -> 83.717634 | BC13: =+AX13*(1+BC48) -> 94.933742 | BD13: =+AZ13+BA13+BB13+BC13 -> 341.51802 | BE13: =+AZ13*(1+BE48) -> 86.867788 | BF13: =+BA13*(1+BF48) -> 84.142187 | BG13: =+BB13*(1+BG48) -> 87.903516 | BH13: =+BC13*(1+BH48) -> 99.68043 | BI13: =+BE13+BF13+BG13+BH13 -> 358.59392 | BJ13: =+BE13*(1+BJ48) -> 91.211177 | BK13: =+BF13*(1+BK48) -> 88.349296 | BL13: =+BG13*(1+BL48) -> 92.298691 | BM13: =+BH13*(1+BM48) -> 104.66445 | BN13: =+BJ13+BK13+BL13+BM13 -> 376.52362 | BO13: =+BJ13*(1+BO48) -> 95.771736 | BP13: =+BK13*(1+BP48) -> 92.766761 | BQ13: =+BL13*(1+BQ48) -> 96.913626 | BR13: =+BM13*(1+BR48) -> 109.89767 | BS13: =+BO13+BP13+BQ13+BR13 -> 395.3498 | BT13: =+BO13*(1+BT48) -> 100.56032 | BU13: =+BP13*(1+BU48) -> 97.405099 | BV13: =+BQ13*(1+BV48) -> 101.75931 | BW13: =+BR13*(1+BW48) -> 115.39256 | BX13: =+BT13+BU13+BV13+BW13 -> 415.11729 | BY13: =+BT13*(1+BY48) -> 105.58834 | BZ13: =+BU13*(1+BZ48) -> 102.27535 | CA13: =+BV13*(1+CA48) -> 106.84727 | CB13: =+BW13*(1+CB48) -> 121.16219 | CC13: =+BY13+BZ13+CA13+CB13 -> 435.87315 | CD13: =+BY13*(1+CD48) -> 110.86776 | CE13: =+BZ13*(1+CE48) -> 107.38912 | CF13: =+CA13*(1+CF48) -> 112.18964 | CG13: =+CB13*(1+CG48) -> 127.22029 | CH13: =+CD13+CE13+CF13+CG13 -> 457.66681 | CI13: =+CD13*(1+CI48) -> 116.41114 | CJ13: =+CE13*(1+CJ48) -> 112.75858 | CK13: =+CF13*(1+CK48) -> 117.79912 | CL13: =+CG13*(1+CL48) -> 133.58131 | CM13: =+CI13+CJ13+CK13+CL13 -> 480.55015
A14: S&M expense | B14: =7.204-0.54/2 -> 6.934 | C14: =7.929-0.54/2 -> 7.659 | D14: =7.808-0.428 -> 7.38 | E14: =9.556-0.066 -> 9.49 | F14: =+B14+C14+D14+E14 -> 31.463 | G14: =11.312-0.374 -> 10.938 | H14: =11.575-0.259 -> 11.316 | I14: =13.464-0.428 -> 13.036 | J14: =17.114-0.666 -> 16.448 | K14: =+G14+H14+I14+J14 -> 51.738 | L14: =17.807-0.826 -> 16.981 | M14: =19.439-0.646 -> 18.793 | N14: =18.802-1.458 -> 17.344 | O14: =22.287-1.786 -> 20.501 | P14: =+L14+M14+N14+O14 -> 73.619 | Q14: =25.115-1.93 -> 23.185 | R14: =25.015-2.065 -> 22.95 | S14: =25.095-2.379 -> 22.716 | T14: =31.288-3.032 -> 28.256 | U14: =+Q14+R14+S14+T14 -> 97.107 | V14: =34.338-2.934 -> 31.404 | W14: =47.716-3.493 -> 44.223 | X14: =50.228-4.127 -> 46.101 | Y14: =59.599-5.208 -> 54.391 | Z14: =+V14+W14+X14+Y14 -> 176.119 | AA14: =64.432-5.57 -> 58.862 | AB14: =73.603-0.134-6.054 -> 67.415 | AC14: =80.37-0.067-6.643 -> 73.66 | AD14: =81.423-7.399 -> 74.024 | AE14: =SUM(AA14:AD14) -> 273.961 | AF14: =76.123-7.543 -> 68.58 | AG14: =71.043-5.977 -> 65.066 | AH14: =68.934-5.137 -> 63.797 | AI14: =79.127-6.438 -> 72.689 | AJ14: =SUM(AF14:AI14) -> 270.132 | AK14: =80.425-7.329 -> 73.096 | AL14: =81.867-7.258 -> 74.609 | AM14: =97.88-13.287 -> 84.593 | AN14: =104.763-8.997 -> 95.766 | AO14: =+AK14+AL14+AM14+AN14 -> 328.064 | AP14: =104.316-10.189 -> 94.127 | AQ14: =119.588-11.756 -> 107.832 | AR14: 115.924 | AS14: 130.536 | AT14: =+AP14+AQ14+AR14+AS14 -> 448.419 | AU14: =+AP14*(1+AU49) -> 117.18812 | AV14: =+AQ14*(1+AV49) -> 134.25084 | AW14: =+AR14*(1+AW49) -> 144.32538 | AX14: =+AS14*(1+AX49) -> 162.51732 | AY14: =+AU14+AV14+AW14+AX14 -> 558.28166 | AZ14: =+AU14*(1+AZ49) -> 140.62574 | BA14: =+AV14*(1+BA49) -> 161.10101 | BB14: =+AW14*(1+BB49) -> 173.19046 | BC14: =+AX14*(1+BC49) -> 195.02078 | BD14: =+AZ14+BA14+BB14+BC14 -> 669.93799 | BE14: =+AZ14*(1+BE49) -> 161.7196 | BF14: =+BA14*(1+BF49) -> 185.26616 | BG14: =+BB14*(1+BG49) -> 199.16902 | BH14: =+BC14*(1+BH49) -> 224.2739 | BI14: =+BE14+BF14+BG14+BH14 -> 770.42868 | BJ14: =+BE14*(1+BJ49) -> 182.90487 | BK14: =+BF14*(1+BK49) -> 209.53603 | BL14: =+BG14*(1+BL49) -> 225.26017 | BM14: =+BH14*(1+BM49) -> 253.65378 | BN14: =+BJ14+BK14+BL14+BM14 -> 871.35484 | BO14: =+BJ14*(1+BO49) -> 205.03635 | BP14: =+BK14*(1+BP49) -> 234.88989 | BQ14: =+BL14*(1+BQ49) -> 252.51665 | BR14: =+BM14*(1+BR49) -> 284.34589 | BS14: =+BO14+BP14+BQ14+BR14 -> 976.78878 | BT14: =+BO14*(1+BT49) -> 227.79539 | BU14: =+BP14*(1+BU49) -> 260.96266 | BV14: =+BQ14*(1+BV49) -> 280.54599 | BW14: =+BR14*(1+BW49) -> 315.90828 | BX14: =+BT14+BU14+BV14+BW14 -> 1085.2123 | BY14: =+BT14*(1+BY49) -> 250.80272 | BZ14: =+BU14*(1+BZ49) -> 287.31989 | CA14: =+BV14*(1+CA49) -> 308.88114 | CB14: =+BW14*(1+CB49) -> 347.81502 | CC14: =+BY14+BZ14+CA14+CB14 -> 1194.8188 | CD14: =+BY14*(1+CD49) -> 273.62577 | CE14: =+BZ14*(1+CE49) -> 313.466 | CF14: =+CA14*(1+CF49) -> 336.98932 | CG14: =+CB14*(1+CG49) -> 379.46619 | CH14: =+CD14+CE14+CF14+CG14 -> 1303.5473 | CI14: =+CD14*(1+CI49) -> 295.78946 | CJ14: =+CE14*(1+CJ49) -> 338.85675 | CK14: =+CF14*(1+CK49) -> 364.28546 | CL14: =+CG14*(1+CL49) -> 410.20295 | CM14: =+CI14+CJ14+CK14+CL14 -> 1409.1346
A15: G&A expense | B15: =5.212-0.331/2 -> 5.0465 | C15: =6.675-0.331/2 -> 6.5095 | D15: =16.095-0.674 -> 15.421 | E15: =8.795-1.248 -> 7.547 | F15: =+B15+C15+D15+E15 -> 34.524 | G15: =6.519-0.636 -> 5.883 | H15: =8.997-0.628 -> 8.369 | I15: =8.129-0.674 -> 7.455 | J15: =12.547-0.99 -> 11.557 | K15: =+G15+H15+I15+J15 -> 33.264 | L15: =12.661-0.976 -> 11.685 | M15: =13.439-1.015 -> 12.424 | N15: =16.44-1.694 -> 14.746 | O15: =18.859-1.782 -> 17.077 | P15: =+L15+M15+N15+O15 -> 55.932 | Q15: =19.785-0.229-1.911+0.19-1.207 -> 16.628 | R15: =37.186-0.349-20.651 -> 16.186 | S15: =66.294-0.503-50.397-0.07 -> 15.324 | T15: =69.505-0.189-50.428 -> 18.888 | U15: =+Q15+R15+S15+T15 -> 67.026 | V15: =67.935-0.333-49.375 -> 18.227 | W15: =48.376-0.336-25.735-0.875 -> 21.43 | X15: =50.055-0.339-26.044-0.97 -> 22.702 | Y15: =40.274-0.339-14.951-0.535 -> 24.449 | Z15: =+V15+W15+X15+Y15 -> 86.808 | AA15: =41.267-0.332-12.835-2.39-0.063 -> 25.647 | AB15: =43.68-0.336-12.252-1.415+0.063 -> 29.74 | AC15: =41.121-0.339-5.955-0.39 -> 34.437 | AD15: =37.888-0.339-6.24-0.11 -> 31.199 | AE15: =+AA15+AB15+AC15+AD15 -> 121.023 | AF15: =40.445-0.331-4.468+0.3 -> 35.946 | AG15: =41.516-0.336-6.755-0.31 -> 34.115 | AH15: =36.174-0.339-6.794-0.22 -> 28.821 | AI15: =37.665-0.339-7.081+0.12 -> 30.365 | AJ15: =+AF15+AG15+AH15+AI15 -> 129.247 | AK15: =38.651-0.336-8.164-0.12 -> 30.031 | AL15: =40.463-0.335-8.659-0.3 -> 31.169 | AM15: =49.129-0.34-14.068-0.34 -> 34.381 | AN15: =51.88-0.34-13.519-0.25 -> 37.771 | AO15: =+AK15+AL15+AM15+AN15 -> 133.352 | AP15: =46.952-0.332-13.571-0.49-2 -> 30.559 | AQ15: =50.259-0.266-14.832-0.23 -> 34.931 | AR15: 37.136 | AS15: 43.519 | AT15: =+AP15+AQ15+AR15+AS15 -> 146.145 | AU15: =+AP15*(1+AU50) -> 32.08695 | AV15: =+AQ15*(1+AV50) -> 36.67755 | AW15: =+AR15*(1+AW50) -> 38.9928 | AX15: =+AS15*(1+AX50) -> 45.69495 | AY15: =+AU15+AV15+AW15+AX15 -> 153.45225 | AZ15: =+AU15*(1+AZ50) -> 33.691298 | BA15: =+AV15*(1+BA50) -> 38.511428 | BB15: =+AW15*(1+BB50) -> 40.94244 | BC15: =+AX15*(1+BC50) -> 47.979698 | BD15: =+AZ15+BA15+BB15+BC15 -> 161.12486 | BE15: =+AZ15*(1+BE50) -> 35.375862 | BF15: =+BA15*(1+BF50) -> 40.436999 | BG15: =+BB15*(1+BG50) -> 42.989562 | BH15: =+BC15*(1+BH50) -> 50.378682 | BI15: =+BE15+BF15+BG15+BH15 -> 169.18111 | BJ15: =+BE15*(1+BJ50) -> 37.144655 | BK15: =+BF15*(1+BK50) -> 42.458849 | BL15: =+BG15*(1+BL50) -> 45.13904 | BM15: =+BH15*(1+BM50) -> 52.897616 | BN15: =+BJ15+BK15+BL15+BM15 -> 177.64016 | BO15: =+BJ15*(1+BO50) -> 39.001888 | BP15: =+BK15*(1+BP50) -> 44.581791 | BQ15: =+BL15*(1+BQ50) -> 47.395992 | BR15: =+BM15*(1+BR50) -> 55.542497 | BS15: =+BO15+BP15+BQ15+BR15 -> 186.52217 | BT15: =+BO15*(1+BT50) -> 40.951983 | BU15: =+BP15*(1+BU50) -> 46.810881 | BV15: =+BQ15*(1+BV50) -> 49.765792 | BW15: =+BR15*(1+BW50) -> 58.319622 | BX15: =+BT15+BU15+BV15+BW15 -> 195.84828 | BY15: =+BT15*(1+BY50) -> 42.999582 | BZ15: =+BU15*(1+BZ50) -> 49.151425 | CA15: =+BV15*(1+CA50) -> 52.254081 | CB15: =+BW15*(1+CB50) -> 61.235603 | CC15: =+BY15+BZ15+CA15+CB15 -> 205.64069 | CD15: =+BY15*(1+CD50) -> 45.149561 | CE15: =+BZ15*(1+CE50) -> 51.608996 | CF15: =+CA15*(1+CF50) -> 54.866785 | CG15: =+CB15*(1+CG50) -> 64.297383 | CH15: =+CD15+CE15+CF15+CG15 -> 215.92273 | CI15: =+CD15*(1+CI50) -> 47.407039 | CJ15: =+CE15*(1+CJ50) -> 54.189446 | CK15: =+CF15*(1+CK50) -> 57.610125 | CL15: =+CG15*(1+CL50) -> 67.512253 | CM15: =+CI15+CJ15+CK15+CL15 -> 226.71886
A16: Operating expenses | B16: =+B13+B14+B15 -> 16.5375 | C16: =+C13+C14+C15 -> 19.5175 | D16: =+D13+D14+D15 -> 29.43 | E16: =+E13+E14+E15 -> 24.957 | F16: =+F13+F14+F15 -> 90.442 | G16: =+G13+G14+G15 -> 24.872 | H16: =+H13+H14+H15 -> 31.025 | I16: =+I13+I14+I15 -> 34.127 | ... CM16: =+CM13+CM14+CM15 -> 2116.4036
A17: Operating income (EBITA , ex-SBC) | B17: =+B11-B16 -> -14.335 | C17: =+C11-C16 -> -16.692 | D17: =+D11-D16 -> -26.847 | E17: =+E11-E16 -> -14.045 | F17: =+F11-F16 -> -71.919 | G17: =+G11-G16 -> -17.37 | H17: =+H11-H16 -> -21.523 | I17: =+I11-I16 -> -22.374 | ... CM17: =+CM11-CM16 -> 1316.823
A18: Interest expense | B18: 1.039 | C18: 1.056 | D18: 0.303 | E18: 0.304 | F18: =+B18+C18+D18+E18 -> 2.702 | G18: 0.331 | H18: 0.317 | I18: 0.304 | J18: 0.299 | K18: =+G18+H18+I18+J18 -> 1.251 | L18: 0.293 | M18: 0.287 | N18: 0.28 | O18: 0.321 | P18: =+L18+M18+N18+O18 -> 1.181 | Q18: 0.012 | R18: 0.01 | S18: 0.008 | T18: 4.736 | U18: =+Q18+R18+S18+T18 -> 4.766 | V18: 0.646 | W18: 0.644 | X18: 0.644 | Y18: 0.643 | Z18: =+V18+W18+X18+Y18 -> 2.577 | AA18: 0.644 | AB18: 0.645 | AC18: 0.644 | AD18: 0.644 | AE18: 2.577 | AF18: 0.644 | AG18: 0.645 | AH18: 0.644 | AI18: 0.645 | AJ18: =SUM(AF18:AI18) -> 2.578 | AK18: 0.645 | AL18: 0.645 | AM18: 0.646 | AN18: 0.645 | AO18: =+AK18+AL18+AM18+AN18 -> 2.581 | AP18: 0.791 | AQ18: 0.983 | AR18: 0.943 | AS18: 1.18 | AT18: =SUM(AP18:AS18) -> 3.897 | AU18: ='Other Accts'!AU40 -> 0.869369 | AV18: ='Other Accts'!AV40 -> 0.869369 | AW18: ='Other Accts'!AW40 -> 0.869369 | AX18: ='Other Accts'!AX40 -> 0.869369 | AY18: =SUM(AU18:AX18) -> 3.477476 | AZ18: ='Other Accts'!AZ40 -> 0.869369 | BA18: ='Other Accts'!BA40 -> 0.869369 | BB18: ='Other Accts'!BB40 -> 0.869369 | BC18: ='Other Accts'!BC40 -> 0.869369 | BD18: =SUM(AZ18:BC18) -> 3.477476 | BE18: ='Other Accts'!BE40 -> 0.625077 | BF18: ='Other Accts'!BF40 -> 0.625077 | BG18: ='Other Accts'!BG40 -> 0.625077 | BH18: ='Other Accts'!BH40 -> 0.625077 | BI18: =SUM(BE18:BH18) -> 2.500308 | BJ18: ='Other Accts'!BJ40 -> 0.625077 | BK18: ='Other Accts'!BK40 -> 0.625077 | BL18: ='Other Accts'!BL40 -> 0.625077 | BM18: ='Other Accts'!BM40 -> 0.625077 | BN18: =SUM(BJ18:BM18) -> 2.500308 | BO18: ='Other Accts'!BO40 -> 0.625077 | BP18: ='Other Accts'!BP40 -> 0.625077 | BQ18: ='Other Accts'!BQ40 -> 0.625077 | BR18: ='Other Accts'!BR40 -> 0.625077 | BS18: =SUM(BO18:BR18) -> 2.500308 | BT18: ='Other Accts'!BT40 -> 0.625077 | BU18: ='Other Accts'!BU40 -> -0.006906419 | BV18: ='Other Accts'!BV40 -> -0.006906419 | BW18: ='Other Accts'!BW40 -> -0.006906419 | BX18: =SUM(BT18:BW18) -> 0.60435774 | BY18: ='Other Accts'!BY40 -> -0.006906419 | BZ18: ='Other Accts'!BZ40 -> 0 | CA18: ='Other Accts'!CA40 -> 0 | CB18: ='Other Accts'!CB40 -> 0 | CC18: =SUM(BY18:CB18) -> -0.006906419 | CD18: ='Other Accts'!CD40 -> 0 | CE18: ='Other Accts'!CE40 -> 0 | CF18: ='Other Accts'!CF40 -> 0 | CG18: ='Other Accts'!CG40 -> 0 | CH18: =SUM(CD18:CG18) -> 0 | CI18: ='Other Accts'!CI40 -> 0 | CJ18: ='Other Accts'!CJ40 -> 0 | CK18: ='Other Accts'!CK40 -> 0 | CL18: ='Other Accts'!CL40 -> 0 | CM18: =SUM(CI18:CL18) -> 0
A19: Interest income | B19: -0.205 | C19: -0.36 | D19: -0.657 | E19: -1.012 | F19: =+B19+C19+D19+E19 -> -2.234 | G19: -0.985 | H19: -0.989 | I19: -0.958 | J19: -2.334 | K19: =+G19+H19+I19+J19 -> -5.266 | L19: -2.485 | M19: -3.099 | N19: -4.286 | O19: -3.871 | P19: =+L19+M19+N19+O19 -> -13.741 | Q19: -3.318 | R19: -2.64 | S19: -2.313 | T19: -1.9 | U19: =+Q19+R19+S19+T19 -> -10.171 | V19: -1.551 | W19: -1.037 | X19: -0.689 | Y19: -0.653 | Z19: =+V19+W19+X19+Y19 -> -3.93 | AA19: -0.778 | AB19: -1.387 | AC19: -1.754 | AD19: -2.15 | AE19: -6.069 | AF19: -3.06 | AG19: -6.727 | AH19: -11.69 | AI19: -13.888 | AJ19: =SUM(AF19:AI19) -> -35.365 | AK19: -14.868 | AL19: -13.913 | AM19: -13.257 | AN19: -11.653 | AO19: =+AK19+AL19+AM19+AN19 -> -53.691 | AP19: -9.112 | AQ19: -7.56 | AR19: -7.391 | AS19: -10.032 | AT19: =SUM(AP19:AS19) -> -34.095 | AU19: =-'Other Accts'!AU8 -> -12.01598 | AV19: =-'Other Accts'!AV8 -> -11.319718 | AW19: =-'Other Accts'!AW8 -> -9.3321193 | AX19: =-'Other Accts'!AX8 -> -9.0730643 | AY19: =SUM(AU19:AX19) -> -41.740882 | AZ19: =-'Other Accts'!AZ8 -> -7.7207031 | BA19: =-'Other Accts'!BA8 -> -7.4608202 | BB19: =-'Other Accts'!BB8 -> -7.1863147 | BC19: =-'Other Accts'!BC8 -> -7.2443052 | BD19: =SUM(AZ19:BC19) -> -29.612143 | BE19: =-'Other Accts'!BE8 -> -3.9290411 | BF19: =-'Other Accts'!BF8 -> -4.0461887 | BG19: =-'Other Accts'!BG8 -> -4.0763709 | BH19: =-'Other Accts'!BH8 -> -4.5782476 | BI19: =SUM(BE19:BH19) -> -16.629848 | BJ19: =-'Other Accts'!BJ8 -> -5.4936504 | BK19: =-'Other Accts'!BK8 -> -6.2002691 | BL19: =-'Other Accts'!BL8 -> -6.5251801 | BM19: =-'Other Accts'!BM8 -> -7.4661191 | BN19: =SUM(BJ19:BM19) -> -25.685219 | BO19: =-'Other Accts'!BO8 -> -8.8860166 | BP19: =-'Other Accts'!BP8 -> -10.006369 | BQ19: =-'Other Accts'!BQ8 -> -10.719199 | BR19: =-'Other Accts'!BR8 -> -12.127092 | BS19: =SUM(BO19:BR19) -> -41.738677 | BT19: =-'Other Accts'!BT8 -> -14.103087 | BU19: =-'Other Accts'!BU8 -> -11.093802 | BV19: =-'Other Accts'!BV8 -> -12.092257 | BW19: =-'Other Accts'!BW8 -> -13.868346 | BX19: =SUM(BT19:BW19) -> -51.157493 | BY19: =-'Other Accts'!BY8 -> -16.263805 | BZ19: =-'Other Accts'!BZ8 -> -18.281468 | CA19: =-'Other Accts'!CA8 -> -19.517817 | CB19: =-'Other Accts'!CB8 -> -21.618196 | CC19: =SUM(BY19:CB19) -> -75.681286 | CD19: =-'Other Accts'!CD8 -> -24.368937 | CE19: =-'Other Accts'!CE8 -> -26.698893 | CF19: =-'Other Accts'!CF8 -> -25.292288 | CG19: =-'Other Accts'!CG8 -> -27.680061 | CH19: =SUM(CD19:CG19) -> -104.04018 | CI19: =-'Other Accts'!CI8 -> -30.743792 | CJ19: =-'Other Accts'!CJ8 -> -33.337621 | CK19: =-'Other Accts'!CK8 -> -35.047224 | CL19: =-'Other Accts'!CL8 -> -37.672196 | CM19: =SUM(CI19:CL19) -> -136.80083
A20: Other expense, net | B20: 0.204 | C20: 0.445 | D20: 0.266 | E20: 0.144 | F20: =+B20+C20+D20+E20 -> 1.059 | G20: -4.149 | H20: -0.395 | I20: -0.043 | J20: -0.115 | K20: =+G20+H20+I20+J20 -> -4.702 | L20: -0.147 | M20: 0.051 | N20: -0.179 | O20: 0.187 | P20: =+L20+M20+N20+O20 -> -0.088 | Q20: 0.209 | R20: -2.285 | S20: -0.345 | T20: =-1.22+1 -> -0.22 | U20: =+Q20+R20+S20+T20 -> -2.641 | V20: 0.29 | W20: 0.243 | X20: 0.187 | Y20: =-25.898+26.1 -> 0.202 | Z20: =+V20+W20+X20+Y20 -> 0.922 | AA20: 0.048 | AB20: =-0.378+99.785 -> 99.407 | AC20: =18.389-13.23-5.261 -> -0.102 | AD20: =-5.281+5.437+1.1 -> 1.256 | AE20: =SUM(AA20:AD20) -> 100.609 | AF20: =1.654+3.882-5.485 -> 0.051 | AG20: =-41.259+63.997-23.569 -> -0.831 | AH20: =-16.885+16.634 -> -0.251 | AI20: =3.316-4.803+2.631 -> 1.144 | AJ20: =SUM(AF20:AI20) -> 0.113 | AK20: =29.12-30.054 -> -0.934 | AL20: =15.145-15.485 -> -0.34 | AM20: =3.007-1.686 -> 1.321 | AN20: =-4.667+2.824+1.1 -> -0.743 | AO20: =+AK20+AL20+AM20+AN20 -> -0.696 | AP20: =-7.851-5+13.672 -> 0.821 | AQ20: 0.025 | AR20: 0.048 | AS20: =18.268-13.582-4.9 -> -0.214 | AT20: =SUM(AP20:AS20) -> 0.68 | AU20: 0 | AV20: 0 | AW20: 0 | AX20: 0 | AY20: =SUM(AU20:AX20) -> 0 | AZ20: 0 | BA20: 0 | BB20: 0 | BC20: 0 | BD20: =SUM(AZ20:BC20) -> 0 | BE20: 0 | BF20: 0 | BG20: 0 | BH20: 0 | BI20: =SUM(BE20:BH20) -> 0 | BJ20: 0 | BK20: 0 | BL20: 0 | BM20: 0 | BN20: =SUM(BJ20:BM20) -> 0 | BO20: 0 | BP20: 0 | BQ20: 0 | BR20: 0 | BS20: =SUM(BO20:BR20) -> 0 | BT20: 0 | BU20: 0 | BV20: 0 | BW20: 0 | BX20: =SUM(BT20:BW20) -> 0 | BY20: 0 | BZ20: 0 | CA20: 0 | CB20: 0 | CC20: =SUM(BY20:CB20) -> 0 | CD20: 0 | CE20: 0 | CF20: 0 | CG20: 0 | CH20: =SUM(CD20:CG20) -> 0 | CI20: 0 | CJ20: 0 | CK20: 0 | CL20: 0 | CM20: =SUM(CI20:CL20) -> 0
A21: Income before taxes | B21: =+B17-B18-B19-B20 -> -15.373 | C21: =+C17-C18-C19-C20 -> -17.833 | D21: =+D17-D18-D19-D20 -> -26.759 | E21: =+E17-E18-E19-E20 -> -13.481 | F21: =+F17-F18-F19-F20 -> -73.446 | G21: =+G17-G18-G19-G20 -> -12.567 | H21: =+H17-H18-H19-H20 -> -20.456 | I21: =+I17-I18-I19-I20 -> -21.677 | ... CM21: =+CM17-CM18-CM19-CM20 -> 1453.6238
A22: Income tax | B22: 0 | C22: 0 | D22: 0 | E22: 0.007 | F22: =+B22+C22+D22+E22 -> 0.007 | G22: 0 | H22: 0.003 | I22: 0 | J22: 0.035 | K22: =+G22+H22+I22+J22 -> 0.038 | L22: 0.026 | M22: -1.207 | N22: -0.202 | O22: -0.489 | P22: =+L22+M22+N22+O22 -> -1.872 | Q22: 0.014 | R22: 0.034 | S22: 0.068 | T22: 0.263 | U22: =+Q22+R22+S22+T22 -> 0.379 | V22: 0.11 | W22: 0.083 | X22: 0.096 | Y22: 0.011 | Z22: =+V22+W22+X22+Y22 -> 0.3 | AA22: -0.024 | AB22: 0.446 | AC22: 0.115 | AD22: 0.602 | AE22: =SUM(AA22:AD22) -> 1.139 | AF22: 0.24 | AG22: 0.496 | AH22: 0.49 | AI22: -0.541 | AJ22: =SUM(AF22:AI22) -> 0.685 | AK22: 0.405 | AL22: 0.133 | AM22: 0.03 | AN22: 0.716 | AO22: =+AK22+AL22+AM22+AN22 -> 1.284 | AP22: 0.29 | AQ22: 0.038 | AR22: 0.136 | AS22: -1.727 | AT22: =+AP22+AQ22+AR22+AS22 -> -1.263 | AU22: =AU21*AU71 -> -0.1873609 | AV22: =AV21*AV71 -> -0.17525911 | AW22: =AW21*AW71 -> -0.16062293 | AX22: =AX21*AX71 -> -0.26612063 | AY22: =+AU22+AV22+AW22+AX22 -> -0.78936357 | AZ22: =AZ21*AZ71 -> 0.077135125 | BA22: =BA21*BA71 -> 0.098661566 | BB22: =BB21*BB71 -> 0.082098157 | BC22: =BC21*BC71 -> -0.020226276 | BD22: =+AZ22+BA22+BB22+BC22 -> 0.23766857 | BE22: =BE21*BE71 -> 0.38684482 | BF22: =BF21*BF71 -> 0.41738274 | BG22: =BG21*BG71 -> 0.41481229 | BH22: =BH21*BH71 -> 0.30273778 | BI22: =+BE22+BF22+BG22+BH22 -> 1.5217776 | BJ22: =BJ21*BJ71 -> 0.7118453 | BK22: =BK21*BK71 -> 0.71120171 | BL22: =BL21*BL71 -> 0.71585063 | BM22: =BM21*BM71 -> 0.56683266 | BN22: =+BJ22+BK22+BL22+BM22 -> 2.7057303 | BO22: =BO21*BO71 -> 1.0324499 | BP22: =BP21*BP71 -> 1.062766 | BQ22: =BQ21*BQ71 -> 1.0395706 | BR22: =BR21*BR71 -> 0.87545702 | BS22: =+BO22+BP22+BQ22+BR22 -> 4.0102435 | BT22: =BT21*BT71 -> 1.3374349 | BU22: =BU21*BU71 -> 1.3192275 | BV22: =BV21*BV71 -> 1.2767532 | BW22: =BW21*BW71 -> 1.0816217 | BX22: =+BT22+BU22+BV22+BW22 -> 5.0150373 | BY22: =BY21*BY71 -> 1.5481693 | BZ22: =BZ21*BZ71 -> 1.5254955 | CA22: =CA21*CA71 -> 1.4869976 | CB22: =CB21*CB71 -> 1.2650553 | CC22: =+BY22+BZ22+CA22+CB22 -> 5.8257177 | CD22: =CD21*CD71 -> 1.7853548 | CE22: =CE21*CE71 -> 1.7723023 | CF22: =CF21*CF71 -> 1.679747 | CG22: =CG21*CG71 -> 1.427857 | CH22: =+CD22+CE22+CF22+CG22 -> 6.6652612 | CI22: =CI21*CI71 -> 1.9705686 | CJ22: =CJ21*CJ71 -> 1.9276202 | CK22: =CK21*CK71 -> 1.8270875 | CL22: =CL21*CL71 -> 1.5428428 | CM22: =+CI22+CJ22+CK22+CL22 -> 7.2681191
A23: Minority interest | B23: 0 | C23: 0 | D23: 0 | E23: 0 | F23: =+B23+C23+D23+E23 -> 0 | G23: 0 | H23: 0 | I23: 0 | J23: 0 | K23: =+G23+H23+I23+J23 -> 0 | L23: 0 | M23: 0 | N23: 0 | O23: 0 | P23: =+L23+M23+N23+O23 -> 0 | Q23: 0 | R23: 0 | S23: 0 | T23: 0 | U23: =+Q23+R23+S23+T23 -> 0 | V23: 0 | W23: 0 | X23: 0 | Y23: 0 | Z23: =+V23+W23+X23+Y23 -> 0 | AA23: 0 | AB23: 99.785 | AC23: 0 | AD23: 0 | AE23: =SUM(AA23:AD23) -> 99.785 | AF23: 0 | AG23: 0 | AH23: 0 | AI23: 0 | AJ23: =SUM(AF23:AI23) -> 0 | AK23: 0 | AL23: 0 | AM23: 0 | AN23: 0 | AO23: =+AK23+AL23+AM23+AN23 -> 0 | AP23: 0 | AQ23: 0 | AR23: 0 | AS23: 0 | AT23: =+AP23+AQ23+AR23+AS23 -> 0 | AU23: 0 | AV23: 0 | AW23: 0 | AX23: 0 | AY23: =+AU23+AV23+AW23+AX23 -> 0 | AZ23: 0 | BA23: 0 | BB23: 0 | BC23: 0 | BD23: =+AZ23+BA23+BB23+BC23 -> 0 | BE23: 0 | BF23: 0 | BG23: 0 | BH23: 0 | BI23: =+BE23+BF23+BG23+BH23 -> 0 | BJ23: 0 | BK23: 0 | BL23: 0 | BM23: 0 | BN23: =+BJ23+BK23+BL23+BM23 -> 0 | BO23: 0 | BP23: 0 | BQ23: 0 | BR23: 0 | BS23: =+BO23+BP23+BQ23+BR23 -> 0 | BT23: 0 | BU23: 0 | BV23: 0 | BW23: 0 | BX23: =+BT23+BU23+BV23+BW23 -> 0 | BY23: 0 | BZ23: 0 | CA23: 0 | CB23: 0 | CC23: =+BY23+BZ23+CA23+CB23 -> 0 | CD23: 0 | CE23: 0 | CF23: 0 | CG23: 0 | CH23: =+CD23+CE23+CF23+CG23 -> 0 | CI23: 0 | CJ23: 0 | CK23: 0 | CL23: 0 | CM23: =+CI23+CJ23+CK23+CL23 -> 0
A24: Non-GAAP net income | B24: =B21-B22+B23 -> -15.373 | C24: =C21-C22+C23 -> -17.833 | D24: =D21-D22+D23 -> -26.759 | E24: =E21-E22+E23 -> -13.488 | F24: =F21-F22+F23 -> -73.453 | G24: =G21-G22+G23 -> -12.567 | H24: =H21-H22+H23 -> -20.459 | I24: =I21-I22+I23 -> -21.677 | ... CM24: =CM21-CM22+CM23 -> 1446.3557
A25: Amortization of intangible assets | B25: 0 | C25: 0 | D25: 0 | E25: 0 | F25: =+B25+C25+D25+E25 -> 0 | G25: 0 | H25: 0 | I25: 0 | J25: 0 | K25: =+G25+H25+I25+J25 -> 0 | L25: 0 | M25: 0 | N25: 0 | O25: 0 | P25: =+L25+M25+N25+O25 -> 0 | Q25: 0.229 | R25: =0.141+0.043+0.349 -> 0.533 | S25: 0.503 | T25: 0.49 | U25: =+Q25+R25+S25+T25 -> 1.755 | V25: 0.481 | W25: =0.149+0.336 -> 0.485 | X25: 0.491 | Y25: 0.491 | Z25: =+V25+W25+X25+Y25 -> 1.948 | AA25: 0.48 | AB25: 0.619 | AC25: 0.691 | AD25: 0.69 | AE25: =SUM(AA25:AD25) -> 2.48 | AF25: 0.68 | AG25: =0.686 -> 0.686 | AH25: 0.691 | AI25: 0.691 | AJ25: =SUM(AF25:AI25) -> 2.748 | AK25: 0.685 | AL25: 0.552 | AM25: 0.491 | AN25: 0.491 | AO25: =+AK25+AL25+AM25+AN25 -> 2.219 | AP25: 0.48 | AQ25: 0.416 | AR25: 0.387 | AS25: 0.387 | AT25: =+AP25+AQ25+AR25+AS25 -> 1.67 | AU25: =-'Other Accts'!AU57 -> 0.81003125 | AV25: =-'Other Accts'!AV57 -> 0.81003125 | AW25: =-'Other Accts'!AW57 -> 0.81003125 | AX25: =-'Other Accts'!AX57 -> 0.81003125 | AY25: =+AU25+AV25+AW25+AX25 -> 3.240125 | AZ25: =-'Other Accts'!AZ57 -> 0.70877734 | BA25: =-'Other Accts'!BA57 -> 0.70877734 | BB25: =-'Other Accts'!BB57 -> 0.70877734 | BC25: =-'Other Accts'!BC57 -> 0.70877734 | BD25: =+AZ25+BA25+BB25+BC25 -> 2.8351094 | BE25: =-'Other Accts'!BE57 -> 0.62018018 | BF25: =-'Other Accts'!BF57 -> 0.62018018 | BG25: =-'Other Accts'!BG57 -> 0.62018018 | BH25: =-'Other Accts'!BH57 -> 0.62018018 | BI25: =+BE25+BF25+BG25+BH25 -> 2.4807207 | BJ25: =-'Other Accts'!BJ57 -> 0.54265765 | BK25: =-'Other Accts'!BK57 -> 0.54265765 | BL25: =-'Other Accts'!BL57 -> 0.54265765 | BM25: =-'Other Accts'!BM57 -> 0.54265765 | BN25: =+BJ25+BK25+BL25+BM25 -> 2.1706306 | BO25: =-'Other Accts'!BO57 -> 0.47482545 | BP25: =-'Other Accts'!BP57 -> 0.47482545 | BQ25: =-'Other Accts'!BQ57 -> 0.47482545 | BR25: =-'Other Accts'!BR57 -> 0.47482545 | BS25: =+BO25+BP25+BQ25+BR25 -> 1.8993018 | BT25: =-'Other Accts'!BT57 -> 0.41547227 | BU25: =-'Other Accts'!BU57 -> 0.41547227 | BV25: =-'Other Accts'!BV57 -> 0.41547227 | BW25: =-'Other Accts'!BW57 -> 0.41547227 | BX25: =+BT25+BU25+BV25+BW25 -> 1.6618891 | BY25: =-'Other Accts'!BY57 -> 0.36353823 | BZ25: =-'Other Accts'!BZ57 -> 0.36353823 | CA25: =-'Other Accts'!CA57 -> 0.36353823 | CB25: =-'Other Accts'!CB57 -> 0.36353823 | CC25: =+BY25+BZ25+CA25+CB25 -> 1.4541529 | CD25: =-'Other Accts'!CD57 -> 0.31809595 | CE25: =-'Other Accts'!CE57 -> 0.31809595 | CF25: =-'Other Accts'!CF57 -> 0.31809595 | CG25: =-'Other Accts'!CG57 -> 0.31809595 | CH25: =+CD25+CE25+CF25+CG25 -> 1.2723838 | CI25: =-'Other Accts'!CI57 -> 0.27833396 | CJ25: =-'Other Accts'!CJ57 -> 0.27833396 | CK25: =-'Other Accts'!CK57 -> 0.27833396 | CL25: =-'Other Accts'!CL57 -> 0.27833396 | CM25: =+CI25+CJ25+CK25+CL25 -> 1.1133358
A26: Equity compensation | B26: =1.29/2 -> 0.645 | C26: =1.29/2 -> 0.645 | D26: 1.831 | E26: 1.572 | F26: =+B26+C26+D26+E26 -> 4.693 | G26: 1.277 | H26: 1.18 | I26: 1.831 | J26: 2.563 | K26: =+G26+H26+I26+J26 -> 6.851 | L26: 3.182 | M26: 3.215 | N26: 5.484 | O26: 5.072 | P26: =+L26+M26+N26+O26 -> 16.953 | Q26: 6.635 | R26: 25.667 | S26: 55.7 | T26: 56.903 | U26: =+Q26+R26+S26+T26 -> 144.905 | V26: 57.499 | W26: 34.775 | X26: 35.557 | Y26: 27.029 | Z26: =+V26+W26+X26+Y26 -> 154.86 | AA26: 24.991 | AB26: 25.726 | AC26: 21.231 | AD26: 23.503 | AE26: =SUM(AA26:AD26) -> 95.451 | AF26: 22.453 | AG26: 22.953 | AH26: 22.099 | AI26: 24.558 | AJ26: =SUM(AF26:AI26) -> 92.063 | AK26: 27.334 | AL26: 27.725 | AM26: 50.022 | AN26: 36.906 | AO26: =+AK26+AL26+AM26+AN26 -> 141.987 | AP26: 39.24 | AQ26: 43.602 | AR26: 43.544 | AS26: 45.312 | AT26: =+AP26+AQ26+AR26+AS26 -> 171.698 | AU26: =+CF!AU13 -> 39.26728 | AV26: =+CF!AV13 -> 44.16048 | AW26: =+CF!AW13 -> 44.52032 | AX26: =+CF!AX13 -> 44.9176 | AY26: =+AU26+AV26+AW26+AX26 -> 172.86568 | AZ26: =+CF!AZ13 -> 40.837971 | BA26: =+CF!BA13 -> 45.926899 | BB26: =+CF!BB13 -> 46.301133 | BC26: =+CF!BC13 -> 46.714304 | BD26: =+AZ26+BA26+BB26+BC26 -> 179.78031 | BE26: =+CF!BE13 -> 42.47149 | BF26: =+CF!BF13 -> 47.763975 | BG26: =+CF!BG13 -> 48.153178 | BH26: =+CF!BH13 -> 48.582876 | BI26: =+BE26+BF26+BG26+BH26 -> 186.97152 | BJ26: =+CF!BJ13 -> 44.17035 | BK26: =+CF!BK13 -> 49.674534 | BL26: =+CF!BL13 -> 50.079305 | BM26: =+CF!BM13 -> 50.526191 | BN26: =+BJ26+BK26+BL26+BM26 -> 194.45038 | BO26: =+CF!BO13 -> 45.937164 | BP26: =+CF!BP13 -> 51.661516 | BQ26: =+CF!BQ13 -> 52.082477 | BR26: =+CF!BR13 -> 52.547239 | BS26: =+BO26+BP26+BQ26+BR26 -> 202.2284 | BT26: =+CF!BT13 -> 47.77465 | BU26: =+CF!BU13 -> 53.727976 | BV26: =+CF!BV13 -> 54.165777 | BW26: =+CF!BW13 -> 54.649128 | BX26: =+BT26+BU26+BV26+BW26 -> 210.31753 | BY26: =+CF!BY13 -> 49.685636 | BZ26: =+CF!BZ13 -> 55.877095 | CA26: =+CF!CA13 -> 56.332408 | CB26: =+CF!CB13 -> 56.835094 | CC26: =+BY26+BZ26+CA26+CB26 -> 218.73023 | CD26: =+CF!CD13 -> 51.673062 | CE26: =+CF!CE13 -> 58.112179 | CF26: =+CF!CF13 -> 58.585704 | CG26: =+CF!CG13 -> 59.108497 | CH26: =+CD26+CE26+CF26+CG26 -> 227.47944 | CI26: =+CF!CI13 -> 53.739984 | CJ26: =+CF!CJ13 -> 60.436666 | CK26: =+CF!CK13 -> 60.929132 | CL26: =+CF!CL13 -> 61.472837 | CM26: =+CI26+CJ26+CK26+CL26 -> 236.57862
A27: Fair value change in contingent exp. | B27: 0 | C27: 0 | D27: 0 | E27: 0 | F27: =+B27+C27+D27+E27 -> 0 | G27: 0 | H27: 0 | I27: 0 | J27: 0 | K27: =+G27+H27+I27+J27 -> 0 | L27: 0 | M27: 0 | N27: 0 | O27: 0 | P27: =+L27+M27+N27+O27 -> 0 | Q27: -0.19 | R27: 0 | S27: 0.07 | T27: 0 | U27: =+Q27+R27+S27+T27 -> -0.12 | V27: 0 | W27: 0.875 | X27: 0.97 | Y27: 0.535 | Z27: =+V27+W27+X27+Y27 -> 2.38 | AA27: 4.51 | AB27: 1.592 | AC27: 0.745 | AD27: 2.687 | AE27: =SUM(AA27:AD27) -> 9.534 | AF27: 0.27 | AG27: 0.841 | AH27: 0.751 | AI27: 0.33 | AJ27: =SUM(AF27:AI27) -> 2.192 | AK27: 0.495 | AL27: 0.41 | AM27: 0.53 | AN27: 0.25 | AO27: =+AK27+AL27+AM27+AN27 -> 1.685 | AP27: 1.024 | AQ27: 0.877 | AR27: 0.532 | AS27: 0.531 | AT27: =+AP27+AQ27+AR27+AS27 -> 2.964 | AU27: 0 | AV27: 0 | AW27: 0 | AX27: 0 | AY27: =+AU27+AV27+AW27+AX27 -> 0 | AZ27: 0 | BA27: 0 | BB27: 0 | BC27: 0 | BD27: =+AZ27+BA27+BB27+BC27 -> 0 | BE27: 0 | BF27: 0 | BG27: 0 | BH27: 0 | BI27: =+BE27+BF27+BG27+BH27 -> 0 | BJ27: 0 | BK27: 0 | BL27: 0 | BM27: 0 | BN27: =+BJ27+BK27+BL27+BM27 -> 0 | BO27: 0 | BP27: 0 | BQ27: 0 | BR27: 0 | BS27: =+BO27+BP27+BQ27+BR27 -> 0 | BT27: 0 | BU27: 0 | BV27: 0 | BW27: 0 | BX27: =+BT27+BU27+BV27+BW27 -> 0 | BY27: 0 | BZ27: 0 | CA27: 0 | CB27: 0 | CC27: =+BY27+BZ27+CA27+CB27 -> 0 | CD27: 0 | CE27: 0 | CF27: 0 | CG27: 0 | CH27: =+CD27+CE27+CF27+CG27 -> 0 | CI27: 0 | CJ27: 0 | CK27: 0 | CL27: 0 | CM27: =+CI27+CJ27+CK27+CL27 -> 0
A28: Acquisition related exp. | B28: 0 | C28: 0 | D28: 0 | E28: 0 | F28: =+B28+C28+D28+E28 -> 0 | G28: 0 | H28: 0 | I28: 0 | J28: 0 | K28: =+G28+H28+I28+J28 -> 0 | L28: 0 | M28: 0 | N28: 0 | O28: 0 | P28: =+L28+M28+N28+O28 -> 0 | Q28: 9.707 | R28: 0 | S28: 0 | T28: 0 | U28: =+Q28+R28+S28+T28 -> 9.707 | V28: 0 | W28: 0 | X28: 0 | Y28: 0 | Z28: =+V28+W28+X28+Y28 -> 0 | AA28: 0.063 | AB28: -0.063 | AC28: 0 | AD28: 0 | AE28: =SUM(AA28:AD28) -> 0 | AF28: 0 | AG28: 0 | AH28: 0 | AI28: 0 | AJ28: =SUM(AF28:AI28) -> 0 | AK28: 0 | AL28: 0 | AM28: 0 | AN28: 0 | AO28: =+AK28+AL28+AM28+AN28 -> 0 | AP28: 0 | AQ28: 0 | AR28: 0 | AS28: 0 | AT28: =+AP28+AQ28+AR28+AS28 -> 0 | AU28: 0 | AV28: 0 | AW28: 0 | AX28: 0 | AY28: =+AU28+AV28+AW28+AX28 -> 0 | AZ28: 0 | BA28: 0 | BB28: 0 | BC28: 0 | BD28: =+AZ28+BA28+BB28+BC28 -> 0 | BE28: 0 | BF28: 0 | BG28: 0 | BH28: 0 | BI28: =+BE28+BF28+BG28+BH28 -> 0 | BJ28: 0 | BK28: 0 | BL28: 0 | BM28: 0 | BN28: =+BJ28+BK28+BL28+BM28 -> 0 | BO28: 0 | BP28: 0 | BQ28: 0 | BR28: 0 | BS28: =+BO28+BP28+BQ28+BR28 -> 0 | BT28: 0 | BU28: 0 | BV28: 0 | BW28: 0 | BX28: =+BT28+BU28+BV28+BW28 -> 0 | BY28: 0 | BZ28: 0 | CA28: 0 | CB28: 0 | CC28: =+BY28+BZ28+CA28+CB28 -> 0 | CD28: 0 | CE28: 0 | CF28: 0 | CG28: 0 | CH28: =+CD28+CE28+CF28+CG28 -> 0 | CI28: 0 | CJ28: 0 | CK28: 0 | CL28: 0 | CM28: =+CI28+CJ28+CK28+CL28 -> 0
A29: Other | B29: 0 | C29: 5.075 | D29: 4.716 | E29: 0 | F29: =+B29+C29+D29+E29 -> 9.791 | G29: 0 | H29: 0 | I29: 0.95 | J29: -0.15 | K29: =+G29+H29+I29+J29 -> 0.8 | L29: 4.7 | M29: 0.3 | N29: -0.3 | O29: 3.1 | P29: =+L29+M29+N29+O29 -> 7.8 | Q29: -4.1 | R29: 4.9 | S29: 6 | T29: =-1+0.7 -> -0.3 | U29: =+Q29+R29+S29+T29 -> 6.5 | V29: 0 | W29: 0 | X29: 0 | Y29: =-26.1+18.6 -> -7.5 | Z29: =+V29+W29+X29+Y29 -> -7.5 | AA29: 0 | AB29: 99.785 | AC29: =13.23+5.261 -> 18.491 | AD29: =-1.1-5.437 -> -6.537 | AE29: =SUM(AA29:AD29) -> 111.739 | AF29: =-3.882+5.485 -> 1.603 | AG29: =-63.997+23.569 -> -40.428 | AH29: -16.634 | AI29: =83.4+4.803-2.631 -> 85.572 | AJ29: =SUM(AF29:AI29) -> 30.113 | AK29: 30.054 | AL29: 15.485 | AM29: 1.686 | AN29: =-2.824-1.1 -> -3.924 | AO29: =+AK29+AL29+AM29+AN29 -> 43.301 | AP29: =2+5-13.672 -> -6.672 | AQ29: 0 | AR29: 0 | AS29: =13.582+4.9 -> 18.482 | AT29: =+AP29+AQ29+AR29+AS29 -> 11.81 | AU29: 0 | AV29: 0 | AW29: 0 | AX29: 0 | AY29: =+AU29+AV29+AW29+AX29 -> 0 | AZ29: 0 | BA29: 0 | BB29: 0 | BC29: 0 | BD29: =+AZ29+BA29+BB29+BC29 -> 0 | BE29: 0 | BF29: 0 | BG29: 0 | BH29: 0 | BI29: =+BE29+BF29+BG29+BH29 -> 0 | BJ29: 0 | BK29: 0 | BL29: 0 | BM29: 0 | BN29: =+BJ29+BK29+BL29+BM29 -> 0 | BO29: 0 | BP29: 0 | BQ29: 0 | BR29: 0 | BS29: =+BO29+BP29+BQ29+BR29 -> 0 | BT29: 0 | BU29: 0 | BV29: 0 | BW29: 0 | BX29: =+BT29+BU29+BV29+BW29 -> 0 | BY29: 0 | BZ29: 0 | CA29: 0 | CB29: 0 | CC29: =+BY29+BZ29+CA29+CB29 -> 0 | CD29: 0 | CE29: 0 | CF29: 0 | CG29: 0 | CH29: =+CD29+CE29+CF29+CG29 -> 0 | CI29: 0 | CJ29: 0 | CK29: 0 | CL29: 0 | CM29: =+CI29+CJ29+CK29+CL29 -> 0
A30: Taxes | B30: 0 | C30: 0 | D30: 0 | E30: 0 | F30: =+B30+C30+D30+E30 -> 0 | G30: 0 | H30: 0 | I30: 0 | J30: 0 | K30: =+G30+H30+I30+J30 -> 0 | L30: 0 | M30: 0 | N30: 0 | O30: 0 | P30: =+L30+M30+N30+O30 -> 0 | Q30: 0 | R30: 0 | S30: 0 | T30: 0 | U30: =+Q30+R30+S30+T30 -> 0 | V30: 2.3 | W30: 0 | X30: 0 | Y30: 0 | Z30: =+V30+W30+X30+Y30 -> 2.3 | AA30: 0 | AB30: 0 | AC30: 0 | AD30: 0 | AE30: =SUM(AA30:AD30) -> 0 | AF30: 0 | AG30: 0 | AH30: 0 | AI30: 0 | AJ30: =SUM(AF30:AI30) -> 0 | AK30: 0 | AL30: 0 | AM30: 0 | AN30: 0 | AO30: =+AK30+AL30+AM30+AN30 -> 0 | AP30: 0 | AQ30: 0 | AR30: 0 | AS30: 0 | AT30: =+AP30+AQ30+AR30+AS30 -> 0 | AU30: 0 | AV30: 0 | AW30: 0 | AX30: 0 | AY30: =+AU30+AV30+AW30+AX30 -> 0 | AZ30: 0 | BA30: 0 | BB30: 0 | BC30: 0 | BD30: =+AZ30+BA30+BB30+BC30 -> 0 | BE30: 0 | BF30: 0 | BG30: 0 | BH30: 0 | BI30: =+BE30+BF30+BG30+BH30 -> 0 | BJ30: 0 | BK30: 0 | BL30: 0 | BM30: 0 | BN30: =+BJ30+BK30+BL30+BM30 -> 0 | BO30: 0 | BP30: 0 | BQ30: 0 | BR30: 0 | BS30: =+BO30+BP30+BQ30+BR30 -> 0 | BT30: 0 | BU30: 0 | BV30: 0 | BW30: 0 | BX30: =+BT30+BU30+BV30+BW30 -> 0 | BY30: 0 | BZ30: 0 | CA30: 0 | CB30: 0 | CC30: =+BY30+BZ30+CA30+CB30 -> 0 | CD30: 0 | CE30: 0 | CF30: 0 | CG30: 0 | CH30: =+CD30+CE30+CF30+CG30 -> 0 | CI30: 0 | CJ30: 0 | CK30: 0 | CL30: 0 | CM30: =+CI30+CJ30+CK30+CL30 -> 0
A31: GAAP net income | B31: =+B24-B25-B26-B27-B28-B29-B30 -> -16.018 | C31: =+C24-C25-C26-C27-C28-C29-C30 -> -23.553 | D31: =+D24-D25-D26-D27-D28-D29-D30 -> -33.306 | E31: =+E24-E25-E26-E27-E28-E29-E30 -> -15.06 | F31: =+F24-F25-F26-F27-F28-F29-F30 -> -87.937 | G31: =+G24-G25-G26-G27-G28-G29-G30 -> -13.844 | H31: =+H24-H25-H26-H27-H28-H29-H30 -> -21.639 | I31: =+I24-I25-I26-I27-I28-I29-I30 -> -24.458 | ... CM31: =+CM24-CM25-CM26-CM27-CM28-CM29-CM30 -> 1208.6637
A33: Basic shares outstanding | B33: -- | C33: -- | D33: 12.073 | E33: 11.851 | F33: 12.582 | G33: 11.92 | H33: 12.388 | I33: 12.582 | J33: 84.123 | K33: 30.403 | L33: 85.935 | M33: 89.036 | N33: 93.303 | O33: =P33*4-SUM(L33:N33) -> 94.114 | P33: 90.597 | Q33: 94.382 | R33: 96.011 | S33: 99.554 | T33: =U33*4-SUM(Q33:S33) -> 100.069 | U33: 97.504 | V33: 100.955 | W33: 101.172 | X33: 101.42 | Y33: 101.697 | Z33: 101.314 | AA33: 101.853 | AB33: 102.047 | AC33: 102.289 | AD33: 102.516 | AE33: 102.178 | AF33: 102.663 | AG33: 108.808 | AH33: 117.736 | AI33: 118.508 | AJ33: =AVERAGE(AF33:AI33) -> 111.92875 | AK33: 121.712 | AL33: 122.447 | AM33: 123.051 | AN33: 123.754 | AO33: =AVERAGE(AK33:AN33) -> 122.741 | AP33: 123.871 | AQ33: 124.114 | AR33: 124.807 | AS33: 128.657 | AT33: =AVERAGE(AP33:AS33) -> 125.36225 | AU33: =AS33+BS!AU57-BS!AU58 -> 129.157 | AV33: =AU33+BS!AV57-BS!AV58 -> 129.457 | AW33: =AV33+BS!AW57-BS!AW58 -> 129.757 | AX33: =AW33+BS!AX57-BS!AX58 -> 130.057 | AY33: =AVERAGE(AU33:AX33) -> 129.607 | AZ33: =AX33+BS!AZ57-BS!AZ58 -> 130.38214 | BA33: =AZ33+BS!BA57-BS!BA58 -> 130.70729 | BB33: =BA33+BS!BB57-BS!BB58 -> 131.03243 | BC33: =BB33+BS!BC57-BS!BC58 -> 131.35757 | BD33: =AVERAGE(AZ33:BC33) -> 130.86986 | BE33: =BC33+BS!BE57-BS!BE58 -> 131.68596 | BF33: =BE33+BS!BF57-BS!BF58 -> 132.01436 | BG33: =BF33+BS!BG57-BS!BG58 -> 132.34275 | BH33: =BG33+BS!BH57-BS!BH58 -> 132.67115 | BI33: =AVERAGE(BE33:BH33) -> 132.17855 | BJ33: =BH33+BS!BJ57-BS!BJ58 -> 133.00282 | BK33: =BJ33+BS!BK57-BS!BK58 -> 133.3345 | BL33: =BK33+BS!BL57-BS!BL58 -> 133.66618 | BM33: =BL33+BS!BM57-BS!BM58 -> 133.99786 | BN33: =AVERAGE(BJ33:BM33) -> 133.50034 | BO33: =BM33+BS!BO57-BS!BO58 -> 134.33285 | BP33: =BO33+BS!BP57-BS!BP58 -> 134.66785 | BQ33: =BP33+BS!BQ57-BS!BQ58 -> 135.00284 | BR33: =BQ33+BS!BR57-BS!BR58 -> 135.33784 | BS33: =AVERAGE(BO33:BR33) -> 134.83534 | BT33: =BR33+BS!BT57-BS!BT58 -> 135.67618 | BU33: =BT33+BS!BU57-BS!BU58 -> 136.01452 | BV33: =BU33+BS!BV57-BS!BV58 -> 136.35287 | BW33: =BV33+BS!BW57-BS!BW58 -> 136.69121 | BX33: =AVERAGE(BT33:BW33) -> 136.1837 | BY33: =BW33+BS!BY57-BS!BY58 -> 137.03294 | BZ33: =BY33+BS!BZ57-BS!BZ58 -> 137.37467 | CA33: =BZ33+BS!CA57-BS!CA58 -> 137.7164 | CB33: =CA33+BS!CB57-BS!CB58 -> 138.05813 | CC33: =AVERAGE(BY33:CB33) -> 137.54553 | CD33: =CB33+BS!CD57-BS!CD58 -> 138.40327 | CE33: =CD33+BS!CE57-BS!CE58 -> 138.74842 | CF33: =CE33+BS!CF57-BS!CF58 -> 139.09356 | CG33: =CF33+BS!CG57-BS!CG58 -> 139.43871 | CH33: =AVERAGE(CD33:CG33) -> 138.92099 | CI33: =CG33+BS!CI57-BS!CI58 -> 139.7873 | CJ33: =CI33+BS!CJ57-BS!CJ58 -> 140.1359 | CK33: =CJ33+BS!CK57-BS!CK58 -> 140.4845 | CL33: =CK33+BS!CL57-BS!CL58 -> 140.83309 | CM33: =AVERAGE(CI33:CL33) -> 140.3102
A34: Diluted shares outstanding | B34: -- | C34: -- | D34: 12.073 | E34: 11.851 | F34: 12.582 | G34: 11.92 | H34: 12.388 | I34: 12.582 | J34: 84.123 | K34: 30.403 | L34: 85.935 | M34: 89.036 | N34: 93.303 | O34: =P34*4-SUM(L34:N34) -> 94.114 | P34: 90.597 | Q34: 94.382 | R34: 96.011 | S34: 99.554 | T34: =U34*4-SUM(Q34:S34) -> 100.069 | U34: 97.504 | V34: 100.955 | W34: 101.172 | X34: 101.42 | Y34: 101.697 | Z34: 101.314 | AA34: 101.853 | AB34: 102.047 | AC34: 102.289 | AD34: 102.516 | AE34: 102.178 | AF34: 102.663 | AG34: 108.808 | AH34: 117.736 | AI34: 118.508 | AJ34: =AVERAGE(AF34:AI34) -> 111.92875 | AK34: 121.712 | AL34: 122.447 | AM34: 123.051 | AN34: 123.754 | AO34: =AVERAGE(AK34:AN34) -> 122.741 | AP34: 123.871 | AQ34: 124.114 | AR34: 124.807 | AS34: 128.657 | AT34: =AVERAGE(AP34:AS34) -> 125.36225 | AU34: =AS34+BS!AU57-BS!AU58 -> 129.157 | AV34: =AU34+BS!AV57-BS!AV58 -> 129.457 | AW34: =AV34+BS!AW57-BS!AW58 -> 129.757 | AX34: =AW34+BS!AX57-BS!AX58 -> 130.057 | AY34: =AVERAGE(AU34:AX34) -> 129.607 | AZ34: =AX34+BS!AZ57-BS!AZ58 -> 130.38214 | BA34: =AZ34+BS!BA57-BS!BA58 -> 130.70729 | BB34: =BA34+BS!BB57-BS!BB58 -> 131.03243 | BC34: =BB34+BS!BC57-BS!BC58 -> 131.35757 | BD34: =AVERAGE(AZ34:BC34) -> 130.86986 | BE34: =BC34+BS!BE57-BS!BE58 -> 131.68596 | BF34: =BE34+BS!BF57-BS!BF58 -> 132.01436 | BG34: =BF34+BS!BG57-BS!BG58 -> 132.34275 | BH34: =BG34+BS!BH57-BS!BH58 -> 132.67115 | BI34: =AVERAGE(BE34:BH34) -> 132.17855 | BJ34: =BH34+BS!BJ57-BS!BJ58 -> 133.00282 | BK34: =BJ34+BS!BK57-BS!BK58 -> 133.3345 | BL34: =BK34+BS!BL57-BS!BL58 -> 133.66618 | BM34: =BL34+BS!BM57-BS!BM58 -> 133.99786 | BN34: =AVERAGE(BJ34:BM34) -> 133.50034 | BO34: =BM34+BS!BO57-BS!BO58 -> 134.33285 | BP34: =BO34+BS!BP57-BS!BP58 -> 134.66785 | BQ34: =BP34+BS!BQ57-BS!BQ58 -> 135.00284 | BR34: =BQ34+BS!BR57-BS!BR58 -> 135.33784 | BS34: =AVERAGE(BO34:BR34) -> 134.83534 | BT34: =BR34+BS!BT57-BS!BT58 -> 135.67618 | BU34: =BT34+BS!BU57-BS!BU58 -> 136.01452 | BV34: =BU34+BS!BV57-BS!BV58 -> 136.35287 | BW34: =BV34+BS!BW57-BS!BW58 -> 136.69121 | BX34: =AVERAGE(BT34:BW34) -> 136.1837 | BY34: =BW34+BS!BY57-BS!BY58 -> 137.03294 | BZ34: =BY34+BS!BZ57-BS!BZ58 -> 137.37467 | CA34: =BZ34+BS!CA57-BS!CA58 -> 137.7164 | CB34: =CA34+BS!CB57-BS!CB58 -> 138.05813 | CC34: =AVERAGE(BY34:CB34) -> 137.54553 | CD34: =CB34+BS!CD57-BS!CD58 -> 138.40327 | CE34: =CD34+BS!CE57-BS!CE58 -> 138.74842 | CF34: =CE34+BS!CF57-BS!CF58 -> 139.09356 | CG34: =CF34+BS!CG57-BS!CG58 -> 139.43871 | CH34: =AVERAGE(CD34:CG34) -> 138.92099 | CI34: =CG34+BS!CI57-BS!CI58 -> 139.7873 | CJ34: =CI34+BS!CJ57-BS!CJ58 -> 140.1359 | CK34: =CJ34+BS!CK57-BS!CK58 -> 140.4845 | CL34: =CK34+BS!CL57-BS!CL58 -> 140.83309 | CM34: =AVERAGE(CI34:CL34) -> 140.3102
A36: Non-GAAP basic E.P.S. | B36: -- | C36: -- | D36: =D24/D33 -> -2.2164334 | E36: =E24/E33 -> -1.1381318 | F36: =F24/F33 -> -5.8379431 | G36: =G24/G33 -> -1.0542785 | H36: =H24/H33 -> -1.6515176 | I36: =I24/I33 -> -1.7228581 | J36: =J24/J33 -> -0.26994995 | K36: =K24/K33 -> -2.5461961 | ... CM36: =CM24/CM33 -> 10.308272
A37: Non-GAAP diluted E.P.S. | B37: -- | C37: -- | D37: =(D24)/D34 -> -2.2164334 | E37: =(E24)/E34 -> -1.1381318 | F37: =(F24)/F34 -> -5.8379431 | G37: =(G24)/G34 -> -1.0542785 | H37: =(H24)/H34 -> -1.6515176 | I37: =(I24)/I34 -> -1.7228581 | J37: =(J24)/J34 -> -0.26994995 | K37: =(K24)/K34 -> -2.5461961 | ... CM37: =(CM24)/CM34 -> 10.308272
A39: GAAP basic E.P.S. | B39: -- | C39: -- | D39: =D31/D33 -> -2.7587178 | E39: =E31/E33 -> -1.2707788 | F39: =F31/F33 -> -6.9891114 | G39: =G31/G33 -> -1.1614094 | H39: =H31/H33 -> -1.7467711 | I39: =I31/I33 -> -1.9438881 | J39: =J31/J33 -> -0.29863414 | K39: =K31/K33 -> -2.7978489 | ... AL39: =AL31/AL33 -> -0.83814222 | AM39: =+AM$31/AM33 -> -0.87568569 | AN39: =+AN$31/AN33 -> -0.89698919 | AO39: =+AO$31/AO33 -> -3.5552342 | AP39: =+AP$31/AP33 -> -0.76821048 | AQ39: =+AQ$31/AQ33 -> -0.80489711 | AR39: =+AR$31/AR33 -> -0.74294711 | AS39: =+AS$31/AS33 -> -0.99873307 | AT39: =+AT$31/AT33 -> -3.3205929 | ... CM39: =+CM$31/CM33 -> 8.6142258
A40: GAAP diluted E.P.S. | B40: -- | C40: -- | D40: =D31/D34 -> -2.7587178 | E40: =E31/E34 -> -1.2707788 | F40: =F31/F34 -> -6.9891114 | G40: =G31/G34 -> -1.1614094 | H40: =H31/H34 -> -1.7467711 | I40: =I31/I34 -> -1.9438881 | J40: =J31/J34 -> -0.29863414 | K40: =K31/K34 -> -2.7978489 | ... AL40: =AL31/AL34 -> -0.83814222 | AM40: =+AM$31/AM34 -> -0.87568569 | AN40: =+AN$31/AN34 -> -0.89698919 | AO40: =+AO$31/AO34 -> -3.5552342 | AP40: =+AP$31/AP34 -> -0.76821048 | AQ40: =+AQ$31/AQ34 -> -0.80489711 | AR40: =+AR$31/AR34 -> -0.74294711 | AS40: =+AS$31/AS34 -> -0.99873307 | AT40: =+AT$31/AT34 -> -3.3205929 | ... CM40: =+CM$31/CM34 -> 8.6142258
A42: EBITDA | B42: -- | C42: -- | D42: =D17+CF!D9-D25 -> -23.033 | E42: =E17+CF!E9-E25 -> -12.653 | F42: =F17+CF!F9-F25 -> -66.713 | G42: =G17+CF!G9-G25 -> -15.975 | H42: =H17+CF!H9-H25 -> -19.954 | I42: =I17+CF!I9-I25 -> -20.371 | J42: =J17+CF!J9-J25 -> -22.655 | K42: =K17+CF!K9-K25 -> -78.955 | ... CM42: =CM17+CF!CM9-CM25 -> 1381.2266
A44: Year-Over-Year
A45: =A7 -> Net sales | B45: -- | C45: -- | D45: -- | E45: -- | F45: -- | G45: =G7/B7-1 -> 0.96099624 | H45: =H7/C7-1 -> 0.90094155 | I45: =I7/D7-1 -> 0.9486166 | J45: =J7/E7-1 -> 0.64348565 | K45: =K7/F7-1 -> 0.81852654 | L45: =L7/G7-1 -> 1.1959621 | M45: =M7/H7-1 -> 1.7848003 | N45: =N7/I7-1 -> 1.8050894 | ... CM45: =CM7/CH7-1 -> 0.063067934
A46: Cost of Sales | B46: -- | C46: -- | D46: -- | E46: -- | F46: -- | G46: =G10/B10-1 -> 0.4565338 | H46: =H10/C10-1 -> 0.34047894 | I46: =I10/D10-1 -> 0.16259212 | J46: =J10/E10-1 -> 0.50594059 | K46: =K10/F10-1 -> 0.36332578 | L46: =L10/G10-1 -> 0.45429815 | M46: =M10/H10-1 -> 0.6909919 | N46: =N10/I10-1 -> 0.8359996 | ... CM46: =CM10/CH10-1 -> 0.04646936
A47: =A11 -> Gross profit | B47: -- | C47: -- | D47: -- | E47: -- | F47: -- | G47: =G11/B11-1 -> 2.4061294 | H47: =H11/C11-1 -> 2.3629446 | I47: =I11/D11-1 -> 3.5501355 | J47: =J11/E11-1 -> 0.75806452 | K47: =K11/F11-1 -> 1.5881877 | L47: =L11/G11-1 -> 2.1045055 | M47: =M11/H11-1 -> 2.9221217 | N47: =N11/I11-1 -> 2.6246065 | ... CM47: =CM11/CH11-1 -> 0.070825696
A48: =A13 -> R&D expense | B48: -- | C48: -- | D48: -- | E48: -- | F48: -- | G48: =G13/B13-1 -> 0.7667325 | H48: =H13/C13-1 -> 1.1200224 | I48: =I13/D13-1 -> 1.0570222 | J48: =J13/E13-1 -> 1.0205808 | K48: =K13/F13-1 -> 1.004907 | L48: =L13/G13-1 -> 0.87628866 | M48: =M13/H13-1 -> 0.59647266 | N48: =N13/I13-1 -> 0.65026401 | ... AT48: =AT13/AO13-1 -> 0.044993342 | AU48: 0.052 | AV48: 0.052 | AW48: 0.052 | AX48: 0.052 | AY48: =AY13/AT13-1 -> 0.052 | AZ48: 0.05 | BA48: 0.05 | BB48: 0.05 | BC48: 0.05 | BD48: =BD13/AY13-1 -> 0.05 | BE48: 0.05 | BF48: 0.05 | BG48: 0.05 | BH48: 0.05 | BI48: =BI13/BD13-1 -> 0.05 | BJ48: 0.05 | BK48: 0.05 | BL48: 0.05 | BM48: 0.05 | BN48: =BN13/BI13-1 -> 0.05 | BO48: 0.05 | BP48: 0.05 | BQ48: 0.05 | BR48: 0.05 | BS48: =BS13/BN13-1 -> 0.05 | BT48: 0.05 | BU48: 0.05 | BV48: 0.05 | BW48: 0.05 | BX48: =BX13/BS13-1 -> 0.05 | BY48: 0.05 | BZ48: 0.05 | CA48: 0.05 | CB48: 0.05 | CC48: =CC13/BX13-1 -> 0.05 | CD48: 0.05 | CE48: 0.05 | CF48: 0.05 | CG48: 0.05 | CH48: =CH13/CC13-1 -> 0.05 | CI48: 0.05 | CJ48: 0.05 | CK48: 0.05 | CL48: 0.05 | CM48: =CM13/CH13-1 -> 0.05
A49: =A14 -> S&M expense | B49: -- | C49: -- | D49: -- | E49: -- | F49: -- | G49: =G14/B14-1 -> 0.57744448 | H49: =H14/C14-1 -> 0.47747748 | I49: =I14/D14-1 -> 0.76639566 | J49: =J14/E14-1 -> 0.73319283 | K49: =K14/F14-1 -> 0.64440772 | L49: =L14/G14-1 -> 0.5524776 | M49: =M14/H14-1 -> 0.66074585 | N49: =N14/I14-1 -> 0.33046947 | ... AT49: =AT14/AO14-1 -> 0.36686439 | AU49: 0.245 | AV49: 0.245 | AW49: 0.245 | AX49: 0.245 | AY49: =AY14/AT14-1 -> 0.245 | AZ49: 0.2 | BA49: 0.2 | BB49: 0.2 | BC49: 0.2 | BD49: =BD14/AY14-1 -> 0.2 | BE49: 0.15 | BF49: 0.15 | BG49: 0.15 | BH49: 0.15 | BI49: =BI14/BD14-1 -> 0.15 | BJ49: 0.131 | BK49: 0.131 | BL49: 0.131 | BM49: 0.131 | BN49: =BN14/BI14-1 -> 0.131 | BO49: 0.121 | BP49: 0.121 | BQ49: 0.121 | BR49: 0.121 | BS49: =BS14/BN14-1 -> 0.121 | BT49: 0.111 | BU49: 0.111 | BV49: 0.111 | BW49: 0.111 | BX49: =BX14/BS14-1 -> 0.111 | BY49: 0.101 | BZ49: 0.101 | CA49: 0.101 | CB49: 0.101 | CC49: =CC14/BX14-1 -> 0.101 | CD49: 0.091 | CE49: 0.091 | CF49: 0.091 | CG49: 0.091 | CH49: =CH14/CC14-1 -> 0.091 | CI49: 0.081 | CJ49: 0.081 | CK49: 0.081 | CL49: 0.081 | CM49: =CM14/CH14-1 -> 0.081
A50: =A15 -> G&A expense | B50: -- | C50: -- | D50: -- | E50: -- | F50: -- | G50: =G15/B15-1 -> 0.16575845 | H50: =H15/C15-1 -> 0.28565942 | I50: =I15/D15-1 -> -0.51656832 | J50: =J15/E15-1 -> 0.53133696 | K50: =K15/F15-1 -> -0.03649635 | L50: =L15/G15-1 -> 0.98623151 | M50: =M15/H15-1 -> 0.48452623 | N50: =N15/I15-1 -> 0.97800134 | ... AT50: =AT15/AO15-1 -> 0.095934069 | AU50: 0.05 | AV50: 0.05 | AW50: 0.05 | AX50: 0.05 | AY50: =AY15/AT15-1 -> 0.05 | AZ50: 0.05 | BA50: 0.05 | BB50: 0.05 | BC50: 0.05 | BD50: =BD15/AY15-1 -> 0.05 | BE50: 0.05 | BF50: 0.05 | BG50: 0.05 | BH50: 0.05 | BI50: =BI15/BD15-1 -> 0.05 | BJ50: 0.05 | BK50: 0.05 | BL50: 0.05 | BM50: 0.05 | BN50: =BN15/BI15-1 -> 0.05 | BO50: 0.05 | BP50: 0.05 | BQ50: 0.05 | BR50: 0.05 | BS50: =BS15/BN15-1 -> 0.05 | BT50: 0.05 | BU50: 0.05 | BV50: 0.05 | BW50: 0.05 | BX50: =BX15/BS15-1 -> 0.05 | BY50: 0.05 | BZ50: 0.05 | CA50: 0.05 | CB50: 0.05 | CC50: =CC15/BX15-1 -> 0.05 | CD50: 0.05 | CE50: 0.05 | CF50: 0.05 | CG50: 0.05 | CH50: =CH15/CC15-1 -> 0.05 | CI50: 0.05 | CJ50: 0.05 | CK50: 0.05 | CL50: 0.05 | CM50: =CM15/CH15-1 -> 0.05
A51: Operating expense | B51: -- | C51: -- | D51: -- | E51: -- | F51: -- | G51: =G16/B16-1 -> 0.50397581 | H51: =H16/C16-1 -> 0.58959908 | I51: =I16/D16-1 -> 0.15959905 | J51: =J16/E16-1 -> 0.76335297 | K51: =K16/F16-1 -> 0.48196634 | L51: =L16/G16-1 -> 0.75989064 | M51: =M16/H16-1 -> 0.58971797 | N51: =N16/I16-1 -> 0.59970112 | ... CM51: =CM16/CH16-1 -> 0.070438629
A52: =A17 -> Operating income (EBITA , ex-SBC) | B52: -- | C52: -- | D52: -- | E52: -- | F52: -- | G52: =G17/B17-1 -> 0.21171957 | H52: =H17/C17-1 -> 0.28942008 | I52: =I17/D17-1 -> -0.16661079 | J52: =J17/E17-1 -> 0.76746173 | K52: =K17/F17-1 -> 0.19705502 | L52: =L17/G17-1 -> 0.17915947 | M52: =M17/H17-1 -> -0.43999442 | N52: =N17/I17-1 -> -0.46397604 | ... CM52: =CM17/CH17-1 -> 0.071448379
A53: EBITDA | B53: -- | C53: -- | D53: -- | E53: -- | F53: -- | G53: -- | H53: -- | I53: =I42/D42-1 -> -0.11557331 | J53: =J42/E42-1 -> 0.79048447 | K53: =K42/F42-1 -> 0.18350247 | L53: =L42/G42-1 -> 0.13477308 | M53: =M42/H42-1 -> -0.52911697 | N53: =N42/I42-1 -> -0.55618281 | O53: =O42/J42-1 -> -0.23010373 | P53: =P42/K42-1 -> -0.31597746 | ... CM53: =CM42/CH42-1 -> 0.071895245
A54: =A21 -> Income before taxes | B54: -- | C54: -- | D54: -- | E54: -- | F54: -- | G54: =G21/B21-1 -> -0.18252781 | H54: =H21/C21-1 -> 0.14708686 | I54: =I21/D21-1 -> -0.18991741 | J54: =J21/E21-1 -> 0.68192271 | K54: =K21/F21-1 -> 0.053481469 | L54: =L21/G21-1 -> 0.44370176 | M54: =M21/H21-1 -> -0.54575675 | N54: =N21/I21-1 -> -0.63980256 | ... CM54: =CM21/CH21-1 -> 0.090447748
A55: =A24 -> Non-GAAP net income | B55: -- | C55: -- | D55: -- | E55: -- | F55: -- | G55: =G24/B24-1 -> -0.18252781 | H55: =H31/C31-1 -> -0.081263533 | I55: =I31/D31-1 -> -0.26565784 | J55: =J31/E31-1 -> 0.66812749 | K55: =K31/F31-1 -> -0.032682489 | L55: =L31/G31-1 -> 0.88175383 | M55: =M31/H31-1 -> -0.46393087 | N55: =N31/I31-1 -> -0.47706272 | O55: =O31/J31-1 -> 0.0035029058 | ... U55: =U31/P31-1 -> 2.3546549 | V55: =V24/Q24-1 -> 2.1964008 | W55: =W24/R24-1 -> 1.6101364 | X55: =X24/S24-1 -> 3.5793336 | Y55: =Y24/T24-1 -> 0.91956783 | Z55: =Z24/U24-1 -> 1.7646426 | AA55: =AA24/V24-1 -> 0.88715622 | AB55: =AB24/W24-1 -> 0.65646159 | AC55: =AC24/X24-1 -> 0.71379134 | ... CM55: =CM24/CH24-1 -> 0.090447748
A57: =A37 -> Non-GAAP diluted E.P.S. | B57: -- | C57: -- | D57: -- | E57: -- | F57: -- | G57: -- | H57: -- | I57: =I37/D37-1 -> -0.22268899 | J57: =J37/E37-1 -> -0.7628131 | K57: =K37/F37-1 -> -0.5638539 | L57: =L37/G37-1 -> -0.79945789 | M57: =M37/H37-1 -> -0.94501665 | N57: =N37/I37-1 -> -0.95268365 | O57: =O37/J37-1 -> -0.32937286 | P57: =P37/K37-1 -> -0.77935451 | ... CM57: =CM37/CH37-1 -> 0.079651236
A59: Margin Analysis
A60: Gross margin | B60: =B11/B$7 -> 0.25875235 | C60: =C11/C$7 -> 0.27711848 | D60: =D11/D$7 -> 0.23203378 | E60: =E11/E$7 -> 0.54554545 | F60: =F11/F$7 -> 0.37163436 | G60: =G11/G$7 -> 0.44943686 | H60: =H11/H$7 -> 0.49024868 | I60: =I11/I$7 -> 0.54181265 | ... AT60: =AT11/AT$7 -> 0.65663158 | AU60: =AP60-0.008 -> 0.637232 | AV60: =AQ60-0.015 -> 0.6476452 | AW60: =AR60-0.008 -> 0.64934023 | AX60: =AS60-0.008 -> 0.65124783 | AY60: =AY11/AY$7 -> 0.6468455 | AZ60: =AU60+0.005 -> 0.642232 | BA60: =AV60+0.005 -> 0.6526452 | BB60: =AW60+0.005 -> 0.65434023 | BC60: =AX60+0.005 -> 0.65624783 | BD60: =BD11/BD$7 -> 0.6517112 | BE60: =AZ60+0.005 -> 0.647232 | BF60: =BA60+0.005 -> 0.6576452 | BG60: =BB60+0.005 -> 0.65934023 | BH60: =BC60+0.005 -> 0.66124783 | BI60: =BI11/BI$7 -> 0.65666975 | BJ60: =+BE60+0.005 -> 0.652232 | BK60: =+BF60+0.005 -> 0.6626452 | BL60: =+BG60+0.005 -> 0.66434023 | BM60: =+BH60+0.005 -> 0.66624783 | BN60: =BN11/BN$7 -> 0.6615935 | BO60: =+BJ60+0.005 -> 0.657232 | BP60: =+BK60+0.005 -> 0.6676452 | BQ60: =+BL60+0.005 -> 0.66934023 | BR60: =+BM60+0.005 -> 0.67124783 | BS60: =BS11/BS$7 -> 0.66657511 | BT60: =+BO60+0.005 -> 0.662232 | BU60: =+BP60+0.005 -> 0.6726452 | BV60: =+BQ60+0.005 -> 0.67434023 | BW60: =+BR60+0.005 -> 0.67624783 | BX60: =BX11/BX$7 -> 0.67152536 | BY60: =+BT60+0.005 -> 0.667232 | BZ60: =+BU60+0.005 -> 0.6776452 | CA60: =+BV60+0.005 -> 0.67934023 | CB60: =+BW60+0.005 -> 0.68124783 | CC60: =CC11/CC$7 -> 0.67650692 | CD60: =+BY60+0.005 -> 0.672232 | CE60: =+BZ60+0.005 -> 0.6826452 | CF60: =+CA60+0.005 -> 0.68434023 | CG60: =+CB60+0.005 -> 0.68624783 | CH60: =CH11/CH$7 -> 0.68148894 | CI60: =+CD60+0.005 -> 0.677232 | CJ60: =+CE60+0.005 -> 0.6876452 | CK60: =+CF60+0.005 -> 0.68934023 | CL60: =+CG60+0.005 -> 0.69124783 | CM60: =CM11/CM$7 -> 0.68646212
A61: Margin Chg yoy | B61: -- | C61: -- | D61: -- | E61: -- | F61: -- | G61: =+(G60-B60)*10000 -> 1906.8451 | H61: =+(H60-C60)*10000 -> 2131.3021 | I61: =+(I60-D60)*10000 -> 3097.7887 | J61: =+(J60-E60)*10000 -> 380.33784 | K61: =+(K60-F60)*10000 -> 1572.8806 | L61: =+(L60-G60)*10000 -> 1859.4713 | M61: =+(M60-H60)*10000 -> 2002.1912 | N61: =+(N60-I60)*10000 -> 1582.9253 | ... CM61: =+(CM60-CH60)*10000 -> 49.731811
A62: =+A13 -> R&D expense | B62: =B13/B$7 -> 0.53536184 | C62: =C13/C$7 -> 0.5246175 | D62: =D13/D$7 -> 0.59549048 | E62: =E13/E$7 -> 0.3959604 | F62: =F13/F$7 -> 0.49065046 | G62: =G13/G$7 -> 0.48232686 | H62: =H13/H$7 -> 0.58507894 | I62: =I13/I$7 -> 0.62861885 | ... CM62: =CM13/CM$7 -> 0.096084387
A63: =+A14 -> S&M expense | B63: =B14/B$7 -> 0.81461466 | C63: =C14/C$7 -> 0.75117693 | D63: =D14/D$7 -> 0.66295365 | E63: =E14/E$7 -> 0.47445255 | F63: =F14/F$7 -> 0.63125477 | G63: =G14/G$7 -> 0.65528397 | H63: =H14/H$7 -> 0.58384068 | I63: =I14/I$7 -> 0.60095888 | ... CM63: =CM14/CM$7 -> 0.28175173
A64: =+A15 -> G&A expense | B64: =B15/B$7 -> 0.59286889 | C64: =C15/C$7 -> 0.63843664 | D64: =D15/D$7 -> 1.3852857 | E64: =E15/E$7 -> 0.37731227 | F64: =F15/F$7 -> 0.69266883 | G64: =G15/G$7 -> 0.35244428 | H64: =H15/H$7 -> 0.43179238 | I64: =I15/I$7 -> 0.34367509 | ... CM64: =CM15/CM$7 -> 0.045331674
A65: Operating expense | B65: =B16/B$7 -> 1.9428454 | C65: =C16/C$7 -> 1.9142311 | D65: =D16/D$7 -> 2.6437298 | E65: =E16/E$7 -> 1.2477252 | F65: =F16/F$7 -> 1.8145741 | G65: =G16/G$7 -> 1.4900551 | H65: =H16/H$7 -> 1.600712 | I65: =I16/I$7 -> 1.5732528 | ... CM65: =CM16/CM$7 -> 0.42316779
A66: Operating margin | B66: =B17/B$7 -> -1.684093 | C66: =C17/C$7 -> -1.6371126 | D66: =D17/D$7 -> -2.411696 | E66: =E17/E$7 -> -0.70217978 | F66: =F17/F$7 -> -1.4429397 | G66: =G17/G$7 -> -1.0406183 | H66: =H17/H$7 -> -1.1104633 | I66: =I17/I$7 -> -1.0314402 | ... CM66: =CM17/CM$7 -> 0.26329433
A67: Margin Chg yoy | B67: -- | C67: -- | D67: -- | E67: -- | F67: -- | G67: =+(G66-B66)*10000 -> 6434.7478 | H67: =+(H66-C66)*10000 -> 5266.4928 | I67: =+(I66-D66)*10000 -> 13802.558 | J67: =+(J66-E66)*10000 -> -529.6882 | K67: =+(K66-F66)*10000 -> 4931.1677 | L67: =+(L66-G66)*10000 -> 4818.4047 | M67: =+(M66-H66)*10000 -> 8871.5623 | N67: =+(N66-I66)*10000 -> 8343.4248 | ... CM67: =+(CM66-CH66)*10000 -> 20.59384
A68: EBITDA margin | B68: -- | C68: -- | D68: =D42/D7 -> -2.0690801 | E68: =E42/E7 -> -0.63258674 | F68: =F42/F7 -> -1.3384896 | G68: =G42/G7 -> -0.95704529 | H68: =H42/H7 -> -1.0295119 | I68: =I42/I7 -> -0.93910197 | J68: =J42/J7 -> -0.6891674 | K68: =K42/K7 -> -0.87109302 | ... CM68: =CM42/CM7 -> 0.27617161
A69: Margin Chg yoy | B69: -- | C69: -- | D69: -- | E69: -- | F69: -- | G69: -- | H69: -- | I69: =+(I68-D68)*10000 -> 11299.782 | J69: =+(J68-E68)*10000 -> -565.8066 | K69: =+(K68-F68)*10000 -> 4673.9661 | L69: =+(L68-G68)*10000 -> 4624.8793 | M69: =+(M68-H68)*10000 -> 8554.3133 | N69: =+(N68-I68)*10000 -> 7905.1862 | O69: =+(O68-J68)*10000 -> 4118.5688 | P69: =+(P68-K68)*10000 -> 6191.6532 | ... CM69: =+(CM68-CH68)*10000 -> 22.743387
A70: =A21 -> Income before taxes | B70: =B21/B$7 -> -1.8060385 | C70: =C21/C$7 -> -1.7490192 | D70: =D21/D$7 -> -2.4037909 | E70: =E21/E$7 -> -0.6739826 | F70: =F21/F$7 -> -1.4735765 | G70: =G21/G$7 -> -0.75287563 | H70: =H21/H$7 -> -1.0554122 | I70: =I21/I$7 -> -0.9993085 | ... CM70: =CM21/CM$7 -> 0.29064719
A71: =A22 -> Income tax | B71: =-B22/B21 -> 0 | C71: =-C22/C21 -> 0 | D71: =-D22/D21 -> 0 | E71: =-E22/E21 -> 0.00051924931 | F71: =-F22/F21 -> 9.5308118e-05 | G71: =-G22/G21 -> 0 | H71: =-H22/H21 -> 0.00014665624 | I71: =-I22/I21 -> 0 | ... AT71: =-AT22/AT21 -> -0.005505715 | AU71: 0.005 | AV71: 0.005 | AW71: 0.005 | AX71: 0.005 | AY71: =-AY22/AY21 -> -0.005 | AZ71: 0.005 | BA71: 0.005 | BB71: 0.005 | BC71: 0.005 | BD71: =-BD22/BD21 -> -0.005 | BE71: 0.005 | BF71: 0.005 | BG71: 0.005 | BH71: 0.005 | BI71: =-BI22/BI21 -> -0.005 | BJ71: 0.005 | BK71: 0.005 | BL71: 0.005 | BM71: 0.005 | BN71: =-BN22/BN21 -> -0.005 | BO71: 0.005 | BP71: 0.005 | BQ71: 0.005 | BR71: 0.005 | BS71: =-BS22/BS21 -> -0.005 | BT71: 0.005 | BU71: 0.005 | BV71: 0.005 | BW71: 0.005 | BX71: =-BX22/BX21 -> -0.005 | BY71: 0.005 | BZ71: 0.005 | CA71: 0.005 | CB71: 0.005 | CC71: =-CC22/CC21 -> -0.005 | CD71: 0.005 | CE71: 0.005 | CF71: 0.005 | CG71: 0.005 | CH71: =-CH22/CH21 -> -0.005 | CI71: 0.005 | CJ71: 0.005 | CK71: 0.005 | CL71: 0.005 | CM71: =-CM22/CM21 -> -0.005
A72: Non-GAAP net income | B72: =B24/B$7 -> -1.8060385 | C72: =C24/C$7 -> -1.7490192 | D72: =D24/D$7 -> -2.4037909 | E72: =E24/E$7 -> -0.67433257 | F72: =F24/F$7 -> -1.4737169 | G72: =G24/G$7 -> -0.75287563 | H72: =H24/H$7 -> -1.055567 | I72: =I24/I$7 -> -0.9993085 | ... CM72: =CM24/CM$7 -> 0.28919396
A77: Incremental OPM | AT77: =(AT17-AO17)/(AT7-AO7) -> 0.159614 | AY77: =(AY17-AT17)/(AY7-AT7) -> 0.19747832 | BD77: =(BD17-AY17)/(BD7-AY7) -> 0.40879287 | BI77: =(BI17-BD17)/(BI7-BD7) -> 0.45808609 | BN77: =(BN17-BI17)/(BN7-BI7) -> 0.43908648 | BS77: =(BS17-BN17)/(BS7-BN7) -> 0.449173 | BX77: =(BX17-BS17)/(BX7-BS7) -> 0.41091366 | CC77: =(CC17-BX17)/(CC7-BX7) -> 0.35992013 | CH77: =(CH17-CC17)/(CH7-CC7) -> 0.36746929 | CM77: =(CM17-CH17)/(CM7-CH7) -> 0.29594775
F78: =+F11/(F13+F14+F15) -> 0.20480529 | K78: =+K11/(K13+K14+K15) -> 0.35768324 | P78: =+P11/(P13+P14+P15) -> 0.68839075 | U78: =+U11/(U13+U14+U15) -> 0.66567762 | Z78: =+Z11/(Z13+Z14+Z15) -> 0.50310984 | AE78: =+AE11/(AE13+AE14+AE15) -> 0.40687913 | AJ78: =+AJ11/(AJ13+AJ14+AJ15) -> 0.47295754 | AO78: =+AO11/(AO13+AO14+AO15) -> 0.6068796 | AT78: =+AT11/(AT13+AT14+AT15) -> 0.71350673
A79: Source: Company reports, Wells Fargo Securities, LLC estimates.
F80: =+CF!F13/IS!F16 -> 0.040578492 | K80: =+CF!K13/IS!K16 -> 0.051114659 | P80: =+CF!P13/IS!P16 -> 0.080757945 | U80: =+CF!U13/IS!U16 -> 0.4881331 | Z80: =+CF!Z13/IS!Z16 -> 0.29884683 | AE80: =+CF!AE13/IS!AE16 -> 0.12853737 | AJ80: =+CF!AJ13/IS!AJ16 -> 0.12446294 | AO80: =+CF!AO13/IS!AO16 -> 0.18541442 | AT80: =+CF!AT13/IS!AT16 -> 0.18392085
A83: Stock-based Comp
A84: COGS | AK84: =3.526-AL84 -> 1.756 | AL84: 1.77 | AO84: 9.365 | AP84: =4.943-AQ84 -> 2.286 | AQ84: 2.657 | AR84: 2.564 | AS84: 3.499 | AT84: =SUM(AP84:AS84) -> 11.006 | AU84: 10.699
A85: R&D | AK85: =19.77-AL85 -> 9.932 | AL85: 9.838 | AO85: 50.566 | AP85: =26.31-AQ85 -> 12.527 | AQ85: 13.783 | AR85: 13.75 | AS85: 11.904 | AT85: =SUM(AP85:AS85) -> 51.964 | AU85: 50.937
A86: S&M | AK86: =14.418-AL86 -> 7.256 | AL86: 7.162 | AO86: 36.479 | AP86: =21.273-AQ86 -> 9.831 | AQ86: 11.442 | AR86: 11.451 | AS86: 12.846 | AT86: =SUM(AP86:AS86) -> 45.57 | AU86: 44.724
A87: G&A | AK87: =16.562-AL87 -> 8.097 | AL87: 8.465 | AO87: 44.001 | AP87: =27.693-AQ87 -> 13.113 | AQ87: 14.58 | AR87: 15.779 | AS87: 17.063 | AT87: =SUM(AP87:AS87) -> 60.535 | AU87: 59.857
A88: Total | AK88: =SUM(AK84:AK87) -> 27.041 | AL88: =SUM(AL84:AL87) -> 27.235 | AO88: =SUM(AO84:AO87) -> 140.411 | AP88: =SUM(AP84:AP87) -> 37.757 | AQ88: =SUM(AQ84:AQ87) -> 42.462 | AR88: =SUM(AR84:AR87) -> 43.544 | AS88: =SUM(AS84:AS87) -> 45.312 | AT88: =SUM(AT84:AT87) -> 169.075 | AU88: =SUM(AU84:AU87) -> 166.217

Sheet Rev
A1: Guardant Health, Inc. (NASDAQ: GH)
A2: Revenue Build
A3: $ millions except per share data, FY ending Dec
AR4: =AR16/AQ16-1 -> 0.5
B5: =+IS!B5 -> Mar | C5: =+IS!C5 -> Jun | D5: =+IS!D5 -> Sep | E5: =+IS!E5 -> Dec | F5: =+IS!F5 -> 43070 | G5: =+IS!G5 -> Mar | H5: =+IS!H5 -> Jun | I5: =+IS!I5 -> Sep | ... CM5: =+IS!CM5 -> 49279
B6: =+IS!B6 -> 1Q17A | C6: =+IS!C6 -> 2Q17A | D6: =+IS!D6 -> 3Q17A | E6: =+IS!E6 -> 4Q17A | F6: =+IS!F6 -> FY17A | G6: =+IS!G6 -> 1Q18A | H6: =+IS!H6 -> 2Q18A | I6: =+IS!I6 -> 3Q18A | ... CM6: =+IS!CM6 -> FY34E
A7: Revenue Build
A8: Consolidated
A9: Volumes
A10: Oncology | B10: -- | C10: -- | D10: -- | E10: -- | F10: -- | G10: =+G55 -> 7246 | H10: =+H55 -> 6723 | I10: =+I55 -> 7027 | J10: =+J55 -> 8596 | K10: =+K55 -> 29592 | L10: =+L55 -> 9521 | M10: =+M55 -> 11875 | N10: =+N55 -> 13259 | ... CM10: =+CM55 -> 1213765.3
A11: % yoy | B11: -- | C11: -- | D11: -- | E11: -- | F11: -- | G11: -- | H11: -- | I11: -- | J11: -- | K11: -- | L11: =+L10/G10-1 -> 0.31396633 | M11: =+M10/H10-1 -> 0.76632456 | N11: =+N10/I10-1 -> 0.88686495 | O11: =+O10/J10-1 -> 0.77640763 | P11: =+P10/K10-1 -> 0.68711138 | Q11: =+Q10/L10-1 -> 0.60245773 | R11: =+R10/M10-1 -> 0.15317895 | S11: =+S10/N10-1 -> 0.27837695 | ... CM11: =+CM10/CH10-1 -> 0.07855407
A12: % seq | B12: -- | C12: -- | D12: -- | E12: -- | F12: -- | G12: -- | H12: =+H10/G10-1 -> -0.072177753 | I12: =+I10/H10-1 -> 0.045217909 | J12: =+J10/I10-1 -> 0.22328163 | K12: -- | L12: =+L10/J10-1 -> 0.10760819 | M12: =+M10/L10-1 -> 0.24724294 | N12: =+N10/M10-1 -> 0.11654737 | O12: =+O10/N10-1 -> 0.15167056 | P12: -- | Q12: =+Q10/O10-1 -> -0.0008513425 | R12: =+R10/Q10-1 -> -0.10244478 | S12: =+S10/R10-1 -> 0.23776837 | T12: =+T10/S10-1 -> 0.023775811 | U12: -- | V12: =+V10/T10-1 -> 0.059759119 | W12: =+W10/V10-1 -> 0.1326808 | X12: =+X10/W10-1 -> 0.094863178 | Y12: =+Y10/X10-1 -> 0.12251162 | Z12: -- | AA12: =+AA10/Y10-1 -> 0.05859375 | AB12: =+AB10/AA10-1 -> 0.081180812 | AC12: =+AC10/AB10-1 -> 0.10580205 | AD12: =+AD10/AC10-1 -> 0.11111111 | AE12: -- | AF12: =+AF10/AD10-1 -> 0.086111111 | AG12: =+AG10/AF10-1 -> 0.11253197 | AH12: =+AH10/AG10-1 -> 0.0091954023 | AI12: =+AI10/AH10-1 -> 0.056947608 | AJ12: -- | AK12: =+AK10/AI10-1 -> 0.010775862 | AL12: =+AL10/AK10-1 -> 0.053304904 | AM12: =+AM10/AL10-1 -> 0.074898785 | AN12: =+AN10/AM10-1 -> 0.079096045 | AO12: -- | AP12: =+AP10/AN10-1 -> 0.029668412 | AQ12: =+AQ10/AP10-1 -> 0.084745763 | AR12: =+AR10/AQ10-1 -> 0.15625 | AS12: =+AS10/AR10-1 -> 0.067567568 | AT12: -- | AU12: =+AU10/AS10-1 -> 0.0096600736 | AV12: =+AV10/AU10-1 -> 0.10709347 | AW12: =+AW10/AV10-1 -> 0.085531149 | AX12: =+AX10/AW10-1 -> 0.074416877 | AY12: -- | AZ12: =+AZ10/AX10-1 -> 0.09784274 | BA12: =+BA10/AZ10-1 -> 0.07269194 | BB12: =+BB10/BA10-1 -> 0.064688897 | BC12: =+BC10/BB10-1 -> 0.073286493 | BD12: -- | BE12: =+BE10/BC10-1 -> 0.077524558 | BF12: =+BF10/BE10-1 -> 0.059350169 | BG12: =+BG10/BF10-1 -> 0.053302786 | BH12: =+BH10/BG10-1 -> 0.055704631 | BI12: -- | BJ12: =+BJ10/BH10-1 -> 0.037163232 | BK12: =+BK10/BJ10-1 -> 0.021126 | BL12: =+BL10/BK10-1 -> 0.018033072 | BM12: =+BM10/BL10-1 -> 0.022867802 | BN12: -- | BO12: =+BO10/BM10-1 -> 0.048398659 | BP12: =+BP10/BO10-1 -> 0.03151502 | BQ12: =+BQ10/BP10-1 -> 0.027843179 | BR12: =+BR10/BQ10-1 -> 0.032289692 | BS12: -- | BT12: =+BT10/BR10-1 -> 0.01841678 | BU12: =+BU10/BT10-1 -> 0.029061713 | BV12: =+BV10/BU10-1 -> 0.025435737 | BW12: =+BW10/BV10-1 -> 0.030207214 | BX12: -- | BY12: =+BY10/BW10-1 -> 0.016697446 | BZ12: =+BZ10/BY10-1 -> 0.025639551 | CA12: =+CA10/BZ10-1 -> 0.02209215 | CB12: =+CB10/CA10-1 -> 0.027234158 | CC12: -- | CD12: =+CD10/CB10-1 -> 0.0066440227 | CE12: =+CE10/CD10-1 -> 0.024363565 | CF12: =+CF10/CE10-1 -> 0.020744662 | CG12: =+CG10/CF10-1 -> 0.026213819 | CH12: -- | CI12: =+CI10/CG10-1 -> 0.0068332503 | CJ12: =+CJ10/CI10-1 -> 0.023231647 | CK12: =+CK10/CJ10-1 -> 0.019544782 | CL12: =+CL10/CK10-1 -> 0.025305922 | CM12: --
A13: Biopharma & Data | B13: -- | C13: -- | D13: -- | E13: -- | F13: -- | G13: =+G178 -> 2300 | H13: =+H178 -> 2500 | I13: =+I178 -> 2505 | J13: =+J178 -> 3025 | K13: =+K178 -> 10330 | L13: =+L178 -> 3750 | M13: =+M178 -> 5250 | N13: =+N178 -> 5250 | ... CM13: =+CM178 -> 96472.889
A14: % yoy | B14: -- | C14: -- | D14: -- | E14: -- | F14: -- | G14: -- | H14: -- | I14: -- | J14: -- | K14: -- | L14: =+L13/G13-1 -> 0.63043478 | M14: =+M13/H13-1 -> 1.1 | N14: =+N13/I13-1 -> 1.0958084 | O14: =+O13/J13-1 -> 1.0661157 | P14: =+P13/K13-1 -> 0.98451113 | Q14: =+Q13/L13-1 -> 0.40426667 | R14: =+R13/M13-1 -> -0.46571429 | S14: =+S13/N13-1 -> -0.41504762 | ... CM14: =+CM13/CH13-1 -> 0.08
A15: % seq | B15: -- | C15: -- | D15: -- | E15: -- | F15: -- | G15: -- | H15: =+H13/G13-1 -> 0.086956522 | I15: =+I13/H13-1 -> 0.002 | J15: =+J13/I13-1 -> 0.20758483 | K15: -- | L15: =+L13/J13-1 -> 0.23966942 | M15: =+M13/L13-1 -> 0.4 | N15: =+N13/M13-1 -> 0 | O15: =+O13/N13-1 -> 0.19047619 | P15: -- | Q15: =+Q13/O13-1 -> -0.15744 | R15: =+R13/Q13-1 -> -0.46733764 | S15: =+S13/R13-1 -> 0.09483066 | T15: =+T13/S13-1 -> 0.57635949 | U15: -- | V15: =+V13/T13-1 -> -0.27246437 | W15: =+W13/V13-1 -> 0.037194776 | X15: =+X13/W13-1 -> 0.32466466 | Y15: =+Y13/X13-1 -> 0.36391816 | Z15: -- | AA15: =+AA13/Y13-1 -> -0.22727273 | AB15: =+AB13/AA13-1 -> 0.17647059 | AC15: =+AC13/AB13-1 -> 0.125 | AD15: =+AD13/AC13-1 -> 0.21481481 | AE15: -- | AF15: =+AF13/AD13-1 -> -0.25 | AG15: =+AG13/AF13-1 -> 0.089430894 | AH15: =+AH13/AG13-1 -> 0.11940299 | AI15: =+AI13/AH13-1 -> 0.26666667 | AJ15: -- | AK15: =+AK13/AI13-1 -> -0.11052632 | AL15: =+AL13/AK13-1 -> 0.23964497 | AM15: =+AM13/AL13-1 -> 0.0023866348 | AN15: =+AN13/AM13-1 -> 0.052380952 | AO15: -- | AP15: =+AP13/AN13-1 -> -0.074660633 | AQ15: =+AQ13/AP13-1 -> 0.2396088 | AR15: =+AR13/AQ13-1 -> -0.001183432 | AS15: =+AS13/AR13-1 -> -0.066113744 | AT15: -- | AU15: =+AU13/AS13-1 -> -0.065973103 | AV15: =+AV13/AU13-1 -> 0.2396088 | AW15: =+AW13/AV13-1 -> -0.001183432 | AX15: =+AX13/AW13-1 -> -0.066113744 | AY15: -- | AZ15: =+AZ13/AX13-1 -> -0.048676309 | BA15: =+BA13/AZ13-1 -> 0.2396088 | BB15: =+BB13/BA13-1 -> -0.001183432 | BC15: =+BC13/BB13-1 -> -0.066113744 | BD15: -- | BE15: =+BE13/BC13-1 -> -0.065973103 | BF15: =+BF13/BE13-1 -> 0.2396088 | BG15: =+BG13/BF13-1 -> -0.001183432 | BH15: =+BH13/BG13-1 -> -0.066113744 | BI15: -- | BJ15: =+BJ13/BH13-1 -> -0.065973103 | BK15: =+BK13/BJ13-1 -> 0.2396088 | BL15: =+BL13/BK13-1 -> -0.001183432 | BM15: =+BM13/BL13-1 -> -0.066113744 | BN15: -- | BO15: =+BO13/BM13-1 -> -0.065973103 | BP15: =+BP13/BO13-1 -> 0.2396088 | BQ15: =+BQ13/BP13-1 -> -0.001183432 | BR15: =+BR13/BQ13-1 -> -0.066113744 | BS15: -- | BT15: =+BT13/BR13-1 -> -0.065973103 | BU15: =+BU13/BT13-1 -> 0.2396088 | BV15: =+BV13/BU13-1 -> -0.001183432 | BW15: =+BW13/BV13-1 -> -0.066113744 | BX15: -- | BY15: =+BY13/BW13-1 -> -0.065973103 | BZ15: =+BZ13/BY13-1 -> 0.2396088 | CA15: =+CA13/BZ13-1 -> -0.001183432 | CB15: =+CB13/CA13-1 -> -0.066113744 | CC15: -- | CD15: =+CD13/CB13-1 -> -0.065973103 | CE15: =+CE13/CD13-1 -> 0.2396088 | CF15: =+CF13/CE13-1 -> -0.001183432 | CG15: =+CG13/CF13-1 -> -0.066113744 | CH15: -- | CI15: =+CI13/CG13-1 -> -0.065973103 | CJ15: =+CJ13/CI13-1 -> 0.2396088 | CK15: =+CK13/CJ13-1 -> -0.001183432 | CL15: =+CL13/CK13-1 -> -0.066113744 | CM15: --
A16: Screening | B16: -- | C16: -- | D16: -- | E16: -- | F16: -- | G16: =+G196 -> -- | H16: =+H196 -> -- | I16: =+I196 -> -- | J16: =+J196 -> -- | K16: =+K196 -> -- | L16: =+L196 -> -- | M16: =+M196 -> -- | N16: =+N196 -> -- | ... CM16: =+CM196 -> 2327028.5
A17: % yoy | B17: -- | C17: -- | D17: -- | E17: -- | F17: -- | G17: -- | H17: -- | I17: -- | J17: -- | K17: -- | L17: -- | M17: -- | N17: -- | O17: -- | P17: -- | Q17: -- | R17: -- | S17: -- | T17: -- | U17: -- | V17: -- | W17: -- | X17: -- | Y17: -- | Z17: -- | AA17: -- | AB17: -- | AC17: -- | AD17: -- | AE17: -- | AF17: -- | AG17: -- | AH17: -- | AI17: -- | AJ17: -- | AK17: -- | AL17: -- | AM17: -- | AN17: -- | AO17: -- | AP17: -- | AQ17: -- | AR17: =+AR16/AM16-1 -> 4.625 | AS17: =+AS16/AN16-1 -> 4.9375 | AT17: =+AT16/AO16-1 -> 7.15625 | AU17: =+AU16/AP16-1 -> 3.8570381 | AV17: =+AV16/AQ16-1 -> 2.0556971 | AW17: =+AW16/AR16-1 -> 2.0132353 | AX17: =+AX16/AS16-1 -> 1.3858329 | AY17: =+AY16/AT16-1 -> 1.9377448 | ... CM17: =+CM16/CH16-1 -> 0.041998669
A18: % seq | B18: -- | C18: -- | D18: -- | E18: -- | F18: -- | G18: -- | H18: -- | I18: -- | J18: -- | K18: -- | L18: -- | M18: -- | N18: -- | O18: -- | P18: -- | Q18: -- | R18: -- | S18: -- | T18: -- | U18: -- | V18: -- | W18: -- | X18: -- | Y18: -- | Z18: -- | AA18: -- | AB18: -- | AC18: -- | AD18: -- | AE18: -- | AF18: -- | AG18: -- | AH18: -- | AI18: -- | AJ18: -- | AK18: -- | AL18: -- | AM18: -- | AN18: -- | AO18: -- | AP18: =+AP16/AN16-1 -> 0.40625 | AQ18: =+AQ16/AP16-1 -> 0.77777778 | AR18: =+AR16/AQ16-1 -> 0.5 | AS18: =+AS16/AR16-1 -> 0.58333333 | AT18: -- | AU18: =+AU16/AS16-1 -> 0.15035112 | AV18: =+AV16/AU16-1 -> 0.11844923 | AW18: =+AW16/AV16-1 -> 0.47915607 | AX18: =+AX16/AW16-1 -> 0.25365873 | AY18: -- | AZ18: =+AZ16/AX16-1 -> 0.21074729 | BA18: =+BA16/AZ16-1 -> 0.20086236 | BB18: =+BB16/BA16-1 -> 0.12432174 | BC18: =+BC16/BB16-1 -> 0.16093137 | BD18: -- | BE18: =+BE16/BC16-1 -> 0.12669326 | BF18: =+BF16/BE16-1 -> 0.097107327 | BG18: =+BG16/BF16-1 -> 0.088408288 | BH18: =+BH16/BG16-1 -> 0.098230429 | BI18: -- | BJ18: =+BJ16/BH16-1 -> 0.051281865 | BK18: =+BK16/BJ16-1 -> 0.059852124 | BL18: =+BL16/BK16-1 -> 0.10403054 | BM18: =+BM16/BL16-1 -> 0.077522051 | BN18: -- | BO18: =+BO16/BM16-1 -> 0.066123575 | BP18: =+BP16/BO16-1 -> 0.069026387 | BQ18: =+BQ16/BP16-1 -> 0.049678104 | BR18: =+BR16/BQ16-1 -> 0.054115839 | BS18: -- | BT18: =+BT16/BR16-1 -> 0.027786381 | BU18: =+BU16/BT16-1 -> 0.036380847 | BV18: =+BV16/BU16-1 -> 0.033125391 | BW18: =+BW16/BV16-1 -> 0.036988788 | BX18: -- | BY18: =+BY16/BW16-1 -> 0.0028087358 | BZ18: =+BZ16/BY16-1 -> 0.021364078 | CA18: =+CA16/BZ16-1 -> 0.041190384 | CB18: =+CB16/CA16-1 -> 0.030195762 | CC18: -- | CD18: =+CD16/CB16-1 -> 0.012078159 | CE18: =+CE16/CD16-1 -> 0.02783176 | CF18: =+CF16/CE16-1 -> 0.017909229 | CG18: =+CG16/CF16-1 -> 0.020664074 | CH18: -- | CI18: =+CI16/CG16-1 -> -0.0054469798 | CJ18: =+CJ16/CI16-1 -> 0.011054362 | CK18: =+CK16/CJ16-1 -> 0.009173945 | CL18: =+CL16/CK16-1 -> 0.011806501 | CM18: --
A19: Total test volume | B19: -- | C19: -- | D19: -- | E19: -- | F19: -- | G19: =+G55+G178 -> 9546 | H19: =+H55+H178 -> 9223 | I19: =+I55+I178 -> 9532 | J19: =+J55+J178 -> 11621 | K19: =+K55+K178 -> 39922 | L19: =+L55+L178 -> 13271 | M19: =+M55+M178 -> 17125 | N19: =+N55+N178 -> 18509 | ... AJ19: =+AJ55+AJ178 -> 202750 | AK19: =+AK55+AK178+AK196 -> 55350 | AL19: =+AL55+AL178+AL196 -> 59875 | AM19: =+AM55+AM178+AM196 -> 67866.667 | AN19: =+AN55+AN178+AN196 -> 74750 | AO19: =+AO55+AO178+AO196 -> 257841.67 | AP19: =+AP55+AP178+AP196 -> 78225 | AQ19: =+AQ55+AQ178+AQ196 -> 92675 | AR19: =+AR55+AR178+AR196 -> 110660 | ... CM19: =+CM55+CM178+CM196 -> 3637266.7
A20: % yoy | B20: -- | C20: -- | D20: -- | E20: -- | F20: -- | G20: -- | H20: -- | I20: -- | J20: -- | K20: -- | L20: =+L19/G19-1 -> 0.3902158 | M20: =+M19/H19-1 -> 0.85677112 | N20: =+N19/I19-1 -> 0.94177507 | O20: =+O19/J19-1 -> 0.85181998 | P20: =+P19/K19-1 -> 0.76406493 | Q20: =+Q19/L19-1 -> 0.54645468 | R20: =+R19/M19-1 -> -0.036554745 | S20: =+S19/N19-1 -> 0.081689989 | ... CM20: =+CM19/CH19-1 -> 0.054914448
A21: % seq | B21: -- | C21: -- | D21: -- | E21: -- | F21: -- | G21: -- | H21: =+H19/G19-1 -> -0.033836162 | I21: =+I19/H19-1 -> 0.033503199 | J21: =+J19/I19-1 -> 0.21915653 | K21: -- | L21: =+L19/J19-1 -> 0.14198434 | M21: =+M19/L19-1 -> 0.29040766 | N21: =+N19/M19-1 -> 0.080817518 | O21: =+O19/N19-1 -> 0.16267762 | P21: -- | Q21: =+Q19/O19-1 -> -0.046328996 | R21: =+R19/Q19-1 -> -0.1960727 | S21: =+S19/R19-1 -> 0.21346748 | T21: =+T19/S19-1 -> 0.10853604 | U21: -- | V21: =+V19/T19-1 -> -0.012706137 | W21: =+W19/V19-1 -> 0.11733297 | X21: =+X19/W19-1 -> 0.12915084 | Y21: =+Y19/X19-1 -> 0.16476759 | Z21: -- | AA21: =+AA19/Y19-1 -> 0 | AB21: =+AB19/AA19-1 -> 0.096273292 | AC21: =+AC19/AB19-1 -> 0.10906516 | AD21: =+AD19/AC19-1 -> 0.12899106 | AE21: -- | AF21: =+AF19/AD19-1 -> 0.023755656 | AG21: =+AG19/AF19-1 -> 0.10939227 | AH21: =+AH19/AG19-1 -> 0.023904382 | AI21: =+AI19/AH19-1 -> 0.087548638 | AJ21: -- | AK21: =+AK19/AI19-1 -> -0.0098389982 | AL21: =+AL19/AK19-1 -> 0.081752484 | AM21: =+AM19/AL19-1 -> 0.13347251 | AN21: =+AN19/AM19-1 -> 0.10142436 | AO21: -- | AP21: =+AP19/AN19-1 -> 0.046488294 | AQ21: =+AQ19/AP19-1 -> 0.18472355 | AR21: =+AR19/AQ19-1 -> 0.19406528 | AS21: =+AS19/AR19-1 -> 0.16413338 | AT21: -- | AU21: =+AU19/AS19-1 -> 0.044219498 | AV21: =+AV19/AU19-1 -> 0.1216621 | AW21: =+AW19/AV19-1 -> 0.20520966 | AX21: =+AX19/AW19-1 -> 0.1351317 | AY21: -- | AZ21: =+AZ19/AX19-1 -> 0.13836764 | BA21: =+BA19/AZ19-1 -> 0.14119291 | BB21: =+BB19/BA19-1 -> 0.09030288 | BC21: =+BC19/BB19-1 -> 0.11054223 | BD21: -- | BE21: =+BE19/BC19-1 -> 0.097371282 | BF21: =+BF19/BE19-1 -> 0.086528903 | BG21: =+BG19/BF19-1 -> 0.070299163 | BH21: =+BH19/BG19-1 -> 0.074685993 | BI21: -- | BJ21: =+BJ19/BH19-1 -> 0.041709977 | BK21: =+BK19/BJ19-1 -> 0.050110404 | BL21: =+BL19/BK19-1 -> 0.067345324 | BM21: =+BM19/BL19-1 -> 0.052737735 | BN21: -- | BO21: =+BO19/BM19-1 -> 0.055887148 | BP21: =+BP19/BO19-1 -> 0.060341192 | BQ21: =+BQ19/BP19-1 -> 0.040628158 | BR21: =+BR19/BQ19-1 -> 0.043163076 | BS21: -- | BT21: =+BT19/BR19-1 -> 0.022157208 | BU21: =+BU19/BT19-1 -> 0.038879794 | BV21: =+BV19/BU19-1 -> 0.029590827 | BW21: =+BW19/BV19-1 -> 0.031857524 | BX21: -- | BY21: =+BY19/BW19-1 -> 0.005618528 | BZ21: =+BZ19/BY19-1 -> 0.027944968 | CA21: =+CA19/BZ19-1 -> 0.033655106 | CB21: =+CB19/CA19-1 -> 0.026571553 | CC21: -- | CD21: =+CD19/CB19-1 -> 0.0083402219 | CE21: =+CE19/CD19-1 -> 0.03161475 | CF21: =+CF19/CE19-1 -> 0.018297789 | CG21: =+CG19/CF19-1 -> 0.020096568 | CH21: -- | CI21: =+CI19/CG19-1 -> -0.0029397764 | CJ21: =+CJ19/CI19-1 -> 0.020448418 | CK21: =+CK19/CJ19-1 -> 0.012319449 | CL21: =+CL19/CK19-1 -> 0.014125104 | CM21: --
A23: Revenue
A24: Oncology | B24: -- | C24: -- | D24: -- | E24: -- | F24: -- | G24: =+G89 -> 7.1 | H24: =+H89 -> 9.5 | I24: =+I89 -> 9.6 | J24: =+J89 -> 17 | K24: =+K89 -> 43.2 | L24: =+L89 -> 17.2 | M24: =+M89 -> 21.8 | N24: =+N89 -> 30.8 | ... CM24: =+CM89 -> 2493.2556
A25: % yoy | B25: -- | C25: -- | D25: -- | E25: -- | F25: -- | G25: -- | H25: -- | I25: -- | J25: -- | K25: -- | L25: =+L24/G24-1 -> 1.4225352 | M25: =+M24/H24-1 -> 1.2947368 | N25: =+N24/I24-1 -> 2.2083333 | O25: =+O24/J24-1 -> 0.84117647 | P25: =+P24/K24-1 -> 1.3402778 | Q25: =+Q24/L24-1 -> 1.2093023 | R25: =+R24/M24-1 -> 0.81651376 | S25: =+S24/N24-1 -> 0.56818182 | ... CM25: =+CM24/CH24-1 -> 0.076671238
A26: % seq | B26: -- | C26: -- | D26: -- | E26: -- | F26: -- | G26: -- | H26: =+H24/G24-1 -> 0.33802817 | I26: =+I24/H24-1 -> 0.010526316 | J26: =+J24/I24-1 -> 0.77083333 | K26: -- | L26: =+L24/J24-1 -> 0.011764706 | M26: =+M24/L24-1 -> 0.26744186 | N26: =+N24/M24-1 -> 0.41284404 | O26: =+O24/N24-1 -> 0.016233766 | P26: -- | Q26: =+Q24/O24-1 -> 0.21405751 | R26: =+R24/Q24-1 -> 0.042105263 | S26: =+S24/R24-1 -> 0.21969697 | T26: =+T24/S24-1 -> -0.049689441 | U26: -- | V26: =+V24/T24-1 -> 0.08496732 | W26: =+W24/V24-1 -> 0.2248996 | X26: =+X24/W24-1 -> 0.0049180328 | Y26: =+Y24/X24-1 -> 0.048939641 | Z26: -- | AA26: =+AA24/Y24-1 -> 0.031254121 | AB26: =+AB24/AA24-1 -> 0.068811654 | AC26: =+AC24/AB24-1 -> 0.10352495 | AD26: =+AD24/AC24-1 -> 0.079371085 | AE26: -- | AF26: =+AF24/AD24-1 -> 0.084573494 | AG26: =+AG24/AF24-1 -> 0.095674027 | AH26: =+AH24/AG24-1 -> 0.031871657 | AI26: =+AI24/AH24-1 -> 0.053735814 | AJ26: -- | AK26: =+AK24/AI24-1 -> 0.15284925 | AL26: =+AL24/AK24-1 -> 0.035952858 | AM26: =+AM24/AL24-1 -> 0.083887955 | AN26: =+AN24/AM24-1 -> 0.031275452 | AO26: -- | AP26: =+AP24/AN24-1 -> 0.033966747 | AQ26: =+AQ24/AP24-1 -> 0.053972197 | AR26: =+AR24/AQ24-1 -> 0.16206321 | AS26: =+AS24/AR24-1 -> 0.030081019 | AT26: -- | AU26: =+AU24/AS24-1 -> 0.032693456 | AV26: =+AV24/AU24-1 -> 0.071732389 | AW26: =+AW24/AV24-1 -> 0.066588453 | AX26: =+AX24/AW24-1 -> 0.025786582 | AY26: -- | AZ26: =+AZ24/AX24-1 -> 0.15149659 | BA26: =+BA24/AZ24-1 -> 0.014181858 | BB26: =+BB24/BA24-1 -> 0.035113054 | BC26: =+BC24/BB24-1 -> 0.023039262 | BD26: -- | BE26: =+BE24/BC24-1 -> 0.14174305 | BF26: =+BF24/BE24-1 -> 0.028727627 | BG26: =+BG24/BF24-1 -> 0.040792937 | BH26: =+BH24/BG24-1 -> 0.023294763 | BI26: -- | BJ26: =+BJ24/BH24-1 -> 0.086448009 | BK26: =+BK24/BJ24-1 -> 0.0060910934 | BL26: =+BL24/BK24-1 -> 0.021794817 | BM26: =+BM24/BL24-1 -> -3.4259085e-05 | BN26: -- | BO26: =+BO24/BM24-1 -> 0.085538889 | BP26: =+BP24/BO24-1 -> 0.01117044 | BQ26: =+BQ24/BP24-1 -> 0.026246562 | BR26: =+BR24/BQ24-1 -> 0.0056738376 | BS26: -- | BT26: =+BT24/BR24-1 -> 0.06687178 | BU26: =+BU24/BT24-1 -> 0.010132731 | BV26: =+BV24/BU24-1 -> 0.024523072 | BW26: =+BW24/BV24-1 -> 0.0051749315 | BX26: -- | BY26: =+BY24/BW24-1 -> 0.055617849 | BZ26: =+BZ24/BY24-1 -> 0.0071117685 | CA26: =+CA24/BZ24-1 -> 0.020948976 | CB26: =+CB24/CA24-1 -> 0.0029778505 | CC26: -- | CD26: =+CD24/CB24-1 -> 0.047657342 | CE26: =+CE24/CD24-1 -> 0.0067579348 | CF26: =+CF24/CE24-1 -> 0.019973795 | CG26: =+CG24/CF24-1 -> 0.0030711875 | CH26: -- | CI26: =+CI24/CG24-1 -> 0.045923143 | CJ26: =+CJ24/CI24-1 -> 0.0064805249 | CK26: =+CK24/CJ24-1 -> 0.019105197 | CL26: =+CL24/CK24-1 -> 0.0032076321 | CM26: --
A27: Biopharma & Data | B27: -- | C27: -- | D27: -- | E27: -- | F27: -- | G27: =+G173 -> 0 | H27: =+H173 -> 0 | I27: =+I173 -> 0 | J27: =+J173 -> 0 | K27: =+K173 -> 0 | L27: =+L173 -> 0 | M27: =+M173 -> 0 | N27: =+N173 -> 0 | ... CM27: =+CM173 -> 470.28151
A28: % yoy | B28: -- | C28: -- | D28: -- | E28: -- | F28: -- | G28: -- | H28: -- | I28: -- | J28: -- | K28: -- | L28: -- | M28: -- | N28: -- | O28: -- | P28: -- | Q28: -- | R28: -- | S28: -- | T28: -- | U28: -- | V28: -- | W28: -- | X28: -- | Y28: -- | Z28: -- | AA28: -- | AB28: -- | AC28: -- | AD28: -- | AE28: -- | AF28: -- | AG28: -- | AH28: -- | AI28: -- | AJ28: -- | AK28: =+AK27/AF27-1 -> 0.32396794 | AL28: =+AL27/AG27-1 -> 0.3955371 | AM28: =+AM27/AH27-1 -> 0.27656043 | AN28: =+AN27/AI27-1 -> 0.24820865 | AO28: =+AO27/AJ27-1 -> 0.30572794 | AP28: =+AP27/AK27-1 -> 0.2072259 | AQ28: =+AQ27/AL27-1 -> 0.27512348 | AR28: =+AR27/AM27-1 -> 0.17582229 | ... CM28: =+CM27/CH27-1 -> 0.085220466
A29: % seq | B29: -- | C29: -- | D29: -- | E29: -- | F29: -- | G29: -- | H29: -- | I29: -- | J29: -- | K29: -- | L29: -- | M29: -- | N29: -- | O29: -- | P29: -- | Q29: -- | R29: -- | S29: -- | T29: -- | U29: -- | V29: -- | W29: -- | X29: -- | Y29: -- | Z29: -- | AA29: -- | AB29: -- | AC29: -- | AD29: -- | AE29: -- | AF29: -- | AG29: =+AG27/AF27-1 -> 0.10889207 | AH29: =+AH27/AG27-1 -> 0.15824609 | AI29: =+AI27/AH27-1 -> 0.087859895 | AJ29: -- | AK29: =+AK27/AI27-1 -> -0.052423282 | AL29: =+AL27/AK27-1 -> 0.16883497 | AM29: =+AM27/AL27-1 -> 0.059499693 | AN29: =+AN27/AM27-1 -> 0.063699057 | AO29: -- | AP29: =+AP27/AN27-1 -> -0.083535305 | AQ29: =+AQ27/AP27-1 -> 0.23457334 | AR29: =+AR27/AQ27-1 -> -0.023009639 | AS29: =+AS27/AR27-1 -> -0.013264877 | AT29: -- | AU29: =+AU27/AS27-1 -> -0.081262175 | AV29: =+AV27/AU27-1 -> 0.22314934 | AW29: =+AW27/AV27-1 -> -0.0068402505 | AX29: =+AX27/AW27-1 -> 0.022911073 | AY29: -- | AZ29: =+AZ27/AX27-1 -> -0.098506057 | BA29: =+BA27/AZ27-1 -> 0.22197696 | BB29: =+BB27/BA27-1 -> -0.0072489887 | BC29: =+BC27/BB27-1 -> 0.029382939 | BD29: -- | BE29: =+BE27/BC27-1 -> -0.11434104 | BF29: =+BF27/BE27-1 -> 0.22047805 | BG29: =+BG27/BF27-1 -> -0.0077727143 | BH29: =+BH27/BG27-1 -> 0.037683281 | BI29: -- | BJ29: =+BJ27/BH27-1 -> -0.13681707 | BK29: =+BK27/BJ27-1 -> 0.22020817 | BL29: =+BL27/BK27-1 -> -0.0078671489 | BM29: =+BM27/BL27-1 -> 0.039180873 | BN29: -- | BO29: =+BO27/BM27-1 -> -0.13773565 | BP29: =+BP27/BO27-1 -> 0.21993568 | BQ29: =+BQ27/BP27-1 -> -0.0079625375 | BR29: =+BR27/BQ27-1 -> 0.040693885 | BS29: -- | BT29: =+BT27/BR27-1 -> -0.138661 | BU29: =+BU27/BT27-1 -> 0.2196606 | BV29: =+BV27/BU27-1 -> -0.0080588783 | BW29: =+BW27/BV27-1 -> 0.042222295 | BX29: -- | BY29: =+BY27/BW27-1 -> -0.13959303 | BZ29: =+BZ27/BY27-1 -> 0.21938293 | CA29: =+CA27/BZ27-1 -> -0.0081561692 | CB29: =+CB27/CA27-1 -> 0.04376608 | CC29: -- | CD29: =+CD27/CB27-1 -> -0.14053168 | CE29: =+CE27/CD27-1 -> 0.21910268 | CF29: =+CF27/CE27-1 -> -0.0082544077 | CG29: =+CG27/CF27-1 -> 0.045325208 | CH29: -- | CI29: =+CI27/CG27-1 -> -0.14147683 | CJ29: =+CJ27/CI27-1 -> 0.21881987 | CK29: =+CK27/CJ27-1 -> -0.0083535909 | CL29: =+CL27/CK27-1 -> 0.046899644 | CM29: --
A30: Screening | B30: -- | C30: -- | D30: -- | E30: -- | F30: -- | G30: =+G204 -> -- | H30: =+H204 -> -- | I30: =+I204 -> -- | J30: =+J204 -> -- | K30: =+K204 -> -- | L30: =+L204 -> -- | M30: =+M204 -> -- | N30: =+N204 -> -- | ... CM30: =+CM204 -> 2024.5148
A31: % yoy | B31: -- | C31: -- | D31: -- | E31: -- | F31: -- | G31: -- | H31: -- | I31: -- | J31: -- | K31: -- | L31: -- | M31: -- | N31: -- | O31: -- | P31: -- | Q31: -- | R31: -- | S31: -- | T31: -- | U31: -- | V31: -- | W31: -- | X31: -- | Y31: -- | Z31: -- | AA31: -- | AB31: -- | AC31: -- | AD31: -- | AE31: -- | AF31: -- | AG31: -- | AH31: -- | AI31: -- | AJ31: -- | AK31: -- | AL31: -- | AM31: -- | AN31: -- | AO31: -- | AP31: -- | AQ31: -- | AR31: =+AR30/AM30-1 -> 23.03988 | AS31: =+AS30/AN30-1 -> 7.5243873 | AT31: =+AT30/AO30-1 -> 14.5605 | AU31: =+AU30/AP30-1 -> 4.9675604 | AV31: =+AV30/AQ30-1 -> 1.5577592 | AW31: =+AW30/AR30-1 -> 1.3244101 | AX31: =+AX30/AS30-1 -> 1.000136 | AY31: =+AY30/AT30-1 -> 1.4842904 | ... CM31: =+CM30/CH30-1 -> 0.041998669
A32: % seq | B32: -- | C32: -- | D32: -- | E32: -- | F32: -- | G32: -- | H32: -- | I32: -- | J32: -- | K32: -- | L32: -- | M32: -- | N32: -- | O32: -- | P32: -- | Q32: -- | R32: -- | S32: -- | T32: -- | U32: -- | V32: -- | W32: -- | X32: -- | Y32: -- | Z32: -- | AA32: -- | AB32: -- | AC32: -- | AD32: -- | AE32: -- | AF32: -- | AG32: -- | AH32: -- | AI32: -- | AJ32: -- | AK32: -- | AL32: -- | AM32: -- | AN32: =+AN30/AM30-1 -> 3.108674 | AO32: -- | AP32: =+AP30/AN30-1 -> 0.37757826 | AQ32: =+AQ30/AP30-1 -> 1.6094768 | AR32: =+AR30/AQ30-1 -> 0.62764952 | AS32: =+AS30/AR30-1 -> 0.45690942 | AT32: -- | AU32: =+AU30/AS30-1 -> -0.035616144 | AV32: =+AV30/AU30-1 -> 0.11844923 | AW32: =+AW30/AV30-1 -> 0.47915607 | AX32: =+AX30/AW30-1 -> 0.25365873 | AY32: -- | AZ32: =+AZ30/AX30-1 -> 0.29667129 | BA32: =+BA30/AZ30-1 -> 0.20086236 | BB32: =+BB30/BA30-1 -> 0.12432174 | BC32: =+BC30/BB30-1 -> 0.16093137 | BD32: -- | BE32: =+BE30/BC30-1 -> 0.15384249 | BF32: =+BF30/BE30-1 -> 0.097107327 | BG32: =+BG30/BF30-1 -> 0.088408288 | BH32: =+BH30/BG30-1 -> 0.098230429 | BI32: -- | BJ32: =+BJ30/BH30-1 -> 0.076017909 | BK32: =+BK30/BJ30-1 -> 0.059852124 | BL32: =+BL30/BK30-1 -> 0.10403054 | BM32: =+BM30/BL30-1 -> 0.077522051 | BN32: -- | BO32: =+BO30/BM30-1 -> 0.066123575 | BP32: =+BP30/BO30-1 -> 0.069026387 | BQ32: =+BQ30/BP30-1 -> 0.049678104 | BR32: =+BR30/BQ30-1 -> 0.054115839 | BS32: -- | BT32: =+BT30/BR30-1 -> 0.027786381 | BU32: =+BU30/BT30-1 -> 0.036380847 | BV32: =+BV30/BU30-1 -> 0.033125391 | BW32: =+BW30/BV30-1 -> 0.036988788 | BX32: -- | BY32: =+BY30/BW30-1 -> 0.0028087358 | BZ32: =+BZ30/BY30-1 -> 0.021364078 | CA32: =+CA30/BZ30-1 -> 0.041190384 | CB32: =+CB30/CA30-1 -> 0.030195762 | CC32: -- | CD32: =+CD30/CB30-1 -> 0.012078159 | CE32: =+CE30/CD30-1 -> 0.02783176 | CF32: =+CF30/CE30-1 -> 0.017909229 | CG32: =+CG30/CF30-1 -> 0.020664074 | CH32: -- | CI32: =+CI30/CG30-1 -> -0.0054469798 | CJ32: =+CJ30/CI30-1 -> 0.011054362 | CK32: =+CK30/CJ30-1 -> 0.009173945 | CL32: =+CL30/CK30-1 -> 0.011806501 | CM32: --
A33: Licensing & Other | B33: -- | C33: -- | D33: -- | E33: -- | F33: -- | G33: =+G269 -> -- | H33: =+H269 -> -- | I33: =+I269 -> -- | J33: =+J269 -> -- | K33: =+K269 -> -- | L33: =+L269 -> -- | M33: =+M269 -> -- | N33: =+N269 -> -- | ... CM33: =+CM269 -> 13.282472
A34: % yoy | B34: -- | C34: -- | D34: -- | E34: -- | F34: -- | G34: -- | H34: -- | I34: -- | J34: -- | K34: -- | L34: -- | M34: -- | N34: -- | O34: -- | P34: -- | Q34: -- | R34: -- | S34: -- | T34: -- | U34: -- | V34: -- | W34: -- | X34: -- | Y34: -- | Z34: -- | AA34: -- | AB34: -- | AC34: -- | AD34: -- | AE34: -- | AF34: -- | AG34: -- | AH34: -- | AI34: -- | AJ34: -- | AK34: =+AK33/AF33-1 -> -0.41193342 | AL34: =+AL33/AG33-1 -> -0.43337164 | AM34: =+AM33/AH33-1 -> -0.10633434 | AN34: =+AN33/AI33-1 -> -0.59313751 | AO34: =+AO33/AJ33-1 -> -0.42578213 | AP34: =+AP33/AK33-1 -> -0.63944919 | AQ34: =+AQ33/AL33-1 -> -0.15298384 | AR34: =+AR33/AM33-1 -> -0.28508611 | ... CM34: =+CM33/CH33-1 -> 0.05
A35: % seq | B35: -- | C35: -- | D35: -- | E35: -- | F35: -- | G35: -- | H35: -- | I35: -- | J35: -- | K35: -- | L35: -- | M35: -- | N35: -- | O35: -- | P35: -- | Q35: -- | R35: -- | S35: -- | T35: -- | U35: -- | V35: -- | W35: -- | X35: -- | Y35: -- | Z35: -- | AA35: -- | AB35: -- | AC35: -- | AD35: -- | AE35: -- | AF35: -- | AG35: =+AG33/AF33-1 -> -0.38949716 | AH35: =+AH33/AG33-1 -> -0.42950168 | AI35: =+AI33/AH33-1 -> 1.0668973 | AJ35: -- | AK35: =+AK33/AI33-1 -> -0.1831063 | AL35: =+AL33/AK33-1 -> -0.4117533 | AM35: =+AM33/AL33-1 -> -0.10023079 | AN35: =+AN33/AM33-1 -> -0.058995969 | AO35: -- | AP35: =+AP33/AN33-1 -> -0.27609034 | AQ35: =+AQ33/AP33-1 -> 0.38192577 | AR35: =+AR33/AQ33-1 -> -0.24056053 | AS35: =+AS33/AR33-1 -> 0.11891338 | AT35: -- | AU35: =+AU33/AS33-1 -> -0.10584059 | AV35: =+AV33/AU33-1 -> 0.38192577 | AW35: =+AW33/AV33-1 -> -0.24056053 | AX35: =+AX33/AW33-1 -> 0.11891338 | AY35: -- | AZ35: =+AZ33/AX33-1 -> -0.10584059 | BA35: =+BA33/AZ33-1 -> 0.38192577 | BB35: =+BB33/BA33-1 -> -0.24056053 | BC35: =+BC33/BB33-1 -> 0.11891338 | BD35: -- | BE35: =+BE33/BC33-1 -> -0.10584059 | BF35: =+BF33/BE33-1 -> 0.38192577 | BG35: =+BG33/BF33-1 -> -0.24056053 | BH35: =+BH33/BG33-1 -> 0.11891338 | BI35: -- | BJ35: =+BJ33/BH33-1 -> -0.10584059 | BK35: =+BK33/BJ33-1 -> 0.38192577 | BL35: =+BL33/BK33-1 -> -0.24056053 | BM35: =+BM33/BL33-1 -> 0.11891338 | BN35: -- | BO35: =+BO33/BM33-1 -> -0.10584059 | BP35: =+BP33/BO33-1 -> 0.38192577 | BQ35: =+BQ33/BP33-1 -> -0.24056053 | BR35: =+BR33/BQ33-1 -> 0.11891338 | BS35: -- | BT35: =+BT33/BR33-1 -> -0.10584059 | BU35: =+BU33/BT33-1 -> 0.38192577 | BV35: =+BV33/BU33-1 -> -0.24056053 | BW35: =+BW33/BV33-1 -> 0.11891338 | BX35: -- | BY35: =+BY33/BW33-1 -> -0.10584059 | BZ35: =+BZ33/BY33-1 -> 0.38192577 | CA35: =+CA33/BZ33-1 -> -0.24056053 | CB35: =+CB33/CA33-1 -> 0.11891338 | CC35: -- | CD35: =+CD33/CB33-1 -> -0.10584059 | CE35: =+CE33/CD33-1 -> 0.38192577 | CF35: =+CF33/CE33-1 -> -0.24056053 | CG35: =+CG33/CF33-1 -> 0.11891338 | CH35: -- | CI35: =+CI33/CG33-1 -> -0.10584059 | CJ35: =+CJ33/CI33-1 -> 0.38192577 | CK35: =+CK33/CJ33-1 -> -0.24056053 | CL35: =+CL33/CK33-1 -> 0.11891338 | CM35: --
A36: Total Revenue | B36: -- | C36: -- | D36: -- | E36: -- | F36: -- | G36: =+G286 -> 16.692 | H36: =+H286 -> 19.382 | I36: =+I286 -> 21.692 | J36: =+J286 -> 32.873 | K36: =+K286 -> 90.639 | L36: =+L286 -> 36.655 | M36: =+M286 -> 53.975 | N36: =+N286 -> 60.848 | ... AE36: =+AE286 -> 449.538 | AF36: =+AF89+AF173+AF269 -> 128.714 | AG36: =+AG89+AG173+AG269 -> 137.15 | AH36: =+AH89+AH173+AH269 -> 143.03 | AI36: =+AI89+AI173+AI269 -> 155.054 | AJ36: =+AJ89+AJ173+AJ269 -> 563.948 | AK36: =+AK89+AK173+AK204+AK269 -> 168.491 | AL36: =+AL89+AL173+AL204+AL269 -> 177.235 | AM36: =+AM89+AM173+AM204+AM269 -> 191.476 | AN36: =+AN89+AN173+AN204+AN269 -> 201.814 | AO36: =+AO89+AO173+AO204+AO269 -> 739.016 | AP36: =+AP89+AP173+AP204+AP269 -> 203.471 | AQ36: =+AQ89+AQ173+AQ204+AQ269 -> 232.088 | AR36: =+AR89+AR173+AR204+AR269 -> 265.196 | ... CM36: =+CM89+CM173+CM204+CM269 -> 5001.3344
A37: % yoy | B37: -- | C37: -- | D37: -- | E37: -- | F37: -- | G37: -- | H37: -- | I37: -- | J37: -- | K37: -- | L37: =+L36/G36-1 -> 1.1959621 | M37: =+M36/H36-1 -> 1.7848003 | N37: =+N36/I36-1 -> 1.8050894 | O37: =+O36/J36-1 -> 0.91333313 | P37: =+P36/K36-1 -> 1.3651519 | Q37: =+Q36/L36-1 -> 0.84176784 | R37: =+R36/M36-1 -> 0.22899491 | S37: =+S36/N36-1 -> 0.22549632 | ... CM37: =+CM36/CH36-1 -> 0.063067934
A38: % seq | B38: -- | C38: -- | D38: -- | E38: -- | F38: -- | G38: -- | H38: =+H36/G36-1 -> 0.16115504 | I38: =+I36/H36-1 -> 0.11918275 | J38: =+J36/I36-1 -> 0.51544348 | K38: -- | L38: =+L36/J36-1 -> 0.11504882 | M38: =+M36/L36-1 -> 0.47251398 | N38: =+N36/M36-1 -> 0.12733673 | O38: =+O36/N36-1 -> 0.033674073 | P38: -- | Q38: =+Q36/O36-1 -> 0.073342131 | R38: =+R36/Q36-1 -> -0.017404829 | S38: =+S36/R36-1 -> 0.12412753 | T38: =+T36/S36-1 -> 0.050248763 | U38: -- | V38: =+V36/T36-1 -> 0.0044563052 | W38: =+W36/V36-1 -> 0.17080023 | X38: =+X36/W36-1 -> 0.029304785 | Y38: =+Y36/X36-1 -> 0.14037975 | Z38: -- | AA38: =+AA36/Y36-1 -> -0.11108336 | AB38: =+AB36/AA36-1 -> 0.13574543 | AC38: =+AC36/AB36-1 -> 0.075679836 | AD38: =+AD36/AC36-1 -> 0.080806446 | AE38: -- | AF38: =+AF36/AD36-1 -> 0.014366661 | AG38: =+AG36/AF36-1 -> 0.065540656 | AH38: =+AH36/AG36-1 -> 0.042872767 | AI38: =+AI36/AH36-1 -> 0.08406628 | AJ38: -- | AK38: =+AK36/AI36-1 -> 0.086660131 | AL38: =+AL36/AK36-1 -> 0.051895947 | AM38: =+AM36/AL36-1 -> 0.080350946 | AN38: =+AN36/AM36-1 -> 0.053991101 | AO38: -- | AP38: =+AP36/AN36-1 -> 0.0082105305 | AQ38: =+AQ36/AP36-1 -> 0.14064412 | AR38: =+AR36/AQ36-1 -> 0.14265279 | AS38: =+AS36/AR36-1 -> 0.060596691 | AT38: -- | AU38: =+AU36/AS36-1 -> 0.0012063884 | AV38: =+AV36/AU36-1 -> 0.10618102 | AW38: =+AW36/AV36-1 -> 0.099806608 | AX38: =+AX36/AW36-1 -> 0.06311565 | AY38: -- | AZ38: =+AZ36/AX36-1 -> 0.13556345 | BA38: =+BA36/AZ36-1 -> 0.085051099 | BB38: =+BB36/BA36-1 -> 0.048710543 | BC38: =+BC36/BB36-1 -> 0.06042733 | BD38: -- | BE38: =+BE36/BC36-1 -> 0.10839685 | BF38: =+BF36/BE36-1 -> 0.071778729 | BG38: =+BG36/BF36-1 -> 0.047754606 | BH38: =+BH36/BG36-1 -> 0.04910226 | BI38: -- | BJ38: =+BJ36/BH36-1 -> 0.055779768 | BK38: =+BK36/BJ36-1 -> 0.046243138 | BL38: =+BL36/BK36-1 -> 0.045456051 | BM38: =+BM36/BL36-1 -> 0.032584138 | BN38: -- | BO38: =+BO36/BM36-1 -> 0.053459977 | BP38: =+BP36/BO36-1 -> 0.052778117 | BQ38: =+BQ36/BP36-1 -> 0.03081288 | BR38: =+BR36/BQ36-1 -> 0.028564975 | BS38: -- | BT38: =+BT36/BR36-1 -> 0.030042357 | BU38: =+BU36/BT36-1 -> 0.039179885 | BV38: =+BV36/BU36-1 -> 0.023865426 | BW38: =+BW36/BV36-1 -> 0.021907701 | BX38: -- | BY38: =+BY36/BW36-1 -> 0.014514328 | BZ38: =+BZ36/BY36-1 -> 0.031267873 | CA38: =+CA36/BZ36-1 -> 0.025413165 | CB38: =+CB36/CA36-1 -> 0.018245776 | CC38: -- | CD38: =+CD36/CB36-1 -> 0.014395702 | CE38: =+CE36/CD36-1 -> 0.033677351 | CF38: =+CF36/CE36-1 -> 0.01556969 | CG38: =+CG36/CF36-1 -> 0.014567619 | CH38: -- | CI38: =+CI36/CG36-1 -> 0.0061028125 | CJ38: =+CJ36/CI36-1 -> 0.026757484 | CK38: =+CK36/CJ36-1 -> 0.011578636 | CL38: =+CL36/CK36-1 -> 0.011140961 | CM38: --
A39: % of total (check) | K39: =K36/IS!K7 -> 1 | P39: =P36/IS!P7 -> 1 | U39: =U36/IS!U7 -> 1 | Z39: =Z36/IS!Z7 -> 1.0000562 | AE39: =AE36/IS!AE7 -> 1 | AJ39: =AJ36/IS!AJ7 -> 1 | AK39: =AK36/IS!AK7 -> 1 | AL39: =AL36/IS!AL7 -> 1 | AM39: =AM36/IS!AM7 -> 1 | AN39: =AN36/IS!AN7 -> 1 | AO39: =AO36/IS!AO7 -> 1 | AP39: =AP36/IS!AP7 -> 1 | AQ39: =AQ36/IS!AQ7 -> 1 | ... CM39: =CM36/IS!CM7 -> 1
A41: Oncology
A42: Volumes
A43: Guardant 360 Liquid | B43: -- | C43: -- | D43: -- | E43: -- | F43: -- | G43: =+G95 -> 7246 | H43: =+H95 -> 6723 | I43: =+I95 -> 7027 | J43: =+J95 -> 8596 | K43: =+K95 -> 29592 | L43: =+L95 -> 9521 | M43: =+M95 -> 11875 | N43: =+N95 -> 13259 | ... CM43: =+CM95 -> 457800
A44: % yoy | B44: -- | C44: -- | D44: -- | E44: -- | F44: -- | G44: -- | H44: -- | I44: -- | J44: -- | K44: -- | L44: =+L43/G43-1 -> 0.31396633 | M44: =+M43/H43-1 -> 0.76632456 | N44: =+N43/I43-1 -> 0.88686495 | O44: =+O43/J43-1 -> 0.77640763 | P44: =+P43/K43-1 -> 0.68711138 | Q44: =+Q43/L43-1 -> 0.60245773 | R44: =+R43/M43-1 -> 0.15317895 | S44: =+S43/N43-1 -> 0.27837695 | ... CM44: =+CM43/CH43-1 -> 0.051446945
A45: % seq | B45: -- | C45: -- | D45: -- | E45: -- | F45: -- | G45: -- | H45: =+H43/G43-1 -> -0.072177753 | I45: =+I43/H43-1 -> 0.045217909 | J45: =+J43/I43-1 -> 0.22328163 | K45: -- | L45: =+L43/J43-1 -> 0.10760819 | M45: =+M43/L43-1 -> 0.24724294 | N45: =+N43/M43-1 -> 0.11654737 | O45: =+O43/N43-1 -> 0.15167056 | P45: -- | Q45: =+Q43/O43-1 -> -0.0008513425 | R45: =+R43/Q43-1 -> -0.10244478 | S45: =+S43/R43-1 -> 0.23776837 | T45: =+T43/S43-1 -> 0.023775811 | U45: -- | V45: =+V43/T43-1 -> 0.059759119 | W45: =+W43/V43-1 -> 0.1326808 | X45: =+X43/W43-1 -> 0.094863178 | Y45: =+Y43/X43-1 -> 0.12251162 | Z45: -- | AA45: =+AA43/Y43-1 -> -0.019296875 | AB45: =+AB43/AA43-1 -> 0.07352824 | AC45: =+AC43/AB43-1 -> 0.082628376 | AD45: =+AD43/AC43-1 -> 0.070153192 | AE45: -- | AF45: =+AF43/AD43-1 -> 0.0770832 | AG45: =+AG43/AF43-1 -> 0.079297119 | AH45: =+AH43/AG43-1 -> -0.022066116 | AI45: =+AI43/AH43-1 -> 0.036170033 | AJ45: -- | AK45: =+AK43/AI43-1 -> 0.0399913 | AL45: =+AL43/AK43-1 -> 0.019736498 | AM45: =+AM43/AL43-1 -> 0.063728883 | AN45: =+AN43/AM43-1 -> 0.048078082 | AO45: -- | AP45: =+AP43/AN43-1 -> 0.01922281 | AQ45: =+AQ43/AP43-1 -> 0.052835807 | AR45: =+AR43/AQ43-1 -> 0.16452387 | AS45: =+AS43/AR43-1 -> 0.064365363 | AT45: -- | AU45: =+AU43/AS43-1 -> -0.062132633 | AV45: =+AV43/AU43-1 -> 0.096774194 | AW45: =+AW43/AV43-1 -> 0.058823529 | AX45: =+AX43/AW43-1 -> 0.055555556 | AY45: -- | AZ45: =+AZ43/AX43-1 -> 0.026315789 | BA45: =+BA43/AZ43-1 -> 0.012820513 | BB45: =+BB43/BA43-1 -> 0.012658228 | BC45: =+BC43/BB43-1 -> 0.025 | BD45: -- | BE45: =+BE43/BC43-1 -> 0.024390244 | BF45: =+BF43/BE43-1 -> 0.023809524 | BG45: =+BG43/BF43-1 -> 0.023255814 | BH45: =+BH43/BG43-1 -> 0.022727273 | BI45: -- | BJ45: =+BJ43/BH43-1 -> 0.022222222 | BK45: =+BK43/BJ43-1 -> 0.02173913 | BL45: =+BL43/BK43-1 -> 0.021276596 | BM45: =+BM43/BL43-1 -> 0.020833333 | BN45: -- | BO45: =+BO43/BM43-1 -> 0.020408163 | BP45: =+BP43/BO43-1 -> 0.02 | BQ45: =+BQ43/BP43-1 -> 0.019607843 | BR45: =+BR43/BQ43-1 -> 0.019230769 | BS45: -- | BT45: =+BT43/BR43-1 -> 0.018867925 | BU45: =+BU43/BT43-1 -> 0.018518519 | BV45: =+BV43/BU43-1 -> 0.018181818 | BW45: =+BW43/BV43-1 -> 0.017857143 | BX45: -- | BY45: =+BY43/BW43-1 -> 0.014035088 | BZ45: =+BZ43/BY43-1 -> 0.01384083 | CA45: =+CA43/BZ43-1 -> 0.013651877 | CB45: =+CB43/CA43-1 -> 0.013468013 | CC45: -- | CD45: =+CD43/CB43-1 -> 0.013289037 | CE45: =+CE43/CD43-1 -> 0.013114754 | CF45: =+CF43/CE43-1 -> 0.012944984 | CG45: =+CG43/CF43-1 -> 0.012779553 | CH45: -- | CI45: =+CI43/CG43-1 -> 0.012618297 | CJ45: =+CJ43/CI43-1 -> 0.012461059 | CK45: =+CK43/CJ43-1 -> 0.012307692 | CL45: =+CL43/CK43-1 -> 0.012158055 | CM45: --
A46: Guardant 360 Tissue | B46: -- | C46: -- | D46: -- | E46: -- | F46: -- | G46: =+G111 -> -- | H46: =+H111 -> -- | I46: =+I111 -> -- | J46: =+J111 -> -- | K46: =+K111 -> -- | L46: =+L111 -> -- | M46: =+M111 -> -- | N46: =+N111 -> -- | ... CM46: =+CM111 -> 60170.983
A47: % yoy | B47: -- | C47: -- | D47: -- | E47: -- | F47: -- | G47: -- | H47: -- | I47: -- | J47: -- | K47: -- | L47: -- | M47: -- | N47: -- | O47: -- | P47: -- | Q47: -- | R47: -- | S47: -- | T47: -- | U47: -- | V47: -- | W47: -- | X47: -- | Y47: -- | Z47: -- | AA47: -- | AB47: -- | AC47: -- | AD47: -- | AE47: -- | AF47: =+AF46/AA46-1 -> 1.9210526 | AG47: =+AG46/AB46-1 -> 1.8157248 | AH47: =+AH46/AC46-1 -> 1.6878613 | AI47: =+AI46/AD46-1 -> 0.69327252 | AJ47: =+AJ46/AE46-1 -> 1.3426573 | AK47: =+AK46/AF46-1 -> 0.96196196 | AL47: =+AL46/AG46-1 -> 1.0724258 | AM47: =+AM46/AH46-1 -> 0.89964158 | ... CM47: =+CM46/CH46-1 -> 0.12
A48: % seq | B48: -- | C48: -- | D48: -- | E48: -- | F48: -- | G48: -- | H48: -- | I48: -- | J48: -- | K48: -- | L48: -- | M48: -- | N48: -- | O48: -- | P48: -- | Q48: -- | R48: -- | S48: -- | T48: -- | U48: -- | V48: -- | W48: -- | X48: -- | Y48: -- | Z48: -- | AA48: -- | AB48: -- | AC48: -- | AD48: -- | AE48: -- | AF48: =+AF46/AD46-1 -> 0.1391106 | AG48: =+AG46/AF46-1 -> 0.14714715 | AH48: =+AH46/AG46-1 -> 0.21727749 | AI48: =+AI46/AH46-1 -> 0.064516129 | AJ48: -- | AK48: =+AK46/AI46-1 -> 0.31986532 | AL48: =+AL46/AK46-1 -> 0.21173469 | AM48: =+AM46/AL46-1 -> 0.11578947 | AN48: =+AN46/AM46-1 -> 0.14150943 | AO48: -- | AP48: =+AP46/AN46-1 -> 0.060495868 | AQ48: =+AQ46/AP46-1 -> 0.091022444 | AR48: =+AR46/AQ46-1 -> 0.064285714 | AS48: =+AS46/AR46-1 -> 0.16885906 | AT48: -- | AU48: =+AU46/AS46-1 -> 0.04931141 | AV48: =+AV46/AU46-1 -> 0.047975143 | AW48: =+AW46/AV46-1 -> -0.0022902133 | AX48: =+AX46/AW46-1 -> 0.12081683 | AY48: -- | AZ48: =+AZ46/AX46-1 -> 0.049428914 | BA48: =+BA46/AZ46-1 -> 0.040054001 | BB48: =+BB46/BA46-1 -> -0.02794194 | BC48: =+BC46/BB46-1 -> 0.11036382 | BD48: -- | BE48: =+BE46/BC46-1 -> 0.04624045 | BF48: =+BF46/BE46-1 -> 0.037020298 | BG48: =+BG46/BF46-1 -> -0.030666401 | BH48: =+BH46/BG46-1 -> 0.10737093 | BI48: -- | BJ48: =+BJ46/BH46-1 -> 0.033104366 | BK48: =+BK46/BJ46-1 -> 0.037020298 | BL48: =+BL46/BK46-1 -> -0.030666401 | BM48: =+BM46/BL46-1 -> 0.10737093 | BN48: -- | BO48: =+BO46/BM46-1 -> 0.033104366 | BP48: =+BP46/BO46-1 -> 0.037020298 | BQ48: =+BQ46/BP46-1 -> -0.030666401 | BR48: =+BR46/BQ46-1 -> 0.10737093 | BS48: -- | BT48: =+BT46/BR46-1 -> 0.033104366 | BU48: =+BU46/BT46-1 -> 0.037020298 | BV48: =+BV46/BU46-1 -> -0.030666401 | BW48: =+BW46/BV46-1 -> 0.10737093 | BX48: -- | BY48: =+BY46/BW46-1 -> 0.02412085 | BZ48: =+BZ46/BY46-1 -> 0.037020298 | CA48: =+CA46/BZ46-1 -> -0.030666401 | CB48: =+CB46/CA46-1 -> 0.10737093 | CC48: -- | CD48: =+CD46/CB46-1 -> 0.015137333 | CE48: =+CE46/CD46-1 -> 0.037020298 | CF48: =+CF46/CE46-1 -> -0.030666401 | CG48: =+CG46/CF46-1 -> 0.10737093 | CH48: -- | CI48: =+CI46/CG46-1 -> 0.0061538172 | CJ48: =+CJ46/CI46-1 -> 0.037020298 | CK48: =+CK46/CJ46-1 -> -0.030666401 | CL48: =+CL46/CK46-1 -> 0.10737093 | CM48: --
A49: Guardant Reveal | B49: -- | C49: -- | D49: -- | E49: -- | F49: -- | G49: =+G136 -> -- | H49: =+H136 -> -- | I49: =+I136 -> -- | J49: =+J136 -> -- | K49: =+K136 -> -- | L49: =+L136 -> -- | M49: =+M136 -> -- | N49: =+N136 -> -- | ... CM49: =+CM136 -> 632286.76
A50: % yoy | B50: -- | C50: -- | D50: -- | E50: -- | F50: -- | G50: -- | H50: -- | I50: -- | J50: -- | K50: -- | L50: -- | M50: -- | N50: -- | O50: -- | P50: -- | Q50: -- | R50: -- | S50: -- | T50: -- | U50: -- | V50: -- | W50: -- | X50: -- | Y50: -- | Z50: -- | AA50: -- | AB50: -- | AC50: -- | AD50: -- | AE50: -- | AF50: =+AF49/AA49-1 -> 1.4213075 | AG50: =+AG49/AB49-1 -> 1.8335909 | AH50: =+AH49/AC49-1 -> 1.3582531 | AI50: =+AI49/AD49-1 -> 1.0751494 | AJ50: =+AJ49/AE49-1 -> 1.3615416 | AK50: =+AK49/AF49-1 -> 0.5 | AL50: =+AL49/AG49-1 -> 0.31145455 | AM50: =+AM49/AH49-1 -> 0.2405838 | ... CM50: =+CM49/CH49-1 -> 0.087093595
A51: % seq | B51: -- | C51: -- | D51: -- | E51: -- | F51: -- | G51: -- | H51: -- | I51: -- | J51: -- | K51: -- | L51: -- | M51: -- | N51: -- | O51: -- | P51: -- | Q51: -- | R51: -- | S51: -- | T51: -- | U51: -- | V51: -- | W51: -- | X51: -- | Y51: -- | Z51: -- | AA51: -- | AB51: =+AB49/AA49-1 -> 0.17493947 | AC51: =+AC49/AB49-1 -> 0.39206595 | AD51: =+AD49/AC49-1 -> 0.30014804 | AE51: -- | AF51: =+AF49/AD49-1 -> 0.13862795 | AG51: =+AG49/AF49-1 -> 0.375 | AH51: =+AH49/AG49-1 -> 0.15854545 | AI51: =+AI49/AH49-1 -> 0.1440678 | AJ51: -- | AK51: =+AK49/AI49-1 -> -0.17695473 | AL51: =+AL49/AK49-1 -> 0.20216667 | AM51: =+AM49/AL49-1 -> 0.09593789 | AN51: =+AN49/AM49-1 -> 0.19797596 | AO51: -- | AP51: =+AP49/AN49-1 -> 0.11203801 | AQ51: =+AQ49/AP49-1 -> 0.20881208 | AR51: =+AR49/AQ49-1 -> 0.13904163 | AS51: =+AS49/AR49-1 -> 0.04137931 | AT51: -- | AU51: =+AU49/AS49-1 -> 0.26177973 | AV51: =+AV49/AU49-1 -> 0.18344885 | AW51: =+AW49/AV49-1 -> 0.155357 | AX51: =+AX49/AW49-1 -> 0.13353093 | AY51: -- | AZ51: =+AZ49/AX49-1 -> 0.25889621 | BA51: =+BA49/AZ49-1 -> 0.18157853 | BB51: =+BB49/BA49-1 -> 0.15401907 | BC51: =+BC49/BB49-1 -> 0.13252777 | BD51: -- | BE51: =+BE49/BC49-1 -> 0.14334298 | BF51: =+BF49/BE49-1 -> 0.098863852 | BG51: =+BG49/BF49-1 -> 0.090294664 | BH51: =+BH49/BG49-1 -> 0.081896453 | BI51: -- | BJ51: =+BJ49/BH49-1 -> 0.047141971 | BK51: =+BK49/BJ49-1 -> 0.016076405 | BL51: =+BL49/BK49-1 -> 0.01612541 | BM51: =+BM49/BL49-1 -> 0.014969201 | BN51: -- | BO51: =+BO49/BM49-1 -> 0.072445152 | BP51: =+BP49/BO49-1 -> 0.039291016 | BQ51: =+BQ49/BP49-1 -> 0.038115527 | BR51: =+BR49/BQ49-1 -> 0.035809542 | BS51: -- | BT51: =+BT49/BR49-1 -> 0.012201059 | BU51: =+BU49/BT49-1 -> 0.035776753 | BV51: =+BV49/BU49-1 -> 0.034849946 | BW51: =+BW49/BV49-1 -> 0.032770703 | BX51: -- | BY51: =+BY49/BW49-1 -> 0.013663578 | BZ51: =+BZ49/BY49-1 -> 0.032839524 | CA51: =+CA49/BZ49-1 -> 0.032103516 | CB51: =+CB49/CA49-1 -> 0.030200081 | CC51: -- | CD51: =+CD49/CB49-1 -> -0.0043427607 | CE51: =+CE49/CD49-1 -> 0.030934745 | CF51: =+CF49/CE49-1 -> 0.030314104 | CG51: =+CG49/CF49-1 -> 0.028517842 | CH51: -- | CI51: =+CI49/CG49-1 -> -0.0025036225 | CJ51: =+CJ49/CI49-1 -> 0.029238816 | CK51: =+CK49/CJ49-1 -> 0.02871532 | CL51: =+CL49/CK49-1 -> 0.027009863 | CM51: --
A52: Guardant 360 Response | B52: -- | C52: -- | D52: -- | E52: -- | F52: -- | G52: =+G157 -> -- | H52: =+H157 -> -- | I52: =+I157 -> -- | J52: =+J157 -> -- | K52: =+K157 -> -- | L52: =+L157 -> -- | M52: =+M157 -> -- | N52: =+N157 -> -- | ... CM52: =+CM157 -> 63507.535
A53: % yoy | B53: -- | C53: -- | D53: -- | E53: -- | F53: -- | G53: -- | H53: -- | I53: -- | J53: -- | K53: -- | L53: -- | M53: -- | N53: -- | O53: -- | P53: -- | Q53: -- | R53: -- | S53: -- | T53: -- | U53: -- | V53: -- | W53: -- | X53: -- | Y53: -- | Z53: -- | AA53: -- | AB53: -- | AC53: -- | AD53: -- | AE53: -- | AF53: -- | AG53: -- | AH53: -- | AI53: =+AI52/AD52-1 -> 1.1927083 | AJ53: =+AJ52/AE52-1 -> 5.5052083 | AK53: =+AK52/AF52-1 -> 0.46581197 | AL53: =+AL52/AG52-1 -> 0.44945848 | AM53: =+AM52/AH52-1 -> 0.65615142 | AN53: =+AN52/AI52-1 -> 0.56175772 | AO53: =+AO52/AJ52-1 -> 0.54283427 | AP53: =+AP52/AK52-1 -> 0.36297376 | ... CM53: =+CM52/CH52-1 -> 0.1629534
A54: % seq | B54: -- | C54: -- | D54: -- | E54: -- | F54: -- | G54: -- | H54: -- | I54: -- | J54: -- | K54: -- | L54: -- | M54: -- | N54: -- | O54: -- | P54: -- | Q54: -- | R54: -- | S54: -- | T54: -- | U54: -- | V54: -- | W54: -- | X54: -- | Y54: -- | Z54: -- | AA54: -- | AB54: -- | AC54: -- | AD54: -- | AE54: -- | AF54: =+AF52/AD52-1 -> 0.21875 | AG54: =+AG52/AF52-1 -> 0.18376068 | AH54: =+AH52/AG52-1 -> 0.14440433 | AI54: =+AI52/AH52-1 -> 0.32807571 | AJ54: -- | AK54: =+AK52/AI52-1 -> -0.18527316 | AL54: =+AL52/AK52-1 -> 0.17055394 | AM54: =+AM52/AL52-1 -> 0.30759651 | AN54: =+AN52/AM52-1 -> 0.25238095 | AO54: -- | AP54: =+AP52/AN52-1 -> -0.28897338 | AQ54: =+AQ52/AP52-1 -> 0.17860963 | AR54: =+AR52/AQ52-1 -> 0.29673321 | AS54: =+AS52/AR52-1 -> 0.19104269 | AT54: -- | AU54: =+AU52/AS52-1 -> 0.11138077 | AV54: =+AV52/AU52-1 -> -0.22325369 | AW54: =+AW52/AV52-1 -> 0.38169298 | AX54: =+AX52/AW52-1 -> -0.20802135 | AY54: -- | AZ54: =+AZ52/AX52-1 -> 0.25948546 | BA54: =+BA52/AZ52-1 -> 0.18220572 | BB54: =+BB52/BA52-1 -> 0.15412353 | BC54: =+BC52/BB52-1 -> 0.13354163 | BD54: -- | BE54: =+BE52/BC52-1 -> 0.15134347 | BF54: =+BF52/BE52-1 -> 0.10539294 | BG54: =+BG52/BF52-1 -> 0.095344319 | BH54: =+BH52/BG52-1 -> 0.087045067 | BI54: -- | BJ54: =+BJ52/BH52-1 -> 0.11247719 | BK54: =+BK52/BJ52-1 -> 0.074138317 | BL54: =+BL52/BK52-1 -> 0.069021201 | BM54: =+BM52/BL52-1 -> 0.064564857 | BN54: -- | BO54: =+BO52/BM52-1 -> 0.092468531 | BP54: =+BP52/BO52-1 -> 0.057181081 | BQ54: =+BQ52/BP52-1 -> 0.054088256 | BR54: =+BR52/BQ52-1 -> 0.051312834 | BS54: -- | BT54: =+BT52/BR52-1 -> 0.08027259 | BU54: =+BU52/BT52-1 -> 0.046536949 | BV54: =+BV52/BU52-1 -> 0.044467564 | BW54: =+BW52/BV52-1 -> 0.042574385 | BX54: -- | BY54: =+BY52/BW52-1 -> 0.072060899 | BZ54: =+BZ52/BY52-1 -> 0.039233685 | CA54: =+CA52/BZ52-1 -> 0.037752515 | CB54: =+CB52/CA52-1 -> 0.036379112 | CC54: -- | CD54: =+CD52/CB52-1 -> 0.066155191 | CE54: =+CE52/CD52-1 -> 0.033911753 | CF54: =+CF52/CE52-1 -> 0.032799465 | CG54: =+CG52/CF52-1 -> 0.031757826 | CH54: -- | CI54: =+CI52/CG52-1 -> 0.061703719 | CJ54: =+CJ52/CI52-1 -> 0.029861174 | CK54: =+CK52/CJ52-1 -> 0.028995339 | CL54: =+CL52/CK52-1 -> 0.0281783 | CM54: --
A55: Oncology Volumes | B55: -- | C55: -- | D55: -- | E55: -- | F55: -- | G55: 7246 | H55: 6723 | I55: 7027 | J55: 8596 | K55: =+G55+H55+I55+J55 -> 29592 | L55: 9521 | M55: 11875 | N55: 13259 | O55: 15270 | P55: =+L55+M55+N55+O55 -> 49925 | Q55: 15257 | R55: 13694 | S55: 16950 | T55: 17353 | U55: =+Q55+R55+S55+T55 -> 63254 | V55: 18390 | W55: 20830 | X55: 22806 | Y55: 25600 | Z55: =+V55+W55+X55+Y55 -> 87626 | AA55: 27100 | AB55: 29300 | AC55: 32400 | AD55: 36000 | AE55: =+AA55+AB55+AC55+AD55 -> 124800 | AF55: 39100 | AG55: 43500 | AH55: 43900 | AI55: 46400 | AJ55: =+AF55+AG55+AH55+AI55 -> 172900 | AK55: 46900 | AL55: 49400 | AM55: 53100 | AN55: 57300 | AO55: =+AK55+AL55+AM55+AN55 -> 206700 | AP55: 59000 | AQ55: 64000 | AR55: 74000 | AS55: 79000 | AT55: =+AT95+AT111+AT136+AT157 -> 276000 | AU55: =+AU95+AU111+AU136+AU157 -> 79763.146 | AV55: =+AV95+AV111+AV136+AV157 -> 88305.258 | AW55: =+AW95+AW111+AW136+AW157 -> 95858.108 | AX55: =+AX95+AX111+AX136+AX157 -> 102991.57 | AY55: =+AY95+AY111+AY136+AY157 -> 366918.08 | AZ55: =+AZ95+AZ111+AZ136+AZ157 -> 113068.55 | BA55: =+BA95+BA111+BA136+BA157 -> 121287.72 | ... CM55: =+CM95+CM111+CM136+CM157 -> 1213765.3
A56: % yoy | B56: -- | C56: -- | D56: -- | E56: -- | F56: -- | G56: -- | H56: -- | I56: -- | J56: -- | K56: -- | L56: =+L55/G55-1 -> 0.31396633 | M56: =+M55/H55-1 -> 0.76632456 | N56: =+N55/I55-1 -> 0.88686495 | O56: =+O55/J55-1 -> 0.77640763 | P56: =+P55/K55-1 -> 0.68711138 | Q56: =+Q55/L55-1 -> 0.60245773 | R56: =+R55/M55-1 -> 0.15317895 | S56: =+S55/N55-1 -> 0.27837695 | ... CM56: =+CM55/CH55-1 -> 0.07855407
A57: % seq | B57: -- | C57: -- | D57: -- | E57: -- | F57: -- | G57: -- | H57: =+H55/G55-1 -> -0.072177753 | I57: =+I55/H55-1 -> 0.045217909 | J57: =+J55/I55-1 -> 0.22328163 | K57: -- | L57: =+L55/J55-1 -> 0.10760819 | M57: =+M55/L55-1 -> 0.24724294 | N57: =+N55/M55-1 -> 0.11654737 | O57: =+O55/N55-1 -> 0.15167056 | P57: -- | Q57: =+Q55/O55-1 -> -0.0008513425 | R57: =+R55/Q55-1 -> -0.10244478 | S57: =+S55/R55-1 -> 0.23776837 | T57: =+T55/S55-1 -> 0.023775811 | U57: -- | V57: =+V55/T55-1 -> 0.059759119 | W57: =+W55/V55-1 -> 0.1326808 | X57: =+X55/W55-1 -> 0.094863178 | Y57: =+Y55/X55-1 -> 0.12251162 | Z57: -- | AA57: =+AA55/Y55-1 -> 0.05859375 | AB57: =+AB55/AA55-1 -> 0.081180812 | AC57: =+AC55/AB55-1 -> 0.10580205 | AD57: =+AD55/AC55-1 -> 0.11111111 | AE57: -- | AF57: =+AF55/AD55-1 -> 0.086111111 | AG57: =+AG55/AF55-1 -> 0.11253197 | AH57: =+AH55/AG55-1 -> 0.0091954023 | AI57: =+AI55/AH55-1 -> 0.056947608 | AJ57: -- | AK57: =+AK55/AI55-1 -> 0.010775862 | AL57: =+AL55/AK55-1 -> 0.053304904 | AM57: =+AM55/AL55-1 -> 0.074898785 | AN57: =+AN55/AM55-1 -> 0.079096045 | AO57: -- | AP57: =+AP55/AN55-1 -> 0.029668412 | AQ57: =+AQ55/AP55-1 -> 0.084745763 | AR57: =+AR55/AQ55-1 -> 0.15625 | AS57: =+AS55/AR55-1 -> 0.067567568 | AT57: -- | AU57: =+AU55/AS55-1 -> 0.0096600736 | AV57: =+AV55/AU55-1 -> 0.10709347 | AW57: =+AW55/AV55-1 -> 0.085531149 | AX57: =+AX55/AW55-1 -> 0.074416877 | AY57: -- | AZ57: =+AZ55/AX55-1 -> 0.09784274 | BA57: =+BA55/AZ55-1 -> 0.07269194 | BB57: =+BB55/BA55-1 -> 0.064688897 | BC57: =+BC55/BB55-1 -> 0.073286493 | BD57: -- | BE57: =+BE55/BC55-1 -> 0.077524558 | BF57: =+BF55/BE55-1 -> 0.059350169 | BG57: =+BG55/BF55-1 -> 0.053302786 | BH57: =+BH55/BG55-1 -> 0.055704631 | BI57: -- | BJ57: =+BJ55/BH55-1 -> 0.037163232 | BK57: =+BK55/BJ55-1 -> 0.021126 | BL57: =+BL55/BK55-1 -> 0.018033072 | BM57: =+BM55/BL55-1 -> 0.022867802 | BN57: -- | BO57: =+BO55/BM55-1 -> 0.048398659 | BP57: =+BP55/BO55-1 -> 0.03151502 | BQ57: =+BQ55/BP55-1 -> 0.027843179 | BR57: =+BR55/BQ55-1 -> 0.032289692 | BS57: -- | BT57: =+BT55/BR55-1 -> 0.01841678 | BU57: =+BU55/BT55-1 -> 0.029061713 | BV57: =+BV55/BU55-1 -> 0.025435737 | BW57: =+BW55/BV55-1 -> 0.030207214 | BX57: -- | BY57: =+BY55/BW55-1 -> 0.016697446 | BZ57: =+BZ55/BY55-1 -> 0.025639551 | CA57: =+CA55/BZ55-1 -> 0.02209215 | CB57: =+CB55/CA55-1 -> 0.027234158 | CC57: -- | CD57: =+CD55/CB55-1 -> 0.0066440227 | CE57: =+CE55/CD55-1 -> 0.024363565 | CF57: =+CF55/CE55-1 -> 0.020744662 | CG57: =+CG55/CF55-1 -> 0.026213819 | CH57: -- | CI57: =+CI55/CG55-1 -> 0.0068332503 | CJ57: =+CJ55/CI55-1 -> 0.023231647 | CK57: =+CK55/CJ55-1 -> 0.019544782 | CL57: =+CL55/CK55-1 -> 0.025305922 | CM57: --
A59: ASPs
A60: Guardant 360 Liquid | B60: -- | C60: -- | D60: -- | E60: -- | F60: -- | G60: =+G102 -> 979.85095 | H60: =+H102 -> 1413.0596 | I60: =+I102 -> 1366.1591 | J60: =+J102 -> 1977.664 | K60: =+K102 -> 1459.854 | L60: =+L102 -> 1806.5329 | M60: =+M102 -> 1835.7895 | N60: =+N102 -> 2322.9504 | ... CM60: =+CM102 -> 3216.3397
A61: % yoy | B61: -- | C61: -- | D61: -- | E61: -- | F61: -- | G61: -- | H61: -- | I61: -- | J61: -- | K61: -- | L61: =+L60/G60-1 -> 0.84368135 | M61: =+M60/H60-1 -> 0.29915922 | N61: =+N60/I60-1 -> 0.70035133 | O61: =+O60/J60-1 -> 0.036460572 | P61: =+P60/K60-1 -> 0.38715073 | Q61: =+Q60/L60-1 -> 0.37869617 | R61: =+R60/M60-1 -> 0.57522279 | S61: =+S60/N60-1 -> 0.22669751 | ... CM61: =+CM60/CH60-1 -> 1.6151164e-05
A62: % seq | B62: -- | C62: -- | D62: -- | E62: -- | F62: -- | G62: -- | H62: =+H60/G60-1 -> 0.44211693 | I62: =+I60/H60-1 -> -0.033190775 | J62: =+J60/I60-1 -> 0.44760887 | K62: -- | L62: =+L60/J60-1 -> -0.086531939 | M62: =+M60/L60-1 -> 0.016194859 | N62: =+N60/M60-1 -> 0.26536865 | O62: =+O60/N60-1 -> -0.11760029 | P62: -- | Q62: =+Q60/O60-1 -> 0.21509197 | R62: =+R60/Q60-1 -> 0.16104863 | S62: =+S60/R60-1 -> -0.014599982 | T62: =+T60/S60-1 -> -0.071759121 | U62: -- | V62: =+V60/T60-1 -> 0.023786727 | W62: =+W60/V60-1 -> 0.0814164 | X62: =+X60/W60-1 -> -0.08215195 | Y62: =+Y60/X60-1 -> -0.065542287 | Z62: -- | AA62: =+AA60/Y60-1 -> 0.040292116 | AB62: =+AB60/AA60-1 -> -0.0074329295 | AC62: =+AC60/AB60-1 -> 0.014856501 | AD62: =+AD60/AC60-1 -> -0.003501314 | AE62: -- | AF62: =+AF60/AD60-1 -> 0.0021185731 | AG62: =+AG60/AF60-1 -> 0.0072333682 | AH62: =+AH60/AG60-1 -> 0.04597339 | AI62: =+AI60/AH60-1 -> 0.012218148 | AJ62: -- | AK62: =+AK60/AI60-1 -> 0.11353698 | AL62: =+AL60/AK60-1 -> 0.0051245688 | AM62: =+AM60/AL60-1 -> 0.016502481 | AN62: =+AN60/AM60-1 -> -0.026397202 | AO62: -- | AP62: =+AP60/AN60-1 -> 0.0020394481 | AQ62: =+AQ60/AP60-1 -> -0.017893489 | AR62: =+AR60/AQ60-1 -> 0.00093814948 | AS62: =+AS60/AR60-1 -> -0.041090768 | AT62: -- | AU62: =+AU60/AS60-1 -> 0.076769412 | AV62: =+AV60/AU60-1 -> -0.027569415 | AW62: =+AW60/AV60-1 -> 0.00093814948 | AX62: =+AX60/AW60-1 -> -0.041090768 | AY62: -- | AZ62: =+AZ60/AX60-1 -> 0.098197659 | BA62: =+BA60/AZ60-1 -> -0.027569415 | BB62: =+BB60/BA60-1 -> 0.00093814948 | BC62: =+BC60/BB60-1 -> -0.041090768 | BD62: -- | BE62: =+BE60/BC60-1 -> 0.098197659 | BF62: =+BF60/BE60-1 -> -0.027569415 | BG62: =+BG60/BF60-1 -> 0.00093814948 | BH62: =+BH60/BG60-1 -> -0.041090768 | BI62: -- | BJ62: =+BJ60/BH60-1 -> 0.07141235 | BK62: =+BK60/BJ60-1 -> -0.027569415 | BL62: =+BL60/BK60-1 -> 0.00093814948 | BM62: =+BM60/BL60-1 -> -0.041090768 | BN62: -- | BO62: =+BO60/BM60-1 -> 0.07141235 | BP62: =+BP60/BO60-1 -> -0.027569415 | BQ62: =+BQ60/BP60-1 -> 0.00093814948 | BR62: =+BR60/BQ60-1 -> -0.041090768 | BS62: -- | BT62: =+BT60/BR60-1 -> 0.07141235 | BU62: =+BU60/BT60-1 -> -0.027569415 | BV62: =+BV60/BU60-1 -> 0.00093814948 | BW62: =+BW60/BV60-1 -> -0.041090768 | BX62: -- | BY62: =+BY60/BW60-1 -> 0.07141235 | BZ62: =+BZ60/BY60-1 -> -0.027569415 | CA62: =+CA60/BZ60-1 -> 0.00093814948 | CB62: =+CB60/CA60-1 -> -0.041090768 | CC62: -- | CD62: =+CD60/CB60-1 -> 0.07141235 | CE62: =+CE60/CD60-1 -> -0.027569415 | CF62: =+CF60/CE60-1 -> 0.00093814948 | CG62: =+CG60/CF60-1 -> -0.041090768 | CH62: -- | CI62: =+CI60/CG60-1 -> 0.07141235 | CJ62: =+CJ60/CI60-1 -> -0.027569415 | CK62: =+CK60/CJ60-1 -> 0.00093814948 | CL62: =+CL60/CK60-1 -> -0.041090768 | CM62: --
A63: Guardant 360 Tissue | B63: -- | C63: -- | D63: -- | E63: -- | F63: -- | G63: =+G115 -> -- | H63: =+H115 -> -- | I63: =+I115 -> -- | J63: =+J115 -> -- | K63: =+K115 -> -- | L63: =+L115 -> -- | M63: =+M115 -> -- | N63: =+N115 -> -- | ... CM63: =+CM115 -> 3000
A64: % yoy | B64: -- | C64: -- | D64: -- | E64: -- | F64: -- | G64: -- | H64: -- | I64: -- | J64: -- | K64: -- | L64: -- | M64: -- | N64: -- | O64: -- | P64: -- | Q64: -- | R64: -- | S64: -- | T64: -- | U64: -- | V64: -- | W64: -- | X64: -- | Y64: -- | Z64: -- | AA64: -- | AB64: -- | AC64: -- | AD64: -- | AE64: -- | AF64: =+AF63/AA63-1 -> 0.65384615 | AG64: =+AG63/AB63-1 -> 0.44661458 | AH64: =+AH63/AC63-1 -> 0.23809524 | AI64: =+AI63/AD63-1 -> 0.16727273 | AJ64: =+AJ63/AE63-1 -> 0.26677401 | AK64: =+AK63/AF63-1 -> 0.30232558 | AL64: =+AL63/AG63-1 -> 0.35013501 | AM64: =+AM63/AH63-1 -> 0.15384615 | ... CM64: =+CM63/CH63-1 -> 0
A65: % seq | B65: -- | C65: -- | D65: -- | E65: -- | F65: -- | G65: -- | H65: -- | I65: -- | J65: -- | K65: -- | L65: -- | M65: -- | N65: -- | O65: -- | P65: -- | Q65: -- | R65: -- | S65: -- | T65: -- | U65: -- | V65: -- | W65: -- | X65: -- | Y65: -- | Z65: -- | AA65: -- | AB65: =+AB63/AA63-1 -> 0.18153846 | AC65: =+AC63/AB63-1 -> 0.3671875 | AD65: =+AD63/AC63-1 -> 0.047619048 | AE65: -- | AF65: =+AF63/AD63-1 -> -0.022727273 | AG65: =+AG63/AF63-1 -> 0.033488372 | AH65: =+AH63/AG63-1 -> 0.17011701 | AI65: =+AI63/AH63-1 -> -0.012307692 | AJ65: -- | AK65: =+AK63/AI63-1 -> 0.090342679 | AL65: =+AL63/AK63-1 -> 0.071428571 | AM65: =+AM63/AL63-1 -> 0 | AN65: =+AN63/AM63-1 -> 0.033333333 | AO65: -- | AP65: =+AP63/AN63-1 -> 0.11612903 | AQ65: =+AQ63/AP63-1 -> 0.15895954 | AR65: =+AR63/AQ63-1 -> -0.0024937656 | AS65: =+AS63/AR63-1 -> 0.025 | AT65: -- | AU65: =+AU63/AS63-1 -> 0.073170732 | AV65: =+AV63/AU63-1 -> 0 | AW65: =+AW63/AV63-1 -> 0 | AX65: =+AX63/AW63-1 -> 0 | AY65: -- | AZ65: =+AZ63/AX63-1 -> 0.13636364 | BA65: =+BA63/AZ63-1 -> 0 | BB65: =+BB63/BA63-1 -> 0 | BC65: =+BC63/BB63-1 -> 0 | BD65: -- | BE65: =+BE63/BC63-1 -> 0.2 | BF65: =+BF63/BE63-1 -> 0 | BG65: =+BG63/BF63-1 -> 0 | BH65: =+BH63/BG63-1 -> 0 | BI65: -- | BJ65: =+BJ63/BH63-1 -> 0 | BK65: =+BK63/BJ63-1 -> 0 | BL65: =+BL63/BK63-1 -> 0 | BM65: =+BM63/BL63-1 -> 0 | BN65: -- | BO65: =+BO63/BM63-1 -> 0 | BP65: =+BP63/BO63-1 -> 0 | BQ65: =+BQ63/BP63-1 -> 0 | BR65: =+BR63/BQ63-1 -> 0 | BS65: -- | BT65: =+BT63/BR63-1 -> 0 | BU65: =+BU63/BT63-1 -> 0 | BV65: =+BV63/BU63-1 -> 0 | BW65: =+BW63/BV63-1 -> 0 | BX65: -- | BY65: =+BY63/BW63-1 -> 0 | BZ65: =+BZ63/BY63-1 -> 0 | CA65: =+CA63/BZ63-1 -> 0 | CB65: =+CB63/CA63-1 -> 0 | CC65: -- | CD65: =+CD63/CB63-1 -> 0 | CE65: =+CE63/CD63-1 -> 0 | CF65: =+CF63/CE63-1 -> 0 | CG65: =+CG63/CF63-1 -> 0 | CH65: -- | CI65: =+CI63/CG63-1 -> 0 | CJ65: =+CJ63/CI63-1 -> 0 | CK65: =+CK63/CJ63-1 -> 0 | CL65: =+CL63/CK63-1 -> 0 | CM65: --
A66: Guardant Reveal | B66: -- | C66: -- | D66: -- | E66: -- | F66: -- | G66: =+G143 -> -- | H66: =+H143 -> -- | I66: =+I143 -> -- | J66: =+J143 -> -- | K66: =+K143 -> -- | L66: =+L143 -> -- | M66: =+M143 -> -- | N66: =+N143 -> -- | ... T66: =+T143 -> 0 | U66: -- | V66: =+V143 -> 0 | W66: =+W143 -> 0 | X66: =+X143 -> 0 | Y66: =+Y143 -> 0 | Z66: -- | AA66: =+AA143 -> 295 | AB66: =+AB143 -> 340 | AC66: =+AC143 -> 320 | AD66: =+AD143 -> 390 | AE66: =+AE143 -> 344.81954 | AF66: =+AF143 -> 430 | AG66: =+AG143 -> 453 | AH66: =+AH143 -> 450 | ... CM66: =+CM143 -> 1223.024
A67: % yoy | B67: -- | C67: -- | D67: -- | E67: -- | F67: -- | G67: -- | H67: -- | I67: -- | J67: -- | K67: -- | L67: -- | M67: -- | N67: -- | O67: -- | P67: -- | Q67: -- | R67: -- | S67: -- | T67: -- | U67: -- | V67: -- | W67: -- | X67: -- | Y67: -- | Z67: -- | AA67: -- | AB67: -- | AC67: -- | AD67: -- | AE67: -- | AF67: -- | AG67: =+AG66/AB66-1 -> 0.33235294 | AH67: =+AH66/AC66-1 -> 0.40625 | AI67: =+AI66/AD66-1 -> 0.17948718 | AJ67: =+AJ66/AE66-1 -> 0.30620743 | AK67: =+AK66/AF66-1 -> 0.1627907 | AL67: =+AL66/AG66-1 -> 0.10375276 | AM67: =+AM66/AH66-1 -> 0.11111111 | AN67: =+AN66/AI66-1 -> 0.086956522 | ... CM67: =+CM66/CH66-1 -> 0.020842892
A68: % seq | B68: -- | C68: -- | D68: -- | E68: -- | F68: -- | G68: -- | H68: -- | I68: -- | J68: -- | K68: -- | L68: -- | M68: -- | N68: -- | O68: -- | P68: -- | Q68: -- | R68: -- | S68: -- | T68: -- | U68: -- | V68: -- | W68: -- | X68: -- | Y68: -- | Z68: -- | AA68: -- | AB68: -- | AC68: =+AC66/AB66-1 -> -0.058823529 | AD68: =+AD66/AC66-1 -> 0.21875 | AE68: -- | AF68: =+AF66/AD66-1 -> 0.1025641 | AG68: =+AG66/AF66-1 -> 0.053488372 | AH68: =+AH66/AG66-1 -> -0.0066225166 | AI68: =+AI66/AH66-1 -> 0.022222222 | AJ68: -- | AK68: =+AK66/AI66-1 -> 0.086956522 | AL68: =+AL66/AK66-1 -> 0 | AM68: =+AM66/AL66-1 -> 0 | AN68: =+AN66/AM66-1 -> 0 | AO68: -- | AP68: =+AP66/AN66-1 -> 0.19 | AQ68: =+AQ66/AP66-1 -> 0.067226891 | AR68: =+AR66/AQ66-1 -> 0.023622047 | AS68: =+AS66/AR66-1 -> 0 | AT68: -- | AU68: =+AU66/AS66-1 -> 0.046153846 | AV68: =+AV66/AU66-1 -> 0.014705882 | AW68: =+AW66/AV66-1 -> 0.0072463768 | AX68: =+AX66/AW66-1 -> 0.0071942446 | AY68: -- | AZ68: =+AZ66/AX66-1 -> 0.071428571 | BA68: =+BA66/AZ66-1 -> 0.033333333 | BB68: =+BB66/BA66-1 -> 0.032258065 | BC68: =+BC66/BB66-1 -> 0.0625 | BD68: -- | BE68: =+BE66/BC66-1 -> 0.029411765 | BF68: =+BF66/BE66-1 -> 0.057142857 | BG68: =+BG66/BF66-1 -> 0.027027027 | BH68: =+BH66/BG66-1 -> 0.052631579 | BI68: -- | BJ68: =+BJ66/BH66-1 -> 0.025 | BK68: =+BK66/BJ66-1 -> 0.014634146 | BL68: =+BL66/BK66-1 -> 0.014423077 | BM68: =+BM66/BL66-1 -> 0.014218009 | BN68: -- | BO68: =+BO66/BM66-1 -> 0.0046728972 | BP68: =+BP66/BO66-1 -> 0.013953488 | BQ68: =+BQ66/BP66-1 -> 0.013761468 | BR68: =+BR66/BQ66-1 -> 0.013574661 | BS68: -- | BT68: =+BT66/BR66-1 -> 0.0044642857 | BU68: =+BU66/BT66-1 -> 0.013333333 | BV68: =+BV66/BU66-1 -> 0.013157895 | BW68: =+BW66/BV66-1 -> 0.012987013 | BX68: -- | BY68: =+BY66/BW66-1 -> -0.017094017 | BZ68: =+BZ66/BY66-1 -> 0.013043478 | CA68: =+CA66/BZ66-1 -> 0.012875536 | CB68: =+CB66/CA66-1 -> 0.012711864 | CC68: -- | CD68: =+CD66/CB66-1 -> -0.016736402 | CE68: =+CE66/CD66-1 -> 0.012765957 | CF68: =+CF66/CE66-1 -> 0.012605042 | CG68: =+CG66/CF66-1 -> 0.012448133 | CH68: -- | CI68: =+CI66/CG66-1 -> -0.016393443 | CJ68: =+CJ66/CI66-1 -> 0.0125 | CK68: =+CK66/CJ66-1 -> 0.012345679 | CL68: =+CL66/CK66-1 -> 0.012195122 | CM68: --
A69: Guardant 360 Response | B69: -- | C69: -- | D69: -- | E69: -- | F69: -- | G69: =+G164 -> -- | H69: =+H164 -> -- | I69: =+I164 -> -- | J69: =+J164 -> -- | K69: =+K164 -> -- | L69: =+L164 -> -- | M69: =+M164 -> -- | N69: =+N164 -> -- | ... T69: =+T164 -> 0 | U69: -- | V69: =+V164 -> 0 | W69: =+W164 -> 0 | X69: =+X164 -> 0 | Y69: =+Y164 -> 0 | Z69: -- | AA69: =+AA164 -> 0 | AB69: =+AB164 -> 0 | AC69: =+AC164 -> 0 | AD69: =+AD164 -> 475 | AE69: =+AE164 -> 475 | AF69: =+AF164 -> 775 | AG69: =+AG164 -> 815 | AH69: =+AH164 -> 840 | ... CM69: =+CM164 -> 1055
A70: % yoy | B70: -- | C70: -- | D70: -- | E70: -- | F70: -- | G70: -- | H70: -- | I70: -- | J70: -- | K70: -- | L70: -- | M70: -- | N70: -- | O70: -- | P70: -- | Q70: -- | R70: -- | S70: -- | T70: -- | U70: -- | V70: -- | W70: -- | X70: -- | Y70: -- | Z70: -- | AA70: -- | AB70: -- | AC70: -- | AD70: -- | AE70: -- | AF70: -- | AG70: -- | AH70: -- | AI70: -- | AJ70: -- | AK70: -- | AL70: -- | AM70: -- | AN70: =+AN69/AI69-1 -> 0.041176471 | AO70: =+AO69/AJ69-1 -> 0.080619619 | AP70: =+AP69/AK69-1 -> 0.016949153 | AQ70: =+AQ69/AL69-1 -> 0.0022222222 | AR70: =+AR69/AM69-1 -> 0.027777778 | AS70: =+AS69/AN69-1 -> 0.04519774 | AT70: =+AT69/AO69-1 -> 0.026182762 | AU70: =+AU69/AP69-1 -> 0.083333333 | ... CM70: =+CM69/CH69-1 -> 0.0047619048
A71: % seq | B71: -- | C71: -- | D71: -- | E71: -- | F71: -- | G71: -- | H71: -- | I71: -- | J71: -- | K71: -- | L71: -- | M71: -- | N71: -- | O71: -- | P71: -- | Q71: -- | R71: -- | S71: -- | T71: -- | U71: -- | V71: -- | W71: -- | X71: -- | Y71: -- | Z71: -- | AA71: -- | AB71: -- | AC71: -- | AD71: -- | AE71: -- | AF71: -- | AG71: -- | AH71: -- | AI71: -- | AJ71: -- | AK71: =+AK69/AI69-1 -> 0.041176471 | AL71: =+AL69/AK69-1 -> 0.016949153 | AM71: =+AM69/AL69-1 -> 0 | AN71: =+AN69/AM69-1 -> -0.016666667 | AO71: -- | AP71: =+AP69/AN69-1 -> 0.016949153 | AQ71: =+AQ69/AP69-1 -> 0.0022222222 | AR71: =+AR69/AQ69-1 -> 0.025498891 | AS71: =+AS69/AR69-1 -> 0 | AT71: -- | AU71: =+AU69/AS69-1 -> 0.054054054 | AV71: =+AV69/AU69-1 -> 0 | AW71: =+AW69/AV69-1 -> 0 | AX71: =+AX69/AW69-1 -> 0 | AY71: -- | AZ71: =+AZ69/AX69-1 -> 0.025641026 | BA71: =+BA69/AZ69-1 -> 0 | BB71: =+BB69/BA69-1 -> 0 | BC71: =+BC69/BB69-1 -> 0 | BD71: -- | BE71: =+BE69/BC69-1 -> 0.025 | BF71: =+BF69/BE69-1 -> 0 | BG71: =+BG69/BF69-1 -> 0 | BH71: =+BH69/BG69-1 -> 0 | BI71: -- | BJ71: =+BJ69/BH69-1 -> 0.0048780488 | BK71: =+BK69/BJ69-1 -> 0 | BL71: =+BL69/BK69-1 -> 0 | BM71: =+BM69/BL69-1 -> 0 | BN71: -- | BO71: =+BO69/BM69-1 -> 0.0048543689 | BP71: =+BP69/BO69-1 -> 0 | BQ71: =+BQ69/BP69-1 -> 0 | BR71: =+BR69/BQ69-1 -> 0 | BS71: -- | BT71: =+BT69/BR69-1 -> 0.0048309179 | BU71: =+BU69/BT69-1 -> 0 | BV71: =+BV69/BU69-1 -> 0 | BW71: =+BW69/BV69-1 -> 0 | BX71: -- | BY71: =+BY69/BW69-1 -> 0.0048076923 | BZ71: =+BZ69/BY69-1 -> 0 | CA71: =+CA69/BZ69-1 -> 0 | CB71: =+CB69/CA69-1 -> 0 | CC71: -- | CD71: =+CD69/CB69-1 -> 0.004784689 | CE71: =+CE69/CD69-1 -> 0 | CF71: =+CF69/CE69-1 -> 0 | CG71: =+CG69/CF69-1 -> 0 | CH71: -- | CI71: =+CI69/CG69-1 -> 0.0047619048 | CJ71: =+CJ69/CI69-1 -> 0 | CK71: =+CK69/CJ69-1 -> 0 | CL71: =+CL69/CK69-1 -> 0 | CM71: --
A72: Average Selling Price ($ / test) | B72: -- | C72: -- | D72: -- | E72: -- | F72: -- | G72: =+G89/G55*1000000 -> 979.85095 | H72: =+H89/H55*1000000 -> 1413.0596 | I72: =+I89/I55*1000000 -> 1366.1591 | J72: =+J89/J55*1000000 -> 1977.664 | K72: =+K89/K55*1000000 -> 1459.854 | L72: =+L89/L55*1000000 -> 1806.5329 | M72: =+M89/M55*1000000 -> 1835.7895 | N72: =+N89/N55*1000000 -> 2322.9504 | ... CM72: =+CM89/CM55*1000000 -> 2054.1497
A73: % yoy | B73: -- | C73: -- | D73: -- | E73: -- | F73: -- | G73: -- | H73: -- | I73: -- | J73: -- | K73: -- | L73: =+L72/G72-1 -> 0.84368135 | M73: =+M72/H72-1 -> 0.29915922 | N73: =+N72/I72-1 -> 0.70035133 | O73: =+O72/J72-1 -> 0.036460572 | P73: =+P72/K72-1 -> 0.38715073 | Q73: =+Q72/L72-1 -> 0.37869617 | R73: =+R72/M72-1 -> 0.57522279 | S73: =+S72/N72-1 -> 0.22669751 | ... CM73: =+CM72/CH72-1 -> -0.0017456998
A74: % seq | B74: -- | C74: -- | D74: -- | E74: -- | F74: -- | G74: -- | H74: =+H72/G72-1 -> 0.44211693 | I74: =+I72/H72-1 -> -0.033190775 | J74: =+J72/I72-1 -> 0.44760887 | K74: -- | L74: =+L72/J72-1 -> -0.086531939 | M74: =+M72/L72-1 -> 0.016194859 | N74: =+N72/M72-1 -> 0.26536865 | O74: =+O72/N72-1 -> -0.11760029 | P74: -- | Q74: =+Q72/O72-1 -> 0.21509197 | R74: =+R72/Q72-1 -> 0.16104863 | S74: =+S72/R72-1 -> -0.014599982 | T74: =+T72/S72-1 -> -0.071759121 | U74: -- | V74: =+V72/T72-1 -> 0.023786727 | W74: =+W72/V72-1 -> 0.0814164 | X74: =+X72/W72-1 -> -0.08215195 | Y74: =+Y72/X72-1 -> -0.065542287 | Z74: -- | AA74: =+AA72/Y72-1 -> -0.025826365 | AB74: =+AB72/AA72-1 -> -0.011440416 | AC74: =+AC72/AB72-1 -> -0.0020592232 | AD74: =+AD72/AC72-1 -> -0.028566024 | AE74: -- | AF74: =+AF72/AD72-1 -> -0.0014157091 | AG74: =+AG72/AF72-1 -> -0.015152771 | AH74: =+AH72/AG72-1 -> 0.022469637 | AI74: =+AI72/AH72-1 -> -0.0030387452 | AJ74: -- | AK74: =+AK72/AI72-1 -> 0.14055874 | AL74: =+AL72/AK72-1 -> -0.016473906 | AM74: =+AM72/AL72-1 -> 0.0083628055 | AN74: =+AN72/AM72-1 -> -0.044315419 | AO74: -- | AP74: =+AP72/AN72-1 -> 0.0041744853 | AQ74: =+AQ72/AP72-1 -> -0.028369381 | AR74: =+AR72/AQ72-1 -> 0.0050276385 | AS74: =+AS72/AR72-1 -> -0.035113983 | AT74: -- | AU74: =+AU72/AS72-1 -> 0.022813007 | AV74: =+AV72/AU72-1 -> -0.031940463 | AW74: =+AW72/AV72-1 -> -0.017450163 | AX74: =+AX72/AW72-1 -> -0.045262036 | AY74: -- | AZ74: =+AZ72/AX72-1 -> 0.048872076 | BA74: =+BA72/AZ72-1 -> -0.054545094 | BB74: =+BB72/BA72-1 -> -0.027778859 | BC74: =+BC72/BB72-1 -> -0.046816234 | BD74: -- | BE74: =+BE72/BC72-1 -> 0.059598168 | BF74: =+BF72/BE72-1 -> -0.028906913 | BG74: =+BG72/BF72-1 -> -0.011876783 | BH74: =+BH72/BG72-1 -> -0.03069975 | BI74: -- | BJ74: =+BJ72/BH72-1 -> 0.047518824 | BK74: =+BK72/BJ72-1 -> -0.014723851 | BL74: =+BL72/BK72-1 -> 0.0036951111 | BM74: =+BM72/BL72-1 -> -0.02239005 | BN74: -- | BO74: =+BO72/BM72-1 -> 0.035425674 | BP74: =+BP72/BO72-1 -> -0.019723009 | BQ74: =+BQ72/BP72-1 -> -0.0015533663 | BR74: =+BR72/BQ72-1 -> -0.025783319 | BS74: -- | BT74: =+BT72/BR72-1 -> 0.047578753 | BU74: =+BU72/BT72-1 -> -0.018394409 | BV74: =+BV72/BU72-1 -> -0.00089002693 | BW74: =+BW72/BV72-1 -> -0.024298299 | BX74: -- | BY74: =+BY72/BW72-1 -> 0.038281205 | BZ74: =+BZ72/BY72-1 -> -0.018064614 | CA74: =+CA72/BZ72-1 -> -0.0011184647 | CB74: =+CB72/CA72-1 -> -0.023613222 | CC74: -- | CD74: =+CD72/CB72-1 -> 0.040742624 | CE74: =+CE72/CD72-1 -> -0.017186896 | CF74: =+CF72/CE72-1 -> -0.00075520034 | CG74: =+CG72/CF72-1 -> -0.022551472 | CH74: -- | CI74: =+CI72/CG72-1 -> 0.038824594 | CJ74: =+CJ72/CI72-1 -> -0.016370801 | CK74: =+CK72/CJ72-1 -> -0.00043115805 | CL74: =+CL72/CK72-1 -> -0.021552874 | CM74: --
AT75: =+AT72/AJ72-1 -> 0.058782885
A76: Revenue
A77: Guardant 360 Liquid | B77: -- | C77: -- | D77: -- | E77: -- | F77: -- | G77: =+G106 -> 7.1 | H77: =+H106 -> 9.5 | I77: =+I106 -> 9.6 | J77: =+J106 -> 17 | K77: =+K106 -> 43.2 | L77: =+L106 -> 17.2 | M77: =+M106 -> 21.8 | N77: =+N106 -> 30.8 | ... CM77: =+CM106 -> 1472.4403
A78: % yoy | B78: -- | C78: -- | D78: -- | E78: -- | F78: -- | G78: -- | H78: -- | I78: -- | J78: -- | K78: -- | L78: =+L77/G77-1 -> 1.4225352 | M78: =+M77/H77-1 -> 1.2947368 | N78: =+N77/I77-1 -> 2.2083333 | O78: =+O77/J77-1 -> 0.84117647 | P78: =+P77/K77-1 -> 1.3402778 | Q78: =+Q77/L77-1 -> 1.2093023 | R78: =+R77/M77-1 -> 0.81651376 | S78: =+S77/N77-1 -> 0.56818182 | ... CM78: =+CM77/CH77-1 -> 0.051463927
A79: % seq | B79: -- | C79: -- | D79: -- | E79: -- | F79: -- | G79: -- | H79: =+H77/G77-1 -> 0.33802817 | I79: =+I77/H77-1 -> 0.010526316 | J79: =+J77/I77-1 -> 0.77083333 | K79: -- | L79: =+L77/J77-1 -> 0.011764706 | M79: =+M77/L77-1 -> 0.26744186 | N79: =+N77/M77-1 -> 0.41284404 | O79: =+O77/N77-1 -> 0.016233766 | P79: -- | Q79: =+Q77/O77-1 -> 0.21405751 | R79: =+R77/Q77-1 -> 0.042105263 | S79: =+S77/R77-1 -> 0.21969697 | T79: =+T77/S77-1 -> -0.049689441 | U79: -- | V79: =+V77/T77-1 -> 0.08496732 | W79: =+W77/V77-1 -> 0.2248996 | X79: =+X77/W77-1 -> 0.0049180328 | Y79: =+Y77/X77-1 -> 0.048939641 | Z79: -- | AA79: =+AA77/Y77-1 -> 0.020217729 | AB79: =+AB77/AA77-1 -> 0.06554878 | AC79: =+AC77/AB77-1 -> 0.098712446 | AD79: =+AD77/AC77-1 -> 0.06640625 | AE79: -- | AF79: =+AF77/AD77-1 -> 0.079365079 | AG79: =+AG77/AF77-1 -> 0.087104072 | AH79: =+AH77/AG77-1 -> 0.02289282 | AI79: =+AI77/AH77-1 -> 0.048830112 | AJ79: -- | AK79: =+AK77/AI77-1 -> 0.15806877 | AL79: =+AL77/AK77-1 -> 0.024962208 | AM79: =+AM77/AL77-1 -> 0.081283048 | AN79: =+AN77/AM77-1 -> 0.020411753 | AO79: -- | AP79: =+AP77/AN77-1 -> 0.021301462 | AQ79: =+AQ77/AP77-1 -> 0.033996901 | AR79: =+AR77/AQ77-1 -> 0.16561637 | AS79: =+AS77/AR77-1 -> 0.020629773 | AT79: -- | AU79: =+AU77/AS77-1 -> 0.0098668936 | AV79: =+AV77/AU77-1 -> 0.06653677 | AW79: =+AW77/AV77-1 -> 0.059816864 | AX79: =+AX77/AW77-1 -> 0.012181967 | AY79: -- | AZ79: =+AZ77/AX77-1 -> 0.1270976 | BA79: =+BA77/AZ77-1 -> -0.015102357 | BB79: =+BB77/BA77-1 -> 0.013608253 | BC79: =+BC77/BB77-1 -> -0.017118037 | BD79: -- | BE79: =+BE77/BC77-1 -> 0.12498297 | BF79: =+BF77/BE77-1 -> -0.0044163062 | BG79: =+BG77/BF77-1 -> 0.024215781 | BH79: =+BH77/BG77-1 -> -0.019297376 | BI79: -- | BJ79: =+BJ77/BH77-1 -> 0.095221513 | BK79: =+BK77/BJ77-1 -> -0.00642962 | BL79: =+BL77/BK77-1 -> 0.022234706 | BM79: =+BM77/BL77-1 -> -0.021113492 | BN79: -- | BO79: =+BO77/BM77-1 -> 0.093277908 | BP79: =+BP77/BO77-1 -> -0.0081208037 | BQ79: =+BQ77/BP77-1 -> 0.020564388 | BR79: =+BR77/BQ77-1 -> -0.022650206 | BS79: -- | BT79: =+BT77/BR77-1 -> 0.091627677 | BU79: =+BU77/BT77-1 -> -0.0095614416 | BV79: =+BV77/BU77-1 -> 0.019137025 | BW79: =+BW77/BV77-1 -> -0.023967389 | BX79: -- | BY79: =+BY77/BW77-1 -> 0.086449716 | BZ79: =+BZ77/BY77-1 -> -0.014110169 | CA79: =+CA77/BZ77-1 -> 0.014602834 | CB79: =+CB77/CA77-1 -> -0.028176165 | CC79: -- | CD79: =+CD77/CB77-1 -> 0.085650388 | CE79: =+CE77/CD77-1 -> -0.014816227 | CF79: =+CF77/CE77-1 -> 0.013895278 | CG79: =+CG77/CF77-1 -> -0.028836337 | CH79: -- | CI79: =+CI77/CG77-1 -> 0.084931749 | CJ79: =+CJ77/CI77-1 -> -0.0154519 | CK79: =+CK77/CJ77-1 -> 0.013257388 | CL79: =+CL77/CK77-1 -> -0.029432297 | CM79: --
A80: Guardant 360 Tissue | B80: -- | C80: -- | D80: -- | E80: -- | F80: -- | G80: =+G119 -> -- | H80: =+H119 -> -- | I80: =+I119 -> -- | J80: =+J119 -> -- | K80: =+K119 -> -- | L80: =+L119 -> -- | M80: =+M119 -> -- | N80: =+N119 -> -- | ... CM80: =+CM119 -> 180.51295
A81: % yoy | B81: -- | C81: -- | D81: -- | E81: -- | F81: -- | G81: -- | H81: -- | I81: -- | J81: -- | K81: -- | L81: -- | M81: -- | N81: -- | O81: -- | P81: -- | Q81: -- | R81: -- | S81: -- | T81: -- | U81: -- | V81: -- | W81: -- | X81: -- | Y81: -- | Z81: -- | AA81: -- | AB81: -- | AC81: -- | AD81: -- | AE81: -- | AF81: =+AF80/AA80-1 -> 3.8309717 | AG81: =+AG80/AB80-1 -> 3.0732686 | AH81: =+AH80/AC80-1 -> 2.3278282 | AI81: =+AI80/AD80-1 -> 0.97651083 | AJ81: =+AJ80/AE80-1 -> 1.9676174 | AK81: =+AK80/AF80-1 -> 1.5551133 | AL81: =+AL80/AG80-1 -> 1.7980547 | AM81: =+AM80/AH80-1 -> 1.1918941 | ... CM81: =+CM80/CH80-1 -> 0.12
A82: % seq | B82: -- | C82: -- | D82: -- | E82: -- | F82: -- | G82: -- | H82: -- | I82: -- | J82: -- | K82: -- | L82: -- | M82: -- | N82: -- | O82: -- | P82: -- | Q82: -- | R82: -- | S82: -- | T82: -- | U82: -- | V82: -- | W82: -- | X82: -- | Y82: -- | Z82: -- | AA82: -- | AB82: =+AB80/AA80-1 -> 0.40609987 | AC82: =+AC80/AB80-1 -> 0.743416 | AD82: =+AD80/AC80-1 -> 0.77025415 | AE82: -- | AF82: =+AF80/AD80-1 -> 0.11322173 | AG82: =+AG80/AF80-1 -> 0.18556324 | AH82: =+AH80/AG80-1 -> 0.4243571 | AI82: =+AI80/AH80-1 -> 0.051414392 | AJ82: -- | AK82: =+AK80/AI80-1 -> 0.43910549 | AL82: =+AL80/AK80-1 -> 0.29828717 | AM82: =+AM80/AL80-1 -> 0.11578947 | AN82: =+AN80/AM80-1 -> 0.17955975 | AO82: -- | AP82: =+AP80/AN80-1 -> 0.18365023 | AQ82: =+AQ80/AP80-1 -> 0.26445087 | AR82: =+AR80/AQ80-1 -> 0.061631635 | AS82: =+AS80/AR80-1 -> 0.19808054 | AT82: -- | AU82: =+AU80/AS80-1 -> 0.12609029 | AV82: =+AV80/AU80-1 -> 0.047975143 | AW82: =+AW80/AV80-1 -> -0.0022902133 | AX82: =+AX80/AW80-1 -> 0.12081683 | AY82: -- | AZ82: =+AZ80/AX80-1 -> 0.19253286 | BA82: =+BA80/AZ80-1 -> 0.040054001 | BB82: =+BB80/BA80-1 -> -0.02794194 | BC82: =+BC80/BB80-1 -> 0.11036382 | BD82: -- | BE82: =+BE80/BC80-1 -> 0.25548854 | BF82: =+BF80/BE80-1 -> 0.037020298 | BG82: =+BG80/BF80-1 -> -0.030666401 | BH82: =+BH80/BG80-1 -> 0.10737093 | BI82: -- | BJ82: =+BJ80/BH80-1 -> 0.033104366 | BK82: =+BK80/BJ80-1 -> 0.037020298 | BL82: =+BL80/BK80-1 -> -0.030666401 | BM82: =+BM80/BL80-1 -> 0.10737093 | BN82: -- | BO82: =+BO80/BM80-1 -> 0.033104366 | BP82: =+BP80/BO80-1 -> 0.037020298 | BQ82: =+BQ80/BP80-1 -> -0.030666401 | BR82: =+BR80/BQ80-1 -> 0.10737093 | BS82: -- | BT82: =+BT80/BR80-1 -> 0.033104366 | BU82: =+BU80/BT80-1 -> 0.037020298 | BV82: =+BV80/BU80-1 -> -0.030666401 | BW82: =+BW80/BV80-1 -> 0.10737093 | BX82: -- | BY82: =+BY80/BW80-1 -> 0.02412085 | BZ82: =+BZ80/BY80-1 -> 0.037020298 | CA82: =+CA80/BZ80-1 -> -0.030666401 | CB82: =+CB80/CA80-1 -> 0.10737093 | CC82: -- | CD82: =+CD80/CB80-1 -> 0.015137333 | CE82: =+CE80/CD80-1 -> 0.037020298 | CF82: =+CF80/CE80-1 -> -0.030666401 | CG82: =+CG80/CF80-1 -> 0.10737093 | CH82: -- | CI82: =+CI80/CG80-1 -> 0.0061538172 | CJ82: =+CJ80/CI80-1 -> 0.037020298 | CK82: =+CK80/CJ80-1 -> -0.030666401 | CL82: =+CL80/CK80-1 -> 0.10737093 | CM82: --
A83: Guardant Reveal | B83: -- | C83: -- | D83: -- | E83: -- | F83: -- | G83: =+G147 -> -- | H83: =+H147 -> -- | I83: =+I147 -> -- | J83: =+J147 -> -- | K83: =+K147 -> -- | L83: =+L147 -> -- | M83: =+M147 -> -- | N83: =+N147 -> -- | ... CM83: =+CM147 -> 773.30189
A84: % yoy | B84: -- | C84: -- | D84: -- | E84: -- | F84: -- | G84: -- | H84: -- | I84: -- | J84: -- | K84: -- | L84: -- | M84: -- | N84: -- | O84: -- | P84: -- | Q84: -- | R84: -- | S84: -- | T84: -- | U84: -- | V84: -- | W84: -- | X84: -- | Y84: -- | Z84: -- | AA84: -- | AB84: -- | AC84: -- | AD84: -- | AE84: -- | AF84: -- | AG84: =+AG83/AB83-1 -> 2.7753432 | AH84: =+AH83/AC83-1 -> 2.3162935 | AI84: =+AI83/AD83-1 -> 1.4476122 | AJ84: =+AJ83/AE83-1 -> 2.0846632 | AK84: =+AK83/AF83-1 -> 0.74418605 | AL84: =+AL83/AG83-1 -> 0.44752157 | AM84: =+AM83/AH83-1 -> 0.37842645 | AN84: =+AN83/AI83-1 -> 0.41199976 | ... CM84: =+CM83/CH83-1 -> 0.10975177
A85: % seq | B85: -- | C85: -- | D85: -- | E85: -- | F85: -- | G85: -- | H85: -- | I85: -- | J85: -- | K85: -- | L85: -- | M85: -- | N85: -- | O85: -- | P85: -- | Q85: -- | R85: -- | S85: -- | T85: -- | U85: -- | V85: -- | W85: -- | X85: -- | Y85: -- | Z85: -- | AA85: -- | AB85: -- | AC85: =+AC83/AB83-1 -> 0.31017971 | AD85: =+AD83/AC83-1 -> 0.58455542 | AE85: -- | AF85: =+AF83/AD83-1 -> 0.25541031 | AG85: =+AG83/AF83-1 -> 0.44854651 | AH85: =+AH83/AG83-1 -> 0.15087297 | AI85: =+AI83/AH83-1 -> 0.16949153 | AJ85: -- | AK85: =+AK83/AI83-1 -> -0.10538558 | AL85: =+AL83/AK83-1 -> 0.20216667 | AM85: =+AM83/AL83-1 -> 0.09593789 | AN85: =+AN83/AM83-1 -> 0.19797596 | AO85: -- | AP85: =+AP83/AN83-1 -> 0.32332524 | AQ85: =+AQ83/AP83-1 -> 0.29007676 | AR85: =+AR83/AQ83-1 -> 0.16594813 | AS85: =+AS83/AR83-1 -> 0.04137931 | AT85: -- | AU85: =+AU83/AS83-1 -> 0.32001571 | AV85: =+AV83/AU83-1 -> 0.2008525 | AW85: =+AW83/AV83-1 -> 0.16372915 | AX85: =+AX83/AW83-1 -> 0.14168583 | AY85: -- | AZ85: =+AZ83/AX83-1 -> 0.34881737 | BA85: =+BA83/AZ83-1 -> 0.22096448 | BB85: =+BB83/BA83-1 -> 0.19124549 | BC85: =+BC83/BB83-1 -> 0.20331075 | BD85: -- | BE85: =+BE83/BC83-1 -> 0.17697072 | BF85: =+BF83/BE83-1 -> 0.16165607 | BG85: =+BG83/BF83-1 -> 0.11976209 | BH85: =+BH83/BG83-1 -> 0.13883837 | BI85: -- | BJ85: =+BJ83/BH83-1 -> 0.07332052 | BK85: =+BK83/BJ83-1 -> 0.030945816 | BL85: =+BL83/BK83-1 -> 0.030781065 | BM85: =+BM83/BL83-1 -> 0.029400042 | BN85: -- | BO85: =+BO83/BM83-1 -> 0.077456578 | BP85: =+BP83/BO83-1 -> 0.053792751 | BQ85: =+BQ83/BP83-1 -> 0.052401521 | BR85: =+BR83/BQ83-1 -> 0.049870305 | BS85: -- | BT85: =+BT83/BR83-1 -> 0.016719813 | BU85: =+BU83/BT83-1 -> 0.04958711 | BV85: =+BV83/BU83-1 -> 0.048466392 | BW85: =+BW83/BV83-1 -> 0.046183309 | BX85: -- | BY85: =+BY83/BW83-1 -> -0.0036640049 | BZ85: =+BZ83/BY83-1 -> 0.046311344 | CA85: =+CA83/BZ83-1 -> 0.045392403 | CB85: =+CB83/CA83-1 -> 0.043295845 | CC85: -- | CD85: =+CD83/CB83-1 -> -0.02100648 | CE85: =+CE83/CD83-1 -> 0.044095614 | CF85: =+CF83/CE83-1 -> 0.043301257 | CG85: =+CG83/CF83-1 -> 0.041320969 | CH85: -- | CI85: =+CI83/CG83-1 -> -0.018856022 | CJ85: =+CJ83/CI83-1 -> 0.042104302 | CK85: =+CK83/CJ83-1 -> 0.041415509 | CL85: =+CL83/CK83-1 -> 0.039534374 | CM85: --
A86: Guardant 360 Response | B86: -- | C86: -- | D86: -- | E86: -- | F86: -- | G86: =+G168 -> -- | H86: =+H168 -> -- | I86: =+I168 -> -- | J86: =+J168 -> -- | K86: =+K168 -> -- | L86: =+L168 -> -- | M86: =+M168 -> -- | N86: =+N168 -> -- | ... CM86: =+CM168 -> 67.000449
A87: % yoy | B87: -- | C87: -- | D87: -- | E87: -- | F87: -- | G87: -- | H87: -- | I87: -- | J87: -- | K87: -- | L87: -- | M87: -- | N87: -- | O87: -- | P87: -- | Q87: -- | R87: -- | S87: -- | T87: -- | U87: -- | V87: -- | W87: -- | X87: -- | Y87: -- | Z87: -- | AA87: -- | AB87: -- | AC87: -- | AD87: -- | AE87: -- | AF87: -- | AG87: -- | AH87: -- | AI87: -- | AJ87: -- | AK87: -- | AL87: -- | AM87: -- | AN87: =+AN86/AI86-1 -> 0.62606539 | AO87: =+AO86/AJ86-1 -> 0.66721698 | AP87: =+AP86/AK86-1 -> 0.38607501 | AQ87: =+AQ86/AL86-1 -> 0.37540335 | AR87: =+AR86/AM86-1 -> 0.39875661 | AS87: =+AS86/AN86-1 -> 0.35279586 | AT87: =+AT86/AO86-1 -> 0.3760541 | AU87: =+AU86/AP86-1 -> 1.1916587 | ... CM87: =+CM86/CH86-1 -> 0.16849127
A88: % seq | B88: -- | C88: -- | D88: -- | E88: -- | F88: -- | G88: -- | H88: -- | I88: -- | J88: -- | K88: -- | L88: -- | M88: -- | N88: -- | O88: -- | P88: -- | Q88: -- | R88: -- | S88: -- | T88: -- | U88: -- | V88: -- | W88: -- | X88: -- | Y88: -- | Z88: -- | AA88: -- | AB88: -- | AC88: -- | AD88: -- | AE88: -- | AF88: -- | AG88: -- | AH88: -- | AI88: -- | AJ88: -- | AK88: =+AK86/AI86-1 -> -0.15172558 | AL88: =+AL86/AK86-1 -> 0.19039383 | AM88: =+AM86/AL86-1 -> 0.30759651 | AN88: =+AN86/AM86-1 -> 0.23150794 | AO88: -- | AP88: =+AP86/AN86-1 -> -0.27692209 | AQ88: =+AQ86/AP86-1 -> 0.18122876 | AR88: =+AR86/AQ86-1 -> 0.32979847 | AS88: =+AS86/AR86-1 -> 0.19104269 | AT88: -- | AU88: =+AU86/AS86-1 -> 0.1714554 | AV88: =+AV86/AU86-1 -> -0.22325369 | AW88: =+AW86/AV86-1 -> 0.38169298 | AX88: =+AX86/AW86-1 -> -0.20802135 | AY88: -- | AZ88: =+AZ86/AX86-1 -> 0.29177996 | BA88: =+BA86/AZ86-1 -> 0.18220572 | BB88: =+BB86/BA86-1 -> 0.15412353 | BC88: =+BC86/BB86-1 -> 0.13354163 | BD88: -- | BE88: =+BE86/BC86-1 -> 0.18012706 | BF88: =+BF86/BE86-1 -> 0.10539294 | BG88: =+BG86/BF86-1 -> 0.095344319 | BH88: =+BH86/BG86-1 -> 0.087045067 | BI88: -- | BJ88: =+BJ86/BH86-1 -> 0.1179039 | BK88: =+BK86/BJ86-1 -> 0.074138317 | BL88: =+BL86/BK86-1 -> 0.069021201 | BM88: =+BM86/BL86-1 -> 0.064564857 | BN88: -- | BO88: =+BO86/BM86-1 -> 0.097771777 | BP88: =+BP86/BO86-1 -> 0.057181081 | BQ88: =+BQ86/BP86-1 -> 0.054088256 | BR88: =+BR86/BQ86-1 -> 0.051312834 | BS88: -- | BT88: =+BT86/BR86-1 -> 0.085491298 | BU88: =+BU86/BT86-1 -> 0.046536949 | BV88: =+BV86/BU86-1 -> 0.044467564 | BW88: =+BW86/BV86-1 -> 0.042574385 | BX88: -- | BY88: =+BY86/BW86-1 -> 0.077215038 | BZ88: =+BZ86/BY86-1 -> 0.039233685 | CA88: =+CA86/BZ86-1 -> 0.037752515 | CB88: =+CB86/CA86-1 -> 0.036379112 | CC88: -- | CD88: =+CD86/CB86-1 -> 0.071256412 | CE88: =+CE86/CD86-1 -> 0.033911753 | CF88: =+CF86/CE86-1 -> 0.032799465 | CG88: =+CG86/CF86-1 -> 0.031757826 | CH88: -- | CI88: =+CI86/CG86-1 -> 0.066759451 | CJ88: =+CJ86/CI86-1 -> 0.029861174 | CK88: =+CK86/CJ86-1 -> 0.028995339 | CL88: =+CL86/CK86-1 -> 0.0281783 | CM88: --
A89: Total Oncology Revenue | B89: -- | C89: -- | D89: -- | E89: -- | F89: -- | G89: 7.1 | H89: 9.5 | I89: 9.6 | J89: 17 | K89: =+G89+H89+I89+J89 -> 43.2 | L89: 17.2 | M89: 21.8 | N89: 30.8 | O89: 31.3 | P89: =+L89+M89+N89+O89 -> 101.1 | Q89: 38 | R89: 39.6 | S89: 48.3 | T89: 45.9 | U89: =+Q89+R89+S89+T89 -> 171.8 | V89: 49.8 | W89: 61 | X89: 61.3 | Y89: 64.3 | Z89: =+V89+W89+X89+Y89 -> 236.4 | AA89: =+AA106+AA119+AA147+AA168 -> 66.30964 | AB89: =+AB106+AB119+AB147+AB168 -> 70.872516 | AC89: =+AC106+AC119+AC147+AC168 -> 78.20959 | AD89: =+AD106+AD119+AD147+AD168 -> 84.41717 | AE89: =+AA89+AB89+AC89+AD89 -> 299.80892 | AF89: =+AF106+AF119+AF147+AF168 -> 91.556625 | AG89: =+AG106+AG119+AG147+AG168 -> 100.31622 | AH89: =+AH106+AH119+AH147+AH168 -> 103.51346 | AI89: =+AI106+AI119+AI147+AI168 -> 109.07584 | AJ89: =+AF89+AG89+AH89+AI89 -> 404.46214 | AK89: 125.748 | AL89: =+AL278-AL186 -> 130.269 | AM89: =+AM278-AM186 -> 141.197 | AN89: =+AN278-AN186 -> 145.613 | AO89: =+AK89+AL89+AM89+AN89 -> 542.827 | AP89: 150.559 | AQ89: 158.685 | AR89: 184.402 | AS89: 189.949 | AT89: =+AT106+AT119+AT147+AT168 -> 683.595 | AU89: =+AU106+AU119+AU147+AU168 -> 196.15909 | AV89: =+AV106+AV119+AV147+AV168 -> 210.23005 | AW89: =+AW106+AW119+AW147+AW168 -> 224.22894 | AX89: =+AX106+AX119+AX147+AX168 -> 230.01104 | AY89: =+AY106+AY119+AY147+AY168 -> 860.62912 | AZ89: =+AZ106+AZ119+AZ147+AZ168 -> 264.85693 | BA89: =+BA106+BA119+BA147+BA168 -> 268.61309 | ... CM89: =+CM106+CM119+CM147+CM168 -> 2493.2556
A90: % yoy | B90: -- | C90: -- | D90: -- | E90: -- | F90: -- | G90: -- | H90: -- | I90: -- | J90: -- | K90: -- | L90: =+L89/G89-1 -> 1.4225352 | M90: =+M89/H89-1 -> 1.2947368 | N90: =+N89/I89-1 -> 2.2083333 | O90: =+O89/J89-1 -> 0.84117647 | P90: =+P89/K89-1 -> 1.3402778 | Q90: =+Q89/L89-1 -> 1.2093023 | R90: =+R89/M89-1 -> 0.81651376 | S90: =+S89/N89-1 -> 0.56818182 | ... CM90: =+CM89/CH89-1 -> 0.076671238
A91: % seq | B91: -- | C91: -- | D91: -- | E91: -- | F91: -- | G91: -- | H91: =+H89/G89-1 -> 0.33802817 | I91: =+I89/H89-1 -> 0.010526316 | J91: =+J89/I89-1 -> 0.77083333 | K91: -- | L91: =+L89/J89-1 -> 0.011764706 | M91: =+M89/L89-1 -> 0.26744186 | N91: =+N89/M89-1 -> 0.41284404 | O91: =+O89/N89-1 -> 0.016233766 | P91: -- | Q91: =+Q89/O89-1 -> 0.21405751 | R91: =+R89/Q89-1 -> 0.042105263 | S91: =+S89/R89-1 -> 0.21969697 | T91: =+T89/S89-1 -> -0.049689441 | U91: -- | V91: =+V89/T89-1 -> 0.08496732 | W91: =+W89/V89-1 -> 0.2248996 | X91: =+X89/W89-1 -> 0.0049180328 | Y91: =+Y89/X89-1 -> 0.048939641 | Z91: -- | AA91: =+AA89/Y89-1 -> 0.031254121 | AB91: =+AB89/AA89-1 -> 0.068811654 | AC91: =+AC89/AB89-1 -> 0.10352495 | AD91: =+AD89/AC89-1 -> 0.079371085 | AE91: -- | AF91: =+AF89/AD89-1 -> 0.084573494 | AG91: =+AG89/AF89-1 -> 0.095674027 | AH91: =+AH89/AG89-1 -> 0.031871657 | AI91: =+AI89/AH89-1 -> 0.053735814 | AJ91: -- | AK91: =+AK89/AI89-1 -> 0.15284925 | AL91: =+AL89/AK89-1 -> 0.035952858 | AM91: =+AM89/AL89-1 -> 0.083887955 | AN91: =+AN89/AM89-1 -> 0.031275452 | AO91: -- | AP91: =+AP89/AN89-1 -> 0.033966747 | AQ91: =+AQ89/AP89-1 -> 0.053972197 | AR91: =+AR89/AQ89-1 -> 0.16206321 | AS91: =+AS89/AR89-1 -> 0.030081019 | AT91: -- | AU91: =+AU89/AS89-1 -> 0.032693456 | AV91: =+AV89/AU89-1 -> 0.071732389 | AW91: =+AW89/AV89-1 -> 0.066588453 | AX91: =+AX89/AW89-1 -> 0.025786582 | AY91: -- | AZ91: =+AZ89/AX89-1 -> 0.15149659 | BA91: =+BA89/AZ89-1 -> 0.014181858 | BB91: =+BB89/BA89-1 -> 0.035113054 | BC91: =+BC89/BB89-1 -> 0.023039262 | BD91: -- | BE91: =+BE89/BC89-1 -> 0.14174305 | BF91: =+BF89/BE89-1 -> 0.028727627 | BG91: =+BG89/BF89-1 -> 0.040792937 | BH91: =+BH89/BG89-1 -> 0.023294763 | BI91: -- | BJ91: =+BJ89/BH89-1 -> 0.086448009 | BK91: =+BK89/BJ89-1 -> 0.0060910934 | BL91: =+BL89/BK89-1 -> 0.021794817 | BM91: =+BM89/BL89-1 -> -3.4259085e-05 | BN91: -- | BO91: =+BO89/BM89-1 -> 0.085538889 | BP91: =+BP89/BO89-1 -> 0.01117044 | BQ91: =+BQ89/BP89-1 -> 0.026246562 | BR91: =+BR89/BQ89-1 -> 0.0056738376 | BS91: -- | BT91: =+BT89/BR89-1 -> 0.06687178 | BU91: =+BU89/BT89-1 -> 0.010132731 | BV91: =+BV89/BU89-1 -> 0.024523072 | BW91: =+BW89/BV89-1 -> 0.0051749315 | BX91: -- | BY91: =+BY89/BW89-1 -> 0.055617849 | BZ91: =+BZ89/BY89-1 -> 0.0071117685 | CA91: =+CA89/BZ89-1 -> 0.020948976 | CB91: =+CB89/CA89-1 -> 0.0029778505 | CC91: -- | CD91: =+CD89/CB89-1 -> 0.047657342 | CE91: =+CE89/CD89-1 -> 0.0067579348 | CF91: =+CF89/CE89-1 -> 0.019973795 | CG91: =+CG89/CF89-1 -> 0.0030711875 | CH91: -- | CI91: =+CI89/CG89-1 -> 0.045923143 | CJ91: =+CJ89/CI89-1 -> 0.0064805249 | CK91: =+CK89/CJ89-1 -> 0.019105197 | CL91: =+CL89/CK89-1 -> 0.0032076321 | CM91: --
A93: Guardant 360 Liquid
A94: Total Patient Population | B94: -- | C94: -- | D94: -- | E94: -- | F94: -- | G94: =+K94/4 -> 175000 | H94: =+K94/4 -> 175000 | I94: =+K94/4 -> 175000 | J94: =+K94/4 -> 175000 | K94: 700000 | L94: =+P94/4 -> 175000 | M94: =+P94/4 -> 175000 | N94: =+P94/4 -> 175000 | O94: =+P94/4 -> 175000 | P94: 700000 | Q94: =+U94/4 -> 175000 | R94: =+U94/4 -> 175000 | S94: =+U94/4 -> 175000 | T94: =+U94/4 -> 175000 | U94: 700000 | V94: =+Z94/4 -> 175000 | W94: =+Z94/4 -> 175000 | X94: =+Z94/4 -> 175000 | Y94: =+Z94/4 -> 175000 | Z94: 700000 | AA94: =+AE94/4 -> 175000 | AB94: =+AE94/4 -> 175000 | AC94: =+AE94/4 -> 175000 | AD94: =+AE94/4 -> 175000 | AE94: 700000 | AF94: =+AJ94/4 -> 175000 | AG94: =+AJ94/4 -> 175000 | AH94: =+AJ94/4 -> 175000 | AI94: =+AJ94/4 -> 175000 | AJ94: 700000 | AK94: =+AO94/4 -> 175000 | AL94: =+AO94/4 -> 175000 | AM94: =+AO94/4 -> 175000 | AN94: =+AO94/4 -> 175000 | AO94: 700000 | AP94: =+AT94/4 -> 175000 | AQ94: =+AT94/4 -> 175000 | AR94: =+AT94/4 -> 175000 | AS94: =+AT94/4 -> 175000 | AT94: 700000 | AU94: =+AY94/4 -> 175000 | AV94: =+AY94/4 -> 175000 | AW94: =+AY94/4 -> 175000 | AX94: =+AY94/4 -> 175000 | AY94: 700000 | AZ94: =+BD94/4 -> 175000 | BA94: =+BD94/4 -> 175000 | BB94: =+BD94/4 -> 175000 | BC94: =+BD94/4 -> 175000 | BD94: 700000 | BE94: =+BI94/4 -> 175000 | BF94: =+BI94/4 -> 175000 | BG94: =+BI94/4 -> 175000 | BH94: =+BI94/4 -> 175000 | BI94: 700000 | BJ94: =+BN94/4 -> 175000 | BK94: =+BN94/4 -> 175000 | BL94: =+BN94/4 -> 175000 | BM94: =+BN94/4 -> 175000 | BN94: 700000 | BO94: =+BS94/4 -> 175000 | BP94: =+BS94/4 -> 175000 | BQ94: =+BS94/4 -> 175000 | BR94: =+BS94/4 -> 175000 | BS94: 700000 | BT94: =+BX94/4 -> 175000 | BU94: =+BX94/4 -> 175000 | BV94: =+BX94/4 -> 175000 | BW94: =+BX94/4 -> 175000 | BX94: 700000 | BY94: =+CC94/4 -> 175000 | BZ94: =+CC94/4 -> 175000 | CA94: =+CC94/4 -> 175000 | CB94: =+CC94/4 -> 175000 | CC94: 700000 | CD94: =+CH94/4 -> 175000 | CE94: =+CH94/4 -> 175000 | CF94: =+CH94/4 -> 175000 | CG94: =+CH94/4 -> 175000 | CH94: 700000 | CI94: =+CM94/4 -> 175000 | CJ94: =+CM94/4 -> 175000 | CK94: =+CM94/4 -> 175000 | CL94: =+CM94/4 -> 175000 | CM94: 700000
A95: G360 Volume | B95: -- | C95: -- | D95: -- | E95: -- | F95: -- | G95: =+G55 -> 7246 | H95: =+H55 -> 6723 | I95: =+I55 -> 7027 | J95: =+J55 -> 8596 | K95: =+G95+H95+I95+J95 -> 29592 | L95: =+L55 -> 9521 | M95: =+M55 -> 11875 | N95: =+N55 -> 13259 | O95: =+O55 -> 15270 | P95: =+L95+M95+N95+O95 -> 49925 | Q95: =+Q55 -> 15257 | R95: =+R55 -> 13694 | S95: =+S55 -> 16950 | T95: =+T55 -> 17353 | U95: =+Q95+R95+S95+T95 -> 63254 | V95: =+V55 -> 18390 | W95: =+W55 -> 20830 | X95: =+X55 -> 22806 | Y95: =+Y55 -> 25600 | Z95: =+V95+W95+X95+Y95 -> 87626 | AA95: =+AA55-AA111-AA136-AA157 -> 25106 | AB95: =+AB55-AB111-AB136-AB157 -> 26952 | AC95: =+AC55-AC111-AC136-AC157 -> 29179 | AD95: =+AD55-AD111-AD136-AD157 -> 31226 | AE95: =+AA95+AB95+AC95+AD95 -> 112463 | AF95: =+AF55-AF111-AF136-AF157 -> 33633 | AG95: =+AG55-AG111-AG136-AG157 -> 36300 | AH95: =+AH55-AH111-AH136-AH157 -> 35499 | AI95: =+AI55-AI111-AI136-AI157 -> 36783 | AJ95: =+AF95+AG95+AH95+AI95 -> 142215 | AK95: =+AK55-AK111-AK136-AK157 -> 38254 | AL95: =+AL55-AL111-AL136-AL157 -> 39009 | AM95: =+AM55-AM111-AM136-AM157 -> 41495 | AN95: =+AN55-AN111-AN136-AN157 -> 43490 | AO95: =+AK95+AL95+AM95+AN95 -> 162248 | AP95: =+AP55-AP111-AP136-AP157 -> 44326 | AQ95: =+AQ55-AQ111-AQ136-AQ157 -> 46668 | AR95: =+AR55-AR111-AR136-AR157 -> 54346 | AS95: =+AS55-AS111-AS136-AS157 -> 57844 | AT95: =+AP95+AQ95+AR95+AS95 -> 203184 | AU95: =+AU94*AU98 -> 54250 | AV95: =+AV94*AV98 -> 59500 | AW95: =+AW94*AW98 -> 63000 | AX95: =+AX94*AX98 -> 66500 | AY95: =+AU95+AV95+AW95+AX95 -> 243250 | AZ95: =+AZ94*AZ98 -> 68250 | BA95: =+BA94*BA98 -> 69125 | BB95: =+BB94*BB98 -> 70000 | BC95: =+BC94*BC98 -> 71750 | BD95: =+AZ95+BA95+BB95+BC95 -> 279125 | BE95: =+BE94*BE98 -> 73500 | BF95: =+BF94*BF98 -> 75250 | BG95: =+BG94*BG98 -> 77000 | BH95: =+BH94*BH98 -> 78750 | BI95: =+BE95+BF95+BG95+BH95 -> 304500 | BJ95: =+BJ94*BJ98 -> 80500 | BK95: =+BK94*BK98 -> 82250 | BL95: =+BL94*BL98 -> 84000 | BM95: =+BM94*BM98 -> 85750 | BN95: =+BJ95+BK95+BL95+BM95 -> 332500 | BO95: =+BO94*BO98 -> 87500 | BP95: =+BP94*BP98 -> 89250 | BQ95: =+BQ94*BQ98 -> 91000 | BR95: =+BR94*BR98 -> 92750 | BS95: =+BO95+BP95+BQ95+BR95 -> 360500 | BT95: =+BT94*BT98 -> 94500 | BU95: =+BU94*BU98 -> 96250 | BV95: =+BV94*BV98 -> 98000 | BW95: =+BW94*BW98 -> 99750 | BX95: =+BT95+BU95+BV95+BW95 -> 388500 | BY95: =+BY94*BY98 -> 101150 | BZ95: =+BZ94*BZ98 -> 102550 | CA95: =+CA94*CA98 -> 103950 | CB95: =+CB94*CB98 -> 105350 | CC95: =+BY95+BZ95+CA95+CB95 -> 413000 | CD95: =+CD94*CD98 -> 106750 | CE95: =+CE94*CE98 -> 108150 | CF95: =+CF94*CF98 -> 109550 | CG95: =+CG94*CG98 -> 110950 | CH95: =+CD95+CE95+CF95+CG95 -> 435400 | CI95: =+CI94*CI98 -> 112350 | CJ95: =+CJ94*CJ98 -> 113750 | CK95: =+CK94*CK98 -> 115150 | CL95: =+CL94*CL98 -> 116550 | CM95: =+CI95+CJ95+CK95+CL95 -> 457800
A96: % yoy | B96: -- | C96: -- | D96: -- | E96: -- | F96: -- | G96: -- | H96: -- | I96: -- | J96: -- | K96: -- | L96: =+L95/G95-1 -> 0.31396633 | M96: =+M95/H95-1 -> 0.76632456 | N96: =+N95/I95-1 -> 0.88686495 | O96: =+O95/J95-1 -> 0.77640763 | P96: =+P95/K95-1 -> 0.68711138 | Q96: =+Q95/L95-1 -> 0.60245773 | R96: =+R95/M95-1 -> 0.15317895 | S96: =+S95/N95-1 -> 0.27837695 | ... CM96: =+CM95/CH95-1 -> 0.051446945
A97: % seq | B97: -- | C97: -- | D97: -- | E97: -- | F97: -- | G97: -- | H97: =+H95/G95-1 -> -0.072177753 | I97: =+I95/H95-1 -> 0.045217909 | J97: =+J95/I95-1 -> 0.22328163 | K97: -- | L97: =+L95/J95-1 -> 0.10760819 | M97: =+M95/L95-1 -> 0.24724294 | N97: =+N95/M95-1 -> 0.11654737 | O97: =+O95/N95-1 -> 0.15167056 | P97: -- | Q97: =+Q95/O95-1 -> -0.0008513425 | R97: =+R95/Q95-1 -> -0.10244478 | S97: =+S95/R95-1 -> 0.23776837 | T97: =+T95/S95-1 -> 0.023775811 | U97: -- | V97: =+V95/T95-1 -> 0.059759119 | W97: =+W95/V95-1 -> 0.1326808 | X97: =+X95/W95-1 -> 0.094863178 | Y97: =+Y95/X95-1 -> 0.12251162 | Z97: -- | AA97: =+AA95/Y95-1 -> -0.019296875 | AB97: =+AB95/AA95-1 -> 0.07352824 | AC97: =+AC95/AB95-1 -> 0.082628376 | AD97: =+AD95/AC95-1 -> 0.070153192 | AE97: -- | AF97: =+AF95/AD95-1 -> 0.0770832 | AG97: =+AG95/AF95-1 -> 0.079297119 | AH97: =+AH95/AG95-1 -> -0.022066116 | AI97: =+AI95/AH95-1 -> 0.036170033 | AJ97: -- | AK97: =+AK95/AI95-1 -> 0.0399913 | AL97: =+AL95/AK95-1 -> 0.019736498 | AM97: =+AM95/AL95-1 -> 0.063728883 | AN97: =+AN95/AM95-1 -> 0.048078082 | AO97: -- | AP97: =+AP95/AN95-1 -> 0.01922281 | AQ97: =+AQ95/AP95-1 -> 0.052835807 | AR97: =+AR95/AQ95-1 -> 0.16452387 | AS97: =+AS95/AR95-1 -> 0.064365363 | AT97: -- | AU97: =+AU95/AS95-1 -> -0.062132633 | AV97: =+AV95/AU95-1 -> 0.096774194 | AW97: =+AW95/AV95-1 -> 0.058823529 | AX97: =+AX95/AW95-1 -> 0.055555556 | AY97: -- | AZ97: =+AZ95/AX95-1 -> 0.026315789 | BA97: =+BA95/AZ95-1 -> 0.012820513 | BB97: =+BB95/BA95-1 -> 0.012658228 | BC97: =+BC95/BB95-1 -> 0.025 | BD97: -- | BE97: =+BE95/BC95-1 -> 0.024390244 | BF97: =+BF95/BE95-1 -> 0.023809524 | BG97: =+BG95/BF95-1 -> 0.023255814 | BH97: =+BH95/BG95-1 -> 0.022727273 | BI97: -- | BJ97: =+BJ95/BH95-1 -> 0.022222222 | BK97: =+BK95/BJ95-1 -> 0.02173913 | BL97: =+BL95/BK95-1 -> 0.021276596 | BM97: =+BM95/BL95-1 -> 0.020833333 | BN97: -- | BO97: =+BO95/BM95-1 -> 0.020408163 | BP97: =+BP95/BO95-1 -> 0.02 | BQ97: =+BQ95/BP95-1 -> 0.019607843 | BR97: =+BR95/BQ95-1 -> 0.019230769 | BS97: -- | BT97: =+BT95/BR95-1 -> 0.018867925 | BU97: =+BU95/BT95-1 -> 0.018518519 | BV97: =+BV95/BU95-1 -> 0.018181818 | BW97: =+BW95/BV95-1 -> 0.017857143 | BX97: -- | BY97: =+BY95/BW95-1 -> 0.014035088 | BZ97: =+BZ95/BY95-1 -> 0.01384083 | CA97: =+CA95/BZ95-1 -> 0.013651877 | CB97: =+CB95/CA95-1 -> 0.013468013 | CC97: -- | CD97: =+CD95/CB95-1 -> 0.013289037 | CE97: =+CE95/CD95-1 -> 0.013114754 | CF97: =+CF95/CE95-1 -> 0.012944984 | CG97: =+CG95/CF95-1 -> 0.012779553 | CH97: -- | CI97: =+CI95/CG95-1 -> 0.012618297 | CJ97: =+CJ95/CI95-1 -> 0.012461059 | CK97: =+CK95/CJ95-1 -> 0.012307692 | CL97: =+CL95/CK95-1 -> 0.012158055 | CM97: --
A98: % penetration | B98: -- | C98: -- | D98: -- | E98: -- | F98: -- | G98: =+G95/G94 -> 0.041405714 | H98: =+H95/H94 -> 0.038417143 | I98: =+I95/I94 -> 0.040154286 | J98: =+J95/J94 -> 0.04912 | K98: =+K95/K94 -> 0.042274286 | L98: =+L95/L94 -> 0.054405714 | M98: =+M95/M94 -> 0.067857143 | N98: =+N95/N94 -> 0.075765714 | ... AP98: =+AP95/AP94 -> 0.25329143 | AQ98: 0.27 | AR98: 0.281 | AS98: 0.299 | AT98: =+AT95/AT94 -> 0.29026286 | AU98: 0.31 | AV98: 0.34 | AW98: 0.36 | AX98: 0.38 | AY98: =+AY95/AY94 -> 0.3475 | AZ98: =+AX98+0.01 -> 0.39 | BA98: =+AZ98+0.005 -> 0.395 | BB98: =+BA98+0.005 -> 0.4 | BC98: =+BB98+0.01 -> 0.41 | BD98: =+BD95/BD94 -> 0.39875 | BE98: =+BC98+0.01 -> 0.42 | BF98: =+BE98+0.01 -> 0.43 | BG98: =+BF98+0.01 -> 0.44 | BH98: =+BG98+0.01 -> 0.45 | BI98: =+BI95/BI94 -> 0.435 | BJ98: =+BH98+0.01 -> 0.46 | BK98: =+BJ98+0.01 -> 0.47 | BL98: =+BK98+0.01 -> 0.48 | BM98: =+BL98+0.01 -> 0.49 | BN98: =+BN95/BN94 -> 0.475 | BO98: =+BM98+0.01 -> 0.5 | BP98: =+BO98+0.01 -> 0.51 | BQ98: =+BP98+0.01 -> 0.52 | BR98: =+BQ98+0.01 -> 0.53 | BS98: =+BS95/BS94 -> 0.515 | BT98: =+BR98+0.01 -> 0.54 | BU98: =+BT98+0.01 -> 0.55 | BV98: =+BU98+0.01 -> 0.56 | BW98: =+BV98+0.01 -> 0.57 | BX98: =+BX95/BX94 -> 0.555 | BY98: =+BW98+0.008 -> 0.578 | BZ98: =+BY98+0.008 -> 0.586 | CA98: =+BZ98+0.008 -> 0.594 | CB98: =+CA98+0.008 -> 0.602 | CC98: =+CC95/CC94 -> 0.59 | CD98: =+CB98+0.008 -> 0.61 | CE98: =+CD98+0.008 -> 0.618 | CF98: =+CE98+0.008 -> 0.626 | CG98: =+CF98+0.008 -> 0.634 | CH98: =+CH95/CH94 -> 0.622 | CI98: =+CG98+0.008 -> 0.642 | CJ98: =+CI98+0.008 -> 0.65 | CK98: =+CJ98+0.008 -> 0.658 | CL98: =+CK98+0.008 -> 0.666 | CM98: =+CM95/CM94 -> 0.654
A99: penetration chg yoy | B99: -- | C99: -- | D99: -- | E99: -- | F99: -- | G99: -- | H99: -- | I99: -- | J99: -- | K99: -- | L99: =+(L98-G98)*100000 -> 1300 | M99: =+(M98-H98)*100000 -> 2944 | N99: =+(N98-I98)*100000 -> 3561.1429 | O99: =+(O98-J98)*100000 -> 3813.7143 | P99: =+(P98-K98)*100000 -> 2904.7143 | Q99: =+(Q98-L98)*100000 -> 3277.7143 | R99: =+(R98-M98)*100000 -> 1039.4286 | S99: =+(S98-N98)*100000 -> 2109.1429 | ... CM99: =+(CM98-CH98)*100000 -> 3200
A100: penetration chg seq | B100: -- | C100: -- | D100: -- | E100: -- | F100: -- | G100: -- | H100: =+(H98-G98)*100000 -> -298.85714 | I100: =+(I98-H98)*100000 -> 173.71429 | J100: =+(J98-I98)*100000 -> 896.57143 | K100: -- | L100: =+(L98-J98)*100000 -> 528.57143 | M100: =+(M98-L98)*100000 -> 1345.1429 | N100: =+(N98-M98)*100000 -> 790.85714 | O100: =+(O98-N98)*100000 -> 1149.1429 | P100: -- | Q100: =+(Q98-O98)*100000 -> -7.4285714 | R100: =+(R98-Q98)*100000 -> -893.14286 | S100: =+(S98-R98)*100000 -> 1860.5714 | T100: =+(T98-S98)*100000 -> 230.28571 | U100: -- | V100: =+(V98-T98)*100000 -> 592.57143 | W100: =+(W98-V98)*100000 -> 1394.2857 | X100: =+(X98-W98)*100000 -> 1129.1429 | Y100: =+(Y98-X98)*100000 -> 1596.5714 | Z100: -- | AA100: =+(AA98-Y98)*100000 -> -282.28571 | AB100: =+(AB98-AA98)*100000 -> 1054.8571 | AC100: =+(AC98-AB98)*100000 -> 1272.5714 | AD100: =+(AD98-AC98)*100000 -> 1169.7143 | AE100: -- | AF100: =+(AF98-AD98)*100000 -> 1375.4286 | AG100: =+(AG98-AF98)*100000 -> 1524 | AH100: =+(AH98-AG98)*100000 -> -457.71429 | AI100: =+(AI98-AH98)*100000 -> 733.71429 | AJ100: -- | AK100: =+(AK98-AI98)*100000 -> 840.57143 | AL100: =+(AL98-AK98)*100000 -> 431.42857 | AM100: =+(AM98-AL98)*100000 -> 1420.5714 | AN100: =+(AN98-AM98)*100000 -> 1140 | AO100: -- | AP100: =+(AP98-AN98)*100000 -> 477.71429 | AQ100: =+(AQ98-AO98)*100000 -> 3821.7143 | AR100: =+(AR98-AQ98)*100000 -> 1100 | AS100: =+(AS98-AR98)*100000 -> 1800 | AT100: -- | AU100: =+(AU98-AS98)*100000 -> 1100 | AV100: =+(AV98-AU98)*100000 -> 3000 | AW100: =+(AW98-AV98)*100000 -> 2000 | AX100: =+(AX98-AW98)*100000 -> 2000 | AY100: -- | AZ100: =+(AZ98-AX98)*100000 -> 1000 | BA100: =+(BA98-AZ98)*100000 -> 500 | BB100: =+(BB98-BA98)*100000 -> 500 | BC100: =+(BC98-BB98)*100000 -> 1000 | BD100: -- | BE100: =+(BE98-BC98)*100000 -> 1000 | BF100: =+(BF98-BE98)*100000 -> 1000 | BG100: =+(BG98-BF98)*100000 -> 1000 | BH100: =+(BH98-BG98)*100000 -> 1000 | BI100: -- | BJ100: =+(BJ98-BH98)*100000 -> 1000 | BK100: =+(BK98-BJ98)*100000 -> 1000 | BL100: =+(BL98-BK98)*100000 -> 1000 | BM100: =+(BM98-BL98)*100000 -> 1000 | BN100: -- | BO100: =+(BO98-BM98)*100000 -> 1000 | BP100: =+(BP98-BO98)*100000 -> 1000 | BQ100: =+(BQ98-BP98)*100000 -> 1000 | BR100: =+(BR98-BQ98)*100000 -> 1000 | BS100: -- | BT100: =+(BT98-BR98)*100000 -> 1000 | BU100: =+(BU98-BT98)*100000 -> 1000 | BV100: =+(BV98-BU98)*100000 -> 1000 | BW100: =+(BW98-BV98)*100000 -> 1000 | BX100: -- | BY100: =+(BY98-BW98)*100000 -> 800 | BZ100: =+(BZ98-BY98)*100000 -> 800 | CA100: =+(CA98-BZ98)*100000 -> 800 | CB100: =+(CB98-CA98)*100000 -> 800 | CC100: -- | CD100: =+(CD98-CB98)*100000 -> 800 | CE100: =+(CE98-CD98)*100000 -> 800 | CF100: =+(CF98-CE98)*100000 -> 800 | CG100: =+(CG98-CF98)*100000 -> 800 | CH100: -- | CI100: =+(CI98-CG98)*100000 -> 800 | CJ100: =+(CJ98-CI98)*100000 -> 800 | CK100: =+(CK98-CJ98)*100000 -> 800 | CL100: =+(CL98-CK98)*100000 -> 800 | CM100: --
A102: Average Selling Price ($ / test) | B102: -- | C102: -- | D102: -- | E102: -- | F102: -- | G102: =+G106/G95*1000000 -> 979.85095 | H102: =+H106/H95*1000000 -> 1413.0596 | I102: =+I106/I95*1000000 -> 1366.1591 | J102: =+J106/J95*1000000 -> 1977.664 | K102: =+K106/K95*1000000 -> 1459.854 | L102: =+L106/L95*1000000 -> 1806.5329 | M102: =+M106/M95*1000000 -> 1835.7895 | N102: =+N106/N95*1000000 -> 2322.9504 | ... AT102: =+AT106/AT95*1000000 -> 3033.3628 | AU102: =+AP102*(1+AU103) -> 3157.7458 | AV102: =+AQ102*(1+AV103) -> 3070.6886 | AW102: =+AR102*(1+AW103) -> 3073.5694 | AX102: =+AS102*(1+AX103) -> 2947.274 | AY102: =+AY106/AY95*1000000 -> 3057.1111 | AZ102: =+AU102*(1+AZ103) -> 3236.6895 | BA102: =+AV102*(1+BA103) -> 3147.4558 | BB102: =+AW102*(1+BB103) -> 3150.4086 | BC102: =+AX102*(1+BC103) -> 3020.9559 | BD102: =+BD106/BD95*1000000 -> 3137.498 | BE102: =+AZ102*(1+BE103) -> 3317.6067 | BF102: =+BA102*(1+BF103) -> 3226.1422 | BG102: =+BB102*(1+BG103) -> 3229.1688 | BH102: =+BC102*(1+BH103) -> 3096.4798 | BI102: =+BI106/BI95*1000000 -> 3215.4518 | BJ102: =+BE102*(1+BJ103) -> 3317.6067 | BK102: =+BF102*(1+BK103) -> 3226.1422 | BL102: =+BG102*(1+BL103) -> 3229.1688 | BM102: =+BH102*(1+BM103) -> 3096.4798 | BN102: =+BN106/BN95*1000000 -> 3215.6116 | BO102: =+BJ102*(1+BO103) -> 3317.6067 | BP102: =+BK102*(1+BP103) -> 3226.1422 | BQ102: =+BL102*(1+BQ103) -> 3229.1688 | BR102: =+BM102*(1+BR103) -> 3096.4798 | BS102: =+BS106/BS95*1000000 -> 3215.7466 | BT102: =+BO102*(1+BT103) -> 3317.6067 | BU102: =+BP102*(1+BU103) -> 3226.1422 | BV102: =+BQ102*(1+BV103) -> 3229.1688 | BW102: =+BR102*(1+BW103) -> 3096.4798 | BX102: =+BX106/BX95*1000000 -> 3215.8621 | BY102: =+BT102*(1+BY103) -> 3317.6067 | BZ102: =+BU102*(1+BZ103) -> 3226.1422 | CA102: =+BV102*(1+CA103) -> 3229.1688 | CB102: =+BW102*(1+CB103) -> 3096.4798 | CC102: =+CC106/CC95*1000000 -> 3216.2301 | CD102: =+BY102*(1+CD103) -> 3317.6067 | CE102: =+BZ102*(1+CE103) -> 3226.1422 | CF102: =+CA102*(1+CF103) -> 3229.1688 | CG102: =+CB102*(1+CG103) -> 3096.4798 | CH102: =+CH106/CH95*1000000 -> 3216.2877 | CI102: =+CD102*(1+CI103) -> 3317.6067 | CJ102: =+CE102*(1+CJ103) -> 3226.1422 | CK102: =+CF102*(1+CK103) -> 3229.1688 | CL102: =+CG102*(1+CL103) -> 3096.4798 | CM102: =+CM106/CM95*1000000 -> 3216.3397
A103: % yoy | B103: -- | C103: -- | D103: -- | E103: -- | F103: -- | G103: -- | H103: -- | I103: -- | J103: -- | K103: -- | L103: =+L102/G102-1 -> 0.84368135 | M103: =+M102/H102-1 -> 0.29915922 | N103: =+N102/I102-1 -> 0.70035133 | O103: =+O102/J102-1 -> 0.036460572 | P103: =+P102/K102-1 -> 0.38715073 | Q103: =+Q102/L102-1 -> 0.37869617 | R103: =+R102/M102-1 -> 0.57522279 | S103: =+S102/N102-1 -> 0.22669751 | ... AT103: =+AT102/AO102-1 -> -0.033326091 | AU103: 0.015 | AV103: 0.005 | AW103: 0.005 | AX103: 0.005 | AY103: =+AY102/AT102-1 -> 0.0078290371 | AZ103: 0.025 | BA103: 0.025 | BB103: 0.025 | BC103: 0.025 | BD103: 0.01 | BE103: 0.025 | BF103: 0.025 | BG103: 0.025 | BH103: 0.025 | BI103: =+BI102/BD102-1 -> 0.024845855 | BJ103: 0 | BK103: 0 | BL103: 0 | BM103: 0 | BN103: =+BN102/BI102-1 -> 4.9696066e-05 | BO103: 0 | BP103: 0 | BQ103: 0 | BR103: 0 | BS103: =+BS102/BN102-1 -> 4.1974202e-05 | BT103: 0 | BU103: 0 | BV103: 0 | BW103: 0 | BX103: =+BX102/BS102-1 -> 3.5922359e-05 | BY103: 0 | BZ103: 0 | CA103: 0 | CB103: 0 | CC103: =+CC102/BX102-1 -> 0.00011444513 | CD103: 0 | CE103: 0 | CF103: 0 | CG103: 0 | CH103: =+CH102/CC102-1 -> 1.7903475e-05 | CI103: 0 | CJ103: 0 | CK103: 0 | CL103: 0 | CM103: =+CM102/CH102-1 -> 1.6151164e-05
A104: % seq | B104: -- | C104: -- | D104: -- | E104: -- | F104: -- | G104: -- | H104: =+H102/G102-1 -> 0.44211693 | I104: =+I102/H102-1 -> -0.033190775 | J104: =+J102/I102-1 -> 0.44760887 | K104: -- | L104: =+L102/J102-1 -> -0.086531939 | M104: =+M102/L102-1 -> 0.016194859 | N104: =+N102/M102-1 -> 0.26536865 | O104: =+O102/N102-1 -> -0.11760029 | P104: -- | Q104: =+Q102/O102-1 -> 0.21509197 | R104: =+R102/Q102-1 -> 0.16104863 | S104: =+S102/R102-1 -> -0.014599982 | T104: =+T102/S102-1 -> -0.071759121 | U104: -- | V104: =+V102/T102-1 -> 0.023786727 | W104: =+W102/V102-1 -> 0.0814164 | X104: =+X102/W102-1 -> -0.08215195 | Y104: =+Y102/X102-1 -> -0.065542287 | Z104: -- | AA104: =+AA102/Y102-1 -> 0.040292116 | AB104: =+AB102/AA102-1 -> -0.0074329295 | AC104: =+AC102/AB102-1 -> 0.014856501 | AD104: =+AD102/AC102-1 -> -0.003501314 | AE104: -- | AF104: =+AF102/AD102-1 -> 0.0021185731 | AG104: =+AG102/AF102-1 -> 0.0072333682 | AH104: =+AH102/AG102-1 -> 0.04597339 | AI104: =+AI102/AH102-1 -> 0.012218148 | AJ104: -- | AK104: =+AK102/AI102-1 -> 0.11353698 | AL104: =+AL102/AK102-1 -> 0.0051245688 | AM104: =+AM102/AL102-1 -> 0.016502481 | AN104: =+AN102/AM102-1 -> -0.026397202 | AO104: -- | AP104: =+AP102/AN102-1 -> 0.0020394481 | AQ104: =+AQ102/AP102-1 -> -0.017893489 | AR104: =+AR102/AQ102-1 -> 0.00093814948 | AS104: =+AS102/AR102-1 -> -0.041090768 | AT104: -- | AU104: =+AU102/AS102-1 -> 0.076769412 | AV104: =+AV102/AU102-1 -> -0.027569415 | AW104: =+AW102/AV102-1 -> 0.00093814948 | AX104: =+AX102/AW102-1 -> -0.041090768 | AY104: -- | AZ104: =+AZ102/AX102-1 -> 0.098197659 | BA104: =+BA102/AZ102-1 -> -0.027569415 | BB104: =+BB102/BA102-1 -> 0.00093814948 | BC104: =+BC102/BB102-1 -> -0.041090768 | BD104: -- | BE104: =+BE102/BC102-1 -> 0.098197659 | BF104: =+BF102/BE102-1 -> -0.027569415 | BG104: =+BG102/BF102-1 -> 0.00093814948 | BH104: =+BH102/BG102-1 -> -0.041090768 | BI104: -- | BJ104: =+BJ102/BH102-1 -> 0.07141235 | BK104: =+BK102/BJ102-1 -> -0.027569415 | BL104: =+BL102/BK102-1 -> 0.00093814948 | BM104: =+BM102/BL102-1 -> -0.041090768 | BN104: -- | BO104: =+BO102/BM102-1 -> 0.07141235 | BP104: =+BP102/BO102-1 -> -0.027569415 | BQ104: =+BQ102/BP102-1 -> 0.00093814948 | BR104: =+BR102/BQ102-1 -> -0.041090768 | BS104: -- | BT104: =+BT102/BR102-1 -> 0.07141235 | BU104: =+BU102/BT102-1 -> -0.027569415 | BV104: =+BV102/BU102-1 -> 0.00093814948 | BW104: =+BW102/BV102-1 -> -0.041090768 | BX104: -- | BY104: =+BY102/BW102-1 -> 0.07141235 | BZ104: =+BZ102/BY102-1 -> -0.027569415 | CA104: =+CA102/BZ102-1 -> 0.00093814948 | CB104: =+CB102/CA102-1 -> -0.041090768 | CC104: -- | CD104: =+CD102/CB102-1 -> 0.07141235 | CE104: =+CE102/CD102-1 -> -0.027569415 | CF104: =+CF102/CE102-1 -> 0.00093814948 | CG104: =+CG102/CF102-1 -> -0.041090768 | CH104: -- | CI104: =+CI102/CG102-1 -> 0.07141235 | CJ104: =+CJ102/CI102-1 -> -0.027569415 | CK104: =+CK102/CJ102-1 -> 0.00093814948 | CL104: =+CL102/CK102-1 -> -0.041090768 | CM104: --
A106: G360 / G360 Dx Revenue | B106: -- | C106: -- | D106: -- | E106: -- | F106: -- | G106: =+G89 -> 7.1 | H106: =+H89 -> 9.5 | I106: =+I89 -> 9.6 | J106: =+J89 -> 17 | K106: =+G106+H106+I106+J106 -> 43.2 | L106: =+L89 -> 17.2 | M106: =+M89 -> 21.8 | N106: =+N89 -> 30.8 | O106: =+O89 -> 31.3 | P106: =+L106+M106+N106+O106 -> 101.1 | Q106: =+Q89 -> 38 | R106: =+R89 -> 39.6 | S106: =+S89 -> 48.3 | T106: =+T89 -> 45.9 | U106: =+Q106+R106+S106+T106 -> 171.8 | V106: =+V89 -> 49.8 | W106: =+W89 -> 61 | X106: =+X89 -> 61.3 | Y106: =+Y89 -> 64.3 | Z106: =+V106+W106+X106+Y106 -> 236.4 | AA106: 65.6 | AB106: 69.9 | AC106: 76.8 | AD106: 81.9 | AE106: =+AA106+AB106+AC106+AD106 -> 294.2 | AF106: 88.4 | AG106: 96.1 | AH106: 98.3 | AI106: 103.1 | AJ106: =+AF106+AG106+AH106+AI106 -> 385.9 | AK106: =+AK89-AK119-AK147-AK168 -> 119.39689 | AL106: =+AL89-AL119-AL147-AL168 -> 122.3773 | AM106: =+AM89-AM119-AM147-AM168 -> 132.3245 | AN106: =+AN89-AN119-AN147-AN168 -> 135.02548 | AO106: =+AK106+AL106+AM106+AN106 -> 509.12417 | AP106: =+AP89-AP119-AP147-AP168 -> 137.90172 | AQ106: =+AQ89-AQ119-AQ147-AQ168 -> 142.58995 | AR106: =+AR89-AR119-AR147-AR168 -> 166.20517 | AS106: =+AS89-AS119-AS147-AS168 -> 169.63395 | AT106: =+AP106+AQ106+AR106+AS106 -> 616.33079 | AU106: =+AU95*AU102/1000000 -> 171.30771 | AV106: =+AV95*AV102/1000000 -> 182.70597 | AW106: =+AW95*AW102/1000000 -> 193.63487 | AX106: =+AX95*AX102/1000000 -> 195.99372 | AY106: =+AU106+AV106+AW106+AX106 -> 743.64228 | AZ106: =+AZ95*AZ102/1000000 -> 220.90406 | BA106: =+BA95*BA102/1000000 -> 217.56788 | BB106: =+BB95*BB102/1000000 -> 220.5286 | BC106: =+BC95*BC102/1000000 -> 216.75359 | BD106: =+AZ106+BA106+BB106+BC106 -> 875.75413 | BE106: =+BE95*BE102/1000000 -> 243.84409 | BF106: =+BF95*BF102/1000000 -> 242.7672 | BG106: =+BG95*BG102/1000000 -> 248.646 | BH106: =+BH95*BH102/1000000 -> 243.84778 | BI106: =+BE106+BF106+BG106+BH106 -> 979.10508 | BJ106: =+BJ95*BJ102/1000000 -> 267.06734 | BK106: =+BK95*BK102/1000000 -> 265.3502 | BL106: =+BL95*BL102/1000000 -> 271.25018 | BM106: =+BM95*BM102/1000000 -> 265.52314 | BN106: =+BJ106+BK106+BL106+BM106 -> 1069.1909 | BO106: =+BO95*BO102/1000000 -> 290.29059 | BP106: =+BP95*BP102/1000000 -> 287.93319 | BQ106: =+BQ95*BQ102/1000000 -> 293.85436 | BR106: =+BR95*BR102/1000000 -> 287.1985 | BS106: =+BO106+BP106+BQ106+BR106 -> 1159.2766 | BT106: =+BT95*BT102/1000000 -> 313.51383 | BU106: =+BU95*BU102/1000000 -> 310.51619 | BV106: =+BV95*BV102/1000000 -> 316.45854 | BW106: =+BW95*BW102/1000000 -> 308.87386 | BX106: =+BT106+BU106+BV106+BW106 -> 1249.3624 | BY106: =+BY95*BY102/1000000 -> 335.57592 | BZ106: =+BZ95*BZ102/1000000 -> 330.84088 | CA106: =+CA95*CA102/1000000 -> 335.6721 | CB106: =+CB95*CB102/1000000 -> 326.21415 | CC106: =+BY106+BZ106+CA106+CB106 -> 1328.303 | CD106: =+CD95*CD102/1000000 -> 354.15451 | CE106: =+CE95*CE102/1000000 -> 348.90728 | CF106: =+CF95*CF102/1000000 -> 353.75544 | CG106: =+CG95*CG102/1000000 -> 343.55443 | CH106: =+CD106+CE106+CF106+CG106 -> 1400.3717 | CI106: =+CI95*CI102/1000000 -> 372.73311 | CJ106: =+CJ95*CJ102/1000000 -> 366.97368 | CK106: =+CK95*CK102/1000000 -> 371.83879 | CL106: =+CL95*CL102/1000000 -> 360.89472 | CM106: =+CI106+CJ106+CK106+CL106 -> 1472.4403
...

Sheet BS
A1: Guardant Health, Inc. (NASDAQ: GH)
A2: Balance Sheet
A3: $ millions except per share data, FY ending Dec
B5: =+IS!B5 -> Mar | C5: =+IS!C5 -> Jun | D5: =+IS!D5 -> Sep | E5: =+IS!E5 -> Dec | F5: =+IS!F5 -> 43070 | G5: =+IS!G5 -> Mar | H5: =+IS!H5 -> Jun | I5: =+IS!I5 -> Sep | ... CM5: =+IS!CM5 -> 49279
B6: =+IS!B6 -> 1Q17A | C6: =+IS!C6 -> 2Q17A | D6: =+IS!D6 -> 3Q17A | E6: =+IS!E6 -> 4Q17A | F6: =+IS!F6 -> FY17A | G6: =+IS!G6 -> 1Q18A | H6: =+IS!H6 -> 2Q18A | I6: =+IS!I6 -> 3Q18A | ... CM6: =+IS!CM6 -> FY34E
A7: ASSETS
A8: Current Assets
A9: Cash and equivalents | E9: =72.28+149.04 -> 221.32 | F9: =E9 -> 221.32 | I9: =113.957+157.385 -> 271.342 | J9: =140.544+278.417 -> 418.961 | K9: =J9 -> 418.961 | L9: =153.79+313.069 -> 466.859 | M9: =174.653+370.974 -> 545.627 | N9: =147.188+375.768 -> 522.956 | O9: =143.228+379.574 -> 522.802 | P9: =O9 -> 522.802 | Q9: =152.239+367.853 -> 520.092 | R9: =164.671+773.16 -> 937.831 | S9: =142.945+870.459 -> 1013.404 | T9: =832.977+961.903 -> 1794.88 | U9: =T9 -> 1794.88 | V9: =869.372+1071.078 -> 1940.45 | W9: =938.59+853.072 -> 1791.662 | X9: =832.37+653.601 -> 1485.971 | Y9: =492.202+440.546 -> 932.748 | Z9: =Y9 -> 932.748 | AA9: =573.604+388.662 -> 962.266 | AB9: =215.169+638.521 -> 853.69 | AC9: =158.31+799.727 -> 958.037 | AD9: =141.647+869.584 -> 1011.231 | AE9: =AD9 -> 1011.231 | AF9: =223.64+713.38 -> 937.02 | AG9: =271.073+953.776 -> 1224.849 | AH9: =457.339+697.482 -> 1154.821 | AI9: =1133.537+35.097 -> 1168.634 | AJ9: =AI9 -> 1168.634 | AK9: =1129.257 -> 1129.257 | AL9: 1035.239 | AM9: =688.368+310.701 -> 999.069 | AN9: =525.54+314.438 -> 839.978 | AO9: =AN9 -> 839.978 | AP9: 698.572 | AQ9: 629.143 | AR9: 580.013 | AS9: =378.203+823.395 -> 1201.598 | AT9: =AS9 -> 1201.598 | AU9: =+AT9+CF!AU45 -> 1131.9718 | AV9: =+AU9+CF!AV45 -> 1066.5279 | AW9: =+AV9+CF!AW45 -> 1036.9216 | AX9: =+AW9+CF!AX45 -> 1029.4271 | AY9: =AX9 -> 1029.4271 | AZ9: =+AY9+CF!AZ45 -> 994.77603 | BA9: =+AZ9+CF!BA45 -> 958.1753 | BB9: =+BA9+CF!BB45 -> 965.90735 | BC9: =+BB9+CF!BC45 -> 523.87214 | BD9: =BC9 -> 523.87214 | BE9: =+BD9+CF!BE45 -> 539.49183 | BF9: =+BE9+CF!BF45 -> 543.51612 | BG9: =+BF9+CF!BG45 -> 610.43301 | BH9: =+BG9+CF!BH45 -> 732.48672 | BI9: =BH9 -> 732.48672 | BJ9: =+BI9+CF!BJ45 -> 826.70255 | BK9: =+BJ9+CF!BK45 -> 870.02401 | BL9: =+BK9+CF!BL45 -> 995.48254 | BM9: =+BL9+CF!BM45 -> 1184.8022 | BN9: =BM9 -> 1184.8022 | BO9: =+BN9+CF!BO45 -> 1334.1826 | BP9: =+BO9+CF!BP45 -> 1429.2265 | BQ9: =+BP9+CF!BQ45 -> 1616.9456 | BR9: =+BQ9+CF!BR45 -> 1880.4116 | BS9: =BR9 -> 1880.4116 | BT9: =+BS9+CF!BT45 -> 1479.1736 | BU9: =+BT9+CF!BU45 -> 1612.301 | BV9: =+BU9+CF!BV45 -> 1849.1129 | BW9: =+BV9+CF!BW45 -> 2168.5073 | BX9: =BW9 -> 2168.5073 | BY9: =+BX9+CF!BY45 -> 2437.529 | BZ9: =+BY9+CF!BZ45 -> 2602.3757 | CA9: =+BZ9+CF!CA45 -> 2882.4262 | CB9: =+CA9+CF!CB45 -> 3249.1917 | CC9: =CB9 -> 3249.1917 | CD9: =+CC9+CF!CD45 -> 3559.8523 | CE9: =+CD9+CF!CE45 -> 3372.3051 | CF9: =+CE9+CF!CF45 -> 3690.6748 | CG9: =+CF9+CF!CG45 -> 4099.1723 | CH9: =CG9 -> 4099.1723 | CI9: =+CH9+CF!CI45 -> 4445.0161 | CJ9: =+CI9+CF!CJ45 -> 4672.9631 | CK9: =+CJ9+CF!CK45 -> 5022.9595 | CL9: =+CK9+CF!CL45 -> 5463.2198 | CM9: =CL9 -> 5463.2198
A10: Accounts receivable, net | E10: 12.787 | F10: =E10 -> 12.787 | I10: 14.64 | J10: 35.69 | K10: =J10 -> 35.69 | L10: 28.989 | M10: 40.363 | N10: 39.689 | O10: 47.986 | P10: =O10 -> 47.986 | Q10: 48.015 | R10: 41.017 | S10: 36.255 | T10: 53.299 | U10: =T10 -> 53.299 | V10: 48.039 | W10: 53.667 | X10: 60.744 | Y10: 97.652 | Z10: =Y10 -> 97.652 | AA10: 84.331 | AB10: 95.276 | AC10: 86.2 | AD10: 97.256 | AE10: =AD10 -> 97.256 | AF10: 87.204 | AG10: 86.468 | AH10: 88.801 | AI10: 88.783 | AJ10: =AI10 -> 88.783 | AK10: 84.562 | AL10: 100.519 | AM10: 88.465 | AN10: 110.253 | AO10: =AN10 -> 110.253 | AP10: 115.426 | AQ10: 130.252 | AR10: 115.585 | AS10: 137.849 | AT10: =AS10 -> 137.849 | AU10: =AU70/365*AU66 -> 130.70408 | AV10: =AV70/365*AV66 -> 134.25116 | AW10: =AW70/365*AW66 -> 136.70126 | AX10: =AX70/365*AX66 -> 138.89649 | AY10: =AX10 -> 138.89649 | AZ10: =AZ70/365*AZ66 -> 149.07644 | BA10: =BA70/365*BA66 -> 163.36707 | BB10: =BB70/365*BB66 -> 176.69672 | BC10: =BC70/365*BC66 -> 190.73595 | BD10: =BC10 -> 190.73595 | BE10: =BE70/365*BE66 -> 205.26688 | BF10: =BF70/365*BF66 -> 220.26931 | BG10: =BG70/365*BG66 -> 235.94352 | BH10: =BH70/365*BH66 -> 251.83247 | BI10: =BH10 -> 251.83247 | BJ10: =BJ70/365*BJ66 -> 265.87382 | BK10: =BK70/365*BK66 -> 279.09388 | BL10: =BL70/365*BL66 -> 292.77301 | BM10: =BM70/365*BM66 -> 305.82961 | BN10: =BM10 -> 305.82961 | BO10: =BO70/365*BO66 -> 319.42682 | BP10: =BP70/365*BP66 -> 334.20977 | BQ10: =BQ70/365*BQ66 -> 348.35082 | BR10: =BR70/365*BR66 -> 362.5809 | BS10: =BR10 -> 362.5809 | BT10: =BT70/365*BT66 -> 375.34391 | BU10: =BU70/365*BU66 -> 387.44802 | BV10: =BV70/365*BV66 -> 399.21763 | BW10: =BW70/365*BW66 -> 410.62933 | BX10: =BW10 -> 410.62933 | BY10: =BY70/365*BY66 -> 420.72944 | BZ10: =BZ70/365*BZ66 -> 430.37004 | CA10: =CA70/365*CA66 -> 440.41324 | CB10: =CB70/365*CB66 -> 450.2579 | CC10: =CB10 -> 450.2579 | CD10: =CD70/365*CD66 -> 460.23163 | CE10: =CE70/365*CE66 -> 470.80171 | CF10: =CF70/365*CF66 -> 480.43908 | CG10: =CG70/365*CG66 -> 489.79642 | CH10: =CG10 -> 489.79642 | CI10: =CI70/365*CI66 -> 498.24566 | CJ10: =CJ70/365*CJ66 -> 506.10397 | CK10: =CK70/365*CK66 -> 513.56621 | CL10: =CL70/365*CL66 -> 520.68687 | CM10: =CL10 -> 520.68687
A11: Inventory | E11: 7.287 | F11: =E11 -> 7.287 | I11: 7.075 | J11: 9.136 | K11: =J11 -> 9.136 | L11: 10.256 | M11: 14.176 | N11: 14.76 | O11: 15.181 | P11: =O11 -> 15.181 | Q11: 25.148 | R11: 20.354 | S11: 27.731 | T11: 22.716 | U11: =T11 -> 22.716 | V11: 28.876 | W11: 26.494 | X11: 24.739 | Y11: 30.674 | Z11: =Y11 -> 30.674 | AA11: 36.613 | AB11: 59.89 | AC11: 63.047 | AD11: 51.598 | AE11: =AD11 -> 51.598 | AF11: 46.474 | AG11: 60.529 | AH11: 77.036 | AI11: 61.948 | AJ11: =AI11 -> 61.948 | AK11: 62.991 | AL11: 66.984 | AM11: 72.298 | AN11: 71.083 | AO11: =AN11 -> 71.083 | AP11: 77.256 | AQ11: 84.061 | AR11: 90.489 | AS11: 85.876 | AT11: =AS11 -> 85.876 | AU11: =AU74/365*AU67 -> 90.534427 | AV11: =AV74/365*AV67 -> 98.292869 | AW11: =AW74/365*AW67 -> 107.85302 | AX11: =AX74/365*AX67 -> 118.22771 | AY11: =AX11 -> 118.22771 | AZ11: =AZ74/365*AZ67 -> 124.49326 | BA11: =BA74/365*BA67 -> 135.86586 | BB11: =BB74/365*BB67 -> 146.35604 | BC11: =BC74/365*BC67 -> 157.33704 | BD11: =BC11 -> 157.33704 | BE11: =BE74/365*BE67 -> 168.96776 | BF11: =BF74/365*BF67 -> 180.57906 | BG11: =BG74/365*BG67 -> 192.64518 | BH11: =BH74/365*BH67 -> 204.77772 | BI11: =BH11 -> 204.77772 | BJ11: =BJ74/365*BJ67 -> 215.66104 | BK11: =BK74/365*BK67 -> 225.49291 | BL11: =BL74/365*BL67 -> 235.60175 | BM11: =BM74/365*BM67 -> 245.11909 | BN11: =BM11 -> 245.11909 | BO11: =BO74/365*BO67 -> 255.30929 | BP11: =BP74/365*BP67 -> 266.05829 | BQ11: =BQ74/365*BQ67 -> 276.2049 | BR11: =BR74/365*BR67 -> 286.3267 | BS11: =BR11 -> 286.3267 | BT11: =BT74/365*BT67 -> 295.52753 | BU11: =BU74/365*BU67 -> 303.84946 | BV11: =BV74/365*BV67 -> 311.83206 | BW11: =BW74/365*BW67 -> 319.45576 | BX11: =BW11 -> 319.45576 | BY11: =BY74/365*BY67 -> 326.25557 | BZ11: =BZ74/365*BZ67 -> 332.41001 | CA11: =CA74/365*CA67 -> 338.80272 | CB11: =CB74/365*CB67 -> 344.97312 | CC11: =CB11 -> 344.97312 | CD11: =CD74/365*CD67 -> 351.43562 | CE11: =CE74/365*CE67 -> 358.06034 | CF11: =CF74/365*CF67 -> 363.91179 | CG11: =CG74/365*CG67 -> 369.4869 | CH11: =CG11 -> 369.4869 | CI11: =CI74/365*CI67 -> 374.54777 | CJ11: =CJ74/365*CJ67 -> 378.91603 | CK11: =CK74/365*CK67 -> 382.93881 | CL11: =CL74/365*CL67 -> 386.65672 | CM11: =CL11 -> 386.65672
A12: Other current assets | E12: 1.541 | F12: =E12 -> 1.541 | I12: 4.024 | J12: 5.204 | K12: =J12 -> 5.204 | L12: 6.151 | M12: 4.082 | N12: 5.657 | O12: 11.389 | P12: =O12 -> 11.389 | Q12: 14.137 | R12: 11.101 | S12: 9.898 | T12: 17.466 | U12: =T12 -> 17.466 | V12: 15.679 | W12: 19.236 | X12: 21.958 | Y12: 53.052 | Z12: =Y12 -> 53.052 | AA12: 30.07 | AB12: 28.283 | AC12: 23.565 | AD12: 31.509 | AE12: =AD12 -> 31.509 | AF12: 33.762 | AG12: 25.809 | AH12: 26.239 | AI12: 27.741 | AJ12: =AI12 -> 27.741 | AK12: 31.736 | AL12: 87.232 | AM12: =66.883 -> 66.883 | AN12: =33.8 -> 33.8 | AO12: =AN12 -> 33.8 | AP12: 35.772 | AQ12: 39.976 | AR12: 42.798 | AS12: =40.723 -> 40.723 | AT12: =AS12 -> 40.723 | AU12: =AT12 -> 40.723 | AV12: =AU12 -> 40.723 | AW12: =AV12 -> 40.723 | AX12: =AW12 -> 40.723 | AY12: =AX12 -> 40.723 | AZ12: =AY12 -> 40.723 | BA12: =AZ12 -> 40.723 | ... CM12: =CL12 -> 40.723
A13: Total current assets | E13: =SUM(E9:E12) -> 242.935 | F13: =SUM(F9:F12) -> 242.935 | I13: =SUM(I9:I12) -> 297.081 | J13: =SUM(J9:J12) -> 468.991 | K13: =J13 -> 468.991 | L13: =SUM(L9:L12) -> 512.255 | M13: =SUM(M9:M12) -> 604.248 | N13: =SUM(N9:N12) -> 583.062 | O13: =SUM(O9:O12) -> 597.358 | P13: =SUM(P9:P12) -> 597.358 | Q13: =SUM(Q9:Q12) -> 607.392 | R13: =SUM(R9:R12) -> 1010.303 | S13: =SUM(S9:S12) -> 1087.288 | ... CM13: =SUM(CM9:CM12) -> 6411.2864
A15: Plant, property, and equipment, net | E15: 16.036 | F15: =E15 -> 16.036 | I15: 30.318 | J15: 31.003 | K15: =J15 -> 31.003 | L15: 30.581 | M15: 34.811 | N15: 40.759 | O15: 43.668 | P15: =O15 -> 43.668 | Q15: 46.685 | R15: 56.995 | S15: 61.882 | T15: 62.782 | U15: =T15 -> 62.782 | V15: 71.765 | W15: 89.737 | X15: 106.156 | Y15: 124.461 | Z15: =Y15 -> 124.461 | AA15: 151.322 | AB15: 163.362 | AC15: 168.007 | AD15: 167.92 | AE15: =AD15 -> 167.92 | AF15: 163.229 | AG15: 155.741 | AH15: 147.671 | AI15: 145.096 | AJ15: =AI15 -> 145.096 | AK15: 138.387 | AL15: 132.317 | AM15: 125.169 | AN15: 136.813 | AO15: =AN15 -> 136.813 | AP15: 129.294 | AQ15: 126.141 | AR15: 124.609 | AS15: 145.915 | AT15: =AS15 -> 145.915 | AU15: ='Other Accts'!AU50 -> 144.89194 | AV15: ='Other Accts'!AV50 -> 143.92573 | AW15: ='Other Accts'!AW50 -> 143.01319 | AX15: ='Other Accts'!AX50 -> 142.15134 | AY15: =AX15 -> 142.15134 | AZ15: ='Other Accts'!AZ50 -> 143.69849 | BA15: ='Other Accts'!BA50 -> 145.15968 | BB15: ='Other Accts'!BB50 -> 146.5397 | BC15: ='Other Accts'!BC50 -> 147.84305 | BD15: =BC15 -> 147.84305 | BE15: ='Other Accts'!BE50 -> 151.4351 | BF15: ='Other Accts'!BF50 -> 154.8276 | BG15: ='Other Accts'!BG50 -> 158.03162 | BH15: ='Other Accts'!BH50 -> 161.05764 | BI15: =BH15 -> 161.05764 | BJ15: ='Other Accts'!BJ50 -> 166.27666 | BK15: ='Other Accts'!BK50 -> 171.20574 | BL15: ='Other Accts'!BL50 -> 175.86097 | BM15: ='Other Accts'!BM50 -> 180.25759 | BN15: =BM15 -> 180.25759 | BO15: ='Other Accts'!BO50 -> 185.5905 | BP15: ='Other Accts'!BP50 -> 190.62714 | BQ15: ='Other Accts'!BQ50 -> 195.38396 | BR15: ='Other Accts'!BR50 -> 199.87652 | BS15: =BR15 -> 199.87652 | BT15: ='Other Accts'!BT50 -> 205.30005 | BU15: ='Other Accts'!BU50 -> 210.42227 | BV15: ='Other Accts'!BV50 -> 215.25992 | BW15: ='Other Accts'!BW50 -> 219.82881 | BX15: =BW15 -> 219.82881 | BY15: ='Other Accts'!BY50 -> 225.32443 | BZ15: ='Other Accts'!BZ50 -> 230.51474 | CA15: ='Other Accts'!CA50 -> 235.4167 | CB15: ='Other Accts'!CB50 -> 240.04633 | CC15: =CB15 -> 240.04633 | CD15: ='Other Accts'!CD50 -> 245.59931 | CE15: ='Other Accts'!CE50 -> 250.84379 | CF15: ='Other Accts'!CF50 -> 255.79692 | CG15: ='Other Accts'!CG50 -> 260.47487 | CH15: =CG15 -> 260.47487 | CI15: ='Other Accts'!CI50 -> 266.07348 | CJ15: ='Other Accts'!CJ50 -> 271.36107 | CK15: ='Other Accts'!CK50 -> 276.3549 | CL15: ='Other Accts'!CL50 -> 281.07129 | CM15: =CL15 -> 281.07129
A16: Intangible assets, net | E16: 0 | F16: =E16 -> 0 | I16: 0 | J16: 0 | K16: =J16 -> 0 | L16: 0 | M16: 8.987 | N16: 8.755 | O16: 8.524 | P16: =O16 -> 8.524 | Q16: 17.681 | R16: 17.148 | S16: 16.645 | T16: 16.155 | U16: =T16 -> 16.155 | V16: 15.674 | W16: 15.189 | X16: 14.698 | Y16: 14.207 | Z16: =Y16 -> 14.207 | AA16: 13.727 | AB16: 13.108 | AC16: 12.417 | AD16: 11.727 | AE16: =AD16 -> 11.727 | AF16: 11.047 | AG16: 10.361 | AH16: 9.67 | AI16: 8.979 | AJ16: =AI16 -> 8.979 | AK16: 8.294 | AL16: 7.742 | AM16: 7.251 | AN16: 6.76 | AO16: =AN16 -> 6.76 | AP16: 6.28 | AQ16: 5.864 | AR16: 5.477 | AS16: 25.921 | AT16: =AS16 -> 25.921 | AU16: ='Other Accts'!AU58 -> 25.110969 | AV16: ='Other Accts'!AV58 -> 24.300937 | AW16: ='Other Accts'!AW58 -> 23.490906 | AX16: ='Other Accts'!AX58 -> 22.680875 | AY16: =AX16 -> 22.680875 | AZ16: ='Other Accts'!AZ58 -> 21.972098 | BA16: ='Other Accts'!BA58 -> 21.26332 | BB16: ='Other Accts'!BB58 -> 20.554543 | BC16: ='Other Accts'!BC58 -> 19.845766 | BD16: =BC16 -> 19.845766 | BE16: ='Other Accts'!BE58 -> 19.225585 | BF16: ='Other Accts'!BF58 -> 18.605405 | BG16: ='Other Accts'!BG58 -> 17.985225 | BH16: ='Other Accts'!BH58 -> 17.365045 | BI16: =BH16 -> 17.365045 | BJ16: ='Other Accts'!BJ58 -> 16.822387 | BK16: ='Other Accts'!BK58 -> 16.27973 | BL16: ='Other Accts'!BL58 -> 15.737072 | BM16: ='Other Accts'!BM58 -> 15.194414 | BN16: =BM16 -> 15.194414 | BO16: ='Other Accts'!BO58 -> 14.719589 | BP16: ='Other Accts'!BP58 -> 14.244763 | BQ16: ='Other Accts'!BQ58 -> 13.769938 | BR16: ='Other Accts'!BR58 -> 13.295113 | BS16: =BR16 -> 13.295113 | BT16: ='Other Accts'!BT58 -> 12.87964 | BU16: ='Other Accts'!BU58 -> 12.464168 | BV16: ='Other Accts'!BV58 -> 12.048696 | BW16: ='Other Accts'!BW58 -> 11.633223 | BX16: =BW16 -> 11.633223 | BY16: ='Other Accts'!BY58 -> 11.269685 | BZ16: ='Other Accts'!BZ58 -> 10.906147 | CA16: ='Other Accts'!CA58 -> 10.542609 | CB16: ='Other Accts'!CB58 -> 10.179071 | CC16: =CB16 -> 10.179071 | CD16: ='Other Accts'!CD58 -> 9.8609746 | CE16: ='Other Accts'!CE58 -> 9.5428786 | CF16: ='Other Accts'!CF58 -> 9.2247827 | CG16: ='Other Accts'!CG58 -> 8.9066867 | CH16: =CG16 -> 8.9066867 | CI16: ='Other Accts'!CI58 -> 8.6283527 | CJ16: ='Other Accts'!CJ58 -> 8.3500188 | CK16: ='Other Accts'!CK58 -> 8.0716848 | CL16: ='Other Accts'!CL58 -> 7.7933509 | CM16: =CL16 -> 7.7933509
A17: Goodwill, net | E17: 0 | F17: =E17 -> 0 | I17: 0 | J17: 0 | K17: =J17 -> 0 | L17: 0 | M17: 2.935 | N17: 2.928 | O17: 3.29 | P17: =O17 -> 3.29 | Q17: 3.29 | R17: 3.29 | S17: 3.29 | T17: 3.29 | U17: =T17 -> 3.29 | V17: 3.29 | W17: 3.29 | X17: 3.29 | Y17: 3.29 | Z17: =Y17 -> 3.29 | AA17: 3.29 | AB17: 3.29 | AC17: 3.29 | AD17: 3.29 | AE17: =AD17 -> 3.29 | AF17: 3.29 | AG17: 3.29 | AH17: 3.29 | AI17: 3.29 | AJ17: =AI17 -> 3.29 | AK17: 3.29 | AL17: 3.29 | AM17: 3.29 | AN17: 3.29 | AO17: =AN17 -> 3.29 | AP17: 3.29 | AQ17: 3.29 | AR17: 3.29 | AS17: 77.257 | AT17: =AS17 -> 77.257 | AU17: ='Other Accts'!AU65 -> 77.257 | AV17: ='Other Accts'!AV65 -> 77.257 | AW17: ='Other Accts'!AW65 -> 77.257 | AX17: ='Other Accts'!AX65 -> 77.257 | AY17: =AX17 -> 77.257 | AZ17: ='Other Accts'!AZ65 -> 77.257 | BA17: ='Other Accts'!BA65 -> 77.257 | BB17: ='Other Accts'!BB65 -> 77.257 | BC17: ='Other Accts'!BC65 -> 77.257 | BD17: =BC17 -> 77.257 | BE17: ='Other Accts'!BE65 -> 77.257 | BF17: ='Other Accts'!BF65 -> 77.257 | BG17: ='Other Accts'!BG65 -> 77.257 | BH17: ='Other Accts'!BH65 -> 77.257 | BI17: =BH17 -> 77.257 | BJ17: ='Other Accts'!BJ65 -> 77.257 | BK17: ='Other Accts'!BK65 -> 77.257 | BL17: ='Other Accts'!BL65 -> 77.257 | BM17: ='Other Accts'!BM65 -> 77.257 | BN17: =BM17 -> 77.257 | BO17: ='Other Accts'!BO65 -> 77.257 | BP17: ='Other Accts'!BP65 -> 77.257 | BQ17: ='Other Accts'!BQ65 -> 77.257 | BR17: ='Other Accts'!BR65 -> 77.257 | BS17: =BR17 -> 77.257 | BT17: ='Other Accts'!BT65 -> 77.257 | BU17: ='Other Accts'!BU65 -> 77.257 | BV17: ='Other Accts'!BV65 -> 77.257 | BW17: ='Other Accts'!BW65 -> 77.257 | BX17: =BW17 -> 77.257 | BY17: ='Other Accts'!BY65 -> 77.257 | BZ17: ='Other Accts'!BZ65 -> 77.257 | CA17: ='Other Accts'!CA65 -> 77.257 | CB17: ='Other Accts'!CB65 -> 77.257 | CC17: =CB17 -> 77.257 | CD17: ='Other Accts'!CD65 -> 77.257 | CE17: ='Other Accts'!CE65 -> 77.257 | CF17: ='Other Accts'!CF65 -> 77.257 | CG17: ='Other Accts'!CG65 -> 77.257 | CH17: =CG17 -> 77.257 | CI17: ='Other Accts'!CI65 -> 77.257 | CJ17: ='Other Accts'!CJ65 -> 77.257 | CK17: ='Other Accts'!CK65 -> 77.257 | CL17: ='Other Accts'!CL65 -> 77.257 | CM17: =CL17 -> 77.257
A18: Other non-current assets | E18: =73.254+8.739+1.974 -> 83.967 | F18: =E18 -> 83.967 | I18: =2.963+8.044+4.257+1.936 -> 17.2 | J18: =77.563+7.8+2.046 -> 87.409 | K18: =J18 -> 87.409 | L18: =25.916+7.557+2.862 -> 36.335 | M18: =7.313+1.235+3.159+277.301 -> 289.008 | N18: =302.624+7.133+3.073 -> 312.83 | O18: =29.14+6.89+4.882+268.783 -> 309.695 | P18: =O18 -> 309.695 | Q18: =238.206+30.132+0.06+4.721 -> 273.119 | R18: =146.118+38.503+0.055+5.124 -> 189.8 | S18: =51.398+36.103+0.05+5.453 -> 93.004 | T18: =246.597+37.343+0.045+17.208 -> 301.193 | U18: =T18 -> 301.193 | V18: =205.671+17.297 -> 222.968 | W18: =55.368+200.958+36.284 -> 292.61 | X18: =250.226+196.436+61.316 -> 507.978 | Y18: =698.034+189.443+60.938 -> 948.415 | Z18: =Y18 -> 948.415 | AA18: =588.453+188.607+70.919 -> 847.979 | AB18: =382.575+183.703+70.56 -> 636.838 | AC18: =156.741+178.747+51.728 -> 387.216 | AD18: =174.001+61.453 -> 235.454 | AE18: =AD18 -> 235.454 | AF18: =170.651+58.954 -> 229.605 | AG18: =165.273+107.697 -> 272.97 | AH18: =161.668+128.035 -> 289.703 | AI18: =157.616+124.334 -> 281.95 | AJ18: =AI18 -> 281.95 | AK18: =151.881+94.2 -> 246.081 | AL18: =146.111+29.906 -> 176.017 | AM18: =144.964+31.338 -> 176.302 | AN18: =104.215+142.265+37.152 -> 283.632 | AO18: =AN18 -> 283.632 | AP18: =32.555+105.281+140.5 -> 278.336 | AQ18: =169.768+37.167+106.337 -> 313.272 | AR18: =163.55+41.473+109.502 -> 314.525 | AS18: =111.214+158.849+28.457 -> 298.52 | AT18: =AS18 -> 298.52 | AU18: =AT18 -> 298.52 | AV18: =AU18 -> 298.52 | AW18: =AV18 -> 298.52 | AX18: =AW18 -> 298.52 | AY18: =AX18 -> 298.52 | AZ18: =AY18 -> 298.52 | BA18: =AZ18 -> 298.52 | ... CM18: =CL18 -> 298.52
A19: Total long-term assets | E19: =SUM(E15:E18) -> 100.003 | F19: =E19 -> 100.003 | I19: =+I15+I16+I17+I18 -> 47.518 | J19: =+J15+J16+J17+J18 -> 118.412 | K19: =+K15+K16+K17+K18 -> 118.412 | L19: =+L15+L16+L17+L18 -> 66.916 | M19: =+M15+M16+M17+M18 -> 335.741 | N19: =+N15+N16+N17+N18 -> 365.272 | O19: =+O15+O16+O17+O18 -> 365.177 | P19: =+P15+P16+P17+P18 -> 365.177 | ... CL19: =+CL15+CL16+CL17+CL18 -> 664.64164 | CM19: =CL19 -> 664.64164
A21: Total assets | E21: =E13+E19 -> 342.938 | F21: =E21 -> 342.938 | I21: =I13+I19 -> 344.599 | J21: =J13+J19 -> 587.403 | K21: =J21 -> 587.403 | L21: =L13+L19 -> 579.171 | M21: =M13+M19 -> 939.989 | N21: =N13+N19 -> 948.334 | O21: =O13+O19 -> 962.535 | P21: =O21 -> 962.535 | Q21: =Q13+Q19 -> 948.167 | R21: =R13+R19 -> 1277.536 | S21: =S13+S19 -> 1262.109 | T21: =T13+T19 -> 2271.781 | U21: =T21 -> 2271.781 | V21: =V13+V19 -> 2346.741 | W21: =W13+W19 -> 2291.885 | X21: =X13+X19 -> 2225.534 | Y21: =Y13+Y19 -> 2204.499 | Z21: =Z13+Z19 -> 2204.499 | AA21: =AA13+AA19 -> 2129.598 | AB21: =AB13+AB19 -> 1853.737 | AC21: =AC13+AC19 -> 1701.779 | ... AI21: =AI13+AI19 -> 1786.421 | AJ21: =AI21 -> 1786.421 | AK21: =AK13+AK19 -> 1704.598 | AL21: =AL13+AL19 -> 1609.34 | AM21: =AM13+AM19 -> 1538.727 | AN21: =AN13+AN19 -> 1485.609 | AO21: =AN21 -> 1485.609 | AP21: =AP13+AP19 -> 1344.226 | AQ21: =AQ13+AQ19 -> 1331.999 | AR21: =AR13+AR19 -> 1276.786 | AS21: =AS13+AS19 -> 2013.659 | AT21: =AS21 -> 2013.659 | AU21: =AU13+AU19 -> 1939.7133 | AV21: =AV13+AV19 -> 1883.7986 | AW21: =AW13+AW19 -> 1864.48 | AX21: =AX13+AX19 -> 1867.8835 | AY21: =AX21 -> 1867.8835 | AZ21: =AZ13+AZ19 -> 1850.5163 | BA21: =BA13+BA19 -> 1840.3312 | BB21: =BB13+BB19 -> 1872.5544 | BC21: =BC13+BC19 -> 1456.134 | BD21: =BC21 -> 1456.134 | BE21: =BE13+BE19 -> 1500.8872 | BF21: =BF13+BF19 -> 1534.2975 | BG21: =BG13+BG19 -> 1631.5386 | BH21: =BH13+BH19 -> 1784.0196 | BI21: =BH21 -> 1784.0196 | BJ21: =BJ13+BJ19 -> 1907.8365 | BK21: =BK13+BK19 -> 1978.5963 | BL21: =BL13+BL19 -> 2131.9553 | BM21: =BM13+BM19 -> 2347.7029 | BN21: =BM21 -> 2347.7029 | BO21: =BO13+BO19 -> 2525.7288 | BP21: =BP13+BP19 -> 2650.8665 | BQ21: =BQ13+BQ19 -> 2867.1552 | BR21: =BR13+BR19 -> 3158.9909 | BS21: =BR21 -> 3158.9909 | BT21: =BT13+BT19 -> 2784.7247 | BU21: =BU13+BU19 -> 2942.9849 | BV21: =BV13+BV19 -> 3203.9711 | BW21: =BW13+BW19 -> 3546.5545 | BX21: =BW21 -> 3546.5545 | BY21: =BY13+BY19 -> 3837.6081 | BZ21: =BZ13+BZ19 -> 4023.0766 | CA21: =CA13+CA19 -> 4324.1015 | CB21: =CB13+CB19 -> 4711.1481 | CC21: =CB21 -> 4711.1481 | CD21: =CD13+CD19 -> 5043.4799 | CE21: =CE13+CE19 -> 4878.0538 | CF21: =CF13+CF19 -> 5216.5473 | CG21: =CG13+CG19 -> 5644.3372 | CH21: =CG21 -> 5644.3372 | CI21: =CI13+CI19 -> 6009.0114 | CJ21: =CJ13+CJ19 -> 6254.1942 | CK21: =CK13+CK19 -> 6620.3911 | CL21: =CL13+CL19 -> 7075.928 | CM21: =CL21 -> 7075.928
A23: LIABILITIES AND SHAREHOLDERS' EQUITY
A24: Current Liabilities
A25: Accounts payable | E25: 4.998 | F25: =E25 -> 4.998 | I25: 13.081 | J25: 10.642 | K25: =J25 -> 10.642 | L25: 7.163 | M25: 15.7 | N25: 12.054 | O25: 16.197 | P25: =O25 -> 16.197 | Q25: 24.378 | R25: 15.982 | S25: 18.281 | T25: 7.34 | U25: =T25 -> 7.34 | V25: 22.318 | W25: 21.399 | X25: 15.674 | Y25: 17.58 | Z25: =Y25 -> 17.58 | AA25: 32.23 | AB25: 36.971 | AC25: 40.911 | AD25: 0 | AE25: =AD25 -> 0 | AF25: 0 | AG25: 0 | AH25: 0 | AI25: 0 | AJ25: =AI25 -> 0 | AK25: 37.603 | AL25: 42.447 | AM25: 15.473 | AN25: 38.551 | AO25: =AN25 -> 38.551 | AP25: 49.77 | AQ25: 44.802 | AR25: 20.142 | AS25: 54.442 | AT25: =AS25 -> 54.442 | AU25: =AU78*AU67/365 -> 59.28121 | AV25: =AV78*AV67/365 -> 27.303575 | AW25: =AW78*AW67/365 -> 29.307885 | AX25: =AX78*AX67/365 -> 74.206752 | AY25: =AX25 -> 74.206752 | AZ25: =AZ78*AZ67/365 -> 81.517179 | BA25: =BA78*BA67/365 -> 37.740517 | BB25: =BB78*BB67/365 -> 40.654455 | BC25: =BC78*BC67/365 -> 103.14317 | BD25: =BC25 -> 103.14317 | BE25: =BE78*BE67/365 -> 110.63872 | BF25: =BF78*BF67/365 -> 50.16085 | BG25: =BG78*BG67/365 -> 53.512551 | BH25: =BH78*BH67/365 -> 134.24317 | BI25: =BH25 -> 134.24317 | BJ25: =BJ78*BJ67/365 -> 141.2131 | BK25: =BK78*BK67/365 -> 62.63692 | BL25: =BL78*BL67/365 -> 65.44493 | BM25: =BM78*BM67/365 -> 160.68918 | BN25: =BM25 -> 160.68918 | BO25: =BO78*BO67/365 -> 167.17446 | BP25: =BP78*BP67/365 -> 73.905082 | BQ25: =BQ78*BQ67/365 -> 76.723583 | BR25: =BR78*BR67/365 -> 187.70306 | BS25: =BR25 -> 187.70306 | BT25: =BT78*BT67/365 -> 193.50904 | BU25: =BU78*BU67/365 -> 84.402628 | BV25: =BV78*BV67/365 -> 86.620016 | BW25: =BW78*BW67/365 -> 209.421 | BX25: =BW25 -> 209.421 | BY25: =BY78*BY67/365 -> 213.62951 | BZ25: =BZ78*BZ67/365 -> 92.336113 | CA25: =CA78*CA67/365 -> 94.111867 | CB25: =CB78*CB67/365 -> 226.14904 | CC25: =CB25 -> 226.14904 | CD25: =CD78*CD67/365 -> 230.1172 | CE25: =CE78*CE67/365 -> 99.461206 | CF25: =CF78*CF67/365 -> 101.08661 | CG25: =CG78*CG67/365 -> 242.21919 | CH25: =CG25 -> 242.21919 | CI25: =CI78*CI67/365 -> 245.25085 | CJ25: =CJ78*CJ67/365 -> 105.25445 | CK25: =CK78*CK67/365 -> 106.37189 | CL25: =CL78*CL67/365 -> 253.47496 | CM25: =CL25 -> 253.47496
