Workbook
Name Billings: #REF!
Name Billings: #REF!
Name Billings: #REF!
Name BS: 'Balance Sheet'!$A$1:$BL$76
Name CF: 'Cash Flow'!$A$1:$BR$78
Name Current: #REF!
Name Current: #REF!
Name Current: #REF!
Name Current: #REF!
Name Current_Net_Cash: #REF!
Name Current_Shares: #REF!
Name Current_Shares: #REF!
Name Current_Shares: #REF!
Name Current_Shares: #REF!
Name Current_Shares: #REF!
Name Debt: #REF!
Name Rating: #REF!
Name Rating: #REF!
Name Rating: #REF!
Name Rating: #REF!
Name Rating: #REF!
Name REV: 'Revenue Build'!$A$1:$BL$677
Name REV_NOW: [1]Rev!$A$1:$EU$190
Name Target: #REF!

Sheet __FDSCACHE__
B1: This sheet contains FactSet XML data for use with this workbook's =FDS codes. Modifying the worksheet's contents may damage the workbook's =FDS functionality.

Sheet WFS
C5: Equity Research
C7: Financial Model
C8: Software
C9: 46090
C12: Intuit Inc.
C17: Wells Fargo Software Team
C19: Michael Turrin
C20: Senior Analyst
C21: +1 (628) 629-7565
C22: michael.turrin@wellsfargo.com
C24: Austin Williams | E24: Rich Poland | G24: Ronit Shah | I24: Griffin MacMaster
C25: Associate Analyst | E25: Associate Analyst | G25: Associate Analyst | I25: Associate Analyst
C26: +1 (628) 629-7572 | E26: +1 (212) 214-5333 | G26: +1 (212) 214-1379 | I26: +1 (908) 566-6943
C27: austin.r.williams@wellsfargo.com | E27: richard.d.poland@wellsfargo.com | G27: ronit.shah@wellsfargo.com | I27: griffin.macmaster@wellsfargo.com
C32: Important Disclaimers:
AD45: 1 | AE45: +RC[-1]+1*R[-5]C

Sheet Income Statement
A1: Intuit, Inc.
A2: Income Statement | N2: 2019/1F | O2: 2019/2F | P2: 2019/3F | Q2: 2019/4F | R2: 2020/1F | S2: 2020/2F | T2: 2020/3F | U2: 2020/4F | V2: 2021/1F | W2: 2021/2F | X2: 2021/3F | Y2: 2021/4F | Z2: 2022/1F | AA2: 2022/2F | AB2: 2022/3F | AC2: 2022/4F | AD2: 2023/1F | AE2: 2023/2F | AF2: 2023/3F | AG2: 2023/4F | AH2: 2024/1F | AI2: 2024/2F | AJ2: 2024/3F | AK2: 2024/4F | AL2: 2025/1F | AM2: 2025/2F | AN2: 2025/3F | AO2: 2025/4F | AP2: 2026/1F | AQ2: 2026/2F | AR2: 2026/3F | AS2: 2026/4F | AT2: 2027/1F | AU2: 2027/2F | AV2: 2027/3F | AW2: 2027/4F | AX2: 2028/1F | AY2: 2028/2F | AZ2: 2028/3F | BA2: 2028/4F
B3: Fiscal 2016 | F3: Fiscal 2017 | J3: Fiscal 2018 | N3: Fiscal 2019 | R3: Fiscal 2020 | V3: Fiscal 2021 | Z3: Fiscal 2022 | AD3: Fiscal 2023 | AH3: Fiscal 2024 | AL3: Fiscal 2025 | AP3: Fiscal 2026 | AT3: Fiscal 2027 | AX3: Fiscal 2028
A4: ($ in millions, unless otherwise stated) | B4: 42308 | C4: 42400 | D4: 42490 | E4: 42582 | F4: 42674 | G4: 42766 | H4: 42855 | I4: 42947 | J4: 43039 | K4: 43131 | L4: 43220 | M4: 43312 | N4: 43404 | O4: 43496 | P4: 43585 | Q4: 43677 | R4: 43769 | S4: 43861 | T4: 43951 | U4: 44043 | V4: 44135 | W4: Jan-21 | X4: Apr-21 | Y4: Jul-21 | Z4: Oct-21 | AA4: Jan-22 | AB4: Apr-22 | AC4: Jul-22 | AD4: Oct-22 | AE4: Jan-23 | AF4: Apr-23 | AG4: Jul-23 | AH4: Oct-23 | AI4: Jan-24 | AJ4: Apr-24 | AK4: Jul-24 | AL4: Oct-24 | AM4: Jan-25 | AN4: Apr-25 | AO4: Jul-25 | AP4: Oct-25 | AQ4: Jan-26 | AR4: Apr-26E | AS4: Jul-26E | AT4: Oct-26E | AU4: Jan-27E | AV4: Apr-27E | AW4: Jul-27E | AX4: Oct-27E | AY4: Jan-28E | AZ4: Apr-28E | BA4: Jul-28E | BC4: FY15 | BD4: FY16 | BE4: FY17 | BF4: FY18 | BG4: FY19 | BH4: FY20 | BI4: FY21 | BJ4: FY22 | BK4: FY23 | BL4: FY24 | BM4: FY25 | BN4: FY26E | BO4: FY27E | BP4: FY28E
A5: Non-GAAP Income Statement
A6: Revenue
A7: Product Revenue | B7: =+'Revenue Build'!B13 -> 271 | C7: =+'Revenue Build'!C13 -> 264 | D7: =+'Revenue Build'!D13 -> 459 | E7: =+'Revenue Build'!E13 -> 295 | F7: =+'Revenue Build'!F13 -> 297 | G7: =+'Revenue Build'!G13 -> 299 | H7: =+'Revenue Build'!H13 -> 467 | I7: =+'Revenue Build'!I13 -> 313 | ... BA7: =+'Revenue Build'!BA13 -> 644.78226 | BD7: =+SUM(B7:E7) -> 1289 | BE7: =+SUM(F7:I7) -> 1376 | BF7: =+SUM(J7:M7) -> 1624 | BG7: =SUM(N7:Q7) -> 1623 | BH7: =+SUM(R7:U7) -> 1635 | BI7: =SUM(V7:Y7) -> 1709 | BJ7: =+SUM(Z7:AC7) -> 2106.4922 | BK7: =+SUM(AD7:AG7) -> 2380.3345 | BL7: =+SUM(AH7:AK7) -> 2484.0248 | BM7: =+SUM(AL7:AO7) -> 2431.0061 | BN7: =+SUM(AP7:AS7) -> 2566.9111 | BO7: =+SUM(AT7:AW7) -> 2730.1957 | BP7: =+SUM(AX7:BA7) -> 2892.0071
A8: Service and Other Revenue | B8: =+'Revenue Build'!B18 -> 442 | C8: =+'Revenue Build'!C18 -> 659 | D8: =+'Revenue Build'!D18 -> 1845 | E8: =+'Revenue Build'!E18 -> 459 | F8: =+'Revenue Build'!F18 -> 481 | G8: =+'Revenue Build'!G18 -> 717 | H8: =+'Revenue Build'!H18 -> 2074 | I8: =+'Revenue Build'!I18 -> 529 | ... BA8: =+'Revenue Build'!BA18 -> 4688.0901 | BD8: =+SUM(B8:E8) -> 3405 | BE8: =+SUM(F8:I8) -> 3801 | BF8: =+SUM(J8:M8) -> 4401 | BG8: =SUM(N8:Q8) -> 5161 | BH8: =+SUM(R8:U8) -> 6044 | BI8: =SUM(V8:Y8) -> 7924 | BJ8: =+SUM(Z8:AC8) -> 10619.508 | BK8: =+SUM(AD8:AG8) -> 11987.666 | BL8: =+SUM(AH8:AK8) -> 13800.975 | BM8: =+SUM(AL8:AO8) -> 16399.994 | BN8: =+SUM(AP8:AS8) -> 18710.286 | BO8: =+SUM(AT8:AW8) -> 21037.141 | BP8: =+SUM(AX8:BA8) -> 23679.705
A9: Total Revenue | B9: =+'Revenue Build'!B6 -> 713 | C9: =+'Revenue Build'!C6 -> 923 | D9: =+'Revenue Build'!D6 -> 2304 | E9: =+'Revenue Build'!E6 -> 754 | F9: =+'Revenue Build'!F6 -> 778 | G9: =+'Revenue Build'!G6 -> 1016 | H9: =+'Revenue Build'!H6 -> 2541 | I9: =+'Revenue Build'!I6 -> 842 | ... BA9: =+'Revenue Build'!BA6 -> 5332.8724 | BD9: =+SUM(B9:E9) -> 4694 | BE9: =+SUM(F9:I9) -> 5177 | BF9: =+SUM(J9:M9) -> 6025 | BG9: =SUM(N9:Q9) -> 6784 | BH9: =+SUM(R9:U9) -> 7679 | BI9: =SUM(V9:Y9) -> 9633 | BJ9: =+SUM(Z9:AC9) -> 12726 | BK9: =+SUM(AD9:AG9) -> 14368 | BL9: =+SUM(AH9:AK9) -> 16285 | BM9: =+SUM(AL9:AO9) -> 18831 | BN9: =+SUM(AP9:AS9) -> 21277.197 | BO9: =+SUM(AT9:AW9) -> 23767.337 | BP9: =+SUM(AX9:BA9) -> 26571.712
A10: Consensus revenue | N10: {=_xll.FDS("INTU-US","FE_ESTIMATE(SALES,MEAN,QTR_ROLL,"&N2&",NOW,,,'')")} -> 1016 | O10: {=_xll.FDS("INTU-US","FE_ESTIMATE(SALES,MEAN,QTR_ROLL,"&O2&",NOW,,,'')")} -> 1502 | P10: {=_xll.FDS("INTU-US","FE_ESTIMATE(SALES,MEAN,QTR_ROLL,"&P2&",NOW,,,'')")} -> 3272 | Q10: {=_xll.FDS("INTU-US","FE_ESTIMATE(SALES,MEAN,QTR_ROLL,"&Q2&",NOW,,,'')")} -> 994 | R10: {=_xll.FDS("INTU-US","FE_ESTIMATE(SALES,MEAN,QTR_ROLL,"&R2&",NOW,,,'')")} -> 1165 | S10: {=_xll.FDS("INTU-US","FE_ESTIMATE(SALES,MEAN,QTR_ROLL,"&S2&",NOW,,,'')")} -> 1697.26 | T10: {=_xll.FDS("INTU-US","FE_ESTIMATE(SALES,MEAN,QTR_ROLL,"&T2&",NOW,,,'')")} -> 3002 | U10: {=_xll.FDS("INTU-US","FE_ESTIMATE(SALES,MEAN,QTR_ROLL,"&U2&",NOW,,,'')")} -> 1816 | ... BA10: {=_xll.FDS("INTU-US","FE_ESTIMATE(SALES,MEAN,QTR_ROLL,"&BA2&",NOW,,,'')")} -> 5422.1494 | BG10: =SUM(N10:Q10) -> 6784 | BH10: =+SUM(R10:U10) -> 7680.26 | BI10: =SUM(V10:Y10) -> 9633 | BJ10: =+SUM(Z10:AC10) -> 12726 | BK10: =+SUM(AD10:AG10) -> 14368 | BL10: =+SUM(AH10:AK10) -> 16285 | BM10: =+SUM(AL10:AO10) -> 18831 | BN10: =+SUM(AP10:AS10) -> 21180.996 | BO10: =+SUM(AT10:AW10) -> 23751.232 | BP10: =+SUM(AX10:BA10) -> 26404.916
A12: Cost of revenue
A13: Cost of Product Revenue | B13: =+B112 -> 29 | C13: =+C112 -> 40 | D13: =+D112 -> 30 | E13: =+E112 -> 32 | F13: =+F112 -> 29 | G13: =+G112 -> 37 | H13: =+H112 -> 29 | I13: =+I112 -> 25 | ... AQ13: =+AQ112 -> 18 | AR13: =+AR7*(1-AR94) -> 19.082807 | AS13: =+AS7*(1-AS94) -> 16.903711 | AT13: =+AT7*(1-AT94) -> 16.032485 | AU13: =+AU7*(1-AU94) -> 19.237959 | AV13: =+AV7*(1-AV94) -> 20.203133 | AW13: =+AW7*(1-AW94) -> 17.920396 | AX13: =+AX7*(1-AX94) -> 16.785895 | AY13: =+AY7*(1-AY94) -> 20.408013 | ... BA13: =+BA7*(1-BA94) -> 19.10328 | BD13: =+SUM(B13:E13) -> 131 | BE13: =+SUM(F13:I13) -> 120 | BF13: =+SUM(J13:M13) -> 82 | BG13: =SUM(N13:Q13) -> 77 | BH13: =+SUM(R13:U13) -> 72 | BI13: =SUM(V13:Y13) -> 69 | BJ13: =+SUM(Z13:AC13) -> 69 | BK13: =+SUM(AD13:AG13) -> 71 | BL13: =+SUM(AH13:AK13) -> 69 | BM13: =+SUM(AL13:AO13) -> 68 | BN13: =+SUM(AP13:AS13) -> 68.986518 | BO13: =+SUM(AT13:AW13) -> 73.393973 | BP13: =+SUM(AX13:BA13) -> 77.691225
A14: Cost of Service and Other Revenue | B14: =+B113-B146 -> 129 | C14: =+C113-C146 -> 151 | D14: =+D113-D146 -> 179 | E14: =+E113-E146 -> 132 | F14: =+F113-F146 -> 149 | G14: =+G113-G146 -> 164 | H14: =+H113-H146 -> 203 | I14: =+I113-I146 -> 153 | ... AQ14: =+AQ113-AQ146 -> 887 | AR14: =+AR8*(1-AR95) -> 1139.266 | AS14: =+AS8*(1-AS95) -> 820.11579 | AT14: =+AT8*(1-AT95) -> 832.10537 | AU14: =+AU8*(1-AU95) -> 1023.6911 | AV14: =+AV8*(1-AV95) -> 1253.2087 | AW14: =+AW8*(1-AW95) -> 922.24502 | AX14: =+AX8*(1-AX95) -> 944.7039 | AY14: =+AY8*(1-AY95) -> 1177.4226 | ... BA14: =+BA8*(1-BA95) -> 1044.1844 | BD14: =+SUM(B14:E14) -> 591 | BE14: =+SUM(F14:I14) -> 669 | BF14: =+SUM(J14:M14) -> 838 | BG14: =SUM(N14:Q14) -> 1012 | BH14: =+SUM(R14:U14) -> 1224 | BI14: =SUM(V14:Y14) -> 1495 | BJ14: =+SUM(Z14:AC14) -> 2051 | BK14: =+SUM(AD14:AG14) -> 2535 | BL14: =+SUM(AH14:AK14) -> 2848 | BM14: =+SUM(AL14:AO14) -> 3201 | BN14: =+SUM(AP14:AS14) -> 3573.3818 | BO14: =+SUM(AT14:AW14) -> 4031.2501 | BP14: =+SUM(AX14:BA14) -> 4550.7667
A15: Total Cost of Revenue | B15: =+SUM(B13:B14) -> 158 | C15: =+SUM(C13:C14) -> 191 | D15: =+SUM(D13:D14) -> 209 | E15: =+SUM(E13:E14) -> 164 | F15: =+SUM(F13:F14) -> 178 | G15: =+SUM(G13:G14) -> 201 | H15: =+SUM(H13:H14) -> 232 | I15: =+SUM(I13:I14) -> 178 | ... BA15: =+SUM(BA13:BA14) -> 1063.2877 | BD15: =+SUM(B15:E15) -> 722 | BE15: =+SUM(F15:I15) -> 789 | BF15: =+SUM(J15:M15) -> 920 | BG15: =SUM(N15:Q15) -> 1089 | BH15: =+SUM(R15:U15) -> 1296 | BI15: =SUM(V15:Y15) -> 1564 | BJ15: =+SUM(Z15:AC15) -> 2120 | BK15: =+SUM(AD15:AG15) -> 2606 | BL15: =+SUM(AH15:AK15) -> 2917 | BM15: =+SUM(AL15:AO15) -> 3269 | BN15: =+SUM(AP15:AS15) -> 3642.3683 | BO15: =+SUM(AT15:AW15) -> 4104.6441 | BP15: =+SUM(AX15:BA15) -> 4628.458
A16: Gross Profit | B16: =+B9-B15 -> 555 | C16: =+C9-C15 -> 732 | D16: =+D9-D15 -> 2095 | E16: =+E9-E15 -> 590 | F16: =+F9-F15 -> 600 | G16: =+G9-G15 -> 815 | H16: =+H9-H15 -> 2309 | I16: =+I9-I15 -> 664 | ... BA16: =+BA9-BA15 -> 4269.5847 | BD16: =+SUM(B16:E16) -> 3972 | BE16: =+SUM(F16:I16) -> 4388 | BF16: =+SUM(J16:M16) -> 5105 | BG16: =SUM(N16:Q16) -> 5695 | BH16: =+SUM(R16:U16) -> 6383 | BI16: =SUM(V16:Y16) -> 8069 | BJ16: =+SUM(Z16:AC16) -> 10606 | BK16: =+SUM(AD16:AG16) -> 11762 | BL16: =+SUM(AH16:AK16) -> 13368 | BM16: =+SUM(AL16:AO16) -> 15562 | BN16: =+SUM(AP16:AS16) -> 17634.829 | BO16: =+SUM(AT16:AW16) -> 19662.693 | BP16: =+SUM(AX16:BA16) -> 21943.254
A17: Consensus gross profit | N17: {=_xll.FDS("INTU-US","FE_ESTIMATE(GROSS_INC,MEAN,QTR_ROLL,"&N2&",NOW,,,'')")} -> 785.2857 | O17: {=_xll.FDS("INTU-US","FE_ESTIMATE(GROSS_INC,MEAN,QTR_ROLL,"&O2&",NOW,,,'')")} -> 1232 | P17: {=_xll.FDS("INTU-US","FE_ESTIMATE(GROSS_INC,MEAN,QTR_ROLL,"&P2&",NOW,,,'')")} -> 2935.1428 | Q17: {=_xll.FDS("INTU-US","FE_ESTIMATE(GROSS_INC,MEAN,QTR_ROLL,"&Q2&",NOW,,,'')")} -> 732 | R17: {=_xll.FDS("INTU-US","FE_ESTIMATE(GROSS_INC,MEAN,QTR_ROLL,"&R2&",NOW,,,'')")} -> 893 | S17: {=_xll.FDS("INTU-US","FE_ESTIMATE(GROSS_INC,MEAN,QTR_ROLL,"&S2&",NOW,,,'')")} -> 1370.8889 | T17: {=_xll.FDS("INTU-US","FE_ESTIMATE(GROSS_INC,MEAN,QTR_ROLL,"&T2&",NOW,,,'')")} -> 2590.2856 | U17: {=_xll.FDS("INTU-US","FE_ESTIMATE(GROSS_INC,MEAN,QTR_ROLL,"&U2&",NOW,,,'')")} -> 1509.8 | ... BA17: {=_xll.FDS("INTU-US","FE_ESTIMATE(GROSS_INC,MEAN,QTR_ROLL,"&BA2&",NOW,,,'')")} -> 4196.5 | BD17: =+SUM(B17:E17) -> 0 | BE17: =+SUM(F17:I17) -> 0 | BF17: =+SUM(J17:M17) -> 0 | BG17: =SUM(N17:Q17) -> 5684.4285 | BH17: =+SUM(R17:U17) -> 6363.9745 | BI17: =SUM(V17:Y17) -> 8041.3778 | BJ17: =+SUM(Z17:AC17) -> 10533.096 | BK17: =+SUM(AD17:AG17) -> 11621.468 | BL17: =+SUM(AH17:AK17) -> 13265.397 | BM17: =+SUM(AI17:AL17) -> 13533.468 | BN17: =+SUM(AJ17:AP17) -> 26942.214 | BO17: =+SUM(AK17:AT17) -> 39059.374 | BP17: =+SUM(AL17:AX17) -> 56552.509
A19: Operating Expenses
A20: Selling and marketing | B20: =+B119-B147-B155 -> 225 | C20: =+C119-C147-C155 -> 338 | D20: =+D119-D147-D155 -> 405 | E20: =+E119-E147-E155 -> 244 | F20: =+F119-F147-F155 -> 258 | G20: =+G119-G147-G155 -> 383 | H20: =+H119-H147-H155 -> 448 | I20: =+I119-I147-I155 -> 243 | ... AQ20: =+AQ119-AQ147-AQ155 -> 1245 | AR20: =+AR$9*AR97 -> 1733.9771 | AS20: =+AS$9*AS97 -> 1181.3191 | AT20: =+AT$9*AT97 -> 1039.6232 | AU20: =+AU$9*AU97 -> 1397.8687 | AV20: =+AV$9*AV97 -> 1853.8807 | AW20: =+AW$9*AW97 -> 1323.9873 | AX20: =+AX$9*AX97 -> 1161.7301 | AY20: =+AY$9*AY97 -> 1576.1365 | ... BA20: =+BA$9*BA97 -> 1461.207 | BD20: =+SUM(B20:E20) -> 1212 | BE20: =+SUM(F20:I20) -> 1332 | BF20: =+SUM(J20:M20) -> 1530 | BG20: =SUM(N20:Q20) -> 1824 | BH20: =+SUM(R20:U20) -> 1932 | BI20: =SUM(V20:Y20) -> 2461 | BJ20: =+SUM(Z20:AC20) -> 3217 | BK20: =+SUM(AD20:AG20) -> 3333 | BL20: =+SUM(AH20:AK20) -> 3806 | BM20: =+SUM(AL20:AO20) -> 4494 | BN20: =+SUM(AP20:AS20) -> 5086.2962 | BO20: =+SUM(AT20:AW20) -> 5615.3598 | BP20: =+SUM(AX20:BA20) -> 6220.6664
A21: Research and development | B21: =+B120-B148-B156 -> 192 | C21: =+C120-C148-C156 -> 184 | D21: =+D120-D148-D156 -> 207 | E21: =+E120-E148-E156 -> 208 | F21: =+F120-F148-F156 -> 210 | G21: =+G120-G148-G156 -> 214 | H21: =+H120-H148-H156 -> 222 | I21: =+I120-I148-I156 -> 230 | ... AQ21: =+AQ120-AQ148-AQ156 -> 658 | AR21: =+AR$9*AR98 -> 620.44506 | AS21: =+AS$9*AS98 -> 670.13017 | AT21: =+AT$9*AT98 -> 739.32072 | AU21: =+AU$9*AU98 -> 739.39788 | AV21: =+AV$9*AV98 -> 661.38627 | AW21: =+AW$9*AW98 -> 738.30214 | AX21: =+AX$9*AX98 -> 823.28005 | AY21: =+AY$9*AY98 -> 828.01772 | ... BA21: =+BA$9*BA98 -> 819.02396 | BD21: =+SUM(B21:E21) -> 791 | BE21: =+SUM(F21:I21) -> 876 | BF21: =+SUM(J21:M21) -> 1053 | BG21: =SUM(N21:Q21) -> 1097 | BH21: =+SUM(R21:U21) -> 1241 | BI21: =SUM(V21:Y21) -> 1397 | BJ21: =+SUM(Z21:AC21) -> 1826 | BK21: =+SUM(AD21:AG21) -> 2007 | BL21: =+SUM(AH21:AK21) -> 2115 | BM21: =+SUM(AL21:AO21) -> 2299 | BN21: =+SUM(AP21:AS21) -> 2606.5752 | BO21: =+SUM(AT21:AW21) -> 2878.407 | BP21: =+SUM(AX21:BA21) -> 3177.6399
A22: General and administrative | B22: =+B121-B149-B157-B162 -> 92 | C22: =+C121-C149-C157-C162 -> 96 | D22: =+D121-D149-D157-D162 -> 124 | E22: =+E121-E149-E157-E162 -> 102 | F22: =+F121-F149-F157-F162 -> 100 | G22: =+G121-G149-G157-G162 -> 112 | H22: =+H121-H149-H157-H162 -> 120 | I22: =+I121-I149-I157-I162 -> 113 | ... AQ22: =+AQ121-AQ149-AQ157-AQ162 -> 294 | AR22: =+AR$9*AR99 -> 347.85621 | AS22: =+AS$9*AS99 -> 335.61234 | AT22: =+AT$9*AT99 -> 333.40666 | AU22: =+AU$9*AU99 -> 324.504 | AV22: =+AV$9*AV99 -> 362.63547 | AW22: =+AW$9*AW99 -> 365.01628 | AX22: =+AX$9*AX99 -> 365.80258 | AY22: =+AY$9*AY99 -> 356.63778 | ... BA22: =+BA$9*BA99 -> 399.5325 | BD22: =+SUM(B22:E22) -> 414 | BE22: =+SUM(F22:I22) -> 445 | BF22: =+SUM(J22:M22) -> 478 | BG22: =SUM(N22:Q22) -> 492 | BH22: =+SUM(R22:U22) -> 542 | BI22: =SUM(V22:Y22) -> 726 | BJ22: =+SUM(Z22:AC22) -> 1059 | BK22: =+SUM(AD22:AG22) -> 919 | BL22: =+SUM(AH22:AK22) -> 1045 | BM22: =+SUM(AL22:AO22) -> 1197 | BN22: =+SUM(AP22:AS22) -> 1278.4686 | BO22: =+SUM(AT22:AW22) -> 1385.5624 | BP22: =+SUM(AX22:BA22) -> 1500.5441
A23: Total Operating Expenses | B23: =+SUM(B20:B22) -> 509 | C23: =+SUM(C20:C22) -> 618 | D23: =+SUM(D20:D22) -> 736 | E23: =+SUM(E20:E22) -> 554 | F23: =+SUM(F20:F22) -> 568 | G23: =+SUM(G20:G22) -> 709 | H23: =+SUM(H20:H22) -> 790 | I23: =+SUM(I20:I22) -> 586 | ... BA23: =+SUM(BA20:BA22) -> 2679.7635 | BD23: =+SUM(B23:E23) -> 2417 | BE23: =+SUM(F23:I23) -> 2653 | BF23: =+SUM(J23:M23) -> 3061 | BG23: =SUM(N23:Q23) -> 3413 | BH23: =+SUM(R23:U23) -> 3715 | BI23: =SUM(V23:Y23) -> 4584 | BJ23: =+SUM(Z23:AC23) -> 6102 | BK23: =+SUM(AD23:AG23) -> 6259 | BL23: =+SUM(AH23:AK23) -> 6966 | BM23: =+SUM(AL23:AO23) -> 7990 | BN23: =+SUM(AP23:AS23) -> 8971.34 | BO23: =+SUM(AT23:AW23) -> 9879.3293 | BP23: =+SUM(AX23:BA23) -> 10898.85
A24: Operating Income | B24: =+B16-B23 -> 46 | C24: =+C16-C23 -> 114 | D24: =+D16-D23 -> 1359 | E24: =+E16-E23 -> 36 | F24: =+F16-F23 -> 32 | G24: =+G16-G23 -> 106 | H24: =+H16-H23 -> 1519 | I24: =+I16-I23 -> 78 | ... BA24: =+BA16-BA23 -> 1589.8212 | BD24: =+SUM(B24:E24) -> 1555 | BE24: =+SUM(F24:I24) -> 1735 | BF24: =+SUM(J24:M24) -> 2044 | BG24: =SUM(N24:Q24) -> 2282 | BH24: =+SUM(R24:U24) -> 2668 | BI24: =SUM(V24:Y24) -> 3485 | BJ24: =+SUM(Z24:AC24) -> 4504 | BK24: =+SUM(AD24:AG24) -> 5503 | BL24: =+SUM(AH24:AK24) -> 6402 | BM24: =+SUM(AL24:AO24) -> 7572 | BN24: =+SUM(AP24:AS24) -> 8663.4892 | BO24: =+SUM(AT24:AW24) -> 9783.3637 | BP24: =+SUM(AX24:BA24) -> 11044.404
A25: Consensus non-GAAP operating income | N25: {=_xll.FDS("INTU-US","FE_ESTIMATE(EBIT,MEAN,QTR_ROLL,"&N2&",NOW,,,'')")} -> 102 | O25: {=_xll.FDS("INTU-US","FE_ESTIMATE(EBIT,MEAN,QTR_ROLL,"&O2&",NOW,,,'')")} -> 339 | P25: {=_xll.FDS("INTU-US","FE_ESTIMATE(EBIT,MEAN,QTR_ROLL,"&P2&",NOW,,,'')")} -> 1888 | Q25: {=_xll.FDS("INTU-US","FE_ESTIMATE(EBIT,MEAN,QTR_ROLL,"&Q2&",NOW,,,'')")} -> -47 | R25: {=_xll.FDS("INTU-US","FE_ESTIMATE(EBIT,MEAN,QTR_ROLL,"&R2&",NOW,,,'')")} -> 129 | S25: {=_xll.FDS("INTU-US","FE_ESTIMATE(EBIT,MEAN,QTR_ROLL,"&S2&",NOW,,,'')")} -> 383.92307 | T25: {=_xll.FDS("INTU-US","FE_ESTIMATE(EBIT,MEAN,QTR_ROLL,"&T2&",NOW,,,'')")} -> 1539 | U25: {=_xll.FDS("INTU-US","FE_ESTIMATE(EBIT,MEAN,QTR_ROLL,"&U2&",NOW,,,'')")} -> 616 | ... BA25: {=_xll.FDS("INTU-US","FE_ESTIMATE(EBIT,MEAN,QTR_ROLL,"&BA2&",NOW,,,'')")} -> 1589.6897 | BD25: =+SUM(B25:E25) -> 0 | BE25: =+SUM(F25:I25) -> 0 | BF25: =+SUM(J25:M25) -> 0 | BG25: =SUM(N25:Q25) -> 2282 | BH25: =+SUM(R25:U25) -> 2667.9231 | BI25: =SUM(V25:Y25) -> 3485 | BJ25: =+SUM(Z25:AC25) -> 4504 | BK25: =+SUM(AD25:AG25) -> 5503 | BL25: =+SUM(AH25:AK25) -> 6402 | BM25: =+SUM(AL25:AO25) -> 7572 | BN25: =+SUM(AP25:AS25) -> 8668.6563 | BO25: =+SUM(AT25:AW25) -> 9854.9521 | BP25: =+SUM(AX25:BA25) -> 10946.017
A26: Adjusted EBITDA | B26: =+B24+'Cash Flow'!B7+'Cash Flow'!B8 -> 101 | C26: =+C24+'Cash Flow'!C7+'Cash Flow'!C8 -> 172 | D26: =+D24+'Cash Flow'!D7+'Cash Flow'!D8 -> 1421 | E26: =+E24+'Cash Flow'!E7+'Cash Flow'!E8 -> 99 | F26: =+F24+'Cash Flow'!F7+'Cash Flow'!F8 -> 87 | G26: =+G24+'Cash Flow'!G7+'Cash Flow'!G8 -> 163 | H26: =+H24+'Cash Flow'!H7+'Cash Flow'!H8 -> 1581 | I26: =+I24+'Cash Flow'!I7+'Cash Flow'!I8 -> 140 | ... AS26: =+AS24+'Cash Flow'!AS7+'Cash Flow'!AS8 -> 1441.2788 | AT26: =+AT24+'Cash Flow'!BB7+'Cash Flow'!BB8 -> 1456.8116 | AU26: =+AU24+'Cash Flow'!BC7+'Cash Flow'!BC8 -> 1796.5955 | AV26: =+AV24+'Cash Flow'!BD7+'Cash Flow'!BD8 -> 5389.9535 | AW26: =+AW24+'Cash Flow'!BE7+'Cash Flow'!BE8 -> 1614.0031 | AX26: =+AX24+'Cash Flow'!BF7+'Cash Flow'!BF8 -> 1919.1288 | AY26: =+AY24+'Cash Flow'!BG7+'Cash Flow'!BG8 -> 2289.4217 | AZ26: =+AZ24+'Cash Flow'!BH7+'Cash Flow'!BH8 -> 5942.0323 | BA26: =+BA24+'Cash Flow'!BI7+'Cash Flow'!BI8 -> 1952.8212 | BD26: =+SUM(B26:E26) -> 1793 | BE26: =+SUM(F26:I26) -> 1971 | BF26: =+SUM(J26:M26) -> 2297 | BG26: =SUM(N26:Q26) -> 2507 | BH26: =+SUM(R26:U26) -> 2886 | BI26: =SUM(V26:Y26) -> 3848 | BJ26: =+SUM(Z26:AC26) -> 5250 | BK26: =+SUM(AD26:AG26) -> 6309 | BL26: =+SUM(AH26:AK26) -> 7191 | BM26: =+SUM(AL26:AO26) -> 8381 | BN26: =+SUM(AP26:AS26) -> 9506.2953 | BO26: =+SUM(AT26:AW26) -> 10257.364 | BP26: =+SUM(AX26:BA26) -> 12103.404
BJ27: =+(BJ24/BI24)-1 -> 0.29239598 | BK27: =+(BK24/BJ24)-1 -> 0.22180284
A28: Interest expense | B28: =+B127+B164+B165 -> -6 | C28: =+C127+C164+C165 -> -8 | D28: =+D127+D164+D165 -> -8 | E28: =+E127+E164+E165 -> -8 | F28: =+F127+F164+F165 -> -8 | G28: =+G127+G164+G165 -> -5 | H28: =+H127+H164+H165 -> -7 | I28: =+I127+I164+I165 -> -2 | ... AQ28: =+AQ127+AQ164+AQ165 -> -95 | AR28: =+AN28-50 -> -109 | AS28: =+AO28-20 -> -101 | AT28: =+AP28 -> -107 | AU28: =+AQ28 -> -95 | AV28: =+AR28 -> -109 | AW28: =+AS28 -> -101 | AX28: =+AT28 -> -107 | AY28: =+AU28 -> -95 | AZ28: =+AV28 -> -109 | BA28: =+AW28 -> -101 | BD28: =+SUM(B28:E28) -> -30 | BE28: =+SUM(F28:I28) -> -22 | BF28: =+SUM(J28:M28) -> -22 | BG28: =SUM(N28:Q28) -> -9 | BH28: =+SUM(R28:U28) -> -9 | BI28: =SUM(V28:Y28) -> -74 | BJ28: =+SUM(Z28:AC28) -> -130 | BK28: =+SUM(AD28:AG28) -> -231 | BL28: =+SUM(AH28:AK28) -> -233 | BM28: =+SUM(AL28:AO28) -> -226 | BN28: =+SUM(AP28:AS28) -> -412 | BO28: =+SUM(AT28:AW28) -> -412 | BP28: =+SUM(AX28:BA28) -> -412
A29: Other income (expense), net | B29: =+B128 -> -4 | C29: =+C128 -> -5 | D29: =+D128 -> 2 | E29: =+E128 -> 3 | F29: =+F128 -> -2 | G29: =+G128 -> -1 | H29: =+H128 -> 3 | I29: =+I128 -> 3 | ... AQ29: =+AQ128 -> 72 | AR29: =+AN29 -> 32 | AS29: =+AO29-40 -> 46 | AT29: =+AP29 -> 85 | AU29: =+AQ29 -> 72 | AV29: =+AR29 -> 32 | AW29: =+AS29 -> 46 | AX29: =+AT29 -> 85 | AY29: =+AU29 -> 72 | AZ29: =+AV29 -> 32 | BA29: =+AW29 -> 46 | BD29: =+SUM(B29:E29) -> -4 | BE29: =+SUM(F29:I29) -> 3 | BF29: =+SUM(J29:M29) -> 26 | BG29: =SUM(N29:Q29) -> 42 | BH29: =+SUM(R29:U29) -> 36 | BI29: =SUM(V29:Y29) -> 85 | BJ29: =+SUM(Z29:AC29) -> 52 | BK29: =+SUM(AD29:AG29) -> 96 | BL29: =+SUM(AH29:AK29) -> 162 | BM29: =+SUM(AL29:AO29) -> 158 | BN29: =+SUM(AP29:AS29) -> 235 | BO29: =+SUM(AT29:AW29) -> 235 | BP29: =+SUM(AX29:BA29) -> 235
A30: Pre-tax income | B30: =+B24+SUM(B28:B29) -> 36 | C30: =+C24+SUM(C28:C29) -> 101 | D30: =+D24+SUM(D28:D29) -> 1353 | E30: =+E24+SUM(E28:E29) -> 31 | F30: =+F24+SUM(F28:F29) -> 22 | G30: =+G24+SUM(G28:G29) -> 100 | H30: =+H24+SUM(H28:H29) -> 1515 | I30: =+I24+SUM(I28:I29) -> 79 | ... BA30: =+BA24+SUM(BA28:BA29) -> 1534.8212 | BD30: =+SUM(B30:E30) -> 1521 | BE30: =+SUM(F30:I30) -> 1716 | BF30: =+SUM(J30:M30) -> 2048 | BG30: =SUM(N30:Q30) -> 2315 | BH30: =+SUM(R30:U30) -> 2695 | BI30: =SUM(V30:Y30) -> 3496 | BJ30: =+SUM(Z30:AC30) -> 4426 | BK30: =+SUM(AD30:AG30) -> 5368 | BL30: =+SUM(AH30:AK30) -> 6331 | BM30: =+SUM(AL30:AO30) -> 7504 | BN30: =+SUM(AP30:AS30) -> 8486.4892 | BO30: =+SUM(AT30:AW30) -> 9606.3637 | BP30: =+SUM(AX30:BA30) -> 10867.404
A31: Income Taxes | B31: =+B130+B166 -> 12 | C31: =+C130+C166 -> 34 | D31: =+D130+D166 -> 460 | E31: =+E130+E166 -> 11 | F31: =+F130+F166 -> 7 | G31: =+G130+G166 -> 33 | H31: =+H130+H166 -> 500 | I31: =+I130+I166 -> 26 | ... AQ31: =+AQ130+AQ166 -> 366 | AR31: =+AR30*AR32 -> 1057.3785 | AS31: =+AS30*AS32 -> 272.66497 | AT31: =+AT30*AT32 -> 340.54209 | AU31: =+AU30*AU32 -> 420.95 | AV31: =+AV30*AV32 -> 1204.5033 | AW31: =+AW30*AW32 -> 314.00516 | AX31: =+AX30*AX32 -> 390.22202 | AY31: =+AY30*AY32 -> 484.51659 | ... BA31: =+BA30*BA32 -> 364.27865 | BD31: =+SUM(B31:E31) -> 517 | BE31: =+SUM(F31:I31) -> 566 | BF31: =+SUM(J31:M31) -> 537 | BG31: =SUM(N31:Q31) -> 533 | BH31: =+SUM(R31:U31) -> 620 | BI31: =SUM(V31:Y31) -> 839 | BJ31: =+SUM(Z31:AC31) -> 1061 | BK31: =+SUM(AD31:AG31) -> 1288 | BL31: =+SUM(AH31:AK31) -> 1520 | BM31: =+SUM(AL31:AO31) -> 1801 | BN31: =+SUM(AP31:AS31) -> 1993.0434 | BO31: =+SUM(AT31:AW31) -> 2280.0006 | BP31: =+SUM(AX31:BA31) -> 2579.2993
A32: Tax rate (GAAP) | B32: =+B31/B30 -> 0.33333333 | C32: =+C31/C30 -> 0.33663366 | D32: =+D31/D30 -> 0.33998522 | E32: =+E31/E30 -> 0.35483871 | F32: =+F31/F30 -> 0.31818182 | G32: =+G31/G30 -> 0.33 | H32: =+H31/H30 -> 0.330033 | I32: =+I31/I30 -> 0.32911392 | ... AQ32: =+AQ31/AQ30 -> 0.23984273 | AR32: =+AQ32-0.75% -> 0.23234273 | AS32: =+AR32 -> 0.23234273 | AT32: =+AS32+0.5% -> 0.23734273 | AU32: =+AT32 -> 0.23734273 | AV32: =+AU32 -> 0.23734273 | AW32: =+AV32 -> 0.23734273 | AX32: =+AW32 -> 0.23734273 | AY32: =+AX32 -> 0.23734273 | AZ32: =+AY32 -> 0.23734273 | BA32: =+AZ32 -> 0.23734273 | BD32: =+BD31/BD30 -> 0.33990796 | BE32: =+BE31/BE30 -> 0.32983683 | BF32: =+BF31/BF30 -> 0.26220703 | BG32: =+BG31/BG30 -> 0.23023758 | BH32: =+BH31/BH30 -> 0.23005566 | BI32: =+BI31/BI30 -> 0.23998856 | BJ32: =+BJ31/BJ30 -> 0.23971984 | BK32: =+BK31/BK30 -> 0.23994039 | ... BP32: =+BP31/BP30 -> 0.23734273
A33: Net income (loss) | B33: =+B30-B31 -> 24 | C33: =+C30-C31 -> 67 | D33: =+D30-D31 -> 893 | E33: =+E30-E31 -> 20 | F33: =+F30-F31 -> 15 | G33: =+G30-G31 -> 67 | H33: =+H30-H31 -> 1015 | I33: =+I30-I31 -> 53 | ... BA33: =+BA30-BA31 -> 1170.5426 | BD33: =+SUM(B33:E33) -> 1004 | BE33: =+SUM(F33:I33) -> 1150 | BF33: =+SUM(J33:M33) -> 1511 | BG33: =SUM(N33:Q33) -> 1782 | BH33: =+SUM(R33:U33) -> 2075 | BI33: =SUM(V33:Y33) -> 2657 | BJ33: =+SUM(Z33:AC33) -> 3365 | BK33: =+SUM(AD33:AG33) -> 4080 | BL33: =+SUM(AH33:AK33) -> 4811 | BM33: =+SUM(AL33:AO33) -> 5703 | BN33: =+SUM(AP33:AS33) -> 6493.4458 | BO33: =+SUM(AT33:AW33) -> 7326.3632 | BP33: =+SUM(AX33:BA33) -> 8288.1047
A35: Non-GAAP EPS | B35: =B33/B37 -> 0.088235294 | C35: =C33/C37 -> 0.2518797 | D35: =D33/D37 -> 3.4346154 | E35: =E33/E37 -> 0.076923077 | F35: =F33/F37 -> 0.058139535 | G35: =G33/G37 -> 0.25769231 | H35: =H33/H37 -> 3.9038462 | I35: =I33/I37 -> 0.20384615 | ... X35: =X33/X37 -> 6.0797101 | Y35: 1.97 | Z35: =Z33/Z37 -> 1.5270758 | AA35: =AA33/AA37 -> 1.554007 | AB35: =AB33/AB37 -> 7.6398601 | AC35: =AC33/AC37 -> 1.1028369 | AD35: =AD33/AD37 -> 1.6560958 | AE35: =AE33/AE37 -> 2.1954674 | AF35: =AF33/AF37 -> 8.9026112 | AG35: =AG33/AG37 -> 1.6493607 | ... BA35: =BA33/BA37 -> 4.1805092 | BD35: =+BD33/BD37 -> 3.7958412 | BE35: =+BE33/BE37 -> 4.4315992 | BF35: =+BF33/BF37 -> 5.8171319 | BG35: =+BG33/BG37 -> 6.7756654 | BH35: =+BH33/BH37 -> 7.8635718 | BI35: 9.67 | BJ35: =+SUM(Z35:AC35) -> 11.82378 | BK35: =+SUM(AD35:AG35) -> 14.403535 | BL35: =+SUM(AH35:AK35) -> 16.966271 | BM35: 20.15 | BN35: =+BN33/BN37 -> 23.188807 | BO35: =+BO33/BO37 -> 26.072467 | BP35: =+BP33/BP37 -> 29.600374 | BR35: =+BM35/BL35 -> 1.1876505 | BS35: =+BN35/BM35 -> 1.1508093
A36: Consensus non-GAAP EPS | N36: {=_xll.FDS("INTU-US","FE_ESTIMATE(EPS,MEAN,QTR_ROLL,"&N2&",NOW,,,'')")} -> 0.29 | O36: {=_xll.FDS("INTU-US","FE_ESTIMATE(EPS,MEAN,QTR_ROLL,"&O2&",NOW,,,'')")} -> 1 | P36: {=_xll.FDS("INTU-US","FE_ESTIMATE(EPS,MEAN,QTR_ROLL,"&P2&",NOW,,,'')")} -> 5.55 | Q36: {=_xll.FDS("INTU-US","FE_ESTIMATE(EPS,MEAN,QTR_ROLL,"&Q2&",NOW,,,'')")} -> -0.09 | R36: {=_xll.FDS("INTU-US","FE_ESTIMATE(EPS,MEAN,QTR_ROLL,"&R2&",NOW,,,'')")} -> 0.41 | S36: {=_xll.FDS("INTU-US","FE_ESTIMATE(EPS,MEAN,QTR_ROLL,"&S2&",NOW,,,'')")} -> 1.16 | T36: {=_xll.FDS("INTU-US","FE_ESTIMATE(EPS,MEAN,QTR_ROLL,"&T2&",NOW,,,'')")} -> 4.49 | U36: {=_xll.FDS("INTU-US","FE_ESTIMATE(EPS,MEAN,QTR_ROLL,"&U2&",NOW,,,'')")} -> 1.81 | ... BA36: {=_xll.FDS("INTU-US","FE_ESTIMATE(EPS,MEAN,QTR_ROLL,"&BA2&",NOW,,,'')")} -> 4.3006334 | BD36: =+SUM(B36:E36) -> 0 | BE36: =+SUM(F36:I36) -> 0 | BF36: =+SUM(J36:M36) -> 0 | BG36: =SUM(N36:Q36) -> 6.75 | BH36: =+SUM(R36:U36) -> 7.87 | BI36: =SUM(V36:Y36) -> 9.66 | BJ36: =+SUM(Z36:AC36) -> 11.83 | BK36: =+SUM(AD36:AG36) -> 14.43 | BL36: =+SUM(AH36:AK36) -> 16.97 | BM36: =+SUM(AL36:AO36) -> 20.22 | BN36: =+SUM(AP36:AS36) -> 23.142881 | BO36: =+SUM(AT36:AW36) -> 26.2979 | BP36: =+SUM(AX36:BA36) -> 29.418595
A37: Non-GAAP diluted shares outstanding | B37: =+B141 -> 272 | C37: =+C141 -> 266 | D37: =+D141 -> 260 | E37: =+E141 -> 260 | F37: =+F141 -> 258 | G37: =+G141 -> 260 | H37: =+H141 -> 260 | I37: =+I141 -> 260 | ... AQ37: =+AQ141 -> 279.7 | AR37: =+AQ37 -> 279.7 | AS37: =+AR37 -> 279.7 | AT37: 281 | AU37: =+AT37 -> 281 | AV37: =+AU37 -> 281 | AW37: =+AV37 -> 281 | AX37: 280 | AY37: =+AX37 -> 280 | AZ37: =+AY37 -> 280 | BA37: =+AZ37 -> 280 | BD37: =AVERAGE(B37:E37) -> 264.5 | BE37: =+AVERAGE(F37:I37) -> 259.5 | BF37: =+AVERAGE(J37:M37) -> 259.75 | BG37: =AVERAGE(N37:Q37) -> 263 | BH37: =+AVERAGE(R37:U37) -> 263.875 | BI37: =AVERAGE(V37:Y37) -> 272.75 | BJ37: =+AVERAGE(Z37:AC37) -> 283 | BK37: =+AVERAGE(AD37:AG37) -> 283.185 | BL37: =+AVERAGE(AH37:AK37) -> 283.425 | BM37: =+AVERAGE(AL37:AO37) -> 282.375 | BN37: =+AVERAGE(AP37:AS37) -> 280.025 | BO37: =+AVERAGE(AT37:AW37) -> 281 | BP37: =+AVERAGE(AX37:BA37) -> 280
AH38: =+AH35/AD35-1 -> 0.48930456 | AI38: =+AI35/AE35-1 -> 0.19644707 | AJ38: =+AJ35/AF35-1 -> 0.11020012 | AK38: =+AK35/AG35-1 -> 0.20616385 | AL38: =+AL35/AH35-1 -> 0.015759312 | AM38: =+AM35/AI35-1 -> 0.26181567 | AN38: =+AN35/AJ35-1 -> 0.17889947 | AO38: =+AO35/AK35-1 -> 0.38321807 | ... AQ38: =+AQ35/AM35-1 -> 0.25126449 | BD38: =+BD35/BC35 -> #DIV/0! | BE38: =+BE35/BD35 -> 1.167488 | BF38: =+BF35/BE35 -> 1.3126484 | BG38: =+BG35/BF35 -> 1.1647777 | BH38: =+BH35/BG35 -> 1.1605608 | BI38: =+BI35/BH35 -> 1.2297211 | BJ38: =+BJ35/BI35 -> 1.222728 | BK38: =+BK35/BJ35 -> 1.2181836 | BL38: =+BL35/BK35 -> 1.1779241
A39: Dividends per share | B39: 0.3 | C39: 0.3 | D39: 0.3 | E39: 0.3 | F39: 0.34 | G39: 0.34 | H39: 0.34 | I39: 0.34 | J39: 0.39 | K39: 0.39 | L39: 0.39 | M39: 0.39 | N39: 0.47 | O39: 0.47 | P39: 0.47 | Q39: 0.47 | R39: 0.53 | S39: 0.53 | T39: 0.53 | U39: 0.53 | V39: 0.59 | W39: 0.59 | X39: 0.59 | Y39: 0.59 | Z39: 0.68 | AA39: =+Z39 -> 0.68 | AB39: =+X39*(1+AB79) -> 0.68 | AC39: =+Y39*(1+AC79) -> 0.68 | AD39: 0.78 | AE39: =+AD39 -> 0.78 | AF39: =+AE39 -> 0.78 | AG39: =+AF39 -> 0.78 | AH39: 0.9 | AI39: =+AH39 -> 0.9 | AJ39: =+AF39*(1+AJ79) -> 0.9 | AK39: =+AG39*(1+AK79) -> 0.9 | AL39: 1.04 | AM39: =+AL39 -> 1.04 | AN39: 1.04 | AO39: 1.2 | AP39: 1.2 | AQ39: 1.2 | AR39: =+AN39*(1+AR79) -> 1.196 | AS39: =+AO39*(1+AS79) -> 1.38 | AT39: =+AP39*(1+AT79) -> 1.362 | AU39: =+AQ39*(1+AU79) -> 1.362 | AV39: =+AR39*(1+AV79) -> 1.35746 | AW39: =+AS39*(1+AW79) -> 1.5663 | AX39: =+AT39*(1+AX79) -> 1.54587 | AY39: =+AU39*(1+AY79) -> 1.54587 | ... BA39: =+AW39*(1+BA79) -> 1.7777505 | BD39: =+SUM(B39:E39) -> 1.2 | BE39: =+SUM(F39:I39) -> 1.36 | BF39: =+SUM(J39:M39) -> 1.56 | BG39: =SUM(N39:Q39) -> 1.88 | BH39: =+SUM(R39:U39) -> 2.12 | BI39: =SUM(V39:Y39) -> 2.36 | BJ39: =+SUM(Z39:AC39) -> 2.72 | BK39: =+SUM(AD39:AG39) -> 3.12 | BL39: =+SUM(AH39:AK39) -> 3.6 | BM39: =+SUM(AL39:AO39) -> 4.32 | BN39: =+SUM(AP39:AS39) -> 4.976 | BO39: =+SUM(AT39:AW39) -> 5.64776 | BP39: =+SUM(AX39:BA39) -> 6.4102076
A41: Non-GAAP Reconciliation
A42: Adjustments
A43: Share-based compensation | B43: =+B151 -> 67 | C43: =+C151 -> 65 | D43: =+D151 -> 65 | E43: =+E151 -> 81 | F43: =+F151 -> 89 | G43: =+G151 -> 81 | H43: =+H151 -> 71 | I43: =+I151 -> 85 | ... U43: =+U151 -> 114 | V43: =+SUM(V44:V45) -> 111 | W43: =+SUM(W44:W45) -> 180 | X43: =+SUM(X44:X45) -> 218 | Y43: =+SUM(Y44:Y45) -> 244 | Z43: =+SUM(Z44:Z45) -> 280 | AA43: =+SUM(AA44:AA45) -> 336 | AB43: =+SUM(AB44:AB45) -> 346 | AC43: =+SUM(AC44:AC45) -> 346 | ... BA43: =+SUM(BA44:BA45) -> 609.01235 | BD43: =+SUM(B43:E43) -> 278 | BE43: =+SUM(F43:I43) -> 326 | BF43: =+SUM(J43:M43) -> 382 | BG43: =SUM(N43:Q43) -> 401 | BH43: =+SUM(R43:U43) -> 435 | BI43: =SUM(V43:Y43) -> 753 | BJ43: =+SUM(Z43:AC43) -> 1308 | BK43: =+SUM(AD43:AG43) -> 1712 | BL43: =+SUM(AH43:AK43) -> 1915 | BM43: =+SUM(AL43:AO43) -> 1968 | BN43: =+SUM(AP43:AS43) -> 2182.5573 | BO43: =+SUM(AT43:AW43) -> 2247.6724 | BP43: =+SUM(AX43:BA43) -> 2318.7937
A44: Cost of revenue | B44: =+B146 -> 2 | C44: =+C146 -> 2 | D44: =+D146 -> 2 | E44: =+E146 -> 2 | F44: =+F146 -> 2 | G44: =+G146 -> 2 | H44: =+H146 -> 2 | I44: =+I146 -> 2 | ... AQ44: =+AQ146 -> 94 | AR44: =AN44/AN9*AR9*0.9 -> 99.511351 | AS44: =AO44/AO9*AS9*0.9 -> 100.90416 | AT44: =AP44/AP9*AT9 -> 110.29037 | AU44: =AQ44/AQ9*AU9 -> 107.14292 | AV44: =AR44/AR9*AV9 -> 109.06204 | AW44: =AS44/AS9*AW9 -> 112.59817 | AX44: =AT44/AT9*AX9 -> 124.3006 | AY44: =AU44/AU9*AY9 -> 121.72999 | AZ44: =AV44/AV9*AZ9 -> 120.01243 | BA44: =AW44/AW9*BA9 -> 126.53566 | BD44: =+SUM(B44:E44) -> 8 | BE44: =+SUM(F44:I44) -> 8 | BF44: =+SUM(J44:M44) -> 43 | BG44: =SUM(N44:Q44) -> 58 | BH44: =+SUM(R44:U44) -> 60 | BI44: =SUM(V44:Y44) -> 69 | BJ44: =+SUM(Z44:AC44) -> 146 | BK44: =+SUM(AD44:AG44) -> 374 | BL44: =+SUM(AH44:AK44) -> 402 | BM44: =+SUM(AL44:AO44) -> 423 | BN44: =+SUM(AP44:AS44) -> 391.41551 | BO44: =+SUM(AT44:AW44) -> 439.09351 | BP44: =+SUM(AX44:BA44) -> 492.57868
A45: OpEx | B45: =+B150 -> 65 | C45: =+C150 -> 63 | D45: =+D150 -> 63 | E45: =+E150 -> 79 | F45: =+F150 -> 87 | G45: =+G150 -> 79 | H45: =+H150 -> 69 | I45: =+I150 -> 83 | ... AQ45: =+AQ150 -> 427 | AR45: =AN45/AN9*AR9*1.1 -> 443.14846 | AS45: =AO45/AO9*AS9*1.1 -> 474.99329 | AT45: =AP45/AP9*AT9*0.9 -> 456.39748 | AU45: =AQ45/AQ9*AU9*0.9 -> 438.03219 | AV45: =AR45/AR9*AV9*0.9 -> 437.11201 | AW45: =AS45/AS9*AW9*0.9 -> 477.03722 | AX45: =AT45/AT9*AX9*0.9 -> 462.93645 | AY45: =AU45/AU9*AY9*0.9 -> 447.9016 | AZ45: =AV45/AV9*AZ9*0.9 -> 432.9003 | BA45: =AW45/AW9*BA9*0.9 -> 482.4767 | BD45: =+SUM(B45:E45) -> 270 | BE45: =+SUM(F45:I45) -> 318 | BF45: =+SUM(J45:M45) -> 339 | BG45: =SUM(N45:Q45) -> 343 | BH45: =+SUM(R45:U45) -> 375 | BI45: =SUM(V45:Y45) -> 684 | BJ45: =+SUM(Z45:AC45) -> 1162 | BK45: =+SUM(AD45:AG45) -> 1338 | BL45: =+SUM(AH45:AK45) -> 1513 | BM45: =+SUM(AL45:AO45) -> 1545 | BN45: =+SUM(AP45:AS45) -> 1791.1418 | BO45: =+SUM(AT45:AW45) -> 1808.5789 | BP45: =+SUM(AX45:BA45) -> 1826.215
A46: Amortization of acquired intangibles | B46: =+SUM(B47:B48) -> 8 | C46: =+SUM(C47:C48) -> 7 | D46: =+SUM(D47:D48) -> 8 | E46: =+SUM(E47:E48) -> 11 | F46: =+SUM(F47:F48) -> 4 | G46: =+SUM(G47:G48) -> 3 | H46: =+SUM(H47:H48) -> 4 | I46: =+SUM(I47:I48) -> 3 | ... BA46: =+SUM(BA47:BA48) -> 165 | BD46: =+SUM(B46:E46) -> 34 | BE46: =+SUM(F46:I46) -> 14 | BF46: =+SUM(J46:M46) -> 21 | BG46: =SUM(N46:Q46) -> 26 | BH46: =+SUM(R46:U46) -> 28 | BI46: =SUM(V46:Y46) -> 196 | BJ46: =+SUM(Z46:AC46) -> 556 | BK46: =+SUM(AD46:AG46) -> 646 | BL46: =+SUM(AH46:AK46) -> 629 | BM46: =+SUM(AL46:AO46) -> 637 | BN46: =+SUM(AP46:AS46) -> 660 | BO46: =+SUM(AT46:AW46) -> 660 | BP46: =+SUM(AX46:BA46) -> 660
A47: Cost of revenue | B47: =+B114 -> 6 | C47: =+C114 -> 6 | D47: =+D114 -> 5 | E47: =+E114 -> 5 | F47: =+F114 -> 3 | G47: =+G114 -> 3 | H47: =+H114 -> 3 | I47: =+I114 -> 3 | ... AQ47: =+AQ114 -> 44 | AR47: =+AQ47 -> 44 | AS47: =+AR47 -> 44 | AT47: =+AS47 -> 44 | AU47: =+AT47 -> 44 | AV47: =+AU47 -> 44 | AW47: =+AV47 -> 44 | AX47: =+AW47 -> 44 | AY47: =+AX47 -> 44 | ... BA47: =+AZ47 -> 44 | BD47: =+SUM(B47:E47) -> 22 | BE47: =+SUM(F47:I47) -> 12 | BF47: =+SUM(J47:M47) -> 15 | BG47: =SUM(N47:Q47) -> 20 | BH47: =+SUM(R47:U47) -> 22 | BI47: =SUM(V47:Y47) -> 50 | BJ47: =+SUM(Z47:AC47) -> 140 | BK47: =+SUM(AD47:AG47) -> 163 | BL47: =+SUM(AH47:AK47) -> 146 | BM47: =+SUM(AL47:AO47) -> 156 | BN47: =+SUM(AP47:AS47) -> 176 | BO47: =+SUM(AT47:AW47) -> 176 | BP47: =+SUM(AX47:BA47) -> 176
A48: OpEx | B48: =+B122 -> 2 | C48: =+C122 -> 1 | D48: =+D122 -> 3 | E48: =+E122 -> 6 | F48: =+F122 -> 1 | G48: =+G122 -> 0 | H48: =+H122 -> 1 | I48: =+I122 -> 0 | ... AQ48: =+AQ122 -> 121 | AR48: =+AQ48 -> 121 | AS48: =+AR48 -> 121 | AT48: =+AS48 -> 121 | AU48: =+AT48 -> 121 | AV48: =+AU48 -> 121 | AW48: =+AV48 -> 121 | AX48: =+AW48 -> 121 | AY48: =+AX48 -> 121 | ... BA48: =+AZ48 -> 121 | BD48: =+SUM(B48:E48) -> 12 | BE48: =+SUM(F48:I48) -> 2 | BF48: =+SUM(J48:M48) -> 6 | BG48: =SUM(N48:Q48) -> 6 | BH48: =+SUM(R48:U48) -> 6 | BI48: =SUM(V48:Y48) -> 146 | BJ48: =+SUM(Z48:AC48) -> 416 | BK48: =+SUM(AD48:AG48) -> 483 | BL48: =+SUM(AH48:AK48) -> 483 | BM48: =+SUM(AL48:AO48) -> 481 | BN48: =+SUM(AP48:AS48) -> 484 | BO48: =+SUM(AT48:AW48) -> 484 | BP48: =+SUM(AX48:BA48) -> 484
A49: Acquisition related matters | B49: =SUM(B50:B51) -> 0 | C49: =SUM(C50:C51) -> 0 | D49: =SUM(D50:D51) -> 1 | E49: =SUM(E50:E51) -> 0 | F49: =SUM(F50:F51) -> 0 | G49: =SUM(G50:G51) -> 0 | H49: =SUM(H50:H51) -> 0 | I49: =SUM(I50:I51) -> 0 | ... AQ49: =SUM(AQ50:AQ51) -> 0 | AR49: =+SUM(AR50:AR51) -> 0 | AS49: =+SUM(AS50:AS51) -> 0 | AT49: =+SUM(AT50:AT51) -> 0 | AU49: =+SUM(AU50:AU51) -> 0 | AV49: =+SUM(AV50:AV51) -> 0 | AW49: =+SUM(AW50:AW51) -> 0 | AX49: =+SUM(AX50:AX51) -> 0 | AY49: =+SUM(AY50:AY51) -> 0 | ... BA49: =+SUM(BA50:BA51) -> 0 | BD49: =+SUM(B49:E49) -> 1 | BE49: =+SUM(F49:I49) -> 0 | BF49: =+SUM(J49:M49) -> 81 | BG49: =SUM(N49:Q49) -> 1 | BH49: =+SUM(R49:U49) -> 29 | BI49: =SUM(V49:Y49) -> 36 | BJ49: =+SUM(Z49:AC49) -> 69 | BK49: =+SUM(AD49:AG49) -> 4 | BL49: =+SUM(AH49:AK49) -> 228 | BM49: =+SUM(AL49:AO49) -> 17 | BN49: =+SUM(AP49:AS49) -> 0 | BO49: =+SUM(AT49:AW49) -> 0 | BP49: =+SUM(AX49:BA49) -> 0
A50: Cost of revenue | B50: =+B154 -> 0 | C50: =+C154 -> 0 | D50: =+D154 -> 0 | E50: =+E154 -> 0 | F50: =+F154 -> 0 | G50: =+G154 -> 0 | H50: =+H154 -> 0 | I50: =+I154 -> 0 | ... Y50: =+Y154 -> 0 | Z50: =+Z123 -> 0 | AA50: =+AA123 -> 0 | AB50: =+AB123 -> 0 | AC50: =+AC123 -> 0 | AD50: =+AD123 -> 0 | AE50: =+AE123 -> 0 | AF50: =+AF123 -> 0 | AG50: =+AG123 -> 0 | ... AQ50: =+AQ123 -> 0 | AR50: =+AR154 -> 0 | AS50: =+AS154 -> 0 | AT50: =+AT154 -> 0 | AU50: =+AU154 -> 0 | AV50: =+AV154 -> 0 | AW50: =+AW154 -> 0 | AX50: =+AX154 -> 0 | AY50: =+AY154 -> 0 | ... BA50: =+BA154 -> 0 | BD50: =+SUM(B50:E50) -> 0 | BE50: =+SUM(F50:I50) -> 0 | BF50: =+SUM(J50:M50) -> 0 | BG50: =SUM(N50:Q50) -> 0 | BH50: =+SUM(R50:U50) -> 0 | BI50: =SUM(V50:Y50) -> 0 | BJ50: =+SUM(Z50:AC50) -> 0 | BK50: =+SUM(AD50:AG50) -> 0 | BL50: =+SUM(AH50:AK50) -> 223 | BM50: =+SUM(AL50:AO50) -> 15 | BN50: =+SUM(AP50:AS50) -> 0 | BO50: =+SUM(AT50:AW50) -> 0 | BP50: =+SUM(AX50:BA50) -> 0
A51: OpEx | B51: =+B158 -> 0 | C51: =+C158 -> 0 | D51: =+D158 -> 1 | E51: =+E158 -> 0 | F51: =+F158 -> 0 | G51: =+G158 -> 0 | H51: =+H158 -> 0 | I51: =+I158 -> 0 | ... BA51: =+BA158 -> 0 | BD51: =+SUM(B51:E51) -> 1 | BE51: =+SUM(F51:I51) -> 0 | BF51: =+SUM(J51:M51) -> 81 | BG51: =SUM(N51:Q51) -> 1 | BH51: =+SUM(R51:U51) -> 29 | BI51: =SUM(V51:Y51) -> 36 | BJ51: =+SUM(Z51:AC51) -> 69 | BK51: =+SUM(AD51:AG51) -> 4 | BL51: =+SUM(AH51:AK51) -> 5 | BM51: =+SUM(AL51:AO51) -> 2 | BN51: =+SUM(AP51:AS51) -> 0 | BO51: =+SUM(AT51:AW51) -> 0 | BP51: =+SUM(AX51:BA51) -> 0
A53: Net (gain) loss on deferred compensation plan liabilities | B53: =+B162 -> 0 | C53: =+C162 -> 0 | D53: =+D162 -> 0 | E53: =+E162 -> 0 | F53: =+F162 -> 0 | G53: =+G162 -> 0 | H53: =+H162 -> 0 | I53: =+I162 -> 0 | ... BA53: =+BA162 -> 0 | BD53: =+SUM(B53:E53) -> 0 | BE53: =+SUM(F53:I53) -> 0 | BF53: =+SUM(J53:M53) -> 0 | BG53: =SUM(N53:Q53) -> 0 | BH53: =+SUM(R53:U53) -> 0 | BI53: =SUM(V53:Y53) -> 0 | BJ53: =+SUM(Z53:AC53) -> 0 | BK53: =+SUM(AD53:AG53) -> 0 | BL53: =+SUM(AH53:AK53) -> 0 | BM53: =+SUM(AL53:AO53) -> 27 | BN53: =+SUM(AP53:AS53) -> 24 | BO53: =+SUM(AT53:AW53) -> 0 | BP53: =+SUM(AX53:BA53) -> 0
A54: Net (gain) loss on debt securities and other investments | B54: =+B164 -> 1 | C54: =+C164 -> 1 | D54: =+D164 -> 2 | E54: =+E164 -> 1 | F54: =+F164 -> 1 | G54: =+G164 -> 6 | H54: =+H164 -> 1 | I54: =+I164 -> 1 | ... AQ54: =+AQ164 -> -29
A55: Net (gain) loss on deferred compensation plan assets | B55: =+B165 -> 0 | C55: =+C165 -> 0 | D55: =+D165 -> 0 | E55: =+E165 -> 0 | F55: =+F165 -> 0 | G55: =+G165 -> 0 | H55: =+H165 -> 0 | I55: =+I165 -> 0 | ... AQ55: =+AQ165 -> -8
A56: Income tax effects and adjustments | B56: =+B166 -> 21 | C56: =+C166 -> 35 | D56: =+D166 -> 31 | E56: =+E166 -> 33 | F56: =+F166 -> 49 | G56: =+G166 -> 36 | H56: =+H166 -> 25 | I56: =+I166 -> 60 | ... AQ56: =+AQ166 -> 190 | AR56: =((AR30-AR43-AR46)*23%-AR31)*-1 -> 173.42337 | AS56: =((AS30-AS43-AS46)*23%-AS31)*-1 -> 173.15571 | AT56: =((AT30-AT43-AT46)*23%-AT31)*-1 -> 178.82364 | AU56: =((AU30-AU43-AU46)*23%-AU31)*-1 -> 176.3633 | AV56: =((AV30-AV43-AV46)*23%-AV31)*-1 -> 200.83402 | AW56: =((AW30-AW43-AW46)*23%-AW31)*-1 -> 183.28059 | AX56: =((AX30-AX43-AX46)*23%-AX31)*-1 -> 185.08691 | AY56: =((AY30-AY43-AY46)*23%-AY31)*-1 -> 183.95486 | ... BA56: =((BA30-BA43-BA46)*23%-BA31)*-1 -> 189.29261 | BD56: =+SUM(B56:E56) -> 120 | BE56: =+SUM(F56:I56) -> 170 | BF56: =+SUM(J56:M56) -> 300 | BG56: =SUM(N56:Q56) -> 209 | BH56: =+SUM(R56:U56) -> 248 | BI56: =SUM(V56:Y56) -> 345 | BJ56: =+SUM(Z56:AC56) -> 585 | BK56: =+SUM(AD56:AG56) -> 683 | BL56: =+SUM(AH56:AK56) -> 933 | BM56: =+SUM(AL56:AO56) -> 836 | BN56: =+SUM(AP56:AS56) -> 718.57908 | BO56: =+SUM(AT56:AW56) -> 739.30155 | BP56: =+SUM(AX56:BA56) -> 764.91893
A58: GAAP Gross Profit | B58: =+B16-B44-B47-B50 -> 547 | C58: =+C16-C44-C47-C50 -> 724 | D58: =+D16-D44-D47-D50 -> 2088 | E58: =+E16-E44-E47-E50 -> 583 | F58: =+F16-F44-F47-F50 -> 595 | G58: =+G16-G44-G47-G50 -> 810 | H58: =+H16-H44-H47-H50 -> 2304 | I58: =+I16-I44-I47-I50 -> 659 | ... BA58: =+BA16-BA44-BA47-BA50 -> 4099.049 | BD58: =+SUM(B58:E58) -> 3942 | BE58: =+SUM(F58:I58) -> 4368 | BF58: =+SUM(J58:M58) -> 5047 | BG58: =SUM(N58:Q58) -> 5617 | BH58: =+SUM(R58:U58) -> 6301 | BI58: =SUM(V58:Y58) -> 7950 | BJ58: =+SUM(Z58:AC58) -> 10320 | BK58: =+SUM(AD58:AG58) -> 11225 | BL58: =+SUM(AH58:AK58) -> 12597 | BM58: =+SUM(AL58:AO58) -> 14968 | BN58: =+SUM(AP58:AS58) -> 17067.414 | BO58: =+SUM(AT58:AW58) -> 19047.599 | BP58: =+SUM(AX58:BA58) -> 21274.676 | BR58: =9.52/8.43 -> 1.1293001
A59: GAAP Operating Income | B59: =+B24-B43-B46-B49-B53 -> -29 | C59: =+C24-C43-C46-C49-C53 -> 42 | D59: =+D24-D43-D46-D49-D53 -> 1285 | E59: =+E24-E43-E46-E49-E53 -> -56 | F59: =+F24-F43-F46-F49-F53 -> -61 | G59: =+G24-G43-G46-G49-G53 -> 22 | H59: =+H24-H43-H46-H49-H53 -> 1444 | I59: =+I24-I43-I46-I49-I53 -> -10 | ... AQ59: =+AQ24-AQ43-AQ46-AQ49-AQ53 -> 855 | AR59: =+AR24-AR43-AR46-AR49 -> 3920.283 | AS59: =+AS24-AS43-AS46-AS49 -> 487.64894 | AT59: =+AT24-AT43-AT46-AT49 -> 725.1237 | AU59: =+AU24-AU43-AU46-AU49 -> 1086.4204 | AV59: =+AV24-AV43-AV46-AV49 -> 4440.7795 | AW59: =+AW24-AW43-AW46-AW49 -> 623.36769 | AX59: =+AX24-AX43-AX46-AX49 -> 913.89178 | AY59: =+AY24-AY43-AY46-AY49 -> 1329.7901 | ... BA59: =+BA24-BA43-BA46-BA49 -> 815.80887 | BD59: =+SUM(B59:E59) -> 1242 | BE59: =+SUM(F59:I59) -> 1395 | BF59: =+SUM(J59:M59) -> 1560 | BG59: =SUM(N59:Q59) -> 1854 | BH59: =+SUM(R59:U59) -> 2176 | BI59: =SUM(V59:Y59) -> 2500 | BJ59: =+SUM(Z59:AC59) -> 2571 | BK59: =+SUM(AD59:AG59) -> 3141 | BL59: =+SUM(AH59:AK59) -> 3630 | BM59: =+SUM(AL59:AO59) -> 4923 | BN59: =+SUM(AP59:AS59) -> 5796.932 | BO59: =+SUM(AT59:AW59) -> 6875.6913 | BP59: =+SUM(AX59:BA59) -> 8065.6103
A60: Consensus GAAP operating income | AM60: =593-AM59 -> 0 | BD60: =+SUM(B60:E60) -> 0 | BE60: =+SUM(F60:I60) -> 0 | BF60: =+SUM(J60:M60) -> 0 | BG60: =SUM(N60:Q60) -> 0 | BH60: =+SUM(R60:U60) -> 0 | BI60: =SUM(V60:Y60) -> 0 | BJ60: =+SUM(Z60:AC60) -> 0 | BK60: =+SUM(AD60:AG60) -> 0 | BL60: =+SUM(AH60:AK60) -> 0 | BM60: =+SUM(AL60:AO60) -> 0 | BN60: =+SUM(AP60:AS60) -> 0 | BO60: =+SUM(AT60:AW60) -> 0 | BP60: =+SUM(AX60:BA60) -> 0
A61: GAAP Net income | B61: =+B33-B43-B46-B49-B53-B54-B55+B56 -> -31 | C61: =+C33-C43-C46-C49-C53-C54-C55+C56+C134 -> 24 | D61: =+D33-D43-D46-D49-D53-D54-D55+D56+D134 -> 1026 | E61: =+E33-E43-E46-E49-E53-E54-E55+E56 -> -40 | F61: =+F33-F43-F46-F49-F53-F54-F55+F56 -> -30 | G61: =+G33-G43-G46-G49-G53-G54-G55+G56 -> 13 | H61: =+H33-H43-H46-H49-H53-H54-H55+H56 -> 964 | I61: =+I33-I43-I46-I49-I53-I54-I55+I56 -> 24 | J61: =+J33-J43-J46-J49-J53-J54-J55+J56 -> -2 | K61: =+K33-K43-K46-K49-K53-K54-K55+K56 -> 183 | L61: =+L33-L43-L46-L49-L53-L54-L55+L56 -> 1186 | ... AQ61: =+AQ33-AQ43-AQ46-AQ49-AQ53-AQ54-AQ55+AQ56 -> 693 | AR61: =+AR33-AR43-AR46-AR49-AR53+AR56 -> 2959.3279 | AS61: =+AS33-AS43-AS46-AS49-AS53+AS56 -> 333.13968 | AT61: =+AT33-AT43-AT46-AT49-AT53+AT56 -> 541.40525 | AU61: =+AU33-AU43-AU46-AU49-AU53+AU56 -> 818.83374 | AV61: =+AV33-AV43-AV46-AV49-AV53+AV56 -> 3360.1102 | AW61: =+AW33-AW43-AW46-AW49-AW53+AW56 -> 437.64312 | AX61: =+AX33-AX43-AX46-AX49-AX53+AX56 -> 686.75667 | AY61: =+AY33-AY43-AY46-AY49-AY53+AY56 -> 1006.2284 | ... BA61: =+BA33-BA43-BA46-BA49-BA53+BA56 -> 585.82283 | BD61: =+SUM(B61:E61) -> 979 | BE61: =+SUM(F61:I61) -> 971 | BF61: =+SUM(J61:M61) -> 1329 | BG61: =SUM(N61:Q61) -> 1557 | BH61: =+SUM(R61:U61) -> 1826 | BI61: =SUM(V61:Y61) -> 2062 | BJ61: =+SUM(Z61:AC61) -> 2066 | BK61: =+SUM(AD61:AG61) -> 2384 | BL61: =+SUM(AH61:AK61) -> 2963 | BM61: =+SUM(AL61:AO61) -> 3869 | BN61: =+SUM(AP61:AS61) -> 4431.4676 | BO61: =+SUM(AT61:AW61) -> 5157.9923 | BP61: =+SUM(AX61:BA61) -> 6074.2299
A62: GAAP EPS | B62: =B61/B64 -> -0.11397059 | C62: =C61/C64 -> 0.090225564 | D62: =D61/D64 -> 3.9461538 | E62: =E61/E64 -> -0.15564202 | F62: =F61/F64 -> -0.11627907 | G62: =G61/G64 -> 0.05 | H62: =H61/H64 -> 3.7076923 | I62: =I61/I64 -> 0.091954023 | ... BA62: =BA61/BA64 -> 2.0922244 | BD62: =+BD61/BD64 -> 3.7118483 | BE62: =+BE61/BE64 -> 3.7382098 | BF62: =+BF61/BF64 -> 5.1312741 | BG62: =+BG61/BG64 -> 5.8977273 | BH62: =+BH61/BH64 -> 6.9199432 | BI62: =+BI61/BI64 -> 7.5600367 | BJ62: =SUM(Z62:AC62) -> 7.2456825 | BK62: =SUM(AD62:AG62) -> 8.4143269 | BL62: =+BL61/BL64 -> 10.454265 | BM62: =+BM61/BM64 -> 13.701638 | BN62: =+BN61/BN64 -> 15.825257 | BO62: =+BO61/BO64 -> 18.355845 | BP62: =+BP61/BP64 -> 21.693678 | BR62: =+BM62/BL62 -> 1.3106266 | BS62: =+BN62/BM62 -> 1.1549902
A63: Consensus GAAP EPS | N63: {=_xll.FDS("INTU-US","FE_ESTIMATE(EPS_GAAP,MEAN,QTR_ROLL,"&N2&",NOW,,,'')")} -> 0.13 | O63: {=_xll.FDS("INTU-US","FE_ESTIMATE(EPS_GAAP,MEAN,QTR_ROLL,"&O2&",NOW,,,'')")} -> 0.72 | P63: {=_xll.FDS("INTU-US","FE_ESTIMATE(EPS_GAAP,MEAN,QTR_ROLL,"&P2&",NOW,,,'')")} -> 5.22 | Q63: {=_xll.FDS("INTU-US","FE_ESTIMATE(EPS_GAAP,MEAN,QTR_ROLL,"&Q2&",NOW,,,'')")} -> -0.17 | R63: {=_xll.FDS("INTU-US","FE_ESTIMATE(EPS_GAAP,MEAN,QTR_ROLL,"&R2&",NOW,,,'')")} -> 0.22 | S63: {=_xll.FDS("INTU-US","FE_ESTIMATE(EPS_GAAP,MEAN,QTR_ROLL,"&S2&",NOW,,,'')")} -> 0.91 | T63: {=_xll.FDS("INTU-US","FE_ESTIMATE(EPS_GAAP,MEAN,QTR_ROLL,"&T2&",NOW,,,'')")} -> 4.11 | U63: {=_xll.FDS("INTU-US","FE_ESTIMATE(EPS_GAAP,MEAN,QTR_ROLL,"&U2&",NOW,,,'')")} -> 1.68 | ... BA63: {=_xll.FDS("INTU-US","FE_ESTIMATE(EPS_GAAP,MEAN,QTR_ROLL,"&BA2&",NOW,,,'')")} -> 1.9873075
A64: GAAP diluted shares outstanding | B64: =+B140 -> 272 | C64: =+C140 -> 266 | D64: =+D140 -> 260 | E64: =+E140 -> 257 | F64: =+F140 -> 258 | G64: =+G140 -> 260 | H64: =+H140 -> 260 | I64: =+I140 -> 261 | ... AC64: =+AC140 -> 282 | AD64: =+AC64+AD37-AC37 -> 283.8 | AE64: =+AD64+AE37-AD37 -> 282.4 | AF64: =+AE64+AF37-AE37 -> 283.4 | AG64: =+AF64+AG37-AF37 -> 283.14 | AH64: =+AG64+AH37-AG37 -> 283 | AI64: =+AH64+AI37-AH37 -> 284 | AJ64: =+AI64+AJ37-AI37 -> 283.7 | AK64: =+AJ64+AK37-AJ37 -> 283 | AL64: 283 | AM64: =+AL64+AM37-AL37 -> 283 | AN64: =+AM64+AN37-AM37 -> 281.5 | AO64: =+AN64+AO37-AN37 -> 282 | AP64: 281 | AQ64: =+AP64+AQ37-AP37 -> 279.7 | AR64: =+AQ64+AR37-AQ37 -> 279.7 | AS64: =+AR64+AS37-AR37 -> 279.7 | AT64: =+AS64+AT37-AS37 -> 281 | AU64: =+AT64+AU37-AT37 -> 281 | AV64: =+AU64+AV37-AU37 -> 281 | AW64: =+AV64+AW37-AV37 -> 281 | AX64: =+AW64+AX37-AW37 -> 280 | ... BA64: =+AZ64+BA37-AZ37 -> 280 | BD64: =AVERAGE(B64:E64) -> 263.75 | BE64: =+AVERAGE(F64:I64) -> 259.75 | BF64: =+AVERAGE(J64:M64) -> 259 | BG64: =AVERAGE(N64:Q64) -> 264 | BH64: =+AVERAGE(R64:U64) -> 263.875 | BI64: =AVERAGE(V64:Y64) -> 272.75 | BJ64: =+AVERAGE(Z64:AC64) -> 283 | BK64: =+AVERAGE(AD64:AG64) -> 283.185 | BL64: =+AVERAGE(AH64:AK64) -> 283.425 | BM64: =+AVERAGE(AL64:AO64) -> 282.375 | BN64: =+AVERAGE(AP64:AS64) -> 280.025 | BO64: =+AVERAGE(AT64:AW64) -> 281 | BP64: =+AVERAGE(AX64:BA64) -> 280
B66: =+B3 -> Fiscal 2016 | F66: =+F3 -> Fiscal 2017 | J66: =+J3 -> Fiscal 2018 | N66: =+N3 -> Fiscal 2019 | R66: =+R3 -> Fiscal 2020 | V66: =+V3 -> Fiscal 2021 | Z66: =+Z3 -> Fiscal 2022 | AD66: =+AD3 -> Fiscal 2023 | AH66: =+AH3 -> Fiscal 2024 | AL66: =+AL3 -> Fiscal 2025 | AP66: =+AP3 -> Fiscal 2026 | AT66: =+AT3 -> Fiscal 2027 | AX66: =+AX3 -> Fiscal 2028
B67: =+B4 -> 42308 | C67: =+C4 -> 42400 | D67: =+D4 -> 42490 | E67: =+E4 -> 42582 | F67: =+F4 -> 42674 | G67: =+G4 -> 42766 | H67: =+H4 -> 42855 | I67: =+I4 -> 42947 | ... BA67: =+BA4 -> Jul-28E | BD67: =+BD4 -> FY16 | BE67: =+BE4 -> FY17 | BF67: =+BF4 -> FY18 | BG67: =+BG4 -> FY19 | BH67: =+BH4 -> FY20 | BI67: =+BI4 -> FY21 | BJ67: =+BJ4 -> FY22 | BK67: =+BK4 -> FY23 | ... BP67: =+BP4 -> FY28E
A68: Y/Y Growth
A69: Total Revenue | B69: =IFERROR(B7/#REF!-1,"NA") -> NA | C69: =IFERROR(C7/#REF!-1,"NA") -> NA | D69: =IFERROR(D7/#REF!-1,"NA") -> NA | E69: =IFERROR(E7/A7-1,"NA") -> NA | F69: =IF(OR(B9<=0,F9<=0),"NM",(F9-B9)/B9) -> 0.091164095 | G69: =IF(OR(C9<=0,G9<=0),"NM",(G9-C9)/C9) -> 0.1007584 | H69: =IF(OR(D9<=0,H9<=0),"NM",(H9-D9)/D9) -> 0.10286458 | I69: =IF(OR(E9<=0,I9<=0),"NM",(I9-E9)/E9) -> 0.11671088 | J69: =IF(OR(F9<=0,J9<=0),"NM",(J9-F9)/F9) -> 0.16966581 | K69: =IF(OR(G9<=0,K9<=0),"NM",(K9-G9)/G9) -> 0.31791339 | L69: =IF(OR(H9<=0,L9<=0),"NM",(L9-H9)/H9) -> 0.14600551 | M69: =IF(OR(I9<=0,M9<=0),"NM",(M9-I9)/I9) -> 0.026128266 | ... BA69: =IF(OR(AW9<=0,BA9<=0),"NM",(BA9-AW9)/AW9) -> 0.1237807 | BD69: =IFERROR(BD7/BC7-1,"NA") -> NA | BE69: =IFERROR(BE9/BD9-1,"NA") -> 0.10289732 | BF69: =IFERROR(BF9/BE9-1,"NA") -> 0.16380143 | BG69: =IFERROR(BG9/BF9-1,"NA") -> 0.1259751 | BH69: =IFERROR(BH9/BG9-1,"NA") -> 0.13192807 | BI69: =IFERROR(BI9/BH9-1,"NA") -> 0.25446022 | BJ69: =IFERROR(BJ9/BI9-1,"NA") -> 0.32108377 | BK69: =IFERROR(BK9/BJ9-1,"NA") -> 0.12902719 | BL69: =IFERROR(BL9/BK9-1,"NA") -> 0.13342149 | ... BP69: =IFERROR(BP9/BO9-1,"NA") -> 0.11799283
A70: Total cost of revenue | B70: =IFERROR(B15/#REF!-1,"NA") -> NA | C70: =IFERROR(C15/#REF!-1,"NA") -> NA | D70: =IFERROR(D15/#REF!-1,"NA") -> NA | E70: =IFERROR(E15/A15-1,"NA") -> NA | F70: =IF(OR(B15<=0,F15<=0),"NM",(F15-B15)/B15) -> 0.12658228 | G70: =IF(OR(C15<=0,G15<=0),"NM",(G15-C15)/C15) -> 0.052356021 | H70: =IF(OR(D15<=0,H15<=0),"NM",(H15-D15)/D15) -> 0.11004785 | I70: =IF(OR(E15<=0,I15<=0),"NM",(I15-E15)/E15) -> 0.085365854 | J70: =IF(OR(F15<=0,J15<=0),"NM",(J15-F15)/F15) -> 0.084269663 | K70: =IF(OR(G15<=0,K15<=0),"NM",(K15-G15)/G15) -> 0.14427861 | L70: =IF(OR(H15<=0,L15<=0),"NM",(L15-H15)/H15) -> 0.23275862 | M70: =IF(OR(I15<=0,M15<=0),"NM",(M15-I15)/I15) -> 0.18539326 | ... BA70: =IF(OR(AW15<=0,BA15<=0),"NM",(BA15-AW15)/AW15) -> 0.13095806 | BD70: =IFERROR(BD15/BC15-1,"NA") -> NA | BE70: =IFERROR(BE15/BD15-1,"NA") -> 0.092797784 | BF70: =IFERROR(BF15/BE15-1,"NA") -> 0.16603295 | BG70: =IFERROR(BG15/BF15-1,"NA") -> 0.18369565 | BH70: =IFERROR(BH15/BG15-1,"NA") -> 0.19008264 | BI70: =IFERROR(BI15/BH15-1,"NA") -> 0.20679012 | BJ70: =IFERROR(BJ15/BI15-1,"NA") -> 0.35549872 | BK70: =IFERROR(BK15/BJ15-1,"NA") -> 0.22924528 | ... BP70: =IFERROR(BP15/BO15-1,"NA") -> 0.12761493
A71: Gross profit | B71: =IFERROR(B16/#REF!-1,"NA") -> NA | C71: =IFERROR(C16/#REF!-1,"NA") -> NA | D71: =IFERROR(D16/#REF!-1,"NA") -> NA | E71: =IFERROR(E16/A16-1,"NA") -> NA | F71: =IF(OR(B16<=0,F16<=0),"NM",(F16-B16)/B16) -> 0.081081081 | G71: =IF(OR(C16<=0,G16<=0),"NM",(G16-C16)/C16) -> 0.11338798 | H71: =IF(OR(D16<=0,H16<=0),"NM",(H16-D16)/D16) -> 0.10214797 | I71: =IF(OR(E16<=0,I16<=0),"NM",(I16-E16)/E16) -> 0.12542373 | J71: =IF(OR(F16<=0,J16<=0),"NM",(J16-F16)/F16) -> 0.195 | K71: =IF(OR(G16<=0,K16<=0),"NM",(K16-G16)/G16) -> 0.3607362 | L71: =IF(OR(H16<=0,L16<=0),"NM",(L16-H16)/H16) -> 0.13728887 | M71: =IF(OR(I16<=0,M16<=0),"NM",(M16-I16)/I16) -> -0.016566265 | ... BA71: =IF(OR(AW16<=0,BA16<=0),"NM",(BA16-AW16)/AW16) -> 0.12200742 | BD71: =IFERROR(BD16/BC16-1,"NA") -> NA | BE71: =IFERROR(BE16/BD16-1,"NA") -> 0.10473313 | BF71: =IFERROR(BF16/BE16-1,"NA") -> 0.16340018 | BG71: =IFERROR(BG16/BF16-1,"NA") -> 0.11557297 | BH71: =IFERROR(BH16/BG16-1,"NA") -> 0.12080773 | BI71: =IFERROR(BI16/BH16-1,"NA") -> 0.26413912 | BJ71: =IFERROR(BJ16/BI16-1,"NA") -> 0.31441319 | BK71: =IFERROR(BK16/BJ16-1,"NA") -> 0.10899491 | ... BP71: =IFERROR(BP16/BO16-1,"NA") -> 0.11598418
A72: Sales and marketing expenses | B72: =IFERROR(B20/#REF!-1,"NA") -> NA | C72: =IFERROR(C20/#REF!-1,"NA") -> NA | D72: =IFERROR(D20/#REF!-1,"NA") -> NA | E72: =IFERROR(E20/A20-1,"NA") -> NA | F72: =IF(OR(B20<=0,F20<=0),"NM",(F20-B20)/B20) -> 0.14666667 | G72: =IF(OR(C20<=0,G20<=0),"NM",(G20-C20)/C20) -> 0.13313609 | H72: =IF(OR(D20<=0,H20<=0),"NM",(H20-D20)/D20) -> 0.10617284 | I72: =IF(OR(E20<=0,I20<=0),"NM",(I20-E20)/E20) -> -0.0040983607 | J72: =IF(OR(F20<=0,J20<=0),"NM",(J20-F20)/F20) -> 0.096899225 | K72: =IF(OR(G20<=0,K20<=0),"NM",(K20-G20)/G20) -> 0.15926893 | L72: =IF(OR(H20<=0,L20<=0),"NM",(L20-H20)/H20) -> 0.16964286 | M72: =IF(OR(I20<=0,M20<=0),"NM",(M20-I20)/I20) -> 0.14814815 | ... BA72: =IF(OR(AW20<=0,BA20<=0),"NM",(BA20-AW20)/AW20) -> 0.10364126 | BD72: =IFERROR(BD20/BC20-1,"NA") -> NA | BE72: =IFERROR(BE20/BD20-1,"NA") -> 0.099009901 | BF72: =IFERROR(BF20/BE20-1,"NA") -> 0.14864865 | BG72: =IFERROR(BG20/BF20-1,"NA") -> 0.19215686 | BH72: =IFERROR(BH20/BG20-1,"NA") -> 0.059210526 | BI72: =IFERROR(BI20/BH20-1,"NA") -> 0.27380952 | BJ72: =IFERROR(BJ20/BI20-1,"NA") -> 0.3071922 | BK72: =IFERROR(BK20/BJ20-1,"NA") -> 0.03605844 | ... BP72: =IFERROR(BP20/BO20-1,"NA") -> 0.10779479
A73: Research and development expenses | B73: =IFERROR(B21/#REF!-1,"NA") -> NA | C73: =IFERROR(C21/#REF!-1,"NA") -> NA | D73: =IFERROR(D21/#REF!-1,"NA") -> NA | E73: =IFERROR(E21/A21-1,"NA") -> NA | F73: =IF(OR(B21<=0,F21<=0),"NM",(F21-B21)/B21) -> 0.09375 | G73: =IF(OR(C21<=0,G21<=0),"NM",(G21-C21)/C21) -> 0.16304348 | H73: =IF(OR(D21<=0,H21<=0),"NM",(H21-D21)/D21) -> 0.072463768 | I73: =IF(OR(E21<=0,I21<=0),"NM",(I21-E21)/E21) -> 0.10576923 | J73: =IF(OR(F21<=0,J21<=0),"NM",(J21-F21)/F21) -> 0.20952381 | K73: =IF(OR(G21<=0,K21<=0),"NM",(K21-G21)/G21) -> 0.19626168 | L73: =IF(OR(H21<=0,L21<=0),"NM",(L21-H21)/H21) -> 0.1981982 | M73: =IF(OR(I21<=0,M21<=0),"NM",(M21-I21)/I21) -> 0.20434783 | ... BA73: =IF(OR(AW21<=0,BA21<=0),"NM",(BA21-AW21)/AW21) -> 0.10933439 | BD73: =IFERROR(BD21/BC21-1,"NA") -> NA | BE73: =IFERROR(BE21/BD21-1,"NA") -> 0.10745891 | BF73: =IFERROR(BF21/BE21-1,"NA") -> 0.20205479 | BG73: =IFERROR(BG21/BF21-1,"NA") -> 0.041785375 | BH73: =IFERROR(BH21/BG21-1,"NA") -> 0.13126709 | BI73: =IFERROR(BI21/BH21-1,"NA") -> 0.12570508 | BJ73: =IFERROR(BJ21/BI21-1,"NA") -> 0.30708661 | BK73: =IFERROR(BK21/BJ21-1,"NA") -> 0.099123768 | ... BP73: =IFERROR(BP21/BO21-1,"NA") -> 0.10395781
A74: General and administrative expenses | B74: =IFERROR(B22/#REF!-1,"NA") -> NA | C74: =IFERROR(C22/#REF!-1,"NA") -> NA | D74: =IFERROR(D22/#REF!-1,"NA") -> NA | E74: =IFERROR(E22/A22-1,"NA") -> NA | F74: =IF(OR(B22<=0,F22<=0),"NM",(F22-B22)/B22) -> 0.086956522 | G74: =IF(OR(C22<=0,G22<=0),"NM",(G22-C22)/C22) -> 0.16666667 | H74: =IF(OR(D22<=0,H22<=0),"NM",(H22-D22)/D22) -> -0.032258065 | I74: =IF(OR(E22<=0,I22<=0),"NM",(I22-E22)/E22) -> 0.10784314 | J74: =IF(OR(F22<=0,J22<=0),"NM",(J22-F22)/F22) -> 0.15 | K74: =IF(OR(G22<=0,K22<=0),"NM",(K22-G22)/G22) -> 0.026785714 | L74: =IF(OR(H22<=0,L22<=0),"NM",(L22-H22)/H22) -> 0.13333333 | M74: =IF(OR(I22<=0,M22<=0),"NM",(M22-I22)/I22) -> -0.0088495575 | ... BA74: =IF(OR(AW22<=0,BA22<=0),"NM",(BA22-AW22)/AW22) -> 0.094560788 | BD74: =IFERROR(BD22/BC22-1,"NA") -> NA | BE74: =IFERROR(BE22/BD22-1,"NA") -> 0.074879227 | BF74: =IFERROR(BF22/BE22-1,"NA") -> 0.074157303 | BG74: =IFERROR(BG22/BF22-1,"NA") -> 0.029288703 | BH74: =IFERROR(BH22/BG22-1,"NA") -> 0.10162602 | BI74: =IFERROR(BI22/BH22-1,"NA") -> 0.33948339 | BJ74: =IFERROR(BJ22/BI22-1,"NA") -> 0.45867769 | BK74: =IFERROR(BK22/BJ22-1,"NA") -> -0.13220019 | ... BP74: =IFERROR(BP22/BO22-1,"NA") -> 0.082985567
A75: Total operating expenses | B75: =IFERROR(B23/#REF!-1,"NA") -> NA | C75: =IFERROR(C23/#REF!-1,"NA") -> NA | D75: =IFERROR(D23/#REF!-1,"NA") -> NA | E75: =IFERROR(E23/#REF!-1,"NA") -> NA | F75: =IF(OR(B23<=0,F23<=0),"NM",(F23-B23)/B23) -> 0.11591356 | G75: =IF(OR(C23<=0,G23<=0),"NM",(G23-C23)/C23) -> 0.14724919 | H75: =IF(OR(D23<=0,H23<=0),"NM",(H23-D23)/D23) -> 0.073369565 | I75: =IF(OR(E23<=0,I23<=0),"NM",(I23-E23)/E23) -> 0.057761733 | J75: =IF(OR(F23<=0,J23<=0),"NM",(J23-F23)/F23) -> 0.14788732 | K75: =IF(OR(G23<=0,K23<=0),"NM",(K23-G23)/G23) -> 0.14950635 | L75: =IF(OR(H23<=0,L23<=0),"NM",(L23-H23)/H23) -> 0.1721519 | M75: =IF(OR(I23<=0,M23<=0),"NM",(M23-I23)/I23) -> 0.13993174 | ... BA75: =IF(OR(AW23<=0,BA23<=0),"NM",(BA23-AW23)/AW23) -> 0.1040074 | BD75: =IFERROR(BD23/BC23-1,"NA") -> NA | BE75: =IFERROR(BE23/BD23-1,"NA") -> 0.097641705 | BF75: =IFERROR(BF23/BE23-1,"NA") -> 0.15378816 | BG75: =IFERROR(BG23/BF23-1,"NA") -> 0.1149951 | BH75: =IFERROR(BH23/BG23-1,"NA") -> 0.088485204 | BI75: =IFERROR(BI23/BH23-1,"NA") -> 0.23391655 | BJ75: =IFERROR(BJ23/BI23-1,"NA") -> 0.33115183 | BK75: =IFERROR(BK23/BJ23-1,"NA") -> 0.025729269 | ... BP75: =IFERROR(BP23/BO23-1,"NA") -> 0.1031974
A76: Operating income | B76: =IFERROR(B24/#REF!-1,"NA") -> NA | C76: =IFERROR(C24/#REF!-1,"NA") -> NA | D76: =IFERROR(D24/#REF!-1,"NA") -> NA | E76: =IFERROR(E24/#REF!-1,"NA") -> NA | F76: =IF(OR(B24<=0,F24<=0),"NM",(F24-B24)/B24) -> -0.30434783 | G76: =IF(OR(C24<=0,G24<=0),"NM",(G24-C24)/C24) -> -0.070175439 | H76: =IF(OR(D24<=0,H24<=0),"NM",(H24-D24)/D24) -> 0.11773363 | I76: =IF(OR(E24<=0,I24<=0),"NM",(I24-E24)/E24) -> 1.1666667 | J76: =IF(OR(F24<=0,J24<=0),"NM",(J24-F24)/F24) -> 1.03125 | K76: =IF(OR(G24<=0,K24<=0),"NM",(K24-G24)/G24) -> 1.7735849 | L76: =IF(OR(H24<=0,L24<=0),"NM",(L24-H24)/H24) -> 0.11915734 | M76: =IF(OR(I24<=0,M24<=0),"NM",(M24-I24)/I24) -> NM | ... BA76: =IF(OR(AW24<=0,BA24<=0),"NM",(BA24-AW24)/AW24) -> 0.15371384 | BD76: =IFERROR(BD24/BC24-1,"NA") -> NA | BE76: =IFERROR(BE24/BD24-1,"NA") -> 0.11575563 | BF76: =IFERROR(BF24/BE24-1,"NA") -> 0.17809798 | BG76: =IFERROR(BG24/BF24-1,"NA") -> 0.11643836 | BH76: =IFERROR(BH24/BG24-1,"NA") -> 0.16914987 | BI76: =IFERROR(BI24/BH24-1,"NA") -> 0.30622189 | BJ76: =IFERROR(BJ24/BI24-1,"NA") -> 0.29239598 | BK76: =IFERROR(BK24/BJ24-1,"NA") -> 0.22180284 | ... BP76: =IFERROR(BP24/BO24-1,"NA") -> 0.12889639
A77: Net income | B77: =IFERROR(B33/#REF!-1,"NA") -> NA | C77: =IFERROR(C33/#REF!-1,"NA") -> NA | D77: =IFERROR(D33/#REF!-1,"NA") -> NA | E77: =IFERROR(E33/A33-1,"NA") -> NA | F77: =IF(OR(B33<=0,F33<=0),"NM",(F33-B33)/B33) -> -0.375 | G77: =IF(OR(C33<=0,G33<=0),"NM",(G33-C33)/C33) -> 0 | H77: =IF(OR(D33<=0,H33<=0),"NM",(H33-D33)/D33) -> 0.13661814 | I77: =IF(OR(E33<=0,I33<=0),"NM",(I33-E33)/E33) -> 1.65 | J77: =IF(OR(F33<=0,J33<=0),"NM",(J33-F33)/F33) -> 1.9333333 | K77: =IF(OR(G33<=0,K33<=0),"NM",(K33-G33)/G33) -> 2.2686567 | L77: =IF(OR(H33<=0,L33<=0),"NM",(L33-H33)/H33) -> 0.23251232 | M77: =IF(OR(I33<=0,M33<=0),"NM",(M33-I33)/I33) -> NM | ... BA77: =IF(OR(AW33<=0,BA33<=0),"NM",(BA33-AW33)/AW33) -> 0.16010404 | BD77: =IFERROR(BD33/BC33-1,"NA") -> NA | BE77: =IFERROR(BE33/BD33-1,"NA") -> 0.14541833 | BF77: =IFERROR(BF33/BE33-1,"NA") -> 0.31391304 | BG77: =IFERROR(BG33/BF33-1,"NA") -> 0.17935142 | BH77: =IFERROR(BH33/BG33-1,"NA") -> 0.164422 | BI77: =IFERROR(BI33/BH33-1,"NA") -> 0.28048193 | BJ77: =IFERROR(BJ33/BI33-1,"NA") -> 0.26646594 | BK77: =IFERROR(BK33/BJ33-1,"NA") -> 0.21248143 | ... BP77: =IFERROR(BP33/BO33-1,"NA") -> 0.13127135
A78: EPS | B78: =IFERROR(B35/#REF!-1,"NA") -> NA | C78: =IFERROR(C35/#REF!-1,"NA") -> NA | D78: =IFERROR(D35/#REF!-1,"NA") -> NA | E78: =IFERROR(E35/A35-1,"NA") -> NA | F78: =IF(OR(B35<=0,F35<=0),"NM",(F35-B35)/B35) -> -0.34108527 | G78: =IF(OR(C35<=0,G35<=0),"NM",(G35-C35)/C35) -> 0.023076923 | H78: =IF(OR(D35<=0,H35<=0),"NM",(H35-D35)/D35) -> 0.13661814 | I78: =IF(OR(E35<=0,I35<=0),"NM",(I35-E35)/E35) -> 1.65 | J78: =IF(OR(F35<=0,J35<=0),"NM",(J35-F35)/F35) -> 1.9220077 | K78: =IF(OR(G35<=0,K35<=0),"NM",(K35-G35)/G35) -> 2.2686567 | L78: =IF(OR(H35<=0,L35<=0),"NM",(L35-H35)/H35) -> 0.22310382 | M78: =IF(OR(I35<=0,M35<=0),"NM",(M35-I35)/I35) -> NM | ... BA78: =IF(OR(AW35<=0,BA35<=0),"NM",(BA35-AW35)/AW35) -> 0.16424727 | BD78: =IFERROR(BD35/BC35-1,"NA") -> NA | BE78: =IFERROR(BE35/BD35-1,"NA") -> 0.16748804 | BF78: =IFERROR(BF35/BE35-1,"NA") -> 0.31264845 | BG78: =IFERROR(BG35/BF35-1,"NA") -> 0.16477769 | BH78: =IFERROR(BH35/BG35-1,"NA") -> 0.16056082 | BI78: =IFERROR(BI35/BH35-1,"NA") -> 0.22972108 | BJ78: =IFERROR(BJ35/BI35-1,"NA") -> 0.222728 | BK78: =IFERROR(BK35/BJ35-1,"NA") -> 0.21818364 | ... BP78: =IFERROR(BP35/BO35-1,"NA") -> 0.1353116
A79: Dividends | B79: =IFERROR(B36/#REF!-1,"NA") -> NA | C79: =IFERROR(C36/#REF!-1,"NA") -> NA | D79: =IFERROR(D36/#REF!-1,"NA") -> NA | E79: =IFERROR(E36/A36-1,"NA") -> NA | F79: =IF(OR(B39<=0,F39<=0),"NM",(F39-B39)/B39) -> 0.13333333 | G79: =IF(OR(C39<=0,G39<=0),"NM",(G39-C39)/C39) -> 0.13333333 | H79: =IF(OR(D39<=0,H39<=0),"NM",(H39-D39)/D39) -> 0.13333333 | I79: =IF(OR(E39<=0,I39<=0),"NM",(I39-E39)/E39) -> 0.13333333 | J79: =IF(OR(F39<=0,J39<=0),"NM",(J39-F39)/F39) -> 0.14705882 | K79: =IF(OR(G39<=0,K39<=0),"NM",(K39-G39)/G39) -> 0.14705882 | L79: =IF(OR(H39<=0,L39<=0),"NM",(L39-H39)/H39) -> 0.14705882 | M79: =IF(OR(I39<=0,M39<=0),"NM",(M39-I39)/I39) -> 0.14705882 | ... W79: =IF(OR(S39<=0,W39<=0),"NM",(W39-S39)/S39) -> 0.11320755 | X79: =+W79 -> 0.11320755 | Y79: =+X79 -> 0.11320755 | Z79: 0.15 | AA79: =IF(OR(W39<=0,AA39<=0),"NM",(AA39-W39)/W39) -> 0.15254237 | AB79: =+AA79 -> 0.15254237 | AC79: =+AB79 -> 0.15254237 | AD79: 0.135 | AE79: =IF(OR(AA39<=0,AE39<=0),"NM",(AE39-AA39)/AA39) -> 0.14705882 | AF79: =+AE79 -> 0.14705882 | AG79: =+AF79 -> 0.14705882 | AH79: 0.135 | AI79: =IF(OR(AE39<=0,AI39<=0),"NM",(AI39-AE39)/AE39) -> 0.15384615 | AJ79: =+AI79 -> 0.15384615 | AK79: =+AJ79 -> 0.15384615 | AL79: 0.135 | AM79: =+AL79 -> 0.135 | AN79: =+AM79 -> 0.135 | AO79: =+AN79 -> 0.135 | AP79: 0.15 | AQ79: =+AP79 -> 0.15 | AR79: =+AQ79 -> 0.15 | AS79: =+AR79 -> 0.15 | AT79: 0.135 | AU79: =+AT79 -> 0.135 | AV79: =+AU79 -> 0.135 | AW79: =+AV79 -> 0.135 | AX79: 0.135 | AY79: =+AX79 -> 0.135 | AZ79: =+AY79 -> 0.135 | BA79: =+AZ79 -> 0.135 | BD79: NA | BE79: =IFERROR(BE39/BD39-1,"NA") -> 0.13333333 | BF79: =IFERROR(BF39/BE39-1,"NA") -> 0.14705882 | BG79: =IFERROR(BG39/BF39-1,"NA") -> 0.20512821 | BH79: =IFERROR(BH39/BG39-1,"NA") -> 0.12765957 | BI79: =IFERROR(BI39/BH39-1,"NA") -> 0.11320755 | BJ79: =IFERROR(BJ39/BI39-1,"NA") -> 0.15254237 | BK79: =IFERROR(BK39/BJ39-1,"NA") -> 0.14705882 | BL79: =IFERROR(BL39/BK39-1,"NA") -> 0.15384615 | ... BP79: =IFERROR(BP39/BO39-1,"NA") -> 0.135
A81: Q/Q Growth
A82: Total Revenue | B82: =IFERROR(B9/A9-1,"NA") -> NA | C82: =IFERROR(C9/B9-1,"NA") -> 0.29453015 | D82: =IFERROR(D9/C9-1,"NA") -> 1.496208 | E82: =IFERROR(E9/D9-1,"NA") -> -0.67274306 | F82: =IFERROR(F9/E9-1,"NA") -> 0.031830239 | G82: =IFERROR(G9/F9-1,"NA") -> 0.3059126 | H82: =IFERROR(H9/G9-1,"NA") -> 1.5009843 | I82: =IFERROR(I9/H9-1,"NA") -> -0.6686344 | ... BA82: =IFERROR(BA9/AZ9-1,"NA") -> -0.4790776
A83: Total cost of revenue | B83: =IFERROR(B15/A15-1,"NA") -> NA | C83: =IFERROR(C15/B15-1,"NA") -> 0.20886076 | D83: =IFERROR(D15/C15-1,"NA") -> 0.094240838 | E83: =IFERROR(E15/D15-1,"NA") -> -0.215311 | F83: =IFERROR(F15/E15-1,"NA") -> 0.085365854 | G83: =IFERROR(G15/F15-1,"NA") -> 0.12921348 | H83: =IFERROR(H15/G15-1,"NA") -> 0.15422886 | I83: =IFERROR(I15/H15-1,"NA") -> -0.23275862 | ... BA83: =IFERROR(BA15/AZ15-1,"NA") -> -0.24366917
A84: Gross profit | B84: =IFERROR(B16/A16-1,"NA") -> NA | C84: =IFERROR(C16/B16-1,"NA") -> 0.31891892 | D84: =IFERROR(D16/C16-1,"NA") -> 1.8620219 | E84: =IFERROR(E16/D16-1,"NA") -> -0.71837709 | F84: =IFERROR(F16/E16-1,"NA") -> 0.016949153 | G84: =IFERROR(G16/F16-1,"NA") -> 0.35833333 | H84: =IFERROR(H16/G16-1,"NA") -> 1.8331288 | I84: =IFERROR(I16/H16-1,"NA") -> -0.71242962 | ... BA84: =IFERROR(BA16/AZ16-1,"NA") -> -0.51655124
A85: Sales and marketing expenses | B85: =IFERROR(B20/A20-1,"NA") -> NA | C85: =IFERROR(C20/B20-1,"NA") -> 0.50222222 | D85: =IFERROR(D20/C20-1,"NA") -> 0.19822485 | E85: =IFERROR(E20/D20-1,"NA") -> -0.39753086 | F85: =IFERROR(F20/E20-1,"NA") -> 0.057377049 | G85: =IFERROR(G20/F20-1,"NA") -> 0.48449612 | H85: =IFERROR(H20/G20-1,"NA") -> 0.16971279 | I85: =IFERROR(I20/H20-1,"NA") -> -0.45758929 | ... BA85: =IFERROR(BA20/AZ20-1,"NA") -> -0.27720009
A86: Research and development expenses | B86: =IFERROR(B21/A21-1,"NA") -> NA | C86: =IFERROR(C21/B21-1,"NA") -> -0.041666667 | D86: =IFERROR(D21/C21-1,"NA") -> 0.125 | E86: =IFERROR(E21/D21-1,"NA") -> 0.0048309179 | F86: =IFERROR(F21/E21-1,"NA") -> 0.0096153846 | G86: =IFERROR(G21/F21-1,"NA") -> 0.019047619 | H86: =IFERROR(H21/G21-1,"NA") -> 0.037383178 | I86: =IFERROR(I21/H21-1,"NA") -> 0.036036036 | ... BA86: =IFERROR(BA21/AZ21-1,"NA") -> 0.15792862
A87: General and administrative expenses | B87: =IFERROR(B22/A22-1,"NA") -> NA | C87: =IFERROR(C22/B22-1,"NA") -> 0.043478261 | D87: =IFERROR(D22/C22-1,"NA") -> 0.29166667 | E87: =IFERROR(E22/D22-1,"NA") -> -0.17741935 | F87: =IFERROR(F22/E22-1,"NA") -> -0.019607843 | G87: =IFERROR(G22/F22-1,"NA") -> 0.12 | H87: =IFERROR(H22/G22-1,"NA") -> 0.071428571 | I87: =IFERROR(I22/H22-1,"NA") -> -0.058333333 | ... BA87: =IFERROR(BA22/AZ22-1,"NA") -> 0.055369414
A88: Total operating expenses | B88: =IFERROR(B23/A23-1,"NA") -> NA | C88: =IFERROR(C23/B23-1,"NA") -> 0.21414538 | D88: =IFERROR(D23/C23-1,"NA") -> 0.19093851 | E88: =IFERROR(E23/D23-1,"NA") -> -0.24728261 | F88: =IFERROR(F23/E23-1,"NA") -> 0.025270758 | G88: =IFERROR(G23/F23-1,"NA") -> 0.24823944 | H88: =IFERROR(H23/G23-1,"NA") -> 0.11424542 | I88: =IFERROR(I23/H23-1,"NA") -> -0.25822785 | ... BA88: =IFERROR(BA23/AZ23-1,"NA") -> -0.13764154
A89: Operating income | B89: =IFERROR(B24/A24-1,"NA") -> NA | C89: =IFERROR(C24/B24-1,"NA") -> 1.4782609 | D89: =IFERROR(D24/C24-1,"NA") -> 10.921053 | E89: =IFERROR(E24/D24-1,"NA") -> -0.97350993 | F89: =IFERROR(F24/E24-1,"NA") -> -0.11111111 | G89: =IFERROR(G24/F24-1,"NA") -> 2.3125 | H89: =IFERROR(H24/G24-1,"NA") -> 13.330189 | I89: =IFERROR(I24/H24-1,"NA") -> -0.94865043 | ... BA89: =IFERROR(BA24/AZ24-1,"NA") -> -0.72225502
A90: Net income | B90: =IFERROR(B33/A33-1,"NA") -> NA | C90: =IFERROR(C33/B33-1,"NA") -> 1.7916667 | D90: =IFERROR(D33/C33-1,"NA") -> 12.328358 | E90: =IFERROR(E33/D33-1,"NA") -> -0.97760358 | F90: =IFERROR(F33/E33-1,"NA") -> -0.25 | G90: =IFERROR(G33/F33-1,"NA") -> 3.4666667 | H90: =IFERROR(H33/G33-1,"NA") -> 14.149254 | I90: =IFERROR(I33/H33-1,"NA") -> -0.94778325 | ... BA90: =IFERROR(BA33/AZ33-1,"NA") -> -0.72820747
A91: EPS | B91: =IFERROR(B35/A35-1,"NA") -> NA | C91: =IFERROR(C35/B35-1,"NA") -> 1.8546366 | D91: =IFERROR(D35/C35-1,"NA") -> 12.635936 | E91: =IFERROR(E35/D35-1,"NA") -> -0.97760358 | F91: =IFERROR(F35/E35-1,"NA") -> -0.24418605 | G91: =IFERROR(G35/F35-1,"NA") -> 3.4323077 | H91: =IFERROR(H35/G35-1,"NA") -> 14.149254 | I91: =IFERROR(I35/H35-1,"NA") -> -0.94778325 | ... BA91: =IFERROR(BA35/AZ35-1,"NA") -> -0.72820747
A93: Margin Analysis
A94: Product gross margin | B94: =+(B7-B13)/B7 -> 0.89298893 | C94: =+(C7-C13)/C7 -> 0.84848485 | D94: =+(D7-D13)/D7 -> 0.93464052 | E94: =+(E7-E13)/E7 -> 0.89152542 | F94: =+(F7-F13)/F7 -> 0.9023569 | G94: =+(G7-G13)/G7 -> 0.87625418 | H94: =+(H7-H13)/H7 -> 0.9379015 | I94: =+(I7-I13)/I7 -> 0.9201278 | ... AQ94: =+(AQ7-AQ13)/AQ7 -> 0.97688485 | AR94: =+AN94 -> 0.97700561 | AS94: =+AO94 -> 0.97037251 | AT94: =+AP94 -> 0.96131728 | AU94: =+AQ94 -> 0.97688485 | AV94: =+AR94 -> 0.97700561 | AW94: =+AS94 -> 0.97037251 | AX94: =+AT94 -> 0.96131728 | AY94: =+AU94 -> 0.97688485 | ... BA94: =+AW94 -> 0.97037251 | BD94: =+(BD7-BD13)/BD7 -> 0.89837083 | BE94: =+(BE7-BE13)/BE7 -> 0.9127907 | BF94: =+(BF7-BF13)/BF7 -> 0.94950739 | BG94: =+(BG7-BG13)/BG7 -> 0.95255699 | BH94: =+(BH7-BH13)/BH7 -> 0.9559633 | BI94: =+(BI7-BI13)/BI7 -> 0.95962551 | BJ94: =+(BJ7-BJ13)/BJ7 -> 0.96724412 | BK94: =+(BK7-BK13)/BK7 -> 0.97017226 | ... BP94: =+(BP7-BP13)/BP7 -> 0.97313588
A95: Service and other gross margin | B95: =+(B8-B14)/B8 -> 0.7081448 | C95: =+(C8-C14)/C8 -> 0.77086495 | D95: =+(D8-D14)/D8 -> 0.90298103 | E95: =+(E8-E14)/E8 -> 0.7124183 | F95: =+(F8-F14)/F8 -> 0.69022869 | G95: =+(G8-G14)/G8 -> 0.77126918 | H95: =+(H8-H14)/H8 -> 0.9021215 | I95: =+(I8-I14)/I8 -> 0.71077505 | ... AQ95: =+(AQ8-AQ14)/AQ8 -> 0.77093658 | AR95: =+AN95 -> 0.85124513 | AS95: =+AO95 -> 0.77726871 | AT95: =+AP95 -> 0.79212119 | AU95: =+AQ95 -> 0.77093658 | AV95: =+AR95 -> 0.85124513 | AW95: =+AS95 -> 0.77726871 | AX95: =+AT95 -> 0.79212119 | AY95: =+AU95 -> 0.77093658 | ... BA95: =+AW95 -> 0.77726871 | BD95: =+(BD8-BD14)/BD8 -> 0.82643172 | BE95: =+(BE8-BE14)/BE8 -> 0.82399369 | BF95: =+(BF8-BF14)/BF8 -> 0.80958873 | BG95: =+(BG8-BG14)/BG8 -> 0.80391397 | BH95: =+(BH8-BH14)/BH8 -> 0.79748511 | BI95: =+(BI8-BI14)/BI8 -> 0.81133266 | BJ95: =+(BJ8-BJ14)/BJ8 -> 0.80686487 | BK95: =+(BK8-BK14)/BK8 -> 0.78853264 | ... BP95: =+(BP8-BP14)/BP8 -> 0.80781996
A96: Gross margin | B96: =+B16/B$9 -> 0.77840112 | C96: =+C16/C$9 -> 0.79306609 | D96: =+D16/D$9 -> 0.90928819 | E96: =+E16/E$9 -> 0.78249337 | F96: =+F16/F$9 -> 0.77120823 | G96: =+G16/G$9 -> 0.80216535 | H96: =+H16/H$9 -> 0.90869736 | I96: =+I16/I$9 -> 0.78859857 | ... BA96: =+BA16/BA$9 -> 0.80061633 | BD96: =+BD16/BD$9 -> 0.84618662 | BE96: =+BE16/BE$9 -> 0.84759513 | BF96: =+BF16/BF$9 -> 0.8473029 | BG96: =+BG16/BG$9 -> 0.83947524 | BH96: =+BH16/BH$9 -> 0.83122802 | BI96: =+BI16/BI$9 -> 0.83764144 | BJ96: =+BJ16/BJ$9 -> 0.83341191 | BK96: =+BK16/BK$9 -> 0.81862472 | ... BP96: =+BP16/BP$9 -> 0.82581258
A97: Sales and marketing expenses | B97: =+B20/B$9 -> 0.31556802 | C97: =+C20/C$9 -> 0.36619718 | D97: =+D20/D$9 -> 0.17578125 | E97: =+E20/E$9 -> 0.32360743 | F97: =+F20/F$9 -> 0.33161954 | G97: =+G20/G$9 -> 0.3769685 | H97: =+H20/H$9 -> 0.17630854 | I97: =+I20/I$9 -> 0.28859857 | ... AQ97: =+AQ20/AQ$9 -> 0.26768437 | AR97: =+AN97+0.0125 -> 0.20427199 | AS97: =+AO97-0.013 -> 0.2777857 | AT97: =+AP97-0.003 -> 0.23535264 | AU97: =+AQ97-0.004 -> 0.26368437 | AV97: =+AR97-0.005 -> 0.19927199 | AW97: 0.279 | AX97: =+AT97-0.002 -> 0.23335264 | AY97: =+AU97-0.002 -> 0.26168437 | AZ97: =+AV97-0.0018 -> 0.19747199 | BA97: 0.274 | BD97: =+BD20/BD$9 -> 0.25820196 | BE97: =+BE20/BE$9 -> 0.25729187 | BF97: =+BF20/BF$9 -> 0.25394191 | BG97: =+BG20/BG$9 -> 0.26886792 | BH97: =+BH20/BH$9 -> 0.25159526 | BI97: =+BI20/BI$9 -> 0.25547597 | BJ97: =+BJ20/BJ$9 -> 0.25278956 | BK97: =+BK20/BK$9 -> 0.23197383 | ... BP97: =+BP20/BP$9 -> 0.2341086
A98: Research and development expenses | B98: =+B21/B$9 -> 0.26928471 | C98: =+C21/C$9 -> 0.19934995 | D98: =+D21/D$9 -> 0.08984375 | E98: =+E21/E$9 -> 0.27586207 | F98: =+F21/F$9 -> 0.26992288 | G98: =+G21/G$9 -> 0.21062992 | H98: =+H21/H$9 -> 0.087367178 | I98: =+I21/I$9 -> 0.27315914 | ... AQ98: =+AQ21/AQ$9 -> 0.14147495 | AR98: =+AN98+0.001 -> 0.073091824 | AS98: =+AO98-0.01 -> 0.15758027 | AT98: =+AP98-0.002 -> 0.16736937 | AU98: =+AQ98-0.002 -> 0.13947495 | AV98: =+AR98-0.002 -> 0.071091824 | AW98: =+AS98-0.002 -> 0.15558027 | AX98: =+AT98-0.002 -> 0.16536937 | AY98: =+AU98-0.002 -> 0.13747495 | AZ98: =+AV98-0.002 -> 0.069091824 | BA98: =+AW98-0.002 -> 0.15358027 | BD98: =+BD21/BD$9 -> 0.168513 | BE98: =+BE21/BE$9 -> 0.16920997 | BF98: =+BF21/BF$9 -> 0.17477178 | BG98: =+BG21/BG$9 -> 0.16170401 | BH98: =+BH21/BH$9 -> 0.16160958 | BI98: =+BI21/BI$9 -> 0.14502232 | BJ98: =+BJ21/BJ$9 -> 0.14348578 | BK98: =+BK21/BK$9 -> 0.13968541 | ... BP98: =+BP21/BP$9 -> 0.11958732
A99: General and administrative expenses | B99: =+B22/B$9 -> 0.12903226 | C99: =+C22/C$9 -> 0.10400867 | D99: =+D22/D$9 -> 0.053819444 | E99: =+E22/E$9 -> 0.13527851 | F99: =+F22/F$9 -> 0.1285347 | G99: =+G22/G$9 -> 0.11023622 | H99: =+H22/H$9 -> 0.047225502 | I99: =+I22/I$9 -> 0.13420428 | ... AQ99: =+AQ22/AQ$9 -> 0.063212212 | AR99: =+AN99+0.001 -> 0.040979365 | AS99: =+AO99-0.002 -> 0.07891882 | AT99: =+AP99-0.002 -> 0.075477477 | AU99: =+AQ99-0.002 -> 0.061212212 | AV99: =+AR99-0.002 -> 0.038979365 | AW99: =+AS99-0.002 -> 0.07691882 | AX99: =+AT99-0.002 -> 0.073477477 | AY99: =+AU99-0.002 -> 0.059212212 | AZ99: =+AV99-0.002 -> 0.036979365 | BA99: =+AW99-0.002 -> 0.07491882 | BD99: =+BD22/BD$9 -> 0.088197699 | BE99: =+BE22/BE$9 -> 0.085957118 | BF99: =+BF22/BF$9 -> 0.0793361 | BG99: =+BG22/BG$9 -> 0.072523585 | BH99: =+BH22/BH$9 -> 0.070582107 | BI99: =+BI22/BI$9 -> 0.07536593 | BJ99: =+BJ22/BJ$9 -> 0.083215464 | BK99: =+BK22/BK$9 -> 0.063961581 | ... BP99: =+BP22/BP$9 -> 0.056471487
A100: Total operating expenses | B100: =+B23/B$9 -> 0.71388499 | C100: =+C23/C$9 -> 0.6695558 | D100: =+D23/D$9 -> 0.31944444 | E100: =+E23/E$9 -> 0.73474801 | F100: =+F23/F$9 -> 0.73007712 | G100: =+G23/G$9 -> 0.69783465 | H100: =+H23/H$9 -> 0.31090122 | I100: =+I23/I$9 -> 0.695962 | ... BA100: =+BA23/BA$9 -> 0.50249909 | BD100: =+BD23/BD$9 -> 0.51491265 | BE100: =+BE23/BE$9 -> 0.51245895 | BF100: =+BF23/BF$9 -> 0.50804979 | BG100: =+BG23/BG$9 -> 0.50309552 | BH100: =+BH23/BH$9 -> 0.48378695 | BI100: =+BI23/BI$9 -> 0.47586422 | BJ100: =+BJ23/BJ$9 -> 0.47949081 | BK100: =+BK23/BK$9 -> 0.43562082 | ... BP100: =+BP23/BP$9 -> 0.41016741
A101: Operating margin | B101: =+B24/B$9 -> 0.064516129 | C101: =+C24/C$9 -> 0.12351029 | D101: =+D24/D$9 -> 0.58984375 | E101: =+E24/E$9 -> 0.047745358 | F101: =+F24/F$9 -> 0.041131105 | G101: =+G24/G$9 -> 0.10433071 | H101: =+H24/H$9 -> 0.59779614 | I101: =+I24/I$9 -> 0.09263658 | ... BA101: =+BA24/BA$9 -> 0.29811725 | BD101: =+BD24/BD$9 -> 0.33127397 | BE101: =+BE24/BE$9 -> 0.33513618 | BF101: =+BF24/BF$9 -> 0.33925311 | BG101: =+BG24/BG$9 -> 0.33637972 | BH101: =+BH24/BH$9 -> 0.34744107 | BI101: =+BI24/BI$9 -> 0.36177722 | BJ101: =+BJ24/BJ$9 -> 0.35392111 | BK101: =+BK24/BK$9 -> 0.3830039 | ... BP101: =+BP24/BP$9 -> 0.41564518
A102: Net income | B102: =+B33/B$9 -> 0.033660589 | C102: =+C33/C$9 -> 0.072589382 | D102: =+D33/D$9 -> 0.38758681 | E102: =+E33/E$9 -> 0.026525199 | F102: =+F33/F$9 -> 0.019280206 | G102: =+G33/G$9 -> 0.065944882 | H102: =+H33/H$9 -> 0.39944904 | I102: =+I33/I$9 -> 0.062945368 | ... BA102: =+BA33/BA$9 -> 0.2194957 | BD102: =+BD33/BD$9 -> 0.21389007 | BE102: =+BE33/BE$9 -> 0.22213637 | BF102: =+BF33/BF$9 -> 0.25078838 | BG102: =+BG33/BG$9 -> 0.26267689 | BH102: =+BH33/BH$9 -> 0.27021748 | BI102: =+BI33/BI$9 -> 0.27582269 | BJ102: =+BJ33/BJ$9 -> 0.2644193 | BK102: =+BK33/BK$9 -> 0.28396437 | ... BP102: =+BP33/BP$9 -> 0.31191459
A103: Source: Company data, FactSet, Wells Fargo Securities, LLC estimates
A105: GAAP Inputs
A106: Revenue
A107: Product Revenue | B107: =+B7 -> 271 | C107: =+C7 -> 264 | D107: =+D7 -> 459 | E107: =+E7 -> 295 | F107: =+F7 -> 297 | G107: =+G7 -> 299 | H107: =+H7 -> 467 | I107: =+I7 -> 313 | ... Y107: =+Y7 -> 314 | Z107: 397 | AA107: =+AA7 -> 658.54466 | AB107: =+AB7 -> 674.48677 | AC107: =+AC7 -> 362.89554 | AD107: =+AD7 -> 543.97996 | AE107: =+AE7 -> 701.47606 | AF107: =+AF7 -> 721.72772 | AG107: =+AG7 -> 413.15076 | AH107: =+AH7 -> 536.87304 | ... BA107: =+BA7 -> 644.78226 | BD107: =+SUM(B107:E107) -> 1289 | BE107: =+SUM(F107:I107) -> 1376 | BF107: =+SUM(J107:M107) -> 1624 | BG107: =SUM(N107:Q107) -> 1623 | BH107: =+SUM(R107:U107) -> 1635 | BI107: =SUM(V107:Y107) -> 1709 | BJ107: =+SUM(Z107:AC107) -> 2092.927 | BK107: =+SUM(AD107:AG107) -> 2380.3345 | BL107: =+SUM(AH107:AK107) -> 2484.0248 | BM107: =+SUM(AL107:AO107) -> 2431.0061 | BN107: =+SUM(AP107:AS107) -> 2566.9111 | BO107: =+SUM(AT107:AW107) -> 2730.1957 | BP107: =+SUM(AX107:BA107) -> 2892.0071
A108: Service and Other Revenue | B108: =+B8 -> 442 | C108: =+C8 -> 659 | D108: =+D8 -> 1845 | E108: =+E8 -> 459 | F108: =+F8 -> 481 | G108: =+G8 -> 717 | H108: =+H8 -> 2074 | I108: =+I8 -> 529 | ... Y108: =+Y8 -> 2247 | Z108: 1610 | AA108: =+AA8 -> 2014.4553 | AB108: =+AB8 -> 4957.5132 | AC108: =+AC8 -> 2051.1045 | AD108: =+AD8 -> 2053.02 | AE108: =+AE8 -> 2339.5239 | AF108: =+AF8 -> 5296.2723 | AG108: =+AG8 -> 2298.8492 | AH108: =+AH8 -> 2441.127 | ... BA108: =+BA8 -> 4688.0901 | BD108: =+SUM(B108:E108) -> 3405 | BE108: =+SUM(F108:I108) -> 3801 | BF108: =+SUM(J108:M108) -> 4401 | BG108: =SUM(N108:Q108) -> 5161 | BH108: =+SUM(R108:U108) -> 6044 | BI108: =SUM(V108:Y108) -> 7924 | BJ108: =+SUM(Z108:AC108) -> 10633.073 | BK108: =+SUM(AD108:AG108) -> 11987.666 | BL108: =+SUM(AH108:AK108) -> 13800.975 | BM108: =+SUM(AL108:AO108) -> 16399.994 | BN108: =+SUM(AP108:AS108) -> 18710.286 | BO108: =+SUM(AT108:AW108) -> 21037.141 | BP108: =+SUM(AX108:BA108) -> 23679.705
A109: Total Revenue | B109: =+B9 -> 713 | C109: =+C9 -> 923 | D109: =+D9 -> 2304 | E109: =+E9 -> 754 | F109: =+F9 -> 778 | G109: =+G9 -> 1016 | H109: =+H9 -> 2541 | I109: =+I9 -> 842 | ... Y109: =+Y9 -> 2561 | Z109: 2007 | AA109: =+AA9 -> 2673 | AB109: =+AB9 -> 5632 | AC109: =+AC9 -> 2414 | AD109: =+AD9 -> 2597 | AE109: =+AE9 -> 3041 | AF109: =+AF9 -> 6018 | AG109: =+AG9 -> 2712 | AH109: =+AH9 -> 2978 | ... BA109: =+BA9 -> 5332.8724 | BD109: =+SUM(B109:E109) -> 4694 | BE109: =+SUM(F109:I109) -> 5177 | BF109: =+SUM(J109:M109) -> 6025 | BG109: =SUM(N109:Q109) -> 6784 | BH109: =+SUM(R109:U109) -> 7679 | BI109: =SUM(V109:Y109) -> 9633 | BJ109: =+SUM(Z109:AC109) -> 12726 | BK109: =+SUM(AD109:AG109) -> 14368 | BL109: =+SUM(AH109:AK109) -> 16285 | BM109: =+SUM(AL109:AO109) -> 18831 | BN109: =+SUM(AP109:AS109) -> 21277.197 | BO109: =+SUM(AT109:AW109) -> 23767.337 | BP109: =+SUM(AX109:BA109) -> 26571.712
A111: Cost of revenue
...

Sheet Revenue Build
A1: =+'Income Statement'!A1 -> Intuit, Inc.
A2: Revenue Build
B3: =+'Income Statement'!B3:E3 -> Fiscal 2016 | F3: =+'Income Statement'!F3:I3 -> Fiscal 2017 | J3: =+'Income Statement'!J3:M3 -> Fiscal 2018 | N3: =+'Income Statement'!N3:Q3 -> Fiscal 2019 | R3: =+'Income Statement'!R3:U3 -> Fiscal 2020 | V3: =+'Income Statement'!V3:Y3 -> Fiscal 2021 | Z3: =+'Income Statement'!Z3:AC3 -> Fiscal 2022 | AD3: =+'Income Statement'!AD3:AG3 -> Fiscal 2023 | AH3: =+'Income Statement'!AH3:AK3 -> Fiscal 2024 | AL3: =+'Income Statement'!AL3:AO3 -> Fiscal 2025 | AP3: =+'Income Statement'!AP3:AS3 -> Fiscal 2026 | AT3: =+'Income Statement'!AT3:AW3 -> Fiscal 2027 | AX3: =+'Income Statement'!AX3:BA3 -> Fiscal 2028
A4: ($ in millions, unless otherwise stated) | B4: =+'Income Statement'!B4 -> 42308 | C4: =+'Income Statement'!C4 -> 42400 | D4: =+'Income Statement'!D4 -> 42490 | E4: =+'Income Statement'!E4 -> 42582 | F4: =+'Income Statement'!F4 -> 42674 | G4: =+'Income Statement'!G4 -> 42766 | H4: =+'Income Statement'!H4 -> 42855 | I4: =+'Income Statement'!I4 -> 42947 | ... BA4: =+'Income Statement'!BA4 -> Jul-28E | BC4: =+'Income Statement'!BC4 -> FY15 | BD4: =+'Income Statement'!BD4 -> FY16 | BE4: =+'Income Statement'!BE4 -> FY17 | BF4: =+'Income Statement'!BF4 -> FY18 | BG4: =+'Income Statement'!BG4 -> FY19 | BH4: =+'Income Statement'!BH4 -> FY20 | BI4: =+'Income Statement'!BI4 -> FY21 | BJ4: =+'Income Statement'!BJ4 -> FY22 | ... BP4: =+'Income Statement'!BP4 -> FY28E
X5: 210.8 | Y5: 217.8
A6: Total Revenue | B6: =B13+B18 -> 713 | C6: =C13+C18 -> 923 | D6: =D13+D18 -> 2304 | E6: =E13+E18 -> 754 | F6: =F13+F18 -> 778 | G6: =G13+G18 -> 1016 | H6: =H13+H18 -> 2541 | I6: =I13+I18 -> 842 | ... BA6: =BA13+BA18 -> 5332.8724 | BD6: =SUM(B6:E6) -> 4694 | BE6: =SUM(F6:I6) -> 5177 | BF6: =SUM(J6:M6) -> 6025 | BG6: =SUM(N6:Q6) -> 6784 | BH6: =SUM(R6:U6) -> 7679 | BI6: =SUM(V6:Y6) -> 9633 | BJ6: =SUM(Z6:AC6) -> 12726 | BK6: =SUM(AD6:AG6) -> 14368 | BL6: =SUM(AH6:AK6) -> 16285 | BM6: =+BM24+BM178+BM207+BM202 -> 18831 | BN6: =SUM(AP6:AS6) -> 21277.197 | BO6: =SUM(AT6:AW6) -> 23767.337 | BP6: =SUM(AX6:BA6) -> 26571.712
A7: Y/Y Growth | B7: =IF(ISERROR(B6/#REF!-1),"NA",B6/#REF!-1) -> NA | C7: =IF(ISERROR(C6/#REF!-1),"NA",C6/#REF!-1) -> NA | D7: =IF(ISERROR(D6/#REF!-1),"NA",D6/#REF!-1) -> NA | E7: =IF(ISERROR(E6/A6-1),"NA",E6/A6-1) -> NA | F7: =IF(ISERROR(F6/B6-1),"NA",F6/B6-1) -> 0.091164095 | G7: =IF(ISERROR(G6/C6-1),"NA",G6/C6-1) -> 0.1007584 | H7: =IF(ISERROR(H6/D6-1),"NA",H6/D6-1) -> 0.10286458 | I7: =IF(ISERROR(I6/E6-1),"NA",I6/E6-1) -> 0.11671088 | J7: =IF(ISERROR(J6/F6-1),"NA",J6/F6-1) -> 0.16966581 | K7: =IF(ISERROR(K6/G6-1),"NA",K6/G6-1) -> 0.31791339 | L7: =IF(ISERROR(L6/H6-1),"NA",L6/H6-1) -> 0.14600551 | ... BA7: =IF(ISERROR(BA6/AW6-1),"NA",BA6/AW6-1) -> 0.1237807 | BD7: =IF(ISERROR(BD6/BC6-1),"NA",BD6/BC6-1) -> NA | BE7: =IF(ISERROR(BE6/BD6-1),"NA",BE6/BD6-1) -> 0.10289732 | BF7: =IF(ISERROR(BF6/BE6-1),"NA",BF6/BE6-1) -> 0.16380143 | BG7: =IF(ISERROR(BG6/BF6-1),"NA",BG6/BF6-1) -> 0.1259751 | BH7: =IF(ISERROR(BH6/BG6-1),"NA",BH6/BG6-1) -> 0.13192807 | BI7: =IF(ISERROR(BI6/BH6-1),"NA",BI6/BH6-1) -> 0.25446022 | BJ7: =IF(ISERROR(BJ6/BI6-1),"NA",BJ6/BI6-1) -> 0.32108377 | BK7: =IF(ISERROR(BK6/BJ6-1),"NA",BK6/BJ6-1) -> 0.12902719 | ... BP7: =IF(ISERROR(BP6/BO6-1),"NA",BP6/BO6-1) -> 0.11799283
A8: Y/Y Growth ($) | V8: =V6-R6 -> 158 | W8: =W6-S6 -> -120 | X8: =X6-T6 -> 1171 | Y8: =Y6-U6 -> 745 | Z8: =Z6-V6 -> 684 | AA8: =AA6-W6 -> 1097 | AB8: =AB6-X6 -> 1459 | AC8: =AC6-Y6 -> -147 | ... BA8: =BA6-AW6 -> 587.39813 | BJ8: =BJ6-BI6 -> 3093 | BK8: =BK6-BJ6 -> 1642 | BL8: =BL6-BK6 -> 1917 | BM8: =BM6-BL6 -> 2546 | BN8: =BN6-BM6 -> 2446.1975 | BO8: =BO6-BN6 -> 2490.1396 | BP8: =BP6-BO6 -> 2804.3753
A9: Q/Q Growth | B9: =IF(ISERROR(B6/A6-1),"NA",B6/A6-1) -> NA | C9: =IF(ISERROR(C6/B6-1),"NA",C6/B6-1) -> 0.29453015 | D9: =IF(ISERROR(D6/C6-1),"NA",D6/C6-1) -> 1.496208 | E9: =IF(ISERROR(E6/D6-1),"NA",E6/D6-1) -> -0.67274306 | F9: =IF(ISERROR(F6/E6-1),"NA",F6/E6-1) -> 0.031830239 | G9: =IF(ISERROR(G6/F6-1),"NA",G6/F6-1) -> 0.3059126 | H9: =IF(ISERROR(H6/G6-1),"NA",H6/G6-1) -> 1.5009843 | I9: =IF(ISERROR(I6/H6-1),"NA",I6/H6-1) -> -0.6686344 | ... BA9: =IF(ISERROR(BA6/AZ6-1),"NA",BA6/AZ6-1) -> -0.4790776 | BD9: NA | BE9: NA | BF9: NA | BG9: NA | BH9: NA | BI9: NA | BJ9: NA | BK9: NA | BL9: NA | BM9: NA | BN9: NA | BO9: NA | BP9: NA
A10: Q/Q Growth ($) | V10: =V6-U6 -> -493 | W10: =W6-V6 -> 253 | X10: =X6-W6 -> 2597 | Y10: =Y6-X6 -> -1612 | Z10: =Z6-Y6 -> -554 | AA10: =AA6-Z6 -> 666 | AB10: =AB6-AA6 -> 2959 | AC10: =AC6-AB6 -> -3218 | ... BA10: =BA6-AZ6 -> -4904.492 | BI10: N/A | BJ10: N/A | BK10: N/A | BL10: N/A | BM10: N/A | BN10: N/A | BO10: N/A | BP10: N/A
C11: 45761
A12: Revenue by Type
A13: Product Revenue | B13: 271 | C13: 264 | D13: 459 | E13: 295 | F13: 297 | G13: 299 | H13: 467 | I13: 313 | J13: =+J154+J185+J212 -> 370 | K13: =+K154+K185+K212 -> 529 | L13: =+L154+L185+L212 -> 479 | M13: =+M154+M185+M212 -> 246 | N13: =+N154+N185+N212 -> 347 | O13: =+O154+O185+O212 -> 533 | P13: =+P154+P185+P212 -> 498 | Q13: =+Q154+Q185+Q212 -> 245 | ... W13: =+W154+W185+W212 -> 495 | X13: =+X185+X212+X154 -> 533 | Y13: =+Y185+Y212+Y154 -> 314 | Z13: =+Z185+Z212+Z154 -> 410.56522 | AA13: =+AA185+AA212+AA154 -> 658.54466 | AB13: =+AB185+AB212+AB154 -> 674.48677 | AC13: =+AC185+AC212+AC154 -> 362.89554 | AD13: =+AD185+AD212+AD154 -> 543.97996 | AE13: =+AE185+AE212+AE154 -> 701.47606 | ... BA13: =+BA185+BA212+BA154 -> 644.78226 | BD13: =SUM(B13:E13) -> 1289 | BE13: =SUM(F13:I13) -> 1376 | BF13: =SUM(J13:M13) -> 1624 | BG13: =SUM(N13:Q13) -> 1623 | BH13: =SUM(R13:U13) -> 1635 | BI13: =SUM(V13:Y13) -> 1709 | BJ13: =SUM(Z13:AC13) -> 2106.4922 | BK13: =SUM(AD13:AG13) -> 2380.3345 | BL13: =SUM(AH13:AK13) -> 2484.0248 | BM13: =SUM(AL13:AO13) -> 2431.0061 | BN13: =SUM(AP13:AS13) -> 2566.9111 | BO13: =SUM(AT13:AW13) -> 2730.1957 | BP13: =SUM(AX13:BA13) -> 2892.0071
A14: Y/Y Growth | B14: =IF(ISERROR(B13/#REF!-1),"NA",B13/#REF!-1) -> NA | C14: =IF(ISERROR(C13/#REF!-1),"NA",C13/#REF!-1) -> NA | D14: =IF(ISERROR(D13/#REF!-1),"NA",D13/#REF!-1) -> NA | E14: =IF(ISERROR(E13/A13-1),"NA",E13/A13-1) -> NA | F14: =IF(ISERROR(F13/B13-1),"NA",F13/B13-1) -> 0.095940959 | G14: =IF(ISERROR(G13/C13-1),"NA",G13/C13-1) -> 0.13257576 | H14: =IF(ISERROR(H13/D13-1),"NA",H13/D13-1) -> 0.017429194 | I14: =IF(ISERROR(I13/E13-1),"NA",I13/E13-1) -> 0.061016949 | J14: =IF(ISERROR(J13/F13-1),"NA",J13/F13-1) -> 0.24579125 | K14: =IF(ISERROR(K13/G13-1),"NA",K13/G13-1) -> 0.76923077 | L14: =IF(ISERROR(L13/H13-1),"NA",L13/H13-1) -> 0.025695931 | ... BA14: =IF(ISERROR(BA13/AW13-1),"NA",BA13/AW13-1) -> 0.066007674 | BD14: =IF(ISERROR(BD13/BB13-1),"NA",BD13/BB13-1) -> NA | BE14: =IF(ISERROR(BE13/BD13-1),"NA",BE13/BD13-1) -> 0.067494182 | BF14: =IF(ISERROR(BF13/BE13-1),"NA",BF13/BE13-1) -> 0.18023256 | BG14: =IF(ISERROR(BG13/BF13-1),"NA",BG13/BF13-1) -> -0.00061576355 | BH14: =IF(ISERROR(BH13/BG13-1),"NA",BH13/BG13-1) -> 0.0073937153 | BI14: =IF(ISERROR(BI13/BH13-1),"NA",BI13/BH13-1) -> 0.045259939 | BJ14: =IF(ISERROR(BJ13/BI13-1),"NA",BJ13/BI13-1) -> 0.23258759 | BK14: =IF(ISERROR(BK13/BJ13-1),"NA",BK13/BJ13-1) -> 0.1299992 | BL14: =IF(ISERROR(BL13/BK13-1),"NA",BL13/BK13-1) -> 0.043561233 | ... BP14: =IF(ISERROR(BP13/BO13-1),"NA",BP13/BO13-1) -> 0.059267336
A15: Q/Q Growth | B15: =IF(ISERROR(B13/A13-1),"NA",B13/A13-1) -> NA | C15: =IF(ISERROR(C13/B13-1),"NA",C13/B13-1) -> -0.025830258 | D15: =IF(ISERROR(D13/C13-1),"NA",D13/C13-1) -> 0.73863636 | E15: =IF(ISERROR(E13/D13-1),"NA",E13/D13-1) -> -0.35729847 | F15: =IF(ISERROR(F13/E13-1),"NA",F13/E13-1) -> 0.006779661 | G15: =IF(ISERROR(G13/F13-1),"NA",G13/F13-1) -> 0.0067340067 | H15: =IF(ISERROR(H13/G13-1),"NA",H13/G13-1) -> 0.56187291 | I15: =IF(ISERROR(I13/H13-1),"NA",I13/H13-1) -> -0.32976445 | ... BA15: =IF(ISERROR(BA13/AZ13-1),"NA",BA13/AZ13-1) -> -0.30698564 | BD15: NA | BE15: NA | BF15: NA | BG15: NA | BH15: NA | BI15: NA | BJ15: NA | BK15: NA | BL15: NA | BM15: NA | BN15: NA | BO15: NA | BP15: NA
A16: % of total revenue | B16: =B13/B6 -> 0.38008415 | C16: =C13/C6 -> 0.28602384 | D16: =D13/D6 -> 0.19921875 | E16: =E13/E6 -> 0.39124668 | F16: =F13/F6 -> 0.38174807 | G16: =G13/G6 -> 0.29429134 | H16: =H13/H6 -> 0.18378591 | I16: =I13/I6 -> 0.37173397 | ... BA16: =BA13/BA6 -> 0.12090712 | BD16: =+BD13/BD$6 -> 0.27460588 | BE16: =+BE13/BE$6 -> 0.265791 | BF16: =+BF13/BF$6 -> 0.26954357 | BG16: =+BG13/BG$6 -> 0.23923939 | BH16: =+BH13/BH$6 -> 0.21291835 | BI16: =+BI13/BI$6 -> 0.17741098 | BJ16: =+BJ13/BJ$6 -> 0.16552665 | BK16: =+BK13/BK$6 -> 0.16566916 | ... BP16: =+BP13/BP$6 -> 0.10883782
BS17: total online payments 20%
A18: Service and Other Revenue | B18: 442 | C18: 659 | D18: 1845 | E18: 459 | F18: 481 | G18: 717 | H18: 2074 | I18: 529 | J18: =+J160+J191+J218 -> 540 | K18: =+K160+K191+K218 -> 810 | L18: =+L160+L191+L218 -> 2433 | M18: =+M160+M191+M218 -> 618 | N18: =+N160+N191+N218 -> 669 | O18: =+O160+O191+O218 -> 969 | P18: =+P160+P191+P218 -> 2774 | Q18: =+Q160+Q191+Q218 -> 749 | ... V18: =+V160+V191+V218 -> 956 | W18: =+W160+W191+W218+W202 -> 1081 | X18: =+X160+X191+X218+X202 -> 3640 | Y18: =+Y160+Y191+Y218+Y202 -> 2247 | Z18: =+Z160+Z191+Z218+Z202 -> 1596.4348 | AA18: =+AA160+AA191+AA218+AA202 -> 2014.4553 | AB18: =+AB160+AB191+AB218+AB202 -> 4957.5132 | AC18: =+AC160+AC191+AC218+AC202 -> 2051.1045 | AD18: =+AD160+AD191+AD218+AD202 -> 2053.02 | ... AO18: =+AO160+AO191+AO218+AO202 -> 3290.961 | AP18: =+AP160+AP191+AP218+AP197 -> 3497.23 | AQ18: =+AQ160+AQ191+AQ218+AQ197 -> 3872.29 | AR18: =+AR160+AR191+AR218+AR197 -> 7658.6803 | AS18: =+AS160+AS191+AS218+AS197 -> 3682.0861 | AT18: =+AT160+AT191+AT218+AT197 -> 4002.8389 | AU18: =+AU160+AU191+AU218+AU197 -> 4469.0289 | AV18: =+AV160+AV191+AV218+AV197 -> 8424.6564 | AW18: =+AW160+AW191+AW218+AW197 -> 4140.6172 | ... BA18: =+BA160+BA191+BA218+BA197 -> 4688.0901 | BD18: =SUM(B18:E18) -> 3405 | BE18: =SUM(F18:I18) -> 3801 | BF18: =SUM(J18:M18) -> 4401 | BG18: =SUM(N18:Q18) -> 5161 | BH18: =SUM(R18:U18) -> 6044 | BI18: =SUM(V18:Y18) -> 7924 | BJ18: =SUM(Z18:AC18) -> 10619.508 | BK18: =SUM(AD18:AG18) -> 11987.666 | BL18: =SUM(AH18:AK18) -> 13800.975 | BM18: =SUM(AL18:AO18) -> 16399.994 | BN18: =SUM(AP18:AS18) -> 18710.286 | BO18: =SUM(AT18:AW18) -> 21037.141 | BP18: =SUM(AX18:BA18) -> 23679.705
A19: Y/Y Growth | B19: =IF(ISERROR(B18/#REF!-1),"NA",B18/#REF!-1) -> NA | C19: =IF(ISERROR(C18/#REF!-1),"NA",C18/#REF!-1) -> NA | D19: =IF(ISERROR(D18/#REF!-1),"NA",D18/#REF!-1) -> NA | E19: =IF(ISERROR(E18/A18-1),"NA",E18/A18-1) -> NA | F19: =IF(ISERROR(F18/B18-1),"NA",F18/B18-1) -> 0.088235294 | G19: =IF(ISERROR(G18/C18-1),"NA",G18/C18-1) -> 0.08801214 | H19: =IF(ISERROR(H18/D18-1),"NA",H18/D18-1) -> 0.12411924 | I19: =IF(ISERROR(I18/E18-1),"NA",I18/E18-1) -> 0.15250545 | J19: =IF(ISERROR(J18/F18-1),"NA",J18/F18-1) -> 0.12266112 | K19: =IF(ISERROR(K18/G18-1),"NA",K18/G18-1) -> 0.12970711 | L19: =IF(ISERROR(L18/H18-1),"NA",L18/H18-1) -> 0.17309547 | ... BA19: =IF(ISERROR(BA18/AW18-1),"NA",BA18/AW18-1) -> 0.13222013 | BD19: =IF(ISERROR(BD18/BB18-1),"NA",BD18/BB18-1) -> NA | BE19: =IF(ISERROR(BE18/BD18-1),"NA",BE18/BD18-1) -> 0.11629956 | BF19: =IF(ISERROR(BF18/BE18-1),"NA",BF18/BE18-1) -> 0.1578532 | BG19: =IF(ISERROR(BG18/BF18-1),"NA",BG18/BF18-1) -> 0.17268803 | BH19: =IF(ISERROR(BH18/BG18-1),"NA",BH18/BG18-1) -> 0.17109087 | BI19: =IF(ISERROR(BI18/BH18-1),"NA",BI18/BH18-1) -> 0.31105228 | BJ19: =IF(ISERROR(BJ18/BI18-1),"NA",BJ18/BI18-1) -> 0.34017009 | BK19: =IF(ISERROR(BK18/BJ18-1),"NA",BK18/BJ18-1) -> 0.12883438 | BL19: =IF(ISERROR(BL18/BK18-1),"NA",BL18/BK18-1) -> 0.15126462 | ... BP19: =IF(ISERROR(BP18/BO18-1),"NA",BP18/BO18-1) -> 0.12561421
A20: Q/Q Growth | B20: =IF(ISERROR(B18/A18-1),"NA",B18/A18-1) -> NA | C20: =IF(ISERROR(C18/B18-1),"NA",C18/B18-1) -> 0.49095023 | D20: =IF(ISERROR(D18/C18-1),"NA",D18/C18-1) -> 1.7996965 | E20: =IF(ISERROR(E18/D18-1),"NA",E18/D18-1) -> -0.75121951 | F20: =IF(ISERROR(F18/E18-1),"NA",F18/E18-1) -> 0.047930283 | G20: =IF(ISERROR(G18/F18-1),"NA",G18/F18-1) -> 0.49064449 | H20: =IF(ISERROR(H18/G18-1),"NA",H18/G18-1) -> 1.8926081 | I20: =IF(ISERROR(I18/H18-1),"NA",I18/H18-1) -> -0.74493732 | ... BA20: =IF(ISERROR(BA18/AZ18-1),"NA",BA18/AZ18-1) -> -0.49628137 | BD20: NA | BE20: NA | BF20: NA | BG20: NA | BH20: NA | BI20: NA | BJ20: NA | BK20: NA | BL20: NA | BM20: NA | BN20: NA | BO20: NA | BP20: NA
A21: % of total revenue | B21: =+B18/B6 -> 0.61991585 | C21: =+C18/C6 -> 0.71397616 | D21: =+D18/D6 -> 0.80078125 | E21: =+E18/E6 -> 0.60875332 | F21: =+F18/F6 -> 0.61825193 | G21: =+G18/G6 -> 0.70570866 | H21: =+H18/H6 -> 0.81621409 | I21: =+I18/I6 -> 0.62826603 | ... BA21: =+BA18/BA6 -> 0.87909288 | BD21: =+BD18/BD$6 -> 0.72539412 | BE21: =+BE18/BE$6 -> 0.734209 | BF21: =+BF18/BF$6 -> 0.73045643 | BG21: =+BG18/BG$6 -> 0.76076061 | BH21: =+BH18/BH$6 -> 0.78708165 | BI21: =+BI18/BI$6 -> 0.82258902 | BJ21: =+BJ18/BJ$6 -> 0.83447335 | BK21: =+BK18/BK$6 -> 0.83433084 | ... BP21: =+BP18/BP$6 -> 0.89116218
AH22: 1QFY-2024 | AI22: 2QFY-2024 | AJ22: 3QFY-2024 | AK22: 4QFY-2024 | AL22: 1QFY-2025 | AM22: 2QFY-2025 | AN22: 3QFY-2025 | AO22: 4QFY-2025 | AP22: 1QFY-2026 | AQ22: 2QFY-2025 | AR22: 3QFY-2026 | AS22: 4QFY-2026 | AT22: 1QFY-2027 | AU22: 2QFY-2027 | AV22: 3QFY-2027 | AW22: 4QFY-2027 | AX22: 1QFY-2028 | AY22: 2QFY-2028 | AZ22: 3QFY-2028 | BA22: 4QFY-2028
A23: Segment Build(s)
A24: Global Business Solutions (QuickBooks) | B24: 530 | C24: 547 | D24: 557 | E24: 587 | F24: =+F154+F160 -> 593 | G24: =+G154+G160 -> 618 | H24: =+H154+H160 -> 655 | I24: =+I154+I160 -> 708 | J24: =+J154+J160 -> 819 | K24: =+K154+K160 -> 713 | L24: =+L154+L160 -> 747 | M24: =+M154+M160 -> 782 | ... V24: =+V154+V160 -> 1181 | W24: =+W32+W135 -> 1078 | X24: =+X32+X135 -> 1177 | Y24: =+Y154+Y160 -> 1252 | Z24: =+Z154+Z160 -> 1443 | AA24: 1581 | AB24: 1667 | AC24: 1769 | AD24: 1988 | AE24: 1897 | AF24: 2021 | AG24: 2132 | AH24: 2344 | AI24: 2245 | AJ24: =+AJ32+AJ135 -> 2387 | AK24: =+AK32+AK135 -> 2557 | AL24: =+AL32+AL135 -> 2544 | AM24: =+AM32+AM135 -> 2671 | AN24: =+AN32+AN135 -> 2849 | AO24: =+AO32+AO135 -> 3013 | AP24: =+AP32+AP135 -> 2991 | AQ24: =+AQ32+AQ135 -> 3164 | ... BA24: =+BA32+BA135 -> 4374.0334 | BD24: =SUM(B24:E24) -> 2221 | BE24: =SUM(F24:I24) -> 2574 | BF24: =SUM(J24:M24) -> 3061 | BG24: =SUM(N24:Q24) -> 3533 | BH24: =SUM(R24:U24) -> 4050 | BI24: =SUM(V24:Y24) -> 4688 | BJ24: =SUM(Z24:AC24) -> 6460 | BK24: =SUM(AD24:AG24) -> 8038 | BL24: =SUM(AH24:AK24) -> 9533 | BM24: =SUM(AL24:AO24) -> 11077 | BN24: =SUM(AP24:AS24) -> 12778.318 | BO24: =SUM(AT24:AW24) -> 14720.041 | BP24: =SUM(AX24:BA24) -> 16947.932
A25: Y/Y Growth (%) | B25: =IF(ISERROR(B24/#REF!-1),"NA",B24/#REF!-1) -> NA | C25: =IF(ISERROR(C24/#REF!-1),"NA",C24/#REF!-1) -> NA | D25: =IF(ISERROR(D24/#REF!-1),"NA",D24/#REF!-1) -> NA | E25: =IF(ISERROR(E24/A24-1),"NA",E24/A24-1) -> NA | F25: =IF(ISERROR(F24/B24-1),"NA",F24/B24-1) -> 0.11886792 | G25: =IF(ISERROR(G24/C24-1),"NA",G24/C24-1) -> 0.1297989 | H25: =IF(ISERROR(H24/D24-1),"NA",H24/D24-1) -> 0.17594255 | I25: =IF(ISERROR(I24/E24-1),"NA",I24/E24-1) -> 0.20613288 | J25: =IF(ISERROR(J24/F24-1),"NA",J24/F24-1) -> 0.38111298 | K25: =IF(ISERROR(K24/G24-1),"NA",K24/G24-1) -> 0.15372168 | L25: =IF(ISERROR(L24/H24-1),"NA",L24/H24-1) -> 0.14045802 | ... BA25: =IF(ISERROR(BA24/AW24-1),"NA",BA24/AW24-1) -> 0.14108959 | BD25: =IF(ISERROR(BD24/BB24-1),"NA",BD24/BB24-1) -> NA | BE25: =IF(ISERROR(BE24/BD24-1),"NA",BE24/BD24-1) -> 0.15893742 | BF25: =IF(ISERROR(BF24/BE24-1),"NA",BF24/BE24-1) -> 0.18919969 | BG25: =IF(ISERROR(BG24/BF24-1),"NA",BG24/BF24-1) -> 0.15419797 | BH25: =IF(ISERROR(BH24/BG24-1),"NA",BH24/BG24-1) -> 0.14633456 | BI25: =IF(ISERROR(BI24/BH24-1),"NA",BI24/BH24-1) -> 0.15753086 | BJ25: =IF(ISERROR(BJ24/BI24-1),"NA",BJ24/BI24-1) -> 0.37798635 | BK25: =IF(ISERROR(BK24/BJ24-1),"NA",BK24/BJ24-1) -> 0.24427245 | BL25: =IF(ISERROR(BL24/BK24-1),"NA",BL24/BK24-1) -> 0.18599154 | ... BP25: =IF(ISERROR(BP24/BO24-1),"NA",BP24/BO24-1) -> 0.15135087
A26: Y/Y Growth (%) ex Mailchimp | AE26: =(AE24-AE107)/(AA24-AA107)-1 -> 0.19835943 | AF26: =(AF24-AF107)/(AB24-AB107)-1 -> 0.21702128 | AG26: =(AG24-AG107)/(AC24-AC107)-1 -> 0.21409574 | AH26: =(AH24-AH107)/(AD24-AD107)-1 -> 0.17691415 | AI26: =(AI24-AI107)/(AE24-AE107)-1 -> 0.19788426 | AJ26: =(AJ24-AJ107)/(AF24-AF107)-1 -> 0.2016317 | AK26: =(AK24-AK107)/(AG24-AG107)-1 -> 0.2196057 | AL26: =(AL24-AL107)/(AH24-AH107)-1 -> 0.090192213 | ... BA26: =(BA24-BA107)/(AW24-AW107)-1 -> 0.14399647 | BK26: =(BK24-BK107)/(BJ24-BJ107)-1 -> 0.20621271 | BL26: =(BL24-BL107)/(BK24-BK107)-1 -> 0.19933071 | BM26: =(BM24-BM107)/(BL24-BL107)-1 -> 0.18488414 | BN26: =(BN24-BN107)/(BM24-BM107)-1 -> 0.17214267 | BO26: =(BO24-BO107)/(BN24-BN107)-1 -> 0.15912588 | BP26: =(BP24-BP107)/(BO24-BO107)-1 -> 0.15605761
A27: Q/Q Growth | B27: =IF(ISERROR(B24/A24-1),"NA",B24/A24-1) -> NA | C27: =IF(ISERROR(C24/B24-1),"NA",C24/B24-1) -> 0.032075472 | D27: =IF(ISERROR(D24/C24-1),"NA",D24/C24-1) -> 0.018281536 | E27: =IF(ISERROR(E24/D24-1),"NA",E24/D24-1) -> 0.053859964 | F27: =IF(ISERROR(F24/E24-1),"NA",F24/E24-1) -> 0.010221465 | G27: =IF(ISERROR(G24/F24-1),"NA",G24/F24-1) -> 0.042158516 | H27: =IF(ISERROR(H24/G24-1),"NA",H24/G24-1) -> 0.05987055 | I27: =IF(ISERROR(I24/H24-1),"NA",I24/H24-1) -> 0.080916031 | ... BA27: =IF(ISERROR(BA24/AZ24-1),"NA",BA24/AZ24-1) -> 0.026922596 | BD27: NA | BE27: NA | BF27: NA | BG27: NA | BH27: NA | BI27: NA | BJ27: NA | BK27: NA | BL27: NA | BM27: NA | BN27: NA | BO27: NA | BP27: NA
A28: % of total revenue | B28: =+B24/B$6 -> 0.74333801 | C28: =+C24/C$6 -> 0.59263272 | D28: =+D24/D$6 -> 0.24175347 | E28: =+E24/E$6 -> 0.77851459 | F28: =+F24/F$6 -> 0.7622108 | G28: =+G24/G$6 -> 0.60826772 | H28: =+H24/H$6 -> 0.25777253 | I28: =+I24/I$6 -> 0.84085511 | ... BA28: =+BA24/BA$6 -> 0.82020216 | BD28: =+BD24/BD$6 -> 0.47315722 | BE28: =+BE24/BE$6 -> 0.49719915 | BF28: =+BF24/BF$6 -> 0.50804979 | BG28: =+BG24/BG$6 -> 0.5207842 | BH28: =+BH24/BH$6 -> 0.52741242 | BI28: =+BI24/BI$6 -> 0.48666044 | BJ28: =+BJ24/BJ$6 -> 0.50762219 | BK28: =+BK24/BK$6 -> 0.55943764 | ... BP28: =+BP24/BP$6 -> 0.63781859
A29: Consensus | AH29: =_xll.VAData("INTU",AH$22,"Revenue - Global business solutions","consensus.vaactuals","CD","IMPL","Current","","","USD") -> 2344 | AI29: =_xll.VAData("INTU",AI$22,"Revenue - Global business solutions","consensus.vaactuals","CD","IMPL","Current","","","USD") -> 2245 | AJ29: =_xll.VAData("INTU",AJ$22,"Revenue - Global business solutions","consensus.vaactuals","CD","IMPL","Current","","","USD") -> 2387 | AK29: =_xll.VAData("INTU",AK$22,"Revenue - Global business solutions","consensus.vaactuals","CD","IMPL","Current","","","USD") -> 2557 | AL29: =_xll.VAData("INTU",AL$22,"Revenue - Global business solutions","consensus.vaactuals","CD","IMPL","Current","","","USD") -> 2544 | AM29: =_xll.VAData("INTU",AM$22,"Revenue - Global business solutions","consensus.vaactuals","CD","IMPL","Current","","","USD") -> 2671 | AN29: =_xll.VAData("INTU",AN$22,"Revenue - Global business solutions","consensus.vaactuals","CD","IMPL","Current","","","USD") -> 2849 | AO29: =_xll.VAData("INTU",AO$22,"Revenue - Global business solutions","consensus.vaactuals","CD","IMPL","Current","","","USD") -> 3013 | ... BA29: =_xll.VAData("INTU",BA$22,"Revenue - Global business solutions","consensus.vaactuals","CD","IMPL","Current","","","USD") -> 4389.4383 | BL29: =SUM(AH29:AK29) -> 9533 | BM29: =SUM(AL29:AO29) -> 11077 | BN29: =SUM(AP29:AS29) -> 12280.959 | BO29: =SUM(AT29:AW29) -> 14680.742 | BP29: =SUM(AX29:BA29) -> 16820.947
A30: Y/Y Growth (%) | B30: =IF(ISERROR(B29/#REF!-1),"NA",B29/#REF!-1) -> NA | C30: =IF(ISERROR(C29/#REF!-1),"NA",C29/#REF!-1) -> NA | D30: =IF(ISERROR(D29/#REF!-1),"NA",D29/#REF!-1) -> NA | E30: =IF(ISERROR(E29/A29-1),"NA",E29/A29-1) -> NA | F30: =IF(ISERROR(F29/B29-1),"NA",F29/B29-1) -> NA | G30: =IF(ISERROR(G29/C29-1),"NA",G29/C29-1) -> NA | H30: =IF(ISERROR(H29/D29-1),"NA",H29/D29-1) -> NA | I30: =IF(ISERROR(I29/E29-1),"NA",I29/E29-1) -> NA | J30: =IF(ISERROR(J29/F29-1),"NA",J29/F29-1) -> NA | K30: =IF(ISERROR(K29/G29-1),"NA",K29/G29-1) -> NA | L30: =IF(ISERROR(L29/H29-1),"NA",L29/H29-1) -> NA | ... AG30: =IF(ISERROR(AG29/AC29-1),"NA",AG29/AC29-1) -> NA | AL30: =IF(ISERROR(AL29/AH29-1),"NA",AL29/AH29-1) -> 0.085324232 | AM30: =IF(ISERROR(AM29/AI29-1),"NA",AM29/AI29-1) -> 0.18975501 | AN30: =IF(ISERROR(AN29/AJ29-1),"NA",AN29/AJ29-1) -> 0.19354839 | AO30: =IF(ISERROR(AO29/AK29-1),"NA",AO29/AK29-1) -> 0.17833399 | AP30: =IF(ISERROR(AP29/AL29-1),"NA",AP29/AL29-1) -> 0.17570755 | AQ30: =IF(ISERROR(AQ29/AM29-1),"NA",AQ29/AM29-1) -> 0 | AR30: =IF(ISERROR(AR29/AN29-1),"NA",AR29/AN29-1) -> 0.14861731 | AS30: =IF(ISERROR(AS29/AO29-1),"NA",AS29/AO29-1) -> 0.11070301 | ... BA30: =IF(ISERROR(BA29/AW29-1),"NA",BA29/AW29-1) -> 0.13835301 | BD30: =IF(ISERROR(BD29/BB29-1),"NA",BD29/BB29-1) -> NA | BE30: =IF(ISERROR(BE29/BD29-1),"NA",BE29/BD29-1) -> NA | BF30: =IF(ISERROR(BF29/BE29-1),"NA",BF29/BE29-1) -> NA | BG30: =IF(ISERROR(BG29/BF29-1),"NA",BG29/BF29-1) -> NA | BH30: =IF(ISERROR(BH29/BG29-1),"NA",BH29/BG29-1) -> NA | BI30: =IF(ISERROR(BI29/BH29-1),"NA",BI29/BH29-1) -> NA | BJ30: =IF(ISERROR(BJ29/BI29-1),"NA",BJ29/BI29-1) -> NA | BM30: =IF(ISERROR(BM29/BL29-1),"NA",BM29/BL29-1) -> 0.16196371 | BN30: =IF(ISERROR(BN29/BM29-1),"NA",BN29/BM29-1) -> 0.10868998 | BO30: =IF(ISERROR(BO29/BN29-1),"NA",BO29/BN29-1) -> 0.19540679 | BP30: =IF(ISERROR(BP29/BO29-1),"NA",BP29/BO29-1) -> 0.14578319
A32: Online Ecosystem | B32: =+SUM(B63,B86) -> 151 | C32: =+SUM(C63,C86) -> 155 | D32: =+SUM(D63,D86) -> 171 | E32: =+SUM(E63,E86) -> 179 | F32: =+SUM(F63,F86) -> 191 | G32: =+SUM(G63,G86) -> 200 | H32: =+SUM(H63,H86) -> 225 | I32: =+SUM(I63,I86) -> 242 | ... AQ32: =+SUM(AQ63,AQ86) -> 2467 | AR32: =AN32*(1+AR33) -> 2481.54 | AS32: =AO32*(1+AS33) -> 2595.06 | AT32: =AP32*(1+AT33) -> 2785.935 | AU32: =AQ32*(1+AU33) -> 2986.3047 | AV32: =AR32*(1+AV33) -> 2928.2172 | AW32: =AS32*(1+AW33) -> 3036.2202 | AX32: =AT32*(1+AX33) -> 3287.4033 | AY32: =AU32*(1+AY33) -> 3599.9918 | ... BA32: =AW32*(1+BA33) -> 3537.1965 | BD32: =SUM(B32:E32) -> 656 | BE32: =SUM(F32:I32) -> 858 | BF32: =SUM(J32:M32) -> 1206 | BG32: =SUM(N32:Q32) -> 1663 | BH32: =SUM(R32:U32) -> 2182 | BI32: =SUM(V32:Y32) -> 2750 | BJ32: =SUM(Z32:AC32) -> 4438 | BK32: =SUM(AD32:AG32) -> 5759 | BL32: =SUM(AH32:AK32) -> 6892 | BM32: =SUM(AL32:AO32) -> 8302 | BN32: =SUM(AP32:AS32) -> 9894.6 | BO32: =SUM(AT32:AW32) -> 11736.677 | BP32: =SUM(AX32:BA32) -> 13865.247
A33: Y/Y Growth (%) | B33: =IF(ISERROR(B32/#REF!-1),"NA",B32/#REF!-1) -> NA | C33: =IF(ISERROR(C32/#REF!-1),"NA",C32/#REF!-1) -> NA | D33: =IF(ISERROR(D32/#REF!-1),"NA",D32/#REF!-1) -> NA | E33: =IF(ISERROR(E32/A32-1),"NA",E32/A32-1) -> NA | F33: =IF(ISERROR(F32/B32-1),"NA",F32/B32-1) -> 0.26490066 | G33: =IF(ISERROR(G32/C32-1),"NA",G32/C32-1) -> 0.29032258 | H33: =IF(ISERROR(H32/D32-1),"NA",H32/D32-1) -> 0.31578947 | I33: =IF(ISERROR(I32/E32-1),"NA",I32/E32-1) -> 0.35195531 | J33: =IF(ISERROR(J32/F32-1),"NA",J32/F32-1) -> 0.37172775 | K33: =IF(ISERROR(K32/G32-1),"NA",K32/G32-1) -> 0.425 | L33: =IF(ISERROR(L32/H32-1),"NA",L32/H32-1) -> 0.41333333 | ... AQ33: =IF(ISERROR(AQ32/AM32-1),"NA",AQ32/AM32-1) -> 0.21050049 | AR33: 0.18 | AS33: 0.17 | AT33: 0.185 | AU33: =AQ33 -> 0.21050049 | AV33: =AR33 -> 0.18 | AW33: =AS33 -> 0.17 | AX33: =AT33-0.5% -> 0.18 | AY33: =AU33-0.5% -> 0.20550049 | AZ33: =AV33-0.5% -> 0.175 | BA33: =AW33-0.5% -> 0.165 | BD33: =IF(ISERROR(BD32/BB32-1),"NA",BD32/BB32-1) -> NA | BE33: =IF(ISERROR(BE32/BD32-1),"NA",BE32/BD32-1) -> 0.30792683 | BF33: =IF(ISERROR(BF32/BE32-1),"NA",BF32/BE32-1) -> 0.40559441 | BG33: =IF(ISERROR(BG32/BF32-1),"NA",BG32/BF32-1) -> 0.37893864 | BH33: =IF(ISERROR(BH32/BG32-1),"NA",BH32/BG32-1) -> 0.31208659 | BI33: =IF(ISERROR(BI32/BH32-1),"NA",BI32/BH32-1) -> 0.26031164 | BJ33: =IF(ISERROR(BJ32/BI32-1),"NA",BJ32/BI32-1) -> 0.61381818 | BK33: =IF(ISERROR(BK32/BJ32-1),"NA",BK32/BJ32-1) -> 0.2976566 | BL33: =IF(ISERROR(BL32/BK32-1),"NA",BL32/BK32-1) -> 0.19673554 | ... BP33: =IF(ISERROR(BP32/BO32-1),"NA",BP32/BO32-1) -> 0.18136051
A34: Y/Y Growth (%) ex Mailchimp | AH34: =(AH32-AH107)/(AD32-AD107)-1 -> 0.20092166 | AI34: =(AI32-AI107)/(AE32-AE107)-1 -> 0.24250681 | AJ34: =(AJ32-AJ107)/(AF32-AF107)-1 -> 0.22871883 | AK34: =(AK32-AK107)/(AG32-AG107)-1 -> 0.2064257 | AL34: =(AL32-AL107)/(AH32-AH107)-1 -> 0.23637759 | AM34: =(AM32-AM107)/(AI32-AI107)-1 -> 0.25146199 | AN34: =(AN32-AN107)/(AJ32-AJ107)-1 -> 0.24492652 | AO34: =(AO32-AO107)/(AK32-AK107)-1 -> 0.25832224 | ... BA34: =(BA32-BA107)/(AW32-AW107)-1 -> 0.1721573 | BK34: =(BK32-BK53)/(BJ32-BJ53)-1 -> 0.29765754 | BL34: =(BL32-BL53)/(BK32-BK53)-1 -> 0.1967368 | BM34: =(BM32-BM53)/(BL32-BL53)-1 -> 0.20458624 | BN34: =(BN32-BN53)/(BM32-BM53)-1 -> 0.19183432 | BO34: =(BO32-BO53)/(BN32-BN53)-1 -> 0.18617043 | BP34: =(BP32-BP53)/(BO32-BO53)-1 -> 0.18136238
A35: Y/Y Growth ($) | V35: =V32-R32 -> 120 | W35: =W32-S32 -> 114 | X35: =X32-T32 -> 155 | Y35: =Y32-U32 -> 179 | Z35: =Z32-V32 -> 224 | AA35: =AA32-W32 -> 477 | AB35: =AB32-X32 -> 477 | AC35: =AC32-Y32 -> 510 | ... BA35: =BA32-AW32 -> 500.97633 | BI35: =BI32-BH32 -> 568 | BJ35: =BJ32-BI32 -> 1688 | BK35: =BK32-BJ32 -> 1321 | BL35: =BL32-BK32 -> 1133 | BM35: =BM32-BL32 -> 1410 | BN35: =BN32-BM32 -> 1592.6 | BO35: =BO32-BN32 -> 1842.0771 | BP35: =BP32-BO32 -> 2128.5697
A36: Q/Q Growth (%) | B36: =IF(ISERROR(B32/A32-1),"NA",B32/A32-1) -> NA | C36: =IF(ISERROR(C32/B32-1),"NA",C32/B32-1) -> 0.026490066 | D36: =IF(ISERROR(D32/C32-1),"NA",D32/C32-1) -> 0.10322581 | E36: =IF(ISERROR(E32/D32-1),"NA",E32/D32-1) -> 0.046783626 | F36: =IF(ISERROR(F32/E32-1),"NA",F32/E32-1) -> 0.067039106 | G36: =IF(ISERROR(G32/F32-1),"NA",G32/F32-1) -> 0.047120419 | H36: =IF(ISERROR(H32/G32-1),"NA",H32/G32-1) -> 0.125 | I36: =IF(ISERROR(I32/H32-1),"NA",I32/H32-1) -> 0.075555556 | ... BA36: =IF(ISERROR(BA32/AZ32-1),"NA",BA32/AZ32-1) -> 0.028058994 | BD36: NA | BE36: NA | BF36: NA | BG36: NA | BH36: NA | BI36: N/A | BJ36: N/A | BK36: N/A | BL36: N/A | BM36: N/A | BN36: N/A | BO36: N/A | BP36: N/A
A37: Q/Q Growth ($) | V37: =V32-U32 -> 30 | W37: =W32-V32 -> 23 | X37: =X32-W32 -> 71 | Y37: =Y32-X32 -> 55 | Z37: =Z32-Y32 -> 75 | AA37: =AA32-Z32 -> 276 | AB37: =AB32-AA32 -> 71 | AC37: =AC32-AB32 -> 88 | ... BA37: =BA32-AZ32 -> 96.541323 | BI37: N/A | BJ37: N/A | BK37: N/A | BL37: N/A | BM37: N/A | BN37: N/A | BO37: N/A | BP37: N/A
A38: % of Total Revenue | B38: =+B32/B$6 -> 0.21178121 | C38: =+C32/C$6 -> 0.16793066 | D38: =+D32/D$6 -> 0.07421875 | E38: =+E32/E$6 -> 0.23740053 | F38: =+F32/F$6 -> 0.24550129 | G38: =+G32/G$6 -> 0.19685039 | H38: =+H32/H$6 -> 0.088547816 | I38: =+I32/I$6 -> 0.28741093 | ... BA38: =+BA32/BA$6 -> 0.66328168 | BD38: =+BD32/BD$6 -> 0.13975288 | BE38: =+BE32/BE$6 -> 0.16573305 | BF38: =+BF32/BF$6 -> 0.20016598 | BG38: =+BG32/BG$6 -> 0.24513561 | BH38: =+BH32/BH$6 -> 0.28415158 | BI38: =+BI32/BI$6 -> 0.28547701 | BJ38: =+BJ32/BJ$6 -> 0.34873487 | BK38: =+BK32/BK$6 -> 0.40082127 | ... BP38: =+BP32/BP$6 -> 0.52180479
A39: Consensus | AH39: =_xll.VAData("INTU",AH$22,"Revenue - Total online ecosystem","consensus.vaactuals") -> 1618 | AI39: =_xll.VAData("INTU",AI$22,"Revenue - Total online ecosystem","consensus.vaactuals") -> 1688 | AJ39: =_xll.VAData("INTU",AJ$22,"Revenue - Total online ecosystem","consensus.vaactuals") -> 1754 | AK39: =_xll.VAData("INTU",AK$22,"Revenue - Total online ecosystem","consensus.vaactuals") -> 1832 | AL39: =_xll.VAData("INTU",AL$22,"Revenue - Total online ecosystem","consensus.vaactuals") -> 1943 | AM39: =_xll.VAData("INTU",AM$22,"Revenue - Total online ecosystem","consensus.vaactuals") -> 2038 | AN39: =_xll.VAData("INTU",AN$22,"Revenue - Total online ecosystem","consensus.vaactuals") -> 2103 | AO39: =_xll.VAData("INTU",AO$22,"Revenue - Total online ecosystem","consensus.vaactuals") -> 2218 | ... BA39: =_xll.VAData("INTU",BA$22,"Revenue - Total online ecosystem","consensus.vaactuals") -> 3506.8234 | BL39: =SUM(AH39:AK39) -> 6892 | BM39: =SUM(AL39:AO39) -> 8302 | BN39: =SUM(AP39:AS39) -> 9429.8012 | BO39: =SUM(AT39:AW39) -> 11633.227 | BP39: =SUM(AX39:BA39) -> 13625.972
A40: Y/Y Growth (%) | B40: =IF(ISERROR(B39/#REF!-1),"NA",B39/#REF!-1) -> NA | C40: =IF(ISERROR(C39/#REF!-1),"NA",C39/#REF!-1) -> NA | D40: =IF(ISERROR(D39/#REF!-1),"NA",D39/#REF!-1) -> NA | E40: =IF(ISERROR(E39/A39-1),"NA",E39/A39-1) -> NA | F40: =IF(ISERROR(F39/B39-1),"NA",F39/B39-1) -> NA | G40: =IF(ISERROR(G39/C39-1),"NA",G39/C39-1) -> NA | H40: =IF(ISERROR(H39/D39-1),"NA",H39/D39-1) -> NA | I40: =IF(ISERROR(I39/E39-1),"NA",I39/E39-1) -> NA | J40: =IF(ISERROR(J39/F39-1),"NA",J39/F39-1) -> NA | K40: =IF(ISERROR(K39/G39-1),"NA",K39/G39-1) -> NA | L40: =IF(ISERROR(L39/H39-1),"NA",L39/H39-1) -> NA | ... AG40: =IF(ISERROR(AG39/AC39-1),"NA",AG39/AC39-1) -> NA | AL40: =IF(ISERROR(AL39/AH39-1),"NA",AL39/AH39-1) -> 0.20086527 | AM40: =IF(ISERROR(AM39/AI39-1),"NA",AM39/AI39-1) -> 0.20734597 | AN40: =IF(ISERROR(AN39/AJ39-1),"NA",AN39/AJ39-1) -> 0.19897377 | AO40: =IF(ISERROR(AO39/AK39-1),"NA",AO39/AK39-1) -> 0.21069869 | AP40: =IF(ISERROR(AP39/AL39-1),"NA",AP39/AL39-1) -> 0.20998456 | AQ40: =IF(ISERROR(AQ39/AM39-1),"NA",AQ39/AM39-1) -> 0 | AR40: =IF(ISERROR(AR39/AN39-1),"NA",AR39/AN39-1) -> 0.18661413 | AS40: =IF(ISERROR(AS39/AO39-1),"NA",AS39/AO39-1) -> 0.14758868 | ... BA40: =IF(ISERROR(BA39/AW39-1),"NA",BA39/AW39-1) -> 0.16201775 | BD40: =IF(ISERROR(BD39/BB39-1),"NA",BD39/BB39-1) -> NA | BE40: =IF(ISERROR(BE39/BD39-1),"NA",BE39/BD39-1) -> NA | BF40: =IF(ISERROR(BF39/BE39-1),"NA",BF39/BE39-1) -> NA | BG40: =IF(ISERROR(BG39/BF39-1),"NA",BG39/BF39-1) -> NA | BH40: =IF(ISERROR(BH39/BG39-1),"NA",BH39/BG39-1) -> NA | BI40: =IF(ISERROR(BI39/BH39-1),"NA",BI39/BH39-1) -> NA | BJ40: =IF(ISERROR(BJ39/BI39-1),"NA",BJ39/BI39-1) -> NA | BM40: =IF(ISERROR(BM39/BL39-1),"NA",BM39/BL39-1) -> 0.20458503 | BN40: =IF(ISERROR(BN39/BM39-1),"NA",BN39/BM39-1) -> 0.13584693 | BO40: =IF(ISERROR(BO39/BN39-1),"NA",BO39/BN39-1) -> 0.2336662 | BP40: =IF(ISERROR(BP39/BO39-1),"NA",BP39/BO39-1) -> 0.17129768
A42: QBO Ecosystem Advanced Revenue | Z42: 90 | AA42: =Z42+AA46 -> 100 | AB42: =AA42+AB46 -> 110 | AC42: =BJ42-SUM(Z42:AB42) -> 118.20429 | AD42: =AC42+AD46 -> 130.70429 | AE42: =AD42+AE46 -> 143.20429 | AF42: =AE42+AF46 -> 158.20429 | AG42: =BK42-SUM(AD42:AF42) -> 175.47714 | AH42: =AG42+AH46 -> 187.97714 | AI42: =AH42+AI46 -> 200.47714 | AJ42: =AI42+AJ46 -> 212.97714 | AK42: =BL42-SUM(AH42:AJ42) -> 231.56607 | AL42: =AK42+AL46 -> 276.56607 | AM42: =AL42+AM46 -> 289.06607 | AN42: =AM42+AN46 -> 299.06607 | AO42: =AN42+AO46 -> 319.06607 | AP42: =AO42+AP46 -> 364.06607 | AQ42: =AP42+AQ46 -> 376.56607 | AR42: =(AR49*AR52)/4 -> 411.78548 | AS42: =(AS49*AS52)/4 -> 433.48534 | AT42: =(AT49*AT52)/4 -> 478.05557 | AU42: =(AU49*AU52)/4 -> 492.33297 | AV42: =(AV49*AV52)/4 -> 547.36248 | AW42: =(AW49*AW52)/4 -> 565.40547 | AX42: =(AX49*AX52)/4 -> 603.02396 | AY42: =(AY49*AY52)/4 -> 614.36387 | ... BA42: =(BA49*BA52)/4 -> 709.45783 | BI42: =AVERAGE(BH52:BI52)*BI49 -> 242.31429 | BJ42: =AVERAGE(BI52:BJ52)*BJ49 -> 418.20429 | BK42: =AVERAGE(BJ52:BK52)*BK49 -> 607.59 | BL42: =AVERAGE(BK52:BL52)*BL49 -> 832.9975 | BM42: =SUM(AL42:AO42) -> 1183.7643 | BN42: =SUM(AP42:AS42) -> 1585.903 | BO42: =SUM(AT42:AW42) -> 2083.1565 | BP42: =SUM(AX42:BA42) -> 2630.6642
A43: Y/Y Growth (%) | AD43: =AD42/Z42-1 -> 0.45226984 | AE43: =AE42/AA42-1 -> 0.43204286 | AF43: =AF42/AB42-1 -> 0.43822078 | AG43: =AG42/AC42-1 -> 0.48452437 | AH43: =AH42/AD42-1 -> 0.43818653 | AI43: =AI42/AE42-1 -> 0.39993815 | AJ43: =AJ42/AF42-1 -> 0.34621601 | AK43: =AK42/AG42-1 -> 0.31963666 | ... BA43: =BA42/AW42-1 -> 0.25477708 | BJ43: =BJ42/BI42-1 -> 0.72587549 | BK43: =BK42/BJ42-1 -> 0.45285455 | BL43: =BL42/BK42-1 -> 0.37098619 | BM43: =BM42/BL42-1 -> 0.42108984 | BN43: =BN42/BM42-1 -> 0.33971178 | BO43: =BO42/BN42-1 -> 0.313546 | BP43: =BP42/BO42-1 -> 0.26282602
A44: Y/Y Growth ($) | AD44: =AD42-Z42 -> 40.704286 | AE44: =AE42-AA42 -> 43.204286 | AF44: =AF42-AB42 -> 48.204286 | AG44: =AG42-AC42 -> 57.272857 | AH44: =AH42-AD42 -> 57.272857 | AI44: =AI42-AE42 -> 57.272857 | AJ44: =AJ42-AF42 -> 54.772857 | AK44: =AK42-AG42 -> 56.088929 | ... BA44: =BA42-AW42 -> 144.05236 | BJ44: =BJ42-BI42 -> 175.89 | BK44: =BK42-BJ42 -> 189.38571 | BL44: =BL42-BK42 -> 225.4075 | BM44: =BM42-BL42 -> 350.76679 | BN44: =BN42-BM42 -> 402.13868 | BO44: =BO42-BN42 -> 497.25353 | BP44: =BP42-BO42 -> 547.50773
A45: Q/Q Growth (%) | AD45: =AD42/AC42-1 -> 0.10574913 | AE45: =AE42/AD42-1 -> 0.095635732 | AF45: =AF42/AE42-1 -> 0.10474547 | AG45: =AG42/AF42-1 -> 0.10918072 | AH45: =AH42/AG42-1 -> 0.071234349 | AI45: =AI42/AH42-1 -> 0.066497446 | AJ45: =AJ42/AI42-1 -> 0.062351248 | AK45: =AK42/AJ42-1 -> 0.087281331 | ... BA45: =BA42/AZ42-1 -> 0.0080123874 | BJ45: N/A | BK45: N/A | BL45: N/A | BM45: N/A | BN45: N/A | BO45: N/A | BP45: N/A
A46: Q/Q Growth ($) | AA46: 10 | AB46: 10 | AC46: =AC42-AB42 -> 8.2042857 | AD46: 12.5 | AE46: 12.5 | AF46: 15 | AG46: =AG42-AF42 -> 17.272857 | AH46: 12.5 | AI46: 12.5 | AJ46: 12.5 | AK46: =AK42-AJ42 -> 18.588929 | AL46: 45 | AM46: 12.5 | AN46: 10 | AO46: 20 | AP46: 45 | AQ46: 12.5 | AR46: =AR42-AQ42 -> 35.219411 | AS46: =AS42-AR42 -> 21.699854 | AT46: =AT42-AS42 -> 44.570239 | AU46: =AU42-AT42 -> 14.277392 | AV46: =AV42-AU42 -> 55.029517 | AW46: =AW42-AV42 -> 18.042985 | AX46: =AX42-AW42 -> 37.618494 | AY46: =AY42-AX42 -> 11.339911 | ... BA46: =BA42-AZ42 -> 5.639267 | BJ46: N/A | BK46: N/A | BL46: N/A | BM46: N/A | BN46: N/A | BO46: N/A | BP46: N/A
A47: % of Online Ecosystem | Z47: =Z42/Z32 -> 0.10650888 | AA47: =AA42/AA32 -> 0.089206066 | AB47: =AB42/AB32 -> 0.092281879 | AC47: =AC42/AC32 -> 0.092347098 | AD47: =AD42/AD32 -> 0.09688976 | AE47: =AE42/AE32 -> 0.1029506 | AF47: =AF42/AF32 -> 0.10776859 | AG47: =AG42/AG32 -> 0.11313807 | ... BA47: =BA42/BA32 -> 0.20057066 | BJ47: =BJ42/BJ32 -> 0.094232602 | BK47: =BK42/BK32 -> 0.10550269 | BL47: =BL42/BL32 -> 0.12086441 | BM47: =BM42/BM32 -> 0.14258784 | BN47: =BN42/BN32 -> 0.16027964 | BO47: =BO42/BO32 -> 0.17749116 | BP47: =BP42/BP32 -> 0.18973079
A49: QBO Ecosystem Advanced ARPC ($) | Z49: =(Z42*4)/AVERAGE(Y52:Z52) -> 2918.3555 | AA49: =(AA42*4)/AVERAGE(Z52:AA52) -> 2966.1017 | AB49: =(AB42*4)/AVERAGE(AA52:AB52) -> 2996.1089 | AC49: =(AC42*4)/AVERAGE(AB52:AC52) -> 2975.0292 | AD49: =(AD42*4)/AVERAGE(AC52:AD52) -> 3048.4965 | AE49: =(AE42*4)/AVERAGE(AD52:AE52) -> 3096.3089 | AF49: =(AF42*4)/AVERAGE(AE52:AF52) -> 3172.0158 | AG49: =(AG42*4)/AVERAGE(AF52:AG52) -> 3272.301 | ... AQ49: =(AQ42*4)/AVERAGE(AP52:AQ52) -> 4064.5033 | AR49: =AN49*(1+AR50) -> 4169.0297 | AS49: =AO49*(1+AS50) -> 4156.3386 | AT49: =AP49*(1+AT50) -> 4404.2155 | AU49: =AQ49*(1+AU50) -> 4364.8474 | AV49: =AR49*(1+AV50) -> 4656.6207 | AW49: =AS49*(1+AW50) -> 4575.6811 | AX49: =AT49*(1+AX50) -> 4736.3792 | AY49: =AU49*(1+AY50) -> 4687.3853 | ... BA49: =AW49*(1+BA50) -> 5037.3319 | BI49: 2512 | BJ49: 2957 | BK49: 3140 | BL49: 3299 | BM49: 3713 | BN49: =BN42/AVERAGE(BM52:BN52) -> 4144.6887 | BO49: =BO42/AVERAGE(BN52:BO52) -> 4571.0823 | BP49: =BP42/AVERAGE(BO52:BP52) -> 4974.6399
A50: Y/Y Growth (%) | AD50: =AD49/Z49-1 -> 0.044593926 | AE50: =AE49/AA49-1 -> 0.043898423 | AF50: =AF49/AB49-1 -> 0.058711752 | AG50: =AG49/AC49-1 -> 0.099922319 | AH50: =AH49/AD49-1 -> 0.074723266 | AI50: =AI49/AE49-1 -> 0.059257905 | AJ50: =AJ49/AF49-1 -> 0.034952195 | AK50: =AK49/AG49-1 -> 0.029316598 | ... AQ50: =AQ49/AM49-1 -> 0.07389442 | AR50: =AN50-2% -> 0.11695553 | AS50: =AO50-2% -> 0.10089227 | AT50: =AP50 -> 0.075419493 | AU50: =AQ50 -> 0.07389442 | AV50: =AR50 -> 0.11695553 | AW50: =AS50 -> 0.10089227 | AX50: =AT50 -> 0.075419493 | AY50: =AU50 -> 0.07389442 | AZ50: =AV50 -> 0.11695553 | BA50: =AW50 -> 0.10089227 | BJ50: =BJ49/BI49-1 -> 0.17714968 | BK50: =BK49/BJ49-1 -> 0.061887048 | BL50: =BL49/BK49-1 -> 0.050636943 | BM50: =BM49/BL49-1 -> 0.12549257 | BN50: =BN49/BM49-1 -> 0.11626413 | BO50: =BO49/BN49-1 -> 0.10287712 | BP50: =BP49/BO49-1 -> 0.088284915
A52: QBO Advanced Customers | U52: =BH52 -> 0.075068244 | V52: =U52+V53 -> 0.086068244 | W52: =V52+W53 -> 0.097068244 | X52: =W52+X53 -> 0.10806824 | Y52: =BI52 -> 0.11785714 | Z52: =Y52+Z53 -> 0.12885714 | AA52: =Z52+AA53 -> 0.14085714 | AB52: =AA52+AB53 -> 0.15285714 | AC52: =BJ52 -> 0.165 | AD52: =AC52+AD53 -> 0.178 | AE52: =AD52+AE53 -> 0.192 | AF52: =AE52+AF53 -> 0.207 | AG52: =BK52 -> 0.222 | AH52: =AG52+AH53 -> 0.237 | AI52: =AH52+AI53 -> 0.252 | AJ52: =AI52+AJ53 -> 0.267 | AK52: =BL52 -> 0.283 | AL52: =AK52+AL53 -> 0.298 | AM52: =AL52+AM53 -> 0.313 | AN52: =AM52+AN53 -> 0.328 | AO52: =BM52 -> 0.34809 | AP52: =AO52+AP53 -> 0.36309 | AQ52: =AP52+AQ53 -> 0.37809 | AR52: =AQ52+AR53 -> 0.39509 | AS52: =AR52+AS53 -> 0.41718 | AT52: =AS52+AT53 -> 0.43418 | AU52: =AT52+AU53 -> 0.45118 | AV52: =AU52+AV53 -> 0.47018 | AW52: =AV52+AW53 -> 0.49427 | ... BA52: =AZ52+BA53 -> 0.56336 | BH52: =BI52/(1+BI54) -> 0.075068244 | BI52: =BJ52/(1+BJ54) -> 0.11785714 | BJ52: 0.165 | BK52: 0.222 | BL52: 0.283 | BM52: =BL52*(1+BM54) -> 0.34809 | BN52: =AS52 -> 0.41718 | BO52: =AW52 -> 0.49427 | BP52: =BA52 -> 0.56336
A53: Net Adds | V53: 0.011 | W53: 0.011 | X53: 0.011 | Y53: =Y52-X52 -> 0.009788899 | Z53: 0.011 | AA53: 0.012 | AB53: 0.012 | AC53: =AC52-AB52 -> 0.012142857 | AD53: 0.013 | AE53: 0.014 | AF53: 0.015 | AG53: =AG52-AF52 -> 0.015 | AH53: 0.015 | AI53: 0.015 | AJ53: 0.015 | AK53: =AK52-AJ52 -> 0.016 | AL53: 0.015 | AM53: 0.015 | AN53: 0.015 | AO53: =AO52-AN52 -> 0.02009 | AP53: 0.015 | AQ53: 0.015 | AR53: =AN53+0.002 -> 0.017 | AS53: =AO53+0.002 -> 0.02209 | AT53: =AP53+0.002 -> 0.017 | AU53: =AQ53+0.002 -> 0.017 | AV53: =AR53+0.002 -> 0.019 | AW53: =AS53+0.002 -> 0.02409 | AX53: =AT53-0.002 -> 0.015 | AY53: =AU53-0.002 -> 0.015 | AZ53: =AV53-0.002 -> 0.017 | BA53: =AW53-0.002 -> 0.02209 | BI53: =BI52-BH52 -> 0.042788899 | BJ53: =BJ52-BI52 -> 0.047142857 | BK53: =BK52-BJ52 -> 0.057 | BL53: =BL52-BK52 -> 0.061 | BM53: =BM52-BL52 -> 0.06509 | BN53: =BN52-BM52 -> 0.06909 | BO53: =BO52-BN52 -> 0.07709 | BP53: =BP52-BO52 -> 0.06909
A54: Y/Y Growth (%) | Z54: =Z52/V52-1 -> 0.49715083 | AA54: =AA52/W52-1 -> 0.45111457 | AB54: =AB52/X52-1 -> 0.41445014 | AC54: =AC52/Y52-1 -> 0.4 | AD54: =AD52/Z52-1 -> 0.38137472 | AE54: =AE52/AA52-1 -> 0.36308316 | AF54: =AF52/AB52-1 -> 0.35420561 | AG54: =AG52/AC52-1 -> 0.34545455 | ... BA54: =BA52/AW52-1 -> 0.1397819 | BI54: 0.57 | BJ54: 0.4 | BK54: 0.35 | BL54: 0.28 | BM54: 0.23 | BN54: =BN52/BM52-1 -> 0.19848315 | BO54: =BO52/BN52-1 -> 0.18478834 | BP54: =BP52/BO52-1 -> 0.1397819
A56: QBO Ecosystem Non-Advanced Revenue | Z56: =Z32-Z42 -> 755 | AA56: =AA32-AA42 -> 1021 | AB56: =AB32-AB42 -> 1082 | AC56: =AC32-AC42 -> 1161.7957 | AD56: =AD32-AD42 -> 1218.2957 | AE56: =AE32-AE42 -> 1247.7957 | AF56: =AF32-AF42 -> 1309.7957 | AG56: =AG32-AG42 -> 1375.5229 | ... BA56: =BA32-BA42 -> 2827.7387 | BJ56: =SUM(Z56:AC56) -> 4019.7957 | BK56: =SUM(AD56:AG56) -> 5151.41 | BL56: =SUM(AH56:AK56) -> 6059.0025 | BM56: =SUM(AL56:AO56) -> 7118.2357 | BN56: =SUM(AP56:AS56) -> 8308.697 | BO56: =SUM(AT56:AW56) -> 9653.5206 | BP56: =SUM(AX56:BA56) -> 11234.583
A57: Y/Y Growth (%) | AD57: =AD56/Z56-1 -> 0.61363671 | AE57: =AE56/AA56-1 -> 0.22213096 | AF57: =AF56/AB56-1 -> 0.21053208 | AG57: =AG56/AC56-1 -> 0.18396276 | AH57: =AH56/AD56-1 -> 0.17378961 | AI57: =AI56/AE56-1 -> 0.19212051 | AJ57: =AJ56/AF56-1 -> 0.1765368 | AK57: =AK56/AG56-1 -> 0.16350951 | ... BA57: =BA56/AW56-1 -> 0.14445599 | BK57: =BK56/BJ56-1 -> 0.2815104 | BL57: =BL56/BK56-1 -> 0.17618332 | BM57: =BM56/BL56-1 -> 0.17481974 | BN57: =BN56/BM56-1 -> 0.16724107 | BO57: =BO56/BN56-1 -> 0.16185734 | BP57: =BP56/BO56-1 -> 0.16378087
A58: Y/Y Growth ($) | AD58: =AD56-Z56 -> 463.29571 | AE58: =AE56-AA56 -> 226.79571 | AF58: =AF56-AB56 -> 227.79571 | AG58: =AG56-AC56 -> 213.72714 | AH58: =AH56-AD56 -> 211.72714 | AI58: =AI56-AE56 -> 239.72714 | AJ58: =AJ56-AF56 -> 231.22714 | AK58: =AK56-AG56 -> 224.91107 | ... BA58: =BA56-AW56 -> 356.92398 | BK58: =BK56-BJ56 -> 1131.6143 | BL58: =BL56-BK56 -> 907.5925 | BM58: =BM56-BL56 -> 1059.2332 | BN58: =BN56-BM56 -> 1190.4613 | BO58: =BO56-BN56 -> 1344.8236 | BP58: =BP56-BO56 -> 1581.062
A59: Q/Q Growth (%) | AD59: =AD56/AC56-1 -> 0.048631613 | AE59: =AE56/AD56-1 -> 0.024214154 | AF59: =AF56/AE56-1 -> 0.049687621 | AG59: =AG56/AF56-1 -> 0.050181217 | AH59: =AH56/AG56-1 -> 0.039621297 | AI59: =AI56/AH56-1 -> 0.040209148 | AJ59: =AJ56/AI56-1 -> 0.035965834 | AK59: =AK56/AJ56-1 -> 0.038553011 | ... BA59: =BA56/AZ56-1 -> 0.033214279 | BJ59: N/A | BK59: N/A | BL59: N/A | BM59: N/A | BN59: N/A | BO59: N/A | BP59: N/A
A60: Q/Q Growth ($) | AA60: =AA56-Z56 -> 266 | AB60: =AB56-AA56 -> 61 | AC60: =AC56-AB56 -> 79.795714 | AD60: =AD56-AC56 -> 56.5 | AE60: =AE56-AD56 -> 29.5 | AF60: =AF56-AE56 -> 62 | AG60: =AG56-AF56 -> 65.727143 | AH60: =AH56-AG56 -> 54.5 | ... BA60: =BA56-AZ56 -> 90.902056 | BJ60: N/A | BK60: N/A | BL60: N/A | BM60: N/A | BN60: N/A | BO60: N/A | BP60: N/A
A61: % of Online Ecosystem | Z61: =1-Z47 -> 0.89349112 | AA61: =1-AA47 -> 0.91079393 | AB61: =1-AB47 -> 0.90771812 | AC61: =1-AC47 -> 0.9076529 | AD61: =1-AD47 -> 0.90311024 | AE61: =1-AE47 -> 0.8970494 | AF61: =1-AF47 -> 0.89223141 | AG61: =1-AG47 -> 0.88686193 | ... BA61: =1-BA47 -> 0.79942934 | BJ61: =1-BJ47 -> 0.9057674 | BK61: =1-BK47 -> 0.89449731 | BL61: =1-BL47 -> 0.87913559 | BM61: =1-BM47 -> 0.85741216 | BN61: =1-BN47 -> 0.83972036 | BO61: =1-BO47 -> 0.82250884 | BP61: =1-BP47 -> 0.81026921
A63: QuickBooks Online Accounting | B63: 66 | C63: 72 | D63: 78 | E63: 87 | F63: 93 | G63: 103 | H63: 119 | I63: 133 | J63: 149 | K63: 168 | L63: 183 | M63: 195 | N63: 217 | O63: 231 | P63: 260 | Q63: 272 | R63: 306 | S63: 330 | T63: 353 | U63: 365 | V63: 392 | W63: 404 | X63: 437 | Y63: 466 | Z63: 519 | AA63: 547 | AB63: 578 | AC63: 623 | AD63: 668 | AE63: 696 | AF63: 723 | AG63: 762 | AH63: 798 | AI63: 826 | AJ63: 860 | AK63: 895 | AL63: 965 | AM63: 1008 | AN63: 1044 | AO63: 1103 | AP63: 1206 | AQ63: 1248 | AR63: =AR32-AR86 -> 1228.54 | AS63: =AS32-AS86 -> 1297.06 | AT63: =AT32-AT86 -> 1433.935 | AU63: =AU32-AU86 -> 1558.3047 | AV63: =AV32-AV86 -> 1452.2172 | AW63: =AW32-AW86 -> 1505.2202 | AX63: =AX32-AX86 -> 1705.9033 | AY63: =AY32-AY86 -> 1929.9918 | ... BA63: =BA32-BA86 -> 1739.1965 | BD63: =SUM(B63:E63) -> 303 | BE63: =SUM(F63:I63) -> 448 | BF63: =SUM(J63:M63) -> 695 | BG63: =SUM(N63:Q63) -> 980 | BH63: =SUM(R63:U63) -> 1354 | BI63: =SUM(V63:Y63) -> 1699 | BJ63: =SUM(Z63:AC63) -> 2267 | BK63: =SUM(AD63:AG63) -> 2849 | BL63: =SUM(AH63:AK63) -> 3379 | BM63: =SUM(AL63:AO63) -> 4120 | BN63: =SUM(AP63:AS63) -> 4979.6 | BO63: =SUM(AT63:AW63) -> 5949.6771 | BP63: =SUM(AX63:BA63) -> 7085.2468 | BW63: FY25
A64: Y/Y Growth (%) | B64: =IF(ISERROR(B63/#REF!-1),"NA",B63/#REF!-1) -> NA | C64: =IF(ISERROR(C63/#REF!-1),"NA",C63/#REF!-1) -> NA | D64: =IF(ISERROR(D63/#REF!-1),"NA",D63/#REF!-1) -> NA | E64: =IF(ISERROR(E63/A63-1),"NA",E63/A63-1) -> NA | F64: =IF(ISERROR(F63/B63-1),"NA",F63/B63-1) -> 0.40909091 | G64: =IF(ISERROR(G63/C63-1),"NA",G63/C63-1) -> 0.43055556 | H64: =IF(ISERROR(H63/D63-1),"NA",H63/D63-1) -> 0.52564103 | I64: =IF(ISERROR(I63/E63-1),"NA",I63/E63-1) -> 0.52873563 | J64: =IF(ISERROR(J63/F63-1),"NA",J63/F63-1) -> 0.60215054 | K64: =IF(ISERROR(K63/G63-1),"NA",K63/G63-1) -> 0.63106796 | L64: =IF(ISERROR(L63/H63-1),"NA",L63/H63-1) -> 0.53781513 | ... BA64: =IF(ISERROR(BA63/AW63-1),"NA",BA63/AW63-1) -> 0.15544326 | BD64: =IF(ISERROR(BD63/BB63-1),"NA",BD63/BB63-1) -> NA | BE64: =IF(ISERROR(BE63/BD63-1),"NA",BE63/BD63-1) -> 0.47854785 | BF64: =IF(ISERROR(BF63/BE63-1),"NA",BF63/BE63-1) -> 0.55133929 | BG64: =IF(ISERROR(BG63/BF63-1),"NA",BG63/BF63-1) -> 0.41007194 | BH64: =IF(ISERROR(BH63/BG63-1),"NA",BH63/BG63-1) -> 0.38163265 | BI64: =IF(ISERROR(BI63/BH63-1),"NA",BI63/BH63-1) -> 0.25480059 | BJ64: =IF(ISERROR(BJ63/BI63-1),"NA",BJ63/BI63-1) -> 0.3343143 | BK64: =IF(ISERROR(BK63/BJ63-1),"NA",BK63/BJ63-1) -> 0.25672695 | BL64: =IF(ISERROR(BL63/BK63-1),"NA",BL63/BK63-1) -> 0.18603019 | ... BP64: =IF(ISERROR(BP63/BO63-1),"NA",BP63/BO63-1) -> 0.19086241 | BW64: =(BM78-BL78)*BL63 -> 1419180
A65: Y/Y Growth ($) | Z65: =Z63-V63 -> 127 | AA65: =AA63-W63 -> 143 | AB65: =AB63-X63 -> 141 | AC65: =AC63-Y63 -> 157 | AD65: =AD63-Z63 -> 149 | AE65: =AE63-AA63 -> 149 | AF65: =AF63-AB63 -> 145 | AG65: =AG63-AC63 -> 139 | ... BA65: =BA63-AW63 -> 233.97633 | BJ65: =BJ63-BI63 -> 568 | BK65: =BK63-BJ63 -> 582 | BL65: =BL63-BK63 -> 530 | BM65: =BM63-BL63 -> 741 | BN65: =BN63-BM63 -> 859.6 | BO65: =BO63-BN63 -> 970.07711 | BP65: =BP63-BO63 -> 1135.5697
A66: Q/Q Growth (%) | B66: =IF(ISERROR(B63/A63-1),"NA",B63/A63-1) -> NA | C66: =IF(ISERROR(C63/B63-1),"NA",C63/B63-1) -> 0.090909091 | D66: =IF(ISERROR(D63/C63-1),"NA",D63/C63-1) -> 0.083333333 | E66: =IF(ISERROR(E63/D63-1),"NA",E63/D63-1) -> 0.11538462 | F66: =IF(ISERROR(F63/E63-1),"NA",F63/E63-1) -> 0.068965517 | G66: =IF(ISERROR(G63/F63-1),"NA",G63/F63-1) -> 0.10752688 | H66: =IF(ISERROR(H63/G63-1),"NA",H63/G63-1) -> 0.15533981 | I66: =IF(ISERROR(I63/H63-1),"NA",I63/H63-1) -> 0.11764706 | ... BA66: =IF(ISERROR(BA63/AZ63-1),"NA",BA63/AZ63-1) -> 0.016981688 | BD66: NA | BE66: NA | BF66: NA | BG66: NA | BH66: NA | BI66: NA | BJ66: NA | BK66: NA | BL66: NA | BM66: NA | BN66: NA | BO66: NA | BP66: NA
A67: Q/Q Growth ($) | V67: =V63-U63 -> 27 | W67: =W63-V63 -> 12 | X67: =X63-W63 -> 33 | Y67: =Y63-X63 -> 29 | Z67: =Z63-Y63 -> 53 | AA67: =AA63-Z63 -> 28 | AB67: =AB63-AA63 -> 31 | AC67: =AC63-AB63 -> 45 | ... BA67: =BA63-AZ63 -> 29.041323 | BI67: N/A | BJ67: N/A | BK67: N/A | BL67: N/A | BM67: N/A | BN67: N/A | BO67: N/A | BP67: N/A
A68: % of Online Ecosystem | B68: =+B63/B$32 -> 0.43708609 | C68: =+C63/C$32 -> 0.46451613 | D68: =+D63/D$32 -> 0.45614035 | E68: =+E63/E$32 -> 0.48603352 | F68: =+F63/F$32 -> 0.48691099 | G68: =+G63/G$32 -> 0.515 | H68: =+H63/H$32 -> 0.52888889 | I68: =+I63/I$32 -> 0.54958678 | ... AR68: =+AR63/AR$32 -> 0.49507161 | AS68: =1-AS92 -> 0.49981889 | AT68: =+AT63/AT$32 -> 0.51470512 | AU68: =+AU63/AU$32 -> 0.52181705 | AV68: =+AV63/AV$32 -> 0.49593903 | AW68: =1-AW92 -> 0.49575462 | AX68: =+AX63/AX$32 -> 0.51892121 | AY68: =+AY63/AY$32 -> 0.53611005 | AZ68: =+AZ63/AZ$32 -> 0.49704347 | BA68: =1-BA92 -> 0.49168784 | BD68: =+BD63/BD$6 -> 0.06455049 | BE68: =+BE63/BE$6 -> 0.086536604 | BF68: =+BF63/BF$6 -> 0.1153527 | BG68: =+BG63/BG$6 -> 0.14445755 | BH68: =+BH63/BH$6 -> 0.17632504 | BI68: =+BI63/BI$6 -> 0.17637288 | BJ68: =+BJ63/BJ$6 -> 0.17813924 | BK68: =1-BK92 -> 0.49470394 | BL68: =1-BL92 -> 0.49027858 | BM68: =1-BM92 -> 0.49626596 | BN68: =1-BN92 -> 0.50326441 | BO68: =1-BO92 -> 0.50693029 | BP68: =1-BP92 -> 0.51100762
A69: Consensus | AH69: =_xll.VAData("INTU",AH$22,"Revenue - QuickBooks online accounting","consensus.vaactuals","CD","IMPL","Current","","","USD") -> 798 | AI69: =_xll.VAData("INTU",AI$22,"Revenue - QuickBooks online accounting","consensus.vaactuals","CD","IMPL","Current","","","USD") -> 826 | AJ69: =_xll.VAData("INTU",AJ$22,"Revenue - QuickBooks online accounting","consensus.vaactuals","CD","IMPL","Current","","","USD") -> 860 | AK69: =_xll.VAData("INTU",AK$22,"Revenue - QuickBooks online accounting","consensus.vaactuals","CD","IMPL","Current","","","USD") -> 895 | AL69: =_xll.VAData("INTU",AL$22,"Revenue - QuickBooks online accounting","consensus.vaactuals","CD","IMPL","Current","","","USD") -> 965 | AM69: =_xll.VAData("INTU",AM$22,"Revenue - QuickBooks online accounting","consensus.vaactuals","CD","IMPL","Current","","","USD") -> 1008 | AN69: =_xll.VAData("INTU",AN$22,"Revenue - QuickBooks online accounting","consensus.vaactuals","CD","IMPL","Current","","","USD") -> 1044 | AO69: =_xll.VAData("INTU",AO$22,"Revenue - QuickBooks online accounting","consensus.vaactuals","CD","IMPL","Current","","","USD") -> 1103 | ... BA69: =_xll.VAData("INTU",BA$22,"Revenue - QuickBooks online accounting","consensus.vaactuals","CD","IMPL","Current","","","USD") -> 1736.5354 | BL69: =SUM(AH69:AK69) -> 3379 | BM69: =SUM(AL69:AO69) -> 4120 | BN69: =SUM(AP69:AS69) -> 4751.5711 | BO69: =SUM(AT69:AW69) -> 5859.6175 | BP69: =SUM(AX69:BA69) -> 6819.7358
A70: Y/Y Growth (%) | B70: =IF(ISERROR(B69/#REF!-1),"NA",B69/#REF!-1) -> NA | C70: =IF(ISERROR(C69/#REF!-1),"NA",C69/#REF!-1) -> NA | D70: =IF(ISERROR(D69/#REF!-1),"NA",D69/#REF!-1) -> NA | E70: =IF(ISERROR(E69/A69-1),"NA",E69/A69-1) -> NA | F70: =IF(ISERROR(F69/B69-1),"NA",F69/B69-1) -> NA | G70: =IF(ISERROR(G69/C69-1),"NA",G69/C69-1) -> NA | H70: =IF(ISERROR(H69/D69-1),"NA",H69/D69-1) -> NA | I70: =IF(ISERROR(I69/E69-1),"NA",I69/E69-1) -> NA | J70: =IF(ISERROR(J69/F69-1),"NA",J69/F69-1) -> NA | K70: =IF(ISERROR(K69/G69-1),"NA",K69/G69-1) -> NA | L70: =IF(ISERROR(L69/H69-1),"NA",L69/H69-1) -> NA | ... AG70: =IF(ISERROR(AG69/AC69-1),"NA",AG69/AC69-1) -> NA | AL70: =IF(ISERROR(AL69/AH69-1),"NA",AL69/AH69-1) -> 0.20927318 | AM70: =IF(ISERROR(AM69/AI69-1),"NA",AM69/AI69-1) -> 0.22033898 | AN70: =IF(ISERROR(AN69/AJ69-1),"NA",AN69/AJ69-1) -> 0.21395349 | AO70: =IF(ISERROR(AO69/AK69-1),"NA",AO69/AK69-1) -> 0.23240223 | AP70: =IF(ISERROR(AP69/AL69-1),"NA",AP69/AL69-1) -> 0.24974093 | AQ70: =IF(ISERROR(AQ69/AM69-1),"NA",AQ69/AM69-1) -> 0 | AR70: =IF(ISERROR(AR69/AN69-1),"NA",AR69/AN69-1) -> 0.20267874 | AS70: =IF(ISERROR(AS69/AO69-1),"NA",AS69/AO69-1) -> 0.16226153 | ... BA70: =IF(ISERROR(BA69/AW69-1),"NA",BA69/AW69-1) -> 0.15031348 | BD70: =IF(ISERROR(BD69/BB69-1),"NA",BD69/BB69-1) -> NA | BE70: =IF(ISERROR(BE69/BD69-1),"NA",BE69/BD69-1) -> NA | BF70: =IF(ISERROR(BF69/BE69-1),"NA",BF69/BE69-1) -> NA | BG70: =IF(ISERROR(BG69/BF69-1),"NA",BG69/BF69-1) -> NA | BH70: =IF(ISERROR(BH69/BG69-1),"NA",BH69/BG69-1) -> NA | BI70: =IF(ISERROR(BI69/BH69-1),"NA",BI69/BH69-1) -> NA | BJ70: =IF(ISERROR(BJ69/BI69-1),"NA",BJ69/BI69-1) -> NA | BM70: =IF(ISERROR(BM69/BL69-1),"NA",BM69/BL69-1) -> 0.21929565 | BN70: =IF(ISERROR(BN69/BM69-1),"NA",BN69/BM69-1) -> 0.15329395 | BO70: =IF(ISERROR(BO69/BN69-1),"NA",BO69/BN69-1) -> 0.23319581 | BP70: =IF(ISERROR(BP69/BO69-1),"NA",BP69/BO69-1) -> 0.1638534
A72: QBO Accounting Advanced Revenue | V72: =U52*(V78*90%)/4 -> 30.402639 | W72: =V52*(W78*90%)/4 -> 34.857639 | X72: =W52*(X78*90%)/4 -> 39.312639 | Y72: =X52*(Y78*90%)/4 -> 43.767639 | Z72: =Y52*(Z78*90%)/4 -> 63.642857 | AA72: =Z52*(AA78*90%)/4 -> 69.582857 | AB72: =AA52*(AB78*90%)/4 -> 76.062857 | AC72: =AB52*(AC78*90%)/4 -> 82.542857 | ... BA72: =AZ52*(BA78*90%)/4 -> 438.44514 | BI72: =SUM(V72:Y72) -> 148.34056 | BJ72: =SUM(Z72:AC72) -> 291.83143 | BK72: =SUM(AD72:AG72) -> 400.68 | BL72: =SUM(AH72:AK72) -> 528.12 | BM72: =SUM(AL72:AO72) -> 775.359 | BN72: =SUM(AP72:AS72) -> 1102.1373 | BO72: =SUM(AT72:AW72) -> 1382.0568 | BP72: =SUM(AX72:BA72) -> 1676.0176
A73: Y/Y Growth (%) | Z73: =Z72/V72-1 -> 1.0933333 | AA73: =AA72/W72-1 -> 0.99620111 | AB73: =AB72/X72-1 -> 0.93481943 | AC73: =AC72/Y72-1 -> 0.88593352 | AD73: =AD72/Z72-1 -> 0.4 | AE73: =AE72/AA72-1 -> 0.38137472 | AF73: =AF72/AB72-1 -> 0.36308316 | AG73: =AG72/AC72-1 -> 0.35420561 | ... BA73: =BA72/AW72-1 -> 0.19609411 | BJ73: =BJ72/BI72-1 -> 0.96730711 | BK73: =BK72/BJ72-1 -> 0.3729844 | BL73: =BL72/BK72-1 -> 0.3180593 | BM73: =BM72/BL72-1 -> 0.46814928 | BN73: =BN72/BM72-1 -> 0.42145419 | BO73: =BO72/BN72-1 -> 0.25397882 | BP73: =BP72/BO72-1 -> 0.21269807
A74: Y/Y Growth ($) | Z74: =Z72-V72 -> 33.240218 | AA74: =AA72-W72 -> 34.725218 | AB74: =AB72-X72 -> 36.750218 | AC74: =AC72-Y72 -> 38.775218 | AD74: =AD72-Z72 -> 25.457143 | AE74: =AE72-AA72 -> 26.537143 | AF74: =AF72-AB72 -> 27.617143 | AG74: =AG72-AC72 -> 29.237143 | ... BA74: =BA72-AW72 -> 71.881059 | BJ74: =BJ72-BI72 -> 143.49087 | BK74: =BK72-BJ72 -> 108.84857 | BL74: =BL72-BK72 -> 127.44 | BM74: =BM72-BL72 -> 247.239 | BN74: =BN72-BM72 -> 326.7783 | BO74: =BO72-BN72 -> 279.91953 | BP74: =BP72-BO72 -> 293.96082
A75: % of QBO Advanced Revenue | Z75: =Z72/Z42 -> 0.70714286 | AA75: =AA72/AA42 -> 0.69582857 | AB75: =AB72/AB42 -> 0.69148052 | AC75: =AC72/AC42 -> 0.69830681 | AD75: =AD72/AD42 -> 0.6816915 | AE75: =AE72/AE42 -> 0.67120896 | AF75: =AF72/AF42 -> 0.65535519 | AG75: =AG72/AG42 -> 0.63700604 | ... BA75: =BA72/BA42 -> 0.61800029 | BI75: =BI72/BI42 -> 0.61218246 | BJ75: =BJ72/BJ42 -> 0.69782027 | BK75: =BK72/BK42 -> 0.65945786 | BL75: =BL72/BL42 -> 0.6339995 | BM75: =BM72/BM42 -> 0.65499442 | BN75: =BN72/BN42 -> 0.69495885 | BO75: =BO72/BO42 -> 0.66344359 | BP75: =BP72/BP42 -> 0.63710816
A76: % of QBO Accounting | Z76: =Z72/Z63 -> 0.12262593 | AA76: =AA72/AA63 -> 0.12720815 | AB76: =AB72/AB63 -> 0.13159664 | AC76: =AC72/AC63 -> 0.13249255 | AD76: =AD72/AD63 -> 0.13338323 | AE76: =AE72/AE63 -> 0.13810345 | AF76: =AF72/AF63 -> 0.14340249 | AG76: =AG72/AG63 -> 0.14669291 | ... BA76: =BA72/BA63 -> 0.25209637 | BI76: =BI72/BI63 -> 0.087310509 | BJ76: =BJ72/BJ63 -> 0.12873023 | BK76: =BK72/BK63 -> 0.14063882 | BL76: =BL72/BL63 -> 0.15629476 | BM76: =BM72/BM63 -> 0.18819393 | BN76: =BN72/BN63 -> 0.22133049 | BO76: =BO72/BO63 -> 0.23229106 | BP76: =BP72/BP63 -> 0.23655035
A78: QBO Accounting Advanced List Price ($) | V78: 1800 | W78: 1800 | X78: 1800 | Y78: 1800 | Z78: =AD78 -> 2400 | AA78: =AE78 -> 2400 | AB78: =AF78 -> 2400 | AC78: =AG78 -> 2400 | AD78: =AH78 -> 2400 | AE78: =AI78 -> 2400 | AF78: =AJ78 -> 2400 | AG78: =AK78 -> 2400 | AH78: 2400 | AI78: =AH78 -> 2400 | AJ78: =AI78 -> 2400 | AK78: =AJ78 -> 2400 | AL78: 2820 | AM78: 2820 | AN78: 2820 | AO78: 2820 | AP78: 3300 | AQ78: 3300 | AR78: 3300 | AS78: 3300 | AT78: =AP78*(1+AT79) -> 3465 | AU78: =AQ78*(1+AU79) -> 3465 | AV78: =AR78*(1+AV79) -> 3465 | AW78: =AS78*(1+AW79) -> 3465 | AX78: =AT78*(1+AX79) -> 3600.135 | AY78: =AU78*(1+AY79) -> 3600.135 | AZ78: =AV78*(1+AZ79) -> 3600.135 | BA78: =AW78*(1+BA79) -> 3600.135 | BI78: =+Y78 -> 1800 | BJ78: =+AC78 -> 2400 | BK78: =+AG78 -> 2400 | BL78: =+AK78 -> 2400 | BM78: =AO78 -> 2820 | BN78: =AS78 -> 3300 | BO78: =AW78 -> 3465 | BP78: =BA78 -> 3600.135
A79: Y/Y Growth (%) | V79: =V78/R78-1 -> #DIV/0! | W79: =W78/S78-1 -> #DIV/0! | X79: =X78/T78-1 -> #DIV/0! | Y79: =Y78/U78-1 -> #DIV/0! | Z79: =Z78/V78-1 -> 0.33333333 | AA79: =AA78/W78-1 -> 0.33333333 | AB79: =AB78/X78-1 -> 0.33333333 | AC79: =AC78/Y78-1 -> 0.33333333 | ... AS79: =AS78/AO78-1 -> 0.17021277 | AT79: 0.05 | AU79: 0.05 | AV79: 0.05 | AW79: 0.05 | AX79: 0.039 | AY79: 0.039 | AZ79: 0.039 | BA79: 0.039 | BJ79: =BJ78/BI78-1 -> 0.33333333 | BK79: =BK78/BJ78-1 -> 0 | BL79: =BL78/BK78-1 -> 0 | BM79: =BM78/BL78-1 -> 0.175 | BN79: =BN78/BM78-1 -> 0.17021277 | BO79: =BO78/BN78-1 -> 0.05 | BP79: =BP78/BO78-1 -> 0.039
A81: QBO Accounting Non-Advanced Revenue | V81: =V63-V72 -> 361.59736 | W81: =W63-W72 -> 369.14236 | X81: =X63-X72 -> 397.68736 | Y81: =Y63-Y72 -> 422.23236 | Z81: =Z63-Z72 -> 455.35714 | AA81: =AA63-AA72 -> 477.41714 | AB81: =AB63-AB72 -> 501.93714 | AC81: =AC63-AC72 -> 540.45714 | ... BA81: =BA63-BA72 -> 1300.7514 | BI81: =SUM(V81:Y81) -> 1550.6594 | BJ81: =SUM(Z81:AC81) -> 1975.1686 | BK81: =SUM(AD81:AG81) -> 2448.32 | BL81: =SUM(AH81:AK81) -> 2850.88 | BM81: =SUM(AL81:AO81) -> 3344.641 | BN81: =SUM(AP81:AS81) -> 3877.4627 | BO81: =SUM(AT81:AW81) -> 4567.6203 | BP81: =SUM(AX81:BA81) -> 5409.2292
A82: Y/Y Growth (%) | Z82: =Z81/V81-1 -> 0.25929332 | AA82: =AA81/W81-1 -> 0.29331443 | AB82: =AB81/X81-1 -> 0.26214004 | AC82: =AC81/Y81-1 -> 0.27999934 | AD82: =AD81/Z81-1 -> 0.2713098 | AE82: =AE81/AA81-1 -> 0.25651123 | AF82: =AF81/AB81-1 -> 0.23385968 | AG82: =AG81/AC81-1 -> 0.20309262 | ... BA82: =BA81/AW81-1 -> 0.14235665 | BJ82: =BJ81/BI81-1 -> 0.27376038 | BK82: =BK81/BJ81-1 -> 0.2395499 | BL82: =BL81/BK81-1 -> 0.16442295 | BM82: =BM81/BL81-1 -> 0.173196 | BN82: =BN81/BM81-1 -> 0.1593061 | BO82: =BO81/BN81-1 -> 0.17799206 | BP82: =BP81/BO81-1 -> 0.18425545
A83: Y/Y Growth ($) | Z83: =Z81-V81 -> 93.759782 | AA83: =AA81-W81 -> 108.27478 | AB83: =AB81-X81 -> 104.24978 | AC83: =AC81-Y81 -> 118.22478 | AD83: =AD81-Z81 -> 123.54286 | AE83: =AE81-AA81 -> 122.46286 | AF83: =AF81-AB81 -> 117.38286 | AG83: =AG81-AC81 -> 109.76286 | ... BA83: =BA81-AW81 -> 162.09527 | BJ83: =BJ81-BI81 -> 424.50913 | BK83: =BK81-BJ81 -> 473.15143 | BL83: =BL81-BK81 -> 402.56 | BM83: =BM81-BL81 -> 493.761 | BN83: =BN81-BM81 -> 532.8217 | BO83: =BO81-BN81 -> 690.15758 | BP83: =BP81-BO81 -> 841.60891
A84: % of QBO Accounting | Z84: =1-Z76 -> 0.87737407 | AA84: =1-AA76 -> 0.87279185 | AB84: =1-AB76 -> 0.86840336 | AC84: =1-AC76 -> 0.86750745 | AD84: =1-AD76 -> 0.86661677 | AE84: =1-AE76 -> 0.86189655 | AF84: =1-AF76 -> 0.85659751 | AG84: =1-AG76 -> 0.85330709 | ... BA84: =1-BA76 -> 0.74790363 | BI84: =1-BI76 -> 0.91268949 | BJ84: =1-BJ76 -> 0.87126977 | BK84: =1-BK76 -> 0.85936118 | BL84: =1-BL76 -> 0.84370524 | BM84: =1-BM76 -> 0.81180607 | BN84: =1-BN76 -> 0.77866951 | BO84: =1-BO76 -> 0.76770894 | BP84: =1-BP76 -> 0.76344965
A86: Online Services | B86: 85 | C86: 83 | D86: 93 | E86: 92 | F86: 98 | G86: 97 | H86: 106 | I86: 109 | J86: 113 | K86: 117 | L86: 135 | M86: 146 | N86: 154 | O86: 163 | P86: 179 | Q86: 187 | R86: 195 | S86: 200 | T86: 207 | U86: 226 | V86: 229 | W86: 240 | X86: 278 | Y86: 304 | Z86: 326 | AA86: 574 | AB86: 614 | AC86: 657 | AD86: 681 | AE86: 695 | AF86: 745 | AG86: 789 | AH86: 820 | AI86: 862 | AJ86: 894 | AK86: 937 | AL86: 978 | AM86: 1030 | AN86: 1059 | AO86: 1115 | AP86: 1145 | AQ86: 1219 | AR86: =AR107+AR115+AR123+AR129 -> 1253 | AS86: =AS107+AS115+AS123+AS129 -> 1298 | AT86: =AT107+AT115+AT123+AT129 -> 1352 | AU86: =AU107+AU115+AU123+AU129 -> 1428 | AV86: =AV107+AV115+AV123+AV129 -> 1476 | AW86: =AW107+AW115+AW123+AW129 -> 1531 | AX86: =AX107+AX115+AX123+AX129 -> 1581.5 | AY86: =AY107+AY115+AY123+AY129 -> 1670 | ... BA86: =BA107+BA115+BA123+BA129 -> 1798 | BD86: =SUM(B86:E86) -> 353 | BE86: =SUM(F86:I86) -> 410 | BF86: =SUM(J86:M86) -> 511 | BG86: =SUM(N86:Q86) -> 683 | BH86: =SUM(R86:U86) -> 828 | BI86: =SUM(V86:Y86) -> 1051 | BJ86: =SUM(Z86:AC86) -> 2171 | BK86: =SUM(AD86:AG86) -> 2910 | BL86: =SUM(AH86:AK86) -> 3513 | BM86: =SUM(AL86:AO86) -> 4182 | BN86: =SUM(AP86:AS86) -> 4915 | BO86: =SUM(AT86:AW86) -> 5787 | BP86: =SUM(AX86:BA86) -> 6780
A87: Y/Y Growth (%) | B87: =IF(ISERROR(B86/#REF!-1),"NA",B86/#REF!-1) -> NA | C87: =IF(ISERROR(C86/#REF!-1),"NA",C86/#REF!-1) -> NA | D87: =IF(ISERROR(D86/#REF!-1),"NA",D86/#REF!-1) -> NA | E87: =IF(ISERROR(E86/A86-1),"NA",E86/A86-1) -> NA | F87: =IF(ISERROR(F86/B86-1),"NA",F86/B86-1) -> 0.15294118 | G87: =IF(ISERROR(G86/C86-1),"NA",G86/C86-1) -> 0.1686747 | H87: =IF(ISERROR(H86/D86-1),"NA",H86/D86-1) -> 0.13978495 | I87: =IF(ISERROR(I86/E86-1),"NA",I86/E86-1) -> 0.18478261 | J87: =IF(ISERROR(J86/F86-1),"NA",J86/F86-1) -> 0.15306122 | K87: =IF(ISERROR(K86/G86-1),"NA",K86/G86-1) -> 0.20618557 | L87: =IF(ISERROR(L86/H86-1),"NA",L86/H86-1) -> 0.27358491 | ... BA87: =IF(ISERROR(BA86/AW86-1),"NA",BA86/AW86-1) -> 0.17439582 | BD87: =IF(ISERROR(BD86/BB86-1),"NA",BD86/BB86-1) -> NA | BE87: =IF(ISERROR(BE86/BD86-1),"NA",BE86/BD86-1) -> 0.16147309 | BF87: =IF(ISERROR(BF86/BE86-1),"NA",BF86/BE86-1) -> 0.24634146 | BG87: =IF(ISERROR(BG86/BF86-1),"NA",BG86/BF86-1) -> 0.33659491 | BH87: =IF(ISERROR(BH86/BG86-1),"NA",BH86/BG86-1) -> 0.21229868 | BI87: =IF(ISERROR(BI86/BH86-1),"NA",BI86/BH86-1) -> 0.26932367 | BJ87: =IF(ISERROR(BJ86/BI86-1),"NA",BJ86/BI86-1) -> 1.0656518 | BK87: =IF(ISERROR(BK86/BJ86-1),"NA",BK86/BJ86-1) -> 0.34039613 | BL87: =IF(ISERROR(BL86/BK86-1),"NA",BL86/BK86-1) -> 0.20721649 | ... BP87: =IF(ISERROR(BP86/BO86-1),"NA",BP86/BO86-1) -> 0.1715915
A88: Y/Y Growth (%) ex Mailchimp | AH88: =(AH86-AH107)/(AD86-AD107)-1 -> 0.21103118 | AI88: =(AI86-AI107)/(AE86-AE107)-1 -> 0.3382716 | AJ88: =(AJ86-AJ107)/(AF86-AF107)-1 -> 0.29318182 | AK88: =(AK86-AK107)/(AG86-AG107)-1 -> 0.25672878 | AL88: =(AL86-AL107)/(AH86-AH107)-1 -> 0.27920792 | AM88: =(AM86-AM107)/(AI86-AI107)-1 -> 0.29889299 | AN88: =(AN86-AN107)/(AJ86-AJ107)-1 -> 0.29173989 | AO88: =(AO86-AO107)/(AK86-AK107)-1 -> 0.29654036 | ... BA88: =(BA86-BA107)/(AW86-AW107)-1 -> 0.19393939 | BK88: =(BK86-BK107)/(BJ86-BJ107)-1 -> 0.238467 | BL88: =(BL86-BL107)/(BK86-BK107)-1 -> 0.2739255 | BM88: =(BM86-BM107)/(BL86-BL107)-1 -> 0.29194782 | BN88: =(BN86-BN107)/(BM86-BM107)-1 -> 0.24825905 | BO88: =(BO86-BO107)/(BN86-BN107)-1 -> 0.2097629 | BP88: =(BP86-BP107)/(BO86-BO107)-1 -> 0.19275997
A89: Y/Y Growth ($) | Z89: =Z86-V86 -> 97 | AA89: =AA86-W86 -> 334 | AB89: =AB86-X86 -> 336 | AC89: =AC86-Y86 -> 353 | AD89: =AD86-Z86 -> 355 | AE89: =AE86-AA86 -> 121 | AF89: =AF86-AB86 -> 131 | AG89: =AG86-AC86 -> 132 | ... BA89: =BA86-AW86 -> 267 | BJ89: =BJ86-BI86 -> 1120 | BK89: =BK86-BJ86 -> 739 | BL89: =BL86-BK86 -> 603 | BM89: =BM86-BL86 -> 669 | BN89: =BN86-BM86 -> 733 | BO89: =BO86-BN86 -> 872 | BP89: =BP86-BO86 -> 993
A90: Q/Q Growth (%) | B90: =IF(ISERROR(B86/A86-1),"NA",B86/A86-1) -> NA | C90: =IF(ISERROR(C86/B86-1),"NA",C86/B86-1) -> -0.023529412 | D90: =IF(ISERROR(D86/C86-1),"NA",D86/C86-1) -> 0.12048193 | E90: =IF(ISERROR(E86/D86-1),"NA",E86/D86-1) -> -0.010752688 | F90: =IF(ISERROR(F86/E86-1),"NA",F86/E86-1) -> 0.065217391 | G90: =IF(ISERROR(G86/F86-1),"NA",G86/F86-1) -> -0.010204082 | H90: =IF(ISERROR(H86/G86-1),"NA",H86/G86-1) -> 0.092783505 | I90: =IF(ISERROR(I86/H86-1),"NA",I86/H86-1) -> 0.028301887 | ... BA90: =IF(ISERROR(BA86/AZ86-1),"NA",BA86/AZ86-1) -> 0.039006068 | BD90: NA | BE90: NA | BF90: NA | BG90: NA | BH90: NA | BI90: NA | BJ90: NA | BK90: NA | BL90: NA | BM90: NA | BN90: NA | BO90: NA | BP90: NA
A91: Q/Q Growth ($) | V91: =+V86-U86 -> 3 | W91: =+W86-V86 -> 11 | X91: =+X86-W86 -> 38 | Y91: =+Y86-X86 -> 26 | Z91: =+Z86-Y86 -> 22 | AA91: =+AA86-Z86 -> 248 | AB91: =+AB86-AA86 -> 40 | AC91: =+AC86-AB86 -> 43 | ... BA91: =+BA86-AZ86 -> 67.5 | BK91: NA | BL91: NA | BM91: NA | BN91: NA | BO91: NA | BP91: NA
A92: % of Online Ecosystem | B92: =1-B68 -> 0.56291391 | C92: =1-C68 -> 0.53548387 | D92: =1-D68 -> 0.54385965 | E92: =1-E68 -> 0.51396648 | F92: =1-F68 -> 0.51308901 | G92: =1-G68 -> 0.485 | H92: =1-H68 -> 0.47111111 | I92: =1-I68 -> 0.45041322 | ... AQ92: =1-AQ68 -> 0.49412242 | AR92: =AR86/AR32 -> 0.50492839 | AS92: =AS86/AS32 -> 0.50018111 | AT92: =AT86/AT32 -> 0.48529488 | AU92: =AU86/AU32 -> 0.47818295 | AV92: =AV86/AV32 -> 0.50406097 | AW92: =AW86/AW32 -> 0.50424538 | AX92: =AX86/AX32 -> 0.48107879 | AY92: =AY86/AY32 -> 0.46388995 | ... BA92: =BA86/BA32 -> 0.50831216 | BD92: =+BD86/BD$6 -> 0.075202386 | BE92: =+BE86/BE$6 -> 0.079196446 | BF92: =+BF86/BF$6 -> 0.084813278 | BG92: =+BG86/BG$6 -> 0.10067807 | BH92: =+BH86/BH$6 -> 0.10782654 | BI92: =+BI86/BI$6 -> 0.10910412 | BJ92: =+BJ86/BJ$6 -> 0.17059563 | BK92: =BK86/BK32 -> 0.50529606 | BL92: =BL86/BL32 -> 0.50972142 | BM92: =BM86/BM32 -> 0.50373404 | BN92: =BN86/BN32 -> 0.49673559 | BO92: =BO86/BO32 -> 0.49306971 | BP92: =BP86/BP32 -> 0.48899238
A93: Consensus | AH93: =_xll.VAData("INTU",AH$22,"Revenue - Online services","consensus.vaactuals","CD","IMPL","Current","","","USD") -> 820 | AI93: =_xll.VAData("INTU",AI$22,"Revenue - Online services","consensus.vaactuals","CD","IMPL","Current","","","USD") -> 862 | AJ93: =_xll.VAData("INTU",AJ$22,"Revenue - Online services","consensus.vaactuals","CD","IMPL","Current","","","USD") -> 894 | AK93: =_xll.VAData("INTU",AK$22,"Revenue - Online services","consensus.vaactuals","CD","IMPL","Current","","","USD") -> 937 | AL93: =_xll.VAData("INTU",AL$22,"Revenue - Online services","consensus.vaactuals","CD","IMPL","Current","","","USD") -> 978 | AM93: =_xll.VAData("INTU",AM$22,"Revenue - Online services","consensus.vaactuals","CD","IMPL","Current","","","USD") -> 1030 | AN93: =_xll.VAData("INTU",AN$22,"Revenue - Online services","consensus.vaactuals","CD","IMPL","Current","","","USD") -> 1059 | AO93: =_xll.VAData("INTU",AO$22,"Revenue - Online services","consensus.vaactuals","CD","IMPL","Current","","","USD") -> 1115 | ... BA93: =_xll.VAData("INTU",BA$22,"Revenue - Online services","consensus.vaactuals","CD","IMPL","Current","","","USD") -> 1775.639 | BL93: =SUM(AH93:AK93) -> 3513 | BM93: =SUM(AL93:AO93) -> 4182 | BN93: =SUM(AP93:AS93) -> 4684.3238 | BO93: =SUM(AT93:AW93) -> 5774.1509 | BP93: =SUM(AX93:BA93) -> 6783.3286
A94: Y/Y Growth (%) | B94: =IF(ISERROR(B93/#REF!-1),"NA",B93/#REF!-1) -> NA | C94: =IF(ISERROR(C93/#REF!-1),"NA",C93/#REF!-1) -> NA | D94: =IF(ISERROR(D93/#REF!-1),"NA",D93/#REF!-1) -> NA | E94: =IF(ISERROR(E93/A93-1),"NA",E93/A93-1) -> NA | F94: =IF(ISERROR(F93/B93-1),"NA",F93/B93-1) -> NA | G94: =IF(ISERROR(G93/C93-1),"NA",G93/C93-1) -> NA | H94: =IF(ISERROR(H93/D93-1),"NA",H93/D93-1) -> NA | I94: =IF(ISERROR(I93/E93-1),"NA",I93/E93-1) -> NA | J94: =IF(ISERROR(J93/F93-1),"NA",J93/F93-1) -> NA | K94: =IF(ISERROR(K93/G93-1),"NA",K93/G93-1) -> NA | L94: =IF(ISERROR(L93/H93-1),"NA",L93/H93-1) -> NA | ... AG94: =IF(ISERROR(AG93/AC93-1),"NA",AG93/AC93-1) -> NA | AL94: =IF(ISERROR(AL93/AH93-1),"NA",AL93/AH93-1) -> 0.19268293 | AM94: =IF(ISERROR(AM93/AI93-1),"NA",AM93/AI93-1) -> 0.19489559 | AN94: =IF(ISERROR(AN93/AJ93-1),"NA",AN93/AJ93-1) -> 0.18456376 | AO94: 0.2055432 | AP94: =IF(ISERROR(AP93/AL93-1),"NA",AP93/AL93-1) -> 0.17075665 | AQ94: =IF(ISERROR(AQ93/AM93-1),"NA",AQ93/AM93-1) -> 0 | AR94: 0.17691048 | AS94: 0.19032893 | AT94: 0.19000312 | AU94: 0.18758005 | AV94: 0.18556425 | AW94: 0.18242459 | AX94: 0.18018398 | AY94: 0.17817349 | AZ94: 0.17648335 | BA94: 0.17389177 | BD94: =IF(ISERROR(BD93/BB93-1),"NA",BD93/BB93-1) -> NA | BE94: =IF(ISERROR(BE93/BD93-1),"NA",BE93/BD93-1) -> NA | BF94: =IF(ISERROR(BF93/BE93-1),"NA",BF93/BE93-1) -> NA | BG94: =IF(ISERROR(BG93/BF93-1),"NA",BG93/BF93-1) -> NA | BH94: =IF(ISERROR(BH93/BG93-1),"NA",BH93/BG93-1) -> NA | BI94: =IF(ISERROR(BI93/BH93-1),"NA",BI93/BH93-1) -> NA | BJ94: =IF(ISERROR(BJ93/BI93-1),"NA",BJ93/BI93-1) -> NA | BM94: =IF(ISERROR(BM93/BL93-1),"NA",BM93/BL93-1) -> 0.19043553 | BN94: =IF(ISERROR(BN93/BM93-1),"NA",BN93/BM93-1) -> 0.12011568 | BO94: =IF(ISERROR(BO93/BN93-1),"NA",BO93/BN93-1) -> 0.2326541 | BP94: =IF(ISERROR(BP93/BO93-1),"NA",BP93/BO93-1) -> 0.17477508
A96: QBO Services Advanced Revenue | Z96: =Z42-Z72 -> 26.357143 | AA96: =AA42-AA72 -> 30.417143 | AB96: =AB42-AB72 -> 33.937143 | AC96: =AC42-AC72 -> 35.661429 | AD96: =AD42-AD72 -> 41.604286 | AE96: =AE42-AE72 -> 47.084286 | AF96: =AF42-AF72 -> 54.524286 | AG96: =AG42-AG72 -> 63.697143 | ... BA96: =BA42-BA72 -> 271.01268 | BI96: =BI42-BI72 -> 93.973731 | BJ96: =BJ42-BJ72 -> 126.37286 | BK96: =BK42-BK72 -> 206.91 | BL96: =BL42-BL72 -> 304.8775 | BM96: =SUM(AL96:AO96) -> 408.40529 | BN96: =SUM(AP96:AS96) -> 483.76566 | BO96: =SUM(AT96:AW96) -> 701.09966 | BP96: =SUM(AX96:BA96) -> 954.64657
A97: Y/Y Growth (%) | AD97: =AD96/Z96-1 -> 0.57848238 | AE97: =AE96/AA96-1 -> 0.54795228 | AF97: =AF96/AB96-1 -> 0.60662569 | AG97: =AG96/AC96-1 -> 0.78616352 | AH97: =AH96/AD96-1 -> 0.63678192 | AI97: =AI96/AE96-1 -> 0.53973118 | AJ97: =AJ96/AF96-1 -> 0.41032829 | AK97: =AK96/AG96-1 -> 0.37189939 | ... BA97: =BA96/AW96-1 -> 0.36295914 | BJ97: =BJ96/BI96-1 -> 0.34476791 | BK97: =BK96/BJ96-1 -> 0.63729779 | BL97: =BL96/BK96-1 -> 0.47347881 | BM97: =BM96/BL96-1 -> 0.33957175 | BN97: =BN96/BM96-1 -> 0.18452351 | BO97: =BO96/BN96-1 -> 0.44925471 | BP97: =BP96/BO96-1 -> 0.36164175
A98: Y/Y Growth ($) | AD98: =AD96-Z96 -> 15.247143 | AE98: =AE96-AA96 -> 16.667143 | AF98: =AF96-AB96 -> 20.587143 | AG98: =AG96-AC96 -> 28.035714 | AH98: =AH96-AD96 -> 26.492857 | AI98: =AI96-AE96 -> 25.412857 | AJ98: =AJ96-AF96 -> 22.372857 | AK98: =AK96-AG96 -> 23.688929 | ... BA98: =BA96-AW96 -> 72.171298 | BJ98: =BJ96-BI96 -> 32.399126 | BK98: =BK96-BJ96 -> 80.537143 | BL98: =BL96-BK96 -> 97.9675 | BM98: =BM96-BL96 -> 103.52779 | BN98: =BN96-BM96 -> 75.360375 | BO98: =BO96-BN96 -> 217.334 | BP98: =BP96-BO96 -> 253.54691
A99: % of QBO Advanced Revenue | Z99: =Z96/Z42 -> 0.29285714 | AA99: =AA96/AA42 -> 0.30417143 | AB99: =AB96/AB42 -> 0.30851948 | AC99: =AC96/AC42 -> 0.30169319 | AD99: =AD96/AD42 -> 0.3183085 | AE99: =AE96/AE42 -> 0.32879104 | AF99: =AF96/AF42 -> 0.34464481 | AG99: =AG96/AG42 -> 0.36299396 | ... BA99: =BA96/BA42 -> 0.38199971 | BI99: =BI96/BI42 -> 0.38781754 | BJ99: =BJ96/BJ42 -> 0.30217973 | BK99: =BK96/BK42 -> 0.34054214 | BL99: =BL96/BL42 -> 0.3660005 | BM99: =BM96/BM42 -> 0.34500558 | BN99: =BN96/BN42 -> 0.30504115 | BO99: =BO96/BO42 -> 0.33655641 | BP99: =BP96/BP42 -> 0.36289184
A100: % of QBO Services | Z100: =Z96/Z86 -> 0.080850131 | AA100: =AA96/AA86 -> 0.052991538 | AB100: =AB96/AB86 -> 0.05527222 | AC100: =AC96/AC86 -> 0.054279191 | AD100: =AD96/AD86 -> 0.061092931 | AE100: =AE96/AE86 -> 0.067747174 | AF100: =AF96/AF86 -> 0.073186961 | AG100: =AG96/AG86 -> 0.080731487 | ... BA100: =BA96/BA86 -> 0.15073008 | BI100: =BI96/BI86 -> 0.089413635 | BJ100: =BJ96/BJ86 -> 0.058209515 | BK100: =BK96/BK86 -> 0.071103093 | BL100: =BL96/BL86 -> 0.086785511 | BM100: =BM96/BM86 -> 0.097657888 | BN100: =BN96/BN86 -> 0.098426381 | BO100: =BO96/BO86 -> 0.1211508 | BP100: =BP96/BP86 -> 0.14080333
A102: QBO Services Non-Advanced Revenue | Z102: =Z86-Z96 -> 299.64286 | AA102: =AA86-AA96 -> 543.58286 | AB102: =AB86-AB96 -> 580.06286 | AC102: =AC86-AC96 -> 621.33857 | AD102: =AD86-AD96 -> 639.39571 | AE102: =AE86-AE96 -> 647.91571 | AF102: =AF86-AF96 -> 690.47571 | AG102: =AG86-AG96 -> 725.30286 | ... BA102: =BA86-BA96 -> 1526.9873 | BI102: =SUM(V102:Y102) -> 0 | BJ102: =SUM(Z102:AC102) -> 2044.6271 | BK102: =SUM(AD102:AG102) -> 2703.09 | BL102: =SUM(AH102:AK102) -> 3208.1225 | BM102: =SUM(AL102:AO102) -> 3773.5947 | BN102: =SUM(AP102:AS102) -> 4431.2343 | BO102: =SUM(AT102:AW102) -> 5085.9003 | BP102: =SUM(AX102:BA102) -> 5825.3534
A103: Y/Y Growth (%) | AD103: =AD102/Z102-1 -> 1.1338594 | AE103: =AE102/AA102-1 -> 0.19193552 | AF103: =AF102/AB102-1 -> 0.19034637 | AG103: =AG102/AC102-1 -> 0.16732308 | AH103: =AH102/AD102-1 -> 0.17595855 | AI103: =AI102/AE102-1 -> 0.2185271 | AJ103: =AJ102/AF102-1 -> 0.18339116 | AK103: =AK102/AG102-1 -> 0.17139195 | ... BA103: =BA102/AW102-1 -> 0.14625038 | BJ103: =BJ102/BI102-1 -> #DIV/0! | BK103: =BK102/BJ102-1 -> 0.32204544 | BL103: =BL102/BK102-1 -> 0.18683525 | BM103: =BM102/BL102-1 -> 0.17626266 | BN103: =BN102/BM102-1 -> 0.17427405 | BO103: =BO102/BN102-1 -> 0.14773897 | BP103: =BP102/BO102-1 -> 0.14539276
A104: Y/Y Growth ($) | Z104: =Z102-V102 -> 299.64286 | AA104: =AA102-W102 -> 543.58286 | AB104: =AB102-X102 -> 580.06286 | AC104: =AC102-Y102 -> 621.33857 | AD104: =AD102-Z102 -> 339.75286 | AE104: =AE102-AA102 -> 104.33286 | AF104: =AF102-AB102 -> 110.41286 | AG104: =AG102-AC102 -> 103.96429 | ... BA104: =BA102-AW102 -> 194.8287 | BJ104: =BJ102-BI102 -> 2044.6271 | BK104: =BK102-BJ102 -> 658.46286 | BL104: =BL102-BK102 -> 505.0325 | BM104: =BM102-BL102 -> 565.47221 | BN104: =BN102-BM102 -> 657.63962 | BO104: =BO102-BN102 -> 654.666 | BP104: =BP102-BO102 -> 739.45309
A105: % of QBO Services | Z105: =1-Z100 -> 0.91914987 | AA105: =1-AA100 -> 0.94700846 | AB105: =1-AB100 -> 0.94472778 | AC105: =1-AC100 -> 0.94572081 | AD105: =1-AD100 -> 0.93890707 | AE105: =1-AE100 -> 0.93225283 | AF105: =1-AF100 -> 0.92681304 | AG105: =1-AG100 -> 0.91926851 | ... BA105: =1-BA100 -> 0.84926992 | BI105: =1-BI97 -> 1 | BJ105: =1-BJ97 -> 0.65523209 | BK105: =1-BK97 -> 0.36270221 | BL105: =1-BL97 -> 0.52652119 | BM105: =1-BM97 -> 0.66042825 | BN105: =1-BN97 -> 0.81547649 | BO105: =1-BO97 -> 0.55074529 | BP105: =1-BP97 -> 0.63835825
BI106: =+BI135/BI24 -> 0.4133959
A107: Mailchimp | AA107: =+AA388 -> 240 | AB107: =+AB388 -> 257 | AC107: =+AC388 -> 265 | AD107: 264 | AE107: 290 | AF107: =AJ107-AJ109 -> 305 | AG107: =BK107-SUM(AD107:AF107) -> 306 | AH107: 315 | AI107: 320 | AJ107: 325 | AK107: 330 | AL107: =AH107+AL109 -> 332 | AM107: =AI107+AM109 -> 326 | AN107: =AJ107+AN109 -> 324 | AO107: =AK107+AO109 -> 328 | AP107: =AL107+AP109 -> 331 | AQ107: =AM107+AQ109 -> 325 | AR107: =AR111+AQ107 -> 332 | AS107: =AS111+AR107 -> 342 | AT107: =AT111+AS107 -> 350 | AU107: =AU111+AT107 -> 358 | AV107: =AV111+AU107 -> 366 | AW107: =AW111+AV107 -> 376 | AX107: =AX111+AW107 -> 385.5 | AY107: =AY111+AX107 -> 396 | ... BA107: =BA111+AZ107 -> 419 | BJ107: =SUM(AA107:AC107) -> 762 | BK107: =BL107-BL109 -> 1165 | BL107: =SUM(AH107:AK107) -> 1290 | BM107: =SUM(AL107:AO107) -> 1310 | BN107: =SUM(AP107:AS107) -> 1330 | BO107: =SUM(AT107:AW107) -> 1450 | BP107: =SUM(AX107:BA107) -> 1607
A108: Y/Y Growth (%) | AA108: =+(AA107/W107)-1 -> #DIV/0! | AB108: =+(AB107/X107)-1 -> #DIV/0! | AC108: =+(AC107/Y107)-1 -> #DIV/0! | AD108: =+(AD107/Z107)-1 -> #DIV/0! | AE108: =+(AE107/AA107)-1 -> 0.20833333 | AF108: =+(AF107/AB107)-1 -> 0.18677043 | AG108: =+(AG107/AC107)-1 -> 0.15471698 | AH108: =+(AH107/AD107)-1 -> 0.19318182 | ... BA108: =+(BA107/AW107)-1 -> 0.1143617 | BK108: =BK107/BJ107-1 -> 0.52887139 | BL108: =BL107/BK107-1 -> 0.10729614 | BM108: =BM107/BL107-1 -> 0.015503876 | BN108: =BN107/BM107-1 -> 0.015267176 | BO108: =BO107/BN107-1 -> 0.090225564 | BP108: =BP107/BO107-1 -> 0.10827586
A109: Y/Y Net New ($) | AA109: =+AA107-W107 -> 240 | AB109: =+AB107-X107 -> 257 | AC109: =+AC107-Y107 -> 265 | AD109: =+AD107-Z107 -> 264 | AE109: =+AE107-AA107 -> 50 | AF109: =+AF107-AB107 -> 48 | AG109: =+AG107-AC107 -> 41 | AH109: =+AH107-AD107 -> 51 | AI109: =+AI107-AE107 -> 30 | AJ109: 20 | AK109: =+AK107-AG107 -> 24 | AL109: 17 | AM109: 6 | AN109: =22-SUM(AL109:AM109) -> -1 | AO109: =BM109-SUM(AL109:AN109) -> -2 | AP109: -1 | AQ109: -1 | AR109: =+AR107-AN107 -> 8 | AS109: =+AS107-AO107 -> 14 | AT109: =+AT107-AP107 -> 19 | AU109: =+AU107-AQ107 -> 33 | AV109: =+AV107-AR107 -> 34 | AW109: =+AW107-AS107 -> 34 | AX109: =+AX107-AT107 -> 35.5 | AY109: =+AY107-AU107 -> 38 | ... BA109: =+BA107-AW107 -> 43 | BL109: 125 | BM109: 20 | BN109: =+BN107-BM107 -> 20 | BO109: =+BO107-BN107 -> 120 | BP109: =+BP107-BO107 -> 157
A110: Q/Q Growth (%) | AA110: =+(AA107/Z107)-1 -> #DIV/0! | AB110: =+(AB107/AA107)-1 -> 0.070833333 | AC110: =+(AC107/AB107)-1 -> 0.031128405 | AD110: =+(AD107/AC107)-1 -> -0.0037735849 | AE110: =+(AE107/AD107)-1 -> 0.098484848 | AF110: =+(AF107/AE107)-1 -> 0.051724138 | AG110: =+(AG107/AF107)-1 -> 0.0032786885 | AH110: =+(AH107/AG107)-1 -> 0.029411765 | ... BA110: =+(BA107/AZ107)-1 -> 0.030750308 | BK110: NA | BL110: NA | BM110: NA | BN110: NA | BO110: NA | BP110: NA
A111: Q/Q Net New ($) | AA111: =+AA107-Z107 -> 240 | AB111: =+AB107-AA107 -> 17 | AC111: =+AC107-AB107 -> 8 | AD111: =+AD107-AC107 -> -1 | AE111: =+AE107-AD107 -> 26 | AF111: =+AF107-AE107 -> 15 | AG111: =+AG107-AF107 -> 1 | AH111: =+AH107-AG107 -> 9 | ... AQ111: =+AQ107-AP107 -> -6 | AR111: 7 | AS111: 10 | AT111: 8 | AU111: 8 | AV111: 8 | AW111: 10 | AX111: =+AT111+1.5 -> 9.5 | AY111: =+AU111+2.5 -> 10.5 | AZ111: =+AV111+2.5 -> 10.5 | BA111: =+AW111+2.5 -> 12.5 | BK111: NA | BL111: NA | BM111: NA | BN111: NA | BO111: NA | BP111: NA
A112: % of QBO Services | AH112: =+AH107/AH86 -> 0.38414634 | AI112: =+AI107/AI86 -> 0.3712297 | AJ112: =+AJ107/AJ86 -> 0.36353468 | AK112: =+AK107/AK86 -> 0.35218783 | AL112: =+AL107/AL86 -> 0.3394683 | AM112: =+AM107/AM86 -> 0.31650485 | AN112: =+AN107/AN86 -> 0.30594901 | AO112: =+AO107/AO86 -> 0.2941704 | ... BA112: =+BA107/BA86 -> 0.23303671 | BK112: =+BK107/BK86 -> 0.40034364 | BL112: =+BL107/BL86 -> 0.36720751 | BM112: =+BM107/BM86 -> 0.31324725 | BN112: =+BN107/BN86 -> 0.2706002 | BO112: =+BO107/BO86 -> 0.2505616 | BP112: =+BP107/BP86 -> 0.23702065
...

Sheet Balance Sheet
A1: =+'Income Statement'!A1 -> Intuit, Inc.
A2: Balance Sheet | BD2: 0 | BE2: 0 | BF2: 0 | BG2: 0 | BH2: 0 | BI2: 0 | BJ2: 0 | BK2: 0 | BL2: 0 | BM2: 0 | BN2: 0 | BO2: 0 | BP2: 0
B3: =+'Income Statement'!B3:E3 -> Fiscal 2016 | F3: =+'Income Statement'!F3:I3 -> Fiscal 2017 | J3: =+'Income Statement'!J3:M3 -> Fiscal 2018 | N3: =+'Income Statement'!N3:Q3 -> Fiscal 2019 | R3: =+'Income Statement'!R3:U3 -> Fiscal 2020 | V3: =+'Income Statement'!V3:Y3 -> Fiscal 2021 | Z3: =+'Income Statement'!Z3:AC3 -> Fiscal 2022 | AD3: =+'Income Statement'!AD3:AG3 -> Fiscal 2023 | AH3: =+'Income Statement'!AH3:AK3 -> Fiscal 2024 | AL3: =+'Income Statement'!AL3:AO3 -> Fiscal 2025 | AP3: =+'Income Statement'!AP3:AS3 -> Fiscal 2026 | AT3: =+'Income Statement'!AT3:AW3 -> Fiscal 2027 | AX3: =+'Income Statement'!AX3:BA3 -> Fiscal 2028
A4: ($ in millions, unless otherwise stated) | B4: =+'Income Statement'!B4 -> 42308 | C4: =+'Income Statement'!C4 -> 42400 | D4: =+'Income Statement'!D4 -> 42490 | E4: =+'Income Statement'!E4 -> 42582 | F4: =+'Income Statement'!F4 -> 42674 | G4: =+'Income Statement'!G4 -> 42766 | H4: =+'Income Statement'!H4 -> 42855 | I4: =+'Income Statement'!I4 -> 42947 | ... BA4: =+'Income Statement'!BA4 -> Jul-28E | BC4: =+'Income Statement'!BC4 -> FY15 | BD4: =+'Income Statement'!BD4 -> FY16 | BE4: =+'Income Statement'!BE4 -> FY17 | BF4: =+'Income Statement'!BF4 -> FY18 | BG4: =+'Income Statement'!BG4 -> FY19 | BH4: =+'Income Statement'!BH4 -> FY20 | BI4: =+'Income Statement'!BI4 -> FY21 | BJ4: =+'Income Statement'!BJ4 -> FY22 | ... BP4: =+'Income Statement'!BP4 -> FY28E
A5: Current assets
A6: Cash and cash equivalents | B6: 474 | C6: 334 | D6: 1289 | E6: 638 | F6: 360 | G6: 392 | H6: 1350 | I6: 529 | J6: 529 | K6: 478 | L6: 1614 | M6: 1464 | N6: 1084 | O6: 1075 | P6: 2946 | Q6: 2116 | R6: 1630 | S6: 1641 | T6: 3371 | U6: 6442 | V6: 5174 | W6: 1952 | X6: 3164 | Y6: 2562 | Z6: 2864 | AA6: 1257 | AB6: 3531 | AC6: 2796 | AD6: 2125 | AE6: 1547 | AF6: 3745 | AG6: 2848 | AH6: 1734 | AI6: 1474 | AJ6: 4215 | AK6: 3609 | AL6: 2872 | AM6: 2435 | AN6: 5443 | AO6: 2884 | AP6: 3506 | AQ6: 2942 | AR6: =+AQ6+'Cash Flow'!AR59 -> 7485.7456 | AS6: =+AR6+'Cash Flow'!AS59 -> 8746.203 | AT6: =+AS6+'Cash Flow'!AT59 -> 9818.7093 | AU6: =+AT6+'Cash Flow'!AU59 -> 10682.847 | AV6: =+AU6+'Cash Flow'!AV59 -> 15683.56 | AW6: =+AV6+'Cash Flow'!AW59 -> 16690.104 | AX6: =+AW6+'Cash Flow'!AX59 -> 18144.998 | AY6: =+AX6+'Cash Flow'!AY59 -> 19074.678 | ... BA6: =+AZ6+'Cash Flow'!BA59 -> 25668.531 | BD6: =E6 -> 638 | BE6: =I6 -> 529 | BF6: =M6 -> 1464 | BG6: =Q6 -> 2116 | BH6: =U6 -> 6442 | BI6: =Y6 -> 2562 | BJ6: =AC6 -> 2796 | BK6: =+AG6 -> 2848 | BL6: =+AK6 -> 3609 | BM6: =+AO6 -> 2884 | BN6: =+AP6 -> 3506 | BO6: =+AW6 -> 16690.104 | BP6: =+BA6 -> 25668.531
A7: Investments | B7: 0 | C7: 0 | D7: 324 | E7: 442 | F7: 245 | G7: 245 | H7: 243 | I7: 248 | J7: 248 | K7: 248 | L7: 322 | M7: 252 | N7: 248 | O7: 258 | P7: 400 | Q7: 624 | R7: 625 | S7: 625 | T7: 600 | U7: 608 | V7: 619 | W7: 786 | X7: 952 | Y7: 1308 | Z7: 386 | AA7: 157 | AB7: 373 | AC7: 485 | AD7: 599 | AE7: 524 | AF7: 523 | AG7: 814 | AH7: 537 | AI7: 15 | AJ7: 463 | AK7: 465 | AL7: 486 | AM7: 24 | AN7: 731 | AO7: 1668 | AP7: 190 | AQ7: 33 | AR7: =+AQ7 -> 33 | AS7: =+AR7 -> 33 | AT7: =+AS7 -> 33 | AU7: =+AT7 -> 33 | AV7: =+AU7 -> 33 | AW7: =+AV7 -> 33 | AX7: =+AW7 -> 33 | AY7: =+AX7 -> 33 | ... BA7: =+AZ7 -> 33 | BD7: =E7 -> 442 | BE7: =I7 -> 248 | BF7: =M7 -> 252 | BG7: =Q7 -> 624 | BH7: =U7 -> 608 | BI7: =Y7 -> 1308 | BJ7: =AC7 -> 485 | BK7: =+AG7 -> 814 | BL7: =+AK7 -> 465 | BM7: =+AO7 -> 1668 | BN7: =+AP7 -> 190 | BO7: =+AW7 -> 33 | BP7: =+BA7 -> 33
A8: Accounts receivable, net | B8: 124 | C8: 512 | D8: 214 | E8: 108 | F8: 121 | G8: 521 | H8: 245 | I8: 103 | J8: 116 | K8: 532 | L8: 309 | M8: 98 | N8: 77 | O8: 554 | P8: 262 | Q8: 87 | R8: 104 | S8: 603 | T8: 219 | U8: 149 | V8: 99 | W8: 465 | X8: 554 | Y8: 391 | Z8: 411 | AA8: 889 | AB8: 738 | AC8: 446 | AD8: 384 | AE8: 903 | AF8: 717 | AG8: 405 | AH8: 372 | AI8: 928 | AJ8: 790 | AK8: 457 | AL8: 426 | AM8: 1017 | AN8: 724 | AO8: 530 | AP8: 579 | AQ8: 1175 | AR8: =+AR70*(AR64/91.25) -> 792.58766 | AS8: =+AS70*(AS64/91.25) -> 588.33009 | AT8: =+AT70*(AT64/91.25) -> 706.73996 | AU8: =+AU70*(AU64/91.25) -> 1397.3829 | AV8: =+AV70*(AV64/91.25) -> 970.61055 | AW8: =+AW70*(AW64/91.25) -> 708.51821 | AX8: =+AX70*(AX64/91.25) -> 851.07557 | AY8: =+AY70*(AY64/91.25) -> 1653.6368 | ... BA8: =+BA70*(BA64/91.25) -> 854.66152 | BD8: =E8 -> 108 | BE8: =I8 -> 103 | BF8: =M8 -> 98 | BG8: =Q8 -> 87 | BH8: =U8 -> 149 | BI8: =Y8 -> 391 | BJ8: =AC8 -> 446 | BK8: =+AG8 -> 405 | BL8: =+AK8 -> 457 | BM8: =+AO8 -> 530 | BN8: =+AP8 -> 579 | BO8: =+AW8 -> 708.51821 | BP8: =+BA8 -> 854.66152
A9: Income taxes receivable | B9: 100 | C9: 45761 | D9: 4 | E9: 20 | F9: 57 | G9: 41 | H9: 0 | I9: 63 | J9: 61 | K9: 33 | L9: 2 | M9: 39 | N9: 116 | O9: 70 | P9: 3 | Q9: 65 | R9: 86 | S9: 52 | T9: 6 | U9: 12 | V9: 29 | W9: 153 | X9: 4 | Y9: 123 | Z9: 111 | AA9: 241 | AB9: 6 | AC9: =93+509 -> 602 | AD9: =566+88 -> 654 | AE9: =948+67 -> 1015 | AF9: =700+2 -> 702 | AG9: =687+29 -> 716 | AH9: =649+9+17 -> 675 | AI9: =1001+21+126 -> 1148 | AJ9: =698+7+4 -> 709 | AK9: =779+3+78 -> 860 | AL9: =892+10+27 -> 929 | AM9: =1376+14+90 -> 1480 | AN9: =1278+47+9 -> 1334 | AO9: =1403+50 -> 1453 | AP9: =1519+31+48 -> 1598 | AQ9: =1699+84+117 -> 1900 | AR9: =+AQ9 -> 1900 | AS9: =+AR9 -> 1900 | AT9: =+AS9 -> 1900 | AU9: =+AT9 -> 1900 | AV9: =+AU9 -> 1900 | AW9: =+AV9 -> 1900 | AX9: =+AW9 -> 1900 | AY9: =+AX9 -> 1900 | ... BA9: =+AZ9 -> 1900 | BD9: =E9 -> 20 | BE9: =I9 -> 63 | BF9: =M9 -> 39 | BG9: =Q9 -> 65 | BH9: =U9 -> 12 | BI9: =Y9 -> 123 | BJ9: =AC9 -> 602 | BK9: =+AG9 -> 716 | BL9: =+AK9 -> 860 | BM9: =+AO9 -> 1453 | BN9: =+AP9 -> 1598 | BO9: =+AW9 -> 1900 | BP9: =+BA9 -> 1900
A10: Prepaid expenses and other current assets | B10: 244 | C10: 110 | D10: 108 | E10: 102 | F10: 153 | G10: 156 | H10: 94 | I10: 100 | J10: 142 | K10: 189 | L10: 179 | M10: 202 | N10: 269 | O10: 253 | P10: 255 | Q10: 266 | R10: 304 | S10: 308 | T10: 277 | U10: 314 | V10: 246 | W10: 312 | X10: 305 | Y10: 316 | Z10: 409 | AA10: 571 | AB10: 671 | AC10: 287 | AD10: 324 | AE10: 391 | AF10: 574 | AG10: 354 | AH10: 388 | AI10: 345 | AJ10: 337 | AK10: 366 | AL10: 407 | AM10: 845 | AN10: 512 | AO10: 496 | AP10: 630 | AQ10: 1239 | AR10: =AR76*AR$64 -> 560.50398 | AS10: =AS76*AS$64 -> 550.58816 | AT10: =AT76*AT$64 -> 716.31892 | AU10: =AU76*AU$64 -> 1412.2349 | AV10: =AV76*AV$64 -> 614.29882 | AW10: =AW76*AW$64 -> 614.39708 | AX10: =AX76*AX$64 -> 807.31319 | AY10: =AY76*AY$64 -> 1604.5048 | ... BA10: =BA76*BA$64 -> 690.44758 | BD10: =E10 -> 102 | BE10: =I10 -> 100 | BF10: =M10 -> 202 | BG10: =Q10 -> 266 | BH10: =U10 -> 314 | BI10: =Y10 -> 316 | BJ10: =AC10 -> 287 | BK10: =+AG10 -> 354 | BL10: =+AK10 -> 366 | BM10: =+AO10 -> 496 | BN10: =+AP10 -> 630 | BO10: =+AW10 -> 614.39708 | BP10: =+BA10 -> 690.44758
A11: Deferred income taxes | B11: 121 | C11: 0 | D11: 0 | E11: 0 | F11: 0 | G11: 0 | H11: 0 | I11: 0 | J11: 0 | K11: 0 | L11: 0 | M11: 0 | N11: 0 | O11: 0 | P11: 0 | Q11: 0 | R11: 0 | S11: 0 | T11: 0 | U11: 0 | V11: 0 | W11: 0 | X11: 0 | Y11: 0 | Z11: 0 | AA11: 0 | AB11: 0 | AC11: 0 | AD11: 0 | AE11: 0 | AF11: 0 | AG11: 0 | AH11: 0 | AI11: 0 | AJ11: 0 | AK11: 0 | AL11: 0 | AM11: 0 | AN11: 0 | AO11: 0 | AP11: 0 | AQ11: 0 | AR11: 0 | AS11: 0 | AT11: 0 | AU11: 0 | AV11: 0 | AW11: 0 | AX11: 0 | AY11: 0 | AZ11: 0 | BA11: 0 | BD11: =E11 -> 0 | BE11: =I11 -> 0 | BF11: =M11 -> 0 | BG11: =Q11 -> 0 | BH11: =U11 -> 0 | BI11: =Y11 -> 0 | BJ11: =AC11 -> 0 | BK11: =+AG11 -> 0 | BL11: =+AK11 -> 0 | BM11: =+AO11 -> 0 | BN11: =+AP11 -> 0 | BO11: =+AW11 -> 0 | BP11: =+BA11 -> 0
A12: Current assets of discontinued operations | B12: 17 | C12: 30 | D12: 0 | E12: 0 | F12: 0 | G12: 0 | H12: 0 | I12: 0 | J12: 0 | K12: 0 | L12: 0 | M12: 0 | N12: 0 | O12: 0 | P12: 0 | Q12: 0 | R12: 0 | S12: 0 | T12: 0 | U12: 0 | V12: 0 | W12: 0 | X12: 0 | Y12: 0 | Z12: 0 | AA12: 0 | AB12: 0 | AC12: 0 | AD12: 0 | AE12: 0 | AF12: 0 | AG12: 0 | AH12: 0 | AI12: 0 | AJ12: 0 | AK12: 0 | AL12: 0 | AM12: 0 | AN12: 0 | AO12: 0 | AP12: 0 | AQ12: 0 | AR12: 0 | AS12: 0 | AT12: 0 | AU12: 0 | AV12: 0 | AW12: 0 | AX12: 0 | AY12: 0 | AZ12: 0 | BA12: 0 | BD12: =E12 -> 0 | BE12: =I12 -> 0 | BF12: =M12 -> 0 | BG12: =Q12 -> 0 | BH12: =U12 -> 0 | BI12: =Y12 -> 0 | BJ12: =AC12 -> 0 | BK12: =+AG12 -> 0 | BL12: =+AK12 -> 0 | BM12: =+AO12 -> 0 | BN12: =+AP12 -> 0 | BO12: =+AW12 -> 0 | BP12: =+BA12 -> 0
A13: Current assets before funds held for customers | B13: =SUM(B6:B12) -> 1080 | C13: =SUM(C6:C12) -> 46747 | D13: =SUM(D6:D12) -> 1939 | E13: =SUM(E6:E12) -> 1310 | F13: =SUM(F6:F12) -> 936 | G13: =SUM(G6:G12) -> 1355 | H13: =SUM(H6:H12) -> 1932 | I13: =SUM(I6:I12) -> 1043 | ... BA13: =SUM(BA6:BA12) -> 29146.64 | BD13: =E13 -> 1310 | BE13: =I13 -> 1043 | BF13: =M13 -> 2055 | BG13: =Q13 -> 3158 | BH13: =U13 -> 7525 | BI13: =Y13 -> 4700 | BJ13: =AC13 -> 4616 | BK13: =+AG13 -> 5137 | BL13: =+AK13 -> 5757 | BM13: =+AO13 -> 7031 | BN13: =+AP13 -> 6503 | BO13: =+AW13 -> 19946.019 | BP13: =+BA13 -> 29146.64
A14: Funds held for customers | B14: 347 | C14: 373 | D14: 372 | E14: 304 | F14: 326 | G14: 324 | H14: 323 | I14: 372 | J14: 319 | K14: 422 | L14: 419 | M14: 367 | N14: 438 | O14: 434 | P14: 383 | Q14: 436 | R14: 413 | S14: 461 | T14: 389 | U14: 455 | V14: 484 | W14: 426 | X14: 348 | Y14: 457 | Z14: 306 | AA14: 375 | AB14: 539 | AC14: 431 | AD14: 468 | AE14: 376 | AF14: 388 | AG14: 420 | AH14: 2525 | AI14: 3390 | AJ14: 2722 | AK14: 3921 | AL14: 5606 | AM14: 3334 | AN14: 5221 | AO14: 7076 | AP14: 3918 | AQ14: 4414 | AR14: =+AR64*AR74 -> 5715.6079 | AS14: =+AS64*AS74 -> 7854.7617 | AT14: =+AT64*AT74 -> 4454.8215 | AU14: =+AU64*AU74 -> 5031.1582 | AV14: =+AV64*AV74 -> 6264.1683 | AW14: =+AW64*AW74 -> 8765.068 | AX14: =+AX64*AX74 -> 5020.7192 | AY14: =+AY64*AY74 -> 5716.1293 | ... BA14: =+BA64*BA74 -> 9850.0143 | BD14: =E14 -> 304 | BE14: =I14 -> 372 | BF14: =M14 -> 367 | BG14: =Q14 -> 436 | BH14: =U14 -> 455 | BI14: =Y14 -> 457 | BJ14: =AC14 -> 431 | BK14: =+AG14 -> 420 | BL14: =+AK14 -> 3921 | BM14: =+AO14 -> 7076 | BN14: =+AP14 -> 3918 | BO14: =+AW14 -> 8765.068 | BP14: =+BA14 -> 9850.0143
A15: Total Current Assets | B15: =+SUM(B13:B14) -> 1427 | C15: =+SUM(C13:C14) -> 47120 | D15: =+SUM(D13:D14) -> 2311 | E15: =+SUM(E13:E14) -> 1614 | F15: =+SUM(F13:F14) -> 1262 | G15: =+SUM(G13:G14) -> 1679 | H15: =+SUM(H13:H14) -> 2255 | I15: =+SUM(I13:I14) -> 1415 | ... BA15: =+SUM(BA13:BA14) -> 38996.654 | BD15: =E15 -> 1614 | BE15: =I15 -> 1415 | BF15: =M15 -> 2422 | BG15: =Q15 -> 3594 | BH15: =U15 -> 7980 | BI15: =Y15 -> 5157 | BJ15: =AC15 -> 5047 | BK15: =+AG15 -> 5557 | BL15: =+AK15 -> 9678 | BM15: =+AO15 -> 14107 | BN15: =+AP15 -> 10421 | BO15: =+AW15 -> 28711.087 | BP15: =+BA15 -> 38996.654
A17: Long-term investments | B17: 28 | C17: 28 | D17: 28 | E17: 28 | F17: 28 | G17: 28 | H17: 28 | I17: 31 | J17: 31 | K17: 28 | L17: 28 | M17: 13 | N17: 13 | O17: 13 | P17: 13 | Q17: 13 | R17: 13 | S17: 13 | T17: 19 | U17: 19 | V17: 28 | W17: 41 | X17: 41 | Y17: 43 | Z17: 84 | AA17: 90 | AB17: 98 | AC17: 98 | AD17: 98 | AE17: 108 | AF17: 102 | AG17: 105 | AH17: 107 | AI17: 128 | AJ17: 129 | AK17: 131 | AL17: 90 | AM17: 88 | AN17: 88 | AO17: 94 | AP17: 92 | AQ17: 127 | AR17: =+AQ17 -> 127 | AS17: =+AR17 -> 127 | AT17: =+AS17 -> 127 | AU17: =+AT17 -> 127 | AV17: =+AU17 -> 127 | AW17: =+AV17 -> 127 | AX17: =+AW17 -> 127 | AY17: =+AX17 -> 127 | ... BA17: =+AZ17 -> 127 | BD17: =E17 -> 28 | BE17: =I17 -> 31 | BF17: =M17 -> 13 | BG17: =Q17 -> 13 | BH17: =U17 -> 19 | BI17: =Y17 -> 43 | BJ17: =AC17 -> 98 | BK17: =+AG17 -> 105 | BL17: =+AK17 -> 131 | BM17: =+AO17 -> 94 | BN17: =+AP17 -> 92 | BO17: =+AW17 -> 127 | BP17: =+BA17 -> 127
A18: Property and equipment, net | B18: 701 | C18: 980 | D18: 989 | E18: 1031 | F18: 1047 | G18: 1047 | H18: 1041 | I18: 1030 | J18: 1016 | K18: 984 | L18: 950 | M18: 812 | N18: 805 | O18: 810 | P18: 799 | Q18: 780 | R18: 773 | S18: 758 | T18: 745 | U18: 734 | V18: 743 | W18: 792 | X18: 791 | Y18: 780 | Z18: 789 | AA18: 831 | AB18: 858 | AC18: 888 | AD18: 926 | AE18: 931 | AF18: 938 | AG18: 969 | AH18: 1013 | AI18: 1049 | AJ18: 1032 | AK18: 1009 | AL18: 1008 | AM18: 992 | AN18: 975 | AO18: 961 | AP18: 965 | AQ18: 974 | AR18: =+AQ18-'Cash Flow'!AR37-'Cash Flow'!AR36-'Cash Flow'!AR7-'Cash Flow'!AR8 -> 797.92642 | AS18: =+AR18-'Cash Flow'!AS37-'Cash Flow'!AS36-'Cash Flow'!AS7-'Cash Flow'!AS8 -> 621.44398 | AT18: =+AS18-'Cash Flow'!AT37-'Cash Flow'!AT36-'Cash Flow'!AT7-'Cash Flow'!AT8 -> 445.47786 | AU18: =+AT18-'Cash Flow'!AU37-'Cash Flow'!AU36-'Cash Flow'!AU7-'Cash Flow'!AU8 -> 269.65398 | AV18: =+AU18-'Cash Flow'!AV37-'Cash Flow'!AV36-'Cash Flow'!AV7-'Cash Flow'!AV8 -> 90.722631 | AW18: =+AV18-'Cash Flow'!AW37-'Cash Flow'!AW36-'Cash Flow'!AW7-'Cash Flow'!AW8 -> -89.466437 | AX18: =+AW18-'Cash Flow'!AX37-'Cash Flow'!AX36-'Cash Flow'!AX7-'Cash Flow'!AX8 -> -210.85022 | AY18: =+AX18-'Cash Flow'!AY37-'Cash Flow'!AY36-'Cash Flow'!AY7-'Cash Flow'!AY8 -> -332.83021 | ... BA18: =+AZ18-'Cash Flow'!BA37-'Cash Flow'!BA36-'Cash Flow'!BA7-'Cash Flow'!BA8 -> -579.45912 | BD18: =E18 -> 1031 | BE18: =I18 -> 1030 | BF18: =M18 -> 812 | BG18: =Q18 -> 780 | BH18: =U18 -> 734 | BI18: =Y18 -> 780 | BJ18: =AC18 -> 888 | BK18: =+AG18 -> 969 | BL18: =+AK18 -> 1009 | BM18: =+AO18 -> 961 | BN18: =+AP18 -> 965 | BO18: =+AW18 -> -89.466437 | BP18: =+BA18 -> -579.45912
A19: Operating lease right-of-use assets | B19: 0 | C19: 0 | D19: 0 | E19: 0 | F19: 0 | G19: 0 | H19: 0 | I19: 0 | J19: 0 | K19: 0 | L19: 0 | M19: 0 | N19: 0 | O19: 0 | P19: 0 | Q19: 0 | R19: 307 | S19: 297 | T19: 220 | U19: 226 | V19: 232 | W19: 392 | X19: 370 | Y19: 380 | Z19: 405 | AA19: 439 | AB19: 425 | AC19: 549 | AD19: 535 | AE19: 508 | AF19: 485 | AG19: 469 | AH19: 457 | AI19: 444 | AJ19: 428 | AK19: 411 | AL19: 538 | AM19: 518 | AN19: 560 | AO19: 541 | AP19: 596 | AQ19: 593 | AR19: =+AQ19 -> 593 | AS19: =+AR19 -> 593 | AT19: =+AS19 -> 593 | AU19: =+AT19 -> 593 | AV19: =+AU19 -> 593 | AW19: =+AV19 -> 593 | AX19: =+AW19 -> 593 | AY19: =+AX19 -> 593 | ... BA19: =+AZ19 -> 593 | BD19: =E19 -> 0 | BE19: =I19 -> 0 | BF19: =M19 -> 0 | BG19: =Q19 -> 0 | BH19: =U19 -> 226 | BI19: =Y19 -> 380 | BJ19: =AC19 -> 549 | BK19: =+AG19 -> 469 | BL19: =+AK19 -> 411 | BM19: =+AO19 -> 541 | BN19: =+AP19 -> 596 | BO19: =+AW19 -> 593 | BP19: =+BA19 -> 593
A20: Goodwill | B20: 1274 | C20: 1278 | D20: 1282 | E20: 1282 | F20: 1293 | G20: 1293 | H20: 1294 | I20: 1295 | J20: 1294 | K20: 1615 | L20: 1613 | M20: 1611 | N20: 1610 | O20: 1611 | P20: 1611 | Q20: 1655 | R20: 1655 | S20: 1655 | T20: 1653 | U20: 1654 | V20: 1697 | W20: 5598 | X20: 5614 | Y20: 5613 | Z20: 5613 | AA20: 13732 | AB20: 13731 | AC20: 13736 | AD20: 13732 | AE20: 13779 | AF20: 13778 | AG20: 13780 | AH20: 13776 | AI20: 13779 | AJ20: 13778 | AK20: 13844 | AL20: 13844 | AM20: 13841 | AN20: 13847 | AO20: 13980 | AP20: 13980 | AQ20: 13983 | AR20: =+AQ20 -> 13983 | AS20: =+AR20 -> 13983 | AT20: =+AS20 -> 13983 | AU20: =+AT20 -> 13983 | AV20: =+AU20 -> 13983 | AW20: =+AV20 -> 13983 | AX20: =+AW20 -> 13983 | AY20: =+AX20 -> 13983 | ... BA20: =+AZ20 -> 13983 | BD20: =E20 -> 1282 | BE20: =I20 -> 1295 | BF20: =M20 -> 1611 | BG20: =Q20 -> 1655 | BH20: =U20 -> 1654 | BI20: =Y20 -> 5613 | BJ20: =AC20 -> 13736 | BK20: =+AG20 -> 13780 | BL20: =+AK20 -> 13844 | BM20: =+AO20 -> 13980 | BN20: =+AP20 -> 13980 | BO20: =+AW20 -> 13983 | BP20: =+BA20 -> 13983
A21: Acquired intangible assets, net | B21: 77 | C21: 67 | D21: 57 | E21: 44 | F21: 39 | G21: 34 | H21: 27 | I21: 22 | J21: 18 | K21: 75 | L21: 68 | M21: 61 | N21: 55 | O21: 49 | P21: 43 | Q21: 54 | R21: 49 | S21: 41 | T21: 34 | U21: 28 | V21: 63 | W21: 3384 | X21: 3321 | Y21: 3252 | Z21: 3195 | AA21: 7388 | AB21: 7224 | AC21: 7061 | AD21: 6899 | AE21: 6737 | AF21: 6580 | AG21: =6419+64 -> 6483 | AH21: =6261+214 -> 6475 | AI21: 6104 | AJ21: 5950 | AK21: =5820+698 -> 6518 | AL21: =5662+798 -> 6460 | AM21: =5505+934 -> 6439 | AN21: 5397 | AO21: 5302 | AP21: =5136 -> 5136 | AQ21: 4971 | AR21: =+AQ21 -> 4971 | AS21: =+AR21 -> 4971 | AT21: =+AS21 -> 4971 | AU21: =+AT21 -> 4971 | AV21: =+AU21 -> 4971 | AW21: =+AV21 -> 4971 | AX21: =+AW21 -> 4971 | AY21: =+AX21 -> 4971 | ... BA21: =+AZ21 -> 4971 | BD21: =E21 -> 44 | BE21: =I21 -> 22 | BF21: =M21 -> 61 | BG21: =Q21 -> 54 | BH21: =U21 -> 28 | BI21: =Y21 -> 3252 | BJ21: =AC21 -> 7061 | BK21: =+AG21 -> 6483 | BL21: =+AK21 -> 6518 | BM21: =+AO21 -> 5302 | BN21: =+AP21 -> 5136 | BO21: =+AW21 -> 4971 | BP21: =+BA21 -> 4971
A22: Other assets | B22: 326 | C22: 529 | D22: 273 | E22: 251 | F22: 264 | G22: 292 | H22: 324 | I22: 275 | J22: 290 | K22: 294 | L22: 283 | M22: 215 | N22: 213 | O22: 208 | P22: 202 | Q22: 187 | R22: 224 | S22: 247 | T22: 231 | U22: 290 | V22: 293 | W22: =6+291 -> 297 | X22: =7+287 -> 294 | Y22: =8+283 -> 291 | Z22: 297 | AA22: =8+325 -> 333 | AB22: =8+312 -> 320 | AC22: =11+344 -> 355 | AD22: =10+331 -> 341 | AE22: =12+371 -> 383 | AF22: =13+376 -> 389 | AG22: 417 | AH22: 429 | AI22: =383+501 -> 884 | AJ22: =512+495 -> 1007 | AK22: 541 | AL22: 527 | AM22: 669 | AN22: =1062+699 -> 1761 | AO22: =1222+751 -> 1973 | AP22: =1173+828 -> 2001 | AQ22: =1106+825 -> 1931 | AR22: =+AQ22 -> 1931 | AS22: =+AR22 -> 1931 | AT22: =+AS22 -> 1931 | AU22: =+AT22 -> 1931 | AV22: =+AU22 -> 1931 | AW22: =+AV22 -> 1931 | AX22: =+AW22 -> 1931 | AY22: =+AX22 -> 1931 | ... BA22: =+AZ22 -> 1931 | BD22: =E22 -> 251 | BE22: =I22 -> 275 | BF22: =M22 -> 215 | BG22: =Q22 -> 187 | BH22: =U22 -> 290 | BI22: =Y22 -> 291 | BJ22: =AC22 -> 355 | BK22: =+AG22 -> 417 | BL22: =+AK22 -> 541 | BM22: =+AO22 -> 1973 | BN22: =+AP22 -> 2001 | BO22: =+AW22 -> 1931 | BP22: =+BA22 -> 1931
A23: Total assets | B23: =B15+SUM(B17:B22) -> 3833 | C23: =C15+SUM(C17:C22) -> 50002 | D23: =D15+SUM(D17:D22) -> 4940 | E23: =E15+SUM(E17:E22) -> 4250 | F23: =F15+SUM(F17:F22) -> 3933 | G23: =G15+SUM(G17:G22) -> 4373 | H23: =H15+SUM(H17:H22) -> 4969 | I23: =I15+SUM(I17:I22) -> 4068 | ... BA23: =BA15+SUM(BA17:BA22) -> 60022.195 | BD23: =E23 -> 4250 | BE23: =I23 -> 4068 | BF23: =M23 -> 5134 | BG23: =Q23 -> 6283 | BH23: =U23 -> 10931 | BI23: =Y23 -> 15516 | BJ23: =AC23 -> 27734 | BK23: =+AG23 -> 27780 | BL23: =+AK23 -> 32132 | BM23: =+AO23 -> 36958 | BN23: =+AP23 -> 33191 | BO23: =+AW23 -> 50226.621 | BP23: =+BA23 -> 60022.195
AA24: =+AA20-Z20 -> 8119 | BK24: =+AG24 -> 0
A25: Current liabilities
A26: Short-term debt | B26: 0 | C26: 245 | D26: 500 | E26: 512 | F26: 625 | G26: 687 | H26: 50 | I26: 50 | J26: 450 | K26: 690 | L26: 50 | M26: 50 | N26: 50 | O26: 50 | P26: 50 | Q26: 50 | R26: 50 | S26: 38 | T26: 350 | U26: 1338 | V26: 325 | W26: 325 | X26: 0 | Y26: 0 | AA26: 0 | AB26: 0 | AC26: 499 | AD26: 499 | AE26: 501 | AF26: 501 | AG26: 0 | AH26: =+AG26 -> 0 | AI26: =+AH26 -> 0 | AJ26: =+AI26 -> 0 | AK26: 499 | AL26: 499 | AM26: 500 | AN26: 500 | AO26: 0 | AP26: 749 | AQ26: 749 | AR26: =+AQ26 -> 749 | AS26: =+AR26 -> 749 | AT26: =+AS26 -> 749 | AU26: =+AT26 -> 749 | AV26: =+AU26 -> 749 | AW26: =+AV26 -> 749 | AX26: =+AW26 -> 749 | AY26: =+AX26 -> 749 | ... BA26: =+AZ26 -> 749 | BD26: =E26 -> 512 | BE26: =I26 -> 50 | BF26: =M26 -> 50 | BG26: =Q26 -> 50 | BH26: =U26 -> 1338 | BI26: =Y26 -> 0 | BJ26: =AC26 -> 499 | BK26: =+AG26 -> 0 | BL26: =+AK26 -> 499 | BM26: =+AO26 -> 0 | BN26: =+AP26 -> 749 | BO26: =+AW26 -> 749 | BP26: =+BA26 -> 749
A27: Accounts payable | B27: 178 | C27: 286 | D27: 270 | E27: 184 | F27: 165 | G27: 258 | H27: 269 | I27: 157 | J27: 220 | K27: 343 | L27: 325 | M27: 178 | N27: 209 | O27: 400 | P27: 383 | Q27: 274 | R27: 272 | S27: 455 | T27: 384 | U27: 305 | V27: 256 | W27: 486 | X27: 601 | Y27: 623 | Z27: 531 | AA27: 883 | AB27: 900 | AC27: 737 | AD27: 670 | AE27: 811 | AF27: 921 | AG27: 638 | AH27: 630 | AI27: 789 | AJ27: 886 | AK27: 721 | AL27: 652 | AM27: 1038 | AN27: 1002 | AO27: 792 | AP27: 670 | AQ27: 946 | AR27: =AR78*AR$64 -> 1096.9238 | AS27: =AS78*AS$64 -> 879.16496 | AT27: =AT78*AT$64 -> 805.97249 | AU27: =AU78*AU$64 -> 1131.2811 | AV27: =AV78*AV$64 -> 1295.2347 | AW27: =AW78*AW$64 -> 981.0534 | AX27: =AX78*AX$64 -> 908.35549 | AY27: =AY78*AY$64 -> 1285.3003 | ... BA27: =BA78*BA$64 -> 1102.4889 | BD27: =E27 -> 184 | BE27: =I27 -> 157 | BF27: =M27 -> 178 | BG27: =Q27 -> 274 | BH27: =U27 -> 305 | BI27: =Y27 -> 623 | BJ27: =AC27 -> 737 | BK27: =+AG27 -> 638 | BL27: =+AK27 -> 721 | BM27: =+AO27 -> 792 | BN27: =+AP27 -> 670 | BO27: =+AW27 -> 981.0534 | BP27: =+BA27 -> 1102.4889
A28: Accrued compensation and related liabilities | B28: 139 | C28: 179 | D28: 228 | E28: 289 | F28: 136 | G28: 204 | H28: 240 | I28: 300 | J28: 146 | K28: 206 | L28: 286 | M28: 369 | N28: 174 | O28: 221 | P28: 311 | Q28: 385 | R28: 201 | S28: 261 | T28: 348 | U28: 482 | V28: 233 | W28: 326 | X28: 476 | Y28: 530 | Z28: 316 | AA28: 413 | AB28: 543 | AC28: 576 | AD28: 401 | AE28: 502 | AF28: 625 | AG28: 665 | AH28: 439 | AI28: 547 | AJ28: 689 | AK28: 921 | AL28: 413 | AM28: 623 | AN28: 747 | AO28: 858 | AP28: 479 | AQ28: 702 | AR28: =+AR79*AR64 -> 817.76655 | AS28: =+AS79*AS64 -> 952.42871 | AT28: =+AT79*AT64 -> 588.80278 | AU28: =+AU79*AU64 -> 853.16543 | AV28: =+AV79*AV64 -> 989.28506 | AW28: =+AW79*AW64 -> 920.44362 | AX28: =+AX79*AX64 -> 663.59863 | AY28: =+AY79*AY64 -> 969.32034 | ... BA28: =+BA79*BA64 -> 1034.3768 | BD28: =E28 -> 289 | BE28: =I28 -> 300 | BF28: =M28 -> 369 | BG28: =Q28 -> 385 | BH28: =U28 -> 482 | BI28: =Y28 -> 530 | BJ28: =AC28 -> 576 | BK28: =+AG28 -> 665 | BL28: =+AK28 -> 921 | BM28: =+AO28 -> 858 | BN28: =+AP28 -> 479 | BO28: =+AW28 -> 920.44362 | BP28: =+BA28 -> 1034.3768
A29: Deferred revenue | B29: 635 | C29: 961 | D29: 854 | E29: 801 | F29: 739 | G29: 1076 | H29: 955 | I29: 887 | J29: 799 | K29: 1120 | L29: 1040 | M29: 581 | N29: 513 | O29: 639 | P29: 572 | Q29: 619 | R29: 554 | S29: 671 | T29: 632 | U29: 652 | V29: 574 | W29: 752 | X29: 650 | Y29: 684 | Z29: 600 | AA29: 822 | AB29: 741 | AC29: 808 | AD29: 698 | AE29: 852 | AF29: 829 | AG29: 921 | AH29: 763 | AI29: 887 | AJ29: 843 | AK29: 872 | AL29: 892 | AM29: 1025 | AN29: 957 | AO29: 1019 | AP29: 1045 | AQ29: 1141 | AR29: =AR80*AR$64 -> 679.0856 | AS29: =AS80*AS$64 -> 722.94668 | AT29: =AT80*AT$64 -> 1232.3528 | AU29: =AU80*AU$64 -> 1353.5457 | AV29: =AV80*AV$64 -> 744.26142 | AW29: =AW80*AW$64 -> 664.36639 | AX29: =AX80*AX$64 -> 1388.8991 | AY29: =AY80*AY$64 -> 1537.8253 | ... BA29: =BA80*BA$64 -> 746.60213 | BD29: =E29 -> 801 | BE29: =I29 -> 887 | BF29: =M29 -> 581 | BG29: =Q29 -> 619 | BH29: =U29 -> 652 | BI29: =Y29 -> 684 | BJ29: =AC29 -> 808 | BK29: =+AG29 -> 921 | BL29: =+AK29 -> 872 | BM29: =+AO29 -> 1019 | BN29: =+AP29 -> 1045 | BO29: =+AW29 -> 664.36639 | BP29: =+BA29 -> 746.60213
A30: Income taxes payable | B30: 0 | C30: 0 | D30: 442 | E30: 0 | F30: 0 | G30: 0 | H30: 435 | I30: 0 | J30: 0 | K30: 0 | L30: 356 | M30: 3 | N30: 0 | O30: 0 | P30: 338 | Q30: 0 | R30: 0 | S30: 0 | T30: 325 | U30: 0 | V30: 0 | W30: 0 | X30: 218 | Y30: 0 | AA30: 0 | AB30: 198 | AC30: =+Y30 -> 0 | AD30: =+Z30 -> 0 | AE30: =+AA30 -> 0 | AF30: 653 | AG30: =+AC30 -> 0 | AH30: 133 | AI30: 1 | AJ30: 437 | AK30: 8 | AL30: 21 | AM30: 0 | AN30: 614 | AO30: 0 | AP30: 658 | AQ30: 82 | AR30: =+AQ30 -> 82 | AS30: =+AR30 -> 82 | AT30: =+AS30 -> 82 | AU30: =+AT30 -> 82 | AV30: =+AU30 -> 82 | AW30: =+AV30 -> 82 | AX30: =+AW30 -> 82 | AY30: =+AX30 -> 82 | ... BA30: =+AZ30 -> 82 | BD30: =E30 -> 0 | BE30: =I30 -> 0 | BF30: =M30 -> 3 | BG30: =Q30 -> 0 | BH30: =U30 -> 0 | BI30: =Y30 -> 0 | BJ30: =AC30 -> 0 | BK30: =+AG30 -> 0 | BL30: =+AK30 -> 8 | BM30: =+AO30 -> 0 | BN30: =+AP30 -> 658 | BO30: =+AW30 -> 82 | BP30: =+BA30 -> 82
A31: Borrowings under credit facility | B31: 350 | C31: 0 | D31: 0 | E31: 0 | F31: 0 | G31: 0 | H31: 0 | I31: 0 | J31: 0 | K31: 0 | L31: 0 | N31: 0 | O31: 0 | P31: 0 | Q31: 0 | R31: 0 | S31: 0 | T31: 0 | U31: 0 | V31: 0 | W31: 0 | X31: =+W31 -> 0 | Y31: =+X31 -> 0 | AA31: =+Z31 -> 0 | AB31: 0 | AC31: =+AB31 -> 0 | AD31: =+AC31 -> 0 | AE31: =+AD31 -> 0 | AF31: =+AE31 -> 0 | AG31: =+AF31 -> 0 | AH31: =+AG31 -> 0 | AI31: =+AH31 -> 0 | AJ31: =+AI31 -> 0 | ... AM31: =+AL31 -> 0 | AN31: 0 | AO31: =+AN31 -> 0 | AP31: =+AO31 -> 0 | AQ31: =+AP31 -> 0 | AR31: =+AQ31 -> 0 | AS31: =+AR31 -> 0 | AT31: =+AS31 -> 0 | AU31: =+AT31 -> 0 | AV31: =+AU31 -> 0 | ... BA31: =+AZ31 -> 0 | BD31: =E31 -> 0 | BE31: =I31 -> 0 | BF31: =M31 -> 0 | BG31: =Q31 -> 0 | BH31: =U31 -> 0 | BI31: =Y31 -> 0 | BJ31: =AC31 -> 0 | BK31: =+AG31 -> 0 | BL31: =+AK31 -> 0 | BM31: =+AO31 -> 0 | BN31: =+AP31 -> 0 | BO31: =+AW31 -> 0 | BP31: =+BA31 -> 0
A32: Other current liabilities | B32: 238 | C32: 305 | D32: 199 | E32: 161 | F32: 190 | G32: 254 | H32: 222 | I32: 178 | J32: 183 | K32: 251 | L32: 227 | M32: 195 | N32: 202 | O32: 257 | P32: 254 | Q32: 202 | R32: 267 | S32: 318 | T32: 285 | U32: 297 | V32: 280 | W32: 362 | X32: 419 | Y32: 361 | Z32: 385 | AA32: 475 | AB32: 670 | AC32: 579 | AD32: 589 | AE32: 820 | AF32: 498 | AG32: =698+448 -> 1146 | AH32: 506 | AI32: 602 | AJ32: 586 | AK32: 549 | AL32: 536 | AM32: 659 | AN32: 613 | AO32: 625 | AP32: 0 | AQ32: 810 | AR32: =+AQ32 -> 810 | AS32: =+AR32 -> 810 | AT32: =+AS32 -> 810 | AU32: =+AT32 -> 810 | AV32: =+AU32 -> 810 | AW32: =+AV32 -> 810 | AX32: =+AW32 -> 810 | AY32: =+AX32 -> 810 | ... BA32: =+AZ32 -> 810 | BD32: =E32 -> 161 | BE32: =I32 -> 178 | BF32: =M32 -> 195 | BG32: =Q32 -> 202 | BH32: =U32 -> 297 | BI32: =Y32 -> 361 | BJ32: =AC32 -> 579 | BK32: =+AG32 -> 1146 | BL32: =+AK32 -> 549 | BM32: =+AO32 -> 625 | BN32: =+AP32 -> 0 | BO32: =+AW32 -> 810 | BP32: =+BA32 -> 810
A33: Current liabilities before customer fund deposits | B33: =SUM(B26:B32) -> 1540 | C33: =SUM(C26:C32) -> 1976 | D33: =SUM(D26:D32) -> 2493 | E33: =SUM(E26:E32) -> 1947 | F33: =SUM(F26:F32) -> 1855 | G33: =SUM(G26:G32) -> 2479 | H33: =SUM(H26:H32) -> 2171 | I33: =SUM(I26:I32) -> 1572 | ... BA33: =SUM(BA26:BA32) -> 4524.4678 | BD33: =E33 -> 1947 | BE33: =I33 -> 1572 | BF33: =M33 -> 1376 | BG33: =Q33 -> 1530 | BH33: =U33 -> 3074 | BI33: =Y33 -> 2198 | BJ33: =AC33 -> 3199 | BK33: =+AG33 -> 3370 | BL33: =+AK33 -> 3570 | BM33: =+AO33 -> 3294 | BN33: =+AP33 -> 3601 | BO33: =+AW33 -> 4206.8634 | BP33: =+BA33 -> 4524.4678
A34: Customer fund deposits | B34: 347 | C34: 373 | D34: 372 | E34: 304 | F34: 326 | G34: 324 | H34: 323 | I34: 372 | J34: 319 | K34: 422 | L34: 419 | M34: 367 | N34: 438 | O34: 434 | P34: 383 | Q34: 436 | R34: 413 | S34: 461 | T34: 389 | U34: 455 | V34: 484 | W34: 426 | X34: 348 | Y34: 457 | Z34: 306 | AA34: 375 | AB34: =+AB14 -> 539 | AC34: =+AC14 -> 431 | AD34: =+AD14 -> 468 | AE34: 376 | AF34: =+AF14 -> 388 | AG34: =+AG14 -> 420 | AH34: =+AH14 -> 2525 | AI34: =+AI14 -> 3390 | AJ34: =+AJ14 -> 2722 | AK34: =+AK14 -> 3921 | AL34: =+AL14 -> 5606 | AM34: =+AM14 -> 3334 | ... BA34: =+BA14 -> 9850.0143 | BD34: =E34 -> 304 | BE34: =I34 -> 372 | BF34: =M34 -> 367 | BG34: =Q34 -> 436 | BH34: =U34 -> 455 | BI34: =Y34 -> 457 | BJ34: =AC34 -> 431 | BK34: =+AG34 -> 420 | BL34: =+AK34 -> 3921 | BM34: =+AO34 -> 7076 | BN34: =+AP34 -> 3918 | BO34: =+AW34 -> 8765.068 | BP34: =+BA34 -> 9850.0143
A35: Total Current Liabilities | B35: =+SUM(B33:B34) -> 1887 | C35: =+SUM(C33:C34) -> 2349 | D35: =+SUM(D33:D34) -> 2865 | E35: =+SUM(E33:E34) -> 2251 | F35: =+SUM(F33:F34) -> 2181 | G35: =+SUM(G33:G34) -> 2803 | H35: =+SUM(H33:H34) -> 2494 | I35: =+SUM(I33:I34) -> 1944 | ... BA35: =+SUM(BA33:BA34) -> 14374.482 | BD35: =E35 -> 2251 | BE35: =I35 -> 1944 | BF35: =M35 -> 1743 | BG35: =Q35 -> 1966 | BH35: =U35 -> 3529 | BI35: =Y35 -> 2655 | BJ35: =AC35 -> 3630 | BK35: =+AG35 -> 3790 | BL35: =+AK35 -> 7491 | BM35: =+AO35 -> 10370 | BN35: =+AP35 -> 7519 | BO35: =+AW35 -> 12971.931 | BP35: =+BA35 -> 14374.482
A37: Long term liabilities
A38: Long-term debt | B38: 500 | C38: 1000 | D38: 500 | E38: 488 | F38: 475 | G38: 463 | H38: 450 | I38: 438 | J38: 425 | K38: 413 | L38: 400 | M38: 388 | N38: 375 | O38: 363 | P38: 398 | Q38: 386 | R38: 373 | S38: 373 | T38: 48 | U38: 2031 | V38: 2032 | W38: 2033 | X38: 2033 | Y38: 2034 | Z38: 2037 | AA38: 6732 | AB38: 6853 | AC38: 6415 | AD38: 6486 | AE38: 6576 | AF38: 6109 | AG38: 6120 | AH38: 5879 | AI38: 5950 | AJ38: 5952 | AK38: 5539 | AL38: 5625 | AM38: 5760 | AN38: 5906 | AO38: 5973 | AP38: 5391 | AQ38: 5411 | AR38: =+AQ38 -> 5411 | AS38: =+AR38 -> 5411 | AT38: =+AS38 -> 5411 | AU38: =+AT38 -> 5411 | AV38: =+AU38 -> 5411 | AW38: =+AV38 -> 5411 | AX38: =+AW38 -> 5411 | AY38: =+AX38 -> 5411 | ... BA38: =+AZ38 -> 5411 | BD38: =E38 -> 488 | BE38: =I38 -> 438 | BF38: =M38 -> 388 | BG38: =Q38 -> 386 | BH38: =U38 -> 2031 | BI38: =Y38 -> 2034 | BJ38: =AC38 -> 6415 | BK38: =+AG38 -> 6120 | BL38: =+AK38 -> 5539 | BM38: =+AO38 -> 5973 | BN38: =+AP38 -> 5391 | BO38: =+AW38 -> 5411 | BP38: =+BA38 -> 5411
A39: Long-term deferred income tax liabilities | B39: 0 | C39: 0 | D39: 0 | E39: 0 | F39: 0 | G39: 0 | H39: 0 | I39: 0 | J39: 0 | K39: 0 | L39: 0 | M39: 68 | N39: 65 | O39: 51 | P39: 13 | Q39: 37 | R39: 68 | S39: 55 | T39: 22 | U39: 2 | V39: 0 | W39: 580 | X39: 637 | Y39: 525 | Z39: 508 | AA39: 506 | AB39: 608 | AC39: 619 | AD39: 588 | AE39: 320 | AF39: 190 | AG39: 4 | AH39: 3 | AI39: 3 | AJ39: 3 | AK39: 0 | AL39: 0 | AM39: =+AL39 -> 0 | AN39: 0 | AO39: 0 | AP39: 0 | AQ39: 0 | AR39: =+AQ39 -> 0 | AS39: =+AR39 -> 0 | AT39: =+AS39 -> 0 | AU39: =+AT39 -> 0 | AV39: =+AU39 -> 0 | AW39: =+AV39 -> 0 | AX39: =+AW39 -> 0 | AY39: =+AX39 -> 0 | ... BA39: =+AZ39 -> 0 | BD39: =E39 -> 0 | BE39: =I39 -> 0 | BF39: =M39 -> 68 | BG39: =Q39 -> 37 | BH39: =U39 -> 2 | BI39: =Y39 -> 525 | BJ39: =AC39 -> 619 | BK39: =+AG39 -> 4 | BL39: =+AK39 -> 0 | BM39: =+AO39 -> 0 | BN39: =+AP39 -> 0 | BO39: =+AW39 -> 0 | BP39: =+BA39 -> 0
A40: Operating lease liabilities | B40: 0 | C40: 0 | D40: 0 | E40: 0 | F40: 0 | G40: 0 | H40: 0 | I40: 0 | J40: 0 | K40: 0 | L40: 0 | M40: 0 | N40: 0 | O40: 0 | P40: 0 | Q40: 0 | R40: 297 | S40: 286 | T40: 215 | U40: 221 | V40: 228 | W40: 391 | X40: 365 | Y40: 380 | Z40: 403 | AA40: 429 | AB40: 415 | AC40: 542 | AD40: 530 | AE40: 514 | AF40: 499 | AG40: 480 | AH40: 474 | AI40: 473 | AJ40: 468 | AK40: 458 | AL40: 592 | AM40: 573 | AN40: 614 | AO40: 597 | AP40: 643 | AQ40: 646 | AR40: =+AQ40 -> 646 | AS40: =+AR40 -> 646 | AT40: =+AS40 -> 646 | AU40: =+AT40 -> 646 | AV40: =+AU40 -> 646 | AW40: =+AV40 -> 646 | AX40: =+AW40 -> 646 | AY40: =+AX40 -> 646 | ... BA40: =+AZ40 -> 646 | BD40: =E40 -> 0 | BE40: =I40 -> 0 | BF40: =M40 -> 0 | BG40: =Q40 -> 0 | BH40: =U40 -> 221 | BI40: =Y40 -> 380 | BJ40: =AC40 -> 542 | BK40: =+AG40 -> 480 | BL40: =+AK40 -> 458 | BM40: =+AO40 -> 597 | BN40: =+AP40 -> 643 | BO40: =+AW40 -> 646 | BP40: =+BA40 -> 646
A41: Other long-term liabilities | B41: 395 | C41: 359 | D41: 327 | E41: 350 | F41: 341 | G41: 322 | H41: 328 | I41: 332 | J41: 319 | K41: 296 | L41: 320 | M41: 119 | N41: 120 | O41: 124 | P41: 145 | Q41: 145 | R41: 55 | S41: 56 | T41: 26 | U41: 42 | V41: 50 | W41: 49 | X41: 56 | Y41: 53 | Z41: 51 | AA41: 73 | AB41: 86 | AC41: 87 | AD41: 89 | AE41: 88 | AF41: 116 | AG41: 117 | AH41: 144 | AI41: 138 | AJ41: 217 | AK41: 208 | AL41: 221 | AM41: 221 | AN41: 294 | AO41: 308 | AP41: 316 | AQ41: 326 | AR41: =+AQ41 -> 326 | AS41: =+AR41 -> 326 | AT41: =+AS41 -> 326 | AU41: =+AT41 -> 326 | AV41: =+AU41 -> 326 | AW41: =+AV41 -> 326 | AX41: =+AW41 -> 326 | AY41: =+AX41 -> 326 | ... BA41: =+AZ41 -> 326 | BD41: =E41 -> 350 | BE41: =I41 -> 332 | BF41: =M41 -> 119 | BG41: =Q41 -> 145 | BH41: =U41 -> 42 | BI41: =Y41 -> 53 | BJ41: =AC41 -> 87 | BK41: =+AG41 -> 117 | BL41: =+AK41 -> 208 | BM41: =+AO41 -> 308 | BN41: =+AP41 -> 316 | BO41: =+AW41 -> 326 | BP41: =+BA41 -> 326
A42: Total liabilities | B42: =SUM(B35,B38:B41) -> 2782 | C42: =SUM(C35,C38:C41) -> 3708 | D42: =SUM(D35,D38:D41) -> 3692 | E42: =SUM(E35,E38:E41) -> 3089 | F42: =SUM(F35,F38:F41) -> 2997 | G42: =SUM(G35,G38:G41) -> 3588 | H42: =SUM(H35,H38:H41) -> 3272 | I42: =SUM(I35,I38:I41) -> 2714 | ... BA42: =SUM(BA35,BA38:BA41) -> 20757.482 | BD42: =E42 -> 3089 | BE42: =I42 -> 2714 | BF42: =M42 -> 2318 | BG42: =Q42 -> 2534 | BH42: =U42 -> 5825 | BI42: =Y42 -> 5647 | BJ42: =AC42 -> 11293 | BK42: =+AG42 -> 10511 | BL42: =+AK42 -> 13696 | BM42: =+AO42 -> 17248 | BN42: =+AP42 -> 13869 | BO42: =+AW42 -> 19354.931 | BP42: =+BA42 -> 20757.482
A44: Stockholders' equity and minority interest
A45: Preferred stock | B45: 0 | C45: 0 | D45: 0 | E45: 0 | F45: 0 | G45: 0 | H45: 0 | I45: 0 | J45: 0 | K45: 0 | L45: 0 | M45: 0 | N45: 0 | O45: 0 | P45: 0 | Q45: 0 | R45: 0 | S45: 0 | T45: 0 | U45: 0 | V45: 0 | W45: 0 | X45: =+W45 -> 0 | Y45: =+X45 -> 0 | Z45: =+Y45 -> 0 | AA45: =+Z45 -> 0 | AB45: =+AA45 -> 0 | AC45: =+AB45 -> 0 | AD45: 0 | AE45: 0 | AF45: 0 | AG45: 0 | AH45: =+AG45 -> 0 | AI45: =+AH45 -> 0 | AJ45: =+AI45 -> 0 | AK45: =+AJ45 -> 0 | AL45: =+AK45 -> 0 | AM45: 0 | AN45: 0 | AO45: =+AN45 -> 0 | AP45: =+AO45 -> 0 | AQ45: =+AP45 -> 0 | AR45: =+AQ45 -> 0 | AS45: =+AR45 -> 0 | AT45: =+AS45 -> 0 | AU45: =+AT45 -> 0 | AV45: =+AU45 -> 0 | ... BA45: =+AZ45 -> 0 | BD45: =E45 -> 0 | BE45: =I45 -> 0 | BF45: =M45 -> 0 | BG45: =Q45 -> 0 | BH45: =U45 -> 0 | BI45: =Y45 -> 0 | BJ45: =AC45 -> 0 | BK45: =+AG45 -> 0 | BL45: =+AK45 -> 0 | BM45: =+AO45 -> 0 | BN45: =+AP45 -> 0 | BO45: =+AW45 -> 0 | BP45: =+BA45 -> 0
A46: Common stock and additional paid-in capital | B46: 4114 | C46: 4226 | D46: 4334 | E46: 4445 | F46: 4540 | G46: 4660 | H46: 4787 | I46: 4857 | J46: 4999 | K46: 5151 | L46: 5289 | M46: 5338 | N46: 5501 | O46: 5623 | P46: 5782 | Q46: 5775 | R46: 5881 | S46: 6014 | T46: 6132 | U46: 6182 | V46: 6283 | W46: 10212 | X46: 10382 | Y46: =+X46 -> 10382 | Z46: =+Y46 -> 10382 | AA46: =+Z46 -> 10382 | AB46: =+AA46 -> 10382 | AC46: 10382 | AD46: =+AC46-740 -> 9642 | AE46: =+AD46 -> 9642 | AF46: =+AE46 -> 9642 | AG46: 9642 | AH46: =+AG46 -> 9642 | AI46: =+AH46 -> 9642 | AJ46: =+AI46 -> 9642 | AK46: =+AJ46 -> 9642 | AL46: =+AK46 -> 9642 | AM46: =+AL46 -> 9642 | AN46: 21380 | AO46: =+AN46 -> 21380 | AP46: =+AO46 -> 21380 | AQ46: =+AP46 -> 21380 | AR46: =+AQ46 -> 21380 | AS46: =+AR46 -> 21380 | AT46: =+AS46 -> 21380 | AU46: =+AT46 -> 21380 | AV46: =+AU46 -> 21380 | ... BA46: =+AZ46 -> 21380 | BD46: =E46 -> 4445 | BE46: =I46 -> 4857 | BF46: =M46 -> 5338 | BG46: =Q46 -> 5775 | BH46: =U46 -> 6182 | BI46: =Y46 -> 10382 | BJ46: =AC46 -> 10382 | BK46: =+AG46 -> 9642 | BL46: =+AK46 -> 9642 | BM46: =+AO46 -> 21380 | BN46: =+AP46 -> 21380 | BO46: =+AW46 -> 21380 | BP46: =+BA46 -> 21380
A47: Treasury stock, at cost | B47: -8945 | C47: -9400 | D47: -9865 | E47: -9939 | F47: -10131 | G47: -10329 | H47: -10417 | I47: -10778 | J47: -10948 | K47: -11031 | L47: -11050 | M47: -11050 | N47: -11151 | O47: -11328 | P47: -11463 | Q47: -11611 | R47: -11750 | S47: -11889 | T47: -11929 | U47: -11929 | V47: -11929 | W47: -12104 | X47: -12484 | Y47: =+X47 -> -12484 | Z47: =+Y47 -> -12484 | AA47: =+Z47 -> -12484 | AB47: =+AA47 -> -12484 | AC47: -12484 | AD47: =+AC47 -> -12484 | AE47: =+AD47 -> -12484 | AF47: =+AE47 -> -12484 | AG47: -12484 | AH47: =+AG47 -> -12484 | AI47: =+AH47 -> -12484 | AJ47: =+AI47 -> -12484 | AK47: =+AJ47 -> -12484 | AL47: =+AK47 -> -12484 | AM47: =+AL47 -> -12484 | AN47: -20795 | AO47: =+AN47 -> -20795 | AP47: =+AO47 -> -20795 | AQ47: =+AP47 -> -20795 | AR47: =+AQ47 -> -20795 | AS47: =+AR47 -> -20795 | AT47: =+AS47 -> -20795 | AU47: =+AT47 -> -20795 | AV47: =+AU47 -> -20795 | ... BA47: =+AZ47 -> -20795 | BD47: =E47 -> -9939 | BE47: =I47 -> -10778 | BF47: =M47 -> -11050 | BG47: =Q47 -> -11611 | BH47: =U47 -> -11929 | BI47: =Y47 -> -12484 | BJ47: =AC47 -> -12484 | BK47: =+AG47 -> -12484 | BL47: =+AK47 -> -12484 | BM47: =+AO47 -> -20795 | BN47: =+AP47 -> -20795 | BO47: =+AW47 -> -20795 | BP47: =+BA47 -> -20795
A48: Accumulated other comprehensive loss | B48: -32 | C48: -42 | D48: -26 | E48: -32 | F48: -37 | G48: -34 | H48: -36 | I48: -22 | J48: -28 | K48: -20 | L48: -30 | M48: -36 | N48: -40 | O48: -36 | P48: -38 | Q48: -36 | R48: -35 | S48: -35 | T48: -44 | U48: -32 | V48: -35 | W48: -23 | X48: -24 | Y48: =+X48 -> -24 | Z48: =+Y48 -> -24 | AA48: =+Z48 -> -24 | AB48: =+AA48 -> -24 | AC48: -24 | AD48: =+AC48 -> -24 | AE48: =+AD48 -> -24 | AF48: =+AE48 -> -24 | AG48: -24 | AH48: =+AG48 -> -24 | AI48: =+AH48 -> -24 | AJ48: =+AI48 -> -24 | AK48: =+AJ48 -> -24 | AL48: =+AK48 -> -24 | AM48: =+AL48 -> -24 | AN48: -46 | AO48: =+AN48 -> -46 | AP48: =+AO48 -> -46 | AQ48: =+AP48 -> -46 | AR48: =+AQ48 -> -46 | AS48: =+AR48 -> -46 | AT48: =+AS48 -> -46 | AU48: =+AT48 -> -46 | AV48: =+AU48 -> -46 | ... BA48: =+AZ48 -> -46 | BD48: =E48 -> -32 | BE48: =I48 -> -22 | BF48: =M48 -> -36 | BG48: =Q48 -> -36 | BH48: =U48 -> -32 | BI48: =Y48 -> -24 | BJ48: =AC48 -> -24 | BK48: =+AG48 -> -24 | BL48: =+AK48 -> -24 | BM48: =+AO48 -> -46 | BN48: =+AP48 -> -46 | BO48: =+AW48 -> -46 | BP48: =+BA48 -> -46
A49: Retained earnings | B49: 5914 | C49: 5857 | D49: 6805 | E49: 6687 | F49: 6564 | G49: 6488 | H49: 7363 | I49: 7297 | J49: 7180 | K49: 7057 | L49: 8155 | M49: 8564 | N49: 8472 | O49: 8537 | P49: 9789 | Q49: 9621 | R49: 9537 | S49: 9637 | T49: 10581 | U49: 10885 | V49: 10926 | W49: 10783 | X49: 12081 | Y49: =9869-SUM(Y46:Y48) -> 11995 | Z49: =9733-SUM(Z46:Z48) -> 11859 | AA49: =+Z49+'Cash Flow'!AA11+'Cash Flow'!AA53+'Cash Flow'!AA6 -> 12100 | AB49: =16961-AB48-AB47-AB46 -> 19087 | AC49: 19306.635 | AD49: =+AD50-AD48-AD47-AD46 -> 18933 | AE49: =+AE50-AE48-AE47-AE46 -> 18708 | AF49: =+AF50-AF48-AF47-AF46 -> 20458 | AG49: =+AG23-AG42-AG45-AG46-AG47--AG48 -> 20087 | AH49: =+AH23-AH42-SUM(AH46:AH48) -> 19858 | AI49: =16908-SUM(AI45:AI48) -> 19774 | AJ49: =18757-SUM(AJ45:AJ48) -> 21623 | AK49: =18436-SUM(AK45:AK48) -> 21302 | AL49: =18136-SUM(AL45:AL48) -> 21002 | AM49: =+AM23-AM45-AM46-AM47-AM48-AM42 -> 20815 | AN49: 19586 | AO49: =19710-SUM(AO45:AO48) -> 19171 | AP49: =19322-SUM(AP45:AP48) -> 18783 | AQ49: =19055-SUM(AQ45:AQ48) -> 18516 | AR49: =+AR23-AR45-AR46-AR47-AR48-AR42 -> 22017.988 | AS49: =+AS23-AS45-AS46-AS47-AS48-AS42 -> 22927.025 | AT49: =+AT23-AT45-AT46-AT47-AT48-AT42 -> 24035.118 | AU49: =+AU23-AU45-AU46-AU47-AU48-AU42 -> 25399.127 | AV49: =+AV23-AV45-AV46-AV47-AV48-AV42 -> 29305.411 | AW49: =+AW23-AW45-AW46-AW47-AW48-AW42 -> 30332.69 | AX49: =+AX23-AX45-AX46-AX47-AX48-AX42 -> 31606.683 | AY49: =+AY23-AY45-AY46-AY47-AY48-AY42 -> 33182.543 | ... BA49: =+BA23-BA45-BA46-BA47-BA48-BA42 -> 38725.713 | BD49: =E49 -> 6687 | BE49: =I49 -> 7297 | BF49: =M49 -> 8564 | BG49: =Q49 -> 9621 | BH49: =U49 -> 10885 | BI49: =Y49 -> 11995 | BJ49: =AC49 -> 19306.635 | BK49: =+AG49 -> 20087 | BL49: =+AK49 -> 21302 | BM49: =+AO49 -> 19171 | BN49: =+AP49 -> 18783 | BO49: =+AW49 -> 30332.69 | BP49: =+BA49 -> 38725.713
A50: Total stockholders' equity | B50: =SUM(B45:B49) -> 1051 | C50: =SUM(C45:C49) -> 641 | D50: =SUM(D45:D49) -> 1248 | E50: =SUM(E45:E49) -> 1161 | F50: =SUM(F45:F49) -> 936 | G50: =SUM(G45:G49) -> 785 | H50: =SUM(H45:H49) -> 1697 | I50: =SUM(I45:I49) -> 1354 | ... Z50: =SUM(Z45:Z49) -> 9733 | AA50: 15595 | AB50: =SUM(AB45:AB49) -> 16961 | AC50: 16441 | AD50: 16067 | AE50: 15842 | AF50: 17592 | AG50: 17269 | AH50: 16992 | AI50: =SUM(AI45:AI49) -> 16908 | AJ50: =SUM(AJ45:AJ49) -> 18757 | AK50: =SUM(AK45:AK49) -> 18436 | AL50: =SUM(AL45:AL49) -> 18136 | AM50: =SUM(AM45:AM49) -> 17949 | AN50: =SUM(AN45:AN49) -> 20125 | AO50: =SUM(AO45:AO49) -> 19710 | AP50: =SUM(AP45:AP49) -> 19322 | ... BA50: =SUM(BA45:BA49) -> 39264.713 | BD50: =E50 -> 1161 | BE50: =I50 -> 1354 | BF50: =M50 -> 2816 | BG50: =Q50 -> 3749 | BH50: =U50 -> 5106 | BI50: =Y50 -> 9869 | BJ50: =AC50 -> 16441 | BK50: =+AG50 -> 17269 | BL50: =+AK50 -> 18436 | BM50: =+AO50 -> 19710 | BN50: =+AP50 -> 19322 | BO50: =+AW50 -> 30871.69 | BP50: =+BA50 -> 39264.713
A51: Total liabilities and shareholders' equity | B51: =B50+B42 -> 3833 | C51: =C50+C42 -> 4349 | D51: =D50+D42 -> 4940 | E51: =E50+E42 -> 4250 | F51: =F50+F42 -> 3933 | G51: =G50+G42 -> 4373 | H51: =H50+H42 -> 4969 | I51: =I50+I42 -> 4068 | ... BA51: =BA50+BA42 -> 60022.195 | BD51: =E51 -> 4250 | BE51: =I51 -> 4068 | BF51: =M51 -> 5134 | BG51: =Q51 -> 6283 | BH51: =U51 -> 10931 | BI51: =Y51 -> 15516 | BJ51: =AC51 -> 27734 | BK51: =+AG51 -> 27780 | BL51: =+AK51 -> 32132 | BM51: =+AO51 -> 36958 | BN51: =+AP51 -> 33191 | BO51: =+AW51 -> 50226.621 | BP51: =+BA51 -> 60022.195
A53: Net Cash | B53: =+B6+B7-B26-B38 -> -26 | C53: =+C6+C7-C26-C38 -> -911 | D53: =+D6+D7-D26-D38 -> 613 | E53: =+E6+E7-E26-E38 -> 80 | F53: =+F6+F7-F26-F38 -> -495 | G53: =+G6+G7-G26-G38 -> -513 | H53: =+H6+H7-H26-H38 -> 1093 | I53: =+I6+I7-I26-I38 -> 289 | ... BA53: =+BA6+BA7-BA26-BA38 -> 19541.531 | BD53: =E53 -> 80 | BE53: =I53 -> 289 | BF53: =M53 -> 1278 | BG53: =Q53 -> 2304 | BH53: =U53 -> 3681 | BI53: =Y53 -> 1836 | BJ53: =AC53 -> -3633 | BK53: =+AG53 -> -2458 | BL53: =+AK53 -> -1964 | BM53: =+AO53 -> -1421 | BN53: =+AP53 -> -2444 | BO53: =+AW53 -> 10563.104 | BP53: =+BA53 -> 19541.531
A54: Y/Y Growth | B54: =IF(ISERROR(B53/#REF!-1),"NA",B53/#REF!-1) -> NA | C54: =IF(ISERROR(C53/#REF!-1),"NA",C53/#REF!-1) -> NA | D54: =IF(ISERROR(D53/#REF!-1),"NA",D53/#REF!-1) -> NA | E54: =IF(ISERROR(E53/#REF!-1),"NA",E53/#REF!-1) -> NA | F54: =IF(ISERROR(F53/B53-1),"NA",F53/B53-1) -> 18.038462 | G54: =IF(ISERROR(G53/C53-1),"NA",G53/C53-1) -> -0.43688255 | H54: =IF(ISERROR(H53/D53-1),"NA",H53/D53-1) -> 0.78303426 | I54: =IF(ISERROR(I53/E53-1),"NA",I53/E53-1) -> 2.6125 | J54: =IF(ISERROR(J53/F53-1),"NA",J53/F53-1) -> -0.8020202 | K54: =IF(ISERROR(K53/G53-1),"NA",K53/G53-1) -> -0.26510721 | L54: =IF(ISERROR(L53/H53-1),"NA",L53/H53-1) -> 0.35956084 | M54: =IF(ISERROR(M53/I53-1),"NA",M53/I53-1) -> 3.4221453 | ... BA54: =IF(ISERROR(BA53/AW53-1),"NA",BA53/AW53-1) -> 0.84997996 | BD54: =E54 -> NA | BE54: =I54 -> 2.6125 | BF54: =M54 -> 3.4221453 | BG54: =Q54 -> 0.8028169 | BH54: =U54 -> 0.59765625 | BI54: =Y54 -> -0.50122249 | BJ54: =AC54 -> -2.9787582 | BK54: =+AG54 -> -0.32342417 | BL54: =+AK54 -> -0.2009764 | BM54: =+AO54 -> -0.27647658 | BN54: =+AP54 -> -0.11641359 | BO54: =+AW54 -> 3.032946 | BP54: =+BA54 -> 0.84997996
A55: Q/Q Growth | B55: =IF(ISERROR(B53/A53-1),"NA",B53/A53-1) -> NA | C55: =IF(ISERROR(C53/B53-1),"NA",C53/B53-1) -> 34.038462 | D55: =IF(ISERROR(D53/C53-1),"NA",D53/C53-1) -> -1.6728869 | E55: =IF(ISERROR(E53/D53-1),"NA",E53/D53-1) -> -0.86949429 | F55: =IF(ISERROR(F53/E53-1),"NA",F53/E53-1) -> -7.1875 | G55: =IF(ISERROR(G53/F53-1),"NA",G53/F53-1) -> 0.036363636 | H55: =IF(ISERROR(H53/G53-1),"NA",H53/G53-1) -> -3.1306043 | I55: =IF(ISERROR(I53/H53-1),"NA",I53/H53-1) -> -0.73559012 | ... BA55: =IF(ISERROR(BA53/AZ53-1),"NA",BA53/AZ53-1) -> 0.064345799 | BD55: NA | BE55: NA | BF55: NA | BG55: NA | BH55: NA | BI55: NA | BJ55: NA | BK55: NA | BL55: NA | BM55: NA | BN55: NA | BO55: NA | BP55: NA
A56: Net cash per share | B56: =+B53/'Income Statement'!B37 -> -0.095588235 | C56: =+C53/'Income Statement'!C37 -> -3.424812 | D56: =+D53/'Income Statement'!D37 -> 2.3576923 | E56: =+E53/'Income Statement'!E37 -> 0.30769231 | F56: =+F53/'Income Statement'!F37 -> -1.9186047 | G56: =+G53/'Income Statement'!G37 -> -1.9730769 | H56: =+H53/'Income Statement'!H37 -> 4.2038462 | I56: =+I53/'Income Statement'!I37 -> 1.1115385 | ... BA56: =+BA53/'Income Statement'!BA37 -> 69.791182 | BD56: =E56 -> 0.30769231 | BE56: =I56 -> 1.1115385 | BF56: =M56 -> 4.9534884 | BG56: =Q56 -> 8.8615385 | BH56: =U56 -> 13.943182 | BI56: =Y56 -> 6.6281588 | BJ56: =AC56 -> -12.882979 | BK56: =+AG56 -> -8.6812178 | BL56: =+AK56 -> -6.9399293 | BM56: =+AO56 -> -5.0390071 | BN56: =+AP56 -> -8.6975089 | BO56: =+AW56 -> 37.591118 | BP56: =+BA56 -> 69.791182
A58: Source: Company data, Wells Fargo Securities, LLC estimates
A60: Check | B60: =IF((B23=B51)*AND(B23>0),"—","X") -> — | C60: =IF((C23=C51)*AND(C23>0),"—","X") -> X | D60: =IF((D23=D51)*AND(D23>0),"—","X") -> — | E60: =IF((E23=E51)*AND(E23>0),"—","X") -> — | F60: =IF((F23=F51)*AND(F23>0),"—","X") -> — | G60: =IF((G23=G51)*AND(G23>0),"—","X") -> — | H60: =IF((H23=H51)*AND(H23>0),"—","X") -> — | I60: =IF((I23=I51)*AND(I23>0),"—","X") -> — | ... BA60: =IF((BA23=BA51)*AND(BA23>0),"—","X") -> X | BD60: =IF((BD23=BD51)*AND(BD23>0),"—","X") -> — | BE60: =IF((BE23=BE51)*AND(BE23>0),"—","X") -> — | BF60: =IF((BF23=BF51)*AND(BF23>0),"—","X") -> — | BG60: =IF((BG23=BG51)*AND(BG23>0),"—","X") -> — | BH60: =IF((BH23=BH51)*AND(BH23>0),"—","X") -> — | BI60: =IF((BI23=BI51)*AND(BI23>0),"—","X") -> — | BJ60: =IF((BJ23=BJ51)*AND(BJ23>0),"—","X") -> — | BK60: =IF((BK23=BK51)*AND(BK23>0),"—","X") -> — | ... BP60: =IF((BP23=BP51)*AND(BP23>0),"—","X") -> X
B61: =IF(B60="X",B23-B51,"") | C61: =IF(C60="X",C23-C51,"") -> 45653 | D61: =IF(D60="X",D23-D51,"") | E61: =IF(E60="X",E23-E51,"") | F61: =IF(F60="X",F23-F51,"") | G61: =IF(G60="X",G23-G51,"") | H61: =IF(H60="X",H23-H51,"") | I61: =IF(I60="X",I23-I51,"") | ... BA61: =IF(BA60="X",BA23-BA51,"") -> -7.2759576e-12 | BC61: =IF(BC60="X",BC23-BC51,"") | BD61: =IF(BD60="X",BD23-BD51,"") | BE61: =IF(BE60="X",BE23-BE51,"") | BF61: =IF(BF60="X",BF23-BF51,"") | BG61: =IF(BG60="X",BG23-BG51,"") | BH61: =IF(BH60="X",BH23-BH51,"") | BI61: =IF(BI60="X",BI23-BI51,"") | BJ61: =IF(BJ60="X",BJ23-BJ51,"") | ... BP61: =IF(BP60="X",BP23-BP51,"") -> -7.2759576e-12
A63: Income Statement
A64: Revenue | B64: =+'Income Statement'!B9 -> 713 | C64: =+'Income Statement'!C9 -> 923 | D64: =+'Income Statement'!D9 -> 2304 | E64: =+'Income Statement'!E9 -> 754 | F64: =+'Income Statement'!F9 -> 778 | G64: =+'Income Statement'!G9 -> 1016 | H64: =+'Income Statement'!H9 -> 2541 | I64: =+'Income Statement'!I9 -> 842 | ... BA64: =+'Income Statement'!BA9 -> 5332.8724
A65: COGS | B65: =+'Income Statement'!B15 -> 158 | C65: =+'Income Statement'!C15 -> 191 | D65: =+'Income Statement'!D15 -> 209 | E65: =+'Income Statement'!E15 -> 164 | F65: =+'Income Statement'!F15 -> 178 | G65: =+'Income Statement'!G15 -> 201 | H65: =+'Income Statement'!H15 -> 232 | I65: =+'Income Statement'!I15 -> 178 | ... BA65: =+'Income Statement'!BA15 -> 1063.2877
A66: R&D | B66: =+'Income Statement'!B21 -> 192 | C66: =+'Income Statement'!C21 -> 184 | D66: =+'Income Statement'!D21 -> 207 | E66: =+'Income Statement'!E21 -> 208 | F66: =+'Income Statement'!F21 -> 210 | G66: =+'Income Statement'!G21 -> 214 | H66: =+'Income Statement'!H21 -> 222 | I66: =+'Income Statement'!I21 -> 230 | ... BA66: =+'Income Statement'!BA21 -> 819.02396
A67: EBIT | B67: =+'Income Statement'!B24 -> 46 | C67: =+'Income Statement'!C24 -> 114 | D67: =+'Income Statement'!D24 -> 1359 | E67: =+'Income Statement'!E24 -> 36 | F67: =+'Income Statement'!F24 -> 32 | G67: =+'Income Statement'!G24 -> 106 | H67: =+'Income Statement'!H24 -> 1519 | I67: =+'Income Statement'!I24 -> 78 | ... BA67: =+'Income Statement'!BA24 -> 1589.8212
A68: Net Income | B68: =+'Income Statement'!B33 -> 24 | C68: =+'Income Statement'!C33 -> 67 | D68: =+'Income Statement'!D33 -> 893 | E68: =+'Income Statement'!E33 -> 20 | F68: =+'Income Statement'!F33 -> 15 | G68: =+'Income Statement'!G33 -> 67 | H68: =+'Income Statement'!H33 -> 1015 | I68: =+'Income Statement'!I33 -> 53 | ... BA68: =+'Income Statement'!BA33 -> 1170.5426
A70: DSOs | B70: =+(B8/B64)*91.25 -> 15.869565 | C70: =+(C8/C64)*91.25 -> 50.617551 | D70: =+(D8/D64)*91.25 -> 8.4754774 | E70: =+(E8/E64)*91.25 -> 13.070292 | F70: =+(F8/F64)*91.25 -> 14.191838 | G70: =+(G8/G64)*91.25 -> 46.792569 | H70: =+(H8/H64)*91.25 -> 8.7982094 | I70: =+(I8/I64)*91.25 -> 11.162411 | ... AQ70: =+(AQ8/AQ64)*91.25 -> 23.052838 | AR70: =+AN70 -> 8.5201186 | AS70: =+AO70 -> 12.623989 | AT70: =+AP70+1 -> 14.599421 | AU70: =+AQ70+1 -> 24.052838 | AV70: =+AR70+1 -> 9.5201186 | AW70: =+AS70+1 -> 13.623989 | AX70: =+AT70+1 -> 15.599421 | AY70: =+AU70+1 -> 25.052838 | AZ70: =+AV70+1 -> 10.520119 | BA70: =+AW70+1 -> 14.623989
A72: Working Capital Ratios
A73: Income taxes receivable | B73: =B9/B64 -> 0.14025245 | C73: =C9/C64 -> 49.578548 | D73: =D9/D64 -> 0.0017361111 | E73: =E9/E64 -> 0.026525199 | F73: =F9/F64 -> 0.073264781 | G73: =G9/G64 -> 0.040354331 | H73: =H9/H64 -> 0 | I73: =I9/I64 -> 0.074821853 | ... AQ73: =AQ9/AQ64 -> 0.4085143 | AR73: =+AN73 -> 0.17204024 | AS73: =+AO73 -> 0.37927434 | AT73: =+AP73 -> 0.41132561 | AU73: =+AQ73 -> 0.4085143 | AV73: =+AR73 -> 0.17204024 | AW73: =+AS73 -> 0.37927434 | AX73: =+AT73 -> 0.41132561 | AY73: =+AU73 -> 0.4085143 | ... BA73: =+AW73 -> 0.37927434
A74: Funds held for customers | B74: =+B14/B64 -> 0.48667602 | C74: =+C14/C64 -> 0.40411701 | D74: =+D14/D64 -> 0.16145833 | E74: =+E14/E64 -> 0.40318302 | F74: =+F14/F64 -> 0.41902314 | G74: =+G14/G64 -> 0.31889764 | H74: =+H14/H64 -> 0.12711531 | I74: =+I14/I64 -> 0.44180523 | ... AQ74: =+AQ14/AQ64 -> 0.94904322 | AR74: =+AN74 -> 0.67332989 | AS74: =+AO74 -> 1.8470373 | AT74: =+AP74 -> 1.0084942 | AU74: =+AQ74 -> 0.94904322 | AV74: =+AR74 -> 0.67332989 | AW74: =+AS74 -> 1.8470373 | AX74: =+AT74 -> 1.0084942 | AY74: =+AU74 -> 0.94904322 | ... BA74: =+AW74 -> 1.8470373
A75: Other assets | B75: =B22/B64 -> 0.457223 | C75: =C22/C64 -> 0.57313109 | D75: =D22/D64 -> 0.11848958 | E75: =E22/E64 -> 0.33289125 | F75: =F22/F64 -> 0.33933162 | G75: =G22/G64 -> 0.28740157 | H75: =H22/H64 -> 0.12750885 | I75: =I22/I64 -> 0.32660333 | ... AQ75: =AQ22/AQ64 -> 0.41517953 | AR75: =+AN75 -> 0.22710859 | AS75: =+AO75 -> 0.51500914 | AT75: =+AP75 -> 0.51505792 | AU75: =+AQ75 -> 0.41517953 | AV75: =+AR75 -> 0.22710859 | AW75: =+AS75 -> 0.51500914 | AX75: =+AT75 -> 0.51505792 | AY75: =+AU75 -> 0.41517953 | ... BA75: =+AW75 -> 0.51500914
