Workbook
Name \P: #REF!
Name \P: #REF!
Name \P: #REF!
Name \P: #REF!
Name \S: #REF!
Name \S: #REF!
Name \T: #REF!
Name \T: #REF!
Name \T: #REF!
Name \X: #REF!
Name \X: #REF!
Name \Z: #REF!
Name \Z: #REF!
Name ____________________________________________EPS94: #REF!
Name ____________________________________________EPS94: #REF!
Name ____________________________________________EPS95: #REF!
Name ____________________________________________EPS95: #REF!
Name ____________________________________________EPS96: #REF!
Name ____________________________________________EPS96: #REF!
Name ____________________________________________QTR195: #REF!
Name ____________________________________________QTR295: #REF!
Name ____________________________________________QTR394: #REF!
Name ____________________________________________QTR395: #REF!
Name ____________________________________________QTR494: #REF!
Name ____________________________________________QTR495: #REF!
Name ___________________________________________EPS94: #REF!
Name ___________________________________________EPS95: #REF!
Name ___________________________________________EPS96: #REF!
Name ___________________________________________QTR195: #REF!
Name ___________________________________________QTR295: #REF!
Name ___________________________________________QTR394: #REF!
Name ___________________________________________QTR395: #REF!
Name ___________________________________________QTR494: #REF!
Name ___________________________________________QTR495: #REF!
Name _________________________________________EPS94: #REF!
Name _________________________________________EPS95: #REF!
Name _________________________________________EPS96: #REF!
Name _________________________________________QTR195: #REF!
Name _________________________________________QTR295: #REF!
Name _________________________________________QTR394: #REF!
Name _________________________________________QTR395: #REF!
Name _________________________________________QTR494: #REF!
Name _________________________________________QTR495: #REF!
Name _______________________________________EPS94: #REF!
Name _______________________________________EPS95: #REF!
Name _______________________________________EPS96: #REF!
Name _______________________________________QTR195: #REF!
Name _______________________________________QTR295: #REF!
Name _______________________________________QTR394: #REF!
Name _______________________________________QTR395: #REF!
Name _______________________________________QTR494: #REF!
Name _______________________________________QTR495: #REF!
Name ______________________________________EPS94: #REF!
Name ______________________________________EPS95: #REF!
Name ______________________________________EPS96: #REF!
Name ______________________________________QTR195: #REF!
Name ______________________________________QTR295: #REF!
Name ______________________________________QTR394: #REF!
Name ______________________________________QTR395: #REF!
Name ______________________________________QTR494: #REF!

Sheet __FDSCACHE__
B1: This sheet contains FactSet XML data for use with this workbook's =FDS codes. Modifying the worksheet's contents may damage the workbook's =FDS functionality.

Sheet CW_Drivers
A1: Curtiss-Wright
A2: ($ in millions) | Q2: C4Q11 | R2: C1Q12 | S2: C2Q12 | T2: C3Q12 | V2: C4Q12 | W2: C1Q13 | X2: C2Q13 | Y2: C3Q13 | AK2: C3Q15 | AL2: C4Q15 | AM2: C1Q16 | AN2: C2Q16
B3: 1Q09 | C3: 2Q09 | D3: 3Q09 | E3: 4Q09 | F3: 2009 | G3: 1Q10 | H3: 2Q10 | I3: 3Q10 | J3: 4Q10 | K3: 2010 | L3: 1Q11 | M3: 2Q11 | N3: 3Q11 | O3: 4Q11 | P3: 2011 | Q3: 1Q12 | R3: 2Q12 | S3: 3Q12 | T3: 4Q12 | U3: 2012 | V3: 1Q13 | W3: 2Q13 | X3: 3Q13 | Y3: 4Q13 | Z3: 2013 | AA3: 1Q14 | AB3: 2Q14 | AC3: 3Q14 | AD3: 4Q14 | AE3: F2014 | AF3: 1Q15 | AG3: 2Q15 | AH3: 3Q15 | AI3: 4Q15 | AJ3: F2015 | AK3: F1Q16 | AL3: F2Q16 | AM3: F3Q16 | AN3: F4Q16 | AO3: F2016 | AP3: F1Q17 | AQ3: F2Q17 | AR3: F3Q17 | AS3: F4Q17 | AT3: 2017 | AU3: 1Q18 | AV3: 2Q18 | AW3: 3Q18 | AX3: 4Q18 | AY3: 2018 | AZ3: F1Q19 | BA3: F2Q19 | BB3: F3Q19 | BC3: F4Q19 | BD3: 2019 | BE3: 1Q20 | BF3: 2Q20 | BG3: 3Q20 | BH3: 4Q20 | BI3: 2020 | BJ3: 1Q21 | BK3: 2Q21 | BL3: 3Q21 | BM3: 4Q21 | BN3: 2021 | BO3: 1Q22 | BP3: 2Q22 | BQ3: 3Q22 | BR3: 4Q22 | BS3: 2022 | BT3: 1Q23 | BU3: 2Q23 | BV3: 3Q23 | BW3: 4Q23 | BX3: 2023 | BY3: 1Q24 | BZ3: 2Q24 | CA3: 3Q24 | CB3: 4Q24 | CC3: 2024 | CD3: 1Q25 | CE3: 2Q25 | CF3: 3Q25 | CG3: 4Q25 | CH3: 2025 | CI3: 1Q26E | CJ3: 2Q26E | CK3: 3Q26E | CL3: 4Q26E | CM3: 2026E | CN3: 1Q27E | CO3: 2Q27E | CP3: 3Q27E | CQ3: 4Q27E | CR3: 2027E
A5: Aerospace & Defense Revenue
A6: Aerospace Defense | AT6: 372.678 | AY6: 376.951 | BD6: 416.841 | BE6: 101.827 | BF6: 109.506 | BG6: 122.735 | BH6: 130.785 | BI6: =SUM(BE6:BH6) -> 464.853 | BJ6: 111.016 | BK6: 99.977 | BL6: 116.853 | BM6: 124.815 | BN6: =SUM(BJ6:BM6) -> 452.661 | BO6: 98.004 | BP6: 94.545 | BQ6: 114.431 | BR6: 172.763 | BS6: =SUM(BO6:BR6) -> 479.743 | BT6: 99.879 | BU6: 132.192 | BV6: 148.023 | BW6: 171.527 | BX6: =SUM(BT6:BW6) -> 551.621 | BY6: 132.074 | BZ6: 154.104 | CA6: 158.98 | CB6: 171.432 | CC6: =SUM(BY6:CB6) -> 616.59 | CD6: 151.722 | CE6: 167.587 | CF6: 161.162 | CG6: 192.055 | CH6: =SUM(CD6:CG6) -> 672.526 | CI6: =CD6*(1+CI7) -> 166.8942 | CJ6: =CE6*(1+CJ7) -> 180.99396 | CK6: =CF6*(1+CK7) -> 185.3363 | CL6: =CG6*(1+CL7) -> 207.4194 | CM6: =SUM(CI6:CL6) -> 740.64386 | CN6: =CI6*(1+CN7) -> 175.23891 | CO6: =CJ6*(1+CO7) -> 190.04366 | CP6: =CK6*(1+CP7) -> 194.60312 | CQ6: =CL6*(1+CQ7) -> 217.79037 | CR6: =SUM(CN6:CQ6) -> 777.67605
A7: y/y growth | AY7: =AY6/AT6-1 -> 0.011465662 | BD7: =BD6/AY6-1 -> 0.10582277 | BI7: =BI6/BD6-1 -> 0.11518061 | BJ7: =BJ6/BE6-1 -> 0.090241292 | BK7: =BK6/BF6-1 -> -0.087018063 | BL7: =BL6/BG6-1 -> -0.04792439 | BM7: =BM6/BH6-1 -> -0.045647437 | BN7: =BN6/BI6-1 -> -0.026227646 | BO7: =BO6/BJ6-1 -> -0.11720833 | BP7: =BP6/BK6-1 -> -0.054332496 | ... CH7: =CH6/CC6-1 -> 0.090718306 | CI7: 0.1 | CJ7: 0.08 | CK7: 0.15 | CL7: 0.08 | CM7: =CM6/CH6-1 -> 0.10128658 | CN7: 0.05 | CO7: 0.05 | CP7: 0.05 | CQ7: 0.05 | CR7: =CR6/CM6-1 -> 0.05
A8: % of total | AT8: =AT6/AT77 -> 0.15784578 | AY8: =AY6/AY77 -> 0.1562922 | BD8: =BD6/BD77 -> 0.16754322 | BE8: =BE6/BE77 -> 0.16936419 | BF8: =BF6/BF77 -> 0.2055667 | BG8: =BG6/BG77 -> 0.22317808 | BH8: =BH6/BH77 -> 0.20388454 | BI8: =BI6/BI77 -> 0.19990737 | BJ8: =BJ6/BJ77 -> 0.18817643 | BK8: =BK6/BK77 -> 0.16406428 | ... CH8: =CH6/CH77 -> 0.1922397 | CM8: =CM6/CM77 -> 0.19808174 | CR8: =CR6/CR77 -> 0.19647926
A9: Guidance - Full Yr | BH9: 2-4% | BI9: =BH9 -> 2-4% | BJ9: 2-4% | BM9: 0-2% | BN9: =BM9 -> 0-2% | BP9: 9-11% | BQ9: 3-5% | BR9: 9-11% | BS9: =BR9 -> 9-11% | BT9: 9-11% | BU9: 9-11% | BV9: 11-13% | BW9: 5-7% | BX9: =BW9 -> 5-7% | BY9: 6-8% | BZ9: 7-9% | CA9: 9-11% | CB9: 6-8% | CC9: =CB9 -> 6-8% | CD9: 6-8% | CE9: 7-9% | CF9: 7-9% | CG9: 9-11% | CH9: =CG9 -> 9-11%
A11: Ground Defense | AT11: 96.042 | AY11: 97.131 | BD11: 93.432 | BE11: 22.657 | BF11: 20.029 | BG11: 20.519 | BH11: 44.963 | BI11: =SUM(BE11:BH11) -> 108.168 | BJ11: 56.826 | BK11: 49.301 | BL11: 56.204 | BM11: 61.559 | BN11: =SUM(BJ11:BM11) -> 223.89 | BO11: 39.108 | BP11: 44.393 | BQ11: 54.89 | BR11: 81.348 | BS11: =SUM(BO11:BR11) -> 219.739 | BT11: 66.256 | BU11: 70.875 | BV11: 83.185 | BW11: 87.691 | BX11: =SUM(BT11:BW11) -> 308.007 | BY11: 90.76 | BZ11: 84.939 | CA11: 92.973 | CB11: 84.654 | CC11: =SUM(BY11:CB11) -> 353.326 | CD11: 97.237 | CE11: 97.542 | CF11: 96.789 | CG11: 115.235 | CH11: =SUM(CD11:CG11) -> 406.803 | CI11: =CD11*(1+CI12) -> 93.34752 | CJ11: =CE11*(1+CJ12) -> 96.56658 | CK11: =CF11*(1+CK12) -> 96.789 | CL11: =CG11*(1+CL12) -> 103.7115 | CM11: =SUM(CI11:CL11) -> 390.4146 | CN11: =CI11*(1+CN12) -> 97.081421 | CO11: =CJ11*(1+CO12) -> 100.42924 | CP11: =CK11*(1+CP12) -> 100.66056 | CQ11: =CL11*(1+CQ12) -> 107.85996 | CR11: =SUM(CN11:CQ11) -> 406.03118
A12: y/y growth | AY12: =AY11/AT11-1 -> 0.011338789 | BD12: =BD11/AY11-1 -> -0.038082589 | BI12: =BI11/BD11-1 -> 0.15771898 | BJ12: =BJ11/BE11-1 -> 1.508099 | BK12: =BK11/BF11-1 -> 1.4614809 | BL12: =BL11/BG11-1 -> 1.7391198 | BM12: =BM11/BH11-1 -> 0.36910349 | BN12: =BN11/BI11-1 -> 1.0698358 | BO12: =BO11/BJ11-1 -> -0.3117939 | BP12: =BP11/BK11-1 -> -0.099551733 | ... CH12: =CH11/CC11-1 -> 0.15135314 | CI12: -0.04 | CJ12: -0.01 | CK12: 0 | CL12: -0.1 | CM12: =CM11/CH11-1 -> -0.040285839 | CN12: 0.04 | CO12: 0.04 | CP12: 0.04 | CQ12: 0.04 | CR12: =CR11/CM11-1 -> 0.04
A13: % of total | AT13: =AT11/AT77 -> 0.040678078 | AY13: =AY11/AY77 -> 0.040272655 | BD13: =BD11/BD77 -> 0.037553643 | BE13: =BE11/BE77 -> 0.037684351 | BF13: =BF11/BF77 -> 0.037598812 | BG13: =BG11/BG77 -> 0.037311207 | BH13: =BH11/BH77 -> 0.070094128 | BI13: =BI11/BI77 -> 0.046517028 | BJ13: =BJ11/BJ77 -> 0.096322274 | BK13: =BK11/BK77 -> 0.08090394 | ... CH13: =CH11/CH77 -> 0.11628352 | CM13: =CM11/CM77 -> 0.10441456 | CR13: =CR11/CR77 -> 0.10258347
A14: Guidance - Full Yr | BH14: 100-105% | BI14: =BH14 -> 100-105% | BM14: 2-4% | BN14: =BM14 -> 2-4% | BP14: (1-3)% | BQ14: (7-9)% | BR14: 4-6% | BS14: =BR14 -> 4-6% | BT14: 4-6% | BU14: 16-18% | BV14: 23-25% | BW14: 4-6% | BX14: =BW14 -> 4-6% | BY14: 10-12% | BZ14: 10-12% | CA14: 10-12% | CB14: 3-5% | CC14: =CB14 -> 3-5% | CD14: 6-8% | CE14: 6-8% | CF14: 6-8% | CG14: (4-6)% | CH14: =CG14 -> (4-6)%
A16: Naval Defense | AT16: 408.221 | AY16: 486.476 | BD16: 568.776 | BE16: 165.693 | BF16: 164.941 | BG16: 165.524 | BH16: 195.995 | BI16: =SUM(BE16:BH16) -> 692.153 | BJ16: 177.905 | BK16: 177.724 | BL16: 175.8 | BM16: 179.259 | BN16: =SUM(BJ16:BM16) -> 710.688 | BO16: 162.967 | BP16: 172.786 | BQ16: 174.844 | BR16: 183.418 | BS16: =SUM(BO16:BR16) -> 694.015 | BT16: 171.956 | BU16: 180.956 | BV16: 179.862 | BW16: 187.24 | BX16: =SUM(BT16:BW16) -> 720.014 | BY16: 177.647 | BZ16: 209.847 | CA16: 217.51 | CB16: 216.894 | CC16: =SUM(BY16:CB16) -> 821.898 | CD16: 221.086 | CE16: 240.086 | CF16: 245.906 | CG16: 234.576 | CH16: =SUM(CD16:CG16) -> 941.654 | CI16: =CD16*(1+CI17) -> 237.66745 | CJ16: =CE16*(1+CJ17) -> 254.49116 | CK16: =CF16*(1+CK17) -> 260.66036 | CL16: =CG16*(1+CL17) -> 246.3048 | CM16: =SUM(CI16:CL16) -> 999.12377 | CN16: =CI16*(1+CN17) -> 251.9275 | CO16: =CJ16*(1+CO17) -> 269.76063 | CP16: =CK16*(1+CP17) -> 276.29998 | CQ16: =CL16*(1+CQ17) -> 261.08309 | CR16: =SUM(CN16:CQ16) -> 1059.0712
A17: y/y growth | AY17: =AY16/AT16-1 -> 0.19169763 | BD17: =BD16/AY16-1 -> 0.16917587 | BI17: =BI16/BD16-1 -> 0.21691668 | BJ17: =BJ16/BE16-1 -> 0.07370257 | BK17: =BK16/BF16-1 -> 0.07750044 | BL17: =BL16/BG16-1 -> 0.062081632 | BM17: =BM16/BH16-1 -> -0.085389933 | BN17: =BN16/BI16-1 -> 0.026778761 | BO17: =BO16/BJ16-1 -> -0.083966162 | BP17: =BP16/BK16-1 -> -0.027784655 | ... CH17: =CH16/CC16-1 -> 0.14570664 | CI17: 0.075 | CJ17: 0.06 | CK17: 0.06 | CL17: 0.05 | CM17: =CM16/CH16-1 -> 0.061030665 | CN17: 0.06 | CO17: 0.06 | CP17: 0.06 | CQ17: 0.06 | CR17: =CR16/CM16-1 -> 0.06
A18: % of total | AT18: =AT16/AT77 -> 0.17289983 | AY18: =AY16/AY77 -> 0.20170368 | BD18: =BD16/BD77 -> 0.2286113 | BE18: =BE16/BE77 -> 0.27558958 | BF18: =BF16/BF77 -> 0.30963032 | BG18: =BG16/BG77 -> 0.30098447 | BH18: =BH16/BH77 -> 0.3055423 | BI18: =BI16/BI77 -> 0.29765643 | BJ18: =BJ16/BJ77 -> 0.30155588 | BK18: =BK16/BK77 -> 0.29164868 | ... CH18: =CH16/CH77 -> 0.2691692 | CM18: =CM16/CM77 -> 0.26721098 | CR18: =CR16/CR77 -> 0.26757352
A19: Guidance - Full Yr | BH19: 0 | BI19: =BH19 -> 0 | BK19: 0-2% | BM19: 1-3% | BN19: =BM19 -> 1-3% | BQ19: 0 | BR19: 4-6% | BS19: =BR19 -> 4-6% | BT19: 4-6% | BU19: 6-8% | BV19: 5-7% | BW19: 3-5% | BX19: =BW19 -> 3-5% | BY19: 3-5% | BZ19: 5-7% | CA19: 9-11% | CB19: 3-5% | CC19: =CB19 -> 3-5% | CD19: 5-7% | CE19: 7-9% | CF19: 9-11% | CG19: 5-7% | CH19: =CG19 -> 5-7%
A21: Total Defense Revenue | AT21: =AT16+AT11+AT6 -> 876.941 | AU21: =AU16+AU11+AU6 -> 0 | AV21: =AV16+AV11+AV6 -> 0 | AW21: =AW16+AW11+AW6 -> 0 | AX21: =AX16+AX11+AX6 -> 0 | AY21: =AY16+AY11+AY6 -> 960.558 | AZ21: =AZ16+AZ11+AZ6 -> 0 | BA21: =BA16+BA11+BA6 -> 0 | ... CR21: =CR16+CR11+CR6 -> 2242.7784
A22: y/y growth | AY22: =AY21/AT21-1 -> 0.09535077 | BD22: =BD21/AY21-1 -> 0.12335642 | BI22: =BI21/BD21-1 -> 0.17248985 | BJ22: =BJ21/BE21-1 -> 0.19150381 | BK22: =BK21/BF21-1 -> 0.11045382 | BL22: =BL21/BG21-1 -> 0.12979876 | BM22: =BM21/BH21-1 -> -0.016436086 | BN22: =BN21/BI21-1 -> 0.0964808 | BO22: =BO21/BJ21-1 -> -0.13208502 | BP22: =BP21/BK21-1 -> -0.046721427 | ... CR22: =CR21/CM21-1 -> 0.052857545
A23: % of total | AT23: =AT21/AT77 -> 0.37142369 | AU23: =AU21/AU77 -> #DIV/0! | AV23: =AV21/AV77 -> #DIV/0! | AW23: =AW21/AW77 -> #DIV/0! | AX23: =AX21/AX77 -> #DIV/0! | AY23: =AY21/AY77 -> 0.39826854 | AZ23: =AZ21/AZ77 -> #DIV/0! | BA23: =BA21/BA77 -> #DIV/0! | ... CR23: =CR21/CR77 -> 0.56663625
A26: Narrowbody | BI26: =BI27*BI30 -> 117.61025 | BN26: =BN27*BN30 -> 102.616 | BS26: =BS27*BS30 -> 132.72912 | BX26: =BX27*BX30 -> 165.72399 | CC26: =CC27*CC30 -> 204.16644 | CH26: =CH27*CH30 -> 232.25886 | CM26: =CM27*CM30 -> 252.71639
A27: % of total | BI27: 0.5 | BN27: 0.5 | BS27: 0.6 | BX27: 0.6 | CC27: 0.6 | CH27: 0.6 | CM27: 0.6
A28: Widebody | BI28: =BI30-BI26 -> 117.61025 | BN28: =BN30-BN26 -> 102.616 | BS28: =BS30-BS26 -> 88.48608 | BX28: =BX30-BX26 -> 110.48266 | CC28: =CC30-CC26 -> 136.11096 | CH28: =CH30-CH26 -> 154.83924 | CM28: =CM30-CM26 -> 168.47759
A29: % of total | BI29: =BI28/BI30 -> 0.5 | BN29: =BN28/BN30 -> 0.5 | BS29: =BS28/BS30 -> 0.4 | BX29: =BX28/BX30 -> 0.4 | CC29: =CC28/CC30 -> 0.4 | CH29: =CH28/CH30 -> 0.4 | CM29: =CM28/CM30 -> 0.4
A30: OEM | BI30: =BI31*BI34 -> 235.2205 | BN30: =BN31*BN34 -> 205.232 | BS30: =BS31*BS34 -> 221.2152 | BX30: =BX31*BX34 -> 276.20665 | CC30: =CC31*CC34 -> 340.2774 | CH30: =CH31*CH34 -> 387.0981 | CM30: =CM31*CM34 -> 421.19399
BI31: 0.85 | BN31: 0.8 | BS31: 0.8 | BX31: 0.85 | CC31: 0.9 | CH31: 0.9 | CM31: 0.88
A32: Aftermarket | BI32: =BI34-BI30 -> 41.5095 | BN32: =BN34-BN30 -> 51.308 | BS32: =BS34-BS30 -> 55.3038 | BX32: =BX34-BX30 -> 48.74235 | CC32: =CC34-CC30 -> 37.8086 | CH32: =CH34-CH30 -> 43.0109 | CM32: =CM34-CM30 -> 57.435544
BI33: =BI32/BI34 -> 0.15 | BN33: =BN32/BN34 -> 0.2 | BS33: =BS32/BS34 -> 0.2 | BX33: =BX32/BX34 -> 0.15 | CC33: =CC32/CC34 -> 0.1 | CH33: =CH32/CH34 -> 0.1 | CM33: =CM32/CM34 -> 0.12
A34: Commercial Aerospace | AT34: 409.384 | AY34: 414.422 | BD34: 433.038 | BE34: 100.68 | BF34: 59.374 | BG34: 54.419 | BH34: 62.257 | BI34: =SUM(BE34:BH34) -> 276.73 | BJ34: 54.67 | BK34: 65.771 | BL34: 67.08 | BM34: 69.019 | BN34: =SUM(BJ34:BM34) -> 256.54 | BO34: 60.892 | BP34: 68.192 | BQ34: 70.257 | BR34: 77.178 | BS34: =SUM(BO34:BR34) -> 276.519 | BT34: 70.49 | BU34: 82.033 | BV34: 79.703 | BW34: 92.723 | BX34: =SUM(BT34:BW34) -> 324.949 | BY34: 89.775 | BZ34: 93.316 | CA34: 96.677 | CB34: 98.318 | CC34: =SUM(BY34:CB34) -> 378.086 | CD34: 92.877 | CE34: 103.318 | CF34: 113.856 | CG34: 120.058 | CH34: =SUM(CD34:CG34) -> 430.109 | CI34: =CD34*(1+CI35) -> 106.80855 | CJ34: =CE34*(1+CJ35) -> 115.71616 | CK34: =CF34*(1+CK35) -> 125.2416 | CL34: =CG34*(1+CL35) -> 130.86322 | CM34: =SUM(CI34:CL34) -> 478.62953 | CN34: =CI34*(1+CN35) -> 114.28515 | CO34: =CJ34*(1+CO35) -> 123.81629 | CP34: =CK34*(1+CP35) -> 134.00851 | CQ34: =CL34*(1+CQ35) -> 140.02365 | CR34: =SUM(CN34:CQ34) -> 512.1336
A35: y/y growth | AY35: =AY34/AT34-1 -> 0.012306294 | BD35: =BD34/AY34-1 -> 0.044920395 | BI35: =BI34/BD34-1 -> -0.36095678 | BJ35: =BJ34/BE34-1 -> -0.45699245 | BK35: =BK34/BF34-1 -> 0.10774076 | BL35: =BL34/BG34-1 -> 0.23265771 | BM35: =BM34/BH34-1 -> 0.10861429 | BN35: =BN34/BI34-1 -> -0.072959202 | BO35: =BO34/BJ34-1 -> 0.11381013 | BP35: =BP34/BK34-1 -> 0.036809536 | ... CH35: =CH34/CC34-1 -> 0.13759568 | CI35: 0.15 | CJ35: 0.12 | CK35: 0.1 | CL35: 0.09 | CM35: =CM34/CH34-1 -> 0.11280985 | CN35: 0.07 | CO35: 0.07 | CP35: 0.07 | CQ35: 0.07 | CR35: =CR34/CM34-1 -> 0.07
A36: % of total | AT36: =AT34/AT77 -> 0.17339241 | AY36: =AY34/AY77 -> 0.1718285 | BD36: =BD34/BD77 -> 0.17405337 | BE36: =BE34/BE77 -> 0.16745644 | BF36: =BF34/BF77 -> 0.11145798 | BG36: =BG34/BG77 -> 0.098954072 | BH36: =BH34/BH77 -> 0.097054248 | BI36: =BI34/BI77 -> 0.11900615 | BJ36: =BJ34/BJ77 -> 0.092667771 | BK36: =BK34/BK77 -> 0.10793154 | ... CH36: =CH34/CH77 -> 0.12294547 | CM36: =CM34/CM77 -> 0.12800723 | CR36: =CR34/CR77 -> 0.12939016
A37: Guidance - Full Yr | BH37: 0 | BI37: =BH37 -> 0 | BM37: 9-11% | BN37: =BM37 -> 9-11% | BR37: 5-7% | BS37: =BR37 -> 5-7% | BT37: 5-7% | BU37: 9-11% | BV37: 14-16% | BW37: 10-12% | BX37: =BW37 -> 10-12% | BY37: 10-12% | BZ37: 13-15% | CA37: 16-18% | CB37: 10-12% | CC37: =CB37 -> 10-12% | CD37: 13-15% | CE37: 13-15% | CF37: 13-15% | CG37: 10-12% | CH37: =CG37 -> 10-12%
A40: Total Aerospace & Defense Revenue | AT40: =AT6+AT11+AT16+AT34 -> 1286.325 | AY40: =AY6+AY11+AY16+AY34 -> 1374.98 | BD40: =BD6+BD11+BD16+BD34 -> 1512.087 | BE40: =BE6+BE11+BE16+BE34 -> 390.857 | BF40: =BF6+BF11+BF16+BF34 -> 353.85 | BG40: =BG6+BG11+BG16+BG34 -> 363.197 | BH40: =BH6+BH11+BH16+BH34 -> 434 | BI40: =SUM(BE40:BH40) -> 1541.904 | BJ40: =BJ6+BJ11+BJ16+BJ34 -> 400.417 | BK40: =BK6+BK11+BK16+BK34 -> 392.773 | BL40: =BL6+BL11+BL16+BL34 -> 415.937 | BM40: =BM6+BM11+BM16+BM34 -> 434.652 | BN40: =SUM(BJ40:BM40) -> 1643.779 | BO40: =BO6+BO11+BO16+BO34 -> 360.971 | BP40: =BP6+BP11+BP16+BP34 -> 379.916 | BQ40: =BQ6+BQ11+BQ16+BQ34 -> 414.422 | BR40: =BR6+BR11+BR16+BR34 -> 514.707 | BS40: =SUM(BO40:BR40) -> 1670.016 | BT40: =BT6+BT11+BT16+BT34 -> 408.581 | BU40: =BU6+BU11+BU16+BU34 -> 466.056 | BV40: =BV6+BV11+BV16+BV34 -> 490.773 | BW40: =BW6+BW11+BW16+BW34 -> 539.181 | BX40: =SUM(BT40:BW40) -> 1904.591 | BY40: =BY6+BY11+BY16+BY34 -> 490.256 | BZ40: =BZ6+BZ11+BZ16+BZ34 -> 542.206 | CA40: =CA6+CA11+CA16+CA34 -> 566.14 | CB40: =CB6+CB11+CB16+CB34 -> 571.298 | CC40: =SUM(BY40:CB40) -> 2169.9 | CD40: =CD6+CD11+CD16+CD34 -> 562.922 | CE40: =CE6+CE11+CE16+CE34 -> 608.533 | CF40: =CF6+CF11+CF16+CF34 -> 617.713 | CG40: =CG6+CG11+CG16+CG34 -> 661.924 | CH40: =SUM(CD40:CG40) -> 2451.092 | CI40: =CI6+CI11+CI16+CI34 -> 604.71772 | CJ40: =CJ6+CJ11+CJ16+CJ34 -> 647.76786 | CK40: =CK6+CK11+CK16+CK34 -> 668.02726 | CL40: =CL6+CL11+CL16+CL34 -> 688.29892 | CM40: =SUM(CI40:CL40) -> 2608.8118 | CN40: =CN6+CN11+CN16+CN34 -> 638.53298 | CO40: =CO6+CO11+CO16+CO34 -> 684.04982 | CP40: =CP6+CP11+CP16+CP34 -> 705.57217 | CQ40: =CQ6+CQ11+CQ16+CQ34 -> 726.75706 | CR40: =SUM(CN40:CQ40) -> 2754.912
A41: y/y growth | AY41: =AY40/AT40-1 -> 0.068921151 | BD41: =BD40/AY40-1 -> 0.099715632 | BI41: =BI40/BD40-1 -> 0.019719103 | BJ41: =BJ40/BE40-1 -> 0.024459073 | BK41: =BK40/BF40-1 -> 0.10999859 | BL41: =BL40/BG40-1 -> 0.14521045 | BM41: =BM40/BH40-1 -> 0.0015023041 | BN41: =BN40/BI40-1 -> 0.06607091 | BO41: =BO40/BJ40-1 -> -0.098512301 | BP41: =BP40/BK40-1 -> -0.03273392 | ... CR41: =CR40/CM40-1 -> 0.056002611
A42: % of total | AT42: =AT40/AT77 -> 0.54481611 | AY42: =AY40/AY77 -> 0.57009704 | BD42: =BD40/BD77 -> 0.60776154 | BE42: =BE40/BE77 -> 0.65009456 | BF42: =BF40/BF77 -> 0.66425381 | BG42: =BG40/BG77 -> 0.66042783 | BH42: =BH40/BH77 -> 0.67657522 | BI42: =BI40/BI77 -> 0.66308698 | BJ42: =BJ40/BJ77 -> 0.67872235 | BK42: =BK40/BK77 -> 0.64454845 | ... CH42: =CH40/CH77 -> 0.7006379 | CM42: =CM40/CM77 -> 0.69771451 | CR42: =CR40/CR77 -> 0.6960264
A43: Guidance - Full Yr | BH43: 6-8% | BI43: 6-8% | BJ43: 7-9% | BM43: 2-4% | BN43: =BM43 -> 2-4% | BP43: 4-6% | BQ43: 1-3% | BR43: 6-8% | BS43: =BR43 -> 6-8% | BT43: 6-8% | BU43: 9-11% | BV43: 10-12% | BW43: 5-7% | BX43: =BW43 -> 5-7% | BY43: 6-8% | BZ43: 8-10% | CA43: 10-12% | CB43: 5-7% | CC43: =CB43 -> 5-7% | CD43: 7-9% | CE43: 8-10% | CF43: 10-11% | CG43: 5-7% | CH43: =CG43 -> 5-7%
A45: Commercial Revenue
A48: Aftermarket & Government | BS48: =BS49*BS52 -> 255.042 | BX48: =BX49*BX52 -> 275.39892 | CC48: =CC49*CC52 -> 292.02552 | CH48: =CH49*CH52 -> 342.9756 | CM48: =CM49*CM52 -> 410.77049
A49: % of total | BS49: 0.9 | BX49: 0.9 | CC49: 0.9 | CH49: 0.9 | CM49: 0.88
A50: New Build Gen III/IV (SMRs) | BS50: =BS52-BS48 -> 28.338 | BX50: =BX52-BX48 -> 30.59988 | CC50: =CC52-CC48 -> 32.44728 | CH50: =CH52-CH48 -> 38.1084 | CM50: =CM52-CM48 -> 56.014158
A51: % of total | BS51: =BS50/BS52 -> 0.1 | BX51: =BX50/BX52 -> 0.1 | CC51: =CC50/CC52 -> 0.1 | CH51: =CH50/CH52 -> 0.1 | CM51: =CM50/CM52 -> 0.12
A52: Commercial Nuclear | BI52: =BI53*BI57 -> 296.23815 | BN52: =BN53*BN57 -> 288.35235 | BS52: =BS53*BS57 -> 283.38 | BX52: =BX53*BX57 -> 305.9988 | CC52: =CC53*CC57 -> 324.4728 | CH52: =CH53*CH57 -> 381.084 | CM52: =CM53*CM57 -> 466.78465 | CT52: =1500 -> 1500 | CU52: =+CT52-CH52 -> 1118.916
A53: % of total | BI53: 0.65 | BN53: 0.65 | BS53: 0.6 | BX53: 0.6 | CC53: 0.6 | CH53: 0.6 | CM53: 0.65 | CT53: =+(CT52/CH52)^(1/10)-1 -> 0.14685115
BN54: =+BN52/BI52-1 -> -0.026619799 | BS54: =+BS52/BN52-1 -> -0.017244007 | BX54: =+BX52/BS52-1 -> 0.079817912 | CC54: =+CC52/BX52-1 -> 0.060372786 | CH54: =+CH52/CC52-1 -> 0.17447133 | CM54: =+CM52/CH52-1 -> 0.22488651 | CT54: =+CH52/CC52-1 -> 0.17447133
A55: Process | BI55: =BI57-BI52 -> 159.51285 | BN55: =BN57-BN52 -> 155.26665 | BS55: =BS57-BS52 -> 188.92 | BX55: =BX57-BX52 -> 203.9992 | CC55: =CC57-CC52 -> 216.3152 | CH55: =CH57-CH52 -> 254.056 | CM55: =CM57-CM52 -> 251.34558
A56: % of total | BI56: =BI55/BI57 -> 0.35 | BN56: =BN55/BN57 -> 0.35 | BS56: =BS55/BS57 -> 0.4 | BX56: =BX55/BX57 -> 0.4 | CC56: =CC55/CC57 -> 0.4 | CH56: =CH55/CH57 -> 0.4 | CM56: =CM55/CM57 -> 0.35
A57: Power and Process | U57: 433.8 | Z57: 461.6 | AE57: 427.5 | AJ57: 436.4 | AO57: 408.4 | AT57: 423.747 | AY57: 431.793 | BD57: 392.173 | BE57: 123.926 | BF57: 106.952 | BG57: 108.023 | BH57: 116.85 | BI57: =SUM(BE57:BH57) -> 455.751 | BJ57: 99.921 | BK57: 117.919 | BL57: 105.264 | BM57: 120.515 | BN57: =SUM(BJ57:BM57) -> 443.619 | BO57: 104.788 | BP57: 125.355 | BQ57: 110.559 | BR57: 131.598 | BS57: =SUM(BO57:BR57) -> 472.3 | BT57: 120.339 | BU57: 131 | BV57: 122.118 | BW57: 136.541 | BX57: =SUM(BT57:BW57) -> 509.998 | BY57: 124.039 | BZ57: 138.601 | CA57: 131.376 | CB57: 146.772 | CC57: =SUM(BY57:CB57) -> 540.788 | CD57: 142.934 | CE57: 163.473 | CF57: 149.9 | CG57: 178.833 | CH57: =SUM(CD57:CG57) -> 635.14 | CI57: =CD57*(1+CI58) -> 165.80344 | CJ57: =CE57*(1+CJ58) -> 184.72449 | CK57: =CF57*(1+CK58) -> 170.886 | CL57: =CG57*(1+CL58) -> 196.7163 | CM57: =SUM(CI57:CL57) -> 718.13023 | CN57: =CI57*(1+CN58) -> 180.72575 | CO57: =CJ57*(1+CO58) -> 201.34969 | CP57: =CK57*(1+CP58) -> 186.26574 | CQ57: =CL57*(1+CQ58) -> 214.42077 | CR57: =SUM(CN57:CQ57) -> 782.76195 | CT57: =+BX57*2 -> 1019.996
A58: y/y growth | Z58: =Z57/U57-1 -> 0.064084832 | AE58: =AE57/Z57-1 -> -0.073873484 | AJ58: =AJ57/AE57-1 -> 0.020818713 | AO58: =AO57/AJ57-1 -> -0.06416132 | AT58: =AT57/AO57-1 -> 0.037578355 | AY58: =AY57/AT57-1 -> 0.018987745 | BD58: =BD57/AY57-1 -> -0.09175693 | BI58: =BI57/BD57-1 -> 0.16211723 | BJ58: =BJ57/BE57-1 -> -0.19370431 | BK58: =BK57/BF57-1 -> 0.10254133 | BL58: =BL57/BG57-1 -> -0.025540857 | BM58: =BM57/BH57-1 -> 0.031364998 | BN58: =BN57/BI57-1 -> -0.026619799 | BO58: =BO57/BJ57-1 -> 0.04870848 | BP58: =BP57/BK57-1 -> 0.063060236 | ... CH58: =CH57/CC57-1 -> 0.17447133 | CI58: 0.16 | CJ58: 0.13 | CK58: 0.14 | CL58: 0.1 | CM58: =CM57/CH57-1 -> 0.13066447 | CN58: 0.09 | CO58: 0.09 | CP58: 0.09 | CQ58: 0.09 | CR58: =CR57/CM57-1 -> 0.09
A59: % of total | AT59: =AT57/AT77 -> 0.17947579 | AY59: =AY57/AY77 -> 0.1790309 | BD59: =BD57/BD77 -> 0.15762827 | BE59: =BE57/BE77 -> 0.20612044 | BF59: =BF57/BF77 -> 0.20077229 | BG59: =BG57/BG77 -> 0.19642617 | BH59: =BH57/BH77 -> 0.18216086 | BI59: =BI57/BI77 -> 0.19599311 | BJ59: =BJ57/BJ77 -> 0.16936997 | BK59: =BK57/BK77 -> 0.19350747 | ... CH59: =CH57/CH77 -> 0.18155302 | CM59: =CM57/CM77 -> 0.19206057 | CR59: =CR57/CR77 -> 0.1977642
A60: Guidance - Full Yr | BH60: 3-5% | BI60: =BH60 -> 3-5% | BK60: 1-3% | BM60: 1-3% | BN60: =BM60 -> 1-3% | BP60: 4-6% | BQ60: 5-7% | BR60: 0 | BS60: =BR60 -> 0 | BT60: 0 | BU60: 3-5% | BV60: 4-6% | BW60: 3-5% | BX60: =BW60 -> 3-5% | BY60: 4-6% | BZ60: 4-6% | CA60: 5-7% | CB60: 16-18% | CC60: =CB60 -> 16-18% | CD60: 16-18% | CE60: 16-18% | CF60: 16-18% | CG60: 12-14% | CH60: =CG60 -> 12-14%
A62: Industrial Vehicles | BI62: =BI63*BI66 -> 212.99655 | BN62: =BN63*BN66 -> 266.7567 | BS62: =BS63*BS66 -> 290.297 | BX62: =BX63*BX66 -> 280.0096 | CC62: =CC63*CC66 -> 266.82565 | CH62: =CH63*CH66 -> 267.891 | CM62: =CM63*CM66 -> 267.891
BI63: 0.65 | BN63: 0.7 | BS63: 0.7 | BX63: 0.65 | CC63: 0.65 | CH63: 0.65 | CM63: 0.65
A64: Industrial Automation and Services | BI64: =BI66-BI62 -> 114.69045 | BN64: =BN66-BN62 -> 114.3243 | BS64: =BS66-BS62 -> 124.413 | BX64: =BX66-BX62 -> 150.7744 | CC64: =CC66-CC62 -> 143.67535 | CH64: =CH66-CH62 -> 144.249 | CM64: =CM66-CM62 -> 144.249
BI65: =BI64/BI66 -> 0.35 | BN65: =BN64/BN66 -> 0.3 | BS65: =BS64/BS66 -> 0.3 | BX65: =BX64/BX66 -> 0.35 | CC65: =CC64/CC66 -> 0.35 | CH65: =CH64/CH66 -> 0.35 | CM65: =CM64/CM66 -> 0.35
A66: General Industrial | AT66: 650.954 | AY66: 605.062 | BD66: 583.701 | BE66: 86.448 | BF66: 71.901 | BG66: 78.722 | BH66: 90.616 | BI66: =SUM(BE66:BH66) -> 327.687 | BJ66: 89.619 | BK66: 98.685 | BL66: 92.645 | BM66: 100.132 | BN66: =SUM(BJ66:BM66) -> 381.081 | BO66: 93.702 | BP66: 104.086 | BQ66: 105.562 | BR66: 111.36 | BS66: =SUM(BO66:BR66) -> 414.71 | BT66: 101.94 | BU66: 107.34 | BV66: 111.435 | BW66: 110.069 | BX66: =SUM(BT66:BW66) -> 430.784 | BY66: 98.872 | BZ66: 103.984 | CA66: 101.402 | CB66: 106.243 | CC66: =SUM(BY66:CB66) -> 410.501 | CD66: 99.789 | CE66: 104.57 | CF66: 101.557 | CG66: 106.224 | CH66: =SUM(CD66:CG66) -> 412.14 | CI66: =CD66*(1+CI67) -> 99.789 | CJ66: =CE66*(1+CJ67) -> 104.57 | CK66: =CF66*(1+CK67) -> 101.557 | CL66: =CG66*(1+CL67) -> 106.224 | CM66: =SUM(CI66:CL66) -> 412.14 | CN66: =CI66*(1+CN67) -> 101.78478 | CO66: =CJ66*(1+CO67) -> 106.6614 | CP66: =CK66*(1+CP67) -> 103.58814 | CQ66: =CL66*(1+CQ67) -> 108.34848 | CR66: =SUM(CN66:CQ66) -> 420.3828
A67: y/y growth | AY67: =AY66/AT66-1 -> -0.070499605 | BD67: =BD66/AY66-1 -> -0.03530382 | BI67: =BI66/BD66-1 -> -0.4386047 | BJ67: =BJ66/BE66-1 -> 0.036681011 | BK67: =BK66/BF66-1 -> 0.3725122 | BL67: =BL66/BG66-1 -> 0.17686288 | BM67: =BM66/BH66-1 -> 0.10501457 | BN67: =BN66/BI66-1 -> 0.16294208 | BO67: =BO66/BJ66-1 -> 0.045559535 | BP67: =BP66/BK66-1 -> 0.054729695 | ... CH67: =CH66/CC66-1 -> 0.0039926821 | CI67: 0 | CJ67: 0 | CK67: 0 | CL67: 0 | CM67: =CM66/CH66-1 -> 0 | CN67: 0.02 | CO67: 0.02 | CP67: 0.02 | CQ67: 0.02 | CR67: =CR66/CM66-1 -> 0.02
A68: % of total | AT68: =AT66/AT77 -> 0.2757081 | AY68: =AY66/AY77 -> 0.25087205 | BD68: =BD66/BD77 -> 0.23461019 | BE68: =BE66/BE77 -> 0.143785 | BF68: =BF66/BF77 -> 0.1349739 | BG68: =BG66/BG77 -> 0.143146 | BH68: =BH66/BH77 -> 0.14126392 | BI68: =BI66/BI77 -> 0.14091992 | BJ68: =BJ66/BJ77 -> 0.15190768 | BK68: =BK66/BK77 -> 0.16194408 | ... CH68: =CH66/CH77 -> 0.11780908 | CM68: =CM66/CM77 -> 0.11022492 | CR68: =CR66/CR77 -> 0.10620939
A69: Guidance - Full Yr | BH69: 9-11% | BI69: =BH69 -> 9-11% | BK69: 15-17% | BO69: 6-8% | BR69: 2-4% | BS69: =BR69 -> 2-4% | BT69: 2-4% | BU69: 3-5% | BV69: 3-5% | BW69: 1-3% | BX69: =BW69 -> 1-3% | BY69: 1-3% | BZ69: 0 | CA69: (2-4%) | CB69: 0 | CC69: =CB69 -> 0 | CD69: 0 | CE69: 0 | CF69: 0 | CG69: 0 | CH69: =CG69 -> 0
A71: Total Commercial Revenue | AT71: =AT57+AT66 -> 1074.701 | AY71: =AY57+AY66 -> 1036.855 | BD71: =BD57+BD66 -> 975.874 | BE71: =BE57+BE66 -> 210.374 | BF71: =BF57+BF66 -> 178.853 | BG71: =BG57+BG66 -> 186.745 | BH71: =BH57+BH66 -> 207.466 | BI71: =SUM(BE71:BH71) -> 783.438 | BJ71: =BJ57+BJ66 -> 189.54 | BK71: =BK57+BK66 -> 216.604 | BL71: =BL57+BL66 -> 197.909 | BM71: =BM57+BM66 -> 220.647 | BN71: =SUM(BJ71:BM71) -> 824.7 | BO71: =BO57+BO66 -> 198.49 | BP71: =BP57+BP66 -> 229.441 | BQ71: =BQ57+BQ66 -> 216.121 | BR71: =BR57+BR66 -> 242.958 | BS71: =SUM(BO71:BR71) -> 887.01 | BT71: =BT57+BT66 -> 222.279 | BU71: =BU57+BU66 -> 238.34 | BV71: =BV57+BV66 -> 233.553 | BW71: =BW57+BW66 -> 246.61 | BX71: =SUM(BT71:BW71) -> 940.782 | BY71: =BY57+BY66 -> 222.911 | BZ71: =BZ57+BZ66 -> 242.585 | CA71: =CA57+CA66 -> 232.778 | CB71: =CB57+CB66 -> 253.015 | CC71: =SUM(BY71:CB71) -> 951.289 | CD71: =CD57+CD66 -> 242.723 | CE71: =CE57+CE66 -> 268.043 | CF71: =CF57+CF66 -> 251.457 | CG71: =CG57+CG66 -> 285.057 | CH71: =SUM(CD71:CG71) -> 1047.28 | CI71: =CI57+CI66 -> 265.59244 | CJ71: =CJ57+CJ66 -> 289.29449 | CK71: =CK57+CK66 -> 272.443 | CL71: =CL57+CL66 -> 302.9403 | CM71: =SUM(CI71:CL71) -> 1130.2702 | CN71: =CN57+CN66 -> 282.51053 | CO71: =CO57+CO66 -> 308.01109 | CP71: =CP57+CP66 -> 289.85388 | CQ71: =CQ57+CQ66 -> 322.76925 | CR71: =SUM(CN71:CQ71) -> 1203.1448
A72: y/y growth | AY72: =AY71/AT71-1 -> -0.035215376 | BD72: =BD71/AY71-1 -> -0.058813431 | BI72: =BI71/BD71-1 -> -0.19719349 | BJ72: =BJ71/BE71-1 -> -0.09903315 | BK72: =BK71/BF71-1 -> 0.21107278 | BL72: =BL71/BG71-1 -> 0.059782056 | BM72: =BM71/BH71-1 -> 0.063533302 | BN72: =BN71/BI71-1 -> 0.052667856 | BO72: =BO71/BJ71-1 -> 0.047219584 | BP72: =BP71/BK71-1 -> 0.059264834 | ... CR72: =CR71/CM71-1 -> 0.064475308
A73: % of total | AT73: =AT71/AT77 -> 0.45518389 | AY73: =AY71/AY77 -> 0.42990296 | BD73: =BD71/BD77 -> 0.39223846 | BE73: =BE71/BE77 -> 0.34990544 | BF73: =BF71/BF77 -> 0.33574619 | BG73: =BG71/BG77 -> 0.33957217 | BH73: =BH71/BH77 -> 0.32342478 | BI73: =BI71/BI77 -> 0.33691302 | BJ73: =BJ71/BJ77 -> 0.32127765 | BK73: =BK71/BK77 -> 0.35545155 | ... CH73: =CH71/CH77 -> 0.2993621 | CM73: =CM71/CM77 -> 0.30228549 | CR73: =CR71/CR77 -> 0.3039736
A74: Guidance - Full Yr | BH74: 6-8% | BI74: =BH74 -> 6-8% | BM74: 4-6% | BN74: =BM74 -> 4-6% | BP74: 5-7% | BQ74: 6-8% | BR74: 0-2% | BS74: =BR74 -> 0-2% | BT74: 0-2% | BU74: 3-5% | BV74: 3-5% | BW74: 2-4% | BX74: =BW74 -> 2-4% | BY74: 2-4% | BZ74: 1-3% | CA74: 1-3% | CB74: 9-11% | CC74: =CB74 -> 9-11% | CD74: 9-11% | CE74: 9-11% | CF74: 9-11% | CG74: 7-9% | CH74: =CG74 -> 7-9%
A76: Consolidated
A77: Total Revenue | AT77: =AT71+AT40 -> 2361.026 | AY77: =AY71+AY40 -> 2411.835 | BD77: =BD71+BD40 -> 2487.961 | BE77: =BE40+BE71 -> 601.231 | BF77: =BF40+BF71 -> 532.703 | BG77: =BG40+BG71 -> 549.942 | BH77: =BH40+BH71 -> 641.466 | BI77: =SUM(BE77:BH77) -> 2325.342 | BJ77: =BJ40+BJ71 -> 589.957 | BK77: =BK40+BK71 -> 609.377 | BL77: =BL40+BL71 -> 613.846 | BM77: =BM40+BM71 -> 655.299 | BN77: =SUM(BJ77:BM77) -> 2468.479 | BO77: =BO40+BO71 -> 559.461 | BP77: =BP40+BP71 -> 609.357 | BQ77: =BQ40+BQ71 -> 630.543 | BR77: =BR40+BR71 -> 757.665 | BS77: =SUM(BO77:BR77) -> 2557.026 | BT77: =BT40+BT71 -> 630.86 | BU77: =BU40+BU71 -> 704.396 | BV77: =BV40+BV71 -> 724.326 | BW77: =BW40+BW71 -> 785.791 | BX77: =SUM(BT77:BW77) -> 2845.373 | BY77: =BY40+BY71 -> 713.167 | BZ77: =BZ40+BZ71 -> 784.791 | CA77: =CA40+CA71 -> 798.918 | CB77: =CB40+CB71 -> 824.313 | CC77: =SUM(BY77:CB77) -> 3121.189 | CD77: =CD40+CD71 -> 805.645 | CE77: =CE40+CE71 -> 876.576 | CF77: =CF40+CF71 -> 869.17 | CG77: =CG40+CG71 -> 946.981 | CH77: =SUM(CD77:CG77) -> 3498.372 | CI77: =CI40+CI71 -> 870.31016 | CJ77: =CJ40+CJ71 -> 937.06235 | CK77: =CK40+CK71 -> 940.47026 | CL77: =CL40+CL71 -> 991.23922 | CM77: =SUM(CI77:CL77) -> 3739.082 | CN77: =CN40+CN71 -> 921.04351 | CO77: =CO40+CO71 -> 992.06092 | CP77: =CP40+CP71 -> 995.42605 | CQ77: =CQ40+CQ71 -> 1049.5263 | CR77: =SUM(CN77:CQ77) -> 3958.0568
A78: y/y growth | AY78: =AY77/AT77-1 -> 0.021519882 | BD78: =BD77/AY77-1 -> 0.031563519 | BI78: =BI77/BD77-1 -> -0.065362359 | BJ78: =BJ77/BE77-1 -> -0.018751528 | BK78: =BK77/BF77-1 -> 0.14393386 | BL78: =BL77/BG77-1 -> 0.11620134 | BM78: =BM77/BH77-1 -> 0.021564666 | BN78: =BN77/BI77-1 -> 0.061555246 | BO78: =BO77/BJ77-1 -> -0.051691903 | BP78: =BP77/BK77-1 -> -3.2820405e-05 | ... CR78: =CR77/CM77-1 -> 0.058563784
A79: Guidance - Full Yr | BH79: 2445-2495 | BI79: =BH79 -> 2445-2495 | BJ79: 2450-2500 | BK79: 2465-2515 | BM79: 2530-2580 | BN79: =BM79 -> 2530-2580 | BP79: 2570-2620 | BQ79: 2525-2575 | BR79: 2655-2710 | BS79: =BR79 -> 2655-2710 | BT79: 2655-2710 | BU79: 2730-2790 | BV79: 2765-2815 | BW79: 2960-3010 | BX79: =BW79 -> 2960-3010 | BY79: 2985-3035 | BZ79: 3010-3060 | CA79: 3050-3095 | CB79: 3335-3385 | CC79: =CB79 -> 3335-3385 | CD79: 3365-3415 | CE79: 3390-3435 | CF79: 3420-3455 | CG79: 3710-3765 | CH79: =CG79 -> 3710-3765 | CI79: {=_xll.FDS("CW-US","FE_ESTIMATE(SALES,MEAN,QTR_ROLL,+1,NOW,,,'')")} -> #NAME? | CJ79: {=_xll.FDS("CW-US","FE_ESTIMATE(SALES,MEAN,QTR_ROLL,+2,NOW,,,'')")} -> #NAME? | CK79: {=_xll.FDS("CW-US","FE_ESTIMATE(SALES,MEAN,QTR_ROLL,+3,NOW,,,'')")} -> #NAME? | CL79: {=_xll.FDS("CW-US","FE_ESTIMATE(SALES,MEAN,QTR_ROLL,+4,NOW,,,'')")} -> #NAME?
A80: Consensus | BH80: 2445-2495 | BJ80: 2450-2500 | BK80: 2465-2515 | BM80: 2530-2580 | BT80: 585 | BU80: 652 | BV80: 683 | BW80: 737 | BY80: 664 | BZ80: 736 | CA80: 757 | CB80: 785.3 | CD80: 767.2 | CE80: 852 | CF80: 870.3051 | CG80: 890.3 | CM80: {=_xll.FDS("CW-US","FE_ESTIMATE(SALES,MEAN,ANN_ROLL,+1,NOW,,,'')")} -> #NAME? | CR80: {=_xll.FDS("CW-US","FE_ESTIMATE(SALES,MEAN,ANN_ROLL,+2,NOW,,,'')")} -> #NAME?
CM81: =CM80/CH77-1 -> #NAME? | CR81: =CR80/CM80-1 -> #NAME?
BS83: =0.11*BS77 -> 281.27286
A84: Sources: Company Reports, William Blair Equity Research

Sheet CW_IS
B2: Curtiss-Wright Corporation
B3: Sales & Earnings Model
B4: ($ in millions; December fiscal year end)
B5: Period | C5: 1Q13 | D5: 2Q13 | E5: 3Q13 | F5: 4Q13 | G5: FY13 | H5: 1Q14 | I5: 2Q14 | J5: 3Q14 | K5: 4Q14 | L5: FY14 | M5: 1Q15 | N5: 2Q15 | O5: 3Q15 | P5: 4Q15 | Q5: FY15 | R5: 1Q16 | S5: 2Q16 | T5: 3Q16 | U5: 4Q16 | V5: FY16 | W5: 1Q17 | X5: 2Q17 | Y5: 3Q17 | Z5: 4Q17 | AA5: FY17 | AB5: 1Q18 | AC5: 2Q18 | AD5: 3Q18 | AE5: 4Q18 | AF5: FY18 | AG5: 1Q19 | AH5: 2Q19 | AI5: 3Q19 | AJ5: 4Q19 | AK5: FY19 | AL5: 1Q20 | AM5: 2Q20 | AN5: 3Q20 | AO5: 4Q20 | AP5: FY20 | AQ5: 1Q21 | AR5: 2Q21 | AS5: 3Q21 | AT5: 4Q21 | AU5: FY21 | AV5: 1Q22 | AW5: 2Q22 | AX5: 3Q22 | AY5: 4Q22 | AZ5: FY22 | BA5: 1Q23 | BB5: 2Q23 | BC5: 3Q23 | BD5: 4Q23 | BE5: FY23 | BF5: =CW_Drivers!BY3 -> 1Q24 | BG5: =CW_Drivers!BZ3 -> 2Q24 | BH5: =CW_Drivers!CA3 -> 3Q24 | BI5: =CW_Drivers!CB3 -> 4Q24 | BJ5: FY24 | BK5: =CW_Drivers!CD3 -> 1Q25 | BL5: =CW_Drivers!CE3 -> 2Q25 | BM5: =CW_Drivers!CF3 -> 3Q25 | BN5: =CW_Drivers!CG3 -> 4Q25 | BO5: FY25 | BP5: =CW_Drivers!CI3 -> 1Q26E | BQ5: =CW_Drivers!CJ3 -> 2Q26E | BR5: =CW_Drivers!CK3 -> 3Q26E | BS5: =CW_Drivers!CL3 -> 4Q26E | BT5: FY26E | BU5: =CW_Drivers!CN3 -> 1Q27E | BV5: =CW_Drivers!CO3 -> 2Q27E | BW5: =CW_Drivers!CP3 -> 3Q27E | BX5: =CW_Drivers!CQ3 -> 4Q27E | BY5: FY27E
B6: Fiscal Year Ends December | H6: 41729 | I6: 41820 | J6: 41912 | K6: 42004 | L6: FY 2014 | M6: =DATE(YEAR(H6)+1,MONTH(H6),DAY(H6)) -> 42094 | N6: =DATE(YEAR(I6)+1,MONTH(I6),DAY(I6)) -> 42185 | O6: =DATE(YEAR(J6)+1,MONTH(J6),DAY(J6)) -> 42277 | P6: =DATE(YEAR(K6)+1,MONTH(K6),DAY(K6)) -> 42369 | Q6: =CONCATENATE( "FY ", MID(L6,4,4)+1, IF(RIGHT(P5,1)="E", "E", "") ) -> FY 2015 | R6: =DATE(YEAR(M6)+1,MONTH(M6),DAY(M6)) -> 42460 | S6: =DATE(YEAR(N6)+1,MONTH(N6),DAY(N6)) -> 42551 | T6: =DATE(YEAR(O6)+1,MONTH(O6),DAY(O6)) -> 42643 | U6: =DATE(YEAR(P6)+1,MONTH(P6),DAY(P6)) -> 42735 | V6: =CONCATENATE( "FY ", MID(Q6,4,4)+1, IF(RIGHT(U5,1)="E", "E", "") ) -> FY 2016 | W6: =DATE(YEAR(R6)+1,MONTH(R6),DAY(R6)) -> 42825 | X6: =DATE(YEAR(S6)+1,MONTH(S6),DAY(S6)) -> 42916 | Y6: =DATE(YEAR(T6)+1,MONTH(T6),DAY(T6)) -> 43008 | Z6: =DATE(YEAR(U6)+1,MONTH(U6),DAY(U6)) -> 43100 | AA6: =CONCATENATE( "FY ", MID(V6,4,4)+1, IF(RIGHT(Z5,1)="E", "E", "") ) -> FY 2017 | AB6: =DATE(YEAR(W6)+1,MONTH(W6),DAY(W6)) -> 43190 | AC6: =DATE(YEAR(X6)+1,MONTH(X6),DAY(X6)) -> 43281 | AD6: =DATE(YEAR(Y6)+1,MONTH(Y6),DAY(Y6)) -> 43373 | AE6: =DATE(YEAR(Z6)+1,MONTH(Z6),DAY(Z6)) -> 43465 | AF6: =CONCATENATE( "FY ", MID(AA6,4,4)+1, IF(RIGHT(AE5,1)="E", "E", "") ) -> FY 2018 | AG6: =DATE(YEAR(AB6)+1,MONTH(AB6),DAY(AB6)) -> 43555 | AH6: =DATE(YEAR(AC6)+1,MONTH(AC6),DAY(AC6)) -> 43646 | AI6: =DATE(YEAR(AD6)+1,MONTH(AD6),DAY(AD6)) -> 43738 | AJ6: =DATE(YEAR(AE6)+1,MONTH(AE6),DAY(AE6)) -> 43830 | AK6: =CONCATENATE( "FY ", MID(AF6,4,4)+1, IF(RIGHT(AJ5,1)="E", "E", "") ) -> FY 2019 | AL6: =DATE(YEAR(AG6)+1,MONTH(AG6),DAY(AG6)) -> 43921 | AM6: =DATE(YEAR(AH6)+1,MONTH(AH6),DAY(AH6)) -> 44012 | AN6: =DATE(YEAR(AI6)+1,MONTH(AI6),DAY(AI6)) -> 44104 | AO6: =DATE(YEAR(AJ6)+1,MONTH(AJ6),DAY(AJ6)) -> 44196 | AP6: =CONCATENATE( "FY ", MID(AK6,4,4)+1, IF(RIGHT(AO5,1)="E", "E", "") ) -> FY 2020 | AQ6: =DATE(YEAR(AL6)+1,MONTH(AL6),DAY(AL6)) -> 44286 | AR6: =DATE(YEAR(AM6)+1,MONTH(AM6),DAY(AM6)) -> 44377 | AS6: =DATE(YEAR(AN6)+1,MONTH(AN6),DAY(AN6)) -> 44469 | AT6: =DATE(YEAR(AO6)+1,MONTH(AO6),DAY(AO6)) -> 44561 | AU6: =CONCATENATE( "FY ", MID(AP6,4,4)+1, IF(RIGHT(AT5,1)="E", "E", "") ) -> FY 2021 | AV6: =DATE(YEAR(AQ6)+1,MONTH(AQ6),DAY(AQ6)) -> 44651 | AW6: =DATE(YEAR(AR6)+1,MONTH(AR6),DAY(AR6)) -> 44742 | AX6: =DATE(YEAR(AS6)+1,MONTH(AS6),DAY(AS6)) -> 44834 | AY6: =DATE(YEAR(AT6)+1,MONTH(AT6),DAY(AT6)) -> 44926 | AZ6: =CONCATENATE( "FY ", MID(AU6,4,4)+1, IF(RIGHT(AY5,1)="E", "E", "") ) -> FY 2022 | BA6: =DATE(YEAR(AV6)+1,MONTH(AV6),DAY(AV6)) -> 45016 | BB6: =DATE(YEAR(AW6)+1,MONTH(AW6),DAY(AW6)) -> 45107 | BC6: =DATE(YEAR(AX6)+1,MONTH(AX6),DAY(AX6)) -> 45199 | BD6: =DATE(YEAR(AY6)+1,MONTH(AY6),DAY(AY6)) -> 45291 | BE6: =CONCATENATE( "FY ", MID(AZ6,4,4)+1, IF(RIGHT(BD5,1)="E", "E", "") ) -> FY 2023 | BF6: =DATE(YEAR(BA6)+1,MONTH(BA6),DAY(BA6)) -> 45382 | BG6: =DATE(YEAR(BB6)+1,MONTH(BB6),DAY(BB6)) -> 45473 | BH6: =DATE(YEAR(BC6)+1,MONTH(BC6),DAY(BC6)) -> 45565 | BI6: =DATE(YEAR(BD6)+1,MONTH(BD6),DAY(BD6)) -> 45657 | BJ6: =CONCATENATE( "FY ", MID(BE6,4,4)+1, IF(RIGHT(BI5,1)="E", "E", "") ) -> FY 2024 | BK6: =DATE(YEAR(BF6)+1,MONTH(BF6),DAY(BF6)) -> 45747 | BL6: =DATE(YEAR(BG6)+1,MONTH(BG6),DAY(BG6)) -> 45838 | BM6: =DATE(YEAR(BH6)+1,MONTH(BH6),DAY(BH6)) -> 45930 | BN6: =DATE(YEAR(BI6)+1,MONTH(BI6),DAY(BI6)) -> 46022 | BO6: =CONCATENATE( "FY ", MID(BJ6,4,4)+1, IF(RIGHT(BN5,1)="E", "E", "") ) -> FY 2025 | BP6: =DATE(YEAR(BK6)+1,MONTH(BK6),DAY(BK6)) -> 46112 | BQ6: =DATE(YEAR(BL6)+1,MONTH(BL6),DAY(BL6)) -> 46203 | BR6: =DATE(YEAR(BM6)+1,MONTH(BM6),DAY(BM6)) -> 46295 | BS6: =DATE(YEAR(BN6)+1,MONTH(BN6),DAY(BN6)) -> 46387 | BT6: =CONCATENATE( "FY ", MID(BO6,4,4)+1, IF(RIGHT(BS5,1)="E", "E", "") ) -> FY 2026E | BU6: =DATE(YEAR(BP6)+1,MONTH(BP6),DAY(BP6)) -> 46477 | BV6: =DATE(YEAR(BQ6)+1,MONTH(BQ6),DAY(BQ6)) -> 46568 | BW6: =DATE(YEAR(BR6)+1,MONTH(BR6),DAY(BR6)) -> 46660 | BX6: =DATE(YEAR(BS6)+1,MONTH(BS6),DAY(BS6)) -> 46752 | BY6: =CONCATENATE( "FY ", MID(BT6,4,4)+1, IF(RIGHT(BX5,1)="E", "E", "") ) -> FY 2027E
B8: Aerospace & Industrial | C8: 249.2 | D8: 272.8 | E8: 272.7 | F8: 281.4 | G8: =SUM(C8:F8) -> 1076.1 | H8: 300.953 | I8: 313.798 | J8: 312.808 | K8: 300.538 | AG8: 215.21941 | AH8: 230.30368 | AI8: 218.06607 | AJ8: 228.8875 | AK8: =SUM(AG8:AJ8) -> 892.47666 | AL8: 208.03326 | AM8: 165.70081 | AN8: 172.24312 | AO8: 192.21352 | AP8: =SUM(AL8:AO8) -> 738.19071 | AQ8: 177.7 | AR8: 193.9 | AS8: 195.9 | AT8: 207.576 | AU8: =SUM(AQ8:AT8) -> 775.076 | AV8: 191.112 | AW8: 208.572 | AX8: 213.093 | AY8: 223.258 | AZ8: =SUM(AV8:AY8) -> 836.035 | BA8: 202.447 | BB8: 226.26 | BC8: 220.297 | BD8: 238.224 | BE8: =SUM(BA8:BD8) -> 887.228 | BF8: 219.325 | BG8: 233.232 | BH8: 228.659 | BI8: 250.917 | BJ8: =SUM(BF8:BI8) -> 932.133 | BK8: 227.246 | BL8: 239.138 | BM8: 247.985 | BN8: 262.391 | BO8: =SUM(BK8:BN8) -> 976.76
B9: Y/Y Growth | H9: =H8/C8-1 -> 0.20767657 | I9: =I8/D8-1 -> 0.15028592 | J9: =J8/E8-1 -> 0.14707737 | K9: =K8/F8-1 -> 0.06800995 | AL9: =AL8/AG8-1 -> -0.03338987 | AM9: =AM8/AH8-1 -> -0.28051167 | AN9: =AN8/AI8-1 -> -0.21013333 | AO9: =AO8/AJ8-1 -> -0.1602271 | AP9: =AP8/AK8-1 -> -0.17287393 | AQ9: =AQ8/AL8-1 -> -0.14580965 | AR9: =AR8/AM8-1 -> 0.17018137 | AS9: =AS8/AN8-1 -> 0.13734584 | ... BO9: =BO8/BJ8-1 -> 0.047876215
B10: Forward Year Guidance | AV10: 805-825 | AW10: 820-840 | AY10: 845-860 | AZ10: =AY10 -> 845-860 | BA10: 845-860 | BB10: 865-885 | BC10: 873-888 | BD10: 915-930 | BE10: =BD10 -> 915-930 | BF10: 915-930 | BG10: 925-940 | BH10: 925-940 | BI10: 960-975 | BJ10: =BI10 -> 960-975 | BK10: 960-975 | BL10: 965-980 | BM10: 970-980 | BN10: 1030-1045 | BO10: =BN10 -> 1030-1045
BT11: {=_xll.FDS("CW-US","FE_ESTIMATE(PRODLINE_SALES_1,MEAN,ANN_ROLL,+1,NOW,,,'')")} -> 1027.8357 | BY11: {=_xll.FDS("CW-US","FE_ESTIMATE(PRODLINE_SALES_1,MEAN,ANN_ROLL,+2,NOW,,,'')")} -> 1072.335
B12: Organic | AQ12: -0.22 | AR12: 0.1 | AS12: 0.03 | AT12: =+AT9 -> 0.079924047 | AU12: =((AQ12*AL$8)+(AR12*AM$8)+(AS12*AN$8)+(AT12*AO$8))/AP$8 -> -0.011741491 | AV12: 0.07 | AW12: 0.07 | AX12: 0.12 | AY12: 0.11 | AZ12: =((AV12*AQ$8)+(AW12*AR$8)+(AX12*AS$8)+(AY12*AT$8))/AU$8 -> 0.09335002 | BA12: 0.08 | BB12: 0.09 | BC12: 0.02 | BD12: 0.06 | BE12: =((BA12*AV$8)+(BB12*AW$8)+(BC12*AX$8)+(BD12*AY$8))/AZ$8 -> 0.061860783 | BF12: 0.08 | BG12: 0.03 | BH12: 0.03 | BI12: 0.05 | BJ12: =((BF12*BA$8)+(BG12*BB$8)+(BH12*BC$8)+(BI12*BD$8))/BE$8 -> 0.046779035 | BK12: 0.04 | BL12: 0.02 | BM12: 0.08 | BN12: 0.04 | BO12: =((BK12*BF$8)+(BL12*BG$8)+(BM12*BH$8)+(BN12*BI$8))/BJ$8 -> 0.044808026 | BT12: =BT11/BO8-1 -> 0.052290941 | BY12: =BY11/BT11-1 -> 0.043294176
B13: Acq. / Divest | AQ13: 0 | AR13: 0 | AS13: 0 | AT13: 0 | AU13: =((AQ13*AL$8)+(AR13*AM$8)+(AS13*AN$8)+(AT13*AO$8))/AP$8 -> 0 | AV13: 0 | AW13: 0 | AX13: 0 | AY13: 0.01 | AZ13: =((AV13*AQ$8)+(AW13*AR$8)+(AX13*AS$8)+(AY13*AT$8))/AU$8 -> 0.0026781374 | BA13: 0 | BB13: 0 | BC13: 0 | BD13: 0 | BE13: =((BA13*AV$8)+(BB13*AW$8)+(BC13*AX$8)+(BD13*AY$8))/AZ$8 -> 0 | BF13: 0 | BG13: 0 | BH13: 0 | BI13: 0 | BJ13: =((BF13*BA$8)+(BG13*BB$8)+(BH13*BC$8)+(BI13*BD$8))/BE$8 -> 0 | BK13: 0 | BL13: 0 | BM13: 0 | BN13: 0 | BO13: =((BK13*BF$8)+(BL13*BG$8)+(BM13*BH$8)+(BN13*BI$8))/BJ$8 -> 0
B14: FX | AQ14: 0.02 | AR14: 0.03 | AS14: 0.01 | AT14: 0 | AU14: =((AQ14*AL$8)+(AR14*AM$8)+(AS14*AN$8)+(AT14*AO$8))/AP$8 -> 0.014703681 | AV14: 0.01 | AW14: -0.03 | AX14: 0.03 | AY14: 0.04 | AZ14: =((AV14*AQ$8)+(AW14*AR$8)+(AX14*AS$8)+(AY14*AT$8))/AU$8 -> 0.01308264 | BA14: 0.02 | BB14: 0.01 | BC14: -0.01 | BD14: -0.01 | BE14: =((BA14*AV$8)+(BB14*AW$8)+(BC14*AX$8)+(BD14*AY$8))/AZ$8 -> 0.0018473509 | BF14: 0 | BG14: 0 | BH14: -0.01 | BI14: 0 | BJ14: =((BF14*BA$8)+(BG14*BB$8)+(BH14*BC$8)+(BI14*BD$8))/BE$8 -> -0.0024829807 | BK14: 0 | BL14: 0.01 | BM14: 0 | BN14: -0.01 | BO14: =((BK14*BF$8)+(BL14*BG$8)+(BM14*BH$8)+(BN14*BI$8))/BJ$8 -> -0.00018972614
B16: Commercial Aerospace | AP16: =+(AP$8-AP$20)*(28/(28+21)) -> 234.57412 | AU16: =+(AU$8-AU$20)*(26/(26+21)) -> 217.95468 | AZ16: =+AZ8-AZ18-AZ20 -> 233.07396 | BE16: =+BE8-BE18-BE20 -> 252.50149 | BJ16: =+BJ8-BJ18-BJ20 -> 288.56238 | BO16: =+BO8-BO18-BO20 -> 312.34298
B17: y/y | AU17: =+AU16/AP16-1 -> -0.070849409 | AZ17: =+AZ16/AU16-1 -> 0.069368901 | BE17: =+BE16/AZ16-1 -> 0.083353508 | BJ17: =+BJ16/BE16-1 -> 0.14281458 | BO17: =+BO16/BJ16-1 -> 0.082410588
B18: Aerospace Defense | AP18: =+(AP$8-AP$20)*(21/(28+21)) -> 175.93059 | AU18: =+(AU$8-AU$20)*(21/(26+21)) -> 176.04032 | AZ18: =+(AZ$8-AZ$20)*(21/(26+21)) -> 188.25204 | BE18: =+(BE$8-BE$20)*(21/(26+21)) -> 203.94351 | BJ18: =+(BJ$8-BJ$20)*(21/(26+21)) -> 233.06962 | BO18: =+(BO$8-BO$20)*(21/(26+21)) -> 252.27702
B19: y/y | AU19: =+AU18/AP18-1 -> 0.00062371356 | AZ19: =+AZ18/AU18-1 -> 0.069368901 | BE19: =+BE18/AZ18-1 -> 0.083353508 | BJ19: =+BJ18/BE18-1 -> 0.14281458 | BO19: =+BO18/BJ18-1 -> 0.082410588
B20: General Industrial | AP20: 327.686 | AU20: 381.081 | AZ20: 414.709 | BE20: 430.783 | BJ20: 410.501 | BO20: 412.14
B21: y/y | AU21: =+AU20/AP20-1 -> 0.16294562 | AW21: MSD | AZ21: =+AZ20/AU20-1 -> 0.088243707 | BE21: =+BE20/AZ20-1 -> 0.038759709 | BJ21: =+BJ20/BE20-1 -> -0.047081709 | BO21: =+BO20/BJ20-1 -> 0.0039926821
B23: Defense Electronics | C23: 108.1 | D23: 113.4 | E23: 105.8 | F23: 153 | G23: =SUM(C23:F23) -> 480.3 | H23: 112.371 | I23: 118.507 | J23: 127.061 | K23: 131.918 | AG23: 110.30102 | AH23: 133.70865 | AI23: 134.96496 | AJ23: 146.46782 | AK23: =SUM(AG23:AJ23) -> 525.44245 | AL23: 139.581 | AM23: 139.812 | AN23: 149.073 | AO23: 182.173 | AP23: =SUM(AL23:AO23) -> 610.639 | AQ23: 182.3 | AR23: 163.4 | AS23: 182.6 | AT23: 199.619 | AU23: =SUM(AQ23:AT23) -> 727.919 | AV23: 143.069 | AW23: 149.549 | AX23: 161.188 | AY23: 236.456 | AZ23: =SUM(AV23:AY23) -> 690.262 | BA23: 162.154 | BB23: 197.722 | BC23: 216.285 | BD23: 239.751 | BE23: =SUM(BA23:BD23) -> 815.912 | BF23: 211.741 | BG23: 228.461 | BH23: 243.029 | BI23: 227.475 | BJ23: =SUM(BF23:BI23) -> 910.706 | BK23: 245.164 | BL23: 253.011 | BM23: 253.159 | BN23: 267.276 | BO23: =SUM(BK23:BN23) -> 1018.61
B24: Y/Y Growth | H24: =H23/C23-1 -> 0.039509713 | I24: =I23/D23-1 -> 0.045035273 | J24: =J23/E23-1 -> 0.20095463 | K24: =K23/F23-1 -> -0.13779085 | AL24: =AL23/AG23-1 -> 0.26545515 | AM24: =AM23/AH23-1 -> 0.045646668 | AN24: =AN23/AI23-1 -> 0.10453111 | AO24: =AO23/AJ23-1 -> 0.2437749 | AP24: =AP23/AK23-1 -> 0.16214249 | AQ24: =AQ23/AL23-1 -> 0.30605168 | AR24: =AR23/AM23-1 -> 0.16871227 | AS24: =AS23/AN23-1 -> 0.22490324 | ... BO24: =BO23/BJ23-1 -> 0.1184839
B25: Forward Year Guidance | AV25: 745-760 | AW25: 720-735 | AX25: 675-690 | AY25: 725-750 | AZ25: =AY25 -> 725-750 | BA25: 725-750 | BB25: 755-775 | BC25: 775-790 | BD25: 857-872 | BE25: =BD25 -> 857-872 | BF25: 882-897 | BG25: 882-897 | BH25: 892-907 | BI25: 975-990 | BJ25: =BI25 -> 975-990 | BK25: 995-1010 | BL25: 995-1010 | BM25: 1000-1010 | BN25: 1055-1075 | BO25: =BN25 -> 1055-1075
B26: Consensus | BT26: {=_xll.FDS("CW-US","FE_ESTIMATE(PRODLINE_SALES_2,MEAN,ANN_ROLL,+1,NOW,,,'')")} -> 1082.9347 | BY26: {=_xll.FDS("CW-US","FE_ESTIMATE(PRODLINE_SALES_2,MEAN,ANN_ROLL,+2,NOW,,,'')")} -> 1167.366
B27: Organic | AQ27: 0.04 | AR27: -0.06 | AS27: -0.03 | AT27: 0.04 | AU27: =((AQ27*AL$23)+(AR27*AM$23)+(AS27*AN$23)+(AT27*AO$23))/AP$23 -> 1.5148066e-05 | AV27: -0.21 | AW27: -0.07 | AX27: -0.1 | AY27: 0.185 | AZ27: =((AV27*AQ$23)+(AW27*AR$23)+(AX27*AS$23)+(AY27*AT$23))/AU$23 -> -0.042657885 | BA27: 0.14 | BB27: 0.32 | BC27: 0.33 | BD27: 0.01 | BE27: =((BA27*AV$23)+(BB27*AW$23)+(BC27*AX$23)+(BD27*AY$23))/AZ$23 -> 0.17883346 | BF27: 0.31 | BG27: 0.16 | BH27: 0.12 | BI27: -0.05 | BJ27: =((BF27*BA$23)+(BG27*BB$23)+(BH27*BC$23)+(BI27*BD$23))/BE$23 -> 0.11750031 | BK27: 0.16 | BL27: 0.1 | BM27: 0.04 | BN27: 0.17 | BO27: =((BK27*BF$23)+(BL27*BG$23)+(BM27*BH$23)+(BN27*BI$23))/BJ$23 -> 0.11542317 | BT27: =BT26/BO23-1 -> 0.063149488 | BY27: =BY26/BT26-1 -> 0.077965273
B28: Acq. / Divest | AQ28: 0.25 | AR28: 0.22 | AS28: 0.25 | AT28: 0.06 | AU28: =((AQ28*AL$23)+(AR28*AM$23)+(AS28*AN$23)+(AT28*AO$23))/AP$23 -> 0.18644816 | AV28: 0 | AW28: 0 | AX28: 0 | AY28: 0 | AZ28: =((AV28*AQ$23)+(AW28*AR$23)+(AX28*AS$23)+(AY28*AT$23))/AU$23 -> 0 | BA28: 0 | BB28: 0 | BC28: 0 | BD28: 0 | BE28: =((BA28*AV$23)+(BB28*AW$23)+(BC28*AX$23)+(BD28*AY$23))/AZ$23 -> 0 | BF28: 0 | BG28: 0 | BH28: 0 | BI28: 0 | BJ28: =((BF28*BA$23)+(BG28*BB$23)+(BH28*BC$23)+(BI28*BD$23))/BE$23 -> 0 | BK28: 0 | BL28: 0 | BM28: 0 | BN28: 0 | BO28: =((BK28*BF$23)+(BL28*BG$23)+(BM28*BH$23)+(BN28*BI$23))/BJ$23 -> 0
B29: FX | AQ29: 0.01 | AR29: 0 | AS29: 0 | AT29: 0 | AU29: =((AQ29*AL$23)+(AR29*AM$23)+(AS29*AN$23)+(AT29*AO$23))/AP$23 -> 0.0022858186 | AV29: 0 | AW29: 0.01 | AX29: -0.01 | AY29: 0 | AZ29: =((AV29*AQ$23)+(AW29*AR$23)+(AX29*AS$23)+(AY29*AT$23))/AU$23 -> -0.00026376561 | BA29: 0.01 | BB29: 0 | BC29: -0.01 | BD29: 0 | BE29: =((BA29*AV$23)+(BB29*AW$23)+(BC29*AX$23)+(BD29*AY$23))/AZ$23 -> -0.00026249453 | BF29: -0.01 | BG29: 0 | BH29: 0 | BI29: 0 | BJ29: =((BF29*BA$23)+(BG29*BB$23)+(BH29*BC$23)+(BI29*BD$23))/BE$23 -> -0.0019873957 | BK29: 0 | BL29: 0.01 | BM29: 0 | BN29: 0 | BO29: =((BK29*BF$23)+(BL29*BG$23)+(BM29*BH$23)+(BN29*BI$23))/BJ$23 -> 0.0025086142
B31: Commercial Aerospace | AP31: =+(AP$23-AP$35-AP$37)*(7/(7+45)) -> 38.653418 | AU31: =+(AU$23-AU$35-AU$37)*(6/(6+45)) -> 37.061765 | AZ31: =276.519-AZ16 -> 43.445043 | BE31: =324.949-BE16 -> 72.447511 | BJ31: =378.086-BJ16 -> 89.523617 | BO31: =430.109-BO16 -> 117.76602
B32: y/y | AU32: =+AU31/AP31-1 -> -0.041177561 | AZ32: =+AZ31/AU31-1 -> 0.17223351 | BE32: =+BE31/AZ31-1 -> 0.6675668 | BJ32: =+BJ31/BE31-1 -> 0.23570315 | BO32: =+BO31/BJ31-1 -> 0.31547434
B33: Aerospace Defense | AP33: =+(AP$23-AP$35-AP$37)*(45/(7+45)) -> 248.48626 | AU33: =+(AU$23-AU$35-AU$37)*(45/(6+45)) -> 277.96324 | AZ33: =479.743-AZ18 -> 291.49096 | BE33: =551.622-BE18 -> 347.67849 | BJ33: =616.59-BJ18 -> 383.52038 | BO33: =672.526-BO18 -> 420.24898
B34: y/y | AU34: =+AU33/AP33-1 -> 0.11862618 | AZ34: =+AZ33/AU33-1 -> 0.048667307 | BE34: =+BE33/AZ33-1 -> 0.19275909 | BJ34: =+BJ33/BE33-1 -> 0.10308919 | BO34: =+BO33/BJ33-1 -> 0.095766998
B35: Ground Defense | AP35: 107.448 | AU35: 223.89 | AZ35: 219.739 | BE35: 308.008 | BJ35: 353.326 | BO35: 406.803
B36: y/y | AU36: =+AU35/AP35-1 -> 1.0837056 | AZ36: =+AZ35/AU35-1 -> -0.018540355 | BE36: =+BE35/AZ35-1 -> 0.40169929 | BJ36: =+BJ35/BE35-1 -> 0.14713254 | BO36: =+BO35/BJ35-1 -> 0.15135314
B37: Naval Defense | AP37: =692.152-AP48 -> 216.05132 | AU37: =710.688-AU48 -> 189.004 | AZ37: =694.015-AZ48 -> 135.587 | BE37: =720.013-BE48 -> 87.778 | BJ37: =821.898-BJ48 -> 84.336 | BO37: =941.654-BO48 -> 73.792
B38: y/y | AU38: =+AU37/AP37-1 -> -0.12518934 | AZ38: =+AZ37/AU37-1 -> -0.28262365 | BE38: =+BE37/AZ37-1 -> -0.35260755 | BJ38: =+BJ37/BE37-1 -> -0.039212559 | BO38: =+BO37/BJ37-1 -> -0.12502371
B40: Naval & Power | C40: 137.1 | D40: 137.9 | E40: 132.9 | F40: 153.8 | G40: =SUM(C40:F40) -> 561.7 | H40: 129.635 | I40: 136.893 | J40: 118.514 | K40: 140.13 | AG40: 229.40577 | AH40: 247.97098 | AI40: 233.41161 | AJ40: 250.09977 | AK40: =SUM(AG40:AJ40) -> 960.88813 | AL40: 228.04815 | AM40: 227.18944 | AN40: 228.62577 | AO40: 267.07931 | AP40: =SUM(AL40:AO40) -> 950.94268 | AQ40: 229.9 | AR40: 252 | AS40: 235.3 | AT40: 248.104 | AU40: =SUM(AQ40:AT40) -> 965.304 | AV40: 225.28 | AW40: 251.236 | AX40: 256.261 | AY40: 297.951 | AZ40: =SUM(AV40:AY40) -> 1030.728 | BA40: 266.259 | BB40: 280.414 | BC40: 287.744 | BD40: 307.816 | BE40: =SUM(BA40:BD40) -> 1142.233 | BF40: 282.101 | BG40: 323.098 | BH40: 327.23 | BI40: 345.921 | BJ40: =SUM(BF40:BI40) -> 1278.35 | BK40: 333.235 | BL40: 384.427 | BM40: 368.026 | BN40: 417.314 | BO40: =SUM(BK40:BN40) -> 1503.002
B41: Y/Y Growth | H41: =H40/C40-1 -> -0.054449307 | I41: =I40/D40-1 -> -0.007302393 | J41: =J40/E40-1 -> -0.1082468 | K41: =K40/F40-1 -> -0.088881664 | AL41: =AL40/AG40-1 -> -0.0059179569 | AM41: =AM40/AH40-1 -> -0.083806329 | AN41: =AN40/AI40-1 -> -0.020503848 | AO41: =AO40/AJ40-1 -> 0.067891053 | AP41: =AP40/AK40-1 -> -0.010350268 | AQ41: =AQ40/AL40-1 -> 0.0081204165 | AR41: =AR40/AM40-1 -> 0.10920647 | AS41: =AS40/AN40-1 -> 0.029192816 | ... BO41: =BO40/BJ40-1 -> 0.17573591
B42: Forward Year Guidance | AV42: 980-995 | AW42: 1030-1045 | AY42: 1085-1100 | AZ42: =AY42 -> 1085-1100 | BA42: 1085-1100 | BB42: 1110-1130 | BC42: 1117-1137 | BD42: 1188-1208 | BE42: =BD42 -> 1188-1208 | BF42: 1188-1208 | BG42: 1203-1223 | BH42: 1233-1248 | BI42: 1400-1420 | BJ42: =BI42 -> 1400-1420 | BK42: 1410-1430 | BL42: 1430-1445 | BM42: 1450-1465 | BN42: 1625-1645 | BO42: =BN42 -> 1625-1645
B43: Consensus | BT43: {=_xll.FDS("CW-US","FE_ESTIMATE(PRODLINE_SALES_3,MEAN,ANN_ROLL,+1,NOW,,,'')")} -> 1592.35 | BY43: {=_xll.FDS("CW-US","FE_ESTIMATE(PRODLINE_SALES_3,MEAN,ANN_ROLL,+2,NOW,,,'')")} -> 1752.518
B44: Organic | AQ44: -0.01 | AR44: 0.1 | AS44: 0.03 | AT44: =+AT41 -> -0.071047476 | AU44: =((AQ44*AL$40)+(AR44*AM$40)+(AS44*AN$40)+(AT44*AO$40))/AP$40 -> 0.0087512371 | AV44: -0.04 | AW44: -0.03 | AX44: 0 | AY44: 0.12 | AZ44: =((AV44*AQ$40)+(AW44*AR$40)+(AX44*AS$40)+(AY44*AT$40))/AU$40 -> 0.013484332 | BA44: 0.11 | BB44: 0.03 | BC44: 0.12 | BD44: 0.03 | BE44: =((BA44*AV$40)+(BB44*AW$40)+(BC44*AX$40)+(BD44*AY$40))/AZ$40 -> 0.06986104 | BF44: 0.06 | BG44: 0.14 | BH44: 0.13 | BI44: 0.12 | BJ44: =((BF44*BA$40)+(BG44*BB$40)+(BH44*BC$40)+(BI44*BD$40))/BE$40 -> 0.11344283 | BK44: 0.18 | BL44: 0.12 | BM44: 0.08 | BN44: 0.13 | BO44: =((BK44*BF$40)+(BL44*BG$40)+(BM44*BH$40)+(BN44*BI$40))/BJ$40 -> 0.12570741 | BT44: =BT43/BO40-1 -> 0.059446361 | BY44: =BY43/BT43-1 -> 0.10058593
B45: Acq. / Divest | AQ45: 0.01 | AR45: 0 | AS45: 0 | AT45: 0 | AU45: =((AQ45*AL$40)+(AR45*AM$40)+(AS45*AN$40)+(AT45*AO$40))/AP$40 -> 0.0023981272 | AV45: 0 | AW45: 0 | AX45: -0.06 | AY45: 0.09 | AZ45: =((AV45*AQ$40)+(AW45*AR$40)+(AX45*AS$40)+(AY45*AT$40))/AU$40 -> 0.0085065016 | BA45: -0.07 | BB45: -0.09 | BC45: 0 | BD45: 0 | BE45: =((BA45*AV$40)+(BB45*AW$40)+(BC45*AX$40)+(BD45*AY$40))/AZ$40 -> -0.037236633 | BF45: 0 | BG45: -0.01 | BH45: -0.01 | BI45: 0 | BJ45: =((BF45*BA$40)+(BG45*BB$40)+(BH45*BC$40)+(BI45*BD$40))/BE$40 -> -0.004974099 | BK45: -0.07 | BL45: 0 | BM45: -0.04 | BN45: -0.08 | BO45: =((BK45*BF$40)+(BL45*BG$40)+(BM45*BH$40)+(BN45*BI$40))/BJ$40 -> -0.047334415
B46: FX | AQ46: 0 | AR46: 0.01 | AS46: 0.01 | AT46: 0 | AU46: =((AQ46*AL$40)+(AR46*AM$40)+(AS46*AN$40)+(AT46*AO$40))/AP$40 -> 0.0047932985 | AV46: 0 | AW46: 0 | AX46: 0 | AY46: -0.01 | AZ46: =((AV46*AQ$40)+(AW46*AR$40)+(AX46*AS$40)+(AY46*AT$40))/AU$40 -> -0.0025702162 | BA46: 0 | BB46: 0 | BC46: 0 | BD46: 0 | BE46: =((BA46*AV$40)+(BB46*AW$40)+(BC46*AX$40)+(BD46*AY$40))/AZ$40 -> 0 | BF46: 0 | BG46: 0 | BH46: 0 | BI46: 0 | BJ46: =((BF46*BA$40)+(BG46*BB$40)+(BH46*BC$40)+(BI46*BD$40))/BE$40 -> 0 | BK46: 0.01 | BL46: 0.07 | BM46: 0 | BN46: 0 | BO46: =((BK46*BF$40)+(BL46*BG$40)+(BM46*BH$40)+(BN46*BI$40))/BJ$40 -> 0.019898987
B48: Naval Defense | AP48: =+AP40-AP50 -> 476.10068 | AU48: =+AU40-AU50 -> 521.684 | AZ48: =+AZ40-AZ50 -> 558.428 | BE48: =+BE40-BE50 -> 632.235 | BJ48: =+BJ40-BJ50 -> 737.562 | BO48: =+BO40-BO50 -> 867.862
B49: y/y | AU49: =+AU48/AP48-1 -> 0.095743031 | AZ49: =+AZ48/AU48-1 -> 0.070433442 | BE49: =+BE48/AZ48-1 -> 0.13216923 | BJ49: =+BJ48/BE48-1 -> 0.1665947 | BO49: =+BO48/BJ48-1 -> 0.17666311
B50: Power & Process | AP50: 474.842 | AU50: 443.62 | AZ50: 472.3 | BE50: 509.998 | BJ50: 540.788 | BO50: 635.14
B51: y/y | AU51: =+AU50/AP50-1 -> -0.065752398 | AZ51: =+AZ50/AU50-1 -> 0.064649926 | BE51: =+BE50/AZ50-1 -> 0.079817912 | BJ51: =+BJ50/BE50-1 -> 0.060372786 | BO51: =+BO50/BJ50-1 -> 0.17447133
B53: Process | AU53: =0.4*AU50 -> 177.448 | AZ53: =+AZ50-AZ55 -> 188.92 | BE53: =+BE50-BE55 -> 203.9992 | BJ53: =+BJ50-BJ55 -> 216.3152 | BO53: =+BO50-BO55 -> 222.299
B54: y/y | AZ54: =+AZ53/AU53-1 -> 0.064649926 | BE54: =+BE53/AZ53-1 -> 0.079817912 | BJ54: =+BJ53/BE53-1 -> 0.060372786 | BO54: =+BO53/BJ53-1 -> 0.027662411
B55: Nuclear | AU55: =0.6*CW_Drivers!BN57 -> 266.1714 | AZ55: =0.6*CW_Drivers!BS57 -> 283.38 | BE55: =0.6*CW_Drivers!BX57 -> 305.9988 | BJ55: =0.6*CW_Drivers!CC57 -> 324.4728 | BO55: =0.65*CW_Drivers!CH57 -> 412.841
B56: y/y | AZ56: =+AZ55/AU55-1 -> 0.064652326 | BE56: =+BE55/AZ55-1 -> 0.079817912 | BJ56: =+BJ55/BE55-1 -> 0.060372786 | BO56: =+BO55/BJ55-1 -> 0.27234394
B58: Nuclear OEM | AU58: =AU55*0.1 -> 26.61714 | AZ58: =AZ55*0.1 -> 28.338 | BE58: =BE55*0.1 -> 30.59988 | BJ58: =BJ55*0.1 -> 32.44728 | BO58: =BO55*0.1 -> 41.2841
B59: y/y | AZ59: =+AZ58/AU58-1 -> 0.064652326 | BE59: =+BE58/AZ58-1 -> 0.079817912 | BJ59: =+BJ58/BE58-1 -> 0.060372786 | BO59: =+BO58/BJ58-1 -> 0.27234394
B60: Nuclear Aftermarket | AU60: =AU55*0.9 -> 239.55426 | AZ60: =AZ55*0.9 -> 255.042 | BE60: =BE55*0.9 -> 275.39892 | BJ60: =BJ55*0.9 -> 292.02552 | BO60: =BO55*0.9 -> 371.5569
B61: y/y | AZ61: =AZ60/AU60-1 -> 0.064652326 | BE61: =BE60/AZ60-1 -> 0.079817912 | BJ61: =BJ60/BE60-1 -> 0.060372786 | BO61: =BO60/BJ60-1 -> 0.27234394
B63: Total Revenue | C63: 494.4 | D63: 524.1 | E63: 511.4 | F63: 588.2 | G63: 2118.1 | H63: 542.959 | I63: 569.198 | J63: 558.383 | K63: 572.586 | L63: 2243.126 | M63: 546.199 | N63: 545.194 | O63: 525.535 | P63: 588.755 | Q63: 2205.683 | R63: 503.507 | S63: 532.766 | T63: 507.092 | U63: 565.566 | V63: 2108.931 | W63: 523.591 | X63: 567.653 | Y63: 567.901 | Z63: 611.881 | AA63: 2271.026 | AB63: 547.522 | AC63: 620.298 | AD63: 595.393 | AE63: 648.622 | AF63: 2411.835 | AG63: =SUM(AG8,AG23,AG40, ) -> 554.9262 | AH63: =SUM(AH8,AH23,AH40, ) -> 611.9833 | AI63: =SUM(AI8,AI23,AI40, ) -> 586.44264 | AJ63: =SUM(AJ8,AJ23,AJ40, ) -> 625.45509 | AK63: =SUM(AK8,AK23,AK40, ) -> 2378.8072 | AL63: =SUM(AL8,AL23,AL40, ) -> 575.66241 | AM63: =SUM(AM8,AM23,AM40, ) -> 532.70225 | AN63: =SUM(AN8,AN23,AN40, ) -> 549.94189 | ... BO63: =SUM(BO8,BO23,BO40, ) -> 3498.372
B64: Y/Y Growth | H64: =H63/C63-1 -> 0.098218042 | I64: =I63/D63-1 -> 0.086048464 | J64: =J63/E63-1 -> 0.091871334 | K64: =K63/F63-1 -> -0.026545393 | L64: =L63/G63-1 -> 0.05902743 | M64: =M63/H63-1 -> 0.0059673014 | N64: =N63/I63-1 -> -0.042171617 | O64: =O63/J63-1 -> -0.058827006 | ... BO64: =BO63/BJ63-1 -> 0.12084593
B65: Organic | Q65: - | R65: -0.02 | S65: -0.02 | T65: -0.03 | U65: -0.03 | V65: -0.04 | W65: 0.03 | X65: 0.05 | Y65: 0.08 | Z65: 0.03 | AA65: 0.05 | AB65: 0.03 | AC65: 0.04 | AD65: 0.02 | AE65: 0.03 | AF65: 0.03 | AG65: 0.02 | AH65: 0.03 | AI65: 0.03 | AJ65: 0.01 | AK65: 0.02 | AL65: 0.01 | AM65: -0.17 | AN65: -0.1 | AO65: -0.05 | AP65: =((AL65*AG$63)+(AM65*AH$63)+(AN65*AI$63)+(AO65*AJ$63))/AK$63 -> -0.079201423 | AQ65: -0.08 | AR65: =((AR12*AM$8)+(AR27*AM$23)+(AR44*AM$40))/AM$63 -> 0.05800671 | AS65: =((AS12*AN$8)+(AS27*AN$23)+(AS44*AN$40))/AN$63 -> 0.013735773 | AT65: =((AT12*AO$8)+(AT27*AO$23)+(AT44*AO$40))/AO$63 -> 0.0057276492 | AU65: =((AQ65*AL$63)+(AR65*AM$63)+(AS65*AN$63)+(AT65*AO$63))/AP$63 -> -0.0017065687 | AV65: =((AV12*AQ$8)+(AV27*AQ$23)+(AV44*AQ$40))/AQ$63 -> -0.059399898 | AW65: =((AW12*AR$8)+(AW27*AR$23)+(AW44*AR$40))/AR$63 -> -0.0089036599 | AX65: =((AX12*AS$8)+(AX27*AS$23)+(AX44*AS$40))/AS$63 -> 0.0085500163 | AY65: =((AY12*AT$8)+(AY27*AT$23)+(AY44*AT$40))/AT$63 -> 0.13663283 | AZ65: =((AV65*AQ$63)+(AW65*AR$63)+(AX65*AS$63)+(AY65*AT$63))/AU$63 -> 0.022006392 | BA65: =((BA12*AV$8)+(BA27*AV$23)+(BA44*AV$40))/AV$63 -> 0.10742379 | BB65: =((BB12*AW$8)+(BB27*AW$23)+(BB44*AW$40))/AW$63 -> 0.12170901 | BC65: =((BC12*AX$8)+(BC27*AX$23)+(BC44*AX$40))/AX$63 -> 0.13988794 | BD65: =((BD12*AY$8)+(BD27*AY$23)+(BD44*AY$40))/AY$63 -> 0.032598272 | BE65: =((BA65*AV$63)+(BB65*AW$63)+(BC65*AX$63)+(BD65*AY$63))/AZ$63 -> 0.096662117 | BF65: =((BF12*BA$8)+(BF27*BA$23)+(BF44*BA$40))/BA$63 -> 0.13067723 | BG65: =((BG12*BB$8)+(BG27*BB$23)+(BG44*BB$40))/BB$63 -> 0.11028069 | BH65: =((BH12*BC$8)+(BH27*BC$23)+(BH44*BC$40))/BC$63 -> 0.096599915 | BI65: =((BI12*BD$8)+(BI27*BD$23)+(BI44*BD$40))/BD$63 -> 0.046910145 | BJ65: =((BF65*BA$63)+(BG65*BB$63)+(BH65*BC$63)+(BI65*BD$63))/BE$63 -> 0.093819587 | BK65: =((BK12*BF$8)+(BK27*BF$23)+(BK44*BF$40))/BF$63 -> 0.13100682 | BL65: =((BL12*BG$8)+(BL27*BG$23)+(BL44*BG$40))/BG$63 -> 0.084458792 | BM65: =((BM12*BH$8)+(BM27*BH$23)+(BM44*BH$40))/BH$63 -> 0.067832093 | BN65: =((BN12*BI$8)+(BN27*BI$23)+(BN44*BI$40))/BI$63 -> 0.11364271 | BO65: =((BK65*BF$63)+(BL65*BG$63)+(BM65*BH$63)+(BN65*BI$63))/BJ$63 -> 0.098546317
B66: Acq. / Divest | Q66: - | R66: - | S66: - | T66: - | U66: - | V66: - | W66: 0.02 | X66: 0.03 | Y66: 0.04 | Z66: 0.04 | AA66: 0.03 | AB66: - | AC66: 0.04 | AD66: 0.03 | AE66: 0.04 | AF66: 0.03 | AG66: 0.05 | AH66: 0.01 | AI66: 0.01 | AJ66: 0.01 | AK66: 0.02 | AL66: 0.03 | AM66: 0.03 | AN66: 0.03 | AO66: 0.06 | AP66: =((AL66*AG$63)+(AM66*AH$63)+(AN66*AI$63)+(AO66*AJ$63))/AK$63 -> 0.037887841 | AQ66: 0.06 | AR66: =((AR13*AM$8)+(AR28*AM$23)+(AR45*AM$40))/AM$63 -> 0.057740773 | AS66: =((AS13*AN$8)+(AS28*AN$23)+(AS45*AN$40))/AN$63 -> 0.067767614 | AT66: =((AT13*AO$8)+(AT28*AO$23)+(AT45*AO$40))/AO$63 -> 0.017039692 | AU66: =((AQ66*AL$63)+(AR66*AM$63)+(AS66*AN$63)+(AT66*AO$63))/AP$63 -> 0.049351412 | AV66: =((AV13*AQ$8)+(AV28*AQ$23)+(AV45*AQ$40))/AQ$63 -> 0 | AW66: =((AW13*AR$8)+(AW28*AR$23)+(AW45*AR$40))/AR$63 -> 0 | AX66: =((AX13*AS$8)+(AX28*AS$23)+(AX45*AS$40))/AS$63 -> -0.023000978 | AY66: =((AY13*AT$8)+(AY28*AT$23)+(AY45*AT$40))/AT$63 -> 0.037242724 | AZ66: =((AV66*AQ$63)+(AW66*AR$63)+(AX66*AS$63)+(AY66*AT$63))/AU$63 -> 0.0041676961 | BA66: =((BA13*AV$8)+(BA28*AV$23)+(BA45*AV$40))/AV$63 -> -0.02818713 | BB66: =((BB13*AW$8)+(BB28*AW$23)+(BB45*AW$40))/AW$63 -> -0.037106721 | BC66: =((BC13*AX$8)+(BC28*AX$23)+(BC45*AX$40))/AX$63 -> 0 | BD66: =((BD13*AY$8)+(BD28*AY$23)+(BD45*AY$40))/AY$63 -> 0 | BE66: =((BA66*AV$63)+(BB66*AW$63)+(BC66*AX$63)+(BD66*AY$63))/AZ$63 -> -0.015009959 | BF66: =((BF13*BA$8)+(BF28*BA$23)+(BF45*BA$40))/BA$63 -> 0 | BG66: =((BG13*BB$8)+(BG28*BB$23)+(BG45*BB$40))/BB$63 -> -0.0039809141 | BH66: =((BH13*BC$8)+(BH28*BC$23)+(BH45*BC$40))/BC$63 -> -0.0039725759 | BI66: =((BI13*BD$8)+(BI28*BD$23)+(BI45*BD$40))/BD$63 -> 0 | BJ66: =((BF66*BA$63)+(BG66*BB$63)+(BH66*BC$63)+(BI66*BD$63))/BE$63 -> -0.0019967786 | BK66: =((BK13*BF$8)+(BK28*BF$23)+(BK45*BF$40))/BF$63 -> -0.027689265 | BL66: =((BL13*BG$8)+(BL28*BG$23)+(BL45*BG$40))/BG$63 -> 0 | BM66: =((BM13*BH$8)+(BM28*BH$23)+(BM45*BH$40))/BH$63 -> -0.016383659 | BN66: =((BN13*BI$8)+(BN28*BI$23)+(BN45*BI$40))/BI$63 -> -0.033571811 | BO66: =((BK66*BF$63)+(BL66*BG$63)+(BM66*BH$63)+(BN66*BI$63))/BJ$63 -> -0.019386827
B67: FX | Q67: -0.02 | R67: - | S67: - | T67: -0.01 | U67: -0.01 | V67: - | W67: -0.01 | X67: -0.01 | Y67: - | Z67: 0.01 | AA67: - | AB67: 0.02 | AC67: 0.01 | AD67: - | AE67: -0.01 | AF67: - | AG67: -0.01 | AH67: -0.01 | AI67: -0.01 | AJ67: -0.01 | AK67: -0.01 | AL67: 0 | AM67: 0 | AN67: 0 | AO67: 0.01 | AP67: =((AL67*AG$63)+(AM67*AH$63)+(AN67*AI$63)+(AO67*AJ$63))/AK$63 -> 0.0026292803 | AQ67: 0.01 | AR67: 0.01 | AS67: =((AS14*AN$8)+(AS29*AN$23)+(AS46*AN$40))/AN$63 -> 0.0072892954 | AT67: =((AT14*AO$8)+(AT29*AO$23)+(AT46*AO$40))/AO$63 -> 0 | AU67: =((AQ67*AL$63)+(AR67*AM$63)+(AS67*AN$63)+(AT67*AO$63))/AP$63 -> 0.0065625345 | AV67: =((AV14*AQ$8)+(AV29*AQ$23)+(AV46*AQ$40))/AQ$63 -> 0.003012375 | AW67: =((AW14*AR$8)+(AW29*AR$23)+(AW46*AR$40))/AR$63 -> -0.0068652552 | AX67: =((AX14*AS$8)+(AX29*AS$23)+(AX46*AS$40))/AS$63 -> 0.0065998697 | AY67: =((AY14*AT$8)+(AY29*AT$23)+(AY46*AT$40))/AT$63 -> 0.0088844939 | AZ67: =((AV67*AQ$63)+(AW67*AR$63)+(AX67*AS$63)+(AY67*AT$63))/AU$63 -> 0.0030251602 | BA67: =((BA14*AV$8)+(BA29*AV$23)+(BA46*AV$40))/AV$63 -> 0.0093892693 | BB67: =((BB14*AW$8)+(BB29*AW$23)+(BB46*AW$40))/AW$63 -> 0.0034228211 | BC67: =((BC14*AX$8)+(BC29*AX$23)+(BC46*AX$40))/AX$63 -> -0.0059358615 | BD67: =((BD14*AY$8)+(BD29*AY$23)+(BD46*AY$40))/AY$63 -> -0.0029466585 | BE67: =((BA67*AV$63)+(BB67*AW$63)+(BC67*AX$63)+(BD67*AY$63))/AZ$63 -> 0.00053314301 | BF67: =((BF14*BA$8)+(BF29*BA$23)+(BF46*BA$40))/BA$63 -> -0.0025703643 | BG67: =((BG14*BB$8)+(BG29*BB$23)+(BG46*BB$40))/BB$63 -> 0 | BH67: =((BH14*BC$8)+(BH29*BC$23)+(BH46*BC$40))/BC$63 -> -0.0030414068 | BI67: =((BI14*BD$8)+(BI29*BD$23)+(BI46*BD$40))/BD$63 -> 0 | BJ67: =((BF67*BA$63)+(BG67*BB$63)+(BH67*BC$63)+(BI67*BD$63))/BE$63 -> -0.0013441155 | BK67: =((BK14*BF$8)+(BK29*BF$23)+(BK46*BF$40))/BF$63 -> 0.0039556093 | BL67: =((BL14*BG$8)+(BL29*BG$23)+(BL46*BG$40))/BG$63 -> 0.034701965 | BM67: =((BM14*BH$8)+(BM29*BH$23)+(BM46*BH$40))/BH$63 -> 0 | BN67: =((BN14*BI$8)+(BN29*BI$23)+(BN46*BI$40))/BI$63 -> -0.003043953 | BO67: =((BK67*BF$63)+(BL67*BG$63)+(BM67*BH$63)+(BN67*BI$63))/BJ$63 -> 0.0088253643
B68: Forward Year Guidance | AJ68: 2590-2630 | AK68: =AJ68 -> 2590-2630 | AO68: 2445-2495 | AP68: =AO68 -> 2445-2495 | AQ68: 2450-2500 | AR68: 2465-2515 | AT68: 2530-2580 | AU68: =AT68 -> 2530-2580 | AW68: 2570-2620 | AX68: 2525-2575 | AY68: 2655-2710 | AZ68: =AY68 -> 2655-2710 | BA68: 2655-2710 | BB68: 2730-2790 | BC68: 2765-2815 | BD68: 2960-3010 | BE68: =BD68 -> 2960-3010 | BF68: 2985-3035 | BG68: 3010-3060 | BH68: 3050-2095 | BI68: 3335-3385 | BJ68: =BI68 -> 3335-3385 | BK68: 3365-3415 | BL68: 3390-3435 | BM68: =CW_Drivers!CF79 -> 3420-3455 | BN68: =CW_Drivers!CG79 -> 3710-3765 | BO68: =BN68 -> 3710-3765
B70: Operating Margins
B71: =B8 -> Aerospace & Industrial | C71: =C78/C8 -> 0.10152488 | D71: =D78/D8 -> 0.12316716 | E71: =E78/E8 -> 0.1430143 | F71: =F78/F8 -> 0.11869225 | G71: =G78/G8 -> 0.12201468 | H71: =H78/H8 -> 0.12791366 | I71: =I78/I8 -> 0.14579443 | J71: =J78/J8 -> 0.16325989 | K71: =K78/K8 -> 0.14430455 | AG71: =AG78/AG8 -> 0.12372715 | AH71: =AH78/AH8 -> 0.16819428 | AI71: =AI78/AI8 -> 0.1380747 | AJ71: =AJ78/AJ8 -> 0.14640331 | AK71: =AK78/AK8 -> 0.14452315 | AL71: =AL78/AL8 -> 0.13661413 | AM71: =AM78/AM8 -> 0.077238157 | AN71: =AN78/AN8 -> 0.13293968 | ... BO71: =BO78/BO8 -> 0.17406528
B72: =B23 -> Defense Electronics | C72: =C80/C23 -> 0.076780759 | D72: =D80/D23 -> 0.16843034 | E72: =E80/E23 -> 0.1758034 | F72: =F80/F23 -> 0.18562092 | G72: =G80/G23 -> 0.15490319 | H72: =H80/H23 -> 0.14046329 | I72: =I80/I23 -> 0.15190664 | J72: =J80/J23 -> 0.1769229 | K72: =K80/K23 -> 0.19926015 | AG72: =AG80/AG23 -> 0.15289522 | AH72: =AH80/AH23 -> 0.21323322 | AI72: =(AI80/AI23)-0.001 -> 0.26875279 | AJ72: =AJ80/AJ23 -> 0.26867878 | AK72: =AK80/AK23 -> 0.23054017 | AL72: =AL80/AL23 -> 0.19229318 | AM72: =AM80/AM23 -> 0.23993018 | AN72: =AN80/AN23 -> 0.25926276 | AO72: =AO80/AO23 -> 0.24887035 | AP72: =AP80/AP23 -> 0.23642795 | AQ72: =AQ80/AQ23 -> 0.20954471 | ... BO72: =BO80/BO23 -> 0.2732724
B73: =B40 -> Naval & Power | C73: =C82/C40 -> 0.12326769 | D73: =D82/D40 -> 0.13343002 | E73: =E82/E40 -> 0.1075997 | F73: =F82/F40 -> 0.15409623 | G73: =G82/G40 -> 0.13049671 | H73: =H82/H40 -> 0.11011687 | I73: =I82/I40 -> 0.10858846 | J73: =J82/J40 -> 0.093837015 | K73: =K82/K40 -> 0.079840148 | AG73: =AG82/AG40 -> 0.15252154 | AH73: =AH82/AH40 -> 0.18388321 | AI73: =AI82/AI40 -> 0.17841039 | AJ73: =AJ82/AJ40 -> 0.20722324 | AK73: =AK82/AK40 -> 0.18114134 | AL73: =AL82/AL40 -> 0.14689518 | AM73: =AM82/AM40 -> 0.16868899 | AN73: =AN82/AN40 -> 0.18371499 | ... BO73: =BO82/BO40 -> 0.16271302
B74: Total Operating Margins - Adjusted | C74: =+C85/C63 -> 0.082322006 | D74: =+D85/D63 -> 0.11257394 | E74: =+E85/E63 -> 0.12866641 | F74: =+F85/F63 -> 0.12155729 | G74: =+G85/G63 -> 0.11193995 | H74: =+H85/H63 -> 0.11240996 | I74: =+I85/I63 -> 0.12677311 | J74: =+J85/J63 -> 0.13297146 | ... BO74: =+BO85/BO63 -> 0.18608513
B75: Forward Year Guidance | AJ75: 16.5-16.6% | AK75: =AJ75 -> 16.5-16.6% | AO75: 16.5-16.6% | AP75: =AO75 -> 16.5-16.6% | AQ75: 16.6-16.7% | AR75: 16.7-16.8% | AT75: 17.1-17.3% | AU75: =AT75 -> 17.1-17.3% | AY75: 17.4-17.6% | AZ75: =AY75 -> 17.4-17.6% | BA75: 17.4-17.6% | BB75: 17.4-17.6% | BC75: 17.4-17.6% | BD75: 17.4-17.6% | BE75: =BD75 -> 17.4-17.6% | BF75: 17.4-17.6% | BG75: 17.4-17.6% | BH75: 17.4-17.6% | BI75: 17.9-18.1% | BJ75: =BI75 -> 17.9-18.1% | BK75: 18.3-18.5% | BL75: 18.5-18.7% | BM75: 18.5-18.7% | BN75: 18.9-19.2% | BO75: =BN75 -> 18.9-19.2%
BN76: =BN71-BI71 -> -0.012510579
B77: Operating Profit
B78: Aerospace & Industrial | C78: 25.3 | D78: 33.6 | E78: 39 | F78: 33.4 | G78: =SUM(C78:F78) -> 131.3 | H78: 38.496 | I78: 45.75 | J78: 51.069 | K78: 43.369 | AG78: 26.628483 | AH78: 38.73576 | AI78: 30.109407 | AJ78: 33.509888 | AK78: =SUM(AG78:AJ78) -> 128.98354 | AL78: 28.420283 | AM78: 12.798425 | AN78: 22.897945 | AO78: 33.718109 | AP78: =SUM(AL78:AO78) -> 97.834762 | AQ78: 18.5 | AR78: 30.5 | AS78: 30.8 | AT78: 40.436 | AU78: =SUM(AQ78:AT78) -> 120.236 | AV78: 24.853 | AW78: 32.464 | AX78: 39.08 | AY78: 41.302 | AZ78: =SUM(AV78:AY78) -> 137.699 | BA78: 26.545 | BB78: 35.665 | BC78: 39.014 | BD78: 44.054 | BE78: =SUM(BA78:BD78) -> 145.278 | BF78: 27.466 | BG78: 37.865 | BH78: 39.361 | BI78: 53.57 | BJ78: =SUM(BF78:BI78) -> 158.262 | BK78: 31.686 | BL78: 39.588 | BM78: 46.009 | BN78: 52.737 | BO78: =SUM(BK78:BN78) -> 170.02
B79: Forward Year Guidance | AT79: 131-135 | AU79: =AT79 -> 131-135 | AW79: 133-137 | AX79: 135-139 | AY79: 143-148 | AZ79: =AY79 -> 143-148 | BA79: 143-148 | BB79: 145-150 | BC79: 146-150 | BD79: 152-156 | BE79: =BD79 -> 152-156 | BF79: 152-156 | BG79: 157-161 | BH79: 157-161 | BI79: 167-172 | BJ79: =BI79 -> 167-172 | BK79: 163-172 | BL79: 167-173 | BM79: 168-173 | BN79: 189-193 | BO79: =BN79 -> 189-193
B80: =B23 -> Defense Electronics | C80: 8.3 | D80: 19.1 | E80: 18.6 | F80: 28.4 | G80: =SUM(C80:F80) -> 74.4 | H80: 15.784 | I80: 18.002 | J80: 22.48 | K80: 26.286 | AG80: 16.864499 | AH80: 28.511125 | AI80: 36.407175 | AJ80: 39.352795 | AK80: =SUM(AG80:AJ80) -> 121.13559 | AL80: 26.840474 | AM80: 33.545118 | AN80: 38.649078 | AO80: 45.337458 | AP80: =SUM(AL80:AO80) -> 144.37213 | AQ80: 38.2 | AR80: 30.8 | AS80: 42.3 | AT80: 52.875 | AU80: =SUM(AQ80:AT80) -> 164.175 | AV80: 23.29 | AW80: 24.46 | AX80: 36.588 | AY80: 70.23 | AZ80: =SUM(AV80:AY80) -> 154.568 | BA80: 23.368 | BB80: 43.18 | BC80: 56.212 | BD80: 69.015 | BE80: =SUM(BA80:BD80) -> 191.775 | BF80: 48.081 | BG80: 58.767 | BH80: 64.458 | BI80: 55.362 | BJ80: =SUM(BF80:BI80) -> 226.668 | BK80: 67.449 | BL80: 67.852 | BM80: 73.957 | BN80: 69.1 | BO80: =SUM(BK80:BN80) -> 278.358
B81: Forward Year Guidance | AT81: 164-169 | AU81: =AT81 -> 164-169 | AW81: 160-165 | AX81: 150-155 | AY81: 165-172 | AZ81: =AY81 -> 165-172 | BA81: 165-172 | BB81: 174-180 | BC81: 182-188 | BD81: 198-203 | BE81: =BD81 -> 198-203 | BF81: 212-218 | BG81: 212-218 | BH81: 216-221 | BI81: 244-250 | BJ81: =BI81 -> 244-250 | BK81: 261-267 | BL81: 267-273 | BM81: 271-276 | BN81: 288-296 | BO81: =BN81 -> 288-296
B82: =B40 -> Naval & Power | C82: 16.9 | D82: 18.4 | E82: 14.3 | F82: 23.7 | G82: =SUM(C82:F82) -> 73.3 | H82: 14.275 | I82: 14.865 | J82: 11.121 | K82: 11.188 | AG82: 34.989322 | AH82: 45.597699 | AI82: 41.643056 | AJ82: 51.826486 | AK82: =SUM(AG82:AJ82) -> 174.05656 | AL82: 33.499174 | AM82: 38.324357 | AN82: 42.001981 | AO82: 57.040645 | AP82: =SUM(AL82:AO82) -> 170.86616 | AQ82: 40.6 | AR82: 43.5 | AS82: 43.9 | AT82: 47.827 | AU82: =SUM(AQ82:AT82) -> 175.827 | AV82: 32.715 | AW82: 50.001 | AX82: 48.481 | AY82: 60.441 | AZ82: =SUM(AV82:AY82) -> 191.638 | BA82: 40.613 | BB82: 49.441 | BC82: 48.996 | BD82: 59.374 | BE82: =SUM(BA82:BD82) -> 198.424 | BF82: 35.191 | BG82: 46.625 | BH82: 53.798 | BI82: 66.112 | BJ82: =SUM(BF82:BI82) -> 201.726 | BK82: 44.932 | BL82: 63.55 | BM82: 61.253 | BN82: 74.823 | BO82: =SUM(BK82:BN82) -> 244.558
B83: Forward Year Guidance | AT83: 177-182 | AU83: =AT83 -> 177-182 | AW83: 186-190 | AY83: 190-194 | AZ83: =AY83 -> 190-194 | BA83: 190-194 | BB83: 195-200 | BC83: 192-197 | BD83: 202-207 | BE83: =BD83 -> 202-207 | BF83: 192-197 | BG83: 194-199 | BH83: 198-203 | BI83: 228-234 | BJ83: =BI83 -> 228-234 | BK83: 229-236 | BL83: 232-238 | BM83: 236-241 | BN83: 270-276 | BO83: =BN83 -> 270-276
B84: Corporate expense | C84: -9.8 | D84: -12.1 | E84: -6.1 | F84: -14 | G84: -41.9 | H84: -7.521 | I84: -6.458 | J84: -10.421 | K84: -5.912 | AG84: -9.1151823 | AH84: -10.31418 | AI84: -6.9166362 | AJ84: -8.4409762 | AK84: =SUM(AG84:AJ84) -> -34.786975 | AL84: -11.81647 | AM84: -8.1137691 | AN84: -7.7403913 | AO84: -9.9082249 | AP84: =SUM(AL84:AO84) -> -37.578855 | AQ84: =-8.639+0.1 -> -8.539 | AR84: -9.76 | AS84: -9.5 | AT84: -12.058 | AU84: =SUM(AQ84:AT84) -> -39.857 | AV84: -10.045 | AW84: -8.82 | AX84: -9.661 | AY84: -12.301 | AZ84: =SUM(AV84:AY84) -> -40.827 | BA84: -9.235 | BB84: -12.852 | BC84: -10.37 | BD84: -9.221 | BE84: =SUM(BA84:BD84) -> -41.678 | BF84: -10.777 | BG84: -9.912 | BH84: -8.55 | BI84: -11.551 | BJ84: =SUM(BF84:BI84) -> -40.79 | BK84: -10.057 | BL84: -10.948 | BM84: -10.846 | BN84: -10.09 | BO84: =SUM(BK84:BN84) -> -41.941
B85: Total Operating Profit - Adjusted | C85: =+SUM(C78:C84) -> 40.7 | D85: =+SUM(D78:D84) -> 59 | E85: =+SUM(E78:E84) -> 65.8 | F85: =+SUM(F78:F84) -> 71.5 | G85: =+SUM(G78:G84) -> 237.1 | H85: =+SUM(H78:H84) -> 61.034 | I85: =+SUM(I78:I84) -> 72.159 | J85: =+SUM(J78:J84) -> 74.249 | K85: =+SUM(K78:K84) -> 74.931 | L85: 282.373 | M85: 72.835 | N85: 65.442 | O85: 63.813 | P85: 108.527 | Q85: 310.617 | R85: 57.263 | S85: 68.089 | T85: 76.573 | U85: 106.173 | V85: 308.098 | W85: 52.13575 | X85: 84.88975 | Y85: 92.29975 | Z85: 105.26575 | AA85: 334.591 | AB85: 64.498 | AC85: 109.075 | AD85: 98.297 | AE85: 110.405 | AF85: 382.275 | AG85: =+SUM(AG78:AG84) -> 69.367122 | AH85: =+SUM(AH78:AH84) -> 102.5304 | AI85: =+SUM(AI78:AI84) -> 101.243 | AJ85: =+SUM(AJ78:AJ84) -> 116.24819 | AK85: =+SUM(AK78:AK84) -> 389.38872 | AL85: =+SUM(AL78:AL84) -> 76.943461 | AM85: =+SUM(AM78:AM84) -> 76.554131 | AN85: =+SUM(AN78:AN84) -> 95.808613 | ... BK85: =+SUM(BK78:BK84) -> 134.01 | BL85: =SUM(BL78,BL80,BL82,BL84) -> 160.042 | BM85: =SUM(BM78,BM80,BM82,BM84) -> 170.373 | BN85: =+SUM(BN78:BN84) -> 186.57 | BO85: =+SUM(BO78:BO84) -> 650.995
B86: Y/Y Change | H86: =+H85/H63 -> 0.11240996 | I86: =+I85/I63 -> 0.12677311 | J86: =+J85/J63 -> 0.13297146 | K86: =+K85/K63 -> 0.13086418 | L86: =+L85/L63 -> 0.1258837 | M86: =+M85/M63 -> 0.13334883 | N86: =+N85/N63 -> 0.12003434 | O86: =+O85/O63 -> 0.12142483 | ... BO86: =+BO85/BO63 -> 0.18608513
B87: Consensus | BT87: {=_xll.FDS("CW-US","FE_ESTIMATE(EBIT,MEAN,ANN_ROLL,+1,NOW,,,'')")} -> 707.8004 | BY87: {=_xll.FDS("CW-US","FE_ESTIMATE(EBIT,MEAN,ANN_ROLL,+2,NOW,,,'')")} -> 780.836
B88: Forward Year Guidance | AJ88: 428-437 | AK88: =AJ88 -> 428-437 | AO88: 404-414 | AP88: =AO88 -> 404-414 | AQ88: 408-418 | AR88: 411-421 | AT88: 432-446 | AU88: =AT88 -> 432-446 | AW88: 439-452 | AX88: 433-444 | AY88: 463-477 | AZ88: =AY88 -> 463-477 | BA88: 463-477 | BB88: 476-490 | BC88: 480-494 | BD88: 514-528 | BE88: =BD88 -> 514-528 | BF88: 518-533 | BG88: 525-539 | BH88: 531-545 | BI88: 598-613 | BJ88: =BI88 -> 598-613 | BK88: 614-632 | BL88: 626-642 | BM88: 634-647 | BN88: 703-722 | BO88: =BN88 -> 703-722
B91: Total Revenue | C91: 494.4 | D91: 524.1 | E91: 511.4 | F91: 588.2 | G91: 2118.1 | H91: 542.959 | I91: 569.198 | J91: 558.383 | K91: 572.586 | L91: 2243.126 | M91: 546.199 | N91: 545.194 | O91: 525.535 | P91: 588.755 | Q91: 2205.683 | R91: 503.507 | S91: 532.766 | T91: 507.092 | U91: 565.566 | V91: 2108.931 | W91: 523.591 | X91: 567.653 | Y91: 567.901 | Z91: 611.881 | AA91: 2271.026 | AB91: 547.522 | AC91: 620.298 | AD91: 595.393 | AE91: 648.622 | AF91: 2411.835 | AG91: 554.9262 | AH91: 611.9833 | AI91: 586.44264 | AJ91: 625.45509 | AK91: =SUM(AG91:AJ91) -> 2378.8072 | AL91: 575.66241 | AM91: 532.70225 | AN91: 549.94189 | AO91: 641.46583 | AP91: =CW_Drivers!BI77 -> 2325.342 | AQ91: =CW_Drivers!BJ77 -> 589.957 | AR91: =CW_Drivers!BK77 -> 609.377 | AS91: =CW_Drivers!BL77 -> 613.846 | AT91: =CW_Drivers!BM77 -> 655.299 | AU91: =CW_Drivers!BN77 -> 2468.479 | AV91: =CW_Drivers!BO77 -> 559.461 | AW91: =CW_Drivers!BP77 -> 609.357 | ... BY91: =CW_Drivers!CR77 -> 3958.0568
B92: Y/Y Growth | H92: =H91/C91-1 -> 0.098218042 | I92: =I91/D91-1 -> 0.086048464 | J92: =J91/E91-1 -> 0.091871334 | K92: =K91/F91-1 -> -0.026545393 | L92: =L91/G91-1 -> 0.05902743 | M92: =M91/H91-1 -> 0.0059673014 | N92: =N91/I91-1 -> -0.042171617 | O92: =O91/J91-1 -> -0.058827006 | ... BY92: =BY91/BT91-1 -> 0.058563784
B93: Consensus | BA93: =CW_Drivers!BT80 -> 585 | BB93: =CW_Drivers!BU80 -> 652 | BC93: =CW_Drivers!BV80 -> 683 | BD93: =CW_Drivers!BW80 -> 737 | BF93: =CW_Drivers!BY80 -> 664 | BG93: =CW_Drivers!BZ80 -> 736 | BH93: =CW_Drivers!CA80 -> 757 | BI93: =CW_Drivers!CB80 -> 785.3 | BK93: =CW_Drivers!CD80 -> 767.2 | BL93: =CW_Drivers!CE80 -> 852 | BM93: =CW_Drivers!CF80 -> 870.3051 | BN93: =CW_Drivers!CG80 -> 890.3 | BT93: =CW_Drivers!CM80 -> #NAME? | BY93: =CW_Drivers!CR80 -> #NAME?
B94: Forward Year Guidance | AJ94: 2590-2630 | AK94: =AJ94 -> 2590-2630 | AO94: 2445-2495 | AP94: =AO94 -> 2445-2495 | AQ94: 2450-2500 | AR94: 2465-2515 | AT94: 2530-2580 | AU94: =AT94 -> 2530-2580 | AW94: 2570-2620 | AX94: 2525-2575 | AY94: 2655-2710 | AZ94: =AY94 -> 2655-2710 | BA94: =CW_Drivers!BT79 -> 2655-2710 | BB94: =CW_Drivers!BU79 -> 2730-2790 | BC94: =CW_Drivers!BV79 -> 2765-2815 | BD94: 2960-3010 | BE94: =BD94 -> 2960-3010 | BF94: =CW_Drivers!BY79 -> 2985-3035 | BG94: =CW_Drivers!BZ79 -> 3010-3060 | BH94: =CW_Drivers!CA79 -> 3050-3095 | BI94: =CW_Drivers!CB79 -> 3335-3385 | BJ94: =BI94 -> 3335-3385 | BK94: =CW_Drivers!CD79 -> 3365-3415 | BL94: =CW_Drivers!CE79 -> 3390-3435 | BM94: =CW_Drivers!CF79 -> 3420-3455 | BN94: =CW_Drivers!CG79 -> 3710-3765 | BO94: =BN94 -> 3710-3765 | BT94: =BT93/BO91-1 -> #NAME? | BY94: =BY93/BT93-1 -> #NAME?
B96: Cost of Sales | AF96: 1540.574 | AK96: 1589.216 | AP96: 1550.109 | AU96: 1572.575 | AV96: 358.059 | AW96: 380.843 | AX96: 398.333 | AY96: 465.181 | AZ96: =SUM(AV96:AY96) -> 1602.416 | BA96: 409.452 | BB96: 444.823 | BC96: 442.858 | BD96: 481.061 | BE96: =SUM(BA96:BD96) -> 1778.194 | BF96: 459.412 | BG96: 500.69 | BH96: 500.655 | BI96: 506.883 | BJ96: =SUM(BF96:BI96) -> 1967.64 | BK96: 513.181 | BL96: 550.419 | BM96: 541.7 | BN96: 591.538 | BO96: =SUM(BK96:BN96) -> 2196.838
B97: Gross Profit | AF97: =AF91-AF96 -> 871.261 | AK97: =AK91-AK96 -> 789.59124 | AP97: =AP91-AP96 -> 775.233 | AU97: =AU91-AU96 -> 895.904 | AV97: =AV91-AV96 -> 201.402 | AW97: =AW91-AW96 -> 228.514 | AX97: =AX91-AX96 -> 232.21 | AY97: =AY91-AY96 -> 292.484 | AZ97: =SUM(AV97:AY97) -> 954.61 | BA97: =BA91-BA96 -> 221.408 | BB97: =BB91-BB96 -> 259.573 | BC97: =BC91-BC96 -> 281.468 | BD97: =BD91-BD96 -> 304.73 | BE97: =SUM(BA97:BD97) -> 1067.179 | BF97: =BF91-BF96 -> 253.755 | BG97: =BG91-BG96 -> 284.101 | BH97: =BH91-BH96 -> 298.263 | BI97: =BI91-BI96 -> 317.43 | BJ97: =SUM(BF97:BI97) -> 1153.549 | BK97: =BK91-BK96 -> 292.464 | BL97: =BL91-BL96 -> 326.157 | BM97: =BM91-BM96 -> 327.47 | BN97: =BN91-BN96 -> 355.443 | BO97: =SUM(BK97:BN97) -> 1301.534
B98: Gross margin | AF98: =AF97/AF$91 -> 0.36124403 | AK98: =AK97/AK$91 -> 0.33192737 | AP98: =AP97/AP$91 -> 0.33338451 | AU98: =AU97/AU$91 -> 0.36293766 | AV98: =AV97/AV$91 -> 0.35999292 | AW98: =AW97/AW$91 -> 0.37500841 | AX98: =AX97/AX$91 -> 0.36826989 | AY98: =AY97/AY$91 -> 0.38603341 | AZ98: =AZ97/AZ$91 -> 0.37332823 | BA98: =BA97/BA$91 -> 0.35096218 | BB98: =BB97/BB$91 -> 0.36850436 | ... BO98: =BO97/BO$91 -> 0.37203991
B100: R&D expenses | AF100: 64.525 | AK100: 72.52 | AP100: 74.816 | AU100: 88.489 | AV100: 20.549 | AW100: 23.868 | AX100: 17.387 | AY100: 19.032 | AZ100: =SUM(AV100:AY100) -> 80.836 | BA100: 22.024 | BB100: 20.21 | BC100: 23.464 | BD100: 20.066 | BE100: =SUM(BA100:BD100) -> 85.764 | BF100: 22.98 | BG100: 22.152 | BH100: 20.734 | BI100: 25.781 | BJ100: =SUM(BF100:BI100) -> 91.647 | BK100: 23.019 | BL100: 23.308 | BM100: 23.407 | BN100: 25.427 | BO100: =SUM(BK100:BN100) -> 95.161
B101: % of revenue | AF101: =AF100/AF$91 -> 0.026753489 | AK101: =AK100/AK$91 -> 0.030485867 | AP101: =AP100/AP$91 -> 0.032174192 | AU101: =AU100/AU$91 -> 0.035847581 | AV101: =AV100/AV$91 -> 0.036729995 | AW101: =AW100/AW$91 -> 0.039169157 | AX101: =AX100/AX$91 -> 0.027574646 | AY101: =AY100/AY$91 -> 0.025119281 | AZ101: =AZ100/AZ$91 -> 0.031613288 | BA101: =BA100/BA$91 -> 0.034911074 | BB101: =BB100/BB$91 -> 0.028691248 | ... BO101: =BO100/BO$91 -> 0.02720151
B102: Selling expenses | AF102: 126.641 | AK102: 120.861 | AP102: 109.537 | AU102: 116.956 | AV102: 28.092 | AW102: 30.407 | AX102: 31.888 | AY102: 31.199 | AZ102: =SUM(AV102:AY102) -> 121.586 | BA102: 32.425 | BB102: 34.273 | BC102: 34.084 | BD102: 36.306 | BE102: =SUM(BA102:BD102) -> 137.088 | BF102: 36.765 | BG102: 35.126 | BH102: 37.311 | BI102: 36.158 | BJ102: =SUM(BF102:BI102) -> 145.36 | BK102: 39.925 | BL102: 41.764 | BM102: 40.559 | BN102: 46.492 | BO102: =SUM(BK102:BN102) -> 168.74
B103: % of revenue | AF103: =AF102/AF$91 -> 0.052508153 | AK103: =AK102/AK$91 -> 0.050807395 | AP103: =AP102/AP$91 -> 0.047105759 | AU103: =AU102/AU$91 -> 0.047379783 | AV103: =AV102/AV$91 -> 0.050212615 | AW103: =AW102/AW$91 -> 0.049900141 | AX103: =AX102/AX$91 -> 0.050572285 | AY103: =AY102/AY$91 -> 0.041177829 | AZ103: =AZ102/AZ$91 -> 0.047549771 | BA103: =BA102/BA$91 -> 0.051398091 | BB103: =BB102/BB$91 -> 0.04865587 | ... BO103: =BO102/BO$91 -> 0.048233864
B104: G&A expenses | AF104: 306.469 | AK104: 301.411 | AP104: 303.288 | AU104: 326.24 | AV104: 87.6 | AW104: 76.134 | AX104: 75.351 | AY104: 85.008 | AZ104: =SUM(AV104:AY104) -> 324.093 | BA104: 88.344 | BB104: 92.315 | BC104: 91.401 | BD104: 87.664 | BE104: =SUM(BA104:BD104) -> 359.724 | BF104: 94.049 | BG104: 95.008 | BH104: 92.035 | BI104: 92.405 | BJ104: =SUM(BF104:BI104) -> 373.497 | BK104: 99.029 | BL104: 104.071 | BM104: 96.449 | BN104: 100.059 | BO104: =SUM(BK104:BN104) -> 399.608
B105: % of revenue | AF105: =AF104/AF$91 -> 0.12706881 | AK105: =AK104/AK$91 -> 0.12670678 | AP105: =AP104/AP$91 -> 0.13042727 | AU105: =AU104/AU$91 -> 0.13216236 | AV105: =AV104/AV$91 -> 0.15657928 | AW105: =AW104/AW$91 -> 0.12494154 | AX105: =AX104/AX$91 -> 0.11950176 | AY105: =AY104/AY$91 -> 0.11219734 | AZ105: =AZ104/AZ$91 -> 0.12674607 | BA105: =BA104/BA$91 -> 0.14003741 | BB105: =BB104/BB$91 -> 0.13105554 | ... BO105: =BO104/BO$91 -> 0.11422685
B106: Restructuring expenses | BG106: 2.918 | BH106: 3.28 | BI106: 8.25 | BK106: 1.286 | BL106: 0.707 | BM106: 0.804 | BN106: 1.707
B107: GAAP Operating Income | AF107: =AF97-AF100-AF102-AF104 -> 373.626 | AK107: =AK97-AK100-AK102-AK104 -> 294.79924 | AP107: =AP97-AP100-AP102-AP104 -> 287.592 | AU107: =AU97-AU100-AU102-AU104 -> 364.219 | AV107: =AV97-AV100-AV102-AV104 -> 65.161 | AW107: =AW97-AW100-AW102-AW104 -> 98.105 | AX107: =AX97-AX100-AX102-AX104 -> 107.584 | AY107: =AY97-AY100-AY102-AY104 -> 157.245 | AZ107: =AZ97-AZ100-AZ102-AZ104 -> 428.095 | BA107: =BA97-BA100-BA102-BA104 -> 78.615 | BB107: =BB97-BB100-BB102-BB104 -> 112.775 | ... BF107: =BF97-BF100-BF102-BF104 -> 99.961 | BG107: =BG97-BG100-BG102-BG104-BG106 -> 128.897 | BH107: =BH97-BH100-BH102-BH104-BH106 -> 144.903 | BI107: =BI97-BI100-BI102-BI104-BI106 -> 154.836 | BJ107: =BJ97-BJ100-BJ102-BJ104 -> 543.045 | BK107: =BK97-BK100-BK102-BK104-BK106 -> 129.205 | BL107: =BL97-BL100-BL102-BL104-BL106 -> 156.307 | BM107: =BM97-BM100-BM102-BM104-BM106 -> 166.251 | BN107: =BN97-BN100-BN102-BN104-BN106 -> 181.758 | BO107: =BO97-BO100-BO102-BO104 -> 638.025
B108: Operating Margin | AF108: =AF107/AF91 -> 0.15491358 | AK108: =AK107/AK91 -> 0.12392733 | AP108: =AP107/AP91 -> 0.12367729 | AU108: =AU107/AU91 -> 0.14754794 | AV108: =AV107/AV91 -> 0.11647103 | AW108: =AW107/AW91 -> 0.16099758 | AX108: =AX107/AX91 -> 0.17062119 | AY108: =AY107/AY91 -> 0.20753895 | AZ108: =AZ107/AZ91 -> 0.1674191 | BA108: =BA107/BA91 -> 0.1246156 | BB108: =BB107/BB91 -> 0.1601017 | ... BO108: =BO107/BO91 -> 0.18237769
B110: Total Operating Profit - Adjusted | C110: 40.7 | D110: 59 | E110: 65.8 | F110: 71.5 | G110: 237.1 | H110: 61.034 | I110: 72.159 | J110: 74.249 | K110: 74.931 | L110: 282.373 | M110: 72.835 | N110: 65.442 | O110: 63.813 | P110: 108.527 | Q110: 310.617 | R110: 57.263 | S110: 68.089 | T110: 76.573 | U110: 106.173 | V110: 308.098 | W110: 52.13575 | X110: 84.88975 | Y110: 92.29975 | Z110: 105.26575 | AA110: 334.591 | AB110: 64.498 | AC110: 109.075 | AD110: 98.297 | AE110: 110.405 | AF110: 382.275 | AG110: 69.367122 | AH110: 102.5304 | AI110: 101.243 | AJ110: 116.24819 | AK110: 389.38872 | AL110: 76.943461 | AM110: 76.554131 | AN110: 95.808613 | AO110: 126.18799 | AP110: 375.49419 | AQ110: 88.761 | AR110: 95.04 | AS110: 107.5 | AT110: 129.08 | AU110: 420.381 | AV110: 70.813 | AW110: 98.105 | AX110: 114.488 | AY110: 159.672 | AZ110: 443.078 | BA110: 81.291 | BB110: 115.434 | BC110: 133.852 | BD110: 163.222 | BE110: =SUM(BA110:BD110) -> 493.799 | BF110: 99.961 | BG110: 133.345 | BH110: 149.067 | BI110: 160.693 | BJ110: =SUM(BF110:BI110) -> 543.066 | BK110: =BK85 -> 134.01 | BL110: =BL85 -> 160.042 | BM110: =BM85 -> 170.373 | BN110: =BN85 -> 186.57 | BO110: =SUM(BK110:BN110) -> 650.995 | BP110: =BP91*BP111 -> 148.82304 | BQ110: =BQ91*BQ111 -> 174.2936 | BR110: =BR91*BR111 -> 188.09405 | BS110: =BS91*BS111 -> 202.2128 | BT110: =SUM(BP110:BS110) -> 713.42349 | BU110: =BU91*BU111 -> 162.10366 | BV110: =BV91*BV111 -> 190.4757 | BW110: =BW91*BW111 -> 205.05777 | BX110: =BX91*BX111 -> 220.40053 | BY110: =SUM(BU110:BX110) -> 778.03764
B111: Operating Margin | C111: =C110/C91 -> 0.082322006 | D111: =D110/D91 -> 0.11257394 | E111: =E110/E91 -> 0.12866641 | F111: =F110/F91 -> 0.12155729 | G111: =G110/G91 -> 0.11193995 | H111: =H110/H91 -> 0.11240996 | I111: =I110/I91 -> 0.12677311 | J111: =J110/J91 -> 0.13297146 | ... BO111: =BO110/BO91 -> 0.18608513 | BP111: 0.171 | BQ111: 0.186 | BR111: 0.2 | BS111: 0.204 | BT111: =BT110/BT91 -> 0.19080178 | BU111: 0.176 | BV111: 0.192 | BW111: 0.206 | BX111: 0.21 | BY111: =BY110/BY91 -> 0.19657061
B112: Y/Y Change | H112: =H110/C110-1 -> 0.49960688 | I112: =I110/D110-1 -> 0.2230339 | J112: =J110/E110-1 -> 0.12840426 | K112: =K110/F110-1 -> 0.047986014 | L112: =L110/G110-1 -> 0.19094475 | M112: =M110/H110-1 -> 0.19335125 | N112: =N110/I110-1 -> -0.093086102 | O112: =O110/J110-1 -> -0.14055408 | ... BY112: =BY110/BT110-1 -> 0.090569147
B113: Consensus | BA113: 77 | BB113: 106 | BC113: 127 | BD113: 156 | BF113: 90 | BG113: 117 | BH113: 136 | BI113: 158.8 | BK113: 118.2 | BL113: 153.9 | BM113: 163.73428 | BN113: 180.3 | BT113: {=_xll.FDS("CW-US","FE_ESTIMATE(EBIT,MEAN,ANN_ROLL,+1,NOW,,,'')")} -> 707.8004 | BY113: {=_xll.FDS("CW-US","FE_ESTIMATE(EBIT,MEAN,ANN_ROLL,+2,NOW,,,'')")} -> 780.836
B114: Forward Year Guidance | AJ114: 428-437 | AK114: =AJ114 -> 428-437 | AO114: 404-414 | AP114: =AO114 -> 404-414 | AQ114: 408-418 | AR114: 411-421 | AT114: 432-446 | AU114: =AT114 -> 432-446 | AW114: 439-452 | AX114: 433-444 | AY114: 463-477 | AZ114: =AY114 -> 463-477 | BA114: 463-477 | BB114: 476-490 | BC114: 480-494 | BD114: 514-528 | BE114: =BD114 -> 514-528 | BF114: 518-533 | BG114: 525-539 | BH114: 531-545 | BI114: 598-613 | BJ114: =BI114 -> 598-613 | BK114: 614-632 | BL114: =BL88 -> 626-642 | BM114: =BM88 -> 634-647 | BN114: =BN88 -> 703-722 | BO114: =BN114 -> 703-722
B116: Depreciation & Amortization | L116: 118.931 | Q116: 100.81 | V116: 96.008 | AA116: 99.995 | AB116: 24.601 | AC116: =51.257-AB116 -> 26.656 | AD116: =77.146-AC116-AB116 -> 25.889 | AE116: =102.949-AD116-AC116-AB116 -> 25.803 | AF116: =SUM(AB116:AE116) -> 102.949 | AG116: 25.793 | AH116: =51.6-AG116 -> 25.807 | AI116: =76.998-AH116-AG116 -> 25.398 | AJ116: =102.412-AI116-AH116-AG116 -> 25.414 | AK116: =SUM(AG116:AJ116) -> 102.412 | AL116: 28.142 | AM116: =56.568-AL116 -> 28.426 | AN116: =84.769-AM116-AL116 -> 28.201 | AO116: =115.903-AN116-AM116-AL116 -> 31.134 | AP116: =SUM(AL116:AO116) -> 115.903 | AQ116: 28.595 | AR116: =57.616-AQ116 -> 29.021 | AS116: =86.24-AR116-AQ116 -> 28.624 | AT116: =114.384-AS116-AR116-AQ116 -> 28.144 | AU116: =SUM(AQ116:AT116) -> 114.384 | AV116: 27.363 | AW116: =53.645-AV116 -> 26.282 | AX116: =83.52-AW116-AV116 -> 29.875 | AY116: =112.027-AX116-AW116-AV116 -> 28.507 | AZ116: =SUM(AV116:AY116) -> 112.027 | BA116: 28.927 | BB116: =57.975-BA116 -> 29.048 | BC116: =86.836-BB116-BA116 -> 28.861 | BD116: 29 | BE116: =SUM(BA116:BD116) -> 115.836 | BF116: 26.983 | BG116: =54.151-BF116 -> 27.168 | BH116: =80.844-BG116-BF116 -> 26.693 | BI116: 27 | BJ116: =SUM(BF116:BI116) -> 107.844 | BK116: 30.821 | BL116: =62.128-BK116 -> 31.307 | BM116: =93.319-BL116-BK116 -> 31.191 | BN116: =124.817-BM116-BL116-BK116 -> 31.498 | BO116: =SUM(BK116:BN116) -> 124.817 | BP116: 29.5 | BQ116: 29.5 | BR116: 29.5 | BS116: 29.5 | BT116: =SUM(BP116:BS116) -> 118 | BU116: =BS116 -> 29.5 | BV116: =BU116 -> 29.5 | BW116: =BV116 -> 29.5 | BX116: =BW116 -> 29.5 | BY116: =SUM(BU116:BX116) -> 118
B117: Stock-based Compensation | L117: 8.5 | Q117: 9.473 | V117: 9.478 | AA117: 11.572 | AB117: 4.591 | AC117: =7.801-AB117 -> 3.21 | AD117: =11.846-AC117-AB117 -> 4.045 | AE117: =14.094-AD117-AC117-AB117 -> 2.248 | AF117: =SUM(AB117:AE117) -> 14.094 | AG117: 3.495 | AH117: =6.98-AG117 -> 3.485 | AI117: =11.262-AH117-AG117 -> 4.282 | AJ117: =13.669-AI117-AH117-AG117 -> 2.407 | AK117: =SUM(AG117:AJ117) -> 13.669 | AL117: 3.34 | AM117: =7.14-AL117 -> 3.8 | AN117: =11.777-AM117-AL117 -> 4.637 | AO117: =14.437-AN117-AM117-AL117 -> 2.66 | AP117: =SUM(AL117:AO117) -> 14.437 | AQ117: 3.327 | AR117: =6.725-AQ117 -> 3.398 | AS117: =10.861-AR117-AQ117 -> 4.136 | AT117: =13.45-AS117-AR117-AQ117 -> 2.589 | AU117: =SUM(AQ117:AT117) -> 13.45 | AV117: 3.809 | AW117: =7.58-AV117 -> 3.771 | AX117: =12.027-AW117-AV117 -> 4.447 | AY117: =15.384-AX117-AW117-AV117 -> 3.357 | AZ117: =SUM(AV117:AY117) -> 15.384 | BA117: 5.179 | BB117: =8.859-BA117 -> 3.68 | BC117: =13.213-BB117-BA117 -> 4.354 | BD117: =AVERAGE(BA117:BC117) -> 4.4043333 | BE117: =SUM(BA117:BD117) -> 17.617333 | BF117: 4.695 | BG117: =9.466-BF117 -> 4.771 | BH117: =15.164-BG117-BF117 -> 5.698 | BI117: =AVERAGE(BF117:BH117) -> 5.0546667 | BJ117: =SUM(BF117:BI117) -> 20.218667 | BK117: 5.271 | BL117: =10.484-BK117 -> 5.213 | BM117: =16.61-BL117-BK117 -> 6.126 | BN117: =21.52-BM117-BL117-BK117 -> 4.91 | BO117: =SUM(BK117:BN117) -> 21.52 | BP117: =BK117*1.05 -> 5.53455 | BQ117: =BL117*1.05 -> 5.47365 | BR117: =BM117*1.05 -> 6.4323 | BS117: =BN117*1.05 -> 5.1555 | BT117: =SUM(BP117:BS117) -> 22.596 | BU117: =BP117*1.05 -> 5.8112775 | BV117: =BQ117*1.05 -> 5.7473325 | BW117: =BR117*1.05 -> 6.753915 | BX117: =BS117*1.05 -> 5.413275 | BY117: =SUM(BU117:BX117) -> 23.7258
...

Sheet CW_FCF
A3: Curtiss-Wright Free Cash Flow Estimates
BD5: =-BD17/CW_IS!AZ91 -> 0.014945879 | BI5: =-BI17/CW_IS!BE91 -> 0.015661918 | BN5: =-BN17/CW_IS!BJ91 -> 0.019448678 | BS5: =-BS17/CW_IS!BO91 -> 0.025638211 | BX5: =-BX17/CW_IS!BT91 -> 0.030756212 | CC5: =-CC17/CW_IS!BY91 -> 0.03
A7: ($ in millions, except per share data) | B7: =[46]Drivers!V4 -> 1Q13 | C7: =[46]Drivers!W4 -> 2Q13 | D7: =[46]Drivers!X4 -> 3Q13 | E7: =[46]Drivers!Y4 -> 4Q13 | F7: =[46]Drivers!Z4 -> 2013 | G7: =[46]Drivers!AA4 -> 1Q14 | H7: =[46]Drivers!AB4 -> 2Q14 | I7: =[46]Drivers!AC4 -> 3Q14 | ... P7: =[46]Drivers!AJ4 -> 2015 | Q7: 1Q16 | R7: 2Q16 | S7: 3Q16 | T7: 4Q16 | U7: 2016 | V7: F1Q17 | W7: F2Q17 | X7: F3Q17 | Y7: 4Q17 | Z7: F2016 | AA7: F1Q17 | AB7: F2Q17 | AC7: F3Q17 | AD7: F4Q17 | AE7: F2017 | AF7: F1Q18 | AG7: F2Q18 | AH7: F3Q18 | AI7: F4Q18 | AJ7: F2018 | AK7: 1Q19 | AL7: 2Q19 | AM7: 3Q19 | AN7: 4Q19 | AO7: 2019 | AP7: 1Q20 | AQ7: 2Q20 | AR7: 3Q20 | AS7: 4Q20 | AT7: 2020 | AU7: 1Q21 | AV7: 2Q21 | AW7: 3Q21 | AX7: 4Q21 | AY7: 2021 | AZ7: 1Q22 | BA7: 2Q22 | BB7: 3Q22 | BC7: 4Q22 | BD7: 2022 | BE7: 1Q23 | BF7: 2Q23 | BG7: 3Q23 | BH7: 4Q23 | BI7: 2023 | BJ7: =CW_IS!BF5 -> 1Q24 | BK7: =CW_IS!BG5 -> 2Q24 | BL7: =CW_IS!BH5 -> 3Q24 | BM7: =CW_IS!BI5 -> 4Q24 | BN7: =CW_Drivers!CC3 -> 2024 | BO7: =CW_IS!BK5 -> 1Q25 | BP7: =CW_IS!BL5 -> 2Q25 | BQ7: =CW_IS!BM5 -> 3Q25 | BR7: =CW_IS!BN5 -> 4Q25 | BS7: =CW_Drivers!CH3 -> 2025 | BT7: =CW_IS!BP5 -> 1Q26E | BU7: =CW_IS!BQ5 -> 2Q26E | BV7: =CW_IS!BR5 -> 3Q26E | BW7: =CW_IS!BS5 -> 4Q26E | BX7: =CW_Drivers!CM3 -> 2026E | BY7: =CW_IS!BU5 -> 1Q27E | BZ7: =CW_IS!BV5 -> 2Q27E | CA7: =CW_IS!BW5 -> 3Q27E | CB7: =CW_IS!BX5 -> 4Q27E | CC7: =CW_Drivers!CR3 -> 2027E
A8: FCF Analysis
A9: BOP Cash | AO9: =+AK9 -> 0 | AT9: =+AP9 -> 0 | AU9: =+AT29 -> 198.248 | AV9: =+AU29 -> 147.069 | AW9: =AV29 -> 197.508 | AX9: =AW29 -> 234.416 | AY9: =+AU9 -> 198.248 | AZ9: =+AY29 -> 171.004 | BA9: =AZ29 -> 136.682 | BB9: =BA29 -> 171.414 | BC9: =BB29 -> 113.552 | BD9: =+AZ9 -> 171.004 | BE9: =+BD29 -> 256.974 | BF9: =BE29 -> 130.659 | BG9: =BF29 -> 158.737 | BH9: =BG29 -> 148.809 | BI9: =+BE9 -> 256.974 | BJ9: =+BI29 -> 406.867 | BK9: =BJ29 -> 338.034 | BL9: =BK29 -> 382.564 | BM9: =BL29 -> 443.85 | BN9: =+BJ9 -> 406.867 | BO9: =+BN29 -> 385.042 | BP9: =BO29 -> 226.459 | BQ9: =BP29 -> 331.664 | BR9: =BQ29 -> 225.427 | BS9: =+BO9 -> 385.042 | BT9: =+BR29 -> 371.345 | BU9: =BT29 -> 295.13765 | BV9: =BU29 -> 251.74069 | BW9: =BV29 -> 544.93353 | BX9: =+BT9 -> 371.345 | BY9: =+BW29 -> 856.72474 | BZ9: =BY29 -> 973.2768 | CA9: =BZ29 -> 1086.7074 | CB9: =CA29 -> 1212.2765 | CC9: =+BY9 -> 856.72474
A10: Adjusted EBITDA | AO10: =SUM(AK10:AN10) -> 0 | AT10: =CW_IS!AP118 -> 505.83419 | AU10: =CW_IS!AQ118 -> 120.683 | AV10: =CW_IS!AR118 -> 127.459 | AW10: =CW_IS!AS118 -> 140.26 | AX10: =CW_IS!AT118 -> 159.813 | AY10: =SUM(AU10:AX10) -> 548.215 | AZ10: =CW_IS!AV118 -> 101.985 | BA10: =CW_IS!AW118 -> 128.158 | BB10: =CW_IS!AX118 -> 148.81 | BC10: =CW_IS!AY118 -> 191.536 | BD10: =SUM(AZ10:BC10) -> 570.489 | BE10: =CW_IS!BA118 -> 115.397 | BF10: =CW_IS!BB118 -> 148.162 | BG10: =CW_IS!BC118 -> 167.067 | BH10: =CW_IS!BD118 -> 196.62633 | BI10: =SUM(BE10:BH10) -> 627.25233 | BJ10: =CW_IS!BF118 -> 131.639 | BK10: =CW_IS!BG118 -> 165.284 | BL10: =CW_IS!BH118 -> 181.458 | BM10: =CW_IS!BI118 -> 192.74767 | BN10: =SUM(BJ10:BM10) -> 671.12867 | BO10: =CW_IS!BK118 -> 170.102 | BP10: =CW_IS!BL118 -> 196.562 | BQ10: =CW_IS!BM118 -> 207.69 | BR10: =CW_IS!BN118 -> 222.978 | BS10: =SUM(BO10:BR10) -> 797.332 | BT10: =CW_IS!BP118 -> 183.85759 | BU10: =CW_IS!BQ118 -> 209.26725 | BV10: =CW_IS!BR118 -> 224.02635 | BW10: =CW_IS!BS118 -> 236.8683 | BX10: =SUM(BT10:BW10) -> 854.01949 | BY10: =CW_IS!BU118 -> 197.41493 | BZ10: =CW_IS!BV118 -> 225.72303 | CA10: =CW_IS!BW118 -> 241.31168 | CB10: =CW_IS!BX118 -> 255.3138 | CC10: =SUM(BY10:CB10) -> 919.76344
A11: Taxes | AO11: =SUM(AK11:AN11) -> 0 | AT11: =(CW_IS!AP124)*-1 -> -82.6456 | AU11: =(CW_IS!AQ124)*-1 -> -21.381 | AV11: =(CW_IS!AR124)*-1 -> -21.335 | AW11: =(CW_IS!AS124)*-1 -> -24.338 | AX11: =(CW_IS!AT124)*-1 -> -27.33036 | AY11: =SUM(AU11:AX11) -> -94.38436 | AZ11: =(CW_IS!AV124)*-1 -> -13.541 | BA11: =(CW_IS!AW124)*-1 -> -22 | BB11: =(CW_IS!AX124)*-1 -> -24.264 | BC11: =(CW_IS!AY124)*-1 -> -34.80528 | BD11: =SUM(AZ11:BC11) -> -94.61028 | BE11: =(CW_IS!BA124)*-1 -> -16.642 | BF11: =(CW_IS!BB124)*-1 -> -24.738 | BG11: =(CW_IS!BC124)*-1 -> -30.268 | BH11: =(CW_IS!BD124)*-1 -> -36.963 | BI11: =SUM(BE11:BH11) -> -108.611 | BJ11: =(CW_IS!BF124)*-1 -> -22.504 | BK11: =(CW_IS!BG124)*-1 -> -26.77 | BL11: =(CW_IS!BH124)*-1 -> -32.461 | BM11: =(CW_IS!BI124)*-1 -> -35.343 | BN11: =SUM(BJ11:BM11) -> -117.078 | BO11: =(CW_IS!BK124)*-1 -> -23.755 | BP11: =(CW_IS!BL124)*-1 -> -35.704 | BQ11: =(CW_IS!BM124)*-1 -> -36.321 | BR11: =(CW_IS!BN124)*-1 -> -40.002 | BS11: =SUM(BO11:BR11) -> -135.782 | BT11: =(CW_IS!BP124)*-1 -> -22.023456 | BU11: =(CW_IS!BQ124)*-1 -> -39.627527 | BV11: =(CW_IS!BR124)*-1 -> -42.801632 | BW11: =(CW_IS!BS124)*-1 -> -47.050008 | BX11: =SUM(BT11:BW11) -> -151.50262 | BY11: =(CW_IS!BU124)*-1 -> -23.959299 | BZ11: =(CW_IS!BV124)*-1 -> -43.26316 | CA11: =(CW_IS!BW124)*-1 -> -46.617036 | CB11: =(CW_IS!BX124)*-1 -> -51.235998 | CC11: =SUM(BY11:CB11) -> -165.07549
A12: Cash interest | AO12: =SUM(AK12:AN12) -> 0 | AT12: =CW_IS!AP121 -> -35.545 | AU12: =CW_IS!AQ121 -> -9.959 | AV12: =CW_IS!AR121 -> -10.18 | AW12: =CW_IS!AS121 -> -9.955 | AX12: =CW_IS!AT121 -> -10.146 | AY12: =SUM(AU12:AX12) -> -40.24 | AZ12: =CW_IS!AV121 -> -9.53 | BA12: =CW_IS!AW121 -> -9.788 | BB12: =CW_IS!AX121 -> -13.997 | BC12: =CW_IS!AY121 -> -13.665 | BD12: =SUM(AZ12:BC12) -> -46.98 | BE12: =CW_IS!BA121 -> -12.944 | BF12: =CW_IS!BB121 -> -14.992 | BG12: =CW_IS!BC121 -> -12.496 | BH12: =CW_IS!BD121 -> -10.961 | BI12: =SUM(BE12:BH12) -> -51.393 | BJ12: =CW_IS!BF121 -> -10.57 | BK12: =CW_IS!BG121 -> -11.216 | BL12: =CW_IS!BH121 -> -11.408 | BM12: =CW_IS!BI121 -> -11.675 | BN12: =SUM(BJ12:BM12) -> -44.869 | BO12: =CW_IS!BK121 -> -10.143 | BP12: =CW_IS!BL121 -> -10.524 | BQ12: =CW_IS!BM121 -> -10.484 | BR12: =CW_IS!BN121 -> -11.997 | BS12: =SUM(BO12:BR12) -> -43.148 | BT12: =CW_IS!BP121 -> -10.375 | BU12: =CW_IS!BQ121 -> -10.375 | BV12: =CW_IS!BR121 -> -10.375 | BW12: =CW_IS!BS121 -> -10.375 | BX12: =SUM(BT12:BW12) -> -41.5 | BY12: =CW_IS!BU121 -> -10.375 | BZ12: =CW_IS!BV121 -> -10.375 | CA12: =CW_IS!BW121 -> -10.375 | CB12: =CW_IS!BX121 -> -10.375 | CC12: =SUM(BY12:CB12) -> -41.5
A13: Working Capital | AO13: =SUM(AK13:AN13) -> 0 | AT13: -121.526 | AU13: -96 | AV13: -20 | AW13: 0 | AX13: 100 | AY13: =SUM(AU13:AX13) -> -16 | AZ13: -100 | BA13: -25 | BB13: 0 | BC13: 25 | BD13: =SUM(AZ13:BC13) -> -100 | BE13: =6.153-42.773-0.163-85.442-8.252-4.946-44.602 -> -180.025 | BF13: =(-22.37-57.557+1.83-72.019+21.586-9.392-40.867)-BE13 -> 1.236 | BG13: =(-56.138-56.753+0.064-42.02+37.598-14.128-31.343)-BF13-BE13 -> 16.069 | BH13: 25 | BI13: =SUM(BE13:BH13) -> -137.72 | BJ13: -151 | BK13: =-85.914-54.113-55.306+36.573-9.528+0.751-BJ13 -> -16.537 | BL13: =(-120.795-71.683-15.206+85.579-13.218+5.034)-BK13-BJ13 -> 37.248 | BM13: =(-2.394-21.568-15.779+47.914-18.307-29.286)-BL13-BK13-BJ13 -> 90.869 | BN13: =SUM(BJ13:BM13) -> -39.42 | BO13: =-72.749-34.079-35.967-12.714-6.03-12.862 -> -174.401 | BP13: =-110.541-57.614-40.083+35.719-10.691-13.544 -> -196.754 | BQ13: =(-128.774-86.139+28.48+40.119-14.433-12.116)-BP13-BO13 -> 198.292 | BR13: =(-88.808-34.5+16.024+144.269-18.88+2.195)-BQ13-BP13-BO13 -> 193.163 | BS13: =SUM(BO13:BR13) -> 20.3 | BT13: -175 | BU13: -150 | BV13: 175 | BW13: 185 | BX13: =SUM(BT13:BW13) -> 35 | BY13: 5 | BZ13: -5 | CA13: -5 | CB13: 5 | CC13: =SUM(BY13:CB13) -> 0
A14: Other, net | AO14: =SUM(AK14:AN14) -> 0 | AT14: =SUM(AP14:AS14) -> 0 | AU14: 0 | AV14: 0 | AW14: 0 | AX14: 0 | AY14: =SUM(AU14:AX14) -> 0 | AZ14: 0 | BA14: 0 | BB14: 0 | BC14: 0 | BD14: =SUM(AZ14:BC14) -> 0 | BE14: 0 | BF14: 0 | BG14: 0 | BH14: 0 | BI14: =SUM(BE14:BH14) -> 0 | BJ14: -145 | BK14: 0 | BL14: 0 | BM14: 0 | BN14: =SUM(BJ14:BM14) -> -145 | BO14: 0 | BP14: 0 | BQ14: 0 | BR14: 0 | BS14: =SUM(BO14:BR14) -> 0 | BT14: 0 | BU14: 0 | BV14: 0 | BW14: 0 | BX14: =SUM(BT14:BW14) -> 0 | BY14: 0 | BZ14: 0 | CA14: 0 | CB14: 0 | CC14: =SUM(BY14:CB14) -> 0
A15: Guidance - Full Year
A16: Cash flows from operations | AO16: =SUM(AK16:AN16) -> 0 | AT16: 261.18 | AU16: -26.603 | AV16: 75.079 | AW16: 107.195 | AX16: 231.997 | AY16: =SUM(AU16:AX16) -> 387.668 | AZ16: -124.315 | BA16: 31 | BB16: 95.658 | BC16: 292.389 | BD16: =SUM(AZ16:BC16) -> 294.732 | BE16: -91.599 | BF16: =19.353-BE16 -> 110.952 | BG16: 146.364 | BH16: 282 | BI16: =SUM(BE16:BH16) -> 447.717 | BJ16: -45.633 | BK16: 111.335 | BL16: =242.976-BK16-BJ16 -> 177.274 | BM16: 301 | BN16: =SUM(BJ16:BM16) -> 543.976 | BO16: -38.765 | BP16: 136.585 | BQ16: 192.838 | BR16: 352.744 | BS16: =SUM(BO16:BR16) -> 643.402 | BT16: =SUM(BT10:BT14) -> -23.540868 | BU16: =SUM(BU10:BU14) -> 9.2647198 | BV16: =SUM(BV10:BV14) -> 345.84972 | BW16: =SUM(BW10:BW14) -> 364.44329 | BX16: =SUM(BT16:BW16) -> 696.01686 | BY16: =SUM(BY10:BY14) -> 168.08064 | BZ16: =SUM(BZ10:BZ14) -> 167.08487 | CA16: =SUM(CA10:CA14) -> 179.31964 | CB16: =SUM(CB10:CB14) -> 198.7028 | CC16: =SUM(BY16:CB16) -> 713.18795
A17: Capex | AO17: =SUM(AK17:AN17) -> 0 | AT17: -47.499 | AU17: -8.537 | AV17: -9.234 | AW17: -10.087 | AX17: -13.25 | AY17: =SUM(AU17:AX17) -> -41.108 | AZ17: -10.896 | BA17: -8.596 | BB17: -9.297 | BC17: -9.428 | BD17: =SUM(AZ17:BC17) -> -38.217 | BE17: -10.661 | BF17: =-22.191-BE17 -> -11.53 | BG17: -9.373 | BH17: -13 | BI17: =SUM(BE17:BH17) -> -44.564 | BJ17: -12.055 | BK17: -11.064 | BL17: =-37.703-BK17-BJ17 -> -14.584 | BM17: -23 | BN17: =SUM(BJ17:BM17) -> -60.703 | BO17: -15.773 | BP17: -19.381 | BQ17: -16.9 | BR17: -37.638 | BS17: =SUM(BO17:BR17) -> -89.692 | BT17: =-115/4 -> -28.75 | BU17: =-115/4 -> -28.75 | BV17: =-115/4 -> -28.75 | BW17: =-115/4 -> -28.75 | BX17: =SUM(BT17:BW17) -> -115 | BY17: =-(0.03*CW_IS!BU91) -> -27.631305 | BZ17: =-(0.03*CW_IS!BV91) -> -29.761827 | CA17: =-(0.03*CW_IS!BW91) -> -29.862781 | CB17: =-(0.03*CW_IS!BX91) -> -31.485789 | CC17: =SUM(BY17:CB17) -> -118.7417
A18: FCF | AO18: =AO16+AO17 -> 0 | AT18: =+AT16+AT17 -> 213.681 | AU18: =+AU16+AU17 -> -35.14 | AV18: =+AV16+AV17 -> 65.845 | AW18: =+AW16+AW17 -> 97.108 | AX18: =+AX16+AX17 -> 218.747 | AY18: =SUM(AU18:AX18) -> 346.56 | AZ18: =+AZ16+AZ17 -> -135.211 | BA18: =+BA16+BA17 -> 22.404 | BB18: =+BB16+BB17 -> 86.361 | BC18: =+BC16+BC17 -> 282.961 | BD18: =SUM(AZ18:BC18) -> 256.515 | BE18: =+BE16+BE17 -> -102.26 | BF18: =+BF16+BF17 -> 99.422 | BG18: =+BG16+BG17 -> 136.991 | BH18: 270 | BI18: =SUM(BE18:BH18) -> 404.153 | BJ18: =+BJ16+BJ17 -> -57.688 | BK18: =+BK16+BK17 -> 100.271 | BL18: =+BL16+BL17 -> 162.69 | BM18: =+BM16+BM17 -> 278 | BN18: =SUM(BJ18:BM18) -> 483.273 | BO18: =+BO16+BO17 -> -54.538 | BP18: =+BP16+BP17 -> 117.204 | BQ18: =+BQ16+BQ17 -> 175.938 | BR18: =+BR16+BR17 -> 315.106 | BS18: =SUM(BO18:BR18) -> 553.71 | BT18: =+BT16+BT17 -> -52.290868 | BU18: =+BU16+BU17 -> -19.48528 | BV18: =+BV16+BV17 -> 317.09972 | BW18: =+BW16+BW17 -> 335.69329 | BX18: =SUM(BT18:BW18) -> 581.01686 | BY18: =+BY16+BY17 -> 140.44933 | BZ18: =+BZ16+BZ17 -> 137.32304 | CA18: =+CA16+CA17 -> 149.45686 | CB18: =+CB16+CB17 -> 167.21701 | CC18: =SUM(BY18:CB18) -> 594.44625
A19: Consensus | BS19: =-BS17/-BN17-1 -> 0.47755465 | BX19: =-BX17/-BS17-1 -> 0.28216563
A20: Guidance - Full Year | AT20: 330-360 | AX20: 345-365 | AY20: =AX20 -> 345-365 | BB20: 275-315 | BC20: 360-400 | BD20: =BC20 -> 360-400 | BE20: 360-400 | BF20: 370-400 | BG20: 380-400 | BH20: 415-435 | BI20: =BH20 -> 415-435 | BJ20: 415-435 | BK20: 425-445 | BL20: 430-450 | BM20: 485-505 | BN20: =BM20 -> 485-505 | BO20: 495-515 | BP20: 520-535 | BQ20: 520-535 | BR20: 575-595 | BS20: =BR20 -> 575-595
A22: CapEx % of revenue | AT22: =-AT17/CW_IS!AP91 -> 0.020426673 | AY22: =-AY17/CW_IS!AU91 -> 0.01665317 | BD22: =-BD17/CW_IS!AZ91 -> 0.014945879 | BI22: =-BI17/CW_IS!BE91 -> 0.015661918 | BN22: =-BN17/CW_IS!BJ91 -> 0.019448678 | BS22: =-BS17/CW_IS!BO91 -> 0.025638211 | BX22: =-BX17/CW_IS!BT91 -> 0.030756212 | CC22: =-CC17/CW_IS!BY91 -> 0.03
A23: FCF Conversion | AT23: =AT18/CW_IS!AP128 -> 0.7712679 | AY23: =AY18/CW_IS!AU128 -> 1.1636417 | BD23: =BD18/CW_IS!AZ128 -> 0.81635551 | BI23: =BI18/CW_IS!BE128 -> 1.1113607 | BN23: =BN18/CW_IS!BJ128 -> 1.152167 | BS23: =BS18/CW_IS!BO128 -> 1.1036631 | BX23: =BX18/CW_IS!BT128 -> 1.0489167 | CC23: =CC18/CW_IS!BY128 -> 0.9850597
A25: Dividends | AO25: =SUM(AK25:AN25) -> 0 | AT25: -28.175 | AU25: 0 | AV25: -6.961 | AW25: =-14.32-AV25-AU25 -> -7.359 | AX25: =-28.66-AW25-AV25-AU25 -> -14.34 | AY25: =SUM(AU25:AX25) -> -28.66 | AZ25: 0 | BA25: -14.22 | BB25: =-14.22-BA25-AZ25 -> 0 | BC25: =-28.779-BB25-BA25-AZ25 -> -14.559 | BD25: =SUM(AZ25:BC25) -> -28.779 | BE25: 0 | BF25: =-7.29-BE25 -> -7.29 | BG25: =-0.2*CW_IS!BC140 -> -7.7116 | BH25: =-0.2*CW_IS!BD140 -> -7.701 | BI25: =SUM(BE25:BH25) -> -22.7026 | BJ25: 0 | BK25: =-7.665-BJ25 -> -7.665 | BL25: =-15.707-BK25-BJ25 -> -8.042 | BM25: =-0.21*CW_IS!BI140 -> -8.00877 | BN25: =SUM(BJ25:BM25) -> -23.71577 | BO25: 0 | BP25: =-7.923-BO25 -> -7.923 | BQ25: =-16.967-BP25-BO25 -> -9.044 | BR25: =-34.727-BQ25-BP25-BO25 -> -17.76 | BS25: =SUM(BO25:BR25) -> -34.727 | BT25: =-0.24*CW_IS!BP140 -> -8.91648 | BU25: =-0.24*CW_IS!BQ140 -> -8.91168 | BV25: =-0.24*CW_IS!BR140 -> -8.90688 | BW25: =-0.24*CW_IS!BS140 -> -8.90208 | BX25: =SUM(BT25:BW25) -> -35.63712 | BY25: =-0.24*CW_IS!BU140 -> -8.89728 | BZ25: =-0.24*CW_IS!BV140 -> -8.89248 | CA25: =-0.24*CW_IS!BW140 -> -8.88768 | CB25: =-0.24*CW_IS!BX140 -> -8.88288 | CC25: =SUM(BY25:CB25) -> -35.56032
A26: Proceeds (Repayments) of debt | AO26: =SUM(AK26:AN26) -> 0 | AT26: 300 | AU26: 0 | AV26: 0 | AW26: 0 | AX26: =(455.95-362.05-100)-AW26-AV26-AU26 -> -6.1 | AY26: =SUM(AU26:AX26) -> -6.1 | AZ26: =241.198-121.198 -> 120 | BA26: =(653.547-494.347)-AZ26 -> 39.2 | BB26: =(1332.219-1038.019)-BA26-AZ26 -> 135 | BC26: =(1697.647-1791.547+300)-BB26-BA26-AZ26 -> -88.1 | BD26: =SUM(AZ26:BC26) -> 206.1 | BE26: =BE32-BC32 -> -24.781 | BF26: =BF32-BE32 -> -53.553 | BG26: =BG32-BF32 -> -125.353 | BH26: =BH32-BG32 -> -0.351 | BI26: =SUM(BE26:BH26) -> -204.038 | BJ26: =BJ32-BH32 -> -0.353 | BK26: =BK32-BJ32 -> -0.354 | BL26: =BL32-BK32 -> -0.353 | BM26: =BM32-BL32 -> -0.353 | BN26: =SUM(BJ26:BM26) -> -1.413 | BO26: =BO32-BM32 -> -90.32 | BP26: =BP32-BO32 -> -0.248 | BQ26: =BQ32-BP32 -> 10.251 | BR26: =BR32-BQ32 -> -10.748 | BS26: =SUM(BO26:BR26) -> -91.065 | BT26: 0 | BU26: 0 | BV26: 0 | BW26: 0 | BX26: =SUM(BT26:BW26) -> 0 | BY26: 0 | BZ26: 0 | CA26: 0 | CB26: 0 | CC26: =SUM(BY26:CB26) -> 0
A27: Acquisitions, distributions | AO27: =SUM(AK27:AN27) -> 0 | AT27: =-487.944+2.93 -> -485.014 | AU27: =1.022-5.34 -> -4.318 | AV27: =(2.982-5.34)-AU27 -> 1.96 | AW27: =(3.389-AV27-AU27) -> 5.747 | AX27: =(4.045-5.34)-AW27-AV27-AU27 -> -4.684 | AY27: =SUM(AU27:AX27) -> -1.295 | AZ27: =5.567-5.062 -> 0.505 | BA27: =(6.319-5.062)-AZ27 -> 0.752 | BB27: =(9.11-247.215)-BA27-AZ27 -> -239.362 | BC27: =(9.841-282.429)-BB27-BA27-AZ27 -> -34.483 | BD27: =SUM(AZ27:BC27) -> -272.588 | BE27: 0 | BF27: =0.473 -> 0.473 | BG27: 0 | BH27: 0 | BI27: =SUM(BE27:BH27) -> 0.473 | BJ27: 0 | BK27: =-33.756-BJ27 -> -33.756 | BL27: =-33.756-BK27-BJ27 -> 0 | BM27: -200 | BN27: =SUM(BJ27:BM27) -> -233.756 | BO27: -9.619 | BP27: =-9.619-BO27 -> 0 | BQ27: =-9.619-BP27-BO27 -> 0 | BR27: =-9.619 -> -9.619 | BS27: =SUM(BO27:BR27) -> -19.238 | BT27: 0 | BU27: 0 | BV27: 0 | BW27: 0 | BX27: =SUM(BT27:BW27) -> 0 | BY27: 0 | BZ27: 0 | CA27: 0 | CB27: 0 | CC27: =SUM(BY27:CB27) -> 0
A28: Share buybacks | AO28: =SUM(AK28:AN28) -> 0 | AT28: -200.018 | AU28: -11.797 | AV28: =-24.395-AU28 -> -12.598 | AW28: =-79.092-AV28-AU28 -> -54.697 | AX28: =-343.129-AW28-AV28-AU28 -> -264.037 | AY28: =SUM(AU28:AX28) -> -343.129 | AZ28: -18.857 | BA28: =-31.645-AZ28 -> -12.788 | BB28: =-44.434-BA28-AZ28 -> -12.789 | BC28: =-56.87-BB28-BA28-AZ28 -> -12.436 | BD28: =SUM(AZ28:BC28) -> -56.87 | BE28: -12 | BF28: =-24.365-BE28 -> -12.365 | BG28: -13 | BH28: -13 | BI28: =SUM(BE28:BH28) -> -50.365 | BJ28: -12.19 | BK28: =-24.796-BJ28 -> -12.606 | BL28: =-137.58-BK28-BJ28 -> -112.784 | BM28: -112 | BN28: =SUM(BJ28:BM28) -> -249.58 | BO28: -14 | BP28: =-35.075-BO28 -> -21.075 | BQ28: =-325.112-BP28-BO28 -> -290.037 | BR28: =-464.95-BQ28-BP28-BO28 -> -139.838 | BS28: =SUM(BO28:BR28) -> -464.95 | BT28: =-15 -> -15 | BU28: =-15 -> -15 | BV28: =-15 -> -15 | BW28: =-15 -> -15 | BX28: =SUM(BT28:BW28) -> -60 | BY28: =-15 -> -15 | BZ28: =-15 -> -15 | CA28: =-15 -> -15 | CB28: =-15 -> -15 | CC28: =SUM(BY28:CB28) -> -60
A29: EOP Cash | AO29: 391.033 | AT29: 198.248 | AU29: 147.069 | AV29: =197.508 -> 197.508 | AW29: 234.416 | AX29: 171.004 | AY29: =+AX29 -> 171.004 | AZ29: 136.682 | BA29: 171.414 | BB29: 113.552 | BC29: 256.974 | BD29: =+BC29 -> 256.974 | BE29: 130.659 | BF29: 158.737 | BG29: 148.809 | BH29: 406.867 | BI29: =+BH29 -> 406.867 | BJ29: 338.034 | BK29: 382.564 | BL29: 443.85 | BM29: 385.042 | BN29: =+BM29 -> 385.042 | BO29: 226.459 | BP29: 331.664 | BQ29: 225.427 | BR29: 371.345 | BS29: =+BR29 -> 371.345 | BT29: =+BT18+BT9+SUM(BT25:BT28) -> 295.13765 | BU29: =+BU18+BU9+SUM(BU25:BU28) -> 251.74069 | BV29: =+BV18+BV9+SUM(BV25:BV28) -> 544.93353 | BW29: =+BW18+BW9+SUM(BW25:BW28) -> 856.72474 | BX29: =+BW29 -> 856.72474 | BY29: =+BY18+BY9+SUM(BY25:BY28) -> 973.2768 | BZ29: =+BZ18+BZ9+SUM(BZ25:BZ28) -> 1086.7074 | CA29: =+CA18+CA9+SUM(CA25:CA28) -> 1212.2765 | CB29: =+CB18+CB9+SUM(CB25:CB28) -> 1355.6107 | CC29: =+CB29 -> 1355.6107
A31: Debt/Leverage Analysis | AW31: =CW_IS!AS136 -> 0
A32: Total debt | AO32: =AN32 -> 0 | AT32: =100+958.292 -> 1058.292 | AU32: 1050.61 | AV32: 1050.61 | AW32: 1050.61 | AX32: 1050.61 | AY32: =AX32 -> 1050.61 | AZ32: =202.5+967.744 -> 1170.244 | BA32: =202.5+1006.577 -> 1209.077 | BB32: =202.5+1141.211 -> 1343.711 | BC32: =202.5+1051.9 -> 1254.4 | BD32: =BC32 -> 1254.4 | BE32: 1229.619 | BF32: 1176.066 | BG32: 1050.713 | BH32: 1050.362 | BI32: =BH32 -> 1050.362 | BJ32: =90+960.009 -> 1050.009 | BK32: =90+959.655 -> 1049.655 | BL32: =90+959.302 -> 1049.302 | BM32: =90+958.949 -> 1048.949 | BN32: =BM32 -> 1048.949 | BO32: =958.629 -> 958.629 | BP32: 958.381 | BQ32: 968.632 | BR32: =200+757.884 -> 957.884 | BS32: =BR32 -> 957.884 | BT32: =BS32 -> 957.884 | BU32: =BT32 -> 957.884 | BV32: =BU32 -> 957.884 | BW32: =BV32+BW26 -> 957.884 | BX32: =BW32 -> 957.884 | BY32: =BX32 -> 957.884 | BZ32: =BY32 -> 957.884 | CA32: =BZ32 -> 957.884 | CB32: =CA32 -> 957.884 | CC32: =CB32 -> 957.884
A33: Net debt | AT33: =AT32-AT29 -> 860.044 | AU33: =AU32-AU29 -> 903.541 | AV33: =AV32-AV29 -> 853.102 | AW33: =AW32-AW29 -> 816.194 | AX33: =AX32-AX29 -> 879.606 | AY33: =AY32-AY29 -> 879.606 | AZ33: =AZ32-AZ29 -> 1033.562 | BA33: =BA32-BA29 -> 1037.663 | ... CC33: =CC32-CC29 -> -397.72667
A34: Net leverage (Net debt /EBITDA) | AT34: =AT33/AT10 -> 1.7002488 | AY34: =AY33/AY10 -> 1.6044909 | BD34: =BD33/BD10 -> 1.7483703 | BI34: =BI33/BI10 -> 1.0258949 | BN34: =BN33/BN10 -> 0.98923952 | BS34: =BS33/BS10 -> 0.73562707 | BX34: =BX33/BX10 -> 0.11845076 | CC34: =CC33/CC10 -> -0.43242279
A36: Liquidity
A37: Cash | AO37: =AO29 -> 391.033 | AT37: =AT29 -> 198.248 | AU37: =AU29 -> 147.069 | AV37: =AV29 -> 197.508 | AW37: =AW29 -> 234.416 | AX37: =AX29 -> 171.004 | AY37: =AY29 -> 171.004 | AZ37: =AZ29 -> 136.682 | BA37: =BA29 -> 171.414 | ... CC37: =CC29 -> 1355.6107
A38: Credit Facility | AT38: 479 | AU38: 480 | AV38: 477 | AW38: 478 | AX38: 385 | AY38: =AX38 -> 385 | AZ38: 267 | BA38: 480 | BB38: 347 | BC38: 733 | BD38: =BC38 -> 733 | BE38: 553 | BF38: 604 | BG38: =BF38 -> 604 | BH38: =BG38 -> 604 | BI38: =BH38 -> 604 | BJ38: 731 | BK38: 732 | BL38: =BK38 -> 732 | BM38: =BL38 -> 732 | BN38: =BM38 -> 732 | BO38: =BN38 -> 732 | BP38: =BO38 -> 732 | BQ38: =BP38 -> 732 | BR38: =BQ38 -> 732 | BS38: =BR38 -> 732 | ... CC38: =CB38 -> 732
A39: Total Liquidity | AT39: =SUM(AT37:AT38) -> 677.248 | AU39: =SUM(AU37:AU38) -> 627.069 | AV39: =SUM(AV37:AV38) -> 674.508 | AW39: =SUM(AW37:AW38) -> 712.416 | AX39: =SUM(AX37:AX38) -> 556.004 | AY39: =SUM(AY37:AY38) -> 556.004 | AZ39: =SUM(AZ37:AZ38) -> 403.682 | BA39: =SUM(BA37:BA38) -> 651.414 | ... CC39: =SUM(CC37:CC38) -> 2087.6107
A41: Cash interest expense
A42: Estimated Cash Interest Expense | AT42: =AT12*-1 -> 35.545 | AU42: =AU12*-1 -> 9.959 | AV42: =AV12*-1 -> 10.18 | AW42: =AW12*-1 -> 9.955 | AX42: =AX12*-1 -> 10.146 | AY42: =SUM(AU42:AX42) -> 40.24 | AZ42: =AZ12*-1 -> 9.53 | BA42: =BA12*-1 -> 9.788 | BB42: =BB12*-1 -> 13.997 | BC42: =BC12*-1 -> 13.665 | BD42: =SUM(AZ42:BC42) -> 46.98 | BE42: =BE12*-1 -> 12.944 | BF42: =BF12*-1 -> 14.992 | BG42: =BG12*-1 -> 12.496 | BH42: =BH12*-1 -> 10.961 | BI42: =SUM(BE42:BH42) -> 51.393 | BJ42: =BJ12*-1 -> 10.57 | BK42: =BK12*-1 -> 11.216 | BL42: =BL12*-1 -> 11.408 | BM42: =BM12*-1 -> 11.675 | BN42: =SUM(BJ42:BM42) -> 44.869 | BO42: =BO12*-1 -> 10.143 | BP42: =BP12*-1 -> 10.524 | BQ42: =BQ12*-1 -> 10.484 | BR42: =BR12*-1 -> 11.997 | BS42: =SUM(BO42:BR42) -> 43.148 | BT42: =BT12*-1 -> 10.375 | BU42: =BU12*-1 -> 10.375 | BV42: =BV12*-1 -> 10.375 | BW42: =BW12*-1 -> 10.375 | BX42: =SUM(BT42:BW42) -> 41.5 | BY42: =BY12*-1 -> 10.375 | BZ42: =BZ12*-1 -> 10.375 | CA42: =CA12*-1 -> 10.375 | CB42: =CB12*-1 -> 10.375 | CC42: =SUM(BY42:CB42) -> 41.5
A43: Blended Interest Rate | AT43: =(AT42/AT32) -> 0.033587139 | AU43: =AU42/AU32*4 -> 0.03791702 | AV43: =AV42/AV32*4 -> 0.038758436 | AW43: =AW42/AW32*4 -> 0.03790179 | AX43: =AX42/AX32*4 -> 0.038628987 | AY43: =(AY42/AY32) -> 0.038301558 | AZ43: =AZ42/AZ32*4 -> 0.032574403 | BA43: =BA42/BA32*4 -> 0.032381726 | BB43: =BB42/BB32*4 -> 0.041666698 | BC43: =BC42/BC32*4 -> 0.043574617 | BD43: =(BD42/BD32) -> 0.037452168 | BE43: =BE42/BE32*4 -> 0.042107352 | BF43: =BF42/BF32*4 -> 0.050990336 | BG43: =BG42/BG32*4 -> 0.047571506 | BH43: =BH42/BH32*4 -> 0.041741799 | BI43: =(BI42/BI32) -> 0.048928845 | BJ43: =BJ42/BJ32*4 -> 0.040266322 | BK43: =BK42/BK32*4 -> 0.042741663 | BL43: =BL42/BL32*4 -> 0.043487957 | BM43: =BM42/BM32*4 -> 0.044520754 | BN43: =(BN42/BN32) -> 0.042775197 | BO43: =BO42/BO32*4 -> 0.042322942 | BP43: =BP42/BP32*4 -> 0.043924076 | BQ43: =BQ42/BQ32*4 -> 0.043294048 | BR43: =BR42/BR32*4 -> 0.050097924 | BS43: =(BS42/BS32) -> 0.04504512 | BT43: =BT42/BT32*4 -> 0.043324661 | BU43: =BU42/BU32*4 -> 0.043324661 | BV43: =BV42/BV32*4 -> 0.043324661 | BW43: =BW42/BW32*4 -> 0.043324661 | BX43: =(BX42/BX32) -> 0.043324661 | BY43: =BY42/BY32*4 -> 0.043324661 | BZ43: =BZ42/BZ32*4 -> 0.043324661 | CA43: =CA42/CA32*4 -> 0.043324661 | CB43: =CB42/CB32*4 -> 0.043324661 | CC43: =(CC42/CC32) -> 0.043324661
A45: Source: Company reports and William Blair Equity Research

Sheet WB FIN STATEMENT
B2: Curtiss-Wright Corporation
B3: Summary Financial Statements 2017-2024E
B4: (fiscal year end in December; dollars and shares in millions, except per share data)
B6: INCOME STATEMENT | C6: FY13 | E6: FY14 | G6: FY15 | I6: FY16 | K6: FY17 | M6: FY18 | O6: FY19 | Q6: FY20 | S6: FY21 | U6: FY22 | W6: FY23E | Y6: FY24E
C7: Revenue | D7: Oper. | E7: Revenue | F7: Oper. | G7: Revenue | H7: Oper. | I7: Revenue | J7: Oper. | K7: Revenue | L7: Oper. | M7: Revenue | N7: Oper. | O7: Revenue | P7: Oper. | Q7: Revenue | R7: Oper. | S7: Revenue | T7: Oper. | U7: Revenue | V7: Oper. | W7: Revenue | X7: Oper. | Y7: Revenue | Z7: Oper.
B8: Revenue | D8: Profit | F8: Profit | H8: Profit | J8: Profit | L8: Profit | N8: Profit | P8: Profit | R8: Profit | T8: Profit | V8: Profit | X8: Profit | Z8: Profit
B9: =CW_IS!B8 -> Aerospace & Industrial | C9: =INDEX(CW_IS!$B$7:$BJ$64,MATCH('WB FIN STATEMENT'!$B9,CW_IS!$B$7:$B$64,0),MATCH('WB FIN STATEMENT'!C$6,CW_IS!$B$5:$BJ$5,0)) -> 1076.1 | D9: =INDEX(CW_IS!$B$77:$L$142,MATCH('WB FIN STATEMENT'!$B9,CW_IS!$B$77:$B$142,0),MATCH('WB FIN STATEMENT'!C$6,CW_IS!$B$5:$BJ$5,0)) -> #N/A | E9: =INDEX(CW_IS!$B$7:$BJ$64,MATCH('WB FIN STATEMENT'!$B9,CW_IS!$B$7:$B$64,0),MATCH('WB FIN STATEMENT'!E$6,CW_IS!$B$5:$BJ$5,0)) -> 0 | F9: =INDEX(CW_IS!$B$77:$L$142,MATCH('WB FIN STATEMENT'!$B9,CW_IS!$B$77:$B$142,0),MATCH('WB FIN STATEMENT'!E$6,CW_IS!$B$5:$BJ$5,0)) -> #N/A | G9: =INDEX(CW_IS!$B$7:$BJ$64,MATCH('WB FIN STATEMENT'!$B9,CW_IS!$B$7:$B$64,0),MATCH('WB FIN STATEMENT'!G$6,CW_IS!$B$5:$BJ$5,0)) -> 0 | H9: =INDEX(CW_IS!$B$77:$BJ$142,MATCH('WB FIN STATEMENT'!$B9,CW_IS!$B$77:$B$142,0),MATCH('WB FIN STATEMENT'!G$6,CW_IS!$B$5:$BJ$5,0)) -> #N/A | I9: =INDEX(CW_IS!$B$7:$BJ$64,MATCH('WB FIN STATEMENT'!$B9,CW_IS!$B$7:$B$64,0),MATCH('WB FIN STATEMENT'!I$6,CW_IS!$B$5:$BJ$5,0)) -> 0 | J9: =INDEX(CW_IS!$B$77:$BJ$142,MATCH('WB FIN STATEMENT'!$B9,CW_IS!$B$77:$B$142,0),MATCH('WB FIN STATEMENT'!I$6,CW_IS!$B$5:$BJ$5,0)) -> #N/A | K9: =INDEX(CW_IS!$B$7:$BJ$64,MATCH('WB FIN STATEMENT'!$B9,CW_IS!$B$7:$B$64,0),MATCH('WB FIN STATEMENT'!K$6,CW_IS!$B$5:$BJ$5,0)) -> 0 | L9: =INDEX(CW_IS!$B$77:$BJ$142,MATCH('WB FIN STATEMENT'!$B9,CW_IS!$B$77:$B$142,0),MATCH('WB FIN STATEMENT'!K$6,CW_IS!$B$5:$BJ$5,0)) -> #N/A | M9: =INDEX(CW_IS!$B$7:$BJ$64,MATCH('WB FIN STATEMENT'!$B9,CW_IS!$B$7:$B$64,0),MATCH('WB FIN STATEMENT'!M$6,CW_IS!$B$5:$BJ$5,0)) -> 0 | N9: =INDEX(CW_IS!$B$77:$BJ$142,MATCH('WB FIN STATEMENT'!$B9,CW_IS!$B$77:$B$142,0),MATCH('WB FIN STATEMENT'!M$6,CW_IS!$B$5:$BJ$5,0)) -> #N/A | O9: =INDEX(CW_IS!$B$7:$BJ$64,MATCH('WB FIN STATEMENT'!$B9,CW_IS!$B$7:$B$64,0),MATCH('WB FIN STATEMENT'!O$6,CW_IS!$B$5:$BJ$5,0)) -> 892.47666 | P9: =INDEX(CW_IS!$B$77:$BJ$142,MATCH('WB FIN STATEMENT'!$B9,CW_IS!$B$77:$B$142,0),MATCH('WB FIN STATEMENT'!O$6,CW_IS!$B$5:$BJ$5,0)) -> #N/A | Q9: =INDEX(CW_IS!$B$7:$BJ$64,MATCH('WB FIN STATEMENT'!$B9,CW_IS!$B$7:$B$64,0),MATCH('WB FIN STATEMENT'!Q$6,CW_IS!$B$5:$BJ$5,0)) -> 738.19071 | R9: =INDEX(CW_IS!$B$77:$BJ$142,MATCH('WB FIN STATEMENT'!$B9,CW_IS!$B$77:$B$142,0),MATCH('WB FIN STATEMENT'!Q$6,CW_IS!$B$5:$BJ$5,0)) -> #N/A | S9: =INDEX(CW_IS!$B$7:$BJ$64,MATCH('WB FIN STATEMENT'!$B9,CW_IS!$B$7:$B$64,0),MATCH('WB FIN STATEMENT'!S$6,CW_IS!$B$5:$BJ$5,0)) -> 775.076 | T9: =INDEX(CW_IS!$B$77:$BJ$142,MATCH('WB FIN STATEMENT'!$B9,CW_IS!$B$77:$B$142,0),MATCH('WB FIN STATEMENT'!S$6,CW_IS!$B$5:$BJ$5,0)) -> #N/A | U9: =INDEX(CW_IS!$B$7:$BJ$64,MATCH('WB FIN STATEMENT'!$B9,CW_IS!$B$7:$B$64,0),MATCH('WB FIN STATEMENT'!U$6,CW_IS!$B$5:$BJ$5,0)) -> 836.035 | V9: =INDEX(CW_IS!$B$77:$BJ$142,MATCH('WB FIN STATEMENT'!$B9,CW_IS!$B$77:$B$142,0),MATCH('WB FIN STATEMENT'!U$6,CW_IS!$B$5:$BJ$5,0)) -> #N/A | W9: =INDEX(CW_IS!$B$7:$BJ$64,MATCH('WB FIN STATEMENT'!$B9,CW_IS!$B$7:$B$64,0),MATCH('WB FIN STATEMENT'!W$6,CW_IS!$B$5:$BJ$5,0)) -> #N/A | X9: =INDEX(CW_IS!$B$77:$BJ$142,MATCH('WB FIN STATEMENT'!$B9,CW_IS!$B$77:$B$142,0),MATCH('WB FIN STATEMENT'!W$6,CW_IS!$B$5:$BJ$5,0)) -> #N/A | Y9: =INDEX(CW_IS!$B$7:$BJ$64,MATCH('WB FIN STATEMENT'!$B9,CW_IS!$B$7:$B$64,0),MATCH('WB FIN STATEMENT'!Y$6,CW_IS!$B$5:$BJ$5,0)) -> #N/A | Z9: =INDEX(CW_IS!$B$77:$BJ$142,MATCH('WB FIN STATEMENT'!$B9,CW_IS!$B$77:$B$142,0),MATCH('WB FIN STATEMENT'!Y$6,CW_IS!$B$5:$BJ$5,0)) -> #N/A
B10: =CW_IS!B23 -> Defense Electronics | C10: =INDEX(CW_IS!$B$7:$BJ$64,MATCH('WB FIN STATEMENT'!$B10,CW_IS!$B$7:$B$64,0),MATCH('WB FIN STATEMENT'!C$6,CW_IS!$B$5:$BJ$5,0)) -> 480.3 | D10: =INDEX(CW_IS!$B$77:$L$142,MATCH('WB FIN STATEMENT'!$B10,CW_IS!$B$77:$B$142,0),MATCH('WB FIN STATEMENT'!C$6,CW_IS!$B$5:$BJ$5,0)) -> 74.4 | E10: =INDEX(CW_IS!$B$7:$BJ$64,MATCH('WB FIN STATEMENT'!$B10,CW_IS!$B$7:$B$64,0),MATCH('WB FIN STATEMENT'!E$6,CW_IS!$B$5:$BJ$5,0)) -> 0 | F10: =INDEX(CW_IS!$B$77:$L$142,MATCH('WB FIN STATEMENT'!$B10,CW_IS!$B$77:$B$142,0),MATCH('WB FIN STATEMENT'!E$6,CW_IS!$B$5:$BJ$5,0)) -> 0 | G10: =INDEX(CW_IS!$B$7:$BJ$64,MATCH('WB FIN STATEMENT'!$B10,CW_IS!$B$7:$B$64,0),MATCH('WB FIN STATEMENT'!G$6,CW_IS!$B$5:$BJ$5,0)) -> 0 | H10: =INDEX(CW_IS!$B$77:$BJ$142,MATCH('WB FIN STATEMENT'!$B10,CW_IS!$B$77:$B$142,0),MATCH('WB FIN STATEMENT'!G$6,CW_IS!$B$5:$BJ$5,0)) -> 0 | I10: =INDEX(CW_IS!$B$7:$BJ$64,MATCH('WB FIN STATEMENT'!$B10,CW_IS!$B$7:$B$64,0),MATCH('WB FIN STATEMENT'!I$6,CW_IS!$B$5:$BJ$5,0)) -> 0 | J10: =INDEX(CW_IS!$B$77:$BJ$142,MATCH('WB FIN STATEMENT'!$B10,CW_IS!$B$77:$B$142,0),MATCH('WB FIN STATEMENT'!I$6,CW_IS!$B$5:$BJ$5,0)) -> 0 | K10: =INDEX(CW_IS!$B$7:$BJ$64,MATCH('WB FIN STATEMENT'!$B10,CW_IS!$B$7:$B$64,0),MATCH('WB FIN STATEMENT'!K$6,CW_IS!$B$5:$BJ$5,0)) -> 0 | L10: =INDEX(CW_IS!$B$77:$BJ$142,MATCH('WB FIN STATEMENT'!$B10,CW_IS!$B$77:$B$142,0),MATCH('WB FIN STATEMENT'!K$6,CW_IS!$B$5:$BJ$5,0)) -> 0 | M10: =INDEX(CW_IS!$B$7:$BJ$64,MATCH('WB FIN STATEMENT'!$B10,CW_IS!$B$7:$B$64,0),MATCH('WB FIN STATEMENT'!M$6,CW_IS!$B$5:$BJ$5,0)) -> 0 | N10: =INDEX(CW_IS!$B$77:$BJ$142,MATCH('WB FIN STATEMENT'!$B10,CW_IS!$B$77:$B$142,0),MATCH('WB FIN STATEMENT'!M$6,CW_IS!$B$5:$BJ$5,0)) -> 0 | O10: =INDEX(CW_IS!$B$7:$BJ$64,MATCH('WB FIN STATEMENT'!$B10,CW_IS!$B$7:$B$64,0),MATCH('WB FIN STATEMENT'!O$6,CW_IS!$B$5:$BJ$5,0)) -> 525.44245 | P10: =INDEX(CW_IS!$B$77:$BJ$142,MATCH('WB FIN STATEMENT'!$B10,CW_IS!$B$77:$B$142,0),MATCH('WB FIN STATEMENT'!O$6,CW_IS!$B$5:$BJ$5,0)) -> 121.13559 | Q10: =INDEX(CW_IS!$B$7:$BJ$64,MATCH('WB FIN STATEMENT'!$B10,CW_IS!$B$7:$B$64,0),MATCH('WB FIN STATEMENT'!Q$6,CW_IS!$B$5:$BJ$5,0)) -> 610.639 | R10: =INDEX(CW_IS!$B$77:$BJ$142,MATCH('WB FIN STATEMENT'!$B10,CW_IS!$B$77:$B$142,0),MATCH('WB FIN STATEMENT'!Q$6,CW_IS!$B$5:$BJ$5,0)) -> 144.37213 | S10: =INDEX(CW_IS!$B$7:$BJ$64,MATCH('WB FIN STATEMENT'!$B10,CW_IS!$B$7:$B$64,0),MATCH('WB FIN STATEMENT'!S$6,CW_IS!$B$5:$BJ$5,0)) -> 727.919 | T10: =INDEX(CW_IS!$B$77:$BJ$142,MATCH('WB FIN STATEMENT'!$B10,CW_IS!$B$77:$B$142,0),MATCH('WB FIN STATEMENT'!S$6,CW_IS!$B$5:$BJ$5,0)) -> 164.175 | U10: =INDEX(CW_IS!$B$7:$BJ$64,MATCH('WB FIN STATEMENT'!$B10,CW_IS!$B$7:$B$64,0),MATCH('WB FIN STATEMENT'!U$6,CW_IS!$B$5:$BJ$5,0)) -> 690.262 | V10: =INDEX(CW_IS!$B$77:$BJ$142,MATCH('WB FIN STATEMENT'!$B10,CW_IS!$B$77:$B$142,0),MATCH('WB FIN STATEMENT'!U$6,CW_IS!$B$5:$BJ$5,0)) -> 154.568 | W10: =INDEX(CW_IS!$B$7:$BJ$64,MATCH('WB FIN STATEMENT'!$B10,CW_IS!$B$7:$B$64,0),MATCH('WB FIN STATEMENT'!W$6,CW_IS!$B$5:$BJ$5,0)) -> #N/A | X10: =INDEX(CW_IS!$B$77:$BJ$142,MATCH('WB FIN STATEMENT'!$B10,CW_IS!$B$77:$B$142,0),MATCH('WB FIN STATEMENT'!W$6,CW_IS!$B$5:$BJ$5,0)) -> #N/A | Y10: =INDEX(CW_IS!$B$7:$BJ$64,MATCH('WB FIN STATEMENT'!$B10,CW_IS!$B$7:$B$64,0),MATCH('WB FIN STATEMENT'!Y$6,CW_IS!$B$5:$BJ$5,0)) -> #N/A | Z10: =INDEX(CW_IS!$B$77:$BJ$142,MATCH('WB FIN STATEMENT'!$B10,CW_IS!$B$77:$B$142,0),MATCH('WB FIN STATEMENT'!Y$6,CW_IS!$B$5:$BJ$5,0)) -> #N/A
B11: =CW_IS!B40 -> Naval & Power | C11: =INDEX(CW_IS!$B$7:$BJ$64,MATCH('WB FIN STATEMENT'!$B11,CW_IS!$B$7:$B$64,0),MATCH('WB FIN STATEMENT'!C$6,CW_IS!$B$5:$BJ$5,0)) -> 561.7 | D11: =INDEX(CW_IS!$B$77:$L$142,MATCH('WB FIN STATEMENT'!$B11,CW_IS!$B$77:$B$142,0),MATCH('WB FIN STATEMENT'!C$6,CW_IS!$B$5:$BJ$5,0)) -> 73.3 | E11: =INDEX(CW_IS!$B$7:$BJ$64,MATCH('WB FIN STATEMENT'!$B11,CW_IS!$B$7:$B$64,0),MATCH('WB FIN STATEMENT'!E$6,CW_IS!$B$5:$BJ$5,0)) -> 0 | F11: =INDEX(CW_IS!$B$77:$L$142,MATCH('WB FIN STATEMENT'!$B11,CW_IS!$B$77:$B$142,0),MATCH('WB FIN STATEMENT'!E$6,CW_IS!$B$5:$BJ$5,0)) -> 0 | G11: =INDEX(CW_IS!$B$7:$BJ$64,MATCH('WB FIN STATEMENT'!$B11,CW_IS!$B$7:$B$64,0),MATCH('WB FIN STATEMENT'!G$6,CW_IS!$B$5:$BJ$5,0)) -> 0 | H11: =INDEX(CW_IS!$B$77:$BJ$142,MATCH('WB FIN STATEMENT'!$B11,CW_IS!$B$77:$B$142,0),MATCH('WB FIN STATEMENT'!G$6,CW_IS!$B$5:$BJ$5,0)) -> 0 | I11: =INDEX(CW_IS!$B$7:$BJ$64,MATCH('WB FIN STATEMENT'!$B11,CW_IS!$B$7:$B$64,0),MATCH('WB FIN STATEMENT'!I$6,CW_IS!$B$5:$BJ$5,0)) -> 0 | J11: =INDEX(CW_IS!$B$77:$BJ$142,MATCH('WB FIN STATEMENT'!$B11,CW_IS!$B$77:$B$142,0),MATCH('WB FIN STATEMENT'!I$6,CW_IS!$B$5:$BJ$5,0)) -> 0 | K11: =INDEX(CW_IS!$B$7:$BJ$64,MATCH('WB FIN STATEMENT'!$B11,CW_IS!$B$7:$B$64,0),MATCH('WB FIN STATEMENT'!K$6,CW_IS!$B$5:$BJ$5,0)) -> 0 | L11: =INDEX(CW_IS!$B$77:$BJ$142,MATCH('WB FIN STATEMENT'!$B11,CW_IS!$B$77:$B$142,0),MATCH('WB FIN STATEMENT'!K$6,CW_IS!$B$5:$BJ$5,0)) -> 0 | M11: =INDEX(CW_IS!$B$7:$BJ$64,MATCH('WB FIN STATEMENT'!$B11,CW_IS!$B$7:$B$64,0),MATCH('WB FIN STATEMENT'!M$6,CW_IS!$B$5:$BJ$5,0)) -> 0 | N11: =INDEX(CW_IS!$B$77:$BJ$142,MATCH('WB FIN STATEMENT'!$B11,CW_IS!$B$77:$B$142,0),MATCH('WB FIN STATEMENT'!M$6,CW_IS!$B$5:$BJ$5,0)) -> 0 | O11: =INDEX(CW_IS!$B$7:$BJ$64,MATCH('WB FIN STATEMENT'!$B11,CW_IS!$B$7:$B$64,0),MATCH('WB FIN STATEMENT'!O$6,CW_IS!$B$5:$BJ$5,0)) -> 960.88813 | P11: =INDEX(CW_IS!$B$77:$BJ$142,MATCH('WB FIN STATEMENT'!$B11,CW_IS!$B$77:$B$142,0),MATCH('WB FIN STATEMENT'!O$6,CW_IS!$B$5:$BJ$5,0)) -> 174.05656 | Q11: =INDEX(CW_IS!$B$7:$BJ$64,MATCH('WB FIN STATEMENT'!$B11,CW_IS!$B$7:$B$64,0),MATCH('WB FIN STATEMENT'!Q$6,CW_IS!$B$5:$BJ$5,0)) -> 950.94268 | R11: =INDEX(CW_IS!$B$77:$BJ$142,MATCH('WB FIN STATEMENT'!$B11,CW_IS!$B$77:$B$142,0),MATCH('WB FIN STATEMENT'!Q$6,CW_IS!$B$5:$BJ$5,0)) -> 170.86616 | S11: =INDEX(CW_IS!$B$7:$BJ$64,MATCH('WB FIN STATEMENT'!$B11,CW_IS!$B$7:$B$64,0),MATCH('WB FIN STATEMENT'!S$6,CW_IS!$B$5:$BJ$5,0)) -> 965.304 | T11: =INDEX(CW_IS!$B$77:$BJ$142,MATCH('WB FIN STATEMENT'!$B11,CW_IS!$B$77:$B$142,0),MATCH('WB FIN STATEMENT'!S$6,CW_IS!$B$5:$BJ$5,0)) -> 175.827 | U11: =INDEX(CW_IS!$B$7:$BJ$64,MATCH('WB FIN STATEMENT'!$B11,CW_IS!$B$7:$B$64,0),MATCH('WB FIN STATEMENT'!U$6,CW_IS!$B$5:$BJ$5,0)) -> 1030.728 | V11: =INDEX(CW_IS!$B$77:$BJ$142,MATCH('WB FIN STATEMENT'!$B11,CW_IS!$B$77:$B$142,0),MATCH('WB FIN STATEMENT'!U$6,CW_IS!$B$5:$BJ$5,0)) -> 191.638 | W11: =INDEX(CW_IS!$B$7:$BJ$64,MATCH('WB FIN STATEMENT'!$B11,CW_IS!$B$7:$B$64,0),MATCH('WB FIN STATEMENT'!W$6,CW_IS!$B$5:$BJ$5,0)) -> #N/A | X11: =INDEX(CW_IS!$B$77:$BJ$142,MATCH('WB FIN STATEMENT'!$B11,CW_IS!$B$77:$B$142,0),MATCH('WB FIN STATEMENT'!W$6,CW_IS!$B$5:$BJ$5,0)) -> #N/A | Y11: =INDEX(CW_IS!$B$7:$BJ$64,MATCH('WB FIN STATEMENT'!$B11,CW_IS!$B$7:$B$64,0),MATCH('WB FIN STATEMENT'!Y$6,CW_IS!$B$5:$BJ$5,0)) -> #N/A | Z11: =INDEX(CW_IS!$B$77:$BJ$142,MATCH('WB FIN STATEMENT'!$B11,CW_IS!$B$77:$B$142,0),MATCH('WB FIN STATEMENT'!Y$6,CW_IS!$B$5:$BJ$5,0)) -> #N/A
B12: Total | C12: =SUM(C9:C11) -> 2118.1 | D12: =SUM(D9:D11) -> #N/A | E12: =SUM(E9:E11) -> 0 | F12: =SUM(F9:F11) -> #N/A | G12: =SUM(G9:G11) -> 0 | H12: =SUM(H9:H11) -> #N/A | I12: =SUM(I9:I11) -> 0 | J12: =SUM(J9:J11) -> #N/A | ... Z12: =SUM(Z9:Z11) -> #N/A
B14: Total Operating Profit - Adjusted* | C14: =INDEX(CW_IS!$B$77:$L$142,MATCH('WB FIN STATEMENT'!$B14,CW_IS!$B$77:$B$142,0),MATCH('WB FIN STATEMENT'!C$6,CW_IS!$B$5:$BJ$5,0)) -> 237.1 | E14: =INDEX(CW_IS!$B$77:$L$142,MATCH('WB FIN STATEMENT'!$B14,CW_IS!$B$77:$B$142,0),MATCH('WB FIN STATEMENT'!E$6,CW_IS!$B$5:$BJ$5,0)) -> 282.373 | G14: =INDEX(CW_IS!$B$77:$BJ$142,MATCH('WB FIN STATEMENT'!$B14,CW_IS!$B$77:$B$142,0),MATCH('WB FIN STATEMENT'!G$6,CW_IS!$B$5:$BJ$5,0)) -> 310.617 | I14: =INDEX(CW_IS!$B$77:$BJ$142,MATCH('WB FIN STATEMENT'!$B14,CW_IS!$B$77:$B$142,0),MATCH('WB FIN STATEMENT'!I$6,CW_IS!$B$5:$BJ$5,0)) -> 308.098 | K14: =INDEX(CW_IS!$B$77:$BJ$142,MATCH('WB FIN STATEMENT'!$B14,CW_IS!$B$77:$B$142,0),MATCH('WB FIN STATEMENT'!K$6,CW_IS!$B$5:$BJ$5,0)) -> 334.591 | M14: =INDEX(CW_IS!$B$77:$BJ$142,MATCH('WB FIN STATEMENT'!$B14,CW_IS!$B$77:$B$142,0),MATCH('WB FIN STATEMENT'!M$6,CW_IS!$B$5:$BJ$5,0)) -> 382.275 | O14: =INDEX(CW_IS!$B$77:$BJ$142,MATCH('WB FIN STATEMENT'!$B14,CW_IS!$B$77:$B$142,0),MATCH('WB FIN STATEMENT'!O$6,CW_IS!$B$5:$BJ$5,0)) -> 389.38872 | Q14: =INDEX(CW_IS!$B$77:$BJ$142,MATCH('WB FIN STATEMENT'!$B14,CW_IS!$B$77:$B$142,0),MATCH('WB FIN STATEMENT'!Q$6,CW_IS!$B$5:$BJ$5,0)) -> 375.49419 | S14: =INDEX(CW_IS!$B$77:$BJ$142,MATCH('WB FIN STATEMENT'!$B14,CW_IS!$B$77:$B$142,0),MATCH('WB FIN STATEMENT'!S$6,CW_IS!$B$5:$BJ$5,0)) -> 420.381 | U14: =INDEX(CW_IS!$B$77:$BJ$142,MATCH('WB FIN STATEMENT'!$B14,CW_IS!$B$77:$B$142,0),MATCH('WB FIN STATEMENT'!U$6,CW_IS!$B$5:$BJ$5,0)) -> 443.078 | W14: =INDEX(CW_IS!$B$77:$BJ$142,MATCH('WB FIN STATEMENT'!$B14,CW_IS!$B$77:$B$142,0),MATCH('WB FIN STATEMENT'!W$6,CW_IS!$B$5:$BJ$5,0)) -> #N/A | Y14: =INDEX(CW_IS!$B$77:$BJ$142,MATCH('WB FIN STATEMENT'!$B14,CW_IS!$B$77:$B$142,0),MATCH('WB FIN STATEMENT'!Y$6,CW_IS!$B$5:$BJ$5,0)) -> #N/A
B15: Corporate expense | C15: =INDEX(CW_IS!$B$77:$L$142,MATCH('WB FIN STATEMENT'!$B15,CW_IS!$B$77:$B$142,0),MATCH('WB FIN STATEMENT'!C$6,CW_IS!$B$5:$BJ$5,0)) -> -41.9 | E15: =INDEX(CW_IS!$B$77:$L$142,MATCH('WB FIN STATEMENT'!$B15,CW_IS!$B$77:$B$142,0),MATCH('WB FIN STATEMENT'!E$6,CW_IS!$B$5:$BJ$5,0)) -> 0 | G15: =INDEX(CW_IS!$B$77:$BJ$142,MATCH('WB FIN STATEMENT'!$B15,CW_IS!$B$77:$B$142,0),MATCH('WB FIN STATEMENT'!G$6,CW_IS!$B$5:$BJ$5,0)) -> 0 | I15: =INDEX(CW_IS!$B$77:$BJ$142,MATCH('WB FIN STATEMENT'!$B15,CW_IS!$B$77:$B$142,0),MATCH('WB FIN STATEMENT'!I$6,CW_IS!$B$5:$BJ$5,0)) -> 0 | K15: =INDEX(CW_IS!$B$77:$BJ$142,MATCH('WB FIN STATEMENT'!$B15,CW_IS!$B$77:$B$142,0),MATCH('WB FIN STATEMENT'!K$6,CW_IS!$B$5:$BJ$5,0)) -> 0 | M15: =INDEX(CW_IS!$B$77:$BJ$142,MATCH('WB FIN STATEMENT'!$B15,CW_IS!$B$77:$B$142,0),MATCH('WB FIN STATEMENT'!M$6,CW_IS!$B$5:$BJ$5,0)) -> 0 | O15: =INDEX(CW_IS!$B$77:$BJ$142,MATCH('WB FIN STATEMENT'!$B15,CW_IS!$B$77:$B$142,0),MATCH('WB FIN STATEMENT'!O$6,CW_IS!$B$5:$BJ$5,0)) -> -34.786975 | Q15: =INDEX(CW_IS!$B$77:$BJ$142,MATCH('WB FIN STATEMENT'!$B15,CW_IS!$B$77:$B$142,0),MATCH('WB FIN STATEMENT'!Q$6,CW_IS!$B$5:$BJ$5,0)) -> -37.578855 | S15: =INDEX(CW_IS!$B$77:$BJ$142,MATCH('WB FIN STATEMENT'!$B15,CW_IS!$B$77:$B$142,0),MATCH('WB FIN STATEMENT'!S$6,CW_IS!$B$5:$BJ$5,0)) -> -39.857 | U15: =INDEX(CW_IS!$B$77:$BJ$142,MATCH('WB FIN STATEMENT'!$B15,CW_IS!$B$77:$B$142,0),MATCH('WB FIN STATEMENT'!U$6,CW_IS!$B$5:$BJ$5,0)) -> -40.827 | W15: =INDEX(CW_IS!$B$77:$BJ$142,MATCH('WB FIN STATEMENT'!$B15,CW_IS!$B$77:$B$142,0),MATCH('WB FIN STATEMENT'!W$6,CW_IS!$B$5:$BJ$5,0)) -> #N/A | Y15: =INDEX(CW_IS!$B$77:$BJ$142,MATCH('WB FIN STATEMENT'!$B15,CW_IS!$B$77:$B$142,0),MATCH('WB FIN STATEMENT'!Y$6,CW_IS!$B$5:$BJ$5,0)) -> #N/A
B16: Interest expense, net | C16: =INDEX(CW_IS!$B$77:$L$142,MATCH('WB FIN STATEMENT'!$B16,CW_IS!$B$77:$B$142,0),MATCH('WB FIN STATEMENT'!C$6,CW_IS!$B$5:$BJ$5,0)) -> -37.053 | E16: =INDEX(CW_IS!$B$77:$L$142,MATCH('WB FIN STATEMENT'!$B16,CW_IS!$B$77:$B$142,0),MATCH('WB FIN STATEMENT'!E$6,CW_IS!$B$5:$BJ$5,0)) -> -35.794 | G16: =INDEX(CW_IS!$B$77:$BJ$142,MATCH('WB FIN STATEMENT'!$B16,CW_IS!$B$77:$B$142,0),MATCH('WB FIN STATEMENT'!G$6,CW_IS!$B$5:$BJ$5,0)) -> -36.038 | I16: =INDEX(CW_IS!$B$77:$BJ$142,MATCH('WB FIN STATEMENT'!$B16,CW_IS!$B$77:$B$142,0),MATCH('WB FIN STATEMENT'!I$6,CW_IS!$B$5:$BJ$5,0)) -> -41.248 | K16: =INDEX(CW_IS!$B$77:$BJ$142,MATCH('WB FIN STATEMENT'!$B16,CW_IS!$B$77:$B$142,0),MATCH('WB FIN STATEMENT'!K$6,CW_IS!$B$5:$BJ$5,0)) -> -40.784 | M16: =INDEX(CW_IS!$B$77:$BJ$142,MATCH('WB FIN STATEMENT'!$B16,CW_IS!$B$77:$B$142,0),MATCH('WB FIN STATEMENT'!M$6,CW_IS!$B$5:$BJ$5,0)) -> -33.983 | O16: =INDEX(CW_IS!$B$77:$BJ$142,MATCH('WB FIN STATEMENT'!$B16,CW_IS!$B$77:$B$142,0),MATCH('WB FIN STATEMENT'!O$6,CW_IS!$B$5:$BJ$5,0)) -> -31.347 | Q16: =INDEX(CW_IS!$B$77:$BJ$142,MATCH('WB FIN STATEMENT'!$B16,CW_IS!$B$77:$B$142,0),MATCH('WB FIN STATEMENT'!Q$6,CW_IS!$B$5:$BJ$5,0)) -> -35.545 | S16: =INDEX(CW_IS!$B$77:$BJ$142,MATCH('WB FIN STATEMENT'!$B16,CW_IS!$B$77:$B$142,0),MATCH('WB FIN STATEMENT'!S$6,CW_IS!$B$5:$BJ$5,0)) -> -40.24 | U16: =INDEX(CW_IS!$B$77:$BJ$142,MATCH('WB FIN STATEMENT'!$B16,CW_IS!$B$77:$B$142,0),MATCH('WB FIN STATEMENT'!U$6,CW_IS!$B$5:$BJ$5,0)) -> -46.98 | W16: =INDEX(CW_IS!$B$77:$BJ$142,MATCH('WB FIN STATEMENT'!$B16,CW_IS!$B$77:$B$142,0),MATCH('WB FIN STATEMENT'!W$6,CW_IS!$B$5:$BJ$5,0)) -> #N/A | Y16: =INDEX(CW_IS!$B$77:$BJ$142,MATCH('WB FIN STATEMENT'!$B16,CW_IS!$B$77:$B$142,0),MATCH('WB FIN STATEMENT'!Y$6,CW_IS!$B$5:$BJ$5,0)) -> #N/A
B18: Pre-Tax Income | C18: =INDEX(CW_IS!$B$77:$L$142,MATCH('WB FIN STATEMENT'!$B18,CW_IS!$B$77:$B$142,0),MATCH('WB FIN STATEMENT'!C$6,CW_IS!$B$5:$BJ$5,0)) -> 201.027 | E18: =INDEX(CW_IS!$B$77:$L$142,MATCH('WB FIN STATEMENT'!$B18,CW_IS!$B$77:$B$142,0),MATCH('WB FIN STATEMENT'!E$6,CW_IS!$B$5:$BJ$5,0)) -> 246.944 | G18: =INDEX(CW_IS!$B$77:$BJ$142,MATCH('WB FIN STATEMENT'!$B18,CW_IS!$B$77:$B$142,0),MATCH('WB FIN STATEMENT'!G$6,CW_IS!$B$5:$BJ$5,0)) -> 275.194 | I18: =INDEX(CW_IS!$B$77:$BJ$142,MATCH('WB FIN STATEMENT'!$B18,CW_IS!$B$77:$B$142,0),MATCH('WB FIN STATEMENT'!I$6,CW_IS!$B$5:$BJ$5,0)) -> 267.961 | K18: =INDEX(CW_IS!$B$77:$BJ$142,MATCH('WB FIN STATEMENT'!$B18,CW_IS!$B$77:$B$142,0),MATCH('WB FIN STATEMENT'!K$6,CW_IS!$B$5:$BJ$5,0)) -> 309.84 | M18: =INDEX(CW_IS!$B$77:$BJ$142,MATCH('WB FIN STATEMENT'!$B18,CW_IS!$B$77:$B$142,0),MATCH('WB FIN STATEMENT'!M$6,CW_IS!$B$5:$BJ$5,0)) -> 364.888 | O18: =INDEX(CW_IS!$B$77:$BJ$142,MATCH('WB FIN STATEMENT'!$B18,CW_IS!$B$77:$B$142,0),MATCH('WB FIN STATEMENT'!O$6,CW_IS!$B$5:$BJ$5,0)) -> 381.89772 | Q18: =INDEX(CW_IS!$B$77:$BJ$142,MATCH('WB FIN STATEMENT'!$B18,CW_IS!$B$77:$B$142,0),MATCH('WB FIN STATEMENT'!Q$6,CW_IS!$B$5:$BJ$5,0)) -> 359.69719 | S18: =INDEX(CW_IS!$B$77:$BJ$142,MATCH('WB FIN STATEMENT'!$B18,CW_IS!$B$77:$B$142,0),MATCH('WB FIN STATEMENT'!S$6,CW_IS!$B$5:$BJ$5,0)) -> 392.208 | U18: =INDEX(CW_IS!$B$77:$BJ$142,MATCH('WB FIN STATEMENT'!$B18,CW_IS!$B$77:$B$142,0),MATCH('WB FIN STATEMENT'!U$6,CW_IS!$B$5:$BJ$5,0)) -> 408.83 | W18: =INDEX(CW_IS!$B$77:$BJ$142,MATCH('WB FIN STATEMENT'!$B18,CW_IS!$B$77:$B$142,0),MATCH('WB FIN STATEMENT'!W$6,CW_IS!$B$5:$BJ$5,0)) -> #N/A | Y18: =INDEX(CW_IS!$B$77:$BJ$142,MATCH('WB FIN STATEMENT'!$B18,CW_IS!$B$77:$B$142,0),MATCH('WB FIN STATEMENT'!Y$6,CW_IS!$B$5:$BJ$5,0)) -> #N/A
B19: Income Tax Provision (Benefit) | C19: =INDEX(CW_IS!$B$77:$L$142,MATCH('WB FIN STATEMENT'!$B19,CW_IS!$B$77:$B$142,0),MATCH('WB FIN STATEMENT'!C$6,CW_IS!$B$5:$BJ$5,0)) -> 61.646 | E19: =INDEX(CW_IS!$B$77:$L$142,MATCH('WB FIN STATEMENT'!$B19,CW_IS!$B$77:$B$142,0),MATCH('WB FIN STATEMENT'!E$6,CW_IS!$B$5:$BJ$5,0)) -> 76.995 | G19: =INDEX(CW_IS!$B$77:$BJ$142,MATCH('WB FIN STATEMENT'!$B19,CW_IS!$B$77:$B$142,0),MATCH('WB FIN STATEMENT'!G$6,CW_IS!$B$5:$BJ$5,0)) -> 82.946 | I19: =INDEX(CW_IS!$B$77:$BJ$142,MATCH('WB FIN STATEMENT'!$B19,CW_IS!$B$77:$B$142,0),MATCH('WB FIN STATEMENT'!I$6,CW_IS!$B$5:$BJ$5,0)) -> 78.579 | K19: =INDEX(CW_IS!$B$77:$BJ$142,MATCH('WB FIN STATEMENT'!$B19,CW_IS!$B$77:$B$142,0),MATCH('WB FIN STATEMENT'!K$6,CW_IS!$B$5:$BJ$5,0)) -> 87.713 | M19: =INDEX(CW_IS!$B$77:$BJ$142,MATCH('WB FIN STATEMENT'!$B19,CW_IS!$B$77:$B$142,0),MATCH('WB FIN STATEMENT'!M$6,CW_IS!$B$5:$BJ$5,0)) -> 82.54 | O19: =INDEX(CW_IS!$B$77:$BJ$142,MATCH('WB FIN STATEMENT'!$B19,CW_IS!$B$77:$B$142,0),MATCH('WB FIN STATEMENT'!O$6,CW_IS!$B$5:$BJ$5,0)) -> 90.379 | Q19: =INDEX(CW_IS!$B$77:$BJ$142,MATCH('WB FIN STATEMENT'!$B19,CW_IS!$B$77:$B$142,0),MATCH('WB FIN STATEMENT'!Q$6,CW_IS!$B$5:$BJ$5,0)) -> 82.6456 | S19: =INDEX(CW_IS!$B$77:$BJ$142,MATCH('WB FIN STATEMENT'!$B19,CW_IS!$B$77:$B$142,0),MATCH('WB FIN STATEMENT'!S$6,CW_IS!$B$5:$BJ$5,0)) -> 94.38436 | U19: =INDEX(CW_IS!$B$77:$BJ$142,MATCH('WB FIN STATEMENT'!$B19,CW_IS!$B$77:$B$142,0),MATCH('WB FIN STATEMENT'!U$6,CW_IS!$B$5:$BJ$5,0)) -> 94.61028 | W19: =INDEX(CW_IS!$B$77:$BJ$142,MATCH('WB FIN STATEMENT'!$B19,CW_IS!$B$77:$B$142,0),MATCH('WB FIN STATEMENT'!W$6,CW_IS!$B$5:$BJ$5,0)) -> #N/A | Y19: =INDEX(CW_IS!$B$77:$BJ$142,MATCH('WB FIN STATEMENT'!$B19,CW_IS!$B$77:$B$142,0),MATCH('WB FIN STATEMENT'!Y$6,CW_IS!$B$5:$BJ$5,0)) -> #N/A
B21: Net Income - Adjusted from Continuing Ops | C21: =C18-C19 -> 139.381 | E21: =E18-E19 -> 169.949 | G21: =G18-G19 -> 192.248 | I21: =I18-I19 -> 189.382 | K21: =K18-K19+K23 -> 222.127 | M21: =M18-M19 -> 282.348 | O21: =O18-O19 -> 291.51872 | Q21: =Q18-Q19 -> 277.05159 | S21: =S18-S19 -> 297.82364 | U21: =U18-U19 -> 314.21972 | W21: =W18-W19 -> #N/A | Y21: =Y18-Y19 -> #N/A
B23: Loss from discontinued operations, net of tax | C23: =INDEX(CW_IS!$B$77:$L$142,MATCH('WB FIN STATEMENT'!$B23,CW_IS!$B$77:$B$142,0),MATCH('WB FIN STATEMENT'!C$6,CW_IS!$B$5:$BJ$5,0)) -> -1.423 | E23: =INDEX(CW_IS!$B$77:$L$142,MATCH('WB FIN STATEMENT'!$B23,CW_IS!$B$77:$B$142,0),MATCH('WB FIN STATEMENT'!E$6,CW_IS!$B$5:$BJ$5,0)) -> 56.611 | G23: =INDEX(CW_IS!$B$77:$BJ$142,MATCH('WB FIN STATEMENT'!$B23,CW_IS!$B$77:$B$142,0),MATCH('WB FIN STATEMENT'!G$6,CW_IS!$B$5:$BJ$5,0)) -> 46.787 | I23: =INDEX(CW_IS!$B$77:$BJ$142,MATCH('WB FIN STATEMENT'!$B23,CW_IS!$B$77:$B$142,0),MATCH('WB FIN STATEMENT'!I$6,CW_IS!$B$5:$BJ$5,0)) -> 2.053 | K23: =INDEX(CW_IS!$B$77:$BJ$142,MATCH('WB FIN STATEMENT'!$B23,CW_IS!$B$77:$B$142,0),MATCH('WB FIN STATEMENT'!K$6,CW_IS!$B$5:$BJ$5,0)) -> 0 | M23: =INDEX(CW_IS!$B$77:$BJ$142,MATCH('WB FIN STATEMENT'!$B23,CW_IS!$B$77:$B$142,0),MATCH('WB FIN STATEMENT'!M$6,CW_IS!$B$5:$BJ$5,0)) -> 0 | O23: =INDEX(CW_IS!$B$77:$BJ$142,MATCH('WB FIN STATEMENT'!$B23,CW_IS!$B$77:$B$142,0),MATCH('WB FIN STATEMENT'!O$6,CW_IS!$B$5:$BJ$5,0)) -> 0 | Q23: =INDEX(CW_IS!$B$77:$BJ$142,MATCH('WB FIN STATEMENT'!$B23,CW_IS!$B$77:$B$142,0),MATCH('WB FIN STATEMENT'!Q$6,CW_IS!$B$5:$BJ$5,0)) -> 0 | S23: =INDEX(CW_IS!$B$77:$BJ$142,MATCH('WB FIN STATEMENT'!$B23,CW_IS!$B$77:$B$142,0),MATCH('WB FIN STATEMENT'!S$6,CW_IS!$B$5:$BJ$5,0)) -> 0 | U23: =INDEX(CW_IS!$B$77:$BJ$142,MATCH('WB FIN STATEMENT'!$B23,CW_IS!$B$77:$B$142,0),MATCH('WB FIN STATEMENT'!U$6,CW_IS!$B$5:$BJ$5,0)) -> 0 | W23: =INDEX(CW_IS!$B$77:$BJ$142,MATCH('WB FIN STATEMENT'!$B23,CW_IS!$B$77:$B$142,0),MATCH('WB FIN STATEMENT'!W$6,CW_IS!$B$5:$BJ$5,0)) -> #N/A | Y23: =INDEX(CW_IS!$B$77:$BJ$142,MATCH('WB FIN STATEMENT'!$B23,CW_IS!$B$77:$B$142,0),MATCH('WB FIN STATEMENT'!Y$6,CW_IS!$B$5:$BJ$5,0)) -> #N/A
B24: One-Time Adjustments | C24: =INDEX(CW_IS!$B$77:$L$142,MATCH('WB FIN STATEMENT'!$B24,CW_IS!$B$77:$B$142,0),MATCH('WB FIN STATEMENT'!C$6,CW_IS!$B$5:$BJ$5,0)) -> 0 | E24: =INDEX(CW_IS!$B$77:$L$142,MATCH('WB FIN STATEMENT'!$B24,CW_IS!$B$77:$B$142,0),MATCH('WB FIN STATEMENT'!E$6,CW_IS!$B$5:$BJ$5,0)) -> 0 | G24: =INDEX(CW_IS!$B$77:$BJ$142,MATCH('WB FIN STATEMENT'!$B24,CW_IS!$B$77:$B$142,0),MATCH('WB FIN STATEMENT'!G$6,CW_IS!$B$5:$BJ$5,0)) -> 0 | I24: =INDEX(CW_IS!$B$77:$BJ$142,MATCH('WB FIN STATEMENT'!$B24,CW_IS!$B$77:$B$142,0),MATCH('WB FIN STATEMENT'!I$6,CW_IS!$B$5:$BJ$5,0)) -> 0 | K24: =INDEX(CW_IS!$B$77:$BJ$142,MATCH('WB FIN STATEMENT'!$B24,CW_IS!$B$77:$B$142,0),MATCH('WB FIN STATEMENT'!K$6,CW_IS!$B$5:$BJ$5,0)) -> 7.2 | M24: =INDEX(CW_IS!$B$77:$BJ$142,MATCH('WB FIN STATEMENT'!$B24,CW_IS!$B$77:$B$142,0),MATCH('WB FIN STATEMENT'!M$6,CW_IS!$B$5:$BJ$5,0)) -> 6.75 | O24: =INDEX(CW_IS!$B$77:$BJ$142,MATCH('WB FIN STATEMENT'!$B24,CW_IS!$B$77:$B$142,0),MATCH('WB FIN STATEMENT'!O$6,CW_IS!$B$5:$BJ$5,0)) -> 5.1 | Q24: =INDEX(CW_IS!$B$77:$BJ$142,MATCH('WB FIN STATEMENT'!$B24,CW_IS!$B$77:$B$142,0),MATCH('WB FIN STATEMENT'!Q$6,CW_IS!$B$5:$BJ$5,0)) -> 77.7662 | S24: =INDEX(CW_IS!$B$77:$BJ$142,MATCH('WB FIN STATEMENT'!$B24,CW_IS!$B$77:$B$142,0),MATCH('WB FIN STATEMENT'!S$6,CW_IS!$B$5:$BJ$5,0)) -> 30.68104 | U24: =INDEX(CW_IS!$B$77:$BJ$142,MATCH('WB FIN STATEMENT'!$B24,CW_IS!$B$77:$B$142,0),MATCH('WB FIN STATEMENT'!U$6,CW_IS!$B$5:$BJ$5,0)) -> 20.1005 | W24: =INDEX(CW_IS!$B$77:$BJ$142,MATCH('WB FIN STATEMENT'!$B24,CW_IS!$B$77:$B$142,0),MATCH('WB FIN STATEMENT'!W$6,CW_IS!$B$5:$BJ$5,0)) -> #N/A | Y24: =INDEX(CW_IS!$B$77:$BJ$142,MATCH('WB FIN STATEMENT'!$B24,CW_IS!$B$77:$B$142,0),MATCH('WB FIN STATEMENT'!Y$6,CW_IS!$B$5:$BJ$5,0)) -> #N/A
B25: Loss from divestiture | C25: =INDEX(CW_IS!$B$77:$L$142,MATCH('WB FIN STATEMENT'!$B25,CW_IS!$B$77:$B$142,0),MATCH('WB FIN STATEMENT'!C$6,CW_IS!$B$5:$BJ$5,0)) -> 0 | E25: =INDEX(CW_IS!$B$77:$L$142,MATCH('WB FIN STATEMENT'!$B25,CW_IS!$B$77:$B$142,0),MATCH('WB FIN STATEMENT'!E$6,CW_IS!$B$5:$BJ$5,0)) -> 0 | G25: =INDEX(CW_IS!$B$77:$BJ$142,MATCH('WB FIN STATEMENT'!$B25,CW_IS!$B$77:$B$142,0),MATCH('WB FIN STATEMENT'!G$6,CW_IS!$B$5:$BJ$5,0)) -> 0 | I25: =INDEX(CW_IS!$B$77:$BJ$142,MATCH('WB FIN STATEMENT'!$B25,CW_IS!$B$77:$B$142,0),MATCH('WB FIN STATEMENT'!I$6,CW_IS!$B$5:$BJ$5,0)) -> 0 | K25: =INDEX(CW_IS!$B$77:$BJ$142,MATCH('WB FIN STATEMENT'!$B25,CW_IS!$B$77:$B$142,0),MATCH('WB FIN STATEMENT'!K$6,CW_IS!$B$5:$BJ$5,0)) -> 0 | M25: =INDEX(CW_IS!$B$77:$BJ$142,MATCH('WB FIN STATEMENT'!$B25,CW_IS!$B$77:$B$142,0),MATCH('WB FIN STATEMENT'!M$6,CW_IS!$B$5:$BJ$5,0)) -> 0 | O25: =INDEX(CW_IS!$B$77:$BJ$142,MATCH('WB FIN STATEMENT'!$B25,CW_IS!$B$77:$B$142,0),MATCH('WB FIN STATEMENT'!O$6,CW_IS!$B$5:$BJ$5,0)) -> 0 | Q25: =INDEX(CW_IS!$B$77:$BJ$142,MATCH('WB FIN STATEMENT'!$B25,CW_IS!$B$77:$B$142,0),MATCH('WB FIN STATEMENT'!Q$6,CW_IS!$B$5:$BJ$5,0)) -> 0 | S25: =INDEX(CW_IS!$B$77:$BJ$142,MATCH('WB FIN STATEMENT'!$B25,CW_IS!$B$77:$B$142,0),MATCH('WB FIN STATEMENT'!S$6,CW_IS!$B$5:$BJ$5,0)) -> 0 | U25: =INDEX(CW_IS!$B$77:$BJ$142,MATCH('WB FIN STATEMENT'!$B25,CW_IS!$B$77:$B$142,0),MATCH('WB FIN STATEMENT'!U$6,CW_IS!$B$5:$BJ$5,0)) -> 0 | W25: =INDEX(CW_IS!$B$77:$BJ$142,MATCH('WB FIN STATEMENT'!$B25,CW_IS!$B$77:$B$142,0),MATCH('WB FIN STATEMENT'!W$6,CW_IS!$B$5:$BJ$5,0)) -> #N/A | Y25: =INDEX(CW_IS!$B$77:$BJ$142,MATCH('WB FIN STATEMENT'!$B25,CW_IS!$B$77:$B$142,0),MATCH('WB FIN STATEMENT'!Y$6,CW_IS!$B$5:$BJ$5,0)) -> #N/A
B27: Net Income - GAAP | C27: =C21-C23-C24-C25 -> 140.804 | E27: =E21-E23-E24-E25 -> 113.338 | G27: =G21-G23-G24-G25 -> 145.461 | I27: =I21-I23-I24-I25 -> 187.329 | K27: =K21-K23-K24-K25 -> 214.927 | M27: =M21-M23-M24-M25 -> 275.598 | O27: =O21-O23-O24-O25 -> 286.41872 | Q27: =Q21-Q23-Q24-Q25 -> 199.28539 | S27: =S21-S23-S24-S25 -> 267.1426 | U27: =U21-U23-U24-U25 -> 294.11922 | W27: =W21-W23-W24-W25 -> #N/A | Y27: =Y21-Y23-Y24-Y25 -> #N/A
B29: Reported EPS (Consolidated) | C29: =C27/C33 -> 2.912182 | E29: =E27/E33 -> 2.3094855 | G29: =G27/G33 -> 3.0548765 | I29: =I27/I33 -> 4.158708 | K29: =K27/K33 -> 4.8016577 | M29: =M27/M33 -> 6.2169637 | O29: =O27/O33 -> 6.6584616 | Q29: =Q27/Q33 -> 4.7482254 | S29: =S27/S33 -> 6.579867 | U29: =U27/U33 -> 7.6097132 | W29: =W27/W33 -> #N/A | Y29: =Y27/Y33 -> #N/A
B31: Adjusted EPS (Continuing Operations) | C31: =C21/C33 -> 2.8827508 | E31: =E21/E33 -> 3.4630464 | G31: =G21/G33 -> 4.0374664 | I31: =I21/I33 -> 4.2042846 | K31: =K21/K33 -> 4.962512 | M31: =M21/M33 -> 6.3692308 | O31: =O21/O33 -> 6.7770228 | Q31: =Q21/Q33 -> 6.601103 | S31: =S21/S33 -> 7.3355576 | U31: =U21/U33 -> 8.1297712 | W31: =W21/W33 -> #N/A | Y31: =Y21/Y33 -> #N/A
B33: Diluted Shares Out (Mil) | C33: =INDEX(CW_IS!$B$77:$L$142,MATCH('WB FIN STATEMENT'!$B33,CW_IS!$B$77:$B$142,0),MATCH('WB FIN STATEMENT'!C$6,CW_IS!$B$5:$BJ$5,0)) -> 48.35 | E33: =INDEX(CW_IS!$B$77:$L$142,MATCH('WB FIN STATEMENT'!$B33,CW_IS!$B$77:$B$142,0),MATCH('WB FIN STATEMENT'!E$6,CW_IS!$B$5:$BJ$5,0)) -> 49.075 | G33: =INDEX(CW_IS!$B$77:$BJ$142,MATCH('WB FIN STATEMENT'!$B33,CW_IS!$B$77:$B$142,0),MATCH('WB FIN STATEMENT'!G$6,CW_IS!$B$5:$BJ$5,0)) -> 47.616 | I33: =INDEX(CW_IS!$B$77:$BJ$142,MATCH('WB FIN STATEMENT'!$B33,CW_IS!$B$77:$B$142,0),MATCH('WB FIN STATEMENT'!I$6,CW_IS!$B$5:$BJ$5,0)) -> 45.045 | K33: =INDEX(CW_IS!$B$77:$BJ$142,MATCH('WB FIN STATEMENT'!$B33,CW_IS!$B$77:$B$142,0),MATCH('WB FIN STATEMENT'!K$6,CW_IS!$B$5:$BJ$5,0)) -> 44.761 | M33: =INDEX(CW_IS!$B$77:$BJ$142,MATCH('WB FIN STATEMENT'!$B33,CW_IS!$B$77:$B$142,0),MATCH('WB FIN STATEMENT'!M$6,CW_IS!$B$5:$BJ$5,0)) -> 44.33 | O33: =INDEX(CW_IS!$B$77:$BJ$142,MATCH('WB FIN STATEMENT'!$B33,CW_IS!$B$77:$B$142,0),MATCH('WB FIN STATEMENT'!O$6,CW_IS!$B$5:$BJ$5,0)) -> 43.01575 | Q33: =INDEX(CW_IS!$B$77:$BJ$142,MATCH('WB FIN STATEMENT'!$B33,CW_IS!$B$77:$B$142,0),MATCH('WB FIN STATEMENT'!Q$6,CW_IS!$B$5:$BJ$5,0)) -> 41.9705 | S33: =INDEX(CW_IS!$B$77:$BJ$142,MATCH('WB FIN STATEMENT'!$B33,CW_IS!$B$77:$B$142,0),MATCH('WB FIN STATEMENT'!S$6,CW_IS!$B$5:$BJ$5,0)) -> 40.6 | U33: =INDEX(CW_IS!$B$77:$BJ$142,MATCH('WB FIN STATEMENT'!$B33,CW_IS!$B$77:$B$142,0),MATCH('WB FIN STATEMENT'!U$6,CW_IS!$B$5:$BJ$5,0)) -> 38.6505 | W33: =INDEX(CW_IS!$B$77:$BJ$142,MATCH('WB FIN STATEMENT'!$B33,CW_IS!$B$77:$B$142,0),MATCH('WB FIN STATEMENT'!W$6,CW_IS!$B$5:$BJ$5,0)) -> #N/A | Y33: =INDEX(CW_IS!$B$77:$BJ$142,MATCH('WB FIN STATEMENT'!$B33,CW_IS!$B$77:$B$142,0),MATCH('WB FIN STATEMENT'!Y$6,CW_IS!$B$5:$BJ$5,0)) -> #N/A
B35: Quarterly EPS - Adjusted
B36: Q1 | C36: =CW_IS!C135 -> 0 | E36: =CW_IS!H135 -> 0.74195519 | G36: =CW_IS!M135 -> 0.88695313 | I36: =CW_IS!R135 -> 0.72544209 | K36: =CW_IS!W135 -> 0.8093123 | M36: =CW_IS!AB135 -> 0.97683424 | O36: =CW_IS!AG135 -> 1.2266042 | Q36: =+CW_IS!AL135 -> 1.288484 | S36: =CW_IS!AQ135 -> 1.5148286 | U36: =CW_IS!AV135 -> 1.3121703 | W36: =+CW_IS!BA135 -> 1.53 | X36: E
B37: Q2 | C37: =CW_IS!D135 -> 0 | E37: =CW_IS!I135 -> 0.87347428 | G37: =CW_IS!N135 -> 0.83138547 | I37: =CW_IS!S135 -> 0.88484191 | K37: =CW_IS!X135 -> 1.2098054 | M37: =CW_IS!AC135 -> 1.7998115 | O37: =CW_IS!AH135 -> 1.7761576 | Q37: =+CW_IS!AM135 -> 1.2811643 | S37: =CW_IS!AR135 -> 1.5567806 | U37: =CW_IS!AW135 -> 1.8334972 | W37: =+CW_IS!BB135 -> 2.15 | X37: E
B38: Q3 | C38: =CW_IS!E135 -> 0.79185031 | E38: =CW_IS!J135 -> 0.90381051 | G38: =CW_IS!O135 -> 0.80476844 | I38: =CW_IS!T135 -> 1.0207792 | K38: =CW_IS!Y135 -> 1.428406 | M38: =CW_IS!AD135 -> 1.7003429 | O38: =CW_IS!AI135 -> 1.8114665 | Q38: =+CW_IS!AN135 -> 1.7717925 | S38: =CW_IS!AS135 -> 1.8762882 | U38: =CW_IS!AX135 -> 2.0693197 | W38: =+CW_IS!BC135 -> 2.5445044 | X38: E
B39: Q4 | C39: =CW_IS!F135 -> 0.91860082 | E39: =CW_IS!K135 -> 0.94329823 | G39: =CW_IS!P135 -> 1.533537 | I39: =CW_IS!U135 -> 1.5780095 | K39: =CW_IS!Z135 -> 1.5166864 | M39: =CW_IS!AE135 -> 1.8988397 | O39: =CW_IS!AJ135 -> 1.963481 | Q39: =+CW_IS!AO135 -> 2.2736225 | S39: =CW_IS!AT135 -> 2.3975468 | U39: =CW_IS!AY135 -> 2.9155313 | W39: =+CW_IS!BD135 -> 3.1635437 | X39: E
B41: CASH FLOW | C41: =C6 -> FY13 | E41: =E6 -> FY14 | G41: =G6 -> FY15 | I41: FY16 | K41: FY17 | M41: =M6 -> FY18 | O41: =O6 -> FY19 | Q41: =Q6 -> FY20 | S41: =S6 -> FY21 | U41: =U6 -> FY22 | W41: =W6 -> FY23E | Y41: =Y6 -> FY24E
B43: Sources
B44: Net Income | C44: 137.981 | E44: 113.338 | G44: 145.461 | I44: 187.329 | K44: 214.891 | M44: 275.749 | O44: 307.583 | Q44: 201.392 | S44: 267.159 | U44: 294.348 | W44: =W27 -> #N/A | Y44: =Y27 -> #N/A
B45: Depr. & Amort. | C45: 121.497 | E45: 118.931 | G45: 100.81 | I45: 96.008 | K45: 99.995 | M45: 102.949 | O45: 102.412 | Q45: 115.903 | S45: 114.384 | U45: 112.027 | W45: 112.5 | Y45: 115
B46: Stock Based Compensation | C46: 7.349 | E46: 8.5 | G46: 9.473 | I46: 9.478 | K46: 11.572 | M46: 14.094 | O46: 13.669 | Q46: 14.437 | S46: 13.45 | U46: 15.384 | W46: 15 | Y46: 15
B47: Loss on disposals | C47: 0.077 | E47: =29.184+0.632 -> 29.816 | G47: =16.991-0.945 -> 16.046 | I47: =-0.845-2.069 -> -2.914 | K47: =-0.875+0.029 -> -0.846 | M47: =-1.735-1.12 -> -2.855 | O47: =0-11.054 -> -11.054 | Q47: 0 | S47: -0.568 | U47: =-4.671+4.651 -> -0.02 | W47: 0 | Y47: 0
B48: Deferred income taxes | C48: 5.928 | E48: -27.241 | G48: 63.535 | I48: 1.224 | K48: -5.782 | M48: 8.562 | O48: 40.787 | Q48: -7.048 | S48: -10.2 | U48: -23.635 | W48: -10 | Y48: -10
B49: Other (net) | C49: 0.887 | E49: =41.369+3.202 -> 44.571 | G49: 40.813 | I49: 0 | K49: 0 | M49: 0 | O49: 0 | Q49: =33.043+9.351+15.628 -> 58.022 | S49: 19.088 | U49: 0 | W49: 0 | Y49: 0
B50: Change in Non Cash Working Capital | C50: =6.599-25.499-6.131+8.567-7.281-16.811-1.63+6.294 -> -35.892 | E50: =12.845-19.375-6.971+16.147+24.471+38.946-26.431+4.219 -> 43.851 | G50: =-77.106-4.039+3.68-0.447+4.839-7.436-139.61+6.46 -> -213.659 | I50: =91.692+4.391+2.583+4.125-11.084+11.797+3.405+20.405+4.758 -> 132.072 | K50: =-16.388+19.711-0.774+4.323+36.898-5.479+3.481+25.686+1.424 -> 68.882 | M50: =-57.492-41.197-11.121+48.93+23.082-8.847-43.759+23.357+4.821 -> -62.226 | O50: =-12.613-3.485-4.834-18.629+36.134-15.625-1.31-11.631 -> -31.993 | Q50: =71.147+15.535-7.689-55.513-33.179+15.171-153.375+26.377 -> -121.526 | S50: =-59.372+15.321-3.672+17.713+9.584-12.988-1.236+19.005 -> -15.645 | U50: =-74.798-60.62-3.099+42.493-17.646+55.847-15.049-30.456 -> -103.328 | W50: =+(W12-U12)*-0.14+20 -> #N/A | Y50: =+(Y12-W12)*-0.1 -> #N/A
B51: From Operations | C51: =SUM(C44:D50) -> 237.827 | E51: =SUM(E44:F50) -> 331.766 | G51: =SUM(G44:H50) -> 162.479 | I51: =SUM(I44:J50) -> 423.197 | K51: =SUM(K44:L50) -> 388.712 | M51: =SUM(M44:N50) -> 336.273 | O51: =SUM(O44:P50) -> 421.404 | Q51: =SUM(Q44:R50) -> 261.18 | S51: =SUM(S44:T50) -> 387.668 | U51: =SUM(U44:V50) -> 294.776 | W51: =SUM(W44:X50) -> #N/A | Y51: =SUM(Y44:Z50) -> #N/A
B53: Proceeds from sale of short-term investments | C53: 0 | E53: 2.357 | G53: 0 | I53: 0 | K53: 0 | M53: 0 | O53: 0 | Q53: 0 | S53: 0 | U53: -10 | W53: 0 | Y53: 0
B54: Dispositions | C54: 1.348 | E54: =0.594+152.965 -> 153.559 | G54: =2.277+31.344 -> 33.621 | I54: =3.674+1.027 -> 4.701 | K54: =6.769+6.973 -> 13.742 | M54: =9.117+0.958 -> 10.075 | O54: 15.093 | Q54: 2.93 | S54: 4.045 | U54: 9.841 | W54: 0 | Y54: 0
B55: Net Debt | C55: =500+983.109-1229.148-125.033 -> 128.928 | E55: =364.557-414.77-0.08 -> -50.293 | G55: =70.324-70.134-8.4 -> -8.21 | I55: =7.839-8.43 -> -0.591 | K55: =7.658-8.176-150 -> -150.518 | M55: =372.98-372.887-50 -> -49.907 | O55: =37.692-37.934 -> -0.242 | Q55: =570.675-570.675+300 -> 300 | S55: =455.95-362.05-100 -> -6.1 | U55: =1697.647-1791.547+300 -> 206.1 | W55: =-202.5+150 -> -52.5 | Y55: 0
B56: Effect of Exch. Rate | C56: -1.002 | E56: -17.954 | G56: -19.104 | I56: -18.971 | K56: 18.786 | M56: -16.172 | O56: 1.748 | Q56: -3.516 | S56: -3.38 | U56: -12.367 | W56: 2 | Y56: 2
B57: Other | C57: 0 | E57: 0 | G57: 0 | I57: =22.3+11.101 -> 33.401 | K57: 14.179 | M57: =11.94-1.547 -> 10.393 | O57: -0.172 | Q57: -0.017 | S57: 0 | U57: 0 | W57: 10 | Y57: 10
B58: Total Sources | C58: =SUM(C51:D57) -> 367.101 | E58: =SUM(E51:F57) -> 419.435 | G58: =SUM(G51:H57) -> 168.786 | I58: =SUM(I51:J57) -> 441.737 | K58: =SUM(K51:L57) -> 284.901 | M58: =SUM(M51:N57) -> 290.662 | O58: =SUM(O51:P57) -> 437.831 | Q58: =SUM(Q51:R57) -> 560.577 | S58: =SUM(S51:T57) -> 382.233 | U58: =SUM(U51:V57) -> 488.35 | W58: =SUM(W51:X57) -> #N/A | Y58: =SUM(Y51:Z57) -> #N/A
B60: Uses:
B61: Net Capital Spending | C61: 72.242 | E61: 67.115 | G61: 35.512 | I61: 46.776 | K61: 52.705 | M61: 53.417 | O61: =69.752 -> 69.752 | Q61: 47.499 | S61: 41.108 | U61: 38.217 | W61: 55 | Y61: 55
B62: Purchase of short-term investments | I62: 0 | K62: 0 | M62: 0 | O62: 0 | Q62: 0 | S62: 0 | U62: 0 | W62: 0 | Y62: 0
B63: Dividends | C63: 18.377 | E63: 25.013 | G63: 24.122 | I63: 23.067 | K63: 24.74 | M63: 26.328 | O63: 28.2 | Q63: 28.175 | S63: 28.66 | U63: 28.779 | W63: =+U63*1.1 -> 31.6569 | Y63: =+W63*1.1 -> 34.82259
B64: Acquisitions Net | C64: =236.135+6.663 -> 242.798 | E64: =34.364+0.989 -> 35.353 | G64: =13.228+0.457 -> 13.685 | I64: =0.295+0.564 -> 0.859 | K64: =232.63+0.735 -> 233.365 | M64: =210.167+0.46 -> 210.627 | O64: 185.209 | Q64: 487.944 | S64: 5.34 | U64: =282.429+5.062 -> 287.491 | W64: 0 | Y64: 0
B65: Net Equity | C65: 0 | E65: 65.22 | G65: 294.13 | I65: 105.249 | K65: 52.127 | M65: 198.592 | O65: 50.661 | Q65: 200.018 | S65: =343.129-9.705 -> 333.424 | U65: =56.87-9.997 -> 46.873 | W65: 150 | Y65: 100
B66: Other (net) | C66: -27.45 | E66: -38.182 | G66: -28.706 | I66: 0.635 | K66: 0.692 | M66: 0.752 | O66: =-11.77 -> -11.77 | Q66: -11.148 | S66: 0 | U66: 0 | W66: 0 | Y66: 0
B67: Other (net) - Discontinued ops | C67: -2.137 | E67: =-0.296-9.61 -> -9.906 | G67: =0.581-9.119 -> -8.538 | I67: 0 | K67: 0 | M67: 0 | O67: 0.812 | Q67: 0.874 | S67: 0.945 | U67: 1.02 | W67: 0 | Y67: 0
B68: Total Uses | C68: =SUM(C61:D67) -> 303.83 | E68: =SUM(E61:F67) -> 144.613 | G68: =SUM(G61:H67) -> 330.205 | I68: =SUM(I61:J67) -> 176.586 | K68: =SUM(K61:L67) -> 363.629 | M68: =SUM(M61:N67) -> 489.716 | O68: =SUM(O61:P67) -> 322.864 | Q68: =SUM(Q61:R67) -> 753.362 | S68: =SUM(S61:T67) -> 409.477 | U68: =SUM(U61:V67) -> 402.38 | W68: =SUM(W61:X67) -> 236.6569 | Y68: =SUM(Y61:Z67) -> 189.82259
B70: Change in Cash | C70: =C58-C68 -> 63.271 | E70: =E58-E68 -> 274.822 | G70: =G58-G68 -> -161.419 | I70: =I58-I68 -> 265.151 | K70: =K58-K68 -> -78.728 | M70: =M58-M68 -> -199.054 | O70: =O58-O68 -> 114.967 | Q70: =Q58-Q68 -> -192.785 | S70: =S58-S68 -> -27.244 | U70: =U58-U68 -> 85.97 | W70: =W58-W68 -> #N/A | Y70: =Y58-Y68 -> #N/A
B74: CAPITALIZATION | C74: =C41 -> FY13 | E74: =E41 -> FY14 | G74: =G41 -> FY15 | I74: =I41 -> FY16 | K74: =K41 -> FY17 | M74: =M41 -> FY18 | O74: =O41 -> FY19 | Q74: =Q41 -> FY20 | S74: =S41 -> FY21 | U74: =U41 -> FY22 | W74: =W41 -> FY23E | Y74: =Y41 -> FY24E
B76: Short-Term Debt | C76: 1.334 | E76: 1.069 | G76: 1.259 | I76: 150.668 | K76: 0.15 | M76: 0.243 | O76: 0 | Q76: 100 | S76: 0 | U76: 202.5 | W76: 0 | Y76: 0
B77: Long-Term Debt | C77: 958.604 | E77: 953.279 | G77: 953.083 | I77: 815.63 | K77: 813.989 | M77: 762.313 | O77: 760.639 | Q77: 958.292 | S77: 1050.61 | U77: 1051.9 | W77: =+S77+W55 -> 998.11 | Y77: =+U77+Y55 -> 1051.9
B78: Shareholders' Equity | C78: 1552.705 | E78: 1478.433 | G78: 1225.423 | I78: 1291.191 | K78: 1527.8 | M78: 1530.781 | O78: 1774.372 | Q78: 1787.574 | S78: 1826.49 | U78: 1992.119 | W78: =S78+W44-W63-W65 -> #N/A | Y78: =U78+Y44-Y63-Y65 -> #N/A
B79: Total Capitalization | C79: =C76+C77+C78 -> 2512.643 | E79: =E76+E77+E78 -> 2432.781 | G79: =G76+G77+G78 -> 2179.765 | I79: =I76+I77+I78 -> 2257.489 | K79: =K76+K77+K78 -> 2341.939 | M79: =M76+M77+M78 -> 2293.337 | O79: =O76+O77+O78 -> 2535.011 | Q79: =Q76+Q77+Q78 -> 2845.866 | S79: =S76+S77+S78 -> 2877.1 | U79: =U76+U77+U78 -> 3246.519 | W79: =W76+W77+W78 -> #N/A | Y79: =Y76+Y77+Y78 -> #N/A
B81: Cash & Equivalents | C81: 175.294 | E81: 450.116 | G81: 288.697 | I81: 553.848 | K81: 475.12 | M81: =K81+M70 -> 276.066 | O81: =M81+O70 -> 391.033 | Q81: 198.248 | S81: 171.004 | U81: 256.974 | W81: =S81+W70 -> #N/A | Y81: =U81+Y70 -> #N/A
B82: 1 Yr Cash Return to Shareholders | C82: =(C63+C65)/C44 -> 0.133185 | E82: =(E63+E65)/E44 -> 0.79614075 | G82: =(G63+G65)/G44 -> 2.1878854 | I82: =(I63+I65)/I44 -> 0.6849767 | K82: =(K63+K65)/K44 -> 0.35770228 | M82: =(M63+M65)/M44 -> 0.81566932 | O82: =(O63+O65)/O44 -> 0.25638933 | Q82: =(Q63+Q65)/Q44 -> 1.1330788 | S82: =(S63+S65)/S44 -> 1.3553128 | U82: =(U63+U65)/U44 -> 0.25701551 | W82: =(W63+W65)/W44 -> #N/A | Y82: =(Y63+Y65)/Y44 -> #N/A
B83: 3 Yr Avg. Cash Return to Shareholders | C83: - | E83: - | G83: =(G82+E82+C82)/3 -> 1.0390704 | I83: =(I82+G82+E82)/3 -> 1.223001 | K83: =(K82+I82+G82)/3 -> 1.0768548 | M83: =(M82+K82+I82)/3 -> 0.61944943 | O83: =(O82+M82+K82)/3 -> 0.47658698 | Q83: =(Q82+O82+M82)/3 -> 0.73504581 | S83: =(S82+Q82+O82)/3 -> 0.91492695 | U83: =(U82+S82+Q82)/3 -> 0.91513568 | W83: =(W82+S82+Q82)/3 -> #N/A | Y83: =(Y82+U82+S82)/3 -> #N/A
B84: 1 Yr Internal Growth Efficiency | C84: =#REF!/#REF! -> #REF! | E84: =#REF!/#REF! -> #REF! | G84: =#REF!/#REF! -> #REF! | I84: =#REF!/#REF! -> #REF! | K84: =#REF!/#REF! -> #REF! | M84: =#REF!/#REF! -> #REF! | O84: =#REF!/#REF! -> #REF! | Q84: =#REF!/#REF! -> #REF! | S84: =#REF!/#REF! -> #REF! | U84: =#REF!/#REF! -> #REF! | W84: =#REF!/#REF! -> #REF! | Y84: =#REF!/#REF! -> #REF!
B85: Internal Growth Efficiency (IGE) | C85: =AVERAGE(C84:D84) -> #REF! | E85: =AVERAGE(C84:F84) -> #REF! | G85: =AVERAGE(E84:H84) -> #REF! | I85: =AVERAGE(G84:J84) -> #REF! | K85: =AVERAGE(I84:L84) -> #REF! | M85: =AVERAGE(K84:N84) -> #REF! | O85: =AVERAGE(M84:P84) -> #REF! | Q85: =AVERAGE(O84:R84) -> #REF! | S85: =AVERAGE(Q84:T84) -> #REF! | U85: =AVERAGE(S84:V84) -> #REF! | W85: =AVERAGE(S84:X84) -> #REF! | Y85: =AVERAGE(U84:Z84) -> #REF!
B87: Debt/Total Capital | C87: =(C77+C76)/(C79) -> 0.38204313 | E87: =(E77+E76)/(E79) -> 0.39228685 | G87: =(G77+G76)/(G79) -> 0.43781876 | I87: =(I77+I76)/(I79) -> 0.42804107 | K87: =(K77+K76)/(K79) -> 0.34763459 | M87: =(M77+M76)/(M79) -> 0.33250935 | O87: =(O77+O76)/(O79) -> 0.30005353 | Q87: =(Q77+Q76)/(Q79) -> 0.37186993 | S87: =(S77+S76)/(S79) -> 0.36516284 | U87: =(U77+U76)/(U79) -> 0.38638308 | W87: =(W77+W76)/(W79) -> #N/A | Y87: =(Y77+Y76)/(Y79) -> #N/A
B88: Net Total Capital | C88: =C79-C81 -> 2337.349 | E88: =E79-E81 -> 1982.665 | G88: =G79-G81 -> 1891.068 | I88: =I79-I81 -> 1703.641 | K88: =K79-K81 -> 1866.819 | M88: =M79-M81 -> 2017.271 | O88: =O79-O81 -> 2143.978 | Q88: =Q79-Q81 -> 2647.618 | S88: =S79-S81 -> 2706.096 | U88: =U79-U81 -> 2989.545 | W88: =W79-W81 -> #N/A | Y88: =Y79-Y81 -> #N/A
B89: Net Debt | C89: =C76+C77-C81 -> 784.644 | E89: =E76+E77-E81 -> 504.232 | G89: =G76+G77-G81 -> 665.645 | I89: =I76+I77-I81 -> 412.45 | K89: =K76+K77-K81 -> 339.019 | M89: =M76+M77-M81 -> 486.49 | O89: =O76+O77-O81 -> 369.606 | Q89: =Q76+Q77-Q81 -> 860.044 | S89: =S76+S77-S81 -> 879.606 | U89: =U76+U77-U81 -> 997.426 | W89: =W76+W77-W81 -> #N/A | Y89: =Y76+Y77-Y81 -> #N/A
B90: Net Debt/ EBITDA | C90: =(C77+C76-C81)/(D12+C45) -> #N/A | E90: =(E77+E76-E81)/(F12+E45) -> #N/A | G90: =(G77+G76-G81)/(H12+G45) -> #N/A | I90: =(I77+I76-I81)/(J12+I45) -> #N/A | K90: =(K77+K76-K81)/(L12+K45) -> #N/A | M90: =(M77+M76-M81)/(N12+M45) -> #N/A | O90: =(O77+O76-O81)/(P12+O45) -> #N/A | Q90: =(Q77+Q76-Q81)/(R12+Q45) -> #N/A | S90: =(S77+S76-S81)/(T12+S45) -> #N/A | U90: =(U77+U76-U81)/(V12+U45) -> #N/A | W90: =(W77+W76-W81)/(X12+W45) -> #N/A | Y90: =(Y77+Y76-Y81)/(Z12+Y45) -> #N/A
B91: Net Debt/Total Cap. | C91: =(C77+C76-C81)/(C79) -> 0.31227835 | E91: =(E77+E76-E81)/(E79) -> 0.20726568 | G91: =(G77+G76-G81)/(G79) -> 0.30537466 | I91: =(I77+I76-I81)/(I79) -> 0.18270299 | K91: =(K77+K76-K81)/(K79) -> 0.14475996 | M91: =(M77+M76-M81)/(M79) -> 0.21213193 | O91: =(O77+O76-O81)/(O79) -> 0.14580055 | Q91: =(Q77+Q76-Q81)/(Q79) -> 0.30220819 | S91: =(S77+S76-S81)/(S79) -> 0.3057266 | U91: =(U77+U76-U81)/(U79) -> 0.30722937 | W91: =(W77+W76-W81)/(W79) -> #N/A | Y91: =(Y77+Y76-Y81)/(Y79) -> #N/A
B93: Average ROE | C93: - | E93: =E44/((E78+C78)/2) -> 0.074782474 | G93: =G44/((G78+E78)/2) -> 0.10759523 | I93: =I44/((I78+G78)/2) -> 0.14887384 | K93: =K44/((K78+I78)/2) -> 0.15245951 | M93: =M44/((M78+K78)/2) -> 0.18031172 | O93: =O44/((O78+M78)/2) -> 0.18612331 | Q93: =Q44/((Q78+O78)/2) -> 0.11307976 | S93: =S44/((S78+Q78)/2) -> 0.14784409 | U93: =U44/((U78+S78)/2) -> 0.15416504 | W93: =W44/((W78+S78)/2) -> #N/A | Y93: =Y44/((Y78+U78)/2) -> #N/A
B94: Average ROTC | C94: - | E94: =E44/((E79+C79)/2) -> 0.045835504 | G94: =G44/((G79+E79)/2) -> 0.063071891 | I94: =I44/((I79+G79)/2) -> 0.084434653 | K94: =K44/((K79+I79)/2) -> 0.093442489 | M94: =M44/((M79+K79)/2) -> 0.11897846 | O94: =O44/((O79+M79)/2) -> 0.12740714 | Q94: =Q44/((Q79+O79)/2) -> 0.074854712 | S94: =S44/((S79+Q79)/2) -> 0.093363826 | U94: =U44/((U79+S79)/2) -> 0.096135308 | W94: =W44/((W79+S79)/2) -> #N/A | Y94: =Y44/((Y79+U79)/2) -> #N/A
B95: Average Net Total Capital | C95: - | E95: =(E88+C88)/2 -> 2160.007 | G95: =(G88+E88)/2 -> 1936.8665 | I95: =(I88+G88)/2 -> 1797.3545 | K95: =(K88+I88)/2 -> 1785.23 | M95: =(M88+K88)/2 -> 1942.045 | O95: =(O88+M88)/2 -> 2080.6245 | Q95: =(Q88+O88)/2 -> 2395.798 | S95: =(S88+Q88)/2 -> 2676.857 | U95: =(U88+S88)/2 -> 2847.8205 | W95: =(W88+S88)/2 -> #N/A | Y95: =(Y88+U88)/2 -> #N/A
B96: Average Net ROTC | C96: - | E96: =E44/E95 -> 0.052471126 | G96: =G44/G95 -> 0.075101201 | I96: =I44/I95 -> 0.10422485 | K96: =K44/K95 -> 0.1203716 | M96: =M44/M95 -> 0.14198899 | O96: =O44/O95 -> 0.14783206 | Q96: =Q44/Q95 -> 0.084060509 | S96: =S44/S95 -> 0.099803239 | U96: =U44/U95 -> 0.10335904 | W96: =W44/W95 -> #N/A | Y96: =Y44/Y95 -> #N/A
B98: Other | C98: =C74 -> FY13 | E98: =E74 -> FY14 | G98: =G74 -> FY15 | I98: =I74 -> FY16 | K98: =K74 -> FY17 | M98: =M74 -> FY18 | O98: =O74 -> FY19 | Q98: =Q74 -> FY20 | S98: =S74 -> FY21 | U98: =U74 -> FY22 | W98: =W74 -> FY23E | Y98: =Y74 -> FY24E
B100: Cash Flow From Operations | C100: =C51 -> 237.827 | E100: =E51 -> 331.766 | G100: =G51 -> 162.479 | I100: =I51 -> 423.197 | K100: =K51 -> 388.712 | M100: =M51 -> 336.273 | O100: =O51 -> 421.404 | Q100: =Q51 -> 261.18 | S100: =S51 -> 387.668 | U100: =U51 -> 294.776 | W100: =W51 -> #N/A | Y100: =Y51 -> #N/A
B101: Capex | C101: =C61 -> 72.242 | E101: =E61 -> 67.115 | G101: =G61 -> 35.512 | I101: =I61 -> 46.776 | K101: =K61 -> 52.705 | M101: =M61 -> 53.417 | O101: =O61-19.284 -> 50.468 | Q101: =Q61 -> 47.499 | S101: =S61 -> 41.108 | U101: =U61 -> 38.217 | W101: =W61 -> 55 | Y101: =Y61 -> 55
B102: Dividends | C102: =C63 -> 18.377 | E102: =E63 -> 25.013 | G102: =G63 -> 24.122 | I102: =I63 -> 23.067 | K102: =K63 -> 24.74 | M102: =M63 -> 26.328 | O102: =O63 -> 28.2 | Q102: =Q63 -> 28.175 | S102: =S63 -> 28.66 | U102: =U63 -> 28.779 | W102: =W63 -> 31.6569 | Y102: =Y63 -> 34.82259
B103: Free Cash Flow | C103: =C100-C101 -> 165.585 | E103: =E100-E101 -> 264.651 | G103: =G100-G101 -> 126.967 | I103: =I100-I101 -> 376.421 | K103: =K100-K101 -> 336.007 | M103: =M100-M101 -> 282.856 | O103: =O100-O101 -> 370.936 | Q103: =Q100-Q101 -> 213.681 | S103: =S100-S101 -> 346.56 | U103: =U100-U101 -> 256.559 | W103: =W100-W101 -> #N/A | Y103: =Y100-Y101 -> #N/A
B104: FCF/Share | C104: =C103/C33 -> 3.4247156 | E104: =E103/E33 -> 5.3927866 | G104: =G103/G33 -> 2.6664777 | I104: =I103/I33 -> 8.3565546 | K104: =K103/K33 -> 7.5066911 | M104: =M103/M33 -> 6.3806903 | O104: =O103/O33 -> 8.6232601 | Q104: =Q103/Q33 -> 5.0912188 | S104: =S103/S33 -> 8.5359606 | U104: =U103/U33 -> 6.6379219 | W104: =W103/W33 -> #N/A | Y104: =Y103/Y33 -> #N/A
B105: Adj. FCF % of Adj. Net Income | C105: =(C103)/C21 -> 1.1880027 | E105: =(E103)/E21 -> 1.5572378 | G105: =(G103)/G21 -> 0.6604334 | I105: =(I103)/I21 -> 1.9876282 | K105: =(K103)/K21 -> 1.5126797 | M105: =(M103)/M21 -> 1.0017992 | O105: =(O103)/O21 -> 1.272426 | Q105: =(Q103)/Q21 -> 0.7712679 | S105: =(S103)/S21 -> 1.1636417 | U105: =(U103)/U21 -> 0.81649554 | W105: =(W103)/W21 -> #N/A | Y105: =(Y103)/Y21 -> #N/A
B106: EBITDA | C106: =C14+C45 -> 358.597 | E106: =E14+E45 -> 401.304 | G106: =G14+G45 -> 411.427 | I106: =I14+I45 -> 404.106 | K106: =K14+K45 -> 434.586 | M106: =M14+M45 -> 485.224 | O106: =O14+O45 -> 491.80072 | Q106: =Q14+Q45 -> 491.39719 | S106: =S14+S45 -> 534.765 | U106: =U14+U45 -> 555.105 | W106: =W14+W45 -> #N/A | Y106: =Y14+Y45 -> #N/A
B107: Working Cap
B108: Working Cap/Sales
B109: Shares Outstanding | C109: =C33 -> 48.35 | E109: =E33 -> 49.075 | G109: =G33 -> 47.616 | I109: =I33 -> 45.045 | K109: =K33 -> 44.761 | M109: =M33 -> 44.33 | O109: =O33 -> 43.01575 | Q109: =Q33 -> 41.9705 | S109: =S33 -> 40.6 | U109: =U33 -> 38.6505 | W109: =W33 -> #N/A | Y109: =Y33 -> #N/A
B111: Sources: Curtiss-Wright Corporation reports and William Blair Equity Research

Sheet Comps
A5: Curtiss-Wright Valuation Comp Table
A6: Stock Data | N6: Valuation | Z6: Leverage | AC6: Growth | AJ6: Margin | AM6: Yield
H7: Shares
F8: Price | H8: Out | I8: Mkt Cap | J8: Debt+Pr | K8: Cash | L8: EV | N8: EV/Sales | Q8: EV/EBITDA | T8: P/E | W8: EV/FCF | Z8: Net Debt/EBITDA | AC8: Sales Growth | AF8: EBITDA Growth | AI8: EBITDA Margin | AM8: Dividend | AO8: Revenue | AS8: EBITDA | AW8: EPS | BA8: FCF
B9: Company Name | C9: Ticker | D9: Analyst | E9: Rating | F9: =TODAY() -> 46125 | H9: (mn) | I9: ($m) | N9: 2020 | O9: 2021 | Q9: +1 | R9: +2 | T9: +1 | U9: +2 | W9: 1 | X9: 2 | Z9: 2020 | AA9: 2021 | AC9: +1 | AD9: +2 | AF9: 2017 | AG9: 2018 | AI9: 2016 | AJ9: +1 | AK9: +2 | AM9: Yield | AO9: +0 | AP9: +1 | AQ9: +2 | AS9: +0 | AT9: +1 | AU9: +2 | AW9: +0 | AX9: +1 | AY9: +2 | BA9: +0 | BB9: +1 | BC9: +2
A11: Specialty Manufacturers and Service Providers
B12: {=_xll.FDS(C12,"FG_COMPANY_NAME")} -> AAR CORP. | C12: AIR | E12: O | F12: {=_xll.FDS(C12,"FG_PRICE(NOW)")} -> 113.22 | H12: {=_xll.FDS(C12,"FF_COM_SHS_OUT_EPS_DIL(MON,NOW)")} -> 38.1 | I12: =F12*H12 -> 4313.682 | J12: {=_xll.FDS(C12,"FF_DEBT(MON,NOW)")} -> 1044.3 | K12: {=_xll.FDS(C12,"FF_CASH_ST(MON,NOW)")} -> 96.2 | L12: =I12+J12-K12 -> 5261.782 | N12: =IF($L12/AP12<0,"NM",$L12/AP12) -> 1.6380575 | O12: =IF($L12/AQ12<0,"NM",$L12/AQ12) -> 1.4825769 | Q12: =IF($L12/AT12<0,"NM",$L12/AT12) -> 13.622263 | R12: =IF($L12/AU12<0,"NM",$L12/AU12) -> 12.060572 | T12: =IF($F12/AX12<0,"NM",$F12/AX12) -> 24.052807 | U12: =IF($F12/AY12<0,"NM",$F12/AY12) -> 20.574767 | W12: =IF(L12/BB12<0,"NM",L12/BB12) -> 241.14491 | X12: =IF(L12/BC12<0,"NM",L12/BC12) -> 51.18465 | Z12: =IF((J12-K12)/AT12<0,"NM",(J12-K12)/AT12) -> 2.4545425 | AA12: =IF((J12-K12)/AU12<0,"NM",(J12-K12)/AU12) -> 2.1731475 | AC12: =AP12/AO12-1 -> 0.15526283 | AD12: =AQ12/AP12-1 -> 0.10487187 | AF12: =AT12/AS12-1 -> 0.19024245 | AG12: =AU12/AT12-1 -> 0.12948728 | AI12: =IF(AS12/AO12<0,"NM",AS12/AO12) -> 0.11671462 | AJ12: =IF(AT12/AP12<0,"NM",AT12/AP12) -> 0.12024856 | AK12: =IF(AU12/AQ12<0,"NM",AU12/AQ12) -> 0.12292758 | AM12: {=_xll.FDS(C12,"P_DIV_YLD")} -> 0 | AO12: {=_xll.FDS($C12,"FE_ESTIMATE(SALES,MEAN,ANN_ROLL,+0,NOW,,,'')")} -> 2780.5 | AP12: {=_xll.FDS($C12,"FE_ESTIMATE(SALES,MEAN,ANN_ROLL,+1,NOW,,,'')")} -> 3212.2083 | AQ12: {=_xll.FDS($C12,"FE_ESTIMATE(SALES,MEAN,ANN_ROLL,+2,NOW,,,'')")} -> 3549.0786 | AS12: {=_xll.FDS($C12,"FE_ESTIMATE(EBITDA,MEAN,ANN_ROLL,+0,NOW,,,'')")} -> 324.525 | AT12: {=_xll.FDS($C12,"FE_ESTIMATE(EBITDA,MEAN,ANN_ROLL,+1,NOW,,,'')")} -> 386.26343 | AU12: {=_xll.FDS($C12,"FE_ESTIMATE(EBITDA,MEAN,ANN_ROLL,+2,NOW,,,'')")} -> 436.27963 | AW12: {=_xll.FDS($C12,"FE_ESTIMATE(EPS,MEAN,ANN_ROLL,+0,NOW,,,'')")} -> 3.91 | AX12: {=_xll.FDS($C12,"FE_ESTIMATE(EPS,MEAN,ANN_ROLL,+1,NOW,,,'')")} -> 4.707143 | AY12: {=_xll.FDS($C12,"FE_ESTIMATE(EPS,MEAN,ANN_ROLL,+2,NOW,,,'')")} -> 5.502857 | BA12: {=_xll.FDS($C12,"FE_ESTIMATE(FCF,MEAN,ANN_ROLL,+0,NOW,,,'')")} -> 1.1333333 | BB12: {=_xll.FDS($C12,"FE_ESTIMATE(FCF,MEAN,ANN_ROLL,+1,NOW,,,'')")} -> 21.82 | BC12: {=_xll.FDS($C12,"FE_ESTIMATE(FCF,MEAN,ANN_ROLL,+2,NOW,,,'')")} -> 102.8
B13: {=_xll.FDS(C13,"FG_COMPANY_NAME")} -> BWX Technologies, Inc. | C13: BWXT | E13: NC | F13: {=_xll.FDS(C13,"FG_PRICE(NOW)")} -> 196.9 | H13: {=_xll.FDS(C13,"FF_COM_SHS_OUT_EPS_DIL(MON,NOW)")} -> 91.787602 | I13: =F13*H13 -> 18072.979 | J13: {=_xll.FDS(C13,"FF_DEBT(MON,NOW)")} -> 1509.57 | K13: {=_xll.FDS(C13,"FF_CASH_ST(MON,NOW)")} -> 82.65 | L13: =I13+J13-K13 -> 19499.899 | N13: =IF($L13/AP13<0,"NM",$L13/AP13) -> 6.1829611 | O13: =IF($L13/AQ13<0,"NM",$L13/AQ13) -> 5.3078326 | Q13: =IF($L13/AT13<0,"NM",$L13/AT13) -> 34.124355 | R13: =IF($L13/AU13<0,"NM",$L13/AU13) -> 29.911307 | T13: =IF($F13/AX13<0,"NM",$F13/AX13) -> 51.53225 | U13: =IF($F13/AY13<0,"NM",$F13/AY13) -> 45.838935 | W13: =IF(L13/BB13<0,"NM",L13/BB13) -> 67.546925 | X13: =IF(L13/BC13<0,"NM",L13/BC13) -> 70.473947 | Z13: =IF((J13-K13)/AT13<0,"NM",(J13-K13)/AT13) -> 2.4970758 | AA13: =IF((J13-K13)/AU13<0,"NM",(J13-K13)/AU13) -> 2.1887827 | AC13: =AP13/AO13-1 -> 0.16649997 | AD13: =AQ13/AP13-1 -> 0.16487494 | AF13: =AT13/AS13-1 -> 0.14585202 | AG13: =AU13/AT13-1 -> 0.14085137 | AI13: =IF(AS13/AO13<0,"NM",AS13/AO13) -> 0.18445408 | AJ13: =IF(AT13/AP13<0,"NM",AT13/AP13) -> 0.1811891 | AK13: =IF(AU13/AQ13<0,"NM",AU13/AQ13) -> 0.17745238 | AM13: {=_xll.FDS(C13,"P_DIV_YLD")} -> 0.50377834 | AO13: {=_xll.FDS($C13,"FE_ESTIMATE(SALES,MEAN,ANN_ROLL,+0,NOW,,,'')")} -> 2703.654 | AP13: {=_xll.FDS($C13,"FE_ESTIMATE(SALES,MEAN,ANN_ROLL,+1,NOW,,,'')")} -> 3153.8123 | AQ13: {=_xll.FDS($C13,"FE_ESTIMATE(SALES,MEAN,ANN_ROLL,+2,NOW,,,'')")} -> 3673.7969 | AS13: {=_xll.FDS($C13,"FE_ESTIMATE(EBITDA,MEAN,ANN_ROLL,+0,NOW,,,'')")} -> 498.7 | AT13: {=_xll.FDS($C13,"FE_ESTIMATE(EBITDA,MEAN,ANN_ROLL,+1,NOW,,,'')")} -> 571.4364 | AU13: {=_xll.FDS($C13,"FE_ESTIMATE(EBITDA,MEAN,ANN_ROLL,+2,NOW,,,'')")} -> 651.924 | AW13: {=_xll.FDS($C13,"FE_ESTIMATE(EPS,MEAN,ANN_ROLL,+0,NOW,,,'')")} -> 3.33 | AX13: {=_xll.FDS($C13,"FE_ESTIMATE(EPS,MEAN,ANN_ROLL,+1,NOW,,,'')")} -> 3.8209083 | AY13: {=_xll.FDS($C13,"FE_ESTIMATE(EPS,MEAN,ANN_ROLL,+2,NOW,,,'')")} -> 4.295475 | BA13: {=_xll.FDS($C13,"FE_ESTIMATE(FCF,MEAN,ANN_ROLL,+0,NOW,,,'')")} -> 254.8 | BB13: {=_xll.FDS($C13,"FE_ESTIMATE(FCF,MEAN,ANN_ROLL,+1,NOW,,,'')")} -> 288.6867 | BC13: {=_xll.FDS($C13,"FE_ESTIMATE(FCF,MEAN,ANN_ROLL,+2,NOW,,,'')")} -> 276.69656
B14: {=_xll.FDS(C14,"FG_COMPANY_NAME")} -> HEICO Corporation | C14: HEI | E14: O | F14: {=_xll.FDS(C14,"FG_PRICE(NOW)")} -> 328.45 | H14: {=_xll.FDS(C14,"FF_COM_SHS_OUT_EPS_DIL(MON,NOW)")} -> 140.771 | I14: =F14*H14 -> 46236.235 | J14: {=_xll.FDS(C14,"FF_DEBT(MON,NOW)")} -> 2308.666 | K14: {=_xll.FDS(C14,"FF_CASH_ST(MON,NOW)")} -> 217.781 | L14: =I14+J14-K14 -> 48327.12 | N14: =IF($L14/AP14<0,"NM",$L14/AP14) -> 9.6827519 | O14: =IF($L14/AQ14<0,"NM",$L14/AQ14) -> 8.972073 | Q14: =IF($L14/AT14<0,"NM",$L14/AT14) -> 35.386474 | R14: =IF($L14/AU14<0,"NM",$L14/AU14) -> 32.52067 | T14: =IF($F14/AX14<0,"NM",$F14/AX14) -> 59.733615 | U14: =IF($F14/AY14<0,"NM",$F14/AY14) -> 53.134954 | W14: =IF(L14/BB14<0,"NM",L14/BB14) -> 54.255746 | X14: =IF(L14/BC14<0,"NM",L14/BC14) -> 47.119701 | Z14: =IF((J14-K14)/AT14<0,"NM",(J14-K14)/AT14) -> 1.5310047 | AA14: =IF((J14-K14)/AU14<0,"NM",(J14-K14)/AU14) -> 1.407015 | AC14: =AP14/AO14-1 -> 0.11282123 | AD14: =AQ14/AP14-1 -> 0.079210111 | AF14: =AT14/AS14-1 -> 0.12028836 | AG14: =AU14/AT14-1 -> 0.08812255 | AI14: =IF(AS14/AO14<0,"NM",AS14/AO14) -> 0.27180478 | AJ14: =IF(AT14/AP14<0,"NM",AT14/AP14) -> 0.27362861 | AK14: =IF(AU14/AQ14<0,"NM",AU14/AQ14) -> 0.27588832 | AM14: {=_xll.FDS(C14,"P_DIV_YLD")} -> 0.074441686 | AO14: {=_xll.FDS($C14,"FE_ESTIMATE(SALES,MEAN,ANN_ROLL,+0,NOW,,,'')")} -> 4485.044 | AP14: {=_xll.FDS($C14,"FE_ESTIMATE(SALES,MEAN,ANN_ROLL,+1,NOW,,,'')")} -> 4991.0522 | AQ14: {=_xll.FDS($C14,"FE_ESTIMATE(SALES,MEAN,ANN_ROLL,+2,NOW,,,'')")} -> 5386.394 | AS14: {=_xll.FDS($C14,"FE_ESTIMATE(EBITDA,MEAN,ANN_ROLL,+0,NOW,,,'')")} -> 1219.0564 | AT14: {=_xll.FDS($C14,"FE_ESTIMATE(EBITDA,MEAN,ANN_ROLL,+1,NOW,,,'')")} -> 1365.6947 | AU14: {=_xll.FDS($C14,"FE_ESTIMATE(EBITDA,MEAN,ANN_ROLL,+2,NOW,,,'')")} -> 1486.0432 | AW14: {=_xll.FDS($C14,"FE_ESTIMATE(EPS,MEAN,ANN_ROLL,+0,NOW,,,'')")} -> 4.9 | AX14: {=_xll.FDS($C14,"FE_ESTIMATE(EPS,MEAN,ANN_ROLL,+1,NOW,,,'')")} -> 5.498579 | AY14: {=_xll.FDS($C14,"FE_ESTIMATE(EPS,MEAN,ANN_ROLL,+2,NOW,,,'')")} -> 6.18143 | BA14: {=_xll.FDS($C14,"FE_ESTIMATE(FCF,MEAN,ANN_ROLL,+0,NOW,,,'')")} -> 861.9067 | BB14: {=_xll.FDS($C14,"FE_ESTIMATE(FCF,MEAN,ANN_ROLL,+1,NOW,,,'')")} -> 890.72815 | BC14: {=_xll.FDS($C14,"FE_ESTIMATE(FCF,MEAN,ANN_ROLL,+2,NOW,,,'')")} -> 1025.6245
B15: {=_xll.FDS(C15,"FG_COMPANY_NAME")} -> Hexcel Corporation | C15: HXL | E15: NC | F15: {=_xll.FDS(C15,"FG_PRICE(NOW)")} -> 88.95 | H15: {=_xll.FDS(C15,"FF_COM_SHS_OUT_EPS_DIL(MON,NOW)")} -> 80 | I15: =F15*H15 -> 7116 | J15: {=_xll.FDS(C15,"FF_DEBT(MON,NOW)")} -> 1018.7 | K15: {=_xll.FDS(C15,"FF_CASH_ST(MON,NOW)")} -> 71 | L15: =I15+J15-K15 -> 8063.7 | N15: =IF($L15/AP15<0,"NM",$L15/AP15) -> 3.9077254 | O15: =IF($L15/AQ15<0,"NM",$L15/AQ15) -> 3.5297458 | Q15: =IF($L15/AT15<0,"NM",$L15/AT15) -> 20.406224 | R15: =IF($L15/AU15<0,"NM",$L15/AU15) -> 17.055217 | T15: =IF($F15/AX15<0,"NM",$F15/AX15) -> 39.760004 | U15: =IF($F15/AY15<0,"NM",$F15/AY15) -> 29.011963 | W15: =IF(L15/BB15<0,"NM",L15/BB15) -> 40.943299 | X15: =IF(L15/BC15<0,"NM",L15/BC15) -> 30.757507 | Z15: =IF((J15-K15)/AT15<0,"NM",(J15-K15)/AT15) -> 2.3982761 | AA15: =IF((J15-K15)/AU15<0,"NM",(J15-K15)/AU15) -> 2.0044432 | AC15: =AP15/AO15-1 -> 0.089565341 | AD15: =AQ15/AP15-1 -> 0.10708409 | AF15: =AT15/AS15-1 -> 0.17183924 | AG15: =AU15/AT15-1 -> 0.19647993 | AI15: =IF(AS15/AO15<0,"NM",AS15/AO15) -> 0.1780519 | AJ15: =IF(AT15/AP15<0,"NM",AT15/AP15) -> 0.19149674 | AK15: =IF(AU15/AQ15<0,"NM",AU15/AQ15) -> 0.20695989 | AM15: {=_xll.FDS(C15,"P_DIV_YLD")} -> 0.8195788 | AO15: {=_xll.FDS($C15,"FE_ESTIMATE(SALES,MEAN,ANN_ROLL,+0,NOW,,,'')")} -> 1893.9 | AP15: {=_xll.FDS($C15,"FE_ESTIMATE(SALES,MEAN,ANN_ROLL,+1,NOW,,,'')")} -> 2063.5278 | AQ15: {=_xll.FDS($C15,"FE_ESTIMATE(SALES,MEAN,ANN_ROLL,+2,NOW,,,'')")} -> 2284.4988 | AS15: {=_xll.FDS($C15,"FE_ESTIMATE(EBITDA,MEAN,ANN_ROLL,+0,NOW,,,'')")} -> 337.2125 | AT15: {=_xll.FDS($C15,"FE_ESTIMATE(EBITDA,MEAN,ANN_ROLL,+1,NOW,,,'')")} -> 395.15884 | AU15: {=_xll.FDS($C15,"FE_ESTIMATE(EBITDA,MEAN,ANN_ROLL,+2,NOW,,,'')")} -> 472.79962 | AW15: {=_xll.FDS($C15,"FE_ESTIMATE(EPS,MEAN,ANN_ROLL,+0,NOW,,,'')")} -> 1.76 | AX15: {=_xll.FDS($C15,"FE_ESTIMATE(EPS,MEAN,ANN_ROLL,+1,NOW,,,'')")} -> 2.2371728 | AY15: {=_xll.FDS($C15,"FE_ESTIMATE(EPS,MEAN,ANN_ROLL,+2,NOW,,,'')")} -> 3.0659766 | BA15: {=_xll.FDS($C15,"FE_ESTIMATE(FCF,MEAN,ANN_ROLL,+0,NOW,,,'')")} -> 157.2 | BB15: {=_xll.FDS($C15,"FE_ESTIMATE(FCF,MEAN,ANN_ROLL,+1,NOW,,,'')")} -> 196.94798 | BC15: {=_xll.FDS($C15,"FE_ESTIMATE(FCF,MEAN,ANN_ROLL,+2,NOW,,,'')")} -> 262.17014
B16: {=_xll.FDS(C16,"FG_COMPANY_NAME")} -> Huntington Ingalls Industries, Inc. | C16: HII | E16: NC | F16: {=_xll.FDS(C16,"FG_PRICE(NOW)")} -> 406.76 | H16: {=_xll.FDS(C16,"FF_COM_SHS_OUT_EPS_DIL(MON,NOW)")} -> 39.3 | I16: =F16*H16 -> 15985.668 | J16: {=_xll.FDS(C16,"FF_DEBT(MON,NOW)")} -> 2981 | K16: {=_xll.FDS(C16,"FF_CASH_ST(MON,NOW)")} -> 774 | L16: =I16+J16-K16 -> 18192.668 | N16: =IF($L16/AP16<0,"NM",$L16/AP16) -> 1.4085169 | O16: =IF($L16/AQ16<0,"NM",$L16/AQ16) -> 1.3278662 | Q16: =IF($L16/AT16<0,"NM",$L16/AT16) -> 17.661166 | R16: =IF($L16/AU16<0,"NM",$L16/AU16) -> 15.158405 | T16: =IF($F16/AX16<0,"NM",$F16/AX16) -> 23.539276 | W16: =IF(L16/BB16<0,"NM",L16/BB16) -> 32.04954 | X16: =IF(L16/BC16<0,"NM",L16/BC16) -> 27.729392 | Z16: =IF((J16-K16)/AT16<0,"NM",(J16-K16)/AT16) -> 2.1425221 | AA16: =IF((J16-K16)/AU16<0,"NM",(J16-K16)/AU16) -> 1.8389057 | AC16: =AP16/AO16-1 -> 0.034619313 | AD16: =AQ16/AP16-1 -> 0.060737079 | AF16: =AT16/AS16-1 -> 0.044720487 | AG16: =AU16/AT16-1 -> 0.1651071 | AI16: =IF(AS16/AO16<0,"NM",AS16/AO16) -> 0.078981096 | AJ16: =IF(AT16/AP16<0,"NM",AT16/AP16) -> 0.079752202 | AK16: =IF(AU16/AQ16<0,"NM",AU16/AQ16) -> 0.08759933 | AM16: {=_xll.FDS(C16,"P_DIV_YLD")} -> 1.4056531 | AO16: {=_xll.FDS($C16,"FE_ESTIMATE(SALES,MEAN,ANN_ROLL,+0,NOW,,,'')")} -> 12484 | AP16: {=_xll.FDS($C16,"FE_ESTIMATE(SALES,MEAN,ANN_ROLL,+1,NOW,,,'')")} -> 12916.188 | AQ16: {=_xll.FDS($C16,"FE_ESTIMATE(SALES,MEAN,ANN_ROLL,+2,NOW,,,'')")} -> 13700.679 | AS16: {=_xll.FDS($C16,"FE_ESTIMATE(EBITDA,MEAN,ANN_ROLL,+0,NOW,,,'')")} -> 986 | AT16: {=_xll.FDS($C16,"FE_ESTIMATE(EBITDA,MEAN,ANN_ROLL,+1,NOW,,,'')")} -> 1030.0944 | AU16: {=_xll.FDS($C16,"FE_ESTIMATE(EBITDA,MEAN,ANN_ROLL,+2,NOW,,,'')")} -> 1200.1703 | AW16: {=_xll.FDS($C16,"FE_ESTIMATE(EPS,MEAN,ANN_ROLL,+0,NOW,,,'')")} -> 15.39 | AX16: {=_xll.FDS($C16,"FE_ESTIMATE(EPS,MEAN,ANN_ROLL,+1,NOW,,,'')")} -> 17.280056 | AY16: {=_xll.FDS($C16,"FE_ESTIMATE(EPS,MEAN,ANN_ROLL,+2,NOW,,,'')")} -> 20.31125 | BA16: {=_xll.FDS($C16,"FE_ESTIMATE(FCF,MEAN,ANN_ROLL,+0,NOW,,,'')")} -> 800 | BB16: {=_xll.FDS($C16,"FE_ESTIMATE(FCF,MEAN,ANN_ROLL,+1,NOW,,,'')")} -> 567.6421 | BC16: {=_xll.FDS($C16,"FE_ESTIMATE(FCF,MEAN,ANN_ROLL,+2,NOW,,,'')")} -> 656.07886
B17: {=_xll.FDS(C17,"FG_COMPANY_NAME")} -> ITT, Inc. | C17: ITT | E17: NC | F17: {=_xll.FDS(C17,"FG_PRICE(NOW)")} -> 199.11 | H17: {=_xll.FDS(C17,"FF_COM_SHS_OUT_EPS_DIL(MON,NOW)")} -> 79.9 | I17: =F17*H17 -> 15908.889 | J17: {=_xll.FDS(C17,"FF_DEBT(MON,NOW)")} -> 867.2 | K17: {=_xll.FDS(C17,"FF_CASH_ST(MON,NOW)")} -> 1742.9 | L17: =I17+J17-K17 -> 15033.189 | N17: =IF($L17/AP17<0,"NM",$L17/AP17) -> 3.5940999 | O17: =IF($L17/AQ17<0,"NM",$L17/AQ17) -> 3.4273146 | Q17: =IF($L17/AT17<0,"NM",$L17/AT17) -> 16.106136 | R17: =IF($L17/AU17<0,"NM",$L17/AU17) -> 14.843104 | T17: =IF($F17/AX17<0,"NM",$F17/AX17) -> 27.390476 | U17: =IF($F17/AY17<0,"NM",$F17/AY17) -> 24.723569 | W17: =IF(L17/BB17<0,"NM",L17/BB17) -> 25.941015 | X17: =IF(L17/BC17<0,"NM",L17/BC17) -> 22.811546 | Z17: =IF((J17-K17)/AT17<0,"NM",(J17-K17)/AT17) -> NM | AA17: =IF((J17-K17)/AU17<0,"NM",(J17-K17)/AU17) -> NM | AC17: =AP17/AO17-1 -> 0.062013711 | AD17: =AQ17/AP17-1 -> 0.048663544 | AF17: =AT17/AS17-1 -> 0.089747902 | AG17: =AU17/AT17-1 -> 0.085092214 | AI17: =IF(AS17/AO17<0,"NM",AS17/AO17) -> 0.21747175 | AJ17: =IF(AT17/AP17<0,"NM",AT17/AP17) -> 0.22315097 | AK17: =IF(AU17/AQ17<0,"NM",AU17/AQ17) -> 0.23090283 | AM17: {=_xll.FDS(C17,"P_DIV_YLD")} -> 0.7651899 | AO17: {=_xll.FDS($C17,"FE_ESTIMATE(SALES,MEAN,ANN_ROLL,+0,NOW,,,'')")} -> 3938.5 | AP17: {=_xll.FDS($C17,"FE_ESTIMATE(SALES,MEAN,ANN_ROLL,+1,NOW,,,'')")} -> 4182.741 | AQ17: {=_xll.FDS($C17,"FE_ESTIMATE(SALES,MEAN,ANN_ROLL,+2,NOW,,,'')")} -> 4386.288 | AS17: {=_xll.FDS($C17,"FE_ESTIMATE(EBITDA,MEAN,ANN_ROLL,+0,NOW,,,'')")} -> 856.5125 | AT17: {=_xll.FDS($C17,"FE_ESTIMATE(EBITDA,MEAN,ANN_ROLL,+1,NOW,,,'')")} -> 933.3827 | AU17: {=_xll.FDS($C17,"FE_ESTIMATE(EBITDA,MEAN,ANN_ROLL,+2,NOW,,,'')")} -> 1012.8063 | AW17: {=_xll.FDS($C17,"FE_ESTIMATE(EPS,MEAN,ANN_ROLL,+0,NOW,,,'')")} -> 6.72 | AX17: {=_xll.FDS($C17,"FE_ESTIMATE(EPS,MEAN,ANN_ROLL,+1,NOW,,,'')")} -> 7.269315 | AY17: {=_xll.FDS($C17,"FE_ESTIMATE(EPS,MEAN,ANN_ROLL,+2,NOW,,,'')")} -> 8.053449 | BA17: {=_xll.FDS($C17,"FE_ESTIMATE(FCF,MEAN,ANN_ROLL,+0,NOW,,,'')")} -> 555.4 | BB17: {=_xll.FDS($C17,"FE_ESTIMATE(FCF,MEAN,ANN_ROLL,+1,NOW,,,'')")} -> 579.5143 | BC17: {=_xll.FDS($C17,"FE_ESTIMATE(FCF,MEAN,ANN_ROLL,+2,NOW,,,'')")} -> 659.01666
B18: {=_xll.FDS(C18,"FG_COMPANY_NAME")} -> Karman Holdings Inc. | C18: KRMN | E18: O | F18: {=_xll.FDS(C18,"FG_PRICE(NOW)")} -> 78.71 | H18: {=_xll.FDS(C18,"FF_COM_SHS_OUT_EPS_DIL(MON,NOW)")} -> 132.32244 | I18: =F18*H18 -> 10415.099 | J18: {=_xll.FDS(C18,"FF_DEBT(MON,NOW)")} -> 483.685 | K18: {=_xll.FDS(C18,"FF_CASH_ST(MON,NOW)")} -> 18.665 | L18: =I18+J18-K18 -> 10880.119 | N18: =IF($L18/AP18<0,"NM",$L18/AP18) -> 23.186478 | O18: =IF($L18/AQ18<0,"NM",$L18/AQ18) -> 15.315098 | Q18: =IF($L18/AT18<0,"NM",$L18/AT18) -> 75.167343 | R18: =IF($L18/AU18<0,"NM",$L18/AU18) -> 51.428012 | T18: =IF($F18/AX18<0,"NM",$F18/AX18) -> 214.53942 | U18: =IF($F18/AY18<0,"NM",$F18/AY18) -> 125.44171 | W18: =IF(L18/BB18<0,"NM",L18/BB18) -> NM | X18: =IF(L18/BC18<0,"NM",L18/BC18) -> 201.56804 | Z18: =IF((J18-K18)/AT18<0,"NM",(J18-K18)/AT18) -> 3.2126779 | AA18: =IF((J18-K18)/AU18<0,"NM",(J18-K18)/AU18) -> 2.1980508 | AC18: =AP18/AO18-1 -> 0.35913884 | AD18: =AQ18/AP18-1 -> 0.51396211 | AF18: =AT18/AS18-1 -> 0.36366156 | AG18: =AU18/AT18-1 -> 0.46160314 | AI18: =IF(AS18/AO18<0,"NM",AS18/AO18) -> 0.30744173 | AJ18: =IF(AT18/AP18<0,"NM",AT18/AP18) -> 0.30846478 | AK18: =IF(AU18/AQ18<0,"NM",AU18/AQ18) -> 0.29779681 | AM18: {=_xll.FDS(C18,"P_DIV_YLD")} -> 0 | AO18: {=_xll.FDS($C18,"FE_ESTIMATE(SALES,MEAN,ANN_ROLL,+0,NOW,,,'')")} -> 345.25107 | AP18: {=_xll.FDS($C18,"FE_ESTIMATE(SALES,MEAN,ANN_ROLL,+1,NOW,,,'')")} -> 469.24414 | AQ18: {=_xll.FDS($C18,"FE_ESTIMATE(SALES,MEAN,ANN_ROLL,+2,NOW,,,'')")} -> 710.41785 | AS18: {=_xll.FDS($C18,"FE_ESTIMATE(EBITDA,MEAN,ANN_ROLL,+0,NOW,,,'')")} -> 106.14459 | AT18: {=_xll.FDS($C18,"FE_ESTIMATE(EBITDA,MEAN,ANN_ROLL,+1,NOW,,,'')")} -> 144.74529 | AU18: {=_xll.FDS($C18,"FE_ESTIMATE(EBITDA,MEAN,ANN_ROLL,+2,NOW,,,'')")} -> 211.56017 | AW18: {=_xll.FDS($C18,"FE_ESTIMATE(EPS,MEAN,ANN_ROLL,+0,NOW,,,'')")} -> 0.08 | AX18: {=_xll.FDS($C18,"FE_ESTIMATE(EPS,MEAN,ANN_ROLL,+1,NOW,,,'')")} -> 0.36687896 | AY18: {=_xll.FDS($C18,"FE_ESTIMATE(EPS,MEAN,ANN_ROLL,+2,NOW,,,'')")} -> 0.62746274 | BA18: {=_xll.FDS($C18,"FE_ESTIMATE(FCF,MEAN,ANN_ROLL,+0,NOW,,,'')")} -> 6.25 | BB18: {=_xll.FDS($C18,"FE_ESTIMATE(FCF,MEAN,ANN_ROLL,+1,NOW,,,'')")} -> -17.4238 | BC18: {=_xll.FDS($C18,"FE_ESTIMATE(FCF,MEAN,ANN_ROLL,+2,NOW,,,'')")} -> 53.9774
B19: {=_xll.FDS(C19,"FG_COMPANY_NAME")} -> Mercury Systems, Inc. | C19: MRCY | E19: O | F19: {=_xll.FDS(C19,"FG_PRICE(NOW)")} -> 80.25 | H19: {=_xll.FDS(C19,"FF_COM_SHS_OUT_EPS_DIL(MON,NOW)")} -> 59.415 | I19: =F19*H19 -> 4768.0538 | J19: {=_xll.FDS(C19,"FF_DEBT(MON,NOW)")} -> 642.46 | K19: {=_xll.FDS(C19,"FF_CASH_ST(MON,NOW)")} -> 334.99 | L19: =I19+J19-K19 -> 5075.5238 | N19: =IF($L19/AP19<0,"NM",$L19/AP19) -> 5.3248793 | O19: =IF($L19/AQ19<0,"NM",$L19/AQ19) -> 4.8607547 | Q19: =IF($L19/AT19<0,"NM",$L19/AT19) -> 36.299608 | R19: =IF($L19/AU19<0,"NM",$L19/AU19) -> 26.090528 | T19: =IF($F19/AX19<0,"NM",$F19/AX19) -> 83.768267 | U19: =IF($F19/AY19<0,"NM",$F19/AY19) -> 53.420859 | W19: =IF(L19/BB19<0,"NM",L19/BB19) -> 65.59643 | X19: =IF(L19/BC19<0,"NM",L19/BC19) -> 45.804599 | Z19: =IF((J19-K19)/AT19<0,"NM",(J19-K19)/AT19) -> 2.1989929 | AA19: =IF((J19-K19)/AU19<0,"NM",(J19-K19)/AU19) -> 1.5805373 | AC19: =AP19/AO19-1 -> 0.045121379 | AD19: =AQ19/AP19-1 -> 0.095484066 | AF19: =AT19/AS19-1 -> 0.16524426 | AG19: =AU19/AT19-1 -> 0.3912945 | AI19: =IF(AS19/AO19<0,"NM",AS19/AO19) -> 0.13157022 | AJ19: =IF(AT19/AP19<0,"NM",AT19/AP19) -> 0.14669247 | AK19: =IF(AU19/AQ19<0,"NM",AU19/AQ19) -> 0.18630342 | AM19: {=_xll.FDS(C19,"P_DIV_YLD")} -> 0 | AO19: {=_xll.FDS($C19,"FE_ESTIMATE(SALES,MEAN,ANN_ROLL,+0,NOW,,,'')")} -> 912.02 | AP19: {=_xll.FDS($C19,"FE_ESTIMATE(SALES,MEAN,ANN_ROLL,+1,NOW,,,'')")} -> 953.1716 | AQ19: {=_xll.FDS($C19,"FE_ESTIMATE(SALES,MEAN,ANN_ROLL,+2,NOW,,,'')")} -> 1044.1843 | AS19: {=_xll.FDS($C19,"FE_ESTIMATE(EBITDA,MEAN,ANN_ROLL,+0,NOW,,,'')")} -> 119.99467 | AT19: {=_xll.FDS($C19,"FE_ESTIMATE(EBITDA,MEAN,ANN_ROLL,+1,NOW,,,'')")} -> 139.8231 | AU19: {=_xll.FDS($C19,"FE_ESTIMATE(EBITDA,MEAN,ANN_ROLL,+2,NOW,,,'')")} -> 194.53511 | AW19: {=_xll.FDS($C19,"FE_ESTIMATE(EPS,MEAN,ANN_ROLL,+0,NOW,,,'')")} -> 0.64 | AX19: {=_xll.FDS($C19,"FE_ESTIMATE(EPS,MEAN,ANN_ROLL,+1,NOW,,,'')")} -> 0.958 | AY19: {=_xll.FDS($C19,"FE_ESTIMATE(EPS,MEAN,ANN_ROLL,+2,NOW,,,'')")} -> 1.5022222 | BA19: {=_xll.FDS($C19,"FE_ESTIMATE(FCF,MEAN,ANN_ROLL,+0,NOW,,,'')")} -> 119.016 | BB19: {=_xll.FDS($C19,"FE_ESTIMATE(FCF,MEAN,ANN_ROLL,+1,NOW,,,'')")} -> 77.375 | BC19: {=_xll.FDS($C19,"FE_ESTIMATE(FCF,MEAN,ANN_ROLL,+2,NOW,,,'')")} -> 110.80817
B20: {=_xll.FDS(C20,"FG_COMPANY_NAME")} -> Teledyne Technologies Incorporated | C20: TDY | E20: NC | F20: {=_xll.FDS(C20,"FG_PRICE(NOW)")} -> 646.3 | H20: {=_xll.FDS(C20,"FF_COM_SHS_OUT_EPS_DIL(MON,NOW)")} -> 47.4 | I20: =F20*H20 -> 30634.62 | J20: {=_xll.FDS(C20,"FF_DEBT(MON,NOW)")} -> 2475.4 | K20: {=_xll.FDS(C20,"FF_CASH_ST(MON,NOW)")} -> 352.4 | L20: =I20+J20-K20 -> 32757.62 | N20: =IF($L20/AP20<0,"NM",$L20/AP20) -> 5.1310296 | O20: =IF($L20/AQ20<0,"NM",$L20/AQ20) -> 4.8809377 | Q20: =IF($L20/AT20<0,"NM",$L20/AT20) -> 20.532622 | R20: =IF($L20/AU20<0,"NM",$L20/AU20) -> 19.096663 | T20: =IF($F20/AX20<0,"NM",$F20/AX20) -> 27.170102 | U20: =IF($F20/AY20<0,"NM",$F20/AY20) -> 25.100801 | W20: =IF(L20/BB20<0,"NM",L20/BB20) -> 28.039824 | X20: =IF(L20/BC20<0,"NM",L20/BC20) -> 25.705164 | Z20: =IF((J20-K20)/AT20<0,"NM",(J20-K20)/AT20) -> 1.3307059 | AA20: =IF((J20-K20)/AU20<0,"NM",(J20-K20)/AU20) -> 1.2376423 | AC20: =AP20/AO20-1 -> 0.043957828 | AD20: =AQ20/AP20-1 -> 0.051238478 | AF20: =AT20/AS20-1 -> 0.064285164 | AG20: =AU20/AT20-1 -> 0.07519422 | AI20: =IF(AS20/AO20<0,"NM",AS20/AO20) -> 0.24512356 | AJ20: =IF(AT20/AP20<0,"NM",AT20/AP20) -> 0.24989646 | AK20: =IF(AU20/AQ20<0,"NM",AU20/AQ20) -> 0.25559113 | AM20: {=_xll.FDS(C20,"P_DIV_YLD")} -> 0 | AO20: {=_xll.FDS($C20,"FE_ESTIMATE(SALES,MEAN,ANN_ROLL,+0,NOW,,,'')")} -> 6115.4 | AP20: {=_xll.FDS($C20,"FE_ESTIMATE(SALES,MEAN,ANN_ROLL,+1,NOW,,,'')")} -> 6384.2197 | AQ20: {=_xll.FDS($C20,"FE_ESTIMATE(SALES,MEAN,ANN_ROLL,+2,NOW,,,'')")} -> 6711.3374 | AS20: {=_xll.FDS($C20,"FE_ESTIMATE(EBITDA,MEAN,ANN_ROLL,+0,NOW,,,'')")} -> 1499.0286 | AT20: {=_xll.FDS($C20,"FE_ESTIMATE(EBITDA,MEAN,ANN_ROLL,+1,NOW,,,'')")} -> 1595.3939 | AU20: {=_xll.FDS($C20,"FE_ESTIMATE(EBITDA,MEAN,ANN_ROLL,+2,NOW,,,'')")} -> 1715.3583 | AW20: {=_xll.FDS($C20,"FE_ESTIMATE(EPS,MEAN,ANN_ROLL,+0,NOW,,,'')")} -> 21.99 | AX20: {=_xll.FDS($C20,"FE_ESTIMATE(EPS,MEAN,ANN_ROLL,+1,NOW,,,'')")} -> 23.787176 | AY20: {=_xll.FDS($C20,"FE_ESTIMATE(EPS,MEAN,ANN_ROLL,+2,NOW,,,'')")} -> 25.748182 | BA20: {=_xll.FDS($C20,"FE_ESTIMATE(FCF,MEAN,ANN_ROLL,+0,NOW,,,'')")} -> 1074 | BB20: {=_xll.FDS($C20,"FE_ESTIMATE(FCF,MEAN,ANN_ROLL,+1,NOW,,,'')")} -> 1168.2534 | BC20: {=_xll.FDS($C20,"FE_ESTIMATE(FCF,MEAN,ANN_ROLL,+2,NOW,,,'')")} -> 1274.3595
B21: {=_xll.FDS(C21,"FG_COMPANY_NAME")} -> Woodward, Inc. | C21: WWD | E21: NC | F21: {=_xll.FDS(C21,"FG_PRICE(NOW)")} -> 380.43 | H21: {=_xll.FDS(C21,"FF_COM_SHS_OUT_EPS_DIL(MON,NOW)")} -> 61.59 | I21: =F21*H21 -> 23430.684 | J21: {=_xll.FDS(C21,"FF_DEBT(MON,NOW)")} -> 912.504 | K21: {=_xll.FDS(C21,"FF_CASH_ST(MON,NOW)")} -> 454.245 | L21: =I21+J21-K21 -> 23888.943 | N21: =IF($L21/AP21<0,"NM",$L21/AP21) -> 5.771917 | O21: =IF($L21/AQ21<0,"NM",$L21/AQ21) -> 5.3276916 | Q21: =IF($L21/AT21<0,"NM",$L21/AT21) -> 28.187729 | R21: =IF($L21/AU21<0,"NM",$L21/AU21) -> 24.843852 | T21: =IF($F21/AX21<0,"NM",$F21/AX21) -> 43.598899 | U21: =IF($F21/AY21<0,"NM",$F21/AY21) -> 37.58623 | W21: =IF(L21/BB21<0,"NM",L21/BB21) -> 74.028424 | X21: =IF(L21/BC21<0,"NM",L21/BC21) -> 51.296959 | Z21: =IF((J21-K21)/AT21<0,"NM",(J21-K21)/AT21) -> 0.54072216 | AA21: =IF((J21-K21)/AU21<0,"NM",(J21-K21)/AU21) -> 0.47657693 | AC21: =AP21/AO21-1 -> 0.16028841 | AD21: =AQ21/AP21-1 -> 0.083380468 | AF21: =AT21/AS21-1 -> 0.26374663 | AG21: =AU21/AT21-1 -> 0.13459574 | AI21: =IF(AS21/AO21<0,"NM",AS21/AO21) -> 0.1880035 | AJ21: =IF(AT21/AP21<0,"NM",AT21/AP21) -> 0.20476701 | AK21: =IF(AU21/AQ21<0,"NM",AU21/AQ21) -> 0.21444708 | AM21: {=_xll.FDS(C21,"P_DIV_YLD")} -> 0.32853368 | AO21: {=_xll.FDS($C21,"FE_ESTIMATE(SALES,MEAN,ANN_ROLL,+0,NOW,,,'')")} -> 3567.064 | AP21: {=_xll.FDS($C21,"FE_ESTIMATE(SALES,MEAN,ANN_ROLL,+1,NOW,,,'')")} -> 4138.823 | AQ21: {=_xll.FDS($C21,"FE_ESTIMATE(SALES,MEAN,ANN_ROLL,+2,NOW,,,'')")} -> 4483.92 | AS21: {=_xll.FDS($C21,"FE_ESTIMATE(EBITDA,MEAN,ANN_ROLL,+0,NOW,,,'')")} -> 670.6205 | AT21: {=_xll.FDS($C21,"FE_ESTIMATE(EBITDA,MEAN,ANN_ROLL,+1,NOW,,,'')")} -> 847.4944 | AU21: {=_xll.FDS($C21,"FE_ESTIMATE(EBITDA,MEAN,ANN_ROLL,+2,NOW,,,'')")} -> 961.56354 | AW21: {=_xll.FDS($C21,"FE_ESTIMATE(EPS,MEAN,ANN_ROLL,+0,NOW,,,'')")} -> 6.89 | AX21: {=_xll.FDS($C21,"FE_ESTIMATE(EPS,MEAN,ANN_ROLL,+1,NOW,,,'')")} -> 8.725679 | AY21: {=_xll.FDS($C21,"FE_ESTIMATE(EPS,MEAN,ANN_ROLL,+2,NOW,,,'')")} -> 10.121526 | BA21: {=_xll.FDS($C21,"FE_ESTIMATE(FCF,MEAN,ANN_ROLL,+0,NOW,,,'')")} -> 340 | BB21: {=_xll.FDS($C21,"FE_ESTIMATE(FCF,MEAN,ANN_ROLL,+1,NOW,,,'')")} -> 322.6996 | BC21: {=_xll.FDS($C21,"FE_ESTIMATE(FCF,MEAN,ANN_ROLL,+2,NOW,,,'')")} -> 465.699
L22: Median | N22: =MEDIAN(N6:N19) -> 5.3248793 | O22: =MEDIAN(O6:O19) -> 4.8607547 | Q22: =MEDIAN(Q12:Q21) -> 24.360176 | R22: =MEDIAN(R12:R21) -> 21.970258 | T22: =MEDIAN(T12:T21) -> 41.679452 | U22: =MEDIAN(U12:U21) -> 37.58623 | V22: =MEDIAN(V17:V21) -> #NUM! | W22: =MEDIAN(W12:W21) -> 54.255746 | X22: =MEDIAN(X12:X21) -> 46.46215 | Z22: =MEDIAN(Z17:Z21) -> 1.7648494 | AA22: =MEDIAN(AA17:AA21) -> 1.4090898 | AB22: =MEDIAN(AB17:AB21) -> #NUM! | AC22: =MEDIAN(AC12:AC21) -> 0.10119329 | AD22: =MEDIAN(AD12:AD21) -> 0.089432267 | AF22: =MEDIAN(AF17:AF21) -> 0.16524426 | AG22: =MEDIAN(AG17:AG21) -> 0.13459574 | AH22: =MEDIAN(AH17:AH21) -> #NUM! | AI22: =MEDIAN(AI17:AI21) -> 0.21747175 | AJ22: =MEDIAN(AJ12:AJ21) -> 0.19813187 | AK22: =MEDIAN(AK12:AK21) -> 0.21070348 | AM22: =MEDIAN(AM12:AM21) -> 0.20148768
A23: Defense Prime Contractors
B24: {=_xll.FDS(C24,"FG_COMPANY_NAME")} -> Boeing Company | C24: BA | E24: O | F24: {=_xll.FDS(C24,"FG_PRICE(NOW)")} -> 239.35 | H24: {=_xll.FDS(C24,"FF_COM_SHS_OUT_EPS_DIL(MON,NOW)")} -> 762.3 | I24: =F24*H24 -> 182456.5 | J24: {=_xll.FDS(C24,"FF_DEBT(MON,NOW)")} -> 56365 | K24: {=_xll.FDS(C24,"FF_CASH_ST(MON,NOW)")} -> 29400 | L24: =I24+J24-K24 -> 209421.5 | N24: =IF($L24/AP24<0,"NM",$L24/AP24) -> 2.1571381 | O24: =IF($L24/AQ24<0,"NM",$L24/AQ24) -> 1.8859452 | Q24: =IF($L24/AT24<0,"NM",$L24/AT24) -> 37.305824 | R24: =IF($L24/AU24<0,"NM",$L24/AU24) -> 21.825241 | T24: =IF($F24/AX24<0,"NM",$F24/AX24) -> 139.09215 | U24: =IF($F24/AY24<0,"NM",$F24/AY24) -> 48.17154 | W24: =IF(L24/BB24<0,"NM",L24/BB24) -> 89.645411 | X24: =IF(L24/BC24<0,"NM",L24/BC24) -> 30.957854 | Z24: =IF((J24-K24)/AT24<0,"NM",(J24-K24)/AT24) -> 4.8034778 | AA24: =IF((J24-K24)/AU24<0,"NM",(J24-K24)/AU24) -> 2.8102063 | AC24: =AP24/AO24-1 -> 0.085175212 | AD24: =AQ24/AP24-1 -> 0.14379681 | AF24: =AT24/AS24-1 -> -0.10239421 | AG24: =AU24/AT24-1 -> 0.70929723 | AI24: =IF(AS24/AO24<0,"NM",AS24/AO24) -> 0.069906174 | AJ24: =IF(AT24/AP24<0,"NM",AT24/AP24) -> 0.057823092 | AK24: =IF(AU24/AQ24<0,"NM",AU24/AQ24) -> 0.086411197 | AM24: {=_xll.FDS(C24,"P_DIV_YLD")} -> 0 | AO24: {=_xll.FDS($C24,"FE_ESTIMATE(SALES,MEAN,ANN_ROLL,+0,NOW,,,'')")} -> 89463 | AP24: {=_xll.FDS($C24,"FE_ESTIMATE(SALES,MEAN,ANN_ROLL,+1,NOW,,,'')")} -> 97083.03 | AQ24: {=_xll.FDS($C24,"FE_ESTIMATE(SALES,MEAN,ANN_ROLL,+2,NOW,,,'')")} -> 111043.26 | AS24: {=_xll.FDS($C24,"FE_ESTIMATE(EBITDA,MEAN,ANN_ROLL,+0,NOW,,,'')")} -> 6254.016 | AT24: {=_xll.FDS($C24,"FE_ESTIMATE(EBITDA,MEAN,ANN_ROLL,+1,NOW,,,'')")} -> 5613.641 | AU24: {=_xll.FDS($C24,"FE_ESTIMATE(EBITDA,MEAN,ANN_ROLL,+2,NOW,,,'')")} -> 9595.381 | AW24: {=_xll.FDS($C24,"FE_ESTIMATE(EPS,MEAN,ANN_ROLL,+0,NOW,,,'')")} -> 1.19 | AX24: {=_xll.FDS($C24,"FE_ESTIMATE(EPS,MEAN,ANN_ROLL,+1,NOW,,,'')")} -> 1.7208017 | AY24: {=_xll.FDS($C24,"FE_ESTIMATE(EPS,MEAN,ANN_ROLL,+2,NOW,,,'')")} -> 4.9687014 | BA24: {=_xll.FDS($C24,"FE_ESTIMATE(FCF,MEAN,ANN_ROLL,+0,NOW,,,'')")} -> -1877 | BB24: {=_xll.FDS($C24,"FE_ESTIMATE(FCF,MEAN,ANN_ROLL,+1,NOW,,,'')")} -> 2336.1096 | BC24: {=_xll.FDS($C24,"FE_ESTIMATE(FCF,MEAN,ANN_ROLL,+2,NOW,,,'')")} -> 6764.7295
B25: {=_xll.FDS(C25,"FG_COMPANY_NAME")} -> General Dynamics Corporation | C25: GD | E25: O | F25: {=_xll.FDS(C25,"FG_PRICE(NOW)")} -> 340.75 | H25: {=_xll.FDS(C25,"FF_COM_SHS_OUT_EPS_DIL(MON,NOW)")} -> 272.425 | I25: =F25*H25 -> 92828.819 | J25: {=_xll.FDS(C25,"FF_DEBT(MON,NOW)")} -> 9789 | K25: {=_xll.FDS(C25,"FF_CASH_ST(MON,NOW)")} -> 2333 | L25: =I25+J25-K25 -> 100284.82 | N25: =IF($L25/AP25<0,"NM",$L25/AP25) -> 1.8331013 | O25: =IF($L25/AQ25<0,"NM",$L25/AQ25) -> 1.7527552 | Q25: =IF($L25/AT25<0,"NM",$L25/AT25) -> 14.999808 | R25: =IF($L25/AU25<0,"NM",$L25/AU25) -> 13.82181 | T25: =IF($F25/AX25<0,"NM",$F25/AX25) -> 20.74147 | U25: =IF($F25/AY25<0,"NM",$F25/AY25) -> 18.715991 | W25: =IF(L25/BB25<0,"NM",L25/BB25) -> 22.587538 | X25: =IF(L25/BC25<0,"NM",L25/BC25) -> 21.249092 | Z25: =IF((J25-K25)/AT25<0,"NM",(J25-K25)/AT25) -> 1.1152094 | AA25: =IF((J25-K25)/AU25<0,"NM",(J25-K25)/AU25) -> 1.0276273 | AC25: =AP25/AO25-1 -> 0.04106059 | AD25: =AQ25/AP25-1 -> 0.045839881 | AF25: =AT25/AS25-1 -> 0.058863558 | AG25: =AU25/AT25-1 -> 0.085227514 | AI25: =IF(AS25/AO25<0,"NM",AS25/AO25) -> 0.12015359 | AJ25: =IF(AT25/AP25<0,"NM",AT25/AP25) -> 0.12220832 | AK25: =IF(AU25/AQ25<0,"NM",AU25/AQ25) -> 0.12681083 | AM25: {=_xll.FDS(C25,"P_DIV_YLD")} -> 1.7324017 | AO25: {=_xll.FDS($C25,"FE_ESTIMATE(SALES,MEAN,ANN_ROLL,+0,NOW,,,'')")} -> 52550 | AP25: {=_xll.FDS($C25,"FE_ESTIMATE(SALES,MEAN,ANN_ROLL,+1,NOW,,,'')")} -> 54707.734 | AQ25: {=_xll.FDS($C25,"FE_ESTIMATE(SALES,MEAN,ANN_ROLL,+2,NOW,,,'')")} -> 57215.53 | AS25: {=_xll.FDS($C25,"FE_ESTIMATE(EBITDA,MEAN,ANN_ROLL,+0,NOW,,,'')")} -> 6314.0713 | AT25: {=_xll.FDS($C25,"FE_ESTIMATE(EBITDA,MEAN,ANN_ROLL,+1,NOW,,,'')")} -> 6685.74 | AU25: {=_xll.FDS($C25,"FE_ESTIMATE(EBITDA,MEAN,ANN_ROLL,+2,NOW,,,'')")} -> 7255.549 | AW25: {=_xll.FDS($C25,"FE_ESTIMATE(EPS,MEAN,ANN_ROLL,+0,NOW,,,'')")} -> 15.45 | AX25: {=_xll.FDS($C25,"FE_ESTIMATE(EPS,MEAN,ANN_ROLL,+1,NOW,,,'')")} -> 16.42844 | AY25: {=_xll.FDS($C25,"FE_ESTIMATE(EPS,MEAN,ANN_ROLL,+2,NOW,,,'')")} -> 18.206356 | BA25: {=_xll.FDS($C25,"FE_ESTIMATE(FCF,MEAN,ANN_ROLL,+0,NOW,,,'')")} -> 3959 | BB25: {=_xll.FDS($C25,"FE_ESTIMATE(FCF,MEAN,ANN_ROLL,+1,NOW,,,'')")} -> 4439.8296 | BC25: {=_xll.FDS($C25,"FE_ESTIMATE(FCF,MEAN,ANN_ROLL,+2,NOW,,,'')")} -> 4719.4873
B26: {=_xll.FDS(C26,"FG_COMPANY_NAME")} -> L3Harris Technologies Inc | C26: LHX | E26: NC | F26: {=_xll.FDS(C26,"FG_PRICE(NOW)")} -> 339.9 | H26: {=_xll.FDS(C26,"FF_COM_SHS_OUT_EPS_DIL(MON,NOW)")} -> 188.4 | I26: =F26*H26 -> 64037.16 | J26: {=_xll.FDS(C26,"FF_DEBT(MON,NOW)")} -> 10443 | K26: {=_xll.FDS(C26,"FF_CASH_ST(MON,NOW)")} -> 1069 | L26: =I26+J26-K26 -> 73411.16 | N26: =IF($L26/AP26<0,"NM",$L26/AP26) -> 3.1329734 | O26: =IF($L26/AQ26<0,"NM",$L26/AQ26) -> 2.922255 | Q26: =IF($L26/AT26<0,"NM",$L26/AT26) -> 17.236484 | R26: =IF($L26/AU26<0,"NM",$L26/AU26) -> 16.134752 | T26: =IF($F26/AX26<0,"NM",$F26/AX26) -> 28.684934 | U26: =IF($F26/AY26<0,"NM",$F26/AY26) -> 24.843275 | W26: =IF(L26/BB26<0,"NM",L26/BB26) -> 24.211434 | X26: =IF(L26/BC26<0,"NM",L26/BC26) -> 23.716518 | Z26: =IF((J26-K26)/AT26<0,"NM",(J26-K26)/AT26) -> 2.2009569 | AA26: =IF((J26-K26)/AU26<0,"NM",(J26-K26)/AU26) -> 2.0602748 | AC26: =AP26/AO26-1 -> 0.071657215 | AD26: =AQ26/AP26-1 -> 0.072108164 | AF26: =AT26/AS26-1 -> 0.10906001 | AG26: =AU26/AT26-1 -> 0.06828315 | AI26: =IF(AS26/AO26<0,"NM",AS26/AO26) -> 0.17563412 | AJ26: =IF(AT26/AP26<0,"NM",AT26/AP26) -> 0.18176407 | AK26: =IF(AU26/AQ26<0,"NM",AU26/AQ26) -> 0.18111558 | AM26: {=_xll.FDS(C26,"P_DIV_YLD")} -> 1.469335 | AO26: {=_xll.FDS($C26,"FE_ESTIMATE(SALES,MEAN,ANN_ROLL,+0,NOW,,,'')")} -> 21865 | AP26: {=_xll.FDS($C26,"FE_ESTIMATE(SALES,MEAN,ANN_ROLL,+1,NOW,,,'')")} -> 23431.785 | AQ26: {=_xll.FDS($C26,"FE_ESTIMATE(SALES,MEAN,ANN_ROLL,+2,NOW,,,'')")} -> 25121.408 | AS26: {=_xll.FDS($C26,"FE_ESTIMATE(EBITDA,MEAN,ANN_ROLL,+0,NOW,,,'')")} -> 3840.24 | AT26: {=_xll.FDS($C26,"FE_ESTIMATE(EBITDA,MEAN,ANN_ROLL,+1,NOW,,,'')")} -> 4259.0566 | AU26: {=_xll.FDS($C26,"FE_ESTIMATE(EBITDA,MEAN,ANN_ROLL,+2,NOW,,,'')")} -> 4549.8784 | AW26: {=_xll.FDS($C26,"FE_ESTIMATE(EPS,MEAN,ANN_ROLL,+0,NOW,,,'')")} -> 10.73 | AX26: {=_xll.FDS($C26,"FE_ESTIMATE(EPS,MEAN,ANN_ROLL,+1,NOW,,,'')")} -> 11.849426 | AY26: {=_xll.FDS($C26,"FE_ESTIMATE(EPS,MEAN,ANN_ROLL,+2,NOW,,,'')")} -> 13.681771 | BA26: {=_xll.FDS($C26,"FE_ESTIMATE(FCF,MEAN,ANN_ROLL,+0,NOW,,,'')")} -> 2814 | BB26: {=_xll.FDS($C26,"FE_ESTIMATE(FCF,MEAN,ANN_ROLL,+1,NOW,,,'')")} -> 3032.0864 | BC26: {=_xll.FDS($C26,"FE_ESTIMATE(FCF,MEAN,ANN_ROLL,+2,NOW,,,'')")} -> 3095.36
B27: {=_xll.FDS(C27,"FG_COMPANY_NAME")} -> Lockheed Martin Corporation | C27: LMT | E27: NC | F27: {=_xll.FDS(C27,"FG_PRICE(NOW)")} -> 637.43 | H27: {=_xll.FDS(C27,"FF_COM_SHS_OUT_EPS_DIL(MON,NOW)")} -> 233.5 | I27: =F27*H27 -> 148839.9 | J27: {=_xll.FDS(C27,"FF_DEBT(MON,NOW)")} -> 22771 | K27: {=_xll.FDS(C27,"FF_CASH_ST(MON,NOW)")} -> 4121 | L27: =I27+J27-K27 -> 167489.9 | N27: =IF($L27/AP27<0,"NM",$L27/AP27) -> 2.1174138 | O27: =IF($L27/AQ27<0,"NM",$L27/AQ27) -> 2.0146569 | Q27: =IF($L27/AT27<0,"NM",$L27/AT27) -> 14.783357 | R27: =IF($L27/AU27<0,"NM",$L27/AU27) -> 14.265823 | T27: =IF($F27/AX27<0,"NM",$F27/AX27) -> 21.287308 | U27: =IF($F27/AY27<0,"NM",$F27/AY27) -> 19.995117 | W27: =IF(L27/BB27<0,"NM",L27/BB27) -> 25.093989 | X27: =IF(L27/BC27<0,"NM",L27/BC27) -> 26.186705 | Z27: =IF((J27-K27)/AT27<0,"NM",(J27-K27)/AT27) -> 1.6461267 | AA27: =IF((J27-K27)/AU27<0,"NM",(J27-K27)/AU27) -> 1.5884993 | AC27: =AP27/AO27-1 -> 0.054007702 | AD27: =AQ27/AP27-1 -> 0.051004619 | AF27: =AT27/AS27-1 -> 0.20251064 | AG27: =AU27/AT27-1 -> 0.036277897 | AI27: =IF(AS27/AO27<0,"NM",AS27/AO27) -> 0.12554156 | AJ27: =IF(AT27/AP27<0,"NM",AT27/AP27) -> 0.14322956 | AK27: =IF(AU27/AQ27<0,"NM",AU27/AQ27) -> 0.14122262 | AM27: {=_xll.FDS(C27,"P_DIV_YLD")} -> 2.1950054 | AO27: {=_xll.FDS($C27,"FE_ESTIMATE(SALES,MEAN,ANN_ROLL,+0,NOW,,,'')")} -> 75048 | AP27: {=_xll.FDS($C27,"FE_ESTIMATE(SALES,MEAN,ANN_ROLL,+1,NOW,,,'')")} -> 79101.17 | AQ27: {=_xll.FDS($C27,"FE_ESTIMATE(SALES,MEAN,ANN_ROLL,+2,NOW,,,'')")} -> 83135.695 | AS27: {=_xll.FDS($C27,"FE_ESTIMATE(EBITDA,MEAN,ANN_ROLL,+0,NOW,,,'')")} -> 9421.643 | AT27: {=_xll.FDS($C27,"FE_ESTIMATE(EBITDA,MEAN,ANN_ROLL,+1,NOW,,,'')")} -> 11329.626 | AU27: {=_xll.FDS($C27,"FE_ESTIMATE(EBITDA,MEAN,ANN_ROLL,+2,NOW,,,'')")} -> 11740.641 | AW27: {=_xll.FDS($C27,"FE_ESTIMATE(EPS,MEAN,ANN_ROLL,+0,NOW,,,'')")} -> 21.49 | AX27: {=_xll.FDS($C27,"FE_ESTIMATE(EPS,MEAN,ANN_ROLL,+1,NOW,,,'')")} -> 29.944134 | AY27: {=_xll.FDS($C27,"FE_ESTIMATE(EPS,MEAN,ANN_ROLL,+2,NOW,,,'')")} -> 31.879284 | BA27: {=_xll.FDS($C27,"FE_ESTIMATE(FCF,MEAN,ANN_ROLL,+0,NOW,,,'')")} -> 6908 | BB27: {=_xll.FDS($C27,"FE_ESTIMATE(FCF,MEAN,ANN_ROLL,+1,NOW,,,'')")} -> 6674.503 | BC27: {=_xll.FDS($C27,"FE_ESTIMATE(FCF,MEAN,ANN_ROLL,+2,NOW,,,'')")} -> 6395.99
B28: {=_xll.FDS(C28,"FG_COMPANY_NAME")} -> Northrop Grumman Corp. | C28: NOC | E28: NC | F28: {=_xll.FDS(C28,"FG_PRICE(NOW)")} -> 695.06 | H28: {=_xll.FDS(C28,"FF_COM_SHS_OUT_EPS_DIL(MON,NOW)")} -> 143.8 | I28: =F28*H28 -> 99949.628 | J28: {=_xll.FDS(C28,"FF_DEBT(MON,NOW)")} -> 17884 | K28: {=_xll.FDS(C28,"FF_CASH_ST(MON,NOW)")} -> 4403 | L28: =I28+J28-K28 -> 113430.63 | N28: =IF($L28/AP28<0,"NM",$L28/AP28) -> 2.5826028 | O28: =IF($L28/AQ28<0,"NM",$L28/AQ28) -> 2.4307567 | Q28: =IF($L28/AT28<0,"NM",$L28/AT28) -> 18.091817 | R28: =IF($L28/AU28<0,"NM",$L28/AU28) -> 17.03115 | T28: =IF($F28/AX28<0,"NM",$F28/AX28) -> 24.79474 | U28: =IF($F28/AY28<0,"NM",$F28/AY28) -> 23.00431 | W28: =IF(L28/BB28<0,"NM",L28/BB28) -> 34.404877 | X28: =IF(L28/BC28<0,"NM",L28/BC28) -> 32.192175 | Z28: =IF((J28-K28)/AT28<0,"NM",(J28-K28)/AT28) -> 2.1501758 | AA28: =IF((J28-K28)/AU28<0,"NM",(J28-K28)/AU28) -> 2.0241176 | AC28: =AP28/AO28-1 -> 0.046885875 | AD28: =AQ28/AP28-1 -> 0.06246868 | AF28: =AT28/AS28-1 -> 0.052496223 | AG28: =AU28/AT28-1 -> 0.06227806 | AI28: =IF(AS28/AO28<0,"NM",AS28/AO28) -> 0.14198884 | AJ28: =IF(AT28/AP28<0,"NM",AT28/AP28) -> 0.14274977 | AK28: =IF(AU28/AQ28<0,"NM",AU28/AQ28) -> 0.14272416 | AM28: {=_xll.FDS(C28,"P_DIV_YLD")} -> 1.3611655 | AO28: {=_xll.FDS($C28,"FE_ESTIMATE(SALES,MEAN,ANN_ROLL,+0,NOW,,,'')")} -> 41954 | AP28: {=_xll.FDS($C28,"FE_ESTIMATE(SALES,MEAN,ANN_ROLL,+1,NOW,,,'')")} -> 43921.05 | AQ28: {=_xll.FDS($C28,"FE_ESTIMATE(SALES,MEAN,ANN_ROLL,+2,NOW,,,'')")} -> 46664.74 | AS28: {=_xll.FDS($C28,"FE_ESTIMATE(EBITDA,MEAN,ANN_ROLL,+0,NOW,,,'')")} -> 5957 | AT28: {=_xll.FDS($C28,"FE_ESTIMATE(EBITDA,MEAN,ANN_ROLL,+1,NOW,,,'')")} -> 6269.72 | AU28: {=_xll.FDS($C28,"FE_ESTIMATE(EBITDA,MEAN,ANN_ROLL,+2,NOW,,,'')")} -> 6660.186 | AW28: {=_xll.FDS($C28,"FE_ESTIMATE(EPS,MEAN,ANN_ROLL,+0,NOW,,,'')")} -> 26.34 | AX28: {=_xll.FDS($C28,"FE_ESTIMATE(EPS,MEAN,ANN_ROLL,+1,NOW,,,'')")} -> 28.032558 | AY28: {=_xll.FDS($C28,"FE_ESTIMATE(EPS,MEAN,ANN_ROLL,+2,NOW,,,'')")} -> 30.214338 | BA28: {=_xll.FDS($C28,"FE_ESTIMATE(FCF,MEAN,ANN_ROLL,+0,NOW,,,'')")} -> 3307 | BB28: {=_xll.FDS($C28,"FE_ESTIMATE(FCF,MEAN,ANN_ROLL,+1,NOW,,,'')")} -> 3296.9346 | BC28: {=_xll.FDS($C28,"FE_ESTIMATE(FCF,MEAN,ANN_ROLL,+2,NOW,,,'')")} -> 3523.5466
B29: {=_xll.FDS(C29,"FG_COMPANY_NAME")} -> RTX Corporation | C29: RTX | E29: NC | F29: {=_xll.FDS(C29,"FG_PRICE(NOW)")} -> 201.14 | H29: {=_xll.FDS(C29,"FF_COM_SHS_OUT_EPS_DIL(MON,NOW)")} -> 1356.4 | I29: =F29*H29 -> 272826.3 | J29: {=_xll.FDS(C29,"FF_DEBT(MON,NOW)")} -> 39956 | K29: {=_xll.FDS(C29,"FF_CASH_ST(MON,NOW)")} -> 7435 | L29: =I29+J29-K29 -> 305347.3 | N29: =IF($L29/AP29<0,"NM",$L29/AP29) -> 3.2659131 | O29: =IF($L29/AQ29<0,"NM",$L29/AQ29) -> 3.0578585 | Q29: =IF($L29/AT29<0,"NM",$L29/AT29) -> 19.830572 | R29: =IF($L29/AU29<0,"NM",$L29/AU29) -> 18.189543 | T29: =IF($F29/AX29<0,"NM",$F29/AX29) -> 29.407813 | U29: =IF($F29/AY29<0,"NM",$F29/AY29) -> 26.589626 | W29: =IF(L29/BB29<0,"NM",L29/BB29) -> 35.762779 | X29: =IF(L29/BC29<0,"NM",L29/BC29) -> 30.632241 | Z29: =IF((J29-K29)/AT29<0,"NM",(J29-K29)/AT29) -> 2.1120541 | AA29: =IF((J29-K29)/AU29<0,"NM",(J29-K29)/AU29) -> 1.9372765 | AC29: =AP29/AO29-1 -> 0.055215173 | AD29: =AQ29/AP29-1 -> 0.0680393 | AF29: =AT29/AS29-1 -> 0.12312404 | AG29: =AU29/AT29-1 -> 0.090218243 | AI29: =IF(AS29/AO29<0,"NM",AS29/AO29) -> 0.15473291 | AJ29: =IF(AT29/AP29<0,"NM",AT29/AP29) -> 0.16469082 | AK29: =IF(AU29/AQ29<0,"NM",AU29/AQ29) -> 0.16811079 | AM29: {=_xll.FDS(C29,"P_DIV_YLD")} -> 1.3841535 | AO29: {=_xll.FDS($C29,"FE_ESTIMATE(SALES,MEAN,ANN_ROLL,+0,NOW,,,'')")} -> 88603 | AP29: {=_xll.FDS($C29,"FE_ESTIMATE(SALES,MEAN,ANN_ROLL,+1,NOW,,,'')")} -> 93495.23 | AQ29: {=_xll.FDS($C29,"FE_ESTIMATE(SALES,MEAN,ANN_ROLL,+2,NOW,,,'')")} -> 99856.58 | AS29: {=_xll.FDS($C29,"FE_ESTIMATE(EBITDA,MEAN,ANN_ROLL,+0,NOW,,,'')")} -> 13709.8 | AT29: {=_xll.FDS($C29,"FE_ESTIMATE(EBITDA,MEAN,ANN_ROLL,+1,NOW,,,'')")} -> 15397.806 | AU29: {=_xll.FDS($C29,"FE_ESTIMATE(EBITDA,MEAN,ANN_ROLL,+2,NOW,,,'')")} -> 16786.969 | AW29: {=_xll.FDS($C29,"FE_ESTIMATE(EPS,MEAN,ANN_ROLL,+0,NOW,,,'')")} -> 6.29 | AX29: {=_xll.FDS($C29,"FE_ESTIMATE(EPS,MEAN,ANN_ROLL,+1,NOW,,,'')")} -> 6.839679 | AY29: {=_xll.FDS($C29,"FE_ESTIMATE(EPS,MEAN,ANN_ROLL,+2,NOW,,,'')")} -> 7.5646043 | BA29: {=_xll.FDS($C29,"FE_ESTIMATE(FCF,MEAN,ANN_ROLL,+0,NOW,,,'')")} -> 7940 | BB29: {=_xll.FDS($C29,"FE_ESTIMATE(FCF,MEAN,ANN_ROLL,+1,NOW,,,'')")} -> 8538.131 | BC29: {=_xll.FDS($C29,"FE_ESTIMATE(FCF,MEAN,ANN_ROLL,+2,NOW,,,'')")} -> 9968.167
L30: Median | N30: =MEDIAN(N13:N28) -> 3.9077254 | O30: =MEDIAN(O13:O28) -> 3.5297458 | Q30: =MEDIAN(Q24:Q29) -> 17.66415 | R30: =MEDIAN(R24:R29) -> 16.582951 | T30: =MEDIAN(T24:T29) -> 26.739837 | U30: =MEDIAN(U24:U29) -> 23.923793 | V30: =MEDIAN(V24:V29) -> #NUM! | W30: =MEDIAN(W24:W29) -> 29.749433 | X30: =MEDIAN(X24:X29) -> 28.409473 | Z30: =MEDIAN(Z24:Z29) -> 2.131115 | AA30: =MEDIAN(AA24:AA29) -> 1.9806971 | AB30: =MEDIAN(AB24:AB29) -> #NUM! | AC30: =MEDIAN(AC24:AC29) -> 0.054611438 | AD30: =MEDIAN(AD24:AD29) -> 0.06525399 | AF30: =MEDIAN(AF24:AF29) -> 0.083961782 | AG30: =MEDIAN(AG24:AG29) -> 0.076755332 | AH30: =MEDIAN(AH24:AH29) -> #NUM! | AI30: =MEDIAN(AI24:AI29) -> 0.1337652 | AJ30: =MEDIAN(AJ24:AJ29) -> 0.14298967 | AK30: =MEDIAN(AK24:AK29) -> 0.14197339 | AM30: =MEDIAN(AM24:AM29) -> 1.4267443
B32: {=_xll.FDS(C32,"FG_COMPANY_NAME")} -> Curtiss-Wright Corporation | C32: CW | E32: O | F32: 671.06 | H32: =CW_IS!BM140 -> 37.663 | I32: =F32*H32 -> 25274.133 | J32: =CW_FCF!BQ32 -> 968.632 | K32: =CW_FCF!BQ29 -> 225.427 | L32: =I32+J32-K32 -> 26017.338 | N32: =IF($L32/AP32<0,"NM",$L32/AP32) -> 7.037287 | O32: =IF($L32/AQ32<0,"NM",$L32/AQ32) -> 6.5235532 | Q32: =IF($L32/AT32<0,"NM",$L32/AT32) -> 31.136607 | R32: =IF($L32/AU32<0,"NM",$L32/AU32) -> 28.483826 | T32: =IF($F32/AX32<0,"NM",$F32/AX32) -> 45.80953 | U32: =IF($F32/AY32<0,"NM",$F32/AY32) -> 40.934037 | W32: =IF(L32/BB32<0,"NM",L32/BB32) -> 45.881083 | X32: =IF(L32/BC32<0,"NM",L32/BC32) -> 44.123604 | Z32: =IF((J32-K32)/AT32<0,"NM",(J32-K32)/AT32) -> 0.88944081 | AA32: =IF((J32-K32)/AU32<0,"NM",(J32-K32)/AU32) -> 0.81366212 | AC32: =AP32/AO32-1 -> 0.056797076 | AD32: =AQ32/AP32-1 -> 0.07875062 | AF32: =AT32/AS32-1 -> 0.094091309 | AG32: =AU32/AT32-1 -> 0.093132874 | AI32: =IF(AS32/AO32<0,"NM",AS32/AO32) -> 0.21830919 | AJ32: =IF(AT32/AP32<0,"NM",AT32/AP32) -> 0.22601329 | AK32: =IF(AU32/AQ32<0,"NM",AU32/AQ32) -> 0.22902657 | AM32: {=_xll.FDS(C32,"P_DIV_YLD")} -> 0.15135987 | AO32: {=_xll.FDS($C32,"FE_ESTIMATE(SALES,MEAN,ANN_ROLL,+0,NOW,,,'')")} -> 3498.372 | AP32: {=_xll.FDS($C32,"FE_ESTIMATE(SALES,MEAN,ANN_ROLL,+1,NOW,,,'')")} -> 3697.0693 | AQ32: {=_xll.FDS($C32,"FE_ESTIMATE(SALES,MEAN,ANN_ROLL,+2,NOW,,,'')")} -> 3988.2158 | AS32: {=_xll.FDS($C32,"FE_ESTIMATE(EBITDA,MEAN,ANN_ROLL,+0,NOW,,,'')")} -> 763.72675 | AT32: {=_xll.FDS($C32,"FE_ESTIMATE(EBITDA,MEAN,ANN_ROLL,+1,NOW,,,'')")} -> 835.5868 | AU32: {=_xll.FDS($C32,"FE_ESTIMATE(EBITDA,MEAN,ANN_ROLL,+2,NOW,,,'')")} -> 913.4074 | AW32: {=_xll.FDS($C32,"FE_ESTIMATE(EPS,MEAN,ANN_ROLL,+0,NOW,,,'')")} -> 13.23 | AX32: {=_xll.FDS($C32,"FE_ESTIMATE(EPS,MEAN,ANN_ROLL,+1,NOW,,,'')")} -> 14.648917 | AY32: {=_xll.FDS($C32,"FE_ESTIMATE(EPS,MEAN,ANN_ROLL,+2,NOW,,,'')")} -> 16.393692 | BA32: {=_xll.FDS($C32,"FE_ESTIMATE(FCF,MEAN,ANN_ROLL,+0,NOW,,,'')")} -> 553.71 | BB32: {=_xll.FDS($C32,"FE_ESTIMATE(FCF,MEAN,ANN_ROLL,+1,NOW,,,'')")} -> 567.06024 | BC32: {=_xll.FDS($C32,"FE_ESTIMATE(FCF,MEAN,ANN_ROLL,+2,NOW,,,'')")} -> 589.6467
A34: Indices
B35: S&P 500 | C35: SPX | T35: {=_xll.FDS("SPX","FG_VALUATION_IDX(0,,,""PE_CY1"")")} -> 25.56711 | U35: {=_xll.FDS("SPX","FG_VALUATION_IDX(0,,,""PE_CY2"")")} -> 23.490593
A37: Note: O=Outperform, M=Market Perform, U= Underperform, NC = Not covered
A38: FactSet consensus estimates used for all values
A39: Source: FactSet

Sheet BlueMatrix
C1: BlueMatrix Excel Toolkit Input Sheet | AQ1: Data Validation Cell Values
AQ3: Rating | AR3: Time Series Qualifier | AS3: Month
A4: SECTION 1 - COMPANY STATISTICS | AQ4: Outperform
AQ5: Market Perform
B6: Enter Company Symbol >> | C6: CW | D6: << Security'sPricing Symbol in BlueMatrix | J6: *Must be logged in to Creator to access link. | AQ6: Underperform | AR6: NULL:FISCAL | AS6: January
