Workbook
Name blank: #REF!
Name blank: #REF!
Name blank: #REF!
Name Current_Q: #REF!
Name Current_Q: #REF!
Name Current_Q: #REF!
Name export: #REF!
Name export: #REF!
Name export: #REF!
Name FY_92: #REF!
Name FY_92: #REF!
Name FY_92: #REF!
Name FY_93: #REF!
Name FY_93: #REF!
Name FY_93: #REF!
Name FY_94: #REF!
Name FY_94: #REF!
Name FY_94: #REF!
Name N_A: #REF!
Name N_A: #REF!
Name N_M: #REF!
Name N_M: #REF!
Name Next_Actual_Period_Range: '[16]Income Statement'!$D$3:$BE$6
Name NM_T: #REF!
Name NM_T: #REF!
Name NM_T: #REF!
Name Prior_Q: #REF!
Name Prior_Q: #REF!
Name Prior_Q: #REF!
Name Same_Q_Last_Yr: #REF!
Name Same_Q_Last_Yr: #REF!
Name Same_Q_Last_Yr: #REF!
Name source: #REF!
Name source: #REF!
Name source: #REF!
Name SPR01A_18: #REF!
Name SPR01C_18: #REF!
Name test: #REF!
Name WIZARD_3YRATCF: #REF!
Name WIZARD_3YRATCF: #REF!
Name WIZARD_3YRATCF: #REF!
Name WIZARD_3YREBITDA: #REF!
Name WIZARD_3YREBITDA: #REF!
Name WIZARD_3YREBITDA: #REF!
Name WIZARD_3YRSECGROWTH: #REF!
Name WIZARD_3YRSECGROWTH: #REF!
Name WIZARD_3YRSECGROWTH: #REF!
Name WIZARD_AVGTRADINGVOLUME: #REF!
Name WIZARD_AVGTRADINGVOLUME: #REF!
Name WIZARD_BKVALSHR: #REF!
Name WIZARD_BKVALSHR: #REF!
Name WIZARD_BURNRATE: #REF!
Name WIZARD_BURNRATE: #REF!
Name WIZARD_CASH: #REF!
Name WIZARD_CASH: #REF!
Name WIZARD_DIVYIELD: #REF!
Name WIZARD_DIVYIELD: #REF!
Name WIZARD_EARNINGS: #REF!
Name WIZARD_EARNINGS: #REF!
Name WIZARD_EBITDABYSHROO: #REF!

Sheet __FDSCACHE__
B1: This sheet contains FactSet XML data for use with this workbook's =FDS codes. Modifying the worksheet's contents may damage the workbook's =FDS functionality.

Sheet Comparison
B2: ='Income Statement'!B2 -> Five9, Inc (Nasdaq: FIVN)
B4: Variance Analysis | D4: 4Q24 | E4: =K4 -> 4Q25 | F4: Y/Y Chg. | G4: 3Q25 | H4: =K4 -> 4Q25 | I4: Q/Q Chg. | J4: =K4&"E" -> 4Q25E | K4: 4Q25 | L4: % Delta | O4: 1Q Cons. | P4: 2Q Guide | Q4: 2Q Cons. | R4: FY Guide Prev | S4: FY Guide New | T4: FY Cons
B5: Total Revenue | D5: ='Income Statement'!BP28 -> 278660 | E5: =K5 -> 300282 | F5: =E5/D5-1 -> 0.077592765 | G5: ='Income Statement'!BT28 -> 285832 | H5: =K5 -> 300282 | I5: =H5/G5-1 -> 0.050554172 | J5: 298082.6 | K5: ='Income Statement'!BU28 -> 300282 | L5: =K5/J5-1 -> 0.007378485 | O5: 170900 | P5: =(179000+180000)/2 -> 179500 | Q5: 174100 | R5: 756000 | S5: =(770000+773000)/2 -> 771500 | T5: 756800 | V5: Initial guide for 24% Y/Y growth
C6: Total Cost of Revenue | D6: ='Income Statement'!BP35 -> 111603 | E6: =K6 -> 123898 | F6: =E6/D6-1 -> 0.11016729 | G6: ='Income Statement'!BT35 -> 118234 | H6: =K6 -> 123898 | I6: =H6/G6-1 -> 0.047905002 | J6: 119233.04 | K6: ='Income Statement'!BU35 -> 123898 | L6: =K6/J6-1 -> 0.039124719
B7: Gross Profit | D7: =D5-D6 -> 167057 | E7: =K7 -> 176384 | F7: =E7/D7-1 -> 0.055831243 | G7: =G5-G6 -> 167598 | H7: =K7 -> 176384 | I7: =H7/G7-1 -> 0.05242306 | J7: 178849.56 | K7: =K5-K6 -> 176384 | L7: =K7/J7-1 -> -0.013785671 | O7: 102000 | Q7: 103300 | T7: 453300
C8: Gross Margins | D8: =D7/D5 -> 0.59950118 | E8: =K8 -> 0.58739452 | G8: =G7/G5 -> 0.58635142 | H8: =K8 -> 0.58739452 | J8: 0.6 | K8: =K7/K5 -> 0.58739452 | N8: =+K8-J8 -> -0.012605484 | O8: =IF(AND(ISNUMBER(O$5), ISNUMBER(O7)), O7/O$5, "- ") -> 0.59684026 | P8: =IF(AND(ISNUMBER(P$5), ISNUMBER(P7)), P7/P$5, "- ") -> - | Q8: =IF(AND(ISNUMBER(Q$5), ISNUMBER(Q7)), Q7/Q$5, "- ") -> 0.59333716 | R8: =IF(AND(ISNUMBER(R$5), ISNUMBER(R7)), R7/R$5, "- ") -> - | S8: =IF(AND(ISNUMBER(S$5), ISNUMBER(S7)), S7/S$5, "- ") -> - | T8: =IF(AND(ISNUMBER(T$5), ISNUMBER(T7)), T7/T$5, "- ") -> 0.59896934
B10: Operating Expenses
C11: R&D | D11: ='Income Statement'!BP41 -> 33221 | E11: =K11 -> 27217 | F11: =E11/D11-1 -> -0.18072906 | G11: ='Income Statement'!BT41 -> 27127 | H11: =K11 -> 27217 | I11: =H11/G11-1 -> 0.0033177277 | J11: 32789.086 | K11: ='Income Statement'!BU41 -> 27217 | L11: =K11/J11-1 -> -0.16993722
C12: S&M | D12: ='Income Statement'!BP43 -> 60261 | E12: =K12 -> 67757 | F12: =E12/D12-1 -> 0.12439223 | G12: ='Income Statement'!BT43 -> 63074 | H12: =K12 -> 67757 | I12: =H12/G12-1 -> 0.074246124 | J12: 67068.585 | K12: ='Income Statement'!BU43 -> 67757 | L12: =K12/J12-1 -> 0.010264337
C13: G&A | D13: ='Income Statement'!BP45 -> 24056 | E13: =K13 -> 19795 | F13: =E13/D13-1 -> -0.17712837 | G13: ='Income Statement'!BT45 -> 20285 | H13: =K13 -> 19795 | I13: =H13/G13-1 -> -0.02415578 | J13: 21760.03 | K13: ='Income Statement'!BU45 -> 19795 | L13: =K13/J13-1 -> -0.090304561
B14: Total Operating Expenses | D14: =SUM(D11:D13) -> 117538 | E14: =K14 -> 114769 | F14: =E14/D14-1 -> -0.023558339 | G14: =SUM(G11:G13) -> 110486 | H14: =K14 -> 114769 | I14: =H14/G14-1 -> 0.038765092 | J14: 121617.7 | K14: =SUM(K11:K13) -> 114769 | L14: =K14/J14-1 -> -0.056313362 | N14: =+K14-J14 -> -6848.7016 | O14: =K14-J14 -> -6848.7016
B16: Non-GAAP Operating Income (Loss) | D16: =D7-D14 -> 49519 | E16: =K16 -> 61615 | F16: =E16/D16-1 -> 0.24426988 | G16: =G7-G14 -> 57112 | H16: =K16 -> 61615 | I16: =H16/G16-1 -> 0.078845076 | J16: 57231.86 | K16: =K7-K14 -> 61615 | L16: =K16/J16-1 -> 0.076585672 | O16: 10800 | Q16: 11900 | T16: 86000
C17: Non-GAAP Operating Margins | D17: =D16/D5 -> 0.17770401 | E17: =K17 -> 0.20519045 | G17: =G16/G5 -> 0.19980968 | H17: =K17 -> 0.20519045 | J17: 0.192 | K17: =K16/K5 -> 0.20519045 | O17: =IF(AND(ISNUMBER(O$5), ISNUMBER(O16)), O16/O$5, "- ") -> 0.063194851 | P17: =IF(AND(ISNUMBER(P$5), ISNUMBER(P16)), P16/P$5, "- ") -> - | Q17: =IF(AND(ISNUMBER(Q$5), ISNUMBER(Q16)), Q16/Q$5, "- ") -> 0.068351522 | R17: =IF(AND(ISNUMBER(R$5), ISNUMBER(R16)), R16/R$5, "- ") -> - | S17: =IF(AND(ISNUMBER(S$5), ISNUMBER(S16)), S16/S$5, "- ") -> - | T17: =IF(AND(ISNUMBER(T$5), ISNUMBER(T16)), T16/T$5, "- ") -> 0.11363636
B19: GAAP & Non-cash charges | D19: ='Income Statement'!BP64 -> 45339 | E19: =K19 -> 41819 | F19: =E19/D19-1 -> -0.077637354 | G19: ='Income Statement'!BT64 -> 41069 | H19: =K19 -> 41819 | I19: =H19/G19-1 -> 0.018261949 | J19: 45600 | K19: ='Income Statement'!BU64 -> 41819 | L19: =K19/J19-1 -> -0.082916667
B21: GAAP Operating Income | D21: =D16-D19 -> 4180 | E21: =K21 -> 19796 | F21: =E21/D21-1 -> 3.7358852 | G21: =G16-G19 -> 16043 | H21: =K21 -> 19796 | I21: =H21/G21-1 -> 0.2339338 | J21: 11631.86 | K21: =K16-K19 -> 19796 | L21: =K21/J21-1 -> 0.70187749
C22: GAAP Operating Margins | D22: =D21/D5 -> 0.015000359 | E22: =K22 -> 0.065924697 | G22: =G21/G5 -> 0.056127376 | H22: =K22 -> 0.065924697 | J22: 0.039022269 | K22: =K21/K5 -> 0.065924697 | O22: =IF(AND(ISNUMBER(O$5), ISNUMBER(O21)), O21/O$5, "- ") -> - | P22: =IF(AND(ISNUMBER(P$5), ISNUMBER(P21)), P21/P$5, "- ") -> - | Q22: =IF(AND(ISNUMBER(Q$5), ISNUMBER(Q21)), Q21/Q$5, "- ") -> - | R22: =IF(AND(ISNUMBER(R$5), ISNUMBER(R21)), R21/R$5, "- ") -> - | S22: =IF(AND(ISNUMBER(S$5), ISNUMBER(S21)), S21/S$5, "- ") -> - | T22: =IF(AND(ISNUMBER(T$5), ISNUMBER(T21)), T21/T$5, "- ") -> -
B24: Total GAAP Other Income | D24: ='Income Statement'!BP74 -> 6971 | E24: =K24 -> 3234 | G24: ='Income Statement'!BT74 -> 2573 | H24: =K24 -> 3234 | J24: 2400 | K24: ='Income Statement'!BU74 -> 3234
B25: Total Non GAAP Other Income | D25: ='Income Statement'!BP79 -> 10956 | E25: =K25 -> 4138 | G25: ='Income Statement'!BT79 -> 3611 | H25: =K25 -> 4138 | J25: 3600 | K25: ='Income Statement'!BU79 -> 4138
B27: Non-GAAP Income before Taxes | D27: =D16+D25 -> 60475 | E27: =K27 -> 65753 | F27: =E27/D27-1 -> 0.087275734 | G27: =G16+G25 -> 60723 | H27: =K27 -> 65753 | I27: =H27/G27-1 -> 0.08283517 | J27: 60831.86 | K27: =K16+K25 -> 65753 | L27: =K27/J27-1 -> 0.080897419
C28: Income Tax | D28: ='Income Statement'!BP87 -> 224 | E28: =K28 -> 3317 | G28: ='Income Statement'!BT87 -> 119 | H28: =K28 -> 3317 | J28: 1000 | K28: ='Income Statement'!BU87 -> 3317 | P28: 500 | S28: 1900
B29: Non-GAAP Net Income | D29: =D27-D28 -> 60251 | E29: =K29 -> 62436 | F29: =E29/D29-1 -> 0.036264958 | G29: =G27-G28 -> 60604 | H29: =K29 -> 62436 | I29: =H29/G29-1 -> 0.030229028 | J29: 59831.86 | K29: =K27-K28 -> 62436 | L29: =K29/J29-1 -> 0.04352431
B31: GAAP Income before Taxes | D31: =D21+D24 -> 11151 | E31: =K31 -> 23030 | F31: =E31/D31-1 -> 1.0652856 | G31: =G21+G24 -> 18616 | H31: =K31 -> 23030 | I31: =H31/G31-1 -> 0.23710786 | J31: 14031.86 | K31: =K21+K24 -> 23030 | L31: =K31/J31-1 -> 0.641265
C32: Income Tax | D32: ='Income Statement'!BP93 -> -426 | E32: =K32 -> 3317 | G32: ='Income Statement'!BT93 -> 643 | H32: =K32 -> 3317 | J32: 1000 | K32: ='Income Statement'!BU93 -> 3317
B33: GAAP Net Income | D33: =D31-D32 -> 11577 | E33: =K33 -> 19713 | F33: =E33/D33-1 -> 0.70277274 | G33: =G31-G32 -> 17973 | H33: =K33 -> 19713 | I33: =H33/G33-1 -> 0.096811884 | J33: 13031.86 | K33: =K31-K32 -> 19713 | L33: =K33/J33-1 -> 0.51267744
B35: Non-GAAP EPS | D35: =D29/D39 -> 0.79278675 | E35: =K35 -> 0.80433886 | F35: =E35/D35-1 -> 0.014571532 | G35: =G29/G39 -> 0.77814157 | H35: =K35 -> 0.80433886 | I35: =H35/G35-1 -> 0.033666487 | J35: 0.76332699 | K35: =K29/K39 -> 0.80433886 | L35: =K35/J35-1 -> 0.05372779 | O35: 0.13 | P35: =(0.17+0.19)/2 -> 0.18 | Q35: 0.15 | R35: 1.14 | S35: =(1.22+1.24)/2 -> 1.23 | T35: 1.12
B36: GAAP EPS | D36: =D33/D38 -> 0.15348005 | E36: =K36 -> 0.25433176 | G36: =G33/G38 -> 0.23182592 | H36: =K36 -> 0.25433176 | J36: 0.16701517 | K36: =K33/K38 -> 0.25433176
B38: Basic Shares Outstanding | D38: ='Income Statement'!BP103 -> 75430 | E38: =K38 -> 77509 | G38: ='Income Statement'!BT103 -> 77528 | H38: =K38 -> 77509 | J38: 78028 | K38: ='Income Statement'!BU103 -> 77509
B39: Diluted Shares Outstanding | D39: ='Income Statement'!BP104 -> 75999 | E39: =K39 -> 77624 | G39: ='Income Statement'!BT104 -> 77883 | H39: =K39 -> 77624 | J39: 78383 | K39: ='Income Statement'!BU104 -> 77624 | P39: 72000 | S39: 73000
B42: Source: Company reports and Needham & Co estimates | L42: Capex | P42: =(10000+11000)/2 -> 10500 | S42: =(69000+71000)/2 -> 70000

Sheet G CHANGE
C5: FY26 Guidance | D5: FY26 Street Expectations | E5: Initial FY26 Guide | F5: Delta | G5: 3Q25 Guide | H5: 3Q25 Results | I5: 3Q25 Beat | J5: Rest of Year Raise / (Reduce)
C6: Revenue ($mm) | D6: 1254 | E6: 1254 | F6: =E6-D6 -> 0 | G6: 284.5 | H6: =Comparison!K5/1000 -> 300.282 | I6: =H6-G6 -> 15.782 | J6: =F6-I6 -> -15.782
C7: Growth | D7: =D6/('Income Statement'!BV28/1000)-1 -> 0.091300231 | E7: =E6/('Income Statement'!BV28/1000)-1 -> 0.091300231
C8: Non-GAAP EPS | D8: 3.18 | E8: 3.18 | F8: =E8-D8 -> 0 | G8: 0.73 | H8: =Comparison!K35 -> 0.80433886 | I8: =H8-G8 -> 0.074338864 | J8: =F8-I8 -> -0.074338864

Sheet Income Statement
B2: Five9, Inc (Nasdaq: FIVN)
B4: Income Statement | D4: 2011 | E4: 1Q12 | F4: 2Q12 | G4: 3Q12 | H4: 4Q12 | I4: 2012 | J4: 1Q13 | K4: 2Q13 | L4: 3Q13 | M4: 4Q13 | N4: 2013 | O4: 1Q14 | P4: 2Q14 | Q4: 3Q14 | R4: 4Q14 | S4: 2014 | T4: 1Q15 | U4: 2Q15 | V4: 3Q15 | W4: 4Q15 | X4: 2015 | Y4: 1Q16 | Z4: 2Q16 | AA4: 3Q16 | AB4: 4Q16 | AC4: 2016 | AD4: 1Q17 | AE4: 2Q17 | AF4: 3Q17 | AG4: 4Q17 | AH4: 2017 | AI4: 1Q18 | AJ4: 2Q18 | AK4: 3Q18 | AL4: 4Q18 | AM4: 2018 | AN4: 1Q19 | AO4: 2Q19 | AP4: 3Q19 | AQ4: 4Q19 | AR4: 2019 | AS4: 1Q20 | AT4: 2Q20 | AU4: 3Q20 | AV4: 4Q20 | AW4: 2020 | AX4: 1Q21 | AY4: 2Q21 | AZ4: 3Q21 | BA4: 4Q21 | BB4: 2021 | BC4: 1Q22 | BD4: 2Q22 | BE4: 3Q22 | BF4: 4Q22 | BG4: 2022 | BH4: 1Q23 | BI4: 2Q23 | BJ4: 3Q23 | BK4: 4Q23 | BL4: 2023 | BM4: 1Q24 | BN4: 2Q24 | BO4: 3Q24 | BP4: 4Q24 | BQ4: 2024 | BR4: 1Q25 | BS4: 2Q25 | BT4: 3Q25 | BU4: 4Q25 | BV4: 2025 | BW4: 1Q26E | BX4: 2Q26E | BY4: 3Q26E | BZ4: 4Q26E | CA4: 2026E
B5: Total Revenues | D5: 43188 | E5: 14321.11 | F5: 15027.74 | G5: 16202.043 | H5: 18271.429 | I5: =SUM(E5:H5) -> 63822.321 | J5: 19115.125 | K5: 20282.901 | L5: 21091.22 | M5: 23642.754 | N5: =SUM(J5:M5) -> 84132 | O5: 24274 | P5: 24685 | Q5: 25869 | R5: 28274 | S5: =SUM(O5:R5) -> 103102 | T5: 30274 | U5: 30274 | V5: 32287 | W5: 36033 | X5: =SUM(T5:W5) -> 128868 | Y5: 38015 | Z5: 38886 | AA5: 40982 | AB5: 44207 | AC5: =SUM(Y5:AB5) -> 162090 | AD5: 47014 | AE5: 47727 | AF5: 50081 | AG5: 55403 | AH5: =SUM(AD5:AG5) -> 200225 | AI5: 58905 | AJ5: 61120 | AK5: 65304 | AL5: 72335 | AM5: =SUM(AI5:AL5) -> 257664 | AN5: 74538 | AO5: =77436 -> 77436 | AP5: 83769 | AQ5: =92263 -> 92263 | AR5: =SUM(AN5:AQ5) -> 328006 | AS5: 95088 | AT5: 99792 | AU5: =112143 -> 112143 | AV5: =127885 -> 127885 | AW5: =SUM(AS5:AV5) -> 434908 | AX5: 137882 | AY5: 143782 | AZ5: 154328 | BA5: 173599 | BB5: =SUM(AX5:BA5) -> 609591 | BC5: 182777 | BD5: 189382 | BE5: 198342 | BF5: 208345 | BG5: =SUM(BC5:BF5) -> 778846 | BH5: 218439 | BI5: 222882 | BJ5: 230105 | BK5: 239062 | BL5: =SUM(BH5:BK5) -> 910488 | BM5: 247010 | BN5: 252086 | BO5: 264182 | BP5: 278660 | BQ5: =SUM(BM5:BP5) -> 1041938 | BR5: 279705 | BS5: 283269 | BT5: 285832 | BU5: 300282 | BV5: =SUM(BR5:BU5) -> 1149088 | BW5: =BW9+BW24 -> 299228.41 | BX5: =BX9+BX24 -> 306327.1 | BY5: =BY9+BY24 -> 313729.2 | BZ5: =BZ9+BZ24 -> 337396.86 | CA5: =SUM(BW5:BZ5) -> 1256681.6
C6: Y/Y Growth | I6: =I5/D5-1 -> 0.47777905 | J6: =J5/E5-1 -> 0.33475164 | K6: =K5/F5-1 -> 0.34969741 | L6: =L5/G5-1 -> 0.30176301 | M6: =M5/H5-1 -> 0.29397397 | N6: =N5/I5-1 -> 0.31822218 | O6: =O5/J5-1 -> 0.26988446 | P6: =P5/K5-1 -> 0.21703497 | ... CA6: =CA5/BV5-1 -> 0.093633877
C7: Q/Q Growth | F7: =F5/E5-1 -> 0.049341833 | G7: =G5/F5-1 -> 0.078142386 | H7: =H5/G5-1 -> 0.12772378 | J7: =J5/H5-1 -> 0.046175674 | K7: =K5/J5-1 -> 0.06109175 | L7: =L5/K5-1 -> 0.039852237 | M7: =M5/L5-1 -> 0.1209761 | O7: =O5/M5-1 -> 0.026699351 | P7: =P5/O5-1 -> 0.016931696 | Q7: =Q5/P5-1 -> 0.047964351 | R7: =R5/Q5-1 -> 0.092968418 | T7: =T5/R5-1 -> 0.070736366 | U7: =U5/T5-1 -> 0 | V7: =V5/U5-1 -> 0.0664927 | W7: =W5/V5-1 -> 0.11602193 | Y7: =Y5/W5-1 -> 0.055005134 | Z7: =Z5/Y5-1 -> 0.022912008 | AA7: =AA5/Z5-1 -> 0.053901147 | AB7: =AB5/AA5-1 -> 0.078693085 | AD7: =AD5/AB5-1 -> 0.063496731 | AE7: =AE5/AD5-1 -> 0.015165695 | AF7: =AF5/AE5-1 -> 0.049322187 | AG7: =AG5/AF5-1 -> 0.10626785 | AI7: =AI5/AG5-1 -> 0.063209573 | AJ7: =AJ5/AI5-1 -> 0.03760292 | AK7: =AK5/AJ5-1 -> 0.068455497 | AL7: =AL5/AK5-1 -> 0.10766569 | AN7: =AN5/AL5-1 -> 0.030455519 | AO7: =AO5/AN5-1 -> 0.038879498 | AP7: =AP5/AO5-1 -> 0.081783667 | AQ7: =AQ5/AP5-1 -> 0.10139789 | AS7: =AS5/AQ5-1 -> 0.030618991 | AT7: =AT5/AS5-1 -> 0.049469965 | AU7: =AU5/AT5-1 -> 0.12376744 | AV7: =AV5/AU5-1 -> 0.14037434 | AX7: =AX5/AV5-1 -> 0.078171795 | AY7: =AY5/AX5-1 -> 0.042790212 | AZ7: =AZ5/AY5-1 -> 0.073347151 | BA7: =BA5/AZ5-1 -> 0.12487041 | BC7: =BC5/BA5-1 -> 0.052868968 | BD7: =BD5/BC5-1 -> 0.036136932 | BE7: =BE5/BD5-1 -> 0.047311783 | BF7: =BF5/BE5-1 -> 0.05043309 | BH7: =BH5/BF5-1 -> 0.048448487 | BI7: =BI5/BH5-1 -> 0.020339774 | BJ7: =BJ5/BI5-1 -> 0.032407283 | BK7: =BK5/BJ5-1 -> 0.038925708 | BM7: =BM5/BK5-1 -> 0.033246605 | BN7: =BN5/BM5-1 -> 0.020549775 | BO7: =BO5/BN5-1 -> 0.047983625 | BP7: =BP5/BO5-1 -> 0.054803128 | BR7: =BR5/BP5-1 -> 0.0037500897 | BS7: =BS5/BR5-1 -> 0.012741996 | BT7: =BT5/BS5-1 -> 0.0090479368 | BU7: =BU5/BT5-1 -> 0.050554172 | BW7: =BW5/BU5-1 -> -0.0035086718 | BX7: =BX5/BW5-1 -> 0.023723308 | BY7: =BY5/BX5-1 -> 0.024164061 | BZ7: =BZ5/BY5-1 -> 0.075439748
B9: Recurring Revenue | T9: =T10*T5 -> 29365.78 | U9: =U10*U5 -> 29063.04 | V9: =V10*V5 -> 30995.52 | W9: =W10*W5 -> 34591.68 | Y9: =Y10*Y5 -> 36114.25 | Z9: =Z10*Z5 -> 36552.84 | AA9: =AA10*AA5 -> 39342.72 | AB9: =AB10*AB5 -> 41996.65 | AD9: =AD10*AD5 -> 44193.16 | AE9: =AE10*AE5 -> 44863.38 | AF9: =AF10*AF5 -> 46575.33 | AG9: =AG10*AG5 -> 52632.85 | AH9: =SUM(AD9:AG9) -> 188264.72 | AI9: =AI10*AI5 -> 54192.6 | AJ9: =AJ10*AJ5 -> 56841.6 | AK9: =AK10*AK5 -> 60732.72 | AL9: =AL10*AL5 -> 67271.55 | AM9: =SUM(AI9:AL9) -> 239038.47 | AN9: =AN10*AN5 -> 69320.34 | AO9: =AO10*AO5 -> 71241.12 | AP9: =AP10*AP5 -> 76229.79 | AQ9: =AQ10*AQ5 -> 84881.96 | AR9: =SUM(AN9:AQ9) -> 301673.21 | AS9: =AS10*AS5 -> 86530.08 | AT9: =AT10*AT5 -> 91808.64 | AU9: =AU10*AU5 -> 104292.99 | AV9: =AV10*AV5 -> 118933.05 | AW9: =SUM(AS9:AV9) -> 401564.76 | AX9: =AX10*AX5 -> 126851.44 | AY9: =AY10*AY5 -> 132279.44 | AZ9: =AZ10*AZ5 -> 141981.76 | BA9: =BA10*BA5 -> 161447.07 | BB9: =SUM(AX9:BA9) -> 562559.71 | BC9: =BC10*BC5 -> 166327.07 | BD9: =BD10*BD5 -> 172337.62 | BE9: =BE10*BE5 -> 180491.22 | BF9: =BF10*BF5 -> 191677.4 | BG9: =SUM(BC9:BF9) -> 710833.31 | BH9: =BH10*BH5 -> 200963.88 | BI9: =BI10*BI5 -> 202822.62 | BJ9: =BJ10*BJ5 -> 211696.6 | BK9: =BK10*BK5 -> 219937.04 | BL9: =SUM(BH9:BK9) -> 835420.14 | BM9: =BM10*BM5 -> 229719.3 | BN9: =BN10*BN5 -> 231919.12 | BO9: =+BO14+BO19 -> 245689.26 | BP9: =+BP14+BP19 -> 259153.8 | BQ9: =SUM(BM9:BP9) -> 966481.48 | BR9: =+BR14+BR19 -> 260125.65 | BS9: =+BS14+BS19 -> 263440.17 | BT9: =+BT14+BT19 -> 265823.76 | BU9: =+BU14+BU19 -> 279262.26 | BV9: =SUM(BR9:BU9) -> 1068651.8 | BW9: =+BW14+BW19 -> 278865.89 | BX9: =+BX14+BX19 -> 285705.11 | BY9: =+BY14+BY19 -> 292920.63 | BZ9: =+BZ14+BZ19 -> 315536.33 | CA9: =SUM(BW9:BZ9) -> 1173028
C10: % of Revenue | T10: 0.97 | U10: 0.96 | V10: 0.96 | W10: 0.96 | Y10: 0.95 | Z10: 0.94 | AA10: 0.96 | AB10: 0.95 | AC10: 0.95 | AD10: 0.94 | AE10: 0.94 | AF10: 0.93 | AG10: 0.95 | AH10: 0.93 | AI10: 0.92 | AJ10: 0.93 | AK10: 0.93 | AL10: 0.93 | AM10: 0.93 | AN10: 0.93 | AO10: 0.92 | AP10: 0.91 | AQ10: 0.92 | AR10: 0.92 | AS10: 0.91 | AT10: 0.92 | AU10: 0.93 | AV10: 0.93 | AX10: 0.92 | AY10: 0.92 | AZ10: 0.92 | BA10: 0.93 | BC10: 0.91 | BD10: 0.91 | BE10: 0.91 | BF10: 0.92 | BH10: 0.92 | BI10: 0.91 | BJ10: 0.92 | BK10: 0.92 | BM10: 0.93 | BN10: 0.92 | BO10: =+BO15+BO20 -> 0.93 | BP10: =+BP15+BP20 -> 0.93 | BR10: =BR9/BR5 -> 0.93 | BS10: =BS9/BS5 -> 0.93 | BT10: =BT9/BT5 -> 0.93 | BU10: =BU9/BU5 -> 0.93 | BW10: =BW9/BW5 -> 0.9319499 | BX10: =BX9/BX5 -> 0.93267986 | BY10: =BY9/BY5 -> 0.93367347 | BZ10: =BZ9/BZ5 -> 0.93520826
C11: Y/Y Growth | T11: =T9/O9-1 -> #DIV/0! | U11: =U9/P9-1 -> #DIV/0! | V11: =V9/Q9-1 -> #DIV/0! | W11: =W9/R9-1 -> #DIV/0! | Y11: =Y9/T9-1 -> 0.22980728 | Z11: =Z9/U9-1 -> 0.25770876 | AA11: =AA9/V9-1 -> 0.26930343 | AB11: =AB9/W9-1 -> 0.21406795 | AD11: =AD9/Y9-1 -> 0.22370422 | AE11: =AE9/Z9-1 -> 0.22735689 | AF11: =AF9/AA9-1 -> 0.18383604 | AG11: =AG9/AB9-1 -> 0.25326306 | AI11: =AI9/AD9-1 -> 0.22626669 | AJ11: =AJ9/AE9-1 -> 0.26699326 | AK11: =AK9/AF9-1 -> 0.30396757 | AL11: =AL9/AG9-1 -> 0.27812858 | AN11: =AN9/AI9-1 -> 0.27914771 | AO11: =AO9/AJ9-1 -> 0.25332714 | AP11: =AP9/AK9-1 -> 0.25516838 | AQ11: =AQ9/AL9-1 -> 0.26178095 | AR11: =AR9/AM9-1 -> 0.26202787 | AS11: =AS9/AN9-1 -> 0.24826393 | AT11: =AT9/AO9-1 -> 0.28870293 | AU11: =AU9/AP9-1 -> 0.36813954 | ... CA11: =CA9/BV9-1 -> 0.097670835
C12: Q/Q Growth | T12: =T9/R9-1 -> #DIV/0! | U12: =U9/T9-1 -> -0.010309278 | V12: =V9/U9-1 -> 0.0664927 | W12: =W9/V9-1 -> 0.11602193 | Y12: =Y9/W9-1 -> 0.044015497 | Z12: =Z9/Y9-1 -> 0.012144514 | AA12: =AA9/Z9-1 -> 0.076324576 | AB12: =AB9/AA9-1 -> 0.067456698 | AD12: =AD9/AB9-1 -> 0.052302029 | AE12: =AE9/AD9-1 -> 0.015165695 | AF12: =AF9/AE9-1 -> 0.038159185 | AG12: =AG9/AF9-1 -> 0.13005855 | AI12: =AI9/AG9-1 -> 0.029634534 | AJ12: =AJ9/AI9-1 -> 0.048881213 | AK12: =AK9/AJ9-1 -> 0.068455497 | AL12: =AL9/AK9-1 -> 0.10766569 | AN12: =AN9/AL9-1 -> 0.030455519 | AO12: =AO9/AN9-1 -> 0.02770875 | AP12: =AP9/AO9-1 -> 0.070025148 | AQ12: =AQ9/AP9-1 -> 0.11350117 | AS12: =AS9/AQ9-1 -> 0.019416611 | AT12: =AT9/AS9-1 -> 0.061002602 | AU12: =AU9/AT9-1 -> 0.1359823 | AV12: =AV9/AU9-1 -> 0.14037434 | AX12: =AX9/AV9-1 -> 0.06657855 | AY12: =AY9/AX9-1 -> 0.042790212 | AZ12: =AZ9/AY9-1 -> 0.073347151 | BA12: =BA9/AZ9-1 -> 0.13709726 | BC12: =BC9/BA9-1 -> 0.030226625 | BD12: =BD9/BC9-1 -> 0.036136932 | BE12: =BE9/BD9-1 -> 0.047311783 | BF12: =BF9/BE9-1 -> 0.061976311 | BH12: =BH9/BF9-1 -> 0.048448487 | BI12: =BI9/BH9-1 -> 0.0092491248 | BJ12: =BJ9/BI9-1 -> 0.043752418 | BK12: =BK9/BJ9-1 -> 0.038925708 | BM12: =BM9/BK9-1 -> 0.044477547 | BN12: =BN9/BL9-1 -> -0.72239223 | BO12: =BO9/BN9-1 -> 0.059374751 | BP12: =BP9/BO9-1 -> 0.054803128 | BR12: =BR9/BP9-1 -> 0.0037500897 | BS12: =BS9/BR9-1 -> 0.012741996 | BT12: =BT9/BS9-1 -> 0.0090479368 | BU12: =BU9/BT9-1 -> 0.050554172 | BW12: =BW9/BU9-1 -> -0.0014193647 | BX12: =BX9/BW9-1 -> 0.024525153 | BY12: =BY9/BX9-1 -> 0.025255131 | BZ12: =BZ9/BY9-1 -> 0.077207576
C14: Subscription Revenue | BM14: =((BR14)/(1.14)) -> 196284.21 | BN14: =+BS14/1.16 -> 197799.91 | BO14: =BO15*BO5 -> 211345.6 | BP14: =BP15*BP5 -> 220141.4 | BQ14: =SUM(BM14:BP14) -> 825571.12 | BR14: =BR15*BR5 -> 223764 | BS14: =BS15*BS5 -> 229447.89 | BT14: =BT15*BT5 -> 231523.92 | BU14: =BU15*BU5 -> 246231.24 | BV14: =SUM(BR14:BU14) -> 930967.05 | BW14: =BR14*(1+BW16) -> 246140.4 | BX14: =BS14*(1+BX16) -> 252392.68 | BY14: =BT14*(1+BY16) -> 259306.79 | BZ14: =BU14*(1+BZ16) -> 283165.93 | CA14: =SUM(BW14:BZ14) -> 1041005.8
C15: % of Revenue | BO15: 0.8 | BP15: 0.79 | BR15: 0.8 | BS15: 0.81 | BT15: 0.81 | BU15: 0.82 | BW15: =BW14/BW5 -> 0.82258366 | BX15: =BX14/BX5 -> 0.82393194 | BY15: =BY14/BY5 -> 0.82653061 | BZ15: =BZ14/BZ5 -> 0.83926664
C16: Y/Y Growth | BR16: =+BR14/BM14-1 -> 0.14 | BS16: =+BS14/BN14-1 -> 0.16 | BT16: =+BT14/BO14-1 -> 0.095475468 | BU16: =+BU14/BP14-1 -> 0.11851401 | BW16: 0.1 | BX16: 0.1 | BY16: 0.12 | BZ16: 0.15 | CA16: =CA14/BV14-1 -> 0.11819832
C17: Q/Q Growth | BR17: =BR14/BP14-1 -> 0.016455787 | BS17: =BS14/BR14-1 -> 0.025401271 | BT17: =BT14/BS14-1 -> 0.0090479368 | BU17: =BU14/BT14-1 -> 0.063523976 | BW17: =BW14/BU14-1 -> -0.00036892151 | BX17: =BX14/BW14-1 -> 0.025401271 | BY17: =BY14/BX14-1 -> 0.027394263 | BZ17: =BZ14/BY14-1 -> 0.092011226
C19: Usage Revenue | BM19: =+BM9-BM14 -> 33435.089 | BN19: =+BN9-BN14 -> 34119.215 | BO19: =BO20*BO5 -> 34343.66 | BP19: =BP20*BP5 -> 39012.4 | BQ19: =SUM(BM19:BP19) -> 140910.36 | BR19: =BR20*BR5 -> 36361.65 | BS19: =BS20*BS5 -> 33992.28 | BT19: =BT20*BT5 -> 34299.84 | BU19: =BU20*BU5 -> 33031.02 | BV19: =SUM(BR19:BU19) -> 137684.79 | BW19: =BR19*(1+BW21) -> 32725.485 | BX19: =BS19*(1+BX21) -> 33312.434 | BY19: =BT19*(1+BY21) -> 33613.843 | BZ19: =BU19*(1+BZ21) -> 32370.4 | CA19: =SUM(BW19:BZ19) -> 132022.16
C20: % of Revenue | BO20: 0.13 | BP20: 0.14 | BR20: 0.13 | BS20: 0.12 | BT20: 0.12 | BU20: 0.11 | BW20: =BW19/BW5 -> 0.10936624 | BX20: =BX19/BX5 -> 0.10874792 | BY20: =BY19/BY5 -> 0.10714286 | BZ20: =BZ19/BZ5 -> 0.095941616
C21: Y/Y Growth | BR21: =BR19/BM19-1 -> 0.087529616 | BS21: =BS19/BN19-1 -> -0.0037203326 | BT21: =BT19/BO19-1 -> -0.0012759269 | BU21: =BU19/BP19-1 -> -0.15331997 | BV21: =BV19/BQ19-1 -> -0.022890966 | BW21: -0.1 | BX21: -0.02 | BY21: -0.02 | BZ21: -0.02 | CA21: =CA19/BV19-1 -> -0.041127475
C22: Q/Q Growth | BR22: =BR19/BP19-1 -> -0.067946345 | BS22: =BS19/BR19-1 -> -0.065161234 | BT22: =BT19/BS19-1 -> 0.0090479368 | BU22: =BU19/BT19-1 -> -0.036992009 | BW22: =BW19/BU19-1 -> -0.0092499414 | BX22: =BX19/BW19-1 -> 0.017935545 | BY22: =BY19/BX19-1 -> 0.0090479368 | BZ22: =BZ19/BY19-1 -> -0.036992009
B24: Non-Recurring Revenue | T24: =T25*T5 -> 908.22 | U24: =U25*U5 -> 1210.96 | V24: =V25*V5 -> 1291.48 | W24: =W25*W5 -> 1441.32 | Y24: =Y25*Y5 -> 1900.75 | Z24: =Z25*Z5 -> 2333.16 | AA24: =AA25*AA5 -> 1639.28 | AB24: =AB25*AB5 -> 2210.35 | AD24: =AD25*AD5 -> 2820.84 | AE24: =AE25*AE5 -> 2863.62 | AF24: =AF25*AF5 -> 3505.67 | AG24: =AG25*AG5 -> 2770.15 | AI24: =AI25*AI5 -> 4712.4 | AJ24: =AJ25*AJ5 -> 4278.4 | AK24: =AK25*AK5 -> 4571.28 | AL24: =AL25*AL5 -> 5063.45 | AM24: =SUM(AI24:AL24) -> 18625.53 | AN24: =AN25*AN5 -> 5217.66 | AO24: =AO25*AO5 -> 6194.88 | AP24: =AP25*AP5 -> 7539.21 | AQ24: =AQ25*AQ5 -> 7381.04 | AR24: =SUM(AN24:AQ24) -> 26332.79 | AS24: =AS25*AS5 -> 8557.92 | AT24: =AT25*AT5 -> 7983.36 | AU24: =AU25*AU5 -> 7850.01 | AV24: =AV25*AV5 -> 8951.95 | AW24: =SUM(AS24:AV24) -> 33343.24 | AX24: =AX25*AX5 -> 11030.56 | AY24: =AY25*AY5 -> 11502.56 | AZ24: =AZ25*AZ5 -> 12346.24 | BA24: =BA25*BA5 -> 12151.93 | BB24: =SUM(AX24:BA24) -> 47031.29 | BC24: =BC25*BC5 -> 16449.93 | BD24: =BD25*BD5 -> 17044.38 | BE24: =BE25*BE5 -> 17850.78 | BF24: =BF25*BF5 -> 16667.6 | BG24: =SUM(BC24:BF24) -> 68012.69 | BH24: =BH25*BH5 -> 17475.12 | BI24: =BI25*BI5 -> 20059.38 | BJ24: =BJ25*BJ5 -> 18408.4 | BK24: =BK25*BK5 -> 19124.96 | BL24: =SUM(BH24:BK24) -> 75067.86 | BM24: =BM25*BM5 -> 17290.7 | BN24: =BN25*BN5 -> 20166.88 | BO24: =BO25*BO5 -> 18492.74 | BP24: =BP25*BP5 -> 19506.2 | BQ24: =SUM(BM24:BP24) -> 75456.52 | BR24: =BR25*BR5 -> 19579.35 | BS24: =BS25*BS5 -> 19828.83 | BT24: =BT25*BT5 -> 20008.24 | BU24: =BU25*BU5 -> 21019.74 | BV24: =SUM(BR24:BU24) -> 80436.16 | BW24: =BR24*(1+BW26) -> 20362.524 | BX24: =BS24*(1+BX26) -> 20621.983 | BY24: =BT24*(1+BY26) -> 20808.57 | BZ24: =BU24*(1+BZ26) -> 21860.53 | CA24: =SUM(BW24:BZ24) -> 83653.606
C25: % of Revenue | T25: =1-T10 -> 0.03 | U25: =1-U10 -> 0.04 | V25: =1-V10 -> 0.04 | W25: =1-W10 -> 0.04 | Y25: =1-Y10 -> 0.05 | Z25: =1-Z10 -> 0.06 | AA25: =1-AA10 -> 0.04 | AB25: =1-AB10 -> 0.05 | AD25: =1-AD10 -> 0.06 | AE25: =1-AE10 -> 0.06 | AF25: =1-AF10 -> 0.07 | AG25: =1-AG10 -> 0.05 | AI25: =1-AI10 -> 0.08 | AJ25: =1-AJ10 -> 0.07 | AK25: =1-AK10 -> 0.07 | AL25: =1-AL10 -> 0.07 | AN25: =1-AN10 -> 0.07 | AO25: =1-AO10 -> 0.08 | AP25: =1-AP10 -> 0.09 | AQ25: =1-AQ10 -> 0.08 | AS25: =1-AS10 -> 0.09 | AT25: 0.08 | AU25: 0.07 | AV25: 0.07 | AX25: =1-AX10 -> 0.08 | AY25: 0.08 | AZ25: 0.08 | BA25: 0.07 | BC25: =1-BC10 -> 0.09 | BD25: =1-BD10 -> 0.09 | BE25: =1-BE10 -> 0.09 | BF25: =1-BF10 -> 0.08 | BH25: =1-BH10 -> 0.08 | BI25: =1-BI10 -> 0.09 | BJ25: 0.08 | BK25: 0.08 | BM25: =1-BM10 -> 0.07 | BN25: =1-BN10 -> 0.08 | BO25: =1-BO10 -> 0.07 | BP25: =1-BP10 -> 0.07 | BR25: 0.07 | BS25: 0.07 | BT25: 0.07 | BU25: 0.07 | BW25: =1-BW10 -> 0.068050103 | BX25: =BX24/BX5 -> 0.067320141 | BY25: =BY24/BY5 -> 0.066326531 | BZ25: =BZ24/BZ5 -> 0.064791741
C26: Y/Y Growth | T26: =T24/O24-1 -> #DIV/0! | U26: =U24/P24-1 -> #DIV/0! | V26: =V24/Q24-1 -> #DIV/0! | W26: =W24/R24-1 -> #DIV/0! | Y26: =Y24/T24-1 -> 1.0928299 | Z26: =Z24/U24-1 -> 0.92670278 | AA26: =AA24/V24-1 -> 0.26930343 | AB26: =AB24/W24-1 -> 0.53355951 | AD26: =AD24/Y24-1 -> 0.48406682 | AE26: =AE24/Z24-1 -> 0.22735689 | AF26: =AF24/AA24-1 -> 1.1385425 | AG26: =AG24/AB24-1 -> 0.25326306 | AI26: =AI24/AD24-1 -> 0.67056621 | AJ26: =AJ24/AE24-1 -> 0.49405298 | AK26: =AK24/AF24-1 -> 0.30396757 | AL26: =AL24/AG24-1 -> 0.82786131 | AN26: =AN24/AI24-1 -> 0.10721925 | AO26: =AO24/AJ24-1 -> 0.44794316 | AP26: =AP24/AK24-1 -> 0.64925579 | AQ26: =AQ24/AL24-1 -> 0.45770966 | AR26: =AR24/AM24-1 -> 0.41380084 | AS26: =AS24/AN24-1 -> 0.64018353 | AT26: =AT24/AO24-1 -> 0.28870293 | AU26: =AU24/AP24-1 -> 0.041224478 | ... BV26: =BV24/BQ24-1 -> 0.065993502 | BW26: 0.04 | BX26: 0.04 | BY26: 0.04 | BZ26: 0.04 | CA26: =CA24/BV24-1 -> 0.04
C27: Q/Q Growth | T27: =T24/R24-1 -> #DIV/0! | U27: =U24/T24-1 -> 0.33333333 | V27: =V24/U24-1 -> 0.0664927 | W27: =W24/V24-1 -> 0.11602193 | Y27: =Y24/W24-1 -> 0.31875642 | Z27: =Z24/Y24-1 -> 0.22749441 | AA27: =AA24/Z24-1 -> -0.29739924 | AB27: =AB24/AA24-1 -> 0.34836636 | AD27: =AD24/AB24-1 -> 0.27619608 | AE27: =AE24/AD24-1 -> 0.015165695 | AF27: =AF24/AE24-1 -> 0.22420922 | AG27: =AG24/AF24-1 -> -0.20980868 | AI27: =AI24/AG24-1 -> 0.70113532 | AJ27: =AJ24/AI24-1 -> -0.092097445 | AK27: =AK24/AJ24-1 -> 0.068455497 | AL27: =AL24/AK24-1 -> 0.10766569 | AN27: =AN24/AL24-1 -> 0.030455519 | AO27: =AO24/AN24-1 -> 0.18729085 | AP27: =AP24/AO24-1 -> 0.21700662 | AQ27: =AQ24/AP24-1 -> -0.020979652 | AS27: =AS24/AQ24-1 -> 0.15944637 | AT27: =AT24/AS24-1 -> -0.067137809 | AU27: =AU24/AT24-1 -> -0.016703493 | AV27: =AV24/AU24-1 -> 0.14037434 | AX27: =AX24/AV24-1 -> 0.23219634 | AY27: =AY24/AX24-1 -> 0.042790212 | AZ27: =AZ24/AY24-1 -> 0.073347151 | BA27: =BA24/AZ24-1 -> -0.015738395 | BC27: =BC24/BA24-1 -> 0.35368867 | BD27: =BD24/BC24-1 -> 0.036136932 | BE27: =BE24/BD24-1 -> 0.047311783 | BF27: =BF24/BE24-1 -> -0.066281697 | BH27: =BH24/BF24-1 -> 0.048448487 | BI27: =BI24/BH24-1 -> 0.14788225 | BJ27: =BJ24/BI24-1 -> -0.082304638 | BK27: =BK24/BJ24-1 -> 0.038925708 | BM27: =BM24/BK24-1 -> -0.09590922 | BN27: =BN24/BM24-1 -> 0.1663426 | BO27: =BO24/BN24-1 -> -0.083014328 | BP27: =BP24/BO24-1 -> 0.054803128 | BR27: =BR24/BP24-1 -> 0.0037500897 | BS27: =BS24/BR24-1 -> 0.012741996 | BT27: =BT24/BS24-1 -> 0.0090479368 | BU27: =BU24/BT24-1 -> 0.050554172 | BW27: =BW24/BU24-1 -> -0.031266609 | BX27: =BX24/BW24-1 -> 0.012741996 | BY27: =BY24/BX24-1 -> 0.0090479368 | BZ27: =BZ24/BY24-1 -> 0.050554172
B28: Total Revenues | D28: =D5 -> 43188 | E28: =E5 -> 14321.11 | F28: =F5 -> 15027.74 | G28: =G5 -> 16202.043 | H28: =H5 -> 18271.429 | I28: =SUM(I5) -> 63822.321 | J28: =J5 -> 19115.125 | K28: =K5 -> 20282.901 | L28: =L5 -> 21091.22 | M28: =M5 -> 23642.754 | N28: =SUM(N5) -> 84132 | O28: =O5 -> 24274 | P28: =P5 -> 24685 | Q28: =Q5 -> 25869 | R28: =R5 -> 28274 | S28: =SUM(S5) -> 103102 | T28: =T5 -> 30274 | U28: =U5 -> 30274 | V28: =V5 -> 32287 | W28: =W5 -> 36033 | X28: =SUM(X5) -> 128868 | Y28: =Y5 -> 38015 | Z28: =Z5 -> 38886 | AA28: =AA5 -> 40982 | AB28: =AB5 -> 44207 | AC28: =SUM(AC5) -> 162090 | AD28: =AD5 -> 47014 | AE28: =AE5 -> 47727 | AF28: =AF5 -> 50081 | AG28: =AG5 -> 55403 | AH28: =AH5 -> 200225 | AI28: =AI5 -> 58905 | AJ28: =AJ5 -> 61120 | AK28: =AK5 -> 65304 | ... AX28: =AX5 -> 137882 | AY28: 143782 | AZ28: =AZ5 -> 154328 | BA28: =BA5 -> 173599 | BB28: =BB5 -> 609591 | BC28: =BC5 -> 182777 | BD28: =BD5 -> 189382 | BE28: =BE5 -> 198342 | BF28: =BF5 -> 208345 | BG28: =BG5 -> 778846 | ... BI28: =BI5 -> 222882 | BJ28: 230105 | BK28: =BK5 -> 239062 | BL28: =BL5 -> 910488 | BM28: =BM5 -> 247010 | BN28: =BN5 -> 252086 | BO28: =BO5 -> 264182 | BP28: 278660 | BQ28: =BQ5 -> 1041938 | BR28: 279705 | BS28: =BS5 -> 283269 | BT28: =BT5 -> 285832 | BU28: =BU5 -> 300282 | BV28: =BV5 -> 1149088 | BW28: =BW5 -> 299228.41 | BX28: =BX5 -> 306327.1 | BY28: =BY5 -> 313729.2 | BZ28: =BZ5 -> 337396.86 | CA28: =CA5 -> 1256681.6
C29: Y/Y Growth | I29: =I28/D28-1 -> 0.47777905 | J29: =J28/E28-1 -> 0.33475164 | K29: =K28/F28-1 -> 0.34969741 | L29: =L28/G28-1 -> 0.30176301 | M29: =M28/H28-1 -> 0.29397397 | N29: =N28/I28-1 -> 0.31822218 | O29: =O28/J28-1 -> 0.26988446 | P29: =P28/K28-1 -> 0.21703497 | ... CA29: =CA28/BV28-1 -> 0.093633877
C30: Q/Q Growth | F30: =F28/E28-1 -> 0.049341833 | G30: =G28/F28-1 -> 0.078142386 | H30: =H28/G28-1 -> 0.12772378 | J30: =J28/H28-1 -> 0.046175674 | K30: =K28/J28-1 -> 0.06109175 | L30: =L28/K28-1 -> 0.039852237 | M30: =M28/L28-1 -> 0.1209761 | O30: =O28/M28-1 -> 0.026699351 | P30: =P28/O28-1 -> 0.016931696 | Q30: =Q28/P28-1 -> 0.047964351 | R30: =R28/Q28-1 -> 0.092968418 | T30: =T28/R28-1 -> 0.070736366 | U30: =U28/T28-1 -> 0 | V30: =V28/U28-1 -> 0.0664927 | W30: =W28/V28-1 -> 0.11602193 | Y30: =Y28/W28-1 -> 0.055005134 | Z30: =Z28/Y28-1 -> 0.022912008 | AA30: =AA28/Z28-1 -> 0.053901147 | AB30: =AB28/AA28-1 -> 0.078693085 | AD30: =AD28/AB28-1 -> 0.063496731 | AE30: =AE28/AD28-1 -> 0.015165695 | AF30: =AF28/AE28-1 -> 0.049322187 | AG30: =AG28/AF28-1 -> 0.10626785 | AI30: =AI28/AG28-1 -> 0.063209573 | AJ30: =AJ28/AI28-1 -> 0.03760292 | AK30: =AK28/AJ28-1 -> 0.068455497 | AL30: =AL28/AK28-1 -> 0.10766569 | AN30: =AN28/AL28-1 -> 0.030455519 | AO30: =AO28/AN28-1 -> 0.038879498 | AP30: =AP28/AO28-1 -> 0.081783667 | AQ30: =AQ28/AP28-1 -> 0.10139789 | AS30: =AS28/AQ28-1 -> 0.030618991 | AT30: =AT28/AS28-1 -> 0.049469965 | AU30: =AU28/AT28-1 -> 0.12376744 | AV30: =AV28/AU28-1 -> 0.14037434 | AX30: =AX28/AV28-1 -> 0.078171795 | AY30: =AY28/AX28-1 -> 0.042790212 | AZ30: =AZ28/AY28-1 -> 0.073347151 | BA30: =BA28/AZ28-1 -> 0.12487041 | BC30: =BC28/BA28-1 -> 0.052868968 | BD30: =BD28/BC28-1 -> 0.036136932 | BE30: =BE28/BD28-1 -> 0.047311783 | BF30: =BF28/BE28-1 -> 0.05043309 | BH30: =BH28/BF28-1 -> 0.048448487 | BI30: =BI28/BH28-1 -> 0.020339774 | BJ30: =BJ28/BI28-1 -> 0.032407283 | BK30: =BK28/BJ28-1 -> 0.038925708 | BM30: =BM28/BK28-1 -> 0.033246605 | BN30: =BN28/BM28-1 -> 0.020549775 | BO30: =BO28/BN28-1 -> 0.047983625 | BP30: =BP28/BO28-1 -> 0.054803128 | BR30: =BR28/BP28-1 -> 0.0037500897 | BS30: =BS28/BR28-1 -> 0.012741996 | BT30: =BT28/BS28-1 -> 0.0090479368 | BU30: =BU28/BT28-1 -> 0.050554172 | BW30: =BW28/BU28-1 -> -0.0035086718 | BX30: =BX28/BW28-1 -> 0.023723308 | BY30: =BY28/BX28-1 -> 0.024164061 | BZ30: =BZ28/BY28-1 -> 0.075439748
B32: Cost of Revenue
C33: Cost of Revenue | D33: 24546 | E33: 8959 | F33: 9224 | G33: 9887 | H33: 11176 | I33: =SUM(E33:H33) -> 39246 | J33: =11681-32 -> 11649 | K33: =12215-44 -> 12171 | L33: =12265-51 -> 12214 | M33: =12646-67-72 -> 12507 | N33: =SUM(J33:M33) -> 48541 | O33: =13148-88-87 -> 12973 | P33: =13469-121-88 -> 13260 | Q33: =13504-158-88 -> 13258 | R33: =14540-176-87 -> 14277 | S33: =SUM(O33:R33) -> 53768 | T33: =14778-188-88 -> 14502 | U33: =14270-218-88 -> 13964 | V33: =14812-233-88 -> 14491 | W33: =15635-227-87 -> 15321 | X33: =SUM(T33:W33) -> 58278 | Y33: =16610-88-265 -> 16257 | Z33: =16764-88-329 -> 16347 | AA33: =17790-88-357 -> 17345 | AB33: =15770-424-87+3114 -> 18373 | AC33: =SUM(Y33:AB33) -> 68322 | AD33: =19971-88-434 -> 19449 | AE33: =20273-575-88 -> 19610 | AF33: =20497-599-87 -> 19811 | AG33: =22363-88-594 -> 21681 | AH33: =SUM(AD33:AG33) -> 80551 | AI33: =24702-88-678 -> 23936 | AJ33: =24814-853-88 -> 23873 | AK33: =26179-860-88 -> 25231 | AL33: =28339-942-88 -> 27309 | AM33: =SUM(AI33:AL33) -> 100349 | AN33: =30851-1229-88 -> 29534 | AO33: =31248-1658-88 -> 29502 | AP33: =34472-1702-88 -> 32682 | AQ33: =37940-1745-618 -> 35577 | AR33: =SUM(AN33:AQ33) -> 127295 | AS33: =40037-1090-1989 -> 36958 | AT33: =42453-1738-2499-618 -> 37598 | AU33: =46561-2603-1738 -> 42220 | AV33: =51233-2331-2283 -> 46619 | AW33: =SUM(AS33:AV33) -> 163395 | AX33: =59803-3105-2947-30 -> 53721 | AY33: =64395-3781-2947 -> 57667 | AZ33: =67137-2947-3994 -> 60196 | BA33: =79764-6854-2947 -> 69963 | BB33: =SUM(AX33:BA33) -> 241547 | BC33: =88867-2947-7793-380-48 -> 77699 | BD33: =88229-2935-8538-3-80+3511 -> 80184 | BE33: =94111-2934-8329-96-187 -> 82565 | BF33: =96294-2890-8638-219-86 -> 84461 | BG33: =SUM(BC33:BF33) -> 324909 | BH33: =104756-2846-9333-23-34 -> 92520 | BI33: =104361-2845-9888-51 -> 91577 | BJ33: =111080-3182-9856-18-492 -> 97532 | BK33: =112493-3146-9182-12-63 -> 100090 | BL33: =SUM(BH33:BK33) -> 381719 | BM33: =114530-7603-2648-53-25 -> 104201 | BN33: =118414-7789-2648-72 -> 107905 | BO33: =121933-3196-7512-94-2115 -> 109016 | BP33: =122663-4099-6921-40 -> 111603 | BQ33: =SUM(BM33:BP33) -> 432725 | BR33: =125973-7184-4100 -> 114689 | BS33: =127865-7296-3464-1565 -> 115540 | BT33: =128552-6852-3464-2 -> 118234 | BU33: =133844-3438-6504-4 -> 123898 | BV33: =SUM(BR33:BU33) -> 472361 | BW33: =BW5*(1-BW34) -> 122683.65 | BX33: =BX5*(1-BX34) -> 124062.47 | BY33: =BY5*(1-BY34) -> 125491.68 | BZ33: =BZ5*(1-BZ34) -> 134958.74 | CA33: =SUM(BW33:BZ33) -> 507196.55
C34: Gross Margin | D34: =(D5-D33)/D5 -> 0.43164768 | E34: =(E5-E33)/E5 -> 0.37441999 | F34: =(F5-F33)/F5 -> 0.38620177 | G34: =(G5-G33)/G5 -> 0.38976831 | H34: =(H5-H33)/H5 -> 0.38833466 | I34: =(I5-I33)/I5 -> 0.38507408 | J34: =(J5-J33)/J5 -> 0.39058729 | K34: =(K5-K33)/K5 -> 0.39993791 | ... BV34: =(BV5-BV33)/BV5 -> 0.5889253 | BW34: 0.59 | BX34: 0.595 | BY34: 0.6 | BZ34: 0.6 | CA34: =(CA5-CA33)/CA5 -> 0.59640011
B35: Total Cost of Revenues | D35: =D33 -> 24546 | E35: =E33 -> 8959 | F35: =F33 -> 9224 | G35: =G33 -> 9887 | H35: =H33 -> 11176 | I35: =SUM(E35:H35) -> 39246 | J35: =J33 -> 11649 | K35: =K33 -> 12171 | L35: =L33 -> 12214 | M35: =M33 -> 12507 | N35: =SUM(J35:M35) -> 48541 | O35: =O33 -> 12973 | P35: =P33 -> 13260 | Q35: =Q33 -> 13258 | R35: =R33 -> 14277 | S35: =SUM(O35:R35) -> 53768 | T35: =T33 -> 14502 | U35: =U33 -> 13964 | V35: =V33 -> 14491 | W35: =W33 -> 15321 | X35: =SUM(T35:W35) -> 58278 | Y35: =Y33 -> 16257 | Z35: =Z33 -> 16347 | AA35: =AA33 -> 17345 | AB35: =AB33 -> 18373 | AC35: =AC33 -> 68322 | AD35: =AD33 -> 19449 | AE35: =AE33 -> 19610 | AF35: =AF33 -> 19811 | ... CA35: =CA33 -> 507196.55
B37: Gross Profit | D37: =D28-D35 -> 18642 | E37: =E28-E35 -> 5362.1097 | F37: =F28-F35 -> 5803.7395 | G37: =G28-G35 -> 6315.043 | H37: =H28-H35 -> 7095.4292 | I37: =I28-I35 -> 24576.321 | J37: =J28-J35 -> 7466.1248 | K37: =K28-K35 -> 8111.9012 | ... CA37: =CA28-CA35 -> 749485.02
C38: Gross Margin | D38: =D37/D28 -> 0.43164768 | E38: =E37/E28 -> 0.37441999 | F38: =F37/F28 -> 0.38620177 | G38: =G37/G28 -> 0.38976831 | H38: =H37/H28 -> 0.38833466 | I38: =I37/I28 -> 0.38507408 | J38: =J37/J28 -> 0.39058729 | K38: =K37/K28 -> 0.39993791 | ... AZ38: =AZ37/AZ28 -> 0.60994764 | BA38: 0.61 | BB38: =BB37/BB28 -> 0.60375563 | BC38: =BC37/BC28 -> 0.57489728 | BD38: =BD37/BD28 -> 0.57660179 | BE38: =BE37/BE28 -> 0.58372407 | BF38: =BF37/BF28 -> 0.5946099 | BG38: =BG37/BG28 -> 0.58283281 | BH38: =BH37/BH28 -> 0.57644926 | BI38: =BI37/BI28 -> 0.58912339 | ... CA38: =CA37/CA28 -> 0.59640011
B40: Operating Expenses
C41: Research & Development | D41: 8688 | E41: 2846 | F41: 3002 | G41: 3439 | H41: 3775 | I41: =SUM(E41:H41) -> 13062 | J41: =4154-53 -> 4101 | K41: =4106-49 -> 4057 | L41: =4419-136 -> 4283 | M41: =4850-261 -> 4589 | N41: =SUM(J41:M41) -> 17030 | O41: =5225-350 -> 4875 | P41: =5554-471 -> 5083 | Q41: =5503-583 -> 4920 | R41: =5828-527 -> 5301 | S41: =SUM(O41:R41) -> 20179 | T41: =6038-574 -> 5464 | U41: =5568-340 -> 5228 | V41: =5473-475 -> 4998 | W41: =5580-401 -> 5179 | X41: =SUM(T41:W41) -> 20869 | Y41: =5802-435 -> 5367 | Z41: =5799-528 -> 5271 | AA41: =6041-547 -> 5494 | AB41: =6236-549 -> 5687 | AC41: =SUM(Y41:AB41) -> 21819 | AD41: =6847-637 -> 6210 | AE41: =6836-801 -> 6035 | AF41: =6689-797 -> 5892 | AG41: =6748-807 -> 5941 | AH41: =SUM(AD41:AG41) -> 24078 | AI41: =7772-877 -> 6895 | AJ41: =8367-1064 -> 7303 | AK41: =9582-2352 -> 7230 | AL41: =8451-1010 -> 7441 | AM41: =SUM(AI41:AL41) -> 28869 | AN41: =10546-1470 -> 9076 | AO41: =10811-1907 -> 8904 | AP41: =11665-2022 -> 9643 | AQ41: =12168-2259 -> 9909 | AR41: =SUM(AN41:AQ41) -> 37532 | AS41: =15189-2806 -> 12383 | AT41: =17208-3684-327 -> 13197 | AU41: =17674-3876 -> 13798 | AV41: =18676-3675 -> 15001 | AW41: =SUM(AS41:AV41) -> 54379 | AX41: =22121-4763 -> 17358 | AY41: =24648-6152 -> 18496 | AZ41: =29680-9101 -> 20579 | BA41: =30448-9163 -> 21285 | BB41: =SUM(AX41:BA41) -> 77718 | BC41: =35824-10145-656-2629 -> 22394 | BD41: =34992-11818-1307-59-334 -> 21474 | BE41: =34113-10603-1654-557 -> 21299 | BF41: =36865-11799-1449-2615 -> 21002 | BG41: =SUM(BC41:BF41) -> 86169 | BH41: =38108-12382 -> 25726 | BI41: =39210-13013 -> 26197 | BJ41: =40391-12980 -> 27411 | BK41: =38873-12055-12-197 -> 26609 | BL41: =SUM(BH41:BK41) -> 105943 | BM41: =41518-10930-323 -> 30265 | BN41: =40717-9827-488 -> 30402 | BO41: =42482-8244-412-18-1942 -> 31866 | BP41: =41480-8259 -> 33221 | BQ41: =SUM(BM41:BP41) -> 125754 | BR41: =41100-8690 -> 32410 | BS41: =39912-8829-742-1931 -> 28410 | BT41: =35218-6896-1170-25 -> 27127 | BU41: =36104-7349-1538 -> 27217 | BV41: =SUM(BR41:BU41) -> 115164 | BW41: =BW28*BW42 -> 32915.125 | BX41: =BX28*BX42 -> 32164.345 | BY41: =BY28*BY42 -> 32941.566 | BZ41: =BZ28*BZ42 -> 32727.495 | CA41: =SUM(BW41:BZ41) -> 130748.53
C42: % of Revenue | D42: =D41/D28 -> 0.20116699 | E42: =E41/E28 -> 0.19872762 | F42: =F41/F28 -> 0.19976391 | G42: =G41/G28 -> 0.21225718 | H42: =H41/H28 -> 0.20660672 | I42: =I41/I28 -> 0.20466194 | J42: =J41/J28 -> 0.21454215 | K42: =K41/K28 -> 0.2000207 | ... BV42: =BV41/BV28 -> 0.10022209 | BW42: 0.11 | BX42: 0.105 | BY42: 0.105 | BZ42: 0.097 | CA42: =CA41/CA28 -> 0.10404269
C43: Sales and Marketing | D43: 10171 | E43: 3289 | F43: 3993 | G43: 4309 | H43: 5105 | I43: =SUM(E43:H43) -> 16696 | J43: =6147-105 -> 6042 | K43: =7227-134 -> 7093 | L43: =6964-182 -> 6782 | M43: =7727-330-23 -> 7374 | N43: =SUM(J43:M43) -> 27291 | O43: =9022-326-28 -> 8668 | P43: =9674-368-28 -> 9278 | Q43: =9296-361-29 -> 8906 | R43: =9453-455-29 -> 8969 | S43: =SUM(O43:R43) -> 35821 | T43: =9931-524-28 -> 9379 | U43: =10594-458-28 -> 10108 | V43: =10797-448-29 -> 10320 | W43: =10720-370-29 -> 10321 | X43: =SUM(T43:W43) -> 40128 | Y43: =12706-434-28 -> 12244 | Z43: =12637-544-28 -> 12065 | AA43: =12925-626-29 -> 12270 | AB43: =14480-759-117+87 -> 13691 | AC43: =SUM(Y43:AB43) -> 50270 | AD43: =15778-928-29 -> 14821 | AE43: =16932-1224-29 -> 15679 | AF43: =16502-1084-28 -> 15390 | AG43: =17358-1128-28 -> 16202 | AH43: =SUM(AD43:AG43) -> 62092 | AI43: =17478-1362-28 -> 16088 | AJ43: =17912-1585-28 -> 16299 | AK43: =17818-1613 -> 16205 | AL43: =18793-1747 -> 17046 | AM43: =SUM(AI43:AL43) -> 65638 | AN43: =21701-2249 -> 19452 | AO43: =23250-2749 -> 20501 | AP43: =25014-3017 -> 21997 | AQ43: =25627-3353 -> 22274 | AR43: =SUM(AN43:AQ43) -> 84224 | AS43: =30160-4106 -> 26054 | AT43: =32231-5265-651 -> 26315 | AU43: =32969-5427 -> 27542 | AV43: =37053-5366 -> 31687 | AW43: =SUM(AS43:AV43) -> 111598 | AX43: =44799-6771 -> 38028 | AY43: =46024-8208 -> 37816 | AZ43: =49712-8304 -> 41408 | BA43: =53394-11987 -> 41407 | BB43: =SUM(AX43:BA43) -> 158659 | BC43: =64611-13424-46 -> 51141 | BD43: =64098-14963-23 -> 49112 | BE43: =67353-15761 -> 51592 | BF43: =65928-15152 -> 50776 | BG43: =SUM(BC43:BF43) -> 202621 | BH43: =76314-17045-1 -> 59268 | BI43: =74077-17391 -> 56686 | BJ43: =73366-16404 -> 56962 | BK43: =72956-15389 -> 57567 | BL43: =SUM(BH43:BK43) -> 230483 | BM43: =81109-14020 -> 67089 | BN43: =78332-13824 -> 64508 | BO43: =78615-12490-4424 -> 61701 | BP43: =73898-10880-2757 -> 60261 | BQ43: =SUM(BM43:BP43) -> 253559 | BR43: =82855-11574 -> 71281 | BS43: =80668-13355-3319 -> 63994 | BT43: =71657-8401-182 -> 63074 | BU43: =76636-8879 -> 67757 | BV43: =SUM(BR43:BU43) -> 266106 | BW43: =BW28*BW44 -> 71814.818 | BX43: =BX28*BX44 -> 71986.868 | BY43: =BY28*BY44 -> 72157.717 | BZ43: =BZ28*BZ44 -> 75914.292 | CA43: =SUM(BW43:BZ43) -> 291873.7
C44: % of Revenue | D44: =D43/D28 -> 0.23550523 | E44: =E43/E28 -> 0.22966097 | F44: =F43/F28 -> 0.26570862 | G44: =G43/G28 -> 0.26595412 | H44: =H43/H28 -> 0.27939796 | I44: =I43/I28 -> 0.26160126 | J44: =J43/J28 -> 0.31608478 | K44: =K43/K28 -> 0.34970342 | ... BV44: =BV43/BV28 -> 0.23158017 | BW44: 0.24 | BX44: 0.235 | BY44: 0.23 | BZ44: 0.225 | CA44: =CA43/CA28 -> 0.23225748
C45: G&A | D45: 6737 | E45: 2364 | F45: 2543 | G45: 2949 | H45: 3552 | I45: =SUM(E45:H45) -> 11408 | J45: =3825-74 -> 3751 | K45: =4052-77 -> 3975 | L45: =4223-89 -> 4134 | M45: =5953-10-265 -> 5678 | N45: =SUM(J45:M45) -> 17538 | O45: =6171-433-12 -> 5726 | P45: =3515-12-763 -> 2740 | Q45: =7967-11-775 -> 7181 | R45: =6763-799-12 -> 5952 | S45: =SUM(O45:R45) -> 21599 | T45: =7275-949-12 -> 6314 | U45: =6027-814-12 -> 5201 | V45: =6087-789-11 -> 5287 | W45: =6433-722-12 -> 5699 | X45: =SUM(T45:W45) -> 22501 | Y45: =6536-860-12 -> 5664 | Z45: =5882-1013-12 -> 4857 | AA45: =6143-989-12 -> 5142 | AB45: =6511-984 -> 5527 | AC45: =SUM(Y45:AB45) -> 21190 | AD45: =8860-1130-1700-135 -> 5895 | AE45: =6845-1254 -> 5591 | AF45: =4679-1240+2133 -> 5572 | AG45: =8767-2111 -> 6656 | AH45: =SUM(AD45:AG45) -> 23714 | AI45: =9103-2408 -> 6695 | AJ45: =9833-3295-241 -> 6297 | AK45: =10746-4044-258-117+88 -> 6415 | AL45: =10766-3794-93-93+88 -> 6874 | AM45: =SUM(AI45:AL45) -> 26281 | AN45: =11762-3738-292 -> 7732 | AO45: =12042-4122-420-64 -> 7436 | AP45: =12146-4334 -> 7812 | AQ45: =13496-4511-338 -> 8647 | AR45: =SUM(AN45:AQ45) -> 31627 | AS45: =14658-4893-329 -> 9436 | AT45: =16129-5343-1637-221 -> 8928 | AU45: =16724-5380-2030 -> 9314 | AV45: =18258-5504-2339 -> 10415 | AW45: =SUM(AS45:AV45) -> 38093 | AX45: =22245-6269-1064-2500 -> 12412 | AY45: =22909-6760-973-2700 -> 12476 | AZ45: =26790-5996-60-9158 -> 11576 | BA45: =21972-7597-2351-380 -> 11644 | BB45: =SUM(AX45:BA45) -> 48108 | BC45: =24314-8032-888-218-260-105 -> 14811 | BD45: =23824-9467-304-152-335 -> 13566 | BE45: =24496-9810-103-121 -> 14462 | BF45: =22509-8235-70-141 -> 14063 | BG45: =SUM(BC45:BF45) -> 56902 | BH45: =28258-11983-1455+34-596+23 -> 14281 | BI45: =30477-13075-877-815+51 -> 15761 | BJ45: =31006-13371-268-659 -> 16708 | BK45: =33338-12945-3595-34 -> 16764 | BL45: =SUM(BH45:BK45) -> 63514 | BM45: =30548-12131-556 -> 17861 | BN45: =33988-12192-3529-32 -> 18235 | BO45: =36575-1144-3-3980-11310 -> 20138 | BP45: =36439-12383 -> 24056 | BQ45: =SUM(BM45:BP45) -> 80290 | BR45: =35205-11797-1265-141-982 -> 21020 | BS45: =36385-12379-746-952-95-974-368 -> 20871 | BT45: =34362-11190-448-196-1851-392 -> 20285 | BU45: =33902-10893-613-1728-873 -> 19795 | BV45: =SUM(BR45:BU45) -> 81971 | BW45: =BW28*BW46 -> 21544.445 | BX45: =BX28*BX46 -> 21442.897 | BY45: =BY28*BY46 -> 20392.398 | BZ45: =BZ28*BZ46 -> 20243.811 | CA45: =SUM(BW45:BZ45) -> 83623.552
C46: % of Revenue | D46: =D45/D28 -> 0.15599241 | E46: =E45/E28 -> 0.16507101 | F46: =F45/F28 -> 0.16922039 | G46: =G45/G28 -> 0.18201408 | H46: =H45/H28 -> 0.19440187 | I46: =I45/I28 -> 0.17874624 | J46: =J45/J28 -> 0.19623204 | K46: =K45/K28 -> 0.19597788 | ... BV46: =BV45/BV28 -> 0.071335703 | BW46: 0.072 | BX46: 0.07 | BY46: 0.065 | BZ46: 0.06 | CA46: =CA45/CA28 -> 0.066543152
B47: Total Operating Expense | D47: =D45+D43+D41 -> 25596 | E47: =E45+E43+E41 -> 8499 | F47: =F45+F43+F41 -> 9538 | G47: =G45+G43+G41 -> 10697 | H47: =H45+H43+H41 -> 12432 | I47: =SUM(E47:H47) -> 41166 | J47: =J45+J43+J41 -> 13894 | K47: =K45+K43+K41 -> 15125 | L47: =L45+L43+L41 -> 15199 | M47: =M45+M43+M41 -> 17641 | N47: =N41+N43+N45 -> 61859 | O47: =O41+O43+O45 -> 19269 | P47: =P41+P43+P45 -> 17101 | Q47: =Q41+Q43+Q45 -> 21007 | R47: =R41+R43+R45 -> 20222 | S47: =S41+S43+S45 -> 77599 | T47: =T41+T43+T45 -> 21157 | U47: =U41+U43+U45 -> 20537 | ... CA47: =CA41+CA43+CA45 -> 506245.78
B49: Non-GAAP Operating Income | D49: =D37-D47 -> -6954 | E49: =E37-E47 -> -3136.8903 | F49: =F37-F47 -> -3734.2605 | G49: =G37-G47 -> -4381.957 | H49: =H37-H47 -> -5336.5708 | I49: =I37-I47 -> -16589.679 | J49: =J37-J47 -> -6427.8752 | K49: =K37-K47 -> -7013.0988 | ... CA49: =CA37-CA47 -> 243239.24
C50: Non-GAAP Operating Margin | D50: =D49/D28 -> -0.16101695 | E50: =E49/E28 -> -0.21903961 | F50: =F49/F28 -> -0.24849116 | G50: =G49/G28 -> -0.27045707 | H50: =H49/H28 -> -0.29207189 | I50: =I49/I28 -> -0.25993537 | J50: =J49/J28 -> -0.33627169 | K50: =K49/K28 -> -0.34576409 | ... CA50: =CA49/CA28 -> 0.19355678
AT51: =+AT49-13754 -> 0
B52: GAAP Adjustments | BD52: =BD49-25046 -> 0
C53: Amortization of intangibles | D53: 0 | E53: 0 | F53: 0 | G53: 0 | H53: 0 | I53: =SUM(E53:H53) -> 0 | J53: 0 | K53: 0 | L53: 0 | M53: 105 | N53: =SUM(J53:M53) -> 105 | O53: 128 | P53: 128 | Q53: 128 | R53: 128 | S53: =SUM(O53:R53) -> 512 | T53: 128 | U53: 128 | V53: 128 | W53: 128 | X53: =SUM(T53:W53) -> 512 | Y53: 128 | Z53: 128 | AA53: 129 | AB53: 117 | AC53: =SUM(Y53:AB53) -> 502 | AD53: 117 | AE53: 117 | AF53: 115 | AG53: 116 | AH53: =SUM(AD53:AG53) -> 465 | AI53: 116 | AJ53: 116 | AK53: 117 | AL53: 93 | AM53: =SUM(AI53:AL53) -> 442 | AN53: 88 | AO53: 88 | AP53: 88 | AQ53: 618 | AR53: =SUM(AN53:AQ53) -> 882 | AS53: 1090 | AT53: 1738 | AU53: 1738 | AV53: 2283 | AW53: =SUM(AS53:AV53) -> 6849 | AX53: 2947 | AY53: 2947 | AZ53: 2947 | BA53: 2947 | BB53: =SUM(AX53:BA53) -> 11788 | BC53: 2947 | BD53: 2935 | BE53: 2934 | BF53: 2890 | BG53: =SUM(BC53:BF53) -> 11706 | BH53: 2846 | BI53: 2845 | BJ53: 3182 | BK53: 3146 | BL53: =SUM(BH53:BK53) -> 12019 | BM53: 2648 | BN53: 2648 | BO53: 3196 | BP53: 4099 | BQ53: =SUM(BM53:BP53) -> 12591 | BR53: 4100 | BS53: 3464 | BT53: 3464 | BU53: 3438 | BV53: =SUM(BR53:BU53) -> 14466 | BW53: 3500 | BX53: 3500 | BY53: 3500 | BZ53: 3500 | CA53: =SUM(BW53:BZ53) -> 14000
C54: Non-cash interest exp | D54: 0 | E54: 0 | F54: 0 | G54: 0 | H54: 0 | I54: =SUM(E54:H54) -> 0 | J54: 0 | K54: 0 | L54: 0 | M54: 6 | N54: =SUM(J54:M54) -> 6 | O54: 51 | P54: 78 | Q54: 81 | R54: 83 | S54: =SUM(O54:R54) -> 293 | T54: 84 | U54: 87 | V54: 89 | W54: 90 | X54: =SUM(T54:W54) -> 350 | Y54: 91 | Z54: 87 | AA54: 43 | AB54: 20 | AC54: =SUM(Y54:AB54) -> 241 | AD54: =20-103 -> -83 | AE54: 20 | AF54: 20 | AG54: 20 | AH54: =SUM(AD54:AG54) -> -23 | AI54: 20 | AJ54: 20 | AK54: 89 | AL54: 93 | AM54: =SUM(AI54:AL54) -> 222 | AR54: =SUM(AN54:AQ54) -> 0 | AW54: =SUM(AS54:AV54) -> 0 | BB54: =SUM(AX54:BA54) -> 0 | BG54: =SUM(BC54:BF54) -> 0 | BL54: =SUM(BH54:BK54) -> 0 | BQ54: =SUM(BM54:BP54) -> 0 | BV54: =SUM(BR54:BU54) -> 0 | CA54: =SUM(BW54:BZ54) -> 0
C55: Amortization of debt discount and issuance costs | AJ55: 1733 | AK55: 3049 | AL55: 3099 | AM55: =SUM(AI55:AL55) -> 7881 | AR55: =SUM(AN55:AQ55) -> 0 | AV55: 0 | AW55: =SUM(AS55:AV55) -> 0 | AX55: 0 | BB55: =SUM(AX55:BA55) -> 0 | BG55: =SUM(BC55:BF55) -> 0 | BL55: =SUM(BH55:BK55) -> 0 | BQ55: =SUM(BM55:BP55) -> 0 | BT55: 0 | BU55: 0 | BV55: =SUM(BR55:BU55) -> 0 | CA55: =SUM(BW55:BZ55) -> 0
C56: Loss on early extinguishment of debt | AN56: 217 | AV56: 0 | AW56: =SUM(AS56:AV56) -> 0 | BB56: =SUM(AX56:BA56) -> 0 | BG56: =SUM(BC56:BF56) -> 0 | BL56: =SUM(BH56:BK56) -> 0 | BQ56: =SUM(BM56:BP56) -> 0 | BT56: 0 | BU56: 0 | BV56: =SUM(BR56:BU56) -> 0 | CA56: =SUM(BW56:BZ56) -> 0
C57: Accrued FCC Charge | D57: 0 | E57: 0 | F57: 0 | G57: 0 | H57: 0 | I57: =SUM(E57:H57) -> 0 | J57: 0 | K57: 0 | L57: 0 | M57: 0 | N57: =SUM(J57:M57) -> 0 | O57: 0 | P57: 0 | Q57: 2000 | R57: 0 | S57: =SUM(O57:R57) -> 2000 | T57: 0 | U57: 0 | V57: 0 | W57: 0 | X57: =SUM(T57:W57) -> 0 | Y57: 0 | Z57: 0 | AC57: =SUM(Y57:AB57) -> 0 | AH57: =SUM(AD57:AG57) -> 0 | AM57: =SUM(AI57:AL57) -> 0 | AR57: =SUM(AN57:AQ57) -> 0 | AW57: =SUM(AS57:AV57) -> 0 | BB57: =SUM(AX57:BA57) -> 0 | BG57: =SUM(BC57:BF57) -> 0 | BL57: =SUM(BH57:BK57) -> 0 | BQ57: =SUM(BM57:BP57) -> 0 | BT57: 0 | BU57: 0 | BV57: =SUM(BR57:BU57) -> 0 | CA57: =SUM(BW57:BZ57) -> 0
C58: Reversal of continue sales tax liability | D58: 0 | E58: 0 | F58: 0 | G58: 0 | H58: 0 | I58: =SUM(E58:H58) -> 0 | J58: 0 | K58: 0 | L58: 0 | M58: 0 | N58: =SUM(J58:M58) -> 0 | O58: 0 | P58: -2766 | Q58: 0 | R58: 418 | S58: =SUM(O58:R58) -> -2348 | T58: 0 | U58: 0 | V58: 0 | W58: 0 | X58: =SUM(T58:W58) -> 0 | Y58: 0 | Z58: 0 | AC58: =SUM(Y58:AB58) -> 0 | AH58: =SUM(AD58:AG58) -> 0 | AM58: =SUM(AI58:AL58) -> 0 | AR58: =SUM(AN58:AQ58) -> 0 | AW58: =SUM(AS58:AV58) -> 0 | BB58: =SUM(AX58:BA58) -> 0 | BG58: =SUM(BC58:BF58) -> 0 | BL58: =SUM(BH58:BK58) -> 0 | BQ58: =SUM(BM58:BP58) -> 0 | BV58: =SUM(BR58:BU58) -> 0 | CA58: =SUM(BW58:BZ58) -> 0
C59: Other | AA59: 1026 | AB59: -3114 | AC59: =SUM(Y59:AB59) -> -2088 | AD59: =1700+135 -> 1835 | AE59: -58 | AF59: =-2133-72 -> -2205 | AG59: -133 | AH59: =SUM(AD59:AG59) -> -561 | AI59: -352 | AJ59: 241 | AK59: 258 | AM59: =SUM(AI59:AL59) -> 147 | AN59: =-217+292 -> 75 | AO59: =420+64 -> 484 | AQ59: 338 | AR59: =SUM(AN59:AQ59) -> 897 | AS59: 329 | AT59: =618+1637+1199 -> 3454 | AU59: =2030 -> 2030 | AV59: 2339 | AW59: =SUM(AS59:AV59) -> 8152 | AX59: =1094+2500 -> 3594 | AY59: =973+2700 -> 3673 | AZ59: =9158+60 -> 9218 | BA59: =2351+380 -> 2731 | BB59: =SUM(AX59:BA59) -> 19216 | BC59: =3332+1638+260 -> 5230 | BD59: =1714+883-3511 -> -914 | BE59: =774+1944 -> 2718 | BF59: =2975+1605 -> 4580 | BG59: =SUM(BC59:BF59) -> 11614 | BH59: =1455+596 -> 2051 | BI59: =815+877 -> 1692 | BJ59: =18+492+268+659 -> 1437 | BK59: =3670+243 -> 3913 | BL59: =SUM(BH59:BK59) -> 9093 | BM59: =932+25 -> 957 | BN59: =32+4089 -> 4121 | BO59: =21+4486 -> 4507 | BP59: =2797 -> 2797 | BQ59: =SUM(BM59:BP59) -> 12382 | BR59: =1265+141+982 -> 2388 | BS59: =742+746+95+368 -> 1951 | BT59: =1170+448+392+2 -> 2012 | BU59: 2155 | BV59: =SUM(BR59:BU59) -> 8506 | BW59: 2100 | BX59: 2100 | BY59: 2100 | BZ59: 2100 | CA59: =SUM(BW59:BZ59) -> 8400
C60: Change in fari value of convertible preferred | D60: 0 | E60: 0 | F60: 0 | G60: 0 | H60: 0 | J60: -230 | K60: 785 | L60: 622 | M60: 694 | N60: =SUM(J60:M60) -> 1871 | O60: -1745 | P60: 0 | Q60: 0 | R60: 0 | S60: =SUM(O60:R60) -> -1745 | T60: 575 | U60: 190 | V60: 0 | W60: 0 | X60: =SUM(T60:W60) -> 765 | Y60: 0 | Z60: 0 | AC60: =SUM(Y60:AB60) -> 0 | AH60: =SUM(AD60:AG60) -> 0 | AM60: =SUM(AI60:AL60) -> 0 | AR60: =SUM(AN60:AQ60) -> 0 | AW60: =SUM(AS60:AV60) -> 0 | BB60: =SUM(AX60:BA60) -> 0 | BG60: =SUM(BC60:BF60) -> 0 | BL60: =SUM(BH60:BK60) -> 0 | BQ60: =SUM(BM60:BP60) -> 0 | BV60: =SUM(BR60:BU60) -> 0 | CA60: =SUM(BW60:BZ60) -> 0
C61: Warrants | D61: 55 | E61: 120 | F61: 707 | G61: 730 | H61: 117 | I61: =SUM(E61:H61) -> 1674 | J61: 0 | K61: 0 | L61: 0 | M61: 0 | N61: =SUM(J61:M61) -> 0 | O61: 0 | P61: 0 | Q61: 0 | R61: 0 | S61: =SUM(O61:R61) -> 0 | T61: 0 | U61: 0 | V61: 0 | W61: 0 | X61: =SUM(T61:W61) -> 0 | Y61: 0 | Z61: 0 | AC61: =SUM(Y61:AB61) -> 0 | AH61: =SUM(AD61:AG61) -> 0 | AM61: =SUM(AI61:AL61) -> 0 | AR61: =SUM(AN61:AQ61) -> 0 | AW61: =SUM(AS61:AV61) -> 0 | BB61: =SUM(AX61:BA61) -> 0 | BG61: =SUM(BC61:BF61) -> 0 | BL61: =SUM(BH61:BK61) -> 0 | BQ61: =SUM(BM61:BP61) -> 0 | BV61: =SUM(BR61:BU61) -> 0 | CA61: =SUM(BW61:BZ61) -> 0
C62: Restructuring Costs | BO62: 9625 | BQ62: =SUM(BM62:BP62) -> 9625 | BS62: =1565+1931+3319+952+974 -> 8741 | BT62: =25+182+196+1851 -> 2254 | BU62: =1728+873 -> 2601 | BV62: =SUM(BR62:BU62) -> 13596
C63: Stock base compensation | D63: 357 | E63: 78.27533 | F63: 71.14902 | G63: 119.27673 | H63: 195.57034 | I63: =SUM(E63:H63) -> 464.27142 | J63: 263.86585 | K63: 304.17114 | L63: 457.26569 | M63: 922.86145 | N63: =SUM(J63:M63) -> 1948.1641 | O63: 1196 | P63: 1723 | Q63: 1877 | R63: 1957 | S63: =SUM(O63:R63) -> 6753 | T63: 2235 | U63: 1830 | V63: 1945 | W63: 1720 | X63: =SUM(T63:W63) -> 7730 | Y63: 1994 | Z63: 2414 | AA63: 2519 | AB63: 2716 | AC63: =SUM(Y63:AB63) -> 9643 | AD63: 3129 | AE63: 3854 | AF63: 3720 | AG63: 4640 | AH63: =SUM(AD63:AG63) -> 15343 | AI63: 5325 | AJ63: 6797 | AK63: 8869 | AL63: 7493 | AM63: =SUM(AI63:AL63) -> 28484 | AN63: 8686 | AO63: 10436 | AP63: 11075 | AQ63: 11868 | AR63: =SUM(AN63:AQ63) -> 42065 | AS63: 13794 | AT63: 16791 | AU63: 17286 | AV63: 16876 | AW63: =SUM(AS63:AV63) -> 64747 | AX63: 20908 | AY63: 24901 | AZ63: 27395 | BA63: 35601 | BB63: =SUM(AX63:BA63) -> 108805 | BC63: 39394 | BD63: 44786 | BE63: 44503 | BF63: 43824 | BG63: =SUM(BC63:BF63) -> 172507 | BH63: 50743 | BI63: 53367 | BJ63: 52611 | BK63: 49571 | BL63: =SUM(BH63:BK63) -> 206292 | BM63: 44684 | BN63: 43632 | BO63: 39556 | BP63: 38443 | BQ63: =SUM(BM63:BP63) -> 166315 | BR63: 39245 | BS63: 41859 | BT63: 33339 | BU63: 33625 | BV63: =SUM(BR63:BU63) -> 148068 | BW63: 35000 | BX63: 35000 | BY63: 40000 | BZ63: 42000 | CA63: =SUM(BW63:BZ63) -> 152000
B64: Total GAAP and non-cash adjustments | D64: =SUM(D53:D63) -> 412 | E64: =SUM(E53:E63) -> 198.27533 | F64: =SUM(F53:F63) -> 778.14902 | G64: =SUM(G53:G63) -> 849.27673 | H64: =SUM(H53:H63) -> 312.57034 | I64: =SUM(I53:I63) -> 2138.2714 | J64: =SUM(J53:J63) -> 33.86585 | K64: =SUM(K53:K63) -> 1089.1711 | ... CA64: =SUM(CA53:CA63) -> 174400
B66: GAAP Operating Income | D66: =D49-D64 -> -7366 | E66: =E49-E64 -> -3335.1656 | F66: =F49-F64 -> -4512.4095 | G66: =G49-G64 -> -5231.2338 | H66: =H49-H64 -> -5649.1411 | I66: =I49-I64 -> -18727.95 | J66: =J49-J64 -> -6461.7411 | K66: =K49-K64 -> -8102.2699 | ... CA66: =CA49-CA64 -> 68839.241
C67: GAAP Operating Margin | D67: =D66/D28 -> -0.17055664 | E67: =E66/E28 -> -0.23288458 | F67: =F66/F28 -> -0.300272 | G67: =G66/G28 -> -0.32287495 | H67: =H66/H28 -> -0.30917894 | I67: =I66/I28 -> -0.29343887 | J67: =J66/J28 -> -0.33804336 | K67: =K66/K28 -> -0.39946307 | ... CA67: =CA66/CA28 -> 0.054778587
B69: Interest expense | D69: 0 | E69: 0 | F69: 0 | G69: 0 | H69: 0 | I69: =SUM(E69:H69) -> 0 | J69: -178 | K69: -215 | L69: -273 | M69: -414 | N69: =SUM(J69:M69) -> -1080 | O69: -778 | P69: =-1092+78 -> -1014 | Q69: =-1116+81 -> -1035 | R69: =-1175+83 -> -1092 | S69: =SUM(O69:R69) -> -3919 | T69: =-1139+84 -> -1055 | U69: =-1155+87 -> -1068 | V69: =-1235+89 -> -1146 | W69: =-1198+90 -> -1108 | X69: =SUM(T69:W69) -> -4377 | Y69: =-1199+91 -> -1108 | Z69: =-1197+87 -> -1110 | AA69: =-961+43 -> -918 | AB69: =-869+20 -> -849 | AC69: =SUM(Y69:AB69) -> -3985 | AD69: =-882+AD54 -> -965 | AE69: =-888+20-58 -> -926 | AF69: =-865+AF54-72 -> -917 | AG69: =-836-133+AG54 -> -949 | AH69: =SUM(AD69:AG69) -> -3757 | AI69: =-810-352+AI54 -> -1142 | AJ69: =-2378+20+1733 -> -625 | AK69: =-3595+3049+89 -> -457 | AL69: -3462 | AM69: =SUM(AI69:AL69) -> -5686 | AN69: -3396 | AO69: -3406 | AP69: -3486 | AQ69: -3506 | AR69: =SUM(AN69:AQ69) -> -13794 | AS69: -3484 | AT69: -5734 | AU69: -9649 | AV69: -9481 | AW69: =SUM(AS69:AV69) -> -28348 | AX69: -1938 | AY69: -2118 | AZ69: -1947 | BA69: -2024 | BB69: =SUM(AX69:BA69) -> -8027 | BC69: =-1870 -> -1870 | BD69: -1857 | BE69: -1879 | BF69: -1887 | BG69: =SUM(BC69:BF69) -> -7493 | BH69: -1845 | BI69: -1866 | BJ69: -1972 | BK69: -1963 | BL69: =SUM(BH69:BK69) -> -7646 | BM69: -2567 | BN69: -3906 | BO69: -4068 | BP69: -4271 | BQ69: =SUM(BM69:BP69) -> -14812 | BR69: -4115 | BS69: -3820 | BT69: -3087 | BU69: -3054 | BV69: =SUM(BR69:BU69) -> -14076 | BW69: -3100 | BX69: -3100 | BY69: -3100 | BZ69: -3100 | CA69: =SUM(BW69:BZ69) -> -12400
B70: Interest income | D70: -442 | E70: 0 | F70: 0 | G70: 0 | H70: 0 | I70: =SUM(E70:H70) -> 0 | J70: 0 | K70: 32 | L70: -15 | M70: =10+6 -> 16 | N70: =SUM(J70:M70) -> 33 | O70: 51 | P70: =-28 -> -28 | Q70: =95 -> 95 | R70: =146 -> 146 | S70: =SUM(O70:R70) -> 264 | T70: =2 -> 2 | U70: =-49 -> -49 | V70: =119 -> 119 | W70: =28 -> 28 | X70: =SUM(T70:W70) -> 100 | Y70: =-45 -> -45 | Z70: -33 | AA70: =12 -> 12 | AB70: 54 | AC70: =SUM(Y70:AB70) -> -12 | AD70: 118 | AE70: 90 | AF70: 118 | AG70: 164 | AH70: =SUM(AD70:AG70) -> 490 | AI70: 398 | AJ70: 206 | AK70: 1352 | AL70: 1359 | AM70: =SUM(AI70:AL70) -> 3315 | AN70: 1745 | AO70: 1490 | AP70: 1460 | AQ70: =1384 -> 1384 | AR70: =SUM(AN70:AQ70) -> 6079 | AS70: 1072 | AT70: -4965 | AU70: 349 | AV70: =501 -> 501 | AW70: =SUM(AS70:AV70) -> -3043 | AX70: 175 | AY70: -353 | AZ70: 213 | BA70: -43 | BB70: =SUM(AX70:BA70) -> -8 | BC70: =845 -> 845 | BD70: 280 | BE70: 982 | BF70: 2706 | BG70: =SUM(BC70:BF70) -> 4813 | BH70: 4121 | BI70: 6123 | BJ70: 8233 | BK70: 8322 | BL70: =SUM(BH70:BK70) -> 26799 | BM70: 10559 | BN70: 13800 | BO70: 11144 | BP70: 11242 | BQ70: =SUM(BM70:BP70) -> 46745 | BR70: 10303 | BS70: 7917 | BT70: 5660 | BU70: 6288 | BV70: =SUM(BR70:BU70) -> 30168 | BW70: 5500 | BX70: 4800 | BY70: 4600 | BZ70: 4400 | CA70: =SUM(BW70:BZ70) -> 19300
C71: Lease amortization for finance lease
B72: Other Income (Expense) | D72: 0 | E72: 0 | F72: 0 | G72: 0 | H72: 0 | I72: =SUM(E72:H72) -> 0 | J72: =2 -> 2 | K72: 0 | L72: 0 | M72: 0 | N72: =SUM(J72:M72) -> 2 | O72: 32 | P72: 0 | Q72: 2000 | R72: 0 | S72: =SUM(O72:R72) -> 2032 | T72: 0 | U72: -651 | V72: 0 | W72: 0 | X72: =SUM(T72:W72) -> -651 | Y72: 0 | AC72: =SUM(Y72:AB72) -> 0 | AH72: =SUM(AD72:AG72) -> 0 | AM72: =SUM(AI72:AL72) -> 0 | AP72: 0 | AQ72: 0 | AV72: =-887 -> -887 | AW72: =SUM(AS72:AV72) -> -887 | AX72: 0 | BB72: =SUM(AX72:BA72) -> 0 | BG72: =SUM(BC72:BF72) -> 0 | BL72: =SUM(BH72:BK72) -> 0 | BM72: 6615 | BQ72: =SUM(BM72:BP72) -> 6615 | BT72: 0 | BU72: 0 | BV72: =SUM(BR72:BU72) -> 0 | CA72: =SUM(BW72:BZ72) -> 0
B73: Other | D73: 0 | J73: 0 | K73: 0 | L73: 0 | M73: 0 | N73: =SUM(J73:M73) -> 0 | O73: 0 | P73: -2766 | Q73: 0 | R73: 418 | S73: =SUM(O73:R73) -> -2348 | T73: 575 | U73: 841 | V73: 0 | W73: 0 | X73: =SUM(T73:W73) -> 1416 | Y73: 0 | AC73: =SUM(Y73:AB73) -> 0 | AH73: =SUM(AD73:AG73) -> 0 | AM73: =SUM(AI73:AL73) -> 0 | AP73: 0 | AQ73: 0 | AT73: 0 | AU73: 0 | AV73: 0 | AW73: =SUM(AS73:AV73) -> 0 | BB73: =SUM(AX73:BA73) -> 0 | BG73: =SUM(BC73:BF73) -> 0 | BL73: =SUM(BH73:BK73) -> 0 | BQ73: =SUM(BM73:BP73) -> 0 | BT73: 0 | BU73: 0 | BV73: =SUM(BR73:BU73) -> 0 | CA73: =SUM(BW73:BZ73) -> 0
B74: Total GAAP Other Income (Expense) | D74: =SUM(D69:D73) -> -442 | E74: -151 | F74: -118 | G74: -151 | H74: -122 | I74: =SUM(E74:H74) -> -542 | J74: =SUM(J69:J73) -> -176 | K74: =SUM(K69:K73) -> -183 | L74: =SUM(L69:L73) -> -288 | M74: =SUM(M69:M72) -> -398 | N74: =SUM(J74:M74) -> -1045 | O74: =SUM(O69:O73) -> -695 | P74: =SUM(P69:P73) -> -3808 | Q74: =SUM(Q69:Q73) -> 1060 | R74: =SUM(R69:R73) -> -528 | S74: =SUM(S69:S73) -> -3971 | T74: =SUM(T69:T73) -> -478 | U74: =SUM(U69:U73) -> -927 | V74: =SUM(V69:V73) -> -1027 | ... X74: =SUM(X69:X73) -> -3512 | Y74: =SUM(Y69:Y72) -> -1153 | Z74: =SUM(Z69:Z73) -> -1143 | AA74: =SUM(AA69:AA73) -> -906 | AB74: =SUM(AB69:AB73) -> -795 | AC74: =SUM(AC69:AC73) -> -3997 | AD74: =SUM(AD69:AD73) -> -847 | AE74: =SUM(AE69:AE73) -> -836 | AF74: =SUM(AF69:AF73) -> -799 | AG74: =SUM(AG69:AG73) -> -785 | AH74: =SUM(AH69:AH72) -> -3267 | AI74: =SUM(AI69:AI73) -> -744 | AJ74: =SUM(AJ69:AJ73) -> -419 | AK74: =SUM(AK69:AK73) -> 895 | AL74: =SUM(AL69:AL73) -> -2103 | AM74: =SUM(AM69:AM72) -> -2371 | AN74: =SUM(AN69:AN73) -> -1651 | AO74: =SUM(AO69:AO73) -> -1916 | AP74: =SUM(AP69:AP73) -> -2026 | AQ74: =SUM(AQ69:AQ73) -> -2122 | AR74: =SUM(AR69:AR72) -> -7715 | AS74: =SUM(AS69:AS73) -> -2412 | AT74: =SUM(AT69:AT73) -> -10699 | AU74: =SUM(AU69:AU73) -> -9300 | AV74: =SUM(AV69:AV73) -> -9867 | AW74: =SUM(AS74:AV74) -> -32278 | AX74: =SUM(AX69:AX73) -> -1763 | AY74: =SUM(AY69:AY73) -> -2471 | AZ74: =SUM(AZ69:AZ73) -> -1734 | BA74: =SUM(BA69:BA73) -> -2067 | BB74: =SUM(BB69:BB72) -> -8035 | BC74: =SUM(BC69:BC73) -> -1025 | BD74: =SUM(BD69:BD73) -> -1577 | BE74: =SUM(BE69:BE73) -> -897 | BF74: =SUM(BF69:BF73) -> 819 | BG74: =SUM(BG69:BG72) -> -2680 | BH74: =SUM(BH69:BH73) -> 2276 | BI74: =SUM(BI69:BI73) -> 4257 | BJ74: =SUM(BJ69:BJ73) -> 6261 | BK74: =SUM(BK69:BK73) -> 6359 | BL74: =SUM(BL69:BL72) -> 19153 | BM74: =SUM(BM69:BM72) -> 14607 | BN74: =SUM(BN69:BN73) -> 9894 | BO74: =SUM(BO69:BO73) -> 7076 | BP74: =SUM(BP69:BP73) -> 6971 | BQ74: =SUM(BQ69:BQ72) -> 38548 | BR74: =SUM(BR69:BR73) -> 6188 | BS74: =SUM(BS69:BS73) -> 4097 | BT74: =SUM(BT69:BT73) -> 2573 | BU74: =SUM(BU69:BU73) -> 3234 | BV74: =SUM(BV69:BV72) -> 16092 | BW74: =SUM(BW69:BW73) -> 2400 | BX74: =SUM(BX69:BX73) -> 1700 | BY74: =SUM(BY69:BY73) -> 1500 | BZ74: =SUM(BZ69:BZ73) -> 1300 | CA74: =SUM(CA69:CA72) -> 6900
B76: Amor of discout & issuance costs on convert | AN76: 3079 | AO76: 3155 | AP76: 3250 | AQ76: 3304 | AR76: =+SUM(AN76:AQ76) -> 12788 | AS76: 3320 | AT76: 5251 | AU76: 8633 | AV76: 8534 | AW76: =+SUM(AS76:AV76) -> 25738 | AX76: 974 | AY76: 985 | AZ76: 1001 | BA76: 997 | BB76: =+SUM(AX76:BA76) -> 3957 | BC76: 930 | BD76: 922 | BE76: 944 | BF76: 947 | BG76: =+SUM(BC76:BF76) -> 3743 | BH76: 908 | BI76: 931 | BJ76: 954 | BK76: 956 | BL76: =+SUM(BH76:BK76) -> 3749 | BM76: 1074 | BN76: 1435 | BO76: 1482 | BP76: 1487 | BQ76: =+SUM(BM76:BP76) -> 5478 | BR76: 1407 | BS76: 1273 | BT76: 933 | BU76: 937 | BV76: =+SUM(BR76:BU76) -> 4550 | BW76: 1200 | BX76: 1200 | BY76: 1200 | BZ76: 1200 | CA76: =+SUM(BW76:BZ76) -> 4800
C77: Russian exit costs | BC77: -583 | BD77: 242 | BE77: =714-774 -> -60 | BF77: =3344-2975 -> 369 | BG77: =SUM(BC77:BF77) -> -32 | BH77: 144 | BI77: =1110-815 -> 295 | BJ77: 195 | BK77: =91-243 -> -152 | BL77: =+SUM(BH77:BK77) -> 482 | BM77: =94-25 -> 69 | BN77: =+-114-32 -> -146 | BO77: =176-21 -> 155 | BP77: =296+2202 -> 2498 | BQ77: =+SUM(BM77:BP77) -> 2576 | BR77: -376 | BS77: -169 | BT77: 105 | BU77: -33 | BV77: =SUM(BR77:BU77) -> -473
B78: Loss on early extinguishment of debt | AN78: -217 | AO78: 0 | AP78: 0 | AQ78: 0 | AR78: =+SUM(AN78:AQ78) -> -217 | AS78: 0 | AT78: 5794 | AU78: 283 | AV78: 887 | AW78: =+SUM(AS78:AV78) -> 6964 | AX78: 0 | BB78: =+SUM(AX78:BA78) -> 0 | BG78: =+SUM(BC78:BF78) -> 0 | BL78: =+SUM(BH78:BK78) -> 0 | BM78: -6615 | BO78: 1250 | BQ78: =+SUM(BM78:BP78) -> -5365 | BU78: 0 | BV78: =+SUM(BR78:BU78) -> 0 | CA78: =+SUM(BW78:BZ78) -> 0
B79: Total Non-GAAP Other Income (Expense) | AN79: =AN74+SUM(AN76:AN78) -> 1211 | AO79: =AO74+SUM(AO76:AO78) -> 1239 | AP79: =AP74+SUM(AP76:AP78) -> 1224 | AQ79: =AQ74+SUM(AQ76:AQ78) -> 1182 | AR79: =AR74+SUM(AR76:AR78) -> 4856 | AS79: =AS74+SUM(AS76:AS78) -> 908 | AT79: =AT74+SUM(AT76:AT78) -> 346 | AU79: =AU74+SUM(AU76:AU78) -> -384 | ... CA79: =CA74+SUM(CA76:CA78) -> 11700
C81: Lease amortization for finance leases | BJ81: 492 | BK81: 449 | BL81: =SUM(BH81:BK81) -> 941 | BM81: 457 | BN81: 455 | BO81: 951 | BP81: 1994 | BQ81: =SUM(BM81:BP81) -> 3857 | BR81: =4319-2311 -> 2008 | BS81: 2311 | BT81: 2300 | BU81: 0 | BV81: =SUM(BR81:BU81) -> 6619 | BW81: 2000 | BX81: 2000 | BY81: 2000 | BZ81: 2000 | CA81: =SUM(BW81:BZ81) -> 8000
C82: Impairment charge related to closure of operating lease facilities | BP82: 2202
B83: Adjusted EBITDA | D83: =D95+'Cash Flows'!D8+'Income Statement'!D93-D69+D64-D70-D53 -> -5858 | E83: =E95+'Cash Flows'!E8+'Income Statement'!E93-E69+E64-E70-E53 -> -2778.8903 | F83: =F95+'Cash Flows'!F8+'Income Statement'!F93-F69+F64-F70-F53 -> -3304.2605 | G83: =G95+'Cash Flows'!G8+'Income Statement'!G93-G69+G64-G70-G53 -> -3864.957 | H83: =H95+'Cash Flows'!H8+'Income Statement'!H93-H69+H64-H70-H53 -> -4559.5708 | I83: =I95+'Cash Flows'!I8+'Income Statement'!I93-I69+I64-I70-I53 -> -14507.679 | J83: =J95+'Cash Flows'!J8+'Income Statement'!J93-J69+J64-J70-J53 -> -5468.8752 | K83: =K95+'Cash Flows'!K8+'Income Statement'!K93-K69+K64-K70-K53 -> -6131.0988 | ... Y83: =Y95+'Cash Flows'!Y8+'Income Statement'!Y93-Y69+Y64-Y70-Y53 -> 458 | Z83: ='Cash Flows'!Z8+Z92-Z69+Z64-Z70-Z53 -> 2278 | AA83: ='Cash Flows'!AA8+AA92-AA69+AA64-AA70-AA53 -> 2741 | AB83: ='Cash Flows'!AB8+AB92-AB69+AB64-AB70-AB53 -> 2900 | AC83: ='Cash Flows'!AC8+AC92-AC69+AC64-AC70-AC53 -> 8377 | AD83: =AD95+'Cash Flows'!AD8+'Income Statement'!AD93-AD69+AD64-AD70-AD53 -> 2617 | AE83: =AE95+'Cash Flows'!AE8+'Income Statement'!AE93-AE69+AE64-AE70-AE53 -> 2965 | AF83: =AF95+'Cash Flows'!AF8+'Income Statement'!AF93-AF69+AF64-AF70-AF53 -> 5182 | AG83: =AG95+'Cash Flows'!AG8+'Income Statement'!AG93-AG69+AG64-AG70-AG53 -> 6875 | AH83: =AH95+'Cash Flows'!AH8+'Income Statement'!AH93-AH69+AH64-AH70-AH53 -> 17639 | AI83: =AI95+'Cash Flows'!AI8+'Income Statement'!AI93-AI69+AI64-AI70-AI53 -> 7495 | AJ83: =AJ95+'Cash Flows'!AJ8+'Income Statement'!AJ93-AJ69+AJ64-AJ70-AJ53 -> 9681 | AK83: =AK95+'Cash Flows'!AK8+'Income Statement'!AK93-AK69+AK64-AK70-AK53 -> 12773 | ... AS83: =AS95+'Cash Flows'!AS8+'Income Statement'!AS93-AS69+AS64-AS70-AS53 -> 14137 | AT83: =AT95+'Cash Flows'!AT8+'Income Statement'!AT93-AT69+AT64-AT70-AT53+AT73 -> 18259 | AU83: =AU95+'Cash Flows'!AU8+'Income Statement'!AU93-AU69+AU64-AU70-AU53+AU73 -> 24068 | AV83: =AV95+'Cash Flows'!AV8+'Income Statement'!AV93-AV69+AV64-AV70-AV53 -> 28330 | AW83: =SUM(AS83:AV83) -> 84794 | AX83: =AX95+'Cash Flows'!AX8+'Income Statement'!AX93-AX69+AX64-AX70-AX53 -> 22179 | AY83: =AY95+'Cash Flows'!AY8+'Income Statement'!AY93-AY69+AY64-AY70-AY53 -> 24031 | AZ83: =AZ95+'Cash Flows'!AZ8+'Income Statement'!AZ93-AZ69+AZ64-AZ70-AZ53 -> 27402 | BA83: =BA95+'Cash Flows'!BA8+'Income Statement'!BA93-BA69+BA64-BA70-BA53 -> 36891 | BB83: =BB95+'Cash Flows'!BB8+'Income Statement'!BB93-BB69+BB64-BB70-BB53 -> 110503 | BC83: =BC95+'Cash Flows'!BC8+'Income Statement'!BC93-BC69+BC64-BC70-BC53-105 -> 24475 | BD83: =BD95+'Cash Flows'!BD8+'Income Statement'!BD93-BD69+BD64-BD70-BD53-669 -> 33082 | BE83: =BE95+'Cash Flows'!BE8+'Income Statement'!BE93-BE69+BE64-BE70-BE53 -> 36705 | BF83: =BF95+'Cash Flows'!BF8+'Income Statement'!BF93-BF69+BF64-BF70-BF53 -> 46174 | BG83: =SUM(BC83:BF83) -> 140436 | BH83: =BH95+'Cash Flows'!BH8+'Income Statement'!BH93-BH69+BH64-BH70-BH53 -> 35145 | BI83: =BI95+'Cash Flows'!BI8+'Income Statement'!BI93-BI69+BI64-BI70-BI53 -> 41540 | BJ83: =BJ95+'Cash Flows'!BJ8+'Income Statement'!BJ93-BJ69+BJ64-BJ70-BJ53+BJ81 -> 41284 | BK83: =BK95+'Cash Flows'!BK8+'Income Statement'!BK93-BK69+BK64-BK70-BK53+BK81 -> 48297 | BL83: =BL95+'Cash Flows'!BL8+'Income Statement'!BL93-BL69+BL64-BL70-BL53+BL81 -> 166266 | BM83: =BM95+'Cash Flows'!BM8+'Income Statement'!BM93-BM69+BM64-BM70-BM53+BM81-BM72 -> 37586 | BN83: =BN95+'Cash Flows'!BN8+'Income Statement'!BN93-BN69+BN64-BN70-BN53+BN81-BN72 -> 41781 | BO83: =BO95+'Cash Flows'!BO8+'Income Statement'!BO93-BO69+BO64-BO70-BO53+BO81-BO72 -> 52360 | BP83: =BP95+'Cash Flows'!BP8+'Income Statement'!BP93-BP69+BP64-BP70-BP53+BP81-BP72+BP82 -> 64256 | BQ83: =BQ95+'Cash Flows'!BQ8+'Income Statement'!BQ93-BQ69+BQ64-BQ70-BQ53+BQ81 -> 200396 | BR83: =BR95+'Cash Flows'!BR8+'Income Statement'!BR93-BR69+BR64-BR70-BR53+BR81-BR72 -> 52703 | BS83: =BS95+'Cash Flows'!BS8+'Income Statement'!BS93-BS69+BS64-BS70-BS53+BS81-BS72 -> 67950 | BT83: =BT95+'Cash Flows'!BT8+'Income Statement'!BT93-BT69+BT64-BT70-BT53+BT81-BT72 -> 71720 | BU83: =BU95+'Cash Flows'!BU8+'Income Statement'!BU93-BU69+BU64-BU70-BU53+BU81-BU72 -> 75030 | BV83: =BV95+'Cash Flows'!BV8+'Income Statement'!BV93-BV69+BV64-BV70-BV53+BV81 -> 267403 | BW83: =BW95+'Cash Flows'!BW8+'Income Statement'!BW93-BW69+BW64-BW70-BW53+BW81-BW72 -> 63794.823 | BX83: =BX95+'Cash Flows'!BX8+'Income Statement'!BX93-BX69+BX64-BX70-BX53+BX81-BX72 -> 70982.377 | BY83: =BY95+'Cash Flows'!BY8+'Income Statement'!BY93-BY69+BY64-BY70-BY53+BY81-BY72 -> 76906.898 | BZ83: =BZ95+'Cash Flows'!BZ8+'Income Statement'!BZ93-BZ69+BZ64-BZ70-BZ53+BZ81-BZ72+BZ82 -> 88442.673 | CA83: =CA95+'Cash Flows'!CA8+'Income Statement'!CA93-CA69+CA64-CA70-CA53+CA81 -> 300126.77
C84: EBITDA Margins | D84: =D83/D28 -> -0.13563953 | E84: =E83/E28 -> -0.19404154 | F84: =F83/F28 -> -0.21987741 | G84: =G83/G28 -> -0.23854751 | H84: =H83/H28 -> -0.24954648 | I84: =I83/I28 -> -0.22731355 | J84: =J83/J28 -> -0.28610199 | K84: =K83/K28 -> -0.30227918 | ... CA84: =CA83/CA28 -> 0.23882484
Y85: =458-Y83 -> 0
B86: Non-GAAP Pre-Tax Income | D86: =D49+D74 -> -7396 | E86: =E49+E74 -> -3287.8903 | F86: =F49+F74 -> -3852.2605 | G86: =G49+G74 -> -4532.957 | H86: =H49+H74 -> -5458.5708 | I86: =I49+I74 -> -17131.679 | J86: =J49+J74 -> -6603.8752 | K86: =K49+K74 -> -7196.0988 | ... AM86: =AM49+AM74 -> 34156 | AN86: =AN49+AN79 -> 9955 | AO86: =AO49+AO79 -> 12332 | AP86: =AP49+AP79 -> 12859 | AQ86: =AQ49+AQ79 -> 17038 | AR86: =AR49+AR74 -> 39613 | AS86: =AS49+AS79 -> 11165 | AT86: =AT49+AT79 -> 14100 | AU86: =AU49+AU79 -> 18885 | AV86: =AV49+AV79 -> 23717 | AW86: =SUM(AS86:AV86) -> 67867 | AX86: =AX49+AX79 -> 15574 | AY86: =AY49+AY79 -> 15841 | AZ86: =AZ49+AZ79 -> 19836 | BA86: =BA49+BA79 -> 28230 | BB86: =BB49+BB79 -> 79481 | BC86: =BC49+BC79 -> 16054 | BD86: =BD49+BD79 -> 24633 | BE86: =BE49+BE79 -> 28411 | ... CA86: =CA49+CA79 -> 254939.24
C87: Income Tax | D87: 64 | E87: 21 | F87: 10 | G87: 22 | H87: 9 | I87: =SUM(E87:H87) -> 62 | J87: 19 | K87: 5 | L87: 45 | M87: 1 | N87: =SUM(J87:M87) -> 70 | O87: =27 -> 27 | P87: 12 | Q87: 13 | R87: 33 | S87: =SUM(O87:R87) -> 85 | T87: 18 | U87: -20 | V87: 50 | W87: 13 | X87: =SUM(T87:W87) -> 61 | Y87: 28 | Z87: 42 | AA87: -2 | AB87: -14 | AC87: =SUM(Y87:AB87) -> 54 | AD87: 49 | AE87: 50 | AF87: 43 | AG87: 126 | AH87: =SUM(AD87:AG87) -> 268 | AI87: 45 | AJ87: 64 | AK87: 41 | AL87: 150 | AM87: =SUM(AI87:AL87) -> 300 | AN87: -49 | AO87: 29 | AP87: 50 | AQ87: 74 | AR87: =SUM(AN87:AQ87) -> 104 | AS87: 69 | AT87: =AT93+2910 -> 34 | AU87: =AU93 -> 346 | AV87: =AV93 -> 8 | AW87: =SUM(AS87:AV87) -> 457 | AX87: -517 | AY87: -135 | AZ87: -188 | BA87: =BA93+8573 -> -1872 | BB87: =SUM(AX87:BA87) -> -2712 | BC87: =BC93+-1830 -> 426 | BD87: 332 | BE87: 579 | BF87: 1221 | BG87: =SUM(BC87:BF87) -> 2558 | BH87: 527 | BI87: 753 | BJ87: 942 | BK87: 119 | BL87: =SUM(BH87:BK87) -> 2341 | BM87: 989 | BN87: =+BN93 -> 3345 | BO87: =+BO93+4831 -> 963 | BP87: =-426+650 -> 224 | BQ87: =SUM(BM87:BP87) -> 5521 | BR87: 184 | BS87: 1382 | BT87: =643-524 -> 119 | BU87: =BU93 -> 3317 | BV87: =SUM(BR87:BU87) -> 5002 | BW87: 1000 | BX87: 1000 | BY87: 1000 | BZ87: 1000 | CA87: =SUM(BW87:BZ87) -> 4000
C88: Tax Rate % | D88: =D87/D86 -> -0.0086533261 | E88: =E87/E86 -> -0.0063870745 | F88: =F87/F86 -> -0.0025958785 | G88: =G87/G86 -> -0.004853344 | H88: =H87/H86 -> -0.0016487832 | I88: =I87/I86 -> -0.0036190266 | J88: =J87/J86 -> -0.0028770986 | K88: =K87/K86 -> -0.00069482092 | ... CA88: =CA87/CA86 -> 0.015690013
B89: Non-GAAP Net Income (Loss) | D89: =D86-D87 -> -7460 | E89: =E86-E87 -> -3308.8903 | F89: =F86-F87 -> -3862.2605 | G89: =G86-G87 -> -4554.957 | H89: =H86-H87 -> -5467.5708 | I89: =I86-I87 -> -17193.679 | J89: =J86-J87 -> -6622.8752 | K89: =K86-K87 -> -7201.0988 | ... CA89: =CA86-CA87 -> 250939.24
C90: Non-GAAP Net Margin | D90: =D89/D28 -> -0.17273317 | E90: =E89/E28 -> -0.23104985 | F90: =F89/F28 -> -0.25700874 | G90: =G89/G28 -> -0.28113473 | H90: =H89/H28 -> -0.29924155 | I90: =I89/I28 -> -0.26939914 | J90: =J89/J28 -> -0.34647303 | K90: =K89/K28 -> -0.35503298 | ... CA90: =CA89/CA28 -> 0.19968403
AA91: =-173-AA89 -> 0 | AT91: =+AT89-14066 -> 0 | BD91: =24301-BD89 -> 0
B92: GAAP Pre-Tax Income | D92: =D66+D74 -> -7808 | E92: =E66+E74 -> -3486.1656 | F92: =F66+F74 -> -4630.4095 | G92: =G66+G74 -> -5382.2338 | H92: =H66+H74 -> -5771.1411 | I92: =I66+I74 -> -19269.95 | J92: =J66+J74 -> -6637.7411 | K92: =K66+K74 -> -8285.2699 | ... AS92: =AS66+AS74 -> -7368 | AT92: =AT66+AT74-AT73 -> -18928 | AU92: =AU66+AU74 -> -11085 | AV92: =AV66+AV74 -> -7202 | AW92: =SUM(AS92:AV92) -> -44583 | AX92: =AX66+AX74 -> -12849 | AY92: =AY66+AY74 -> -16665 | AZ92: =AZ66+AZ74 -> -20725 | BA92: =BA66+BA74 -> -14046 | BB92: =BB66+BB74 -> -64285 | BC92: =BC66+BC74 -> -31864 | BD92: =BD66+BD74 -> -23338 | BE92: =BE66+BE74 -> -22628 | ... CA92: =CA66+CA74 -> 75739.241
C93: Income Tax | D93: 64 | E93: 21 | F93: 10 | G93: 22 | H93: 9 | I93: =SUM(E93:H93) -> 62 | J93: 19 | K93: 5 | L93: 45 | M93: 1 | N93: =SUM(J93:M93) -> 70 | O93: 27 | P93: 12 | Q93: 13 | R93: 33 | S93: =SUM(O93:R93) -> 85 | T93: 18 | U93: -20 | V93: 50 | W93: 13 | X93: =SUM(T93:W93) -> 61 | Y93: 28 | Z93: 42 | AA93: -2 | AB93: -14 | AC93: =SUM(Y93:AB93) -> 54 | AD93: 49 | AE93: =AE87 -> 50 | AF93: 43 | AG93: 126 | AH93: =SUM(AD93:AG93) -> 268 | AI93: 45 | AJ93: 64 | AK93: 41 | AL93: 150 | AM93: =SUM(AI93:AL93) -> 300 | AN93: -49 | AO93: =AO87 -> 29 | AP93: 50 | AQ93: =AQ87 -> 74 | AR93: =SUM(AN93:AQ93) -> 104 | AS93: 69 | AT93: -2876 | AU93: 346 | AV93: 8 | AW93: =SUM(AS93:AV93) -> -2453 | AX93: =AX87 -> -517 | AY93: -135 | AZ93: =AZ87 -> -188 | BA93: -10445 | BB93: =SUM(AX93:BA93) -> -11285 | BC93: 2256 | BD93: =BD87 -> 332 | BE93: =BE87 -> 579 | BF93: 1221 | BG93: =SUM(BC93:BF93) -> 4388 | BH93: 527 | BI93: 753 | BJ93: 942 | BK93: 119 | BL93: =SUM(BH93:BK93) -> 2341 | BM93: 989 | BN93: 3345 | BO93: -3868 | BP93: -426 | BQ93: =SUM(BM93:BP93) -> 40 | BR93: =BR87 -> 184 | BS93: 1382 | BT93: 643 | BU93: 3317 | BV93: =SUM(BR93:BU93) -> 5526 | BW93: =BW87 -> 1000 | BX93: =BX87 -> 1000 | BY93: =BY87 -> 1000 | BZ93: =BZ87 -> 1000 | CA93: =SUM(BW93:BZ93) -> 4000
C94: Tax Rate % | D94: =D93/D92 -> -0.0081967213 | E94: =E93/E92 -> -0.0060238102 | F94: =F93/F92 -> -0.0021596362 | G94: =G93/G92 -> -0.0040875222 | H94: =H93/H92 -> -0.0015594836 | I94: =I93/I92 -> -0.0032174448 | J94: =J93/J92 -> -0.0028624196 | K94: =K93/K92 -> -0.00060348064 | ... S94: =S93/S92 -> -0.0022545821 | T94: 0.38 | U94: =U93/U92 -> 0.0027067262 | V94: =V93/V92 -> -0.008336112 | W94: =W93/W92 -> -0.0037089872 | X94: =X93/X92 -> -0.0023664507 | Y94: =Y93/Y92 -> -0.0057341798 | Z94: =Z93/Z92 -> -0.012259194 | AA94: =AA93/AA92 -> 0.00051387461 | AB94: =AB93/AB92 -> -0.035443038 | ... CA94: =CA93/CA92 -> 0.052812782
B95: GAAP Net Income | D95: =D92-D93 -> -7872 | E95: =E92-E93 -> -3507.1656 | F95: =F92-F93 -> -4640.4095 | G95: =G92-G93 -> -5404.2338 | H95: =H92-H93 -> -5780.1411 | I95: =I92-I93 -> -19331.95 | J95: =J92-J93 -> -6656.7411 | K95: =K92-K93 -> -8290.2699 | ... CA95: =CA92-CA93 -> 71739.241
C96: GAAP Net Margin | D96: =D95/D28 -> -0.18227285 | E96: =E95/E28 -> -0.24489482 | F96: =F95/F28 -> -0.30878959 | G96: =G95/G28 -> -0.33355261 | H96: =H95/H28 -> -0.3163486 | I96: =I95/I28 -> -0.30290264 | J96: =J95/J28 -> -0.34824471 | K96: =K95/K28 -> -0.40873196 | ... CA96: =CA95/CA28 -> 0.057086252
B98: Non-GAAP EPS | D98: =IF(D89>0,D89/D104,D89/D103) -> -2.8316569 | E98: =IF(E89>0,E89/E104,E89/E103) -> -0.99635359 | F98: =IF(F89>0,F89/F104,F89/F103) -> -1.1629812 | G98: =IF(G89>0,G89/G104,G89/G103) -> -1.3715619 | H98: =IF(H89>0,H89/H104,H89/H103) -> -1.6463628 | I98: =IF(I89>0,I89/I104,I89/I103) -> -5.1772594 | J98: =IF(J89>0,J89/J104,J89/J103) -> -1.8729851 | K98: =IF(K89>0,K89/K104,K89/K103) -> -1.9546957 | ... X98: =IF(X89>0,X89/X104,X89/X103) -> -0.32872259 | Y98: =Y89/Y103 -> -0.052513771 | Z98: =Z89/Z103 -> -0.016090367 | AA98: =AA89/AA103 -> -0.0032822342 | AB98: =AB89/AB103 -> 0.0027858299 | AC98: =AC89/AC103 -> -0.068056975 | AD98: =IF(AD89>0,AD89/AD104,AD89/AD103) -> -0.004786917 | AE98: =IF(AE89>0,AE89/AE104,AE89/AE103) -> -0.001352265 | AF98: =IF(AF89>0,AF89/AF104,AF89/AF103) -> 0.043303444 | AG98: =IF(AG89>0,AG89/AG104,AG89/AG103) -> 0.066972707 | AH98: =IF(AH89>0,AH89/AH104,AH89/AH103) -> 0.10985392 | AI98: =IF(AI89>0,AI89/AI104,AI89/AI103) -> 0.075354847 | AJ98: =IF(AJ89>0,AJ89/AJ104,AJ89/AJ103) -> 0.1123476 | AK98: =IF(AK89>0,AK89/AK104,AK89/AK103) -> 0.17866994 | ... CA98: =IF(CA89>0,CA89/CA104,CA89/CA103) -> 3.1815204
C99: Y/Y Growth % | S99: =S98/N98-1 -> -0.8738514 | T99: =T98/O98-1 -> -0.92322454 | U99: =U98/P98-1 -> -0.49269023 | V99: =V98/Q98-1 -> -0.49283619 | W99: =W98/R98-1 -> -0.77524464 | X99: =X98/S98-1 -> -0.61906431 | Y99: =Y98/T98-1 -> -0.55859323 | Z99: =Z98/U98-1 -> -0.84335868 | ... CA99: =CA98/BV98-1 -> 0.075062201
B100: GAAP EPS | D100: =D95/D104 -> -2.9880433 | E100: =E95/E104 -> -0.11668479 | F100: =F95/F104 -> -0.15438826 | G100: =G95/G104 -> -0.179801 | H100: =H95/H104 -> -0.19230759 | I100: =I95/I104 -> -0.64318165 | J100: =J95/J104 -> -1.8825625 | K100: =K95/K104 -> -2.2503447 | ... M100: =M95/M104 -> -1.7219445 | N100: =N95/N103 -> -7.8224242 | O100: =O95/O104 -> -0.8 | P100: =P95/P104 -> -0.18463474 | Q100: =Q95/Q104 -> -0.23670048 | R100: =R95/R104 -> -0.1912536 | S100: =S95/S103 -> -1.008844 | T100: =T95/T103 -> -0.18010236 | U100: =U95/U103 -> -0.14743898 | V100: =V95/V103 -> -0.12007385 | W100: =W95/W103 -> -0.06930108 | X100: =X95/X103 -> -0.51535309 | Y100: =Y95/Y103 -> -0.09558752 | Z100: =Z95/Z103 -> -0.066509407 | ... AC100: =AC95/AC103 -> -0.22660183 | AD100: =AD95/AD104 -> -0.097880346 | AE100: =AE95/AE104 -> -0.073223325 | AF100: =AF95/AF104 -> 0.015544826 | AG100: =AG95/AG104 -> -0.010533344 | AH100: =AH95/AH104 -> -0.15751876 | AI100: =AI95/AI104 -> -0.010160016 | AJ100: =AJ95/AJ104 -> -0.033417887 | AK100: =AK95/AK104 -> -0.021049406 | ... AU100: =AU95/AU104 -> -0.17462573 | AV100: =AV95/AV103 -> -0.10902273 | AW100: =AW95/AW103 -> -0.6567932 | AX100: =AX95/AX104 -> -0.17452837 | AY100: =AY95/AY103 -> -0.24564584 | AZ100: =AZ95/AZ103 -> -0.3029056 | BA100: =BA95/BA104 -> -0.05080561 | BB100: =BB95/BB103 -> -0.78512703 | BC100: =BC95/BC104 -> -0.48280058 | BD100: =BD95/BD104 -> -0.33299101 | BE100: =BE95/BE104 -> -0.32484148 | BF100: =BF95/BF104 -> -0.19085229 | BG100: =BG95/BG104 -> -1.3296714 | BH100: =BH95/BH104 -> -0.376704 | BI100: =BI95/BI104 -> -0.29943526 | BJ100: =BJ95/BJ104 -> -0.27932969 | ... CA100: =CA95/CA104 -> 0.90954232
C101: Y/Y Growth % | S101: =S100/N100-1 -> -0.8710318 | T101: =T100/O100-1 -> -0.77487205 | U101: =U100/P100-1 -> -0.20145593 | V101: =V100/Q100-1 -> -0.49271815 | W101: =W100/R100-1 -> -0.63764823 | X101: =X100/S100-1 -> -0.48916474 | Y101: =Y100/T100-1 -> -0.46926004 | Z101: =Z100/U100-1 -> -0.54890214 | ... CA101: =CA100/BV100-1 -> 0.78289654
C103: Basic Shares Outstanding | D103: 2634.5 | E103: 3321 | F103: 3321 | G103: 3321 | H103: 3321 | I103: 3321 | J103: 3536 | K103: 3684 | L103: 3779 | M103: 5013 | N103: =AVERAGE(J103:M103) -> 4003 | O103: 5608 | P103: 46898 | Q103: 48310 | R103: 49003 | S103: =AVERAGE(O103:R103) -> 37454.75 | T103: 49433 | U103: 49980 | V103: 50369 | W103: 50764 | X103: =AVERAGE(T103:W103) -> 50136.5 | Y103: 51377 | Z103: 52143 | AA103: 52708 | AB103: 53126 | AC103: =AVERAGE(Y103:AB103) -> 52338.5 | AD103: 53688 | AE103: 54723 | AF103: 55310 | AG103: 56034 | AH103: =AVERAGE(AD103:AG103) -> 54938.75 | AI103: 56399 | AJ103: 57903 | AK103: 58454 | AL103: 58926 | AM103: =AVERAGE(AI103:AL103) -> 57920.5 | AN103: 59367 | AO103: 60058 | AP103: 60781 | AQ103: 61253 | AR103: =AVERAGE(AN103:AQ103) -> 60364.75 | AS103: 61705 | AT103: 63282 | AU103: 65460 | AV103: 66133 | AW103: =AVERAGE(AS103:AV103) -> 64145 | AX103: 66721 | AY103: 67292 | AZ103: 67800 | BA103: 68207 | BB103: =AVERAGE(AX103:BA103) -> 67505 | BC103: 68974 | BD103: 69748 | BE103: 70232 | BF103: 70704 | BG103: =AVERAGE(BC103:BF103) -> 69914.5 | BH103: 71259 | BI103: 71627 | BJ103: 72356 | BK103: 72926 | BL103: =AVERAGE(BH103:BK103) -> 72042 | BM103: 73488 | BN103: 74203 | BO103: 74876 | BP103: 75430 | BQ103: =AVERAGE(BM103:BP103) -> 74499.25 | BR103: 75949 | BS103: 76654 | BT103: 77528 | BU103: 77509 | BV103: =AVERAGE(BR103:BU103) -> 76910 | BW103: =+BU103+500 -> 78009 | BX103: =BW103+500 -> 78509 | BY103: =BX103+500 -> 79009 | BZ103: =BY103+500 -> 79509 | CA103: =AVERAGE(BW103:BZ103) -> 78759
C104: Diluted Shares Outstanding | D104: 2634.5 | E104: 30056.75 | F104: 30056.75 | G104: 30056.75 | H104: 30056.75 | I104: 30056.75 | J104: 3536 | K104: 3684 | L104: 3779 | M104: 5013 | N104: =AVERAGE(J104:M104) -> 4003 | O104: 10400 | P104: 46898 | Q104: 48310 | R104: 49003 | S104: =AVERAGE(O104:R104) -> 38652.75 | T104: 49433 | U104: 49980 | V104: 50369 | W104: 50764 | X104: =AVERAGE(T104:W104) -> 50136.5 | Y104: 51377 | Z104: 52143 | AA104: 52708 | AB104: 56633 | AC104: =AVERAGE(Y104:AB104) -> 53215.25 | AD104: 53688 | AE104: 54723 | AF104: 59441 | AG104: 59905 | AH104: =AVERAGE(AD104:AG104) -> 56939.25 | AI104: 59744 | AJ104: 61105 | AK104: 61997 | AL104: 62071 | AM104: =AVERAGE(AI104:AL104) -> 61229.25 | AN104: 62754 | AO104: 62950 | AP104: 63438 | AQ104: 63853 | AR104: =AVERAGE(AN104:AQ104) -> 63248.75 | AS104: 65161 | AT104: 67171 | AU104: 65460 | AV104: 70320 | AW104: 68040 | AX104: 70659 | AY104: 70774 | AZ104: 71102 | BA104: 70878 | BB104: =AVERAGE(AX104:BA104) -> 70853.25 | BC104: 70671 | BD104: 71083 | BE104: 71441 | BF104: 71537 | BG104: =AVERAGE(BC104:BF104) -> 71183 | BH104: 72330 | BI104: 72600 | BJ104: =BI104+500 -> 73100 | BK104: 73785 | BL104: =AVERAGE(BH104:BK104) -> 72953.75 | BM104: 74404 | BN104: 74647 | BO104: 75137 | BP104: 75999 | BQ104: =AVERAGE(BM104:BP104) -> 75046.75 | BR104: 76629 | BS104: 76919 | BT104: 77883 | BU104: 77624 | BV104: =AVERAGE(BR104:BU104) -> 77263.75 | BW104: =+BU104+500 -> 78124 | BX104: =BW104+500 -> 78624 | BY104: =BX104+500 -> 79124 | BZ104: =BY104+500 -> 79624 | CA104: =AVERAGE(BW104:BZ104) -> 78874
C106: Deferred Revenue | J106: ='Balance Sheet '!J56 -> 4150 | K106: ='Balance Sheet '!K56 -> 4482 | L106: ='Balance Sheet '!L56 -> 4594 | M106: ='Balance Sheet '!M56 -> 4375 | O106: ='Balance Sheet '!O56 -> 4957 | P106: ='Balance Sheet '!P56 -> 5009 | Q106: ='Balance Sheet '!Q56 -> 4991 | R106: ='Balance Sheet '!R56 -> 5346 | T106: ='Balance Sheet '!T56 -> 5641 | U106: ='Balance Sheet '!U56 -> 5525 | V106: ='Balance Sheet '!V56 -> 5562 | W106: ='Balance Sheet '!W56 -> 6413 | Y106: ='Balance Sheet '!Y56 -> 7832 | Z106: ='Balance Sheet '!Z56 -> 7898 | AA106: ='Balance Sheet '!AA56 -> 8838 | AB106: ='Balance Sheet '!AB56 -> 10047 | AD106: ='Balance Sheet '!AD56 -> 10920 | AE106: ='Balance Sheet '!AE56 -> 11903 | AF106: ='Balance Sheet '!AF56 -> 13699 | AG106: ='Balance Sheet '!AG56 -> 13975 | AI106: ='Balance Sheet '!AI56 -> 13700 | AJ106: ='Balance Sheet '!AJ56 -> 14750 | AK106: ='Balance Sheet '!AK56 -> 17490 | AL106: ='Balance Sheet '!AL56 -> 17391 | AN106: ='Balance Sheet '!AN56 -> 17853 | AO106: ='Balance Sheet '!AO56 -> 19991 | AP106: ='Balance Sheet '!AP56 -> 21858 | AQ106: ='Balance Sheet '!AQ56 -> 24681 | AS106: ='Balance Sheet '!AS56 -> 25632 | AT106: ='Balance Sheet '!AT56 -> 26306 | AU106: ='Balance Sheet '!AU56 -> 28527 | AV106: ='Balance Sheet '!AV56 -> 31983 | AX106: ='Balance Sheet '!AX56 -> 32835 | AY106: ='Balance Sheet '!AY56 -> 33237 | AZ106: ='Balance Sheet '!AZ56 -> 36887 | BA106: ='Balance Sheet '!BA56 -> 43720 | BC106: ='Balance Sheet '!BC56 -> 46564 | BD106: ='Balance Sheet '!BD56 -> 51553 | BE106: ='Balance Sheet '!BE56 -> 53834 | BF106: ='Balance Sheet '!BF56 -> 57816 | BH106: ='Balance Sheet '!BH56 -> 58082 | BI106: ='Balance Sheet '!BI56 -> 57539 | BJ106: ='Balance Sheet '!BJ56 -> 64565 | BK106: ='Balance Sheet '!BK56 -> 68187 | BM106: ='Balance Sheet '!BM56 -> 67019 | BN106: ='Balance Sheet '!BN56 -> 65286 | BO106: ='Balance Sheet '!BO56 -> 80000 | BP106: ='Balance Sheet '!BP56 -> 79173 | BR106: ='Balance Sheet '!BR56 -> 74809 | BS106: ='Balance Sheet '!BS56 -> 68009 | BT106: ='Balance Sheet '!BT56 -> 74737 | BU106: ='Balance Sheet '!BU56 -> 77515
C107: Cash Flow-Operating | J107: ='Cash Flows'!J42 -> -3842.7411 | K107: ='Cash Flows'!K42 -> -5981.2699 | L107: ='Cash Flows'!L42 -> -5602.0455 | M107: ='Cash Flows'!M42 -> -5532.1076 | N107: ='Cash Flows'!N42 -> -20958.164 | O107: ='Cash Flows'!O42 -> -6180 | P107: ='Cash Flows'!P42 -> -8218 | Q107: ='Cash Flows'!Q42 -> -6361 | ... BF107: ='Cash Flows'!BF42 -> 32740 | BH107: ='Cash Flows'!BH42 -> 33413 | BI107: ='Cash Flows'!BI42 -> 21851 | BJ107: ='Cash Flows'!BJ42 -> 37030 | BK107: ='Cash Flows'!BK42 -> 36544 | BM107: ='Cash Flows'!BM42 -> 32353 | BN107: ='Cash Flows'!BN42 -> 19878 | BO107: ='Cash Flows'!BO42 -> 41122 | BP107: ='Cash Flows'!BP42 -> 49815 | BR107: ='Cash Flows'!BR42 -> 48384 | BS107: ='Cash Flows'!BS42 -> 35061 | BT107: ='Cash Flows'!BT42 -> 59196 | BU107: ='Cash Flows'!BU42 -> 83566
C108: Gross Cash | O108: ='Balance Sheet '!O6+'Balance Sheet '!O7 -> 29238 | P108: ='Balance Sheet '!P6+'Balance Sheet '!P7 -> 91572 | Q108: ='Balance Sheet '!Q6+'Balance Sheet '!Q7 -> 83488 | R108: ='Balance Sheet '!R6+'Balance Sheet '!R7 -> 78289 | T108: ='Balance Sheet '!T6+'Balance Sheet '!T7 -> 70645 | U108: ='Balance Sheet '!U6+'Balance Sheet '!U7 -> 65333 | V108: ='Balance Sheet '!V6+'Balance Sheet '!V7 -> 59501 | W108: ='Balance Sheet '!W6+'Balance Sheet '!W7 -> 58484 | Y108: ='Balance Sheet '!Y6+'Balance Sheet '!Y7 -> 57767 | Z108: ='Balance Sheet '!Z6+'Balance Sheet '!Z7 -> 57638 | AA108: ='Balance Sheet '!AA6+'Balance Sheet '!AA7 -> 57333 | AB108: ='Balance Sheet '!AB6+'Balance Sheet '!AB7 -> 58122 | AD108: ='Balance Sheet '!AD6+'Balance Sheet '!AD7 -> 56452 | AE108: ='Balance Sheet '!AE6+'Balance Sheet '!AE7 -> 57149 | AF108: ='Balance Sheet '!AF6+'Balance Sheet '!AF7 -> 63364 | AG108: ='Balance Sheet '!AG6+'Balance Sheet '!AG7 -> 68947 | AI108: ='Balance Sheet '!AI6+'Balance Sheet '!AI7 -> 80676 | AJ108: ='Balance Sheet '!AJ6+'Balance Sheet '!AJ7 -> 274302 | AK108: ='Balance Sheet '!AK6+'Balance Sheet '!AK7 -> 279626 | AL108: ='Balance Sheet '!AL6+'Balance Sheet '!AL7 -> 291819 | AN108: ='Balance Sheet '!AN6+'Balance Sheet '!AN7 -> 298942 | AO108: ='Balance Sheet '!AO6+'Balance Sheet '!AO7 -> 307476 | AP108: ='Balance Sheet '!AP6+'Balance Sheet '!AP7 -> 320958 | AQ108: ='Balance Sheet '!AQ6+'Balance Sheet '!AQ7 -> 319949 | AS108: ='Balance Sheet '!AS6+'Balance Sheet '!AS7 -> 326296 | AT108: ='Balance Sheet '!AT6+'Balance Sheet '!AT7 -> 685943 | AU108: ='Balance Sheet '!AU6+'Balance Sheet '!AU7 -> 780908 | AV108: ='Balance Sheet '!AV6+'Balance Sheet '!AV7 -> 766342 | AX108: ='Balance Sheet '!AX6+'Balance Sheet '!AX7 -> 643469 | AY108: ='Balance Sheet '!AY6+'Balance Sheet '!AY7 -> 566185 | AZ108: ='Balance Sheet '!AZ6+'Balance Sheet '!AZ7 -> 415289 | BA108: ='Balance Sheet '!BA6+'Balance Sheet '!BA7 -> 469858 | BC108: ='Balance Sheet '!BC6+'Balance Sheet '!BC7 -> 477670 | BD108: ='Balance Sheet '!BD6+'Balance Sheet '!BD7 -> 498382 | BE108: ='Balance Sheet '!BE6+'Balance Sheet '!BE7 -> 577104 | BF108: ='Balance Sheet '!BF6+'Balance Sheet '!BF7 -> 614263 | BH108: ='Balance Sheet '!BH6+'Balance Sheet '!BH7 -> 629740 | BI108: ='Balance Sheet '!BI6+'Balance Sheet '!BI7 -> 659836 | BJ108: ='Balance Sheet '!BJ6+'Balance Sheet '!BJ7 -> 700290 | BK108: ='Balance Sheet '!BK6+'Balance Sheet '!BK7 -> 730297 | BM108: ='Balance Sheet '!BM6+'Balance Sheet '!BM7 -> 1083402 | BN108: ='Balance Sheet '!BN6+'Balance Sheet '!BN7 -> 1106338 | BO108: ='Balance Sheet '!BO6+'Balance Sheet '!BO7 -> 966663 | BP108: ='Balance Sheet '!BP6+'Balance Sheet '!BP7 -> 1005956 | BR108: ='Balance Sheet '!BR6+'Balance Sheet '!BR7 -> 1041738 | BS108: ='Balance Sheet '!BS6+'Balance Sheet '!BS7 -> 635876 | BT108: ='Balance Sheet '!BT6+'Balance Sheet '!BT7 -> 676156 | BU108: ='Balance Sheet '!BU6+'Balance Sheet '!BU7 -> 696919
C109: Net Cash | J109: ='Balance Sheet '!J6 -> 5475 | K109: ='Balance Sheet '!K6 -> 17742 | L109: ='Balance Sheet '!L6 -> 10110 | M109: ='Balance Sheet '!M6 -> 17748 | O109: ='Balance Sheet '!O6+'Balance Sheet '!O7-'Balance Sheet '!O27-'Balance Sheet '!O29-'Balance Sheet '!O34-'Balance Sheet '!O39 -> -10261 | P109: ='Balance Sheet '!P6+'Balance Sheet '!P7-'Balance Sheet '!P27-'Balance Sheet '!P29-'Balance Sheet '!P34-'Balance Sheet '!P39 -> 52252 | Q109: ='Balance Sheet '!Q6+'Balance Sheet '!Q7-'Balance Sheet '!Q27-'Balance Sheet '!Q29-'Balance Sheet '!Q34-'Balance Sheet '!Q39 -> 44350 | R109: ='Balance Sheet '!R6+'Balance Sheet '!R7-'Balance Sheet '!R27-'Balance Sheet '!R29-'Balance Sheet '!R34-'Balance Sheet '!R39 -> 39865 | T109: ='Balance Sheet '!T6+'Balance Sheet '!T7-'Balance Sheet '!T27-'Balance Sheet '!T29-'Balance Sheet '!T34-'Balance Sheet '!T39 -> 32919 | U109: ='Balance Sheet '!U6+'Balance Sheet '!U7-'Balance Sheet '!U27-'Balance Sheet '!U29-'Balance Sheet '!U34-'Balance Sheet '!U39 -> 26635 | V109: ='Balance Sheet '!V6+'Balance Sheet '!V7-'Balance Sheet '!V27-'Balance Sheet '!V29-'Balance Sheet '!V34-'Balance Sheet '!V39 -> 21724 | W109: ='Balance Sheet '!W6+'Balance Sheet '!W7-'Balance Sheet '!W27-'Balance Sheet '!W29-'Balance Sheet '!W34-'Balance Sheet '!W39 -> 21445 | Y109: ='Balance Sheet '!Y6+'Balance Sheet '!Y7-'Balance Sheet '!Y27-'Balance Sheet '!Y29-'Balance Sheet '!Y34-'Balance Sheet '!Y39 -> 22248 | Z109: ='Balance Sheet '!Z6+'Balance Sheet '!Z7-'Balance Sheet '!Z27-'Balance Sheet '!Z29-'Balance Sheet '!Z34-'Balance Sheet '!Z39 -> 23990 | AA109: ='Balance Sheet '!AA6+'Balance Sheet '!AA7-'Balance Sheet '!AA27-'Balance Sheet '!AA29-'Balance Sheet '!AA34-'Balance Sheet '!AA39 -> 23199 | AB109: ='Balance Sheet '!AB6+'Balance Sheet '!AB7-'Balance Sheet '!AB27-'Balance Sheet '!AB29-'Balance Sheet '!AB34-'Balance Sheet '!AB39 -> 24468 | AD109: ='Balance Sheet '!AD6+'Balance Sheet '!AD7-'Balance Sheet '!AD27-'Balance Sheet '!AD29-'Balance Sheet '!AD34-'Balance Sheet '!AD39 -> 23053 | AE109: ='Balance Sheet '!AE6+'Balance Sheet '!AE7-'Balance Sheet '!AE27-'Balance Sheet '!AE29-'Balance Sheet '!AE34-'Balance Sheet '!AE39 -> 23892 | AF109: ='Balance Sheet '!AF6+'Balance Sheet '!AF7-'Balance Sheet '!AF27-'Balance Sheet '!AF29-'Balance Sheet '!AF34-'Balance Sheet '!AF39 -> 30284 | AG109: ='Balance Sheet '!AG6+'Balance Sheet '!AG7-'Balance Sheet '!AG27-'Balance Sheet '!AG29-'Balance Sheet '!AG34-'Balance Sheet '!AG39 -> 36017 | AI109: ='Balance Sheet '!AI6+'Balance Sheet '!AI7-'Balance Sheet '!AI27-'Balance Sheet '!AI29-'Balance Sheet '!AI34-'Balance Sheet '!AI39 -> 47902 | AJ109: ='Balance Sheet '!AJ6+'Balance Sheet '!AJ7-258750 -> 15552 | AK109: ='Balance Sheet '!AK6+'Balance Sheet '!AK7-258750 -> 20876 | AL109: ='Balance Sheet '!AL6+'Balance Sheet '!AL7-258750 -> 33069 | AN109: ='Balance Sheet '!AN6+'Balance Sheet '!AN7-258750 -> 40192 | AO109: ='Balance Sheet '!AO6+'Balance Sheet '!AO7-258750 -> 48726 | AP109: ='Balance Sheet '!AP6+'Balance Sheet '!AP7-258750 -> 62208 | AQ109: ='Balance Sheet '!AQ6+'Balance Sheet '!AQ7-258750 -> 61199 | AS109: ='Balance Sheet '!AS6+'Balance Sheet '!AS7-258750 -> 67546 | AT109: ='Balance Sheet '!AT6+'Balance Sheet '!AT7-'Balance Sheet '!AT35 -> 43740 | AU109: ='Balance Sheet '!AU6+'Balance Sheet '!AU7-'Balance Sheet '!AU35 -> 134316 | AV109: ='Balance Sheet '!AV6+'Balance Sheet '!AV7-'Balance Sheet '!AV35 -> 123026 | AX109: ='Balance Sheet '!AX6+'Balance Sheet '!AX7-'Balance Sheet '!AX35 -> -138772 | AY109: ='Balance Sheet '!AY6+'Balance Sheet '!AY7-'Balance Sheet '!AY35 -> -207403 | AZ109: ='Balance Sheet '!AZ6+'Balance Sheet '!AZ7-'Balance Sheet '!AZ35 -> -358064 | BA109: ='Balance Sheet '!BA6+'Balance Sheet '!BA7-'Balance Sheet '!BA35 -> -298741 | BC109: ='Balance Sheet '!BC6+'Balance Sheet '!BC7-'Balance Sheet '!BC35 -> -260195 | BD109: ='Balance Sheet '!BD6+'Balance Sheet '!BD7-'Balance Sheet '!BD35 -> -238103 | BE109: ='Balance Sheet '!BE6+'Balance Sheet '!BE7-'Balance Sheet '!BE35 -> -160325 | BF109: ='Balance Sheet '!BF6+'Balance Sheet '!BF7-'Balance Sheet '!BF35 -> -124113 | BH109: ='Balance Sheet '!BH6+'Balance Sheet '!BH7-'Balance Sheet '!BH35 -> -109544 | BI109: ='Balance Sheet '!BI6+'Balance Sheet '!BI7-'Balance Sheet '!BI35 -> -80379 | BJ109: ='Balance Sheet '!BJ6+'Balance Sheet '!BJ7-'Balance Sheet '!BJ35 -> -40879 | BK109: ='Balance Sheet '!BK6+'Balance Sheet '!BK7-'Balance Sheet '!BK35 -> -11828 | BM109: ='Balance Sheet '!BM6+'Balance Sheet '!BM7-'Balance Sheet '!BM35 -> -77570 | BN109: ='Balance Sheet '!BN6+'Balance Sheet '!BN7-'Balance Sheet '!BN35-'Balance Sheet '!BN32 -> -56038 | BO109: ='Balance Sheet '!BO6+'Balance Sheet '!BO7-'Balance Sheet '!BO35-'Balance Sheet '!BO32 -> -197196 | BP109: ='Balance Sheet '!BP6+'Balance Sheet '!BP7-'Balance Sheet '!BP35-'Balance Sheet '!BP32 -> -159389 | BR109: ='Balance Sheet '!BR6+'Balance Sheet '!BR7-'Balance Sheet '!BR35-'Balance Sheet '!BR32 -> -125014 | BS109: ='Balance Sheet '!BS6+'Balance Sheet '!BS7-'Balance Sheet '!BS35-'Balance Sheet '!BS32 -> -97744 | BT109: ='Balance Sheet '!BT6+'Balance Sheet '!BT7-'Balance Sheet '!BT35-'Balance Sheet '!BT32 -> -58397 | BU109: ='Balance Sheet '!BU6+'Balance Sheet '!BU7-'Balance Sheet '!BU35-'Balance Sheet '!BU32 -> -38571
C110: Cash/Share | J110: =J109/J104 -> 1.5483597 | K110: =K109/K104 -> 4.8159609 | L110: =L109/L104 -> 2.6753109 | M110: =M109/M104 -> 3.540395 | O110: =O109/O104 -> -0.98663462 | P110: =P109/P104 -> 1.1141627 | Q110: =Q109/Q104 -> 0.91802939 | R110: =R109/R104 -> 0.81352162 | T110: =T109/T104 -> 0.66593167 | U110: =U109/U104 -> 0.53291317 | V110: =V109/V104 -> 0.43129703 | W110: =W109/W104 -> 0.42244504 | Y110: =Y109/Y104 -> 0.43303424 | Z110: =Z109/Z104 -> 0.46008093 | AA110: =AA109/AA104 -> 0.44014191 | AB110: =AB109/AB104 -> 0.43204492 | AD110: =AD109/AD104 -> 0.42938832 | AE110: =AE109/AE104 -> 0.43659887 | AF110: =AF109/AF104 -> 0.50947999 | AG110: =AG109/AG104 -> 0.60123529 | AI110: =AI109/AI104 -> 0.80178763 | AJ110: =AJ109/AJ104 -> 0.25451272 | AK110: =AK109/AK104 -> 0.33672597 | AL110: =AL109/AL104 -> 0.53276087 | AN110: =AN109/AN104 -> 0.64046913 | AO110: =AO109/AO104 -> 0.77404289 | AP110: =AP109/AP104 -> 0.98061099 | AQ110: =AQ109/AQ104 -> 0.95843578 | AS110: =AS109/AS104 -> 1.0366016 | AT110: =AT109/AT104 -> 0.65117387 | AU110: =AU109/AU104 -> 2.051879 | AV110: =AV109/AV104 -> 1.7495165 | AX110: =AX109/AX104 -> -1.9639678 | AY110: =AY109/AY104 -> -2.9304971 | AZ110: =AZ109/AZ104 -> -5.0359202 | BA110: =BA109/BA104 -> -4.2148622 | BC110: =BC109/BC104 -> -3.6817789 | BD110: =BD109/BD104 -> -3.3496476 | BE110: =BE109/BE104 -> -2.2441595 | BF110: =BF109/BF104 -> -1.7349483 | BH110: =BH109/BH104 -> -1.514503 | BI110: =BI109/BI104 -> -1.1071488 | BJ110: =BJ109/BJ104 -> -0.55922025 | BK110: =BK109/BK104 -> -0.16030358 | BM110: =BM109/BM104 -> -1.0425515 | BN110: =BN109/BN104 -> -0.75070666 | BO110: =BO109/BO104 -> -2.6244859 | BP110: =BP109/BP104 -> -2.0972513 | BR110: =BR109/BR104 -> -1.6314189 | BS110: =BS109/BS104 -> -1.2707393 | BT110: =BT109/BT104 -> -0.74980419 | BU110: =BU109/BU104 -> -0.49689529
O114: 2014 Billings | T114: 2015 Billings | Y114: 2016 Billings | AD114: 2017 Billings | AI114: 2018 Billings | AN114: 2018 Billings | AS114: 2020 Billings | AX114: 2021 Billings | BC114: 2022 Billings | BH114: 2022 Billings | BM114: 2024 Billings | BR114: 2025 Billings | BW114: 2026 Billings
O115: 1Q14 | P115: 2Q14 | Q115: 3Q14 | R115: 4Q14 | S115: 2014 | T115: 1Q15 | U115: 2Q15 | V115: 3Q15 | W115: 4Q15 | X115: 2015 | Y115: 1Q16 | Z115: =Z4 -> 2Q16 | AA115: =AA4 -> 3Q16 | AB115: =AB4 -> 4Q16 | AC115: =AC4 -> 2016 | AD115: =AD4 -> 1Q17 | AE115: =AE4 -> 2Q17 | AF115: =AF4 -> 3Q17 | AG115: =AG4 -> 4Q17 | ... CA115: =CA4 -> 2026E
C116: Revenue | O116: =O28 -> 24274 | P116: =P28 -> 24685 | Q116: =Q28 -> 25869 | R116: =R28 -> 28274 | T116: =T28 -> 30274 | U116: =U28 -> 30274 | V116: =V28 -> 32287 | W116: =W28 -> 36033 | Y116: =Y28 -> 38015 | Z116: =Z28 -> 38886 | AA116: =AA28 -> 40982 | AB116: =AB28 -> 44207 | AD116: =AD28 -> 47014 | AE116: =AE28 -> 47727 | AF116: =AF28 -> 50081 | AG116: =AG28 -> 55403 | AI116: =AI28 -> 58905 | AJ116: =AJ28 -> 61120 | AK116: =AK28 -> 65304 | AL116: =AL28 -> 72335 | AN116: =AN28 -> 74538 | AO116: =AO28 -> 77436 | AP116: =AP28 -> 83769 | AQ116: =AQ28 -> 92263 | AS116: =AS28 -> 95088 | AT116: =AT28 -> 99792 | AU116: =AU28 -> 112143 | AV116: =AV28 -> 127885 | AX116: =AX28 -> 137882 | AY116: =AY28 -> 143782 | AZ116: =AZ28 -> 154328 | BA116: =BA28 -> 173599 | BC116: =BC28 -> 182777 | BD116: =BD28 -> 189382 | BE116: =BE28 -> 198342 | BF116: =BF28 -> 208345 | BH116: =BH28 -> 218439 | BI116: =BI28 -> 222882 | BJ116: =BJ28 -> 230105 | BK116: =BK28 -> 239062 | BM116: =BM28 -> 247010 | BN116: =BN28 -> 252086 | BO116: =BO28 -> 264182 | BP116: =BP28 -> 278660 | BR116: =BR28 -> 279705 | BS116: =BS28 -> 283269 | BT116: =BT28 -> 285832 | BU116: =BU28 -> 300282 | BW116: =BW28 -> 299228.41 | BX116: =BX28 -> 306327.1 | BY116: =BY28 -> 313729.2 | BZ116: =BZ28 -> 337396.86
C117: Change In Deferred Revenue | O117: =O106-M106 -> 582 | P117: =P106-O106 -> 52 | Q117: =Q106-P106 -> -18 | R117: =R106-Q106 -> 355 | T117: =T106-R106 -> 295 | U117: =U106-T106 -> -116 | V117: =V106-U106 -> 37 | W117: =W106-V106 -> 851 | Y117: =Y106-W106 -> 1419 | Z117: =Z106-Y106 -> 66 | AA117: =AA106-Z106 -> 940 | AB117: =AB106-AA106 -> 1209 | AD117: =AD106-AB106 -> 873 | AE117: =AE106-AD106 -> 983 | AF117: =AF106-AE106 -> 1796 | AG117: =AG106-AF106 -> 276 | AI117: =AI106-AG106 -> -275 | AJ117: =AJ106-AI106 -> 1050 | AK117: =AK106-AJ106 -> 2740 | AL117: =AL106-AK106 -> -99 | AN117: =AN106-AL106 -> 462 | AO117: =AO106-AN106 -> 2138 | AP117: =AP106-AO106 -> 1867 | AQ117: =AQ106-AP106 -> 2823 | AS117: =AS106-AQ106 -> 951 | AT117: =AT106-AS106 -> 674 | AU117: =AU106-AT106 -> 2221 | AV117: =AV106-AU106 -> 3456 | AX117: =AX106-AV106 -> 852 | AY117: =AY106-AX106 -> 402 | AZ117: =AZ106-AY106 -> 3650 | BA117: =BA106-AZ106 -> 6833 | BC117: =BC106-BA106 -> 2844 | BD117: =BD106-BC106 -> 4989 | BE117: =BE106-BD106 -> 2281 | BF117: =BF106-BE106 -> 3982 | BH117: =BH106-BF106 -> 266 | BI117: =BI106-BH106 -> -543 | BJ117: =BJ106-BI106 -> 7026 | BK117: =BK106-BJ106 -> 3622 | BM117: =BM106-BK106 -> -1168 | BN117: =BN106-BM106 -> -1733 | BO117: =BO106-BN106 -> 14714 | BP117: =BP106-BO106 -> -827 | BR117: =BR106-BP106 -> -4364 | BS117: =BS106-BR106 -> -6800 | BT117: =BT106-BS106 -> 6728 | BU117: =BU106-BT106 -> 2778 | BW117: =BW106-BU106 -> -77515 | BX117: =BX106-BW106 -> 0 | BY117: =BY106-BX106 -> 0 | BZ117: =BZ106-BY106 -> 0
C118: Billings | O118: =O117+O116 -> 24856 | P118: =P117+P116 -> 24737 | Q118: =Q117+Q116 -> 25851 | R118: =R117+R116 -> 28629 | S118: =SUM(O118:R118) -> 104073 | T118: =T117+T116 -> 30569 | U118: =U117+U116 -> 30158 | V118: =V117+V116 -> 32324 | W118: =W117+W116 -> 36884 | X118: =SUM(T118:W118) -> 129935 | Y118: =Y117+Y116 -> 39434 | Z118: =Z117+Z116 -> 38952 | AA118: =AA117+AA116 -> 41922 | AB118: =AB117+AB116 -> 45416 | AC118: =SUM(Y118:AB118) -> 165724 | AD118: =AD117+AD116 -> 47887 | AE118: =AE117+AE116 -> 48710 | AF118: =AF117+AF116 -> 51877 | AG118: =AG117+AG116 -> 55679 | AH118: =SUM(AD118:AG118) -> 204153 | AI118: =AI117+AI116 -> 58630 | AJ118: =AJ117+AJ116 -> 62170 | AK118: =AK117+AK116 -> 68044 | AL118: =AL117+AL116 -> 72236 | AM118: =SUM(AI118:AL118) -> 261080 | AN118: =AN117+AN116 -> 75000 | AO118: =AO117+AO116 -> 79574 | AP118: =AP117+AP116 -> 85636 | AQ118: =AQ117+AQ116 -> 95086 | AR118: =SUM(AN118:AQ118) -> 335296 | AS118: =AS117+AS116 -> 96039 | AT118: =AT117+AT116 -> 100466 | AU118: =AU117+AU116 -> 114364 | AV118: =AV117+AV116 -> 131341 | AW118: =SUM(AS118:AV118) -> 442210 | AX118: =AX117+AX116 -> 138734 | AY118: =AY117+AY116 -> 144184 | AZ118: =AZ117+AZ116 -> 157978 | BA118: =BA117+BA116 -> 180432 | BB118: =SUM(AX118:BA118) -> 621328 | BC118: =BC117+BC116 -> 185621 | BD118: =BD117+BD116 -> 194371 | BE118: =BE117+BE116 -> 200623 | BF118: =BF117+BF116 -> 212327 | BG118: =SUM(BC118:BF118) -> 792942 | BH118: =BH117+BH116 -> 218705 | BI118: =BI117+BI116 -> 222339 | BJ118: =BJ117+BJ116 -> 237131 | BK118: =BK117+BK116 -> 242684 | BL118: =SUM(BH118:BK118) -> 920859 | BM118: =BM117+BM116 -> 245842 | BN118: =BN117+BN116 -> 250353 | BO118: =BO117+BO116 -> 278896 | BP118: =BP117+BP116 -> 277833 | BQ118: =SUM(BM118:BP118) -> 1052924 | BR118: =BR117+BR116 -> 275341 | BS118: =BS117+BS116 -> 276469 | BT118: =BT117+BT116 -> 292560 | BU118: =BU117+BU116 -> 303060 | BV118: =SUM(BR118:BU118) -> 1147430 | BW118: =BW117+BW116 -> 221713.41 | BX118: =BX117+BX116 -> 306327.1 | BY118: =BY117+BY116 -> 313729.2 | BZ118: =BZ117+BZ116 -> 337396.86 | CA118: =SUM(BW118:BZ118) -> 1179166.6
C119: % change y/y | T119: =T118/O118-1 -> 0.2298439 | U119: =U118/P118-1 -> 0.21914541 | V119: =V118/Q118-1 -> 0.2503965 | W119: =W118/R118-1 -> 0.28834399 | X119: =X118/S118-1 -> 0.24849865 | Y119: =Y118/T118-1 -> 0.28999967 | Z119: =Z118/U118-1 -> 0.29159759 | AA119: =AA118/V118-1 -> 0.29693107 | ... CA119: =CA118/BV118-1 -> 0.027658824
C120: % change q/q | Y120: =Y118/W118-1 -> 0.069135669 | Z120: =Z118/Y118-1 -> -0.012222955 | AA120: =AA118/Z118-1 -> 0.076247689 | AB120: =AB118/AA118-1 -> 0.08334526 | AD120: =AD118/AB118-1 -> 0.054408138 | AE120: =AE118/AD118-1 -> 0.017186293 | AF120: =AF118/AE118-1 -> 0.06501745 | AG120: =AG118/AF118-1 -> 0.073288741 | AI120: =AI118/AG118-1 -> 0.053000233 | AJ120: =AJ118/AI118-1 -> 0.060378646 | AK120: =AK118/AJ118-1 -> 0.09448287 | AL120: =AL118/AK118-1 -> 0.061607195 | AN120: =AN118/AL118-1 -> 0.03826347 | AO120: =AO118/AN118-1 -> 0.060986667 | AP120: =AP118/AO118-1 -> 0.076180662 | AQ120: =AQ118/AP118-1 -> 0.11035079 | AS120: =AS118/AQ118-1 -> 0.010022506 | AT120: =AT118/AS118-1 -> 0.046095857 | AU120: =AU118/AT118-1 -> 0.13833536 | AV120: =AV118/AU118-1 -> 0.14844706 | AX120: =AX118/AV118-1 -> 0.056288592 | AY120: =AY118/AX118-1 -> 0.039283809 | AZ120: =AZ118/AY118-1 -> 0.095669422 | BA120: =BA118/AZ118-1 -> 0.14213371 | BC120: =BC118/BA118-1 -> 0.028758757 | BD120: =BD118/BC118-1 -> 0.047139063 | BE120: =BE118/BD118-1 -> 0.032165292 | BF120: =BF118/BE118-1 -> 0.058338276 | BH120: =BH118/BF118-1 -> 0.030038573 | BI120: =BI118/BH118-1 -> 0.01661599 | BJ120: =BJ118/BI118-1 -> 0.066529039 | BK120: =BK118/BJ118-1 -> 0.023417436 | BM120: =BM118/BK118-1 -> 0.013012807 | BN120: =BN118/BM118-1 -> 0.018349184 | BO120: =BO118/BN118-1 -> 0.11401102 | BP120: =BP118/BO118-1 -> -0.0038114566 | BR120: =BR118/BP118-1 -> -0.0089694169 | BS120: =BS118/BR118-1 -> 0.0040967382 | BT120: =BT118/BS118-1 -> 0.058201824 | BU120: =BU118/BT118-1 -> 0.035890074 | BW120: =BW118/BU118-1 -> -0.26841745 | BX120: =BX118/BW118-1 -> 0.38163541 | BY120: =BY118/BX118-1 -> 0.024164061 | BZ120: =BZ118/BY118-1 -> 0.075439748
...

Sheet Balance Sheet 
B2: ='Income Statement'!B2 -> Five9, Inc (Nasdaq: FIVN)
B4: Balance Sheet | D4: 2011 | E4: 1Q12 | F4: 2Q12 | G4: 3Q12 | H4: 4Q12 | I4: 2012 | J4: 1Q13 | K4: 2Q13 | L4: 3Q13 | M4: 4Q13 | N4: 2013 | O4: 1Q14 | P4: 2Q14 | Q4: 3Q14 | R4: 4Q14 | S4: 2014 | T4: 1Q15 | U4: 2Q15 | V4: 3Q15 | W4: 4Q15 | X4: 2015 | Y4: 1Q16 | Z4: 2Q16 | AA4: 3Q16 | AB4: 4Q16 | AC4: 2016 | AD4: 1Q17 | AE4: 2Q17 | AF4: 3Q17 | AG4: 4Q17 | AH4: 2017 | AI4: 1Q18 | AJ4: 2Q18 | AK4: 3Q18 | AL4: 4Q18 | AM4: 2018 | AN4: 1Q19 | AO4: 2Q19 | AP4: 3Q19 | AQ4: 4Q19 | AR4: 2019 | AS4: 1Q20 | AT4: 2Q20 | AU4: 3Q20 | AV4: 4Q20 | AW4: 2020 | AX4: 1Q21 | AY4: 2Q21 | AZ4: 3Q21 | BA4: 4Q21 | BB4: 2021 | BC4: 1Q22 | BD4: 2Q22 | BE4: 3Q22 | BF4: 4Q22 | BG4: 2022 | BH4: 1Q23 | BI4: 2Q23 | BJ4: 3Q23 | BK4: 4Q23 | BL4: 2023 | BM4: 1Q24 | BN4: 2Q24 | BO4: 3Q24 | BP4: 4Q24 | BQ4: 2024 | BR4: 1Q25 | BS4: 2Q25 | BT4: ='Income Statement'!BT4 -> 3Q25 | BU4: 4Q25 | BV4: 2025 | BW4: 1Q26E | BX4: 2Q26E | BY4: 3Q26E | BZ4: 4Q26E | CA4: 2026E
B5: Assets:
C6: Cash and Equivalents | D6: 5378 | E6: 1735 | F6: 13129 | G6: 8468 | H6: 5961 | I6: =H6 -> 5961 | J6: 5475 | K6: 17742 | L6: 10110 | M6: 17748 | N6: =M6 -> 17748 | O6: 29238 | P6: 61577 | Q6: 53489 | R6: 58289 | S6: =R6 -> 58289 | T6: 50646 | U6: 65333 | V6: 59501 | W6: 58484 | X6: =W6 -> 58484 | Y6: 57767 | Z6: 57638 | AA6: 57333 | AB6: 58122 | AC6: =AB6 -> 58122 | AD6: 56452 | AE6: 57149 | AF6: 63364 | AG6: 68947 | AH6: =AG6 -> 68947 | AI6: 80676 | AJ6: 166162 | AK6: 79619 | AL6: 81912 | AM6: =AL6 -> 81912 | AN6: 93492 | AO6: =110469 -> 110469 | AP6: 120573 | AQ6: 77976 | AR6: =AQ6 -> 77976 | AS6: 155863 | AT6: 233235 | AU6: 301767 | AV6: =+AV7 -> 383171 | AW6: =AV6 -> 383171 | AX6: 176326 | AY6: 175199 | AZ6: 82465 | BA6: 90878 | BB6: =BA6 -> 90878 | BC6: 100151 | BD6: 101315 | BE6: 129492 | BF6: 180520 | BG6: =BF6 -> 180520 | BH6: 141359 | BI6: 195592 | BJ6: 127828 | BK6: 143201 | BL6: =BK6 -> 143201 | BM6: 240190 | BN6: 175699 | BO6: 290959 | BP6: 362546 | BQ6: =BP6 -> 362546 | BR6: 370344 | BS6: 205479 | BT6: 193409 | BU6: 232084 | BV6: =BU6 -> 232084 | BW6: =BV6+'Cash Flows'!BW93 -> 275266.52 | BX6: =BW6+'Cash Flows'!BX93 -> 299270.19 | BY6: =BX6+'Cash Flows'!BY93 -> 334709.62 | BZ6: =BY6+'Cash Flows'!BZ93 -> 383119.71 | CA6: =BZ6 -> 383119.71
C7: Short-Term Investments | D7: 3581 | E7: 3581 | F7: 2738 | G7: 2490 | H7: 2490 | I7: =H7 -> 2490 | J7: 2241 | K7: 0 | L7: 0 | M7: 0 | N7: =M7 -> 0 | O7: 0 | P7: 29995 | Q7: 29999 | R7: 20000 | S7: =R7 -> 20000 | T7: 19999 | U7: 0 | V7: 0 | W7: 0 | X7: =W7 -> 0 | Y7: 0 | AC7: =AB7 -> 0 | AH7: =AG7 -> 0 | AJ7: 108140 | AK7: 200007 | AL7: 209907 | AM7: =AL7 -> 209907 | AN7: 205450 | AO7: =197007 -> 197007 | AP7: 200385 | AQ7: 241973 | AR7: =AQ7 -> 241973 | AS7: 170433 | AT7: 452708 | AU7: 479141 | AV7: 383171 | AW7: =AV7 -> 383171 | AX7: 467143 | AY7: 390986 | AZ7: 332824 | BA7: 378980 | BB7: =BA7 -> 378980 | BC7: 377519 | BD7: 397067 | BE7: 447612 | BF7: 433743 | BG7: =BF7 -> 433743 | BH7: 488381 | BI7: 464244 | BJ7: 572462 | BK7: 587096 | BL7: =BK7 -> 587096 | BM7: 843212 | BN7: 930639 | BO7: 675704 | BP7: 643410 | BQ7: =BP7 -> 643410 | BR7: 671394 | BS7: 430397 | BT7: 482747 | BU7: 464835 | BV7: =BU7 -> 464835 | BW7: =BV7 -> 464835 | BX7: =BW7 -> 464835 | BY7: =BX7 -> 464835 | BZ7: =BY7 -> 464835 | CA7: =BZ7 -> 464835
C8: Accounts Rec, Net | D8: 3530 | E8: 4064 | F8: 4127 | G8: 4102 | H8: 5441 | I8: =H8 -> 5441 | J8: 5528 | K8: 5625 | L8: 5124 | M8: 6970 | N8: =M8 -> 6970 | O8: 6650 | P8: 7098 | Q8: 7725 | R8: 8335 | S8: =R8 -> 8335 | T8: 8719 | U8: 8250 | V8: 9309 | W8: 10567 | X8: =W8 -> 10567 | Y8: 12528 | Z8: 10765 | AA8: 12899 | AB8: 13881 | AC8: =AB8 -> 13881 | AD8: 15453 | AE8: 16281 | AF8: 17231 | AG8: 19048 | AH8: =AG8 -> 19048 | AI8: 18534 | AJ8: 20167 | AK8: 23903 | AL8: 24797 | AM8: =AL8 -> 24797 | AN8: 25840 | AO8: 28153 | AP8: 31407 | AQ8: 37655 | AR8: =AQ8 -> 37655 | AS8: 39972 | AT8: 39607 | AU8: 42542 | AV8: 48731 | AW8: =AV8 -> 48731 | AX8: 51987 | AY8: 53811 | AZ8: 60383 | BA8: 83731 | BB8: =BA8 -> 83731 | BC8: 77912 | BD8: 82885 | BE8: 88225 | BF8: 87494 | BG8: =BF8 -> 87494 | BH8: 88085 | BI8: 88461 | BJ8: 94436 | BK8: 97424 | BL8: =BK8 -> 97424 | BM8: 103157 | BN8: 104382 | BO8: 116430 | BP8: 115172 | BQ8: =BP8 -> 115172 | BR8: 118614 | BS8: 127835 | BT8: 138486 | BU8: 130984 | BV8: =BU8 -> 130984 | BW8: =BW61*'Income Statement'!BW28 -> 131660.5 | BX8: =BX61*'Income Statement'!BX28 -> 128657.38 | BY8: =BY61*'Income Statement'!BY28 -> 138040.85 | BZ8: =BZ61*'Income Statement'!BZ28 -> 151828.58 | CA8: =BZ8 -> 151828.58
C9: Prepaid expenses and other current | D9: 592 | E9: 961 | F9: 950 | G9: 1200 | H9: 942 | I9: =H9 -> 942 | J9: 2194 | K9: 1505 | L9: 1592 | M9: 1651 | N9: =M9 -> 1651 | O9: 2647 | P9: 2779 | Q9: 2726 | R9: 1960 | S9: =R9 -> 1960 | T9: 3170 | U9: 4228 | V9: 2917 | W9: 2184 | X9: =W9 -> 2184 | Y9: 3899 | Z9: 3390 | AA9: 4097 | AB9: 3008 | AC9: =AB9 -> 3008 | AD9: 5117 | AE9: 7074 | AF9: 4809 | AG9: 4840 | AH9: =AG9 -> 4840 | AI9: 7150 | AJ9: 8437 | AK9: 7962 | AL9: 9014 | AM9: =AL9 -> 9014 | AN9: 9719 | AO9: 12036 | AP9: 11140 | AQ9: 10656 | AR9: =AQ9 -> 10656 | AS9: 13396 | AT9: 17529 | AU9: 15908 | AV9: 16149 | AW9: =AV9 -> 16149 | AX9: 19673 | AY9: 22110 | AZ9: 29814 | BA9: 30342 | BB9: =BA9 -> 30342 | BC9: 32534 | BD9: 38464 | BE9: 32600 | BF9: 29711 | BG9: =BF9 -> 29711 | BH9: 32018 | BI9: 38476 | BJ9: 37627 | BK9: 34622 | BL9: =BK9 -> 34622 | BM9: 35627 | BN9: 41760 | BO9: 48640 | BP9: 50840 | BQ9: =BP9 -> 50840 | BR9: 47832 | BS9: 47986 | BT9: 49590 | BU9: 43107 | BV9: =BU9 -> 43107 | BW9: =BW62*'Income Statement'!BW28 -> 56853.398 | BX9: =BX62*'Income Statement'!BX28 -> 61265.419 | BY9: =BY62*'Income Statement'!BY28 -> 62745.841 | BZ9: =BZ62*'Income Statement'!BZ28 -> 67479.371 | CA9: =BZ9 -> 67479.371
C10: Deferred contract acquistion cost | AI10: 7562 | AJ10: 8083 | AK10: 8633 | AL10: 9372 | AM10: =AL10 -> 9372 | AN10: 10095 | AO10: 10954 | AP10: 11947 | AQ10: 13014 | AR10: =AQ10 -> 13014 | AS10: 14317 | AT10: 16151 | AU10: 17932 | AV10: 20695 | AW10: =AV10 -> 20695 | AX10: 23249 | AY10: 26791 | AZ10: 29649 | BA10: 33295 | BB10: =BA10 -> 33295 | BC10: 36478 | BD10: 40306 | BE10: 43587 | BF10: 47242 | BG10: =BF10 -> 47242 | BH10: 50566 | BI10: 54462 | BJ10: 58320 | BK10: 61711 | BL10: =BK10 -> 61711 | BM10: 67169 | BN10: 69622 | BO10: 72534 | BP10: 76600 | BQ10: =BP10 -> 76600 | BR10: 79267 | BS10: 82497 | BT10: 85181 | BU10: 88714 | BV10: =BU10 -> 88714 | BW10: =BV10-'Cash Flows'!BW35 -> 108714 | BX10: =BW10-'Cash Flows'!BX35 -> 128714 | BY10: =BX10-'Cash Flows'!BY35 -> 148714 | BZ10: =BY10-'Cash Flows'!BZ35 -> 168714 | CA10: =BZ10 -> 168714
B11: Total Current Assets | D11: =SUM(D6:D9) -> 13081 | E11: =SUM(E6:E9) -> 10341 | F11: =SUM(F6:F9) -> 20944 | G11: =SUM(G6:G9) -> 16260 | H11: =SUM(H6:H9) -> 14834 | I11: =SUM(I6:I9) -> 14834 | J11: =SUM(J6:J9) -> 15438 | K11: =SUM(K6:K9) -> 24872 | ... R11: =SUM(R6:R9) -> 88584 | S11: =R11 -> 88584 | T11: =SUM(T6:T9) -> 82534 | U11: =SUM(U6:U9) -> 77811 | V11: =SUM(V6:V9) -> 71727 | W11: =SUM(W6:W9) -> 71235 | X11: =W11 -> 71235 | Y11: =SUM(Y6:Y9) -> 74194 | Z11: =SUM(Z6:Z9) -> 71793 | AA11: =SUM(AA6:AA9) -> 74329 | AB11: =SUM(AB6:AB9) -> 75011 | AC11: =AB11 -> 75011 | AD11: =SUM(AD6:AD9) -> 77022 | AE11: =SUM(AE6:AE9) -> 80504 | AF11: =SUM(AF6:AF9) -> 85404 | AG11: =SUM(AG6:AG9) -> 92835 | AH11: =AG11 -> 92835 | AI11: =SUM(AI6:AI10) -> 113922 | AJ11: =SUM(AJ6:AJ10) -> 310989 | AK11: =SUM(AK6:AK10) -> 320124 | AL11: =SUM(AL6:AL10) -> 335002 | AM11: =AL11 -> 335002 | AN11: =SUM(AN6:AN10) -> 344596 | AO11: =SUM(AO6:AO10) -> 358619 | AP11: =SUM(AP6:AP10) -> 375452 | AQ11: =SUM(AQ6:AQ10) -> 381274 | AR11: =AQ11 -> 381274 | AS11: =SUM(AS6:AS10) -> 393981 | AT11: =SUM(AT6:AT10) -> 759230 | AU11: =SUM(AU6:AU10) -> 857290 | AV11: =SUM(AV6:AV10) -> 851917 | AW11: =AV11 -> 851917 | AX11: =SUM(AX6:AX10) -> 738378 | AY11: =SUM(AY6:AY10) -> 668897 | AZ11: =SUM(AZ6:AZ10) -> 535135 | BA11: =SUM(BA6:BA10) -> 617226 | BB11: =BA11 -> 617226 | BC11: =SUM(BC6:BC10) -> 624594 | BD11: =SUM(BD6:BD10) -> 660037 | BE11: =SUM(BE6:BE10) -> 741516 | BF11: =SUM(BF6:BF10) -> 778710 | BG11: =BF11 -> 778710 | BH11: =SUM(BH6:BH10) -> 800409 | BI11: =SUM(BI6:BI10) -> 841235 | BJ11: =SUM(BJ6:BJ10) -> 890673 | BK11: =SUM(BK6:BK10) -> 924054 | BL11: =BK11 -> 924054 | BM11: =SUM(BM6:BM10) -> 1289355 | BN11: =SUM(BN6:BN10) -> 1322102 | BO11: =SUM(BO6:BO10) -> 1204267 | BP11: =SUM(BP6:BP10) -> 1248568 | BQ11: =BP11 -> 1248568 | BR11: =SUM(BR6:BR10) -> 1287451 | BS11: =SUM(BS6:BS10) -> 894194 | BT11: =SUM(BT6:BT10) -> 949413 | BU11: =SUM(BU6:BU10) -> 959724 | BV11: =BU11 -> 959724 | BW11: =SUM(BW6:BW10) -> 1037329.4 | BX11: =SUM(BX6:BX10) -> 1082742 | BY11: =SUM(BY6:BY10) -> 1149045.3 | BZ11: =SUM(BZ6:BZ10) -> 1235976.7 | CA11: =BZ11 -> 1235976.7
C12: PPE, net | D12: 4437 | E12: 5787 | F12: 7958 | G12: 8130 | H12: 10874 | I12: =H12 -> 10874 | J12: 10885 | K12: 11672 | L12: 11955 | M12: 11607 | N12: =M12 -> 11607 | O12: 11179 | P12: 11521 | Q12: 12117 | R12: 12571 | S12: =R12 -> 12571 | T12: 12426 | U12: 11964 | V12: 12376 | W12: 13225 | X12: =W12 -> 13225 | Y12: 12795 | Z12: 13188 | AA12: 13690 | AB12: 14688 | AC12: =AB12 -> 14688 | AD12: 15830 | AE12: 15656 | AF12: 17958 | AG12: 19888 | AH12: =AG12 -> 19888 | AI12: 20876 | AJ12: 22019 | AK12: 22909 | AL12: 25885 | AM12: =AL12 -> 25885 | AN12: 27496 | AO12: 28255 | AP12: 28399 | AQ12: 33190 | AR12: =AQ12 -> 33190 | AS12: 34940 | AT12: 39799 | AU12: 41676 | AV12: 51213 | AW12: =AV12 -> 51213 | AX12: 58296 | AY12: 63107 | AZ12: 71444 | BA12: 77785 | BB12: =BA12 -> 77785 | BC12: 91476 | BD12: 99994 | BE12: 101696 | BF12: 101221 | BG12: =BF12 -> 101221 | BH12: 104057 | BI12: 98879 | BJ12: 102029 | BK12: 108572 | BL12: =BK12 -> 108572 | BM12: 113640 | BN12: 124600 | BO12: 136052 | BP12: 144888 | BQ12: =BP12 -> 144888 | BR12: 146460 | BS12: 154499 | BT12: 164305 | BU12: 164635 | BV12: =BU12 -> 164635 | BW12: =BV12-'Cash Flows'!BW46-(0.05*'Cash Flows'!BW8) -> 175883.78 | BX12: =BW12-'Cash Flows'!BX46-(0.05*'Cash Flows'!BX8) -> 187093.18 | BY12: =BX12-'Cash Flows'!BY46-(0.05*'Cash Flows'!BY8) -> 198310.13 | BZ12: =BY12-'Cash Flows'!BZ46-(0.05*'Cash Flows'!BZ8) -> 209490.62 | CA12: =BZ12 -> 209490.62
C13: Operating lease right to use | AN13: 6735 | AO13: 10219 | AP13: 8933 | AQ13: 8746 | AR13: =AQ13 -> 8746 | AS13: 11034 | AT13: 10006 | AU13: 8669 | AV13: 9010 | AW13: =AV13 -> 9010 | AX13: 44960 | AY13: 46966 | AZ13: 45778 | BA13: 48703 | BB13: =BA13 -> 48703 | BC13: 46536 | BD13: 43593 | BE13: 44941 | BF13: 44120 | BG13: =BF13 -> 44120 | BH13: 45339 | BI13: 43748 | BJ13: 41522 | BK13: 38873 | BL13: =BK13 -> 38873 | BM13: 36215 | BN13: 34107 | BO13: 43480 | BP13: 38880 | BQ13: =BP13 -> 38880 | BR13: 36444 | BS13: 37433 | BT13: 37695 | BU13: 46375 | BV13: =BU13 -> 46375 | BW13: =BV13 -> 46375 | BX13: =BW13 -> 46375 | BY13: =BX13 -> 46375 | BZ13: =BY13 -> 46375 | CA13: =BZ13 -> 46375
C14: Finance lease right of use | BI14: 2167 | BJ14: 4612 | BK14: 4564 | BL14: =BK14 -> 4564 | BM14: 4108 | BN14: 3653 | BO14: 21262 | BP14: 19269 | BQ14: =BP14 -> 19269 | BR14: 21113 | BS14: 18803 | BT14: 16507 | BU14: 14216 | BV14: =BU14 -> 14216 | CA14: =BZ14 -> 0
C15: Intangible assets, Net | D15: 0 | E15: 0 | F15: 0 | G15: 0 | H15: 0 | I15: =H15 -> 0 | J15: 0 | K15: 0 | L15: 0 | M15: 3065 | N15: =M15 -> 3065 | O15: 2937 | P15: 2809 | Q15: 2681 | R15: 2553 | S15: =R15 -> 2553 | T15: 2425 | U15: 2297 | V15: 2169 | W15: 2041 | X15: =W15 -> 2041 | Y15: 1913 | Z15: 1785 | AA15: 1657 | AB15: 1539 | AC15: =AB15 -> 1539 | AD15: 1422 | AE15: 1306 | AF15: 1190 | AG15: 1073 | AH15: =AG15 -> 1073 | AI15: 957 | AJ15: 841 | AK15: 724 | AL15: 631 | AM15: =AL15 -> 631 | AN15: 543 | AO15: 455 | AP15: 367 | AQ15: 15533 | AR15: =AQ15 -> 15533 | AS15: 14543 | AT15: 25605 | AU15: 23867 | AV15: 51684 | AW15: =AV15 -> 51684 | AX15: 48737 | AY15: 45790 | AZ15: 42843 | BA15: 39897 | BB15: =BA15 -> 39897 | BC15: 36950 | BD15: 34015 | BE15: 31081 | BF15: 28192 | BG15: =BF15 -> 28192 | BH15: 25346 | BI15: 22501 | BJ15: 41469 | BK15: 38323 | BL15: =BK15 -> 38323 | BM15: 35675 | BN15: 33027 | BO15: 69731 | BP15: 65632 | BQ15: =BP15 -> 65632 | BR15: 61532 | BS15: 58068 | BT15: 54604 | BU15: 51166 | BV15: =BU15 -> 51166 | BW15: =BV15 -> 51166 | BX15: =BW15 -> 51166 | BY15: =BX15 -> 51166 | BZ15: =BY15 -> 51166 | CA15: =BZ15 -> 51166
C16: Goodwill | D16: 0 | E16: 0 | F16: 0 | G16: 0 | H16: 0 | I16: =H16 -> 0 | J16: 0 | K16: 0 | L16: 0 | M16: 11798 | N16: =M16 -> 11798 | O16: =M16 -> 11798 | P16: 11798 | Q16: 11798 | R16: 11798 | S16: =R16 -> 11798 | T16: 11798 | U16: 11798 | V16: 11798 | W16: 11798 | X16: =W16 -> 11798 | Y16: 11798 | Z16: 11798 | AA16: 11798 | AB16: 11798 | AC16: =AB16 -> 11798 | AD16: 11798 | AE16: 11798 | AF16: 11798 | AG16: 11798 | AH16: =AG16 -> 11798 | AI16: 11798 | AJ16: 11798 | AK16: 11798 | AL16: 11798 | AM16: =AL16 -> 11798 | AN16: 11798 | AO16: 11798 | AP16: =AO16 -> 11798 | AQ16: 11798 | AR16: =AQ16 -> 11798 | AS16: 11798 | AT16: 34444 | AU16: 34444 | AV16: 165420 | AW16: =AV16 -> 165420 | AX16: 165420 | AY16: =AX16 -> 165420 | AZ16: 165420 | BA16: 165420 | BB16: =BA16 -> 165420 | BC16: 165420 | BD16: 165420 | BE16: 165420 | BF16: 165420 | BG16: =BF16 -> 165420 | BH16: 165420 | BI16: 165420 | BJ16: 227412 | BK16: =BJ16 -> 227412 | BL16: =BK16 -> 227412 | BM16: 227269 | BN16: 227269 | BO16: 365450 | BP16: 365436 | BQ16: =BP16 -> 365436 | BR16: 366698 | BS16: 366698 | BT16: 366253 | BU16: 366253 | BV16: =BU16 -> 366253 | BW16: =BV16 -> 366253 | BX16: =BW16 -> 366253 | BY16: =BX16 -> 366253 | BZ16: =BY16 -> 366253 | CA16: =BZ16 -> 366253
C17: Marketable investments | AV17: 42127 | AW17: =AV17 -> 42127 | AX17: 0 | AY17: 72758 | AZ17: 208468 | BA17: 147377 | BB17: =BA17 -> 147377 | BC17: 118707 | BD17: 60424 | BE17: 1961 | BF17: 885 | BG17: =BF17 -> 885 | BH17: 13498 | BI17: 85110 | BL17: =BK17 -> 0 | BQ17: =BP17 -> 0 | BV17: =BU17 -> 0 | CA17: =BZ17 -> 0
C18: Other Assets | D18: 921 | E18: 921 | F18: 910 | G18: 917 | H18: 899 | I18: =H18 -> 899 | J18: 1185 | K18: 1628 | L18: 2092 | M18: 3439 | N18: =M18 -> 3439 | O18: 4786 | P18: 1350 | Q18: 1339 | R18: 1428 | S18: =R18 -> 1428 | T18: 863 | U18: 709 | V18: 800 | W18: 934 | X18: =W18 -> 934 | Y18: 964 | Z18: 932 | AA18: 1225 | AB18: 2203 | AC18: =AB18 -> 2203 | AD18: 2276 | AE18: 2199 | AF18: 2365 | AG18: 2602 | AH18: =AG18 -> 2602 | AI18: 1120 | AJ18: 1026 | AK18: 962 | AL18: 836 | AM18: =AL18 -> 836 | AN18: 936 | AO18: 1000 | AP18: 1100 | AQ18: 1184 | AR18: =AQ18 -> 1184 | AS18: 3316 | AT18: 2789 | AU18: 3258 | AV18: 3236 | AW18: =AV18 -> 3236 | AX18: 3135 | AY18: 3089 | AZ18: 5432 | BA18: 11871 | BB18: =BA18 -> 11871 | BC18: 11748 | BD18: 11886 | BE18: 11963 | BF18: 11057 | BG18: =BF18 -> 11057 | BH18: 15240 | BI18: 17329 | BJ18: 16603 | BK18: 16199 | BL18: =BK18 -> 16199 | BM18: 16668 | BN18: 17755 | BO18: 17765 | BP18: 13384 | BQ18: =BP18 -> 13384 | BR18: 12669 | BS18: 11252 | BT18: 11107 | BU18: 10725 | BV18: =BU18 -> 10725 | BW18: =BW63*'Income Statement'!BW28 -> 19449.847 | BX18: =BX63*'Income Statement'!BX28 -> 21442.897 | BY18: =BY63*'Income Statement'!BY28 -> 21961.044 | BZ18: =BZ63*'Income Statement'!BZ28 -> 21930.796 | CA18: =BZ18 -> 21930.796
C19: Deferred contract acquisition cost | AI19: 17238 | AJ19: 18393 | AK19: 19599 | AL19: 21514 | AM19: =AL19 -> 21514 | AN19: 23262 | AO19: 25421 | AP19: 27975 | AQ19: 30655 | AR19: =AQ19 -> 30655 | AS19: 34047 | AT19: 39366 | AU19: 44083 | AV19: 51934 | AW19: =AV19 -> 51934 | AX19: 59823 | AY19: 69689 | AZ19: 76386 | BA19: 84663 | BB19: =BA19 -> 84663 | BC19: 92964 | BD19: 101854 | BE19: 107961 | BF19: 114880 | BG19: =BF19 -> 114880 | BH19: 119799 | BI19: 126555 | BJ19: 132124 | BK19: 136571 | BL19: =BK19 -> 136571 | BM19: 148408 | BN19: 147867 | BO19: 149885 | BP19: 155157 | BQ19: =BP19 -> 155157 | BR19: 157557 | BS19: 163913 | BT19: 168521 | BU19: 176976 | BV19: =BU19 -> 176976 | BW19: =BV19 -> 176976 | BX19: =BW19 -> 176976 | BY19: =BX19 -> 176976 | BZ19: =BY19 -> 176976 | CA19: =BZ19 -> 176976
B20: Total Assets | D20: =D11+SUM(D12:D18) -> 18439 | E20: =E11+SUM(E12:E18) -> 17049 | F20: =F11+SUM(F12:F18) -> 29812 | G20: =G11+SUM(G12:G18) -> 25307 | H20: =H11+SUM(H12:H18) -> 26607 | I20: =I11+SUM(I12:I18) -> 26607 | J20: =J11+SUM(J12:J18) -> 27508 | K20: =K11+SUM(K12:K18) -> 38172 | ... AH20: =AH11+SUM(AH12:AH18) -> 128196 | AI20: =AI11+SUM(AI12:AI19) -> 165911 | AJ20: =AJ11+SUM(AJ12:AJ19) -> 365066 | AK20: =AK11+SUM(AK12:AK19) -> 376116 | AL20: =AL11+SUM(AL12:AL19) -> 395666 | AM20: =AM11+SUM(AM12:AM19) -> 395666 | AN20: =AN11+SUM(AN12:AN19) -> 415366 | AO20: =AO11+SUM(AO12:AO19) -> 435767 | AP20: =AP11+SUM(AP12:AP19) -> 454024 | ... CA20: =CA11+SUM(CA12:CA19) -> 2108168.1
B22: Liabilities:
C23: Accounts payable | D23: 2552 | E23: 2162 | F23: 2975 | G23: 1853 | H23: 4649 | I23: =H23 -> 4649 | J23: 4768 | K23: 4170 | L23: 3159 | M23: 4306 | N23: =M23 -> 4306 | O23: 3753 | P23: 3373 | Q23: 2856 | R23: 4179 | S23: =R23 -> 4179 | T23: 2541 | U23: 2766 | V23: 2865 | W23: 2569 | X23: =W23 -> 2569 | Y23: 3376 | Z23: 3004 | AA23: 3609 | AB23: 3366 | AC23: =AB23 -> 3366 | AD23: 3394 | AE23: 4586 | AF23: 4787 | AG23: 4292 | AH23: =AG23 -> 4292 | AI23: 5482 | AJ23: 6035 | AK23: 4528 | AL23: 7010 | AM23: =AL23 -> 7010 | AN23: 7233 | AO23: 7534 | AP23: 6757 | AQ23: 10156 | AR23: =AQ23 -> 10156 | AS23: 8367 | AT23: 12045 | AU23: 12829 | AV23: 17145 | AW23: =AV23 -> 17145 | AX23: 16056 | AY23: 17632 | AZ23: 21330 | BA23: 20510 | BB23: =BA23 -> 20510 | BC23: 31981 | BD23: 25931 | BE23: 21153 | BF23: 23629 | BG23: =BF23 -> 23629 | BH23: 22461 | BI23: 23286 | BJ23: 28528 | BK23: 24399 | BL23: =BK23 -> 24399 | BM23: 25671 | BN23: 29405 | BO23: 33876 | BP23: 26282 | BQ23: =BP23 -> 26282 | BR23: 29477 | BS23: 31063 | BT23: 30430 | BU23: 29973 | BV23: =BU23 -> 29973 | BW23: =BW67*'Income Statement'!BW28 -> 35907.409 | BX23: =BX67*'Income Statement'!BX28 -> 39822.523 | BY23: =BY67*'Income Statement'!BY28 -> 43922.088 | BZ23: =BZ67*'Income Statement'!BZ28 -> 40487.623 | CA23: =BZ23 -> 40487.623
C24: Accrued and other current liabilities | D24: 2396 | E24: 2965 | F24: 2832 | G24: 3382 | H24: 3470 | I24: =H24 -> 3470 | J24: 4687 | K24: 4745 | L24: 4585 | M24: 5929 | N24: =M24 -> 5929 | O24: 7788 | P24: 8152 | Q24: 7778 | R24: 7318 | S24: =R24 -> 7318 | T24: 8107 | U24: 8718 | V24: 8053 | W24: 7911 | X24: =W24 -> 7911 | Y24: 9747 | Z24: 9153 | AA24: 10500 | AB24: 9604 | AC24: =AB24 -> 9604 | AD24: 13028 | AE24: 10277 | AF24: 11967 | AG24: 11787 | AH24: =AG24 -> 11787 | AI24: 14132 | AJ24: 13615 | AK24: 14144 | AL24: 13771 | AM24: =AL24 -> 13771 | AN24: 17965 | AO24: 14925 | AP24: 20141 | AQ24: 18385 | AR24: =AQ24 -> 18385 | AS24: 24738 | AT24: 34817 | AU24: 40814 | AV24: 44450 | AW24: =AV24 -> 44450 | AX24: 52960 | AY24: 74024 | AZ24: 77905 | BA24: 78577 | BB24: =BA24 -> 78577 | BC24: 91411 | BD24: 56894 | BE24: 63122 | BF24: 53092 | BG24: =BF24 -> 53092 | BH24: 62196 | BI24: 58860 | BJ24: 49511 | BK24: 62131 | BL24: =BK24 -> 62131 | BM24: 79185 | BN24: 76320 | BO24: 84297 | BP24: 83720 | BQ24: =BP24 -> 83720 | BR24: 80354 | BS24: 81870 | BT24: 80568 | BU24: 84120 | BV24: =BU24 -> 84120 | BW24: =BW68*'Income Statement'!BW28 -> 95753.091 | BX24: =BX68*'Income Statement'!BX28 -> 85771.587 | BY24: =BY68*'Income Statement'!BY28 -> 84706.885 | BZ24: =BZ68*'Income Statement'!BZ28 -> 84349.214 | CA24: =BZ24 -> 84349.214
C25: Operating lease liabilities | AN25: 4322 | AO25: 5132 | AP25: 5010 | AQ25: 5064 | AR25: =AQ25 -> 5064 | AS25: 6087 | AT25: 5247 | AU25: 4307 | AV25: 3912 | AW25: =AV25 -> 3912 | AX25: 5478 | AY25: 7758 | AZ25: 8849 | BA25: 9826 | BB25: =BA25 -> 9826 | BC25: 10135 | BD25: 9836 | BE25: 10201 | BF25: 10626 | BG25: =BF25 -> 10626 | BH25: 11739 | BI25: 11931 | BJ25: 11454 | BK25: 10731 | BL25: =BK25 -> 10731 | BM25: 9880 | BN25: 9509 | BO25: 11446 | BP25: 11258 | BQ25: =BP25 -> 11258 | BR25: 11131 | BS25: 11473 | BT25: 11187 | BU25: 12922 | BV25: =BU25 -> 12922 | BW25: =BV25 -> 12922 | BX25: =BW25 -> 12922 | BY25: =BX25 -> 12922 | BZ25: =BY25 -> 12922 | CA25: =BZ25 -> 12922
C26: Accrued federal fees - current portion | D26: 0 | E26: 0 | F26: 0 | G26: 0 | H26: 401 | I26: =H26 -> 401 | J26: 8960 | K26: 8383 | L26: 4269 | M26: 4206 | N26: =M26 -> 4206 | O26: 4353 | P26: 4361 | Q26: 6430 | R26: 7215 | S26: =R26 -> 7215 | T26: 7531 | U26: 5658 | V26: 5595 | W26: 5684 | X26: =W26 -> 5684 | Y26: 5885 | Z26: 6008 | AA26: 5873 | AB26: 2742 | AC26: =AB26 -> 2742 | AD26: 3018 | AE26: 3261 | AF26: 1146 | AG26: 1151 | AH26: =AG26 -> 1151 | AI26: 1331 | AJ26: 1638 | AK26: 1681 | AL26: 1434 | AM26: =AL26 -> 1434 | AN26: 1348 | AO26: 1577 | AP26: 1981 | AQ26: 2303 | AR26: =AQ26 -> 2303 | AS26: 1754 | AT26: 1670 | AU26: 2562 | AV26: 3745 | AW26: =AV26 -> 3745 | AX26: 5024 | AY26: 5138 | AZ26: 242 | BA26: 2282 | BB26: =BA26 -> 2282 | BC26: 1650 | BD26: 0 | BE26: 439 | BF26: 2471 | BG26: =BF26 -> 2471 | BH26: 3360 | BI26: 3384 | BJ26: 3336 | BL26: =BK26 -> 0 | BP26: 0 | BQ26: =BP26 -> 0 | BV26: =BU26 -> 0 | BW26: =BW69*'Income Statement'!BW28 -> 5984.5682 | BX26: =BX69*'Income Statement'!BX28 -> 6126.5419 | BY26: =BY69*'Income Statement'!BY28 -> 6274.5841 | BZ26: =BZ69*'Income Statement'!BZ28 -> 6747.9371 | CA26: =BZ26 -> 6747.9371
C27: Revolving Line of Credit | I27: =H27 -> 0 | J27: 0 | K27: 0 | L27: 0 | M27: 0 | N27: =M27 -> 0 | O27: 12500 | P27: 12500 | Q27: 12500 | R27: 0 | S27: =R27 -> 0 | T27: 0 | U27: 0 | V27: 0 | W27: 12500 | X27: =W27 -> 12500 | Y27: 12500 | Z27: 12500 | AA27: 0 | AC27: =AB27 -> 0 | AD27: =AC27 -> 0 | AE27: =AD27 -> 0 | AF27: =AE27 -> 0 | AG27: =AF27 -> 0 | AH27: =AG27 -> 0 | AI27: =AH27 -> 0 | AJ27: =AI27 -> 0 | AK27: =AJ27 -> 0 | AL27: 0 | AM27: =AL27 -> 0 | AN27: =AM27 -> 0 | AO27: =AN27 -> 0 | AP27: =AO27 -> 0 | AQ27: =AP27 -> 0 | AR27: =AQ27 -> 0 | AS27: =AR27 -> 0 | AT27: =AS27 -> 0 | ... CA27: =BZ27 -> 0
C28: Sales tax liability | D28: 604 | E28: 704 | F28: 795 | G28: 317 | H28: 105 | I28: =H28 -> 105 | J28: 75 | K28: 78 | L28: 77 | M28: 98 | N28: =M28 -> 98 | O28: 90 | P28: 127 | Q28: 260 | R28: 297 | S28: =R28 -> 297 | T28: 1221 | U28: 863 | V28: 1036 | W28: 1262 | X28: =W28 -> 1262 | Y28: 1167 | Z28: 1215 | AA28: 1307 | AB28: 1347 | AC28: =AB28 -> 1347 | AD28: 1138 | AE28: 1191 | AF28: 1174 | AG28: 1326 | AH28: =AG28 -> 1326 | AI28: 1097 | AJ28: 1201 | AK28: 1322 | AL28: 1741 | AM28: =AL28 -> 1741 | AN28: 1404 | AO28: 1266 | AP28: 1435 | AQ28: 1885 | AR28: =AQ28 -> 1885 | AS28: 1723 | AT28: 1565 | AU28: 1629 | AV28: 1714 | AW28: =AV28 -> 1714 | AX28: 1168 | AY28: 1588 | AZ28: 1839 | BA28: 2660 | BB28: =BA28 -> 2660 | BC28: 2047 | BD28: 2253 | BE28: 2485 | BF28: 2973 | BG28: =BF28 -> 2973 | BH28: 2209 | BI28: 2547 | BJ28: 2965 | BL28: =BK28 -> 0 | BQ28: =BP28 -> 0 | BV28: =BU28 -> 0 | BW28: =BW70*'Income Statement'!BW28 -> 1496.142 | BX28: =BX70*'Income Statement'!BX28 -> 1531.6355 | BY28: =BY70*'Income Statement'!BY28 -> 1568.646 | BZ28: =BZ70*'Income Statement'!BZ28 -> 1686.9843 | CA28: =BZ28 -> 1686.9843
C29: Notes Payable - current portion | D29: 737 | E29: 748 | F29: 705 | G29: 571 | H29: 415 | I29: =H29 -> 415 | J29: 247 | K29: 109 | L29: 1079 | M29: 1522 | N29: =M29 -> 1522 | O29: 2037 | P29: 2573 | Q29: 3112 | R29: 3146 | S29: =R29 -> 3146 | T29: 3528 | U29: 5081 | V29: 6045 | W29: 7212 | X29: =W29 -> 7212 | Y29: 7375 | Z29: 6576 | AA29: 1070 | AB29: 742 | AC29: =AB29 -> 742 | AD29: 643 | AE29: 663 | AF29: 486 | AG29: 336 | AH29: =AG29 -> 336 | AI29: 180 | AJ29: 31 | AK29: 0 | AL29: 0 | AM29: =AL29 -> 0 | AN29: =AM29 -> 0 | AO29: =AN29 -> 0 | AP29: =AO29 -> 0 | AQ29: =AP29 -> 0 | AR29: =AQ29 -> 0 | AS29: =AR29 -> 0 | AT29: =AS29 -> 0 | ... BC29: =BB29 -> 0 | BD29: 187 | BE29: 176 | BG29: =BF29 -> 0 | BH29: =BG29 -> 0 | BI29: =BH29 -> 0 | BJ29: =BI29 -> 0 | BK29: =BJ29 -> 0 | BL29: =BK29 -> 0 | BM29: =BL29 -> 0 | BN29: =BM29 -> 0 | ... CA29: =BZ29 -> 0
C30: Capital Lease - current portion | D30: 1121 | E30: 1273 | F30: 2480 | G30: 2561 | H30: 3572 | I30: =H30 -> 3572 | J30: 4255 | K30: 4505 | L30: 4768 | M30: 4857 | N30: =M30 -> 4857 | O30: 4907 | P30: 4742 | Q30: 4988 | R30: 4849 | S30: =R30 -> 4849 | T30: 4467 | U30: 4365 | V30: 4313 | W30: 4972 | X30: =W30 -> 4972 | Y30: 5185 | Z30: 5271 | AA30: 5634 | AB30: 6230 | AC30: =AB30 -> 6230 | AD30: 6009 | AE30: 6155 | AF30: 6057 | AG30: 6651 | AH30: =AG30 -> 6651 | AI30: 6810 | AJ30: 7442 | AK30: 6909 | AL30: 6647 | AM30: =AL30 -> 6647 | AN30: 6208 | AO30: 5545 | AP30: 4457 | AQ30: 3518 | AR30: =AQ30 -> 3518 | AS30: 2812 | AT30: 2032 | AU30: 1299 | AV30: 612 | AW30: =AV30 -> 612 | AX30: 156 | AY30: 36 | AZ30: 0 | BA30: =AZ30-'Cash Flows'!BA11 -> -2253 | BB30: =BA30 -> -2253 | BC30: 0 | BD30: =BC30-'Cash Flows'!BD11 -> -2539 | BE30: 0 | BG30: =BF30 -> 0 | BH30: =BG30-'Cash Flows'!BH11 -> -2934 | BI30: 704 | BJ30: 1617 | BK30: 1767 | BL30: =BK30 -> 1767 | BM30: 1791 | BN30: 1819 | BO30: 7695 | BP30: 7768 | BQ30: =BP30 -> 7768 | BR30: 9090 | BS30: 9174 | BT30: 8826 | BU30: 8480 | BV30: =BU30 -> 8480 | BW30: =BV30-'Cash Flows'!BW11 -> 8480 | BX30: =BW30-'Cash Flows'!BX11 -> 8480 | BY30: =BX30-'Cash Flows'!BY11 -> 8480 | BZ30: =BY30-'Cash Flows'!BZ11 -> 8480 | CA30: =BZ30 -> 8480
C31: Deferred revenue | D31: 2915 | E31: 3249 | F31: 3327 | G31: 3441 | H31: 4269 | I31: =H31 -> 4269 | J31: 4150 | K31: 4482 | L31: 4594 | M31: 4375 | N31: =M31 -> 4375 | O31: 4957 | P31: 5009 | Q31: 4991 | R31: 5346 | S31: =R31 -> 5346 | T31: 5641 | U31: 5525 | V31: 5562 | W31: 6413 | X31: =W31 -> 6413 | Y31: 7832 | Z31: 7898 | AA31: 8838 | AB31: 10047 | AC31: =AB31 -> 10047 | AD31: 10920 | AE31: 11903 | AF31: 13699 | AG31: 13975 | AH31: =AG31 -> 13975 | AI31: 13700 | AJ31: 14750 | AK31: 17490 | AL31: 17391 | AM31: =AL31 -> 17391 | AN31: 17853 | AO31: 19991 | AP31: 21858 | AQ31: 24681 | AR31: =AQ31 -> 24681 | AS31: 25632 | AT31: 26306 | AU31: 28527 | AV31: 31983 | AW31: =AV31 -> 31983 | AX31: 32835 | AY31: 33237 | AZ31: 36887 | BA31: 43720 | BB31: =BA31 -> 43720 | BC31: 46564 | BD31: 51553 | BE31: 53834 | BF31: 57816 | BG31: =BF31 -> 57816 | BH31: 58082 | BI31: 57539 | BJ31: 64565 | BK31: 68187 | BL31: =BK31 -> 68187 | BM31: 67019 | BN31: 65286 | BO31: 80000 | BP31: 79173 | BQ31: =BP31 -> 79173 | BR31: 74809 | BS31: 68009 | BT31: 74737 | BU31: 77515 | BV31: =BU31 -> 77515 | BW31: =BW71*'Income Statement'!BW28 -> 92760.807 | BX31: =BX71*'Income Statement'!BX28 -> 91898.129 | BY31: =BY71*'Income Statement'!BY28 -> 94118.761 | BZ31: =BZ71*'Income Statement'!BZ28 -> 107966.99 | CA31: =BZ31 -> 107966.99
C32: Convertible Senior Notes | BF32: 169 | BG32: =SUM(BF32) -> 169 | BH32: 169 | BN32: 432364 | BO32: 432927 | BP32: 433490 | BR32: 434031
B33: Total Current Liabilities | D33: =SUM(D23:D31) -> 10325 | E33: =SUM(E23:E31) -> 11101 | F33: =SUM(F23:F31) -> 13114 | G33: =SUM(G23:G31) -> 12125 | H33: =SUM(H23:H31) -> 16881 | I33: =SUM(I23:I31) -> 16881 | J33: =SUM(J23:J31) -> 27142 | K33: =SUM(K23:K31) -> 26472 | ... BE33: =SUM(BE23:BE31) -> 151410 | BF33: =SUM(BF23:BF32) -> 150776 | BG33: =SUM(BG23:BG32) -> 150776 | BH33: =SUM(BH23:BH32) -> 157282 | BI33: =SUM(BI23:BI32) -> 158251 | BJ33: =SUM(BJ23:BJ32) -> 161976 | BK33: =SUM(BK23:BK32) -> 167215 | BL33: =SUM(BL23:BL32) -> 167215 | BM33: =SUM(BM23:BM32) -> 183546 | ... CA33: =SUM(CA23:CA32) -> 262640.75
C34: Revolving Line of Credit | D34: 0 | E34: 0 | F34: 0 | G34: 0 | H34: 0 | J34: 0 | K34: 0 | L34: 0 | M34: 0 | N34: =M34 -> 0 | O34: 0 | P34: 0 | Q34: 0 | R34: 12500 | S34: =R34 -> 12500 | T34: 12500 | U34: 12500 | V34: 12500 | W34: 0 | X34: =W34 -> 0 | Y34: 0 | Z34: 0 | AA34: 32594 | AB34: =AA34 -> 32594 | AC34: =AB34 -> 32594 | AD34: 32594 | AE34: 32594 | AF34: 32594 | AG34: 32594 | AH34: =AG34 -> 32594 | AI34: 32594 | AK34: =AJ34 -> 0 | AL34: 0 | AM34: =AL34 -> 0 | AN34: =AM34 -> 0 | AO34: =AN34 -> 0 | AP34: =AO34 -> 0 | AQ34: =AP34 -> 0 | AR34: =AQ34 -> 0 | AS34: =AR34 -> 0 | AT34: =AS34 -> 0 | ... CA34: =BZ34 -> 0
C35: Senior convertible note | AJ35: 190615 | AK35: 193664 | AL35: 196763 | AM35: =AL35 -> 196763 | AN35: 199842 | AO35: 203051 | AP35: 206301 | AQ35: 209604 | AR35: =AQ35 -> 209604 | AS35: 212924 | AT35: 642203 | AU35: 646592 | AV35: 643316 | AW35: =AV35 -> 643316 | AX35: 782241 | AY35: 773588 | AZ35: 773353 | BA35: 768599 | BB35: =BA35 -> 768599 | BC35: 737865 | BD35: 736485 | BE35: 737429 | BF35: 738376 | BG35: =BF35 -> 738376 | BH35: 739284 | BI35: 740215 | BJ35: 741169 | BK35: 742125 | BL35: =BK35 -> 742125 | BM35: 1160972 | BN35: 730012 | BO35: 730932 | BP35: 731855 | BQ35: =BP35 -> 731855 | BR35: 732721 | BS35: 733620 | BT35: 734553 | BU35: 735490 | BV35: =BU35 -> 735490 | BW35: 212924 | BX35: =BW35 -> 212924 | BY35: =BX35 -> 212924 | BZ35: =BY35 -> 212924 | CA35: =BZ35 -> 212924
C36: Accrued federal fees – Less current portion | D36: 4859 | E36: 5799 | F36: 6532 | G36: 7411 | H36: 7703 | I36: =H36 -> 7703 | J36: 0 | K36: 0 | L36: 0 | M36: 0 | N36: =M36 -> 0 | O36: 0 | P36: 0 | Q36: 0 | R36: 0 | S36: =R36 -> 0 | U36: 0 | V36: 0 | W36: 0 | X36: =W36 -> 0 | Y36: 0 | Z36: 0 | AA36: 0 | AB36: 0 | AC36: =AB36 -> 0 | AH36: =AG36 -> 0 | AL36: 0 | AM36: =AL36 -> 0 | AR36: =AQ36 -> 0 | AW36: =AV36 -> 0 | BB36: =BA36 -> 0 | BG36: =BF36 -> 0 | BL36: =BK36 -> 0 | BQ36: =BP36 -> 0 | BV36: =BU36 -> 0 | CA36: =BZ36 -> 0
C37: Sales tax liability | D37: 1588 | E37: 1949 | F37: 2316 | G37: 2714 | H37: 3195 | I37: =H37 -> 3195 | J37: 3652 | K37: 4153 | L37: 4693 | M37: 5350 | N37: =M37 -> 5350 | O37: 5735 | P37: 2358 | Q37: 2177 | R37: 2582 | S37: =R37 -> 2582 | T37: 2303 | U37: 2063 | V37: 1949 | W37: 1915 | X37: =W37 -> 1915 | Y37: 1902 | Z37: 1650 | AA37: 1591 | AB37: 1476 | AC37: =AB37 -> 1476 | AD37: 1399 | AE37: 1284 | AF37: 1207 | AG37: 1044 | AH37: =AG37 -> 1044 | AI37: 979 | AJ37: 928 | AK37: 884 | AL37: 841 | AM37: =AL37 -> 841 | AN37: 839 | AO37: 836 | AP37: 833 | AQ37: 838 | AR37: =AQ37 -> 838 | AS37: 843 | AT37: 847 | AU37: 851 | AV37: 857 | AW37: =AV37 -> 857 | AX37: 862 | AY37: 867 | AZ37: 872 | BA37: 877 | BB37: =BA37 -> 877 | BC37: 883 | BD37: 888 | BE37: 894 | BF37: 899 | BG37: =BF37 -> 899 | BH37: 906 | BI37: 912 | BJ37: 919 | BL37: =BK37 -> 0 | BP37: 0 | BQ37: =BP37 -> 0 | BV37: =BU37 -> 0 | BW37: =BW72*'Income Statement'!BW28 -> 1496.142 | BX37: =BX72*'Income Statement'!BX28 -> 1531.6355 | BY37: =BY72*'Income Statement'!BY28 -> 1568.646 | BZ37: =BZ72*'Income Statement'!BZ28 -> 1686.9843 | CA37: =BZ37 -> 1686.9843
C38: Operating lease liabilities - less current portion | AN38: 3012 | AO38: 5707 | AP38: 4530 | AQ38: 4329 | AR38: =AQ38 -> 4329 | AS38: 5438 | AT38: 5249 | AU38: 4679 | AV38: 5379 | AW38: =AV38 -> 5379 | AX38: 45135 | AY38: 46029 | AZ38: 45144 | BA38: 47088 | BB38: =BA38 -> 47088 | BC38: 44818 | BD38: 42186 | BE38: 42487 | BF38: 41389 | BG38: =BF38 -> 41389 | BH38: 41703 | BI38: 39973 | BJ38: 38336 | BK38: 36378 | BL38: =BK38 -> 36378 | BM38: 34207 | BN38: 32177 | BO38: 39976 | BP38: 37071 | BQ38: =BP38 -> 37071 | BR38: 34987 | BS38: 35225 | BT38: 35398 | BU38: 42116 | BV38: =BU38 -> 42116 | BW38: =BV38 -> 42116 | BX38: =BW38 -> 42116 | BY38: =BX38 -> 42116 | BZ38: =BY38 -> 42116 | CA38: =BZ38 -> 42116
C39: Notes Payable - Less current portion | E39: 0 | F39: 0 | G39: 0 | H39: 0 | I39: =H39 -> 0 | J39: 0 | K39: 0 | L39: 0 | M39: 0 | N39: =M39 -> 0 | O39: 24962 | P39: 24247 | Q39: 23526 | R39: 22778 | S39: =R39 -> 22778 | T39: 21698 | U39: 21117 | V39: 19232 | W39: 17327 | X39: =W39 -> 17327 | Y39: 15644 | Z39: 14572 | AA39: 470 | AB39: 318 | AC39: =AB39 -> 318 | AD39: 162 | AF39: =AE39 -> 0 | AG39: =AF39 -> 0 | AH39: =AG39 -> 0 | AI39: =AH39 -> 0 | AJ39: =AI39 -> 0 | AK39: =AJ39 -> 0 | AL39: 0 | AM39: =AL39 -> 0 | AN39: =AM39 -> 0 | AO39: =AN39 -> 0 | AP39: =AO39 -> 0 | AQ39: =AP39 -> 0 | AR39: =AQ39 -> 0 | AS39: =AR39 -> 0 | AT39: =AS39 -> 0 | ... CA39: =BZ39 -> 0
C40: FSC Debt - Less current portion | D40: 0 | E40: 0 | F40: 0 | G40: 0 | H40: 0 | I40: =H40 -> 0 | J40: 4000 | K40: 0 | M40: 12500 | N40: =M40 -> 12500 | O40: 0 | P40: =O40 -> 0 | Q40: =P40 -> 0 | R40: =Q40 -> 0 | S40: =R40 -> 0 | T40: 0 | U40: 0 | V40: 0 | W40: 0 | X40: =W40 -> 0 | Y40: 0 | AC40: =AB40 -> 0 | AH40: =AG40 -> 0 | AL40: 0 | AM40: =AL40 -> 0 | AR40: =AQ40 -> 0 | AW40: =AV40 -> 0 | BB40: =BA40 -> 0 | BG40: =BF40 -> 0 | BL40: =BK40 -> 0 | BQ40: =BP40 -> 0 | BV40: =BU40 -> 0 | CA40: =BZ40 -> 0
C41: CNB Debt- Less current portion | D41: 431 | E41: 247 | F41: 109 | G41: 55 | H41: 16 | I41: =H41 -> 16 | J41: 0 | K41: 0 | L41: 2773 | M41: 7095 | N41: =M41 -> 7095 | O41: 0 | P41: 0 | Q41: 0 | R41: 0 | S41: =R41 -> 0 | U41: 0 | V41: 0 | W41: 0 | X41: =W41 -> 0 | Y41: 0 | AC41: =AB41 -> 0 | AH41: =AG41 -> 0 | AL41: 0 | AM41: =AL41 -> 0 | AR41: =AQ41 -> 0 | AW41: =AV41 -> 0 | BB41: =BA41 -> 0 | BG41: =BF41 -> 0 | BL41: =BK41 -> 0 | BQ41: =BP41 -> 0 | BV41: =BU41 -> 0 | CA41: =BZ41 -> 0
C42: Capital leases – Less current portion | D42: 1954 | E42: 1915 | F42: 3506 | G42: 3107 | H42: 4191 | I42: =H42 -> 4191 | J42: 4432 | K42: 4663 | L42: 4704 | M42: 4358 | N42: =M42 -> 4358 | O42: 3836 | P42: 3355 | Q42: 4499 | R42: 4423 | S42: =R42 -> 4423 | T42: 4560 | U42: 4676 | V42: 4538 | W42: 4606 | X42: =W42 -> 4606 | Y42: 4494 | Z42: 4617 | AA42: 4902 | AB42: 5915 | AC42: =AB42 -> 5915 | AD42: 6468 | AE42: 6384 | AF42: 6867 | AG42: 7161 | AH42: =AG42 -> 7161 | AI42: 7654 | AJ42: 7869 | AK42: 6250 | AL42: 4509 | AM42: =AL42 -> 4509 | AN42: 3316 | AO42: 2402 | AP42: 1516 | AQ42: 809 | AR42: =AQ42 -> 809 | AS42: 286 | AT42: 100 | AU42: 0 | AV42: =+AU42 -> 0 | AW42: =AV42 -> 0 | AX42: 0 | AZ42: =AY42 -> 0 | BA42: =+AZ42 -> 0 | BB42: =BA42 -> 0 | BC42: 0 | BD42: 0 | BE42: =BD42 -> 0 | BF42: =+BE42 -> 0 | BG42: =BF42 -> 0 | BI42: 1463 | BJ42: 3048 | BK42: 2877 | BL42: =BK42 -> 2877 | BM42: 2414 | BN42: 1949 | BO42: 13716 | BP42: 11688 | BQ42: =BP42 -> 11688 | BR42: 12321 | BS42: 10012 | BT42: 8042 | BU42: 6090 | BV42: =BU42 -> 6090 | BW42: 1516 | BX42: 1516 | BY42: =BX42 -> 1516 | BZ42: =+BY42 -> 1516 | CA42: =BZ42 -> 1516
C43: Convertible preferred stock warrant liability | D43: 305 | E43: 425 | F43: 1132 | G43: 1862 | H43: 1979 | I43: =H43 -> 1979 | J43: 1749 | K43: 2534 | L43: 3156 | M43: 3935 | N43: =M43 -> 3935 | O43: 2647 | P43: 0 | Q43: 0 | R43: 0 | S43: =R43 -> 0 | T43: 0 | U43: 0 | V43: 0 | W43: 0 | X43: =W43 -> 0 | Y43: 0 | AC43: =AB43 -> 0 | AH43: =AG43 -> 0 | AL43: 0 | AM43: =AL43 -> 0 | AR43: =AQ43 -> 0 | AW43: =AV43 -> 0 | BB43: =BA43 -> 0 | BG43: =BF43 -> 0 | BL43: =BK43 -> 0 | BQ43: =BP43 -> 0 | BV43: =BU43 -> 0 | CA43: =BZ43 -> 0
C44: Other long-term liabilities | D44: 169 | E44: 162 | F44: 325 | G44: 518 | H44: 709 | I44: =H44 -> 709 | J44: 906 | K44: 843 | L44: 776 | M44: 715 | N44: =M44 -> 715 | O44: 668 | P44: 613 | Q44: 607 | R44: 548 | S44: =R44 -> 548 | T44: 748 | U44: 672 | V44: 640 | W44: 582 | X44: =W44 -> 582 | Y44: 798 | Z44: 579 | AA44: 532 | AB44: 530 | AC44: =AB44 -> 530 | AD44: 590 | AE44: 1010 | AF44: 959 | AG44: 1041 | AH44: =AG44 -> 1041 | AI44: 1500 | AJ44: 1436 | AK44: 1360 | AL44: 1811 | AM44: =AL44 -> 1811 | AN44: 1358 | AO44: 1231 | AP44: 1234 | AQ44: 4350 | AR44: =AQ44 -> 4350 | AS44: 6589 | AT44: 6814 | AU44: 6809 | AV44: 31465 | AW44: =AV44 -> 31465 | AX44: 32628 | AY44: 13113 | AZ44: 13415 | BA44: 7671 | BB44: =BA44 -> 7671 | BC44: 6682 | BD44: 6108 | BE44: 5147 | BF44: 3080 | BG44: =BF44 -> 3080 | BH44: 4913 | BI44: 3331 | BJ44: 7126 | BK44: 7888 | BL44: =BK44 -> 7888 | BM44: 6601 | BN44: 5661 | BO44: 7441 | BP44: 6717 | BQ44: =BP44 -> 6717 | BR44: 6717 | BS44: 7037 | BT44: 9378 | BU44: 7547 | BV44: =BU44 -> 7547 | BW44: =BW73*'Income Statement'!BW28 -> 10472.994 | BX44: =BX73*'Income Statement'!BX28 -> 9189.8129 | BY44: =BY73*'Income Statement'!BY28 -> 9411.8761 | BZ44: =BZ73*'Income Statement'!BZ28 -> 13495.874 | CA44: =BZ44 -> 13495.874
B45: Total Liabilities | D45: =D33+SUM(D34:D44) -> 19631 | E45: =E33+SUM(E34:E44) -> 21598 | F45: =F33+SUM(F34:F44) -> 27034 | G45: =G33+SUM(G34:G44) -> 27792 | H45: =H33+SUM(H34:H44) -> 34674 | I45: =I33+SUM(I34:I44) -> 34674 | J45: =J33+SUM(J34:J44) -> 41881 | K45: =K33+SUM(K34:K44) -> 38665 | ... CA45: =CA33+SUM(CA34:CA44) -> 534379.61
B47: Shareholders Equity:
C48: Total Shareholder Equity | D48: =D20-D45 -> -1192 | E48: =E20-E45 -> -4549 | F48: =F20-F45 -> 2778 | G48: =G20-G45 -> -2485 | H48: =H20-H45 -> -8067 | I48: =I20-I45 -> -8067 | J48: =J20-J45 -> -14373 | K48: =K20-K45 -> -493 | ... R48: =R20-R45 -> 41753 | S48: =R48 -> 41753 | T48: =T20-T45 -> 35201 | U48: =U20-U45 -> 30575 | V48: =V20-V45 -> 26542 | W48: =W20-W45 -> 26280 | X48: =W48 -> 26280 | Y48: =Y20-Y45 -> 25759 | Z48: =Z20-Z45 -> 26453 | AA48: =AA20-AA45 -> 25779 | AB48: =AB20-AB45 -> 30328 | AC48: =AB48 -> 30328 | AD48: =AD20-AD45 -> 28985 | AE48: =AE20-AE45 -> 32155 | AF48: =AF20-AF45 -> 37772 | AG48: =AG20-AG45 -> 46838 | AH48: =AG48 -> 46838 | AI48: =AI20-AI45 -> 80452 | AJ48: =AJ20-AJ45 -> 119506 | AK48: =AK20-AK45 -> 127884 | AL48: =AL20-AL45 -> 143748 | AM48: =AL48 -> 143748 | AN48: =AN20-AN45 -> 150666 | AO48: =AO20-AO45 -> 166570 | AP48: =AP20-AP45 -> 177971 | AQ48: =AQ20-AQ45 -> 196458 | AR48: =AQ48 -> 196458 | AS48: =AS20-AS45 -> 206466 | AT48: =AT20-AT45 -> 172344 | AU48: =AU20-AU45 -> 262389 | AV48: =AV20-AV45 -> 441963 | AW48: =AV48 -> 441963 | AX48: =AX20-AX45 -> 144206 | AY48: =AY20-AY45 -> 162706 | AZ48: =AZ20-AZ45 -> 171070 | BA48: =BA20-BA45 -> 213385 | BB48: =BA48 -> 213385 | BC48: =BC20-BC45 -> 214359 | BD48: =BD20-BD45 -> 247441 | BE48: =BE20-BE45 -> 269172 | BF48: =BF20-BF45 -> 309965 | BG48: =BF48 -> 309965 | BH48: =BH20-BH45 -> 345020 | BI48: =BI20-BI45 -> 458799 | BJ48: =BJ20-BJ45 -> 503870 | BK48: =BK20-BK45 -> 538085 | BL48: =BK48 -> 538085 | BM48: =BM20-BM45 -> 483598 | BN48: =BN20-BN45 -> 525878 | BO48: =BO20-BO45 -> 565586 | BP48: =BP20-BP45 -> 622192 | BQ48: =BP48 -> 622192 | BR48: =BR20-BR45 -> 664286 | BS48: =BS20-BS45 -> 717377 | BT48: =BT20-BT45 -> 775286 | BU48: =BU20-BU45 -> 785817 | BV48: =BU48 -> 785817 | BW48: =BW20-BW45 -> 1351603.9 | BX48: =BX20-BX45 -> 1418218.2 | BY48: =BY20-BY45 -> 1490557 | BZ48: =BZ20-BZ45 -> 1573788.5 | CA48: =BZ48 -> 1573788.5
B49: Total Liabilities & Shareholders Equity | D49: =D48+D45 -> 18439 | E49: =E48+E45 -> 17049 | F49: =F48+F45 -> 29812 | G49: =G48+G45 -> 25307 | H49: =H48+H45 -> 26607 | I49: =I48+I45 -> 26607 | J49: =J48+J45 -> 27508 | K49: =K48+K45 -> 38172 | ... R49: =R48+R45 -> 116934 | S49: =R49 -> 116934 | T49: =T48+T45 -> 110046 | U49: =U48+U45 -> 104579 | V49: =V48+V45 -> 98870 | W49: =W48+W45 -> 99233 | X49: =W49 -> 99233 | Y49: =Y48+Y45 -> 101664 | Z49: =Z48+Z45 -> 99496 | AA49: =AA48+AA45 -> 102699 | AB49: =AB48+AB45 -> 105239 | AC49: =AB49 -> 105239 | AD49: =AD48+AD45 -> 108348 | AE49: =AE48+AE45 -> 111463 | AF49: =AF48+AF45 -> 118715 | AG49: =AG48+AG45 -> 128196 | AH49: =AG49 -> 128196 | AI49: =AI48+AI45 -> 165911 | AJ49: =AJ48+AJ45 -> 365066 | AK49: =AK48+AK45 -> 376116 | AL49: =AL48+AL45 -> 395666 | AM49: =AL49 -> 395666 | AN49: =AN48+AN45 -> 415366 | AO49: =AO48+AO45 -> 435767 | AP49: =AP48+AP45 -> 454024 | AQ49: =AQ48+AQ45 -> 482380 | AR49: =AQ49 -> 482380 | AS49: =AS48+AS45 -> 503659 | AT49: =AT48+AT45 -> 911239 | AU49: =AU48+AU45 -> 1013287 | AV49: =AV48+AV45 -> 1226541 | AW49: =AV49 -> 1226541 | AX49: =AX48+AX45 -> 1118749 | AY49: =AY48+AY45 -> 1135716 | AZ49: =AZ48+AZ45 -> 1150906 | BA49: =BA48+BA45 -> 1192942 | BB49: =BA49 -> 1192942 | BC49: =BC48+BC45 -> 1188395 | BD49: =BD48+BD45 -> 1177223 | BE49: =BE48+BE45 -> 1206539 | BF49: =BF48+BF45 -> 1244485 | BG49: =BF49 -> 1244485 | BH49: =BH48+BH45 -> 1289108 | BI49: =BI48+BI45 -> 1402944 | BJ49: =BJ48+BJ45 -> 1456444 | BK49: =BK48+BK45 -> 1494568 | BL49: =BK49 -> 1494568 | BM49: =BM48+BM45 -> 1871338 | BN49: =BN48+BN45 -> 1910380 | BO49: =BO48+BO45 -> 2007892 | BP49: =BP48+BP45 -> 2051214 | BQ49: =BP49 -> 2051214 | BR49: =BR48+BR45 -> 2089924 | BS49: =BS48+BS45 -> 1704860 | BT49: =BT48+BT45 -> 1768405 | BU49: =BU48+BU45 -> 1790070 | BV49: =BU49 -> 1790070 | BW49: =BW48+BW45 -> 1873433 | BX49: =BX48+BX45 -> 1932048.1 | BY49: =BY48+BY45 -> 2010086.5 | BZ49: =BZ48+BZ45 -> 2108168.1 | CA49: =BZ49 -> 2108168.1
B50: Scott Berg, sberg@needhamco.com | BB50: Source: Company Reports and Needham & Company, LLC Estimates | BG50: Source: Company Reports and Needham & Company, LLC Estimates | BL50: Source: Company Reports and Needham & Company, LLC Estimates | BQ50: Source: Company Reports and Needham & Company, LLC Estimates | BV50: Source: Company Reports and Needham & Company, LLC Estimates | CA50: Source: Company Reports and Needham & Company, LLC Estimates
B51: 763.350.4027 | BB51: $ in thousands, except per share data | BG51: $ in thousands, except per share data | BL51: $ in thousands, except per share data | BQ51: $ in thousands, except per share data | BV51: $ in thousands, except per share data | CA51: $ in thousands, except per share data
C52: check | D52: =D20-D49 -> 0 | E52: =E20-E49 -> 0 | F52: =F20-F49 -> 0 | G52: =G20-G49 -> 0 | H52: =H20-H49 -> 0 | I52: =I20-I49 -> 0 | J52: =J20-J49 -> 0 | K52: =K20-K49 -> 0 | ... CA52: =CA20-CA49 -> 0
C54: DSO | E54: =((E8+D8)/2)/'Income Statement'!E28*91 -> 24.127111 | F54: =((F8+E8)/2)/'Income Statement'!F28*91 -> 24.80017 | G54: =((G8+F8)/2)/'Income Statement'!G28*91 -> 23.109401 | H54: =((H8+G8)/2)/'Income Statement'!H28*91 -> 23.764233 | J54: =((J8+I8)/2)/'Income Statement'!J28*91 -> 26.109665 | K54: =((K8+J8)/2)/'Income Statement'!K28*91 -> 25.019177 | L54: =((L8+K8)/2)/'Income Statement'!L28*91 -> 23.188772 | M54: =((M8+L8)/2)/'Income Statement'!M28*91 -> 23.274658 | O54: =((O8+N8)/2)/'Income Statement'!O28*91 -> 25.529785 | P54: =((P8+O8)/2)/'Income Statement'!P28*91 -> 25.340652 | Q54: =((Q8+P8)/2)/'Income Statement'!Q28*91 -> 26.071611 | R54: =((R8+Q8)/2)/'Income Statement'!R28*91 -> 25.844592 | T54: =((T8+S8)/2)/'Income Statement'!T28*91 -> 25.631136 | U54: =((U8+T8)/2)/'Income Statement'!U28*91 -> 25.503386 | V54: =((V8+U8)/2)/'Income Statement'!V28*91 -> 24.744773 | W54: =((W8+V8)/2)/'Income Statement'!W28*91 -> 25.098049 | Y54: =((Y8+X8)/2)/'Income Statement'!Y28*91 -> 27.642312 | Z54: =((Z8+Y8)/2)/'Income Statement'!Z28*91 -> 27.254835 | AA54: =((AA8+Z8)/2)/'Income Statement'!AA28*91 -> 26.272803 | AB54: =((AB8+AA8)/2)/'Income Statement'!AB28*91 -> 27.563282 | AD54: =((AD8+AC8)/2)/'Income Statement'!AD28*91 -> 28.389352 | AE54: =((AE8+AD8)/2)/'Income Statement'!AE28*91 -> 30.253253 | AF54: =((AF8+AE8)/2)/'Income Statement'!AF28*91 -> 30.446597 | AG54: =((AG8+AF8)/2)/'Income Statement'!AG28*91 -> 29.794316 | AI54: =((AI8+AH8)/2)/'Income Statement'!AI28*91 -> 29.029471 | AJ54: =((AJ8+AI8)/2)/'Income Statement'!AJ28*91 -> 28.810463 | AK54: =((AK8+AJ8)/2)/'Income Statement'!AK28*91 -> 30.705393 | AL54: =((AL8+AK8)/2)/'Income Statement'!AL28*91 -> 30.633165 | AN54: =((AN8+AM8)/2)/'Income Statement'!AN28*91 -> 30.910187 | AO54: =((AO8+AN8)/2)/'Income Statement'!AO28*91 -> 31.725315 | AP54: =((AP8+AO8)/2)/'Income Statement'!AP28*91 -> 32.350631 | AQ54: =((AQ8+AP8)/2)/'Income Statement'!AQ28*91 -> 34.058301 | AS54: =((AS8+AR8)/2)/'Income Statement'!AS28*91 -> 37.14484 | AT54: =((AT8+AS8)/2)/'Income Statement'!AT28*91 -> 36.283916 | AU54: =((AU8+AT8)/2)/'Income Statement'!AU28*91 -> 33.330475 | AV54: =((AV8+AU8)/2)/'Income Statement'!AV28*91 -> 32.473875 | AX54: =((AX8+AW8)/2)/'Income Statement'!AX28*91 -> 33.236166 | AY54: =((AY8+AX8)/2)/'Income Statement'!AY28*91 -> 33.479914 | AZ54: =((AZ8+AY8)/2)/'Income Statement'!AZ28*91 -> 33.667429 | BA54: =((BA8+AZ8)/2)/'Income Statement'!BA28*91 -> 37.772032 | BC54: =((BC8+BB8)/2)/'Income Statement'!BC28*91 -> 40.238961 | BD54: =((BD8+BC8)/2)/'Income Statement'!BD28*91 -> 38.632307 | BE54: =((BE8+BD8)/2)/'Income Statement'!BE28*91 -> 39.252932 | BF54: =((BF8+BE8)/2)/'Income Statement'!BF28*91 -> 38.374881 | BH54: =((BH8+BG8)/2)/'Income Statement'!BH28*91 -> 36.572428 | BI54: =((BI8+BH8)/2)/'Income Statement'!BI28*91 -> 36.040788 | BJ54: =((BJ8+BI8)/2)/'Income Statement'!BJ28*91 -> 36.165288 | BK54: =((BK8+BJ8)/2)/'Income Statement'!BK28*91 -> 36.516176 | BM54: =((BM8+BL8)/2)/'Income Statement'!BM28*91 -> 36.947636 | BN54: =((BN8+BM8)/2)/'Income Statement'!BN28*91 -> 37.459536 | BO54: =((BO8+BN8)/2)/'Income Statement'!BO28*91 -> 38.030396 | BP54: =((BP8+BO8)/2)/'Income Statement'!BP28*91 -> 37.816303 | BR54: =((BR8+BQ8)/2)/'Income Statement'!BR28*91 -> 38.030293 | BS54: =((BS8+BR8)/2)/'Income Statement'!BS28*91 -> 39.585798 | BT54: =((BT8+BS8)/2)/'Income Statement'!BT28*91 -> 42.394153 | BU54: =((BU8+BT8)/2)/'Income Statement'!BU28*91 -> 40.831235 | BW54: =((BW8+BV8)/2)/'Income Statement'!BW28*91 -> 39.937133 | BX54: =((BX8+BW8)/2)/'Income Statement'!BX28*91 -> 38.666065 | BY54: =((BY8+BX8)/2)/'Income Statement'!BY28*91 -> 38.67912 | BZ54: =((BZ8+BY8)/2)/'Income Statement'!BZ28*91 -> 39.090641
C56: Deferred Revs | E56: =E31 -> 3249 | F56: =F31 -> 3327 | G56: =G31 -> 3441 | H56: =H31 -> 4269 | J56: =J31 -> 4150 | K56: =K31 -> 4482 | L56: =L31 -> 4594 | M56: =M31 -> 4375 | O56: =O31 -> 4957 | P56: =P31 -> 5009 | Q56: =Q31 -> 4991 | R56: =R31 -> 5346 | T56: =T31 -> 5641 | U56: =U31 -> 5525 | V56: =V31 -> 5562 | W56: =W31 -> 6413 | Y56: =Y31 -> 7832 | Z56: =Z31 -> 7898 | AA56: =AA31 -> 8838 | AB56: =AB31 -> 10047 | AD56: =AD31 -> 10920 | AE56: =AE31 -> 11903 | AF56: =AF31 -> 13699 | AG56: =AG31 -> 13975 | AI56: =AI31 -> 13700 | AJ56: =AJ31 -> 14750 | AK56: =AK31 -> 17490 | AL56: =AL31 -> 17391 | AN56: =AN31 -> 17853 | AO56: =AO31 -> 19991 | AP56: =AP31 -> 21858 | AQ56: =AQ31 -> 24681 | AS56: =AS31 -> 25632 | AT56: =AT31 -> 26306 | AU56: =AU31 -> 28527 | AV56: =AV31 -> 31983 | AX56: =AX31 -> 32835 | AY56: =AY31 -> 33237 | AZ56: =AZ31 -> 36887 | BA56: =BA31 -> 43720 | BC56: =BC31 -> 46564 | BD56: =BD31 -> 51553 | BE56: =BE31 -> 53834 | BF56: =BF31 -> 57816 | BH56: =BH31 -> 58082 | BI56: =BI31 -> 57539 | BJ56: =BJ31 -> 64565 | BK56: =BK31 -> 68187 | BM56: =BM31 -> 67019 | BN56: =BN31 -> 65286 | BO56: =BO31 -> 80000 | BP56: =BP31 -> 79173 | BR56: =BR31 -> 74809 | BS56: =BS31 -> 68009 | BT56: =BT31 -> 74737 | BU56: =BU31 -> 77515 | BW56: =BW31 -> 92760.807 | BX56: =BX31 -> 91898.129 | BY56: =BY31 -> 94118.761 | BZ56: =BZ31 -> 107966.99
C57: % y/y change | J57: =J56/E56-1 -> 0.2773161 | K57: =K56/F56-1 -> 0.3471596 | L57: =L56/G56-1 -> 0.33507701 | M57: =M56/H56-1 -> 0.024830171 | O57: =O56/J56-1 -> 0.19445783 | P57: =P56/K56-1 -> 0.11758144 | Q57: =Q56/L56-1 -> 0.086417066 | R57: =R56/M56-1 -> 0.22194286 | T57: =T56/O56-1 -> 0.13798669 | U57: =U56/P56-1 -> 0.10301457 | V57: =V56/Q56-1 -> 0.11440593 | W57: =W56/R56-1 -> 0.19958848 | Y57: =Y56/T56-1 -> 0.38840631 | Z57: =Z56/U56-1 -> 0.42950226 | AA57: =AA56/V56-1 -> 0.58899676 | AB57: =AB56/W56-1 -> 0.56666147 | AD57: =AD56/Y56-1 -> 0.39427988 | AE57: =AE56/Z56-1 -> 0.5070904 | AF57: =AF56/AA56-1 -> 0.55001131 | AG57: =AG56/AB56-1 -> 0.39096248 | AI57: =AI56/AD56-1 -> 0.25457875 | AJ57: =AJ56/AE56-1 -> 0.2391834 | AK57: =AK56/AF56-1 -> 0.27673553 | AL57: =AL56/AG56-1 -> 0.24443649 | AN57: =AN56/AI56-1 -> 0.30313869 | AO57: =AO56/AJ56-1 -> 0.35532203 | AP57: =AP56/AK56-1 -> 0.24974271 | AQ57: =AQ56/AL56-1 -> 0.41918234 | AS57: =AS56/AN56-1 -> 0.43572509 | AT57: =AT56/AO56-1 -> 0.31589215 | AU57: =AU56/AP56-1 -> 0.30510568 | AV57: =AV56/AQ56-1 -> 0.29585511 | AX57: =AX56/AS56-1 -> 0.28101592 | AY57: =AY56/AT56-1 -> 0.26347601 | AZ57: =AZ56/AU56-1 -> 0.2930557 | BA57: =BA56/AV56-1 -> 0.36697621 | BC57: =BC56/AX56-1 -> 0.41812091 | BD57: =BD56/AY56-1 -> 0.5510726 | BE57: =BE56/AZ56-1 -> 0.45943015 | BF57: =BF56/BA56-1 -> 0.32241537 | BH57: =BH56/BC56-1 -> 0.24735847 | BI57: =BI56/BD56-1 -> 0.11611351 | BJ57: =BJ56/BE56-1 -> 0.19933499 | BK57: =BK56/BF56-1 -> 0.17937941 | BM57: =BM56/BH56-1 -> 0.15386867 | BN57: =BN56/BI56-1 -> 0.13463911 | BO57: =BO56/BJ56-1 -> 0.23906141 | BP57: =BP56/BK56-1 -> 0.16111576 | BR57: =BR56/BM56-1 -> 0.11623569 | BS57: =BS56/BN56-1 -> 0.041708789 | BT57: =BT56/BO56-1 -> -0.0657875 | BU57: =BU56/BP56-1 -> -0.020941483 | BW57: =BW56/BR56-1 -> 0.23996854 | BX57: =BX56/BS56-1 -> 0.35126423 | BY57: =BY56/BT56-1 -> 0.25933287 | BZ57: =BZ56/BU56-1 -> 0.39285291
C58: % q/q change | F58: =F56/E56-1 -> 0.024007387 | G58: =G56/F56-1 -> 0.034265104 | H58: =H56/G56-1 -> 0.24062772 | J58: =J56/H56-1 -> -0.027875381 | K58: =K56/J56-1 -> 0.08 | L58: =L56/K56-1 -> 0.024988844 | M58: =M56/L56-1 -> -0.047670875 | O58: =O56/M56-1 -> 0.13302857 | P58: =P56/O56-1 -> 0.010490216 | Q58: =Q56/P56-1 -> -0.0035935316 | R58: =R56/Q56-1 -> 0.07112803 | T58: =T56/R56-1 -> 0.055181444 | U58: =U56/T56-1 -> -0.02056373 | V58: =V56/U56-1 -> 0.0066968326 | W58: =W56/V56-1 -> 0.15300252 | Y58: =Y56/W56-1 -> 0.2212693 | Z58: =Z56/Y56-1 -> 0.0084269663 | AA58: =AA56/Z56-1 -> 0.11901747 | AB58: =AB56/AA56-1 -> 0.13679566 | AD58: =AD56/AB56-1 -> 0.086891609 | AE58: =AE56/AD56-1 -> 0.090018315 | AF58: =AF56/AE56-1 -> 0.15088633 | AG58: =AG56/AF56-1 -> 0.020147456 | AI58: =AI56/AG56-1 -> -0.019677996 | AJ58: =AJ56/AI56-1 -> 0.076642336 | AK58: =AK56/AJ56-1 -> 0.18576271 | AL58: =AL56/AK56-1 -> -0.0056603774 | AN58: =AN56/AL56-1 -> 0.026565465 | AO58: =AO56/AN56-1 -> 0.11975578 | AP58: =AP56/AO56-1 -> 0.093392026 | AQ58: =AQ56/AP56-1 -> 0.1291518 | AS58: =AS56/AQ56-1 -> 0.038531664 | AT58: =AT56/AS56-1 -> 0.026295256 | AU58: =AU56/AT56-1 -> 0.084429408 | AV58: =AV56/AU56-1 -> 0.12114839 | AX58: =AX56/AV56-1 -> 0.026639152 | AY58: =AY56/AX56-1 -> 0.012243033 | AZ58: =AZ56/AY56-1 -> 0.10981737 | BA58: =BA56/AZ56-1 -> 0.18524141 | BC58: =BC56/BA56-1 -> 0.06505032 | BD58: =BD56/BC56-1 -> 0.10714286 | BE58: =BE56/BD56-1 -> 0.044245728 | BF58: =BF56/BE56-1 -> 0.073968124 | BH58: =BH56/BF56-1 -> 0.0046008025 | BI58: =BI56/BH56-1 -> -0.0093488516 | BJ58: =BJ56/BI56-1 -> 0.12210848 | BK58: =BK56/BJ56-1 -> 0.056098505 | BM58: =BM56/BK56-1 -> -0.017129365 | BN58: =BN56/BM56-1 -> -0.025858339 | BO58: =BO56/BN56-1 -> 0.22537757 | BP58: =BP56/BO56-1 -> -0.0103375 | BR58: =BR56/BP56-1 -> -0.055119801 | BS58: =BS56/BR56-1 -> -0.090898154 | BT58: =BT56/BS56-1 -> 0.098928083 | BU58: =BU56/BT56-1 -> 0.037170344 | BW58: =BW56/BU56-1 -> 0.19668202 | BX58: =BX56/BW56-1 -> -0.0093000249 | BY58: =BY56/BX56-1 -> 0.024164061 | BZ58: =BZ56/BY56-1 -> 0.14713573
B60: Drivers of Revenue % - Assets
C61: Accounts Receivable | E61: =E8/'Income Statement'!E28 -> 0.28377689 | F61: =F8/'Income Statement'!F28 -> 0.27462547 | G61: =G8/'Income Statement'!G28 -> 0.25317795 | H61: =H8/'Income Statement'!H28 -> 0.29778732 | J61: =J8/'Income Statement'!J28 -> 0.28919508 | K61: =K8/'Income Statement'!K28 -> 0.27732719 | L61: =L8/'Income Statement'!L28 -> 0.24294469 | M61: =M8/'Income Statement'!M28 -> 0.29480491 | O61: =O8/'Income Statement'!O28 -> 0.27395567 | P61: =P8/'Income Statement'!P28 -> 0.28754304 | Q61: =Q8/'Income Statement'!Q28 -> 0.29861997 | R61: =R8/'Income Statement'!R28 -> 0.2947938 | T61: =T8/'Income Statement'!T28 -> 0.28800291 | U61: =U8/'Income Statement'!U28 -> 0.27251107 | V61: =V8/'Income Statement'!V28 -> 0.28832038 | W61: =W8/'Income Statement'!W28 -> 0.29325896 | Y61: =Y8/'Income Statement'!Y28 -> 0.32955412 | Z61: =Z8/'Income Statement'!Z28 -> 0.27683485 | AA61: =AA8/'Income Statement'!AA28 -> 0.31474794 | AB61: =AB8/'Income Statement'!AB28 -> 0.31400005 | AD61: =AD8/'Income Statement'!AD28 -> 0.32868933 | AE61: =AE8/'Income Statement'!AE28 -> 0.34112766 | AF61: =AF8/'Income Statement'!AF28 -> 0.34406262 | AG61: =AG8/'Income Statement'!AG28 -> 0.3438081 | AI61: =AI8/'Income Statement'!AI28 -> 0.31464222 | AJ61: =AJ8/'Income Statement'!AJ28 -> 0.32995746 | AK61: =AK8/'Income Statement'!AK28 -> 0.36602658 | AL61: =AL8/'Income Statement'!AL28 -> 0.34280777 | AN61: =AN8/'Income Statement'!AN28 -> 0.34666881 | AO61: =AO8/'Income Statement'!AO28 -> 0.36356475 | AP61: =AP8/'Income Statement'!AP28 -> 0.3749239 | AQ61: =AQ8/'Income Statement'!AQ28 -> 0.40812677 | AS61: =AS8/'Income Statement'!AS28 -> 0.4203685 | AT61: =AT8/'Income Statement'!AT28 -> 0.39689554 | AU61: =AU8/'Income Statement'!AU28 -> 0.37935493 | AV61: =AV8/'Income Statement'!AV28 -> 0.38105329 | AX61: =AX8/'Income Statement'!AX28 -> 0.37703979 | AY61: =AY8/'Income Statement'!AY28 -> 0.37425408 | AZ61: =AZ8/'Income Statement'!AZ28 -> 0.39126406 | BA61: =BA8/'Income Statement'!BA28 -> 0.48232421 | BC61: =BC8/'Income Statement'!BC28 -> 0.42626808 | BD61: =BD8/'Income Statement'!BD28 -> 0.43766039 | BE61: =BE8/'Income Statement'!BE28 -> 0.4448125 | BF61: =BF8/'Income Statement'!BF28 -> 0.41994768 | BH61: =BH8/'Income Statement'!BH28 -> 0.40324759 | BI61: =BI8/'Income Statement'!BI28 -> 0.39689612 | BJ61: =BJ8/'Income Statement'!BJ28 -> 0.41040395 | BK61: =BK8/'Income Statement'!BK28 -> 0.40752608 | BM61: =BM8/'Income Statement'!BM28 -> 0.41762277 | BN61: =BN8/'Income Statement'!BN28 -> 0.41407298 | BO61: =BO8/'Income Statement'!BO28 -> 0.4407189 | BP61: =BP8/'Income Statement'!BP28 -> 0.41330654 | BR61: 0.44 | BS61: 0.42 | BT61: 0.44 | BU61: 0.45 | BW61: 0.44 | BX61: 0.42 | BY61: 0.44 | BZ61: 0.45
C62: Prepaid expenses & other | E62: =E9/'Income Statement'!E28 -> 0.067103738 | F62: =F9/'Income Statement'!F28 -> 0.063216427 | G62: =G9/'Income Statement'!G28 -> 0.074064734 | H62: =H9/'Income Statement'!H28 -> 0.051555901 | J62: =J9/'Income Statement'!J28 -> 0.11477822 | K62: =K9/'Income Statement'!K28 -> 0.07420043 | L62: =L9/'Income Statement'!L28 -> 0.075481645 | M62: =M9/'Income Statement'!M28 -> 0.069831121 | O62: =O9/'Income Statement'!O28 -> 0.10904672 | P62: =P9/'Income Statement'!P28 -> 0.11257849 | Q62: =Q9/'Income Statement'!Q28 -> 0.10537709 | R62: =R9/'Income Statement'!R28 -> 0.069321638 | T62: =T9/'Income Statement'!T28 -> 0.10471031 | U62: =U9/'Income Statement'!U28 -> 0.13965779 | V62: =V9/'Income Statement'!V28 -> 0.09034596 | W62: =W9/'Income Statement'!W28 -> 0.060611106 | Y62: =Y9/'Income Statement'!Y28 -> 0.10256478 | Z62: =Z9/'Income Statement'!Z28 -> 0.087177905 | AA62: =AA9/'Income Statement'!AA28 -> 0.099970719 | AB62: =AB9/'Income Statement'!AB28 -> 0.068043523 | AD62: =AD9/'Income Statement'!AD28 -> 0.10883992 | AE62: =AE9/'Income Statement'!AE28 -> 0.14821799 | AF62: =AF9/'Income Statement'!AF28 -> 0.09602444 | AG62: =AG9/'Income Statement'!AG28 -> 0.08735989 | AI62: =AI9/'Income Statement'!AI28 -> 0.12138189 | AJ62: =AJ9/'Income Statement'!AJ28 -> 0.13803992 | AK62: =AK9/'Income Statement'!AK28 -> 0.12192209 | AL62: =AL9/'Income Statement'!AL28 -> 0.12461464 | AN62: =AN9/'Income Statement'!AN28 -> 0.13038987 | AO62: =AO9/'Income Statement'!AO28 -> 0.15543158 | AP62: =AP9/'Income Statement'!AP28 -> 0.13298476 | AQ62: =AQ9/'Income Statement'!AQ28 -> 0.11549592 | AS62: =AS9/'Income Statement'!AS28 -> 0.14088003 | AT62: =AT9/'Income Statement'!AT28 -> 0.17565536 | AU62: =AU9/'Income Statement'!AU28 -> 0.1418546 | AV62: =AV9/'Income Statement'!AV28 -> 0.12627751 | AX62: =AX9/'Income Statement'!AX28 -> 0.14267997 | AY62: =AY9/'Income Statement'!AY28 -> 0.15377446 | AZ62: =AZ9/'Income Statement'!AZ28 -> 0.19318594 | BA62: =BA9/'Income Statement'!BA28 -> 0.17478211 | BC62: =BC9/'Income Statement'!BC28 -> 0.17799833 | BD62: =BD9/'Income Statement'!BD28 -> 0.20310272 | BE62: =BE9/'Income Statement'!BE28 -> 0.16436257 | BF62: =BF9/'Income Statement'!BF28 -> 0.14260481 | BH62: =BH9/'Income Statement'!BH28 -> 0.14657639 | BI62: =BI9/'Income Statement'!BI28 -> 0.17262946 | BJ62: =BJ9/'Income Statement'!BJ28 -> 0.163521 | BK62: =BK9/'Income Statement'!BK28 -> 0.14482436 | BM62: =BM9/'Income Statement'!BM28 -> 0.14423303 | BN62: =BN9/'Income Statement'!BN28 -> 0.16565775 | BO62: =BO9/'Income Statement'!BO28 -> 0.1841155 | BP62: =BP9/'Income Statement'!BP28 -> 0.18244456 | BR62: 0.19 | BS62: 0.2 | BT62: 0.2 | BU62: 0.2 | BW62: 0.19 | BX62: 0.2 | BY62: 0.2 | BZ62: 0.2
C63: Other Assets | E63: =E18/'Income Statement'!E28 -> 0.064310659 | F63: =F18/'Income Statement'!F28 -> 0.060554683 | G63: =G18/'Income Statement'!G28 -> 0.056597801 | H63: =H18/'Income Statement'!H28 -> 0.0492025 | J63: =J18/'Income Statement'!J28 -> 0.061992794 | K63: =K18/'Income Statement'!K28 -> 0.080264652 | L63: =L18/'Income Statement'!L28 -> 0.099188192 | M63: =M18/'Income Statement'!M28 -> 0.14545683 | O63: =O18/'Income Statement'!O28 -> 0.19716569 | P63: =P18/'Income Statement'!P28 -> 0.054689082 | Q63: =Q18/'Income Statement'!Q28 -> 0.051760795 | R63: =R18/'Income Statement'!R28 -> 0.050505765 | T63: =T18/'Income Statement'!T28 -> 0.028506309 | U63: =U18/'Income Statement'!U28 -> 0.023419436 | V63: =V18/'Income Statement'!V28 -> 0.024777774 | W63: =W18/'Income Statement'!W28 -> 0.025920684 | Y63: =Y18/'Income Statement'!Y28 -> 0.025358411 | Z63: =Z18/'Income Statement'!Z28 -> 0.023967495 | AA63: =AA18/'Income Statement'!AA28 -> 0.029891172 | AB63: =AB18/'Income Statement'!AB28 -> 0.049833737 | AD63: =AD18/'Income Statement'!AD28 -> 0.048411112 | AE63: =AE18/'Income Statement'!AE28 -> 0.046074549 | AF63: =AF18/'Income Statement'!AF28 -> 0.047223498 | AG63: =AG18/'Income Statement'!AG28 -> 0.046964966 | AI63: =AI18/'Income Statement'!AI28 -> 0.019013666 | AJ63: =AJ18/'Income Statement'!AJ28 -> 0.016786649 | AK63: =AK18/'Income Statement'!AK28 -> 0.014731104 | AL63: =AL18/'Income Statement'!AL28 -> 0.011557337 | AN63: =AN18/'Income Statement'!AN28 -> 0.012557353 | AO63: =AO18/'Income Statement'!AO28 -> 0.01291389 | AP63: =AP18/'Income Statement'!AP28 -> 0.013131349 | AQ63: =AQ18/'Income Statement'!AQ28 -> 0.01283288 | AS63: =AS18/'Income Statement'!AS28 -> 0.03487296 | AT63: =AT18/'Income Statement'!AT28 -> 0.027948132 | AU63: =AU18/'Income Statement'!AU28 -> 0.029052192 | AV63: =AV18/'Income Statement'!AV28 -> 0.025303984 | AX63: =AX18/'Income Statement'!AX28 -> 0.022736833 | AY63: =AY18/'Income Statement'!AY28 -> 0.021483913 | AZ63: =AZ18/'Income Statement'!AZ28 -> 0.035197761 | BA63: =BA18/'Income Statement'!BA28 -> 0.06838173 | BC63: =BC18/'Income Statement'!BC28 -> 0.064275046 | BD63: =BD18/'Income Statement'!BD28 -> 0.062762037 | BE63: =BE18/'Income Statement'!BE28 -> 0.060315011 | BF63: =BF18/'Income Statement'!BF28 -> 0.053070628 | BH63: =BH18/'Income Statement'!BH28 -> 0.069767761 | BI63: =BI18/'Income Statement'!BI28 -> 0.077749661 | BJ63: =BJ18/'Income Statement'!BJ28 -> 0.072154017 | BK63: =BK18/'Income Statement'!BK28 -> 0.067760665 | BM63: =BM18/'Income Statement'!BM28 -> 0.067479049 | BN63: =BN18/'Income Statement'!BN28 -> 0.070432313 | BO63: =BO18/'Income Statement'!BO28 -> 0.067245308 | BP63: =BP18/'Income Statement'!BP28 -> 0.048029857 | BR63: 0.065 | BS63: 0.07 | BT63: 0.07 | BU63: 0.065 | BW63: 0.065 | BX63: 0.07 | BY63: 0.07 | BZ63: 0.065
B66: Drivers of Revenue % - Liabilities
C67: Accounts Payable | E67: =E23/'Income Statement'!E28 -> 0.15096595 | F67: =F23/'Income Statement'!F28 -> 0.19796723 | G67: =G23/'Income Statement'!G28 -> 0.11436829 | H67: =H23/'Income Statement'!H28 -> 0.25444096 | J67: =J23/'Income Statement'!J28 -> 0.24943599 | K67: =K23/'Income Statement'!K28 -> 0.20559189 | L67: =L23/'Income Statement'!L28 -> 0.14977796 | M67: =M23/'Income Statement'!M28 -> 0.18212768 | O67: =O23/'Income Statement'!O28 -> 0.15460987 | P67: =P23/'Income Statement'!P28 -> 0.13664169 | Q67: =Q23/'Income Statement'!Q28 -> 0.11040241 | R67: =R23/'Income Statement'!R28 -> 0.14780364 | T67: =T23/'Income Statement'!T28 -> 0.083933408 | U67: =U23/'Income Statement'!U28 -> 0.091365528 | V67: =V23/'Income Statement'!V28 -> 0.088735404 | W67: =W23/'Income Statement'!W28 -> 0.071295757 | Y67: =Y23/'Income Statement'!Y28 -> 0.08880705 | Z67: =Z23/'Income Statement'!Z28 -> 0.077251453 | AA67: =AA23/'Income Statement'!AA28 -> 0.088063052 | AB67: =AB23/'Income Statement'!AB28 -> 0.076141787 | AD67: =AD23/'Income Statement'!AD28 -> 0.072191262 | AE67: =AE23/'Income Statement'!AE28 -> 0.096088168 | AF67: =AF23/'Income Statement'!AF28 -> 0.095585152 | AG67: =AG23/'Income Statement'!AG28 -> 0.077468729 | AI67: =AI23/'Income Statement'!AI28 -> 0.093065105 | AJ67: =AJ23/'Income Statement'!AJ28 -> 0.098740183 | AK67: =AK23/'Income Statement'!AK28 -> 0.069337253 | AL67: =AL23/'Income Statement'!AL28 -> 0.096910209 | AN67: =AN23/'Income Statement'!AN28 -> 0.097037753 | AO67: =AO23/'Income Statement'!AO28 -> 0.097293249 | AP67: =AP23/'Income Statement'!AP28 -> 0.080662298 | AQ67: =AQ23/'Income Statement'!AQ28 -> 0.11007663 | AS67: =AS23/'Income Statement'!AS28 -> 0.087992176 | AT67: =AT23/'Income Statement'!AT28 -> 0.12070106 | AU67: =AU23/'Income Statement'!AU28 -> 0.11439858 | AV67: =AV23/'Income Statement'!AV28 -> 0.13406576 | AX67: =AX23/'Income Statement'!AX28 -> 0.1164474 | AY67: =AY23/'Income Statement'!AY28 -> 0.12263009 | AZ67: =AZ23/'Income Statement'!AZ28 -> 0.13821212 | BA67: =BA23/'Income Statement'!BA28 -> 0.11814584 | BC67: =BC23/'Income Statement'!BC28 -> 0.17497278 | BD67: =BD23/'Income Statement'!BD28 -> 0.13692431 | BE67: =BE23/'Income Statement'!BE28 -> 0.10664912 | BF67: =BF23/'Income Statement'!BF28 -> 0.11341285 | BH67: =BH23/'Income Statement'!BH28 -> 0.10282504 | BI67: =BI23/'Income Statement'!BI28 -> 0.10447681 | BJ67: =BJ23/'Income Statement'!BJ28 -> 0.12397818 | BK67: =BK23/'Income Statement'!BK28 -> 0.10206139 | BM67: =BM23/'Income Statement'!BM28 -> 0.10392697 | BN67: =BN23/'Income Statement'!BN28 -> 0.1166467 | BO67: =BO23/'Income Statement'!BO28 -> 0.12822978 | BP67: =BP23/'Income Statement'!BP28 -> 0.094315653 | BR67: 0.12 | BS67: 0.13 | BT67: 0.14 | BU67: 0.12 | BW67: 0.12 | BX67: 0.13 | BY67: 0.14 | BZ67: 0.12
C68: Accrued Liabilities | E68: =E24/'Income Statement'!E28 -> 0.20703703 | F68: =F24/'Income Statement'!F28 -> 0.1884515 | G68: =G24/'Income Statement'!G28 -> 0.20873911 | H68: =H24/'Income Statement'!H28 -> 0.18991399 | J68: =J24/'Income Statement'!J28 -> 0.2451985 | K68: =K24/'Income Statement'!K28 -> 0.23394089 | L68: =L24/'Income Statement'!L28 -> 0.21738903 | M68: =M24/'Income Statement'!M28 -> 0.25077451 | O68: =O24/'Income Statement'!O28 -> 0.32083711 | P68: =P24/'Income Statement'!P28 -> 0.33024104 | Q68: =Q24/'Income Statement'!Q28 -> 0.30066875 | R68: =R24/'Income Statement'!R28 -> 0.25882436 | T68: =T24/'Income Statement'!T28 -> 0.26778754 | U68: =U24/'Income Statement'!U28 -> 0.28796988 | V68: =V24/'Income Statement'!V28 -> 0.24941927 | W68: =W24/'Income Statement'!W28 -> 0.21954875 | Y68: =Y24/'Income Statement'!Y28 -> 0.25639879 | Z68: =Z24/'Income Statement'!Z28 -> 0.23538034 | AA68: =AA24/'Income Statement'!AA28 -> 0.25621004 | AB68: =AB24/'Income Statement'!AB28 -> 0.21725066 | AD68: =AD24/'Income Statement'!AD28 -> 0.27710895 | AE68: =AE24/'Income Statement'!AE28 -> 0.21532885 | AF68: =AF24/'Income Statement'!AF28 -> 0.2389529 | AG68: =AG24/'Income Statement'!AG28 -> 0.21275021 | AI68: =AI24/'Income Statement'!AI28 -> 0.23991172 | AJ68: =AJ24/'Income Statement'!AJ28 -> 0.22275851 | AK68: =AK24/'Income Statement'!AK28 -> 0.21658704 | AL68: =AL24/'Income Statement'!AL28 -> 0.1903781 | AN68: =AN24/'Income Statement'!AN28 -> 0.241018 | AO68: =AO24/'Income Statement'!AO28 -> 0.19273981 | AP68: =AP24/'Income Statement'!AP28 -> 0.24043501 | AQ68: =AQ24/'Income Statement'!AQ28 -> 0.19926731 | AS68: =AS24/'Income Statement'!AS28 -> 0.26015901 | AT68: =AT24/'Income Statement'!AT28 -> 0.3488957 | AU68: =AU24/'Income Statement'!AU28 -> 0.36394603 | AV68: =AV24/'Income Statement'!AV28 -> 0.3475779 | AX68: =AX24/'Income Statement'!AX28 -> 0.38409655 | AY68: =AY24/'Income Statement'!AY28 -> 0.51483496 | AZ68: =AZ24/'Income Statement'!AZ28 -> 0.50480146 | BA68: =BA24/'Income Statement'!BA28 -> 0.4526351 | BC68: =BC24/'Income Statement'!BC28 -> 0.5001231 | BD68: =BD24/'Income Statement'!BD28 -> 0.30041926 | BE68: =BE24/'Income Statement'!BE28 -> 0.31824828 | BF68: =BF24/'Income Statement'!BF28 -> 0.25482733 | BH68: =BH24/'Income Statement'!BH28 -> 0.28472938 | BI68: =BI24/'Income Statement'!BI28 -> 0.26408593 | BJ68: =BJ24/'Income Statement'!BJ28 -> 0.21516699 | BK68: =BK24/'Income Statement'!BK28 -> 0.25989492 | BM68: =BM24/'Income Statement'!BM28 -> 0.32057407 | BN68: =BN24/'Income Statement'!BN28 -> 0.30275382 | BO68: =BO24/'Income Statement'!BO28 -> 0.31908684 | BP68: =BP24/'Income Statement'!BP28 -> 0.30043781 | BR68: 0.32 | BS68: 0.28 | BT68: 0.27 | BU68: 0.25 | BW68: 0.32 | BX68: 0.28 | BY68: 0.27 | BZ68: 0.25
C69: Accrued federal fees | E69: =E26/'Income Statement'!E28 -> 0 | F69: =F26/'Income Statement'!F28 -> 0 | G69: =G26/'Income Statement'!G28 -> 0 | H69: =H26/'Income Statement'!H28 -> 0.021946833 | J69: =J26/'Income Statement'!J28 -> 0.46873877 | K69: =K26/'Income Statement'!K28 -> 0.41330379 | L69: =L26/'Income Statement'!L28 -> 0.2024065 | M69: =M26/'Income Statement'!M28 -> 0.17789806 | O69: =O26/'Income Statement'!O28 -> 0.17932768 | P69: =P26/'Income Statement'!P28 -> 0.17666599 | Q69: =Q26/'Income Statement'!Q28 -> 0.24856005 | R69: =R26/'Income Statement'!R28 -> 0.25518144 | T69: =T26/'Income Statement'!T28 -> 0.24876131 | U69: =U26/'Income Statement'!U28 -> 0.18689304 | V69: =V26/'Income Statement'!V28 -> 0.17328956 | W69: =W26/'Income Statement'!W28 -> 0.15774429 | Y69: =Y26/'Income Statement'!Y28 -> 0.15480731 | Z69: =Z26/'Income Statement'!Z28 -> 0.15450291 | AA69: =AA26/'Income Statement'!AA28 -> 0.14330682 | AB69: =AB26/'Income Statement'!AB28 -> 0.062026376 | AD69: =AD26/'Income Statement'!AD28 -> 0.064193644 | AE69: =AE26/'Income Statement'!AE28 -> 0.068326105 | AF69: =AF26/'Income Statement'!AF28 -> 0.02288293 | AG69: =AG26/'Income Statement'!AG28 -> 0.020775048 | AI69: =AI26/'Income Statement'!AI28 -> 0.022595705 | AJ69: =AJ26/'Income Statement'!AJ28 -> 0.026799738 | AK69: =AK26/'Income Statement'!AK28 -> 0.025741149 | AL69: =AL26/'Income Statement'!AL28 -> 0.019824428 | AN69: =AN26/'Income Statement'!AN28 -> 0.018084735 | AO69: =AO26/'Income Statement'!AO28 -> 0.020365205 | AP69: =AP26/'Income Statement'!AP28 -> 0.023648366 | AQ69: =AQ26/'Income Statement'!AQ28 -> 0.024961252 | AS69: =AS26/'Income Statement'!AS28 -> 0.018446071 | AT69: =AT26/'Income Statement'!AT28 -> 0.016734808 | AU69: =AU26/'Income Statement'!AU28 -> 0.022845831 | AV69: =AV26/'Income Statement'!AV28 -> 0.029284122 | AX69: =AX26/'Income Statement'!AX28 -> 0.036436953 | AY69: =AY26/'Income Statement'!AY28 -> 0.035734654 | AZ69: =AZ26/'Income Statement'!AZ28 -> 0.0015680887 | BA69: =BA26/'Income Statement'!BA28 -> 0.013145237 | BC69: =BC26/'Income Statement'!BC28 -> 0.009027394 | BD69: =BD26/'Income Statement'!BD28 -> 0 | BE69: =BE26/'Income Statement'!BE28 -> 0.0022133487 | BF69: =BF26/'Income Statement'!BF28 -> 0.011860136 | BH69: =BH26/'Income Statement'!BH28 -> 0.015381869 | BI69: =BI26/'Income Statement'!BI28 -> 0.015182922 | BJ69: =BJ26/'Income Statement'!BJ28 -> 0.014497729 | BK69: =BK26/'Income Statement'!BK28 -> 0 | BM69: =BM26/'Income Statement'!BM28 -> 0 | BN69: =BN26/'Income Statement'!BN28 -> 0 | BO69: =BO26/'Income Statement'!BO28 -> 0 | BP69: =BP26/'Income Statement'!BP28 -> 0 | BR69: 0.02 | BS69: 0.02 | BT69: 0.02 | BU69: 0.02 | BW69: 0.02 | BX69: 0.02 | BY69: 0.02 | BZ69: 0.02
C70: Sales tax liability | E70: =E28/'Income Statement'!E28 -> 0.049158202 | F70: =F28/'Income Statement'!F28 -> 0.052902168 | G70: =G28/'Income Statement'!G28 -> 0.019565434 | H70: =H28/'Income Statement'!H28 -> 0.0057466769 | J70: =J28/'Income Statement'!J28 -> 0.0039235946 | K70: =K28/'Income Statement'!K28 -> 0.0038456037 | L70: =L28/'Income Statement'!L28 -> 0.0036508082 | M70: =M28/'Income Statement'!M28 -> 0.0041450332 | O70: =O28/'Income Statement'!O28 -> 0.0037076708 | P70: =P28/'Income Statement'!P28 -> 0.0051448248 | Q70: =Q28/'Income Statement'!Q28 -> 0.01005064 | R70: =R28/'Income Statement'!R28 -> 0.01050435 | T70: =T28/'Income Statement'!T28 -> 0.040331638 | U70: =U28/'Income Statement'!U28 -> 0.028506309 | V70: =V28/'Income Statement'!V28 -> 0.032087218 | W70: =W28/'Income Statement'!W28 -> 0.035023451 | Y70: =Y28/'Income Statement'!Y28 -> 0.030698409 | Z70: =Z28/'Income Statement'!Z28 -> 0.031245178 | AA70: =AA28/'Income Statement'!AA28 -> 0.03189205 | AB70: =AB28/'Income Statement'!AB28 -> 0.030470288 | AD70: =AD28/'Income Statement'!AD28 -> 0.024205556 | AE70: =AE28/'Income Statement'!AE28 -> 0.024954428 | AF70: =AF28/'Income Statement'!AF28 -> 0.023442024 | AG70: =AG28/'Income Statement'!AG28 -> 0.023933722 | AI70: =AI28/'Income Statement'!AI28 -> 0.018623207 | AJ70: =AJ28/'Income Statement'!AJ28 -> 0.019649869 | AK70: =AK28/'Income Statement'!AK28 -> 0.020243783 | AL70: =AL28/'Income Statement'!AL28 -> 0.02406857 | AN70: =AN28/'Income Statement'!AN28 -> 0.01883603 | AO70: =AO28/'Income Statement'!AO28 -> 0.016348985 | AP70: =AP28/'Income Statement'!AP28 -> 0.017130442 | AQ70: =AQ28/'Income Statement'!AQ28 -> 0.020430725 | AS70: =AS28/'Income Statement'!AS28 -> 0.018120057 | AT70: =AT28/'Income Statement'!AT28 -> 0.01568262 | AU70: =AU28/'Income Statement'!AU28 -> 0.014526096 | AV70: =AV28/'Income Statement'!AV28 -> 0.013402666 | AX70: =AX28/'Income Statement'!AX28 -> 0.0084710114 | AY70: =AY28/'Income Statement'!AY28 -> 0.011044498 | AZ70: =AZ28/'Income Statement'!AZ28 -> 0.011916179 | BA70: =BA28/'Income Statement'!BA28 -> 0.015322669 | BC70: =BC28/'Income Statement'!BC28 -> 0.01119944 | BD70: =BD28/'Income Statement'!BD28 -> 0.01189659 | BE70: =BE28/'Income Statement'!BE28 -> 0.012528864 | BF70: =BF28/'Income Statement'!BF28 -> 0.014269601 | BH70: =BH28/'Income Statement'!BH28 -> 0.010112663 | BI70: =BI28/'Income Statement'!BI28 -> 0.011427572 | BJ70: =BJ28/'Income Statement'!BJ28 -> 0.012885422 | BK70: =BK28/'Income Statement'!BK28 -> 0 | BM70: =BM28/'Income Statement'!BM28 -> 0 | BN70: =BN28/'Income Statement'!BN28 -> 0 | BO70: =BO28/'Income Statement'!BO28 -> 0 | BP70: =BP28/'Income Statement'!BP28 -> 0 | BR70: 0.005 | BS70: 0.005 | BT70: 0.005 | BU70: 0.005 | BW70: 0.005 | BX70: 0.005 | BY70: 0.005 | BZ70: 0.005
C71: Deferred Revenue | E71: =E31/'Income Statement'!E28 -> 0.22686789 | F71: =F31/'Income Statement'!F28 -> 0.22139058 | G71: =G31/'Income Statement'!G28 -> 0.21238062 | H71: =H31/'Income Statement'!H28 -> 0.23364346 | J71: =J31/'Income Statement'!J28 -> 0.21710557 | K71: =K31/'Income Statement'!K28 -> 0.22097431 | L71: =L31/'Income Statement'!L28 -> 0.21781575 | M71: =M31/'Income Statement'!M28 -> 0.18504613 | O71: =O31/'Income Statement'!O28 -> 0.20421027 | P71: =P31/'Income Statement'!P28 -> 0.20291675 | Q71: =Q31/'Income Statement'!Q28 -> 0.19293363 | R71: =R31/'Income Statement'!R28 -> 0.18907831 | T71: =T31/'Income Statement'!T28 -> 0.18633151 | U71: =U31/'Income Statement'!U28 -> 0.18249983 | V71: =V31/'Income Statement'!V28 -> 0.17226748 | W71: =W31/'Income Statement'!W28 -> 0.17797574 | Y71: =Y31/'Income Statement'!Y28 -> 0.20602394 | Z71: =Z31/'Income Statement'!Z28 -> 0.20310652 | AA71: =AA31/'Income Statement'!AA28 -> 0.21565565 | AB71: =AB31/'Income Statement'!AB28 -> 0.2272717 | AD71: =AD31/'Income Statement'!AD28 -> 0.23227124 | AE71: =AE31/'Income Statement'!AE28 -> 0.24939762 | AF71: =AF31/'Income Statement'!AF28 -> 0.27353687 | AG71: =AG31/'Income Statement'!AG28 -> 0.25224266 | AI71: =AI31/'Income Statement'!AI28 -> 0.23257788 | AJ71: =AJ31/'Income Statement'!AJ28 -> 0.24132853 | AK71: =AK31/'Income Statement'!AK28 -> 0.26782433 | AL71: =AL31/'Income Statement'!AL28 -> 0.24042303 | AN71: =AN31/'Income Statement'!AN28 -> 0.23951541 | AO71: =AO31/'Income Statement'!AO28 -> 0.25816158 | AP71: =AP31/'Income Statement'!AP28 -> 0.26093185 | AQ71: =AQ31/'Income Statement'!AQ28 -> 0.26750702 | AS71: =AS31/'Income Statement'!AS28 -> 0.26956083 | AT71: =AT31/'Income Statement'!AT28 -> 0.26360831 | AU71: =AU31/'Income Statement'!AU28 -> 0.25438057 | AV71: =AV31/'Income Statement'!AV28 -> 0.25009188 | AX71: =AX31/'Income Statement'!AX28 -> 0.23813841 | AY71: =AY31/'Income Statement'!AY28 -> 0.23116245 | AZ71: =AZ31/'Income Statement'!AZ28 -> 0.2390169 | BA71: =BA31/'Income Statement'!BA28 -> 0.25184477 | BC71: =BC31/'Income Statement'!BC28 -> 0.25475853 | BD71: =BD31/'Income Statement'!BD28 -> 0.272217 | BE71: =BE31/'Income Statement'!BE28 -> 0.27142007 | BF71: =BF31/'Income Statement'!BF28 -> 0.27750126 | BH71: =BH31/'Income Statement'!BH28 -> 0.26589574 | BI71: =BI31/'Income Statement'!BI28 -> 0.25815903 | BJ71: =BJ31/'Income Statement'!BJ28 -> 0.2805893 | BK71: =BK31/'Income Statement'!BK28 -> 0.28522726 | BM71: =BM31/'Income Statement'!BM28 -> 0.271321 | BN71: =BN31/'Income Statement'!BN28 -> 0.25898305 | BO71: =BO31/'Income Statement'!BO28 -> 0.30282154 | BP71: =BP31/'Income Statement'!BP28 -> 0.28412043 | BR71: 0.31 | BS71: 0.3 | BT71: 0.3 | BU71: 0.32 | BW71: 0.31 | BX71: 0.3 | BY71: 0.3 | BZ71: 0.32
C72: Sales tax liability - less current | E72: =E37/'Income Statement'!E28 -> 0.13609281 | F72: =F37/'Income Statement'!F28 -> 0.15411499 | G72: =G37/'Income Statement'!G28 -> 0.16750974 | H72: =H37/'Income Statement'!H28 -> 0.17486317 | J72: =J37/'Income Statement'!J28 -> 0.1910529 | K72: =K37/'Income Statement'!K28 -> 0.20475375 | L72: =L37/'Income Statement'!L28 -> 0.22250965 | M72: =M37/'Income Statement'!M28 -> 0.22628498 | O72: =O37/'Income Statement'!O28 -> 0.23626102 | P72: =P37/'Income Statement'!P28 -> 0.095523597 | Q72: =Q37/'Income Statement'!Q28 -> 0.08415478 | R72: =R37/'Income Statement'!R28 -> 0.091320648 | T72: =T37/'Income Statement'!T28 -> 0.076071877 | U72: =U37/'Income Statement'!U28 -> 0.068144282 | V72: =V37/'Income Statement'!V28 -> 0.060364853 | W72: =W37/'Income Statement'!W28 -> 0.053145728 | Y72: =Y37/'Income Statement'!Y28 -> 0.050032882 | Z72: =Z37/'Income Statement'!Z28 -> 0.042431723 | AA72: =AA37/'Income Statement'!AA28 -> 0.038821922 | AB72: =AB37/'Income Statement'!AB28 -> 0.033388377 | AD72: =AD37/'Income Statement'!AD28 -> 0.029757094 | AE72: =AE37/'Income Statement'!AE28 -> 0.026903011 | AF72: =AF37/'Income Statement'!AF28 -> 0.024100956 | AG72: =AG37/'Income Statement'!AG28 -> 0.018843745 | AI72: =AI37/'Income Statement'!AI28 -> 0.016619981 | AJ72: =AJ37/'Income Statement'!AJ28 -> 0.015183246 | AK72: =AK37/'Income Statement'!AK28 -> 0.01353669 | AL72: =AL37/'Income Statement'!AL28 -> 0.01162646 | AN72: =AN37/'Income Statement'!AN28 -> 0.011256004 | AO72: =AO37/'Income Statement'!AO28 -> 0.010796012 | AP72: =AP37/'Income Statement'!AP28 -> 0.0099440127 | AQ72: =AQ37/'Income Statement'!AQ28 -> 0.0090827309 | AS72: =AS37/'Income Statement'!AS28 -> 0.008865472 | AT72: =AT37/'Income Statement'!AT28 -> 0.0084876543 | AU72: =AU37/'Income Statement'!AU28 -> 0.0075885254 | AV72: =AV37/'Income Statement'!AV28 -> 0.0067013332 | AX72: =AX37/'Income Statement'!AX28 -> 0.0062517225 | AY72: =AY37/'Income Statement'!AY28 -> 0.006029962 | AZ72: =AZ37/'Income Statement'!AZ28 -> 0.0056503033 | BA72: =BA37/'Income Statement'!BA28 -> 0.0050518724 | BC72: =BC37/'Income Statement'!BC28 -> 0.0048310236 | BD72: =BD37/'Income Statement'!BD28 -> 0.0046889356 | BE72: =BE37/'Income Statement'!BE28 -> 0.0045073661 | BF72: =BF37/'Income Statement'!BF28 -> 0.0043149584 | BH72: =BH37/'Income Statement'!BH28 -> 0.004147611 | BI72: =BI37/'Income Statement'!BI28 -> 0.0040918513 | BJ72: =BJ37/'Income Statement'!BJ28 -> 0.0039938289 | BK72: =BK37/'Income Statement'!BK28 -> 0 | BM72: =BM37/'Income Statement'!BM28 -> 0 | BN72: =BN37/'Income Statement'!BN28 -> 0 | BO72: =BO37/'Income Statement'!BO28 -> 0 | BP72: =BP37/'Income Statement'!BP28 -> 0 | BR72: 0.005 | BS72: 0.005 | BT72: 0.005 | BU72: 0.005 | BW72: 0.005 | BX72: 0.005 | BY72: 0.005 | BZ72: 0.005
C73: Other Noncurrent Liabilities | E73: =E44/'Income Statement'!E28 -> 0.011311973 | F73: =F44/'Income Statement'!F28 -> 0.021626672 | G73: =G44/'Income Statement'!G28 -> 0.031971277 | H73: =H44/'Income Statement'!H28 -> 0.038803752 | J73: =J44/'Income Statement'!J28 -> 0.047397023 | K73: =K44/'Income Statement'!K28 -> 0.041562102 | L73: =L44/'Income Statement'!L28 -> 0.036792561 | M73: =M44/'Income Statement'!M28 -> 0.030241824 | O73: =O44/'Income Statement'!O28 -> 0.027519156 | P73: =P44/'Income Statement'!P28 -> 0.024832894 | Q73: =Q44/'Income Statement'!Q28 -> 0.023464378 | R73: =R44/'Income Statement'!R28 -> 0.019381764 | T73: =T44/'Income Statement'!T28 -> 0.02470767 | U73: =U44/'Income Statement'!U28 -> 0.022197265 | V73: =V44/'Income Statement'!V28 -> 0.019822219 | W73: =W44/'Income Statement'!W28 -> 0.016151861 | Y73: =Y44/'Income Statement'!Y28 -> 0.020991714 | Z73: =Z44/'Income Statement'!Z28 -> 0.014889678 | AA73: =AA44/'Income Statement'!AA28 -> 0.012981309 | AB73: =AB44/'Income Statement'!AB28 -> 0.011989052 | AD73: =AD44/'Income Statement'!AD28 -> 0.012549453 | AE73: =AE44/'Income Statement'!AE28 -> 0.021162026 | AF73: =AF44/'Income Statement'!AF28 -> 0.019148979 | AG73: =AG44/'Income Statement'!AG28 -> 0.018789596 | AI73: =AI44/'Income Statement'!AI28 -> 0.025464731 | AJ73: =AJ44/'Income Statement'!AJ28 -> 0.023494764 | AK73: =AK44/'Income Statement'!AK28 -> 0.020825677 | AL73: =AL44/'Income Statement'!AL28 -> 0.025036289 | AN73: =AN44/'Income Statement'!AN28 -> 0.018218895 | AO73: =AO44/'Income Statement'!AO28 -> 0.015896999 | AP73: =AP44/'Income Statement'!AP28 -> 0.014730986 | AQ73: =AQ44/'Income Statement'!AQ28 -> 0.047147827 | AS73: =AS44/'Income Statement'!AS28 -> 0.069293707 | AT73: =AT44/'Income Statement'!AT28 -> 0.068282027 | AU73: =AU44/'Income Statement'!AU28 -> 0.06071712 | AV73: =AV44/'Income Statement'!AV28 -> 0.24604137 | AX73: =AX44/'Income Statement'!AX28 -> 0.23663712 | AY73: =AY44/'Income Statement'!AY28 -> 0.091200568 | AZ73: =AZ44/'Income Statement'!AZ28 -> 0.08692525 | BA73: =BA44/'Income Statement'!BA28 -> 0.044188043 | BC73: =BC44/'Income Statement'!BC28 -> 0.03655821 | BD73: =BD44/'Income Statement'!BD28 -> 0.032252273 | BE73: =BE44/'Income Statement'!BE28 -> 0.025950127 | BF73: =BF44/'Income Statement'!BF28 -> 0.014783172 | BH73: =BH44/'Income Statement'!BH28 -> 0.022491405 | BI73: =BI44/'Income Statement'!BI28 -> 0.014945128 | BJ73: =BJ44/'Income Statement'!BJ28 -> 0.030968471 | BK73: =BK44/'Income Statement'!BK28 -> 0.032995625 | BM73: =BM44/'Income Statement'!BM28 -> 0.026723614 | BN73: =BN44/'Income Statement'!BN28 -> 0.022456622 | BO73: =BO44/'Income Statement'!BO28 -> 0.028166188 | BP73: =BP44/'Income Statement'!BP28 -> 0.024104644 | BR73: 0.035 | BS73: 0.03 | BT73: 0.03 | BU73: 0.04 | BW73: 0.035 | BX73: 0.03 | BY73: 0.03 | BZ73: 0.04

Sheet Cash Flows
B2: ='Income Statement'!B2 -> Five9, Inc (Nasdaq: FIVN) | AV2: =AV42-AQ42 -> 3746 | BE2: =BE42-AZ42 -> 35312 | BS2: =143476-142641 -> 835
B4: Statement of Cash Flows | D4: 2011 | E4: 1Q12 | F4: 2Q12 | G4: 3Q12 | H4: 4Q12 | I4: 2012 | J4: 1Q13 | K4: 2Q13 | L4: 3Q13 | M4: 4Q13 | N4: 2013 | O4: 1Q14 | P4: 2Q14 | Q4: 3Q14 | R4: 4Q14 | S4: 2014 | T4: 1Q15 | U4: 2Q15 | V4: 3Q15 | W4: 4Q15 | X4: 2015 | Y4: 1Q16 | Z4: 2Q16 | AA4: 3Q16 | AB4: 4Q16 | AC4: 2016 | AD4: 1Q17 | AE4: 2Q17 | AF4: 3Q17 | AG4: 4Q17 | AH4: 2017 | AI4: 1Q18 | AJ4: 2Q18 | AK4: 3Q18E | AL4: 4Q18 | AM4: 2018 | AN4: 1Q19 | AO4: 2Q19 | AP4: 3Q19 | AQ4: 4Q19 | AR4: 2019 | AS4: 1Q20 | AT4: 2Q20 | AU4: 3Q20 | AV4: 4Q20 | AW4: 2020 | AX4: 1Q21 | AY4: 2Q21 | AZ4: 3Q21 | BA4: 4Q21 | BB4: 2021 | BC4: 1Q22 | BD4: 2Q22 | BE4: 3Q22 | BF4: 4Q22 | BG4: 2022 | BH4: 1Q23 | BI4: 2Q23 | BJ4: 3Q23 | BK4: 4Q23 | BL4: 2023 | BM4: 1Q24 | BN4: 2Q24 | BO4: 3Q24 | BP4: 4Q24 | BQ4: 2024E | BR4: 1Q25 | BS4: 2Q25 | BT4: ='Income Statement'!BT4 -> 3Q25 | BU4: 4Q25 | BV4: 2025 | BW4: 1Q26E | BX4: 2Q26E | BY4: 3Q26E | BZ4: 4Q26E | CA4: 2026E
B5: Operating Activities
B6: Net Income | D6: ='Income Statement'!D95 -> -7872 | E6: ='Income Statement'!E95 -> -3507.1656 | F6: ='Income Statement'!F95 -> -4640.4095 | G6: ='Income Statement'!G95 -> -5404.2338 | H6: ='Income Statement'!H95 -> -5780.1411 | I6: ='Income Statement'!I95 -> -19331.95 | J6: ='Income Statement'!J95 -> -6656.7411 | K6: ='Income Statement'!K95 -> -8290.2699 | ... AA6: ='Income Statement'!AA95 -> -3890 | AB6: =-11860-AA6-Z6-Y6 -> 409 | AC6: =SUM(Y6:AB6) -> -11860 | AD6: ='Income Statement'!AD95 -> -5255 | AE6: ='Income Statement'!AE95 -> -4007 | AF6: ='Income Statement'!AF95 -> 924 | AG6: ='Income Statement'!AG95 -> -631 | AH6: ='Income Statement'!AH95 -> -8969 | AI6: ='Income Statement'!AI95 -> -607 | AJ6: ='Income Statement'!AJ95 -> -2042 | AK6: ='Income Statement'!AK95 -> -1305 | AL6: =AM6-AK6-AJ6-AI6 -> 3733 | AM6: -221 | AN6: ='Income Statement'!AN95 -> -1924 | AO6: ='Income Statement'!AO95 -> -1860 | AP6: ='Income Statement'!AP95 -> -1604 | AQ6: =AR6-AP6-AO6-AN6 -> 836 | AR6: -4552 | AS6: -7437 | AT6: =-23489-AS6 -> -16052 | AU6: =-34920-AT6-AS6 -> -11431 | AV6: =AW6-AU6-AT6-AS6 -> -7210 | AW6: -42130 | AX6: -12332 | AY6: ='Income Statement'!AY95 -> -16530 | AZ6: ='Income Statement'!AZ95 -> -20537 | BA6: ='Income Statement'!BA95 -> -3601 | BB6: ='Income Statement'!BB95 -> -53000 | BC6: ='Income Statement'!BC95 -> -34120 | BD6: =+-57790-BC6 -> -23670 | BE6: =+-80997-BD6-BC6 -> -23207 | BF6: =-94650-BE6-BD6-BC6 -> -13653 | BG6: ='Income Statement'!BG95 -> -94650 | BH6: ='Income Statement'!BH95 -> -27247 | BI6: =+-48987-BH6 -> -21740 | BJ6: ='Income Statement'!BJ95 -> -20419 | BK6: =+-81764-BJ6-BI6-BH6 -> -12358 | BL6: ='Income Statement'!BL95 -> -81763 | BM6: -7077 | BN6: =+-19893-BM6 -> -12816 | BO6: =+-24372-BN6-BM6 -> -4479 | BP6: =-12795-BO6-BN6-BM6 -> 11577 | BQ6: =SUM(BM6:BP6) -> -12795 | BR6: ='Income Statement'!BR95 -> 576 | BS6: =1730-BR6 -> 1154 | BT6: =19703-BS6-BR6 -> 17973 | BU6: =39416-BT6-BS6-BR6 -> 19713 | BV6: ='Income Statement'!BV95 -> 39416 | BW6: ='Income Statement'!BW95 -> 11070.373 | BX6: ='Income Statement'!BX95 -> 16770.513 | BY6: ='Income Statement'!BY95 -> 17645.841 | BZ6: ='Income Statement'!BZ95 -> 26252.514 | CA6: ='Income Statement'!CA95 -> 71739.241
C7: Adjustments to reconcile net cash
C8: D & A | D8: 1096 | E8: 509 | F8: 548 | G8: 668 | H8: 899 | I8: =SUM(E8:H8) -> 2624 | J8: 957 | K8: 882 | L8: 1061 | M8: 1515 | N8: =SUM(J8:M8) -> 4415 | O8: 1592 | P8: 1699 | Q8: 1567 | R8: 1605 | S8: =SUM(O8:R8) -> 6463 | T8: 1775 | U8: 1910 | V8: 1840 | W8: 1863 | X8: =SUM(T8:W8) -> 7388 | Y8: 2103 | Z8: =4163-Y8 -> 2060 | AA8: =6302-Z8-Y8 -> 2139 | AB8: =8390-AA8-Z8-Y8 -> 2088 | AC8: =SUM(Y8:AB8) -> 8390 | AD8: 2095 | AE8: =4365-AD8 -> 2270 | AF8: =6246-AE8-AD8 -> 1881 | AG8: =8314-AF8-AE8-AD8 -> 2068 | AH8: =SUM(AD8:AG8) -> 8314 | AI8: 2320 | AJ8: =4769-AI8 -> 2449 | AK8: =7436-AJ8-AI8 -> 2667 | AL8: =AM8-AK8-AJ8-AI8 -> 2838 | AM8: 10274 | AN8: 3192 | AO8: =6553-AN8 -> 3361 | AP8: =10050-AO8-AN8 -> 3497 | AQ8: =AR8-AP8-AO8-AN8 -> 4324 | AR8: 14374 | AS8: 4970 | AT8: =11213-AS8 -> 6243 | AU8: =17750-AT8-AS8 -> 6537 | AV8: =AW8-AU8-AT8-AS8 -> 7337 | AW8: 25087 | AX8: 8763 | AY8: =18414-AX8 -> 9651 | AZ8: =28194-AY8-AX8 -> 9780 | BA8: =38732-AZ8-AY8-AX8 -> 10538 | BB8: =SUM(AX8:BA8) -> 38732 | BC8: 10795 | BD8: =22435-BC8 -> 11640 | BE8: =33650-BD8-BC8 -> 11215 | BF8: =44671-BE8-BD8-BC8 -> 11021 | BG8: =SUM(BC8:BF8) -> 44671 | BH8: 11347 | BI8: =23071-BH8 -> 11724 | BJ8: =35553-BI8-BH8 -> 12482 | BK8: =48515-BJ8-BI8-BH8 -> 12962 | BL8: =SUM(BH8:BK8) -> 48515 | BM8: 12183 | BN8: =25121-BM8 -> 12938 | BO8: =38265-BN8-BM8 -> 13144 | BP8: =52905-BO8-BN8-BM8 -> 14640 | BQ8: =SUM(BM8:BP8) -> 52905 | BR8: 14490 | BS8: =29139-BR8 -> 14649 | BT8: =44911-BS8-BR8 -> 15772 | BU8: =61764-BT8-BS8-BR8 -> 16853 | BV8: =SUM(BR8:BU8) -> 61764 | BW8: =BW9+BW10 -> 15024.45 | BX8: =BX9+BX10 -> 15811.864 | BY8: =BY9+BY10 -> 15661.057 | BZ8: =BZ9+BZ10 -> 16390.159 | CA8: =SUM(BW8:BZ8) -> 62887.53
C9: Depreciation | I9: =SUM(E9:H9) -> 0 | N9: =SUM(J9:M9) -> 0 | AH9: =SUM(AD9:AG9) -> 0 | AI9: =+AI8-AI10 -> 2204 | AJ9: =+AJ8-AJ10 -> 2333 | AK9: =+AK8-AK10 -> 2550 | AL9: =+AL8-AL10 -> 2745 | AM9: 0 | AN9: =+AN8-AN10 -> 3104 | AO9: =+AO8-AO10 -> 3273 | AP9: =+AP8-AP10 -> 3409 | AQ9: =+AQ8-AQ10 -> 3706 | AR9: =+AR8-AR10 -> 13492 | AS9: =+AS8-AS10 -> 3880 | AT9: =+AT8-AT10 -> 4505 | AU9: =+AU8-AU10 -> 4799 | ... BA9: =+BA8-BA10 -> 7591 | BB9: =SUM(AX9:BA9) -> 26944 | BC9: =+BC8-BC10 -> 7848 | BD9: =+BD8-BD10 -> 8705 | BE9: =+BE8-BE10 -> 8281 | BF9: =+BF8-BF10 -> 8131 | BG9: =SUM(BC9:BF9) -> 32965 | BH9: =+BH8-BH10 -> 8501 | BI9: =+BI8-BI10 -> 8879 | BJ9: =+BJ8-BJ10 -> 9300 | BK9: =+BK8-BK10 -> 9816 | BL9: =SUM(BH9:BK9) -> 36496 | BM9: =+BM8-BM10 -> 9535 | BN9: =+BN8-BN10 -> 10290 | BO9: =+BO8-BO10 -> 9948 | BP9: =+BP8-BP10 -> 10541 | BQ9: =SUM(BM9:BP9) -> 40314 | BR9: =+BR8-BR10 -> 10390 | BS9: =+BS8-BS10 -> 11185 | BT9: =+BT8-BT10 -> 12308 | BU9: =+BU8-BU10 -> 13415 | BV9: =SUM(BR9:BU9) -> 47298 | BW9: =BW100*('Balance Sheet '!BV12) -> 11524.45 | BX9: =BX100*('Balance Sheet '!BW12) -> 12311.864 | BY9: =BY100*('Balance Sheet '!BX12) -> 12161.057 | BZ9: =BZ100*('Balance Sheet '!BY12) -> 12890.159 | CA9: =SUM(BW9:BZ9) -> 48887.53
C10: Amortization | I10: =SUM(E10:H10) -> 0 | N10: =SUM(J10:M10) -> 0 | AH10: =SUM(AD10:AG10) -> 0 | AI10: ='Income Statement'!AI53 -> 116 | AJ10: ='Income Statement'!AJ53 -> 116 | AK10: ='Income Statement'!AK53 -> 117 | AL10: ='Income Statement'!AL53 -> 93 | AM10: 0 | AN10: ='Income Statement'!AN53 -> 88 | AO10: ='Income Statement'!AO53 -> 88 | AP10: 88 | AQ10: ='Income Statement'!AQ53 -> 618 | AR10: =SUM(AN10:AQ10) -> 882 | AS10: ='Income Statement'!AS53 -> 1090 | AT10: ='Income Statement'!AT53 -> 1738 | AU10: ='Income Statement'!AU53 -> 1738 | AV10: ='Income Statement'!AV53 -> 2283 | AW10: ='Income Statement'!AW53 -> 6849 | AX10: ='Income Statement'!AX53 -> 2947 | AY10: ='Income Statement'!AY53 -> 2947 | AZ10: ='Income Statement'!AZ53 -> 2947 | BA10: ='Income Statement'!BA53 -> 2947 | BB10: =SUM(AX10:BA10) -> 11788 | BC10: ='Income Statement'!BC53 -> 2947 | BD10: ='Income Statement'!BD53 -> 2935 | BE10: ='Income Statement'!BE53 -> 2934 | BF10: ='Income Statement'!BF53 -> 2890 | BG10: =SUM(BC10:BF10) -> 11706 | BH10: ='Income Statement'!BH53 -> 2846 | BI10: ='Income Statement'!BI53 -> 2845 | BJ10: ='Income Statement'!BJ53 -> 3182 | BK10: ='Income Statement'!BK53 -> 3146 | BL10: =SUM(BH10:BK10) -> 12019 | BM10: ='Income Statement'!BM53 -> 2648 | BN10: ='Income Statement'!BN53 -> 2648 | BO10: ='Income Statement'!BO53 -> 3196 | BP10: ='Income Statement'!BP53 -> 4099 | BQ10: =SUM(BM10:BP10) -> 12591 | BR10: ='Income Statement'!BR53 -> 4100 | BS10: ='Income Statement'!BS53 -> 3464 | BT10: ='Income Statement'!BT53 -> 3464 | BU10: ='Income Statement'!BU53 -> 3438 | BV10: =SUM(BR10:BU10) -> 14466 | BW10: ='Income Statement'!BW53 -> 3500 | BX10: ='Income Statement'!BX53 -> 3500 | BY10: ='Income Statement'!BY53 -> 3500 | BZ10: ='Income Statement'!BZ53 -> 3500 | CA10: =SUM(BW10:BZ10) -> 14000
C11: Amortization of operating lease | AN11: 1010 | AO11: =2147-AN11 -> 1137 | AP11: =3420-AO11-AN11 -> 1273 | AQ11: =AR11-AP11-AO11-AN11 -> 1315 | AR11: 4735 | AS11: 1394 | AT11: =2786-AS11 -> 1392 | AU11: =4227-AT11-AS11 -> 1441 | AV11: =AW11-AU11-AT11-AS11 -> 1460 | AW11: 5687 | AX11: 2389 | AY11: =4473-AX11 -> 2084 | AZ11: =6445-AY11-AX11 -> 1972 | BA11: =8698-AZ11-AY11-AX11 -> 2253 | BB11: =SUM(AX11:BA11) -> 8698 | BC11: 2403 | BD11: =4942-BC11 -> 2539 | BE11: =7491-BD11-BC11 -> 2549 | BF11: =10377-BE11-BD11-BC11 -> 2886 | BG11: =SUM(BC11:BF11) -> 10377 | BH11: 2934 | BI11: =5838-BH11 -> 2904 | BJ11: =9234-BI11-BH11 -> 3396 | BK11: =12642-BJ11-BI11-BH11 -> 3408 | BL11: =SUM(BH11:BK11) -> 12642 | BM11: 3323 | BN11: =6312-BM11 -> 2989 | BO11: =10631-BN11-BM11 -> 4319 | BP11: =15358-BO11-BN11-BM11 -> 4727 | BQ11: =SUM(BM11:BP11) -> 15358 | BR11: 5084 | BS11: =10080-BR11 -> 4996 | BT11: =15174-BS11-BR11 -> 5094 | BU11: =20277-BT11-BS11-BR11 -> 5103 | BV11: =SUM(BR11:BU11) -> 20277 | BW11: 0 | BX11: 0 | BY11: 0 | BZ11: 0 | CA11: =SUM(BW11:BZ11) -> 0
C12: Amortization of premium on marketable securities | AJ12: -43 | AK12: =-317-AJ12 -> -274 | AL12: =AM12-AK12-AJ12-AI12 -> -353 | AM12: -670 | AN12: -421 | AO12: =-883-AN12 -> -462 | AP12: =-1036-AO12-AN12 -> -153 | AQ12: =AR12-AP12-AO12-AN12 -> -72 | AR12: -1108 | AS12: 177 | AT12: =630-AS12 -> 453 | AU12: =1819-AT12-AS12 -> 1189 | AV12: =AW12-AU12-AT12-AS12 -> 1271 | AW12: 3090 | AX12: 1682 | AY12: =3521-AX12 -> 1839 | AZ12: =5114-AY12-AX12 -> 1593 | BA12: =6385-AZ12-AY12-AX12 -> 1271 | BB12: =SUM(AX12:BA12) -> 6385 | BC12: 700 | BD12: =1114-BC12 -> 414 | BE12: =1006-BD12-BC12 -> -108 | BF12: =-90-BE12-BD12-BC12 -> -1096 | BG12: =SUM(BC12:BF12) -> -90 | BH12: -1863 | BI12: =+-4315-BH12 -> -2452 | BJ12: =-7684-BI12-BH12 -> -3369 | BK12: =-11351-BJ12-BI12-BH12 -> -3667 | BL12: =SUM(BH12:BK12) -> -11351 | BM12: -4935 | BN12: =+-11217-BM12 -> -6282 | BO12: =+-16833-BN12-BM12 -> -5616 | BP12: =-20818-BO12-BN12-BM12 -> -3985 | BQ12: =SUM(BM12:BP12) -> -20818 | BR12: -3313 | BS12: =-5325-BR12 -> -2012 | BT12: =-6658-BS12-BR12 -> -1333 | BU12: =-7892-BT12-BS12-BR12 -> -1234 | BV12: =SUM(BR12:BU12) -> -7892 | CA12: =SUM(BW12:BZ12) -> 0
C13: Amortization of commission costs | AX13: 5540 | AY13: =11468-AX13 -> 5928 | AZ13: =18358-AY13-AX13 -> 6890 | BA13: =26050-AZ13-AY13-AX13 -> 7692 | BB13: =SUM(AX13:BA13) -> 26050 | BC13: 8678 | BD13: =18653-BC13 -> 9975 | BE13: =29245-BD13-BC13 -> 10592 | BF13: =41034-BE13-BD13-BC13 -> 11789 | BG13: =SUM(BC13:BF13) -> 41034 | BH13: 12423 | BI13: =25710-BH13 -> 13287 | BJ13: =40088-BI13-BH13 -> 14378 | BK13: =55384-BJ13-BI13-BH13 -> 15296 | BL13: =SUM(BH13:BK13) -> 55384 | BM13: 16269 | BN13: =33825-BM13 -> 17556 | BO13: =52152-BN13-BM13 -> 18327 | BP13: =71483-BO13-BN13-BM13 -> 19331 | BQ13: =SUM(BM13:BP13) -> 71483 | BR13: 20362 | BS13: =41528-BR13 -> 21166 | BT13: =63568-BS13-BR13 -> 22040 | BU13: =86006-BT13-BS13-BR13 -> 22438 | BV13: =SUM(BR13:BU13) -> 86006 | CA13: =SUM(BW13:BZ13) -> 0
C14: Provision for doubtful accounts | D14: 51 | E14: 27 | F14: 23 | G14: 9 | H14: 155 | I14: =SUM(E14:H14) -> 214 | J14: 7 | K14: 12 | L14: 10 | M14: 59 | N14: =SUM(J14:M14) -> 88 | O14: 20 | P14: 19 | Q14: 4 | R14: 33 | S14: =SUM(O14:R14) -> 76 | T14: 113 | U14: 21 | V14: 23 | W14: 14 | X14: =SUM(T14:W14) -> 171 | Y14: 25 | Z14: =41-Y14 -> 16 | AA14: =58-Z14-Y14 -> 17 | AB14: =75-AA14-Z14-Y14 -> 17 | AC14: =SUM(Y14:AB14) -> 75 | AD14: 24 | AE14: =45-AD14 -> 21 | AF14: =66-AE14-AD14 -> 21 | AG14: =95-AF14-AE14-AD14 -> 29 | AH14: =SUM(AD14:AG14) -> 95 | AI14: 48 | AJ14: =66-AI14 -> 18 | AK14: =81-AJ14-AI14 -> 15 | AL14: =AM14-AK14-AJ14-AI14 -> 9 | AM14: 90 | AN14: 14 | AO14: =30-AN14 -> 16 | AP14: =78-AO14-AN14 -> 48 | AQ14: =AR14-AP14-AO14-AN14 -> 12 | AR14: 90 | AS14: 255 | AT14: =353-AS14 -> 98 | AU14: =578-AT14-AS14 -> 225 | AV14: =AW14-AU14-AT14-AS14 -> 176 | AW14: 754 | AX14: 160 | AY14: =337-AX14 -> 177 | AZ14: =502-AY14-AX14 -> 165 | BA14: =808-AZ14-AY14-AX14 -> 306 | BB14: =SUM(AX14:BA14) -> 808 | BC14: 222 | BD14: =505-BC14 -> 283 | BE14: =812-BD14-BC14 -> 307 | BF14: =1105-BE14-BD14-BC14 -> 293 | BG14: =SUM(BC14:BF14) -> 1105 | BH14: 317 | BI14: =528-BH14 -> 211 | BJ14: =795-BI14-BH14 -> 267 | BK14: =989-BJ14-BI14-BH14 -> 194 | BL14: =SUM(BH14:BK14) -> 989 | BM14: 352 | BN14: =677-BM14 -> 325 | BO14: =806-BN14-BM14 -> 129 | BP14: =1150-BO14-BN14-BM14 -> 344 | BQ14: =SUM(BM14:BP14) -> 1150 | BR14: 423 | BS14: =945-BR14 -> 522 | BT14: =1254-BS14-BR14 -> 309 | BU14: =1617-BT14-BS14-BR14 -> 363 | BV14: =SUM(BR14:BU14) -> 1617 | CA14: =SUM(BW14:BZ14) -> 0
C15: Stock-based compensation | D15: 357 | E15: 78 | F15: 71 | G15: 119 | H15: 196 | I15: =SUM(E15:H15) -> 464 | J15: 264 | K15: 304 | L15: 457 | M15: 924 | N15: =SUM(J15:M15) -> 1949 | O15: 1196 | P15: 1723 | Q15: 1877 | R15: 1957 | S15: =SUM(O15:R15) -> 6753 | T15: 2235 | U15: 1830 | V15: 1945 | W15: 1720 | X15: =SUM(T15:W15) -> 7730 | Y15: 1994 | Z15: =4408-Y15 -> 2414 | AA15: =6927-Z15-Y15 -> 2519 | AB15: =9643-AA15-Z15-Y15 -> 2716 | AC15: =SUM(Y15:AB15) -> 9643 | AD15: 3129 | AE15: ='Income Statement'!AE63 -> 3854 | AF15: =10703-AE15-AD15 -> 3720 | AG15: =15343-AF15-AE15-AD15 -> 4640 | AH15: =SUM(AD15:AG15) -> 15343 | AI15: 5325 | AJ15: =12122-AI15 -> 6797 | AK15: ='Income Statement'!AK63 -> 8869 | AL15: =AM15-AK15-AJ15-AI15 -> 7493 | AM15: 28484 | AN15: 8686 | AO15: =19122-AN15 -> 10436 | AP15: =30197-AO15-AN15 -> 11075 | AQ15: =AR15-AP15-AO15-AN15 -> 11868 | AR15: 42065 | AS15: 13794 | AT15: =30585-AS15 -> 16791 | AU15: =47871-AT15-AS15 -> 17286 | AV15: =AW15-AU15-AT15-AS15 -> 16876 | AW15: 64747 | AX15: 20908 | AY15: ='Income Statement'!AY63 -> 24901 | AZ15: ='Income Statement'!AZ63 -> 27395 | BA15: ='Income Statement'!BA63 -> 35601 | BB15: =SUM(AX15:BA15) -> 108805 | BC15: ='Income Statement'!BC63 -> 39394 | BD15: =84179-BC15 -> 44785 | BE15: =128682-BD15-BC15 -> 44503 | BF15: =172507-BE15-BD15-BC15 -> 43825 | BG15: =SUM(BC15:BF15) -> 172507 | BH15: 50743 | BI15: =104110-BH15 -> 53367 | BJ15: =156721-BI15-BH15 -> 52611 | BK15: =206292-BJ15-BI15-BH15 -> 49571 | BL15: =SUM(BH15:BK15) -> 206292 | BM15: 44684 | BN15: =88316-BM15 -> 43632 | BO15: =127872-BN15-BM15 -> 39556 | BP15: =166315-BO15-BN15-BM15 -> 38443 | BQ15: =SUM(BM15:BP15) -> 166315 | BR15: 39245 | BS15: =81104-BR15 -> 41859 | BT15: =114443-BS15-BR15 -> 33339 | BU15: =148068-BT15-BS15-BR15 -> 33625 | BV15: =SUM(BR15:BU15) -> 148068 | BW15: ='Income Statement'!BW63 -> 35000 | BX15: ='Income Statement'!BX63 -> 35000 | BY15: ='Income Statement'!BY63 -> 40000 | BZ15: ='Income Statement'!BZ63 -> 42000 | CA15: =SUM(BW15:BZ15) -> 152000
C16: Gain on sale on convertible note | AJ16: -312 | AL16: =AM16-AK16-AJ16-AI16 -> 0 | AM16: -312 | AN16: -217 | AO16: =-217-AN16 -> 0 | AP16: =-217-AN16 -> 0 | AQ16: =AR16-AP16-AO16-AN16 -> 0 | AR16: -217 | AV16: =AW16-AU16-AT16-AS16 -> 0 | BB16: =SUM(AX16:BA16) -> 0 | BG16: =SUM(BC16:BF16) -> 0 | BL16: =SUM(BH16:BK16) -> 0 | BQ16: =SUM(BM16:BP16) -> 0 | BV16: =SUM(BR16:BU16) -> 0 | CA16: =SUM(BW16:BZ16) -> 0
C17: Change in fair of value of contingent consideration | AX17: 2500 | AY17: =5200-AX17 -> 2700 | AZ17: =5260-AY17-AX17 -> 60 | BA17: =5640-AZ17-AY17-AX17 -> 380 | BB17: =SUM(AX17:BA17) -> 5640 | BC17: 260 | BD17: =260-BC17 -> 0 | BE17: =260-BD17-BC17 -> 0 | BF17: =260-BE17-BD17-BC17 -> 0 | BG17: =SUM(BC17:BF17) -> 260 | BL17: =SUM(BH17:BK17) -> 0 | BQ17: =SUM(BM17:BP17) -> 0 | BV17: =SUM(BR17:BU17) -> 0 | CA17: =SUM(BW17:BZ17) -> 0
C18: Other | AF18: =-2133-50 -> -2183 | AG18: =-2133-48-AF18-AE18-AD18 -> 2 | AH18: =SUM(AD18:AG18) -> -2181 | AI18: =-312-10 -> -322 | AJ18: =-19-AI18 -> 303 | AK18: =-59-AJ18-AI18 -> -40 | AL18: =AM18-AK18-AJ18-AI18 -> 86 | AM18: 27 | AN18: -17 | AO18: =-23-AN18 -> -6 | AP18: =2-AO18-AN18 -> 25 | AQ18: =AR18-AP18-AO18-AN18 -> 446 | AR18: 448 | AS18: 147 | AT18: =82-AS18 -> -65 | AU18: =73-AT18-AS18 -> -9 | AV18: =AW18-AU18-AT18-AS18 -> -220 | AW18: -147 | AX18: 186 | AY18: =226-AX18 -> 40 | AZ18: =211-AY18-AX18 -> -15 | BA18: =396-AZ18-AY18-AX18 -> 185 | BB18: =SUM(AX18:BA18) -> 396 | BC18: 210 | BD18: =172-BC18 -> -38 | BE18: =503-BD18-BC18 -> 331 | BF18: =188-BE18-BD18-BC18 -> -315 | BG18: =SUM(BC18:BF18) -> 188 | BH18: 439 | BI18: =622-BH18 -> 183 | BJ18: =669-BI18-BH18 -> 47 | BK18: =807-BI18-BJ18-BH18 -> 138 | BL18: =SUM(BH18:BK18) -> 807 | BM18: -286 | BN18: =+-64-BM18 -> 222 | BO18: =+-145-BN18-BM18 -> -81 | BP18: =-1051-BO18-BN18-BM18 -> -906 | BQ18: =SUM(BM18:BP18) -> -1051 | BR18: -163 | BS18: =-201-BR18 -> -38 | BT18: =159-BS18-BR18 -> 360 | BU18: =45-BT18-BS18-BR18 -> -114 | BV18: =SUM(BR18:BU18) -> 45 | CA18: =SUM(BW18:BZ18) -> 0
C19: Loss on disposal of property and equipment | D19: 48 | E19: 0 | F19: -1 | G19: 0 | H19: 8 | I19: =SUM(E19:H19) -> 7 | J19: 4 | K19: 0 | L19: 1 | M19: -10 | N19: =SUM(J19:M19) -> -5 | O19: 0 | P19: 0 | Q19: 1 | R19: 0 | S19: =SUM(O19:R19) -> 1 | T19: 10 | U19: -1 | V19: 1 | W19: 0 | X19: =SUM(T19:W19) -> 10 | Y19: 1 | Z19: =2-Y19 -> 1 | AA19: =1-Z19-Y19 -> -1 | AC19: =SUM(Y19:AB19) -> 1 | AD19: 3 | AE19: =-13-AD19 -> -16 | AF19: =0-AE19-AD19 -> 13 | AH19: =SUM(AD19:AG19) -> 0 | AL19: =AM19-AK19-AJ19-AI19 -> 0 | AM19: 0 | AQ19: =AR19-AP19-AO19-AN19 -> 0 | AV19: =AW19-AU19-AT19-AS19 -> 0 | BB19: =SUM(AX19:BA19) -> 0 | BG19: =SUM(BC19:BF19) -> 0 | BL19: =SUM(BH19:BK19) -> 0 | BQ19: =SUM(BM19:BP19) -> 0 | BR19: 322 | BS19: =835-BR19 -> 513 | BT19: 0 | BU19: 0 | BV19: =SUM(BR19:BU19) -> 835 | CA19: =SUM(BW19:BZ19) -> 0
C20: Tax benefit from acquisition | AQ20: =AR20-AP20-AO20-AN20 -> 0 | AT20: -2910 | AU20: =-2910-AT20 -> 0 | AV20: =AW20-AU20-AT20-AS20 -> 0 | AW20: =-2910 -> -2910 | BB20: =SUM(AX20:BA20) -> 0 | BG20: =SUM(BC20:BF20) -> 0 | BL20: =SUM(BH20:BK20) -> 0 | BO20: =+-4831 -> -4831 | BP20: =-5482-BO20-BN20-BM20 -> -651 | BQ20: =SUM(BM20:BP20) -> -5482 | BV20: =SUM(BR20:BU20) -> 0 | CA20: =SUM(BW20:BZ20) -> 0
C21: Noncash interest expense | D21: 41 | E21: 7 | F21: 6 | G21: 4 | H21: 5 | I21: =SUM(E21:H21) -> 22 | J21: 0 | K21: 0 | L21: 0 | M21: 6 | N21: =SUM(J21:M21) -> 6 | O21: 51 | P21: 78 | Q21: 81 | R21: 83 | S21: =SUM(O21:R21) -> 293 | T21: 84 | U21: 87 | V21: 89 | W21: 90 | X21: =SUM(T21:W21) -> 350 | Y21: 91 | Z21: =178-Y21 -> 87 | AA21: =221-Z21-Y21 -> 43 | AB21: =241-AA21-Z21-Y21 -> 20 | AC21: =SUM(Y21:AB21) -> 241 | AD21: -103 | AE21: =-161-AD21 -> -58 | AF21: =-233-AE21-AD21 -> -72 | AG21: =-366-AF21-AE21-AD21 -> -133 | AH21: =SUM(AD21:AG21) -> -366 | AI21: -40 | AJ21: 0 | AL21: =AM21-AK21-AJ21-AI21 -> 0 | AM21: -40 | AQ21: =AR21-AP21-AO21-AN21 -> 0 | AV21: =AW21-AU21-AT21-AS21 -> 0 | BB21: =SUM(AX21:BA21) -> 0 | BG21: =SUM(BC21:BF21) -> 0 | BL21: =SUM(BH21:BK21) -> 0 | BO21: 258 | BP21: =0-BO21 -> -258 | BQ21: =SUM(BM21:BP21) -> 0 | BV21: =SUM(BR21:BU21) -> 0 | CA21: =SUM(BW21:BZ21) -> 0
C22: Impairment on equity investment | BO22: 1250 | BQ22: =SUM(BM22:BP22) -> 1250
C23: Impairment charge related to assets | BP23: 2202 | BQ23: =SUM(BM23:BP23) -> 2202 | BT23: 0 | BU23: 0
C24: Interest on finance lease obligations | BP24: 264 | BQ24: =SUM(BM24:BP24) -> 264 | BR24: 266 | BS24: =548-BR24 -> 282 | BT24: =743-BS24-BR24 -> 195 | BU24: =1033-BT24-BS24-BR24 -> 290 | BV24: =SUM(BR24:BU24) -> 1033
