Workbook
Name ___eps95: #REF!
Name ___eps95: #REF!
Name ___eps95: #REF!
Name ___eps95: #REF!
Name ___eps95: #REF!
Name ___eps95: #REF!
Name ___eps95: #REF!
Name ___eps95: #REF!
Name ___eps96: #REF!
Name ___eps96: #REF!
Name ___eps96: #REF!
Name ___eps96: #REF!
Name ___eps96: #REF!
Name ___eps96: #REF!
Name ___eps96: #REF!
Name ___eps96: #REF!
Name ___eps97: #REF!
Name ___eps97: #REF!
Name ___eps97: #REF!
Name ___eps97: #REF!
Name ___eps97: #REF!
Name ___eps97: #REF!
Name ___eps97: #REF!
Name ___eps97: #REF!
Name ___eps98: #REF!
Name ___eps98: #REF!
Name ___eps98: #REF!
Name ___eps98: #REF!
Name ___eps98: #REF!
Name ___fcc97: #REF!
Name ___fcc97: #REF!
Name ___fcc97: #REF!
Name ___fcc97: #REF!
Name ___fcc97: #REF!
Name ___grm98: #REF!
Name ___grm98: #REF!
Name ___grm98: #REF!
Name ___grm98: #REF!
Name ___grm98: #REF!
Name ___grm99: #REF!
Name ___grm99: #REF!
Name ___grm99: #REF!
Name ___grm99: #REF!
Name ___grm99: #REF!
Name ___net96: #REF!
Name ___net96: #REF!
Name ___net96: #REF!
Name ___net96: #REF!
Name ___net96: #REF!
Name ___net97: #REF!
Name ___net97: #REF!
Name ___net97: #REF!
Name ___net97: #REF!
Name ___net97: #REF!
Name ___net98: #REF!
Name ___net98: #REF!
Name ___net98: #REF!
Name ___net98: #REF!
Name ___net98: #REF!
Name ___net99: #REF!

Sheet __FDSCACHE__
B1: This sheet contains FactSet XML data for use with this workbook's =FDS codes. Modifying the worksheet's contents may damage the workbook's =FDS functionality.

Sheet BM Upload
A1: ALL FISCAL DATA MUST BE ENTERED IN MILLION (INCLUDING NUMBER OF SHARE) | CV1: NULL:FISCAL
A2: ALL PER SHARE DATA MUST BE IN UNIT | CV2: ADJUSTED:FISCAL
A3: DATA MUST BE ENTERED IN THE CURRENCY OF THE COMPANY | CV3: BASIC:FISCAL
A4: Click here to find a list of BlueMatrix Client Codes | CV4: DILUTED:FISCAL
BW5: Strong Buy | CV5: GAAP:FISCAL
BW6: Buy | CV6: INDICATED:FISCAL
BW7: Hold | CV7: MANAGED:FISCAL
BW8: Under Perform | CV8: NON-GAAP:FISCAL
A9: Company name | C9: Rapid 7 | BW9: Rating Suspended | CV9: OPERATING:FISCAL
A10: Rating | B10: RATING | C10: Hold | D10: =_xll.BLUEMATRIX2("/servlet/excelData",C10, $C$14,$B10) -> #NAME? | BW10: Restricted | CV10: PRIMARY:FISCAL
A11: Currency | C11: USD | BW11: Under Review | CV11: PROFORMA:FISCAL
BW12: Sell | CV12: RESTATED:FISCAL
A13: 12-Month Price Target | B13: TARGET_PRICE | C13: NA | D13: =_xll.BLUEMATRIX2("/servlet/excelData",C13, $C$14,$B13) -> #NAME? | CV13: REVENUE:FISCAL
A14: Ticker | C14: RPD | BW14: A | CV14: NULL:CALENDAR
BW15: E | CV15: ADJUSTED:CALENDAR
D16: =$B$17-3 -> 2014 | E16: =$B$17-3 -> 2014 | F16: =$B$17-3 -> 2014 | G16: =$B$17-3 -> 2014 | H16: =$B$17-3 -> 2014 | I16: =$B$17-2 -> 2015 | J16: =$B$17-2 -> 2015 | K16: =$B$17-2 -> 2015 | L16: =$B$17-2 -> 2015 | M16: =$B$17-2 -> 2015 | N16: =$B$17-1 -> 2016 | O16: =$B$17-1 -> 2016 | P16: =$B$17-1 -> 2016 | Q16: =$B$17-1 -> 2016 | R16: =$B$17-1 -> 2016 | S16: =$B$17-0 -> 2017 | T16: =$B$17-0 -> 2017 | U16: =$B$17-0 -> 2017 | V16: =$B$17-0 -> 2017 | W16: =$B$17-0 -> 2017 | X16: =$B$17+1 -> 2018 | Y16: =$B$17+1 -> 2018 | Z16: =$B$17+1 -> 2018 | AA16: =$B$17+1 -> 2018 | AB16: =$B$17+1 -> 2018 | AC16: =$B$17+2 -> 2019 | AD16: =$B$17+2 -> 2019 | AE16: =$B$17+2 -> 2019 | AF16: =$B$17+2 -> 2019 | AG16: =$B$17+2 -> 2019 | AH16: =$B$17+3 -> 2020 | AI16: =$B$17+3 -> 2020 | AJ16: =$B$17+3 -> 2020 | AK16: =$B$17+3 -> 2020 | AL16: =$B$17+3 -> 2020 | AM16: =$B$17+4 -> 2021 | AN16: =$B$17+4 -> 2021 | AO16: =$B$17+4 -> 2021 | AP16: =$B$17+4 -> 2021 | AQ16: =$B$17+4 -> 2021 | AR16: =$B$17+5 -> 2022 | AS16: =$B$17+5 -> 2022 | AT16: =$B$17+5 -> 2022 | AU16: =$B$17+5 -> 2022 | AV16: =$B$17+5 -> 2022 | AW16: =$B$17+6 -> 2023 | AX16: =$B$17+6 -> 2023 | AY16: =$B$17+6 -> 2023 | AZ16: =$B$17+6 -> 2023 | BA16: =$B$17+6 -> 2023 | BB16: =$B$17+7 -> 2024 | BC16: =$B$17+7 -> 2024 | BD16: =$B$17+7 -> 2024 | BE16: =$B$17+7 -> 2024 | BF16: =$B$17+7 -> 2024 | BG16: =BB16+1 -> 2025 | BH16: =BC16+1 -> 2025 | BI16: =BD16+1 -> 2025 | BJ16: =BE16+1 -> 2025 | BK16: =BF16+1 -> 2025 | BL16: =BG16+1 -> 2026 | BM16: =BH16+1 -> 2026 | BN16: =BI16+1 -> 2026 | ... BU16: =BP16+1 -> 2027 | BX16: BASIC:CALENDAR
A17: Current Year (Matching What Selected From Drop-down Bars - ie. Fiscal or Calendar) | B17: 2017 | D17: A | E17: A | F17: A | G17: A | H17: A | I17: A | J17: A | K17: A | L17: A | M17: A | N17: A | O17: A | P17: A | Q17: A | R17: A | S17: A | T17: A | U17: A | V17: A | W17: A | X17: A | Y17: A | Z17: A | AA17: A | AB17: A | AC17: A | AD17: A | AE17: A | AF17: A | AG17: =+AF17 -> A | AH17: A | AI17: A | AJ17: A | AK17: A | AL17: =+AK17 -> A | AM17: A | AN17: A | AO17: A | AP17: A | AQ17: =+AP17 -> A | AR17: A | AS17: A | AT17: A | AU17: A | AV17: =+AU17 -> A | AW17: A | AX17: A | AY17: A | AZ17: A | BA17: =+AZ17 -> A | BB17: A | BC17: A | BD17: A | BE17: A | BF17: =+BE17 -> A | BG17: A | BH17: A | BI17: A | BJ17: A | BK17: =+BJ17 -> A | BL17: E | BM17: E | BN17: E | BO17: E | BP17: =+BO17 -> E | BQ17: E | BR17: E | BS17: E | BT17: E | BU17: =+BT17 -> E | BX17: DILUTED:CALENDAR
A18: Current Base Quarter (NOT one just reported - One After That) | B18: Q3 | D18: =D16&D19 -> 2014Q1 | E18: =E16&E19 -> 2014Q2 | F18: =F16&F19 -> 2014Q3 | G18: =G16&G19 -> 2014Q4 | H18: =H16 -> 2014 | I18: =I16&I19&I17 -> 2015Q1A | J18: =J16&J19&J17 -> 2015Q2A | K18: =K16&K19&K17 -> 2015Q3A | L18: =L16&L19&L17 -> 2015Q4A | M18: =M16&M17 -> 2015A | N18: =N16&N19&N17 -> 2016Q1A | O18: =O16&O19&O17 -> 2016Q2A | P18: =P16&P19&P17 -> 2016Q3A | Q18: =Q16&Q19&Q17 -> 2016Q4A | R18: =R16&R17 -> 2016A | S18: =S16&S19&S17 -> 2017Q1A | T18: =T16&T19&T17 -> 2017Q2A | U18: =U16&U19&U17 -> 2017Q3A | V18: =V16&V19&V17 -> 2017Q4A | W18: =W16&W17 -> 2017A | X18: =X16&X19&X17 -> 2018Q1A | Y18: =Y16&Y19&Y17 -> 2018Q2A | Z18: =Z16&Z19&Z17 -> 2018Q3A | AA18: =AA16&AA19&AA17 -> 2018Q4A | AB18: =AB16&AB17 -> 2018A | AC18: =AC16&AC19&AC17 -> 2019Q1A | AD18: =AD16&AD19&AD17 -> 2019Q2A | AE18: =AE16&AE19&AE17 -> 2019Q3A | AF18: =AF16&AF19&AF17 -> 2019Q4A | AG18: =AG16&AG17 -> 2019A | AH18: =AH16&AH19&AH17 -> 2020Q1A | AI18: =AI16&AI19&AI17 -> 2020Q2A | AJ18: =AJ16&AJ19&AJ17 -> 2020Q3A | AK18: =AK16&AK19&AK17 -> 2020Q4A | AL18: =AL16&AL17 -> 2020A | AM18: =AM16&AM19&AM17 -> 2021Q1A | AN18: =AN16&AN19&AN17 -> 2021Q2A | AO18: =AO16&AO19&AO17 -> 2021Q3A | AP18: =AP16&AP19&AP17 -> 2021Q4A | AQ18: =AQ16&AQ17 -> 2021A | AR18: =AR16&AR19&AR17 -> 2022Q1A | AS18: =AS16&AS19&AS17 -> 2022Q2A | AT18: =AT16&AT19&AT17 -> 2022Q3A | AU18: =AU16&AU19&AU17 -> 2022Q4A | AV18: =AV16&AV17 -> 2022A | AW18: =AW16&AW19&AW17 -> 2023Q1A | AX18: =AX16&AX19&AX17 -> 2023Q2A | AY18: =AY16&AY19&AY17 -> 2023Q3A | AZ18: =AZ16&AZ19&AZ17 -> 2023Q4A | BA18: =BA16&BA17 -> 2023A | BB18: =BB16&BB19&BB17 -> 2024Q1A | BC18: =BC16&BC19&BC17 -> 2024Q2A | BD18: =BD16&BD19&BD17 -> 2024Q3A | BE18: =BE16&BE19&BE17 -> 2024Q4A | BF18: =BF16&BF17 -> 2024A | BG18: =BG16&BG19&BG17 -> 2025Q1A | BH18: =BH16&BH19&BH17 -> 2025Q2A | BI18: =BI16&BI19&BI17 -> 2025Q3A | BJ18: =BJ16&BJ19&BJ17 -> 2025Q4A | BK18: =BK16&BK17 -> 2025A | BL18: =BL16&BL19&BL17 -> 2026Q1E | BM18: =BM16&BM19&BM17 -> 2026Q2E | BN18: =BN16&BN19&BN17 -> 2026Q3E | BO18: =BO16&BO19&BO17 -> 2026Q4E | BP18: =BP16&BP17 -> 2026E | BQ18: =BQ16&BQ19&BQ17 -> 2027Q1E | BR18: =BR16&BR19&BR17 -> 2027Q2E | BS18: =BS16&BS19&BS17 -> 2027Q3E | BT18: =BT16&BT19&BT17 -> 2027Q4E | BU18: =BU16&BU17 -> 2027E | BX18: GAAP:CALENDAR
D19: Q1 | E19: Q2 | F19: Q3 | G19: Q4 | H19: AN | I19: Q1 | J19: Q2 | K19: Q3 | L19: Q4 | M19: AN | N19: Q1 | O19: Q2 | P19: Q3 | Q19: Q4 | R19: AN | S19: Q1 | T19: Q2 | U19: Q3 | V19: Q4 | W19: AN | X19: Q1 | Y19: Q2 | Z19: Q3 | AA19: Q4 | AB19: AN | AC19: Q1 | AD19: Q2 | AE19: Q3 | AF19: Q4 | AG19: AN | AH19: Q1 | AI19: Q2 | AJ19: Q3 | AK19: Q4 | AL19: AN | AM19: Q1 | AN19: Q2 | AO19: Q3 | AP19: Q4 | AQ19: AN | AR19: Q1 | AS19: Q2 | AT19: Q3 | AU19: Q4 | AV19: AN | AW19: Q1 | AX19: Q2 | AY19: Q3 | AZ19: Q4 | BA19: AN | BB19: Q1 | BC19: Q2 | BD19: Q3 | BE19: Q4 | BF19: AN | BG19: Q1 | BH19: Q2 | BI19: Q3 | BJ19: Q4 | BK19: AN | BL19: Q1 | BM19: Q2 | BN19: Q3 | BO19: Q4 | BP19: AN | BQ19: Q1 | BR19: Q2 | BS19: Q3 | BT19: Q4 | BU19: AN | BX19: INDICATED:CALENDAR
A20: BlueMatrix Time Series Grids | D20: =($B$45&"/"&31&"/"&(D16+$D$45)) -> 3/31/2014 | E20: =$B$46&"/"&31&"/"&(E16+$D$46) -> 6/31/2014 | F20: =$B$47&"/"&31&"/"&(F16+$D$47) -> 9/31/2014 | G20: =$B$48&"/"&31&"/"&(G16+$D$48) -> 12/31/2014 | H20: =G20 -> 12/31/2014 | I20: =($B$45&"/"&31&"/"&(I16+$D$45)) -> 3/31/2015 | J20: =$B$46&"/"&31&"/"&(J16+$D$46) -> 6/31/2015 | K20: =$B$47&"/"&31&"/"&(K16+$D$47) -> 9/31/2015 | L20: =$B$48&"/"&31&"/"&(L16+$D$48) -> 12/31/2015 | M20: =L20 -> 12/31/2015 | N20: =($B$45&"/"&31&"/"&(N16+$D$45)) -> 3/31/2016 | O20: =$B$46&"/"&31&"/"&(O16+$D$46) -> 6/31/2016 | P20: =$B$47&"/"&31&"/"&(P16+$D$47) -> 9/31/2016 | Q20: =$B$48&"/"&31&"/"&(Q16+$D$48) -> 12/31/2016 | R20: =Q20 -> 12/31/2016 | S20: =($B$45&"/"&31&"/"&(S16+$D$45)) -> 3/31/2017 | T20: =$B$46&"/"&31&"/"&(T16+$D$46) -> 6/31/2017 | U20: =$B$47&"/"&31&"/"&(U16+$D$47) -> 9/31/2017 | V20: =$B$48&"/"&31&"/"&(V16+$D$48) -> 12/31/2017 | W20: =V20 -> 12/31/2017 | X20: =($B$45&"/"&31&"/"&(X16+$D$45)) -> 3/31/2018 | Y20: =$B$46&"/"&31&"/"&(Y16+$D$46) -> 6/31/2018 | Z20: =$B$47&"/"&31&"/"&(Z16+$D$47) -> 9/31/2018 | AA20: =$B$48&"/"&31&"/"&(AA16+$D$48) -> 12/31/2018 | AB20: =AA20 -> 12/31/2018 | AC20: =($B$45&"/"&31&"/"&(AC16+$D$45)) -> 3/31/2019 | AD20: =$B$46&"/"&31&"/"&(AD16+$D$46) -> 6/31/2019 | AE20: =$B$47&"/"&31&"/"&(AE16+$D$47) -> 9/31/2019 | AF20: =$B$48&"/"&31&"/"&(AF16+$D$48) -> 12/31/2019 | AG20: =AF20 -> 12/31/2019 | AH20: =($B$45&"/"&31&"/"&(AH16+$D$45)) -> 3/31/2020 | AI20: =$B$46&"/"&31&"/"&(AI16+$D$46) -> 6/31/2020 | AJ20: =$B$47&"/"&31&"/"&(AJ16+$D$47) -> 9/31/2020 | AK20: =$B$48&"/"&31&"/"&(AK16+$D$48) -> 12/31/2020 | AL20: =AK20 -> 12/31/2020 | AM20: =($B$45&"/"&31&"/"&(AM16+$D$45)) -> 3/31/2021 | AN20: =$B$46&"/"&31&"/"&(AN16+$D$46) -> 6/31/2021 | AO20: =$B$47&"/"&31&"/"&(AO16+$D$47) -> 9/31/2021 | AP20: =$B$48&"/"&31&"/"&(AP16+$D$48) -> 12/31/2021 | AQ20: =AP20 -> 12/31/2021 | AR20: =($B$45&"/"&31&"/"&(AR16+$D$45)) -> 3/31/2022 | AS20: =$B$46&"/"&31&"/"&(AS16+$D$46) -> 6/31/2022 | AT20: =$B$47&"/"&31&"/"&(AT16+$D$47) -> 9/31/2022 | AU20: =$B$48&"/"&31&"/"&(AU16+$D$48) -> 12/31/2022 | AV20: =AU20 -> 12/31/2022 | AW20: =($B$45&"/"&31&"/"&(AW16+$D$45)) -> 3/31/2023 | AX20: =$B$46&"/"&31&"/"&(AX16+$D$46) -> 6/31/2023 | AY20: =$B$47&"/"&31&"/"&(AY16+$D$47) -> 9/31/2023 | AZ20: =$B$48&"/"&31&"/"&(AZ16+$D$48) -> 12/31/2023 | BA20: =AZ20 -> 12/31/2023 | BB20: =($B$45&"/"&31&"/"&(BB16+$D$45)) -> 3/31/2024 | BC20: =$B$46&"/"&31&"/"&(BC16+$D$46) -> 6/31/2024 | BD20: =$B$47&"/"&31&"/"&(BD16+$D$47) -> 9/31/2024 | BE20: =$B$48&"/"&31&"/"&(BE16+$D$48) -> 12/31/2024 | BF20: =BE20 -> 12/31/2024 | BG20: =($B$45&"/"&31&"/"&(BG16+$D$45)) -> 3/31/2025 | BH20: =$B$46&"/"&31&"/"&(BH16+$D$46) -> 6/31/2025 | BI20: =$B$47&"/"&31&"/"&(BI16+$D$47) -> 9/31/2025 | BJ20: =$B$48&"/"&31&"/"&(BJ16+$D$48) -> 12/31/2025 | BK20: =BJ20 -> 12/31/2025 | BL20: =($B$45&"/"&31&"/"&(BL16+$D$45)) -> 3/31/2026 | BM20: =$B$46&"/"&31&"/"&(BM16+$D$46) -> 6/31/2026 | BN20: =$B$47&"/"&31&"/"&(BN16+$D$47) -> 9/31/2026 | BO20: =$B$48&"/"&31&"/"&(BO16+$D$48) -> 12/31/2026 | BP20: =BO20 -> 12/31/2026 | BQ20: =($B$45&"/"&31&"/"&(BQ16+$D$45)) -> 3/31/2027 | BR20: =$B$46&"/"&31&"/"&(BR16+$D$46) -> 6/31/2027 | BS20: =$B$47&"/"&31&"/"&(BS16+$D$47) -> 9/31/2027 | BT20: =$B$48&"/"&31&"/"&(BT16+$D$48) -> 12/31/2027 | BU20: =BT20 -> 12/31/2027 | BX20: MANAGED:CALENDAR
A21: Revenue ($M) | B21: REVENUE | D21: =+IS!D52/1000 -> 16.736 | E21: =+IS!E52/1000 -> 17.88 | F21: =+IS!F52/1000 -> 20.329 | G21: =+IS!G52/1000 -> 21.935 | H21: =+IS!H52/1000 -> 76.88 | I21: =+IS!I52/1000 -> 23.571 | J21: =+IS!J52/1000 -> 25.79 | K21: =+IS!K52/1000 -> 28.312 | ... BU21: =+IS!BU52/1000 -> 852.86558 | BX21: NON-GAAP:CALENDAR
B22: NON-GAAP:CALENDAR | D22: =_xll.BLUEMATRIX2("/servlet/excelData",D21, $C$14,$B21&":"&D$16&D$17&":"&D$19&":"&$B22) -> #NAME? | E22: =_xll.BLUEMATRIX2("/servlet/excelData",E21, $C$14,$B21&":"&E$16&E$17&":"&E$19&":"&$B22) -> #NAME? | F22: =_xll.BLUEMATRIX2("/servlet/excelData",F21, $C$14,$B21&":"&F$16&F$17&":"&F$19&":"&$B22) -> #NAME? | G22: =_xll.BLUEMATRIX2("/servlet/excelData",G21, $C$14,$B21&":"&G$16&G$17&":"&G$19&":"&$B22) -> #NAME? | H22: =_xll.BLUEMATRIX2("/servlet/excelData",H21, $C$14,$B21&":"&H$16&H$17&":"&H$19&":"&$B22) -> #NAME? | I22: =_xll.BLUEMATRIX2("/servlet/excelData",I21, $C$14,$B21&":"&I$16&I$17&":"&I$19&":"&$B22) -> #NAME? | J22: =_xll.BLUEMATRIX2("/servlet/excelData",J21, $C$14,$B21&":"&J$16&J$17&":"&J$19&":"&$B22) -> #NAME? | K22: =_xll.BLUEMATRIX2("/servlet/excelData",K21, $C$14,$B21&":"&K$16&K$17&":"&K$19&":"&$B22) -> #NAME? | ... BU22: =_xll.BLUEMATRIX2("/servlet/excelData",BU21, $C$14,$B21&":"&BU$16&BU$17&":"&BU$19&":"&$B22) -> #NAME? | BX22: OPERATING:CALENDAR
A23: EPS | B23: EPS | D23: =+IS!D117 -> -0.53622507 | E23: =+IS!E117 -> -0.57502434 | F23: =+IS!F117 -> -0.54374463 | G23: =+IS!G117 -> -0.70322603 | H23: =+IS!H117 -> -2.3584839 | I23: =+IS!I117 -> -0.54167839 | J23: =+IS!J117 -> -0.61019764 | K23: =+IS!K117 -> -0.27495054 | ... BU23: =+IS!BU117 -> 1.7035276 | BX23: PRIMARY:CALENDAR
B24: NON-GAAP:CALENDAR | D24: =_xll.BLUEMATRIX2("/servlet/excelData",D23, $C$14,$B23&":"&D$16&D$17&":"&D$19&":"&$B24) -> #NAME? | E24: =_xll.BLUEMATRIX2("/servlet/excelData",E23, $C$14,$B23&":"&E$16&E$17&":"&E$19&":"&$B24) -> #NAME? | F24: =_xll.BLUEMATRIX2("/servlet/excelData",F23, $C$14,$B23&":"&F$16&F$17&":"&F$19&":"&$B24) -> #NAME? | G24: =_xll.BLUEMATRIX2("/servlet/excelData",G23, $C$14,$B23&":"&G$16&G$17&":"&G$19&":"&$B24) -> #NAME? | H24: =_xll.BLUEMATRIX2("/servlet/excelData",H23, $C$14,$B23&":"&H$16&H$17&":"&H$19&":"&$B24) -> #NAME? | I24: =_xll.BLUEMATRIX2("/servlet/excelData",I23, $C$14,$B23&":"&I$16&I$17&":"&I$19&":"&$B24) -> #NAME? | J24: =_xll.BLUEMATRIX2("/servlet/excelData",J23, $C$14,$B23&":"&J$16&J$17&":"&J$19&":"&$B24) -> #NAME? | K24: =_xll.BLUEMATRIX2("/servlet/excelData",K23, $C$14,$B23&":"&K$16&K$17&":"&K$19&":"&$B24) -> #NAME? | ... BU24: =_xll.BLUEMATRIX2("/servlet/excelData",BU23, $C$14,$B23&":"&BU$16&BU$17&":"&BU$19&":"&$B24) -> #NAME? | BX24: PROFORMA:CALENDAR
A25: FCF | B25: FCF | BF25: RESTATED:CALENDAR | BK25: RESTATED:CALENDAR
D26: =_xll.BLUEMATRIX2("/servlet/excelData",D25, $C$14,$B25&":"&D$16&D$17&":"&D$19&":"&$B26) -> #NAME? | E26: =_xll.BLUEMATRIX2("/servlet/excelData",E25, $C$14,$B25&":"&E$16&E$17&":"&E$19&":"&$B26) -> #NAME? | F26: =_xll.BLUEMATRIX2("/servlet/excelData",F25, $C$14,$B25&":"&F$16&F$17&":"&F$19&":"&$B26) -> #NAME? | G26: =_xll.BLUEMATRIX2("/servlet/excelData",G25, $C$14,$B25&":"&G$16&G$17&":"&G$19&":"&$B26) -> #NAME? | H26: =_xll.BLUEMATRIX2("/servlet/excelData",H25, $C$14,$B25&":"&H$16&H$17&":"&H$19&":"&$B26) -> #NAME? | I26: =_xll.BLUEMATRIX2("/servlet/excelData",I25, $C$14,$B25&":"&I$16&I$17&":"&I$19&":"&$B26) -> #NAME? | J26: =_xll.BLUEMATRIX2("/servlet/excelData",J25, $C$14,$B25&":"&J$16&J$17&":"&J$19&":"&$B26) -> #NAME? | K26: =_xll.BLUEMATRIX2("/servlet/excelData",K25, $C$14,$B25&":"&K$16&K$17&":"&K$19&":"&$B26) -> #NAME? | ... W26: =_xll.BLUEMATRIX2("/servlet/excelData",W25, $C$14,$B25&":"&W$16&W$17&":"&W$19&":"&$B26) -> #NAME? | BF26: REVENUE:CALENDAR | BK26: REVENUE:CALENDAR
A27: FFO | B27: FFO
D28: =_xll.BLUEMATRIX2("/servlet/excelData",D27, $C$14,$B27&":"&D$16&D$17&":"&D$19&":"&$B28) -> #NAME? | E28: =_xll.BLUEMATRIX2("/servlet/excelData",E27, $C$14,$B27&":"&E$16&E$17&":"&E$19&":"&$B28) -> #NAME? | F28: =_xll.BLUEMATRIX2("/servlet/excelData",F27, $C$14,$B27&":"&F$16&F$17&":"&F$19&":"&$B28) -> #NAME? | G28: =_xll.BLUEMATRIX2("/servlet/excelData",G27, $C$14,$B27&":"&G$16&G$17&":"&G$19&":"&$B28) -> #NAME? | H28: =_xll.BLUEMATRIX2("/servlet/excelData",H27, $C$14,$B27&":"&H$16&H$17&":"&H$19&":"&$B28) -> #NAME? | I28: =_xll.BLUEMATRIX2("/servlet/excelData",I27, $C$14,$B27&":"&I$16&I$17&":"&I$19&":"&$B28) -> #NAME? | J28: =_xll.BLUEMATRIX2("/servlet/excelData",J27, $C$14,$B27&":"&J$16&J$17&":"&J$19&":"&$B28) -> #NAME? | K28: =_xll.BLUEMATRIX2("/servlet/excelData",K27, $C$14,$B27&":"&K$16&K$17&":"&K$19&":"&$B28) -> #NAME? | ... W28: =_xll.BLUEMATRIX2("/servlet/excelData",W27, $C$14,$B27&":"&W$16&W$17&":"&W$19&":"&$B28) -> #NAME?
A29: Net Cash/Debt ($M) | B29: NET_CASH_DEBT
D30: =_xll.BLUEMATRIX2("/servlet/excelData",D29, $C$14,$B29&":"&D$16&D$17&":"&D$19&":"&$B30) -> #NAME? | E30: =_xll.BLUEMATRIX2("/servlet/excelData",E29, $C$14,$B29&":"&E$16&E$17&":"&E$19&":"&$B30) -> #NAME? | F30: =_xll.BLUEMATRIX2("/servlet/excelData",F29, $C$14,$B29&":"&F$16&F$17&":"&F$19&":"&$B30) -> #NAME? | G30: =_xll.BLUEMATRIX2("/servlet/excelData",G29, $C$14,$B29&":"&G$16&G$17&":"&G$19&":"&$B30) -> #NAME? | H30: =_xll.BLUEMATRIX2("/servlet/excelData",H29, $C$14,$B29&":"&H$16&H$17&":"&H$19&":"&$B30) -> #NAME? | I30: =_xll.BLUEMATRIX2("/servlet/excelData",I29, $C$14,$B29&":"&I$16&I$17&":"&I$19&":"&$B30) -> #NAME? | J30: =_xll.BLUEMATRIX2("/servlet/excelData",J29, $C$14,$B29&":"&J$16&J$17&":"&J$19&":"&$B30) -> #NAME? | K30: =_xll.BLUEMATRIX2("/servlet/excelData",K29, $C$14,$B29&":"&K$16&K$17&":"&K$19&":"&$B30) -> #NAME? | ... W30: =_xll.BLUEMATRIX2("/servlet/excelData",W29, $C$14,$B29&":"&W$16&W$17&":"&W$19&":"&$B30) -> #NAME?
A31: Operating Margin | B31: OP_MARGIN
D32: =_xll.BLUEMATRIX2("/servlet/excelData",D31, $C$14,$B31&":"&D$16&D$17&":"&D$19&":"&$B32) -> #NAME? | E32: =_xll.BLUEMATRIX2("/servlet/excelData",E31, $C$14,$B31&":"&E$16&E$17&":"&E$19&":"&$B32) -> #NAME? | F32: =_xll.BLUEMATRIX2("/servlet/excelData",F31, $C$14,$B31&":"&F$16&F$17&":"&F$19&":"&$B32) -> #NAME? | G32: =_xll.BLUEMATRIX2("/servlet/excelData",G31, $C$14,$B31&":"&G$16&G$17&":"&G$19&":"&$B32) -> #NAME? | H32: =_xll.BLUEMATRIX2("/servlet/excelData",H31, $C$14,$B31&":"&H$16&H$17&":"&H$19&":"&$B32) -> #NAME? | I32: =_xll.BLUEMATRIX2("/servlet/excelData",I31, $C$14,$B31&":"&I$16&I$17&":"&I$19&":"&$B32) -> #NAME? | J32: =_xll.BLUEMATRIX2("/servlet/excelData",J31, $C$14,$B31&":"&J$16&J$17&":"&J$19&":"&$B32) -> #NAME? | K32: =_xll.BLUEMATRIX2("/servlet/excelData",K31, $C$14,$B31&":"&K$16&K$17&":"&K$19&":"&$B32) -> #NAME? | ... W32: =_xll.BLUEMATRIX2("/servlet/excelData",W31, $C$14,$B31&":"&W$16&W$17&":"&W$19&":"&$B32) -> #NAME?
A33: Revenue ($M) | B33: REVENUE
D34: =_xll.BLUEMATRIX2("/servlet/excelData",D33, $C$14,$B33&":"&D$16&D$17&":"&D$19&":"&$B34) -> #NAME? | E34: =_xll.BLUEMATRIX2("/servlet/excelData",E33, $C$14,$B33&":"&E$16&E$17&":"&E$19&":"&$B34) -> #NAME? | F34: =_xll.BLUEMATRIX2("/servlet/excelData",F33, $C$14,$B33&":"&F$16&F$17&":"&F$19&":"&$B34) -> #NAME? | G34: =_xll.BLUEMATRIX2("/servlet/excelData",G33, $C$14,$B33&":"&G$16&G$17&":"&G$19&":"&$B34) -> #NAME? | H34: =_xll.BLUEMATRIX2("/servlet/excelData",H33, $C$14,$B33&":"&H$16&H$17&":"&H$19&":"&$B34) -> #NAME? | I34: =_xll.BLUEMATRIX2("/servlet/excelData",I33, $C$14,$B33&":"&I$16&I$17&":"&I$19&":"&$B34) -> #NAME? | J34: =_xll.BLUEMATRIX2("/servlet/excelData",J33, $C$14,$B33&":"&J$16&J$17&":"&J$19&":"&$B34) -> #NAME? | K34: =_xll.BLUEMATRIX2("/servlet/excelData",K33, $C$14,$B33&":"&K$16&K$17&":"&K$19&":"&$B34) -> #NAME? | ... W34: =_xll.BLUEMATRIX2("/servlet/excelData",W33, $C$14,$B33&":"&W$16&W$17&":"&W$19&":"&$B34) -> #NAME?
A35: ROIC | B35: ROIC
D36: =_xll.BLUEMATRIX2("/servlet/excelData",D35, $C$14,$B35&":"&D$16&D$17&":"&D$19&":"&$B36) -> #NAME? | E36: =_xll.BLUEMATRIX2("/servlet/excelData",E35, $C$14,$B35&":"&E$16&E$17&":"&E$19&":"&$B36) -> #NAME? | F36: =_xll.BLUEMATRIX2("/servlet/excelData",F35, $C$14,$B35&":"&F$16&F$17&":"&F$19&":"&$B36) -> #NAME? | G36: =_xll.BLUEMATRIX2("/servlet/excelData",G35, $C$14,$B35&":"&G$16&G$17&":"&G$19&":"&$B36) -> #NAME? | H36: =_xll.BLUEMATRIX2("/servlet/excelData",H35, $C$14,$B35&":"&H$16&H$17&":"&H$19&":"&$B36) -> #NAME? | I36: =_xll.BLUEMATRIX2("/servlet/excelData",I35, $C$14,$B35&":"&I$16&I$17&":"&I$19&":"&$B36) -> #NAME? | J36: =_xll.BLUEMATRIX2("/servlet/excelData",J35, $C$14,$B35&":"&J$16&J$17&":"&J$19&":"&$B36) -> #NAME? | K36: =_xll.BLUEMATRIX2("/servlet/excelData",K35, $C$14,$B35&":"&K$16&K$17&":"&K$19&":"&$B36) -> #NAME? | ... W36: =_xll.BLUEMATRIX2("/servlet/excelData",W35, $C$14,$B35&":"&W$16&W$17&":"&W$19&":"&$B36) -> #NAME?
D44: Calendar Year = Fiscal Year (If yes =0, if less= -1, if more = 1)
A45: Fiscal 1Q Ending Month Number | B45: 3 | D45: 0
A46: Fiscal 2Q Ending Month Number | B46: 6 | D46: 0
A47: Fiscal 3Q Ending Month Number | B47: 9 | D47: 0
A48: Fiscal 4Q Ending Month Number | B48: 12 | D48: 0

Sheet Variance
B3: Rapid7 Inc. Quarterly Variance Analysis
B4: (Thousands Of Dollars, Except Per-Share Data)
D5: Actual | E5: Actual | F5: Needham | G5: Actual | I5: Variance | L5: Yr-Yr | O5: Q-Q
B6: Fiscal Year Ends December | D6: =+IS!BE23 -> 4Q-Dec 24A | E6: 3Q-Sep 25A | F6: 4Q-Dec 25E | G6: =+IS!BJ23 -> 4Q-Dec 25A | I6: % | J6: Absolute | L6: % | M6: Absolute | O6: % | P6: Absolute
B8: Calculated Billings | D8: =+IS!BE25 -> 252578 | E8: 193374 | F8: 252966.34 | G8: =+IS!BJ25 -> 247229 | I8: =+G8/F8-1 -> -0.022680266 | J8: =+G8-F8 -> -5737.344 | L8: =+G8/D8-1 -> -0.021177616 | M8: =+G8-D8 -> -5349 | O8: =+G8/E8-1 -> 0.27850176 | P8: =+G8-E8 -> 53855
B10: Annual Recurring Revenue | D10: =Metrics!BE41*1000 -> 839819 | E10: 837730 | F10: 836459.72 | G10: =Metrics!BJ41*1000 -> 839900 | I10: =+G10/F10-1 -> 0.004112901 | J10: =+G10-F10 -> 3440.276 | L10: =+G10/D10-1 -> 9.6449354e-05 | M10: =+G10-D10 -> 81 | O10: =+G10/E10-1 -> 0.0025903334 | P10: =+G10-E10 -> 2170
B12: Revenue
B13: Product Subscriptions | D13: =+IS!BE39 -> 206328 | E13: 210146 | F13: 207978.62 | G13: =+IS!BJ39 -> 209147 | I13: =+G13/F13-1 -> 0.0056177696 | J13: =+G13-F13 -> 1168.376 | L13: =+G13/D13-1 -> 0.013662712 | M13: =+G13-D13 -> 2819 | O13: =+G13/E13-1 -> -0.0047538378 | P13: =+G13-E13 -> -999
B14: % of Revenue | D14: =+IS!BE31 -> 0.9223724 | E14: 0.93364297 | F14: 0.93240442 | G14: =+IS!BJ31 -> 0.93150414
B15: Yr-Yr Growth | D15: =+IS!BE32 -> 0.062428065 | E15: 0.023944291 | F15: 0.009305856 | G15: =+IS!BJ32 -> 0.015163165
B16: Q-Q Growth | D16: =+IS!BE33 -> 0.0036983332 | E16: 0.010148246 | F16: -0.010650663 | G16: =+IS!BJ33 -> -0.0049091676
B17: Maintenance and Support | D17: =+IS!BE34 -> 6854.8222 | E17: 6649.1776 | F17: 6649.1776 | G17: =+IS!BJ34 -> 6649.1776 | I17: =+G17/F17-1 -> 0 | J17: =+G17-F17 -> 0 | L17: =+G17/D17-1 -> -0.03 | M17: =+G17-D17 -> -205.64467 | O17: =+G17/E17-1 -> 0 | P17: =+G17-E17 -> 0
B18: % of Revenue | D18: =+IS!BE35 -> 0.031696988 | E18: 0.030506412 | F18: 0.030793918 | G18: =+IS!BJ35 -> 0.030586682
B19: Yr-Yr Growth | D19: =+IS!BE36 -> -0.03 | E19: -0.03 | F19: -0.03 | G19: =+IS!BJ36 -> -0.03
B20: Q-Q Growth | D20: =+IS!BE37 -> 0 | E20: 0.00069397085 | F20: 0 | G20: =+IS!BJ37 -> 0
B21: Professional Services | D21: =+IS!BE47 -> 9933 | E21: 7814 | F21: 7946.4 | G21: =+IS!BJ47 -> 8241 | I21: =+G21/F21-1 -> 0.037073392 | J21: =+G21-F21 -> 294.6 | L21: =+G21/D21-1 -> -0.17034129 | M21: =+G21-D21 -> -1692 | O21: =+G21/E21-1 -> 0.054645508 | P21: =+G21-E21 -> 427
B22: % of Revenue | D22: =+IS!BE50 -> 0.045930612 | E22: 0.035850615 | F22: 0.036801663 | G22: =+IS!BJ50 -> 0.037909176
B23: Yr-Yr Growth | D23: =+IS!BE48 -> -0.049382716 | E23: -0.13762278 | F23: -0.2 | G23: =+IS!BJ48 -> -0.17034129
B24: Q-Q Growth | D24: =+IS!BE49 -> 0.096236618 | E24: 0.28182415 | F24: 0.016943947 | G24: =+IS!BJ49 -> 0.054645508
D25: ______ | E25: ______ | F25: ______ | G25: ______ | I25: ______ | J25: ______ | L25: ______ | M25: ______ | O25: ______ | P25: ______
B26: Total Revenues | D26: =+IS!BE52 -> 216261 | E26: 217960 | F26: 215925.02 | G26: =+IS!BJ52 -> 217388 | I26: =+G26/F26-1 -> 0.0067753888 | J26: =+G26-F26 -> 1462.976 | L26: =+G26/D26-1 -> 0.0052112956 | M26: =+G26-D26 -> 1127 | O26: =+G26/E26-1 -> -0.0026243347 | P26: =+G26-E26 -> -572
C27: Guide: $214-$216M | F27: 215020 | I27: =+G26/F27-1 -> 0.011012929 | J27: =+G26-F27 -> 2368
B28: Yr-Yr Growth | D28: =+IS!BE53 -> 0.053554378 | E28: 0.01540153 | F28: 0.034211336 | G28: =+IS!BJ53 -> 0.0052112956
B29: Q-Q Growth | D29: =+IS!BE54 -> 0.0074864666 | E29: 0.017586943 | F29: -0.011010778 | G29: =+IS!BJ54 -> -0.0026243347
B31: Cost of Goods Sold
B32: Product Subscriptions | D32: =+IS!BE65 -> 51932 | E32: 51908 | F32: 53034.549 | G32: =+IS!BJ65 -> 54081 | I32: =+G32/F32-1 -> 0.019731494 | J32: =+G32-F32 -> 1046.4509 | L32: =+G32/D32-1 -> 0.041381037 | M32: =+G32-D32 -> 2149 | O32: =+G32/E32-1 -> 0.041862526 | P32: =+G32-E32 -> 2173
B33: % of Revenue | D33: =+IS!BE58 -> 0 | E33: 0 | F33: 0 | G33: =+IS!BJ58 -> 0
B34: Yr-Yr Growth | D34: =+IS!BE59 -> 0 | E34: 0 | F34: 0 | G34: =+IS!BJ59 -> 0
B35: Q-Q Growth | D35: =+IS!BE60 -> 0 | E35: 0 | F35: 0 | G35: =+IS!BJ60 -> 0
B36: Maintenance and Support | D36: =+IS!BE61 -> 0 | E36: 0 | F36: 0 | G36: =+IS!BJ61 -> 0 | I36: =+G36/F36-1 -> #DIV/0! | J36: =+G36-F36 -> 0 | L36: =+G36/D36-1 -> #DIV/0! | M36: =+G36-D36 -> 0 | O36: =IFERROR(+G36/E36-1, "N/A") -> N/A | P36: =+G36-E36 -> 0
B37: % of Revenue | D37: =+IS!BE62 -> 0 | E37: 0 | F37: 0 | G37: =+IS!BJ62 -> 0
B38: Yr-Yr Growth | D38: =+IS!BE63 -> 0 | E38: 0 | F38: 0 | G38: =+IS!BJ63 -> 0
B39: Q-Q Growth | D39: =+IS!BE64 -> 0 | E39: 0 | F39: 0 | G39: =+IS!BJ64 -> 0
B40: Professional Services | D40: =+IS!BE69 -> 6427 | E40: 6195 | F40: 6357.12 | G40: =+IS!BJ69 -> 6673 | I40: =+G40/F40-1 -> 0.049689167 | J40: =+G40-F40 -> 315.88 | L40: =+G40/D40-1 -> 0.038276023 | M40: =+G40-D40 -> 246 | O40: =+G40/E40-1 -> 0.077158999 | P40: =+G40-E40 -> 478
B41: % of Revenue | D41: =+IS!BE70 -> 0.02971872 | E41: 0.028422646 | F41: 0.029441331 | G41: =+IS!BJ70 -> 0.030696267
B42: Yr-Yr Growth | D42: =+IS!BE71 -> -0.076447765 | E42: 0.045216804 | F42: -0.01087288 | G42: =+IS!BJ71 -> 0.038276023
B43: Q-Q Growth | D43: =+IS!BE72 -> 0.08435971 | E43: 0.16952992 | F43: 0.026169492 | G43: =+IS!BJ72 -> 0.077158999
D44: =+IS!BE73 -> ______ | E44: ______ | F44: ______ | G44: =+IS!BJ73 -> ______ | I44: ______ | J44: ______ | L44: ______ | M44: ______ | O44: ______ | P44: ______
B45: Total Cost Of Goods Sold (Non GAAP) | D45: =+D32+D40 -> 58359 | E45: 58103 | F45: 59391.669 | G45: =+G32+G40 -> 60754 | I45: =+G45/F45-1 -> 0.02293808 | J45: =+G45-F45 -> 1362.3309 | L45: =+G45/D45-1 -> 0.041039086 | M45: =+G45-D45 -> 2395 | O45: =+G45/E45-1 -> 0.045625871 | P45: =+G45-E45 -> 2651
D46: =+IS!BE75 -> ______ | E46: ______ | F46: ______ | G46: =+IS!BJ75 -> ______ | I46: ______ | J46: ______ | L46: ______ | M46: ______ | O46: ______ | P46: ______
B47: Gross Profit | D47: =+D26-D45 -> 157902 | E47: 159857 | F47: 156533.35 | G47: =+G26-G45 -> 156634 | I47: =+G47/F47-1 -> 0.00064296277 | J47: =+G47-F47 -> 100.64512 | L47: =+G47/D47-1 -> -0.0080302973 | M47: =+G47-D47 -> -1268 | O47: =+G47/E47-1 -> -0.02016177 | P47: =+G47-E47 -> -3223
B49: Products | D49: =1-(D32/D13) -> 0.74830367 | E49: 0.75299078 | F49: 0.745 | G49: =1-(G32/G13) -> 0.74142111 | I49: =+G49/F49-1 -> -0.0048038849 | J49: =+(G49-F49)*10000 -> -35.788943 | K49: BPs | L49: =+G49/D49-1 -> -0.0091975576 | M49: =+(G49-D49)*10000 -> -68.825661 | N49: BPs | O49: =+G49/E49-1 -> -0.015364959 | P49: =+(G49-E49)*10000 -> -115.69672 | Q49: BPs
B50: Maintenance and Support | D50: =1-(D36/D17) -> 1 | E50: 1 | F50: 1 | G50: =1-(G36/G17) -> 1 | I50: =+G50/F50-1 -> 0 | J50: =+(G50-F50)*10000 -> 0 | K50: BPs | L50: =+G50/D50-1 -> 0 | M50: =+(G50-D50)*10000 -> 0 | N50: BPs | O50: =+G50/E50-1 -> 0 | P50: =+(G50-E50)*10000 -> 0 | Q50: BPs
B51: Professional Services | D51: =1-(D40/D21) -> 0.35296486 | E51: 0.20719222 | F51: 0.2 | G51: =1-(G40/G21) -> 0.19026817 | I51: =+G51/F51-1 -> -0.048659143 | J51: =+(G51-F51)*10000 -> -97.318287 | K51: BPs | L51: =+G51/D51-1 -> -0.46094303 | M51: =+(G51-D51)*10000 -> -1626.9669 | N51: BPs | O51: =+G51/E51-1 -> -0.081682835 | P51: =+(G51-E51)*10000 -> -169.24048 | Q51: BPs
D52: =+IS!BE81 -> ______ | E52: ______ | F52: ______ | G52: =+IS!BJ81 -> ______ | I52: ______ | J52: ______ | L52: ______ | M52: ______ | O52: ______ | P52: ______
B53: Overall Gross Margin | D53: =+(D47/D26) -> 0.73014552 | E53: 0.73342356 | F53: 0.72494309 | G53: =+(G47/G26) -> 0.72052735 | I53: =+G53/F53-1 -> -0.0060911561 | J53: =+(G53-F53)*10000 -> -44.157416 | K53: BPs | L53: =+G53/D53-1 -> -0.013172945 | M53: =+(G53-D53)*10000 -> -96.181666 | N53: BPs | O53: =+G53/E53-1 -> -0.01758358 | P53: =+(G53-E53)*10000 -> -128.96212 | Q53: BPs
B55: Operating Expenses
B57: Research and Development | D57: =+IS!BE85 -> 35631 | E57: 37515 | F57: 38640.45 | G57: =+IS!BJ85 -> 39309 | I57: =+G57/F57-1 -> 0.017301817 | J57: =+G57-F57 -> 668.55 | L57: =+G57/D57-1 -> 0.10322472 | M57: =+G57-D57 -> 3678 | O57: =+G57/E57-1 -> 0.047820872 | P57: =+G57-E57 -> 1794
B58: % of Revenue | D58: =+D57/D26 -> 0.16475925 | E58: 0.17211874 | F58: 0.17895309 | G58: =+G57/G26 -> 0.18082415 | I58: =+G58/F58-1 -> 0.010455588 | J58: =+(G58-F58)*10000 -> 18.710597 | K58: BPs | L58: =+G58/D58-1 -> 0.097505296 | M58: =+(G58-D58)*10000 -> 160.64899 | N58: BPs | O58: =+G58/E58-1 -> 0.05057794 | P58: =+(G58-E58)*10000 -> 87.054111 | Q58: BPs
B59: Yr-Yr Growth | D59: =+IS!BE87 -> 0.10374202 | E59: 0.070939195 | F59: 0.084461564 | G59: =+IS!BJ87 -> 0.10322472
B60: Q-Q Growth | D60: =+IS!BE88 -> 0.017156723 | E60: 0.014549585 | F60: 0.03 | G60: =+IS!BJ88 -> 0.047820872
D62: =+IS!#REF! -> #REF! | E62: #REF! | F62: #REF! | G62: =+IS!#REF! -> #REF!
B63: Sales and Marketing | D63: =+IS!BE90 -> 65500 | E63: 71873 | F63: 73310.46 | G63: =+IS!BJ90 -> 73368 | I63: =+G63/F63-1 -> 0.00078488118 | J63: =+G63-F63 -> 57.54 | L63: =+G63/D63-1 -> 0.12012214 | M63: =+G63-D63 -> 7868 | O63: =+G63/E63-1 -> 0.020800579 | P63: =+G63-E63 -> 1495
B64: % of Revenue | D64: =+D63/D26 -> 0.30287477 | E64: 0.32975317 | F64: 0.33951813 | G64: =+G63/G26 -> 0.33749793 | I64: =+G64/F64-1 -> -0.0059501928 | J64: =+(G64-F64)*10000 -> -20.201983 | K64: BPs | L64: =+G64/D64-1 -> 0.11431511 | M64: =+(G64-D64)*10000 -> 346.23163 | N64: BPs | O64: =+G64/E64-1 -> 0.02348655 | P64: =+(G64-E64)*10000 -> 77.447643 | Q64: BPs
B65: Yr-Yr Growth | D65: =+IS!AO92 -> 0.27423652 | E65: 0.39514763 | F65: 0.39514763 | G65: =+IS!AR92 -> 0.39514763
B66: Q-Q Growth | D66: =+IS!AO93 -> 0.1167149 | E66: 0.023395052 | F66: 0.023395052 | G66: =+IS!AR93 -> 0.023395052
D68: =+IS!#REF! -> #REF! | E68: #REF! | F68: #REF! | G68: =+IS!#REF! -> #REF!
B69: General and Administrative | D69: =+IS!BE95 -> 16776 | E69: 13563 | F69: 14648.04 | G69: =+IS!BJ95 -> 13832 | I69: =+G69/F69-1 -> -0.055709842 | J69: =+G69-F69 -> -816.04 | L69: =+G69/D69-1 -> -0.17548879 | M69: =+G69-D69 -> -2944 | O69: =+G69/E69-1 -> 0.01983337 | P69: =+G69-E69 -> 269
B70: % of Revenue | D70: =+D69/D26 -> 0.077572933 | E70: 0.062227014 | F70: 0.067838548 | G70: =+G69/G26 -> 0.063628167 | I70: =+G70/F70-1 -> -0.062064719 | J70: =+(G70-F70)*10000 -> -42.103804 | K70: BPs | L70: =+G70/D70-1 -> -0.17976329 | M70: =+(G70-D70)*10000 -> -139.44766 | N70: BPs | O70: =+G70/E70-1 -> 0.022516797 | P70: =+(G70-E70)*10000 -> 14.01153 | Q70: BPs
B71: Yr-Yr Growth | D71: =+IS!AO97 -> 0.23978259 | E71: 0.52731975 | F71: 0.52731975 | G71: =+IS!AR97 -> 0.52731975
B72: Q-Q Growth | D72: =+IS!AO98 -> 0.21216147 | E72: 0.026510213 | F72: 0.026510213 | G72: =+IS!AR98 -> 0.026510213
D74: =+IS!AO99 -> ______ | E74: ______ | F74: ______ | G74: =+IS!AR99 -> ______ | I74: ______ | J74: ______ | L74: ______ | M74: ______ | O74: ______ | P74: ______
B75: Total Operating Expenses | D75: =+D57+D63+D69 -> 117907 | E75: 122951 | F75: 126598.95 | G75: =+G57+G63+G69 -> 126509 | I75: =+G75/F75-1 -> -0.00071051142 | J75: =+G75-F75 -> -89.95 | L75: =+G75/D75-1 -> 0.072955804 | M75: =+G75-D75 -> 8602 | O75: =+G75/E75-1 -> 0.028938358 | P75: =+G75-E75 -> 3558
B76: % of Revenue | D76: =+D75/D26 -> 0.54520695 | E76: 0.56409892 | F76: 0.58630976 | G76: =+G75/G26 -> 0.58195025 | I76: =+G76/F76-1 -> -0.0074355217 | J76: =+(G76-F76)*10000 -> -43.59519 | K76: BPs | L76: =+G76/D76-1 -> 0.067393302 | M76: =+(G76-D76)*10000 -> 367.43297 | N76: BPs | O76: =+G76/E76-1 -> 0.031645741 | P76: =+(G76-E76)*10000 -> 178.51328 | Q76: BPs
D77: =+IS!AO102 -> ______ | E77: ______ | F77: ______ | G77: =+IS!AR102 -> ______ | I77: ______ | J77: ______ | L77: ______ | M77: ______ | O77: ______ | P77: ______
B78: Operating Income | D78: =+D26-D45-D75 -> 39995 | E78: 36906 | F78: 29934.405 | G78: =+G26-G45-G75 -> 30125 | J78: =+G78-F78 -> 190.59512 | L78: =+G78/D78-1 -> -0.24678085 | M78: =+G78-D78 -> -9870 | O78: NM | P78: =+G78-E78 -> -6781
B79: Operating Margin | D79: =+D78/D26 -> 0.18493857 | E79: 0.16932465 | F79: 0.13863333 | G79: =+G78/G26 -> 0.13857711 | J79: =+(G79-F79)*10000 -> -0.56222575 | K79: BPs | L79: =+G79/D79-1 -> -0.25068575 | M79: =+(G79-D79)*10000 -> -463.61463 | N79: BPs | O79: NM | P79: =+(G79-E79)*10000 -> -307.4754 | Q79: BPs
D80: =+IS!#REF! -> #REF! | E80: #REF! | F80: #REF! | G80: =+IS!#REF! -> #REF!
B82: Interest Income / Expense, net | D82: =+IS!BE106 -> 5461 | E82: 4680 | F82: 6000 | G82: =+IS!BJ106 -> 5417 | I82: =+G82/F82-1 -> -0.097166667 | J82: =+G82-F82 -> -583 | L82: =+G82/D82-1 -> -0.0080571324 | M82: =+G82-D82 -> -44 | O82: =+G82/E82-1 -> 0.15747863 | P82: =+G82-E82 -> 737
B83: Other Income / Expense, net | D83: =+IS!BE107 -> -4361 | E83: -173 | F83: 0 | G83: =+IS!BJ107 -> 444 | I83: NM | J83: =+G83-F83 -> 444 | L83: =+G83/D83-1 -> -1.1018115 | M83: =+G83-D83 -> 4805 | O83: NM | P83: =+G83-E83 -> 617
D84: =+IS!#REF! -> #REF! | E84: #REF! | F84: #REF! | G84: =+IS!#REF! -> #REF!
D85: =+IS!AO108 -> ______ | E85: ______ | F85: ______ | G85: =+IS!AR108 -> ______ | I85: ______ | J85: ______ | L85: ______ | M85: ______ | O85: ______ | P85: ______
B86: Pretax Income | D86: =+D78+D82+D83 -> 41095 | E86: 41413 | F86: 35934.405 | G86: =+G78+G82+G83 -> 35986 | I86: =+G86/F86-1 -> 0.001435814 | J86: =+G86-F86 -> 51.59512 | L86: =+G86/D86-1 -> -0.12432169 | M86: =+G86-D86 -> -5109 | O86: =+G86/E86-1 -> -0.13104581 | P86: =+G86-E86 -> -5427
B87: Pretax Margin | D87: =+D86/D26 -> 0.19002502 | E87: 0.19000275 | F87: 0.16642075 | G87: =+G86/G26 -> 0.16553812 | I87: =+G87/F87-1 -> -0.0053036407 | J87: =+(G87-F87)*10000 -> -8.8263587 | K87: BPs | L87: =+G87/D87-1 -> -0.12886145 | M87: =+(G87-D87)*10000 -> -244.869 | N87: BPs | O87: =+G87/E87-1 -> -0.12875938 | P87: =+(G87-E87)*10000 -> -244.64637 | Q87: BPs
D88: =+IS!#REF! -> #REF! | E88: #REF! | F88: #REF! | G88: =+IS!#REF! -> #REF!
B90: Income Tax Expense (Income) | D90: =+IS!BE112 -> 5182 | E90: -1810 | F90: 3593.4405 | G90: =+IS!BJ112 -> 2597 | I90: =+G90/F90-1 -> -0.27729428 | J90: =+G90-F90 -> -996.44049 | L90: =+G90/D90-1 -> -0.49884215 | M90: =+G90-D90 -> -2585 | O90: =+G90/E90-1 -> -2.4348066 | P90: =+G90-E90 -> 4407
B91: Tax Rate | D91: =+D90/D86 -> 0.12609807 | E91: -0.043706083 | F91: 0.1 | G91: =+G90/G86 -> 0.072166954 | I91: =+G91/F91-1 -> -0.27833046 | J91: =+(G91-F91)*10000 -> -278.33046 | K91: BPs | L91: =+G91/D91-1 -> -0.42769182 | M91: =+(G91-D91)*10000 -> -539.31112 | N91: BPs | O91: =+G91/E91-1 -> -2.6511879 | P91: =+(G91-E91)*10000 -> 1158.7304 | Q91: BPs
D92: =+IS!AO114 -> ______ | E92: ______ | F92: ______ | G92: =+IS!AR114 -> ______ | I92: ______ | J92: ______ | L92: ______ | M92: ______ | O92: ______ | P92: ______
B93: NG-Net Income | D93: =+D86-D90 -> 35913 | E93: 43223 | F93: 32340.964 | G93: =+G86-G90 -> 33389 | I93: =+G93/F93-1 -> 0.032405824 | J93: =+G93-F93 -> 1048.0356 | L93: =+G93/D93-1 -> -0.070280957 | M93: =+G93-D93 -> -2524 | O93: =+G93/E93-1 -> -0.22751776 | P93: =+G93-E93 -> -9834
D94: =+IS!#REF! -> #REF! | E94: #REF! | F94: #REF! | G94: =+IS!#REF! -> #REF!
B96: NG--Earnings Per Share | D96: =+D93/D99 -> 0.47829864 | E96: 0.57164334 | F96: 0.42202624 | G96: =+G93/G99 -> 0.43753515 | I96: =+G96/F96-1 -> 0.036748681 | J96: =+G96-F96 -> 0.015508907 | L96: =+G96/D96-1 -> -0.085226035 | M96: =+G96-D96 -> -0.040763497 | O96: =+G96/E96-1 -> -0.23460116 | P96: =+G96-E96 -> -0.13410819
C97: Guide: $0.37-$0.44 | F97: 0.41 | I97: =+G96/F97-1 -> 0.067158891 | J97: =+G96-F97 -> 0.027535145
B99: Fully Diluted Shares Outstanding | D99: =+IS!BE119 -> 75084.888 | E99: 75611.832 | F99: 76632.592 | G99: =+IS!BJ119 -> 76311.584 | I99: =+G99/F99-1 -> -0.0041889192 | J99: =+G99-F99 -> -321.00773 | L99: =+G99/D99-1 -> 0.016337455 | M99: =+G99-D99 -> 1226.696 | O99: =+G99/E99-1 -> 0.0092545304 | P99: =+G99-E99 -> 699.752
B101: Source: Rapid7 Inc. financial statements, Factset estimates

Sheet BS
B3: Rapid7 Inc.—Balance Sheet
B4: (Thousands Of Dollars, Except Per-Share Data) | D4: March | E4: June | F4: Sept | G4: Dec | H4: Dec | I4: March | J4: June | K4: Sept | L4: Dec | M4: Dec | N4: March | O4: June | P4: Sept | Q4: Dec | R4: Dec | S4: March | T4: June | U4: Sept | V4: Dec | W4: Dec | X4: March | Y4: June | Z4: Sept | AA4: Dec | AB4: Dec | AC4: March | AD4: June | AE4: Sept | AF4: Dec | AG4: Dec | AH4: March | AI4: June | AJ4: Sept | AK4: Dec | AL4: Dec | AM4: March | AN4: June | AO4: Sept | AP4: Dec | AQ4: Dec | AR4: March | AS4: June | AT4: Sept | AU4: Dec | AV4: Dec | AW4: March | AX4: June | AY4: Sept | AZ4: Dec | BA4: Dec | BB4: March | BC4: June | BD4: Sept | BE4: Dec | BF4: Dec | BG4: March | BH4: June | BI4: Sept | BJ4: Dec | BK4: Dec | BL4: March | BM4: June | BN4: Sept | BO4: Dec | BP4: Dec | BQ4: March | BR4: June | BS4: Sept | BT4: Dec | BU4: Dec
D5: 2014A | E5: 2014A | F5: 2014A | G5: 2014A | H5: 2014A | I5: 2015A | J5: 2015A | K5: 2015A | L5: 2015A | M5: 2015A | N5: 2016A | O5: 2016A | P5: 2016A | Q5: 2016A | R5: 2016A | S5: 2017A | T5: 2017A | U5: 2017A | V5: 2017A | W5: 2017A | X5: 2018A | Y5: 2018A | Z5: 2018A | AA5: 2018A | AB5: 2018A | AC5: 2019A | AD5: 2019A | AE5: 2019A | AF5: 2019A | AG5: =AF5 -> 2019A | AH5: 2020A | AI5: 2020A | AJ5: 2020A | AK5: 2020A | AL5: =AK5 -> 2020A | AM5: 2021A | AN5: 2021A | AO5: 2021A | AP5: 2021A | AQ5: =AP5 -> 2021A | AR5: 2022A | AS5: 2022A | AT5: 2022A | AU5: 2022A | AV5: =AU5 -> 2022A | AW5: 2023A | AX5: 2023A | AY5: 2023A | AZ5: 2023A | BA5: =AZ5 -> 2023A | BB5: 2024A | BC5: 2024A | BD5: 2024A | BE5: 2024A | BF5: =BE5 -> 2024A | BG5: 2025A | BH5: 2025A | BI5: 2025A | BJ5: 2025A | BK5: =BJ5 -> 2025A | BL5: 2026E | BM5: 2026E | BN5: 2026E | BO5: 2026E | BP5: =BO5 -> 2026E | BQ5: 2027E | BR5: 2027E | BS5: 2027E | BT5: 2027E | BU5: =BT5 -> 2027E
B6: Current Assets
B7: Cash and Cash Equivalents | G7: 36823 | H7: 36823 | I7: 33343 | J7: 27000 | K7: 123984 | L7: 86553 | M7: =+L7 -> 86553 | N7: 83508 | O7: 84755 | P7: 87715 | Q7: 53148 | R7: =+Q7 -> 53148 | S7: 50662 | T7: 53068 | U7: 49055 | V7: 51562 | W7: =+V7 -> 51562 | X7: 99646 | Y7: 100731 | Z7: 131160 | AA7: 99565 | AB7: =+AA7 -> 99565 | AC7: 89869 | AD7: 126569 | AE7: 114925 | AF7: =123413 -> 123413 | AG7: =+AF7 -> 123413 | AH7: 204434 | AI7: 279343 | AJ7: =239409 -> 239409 | AK7: =173617 -> 173617 | AL7: =+AK7 -> 173617 | AM7: =503804 -> 503804 | AN7: =493568 -> 493568 | AO7: =227104 -> 227104 | AP7: =164582 -> 164582 | AQ7: =+AP7 -> 164582 | AR7: =141365 -> 141365 | AS7: =163469 -> 163469 | AT7: =168353 -> 168353 | AU7: =207287 -> 207287 | AV7: =+AU7 -> 207287 | AW7: =205757 -> 205757 | AX7: =185929 -> 185929 | AY7: =182727 -> 182727 | AZ7: =213629 -> 213629 | BA7: =+AZ7 -> 213629 | BB7: =198716 -> 198716 | BC7: =236975 -> 236975 | BD7: =222571 -> 222571 | BE7: =334686 -> 334686 | BF7: =+BE7 -> 334686 | BG7: =291462 -> 291462 | BH7: =261327 -> 261327 | BI7: =130613 -> 130613 | BJ7: =246664 -> 246664 | BK7: =+BJ7 -> 246664 | BL7: =+CF!BL68 -> 271891.32 | BM7: =+CF!BM68 -> 306313.54 | BN7: =+CF!BN68 -> 333933.51 | BO7: =+CF!BO68 -> 383052.41 | BP7: =+BO7 -> 383052.41 | BQ7: =+CF!BQ68 -> 406981.17 | BR7: =+CF!BR68 -> 437336.4 | BS7: =+CF!BS68 -> 467636.61 | BT7: =+CF!BT68 -> 520132.76 | BU7: =+BT7 -> 520132.76
B8: Short-Term Investments | G8: 0 | H8: 0 | I8: 0 | J8: 0 | K8: 0 | L8: 0 | M8: =+L8 -> 0 | N8: 0 | O8: 0 | P8: 0 | Q8: 18779 | R8: =+Q8 -> 18779 | S8: 28561 | T8: 31213 | U8: 34825 | V8: 39178 | W8: =+V8 -> 39178 | X8: 29630 | Y8: 13983 | Z8: 140633 | AA8: 159210 | AB8: =+AA8 -> 159210 | AC8: 161600 | AD8: 119138 | AE8: 131815 | AF8: =116158 -> 116158 | AG8: =+AF8 -> 116158 | AH8: 36384 | AI8: 36313 | AJ8: =81209 -> 81209 | AK8: =138839 -> 138839 | AL8: =+AK8 -> 138839 | AM8: =101996 -> 101996 | AN8: =114284 -> 114284 | AO8: =77145 -> 77145 | AP8: =58850 -> 58850 | AQ8: =+AP8 -> 58850 | AR8: =93155 -> 93155 | AS8: =76244 -> 76244 | AT8: =83231 -> 83231 | AU8: =84162 -> 84162 | AV8: =+AU8 -> 84162 | AW8: =56483 -> 56483 | AX8: =107573 -> 107573 | AY8: =139434 -> 139434 | AZ8: =169544 -> 169544 | BA8: =+AZ8 -> 169544 | BB8: =213001 -> 213001 | BC8: =205671 -> 205671 | BD8: =221122 -> 221122 | BE8: =187025 -> 187025 | BF8: =+BE8 -> 187025 | BG8: =202011 -> 202011 | BH8: =250410 -> 250410 | BI8: =276515 -> 276515 | BJ8: =228006 -> 228006 | BK8: =+BJ8 -> 228006 | BL8: =+BJ8 -> 228006 | BM8: =+BL8 -> 228006 | BN8: =+BM8 -> 228006 | BO8: =+BN8 -> 228006 | BP8: =+BO8 -> 228006 | BQ8: =+BO8 -> 228006 | BR8: =+BQ8 -> 228006 | BS8: =+BR8 -> 228006 | BT8: =+BS8 -> 228006 | BU8: =+BT8 -> 228006
B9: Accounts Receivable, net | G9: 25412 | H9: 25412 | I9: 21027 | J9: 26363 | K9: 31969 | L9: 44164 | M9: =+L9 -> 44164 | N9: 29817 | O9: 38663 | P9: 38286 | Q9: 49154 | R9: =+Q9 -> 49154 | S9: 33703 | T9: 47560 | U9: 48690 | V9: 73661 | W9: =+V9 -> 73661 | X9: 38718 | Y9: 48476 | Z9: 53771 | AA9: 74935 | AB9: =+AA9 -> 74935 | AC9: 59707 | AD9: 69289 | AE9: 62422 | AF9: =87927 -> 87927 | AG9: =+AF9 -> 87927 | AH9: 64388 | AI9: 76823 | AJ9: =73625 -> 73625 | AK9: =111599 -> 111599 | AL9: =+AK9 -> 111599 | AM9: =76714 -> 76714 | AN9: =98483 -> 98483 | AO9: =96775 -> 96775 | AP9: =146094 -> 146094 | AQ9: =+AP9 -> 146094 | AR9: =107320 -> 107320 | AS9: =124701 -> 124701 | AT9: =121017 -> 121017 | AU9: =152045 -> 152045 | AV9: =+AU9 -> 152045 | AW9: =116683 -> 116683 | AX9: =136300 -> 136300 | AY9: =137690 -> 137690 | AZ9: =164862 -> 164862 | BA9: =+AZ9 -> 164862 | BB9: =124595 -> 124595 | BC9: =143671 -> 143671 | BD9: =141891 -> 141891 | BE9: =168242 -> 168242 | BF9: =+BE9 -> 168242 | BG9: =140541 -> 140541 | BH9: =150683 -> 150683 | BI9: =141339 -> 141339 | BJ9: =167017 -> 167017 | BK9: =+BJ9 -> 167017 | BL9: =+BL62*BL75/90 -> 140957.26 | BM9: =+BM62*BM75/90 -> 148575.13 | BN9: =+BN62*BN75/90 -> 135493.86 | BO9: =+BO62*BO75/90 -> 159967.49 | BP9: =+BO9 -> 159967.49 | BQ9: =+BQ62*BQ75/90 -> 141015.06 | BR9: =+BR62*BR75/90 -> 151120.08 | BS9: =+BS62*BS75/90 -> 144831.07 | BT9: =+BT62*BT75/90 -> 172116.16 | BU9: =+BT9 -> 172116.16
B10: Deferred Contract Acquisition and Fulfillment Costs, Current Portion | G10: 0 | H10: 0 | I10: 0 | J10: 0 | K10: 0 | L10: 0 | M10: =+L10 -> 0 | N10: 0 | O10: 0 | P10: 0 | Q10: 0 | R10: =+Q10 -> 0 | S10: 0 | T10: 0 | U10: =+T10 -> 0 | V10: 7844 | W10: =+V10 -> 7844 | X10: 8583 | Y10: 9481 | Z10: 10376 | AA10: 12321 | AB10: =+AA10 -> 12321 | AC10: 12994 | AD10: 13851 | AE10: 14905 | AF10: =17047 -> 17047 | AG10: =+AF10 -> 17047 | AH10: 17486 | AI10: 18439 | AJ10: =19269 -> 19269 | AK10: =21536 -> 21536 | AL10: =+AK10 -> 21536 | AM10: =22598 -> 22598 | AN10: =23960 -> 23960 | AO10: =25863 -> 25863 | AP10: =29974 -> 29974 | AQ10: =+AP10 -> 29974 | AR10: =30984 -> 30984 | AS10: =31367 -> 31367 | AT10: =33307 -> 33307 | AU10: =34906 -> 34906 | AV10: =+AU10 -> 34906 | AW10: =36171 -> 36171 | AX10: =38661 -> 38661 | AY10: =40909 -> 40909 | AZ10: =45008 -> 45008 | BA10: =+AZ10 -> 45008 | BB10: =47003 -> 47003 | BC10: =48880 -> 48880 | BD10: =49710 -> 49710 | BE10: =52134 -> 52134 | BF10: =+BE10 -> 52134 | BG10: =50667 -> 50667 | BH10: =49292 -> 49292 | BI10: =47557 -> 47557 | BJ10: =48370 -> 48370 | BK10: =+BJ10 -> 48370 | BL10: =+BJ10*(1+BL139) -> 49821.1 | BM10: =+BL10*(1+BM139) -> 51315.733 | BN10: =+BM10*(1+BN139) -> 52855.205 | BO10: =+BN10*(1+BO139) -> 54440.861 | BP10: =+BO10 -> 54440.861 | BQ10: =+BO10*(1+BQ139) -> 56618.496 | BR10: =+BQ10*(1+BR139) -> 58883.235 | BS10: =+BR10*(1+BS139) -> 61238.565 | BT10: =+BS10*(1+BT139) -> 63688.107 | BU10: =+BT10 -> 63688.107
B11: Prepaid Expenses & Other Current Assets | G11: 4209 | H11: 4209 | I11: 4995 | J11: 6297 | K11: 4165 | L11: 6148 | M11: =+L11 -> 6148 | N11: 6618 | O11: 7183 | P11: 6705 | Q11: 9152 | R11: =+Q11 -> 9152 | S11: 7742 | T11: 8892 | U11: 8747 | V11: 8907 | W11: =+V11 -> 8907 | X11: 12232 | Y11: 13212 | Z11: 11616 | AA11: 9746 | AB11: =+AA11 -> 9746 | AC11: 15773 | AD11: 15416 | AE11: 15827 | AF11: =20051 -> 20051 | AG11: =+AF11 -> 20051 | AH11: 19624 | AI11: 20708 | AJ11: =20521 -> 20521 | AK11: =27844 -> 27844 | AL11: =+AK11 -> 27844 | AM11: =28943 -> 28943 | AN11: =27555 -> 27555 | AO11: =27079 -> 27079 | AP11: =33236 -> 33236 | AQ11: =+AP11 -> 33236 | AR11: =38051 -> 38051 | AS11: =34221 -> 34221 | AT11: =33402 -> 33402 | AU11: =31907 -> 31907 | AV11: =+AU11 -> 31907 | AW11: =39527 -> 39527 | AX11: =56463 -> 56463 | AY11: =35087 -> 35087 | AZ11: =41407 -> 41407 | BA11: =+AZ11 -> 41407 | BB11: =42552 -> 42552 | BC11: =39194 -> 39194 | BD11: =37328 -> 37328 | BE11: =44024 -> 44024 | BF11: =+BE11 -> 44024 | BG11: =47964 -> 47964 | BH11: =42805 -> 42805 | BI11: =39001 -> 39001 | BJ11: =47230 -> 47230 | BK11: =+BJ11 -> 47230 | BL11: =+(BL63+BL64)*BL78 -> 43181.964 | BM11: =+(BM63+BM64)*BM78 -> 39749.821 | BN11: =+(BN63+BN64)*BN78 -> 42901.288 | BO11: =+(BO63+BO64)*BO78 -> 41316.794 | BP11: =+BO11 -> 41316.794 | BQ11: =+(BQ63+BQ64)*BQ78 -> 40258.715 | BR11: =+(BR63+BR64)*BR78 -> 36775.366 | BS11: =+(BS63+BS64)*BS78 -> 34973.848 | BT11: =+(BT63+BT64)*BT78 -> 37064.287 | BU11: =+BT11 -> 37064.287
D12: ______ | E12: ______ | F12: ______ | G12: ______ | H12: ______ | I12: ______ | J12: ______ | K12: ______ | L12: ______ | M12: ______ | N12: ______ | O12: ______ | P12: ______ | Q12: ______ | R12: ______ | S12: ______ | T12: ______ | U12: ______ | V12: ______ | W12: ______ | X12: ______ | Y12: ______ | Z12: ______ | AA12: ______ | AB12: ______ | AC12: ______ | AD12: ______ | AE12: ______ | AF12: ______ | AG12: ______ | AH12: ______ | AI12: ______ | AJ12: ______ | AK12: ______ | AL12: ______ | AM12: ______ | AN12: ______ | AO12: ______ | AP12: ______ | AQ12: ______ | AR12: ______ | AS12: ______ | AT12: ______ | AU12: ______ | AV12: ______ | AW12: ______ | AX12: ______ | AY12: ______ | AZ12: ______ | BA12: ______ | BB12: ______ | BC12: ______ | BD12: ______ | BE12: ______ | BF12: ______ | BG12: ______ | BH12: ______ | BI12: ______ | BJ12: ______ | BK12: ______ | BL12: ______ | BM12: ______ | BN12: ______ | BO12: ______ | BP12: ______ | BQ12: ______ | BR12: ______ | BS12: ______ | BT12: ______ | BU12: ______
B13: Total Current Assets | D13: =SUM(D7:D11)-#REF! -> #REF! | E13: =SUM(E7:E11)-#REF! -> #REF! | F13: =SUM(F7:F11)-#REF! -> #REF! | G13: =SUM(G7:G11)-#REF! -> #REF! | H13: =SUM(H7:H11)-#REF! -> #REF! | I13: =SUM(I7:I11)-#REF! -> #REF! | J13: =SUM(J7:J11)-#REF! -> #REF! | K13: =SUM(K7:K11)-#REF! -> #REF! | L13: =SUM(L7:L11)-#REF! -> #REF! | M13: =SUM(M7:M11) -> 136865 | N13: =SUM(N7:N11) -> 119943 | O13: =SUM(O7:O11) -> 130601 | P13: =SUM(P7:P11) -> 132706 | Q13: =SUM(Q7:Q11) -> 130233 | R13: =SUM(R7:R11) -> 130233 | S13: =SUM(S7:S11) -> 120668 | T13: =SUM(T7:T11) -> 140733 | ... BU13: =SUM(BU7:BU11) -> 1021007.3
B15: Long-Term Investments | G15: 0 | H15: 0 | I15: 0 | J15: 0 | K15: 0 | L15: 0 | M15: =+L15 -> 0 | N15: 0 | O15: 0 | P15: 0 | Q15: 20162 | R15: =+Q15 -> 20162 | S15: 16803 | T15: 8799 | U15: 1110 | V15: 1102 | W15: =+V15 -> 1102 | X15: 1096 | Y15: 3929 | Z15: 39275 | AA15: 44892 | AB15: =+AA15 -> 44892 | AC15: 33613 | AD15: 18680 | AE15: 10997 | AF15: =22887 -> 22887 | AG15: =+AF15 -> 22887 | AH15: 12804 | AI15: 5365 | AJ15: =10813 -> 10813 | AK15: =10124 -> 10124 | AL15: =+AK15 -> 10124 | AM15: =11133 -> 11133 | AN15: =5377 -> 5377 | AO15: =5364 -> 5364 | AP15: =34068 -> 34068 | AQ15: =+AP15 -> 34068 | AR15: =28295 -> 28295 | AS15: =14330 -> 14330 | AT15: =16707 -> 16707 | AU15: =9756 -> 9756 | AV15: =+AU15 -> 9756 | AW15: =7343 -> 7343 | AX15: =2437 -> 2437 | AY15: =50603 -> 50603 | AZ15: =56171 -> 56171 | BA15: =+AZ15 -> 56171 | BB15: =52454 -> 52454 | BC15: =51434 -> 51434 | BD15: =60382 -> 60382 | BE15: =37274 -> 37274 | BF15: =+BE15 -> 37274 | BG15: =99136 -> 99136 | BH15: =88012 -> 88012 | BI15: =227418 -> 227418 | BJ15: =184119 -> 184119 | BK15: =+BJ15 -> 184119 | BL15: =+BJ15 -> 184119 | BM15: =+BL15 -> 184119 | BN15: =+BM15 -> 184119 | BO15: =+BN15 -> 184119 | BP15: =+BO15 -> 184119 | BQ15: =+BO15 -> 184119 | BR15: =+BQ15 -> 184119 | BS15: =+BR15 -> 184119 | BT15: =+BS15 -> 184119 | BU15: =+BT15 -> 184119
B16: Property, Plant, And Equipment, net | G16: 7922 | H16: 7922 | I16: 7619 | J16: 7607 | K16: 7356 | L16: 7532 | M16: =+L16 -> 7532 | N16: 7611 | O16: 7386 | P16: 8009 | Q16: 8088 | R16: =+Q16 -> 8088 | S16: 8010 | T16: 8287 | U16: 7995 | V16: 8589 | W16: =+V16 -> 8589 | X16: 9238 | Y16: 11184 | Z16: 11859 | AA16: 17523 | AB16: =+AA16 -> 17523 | AC16: 32771 | AD16: 51860 | AE16: 51519 | AF16: =50670 -> 50670 | AG16: =+AF16 -> 50670 | AH16: 50075 | AI16: 48904 | AJ16: =50305 -> 50305 | AK16: =53114 -> 53114 | AL16: =+AK16 -> 53114 | AM16: =51141 -> 51141 | AN16: =49431 -> 49431 | AO16: =49034 -> 49034 | AP16: =50225 -> 50225 | AQ16: =+AP16 -> 50225 | AR16: =49804 -> 49804 | AS16: =50533 -> 50533 | AT16: =55002 -> 55002 | AU16: =57891 -> 57891 | AV16: =+AU16 -> 57891 | AW16: =56638 -> 56638 | AX16: =47104 -> 47104 | AY16: =42449 -> 42449 | AZ16: =39642 -> 39642 | BA16: =+AZ16 -> 39642 | BB16: =37266 -> 37266 | BC16: =34884 -> 34884 | BD16: =33936 -> 33936 | BE16: =32245 -> 32245 | BF16: =+BE16 -> 32245 | BG16: =31659 -> 31659 | BH16: =29639 -> 29639 | BI16: =31966 -> 31966 | BJ16: =31990 -> 31990 | BK16: =+BJ16 -> 31990 | BL16: =+BL89 -> 31510.497 | BM16: =+BM89 -> 31078.995 | BN16: =+BN89 -> 30695.167 | BO16: =+BO89 -> 30356.77 | BP16: =+BO16 -> 30356.77 | BQ16: =+BQ89 -> 30043.454 | BR16: =+BR89 -> 29765.104 | BS16: =+BS89 -> 29520.748 | BT16: =+BT89 -> 29310.54 | BU16: =+BT16 -> 29310.54
B17: Operating Lease ROU Assets | M17: =+L17 -> 0 | R17: =+Q17 -> 0 | W17: =+V17 -> 0 | AB17: =+AA17 -> 0 | AC17: 15888 | AD17: 59417 | AE17: 61217 | AF17: =60984 -> 60984 | AG17: =+AF17 -> 60984 | AH17: 62942 | AI17: 72005 | AJ17: =69797 -> 69797 | AK17: =67178 -> 67178 | AL17: =+AK17 -> 67178 | AM17: =64965 -> 64965 | AN17: =63472 -> 63472 | AO17: =62105 -> 62105 | AP17: =83751 -> 83751 | AQ17: =+AP17 -> 83751 | AR17: =89196 -> 89196 | AS17: =84937 -> 84937 | AT17: =85250 -> 85250 | AU17: =79342 -> 79342 | AV17: =+AU17 -> 79342 | AW17: =77420 -> 77420 | AX17: =56817 -> 56817 | AY17: =53275 -> 53275 | AZ17: =54693 -> 54693 | BA17: =+AZ17 -> 54693 | BB17: =53036 -> 53036 | BC17: =50645 -> 50645 | BD17: =50756 -> 50756 | BE17: =48877 -> 48877 | BF17: =+BE17 -> 48877 | BG17: =46404 -> 46404 | BH17: =43654 -> 43654 | BI17: =47536 -> 47536 | BJ17: =45485 -> 45485 | BK17: =+BJ17 -> 45485 | BL17: =+BK17 -> 45485 | BM17: =+BL17 -> 45485 | BN17: =+BM17 -> 45485 | BO17: =+BN17 -> 45485 | BP17: =+BO17 -> 45485 | BQ17: =+BP17 -> 45485 | BR17: =+BQ17 -> 45485 | ... BU17: =+BT17 -> 45485
B18: Deferred Contract Acquisition and Fulfillment Costs, Non-Current Portion | G18: 0 | H18: 0 | I18: 0 | J18: 0 | K18: 0 | L18: 0 | M18: =+L18 -> 0 | N18: 0 | O18: 0 | P18: 0 | Q18: 0 | R18: =+Q18 -> 0 | S18: 0 | T18: 0 | U18: =+T18 -> 0 | V18: 19321 | W18: =+V18 -> 19321 | X18: 20295 | Y18: 22214 | Z18: 23174 | AA18: 27634 | AB18: =+AA18 -> 27634 | AC18: 28054 | AD18: 29275 | AE18: 30452 | AF18: =34213 -> 34213 | AG18: =+AF18 -> 34213 | AH18: 34289 | AI18: 35815 | AJ18: =37269 -> 37269 | AK18: =43103 -> 43103 | AL18: =+AK18 -> 43103 | AM18: =43997 -> 43997 | AN18: =46132 -> 46132 | AO18: =48548 -> 48548 | AP18: =57191 -> 57191 | AQ18: =+AP18 -> 57191 | AR18: =59121 -> 59121 | AS18: =60878 -> 60878 | AT18: =61857 -> 61857 | AU18: =68169 -> 68169 | AV18: =+AU18 -> 68169 | AW18: =69144 -> 69144 | AX18: =70377 -> 70377 | AY18: =71654 -> 71654 | AZ18: =76601 -> 76601 | BA18: =+AZ18 -> 76601 | BB18: =75287 -> 75287 | BC18: =74693 -> 74693 | BD18: =72392 -> 72392 | BE18: =73672 -> 73672 | BF18: =+BE18 -> 73672 | BG18: =69843 -> 69843 | BH18: =66714 -> 66714 | BI18: =64109 -> 64109 | BJ18: =66978 -> 66978 | BK18: =+BJ18 -> 66978 | BL18: =+BJ18*(1+BL144) -> 66308.22 | BM18: =+BL18*(1+BM144) -> 65645.138 | BN18: =+BM18*(1+BN144) -> 64988.686 | BO18: =+BN18*(1+BO144) -> 64338.8 | BP18: =+BO18 -> 64338.8 | BQ18: =+BO18*(1+BQ144) -> 63695.412 | BR18: =+BQ18*(1+BR144) -> 63058.457 | BS18: =+BR18*(1+BS144) -> 62427.873 | BT18: =+BS18*(1+BT144) -> 61803.594 | BU18: =+BT18 -> 61803.594
B19: Goodwill | G19: 11265 | H19: 11265 | I19: 11265 | J19: 15758 | K19: 15847 | L19: 74565 | M19: =+L19 -> 74565 | N19: 74943 | O19: 75048 | P19: 75110 | Q19: 75110 | R19: =+Q19 -> 75110 | S19: 75110 | T19: 75110 | U19: 83170 | V19: 83164 | W19: =+V19 -> 83164 | X19: 83164 | Y19: 83164 | Z19: 83164 | AA19: 88420 | AB19: =+AA19 -> 88420 | AC19: 88420 | AD19: 97866 | AE19: 97866 | AF19: =97866 -> 97866 | AG19: =+AF19 -> 97866 | AH19: 97866 | AI19: 213686 | AJ19: =213727 -> 213727 | AK19: =213601 -> 213601 | AL19: =+AK19 -> 213601 | AM19: =253324 -> 253324 | AN19: =254418 -> 254418 | AO19: =515297 -> 515297 | AP19: =515258 -> 515258 | AQ19: =+AP19 -> 515258 | AR19: =515333 -> 515333 | AS19: =515631 -> 515631 | AT19: =515631 -> 515631 | AU19: =515631 -> 515631 | AV19: =+AU19 -> 515631 | AW19: =538037 -> 538037 | AX19: =536326 -> 536326 | AY19: =536305 -> 536305 | AZ19: =536351 -> 536351 | BA19: =+AZ19 -> 536351 | BB19: =536351 -> 536351 | BC19: =536351 -> 536351 | BD19: =575165 -> 575165 | BE19: =575268 -> 575268 | BF19: =+BE19 -> 575268 | BG19: =575268 -> 575268 | BH19: =575268 -> 575268 | BI19: =575268 -> 575268 | BJ19: =575268 -> 575268 | BK19: =+BJ19 -> 575268 | BL19: =+BJ19 -> 575268 | BM19: =+BL19 -> 575268 | BN19: =+BM19 -> 575268 | BO19: =+BN19 -> 575268 | BP19: =+BO19 -> 575268 | BQ19: =+BO19 -> 575268 | BR19: =+BQ19 -> 575268 | BS19: =+BR19 -> 575268 | BT19: =+BS19 -> 575268 | BU19: =+BT19 -> 575268
B20: Intangible Assets, net | G20: 1156 | H20: 1156 | I20: 953 | J20: 2767 | K20: 2482 | L20: 11385 | M20: =+L20 -> 11385 | N20: 10802 | O20: 10219 | P20: 9450 | Q20: 8946 | R20: =+Q20 -> 8946 | S20: 8460 | T20: 8294 | U20: 17208 | V20: 16640 | W20: =+V20 -> 16640 | X20: 16316 | Y20: 16002 | Z20: 16023 | AA20: 23955 | AB20: =+AA20 -> 23955 | AC20: 23979 | AD20: 29726 | AE20: 29183 | AF20: =28561 -> 28561 | AG20: =+AF20 -> 28561 | AH20: 27867 | AI20: 47706 | AJ20: =45942 -> 45942 | AK20: =44296 -> 44296 | AL20: =+AK20 -> 44296 | AM20: =52708 -> 52708 | AN20: =54179 -> 54179 | AO20: =115746 -> 115746 | AP20: =111591 -> 111591 | AQ20: =+AP20 -> 111591 | AR20: =108246 -> 108246 | AS20: =105785 -> 105785 | AT20: =103660 -> 103660 | AU20: =101269 -> 101269 | AV20: =+AU20 -> 101269 | AW20: =111432 -> 111432 | AX20: =104698 -> 104698 | AY20: =99993 -> 99993 | AZ20: =94546 -> 94546 | BA20: =+AZ20 -> 94546 | BB20: =88844 -> 88844 | BC20: =84019 -> 84019 | BD20: =90748 -> 90748 | BE20: =85719 -> 85719 | BF20: =+BE20 -> 85719 | BG20: =79763 -> 79763 | BH20: =74981 -> 74981 | BI20: =69877 -> 69877 | BJ20: =65105 -> 65105 | BK20: =+BJ20 -> 65105 | BL20: =+BL98 -> 57292.4 | BM20: =+BM98 -> 50417.312 | BN20: =+BN98 -> 44367.235 | BO20: =+BO98 -> 39043.166 | BP20: =+BO20 -> 39043.166 | BQ20: =+BQ98 -> 34357.986 | BR20: =+BR98 -> 30235.028 | BS20: =+BS98 -> 26606.825 | BT20: =+BT98 -> 23414.006 | BU20: =+BT20 -> 23414.006
B21: Other Assets | G21: 179 | H21: 179 | I21: 180 | J21: 682 | K21: 735 | L21: 214 | M21: =+L21 -> 214 | N21: 481 | O21: 598 | P21: 760 | Q21: 764 | R21: =+Q21 -> 764 | S21: 720 | T21: 630 | U21: 640 | V21: 1363 | W21: =+V21 -> 1363 | X21: 1552 | Y21: 1395 | Z21: 906 | AA21: 1168 | AB21: =+AA21 -> 1168 | AC21: =1238 -> 1238 | AD21: =5192 -> 5192 | AE21: 5466 | AF21: =5136 -> 5136 | AG21: =+AF21 -> 5136 | AH21: 5518 | AI21: 5304 | AJ21: =4931 -> 4931 | AK21: =8271 -> 8271 | AL21: =+AK21 -> 8271 | AM21: =11370 -> 11370 | AN21: =9450 -> 9450 | AO21: =10820 -> 10820 | AP21: =11191 -> 11191 | AQ21: =+AP21 -> 11191 | AR21: =13000 -> 13000 | AS21: =23452 -> 23452 | AT21: =18132 -> 18132 | AU21: =16626 -> 16626 | AV21: =+AU21 -> 16626 | AW21: =14824 -> 14824 | AX21: =12974 -> 12974 | AY21: =9174 -> 9174 | AZ21: =12894 -> 12894 | BA21: =+AZ21 -> 12894 | BB21: =19368 -> 19368 | BC21: =20176 -> 20176 | BD21: =18530 -> 18530 | BE21: =12868 -> 12868 | BF21: =+BE21 -> 12868 | BG21: =10092 -> 10092 | BH21: =15955 -> 15955 | BI21: =15208 -> 15208 | BJ21: =20232 -> 20232 | BK21: =+BJ21 -> 20232 | BL21: =+BJ21 -> 20232 | BM21: =+BL21 -> 20232 | BN21: =+BM21 -> 20232 | BO21: =+BN21 -> 20232 | BP21: =+BO21 -> 20232 | BQ21: =+BO21 -> 20232 | BR21: =+BQ21 -> 20232 | BS21: =+BR21 -> 20232 | BT21: =+BS21 -> 20232 | BU21: =+BT21 -> 20232
D22: ______ | E22: ______ | F22: ______ | G22: ______ | H22: ______ | I22: ______ | J22: ______ | K22: ______ | L22: ______ | M22: ______ | N22: ______ | O22: ______ | P22: ______ | Q22: ______ | R22: ______ | S22: ______ | T22: ______ | U22: ______ | V22: ______ | W22: ______ | X22: ______ | Y22: ______ | Z22: ______ | AA22: ______ | AB22: ______ | AC22: ______ | AD22: ______ | AE22: ______ | AF22: ______ | AG22: ______ | AH22: ______ | AI22: ______ | AJ22: ______ | AK22: ______ | AL22: ______ | AM22: ______ | AN22: ______ | AO22: ______ | AP22: ______ | AQ22: ______ | AR22: ______ | AS22: ______ | AT22: ______ | AU22: ______ | AV22: ______ | AW22: ______ | AX22: ______ | AY22: ______ | AZ22: ______ | BA22: ______ | BB22: ______ | BC22: ______ | BD22: ______ | BE22: ______ | BF22: ______ | BG22: ______ | BH22: ______ | BI22: ______ | BJ22: ______ | BK22: ______ | BL22: ______ | BM22: ______ | BN22: ______ | BO22: ______ | BP22: ______ | BQ22: ______ | BR22: ______ | BS22: ______ | BT22: ______ | BU22: ______
B23: Total Assets | D23: =SUM(D15:D21)+D13-#REF!-#REF! -> #REF! | E23: =SUM(E15:E21)+E13-#REF!-#REF! -> #REF! | F23: =SUM(F15:F21)+F13-#REF!-#REF! -> #REF! | G23: =SUM(G15:G21)+G13-#REF!-#REF! -> #REF! | H23: =SUM(H15:H21)+H13-#REF!-#REF! -> #REF! | I23: =SUM(I15:I21)+I13-#REF!-#REF! -> #REF! | J23: =SUM(J15:J21)+J13-#REF!-#REF! -> #REF! | K23: =SUM(K15:K21)+K13-#REF!-#REF! -> #REF! | L23: =SUM(L15:L21)+L13-#REF!-#REF! -> #REF! | M23: =SUM(M15:M21)+M13 -> 230561 | N23: =SUM(N15:N21)+N13 -> 213780 | O23: =SUM(O15:O21)+O13 -> 223852 | P23: =SUM(P15:P21)+P13 -> 226035 | Q23: =SUM(Q15:Q21)+Q13 -> 243303 | R23: =SUM(R15:R21)+R13 -> 243303 | S23: =SUM(S15:S21)+S13 -> 229771 | T23: =SUM(T15:T21)+T13 -> 241853 | ... AU23: =SUM(AU15:AU21)+AU13 -> 1358991 | AV23: =SUM(AV13:AV22) -> 1358991 | AW23: =SUM(AW13:AW22) -> 1329459 | AX23: =SUM(AX13:AX22) -> 1355659 | AY23: =SUM(AY13:AY22) -> 1399300 | AZ23: =SUM(AZ13:AZ22) -> 1505348 | BA23: =SUM(BA13:BA22) -> 1505348 | BB23: =SUM(BB13:BB22) -> 1488473 | BC23: =SUM(BC13:BC22) -> 1526593 | ... BU23: =SUM(BU13:BU22) -> 1960639.5
B25: Liabilities and Stock Holders' Equity
B27: Current Liabilities
B28: Accounts Payable | G28: 3536 | H28: 3536 | I28: 2892 | J28: 2990 | K28: 2868 | L28: 2038 | M28: =+L28 -> 2038 | N28: 1657 | O28: 4200 | P28: 2675 | Q28: 4012 | R28: =+Q28 -> 4012 | S28: 3495 | T28: 2257 | U28: 3567 | V28: 2240 | W28: =+V28 -> 2240 | X28: 5669 | Y28: 4612 | Z28: 2766 | AA28: 7048 | AB28: =+AA28 -> 7048 | AC28: 6297 | AD28: 12975 | AE28: 6549 | AF28: =6836 -> 6836 | AG28: =+AF28 -> 6836 | AH28: 10062 | AI28: 7078 | AJ28: =9033 -> 9033 | AK28: =3860 -> 3860 | AL28: =+AK28 -> 3860 | AM28: =4296 -> 4296 | AN28: =2063+44730 -> 46793 | AO28: =7514+44804 -> 52318 | AP28: =3521 -> 3521 | AQ28: =+AP28 -> 3521 | AR28: =12163 -> 12163 | AS28: =6832 -> 6832 | AT28: =13864 -> 13864 | AU28: =10255 -> 10255 | AV28: =+AU28 -> 10255 | AW28: =8475 -> 8475 | AX28: =8989 -> 8989 | AY28: =8951 -> 8951 | AZ28: =15812 -> 15812 | BA28: =+AZ28 -> 15812 | BB28: =11516 -> 11516 | BC28: =12820 -> 12820 | BD28: =6005 -> 6005 | BE28: =18908 -> 18908 | BF28: =+BE28 -> 18908 | BG28: =12318 -> 12318 | BH28: =15943 -> 15943 | BI28: =15571 -> 15571 | BJ28: =11041 -> 11041 | BK28: =+BJ28 -> 11041 | BL28: =+BL63*BL104/90 -> 12555.274 | BM28: =+BM63*BM104/90 -> 16930.954 | BN28: =+BN63*BN104/90 -> 15597.351 | BO28: =+BO63*BO104/90 -> 14755.652 | BP28: =+BO28 -> 14755.652 | BQ28: =+BQ63*BQ104/90 -> 12317.348 | BR28: =+BR63*BR104/90 -> 11747.807 | BS28: =+BS63*BS104/90 -> 15851.806 | BT28: =+BT63*BT104/90 -> 14235.823 | BU28: =+BT28 -> 14235.823
B29: Accrued Expenses and Other Current Liabilities | G29: 11907 | H29: 11907 | I29: 7956 | J29: 12765 | K29: 15725 | L29: 24707 | M29: =+L29 -> 24707 | N29: 14424 | O29: 19798 | P29: 22226 | Q29: 23499 | R29: =+Q29 -> 23499 | S29: 16346 | T29: 20667 | U29: 23737 | V29: 29728 | W29: =+V29 -> 29728 | X29: 18372 | Y29: 21832 | Z29: 27392 | AA29: 37376 | AB29: =+AA29 -> 37376 | AC29: 25062 | AD29: 33069 | AE29: 33174 | AF29: =41021 -> 41021 | AG29: =+AF29 -> 41021 | AH29: 26486 | AI29: 36165 | AJ29: =48035 -> 48035 | AK29: =61677 -> 61677 | AL29: =+AK29 -> 61677 | AM29: =47806 -> 47806 | AN29: =55633 -> 55633 | AO29: =57975 -> 57975 | AP29: =82620 -> 82620 | AQ29: =+AP29 -> 82620 | AR29: =56502 -> 56502 | AS29: =66348 -> 66348 | AT29: =64427 -> 64427 | AU29: =80306 -> 80306 | AV29: =+AU29 -> 80306 | AW29: =57545 -> 57545 | AX29: =69456 -> 69456 | AY29: =63388 -> 63388 | AZ29: =84489 -> 84489 | BA29: =+AZ29 -> 84489 | BB29: =60605 -> 60605 | BC29: =67242 -> 67242 | BD29: =82319 -> 82319 | BE29: =88802 -> 88802 | BF29: =+BE29 -> 88802 | BG29: =69458 -> 69458 | BH29: =78125 -> 78125 | BI29: =80539 -> 80539 | BJ29: =96998 -> 96998 | BK29: =+BJ29 -> 96998 | BL29: =+(BL63+BL64)*BL107 -> 69466.637 | BM29: =+(BM63+BM64)*BM107 -> 72272.403 | BN29: =+(BN63+BN64)*BN107 -> 80439.915 | BO29: =+(BO63+BO64)*BO107 -> 89819.118 | BP29: =+BO29 -> 89819.118 | BQ29: =+(BQ63+BQ64)*BQ107 -> 67707.838 | BR29: =+(BR63+BR64)*BR107 -> 73550.732 | BS29: =+(BS63+BS64)*BS107 -> 82832.797 | BT29: =+(BT63+BT64)*BT107 -> 103780 | BU29: =+BT29 -> 103780
B30: Convertible Senior Notes | AV30: =+AU30 -> 0 | BA30: =+AZ30 -> 0 | BB30: =0 -> 0 | BC30: =45737 -> 45737 | BD30: =45816 -> 45816 | BE30: =45895 -> 45895 | BF30: =+BE30 -> 45895 | BG30: =45967 -> 45967 | BH30: 0 | BI30: =0 -> 0 | BJ30: 0 | BK30: =+BJ30 -> 0 | BP30: =+BO30 -> 0 | BU30: =+BT30 -> 0
B31: Operating Lease Liabilities, Current | M31: =+L31 -> 0 | R31: =+Q31 -> 0 | W31: =+V31 -> 0 | AB31: =+AA31 -> 0 | AC31: 5231 | AD31: =6057 -> 6057 | AE31: 6460 | AF31: =7179 -> 7179 | AG31: =+AF31 -> 7179 | AH31: 8866 | AI31: 9436 | AJ31: =9568 -> 9568 | AK31: =9612 -> 9612 | AL31: =+AK31 -> 9612 | AM31: =9261 -> 9261 | AN31: =9285 -> 9285 | AO31: =9395 -> 9395 | AP31: =9630 -> 9630 | AQ31: =+AP31 -> 9630 | AR31: =11336 -> 11336 | AS31: =11809 -> 11809 | AT31: =11858 -> 11858 | AU31: =12444 -> 12444 | AV31: =+AU31 -> 12444 | AW31: =12853 -> 12853 | AX31: =12116 -> 12116 | AY31: =12472 -> 12472 | AZ31: =13452 -> 13452 | BA31: =+AZ31 -> 13452 | BB31: =14257 -> 14257 | BC31: =15592 -> 15592 | BD31: =15849 -> 15849 | BE31: =15493 -> 15493 | BF31: =+BE31 -> 15493 | BG31: =13614 -> 13614 | BH31: =15185 -> 15185 | BI31: =15955 -> 15955 | BJ31: =16176 -> 16176 | BK31: =+BJ31 -> 16176 | BL31: =+BK31 -> 16176 | BM31: =+BL31 -> 16176 | BN31: =+BM31 -> 16176 | BO31: =+BN31 -> 16176 | BP31: =+BO31 -> 16176 | BQ31: =+BP31 -> 16176 | BR31: =+BQ31 -> 16176 | ... BU31: =+BT31 -> 16176
B32: Deferred Revenue | G32: 58164 | H32: 58164 | I32: 60539 | J32: 66040 | K32: 74347 | L32: 87917 | M32: =+L32 -> 87917 | N32: 90081 | O32: 99360 | P32: 104663 | Q32: 116903 | R32: =+Q32 -> 116903 | S32: 116564 | T32: 126085 | U32: 133117 | V32: 142020 | W32: =+V32 -> 142020 | X32: 140448 | Y32: 153634 | Z32: 159408 | AA32: 189855 | AB32: =+AA32 -> 189855 | AC32: 184453 | AD32: 199048 | AE32: 200314 | AF32: =231518 -> 231518 | AG32: =+AF32 -> 231518 | AH32: 219432 | AI32: 227318 | AJ32: =231560 -> 231560 | AK32: =278585 -> 278585 | AL32: =+AK32 -> 278585 | AM32: =282245 -> 282245 | AN32: =302186 -> 302186 | AO32: =316045 -> 316045 | AP32: =372067 -> 372067 | AQ32: =+AP32 -> 372067 | AR32: =378338 -> 378338 | AS32: =395208 -> 395208 | AT32: =391761 -> 391761 | AU32: =426599 -> 426599 | AV32: =+AU32 -> 426599 | AW32: =413992 -> 413992 | AX32: =429328 -> 429328 | AY32: =421898 -> 421898 | AZ32: =455503 -> 455503 | BA32: =+AZ32 -> 455503 | BB32: =437687 -> 437687 | BC32: =437222 -> 437222 | BD32: =423640 -> 423640 | BE32: =461118 -> 461118 | BF32: =+BE32 -> 461118 | BG32: =447798 -> 447798 | BH32: =446688 -> 446688 | BI32: =422943 -> 422943 | BJ32: =451155 -> 451155 | BK32: =+BJ32 -> 451155 | BL32: =+BG32*(1+BL112) -> 447798 | BM32: =+BH32*(1+BM112) -> 451154.88 | BN32: =+BI32*(1+BN112) -> 427172.43 | BO32: =+BJ32*(1+BO112) -> 460178.1 | BP32: =+BO32 -> 460178.1 | BQ32: =+BL32*(1+BQ112) -> 456753.96 | BR32: =+BM32*(1+BR112) -> 460177.98 | BS32: =+BN32*(1+BS112) -> 435715.88 | BT32: =+BO32*(1+BT112) -> 469381.66 | BU32: =+BT32 -> 469381.66
B33: Term Loan Payable, net of Unamortized Debt Discount | G33: 0 | H33: 0 | I33: 1703 | J33: 3976 | K33: 0 | L33: 0 | M33: =+L33 -> 0 | N33: 0 | O33: 0 | P33: 0 | Q33: 0 | R33: =+Q33 -> 0 | S33: 0 | T33: 0 | U33: =+T33 -> 0 | V33: 0 | W33: =+V33 -> 0 | X33: 0 | Y33: 0 | Z33: 0 | AA33: 0 | AB33: =+AA33 -> 0 | AC33: 0 | AD33: =+AC33 -> 0 | AE33: 0 | AF33: =+AE33 -> 0 | AG33: =+AF33 -> 0 | AH33: =+AF33 -> 0 | AI33: =+AH33 -> 0 | AJ33: =+AI33 -> 0 | AK33: =+AJ33 -> 0 | AL33: =+AK33 -> 0 | AM33: =+AK33 -> 0 | AP33: 0 | AQ33: =+AP33 -> 0 | AV33: =+AU33 -> 0 | BA33: =+AZ33 -> 0 | BF33: =+BE33 -> 0 | BI33: =+BH33 -> 0 | BK33: =+BJ33 -> 0 | BL33: =+BJ33 -> 0 | BM33: =+BL33 -> 0 | BN33: =+BM33 -> 0 | BO33: =+BN33 -> 0 | BP33: =+BO33 -> 0 | BQ33: =+BO33 -> 0 | BR33: =+BQ33 -> 0 | BS33: =+BR33 -> 0 | BT33: =+BS33 -> 0 | BU33: =+BT33 -> 0
B34: Contingent Consideration | G34: 0 | H34: 0 | I34: 0 | J34: 0 | K34: 0 | L34: 0 | M34: =+L34 -> 0 | N34: 0 | O34: 0 | P34: 0 | Q34: 0 | R34: =+Q34 -> 0 | S34: 0 | T34: 0 | U34: =+T34 -> 0 | V34: 0 | W34: =+V34 -> 0 | X34: 0 | Y34: 0 | Z34: 0 | AA34: 0 | AB34: =+AA34 -> 0 | AC34: 0 | AD34: =+AC34 -> 0 | AE34: 0 | AF34: =+AE34 -> 0 | AG34: =+AF34 -> 0 | AH34: =+AF34 -> 0 | AI34: =+AH34 -> 0 | AJ34: =+AI34 -> 0 | AK34: =+AJ34 -> 0 | AL34: =+AK34 -> 0 | AM34: =+AK34 -> 0 | AP34: 0 | AQ34: =+AP34 -> 0 | AV34: =+AU34 -> 0 | BA34: =+AZ34 -> 0 | BF34: =+BE34 -> 0 | BI34: =+BH34 -> 0 | BK34: =+BJ34 -> 0 | BL34: =+BJ34 -> 0 | BM34: =+BL34 -> 0 | BN34: =+BM34 -> 0 | BO34: =+BN34 -> 0 | BP34: =+BO34 -> 0 | BQ34: =+BO34 -> 0 | BR34: =+BQ34 -> 0 | BS34: =+BR34 -> 0 | BT34: =+BS34 -> 0 | BU34: =+BT34 -> 0
B35: Other Current Liabilities | G35: 642 | H35: 642 | I35: 887 | J35: 991 | K35: 1030 | L35: 1105 | M35: =+L35 -> 1105 | N35: 767 | O35: 1047 | P35: 1352 | Q35: 1195 | R35: =+Q35 -> 1195 | S35: 1239 | T35: 1334 | U35: 1394 | V35: 1706 | W35: =+V35 -> 1706 | X35: 1702 | Y35: 1079 | Z35: 838 | AA35: 707 | AB35: =+AA35 -> 707 | AC35: =7385 -> 7385 | AD35: 126 | AE35: 285 | AF35: =119 -> 119 | AG35: =+AF35 -> 119 | AH35: 35 | AI35: 0 | AJ35: =85 -> 85 | AK35: =0 -> 0 | AL35: =+AK35 -> 0 | AM35: =127 -> 127 | AN35: =303 -> 303 | AO35: =809 -> 809 | AP35: =842 -> 842 | AQ35: =+AP35 -> 842 | AR35: =1264 -> 1264 | AS35: =3473 -> 3473 | AT35: =5254 -> 5254 | AU35: =1663 -> 1663 | AV35: =+AU35 -> 1663 | AW35: =809 -> 809 | AX35: =562 -> 562 | AY35: =888 -> 888 | AZ35: =536 -> 536 | BA35: =+AZ35 -> 536 | BB35: 0 | BC35: =0 -> 0 | BD35: =0 -> 0 | BE35: =0 -> 0 | BF35: =+BE35 -> 0 | BG35: =0 -> 0 | BH35: =0 -> 0 | BI35: =0 -> 0 | BK35: =+BJ35 -> 0 | BL35: =+BJ35 -> 0 | BM35: =+BL35 -> 0 | BN35: =+BM35 -> 0 | BO35: =+BN35 -> 0 | BP35: =+BO35 -> 0 | BQ35: =+BO35 -> 0 | BR35: =+BQ35 -> 0 | BS35: =+BR35 -> 0 | BT35: =+BS35 -> 0 | BU35: =+BT35 -> 0
D36: ______ | E36: ______ | F36: ______ | G36: ______ | H36: ______ | I36: ______ | J36: ______ | K36: ______ | L36: ______ | M36: ______ | N36: ______ | O36: ______ | P36: ______ | Q36: ______ | R36: ______ | S36: ______ | T36: ______ | U36: ______ | V36: ______ | W36: ______ | X36: ______ | Y36: ______ | Z36: ______ | AA36: ______ | AB36: ______ | AC36: ______ | AD36: ______ | AE36: ______ | AF36: ______ | AG36: ______ | AH36: ______ | AI36: ______ | AJ36: ______ | AK36: ______ | AL36: ______ | AM36: ______ | AN36: ______ | AO36: ______ | AP36: ______ | AQ36: ______ | AR36: ______ | AS36: ______ | AT36: ______ | AU36: ______ | AV36: ______ | AW36: ______ | AX36: ______ | AY36: ______ | AZ36: ______ | BA36: ______ | BB36: ______ | BC36: ______ | BD36: ______ | BE36: ______ | BF36: ______ | BG36: ______ | BH36: ______ | BI36: ______ | BJ36: ______ | BK36: ______ | BL36: ______ | BM36: ______ | BN36: ______ | BO36: ______ | BP36: ______ | BQ36: ______ | BR36: ______ | BS36: ______ | BT36: ______ | BU36: ______
B37: Total Current Liabilities | D37: =SUM(D28:D35)-#REF! -> #REF! | E37: =SUM(E28:E35)-#REF! -> #REF! | F37: =SUM(F28:F35)-#REF! -> #REF! | G37: =SUM(G28:G35)-#REF! -> #REF! | H37: =SUM(H28:H35)-#REF! -> #REF! | I37: =SUM(I28:I35)-#REF! -> #REF! | J37: =SUM(J28:J35)-#REF! -> #REF! | K37: =SUM(K28:K35)-#REF! -> #REF! | L37: =SUM(L28:L35)-#REF! -> #REF! | M37: =SUM(M28:M35) -> 115767 | N37: =SUM(N28:N35) -> 106929 | O37: =SUM(O28:O35) -> 124405 | P37: =SUM(P28:P35) -> 130916 | Q37: =SUM(Q28:Q35) -> 145609 | R37: =SUM(R28:R35) -> 145609 | S37: =SUM(S28:S35) -> 137644 | T37: =SUM(T28:T35) -> 150343 | ... BU37: =SUM(BU28:BU35) -> 603573.49
B39: Deferred Revenue, Net of Current Portion | G39: 26892 | H39: 26892 | I39: 28104 | J39: 31471 | K39: 35805 | L39: 42400 | M39: =+L39 -> 42400 | N39: 41776 | O39: 45362 | P39: 44601 | Q39: 52160 | R39: =+Q39 -> 52160 | S39: 51083 | T39: 54344 | U39: 55526 | V39: 83373 | W39: =+V39 -> 83373 | X39: 78450 | Y39: 70766 | Z39: 63680 | AA39: 58716 | AB39: =+AA39 -> 58716 | AC39: 52014 | AD39: 44944 | AE39: 36620 | AF39: =36226 -> 36226 | AG39: =+AF39 -> 36226 | AH39: 31641 | AI39: 33280 | AJ39: =30632 -> 30632 | AK39: =31365 -> 31365 | AL39: =+AK39 -> 31365 | AM39: =28833 -> 28833 | AN39: =30124 -> 30124 | AO39: =27905 -> 27905 | AP39: =33056 -> 33056 | AQ39: =+AP39 -> 33056 | AR39: =30616 -> 30616 | AS39: =33098 -> 33098 | AT39: =31659 -> 31659 | AU39: =31040 -> 31040 | AV39: =+AU39 -> 31040 | AW39: =31585 -> 31585 | AX39: =30064 -> 30064 | AY39: =29344 -> 29344 | AZ39: =32577 -> 32577 | BA39: =+AZ39 -> 32577 | BB39: =29207 -> 29207 | BC39: =27512 -> 27512 | BD39: =28239 -> 28239 | BE39: =27078 -> 27078 | BF39: =+BE39 -> 27078 | BG39: =27524 -> 27524 | BH39: =29183 -> 29183 | BI39: =28342 -> 28342 | BJ39: =29971 -> 29971 | BK39: =+BJ39 -> 29971 | BL39: =+BJ39*(1+BL116) -> 28472.45 | BM39: =+BL39*(1+BM116) -> 27903.001 | BN39: =+BM39*(1+BN116) -> 27344.941 | BO39: =+BN39*(1+BO116) -> 27071.492 | BP39: =+BO39 -> 27071.492 | BQ39: =+BO39*(1+BQ116) -> 25717.917 | BR39: =+BQ39*(1+BR116) -> 25203.559 | BS39: =+BR39*(1+BS116) -> 24699.487 | BT39: =+BS39*(1+BT116) -> 24452.493 | BU39: =+BT39 -> 24452.493
B40: Redeemable Convertible Preferred Stock / Convertible Senior Notes, net | G40: 211598 | H40: 211598 | I40: 222871 | J40: 246659 | K40: 0 | L40: 0 | M40: =+L40 -> 0 | N40: 0 | O40: 0 | P40: 0 | Q40: 0 | R40: =+Q40 -> 0 | S40: 0 | T40: 0 | U40: =+T40 -> 0 | V40: 0 | W40: =+V40 -> 0 | X40: 0 | Y40: 0 | Z40: 0 | AA40: 0 | AB40: =+AA40 -> 0 | AC40: 0 | AD40: =+AC40 -> 0 | AE40: =+AD40 -> 0 | AF40: =+AE40 -> 0 | AG40: =+AF40 -> 0 | AH40: =+AF40 -> 0 | AI40: 0 | AJ40: =+AI40 -> 0 | AK40: =+AJ40 -> 0 | AL40: =+AK40 -> 0 | AM40: =+AK40 -> 0 | AQ40: =+AP40 -> 0 | AV40: =+AU40 -> 0 | BA40: =+AZ40 -> 0 | BF40: =+BE40 -> 0 | BI40: =+BH40 -> 0 | BK40: =+BJ40 -> 0 | BL40: =+BJ40 -> 0 | BM40: =+BL40 -> 0 | BN40: =+BM40 -> 0 | BO40: =+BN40 -> 0 | BP40: =+BO40 -> 0 | BQ40: =+BO40 -> 0 | BR40: =+BQ40 -> 0 | BS40: =+BR40 -> 0 | BT40: =+BS40 -> 0 | BU40: =+BT40 -> 0
B41: Convertible Senior Notes, net | G41: 0 | H41: 0 | I41: 0 | J41: 0 | K41: 0 | L41: 0 | M41: =+L41 -> 0 | N41: 0 | O41: 0 | P41: 0 | Q41: 0 | R41: =+Q41 -> 0 | S41: 0 | T41: 0 | U41: =+T41 -> 0 | V41: 0 | W41: =+V41 -> 0 | X41: 0 | Y41: 0 | Z41: 172165 | AA41: 174688 | AB41: =+AA41 -> 174688 | AC41: 177198 | AD41: 179791 | AE41: 182471 | AF41: =185200 -> 185200 | AG41: =+AF41 -> 185200 | AH41: 187944 | AI41: 368161 | AJ41: =373318 -> 373318 | AK41: =378586 -> 378586 | AL41: =+AK41 -> 378586 | AM41: =855709 -> 855709 | AN41: =810093 -> 810093 | AO41: =811068 -> 811068 | AP41: =812063 -> 812063 | AQ41: =+AP41 -> 812063 | AR41: =812995 -> 812995 | AS41: =813950 -> 813950 | AT41: =814947 -> 814947 | AU41: =815948 -> 815948 | AV41: =+AU41 -> 815948 | AW41: =816894 -> 816894 | AX41: =817873 -> 817873 | AY41: =928892 -> 928892 | AZ41: =929996 -> 929996 | BA41: =+AZ41 -> 929996 | BB41: =931001 -> 931001 | BC41: =886272 -> 886272 | BD41: =887362 -> 887362 | BE41: =888356 -> 888356 | BF41: =+BE41 -> 888356 | BG41: =889303 -> 889303 | BH41: =890277 -> 890277 | BI41: =891279 -> 891279 | BJ41: =892284 -> 892284 | BK41: =+BJ41 -> 892284 | BL41: =+BJ41 -> 892284 | BM41: =+BL41 -> 892284 | BN41: =+BM41 -> 892284 | BO41: =+BN41 -> 892284 | BP41: =+BO41 -> 892284 | BQ41: =+BO41 -> 892284 | BR41: =+BQ41 -> 892284 | BS41: =+BR41 -> 892284 | BT41: =+BS41 -> 892284 | BU41: =+BT41 -> 892284
B42: Operating Lease Liabilities, Non-Current | M42: =+L42 -> 0 | R42: =+Q42 -> 0 | W42: =+V42 -> 0 | AB42: =+AA42 -> 0 | AC42: 16394 | AD42: =71722 -> 71722 | AE42: 73266 | AF42: =72294 -> 72294 | AG42: =+AF42 -> 72294 | AH42: 71586 | AI42: 80081 | AJ42: =77863 -> 77863 | AK42: =75737 -> 75737 | AL42: =+AK42 -> 75737 | AM42: =73466 -> 73466 | AN42: =71691 -> 71691 | AO42: =69418 -> 69418 | AP42: =90865 -> 90865 | AQ42: =+AP42 -> 90865 | AR42: =93954 -> 93954 | AS42: =89473 -> 89473 | AT42: =90427 -> 90427 | AU42: =85946 -> 85946 | AV42: =+AU42 -> 85946 | AW42: =84114 -> 84114 | AX42: =84751 -> 84751 | AY42: =81065 -> 81065 | AZ42: =81130 -> 81130 | BA42: =+AZ42 -> 81130 | BB42: =77069 -> 77069 | BC42: =73425 -> 73425 | BD42: =72555 -> 72555 | BE42: =68430 -> 68430 | BF42: =+BE42 -> 68430 | BG42: =65484 -> 65484 | BH42: =62187 -> 62187 | BI42: =63551 -> 63551 | BJ42: =59908 -> 59908 | BK42: =+BJ42 -> 59908 | BL42: =+BK42 -> 59908 | BM42: =+BL42 -> 59908 | BN42: =+BM42 -> 59908 | BO42: =+BN42 -> 59908 | BP42: =+BO42 -> 59908 | BQ42: =+BP42 -> 59908 | BR42: =+BQ42 -> 59908 | ... BU42: =+BT42 -> 59908
B43: Other Long Term Liabilities | G43: 4218 | H43: 4218 | I43: 3958 | J43: 5050 | K43: 4305 | L43: 4319 | M43: =+L43 -> 4319 | N43: 4460 | O43: 2939 | P43: 2872 | Q43: 3496 | R43: =+Q43 -> 3496 | S43: 3187 | T43: 2539 | U43: 2333 | V43: 2238 | W43: =+V43 -> 2238 | X43: 1907 | Y43: 2305 | Z43: 2607 | AA43: 3660 | AB43: =+AA43 -> 3660 | AC43: =1021 -> 1021 | AD43: 1023 | AE43: 1280 | AF43: =1352 -> 1352 | AG43: =+AF43 -> 1352 | AH43: 1325 | AI43: 8204 | AJ43: =1370 -> 1370 | AK43: =2164 -> 2164 | AL43: =+AK43 -> 2164 | AM43: =2175 -> 2175 | AN43: =9596 -> 9596 | AO43: =20950 -> 20950 | AP43: =17342 -> 17342 | AQ43: =+AP43 -> 17342 | AR43: =13253 -> 13253 | AS43: =13512 -> 13512 | AT43: =13636 -> 13636 | AU43: =14864 -> 14864 | AV43: =+AU43 -> 14864 | AW43: =13364 -> 13364 | AX43: =13542 -> 13542 | AY43: =14047 -> 14047 | AZ43: =10032 -> 10032 | BA43: =+AZ43 -> 10032 | BB43: =13580 -> 13580 | BC43: 13691 | BD43: =19050 -> 19050 | BE43: =20243 -> 20243 | BF43: =+BE43 -> 20243 | BG43: =20622 -> 20622 | BH43: =20705 -> 20705 | BI43: =21011 -> 21011 | BJ43: =14201 -> 14201 | BK43: =+BJ43 -> 14201 | BL43: =+BJ43 -> 14201 | BM43: =+BL43 -> 14201 | BN43: =+BM43 -> 14201 | BO43: =+BN43 -> 14201 | BP43: =+BO43 -> 14201 | BQ43: =+BO43 -> 14201 | BR43: =+BQ43 -> 14201 | BS43: =+BR43 -> 14201 | BT43: =+BS43 -> 14201 | BU43: =+BT43 -> 14201
B44: Term Loan Payable, net of Unamortized Debt Discount | G44: 16871 | H44: 16871 | I44: 15306 | J44: 13172 | K44: 0 | L44: 0 | M44: =+L44 -> 0 | N44: 0 | O44: 0 | P44: 0 | Q44: 0 | R44: =+Q44 -> 0 | S44: 0 | T44: 0 | U44: =+T44 -> 0 | V44: 0 | W44: =+V44 -> 0 | X44: 0 | Y44: 0 | Z44: 0 | AA44: 0 | AB44: =+AA44 -> 0 | AC44: 0 | AD44: =+AC44 -> 0 | AE44: =+AD44 -> 0 | AF44: =+AE44 -> 0 | AG44: =+AF44 -> 0 | AH44: =+AF44 -> 0 | AI44: =+AH44 -> 0 | AJ44: =+AI44 -> 0 | AK44: =+AJ44 -> 0 | AL44: =+AK44 -> 0 | AM44: =+AK44 -> 0 | AN44: =+AM44 -> 0 | AO44: =+AN44 -> 0 | AP44: =+AO44 -> 0 | AQ44: =+AP44 -> 0 | AR44: =+AP44 -> 0 | AS44: =+AR44 -> 0 | AT44: =+AS44 -> 0 | AU44: =+AT44 -> 0 | AV44: =+AU44 -> 0 | AW44: =+AU44 -> 0 | AX44: =+AW44 -> 0 | AY44: =+AX44 -> 0 | AZ44: =+AY44 -> 0 | BA44: =+AZ44 -> 0 | BB44: =+AZ44 -> 0 | BC44: =+BB44 -> 0 | BD44: =+BC44 -> 0 | BE44: =+BD44 -> 0 | BF44: =+BE44 -> 0 | BG44: =+BE44 -> 0 | BH44: =+BG44 -> 0 | BI44: =+BH44 -> 0 | BJ44: =+BI44 -> 0 | BK44: =+BJ44 -> 0 | BL44: =+BJ44 -> 0 | BM44: =+BL44 -> 0 | BN44: =+BM44 -> 0 | BO44: =+BN44 -> 0 | BP44: =+BO44 -> 0 | BQ44: =+BO44 -> 0 | BR44: =+BQ44 -> 0 | BS44: =+BR44 -> 0 | BT44: =+BS44 -> 0 | BU44: =+BT44 -> 0
D45: ______ | E45: ______ | F45: ______ | G45: ______ | H45: ______ | I45: ______ | J45: ______ | K45: ______ | L45: ______ | M45: ______ | N45: ______ | O45: ______ | P45: ______ | Q45: ______ | R45: ______ | S45: ______ | T45: ______ | U45: ______ | V45: ______ | W45: ______ | X45: ______ | Y45: ______ | Z45: ______ | AA45: ______ | AB45: ______ | AC45: ______ | AD45: ______ | AE45: ______ | AF45: ______ | AG45: ______ | AH45: ______ | AI45: ______ | AJ45: ______ | AK45: ______ | AL45: ______ | AM45: ______ | AN45: ______ | AO45: ______ | AP45: ______ | AQ45: ______ | AR45: ______ | AS45: ______ | AT45: ______ | AU45: ______ | AV45: ______ | AW45: ______ | AX45: ______ | AY45: ______ | AZ45: ______ | BA45: ______ | BB45: ______ | BC45: ______ | BD45: ______ | BE45: ______ | BF45: ______ | BG45: ______ | BH45: ______ | BI45: ______ | BJ45: ______ | BK45: ______ | BL45: ______ | BM45: ______ | BN45: ______ | BO45: ______ | BP45: ______ | BQ45: ______ | BR45: ______ | BS45: ______ | BT45: ______ | BU45: ______
B46: Total Liabilities | D46: =SUM(D37:D44)-#REF! -> #REF! | E46: =SUM(E37:E44)-#REF! -> #REF! | F46: =SUM(F37:F44)-#REF! -> #REF! | G46: =SUM(G37:G44)-#REF! -> #REF! | H46: =SUM(H37:H44)-#REF! -> #REF! | I46: =SUM(I37:I44)-#REF! -> #REF! | J46: =SUM(J37:J44)-#REF! -> #REF! | K46: =SUM(K37:K44)-#REF! -> #REF! | L46: =SUM(L37:L44)-#REF! -> #REF! | M46: =SUM(M37:M44) -> 162486 | N46: =SUM(N37:N44) -> 153165 | O46: =SUM(O37:O44) -> 172706 | P46: =SUM(P37:P44) -> 178389 | Q46: =SUM(Q37:Q44) -> 201265 | R46: =SUM(R37:R44) -> 201265 | S46: =SUM(S37:S44) -> 191914 | T46: =SUM(T37:T44) -> 207226 | ... AU46: =SUM(AU37:AU44) -> 1479065 | AV46: =SUM(AV37:AV45) -> 1479065 | AW46: =SUM(AW37:AW45) -> 1439631 | AX46: =SUM(AX37:AX45) -> 1466681 | AY46: =SUM(AY37:AY45) -> 1560945 | AZ46: =SUM(AZ37:AZ45) -> 1623527 | BA46: =SUM(BA37:BA45) -> 1623527 | BB46: =SUM(BB37:BB45) -> 1574922 | BC46: =SUM(BC37:BC45) -> 1579513 | ... BU46: =SUM(BU37:BU45) -> 1594419
B48: Stockholders' Equity | G48: -246862 | H48: -246862 | I48: -264834 | J48: -296640 | K48: 52458 | L48: 68075 | M48: =+L48 -> 68075 | N48: 60615 | O48: 51146 | P48: 47646 | Q48: 42038 | R48: =+Q48 -> 42038 | S48: 37857 | T48: 34627 | U48: 31766 | V48: 50026 | W48: =+V48 -> 50026 | X48: 73922 | Y48: 69543 | Z48: 93101 | AA48: 87319 | AB48: =+AA48 -> 87319 | AC48: 88851 | AD48: 87524 | AE48: =+AE23-AE46 -> 86175 | AF48: =83168 -> 83168 | AG48: =+AF48 -> 83168 | AH48: =+AH23-AH46 -> 76300 | AI48: 90688 | AJ48: =85353 -> 85353 | AK48: =71536 -> 71536 | AL48: =+AK48 -> 71536 | AM48: =-81225 -> -81225 | AN48: =-95395 -> -95395 | AO48: =-105003 -> -105003 | AP48: =-125995 -> -125995 | AQ48: =+AP48 -> -125995 | AR48: =-136551 -> -136551 | AS48: =-148155 -> -148155 | AT48: =-142284 -> -142284 | AU48: =-120074 -> -120074 | AV48: =+AU48 -> -120074 | AW48: =-110172 -> -110172 | AX48: =-111022 -> -111022 | AY48: =-161645 -> -161645 | AZ48: =-118179 -> -118179 | BA48: =+AZ48 -> -118179 | BB48: =+BB23-BB46 -> -86449 | BC48: =-52920 -> -52920 | BD48: =-6304 -> -6304 | BE48: 17711 | BF48: =+BE48 -> 17711 | BG48: =52722 -> 52722 | BH48: =90447 -> 90447 | BI48: =127216 -> 127216 | BJ48: =154730 -> 154730 | BK48: =+BJ48 -> 154730 | BL48: =+BL23-BL46 -> 173211.39 | BM48: =+BM23-BM46 -> 195375.43 | BN48: =+BN23-BN46 -> 225221.32 | BO48: =+BO23-BO46 -> 251232.93 | BP48: =+BO48 -> 251232.93 | BQ48: =+BQ23-BQ46 -> 281014.23 | BR48: =+BR23-BR46 -> 307034.6 | BS48: =+BS23-BS46 -> 338676.57 | BT48: =+BT23-BT46 -> 366220.47 | BU48: =+BT48 -> 366220.47
D49: ______ | E49: ______ | F49: ______ | G49: ______ | H49: ______ | I49: ______ | J49: ______ | K49: ______ | L49: ______ | M49: ______ | N49: ______ | O49: ______ | P49: ______ | Q49: ______ | R49: ______ | S49: ______ | T49: ______ | U49: ______ | V49: ______ | W49: ______ | X49: ______ | Y49: ______ | Z49: ______ | AA49: ______ | AB49: ______ | AC49: ______ | AD49: ______ | AE49: ______ | AF49: ______ | AG49: ______ | AH49: ______ | AI49: ______ | AJ49: ______ | AK49: ______ | AL49: ______ | AM49: ______ | AN49: ______ | AO49: ______ | AP49: ______ | AQ49: ______ | AR49: ______ | AS49: ______ | AT49: ______ | AU49: ______ | AV49: ______ | AW49: ______ | AX49: ______ | AY49: ______ | AZ49: ______ | BA49: ______ | BB49: ______ | BC49: ______ | BD49: ______ | BE49: ______ | BF49: ______ | BG49: ______ | BH49: ______ | BI49: ______ | BJ49: ______ | BK49: ______ | BL49: ______ | BM49: ______ | BN49: ______ | BO49: ______ | BP49: ______ | BQ49: ______ | BR49: ______ | BS49: ______ | BT49: ______ | BU49: ______
B50: Total Liabilities and Equity | D50: =+D48+D46 -> #REF! | E50: =+E48+E46 -> #REF! | F50: =+F48+F46 -> #REF! | G50: =+G48+G46 -> #REF! | H50: =+H48+H46 -> #REF! | I50: =+I48+I46 -> #REF! | J50: =+J48+J46 -> #REF! | K50: =+K48+K46 -> #REF! | ... BU50: =+BU48+BU46 -> 1960639.5
B52: Cash and Equivalent Per Share | D52: =+(D7+D8+D15)/D65 -> 0 | E52: =+(E7+E8+E15)/E65 -> 0 | F52: =+(F7+F8+F15)/F65 -> 0 | G52: =+(G7+G8+G15)/G65 -> 2.8788096 | H52: =+(H7+H8+H15)/H65 -> 2.8833484 | I52: =+(I7+I8+I15)/I65 -> 2.637439 | J52: =+(J7+J8+J15)/J65 -> 2.1184694 | K52: =+(K7+K8+K15)/K65 -> 3.7547602 | ... BU52: =+(BU7+BU8+BU15)/BU65 -> 11.74151
B53: Debt | D53: =+D33+D44+D41 -> 0 | E53: =+E33+E44+E41 -> 0 | F53: =+F33+F44+F41 -> 0 | G53: =+G33+G44+G41 -> 16871 | H53: =+H33+H44+H41 -> 16871 | I53: =+I33+I44+I41 -> 17009 | J53: =+J33+J44+J41 -> 17148 | K53: =+K33+K44+K41 -> 0 | ... BU53: =+BU33+BU44+BU41 -> 892284
B54: Net Cash / (Debt) | D54: =+(D52*D65)-D53 -> 0 | E54: =+(E52*E65)-E53 -> 0 | F54: =+(F52*F65)-F53 -> 0 | G54: =+(G52*G65)-G53 -> 19952 | H54: =+(H52*H65)-H53 -> 19952 | I54: =+(I52*I65)-I53 -> 16334 | J54: =+(J52*J65)-J53 -> 9852 | K54: =+(K52*K65)-K53 -> 123984 | ... BU54: =+(BU52*BU65)-BU53 -> 39973.761
B55: Net Cash / (Debt) Per Share | D55: =+D54/D65 -> 0 | E55: =+E54/E65 -> 0 | F55: =+F54/F65 -> 0 | G55: =+G54/G65 -> 1.5598405 | H55: =+H54/H65 -> 1.5622998 | I55: =+I54/I65 -> 1.2920232 | J55: =+J54/J65 -> 0.77300593 | K55: =+K54/K65 -> 3.7547602 | ... BU55: =+BU54/BU65 -> 0.50345766
B56: Book Value Per Share | D56: =+D48/D65 -> 0 | E56: =+E48/E65 -> 0 | F56: =+F48/F65 -> 0 | G56: =+G48/G65 -> -19.299587 | H56: =+H48/H65 -> -19.330015 | I56: =+I48/I65 -> -20.948431 | J56: =+J48/J65 -> -23.274917 | K56: =+K48/K65 -> 1.5886502 | ... BU56: =+BU48/BU65 -> 4.6124382
B57: DSO | D57: =+D9/D62*90 -> 0 | E57: =+E9/E62*90 -> 0 | F57: =+F9/F62*90 -> 0 | G57: =+G9/G62*90 -> 104.26624 | H57: =+H9/H62*90 -> 29.748699 | I57: =+I9/I62*90 -> 80.286369 | J57: =+J9/J62*90 -> 91.999612 | K57: =+K9/K62*90 -> 101.62511 | L57: =+L9/L62*90 -> 120.98621 | M57: =+((M9+H9)/2)/M62*360 -> 113.30981 | N57: =+N9/N62*90 -> 77.121796 | O57: =+O9/O62*90 -> 93.368842 | P57: =+P9/P62*90 -> 85.419569 | Q57: =+Q9/Q62*90 -> 98.233779 | R57: =+((R9+M9)/2)/R62*360 -> 106.69182 | S57: =+S9/S62*90 -> 67.040999 | T57: =+T9/T62*90 -> 90.221951 | U57: =+U9/U62*90 -> 86.738188 | V57: =+V9/V62*90 -> 114.83414 | W57: =+((W9+R9)/2)/W62*360 -> 110.01642 | X57: =+X9/X62*90 -> 63.920389 | Y57: =+Y9/Y62*90 -> 74.653753 | Z57: =+Z9/Z62*90 -> 77.597851 | AA57: =+AA9/AA62*90 -> 98.068198 | AB57: =+((AB9+W9)/2)/AB62*360 -> 109.57913 | AC57: =+AC9/AC62*90 -> 73.425292 | AD57: =+AD9/AD62*90 -> 78.977824 | AE57: =+AE9/AE62*90 -> 67.560339 | AF57: =+AF9/AF62*90 -> 86.34591 | AG57: =+((AG9+AB9)/2)/AG62*360 -> 89.66334 | AH57: =+AH9/AH62*90 -> 61.425906 | AI57: =+AI9/AI62*90 -> 69.901225 | AJ57: =+AJ9/AJ62*90 -> 63.062099 | AK57: =+AK9/AK62*90 -> 88.759268 | AL57: =+((AL9+AG9)/2)/AL62*360 -> 87.280442 | AM57: =+AM9/AM62*90 -> 58.784174 | AN57: =+AN9/AN62*90 -> 70.110741 | AO57: =+AO9/AO62*90 -> 62.259639 | AP57: =+AP9/AP62*90 -> 86.709532 | AQ57: =+((AQ9+AL9)/2)/AQ62*360 -> 86.635027 | AR57: =+AR9/AR62*90 -> 61.370914 | AS57: =+AS9/AS62*90 -> 67.021528 | AT57: =+AT9/AT62*90 -> 61.966432 | AU57: =+AU9/AU62*90 -> 74.176736 | AV57: =+((AV9+AQ9)/2)/AV62*360 -> 78.333603 | AW57: =+AW9/AW62*90 -> 57.330571 | AX57: =+AX9/AX62*90 -> 64.420078 | AY57: =+AY9/AY62*90 -> 62.321027 | AZ57: =+AZ9/AZ62*90 -> 72.283941 | BA57: =+((BA9+AV9)/2)/BA62*360 -> 73.348009 | BB57: =+BB9/BB62*90 -> 54.673307 | BC57: =+BC9/BC62*90 -> 62.168027 | BD57: =+BD9/BD62*90 -> 59.491973 | BE57: =+BE9/BE62*90 -> 70.01623 | BF57: =+((BF9+BA9)/2)/BF62*360 -> 71.040548 | BG57: =+BG9/BG62*90 -> 60.159379 | BH57: =+BH9/BH62*90 -> 63.314254 | BI57: =+BI9/BI62*90 -> 58.361672 | BJ57: =+BJ9/BJ62*90 -> 69.146089 | BK57: =+((BK9+BF9)/2)/BK62*360 -> 70.187301 | BL57: =+BL9/BL62*90 -> 61 | BM57: =+BM9/BM62*90 -> 64 | BN57: =+BN9/BN62*90 -> 58 | BO57: =+BO9/BO62*90 -> 68 | BP57: =+((BP9+BK9)/2)/BP62*360 -> 70.162132 | BQ57: =+BQ9/BQ62*90 -> 60 | BR57: =+BR9/BR62*90 -> 64 | BS57: =+BS9/BS62*90 -> 61 | BT57: =+BT9/BT62*90 -> 72 | BU57: =+((BU9+BP9)/2)/BU62*360 -> 70.087313
B58: Days Payable | D58: =+D28/D63*90 -> 0 | E58: =+E28/E63*90 -> 0 | F58: =+F28/F63*90 -> 0 | G58: =+G28/G63*90 -> 55.365344 | H58: =+H28/H63*90 -> 17.478032 | I58: =+I28/I63*90 -> 41.711538 | J58: =+J28/J63*90 -> 42.053446 | K58: =+K28/K63*90 -> 38.663871 | L58: =+L28/L63*90 -> 22.409285 | M58: =+((M28+H28)/2)/M63*360 -> 36.484364 | N58: =+N28/N63*90 -> 18.34543 | O58: =+O28/O63*90 -> 43.418332 | P58: =+P28/P63*90 -> 25.543767 | Q58: =+Q28/Q63*90 -> 32.609049 | R58: =+((R28+M28)/2)/R63*360 -> 29.169903 | S58: =+S28/S63*90 -> 27.06272 | T58: =+T28/T63*90 -> 16.471781 | U58: =+U28/U63*90 -> 24.303884 | V58: =+V28/V63*90 -> 12.582699 | W58: =+((W28+R28)/2)/W63*360 -> 21.158952 | X58: =+X28/X63*90 -> 33.320925 | Y58: =+Y28/Y63*90 -> 25.892334 | Z58: =+Z28/Z63*90 -> 15.15063 | AA58: =+AA28/AA63*90 -> 35.975499 | AB58: =+((AB28+W28)/2)/AB63*360 -> 25.560958 | AC58: =+AC28/AC63*90 -> 31.411706 | AD58: =+AD28/AD63*90 -> 58.974294 | AE58: =+AE28/AE63*90 -> 27.684829 | AF58: =+AF28/AF63*90 -> 26.640686 | AG58: =+((AG28+AB28)/2)/AG63*360 -> 30.392937 | AH58: =+AH28/AH63*90 -> 36.042985 | AI58: =+AI28/AI63*90 -> 24.714646 | AJ58: =+AJ28/AJ63*90 -> 29.603452 | AK58: =+AK28/AK63*90 -> 11.519713 | AL58: =+((AL28+AG28)/2)/AL63*360 -> 17.741409 | AM58: =+AM28/AM63*90 -> 12.084766 | AN58: =+AN28/AN63*90 -> 121.80038 | AO58: =+AO28/AO63*90 -> 127.06768 | AP58: =+AP28/AP63*90 -> 7.2920358 | AQ58: =+((AQ28+AL28)/2)/AQ63*360 -> 9.032859 | AR58: =+AR28/AR63*90 -> 24.679743 | AS58: =+AS28/AS63*90 -> 13.179012 | AT58: =+AT28/AT63*90 -> 26.732368 | AU58: =+AU28/AU63*90 -> 19.30777 | AV58: =+((AV28+AQ28)/2)/AV63*360 -> 13.36834 | AW58: =+AW28/AW63*90 -> 15.634288 | AX58: =+AX28/AX63*90 -> 16.071876 | AY58: =+AY28/AY63*90 -> 15.943437 | AZ58: =+AZ28/AZ63*90 -> 26.849046 | BA58: =+((BA28+AV28)/2)/BA63*360 -> 23.152945 | BB58: =+BB28/BB63*90 -> 19.191201 | BC58: =+BC28/BC63*90 -> 21.482033 | BD58: =+BD28/BD63*90 -> 9.7192749 | BE58: =+BE28/BE63*90 -> 29.159513 | BF58: =+((BF28+BA28)/2)/BF63*360 -> 28.191861 | BG58: =+BG28/BG63*90 -> 20.999375 | BH58: =+BH28/BH63*90 -> 25.597081 | BI58: =+BI28/BI63*90 -> 24.119064 | BJ58: =+BJ28/BJ63*90 -> 16.35596 | BK58: =+((BK28+BF28)/2)/BK63*360 -> 23.674475 | BL58: =+BL28/BL63*90 -> 21 | BM58: =+BM28/BM63*90 -> 28 | BN58: =+BN28/BN63*90 -> 25 | BO58: =+BO28/BO63*90 -> 23 | BP58: =+((BP28+BK28)/2)/BP63*360 -> 20.904978 | BQ58: =+BQ28/BQ63*90 -> 20 | BR58: =+BR28/BR63*90 -> 19 | BS58: =+BS28/BS63*90 -> 25 | BT58: =+BT28/BT63*90 -> 22 | BU58: =+((BU28+BP28)/2)/BU63*360 -> 23.051843
B60: Source: Rapid7 Inc. financial statements and Needham & Company, LLC estimates | X60: =IF(X50=X23,"","CHECK") | Y60: =IF(Y50=Y23,"","CHECK") | Z60: =IF(Z50=Z23,"","CHECK") | AA60: =IF(AA50=AA23,"","CHECK") | AB60: =IF(AB50=AB23,"","CHECK") | AC60: =IF(AC50=AC23,"","CHECK") | AD60: =IF(AD50=AD23,"","CHECK") | AE60: =IF(AE50=AE23,"","CHECK") | ... BU60: =IF(BU50=BU23,"","CHECK")
B62: Revenue | D62: =+IS!D52 -> 16736 | E62: =+IS!E52 -> 17880 | F62: =+IS!F52 -> 20329 | G62: =+IS!G52 -> 21935 | H62: =+IS!H52 -> 76880 | I62: =+IS!I52 -> 23571 | J62: =+IS!J52 -> 25790 | K62: =+IS!K52 -> 28312 | ... BU62: =+IS!BU52 -> 852865.58
B63: COGS | D63: =+IS!D74 -> 3858 | E63: =+IS!E74 -> 3946 | F63: =+IS!F74 -> 4656 | G63: =+IS!G74 -> 5748 | H63: =+IS!H74 -> 18208 | I63: =+IS!I74 -> 6240 | J63: =+IS!J74 -> 6399 | K63: =+IS!K74 -> 6676 | ... BU63: =+IS!BU74 -> 226379.53
B64: OPEX | D64: =+IS!D100 -> 18947 | E64: =+IS!E100 -> 20479 | F64: =+IS!F100 -> 21621 | G64: =+IS!G100 -> 24259 | H64: =+IS!H100 -> 85306 | I64: =+IS!I100 -> 23115 | J64: =+IS!J100 -> 26497 | K64: =+IS!K100 -> 29388 | ... BU64: =+IS!BU100 -> 509885.78
B65: Shares Outstanding | D65: =+IS!D119 -> 12716.675 | E65: =+IS!E119 -> 12762.938 | F65: =+IS!F119 -> 12813 | G65: =+IS!G119 -> 12791.051 | H65: =+IS!H119 -> 12770.916 | I65: =+IS!I119 -> 12642.188 | J65: =+IS!J119 -> 12745.051 | K65: =+IS!K119 -> 33020.484 | ... BU65: =+IS!BU119 -> 79398.457
B67: Operating Cash Flow | D67: =+CF!D26 -> 0 | E67: =+CF!E26 -> 0 | F67: =+CF!F26 -> 0 | G67: =+CF!G26 -> 0 | H67: =+CF!H26 -> -3356 | I67: =+CF!I26 -> -3012 | J67: =+CF!J26 -> -1241 | K67: =+CF!K26 -> 2273 | ... BU67: =+CF!BU26 -> 155747.01
B68: Free Cash Flow | D68: =+CF!D74 -> 0 | E68: =+CF!E74 -> 0 | F68: =+CF!F74 -> 0 | G68: =+CF!G74 -> 0 | H68: =+CF!H74 -> -10438 | I68: =+CF!I74 -> -3585 | J68: =+CF!J74 -> -1863 | K68: =+CF!K74 -> 629 | ... BU68: =+CF!BU74 -> 130730.35
B70: Drivers
B71: Accounts Receivable | G71: =+G9 -> 25412 | H71: =+H9 -> 25412 | I71: =+I9 -> 21027 | J71: =+J9 -> 26363 | K71: =+K9 -> 31969 | L71: =+L9 -> 44164 | M71: =+M9 -> 44164 | N71: =+N9 -> 29817 | ... BU71: =+BU9 -> 172116.16
B72: % of Sales | G72: =+G71/G$62 -> 1.1585138 | H72: =+H71/H$62 -> 0.3305411 | I72: =+I71/I$62 -> 0.89207076 | J72: =+J71/J$62 -> 1.0222179 | K72: =+K71/K$62 -> 1.1291678 | L72: =+L71/L$62 -> 1.3442912 | M72: =+M71/M$62 -> 0.39958019 | N72: =+N71/N$62 -> 0.85690884 | ... BU72: =+BU71/BU$62 -> 0.20180924
B73: Yr-Yr Growth | L73: =+L71/G71-1 -> 0.73791909 | M73: =+M71/H71-1 -> 0.73791909 | N73: =+N71/I71-1 -> 0.41803396 | O73: =+O71/J71-1 -> 0.46656299 | P73: =+P71/K71-1 -> 0.19759767 | Q73: =+Q71/L71-1 -> 0.11298795 | R73: =+R71/M71-1 -> 0.11298795 | S73: =+S71/N71-1 -> 0.13032834 | ... BU73: =+BU71/BP71-1 -> 0.075944604
B74: Q-Q Growth | I74: =+I71/G71-1 -> -0.17255627 | J74: =+J71/I71-1 -> 0.25376896 | K74: =+K71/J71-1 -> 0.21264651 | L74: =+L71/K71-1 -> 0.38146329 | N74: =+N71/L71-1 -> -0.32485735 | O74: =+O71/N71-1 -> 0.29667639 | P74: =+P71/O71-1 -> -0.0097509247 | Q74: =+Q71/P71-1 -> 0.28386355 | S74: =+S71/Q71-1 -> -0.31433861 | T74: =+T71/S71-1 -> 0.41115034 | U74: =+U71/T71-1 -> 0.023759462 | V74: =+V71/U71-1 -> 0.51285685 | X74: =+X71/V71-1 -> -0.47437586 | Y74: =+Y71/X71-1 -> 0.25202748 | Z74: =+Z71/Y71-1 -> 0.10922931 | AA74: =+AA71/Z71-1 -> 0.39359506 | AC74: =+AC71/AA71-1 -> -0.20321612 | AD74: =+AD71/AC71-1 -> 0.1604837 | AE74: =+AE71/AD71-1 -> -0.09910664 | AF74: =+AF71/AE71-1 -> 0.40858992 | AH74: =+AH71/AF71-1 -> -0.26771071 | AI74: =+AI71/AH71-1 -> 0.19312605 | AJ74: =+AJ71/AI71-1 -> -0.041628158 | AK74: =+AK71/AJ71-1 -> 0.51577589 | AM74: =+AM71/AK71-1 -> -0.31259241 | AN74: =+AN71/AL71-1 -> -0.11752793 | AO74: =+AO71/AM71-1 -> 0.26150377 | AP74: =+AP71/AO71-1 -> 0.50962542 | AR74: =+AR71/AP71-1 -> -0.26540447 | AS74: =+AS71/AQ71-1 -> -0.14643312 | AT74: =+AT71/AR71-1 -> 0.12762766 | AU74: =+AU71/AT71-1 -> 0.25639373 | AW74: =+AW71/AU71-1 -> -0.23257588 | AX74: =+AX71/AV71-1 -> -0.10355487 | AY74: =+AY71/AW71-1 -> 0.1800348 | AZ74: =+AZ71/AX71-1 -> 0.20955246 | BB74: =+BB71/AZ71-1 -> -0.2442467 | BC74: =+BC71/BA71-1 -> -0.12853781 | BD74: =+BD71/BB71-1 -> 0.13881777 | BE74: =+BE71/BC71-1 -> 0.17102268 | BG74: =+BG71/BE71-1 -> -0.16464973 | BH74: =+BH71/BG71-1 -> 0.072163995 | BI74: =+BI71/BH71-1 -> -0.062010977 | BJ74: =+BJ71/BI71-1 -> 0.18167668 | BL74: =+BL71/BJ71-1 -> -0.15603048 | BM74: =+BM71/BL71-1 -> 0.05404386 | BN74: =+BN71/BM71-1 -> -0.088044801 | BO74: =+BO71/BN71-1 -> 0.18062535 | BQ74: =+BQ71/BO71-1 -> -0.11847676 | BR74: =+BR71/BQ71-1 -> 0.07165913 | BS74: =+BS71/BR71-1 -> -0.041615967 | BT74: =+BT71/BS71-1 -> 0.18839252
B75: DSO | G75: =+G57 -> 104.26624 | H75: =+H57 -> 29.748699 | I75: =+I57 -> 80.286369 | J75: =+J57 -> 91.999612 | K75: =+K57 -> 101.62511 | L75: =+L57 -> 120.98621 | M75: =+M57 -> 113.30981 | N75: =+N57 -> 77.121796 | ... BK75: =+BK57 -> 70.187301 | BL75: 61 | BM75: 64 | BN75: 58 | BO75: 68 | BP75: =+BP57 -> 70.162132 | BQ75: 60 | BR75: 64 | BS75: 61 | BT75: 72 | BU75: =+BU57 -> 70.087313
B77: Prepaid Expenses & Other Current Assets | G77: =+G11 -> 4209 | H77: =+H11 -> 4209 | I77: =+I11 -> 4995 | J77: =+J11 -> 6297 | K77: =+K11 -> 4165 | L77: =+L11 -> 6148 | M77: =+M11 -> 6148 | N77: =+N11 -> 6618 | ... BU77: =+BU11 -> 37064.287
B78: % COGS + OPEX | G78: =+G77/(G$63+G$64) -> 0.14026727 | H78: =+H77/(H$63+H$64) -> 0.040661167 | I78: =+I77/(I$63+I$64) -> 0.17015841 | J78: =+J77/(J$63+J$64) -> 0.19142145 | K78: =+K77/(K$63+K$64) -> 0.11548913 | L78: =+L77/(L$63+L$64) -> 0.13669817 | M78: =+M77/(M$63+M$64) -> 0.042905995 | N78: =+N77/(N$63+N$64) -> 0.14934669 | ... BK78: =+BK77/(BK$63+BK$64) -> 0.065229221 | BL78: 0.23 | BM78: 0.22 | BN78: 0.24 | BO78: 0.23 | BP78: =+BP77/(BP$63+BP$64) -> 0.056845801 | BQ78: 0.22 | BR78: 0.2 | BS78: 0.19 | BT78: 0.2 | BU78: =+BU77/(BU$63+BU$64) -> 0.05034094
B79: Yr-Yr Growth | L79: =+L77/G77-1 -> 0.4606795 | M79: =+M77/H77-1 -> 0.4606795 | N79: =+N77/I77-1 -> 0.32492492 | O79: =+O77/J77-1 -> 0.14070192 | P79: =+P77/K77-1 -> 0.60984394 | Q79: =+Q77/L77-1 -> 0.48861418 | R79: =+R77/M77-1 -> 0.48861418 | S79: =+S77/N77-1 -> 0.16983983 | ... BU79: =+BU77/BP77-1 -> -0.10292441
B80: Q-Q Growth | I80: =+I77/G77-1 -> 0.18674269 | J80: =+J77/I77-1 -> 0.26066066 | K80: =+K77/J77-1 -> -0.33857392 | L80: =+L77/K77-1 -> 0.47611044 | N80: =+N77/L77-1 -> 0.076447625 | O80: =+O77/N77-1 -> 0.085373225 | P80: =+P77/O77-1 -> -0.066546011 | Q80: =+Q77/P77-1 -> 0.36495153 | S80: =+S77/Q77-1 -> -0.15406469 | T80: =+T77/S77-1 -> 0.14854043 | U80: =+U77/T77-1 -> -0.016306793 | V80: =+V77/U77-1 -> 0.018291986 | X80: =+X77/V77-1 -> 0.3733019 | Y80: =+Y77/X77-1 -> 0.080117724 | Z80: =+Z77/Y77-1 -> -0.12079927 | AA80: =+AA77/Z77-1 -> -0.16098485 | AC80: =+AC77/AA77-1 -> 0.61840755 | AD80: =+AD77/AC77-1 -> -0.022633614 | AE80: =+AE77/AD77-1 -> 0.026660612 | AF80: =+AF77/AE77-1 -> 0.2668857 | AH80: =+AH77/AF77-1 -> -0.021295696 | AI80: =+AI77/AH77-1 -> 0.055238483 | AJ80: =+AJ77/AI77-1 -> -0.0090303264 | AK80: =+AK77/AJ77-1 -> 0.35685395 | AM80: =+AM77/AK77-1 -> 0.039469904 | AN80: =+AN77/AL77-1 -> -0.010379256 | AO80: =+AO77/AM77-1 -> -0.064402446 | AP80: =+AP77/AO77-1 -> 0.22737176 | AR80: =+AR77/AP77-1 -> 0.14487303 | AS80: =+AS77/AQ77-1 -> 0.029636539 | AT80: =+AT77/AR77-1 -> -0.12217813 | AU80: =+AU77/AT77-1 -> -0.044757799 | AW80: =+AW77/AU77-1 -> 0.23881907 | AX80: =+AX77/AV77-1 -> 0.76961168 | AY80: =+AY77/AW77-1 -> -0.11232828 | AZ80: =+AZ77/AX77-1 -> -0.2666525 | BB80: =+BB77/AZ77-1 -> 0.027652329 | BC80: =+BC77/BA77-1 -> -0.05344507 | BD80: =+BD77/BB77-1 -> -0.12276744 | BE80: =+BE77/BC77-1 -> 0.12323315 | BG80: =+BG77/BE77-1 -> 0.089496638 | BH80: =+BH77/BG77-1 -> -0.10755984 | BI80: =+BI77/BH77-1 -> -0.088868123 | BJ80: =+BJ77/BI77-1 -> 0.21099459 | BL80: =+BL77/BJ77-1 -> -0.085709003 | BM80: =+BM77/BL77-1 -> -0.079480923 | BN80: =+BN77/BM77-1 -> 0.07928253 | BO80: =+BO77/BN77-1 -> -0.036933474 | BQ80: =+BQ77/BO77-1 -> -0.025608946 | BR80: =+BR77/BQ77-1 -> -0.086524089 | BS80: =+BS77/BR77-1 -> -0.048987095 | BT80: =+BT77/BS77-1 -> 0.059771509
B82: Beginning PP&E | I82: =+G16 -> 7922 | J82: =+I16 -> 7619 | K82: =+J16 -> 7607 | L82: =+K16 -> 7356 | M82: =+H16 -> 7922 | N82: =+L16 -> 7532 | O82: =+N16 -> 7611 | P82: =+O16 -> 7386 | Q82: =+P16 -> 8009 | R82: =+M16 -> 7532 | S82: =+Q16 -> 8088 | T82: =+S16 -> 8010 | U82: =+T16 -> 8287 | V82: =+U16 -> 7995 | W82: =+R16 -> 8088 | X82: =+V16 -> 8589 | Y82: =+X16 -> 9238 | Z82: =+Y16 -> 11184 | AA82: =+Z16 -> 11859 | AB82: =+W16 -> 8589 | AC82: =+AA16 -> 17523 | AD82: =+AC16 -> 32771 | AE82: =+AD16 -> 51860 | AF82: =+AE16 -> 51519 | AG82: =+AB16 -> 17523 | AH82: =+AF16 -> 50670 | AI82: =+AH16 -> 50075 | AJ82: =+AI16 -> 48904 | AK82: =+AJ16 -> 50305 | AL82: =+AG16 -> 50670 | AM82: =+AK16 -> 53114 | AN82: =+AM16 -> 51141 | AO82: =+AN16 -> 49431 | AP82: =+AO16 -> 49034 | AQ82: =+AL16 -> 53114 | AR82: =+AP16 -> 50225 | AS82: =+AR16 -> 49804 | AT82: =+AS16 -> 50533 | AU82: =+AT16 -> 55002 | AV82: =+AQ16 -> 50225 | AW82: =+AU16 -> 57891 | AX82: =+AW16 -> 56638 | AY82: =+AX16 -> 47104 | AZ82: =+AY16 -> 42449 | BA82: =+AV16 -> 57891 | BB82: =+AZ16 -> 39642 | BC82: =+BB16 -> 37266 | BD82: =+BC16 -> 34884 | BE82: =+BD16 -> 33936 | BF82: =+BA16 -> 39642 | BG82: =+BE16 -> 32245 | BH82: =+BG16 -> 31659 | BI82: =+BH16 -> 29639 | BJ82: =+BI16 -> 31966 | BK82: =+BF16 -> 32245 | BL82: =+BJ16 -> 31990 | BM82: =+BL16 -> 31510.497 | BN82: =+BM16 -> 31078.995 | BO82: =+BN16 -> 30695.167 | BP82: =+BK16 -> 31990 | BQ82: =+BO16 -> 30356.77 | BR82: =+BQ16 -> 30043.454 | BS82: =+BR16 -> 29765.104 | BT82: =+BS16 -> 29520.748 | BU82: =+BP16 -> 30356.77
B83: CapEx | H83: =+CF!H30*-1 -> 7082 | I83: =+CF!I30*-1 -> 573 | J83: =+CF!J30*-1 -> 622 | K83: =+CF!K30*-1 -> 1644 | L83: =+CF!L30*-1 -> 1297 | M83: =+SUM(I83:L83) -> 4136 | N83: =+CF!N30*-1 -> 1092 | O83: =+CF!O30*-1 -> 750 | P83: =+CF!P30*-1 -> 1465 | Q83: =+CF!Q30*-1 -> 1192 | R83: =+SUM(N83:Q83) -> 4499 | S83: =+CF!S30*-1 -> 1335 | T83: =+CF!T30*-1 -> 1243 | U83: =+CF!U30*-1 -> 928 | V83: =+CF!V30*-1 -> 1318 | W83: =+SUM(S83:V83) -> 4824 | X83: =+CF!X30*-1 -> 2147 | Y83: =+CF!Y30*-1 -> 3503 | Z83: =+CF!Z30*-1 -> 2754 | AA83: =+CF!AA30*-1 -> 4409 | AB83: =+SUM(X83:AA83) -> 12813 | AC83: =+CF!AC30*-1 -> 8463 | AD83: =+CF!AD30*-1 -> 9249 | AE83: =+CF!AE30*-1 -> 9341 | AF83: =+CF!AF30*-1 -> 2375 | AG83: =+SUM(AC83:AF83) -> 29428 | AH83: =+CF!AH30*-1 -> 2756 | AI83: =+CF!AI30*-1 -> 1199 | AJ83: =+CF!AJ30*-1 -> 3170 | AK83: =+CF!AK30*-1 -> 6677 | AL83: =+SUM(AH83:AK83) -> 13802 | AM83: =+CF!AM30*-1 -> 972 | AN83: =+CF!AN30*-1 -> 1699 | AO83: =+CF!AO30*-1 -> 2164 | AP83: =+CF!AP30*-1 -> 4175 | AQ83: =+SUM(AM83:AP83) -> 9010 | AR83: =+CF!AR30*-1 -> 3053 | AS83: =+CF!AS30*-1 -> 4171 | AT83: =+CF!AT30*-1 -> 5863 | AU83: =+CF!AU30*-1 -> 7295 | AV83: =+SUM(AR83:AU83) -> 20382 | AW83: =+CF!AW30*-1 -> 2285 | AX83: =+CF!AX30*-1 -> 1419 | AY83: =+CF!AY30*-1 -> 295 | AZ83: =+CF!AZ30*-1 -> 367 | BA83: =+SUM(AW83:AZ83) -> 4366 | BB83: =+CF!BB30*-1 -> 620 | BC83: =+CF!BC30*-1 -> 280 | BD83: =+CF!BD30*-1 -> 1342 | BE83: =+CF!BE30*-1 -> 1183 | BF83: =+SUM(BB83:BE83) -> 3425 | BG83: =+CF!BG30*-1 -> 1361 | BH83: =+CF!BH30*-1 -> 948 | BI83: =+CF!BI30*-1 -> 4137 | BJ83: =+CF!BJ30*-1 -> 1153 | BK83: =+SUM(BG83:BJ83) -> 7599 | BL83: =+BL84*BL$62 -> 2079.6973 | BM83: =+BM84*BM$62 -> 2089.3378 | BN83: =+BN84*BN$62 -> 2102.491 | BO83: =+BO84*BO$62 -> 2117.2168 | BP83: =+SUM(BL83:BO83) -> 8388.7429 | BQ83: =+BQ84*BQ$62 -> 2115.2259 | BR83: =+BR84*BR$62 -> 2125.1261 | BS83: =+BS84*BS$62 -> 2136.8518 | BT83: =+BT84*BT$62 -> 2151.452 | BU83: =+SUM(BQ83:BT83) -> 8528.6558
B84: CapEx (as a % of Sales) | H84: =+H83/H$62 -> 0.092117586 | I84: =+I83/I$62 -> 0.024309533 | J84: =+J83/J$62 -> 0.024117875 | K84: =+K83/K$62 -> 0.058067251 | L84: =+L83/L$62 -> 0.039478891 | M84: =+M83/M$62 -> 0.037421059 | N84: =+N83/N$62 -> 0.031382918 | O84: =+O83/O$62 -> 0.020124504 | ... BK84: =+BK83/BK$62 -> 0.0088381636 | BL84: 0.01 | BM84: 0.01 | BN84: 0.01 | BO84: 0.01 | BP84: =+BP83/BP$62 -> 0.01 | BQ84: 0.01 | BR84: 0.01 | BS84: 0.01 | BT84: 0.01 | BU84: =+BU83/BU$62 -> 0.01
B85: Depreciation and Amortization of PP&E | H85: =+'Billings & Recs'!H80 -> 3271 | I85: =+'Billings & Recs'!I80 -> 931 | J85: =+'Billings & Recs'!J80 -> 951 | K85: =+'Billings & Recs'!K80 -> 1054 | L85: =+'Billings & Recs'!L80 -> 1130 | M85: =+'Billings & Recs'!M80 -> 4066 | N85: =+'Billings & Recs'!N80 -> 1128 | O85: =+'Billings & Recs'!O80 -> 1125 | ... AP85: =+'Billings & Recs'!AP80 -> 3155 | AQ85: =+SUM(AM85:AP85) -> 12357 | AR85: =+'Billings & Recs'!AR80 -> 3303 | AS85: =+'Billings & Recs'!AS80 -> 3226 | AT85: =+'Billings & Recs'!AT80 -> 3479 | AU85: =+'Billings & Recs'!AU80 -> 3563 | AV85: =+SUM(AR85:AU85) -> 13571 | AW85: =+'Billings & Recs'!AW80 -> 3837 | AX85: =+'Billings & Recs'!AX80 -> 3749 | AY85: =+'Billings & Recs'!AY80 -> 3343 | AZ85: =+'Billings & Recs'!AZ80 -> 3118 | BA85: =+SUM(AW85:AZ85) -> 14047 | BB85: =2908 -> 2908 | BF85: =+SUM(BB85:BE85) -> 2908 | BG85: =2791 -> 2791 | BH85: =2791 -> 2791 | BI85: =2339 -> 2339 | BJ85: =2289 -> 2289 | BK85: =+SUM(BG85:BJ85) -> 10210 | BL85: =+BL86*BL82 -> 2559.2 | BM85: =+BM86*BM82 -> 2520.8398 | BN85: =+BN86*BN82 -> 2486.3196 | BO85: =+BO86*BO82 -> 2455.6133 | BP85: =+SUM(BL85:BO85) -> 10021.973 | BQ85: =+BQ86*BQ82 -> 2428.5416 | BR85: =+BR86*BR82 -> 2403.4764 | BS85: =+BS86*BS82 -> 2381.2083 | BT85: =+BT86*BT82 -> 2361.6598 | BU85: =+SUM(BQ85:BT85) -> 9574.8861
B86: Depreciation and Amortization of PP&E (as a % of PP&E) | I86: =+I85/I82 -> 0.11752083 | J86: =+J85/J82 -> 0.12481953 | K86: =+K85/K82 -> 0.13855659 | L86: =+L85/L82 -> 0.1536161 | M86: =+M85/M82 -> 0.51325423 | N86: =+N85/N82 -> 0.14976102 | O86: =+O85/O82 -> 0.14781238 | P86: =+P85/P82 -> 0.15461684 | ... BK86: =+BK85/BK82 -> 0.31663824 | BL86: 0.08 | BM86: 0.08 | BN86: 0.08 | BO86: 0.08 | BP86: =+BP85/BP82 -> 0.31328455 | BQ86: 0.08 | BR86: 0.08 | BS86: 0.08 | BT86: 0.08 | BU86: =+BU85/BU82 -> 0.31541189
B87: Acquisitions/(Write-offs) | G87: =+(G82+G83-G85-G89)*-1 -> 7922 | H87: =+(H82+H83-H85-H89)*-1 -> 4111 | I87: =+(I82+I83-I85-I89)*-1 -> 55 | J87: =+(J82+J83-J85-J89)*-1 -> 317 | K87: =+(K82+K83-K85-K89)*-1 -> -841 | L87: =+(L82+L83-L85-L89)*-1 -> 9 | M87: =+(M82+M83-M85-M89)*-1 -> -460 | N87: =+(N82+N83-N85-N89)*-1 -> 115 | ... BU87: =+(BU82+BU83-BU85-BU89)*-1 -> 0
D88: ______ | E88: ______ | F88: ______ | G88: ______ | H88: ______ | I88: ______ | J88: ______ | K88: ______ | L88: ______ | M88: ______ | N88: ______ | O88: ______ | P88: ______ | Q88: ______ | R88: ______ | S88: ______ | T88: ______ | U88: ______ | V88: ______ | W88: ______ | X88: ______ | Y88: ______ | Z88: ______ | AA88: ______ | AB88: ______ | AC88: ______ | AD88: ______ | AE88: ______ | AF88: ______ | AG88: ______ | AH88: ______ | AI88: ______ | AJ88: ______ | AK88: ______ | AL88: ______ | AM88: ______ | AN88: ______ | AO88: ______ | AP88: ______ | AQ88: ______ | AR88: ______ | AS88: ______ | AT88: ______ | AU88: ______ | AV88: ______ | AW88: ______ | AX88: ______ | AY88: ______ | AZ88: ______ | BA88: ______ | BB88: ______ | BC88: ______ | BD88: ______ | BE88: ______ | BF88: ______ | BG88: ______ | BH88: ______ | BI88: ______ | BJ88: ______ | BK88: ______ | BL88: ______ | BM88: ______ | BN88: ______ | BO88: ______ | BP88: ______ | BQ88: ______ | BR88: ______ | BS88: ______ | BT88: ______ | BU88: ______
B89: Ending PP&E | G89: =+G16 -> 7922 | H89: =+H16 -> 7922 | I89: =+I16 -> 7619 | J89: =+J16 -> 7607 | K89: =+K16 -> 7356 | L89: =+L16 -> 7532 | M89: =+M16 -> 7532 | N89: =+N16 -> 7611 | ... AL89: =+AL16 -> 53114 | AM89: =+AM82+AM83-AM85 -> 51092 | AN89: =+AN82+AN83-AN85 -> 49787 | AO89: =+AO82+AO83-AO85 -> 48440 | AP89: =+AP82+AP83-AP85 -> 50054 | AQ89: =+AQ82+AQ83-AQ85 -> 49767 | AR89: =+AR82+AR83-AR85 -> 49975 | AS89: =+AS82+AS83-AS85 -> 50749 | AT89: =+AT82+AT83-AT85 -> 52917 | ... BU89: =+BU82+BU83-BU85 -> 29310.54
B91: Beginning Intangibles | I91: =+G20 -> 1156 | J91: =+I20 -> 953 | K91: =+J20 -> 2767 | L91: =+K20 -> 2482 | M91: =+H20 -> 1156 | N91: =+L20 -> 11385 | O91: =+N20 -> 10802 | P91: =+O20 -> 10219 | Q91: =+P20 -> 9450 | R91: =+M20 -> 11385 | S91: =+Q20 -> 8946 | T91: =+S20 -> 8460 | U91: =+T20 -> 8294 | V91: =+U20 -> 17208 | W91: =+R20 -> 8946 | X91: =+V20 -> 16640 | Y91: =+X20 -> 16316 | Z91: =+Y20 -> 16002 | AA91: =+Z20 -> 16023 | AB91: =+W20 -> 16640 | AC91: =+AA20 -> 23955 | AD91: =+AC20 -> 23979 | AE91: =+AD20 -> 29726 | AF91: =+AE20 -> 29183 | AG91: =+AB20 -> 23955 | AH91: =+AF20 -> 28561 | AI91: =+AH20 -> 27867 | AJ91: =+AI20 -> 47706 | AK91: =+AJ20 -> 45942 | AL91: =+AG20 -> 28561 | AM91: =+AK20 -> 44296 | AN91: =+AM20 -> 52708 | AO91: =+AN20 -> 54179 | AP91: =+AO20 -> 115746 | AQ91: =+AL20 -> 44296 | AR91: =+AP20 -> 111591 | AS91: =+AR20 -> 108246 | AT91: =+AS20 -> 105785 | AU91: =+AT20 -> 103660 | AV91: =+AQ20 -> 111591 | AW91: =+AU20 -> 101269 | AX91: =+AW20 -> 111432 | AY91: =+AX20 -> 104698 | AZ91: =+AY20 -> 99993 | BA91: =+AV20 -> 101269 | BB91: =+AZ20 -> 94546 | BC91: =+BB20 -> 88844 | BD91: =+BC20 -> 84019 | BE91: =+BD20 -> 90748 | BF91: =+BA20 -> 94546 | BG91: =+BE20 -> 85719 | BH91: =+BG20 -> 79763 | BI91: =+BH20 -> 74981 | BJ91: =+BI20 -> 69877 | BK91: =+BF20 -> 85719 | BL91: =+BJ20 -> 65105 | BM91: =+BL20 -> 57292.4 | BN91: =+BM20 -> 50417.312 | BO91: =+BN20 -> 44367.235 | BP91: =+BK20 -> 65105 | BQ91: =+BO20 -> 39043.166 | BR91: =+BQ20 -> 34357.986 | BS91: =+BR20 -> 30235.028 | BT91: =+BS20 -> 26606.825 | BU91: =+BP20 -> 39043.166
B92: Purchases of Intangibles
B93: Purchases of Intangibles (as a % of Sales) | I93: =+I92/I$62 -> 0 | J93: =+J92/J$62 -> 0 | K93: =+K92/K$62 -> 0 | L93: =+L92/L$62 -> 0 | M93: =+M92/M$62 -> 0 | N93: =+N92/N$62 -> 0 | O93: =+O92/O$62 -> 0 | P93: =+P92/P$62 -> 0 | ... BK93: =+BK92/BK$62 -> 0 | BL93: 0 | BM93: 0 | BN93: 0 | BO93: 0 | BP93: =+BP92/BP$62 -> 0 | BQ93: 0 | BR93: 0 | BS93: 0 | BT93: 0 | BU93: =+BU92/BU$62 -> 0
B94: Amortization of Intangibles | H94: =+'Billings & Recs'!H81 -> 869 | I94: =+'Billings & Recs'!I81 -> 203 | J94: =+'Billings & Recs'!J81 -> 276 | K94: =+'Billings & Recs'!K81 -> 285 | L94: =+'Billings & Recs'!L81 -> 522 | M94: =+'Billings & Recs'!M81 -> 1286 | N94: =+'Billings & Recs'!N81 -> 583 | O94: =+'Billings & Recs'!O81 -> 583 | ... AK94: =+'Billings & Recs'!AK81 -> 3369 | AL94: =+SUM(AH94:AK94) -> 11044 | AM94: =+'Billings & Recs'!AM81 -> 3746 | AN94: =+'Billings & Recs'!AN81 -> 3975 | AO94: =+'Billings & Recs'!AO81 -> 6590 | AP94: =+'Billings & Recs'!AP81 -> 6590 | AQ94: =+SUM(AM94:AP94) -> 20901 | AR94: =+'Billings & Recs'!AR81 -> 6866 | AS94: =+'Billings & Recs'!AS81 -> 6997 | AT94: =+'Billings & Recs'!AT81 -> 6716 | AU94: =+'Billings & Recs'!AU81 -> 6888 | AV94: =+SUM(AR94:AU94) -> 27467 | AW94: =+'Billings & Recs'!AW81 -> 7213 | AX94: =+'Billings & Recs'!AX81 -> 8080 | AY94: =+'Billings & Recs'!AY81 -> 8306 | AZ94: =+'Billings & Recs'!AZ81 -> 8293 | BA94: =+SUM(AW94:AZ94) -> 31892 | BB94: =8440 -> 8440 | BF94: =+SUM(BB94:BE94) -> 8440 | BG94: =8874 -> 8874 | BH94: =8874 -> 8874 | BI94: =8861 -> 8861 | BJ94: =8892 -> 8892 | BK94: =+SUM(BG94:BJ94) -> 35501 | BL94: =+BL95*BL91 -> 7812.6 | BM94: =+BM95*BM91 -> 6875.088 | BN94: =+BN95*BN91 -> 6050.0774 | BO94: =+BO95*BO91 -> 5324.0681 | BP94: =+SUM(BL94:BO94) -> 26061.834 | BQ94: =+BQ95*BQ91 -> 4685.18 | BR94: =+BR95*BR91 -> 4122.9584 | BS94: =+BS95*BS91 -> 3628.2034 | BT94: =+BT95*BT91 -> 3192.819 | BU94: =+SUM(BQ94:BT94) -> 15629.161
B95: Amortization (as a % of Intangibles) | I95: =+I94/I91 -> 0.17560554 | J95: =+J94/J91 -> 0.28961175 | K95: =+K94/K91 -> 0.10299964 | L95: =+L94/L91 -> 0.21031426 | M95: =+M94/M91 -> 1.1124567 | N95: =+N94/N91 -> 0.051207729 | O95: =+O94/O91 -> 0.053971487 | P95: =+P94/P91 -> 0.075251982 | ... BK95: =+BK94/BK91 -> 0.41415555 | BL95: 0.12 | BM95: 0.12 | BN95: 0.12 | BO95: 0.12 | BP95: =+BP94/BP91 -> 0.40030464 | BQ95: 0.12 | BR95: 0.12 | BS95: 0.12 | BT95: 0.12 | BU95: =+BU94/BU91 -> 0.40030464
B96: Acquisitions/(Write-offs) | G96: =+(G91+G92-G94-G98)*-1 -> 1156 | H96: =+(H91+H92-H94-H98)*-1 -> 2025 | I96: =+(I91+I92-I94-I98)*-1 -> 0 | J96: =+(J91+J92-J94-J98)*-1 -> 2090 | K96: =+(K91+K92-K94-K98)*-1 -> 0 | L96: =+(L91+L92-L94-L98)*-1 -> 9425 | M96: =+(M91+M92-M94-M98)*-1 -> 11515 | N96: =+(N91+N92-N94-N98)*-1 -> 0 | ... BU96: =+(BU91+BU92-BU94-BU98)*-1 -> 0
D97: ______ | E97: ______ | F97: ______ | G97: ______ | H97: ______ | I97: ______ | J97: ______ | K97: ______ | L97: ______ | M97: ______ | N97: ______ | O97: ______ | P97: ______ | Q97: ______ | R97: ______ | S97: ______ | T97: ______ | U97: ______ | V97: ______ | W97: ______ | X97: ______ | Y97: ______ | Z97: ______ | AA97: ______ | AB97: ______ | AC97: ______ | AD97: ______ | AE97: ______ | AF97: ______ | AG97: ______ | AH97: ______ | AI97: ______ | AJ97: ______ | AK97: ______ | AL97: ______ | AM97: ______ | AN97: ______ | AO97: ______ | AP97: ______ | AQ97: ______ | AR97: ______ | AS97: ______ | AT97: ______ | AU97: ______ | AV97: ______ | AW97: ______ | AX97: ______ | AY97: ______ | AZ97: ______ | BA97: ______ | BB97: ______ | BC97: ______ | BD97: ______ | BE97: ______ | BF97: ______ | BG97: ______ | BH97: ______ | BI97: ______ | BJ97: ______ | BK97: ______ | BL97: ______ | BM97: ______ | BN97: ______ | BO97: ______ | BP97: ______ | BQ97: ______ | BR97: ______ | BS97: ______ | BT97: ______ | BU97: ______
B98: Ending Intangibles | G98: =+G20 -> 1156 | H98: =+H20 -> 1156 | I98: =+I20 -> 953 | J98: =+J20 -> 2767 | K98: =+K20 -> 2482 | L98: =+L20 -> 11385 | M98: =+M20 -> 11385 | N98: =+N20 -> 10802 | ... AK98: =+AK20 -> 44296 | AL98: =+AL91+AL92-AL94 -> 17517 | AM98: =+AM20 -> 52708 | AN98: =+AN91+AN92-AN94 -> 48733 | AO98: =+AO91+AO92-AO94 -> 47589 | AP98: =+AP91+AP92-AP94 -> 109156 | AQ98: =+AQ91+AQ92-AQ94 -> 23395 | AR98: =+AR20 -> 108246 | AS98: =+AS91+AS92-AS94 -> 101249 | AT98: =+AT91+AT92-AT94 -> 99069 | AU98: =+AU91+AU92-AU94 -> 96772 | AV98: =+AV91+AV92-AV94 -> 84124 | AW98: =+AW20 -> 111432 | AX98: =+AX91+AX92-AX94 -> 103352 | AY98: =+AY91+AY92-AY94 -> 96392 | AZ98: =+AZ91+AZ92-AZ94 -> 91700 | BA98: =+BA91+BA92-BA94 -> 69377 | BB98: =+BB91+BB92-BB94 -> 86106 | BC98: =+BC91+BC92-BC94 -> 88844 | BD98: =+BD91+BD92-BD94 -> 84019 | BE98: =+BE91+BE92-BE94 -> 90748 | ... BU98: =+BU91+BU92-BU94 -> 23414.006
B100: Accounts Payable | G100: =+G28 -> 3536 | H100: =+H28 -> 3536 | I100: =+I28 -> 2892 | J100: =+J28 -> 2990 | K100: =+K28 -> 2868 | L100: =+L28 -> 2038 | M100: =+M28 -> 2038 | N100: =+N28 -> 1657 | ... BU100: =+BU28 -> 14235.823
B101: % of COGS | G101: =+G100/G$63 -> 0.61517049 | H101: =+H100/H$63 -> 0.19420035 | I101: =+I100/I$63 -> 0.46346154 | J101: =+J100/J$63 -> 0.46726051 | K101: =+K100/K$63 -> 0.42959856 | L101: =+L100/L$63 -> 0.24899206 | M101: =+M100/M$63 -> 0.074109091 | N101: =+N100/N$63 -> 0.20383811 | ... BU101: =+BU100/BU$63 -> 0.062884761
B102: Yr-Yr Growth | L102: =+L100/G100-1 -> -0.42364253 | M102: =+M100/H100-1 -> -0.42364253 | N102: =+N100/I100-1 -> -0.42704011 | O102: =+O100/J100-1 -> 0.40468227 | P102: =+P100/K100-1 -> -0.067294282 | Q102: =+Q100/L100-1 -> 0.96859666 | R102: =+R100/M100-1 -> 0.96859666 | S102: =+S100/N100-1 -> 1.1092336 | ... BU102: =+BU100/BP100-1 -> -0.035229152
B103: Q-Q Growth | I103: =+I100/G100-1 -> -0.1821267 | J103: =+J100/I100-1 -> 0.033886584 | K103: =+K100/J100-1 -> -0.040802676 | L103: =+L100/K100-1 -> -0.28940028 | N103: =+N100/L100-1 -> -0.18694799 | O103: =+O100/N100-1 -> 1.5347013 | P103: =+P100/O100-1 -> -0.36309524 | Q103: =+Q100/P100-1 -> 0.49981308 | S103: =+S100/Q100-1 -> -0.12886341 | T103: =+T100/S100-1 -> -0.35422031 | U103: =+U100/T100-1 -> 0.58041648 | V103: =+V100/U100-1 -> -0.37202131 | X103: =+X100/V100-1 -> 1.5308036 | Y103: =+Y100/X100-1 -> -0.18645264 | Z103: =+Z100/Y100-1 -> -0.40026019 | AA103: =+AA100/Z100-1 -> 1.5480839 | AC103: =+AC100/AA100-1 -> -0.10655505 | AD103: =+AD100/AC100-1 -> 1.060505 | AE103: =+AE100/AD100-1 -> -0.49526012 | AF103: =+AF100/AE100-1 -> 0.043823485 | AH103: =+AH100/AF100-1 -> 0.4719134 | AI103: =+AI100/AH100-1 -> -0.29656132 | AJ103: =+AJ100/AI100-1 -> 0.27620797 | AK103: =+AK100/AJ100-1 -> -0.57267796 | AM103: =+AM100/AK100-1 -> 0.11295337 | AN103: =+AN100/AL100-1 -> 11.122539 | AO103: =+AO100/AM100-1 -> 11.178305 | AP103: =+AP100/AN100-1 -> -0.9247537 | AR103: =+AR100/AP100-1 -> 2.4544164 | AS103: =+AS100/AQ100-1 -> 0.94035785 | AT103: =+AT100/AR100-1 -> 0.13985037 | AU103: =+AU100/AS100-1 -> 0.50102459 | AW103: =+AW100/AU100-1 -> -0.17357387 | AX103: =+AX100/AV100-1 -> -0.12345197 | AY103: =+AY100/AW100-1 -> 0.056165192 | AZ103: =+AZ100/AX100-1 -> 0.75903883 | BB103: =+BB100/AZ100-1 -> -0.27169239 | BC103: =+BC100/BA100-1 -> -0.18922337 | BD103: =+BD100/BB100-1 -> -0.47855158 | BE103: =+BE100/BC100-1 -> 0.474883 | BG103: =+BG100/BE100-1 -> -0.34852972 | BH103: =+BH100/BG100-1 -> 0.29428479 | BI103: =+BI100/BH100-1 -> -0.023333124 | BJ103: =+BJ100/BI100-1 -> -0.29092544 | BL103: =+BL100/BJ100-1 -> 0.13715011 | BM103: =+BM100/BL100-1 -> 0.34851325 | BN103: =+BN100/BM100-1 -> -0.078767138 | BO103: =+BO100/BN100-1 -> -0.053964236 | BQ103: =+BQ100/BO100-1 -> -0.16524543 | BR103: =+BR100/BQ100-1 -> -0.046238916 | BS103: =+BS100/BR100-1 -> 0.34934173 | BT103: =+BT100/BS100-1 -> -0.10194318
B104: Days Payable | G104: =+G58 -> 55.365344 | H104: =+H58 -> 17.478032 | I104: =+I58 -> 41.711538 | J104: =+J58 -> 42.053446 | K104: =+K58 -> 38.663871 | L104: =+L58 -> 22.409285 | M104: =+M58 -> 36.484364 | N104: =+N58 -> 18.34543 | ... BK104: =+BK58 -> 23.674475 | BL104: 21 | BM104: 28 | BN104: 25 | BO104: 23 | BP104: =+BP58 -> 20.904978 | BQ104: 20 | BR104: 19 | BS104: 25 | BT104: 22 | BU104: =+BU58 -> 23.051843
B106: Accrued Expenses | G106: =+G29 -> 11907 | H106: =+H29 -> 11907 | I106: =+I29 -> 7956 | J106: =+J29 -> 12765 | K106: =+K29 -> 15725 | L106: =+L29 -> 24707 | M106: =+M29 -> 24707 | N106: =+N29 -> 14424 | ... BU106: =+BU29 -> 103780
B107: % COGS + OPEX | G107: =+G106/(G$63+G$64) -> 0.39680741 | H107: =+H106/(H$63+H$64) -> 0.11502792 | I107: =+I106/(I$63+I$64) -> 0.27102708 | J107: =+J106/(J$63+J$64) -> 0.3880411 | K107: =+K106/(K$63+K$64) -> 0.43603039 | L107: =+L106/(L$63+L$64) -> 0.54934964 | M107: =+M106/(M$63+M$64) -> 0.17242655 | N107: =+N106/(N$63+N$64) -> 0.32550267 | ... BK107: =+BK106/(BK$63+BK$64) -> 0.13396367 | BL107: 0.37 | BM107: 0.4 | BN107: 0.45 | BO107: 0.5 | BP107: =+BP106/(BP$63+BP$64) -> 0.12357783 | BQ107: 0.37 | BR107: 0.4 | BS107: 0.45 | BT107: 0.56 | BU107: =+BU106/(BU$63+BU$64) -> 0.14095463
B108: Yr-Yr Growth | L108: =+L106/G106-1 -> 1.0749979 | M108: =+M106/H106-1 -> 1.0749979 | N108: =+N106/I106-1 -> 0.81297134 | O108: =+O106/J106-1 -> 0.55095966 | P108: =+P106/K106-1 -> 0.41341812 | Q108: =+Q106/L106-1 -> -0.048893026 | R108: =+R106/M106-1 -> -0.048893026 | S108: =+S106/N106-1 -> 0.13325014 | ... BU108: =+BU106/BP106-1 -> 0.15543336
B109: Q-Q Growth | I109: =+I106/G106-1 -> -0.33182162 | J109: =+J106/I106-1 -> 0.60444947 | K109: =+K106/J106-1 -> 0.23188406 | L109: =+L106/K106-1 -> 0.57119237 | N109: =+N106/L106-1 -> -0.41619784 | O109: =+O106/N106-1 -> 0.37257349 | P109: =+P106/O106-1 -> 0.12263865 | Q109: =+Q106/P106-1 -> 0.057275263 | S109: =+S106/Q106-1 -> -0.30439593 | T109: =+T106/S106-1 -> 0.26434602 | U109: =+U106/T106-1 -> 0.14854599 | V109: =+V106/U106-1 -> 0.25239078 | X109: =+X106/V106-1 -> -0.38199677 | Y109: =+Y106/X106-1 -> 0.18833007 | Z109: =+Z106/Y106-1 -> 0.25467204 | AA109: =+AA106/Z106-1 -> 0.36448598 | AC109: =+AC106/AA106-1 -> -0.32946276 | AD109: =+AD106/AC106-1 -> 0.31948767 | AE109: =+AE106/AD106-1 -> 0.0031751792 | AF109: =+AF106/AE106-1 -> 0.23654066 | AH109: =+AH106/AF106-1 -> -0.35433071 | AI109: =+AI106/AH106-1 -> 0.36543834 | AJ109: =+AJ106/AI106-1 -> 0.32821789 | AK109: =+AK106/AJ106-1 -> 0.28400125 | AM109: =+AM106/AK106-1 -> -0.22489745 | AN109: =+AN106/AL106-1 -> -0.09799439 | AO109: =+AO106/AM106-1 -> 0.21271389 | AP109: =+AP106/AN106-1 -> 0.48508978 | AR109: =+AR106/AP106-1 -> -0.316122 | AS109: =+AS106/AQ106-1 -> -0.19694989 | AT109: =+AT106/AR106-1 -> 0.14026052 | AU109: =+AU106/AS106-1 -> 0.2103756 | AW109: =+AW106/AU106-1 -> -0.28342839 | AX109: =+AX106/AV106-1 -> -0.13510821 | AY109: =+AY106/AW106-1 -> 0.10153793 | AZ109: =+AZ106/AX106-1 -> 0.21643918 | BB109: =+BB106/AZ106-1 -> -0.28268769 | BC109: =+BC106/BA106-1 -> -0.20413308 | BD109: =+BD106/BB106-1 -> 0.35828727 | BE109: =+BE106/BC106-1 -> 0.32063294 | BG109: =+BG106/BE106-1 -> -0.21783293 | BH109: =+BH106/BG106-1 -> 0.12478044 | BI109: =+BI106/BH106-1 -> 0.0308992 | BJ109: =+BJ106/BI106-1 -> 0.20436062 | BL109: =+BL106/BJ106-1 -> -0.28383433 | BM109: =+BM106/BL106-1 -> 0.040390111 | BN109: =+BN106/BM106-1 -> 0.11301011 | BO109: =+BO106/BN106-1 -> 0.11659887 | BQ109: =+BQ106/BO106-1 -> -0.24617565 | BR109: =+BR106/BQ106-1 -> 0.086295678 | BS109: =+BS106/BR106-1 -> 0.12619949 | BT109: =+BT106/BS106-1 -> 0.25288543
B111: ST Deferred Revenue | G111: =+G32 -> 58164 | H111: =+H32 -> 58164 | I111: =+I32 -> 60539 | J111: =+J32 -> 66040 | K111: =+K32 -> 74347 | L111: =+L32 -> 87917 | M111: =+M32 -> 87917 | N111: =+N32 -> 90081 | ... BU111: =+BU32 -> 469381.66
B112: Growth Rate Input | BL112: 0 | BM112: 0.01 | BN112: 0.01 | BO112: 0.02 | BQ112: 0.02 | BR112: 0.02 | BS112: 0.02 | BT112: 0.02
B113: Yr-Yr Growth (Deferred Revenue) | L113: =+L32/G32-1 -> 0.51153635 | M113: =+M32/H32-1 -> 0.51153635 | N113: =+N32/I32-1 -> 0.48798295 | O113: =+O32/J32-1 -> 0.5045427 | P113: =+P32/K32-1 -> 0.4077636 | Q113: =+Q32/L32-1 -> 0.32969733 | R113: =+R32/M32-1 -> 0.32969733 | S113: =+S32/N32-1 -> 0.29399096 | ... BU113: =+BU32/BP32-1 -> 0.02
B115: LT Deferred Revenue | G115: =+G39 -> 26892 | H115: =+H39 -> 26892 | I115: =+I39 -> 28104 | J115: =+J39 -> 31471 | K115: =+K39 -> 35805 | L115: =+L39 -> 42400 | M115: =+M39 -> 42400 | N115: =+N39 -> 41776 | ... BU115: =+BU39 -> 24452.493
B116: Growth Rate Input | BL116: -0.05 | BM116: -0.02 | BN116: -0.02 | BO116: -0.01 | BQ116: -0.05 | BR116: -0.02 | BS116: -0.02 | BT116: -0.01
B117: Yr-Yr Growth | L117: =+L39/G39-1 -> 0.57667708 | M117: =+M39/H39-1 -> 0.57667708 | N117: =+N39/I39-1 -> 0.48647879 | O117: =+O39/J39-1 -> 0.44139049 | P117: =+P39/K39-1 -> 0.24566401 | Q117: =+Q39/L39-1 -> 0.23018868 | R117: =+R39/M39-1 -> 0.23018868 | S117: =+S39/N39-1 -> 0.22278342 | ... BU117: =+BU39/BP39-1 -> -0.0967438
B118: Q-Q Growth | I118: =+I39/G39-1 -> 0.045069166 | J118: =+J39/I39-1 -> 0.11980501 | K118: =+K39/J39-1 -> 0.13771409 | L118: =+L39/K39-1 -> 0.18419215 | N118: =+N39/L39-1 -> -0.014716981 | O118: =+O39/N39-1 -> 0.085838759 | P118: =+P39/O39-1 -> -0.016776156 | Q118: =+Q39/P39-1 -> 0.1694805 | S118: =+S39/Q39-1 -> -0.020648006 | T118: =+T39/S39-1 -> 0.063837284 | U118: =+U39/T39-1 -> 0.021750331 | V118: =+V39/U39-1 -> 0.5015128 | X118: =+X39/V39-1 -> -0.059047893 | Y118: =+Y39/X39-1 -> -0.097947737 | Z118: =+Z39/Y39-1 -> -0.10013283 | AA118: =+AA39/Z39-1 -> -0.077952261 | AC118: =+AC39/AA39-1 -> -0.11414265 | AD118: =+AD39/AC39-1 -> -0.13592494 | AE118: =+AE39/AD39-1 -> -0.18520826 | AF118: =+AF39/AE39-1 -> -0.010759148 | AH118: =+AH39/AF39-1 -> -0.12656655 | AI118: =+AI39/AH39-1 -> 0.05179988 | AJ118: =+AJ39/AI39-1 -> -0.079567308 | AK118: =+AK39/AJ39-1 -> 0.023929224 | AM118: =+AM39/AK39-1 -> -0.080726925 | AN118: =+AN39/AM39-1 -> 0.044775084 | AO118: =+AO39/AN39-1 -> -0.073662196 | AP118: =+AP39/AO39-1 -> 0.18459058 | AR118: =+AR39/AP39-1 -> -0.073814134 | AS118: =+AS39/AR39-1 -> 0.081068722 | AT118: =+AT39/AS39-1 -> -0.043476947 | AU118: =+AU39/AT39-1 -> -0.019552102 | AW118: =+AW39/AU39-1 -> 0.01755799 | AX118: =+AX39/AW39-1 -> -0.04815577 | AY118: =+AY39/AX39-1 -> -0.023948909 | AZ118: =+AZ39/AY39-1 -> 0.11017585 | BB118: =+BB39/AZ39-1 -> -0.10344722 | BC118: =+BC39/BB39-1 -> -0.058034033 | BD118: =+BD39/BC39-1 -> 0.026424833 | BE118: =+BE39/BD39-1 -> -0.041113354 | BG118: =+BG39/BE39-1 -> 0.016470936 | BH118: =+BH39/BG39-1 -> 0.060274669 | BI118: =+BI39/BH39-1 -> -0.028818148 | BJ118: =+BJ39/BI39-1 -> 0.057476537 | BL118: =+BL39/BJ39-1 -> -0.05 | BM118: =+BM39/BL39-1 -> -0.02 | BN118: =+BN39/BM39-1 -> -0.02 | BO118: =+BO39/BN39-1 -> -0.01 | BQ118: =+BQ39/BO39-1 -> -0.05 | BR118: =+BR39/BQ39-1 -> -0.02 | BS118: =+BS39/BR39-1 -> -0.02 | BT118: =+BT39/BS39-1 -> -0.01
B120: Total Deferred Revenue, End of Period | G120: =+G115+G111 -> 85056 | H120: =+H115+H111 -> 85056 | I120: =+I115+I111 -> 88643 | J120: =+J115+J111 -> 97511 | K120: =+K115+K111 -> 110152 | L120: =+L115+L111 -> 130317 | M120: =+M115+M111 -> 130317 | N120: =+N115+N111 -> 131857 | ... BU120: =+BU115+BU111 -> 493834.15
...

Sheet CF
B3: Rapid7 Inc.—Cash Flow
B4: (Thousands Of Dollars, Except Per-Share Data) | D4: Mar | E4: June | F4: Sept | G4: Dec | H4: Dec | I4: Mar | J4: June | K4: Sept | L4: Dec | M4: Dec | N4: Mar | O4: June | P4: Sept | Q4: Dec | R4: Dec | S4: Mar | T4: June | U4: Sept | V4: Dec | W4: Dec | X4: Mar | Y4: June | Z4: Sept | AA4: Dec | AB4: Dec | AC4: Mar | AD4: June | AE4: Sept | AF4: Dec | AG4: Dec | AH4: Mar | AI4: June | AJ4: Sept | AK4: Dec | AL4: Dec | AM4: Mar | AN4: June | AO4: Sept | AP4: Dec | AQ4: Dec | AR4: Mar | AS4: June | AT4: Sept | AU4: Dec | AV4: Dec | AW4: Mar | AX4: June | AY4: Sept | AZ4: Dec | BA4: Dec | BB4: Mar | BC4: June | BD4: Sept | BE4: Dec | BF4: Dec | BG4: Mar | BH4: June | BI4: Sept | BJ4: Dec | BK4: Dec | BL4: Mar | BM4: June | BN4: Sept | BO4: Dec | BP4: Dec | BQ4: Mar | BR4: June | BS4: Sept | BT4: Dec | BU4: Dec
D5: =+BS!D5 -> 2014A | E5: =+BS!E5 -> 2014A | F5: =+BS!F5 -> 2014A | G5: =+BS!G5 -> 2014A | H5: =+BS!H5 -> 2014A | I5: =+BS!I5 -> 2015A | J5: =+BS!J5 -> 2015A | K5: =+BS!K5 -> 2015A | ... AN5: =+BS!AN5 -> 2021A | AO5: 2021A | AP5: =+BS!AP5 -> 2021A | AQ5: =+BS!AQ5 -> 2021A | AR5: =+BS!AR5 -> 2022A | AS5: =+BS!AS5 -> 2022A | AT5: =+BS!AT5 -> 2022A | AU5: =+BS!AU5 -> 2022A | AV5: =+BS!AV5 -> 2022A | AW5: =+BS!AW5 -> 2023A | ... BU5: =+BS!BU5 -> 2027E
B6: Cash from Operating Activities
A7: x | B7: Net Income(Loss) | H7: -32627 | I7: -7682 | J7: -9244 | K7: -11825 | L7: -21106 | M7: -49857 | N7: -15580 | O7: -13452 | P7: -10194 | Q7: -9774 | R7: -49000 | S7: -10545 | T7: -11637 | U7: -10284 | V7: -13004 | W7: =+SUM(S7:V7) -> -45470 | X7: -16361 | Y7: -14333 | Z7: -11831 | AA7: -13020 | AB7: =+SUM(X7:AA7) -> -55545 | AC7: -11673 | AD7: -13420 | AE7: -14406 | AF7: -14346 | AG7: =+SUM(AC7:AF7) -> -53845 | AH7: -22924 | AI7: -21466 | AJ7: =-25541 -> -25541 | AK7: =-28918 -> -28918 | AL7: =+SUM(AH7:AK7) -> -98849 | AM7: =-29845 -> -29845 | AN7: =-34164 -> -34164 | AO7: =-37700 -> -37700 | AP7: =-44625 -> -44625 | AQ7: =+SUM(AM7:AP7) -> -146334 | AR7: =-44999 -> -44999 | AS7: =-39606 -> -39606 | AT7: =-28727 -> -28727 | AU7: =-11385 -> -11385 | AV7: =SUM(AR7:AU7) -> -124717 | AW7: =-25915 -> -25915 | AX7: =-66782 -> -66782 | AY7: =-76611 -> -76611 | AZ7: =20048 -> 20048 | BA7: =SUM(AW7:AZ7) -> -149260 | BB7: =2258 -> 2258 | BC7: =8195 -> 8195 | BD7: =16554 -> 16554 | BE7: =2172 -> 2172 | BF7: =SUM(BB7:BE7) -> 29179 | BG7: =2105 -> 2105 | BH7: =8338 -> 8338 | BI7: =9809 -> 9809 | BJ7: =3129 -> 3129 | BK7: =SUM(BG7:BJ7) -> 23381 | BL7: =+'Billings & Recs'!BL74 -> -12667.008 | BM7: =+'Billings & Recs'!BM74 -> -3083.4566 | BN7: =+'Billings & Recs'!BN74 -> -2278.0267 | BO7: =+'Billings & Recs'!BO74 -> -1923.9633 | BP7: =SUM(BL7:BO7) -> -19952.455 | BQ7: =+'Billings & Recs'!BQ74 -> -3373.3508 | BR7: =+'Billings & Recs'!BR74 -> -1284.8495 | BS7: =+'Billings & Recs'!BS74 -> -2646.4395 | BT7: =+'Billings & Recs'!BT74 -> -2649.9539 | BU7: =SUM(BQ7:BT7) -> -9954.5936
A8: x | B8: Depreciation and Amortization | H8: 4140 | I8: 1134 | J8: 1227 | K8: 1339 | L8: 1652 | M8: 5352 | N8: 1711 | O8: 1708 | P8: 1911 | Q8: 1395 | R8: 6725 | S8: 1624 | T8: 1613 | U8: 2067 | V8: 2324 | W8: =+SUM(S8:V8) -> 7628 | X8: 2399 | Y8: 2678 | Z8: 2660 | AA8: 3360 | AB8: =+SUM(X8:AA8) -> 11097 | AC8: 3427 | AD8: 3944 | AE8: 4598 | AF8: 4559 | AG8: =+SUM(AC8:AF8) -> 16528 | AH8: 4843 | AI8: 5576 | AJ8: =5928 -> 5928 | AK8: =6284 -> 6284 | AL8: =+SUM(AH8:AK8) -> 22631 | AM8: =6740 -> 6740 | AN8: =7028 -> 7028 | AO8: =9745 -> 9745 | AP8: =9988 -> 9988 | AQ8: =+SUM(AM8:AP8) -> 33501 | AR8: =10169 -> 10169 | AS8: =10223 -> 10223 | AT8: =10195 -> 10195 | AU8: =10451 -> 10451 | AV8: =+SUM(AR8:AU8) -> 41038 | AW8: =11050 -> 11050 | AX8: =11829 -> 11829 | AY8: =11649 -> 11649 | AZ8: =11411 -> 11411 | BA8: =+SUM(AW8:AZ8) -> 45939 | BB8: =11348 -> 11348 | BC8: =10871 -> 10871 | BD8: =11238 -> 11238 | BE8: =11436 -> 11436 | BF8: =+SUM(BB8:BE8) -> 44893 | BG8: =11665 -> 11665 | BH8: =11390 -> 11390 | BI8: =11200 -> 11200 | BJ8: =11181 -> 11181 | BK8: =+SUM(BG8:BJ8) -> 45436 | BL8: =+BS!BL85+BS!BL94 -> 10371.8 | BM8: =+BS!BM85+BS!BM94 -> 9395.9278 | BN8: =+BS!BN85+BS!BN94 -> 8536.3971 | BO8: =+BS!BO85+BS!BO94 -> 7779.6815 | BP8: =+SUM(BL8:BO8) -> 36083.806 | BQ8: =+BS!BQ85+BS!BQ94 -> 7113.7216 | BR8: =+BS!BR85+BS!BR94 -> 6526.4347 | BS8: =+BS!BS85+BS!BS94 -> 6009.4117 | BT8: =+BS!BT85+BS!BT94 -> 5554.4788 | BU8: =+SUM(BQ8:BT8) -> 25204.047
B9: Amortization of Debt Discount | H9: 553 | I9: 138 | J9: 138 | K9: 853 | L9: 0 | M9: 1129 | N9: 0 | O9: 0 | P9: 0 | Q9: 0 | R9: 0 | S9: 0 | T9: 0 | U9: 0 | V9: 0 | W9: =+SUM(S9:V9) -> 0 | X9: 0 | Y9: 0 | Z9: 1296 | AA9: 2535 | AB9: =+SUM(X9:AA9) -> 3831 | AC9: 2510 | AD9: 2594 | AE9: 2679 | AF9: 2730 | AG9: =+SUM(AC9:AF9) -> 10513 | AH9: 2743 | AI9: 4264 | AJ9: =5206 -> 5206 | AK9: =5305 -> 5305 | AL9: =+SUM(AH9:AK9) -> 17518 | AM9: =658 -> 658 | AN9: =1133 -> 1133 | AO9: =1095 -> 1095 | AP9: =1096 -> 1096 | AQ9: =+SUM(AM9:AP9) -> 3982 | AR9: =979 -> 979 | AS9: =1011 -> 1011 | AT9: =1046 -> 1046 | AU9: =1049 -> 1049 | AV9: =+SUM(AR9:AU9) -> 4085 | AW9: =994 -> 994 | AX9: =1026 -> 1026 | AY9: =1041 -> 1041 | AZ9: =1077 -> 1077 | BA9: =+SUM(AW9:AZ9) -> 4138 | BB9: =1053 -> 1053 | BC9: =1055 -> 1055 | BD9: =1217 -> 1217 | BE9: =1122 -> 1122 | BF9: =+SUM(BB9:BE9) -> 4447 | BG9: =1019 -> 1019 | BH9: =999 -> 999 | BI9: =1098 -> 1098 | BJ9: =1095 -> 1095 | BK9: =+SUM(BG9:BJ9) -> 4211 | BL9: =BJ9 -> 1095 | BM9: =BL9 -> 1095 | BN9: =BM9 -> 1095 | BO9: =BN9 -> 1095 | BP9: =+SUM(BL9:BO9) -> 4380 | BQ9: =BO9 -> 1095 | BR9: =BQ9 -> 1095 | BS9: =BR9 -> 1095 | BT9: =BS9 -> 1095 | BU9: =+SUM(BQ9:BT9) -> 4380
A10: x | B10: Stock-Based Compensation Expense | H10: 2159 | I10: 575 | J10: 831 | K10: 1427 | L10: 7852 | M10: 10685 | N10: 5519 | O10: 3641 | P10: 4177 | Q10: 3979 | R10: 17316 | S10: 4279 | T10: 5171 | U10: 5288 | V10: 4803 | W10: =+SUM(S10:V10) -> 19541 | X10: 6225 | Y10: 7350 | Z10: 7424 | AA10: 6594 | AB10: =+SUM(X10:AA10) -> 27593 | AC10: 8634 | AD10: 10430 | AE10: 10426 | AF10: 11174 | AG10: =+SUM(AC10:AF10) -> 40664 | AH10: 13347 | AI10: 16446 | AJ10: =17128 -> 17128 | AK10: =16967 -> 16967 | AL10: =+SUM(AH10:AK10) -> 63888 | AM10: =20862 -> 20862 | AN10: =23814 -> 23814 | AO10: =29196 -> 29196 | AP10: =28707 -> 28707 | AQ10: =+SUM(AM10:AP10) -> 102579 | AR10: =28922 -> 28922 | AS10: =32411 -> 32411 | AT10: =30971 -> 30971 | AU10: =27598 -> 27598 | AV10: =+'Billings & Recs'!AV111 -> 119902 | AW10: =29373 -> 29373 | AX10: =31695 -> 31695 | AY10: =23768 -> 23768 | AZ10: =23245 -> 23245 | BA10: =+'Billings & Recs'!BA111 -> 108081 | BB10: =24893 -> 24893 | BC10: =27409 -> 27409 | BD10: =24594 -> 24594 | BE10: =27412 -> 27412 | BF10: =+'Billings & Recs'!BF111 -> 104308 | BG10: =27151 -> 27151 | BH10: =27581 -> 27581 | BI10: =26327 -> 26327 | BJ10: =23276 -> 23276 | BK10: =+'Billings & Recs'!BK111 -> 104335 | BL10: =+'Billings & Recs'!BL111 -> 29115.762 | BM10: =+'Billings & Recs'!BM111 -> 27161.391 | BN10: =+'Billings & Recs'!BN111 -> 29434.874 | BO10: =+'Billings & Recs'!BO111 -> 29641.035 | BP10: =+'Billings & Recs'!BP111 -> 115353.06 | BQ10: =+'Billings & Recs'!BQ111 -> 29613.163 | BR10: =+'Billings & Recs'!BR111 -> 27626.639 | ... BU10: =+'Billings & Recs'!BU111 -> 117276.06
B11: Provision for Doubtful Accounts | H11: 581 | I11: 165 | J11: 211 | K11: 200 | L11: 252 | M11: 828 | N11: 124 | O11: 270 | P11: 110 | Q11: 427 | R11: 931 | S11: 316 | T11: 162 | U11: 31 | V11: 396 | W11: =+SUM(S11:V11) -> 905 | X11: 156 | Y11: 300 | Z11: 24 | AA11: 260 | AB11: =+SUM(X11:AA11) -> 740 | AC11: 437 | AD11: 916 | AE11: 429 | AF11: 459 | AG11: =+SUM(AC11:AF11) -> 2241 | AH11: 527 | AI11: 481 | AJ11: =752 -> 752 | AK11: =237 -> 237 | AL11: =+SUM(AH11:AK11) -> 1997 | AM11: =0 -> 0 | AN11: 0 | AO11: 0 | AP11: 0 | AQ11: =+SUM(AM11:AP11) -> 0 | AR11: 0 | AS11: 0 | AT11: 0 | AU11: 0 | AV11: =+SUM(AR11:AU11) -> 0 | BA11: =+SUM(AW11:AZ11) -> 0 | BF11: =+SUM(BB11:BE11) -> 0 | BK11: =+SUM(BG11:BJ11) -> 0 | BP11: =+SUM(BL11:BO11) -> 0 | BU11: =+SUM(BQ11:BT11) -> 0
B12: Impairment of Long-Lived Assets | H12: 0 | I12: 0 | J12: 0 | K12: 483 | L12: 0 | M12: 483 | N12: 0 | O12: 0 | P12: 0 | Q12: 0 | R12: 0 | S12: 0 | T12: 0 | U12: 0 | V12: 0 | W12: =+SUM(S12:V12) -> 0 | X12: 0 | Y12: 0 | Z12: 0 | AA12: 0 | AB12: =+SUM(X12:AA12) -> 0 | AC12: 0 | AG12: =+SUM(AC12:AF12) -> 0 | AL12: =+SUM(AH12:AK12) -> 0 | AQ12: =+SUM(AM12:AP12) -> 0 | AV12: =+SUM(AR12:AU12) -> 0 | BA12: =+SUM(AW12:AZ12) -> 0 | BF12: =+SUM(BB12:BE12) -> 0 | BK12: =+SUM(BG12:BJ12) -> 0 | BP12: =+SUM(BL12:BO12) -> 0 | BU12: =+SUM(BQ12:BT12) -> 0
B13: Deferred Income Taxes | H13: 196 | I13: 0 | J13: 0 | K13: 0 | L13: 119 | M13: 119 | N13: 0 | O13: 0 | P13: 0 | Q13: 75 | R13: 75 | S13: 0 | T13: 0 | U13: -2632 | V13: -228 | W13: =+SUM(S13:V13) -> -2860 | X13: 0 | Y13: 0 | Z13: 0 | AA13: -69 | AB13: =+SUM(X13:AA13) -> -69 | AC13: 0 | AD13: -761 | AE13: 0 | AF13: 116 | AG13: =+SUM(AC13:AF13) -> -645 | AH13: =0 -> 0 | AI13: =0 -> 0 | AJ13: =0 -> 0 | AK13: =737 -> 737 | AL13: =+SUM(AH13:AK13) -> 737 | AM13: =0 -> 0 | AN13: =3924 -> 3924 | AO13: 0 | AP13: =-3458 -> -3458 | AQ13: =+SUM(AM13:AP13) -> 466 | AR13: 0 | AS13: 0 | AT13: 0 | AU13: =332 -> 332 | AV13: =+SUM(AR13:AU13) -> 332 | AZ13: =-5624 -> -5624 | BA13: =+SUM(AW13:AZ13) -> -5624 | BB13: =1840 -> 1840 | BC13: =0 -> 0 | BD13: =0 -> 0 | BE13: =-1049 -> -1049 | BF13: =+SUM(BB13:BE13) -> 791 | BG13: 0 | BH13: 0 | BI13: =-1300 -> -1300 | BJ13: =-390 -> -390 | BK13: =+SUM(BG13:BJ13) -> -1690 | BL13: =0 -> 0 | BM13: =0 -> 0 | BN13: =0 -> 0 | BO13: =0 -> 0 | BP13: =+SUM(BL13:BO13) -> 0 | BQ13: =0 -> 0 | BR13: =0 -> 0 | BS13: =0 -> 0 | BT13: =0 -> 0 | BU13: =+SUM(BQ13:BT13) -> 0
B14: Loss on Sale of Property and Equipment | H14: 0 | I14: 0 | J14: 0 | K14: 0 | L14: 0 | M14: 0 | N14: 0 | O14: 0 | P14: 0 | Q14: 0 | R14: 0 | S14: 0 | T14: 0 | U14: 0 | V14: 0 | W14: =+SUM(S14:V14) -> 0 | X14: 0 | Y14: 0 | Z14: 0 | AA14: 0 | AB14: =+SUM(X14:AA14) -> 0 | AC14: 0 | AG14: =+SUM(AC14:AF14) -> 0 | AL14: =+SUM(AH14:AK14) -> 0 | AQ14: =+SUM(AM14:AP14) -> 0 | AV14: =+SUM(AR14:AU14) -> 0 | BA14: =+SUM(AW14:AZ14) -> 0 | BF14: =+SUM(BB14:BE14) -> 0 | BK14: =+SUM(BG14:BJ14) -> 0 | BP14: =+SUM(BL14:BO14) -> 0 | BU14: =+SUM(BQ14:BT14) -> 0
B15: Foreign Currency Re-Measurement Gain / Loss | H15: 0 | I15: 241 | J15: -188 | K15: 37 | L15: 63 | M15: 153 | N15: -223 | O15: 104 | P15: -47 | Q15: 224 | R15: 58 | S15: 44 | T15: -282 | U15: -172 | V15: 46 | W15: =+SUM(S15:V15) -> -364 | X15: 147 | Y15: 324 | Z15: 95 | AA15: 191 | AB15: =+SUM(X15:AA15) -> 757 | AC15: 249 | AD15: -58 | AE15: 379 | AF15: -315 | AG15: =+SUM(AC15:AF15) -> 255 | AH15: 447 | AI15: -248 | AJ15: =109 -> 109 | AK15: =-45 -> -45 | AL15: =+SUM(AH15:AK15) -> 263 | AM15: =0 -> 0 | AN15: 0 | AO15: 0 | AP15: 0 | AQ15: =+SUM(AM15:AP15) -> 0 | AR15: 0 | AS15: 0 | AT15: 0 | AU15: 0 | AV15: =+SUM(AR15:AU15) -> 0 | BA15: =+SUM(AW15:AZ15) -> 0 | BF15: =+SUM(BB15:BE15) -> 0 | BK15: =+SUM(BG15:BJ15) -> 0 | BP15: =+SUM(BL15:BO15) -> 0 | BU15: =+SUM(BQ15:BT15) -> 0
B16: Other | H16: 0 | I16: 0 | J16: 51 | K16: 79 | L16: 79 | M16: 209 | N16: 78 | O16: 52 | P16: 38 | Q16: 54 | R16: 222 | S16: 97 | T16: 78 | U16: 39 | V16: -5 | W16: =+SUM(S16:V16) -> 209 | X16: -52 | Y16: -19 | Z16: -274 | AA16: -161 | AB16: =+SUM(X16:AA16) -> -506 | AC16: -722 | AD16: -568 | AE16: -345 | AF16: -254 | AG16: =+SUM(AC16:AF16) -> -1889 | AH16: -138 | AI16: -9 | AJ16: =60 -> 60 | AK16: 255 | AL16: =+SUM(AH16:AK16) -> 168 | AM16: =2740+1404 -> 4144 | AN16: =42 -> 42 | AO16: =209 -> 209 | AP16: =265 -> 265 | AQ16: =+SUM(AM16:AP16) -> 4660 | AR16: =526 -> 526 | AS16: =1755 -> 1755 | AT16: =1547 -> 1547 | AU16: =-4028 -> -4028 | AV16: =+SUM(AR16:AU16) -> -200 | AW16: =995 -> 995 | AX16: =27231+12660+3428 -> 43319 | AY16: =1203+53889+2851+3553 -> 61496 | AZ16: =-5157 -> -5157 | BA16: =+SUM(AW16:AZ16) -> 100653 | BB16: =-203 -> -203 | BC16: =-1149 -> -1149 | BD16: =-3182 -> -3182 | BE16: =3031 -> 3031 | BF16: =+SUM(BB16:BE16) -> -1503 | BG16: =-1153 -> -1153 | BH16: =-3541 -> -3541 | BI16: =-36 -> -36 | BJ16: =-1624 -> -1624 | BK16: =+SUM(BG16:BJ16) -> -6354 | BL16: =0 -> 0 | BM16: =0 -> 0 | BN16: =0 -> 0 | BO16: =0 -> 0 | BP16: =+SUM(BL16:BO16) -> 0 | BQ16: =0 -> 0 | BR16: =0 -> 0 | BS16: =0 -> 0 | BT16: =0 -> 0 | BU16: =+SUM(BQ16:BT16) -> 0
B17: Accounts Receivables | H17: -7127 | I17: 4179 | J17: -5019 | K17: -5809 | L17: -11721 | M17: -18370 | N17: 14048 | O17: -9103 | P17: 189 | Q17: -11329 | R17: -6195 | S17: 15182 | T17: -13942 | U17: -1110 | V17: -25347 | W17: =+SUM(S17:V17) -> -25217 | X17: 34722 | Y17: -10136 | Z17: -5299 | AA17: -20972 | AB17: =+SUM(X17:AA17) -> -1685 | AC17: 14729 | AD17: -10180 | AE17: 6311 | AF17: -25660 | AG17: =+SUM(AC17:AF17) -> -14800 | AH17: 22608 | AI17: -11773 | AJ17: =2393 -> 2393 | AK17: =-37608 -> -37608 | AL17: =+SUM(AH17:AK17) -> -24380 | AM17: =34414 -> 34414 | AN17: =-21598 -> -21598 | AO17: =10706 -> 10706 | AP17: =-48997 -> -48997 | AQ17: =+SUM(AM17:AP17) -> -25475 | AR17: =36327 -> 36327 | AS17: =-18180 -> -18180 | AT17: =3278 -> 3278 | AU17: =-30475 -> -30475 | AV17: =+SUM(AR17:AU17) -> -9050 | AW17: =35805 -> 35805 | AX17: =-20695 -> -20695 | AY17: =-2682 -> -2682 | AZ17: =-26449 -> -26449 | BA17: =+SUM(AW17:AZ17) -> -14021 | BB17: =39529 -> 39529 | BC17: =-19539 -> -19539 | BD17: =2442 -> 2442 | BE17: =-27912 -> -27912 | BF17: =+SUM(BB17:BE17) -> -5480 | BG17: =27668 -> 27668 | BH17: =-10176 -> -10176 | BI17: =8419 -> 8419 | BJ17: =-24244 -> -24244 | BK17: =+SUM(BG17:BJ17) -> 1667 | BL17: =+-(BS!BL9-BS!BJ9) -> 26059.742 | BM17: =+-(BS!BM9-BS!BL9) -> -7617.8744 | BN17: =+-(BS!BN9-BS!BM9) -> 13081.268 | BO17: =+-(BS!BO9-BS!BN9) -> -24473.627 | BP17: =+SUM(BL17:BO17) -> 7049.5084 | BQ17: =+-(BS!BQ9-BS!BO9) -> 18952.431 | BR17: =+-(BS!BR9-BS!BQ9) -> -10105.017 | BS17: =+-(BS!BS9-BS!BR9) -> 6289.0082 | BT17: =+-(BS!BT9-BS!BS9) -> -27285.09 | BU17: =+SUM(BQ17:BT17) -> -12148.668
B18: Deferred Contract Acquisition and Fulfillment Costs | H18: 0 | I18: 0 | J18: 0 | K18: 0 | L18: 0 | M18: 0 | N18: 0 | O18: 0 | P18: 0 | Q18: 0 | R18: 0 | S18: 0 | T18: 0 | U18: 0 | V18: 0 | W18: =+SUM(S18:V18) -> 0 | X18: -1713 | Y18: -2818 | Z18: -1854 | AA18: -6405 | AB18: =+SUM(X18:AA18) -> -12790 | AC18: -1094 | AD18: -2078 | AE18: -2231 | AF18: -5903 | AG18: =+SUM(AC18:AF18) -> -11306 | AH18: -516 | AI18: -2478 | AJ18: =-2284 -> -2284 | AK18: =-8101 -> -8101 | AL18: =+SUM(AH18:AK18) -> -13379 | AM18: =-1956 -> -1956 | AN18: =-3497 -> -3497 | AO18: =-4319 -> -4319 | AP18: =-12754 -> -12754 | AQ18: =+SUM(AM18:AP18) -> -22526 | AR18: =-2939 -> -2939 | AS18: =-2141 -> -2141 | AT18: =-2919 -> -2919 | AU18: =-7911 -> -7911 | AV18: =+SUM(AR18:AU18) -> -15910 | AW18: =-2240 -> -2240 | AX18: =-3723 -> -3723 | AY18: =-3525 -> -3525 | AZ18: =-9046 -> -9046 | BA18: =+SUM(AW18:AZ18) -> -18534 | BB18: =-679 -> -679 | BC18: =-1285 -> -1285 | BD18: =1471 -> 1471 | BE18: =-3703 -> -3703 | BF18: =+SUM(BB18:BE18) -> -4196 | BG18: =5295 -> 5295 | BH18: =4505 -> 4505 | BI18: =4338 -> 4338 | BJ18: =-3681 -> -3681 | BK18: =+SUM(BG18:BJ18) -> 10457 | BL18: =+(BS!BL10-BS!BJ10)+(BS!BL18-BS!BJ18) -> 781.32 | BM18: =+(BS!BM10-BS!BL10)+(BS!BM18-BS!BL18) -> 831.5508 | BN18: =+(BS!BN10-BS!BM10)+(BS!BN18-BS!BM18) -> 883.02061 | BO18: =+(BS!BO10-BS!BN10)+(BS!BO18-BS!BN18) -> 935.76929 | BP18: =+SUM(BL18:BO18) -> 3431.6607 | BQ18: =+(BS!BQ10-BS!BO10)+(BS!BQ18-BS!BO18) -> 1534.2465 | BR18: =+(BS!BR10-BS!BQ10)+(BS!BR18-BS!BQ18) -> 1627.7857 | BS18: =+(BS!BS10-BS!BR10)+(BS!BS18-BS!BR18) -> 1724.7448 | BT18: =+(BS!BT10-BS!BS10)+(BS!BT18-BS!BS18) -> 1825.2639 | BU18: =+SUM(BQ18:BT18) -> 6712.0409
B19: Prepaid Expenses and Other Assets | H19: -2165 | I19: -778 | J19: -289 | K19: 546 | L19: -1266 | M19: -1787 | N19: -716 | O19: -685 | P19: 325 | Q19: -2447 | R19: -3523 | S19: 1466 | T19: -1054 | U19: 189 | V19: -675 | W19: =+SUM(S19:V19) -> -74 | X19: -3190 | Y19: -412 | Z19: 1168 | AA19: 2147 | AB19: =+SUM(X19:AA19) -> -287 | AC19: -5940 | AD19: -3394 | AE19: -544 | AF19: -3813 | AG19: =+SUM(AC19:AF19) -> -13691 | AH19: 135 | AI19: 1638 | AJ19: =-421 -> -421 | AK19: =-10308 -> -10308 | AL19: =+SUM(AH19:AK19) -> -8956 | AM19: =-136 -> -136 | AN19: =530 -> 530 | AO19: =2697 -> 2697 | AP19: =-6446 -> -6446 | AQ19: =+SUM(AM19:AP19) -> -3355 | AR19: =-6556 -> -6556 | AS19: =-3971 -> -3971 | AT19: =5224 -> 5224 | AU19: =3072 -> 3072 | AV19: =+SUM(AR19:AU19) -> -2231 | AW19: =-5567 -> -5567 | AX19: =6967 -> 6967 | AY19: =4033 -> 4033 | AZ19: =-9558 -> -9558 | BA19: =+SUM(AW19:AZ19) -> -4125 | BB19: =-1223 -> -1223 | BC19: =1653 -> 1653 | BD19: =5632 -> 5632 | BE19: =-3257 -> -3257 | BF19: =+SUM(BB19:BE19) -> 2805 | BG19: =-1995 -> -1995 | BH19: =-3803 -> -3803 | BI19: =4459 -> 4459 | BJ19: =-8884 -> -8884 | BK19: =+SUM(BG19:BJ19) -> -10223 | BL19: =+-(BS!BL11-BS!BJ11) -> 4048.0362 | BM19: =+-(BS!BM11-BS!BL11) -> 3432.1423 | BN19: =+-(BS!BN11-BS!BM11) -> -3151.4664 | BO19: =+-(BS!BO11-BS!BN11) -> 1584.4936 | BP19: =+SUM(BL19:BO19) -> 5913.2058 | BQ19: =+-(BS!BQ11-BS!BO11) -> 1058.0795 | BR19: =+-(BS!BR11-BS!BQ11) -> 3483.3486 | BS19: =+-(BS!BS11-BS!BR11) -> 1801.5183 | BT19: =+-(BS!BT11-BS!BS11) -> -2090.4397 | BU19: =+SUM(BQ19:BT19) -> 4252.5068
B20: Accounts Payable | H20: 567 | I20: -688 | J20: -680 | K20: -233 | L20: -701 | M20: -2302 | N20: -500 | O20: 2404 | P20: -1355 | Q20: 1070 | R20: 1619 | S20: -244 | T20: -1413 | U20: 1335 | V20: -1935 | W20: =+SUM(S20:V20) -> -2257 | X20: 3219 | Y20: -828 | Z20: -1826 | AA20: 3110 | AB20: =+SUM(X20:AA20) -> 3675 | AC20: 66 | AD20: 2118 | AE20: -1052 | AF20: -1040 | AG20: =+SUM(AC20:AF20) -> 92 | AH20: 4010 | AI20: -3873 | AJ20: =1785 -> 1785 | AK20: =-4316 -> -4316 | AL20: =+SUM(AH20:AK20) -> -2394 | AM20: =550 -> 550 | AN20: =-1879 -> -1879 | AO20: =3408 -> 3408 | AP20: =-4156 -> -4156 | AQ20: =+SUM(AM20:AP20) -> -2077 | AR20: =8673 -> 8673 | AS20: =-5116 -> -5116 | AT20: =4947 -> 4947 | AU20: =-527 -> -527 | AV20: =+SUM(AR20:AU20) -> 7977 | AW20: =-2744 -> -2744 | AX20: =1462 -> 1462 | AY20: =27 -> 27 | AZ20: =6704 -> 6704 | BA20: =+SUM(AW20:AZ20) -> 5449 | BB20: =-4190 -> -4190 | BC20: =1169 -> 1169 | BD20: =-7429 -> -7429 | BE20: =13227 -> 13227 | BF20: =+SUM(BB20:BE20) -> 2777 | BG20: =-6555 -> -6555 | BH20: =3596 -> 3596 | BI20: =-847 -> -847 | BJ20: =-5123 -> -5123 | BK20: =+SUM(BG20:BJ20) -> -8929 | BL20: =+(BS!BL28-BS!BJ28) -> 1514.2743 | BM20: =+(BS!BM28-BS!BL28) -> 4375.6795 | BN20: =+(BS!BN28-BS!BM28) -> -1333.6028 | BO20: =+(BS!BO28-BS!BN28) -> -841.69914 | BP20: =+SUM(BL20:BO20) -> 3714.6519 | BQ20: =+(BS!BQ28-BS!BO28) -> -2438.304 | BR20: =+(BS!BR28-BS!BQ28) -> -569.54081 | BS20: =+(BS!BS28-BS!BR28) -> 4103.9993 | BT20: =+(BS!BT28-BS!BS28) -> -1615.9835 | BU20: =+SUM(BQ20:BT20) -> -519.8291
B21: Accrued Expenses | H21: 3534 | I21: -3928 | J21: 2846 | K21: 2673 | L21: 5111 | M21: 6702 | N21: -7427 | O21: 3965 | P21: 1855 | Q21: 3185 | R21: 1578 | S21: -7216 | T21: 5094 | U21: 2925 | V21: 5955 | W21: =+SUM(S21:V21) -> 6758 | X21: -11317 | Y21: 3511 | Z21: 5632 | AA21: 8192 | AB21: =+SUM(X21:AA21) -> 6018 | AC21: -13690 | AD21: 6378 | AE21: 2490 | AF21: 9581 | AG21: =+SUM(AC21:AF21) -> 4759 | AH21: -14563 | AI21: 7126 | AJ21: =4358 -> 4358 | AK21: =11719 -> 11719 | AL21: =+SUM(AH21:AK21) -> 8640 | AM21: =-15429 -> -15429 | AN21: =7837 -> 7837 | AO21: =3038 -> 3038 | AP21: =23759 -> 23759 | AQ21: =+SUM(AM21:AP21) -> 19205 | AR21: =-24048 -> -24048 | AS21: =11555 -> 11555 | AT21: =252 -> 252 | AU21: =14210 -> 14210 | AV21: =+SUM(AR21:AU21) -> 1969 | AW21: =-23951 -> -23951 | AX21: =11983 -> 11983 | AY21: =-6000 -> -6000 | AZ21: =20390 -> 20390 | BA21: =+SUM(AW21:AZ21) -> 2422 | BB21: =-24890 -> -24890 | BC21: =6499 -> 6499 | BD21: =978 -> 978 | BE21: =7584 -> 7584 | BF21: =+SUM(BB21:BE21) -> -9829 | BG21: =-20325 -> -20325 | BH21: =7089 -> 7089 | BI21: =1658 -> 1658 | BJ21: =20913 -> 20913 | BK21: =+SUM(BG21:BJ21) -> 9335 | BL21: =+(BS!BL29-BS!BJ29) -> -27531.363 | BM21: =+(BS!BM29-BS!BL29) -> 2805.7652 | BN21: =+(BS!BN29-BS!BM29) -> 8167.5121 | BO21: =+(BS!BO29-BS!BN29) -> 9379.2032 | BP21: =+SUM(BL21:BO21) -> -7178.8821 | BQ21: =+(BS!BQ29-BS!BO29) -> -22111.28 | BR21: =+(BS!BR29-BS!BQ29) -> 5842.8938 | BS21: =+(BS!BS29-BS!BR29) -> 9282.0651 | BT21: =+(BS!BT29-BS!BS29) -> 20947.207 | BU21: =+SUM(BQ21:BT21) -> 13960.887
B22: Deferred Revenue | H22: 25200 | I22: 3588 | J22: 8837 | K22: 12643 | L22: 19800 | M22: 44868 | N22: 1540 | O22: 12865 | P22: 4543 | Q22: 19800 | R22: 38748 | S22: -1416 | T22: 12782 | U22: 8214 | V22: 35857 | W22: =+SUM(S22:V22) -> 55437 | X22: -6495 | Y22: 5494 | Z22: -1312 | AA22: 25183 | AB22: =+SUM(X22:AA22) -> 22870 | AC22: -12104 | AD22: 7038 | AE22: =+(BS!AE32-BS!AD32)+(BS!AE39-BS!AD39) -> -7058 | AF22: 30810 | AG22: =+SUM(AC22:AF22) -> 18686 | AH22: -16671 | AI22: 4675 | AJ22: =1540 -> 1540 | AK22: =47884 -> 47884 | AL22: =+SUM(AH22:AK22) -> 37428 | AM22: =987 -> 987 | AN22: =21233 -> 21233 | AO22: =2169 -> 2169 | AP22: =61173 -> 61173 | AQ22: =+SUM(AM22:AP22) -> 85562 | AR22: =3830 -> 3830 | AS22: =19353 -> 19353 | AT22: =-4886 -> -4886 | AU22: =34219 -> 34219 | AV22: =+SUM(AR22:AU22) -> 52516 | AW22: =-12062 -> -12062 | AX22: =13845 -> 13845 | AY22: =-8150 -> -8150 | AZ22: =36839 -> 36839 | BA22: =+SUM(AW22:AZ22) -> 30472 | BB22: =-21186 -> -21186 | BC22: =-2160 -> -2160 | BD22: =-13766 -> -13766 | BE22: =36317 -> 36317 | BF22: =+SUM(BB22:BE22) -> -795 | BG22: =-12874 -> -12874 | BH22: =549 -> 549 | BI22: =-24586 -> -24586 | BJ22: =28540 -> 28540 | BK22: =+SUM(BG22:BJ22) -> -8371 | BL22: =+(BS!BL32-BS!BJ32)+(BS!BL39-BS!BJ39) -> -4855.55 | BM22: =+(BS!BM32-BS!BL32)+(BS!BM39-BS!BL39) -> 2787.431 | BN22: =+(BS!BN32-BS!BM32)+(BS!BN39-BS!BM39) -> -24540.51 | BO22: =+(BS!BO32-BS!BN32)+(BS!BO39-BS!BN39) -> 32732.221 | BP22: =+SUM(BL22:BO22) -> 6123.5916 | BQ22: =+(BS!BQ32-BS!BO32)+(BS!BQ39-BS!BO39) -> -4777.7146 | BR22: =+(BS!BR32-BS!BQ32)+(BS!BR39-BS!BQ39) -> 2909.6593 | BS22: =+(BS!BS32-BS!BR32)+(BS!BS39-BS!BR39) -> -24966.17 | BT22: =+(BS!BT32-BS!BS32)+(BS!BT39-BS!BS39) -> 33418.789 | BU22: =+SUM(BQ22:BT22) -> 6584.563
B23: Contingent Consideration | H23: -560 | I23: 0 | J23: 0 | K23: 0 | L23: 0 | M23: 0 | N23: 0 | O23: 0 | P23: 0 | Q23: 0 | R23: 0 | S23: 0 | T23: 0 | U23: 0 | V23: 0 | W23: =+SUM(S23:V23) -> 0 | X23: 0 | Y23: 0 | Z23: 0 | AA23: 0 | AB23: =+SUM(X23:AA23) -> 0 | AC23: 0 | AD23: =+(BS!AD34-BS!AC34) -> 0 | AE23: =+(BS!AE34-BS!AD34) -> 0 | AF23: =+(BS!AF34-BS!AE34) -> 0 | AG23: =+SUM(AC23:AF23) -> 0 | AH23: =+(BS!AH34-BS!AF34) -> 0 | AI23: =+(BS!AI34-BS!AH34) -> 0 | AJ23: =0 -> 0 | AK23: =0 -> 0 | AL23: =+SUM(AH23:AK23) -> 0 | AQ23: =+SUM(AM23:AP23) -> 0 | AV23: =+SUM(AR23:AU23) -> 0 | BA23: =+SUM(AW23:AZ23) -> 0 | BC23: =+(BS!BC34-BS!BB34) -> 0 | BF23: =+SUM(BB23:BE23) -> 0 | BI23: =+(BS!BI34-BS!BH34) -> 0 | BK23: =+SUM(BG23:BJ23) -> 0 | BL23: =+(BS!BL34-BS!BJ34) -> 0 | BM23: =+(BS!BM34-BS!BL34) -> 0 | BN23: =+(BS!BN34-BS!BM34) -> 0 | BO23: =+(BS!BO34-BS!BN34) -> 0 | BP23: =+SUM(BL23:BO23) -> 0 | BQ23: =+(BS!BQ34-BS!BO34) -> 0 | BR23: =+(BS!BR34-BS!BQ34) -> 0 | BS23: =+(BS!BS34-BS!BR34) -> 0 | BT23: =+(BS!BT34-BS!BS34) -> 0 | BU23: =+SUM(BQ23:BT23) -> 0
B24: Other Liabilities | H24: 2193 | I24: 44 | J24: 38 | K24: -140 | L24: -61 | M24: -119 | N24: -166 | O24: 94 | P24: 238 | Q24: 392 | R24: 558 | S24: -266 | T24: -553 | U24: -146 | V24: 15 | W24: =+SUM(S24:V24) -> -950 | X24: -444 | Y24: -225 | Z24: 47 | AA24: 989 | AB24: =+SUM(X24:AA24) -> 367 | AC24: 1605 | AD24: -476 | AE24: 163 | AF24: -274 | AG24: =+SUM(AC24:AF24) -> 1018 | AH24: -1063 | AI24: 83 | AJ24: =65 -> 65 | AK24: =490 -> 490 | AL24: =+SUM(AH24:AK24) -> -425 | AM24: =-394 -> -394 | AN24: =4783 -> 4783 | AO24: =-796 -> -796 | AP24: =136 -> 136 | AQ24: =+SUM(AM24:AP24) -> 3729 | AR24: =-481 -> -481 | AS24: =155 -> 155 | AT24: =-818 -> -818 | AU24: =3637 -> 3637 | AV24: =+SUM(AR24:AU24) -> 2493 | AW24: =104 -> 104 | AX24: =379 -> 379 | AY24: =-1381 -> -1381 | AZ24: =-414 -> -414 | BA24: =+SUM(AW24:AZ24) -> -1312 | BB24: =2520 -> 2520 | BC24: =140 -> 140 | BD24: =4220 -> 4220 | BE24: =-2607 -> -2607 | BF24: =+SUM(BB24:BE24) -> 4273 | BG24: =-2244 -> -2244 | BH24: =1015 -> 1015 | BI24: =-2340 -> -2340 | BJ24: =-6614 -> -6614 | BK24: =+SUM(BG24:BJ24) -> -10183 | BL24: =+(BS!BL35-BS!BJ35) -> 0 | BM24: =+(BS!BM35-BS!BL35) -> 0 | BN24: =+(BS!BN35-BS!BM35) -> 0 | BO24: =+(BS!BO35-BS!BN35) -> 0 | BP24: =+SUM(BL24:BO24) -> 0 | BQ24: =+(BS!BQ35-BS!BO35) -> 0 | BR24: =+(BS!BR35-BS!BQ35) -> 0 | BS24: =+(BS!BS35-BS!BR35) -> 0 | BT24: =+(BS!BT35-BS!BS35) -> 0 | BU24: =+SUM(BQ24:BT24) -> 0
D25: ______ | E25: ______ | F25: ______ | G25: ______ | H25: ______ | I25: ______ | J25: ______ | K25: ______ | L25: ______ | M25: ______ | N25: ______ | O25: ______ | P25: ______ | Q25: ______ | R25: ______ | S25: ______ | T25: ______ | U25: ______ | V25: ______ | W25: ______ | X25: ______ | Y25: ______ | Z25: ______ | AA25: ______ | AB25: ______ | AC25: ______ | AD25: ______ | AE25: ______ | AF25: ______ | AG25: ______ | AH25: ______ | AI25: ______ | AJ25: ______ | AK25: ______ | AL25: ______ | AM25: ______ | AN25: ______ | AO25: ______ | AP25: ______ | AQ25: ______ | AR25: ______ | AS25: ______ | AT25: ______ | AU25: ______ | AV25: ______ | AW25: ______ | AX25: ______ | AY25: ______ | AZ25: ______ | BA25: ______ | BB25: ______ | BC25: ______ | BD25: ______ | BE25: ______ | BF25: ______ | BG25: ______ | BH25: ______ | BI25: ______ | BJ25: ______ | BK25: ______ | BL25: ______ | BM25: ______ | BN25: ______ | BO25: ______ | BP25: ______ | BQ25: ______ | BR25: ______ | BS25: ______ | BT25: ______ | BU25: ______
B26: Net Cash (Used In)/Provided by Operating Activities | H26: =SUM(H7:H24) -> -3356 | I26: =SUM(I7:I24) -> -3012 | J26: =SUM(J7:J24) -> -1241 | K26: =SUM(K7:K24) -> 2273 | L26: =SUM(L7:L24) -> 73 | M26: =SUM(M7:M24) -> -1907 | N26: =SUM(N7:N24) -> -1592 | O26: =SUM(O7:O24) -> 1863 | ... BU26: =SUM(BU7:BU24) -> 155747.01
B28: Cash from Investing Activity
B29: Business Acquisitions, net of Cash Acquired | H29: 0 | I29: 0 | J29: -3344 | K29: 0 | L29: -35467 | M29: -38811 | N29: 0 | O29: 0 | P29: 0 | Q29: 0 | R29: 0 | S29: 0 | T29: 0 | U29: -14717 | V29: 0 | W29: =+SUM(S29:V29) -> -14717 | X29: 0 | Y29: 0 | Z29: 0 | AA29: -14460 | AB29: =+SUM(X29:AA29) -> -14460 | AC29: 0 | AD29: -14621 | AE29: 14 | AG29: =+SUM(AC29:AF29) -> -14607 | AI29: -125771 | AJ29: =-55 -> -55 | AK29: 0 | AL29: =+SUM(AH29:AK29) -> -125826 | AM29: =-49720 -> -49720 | AN29: =-2700 -> -2700 | AO29: =-306000 -> -306000 | AP29: =0 -> 0 | AQ29: =+SUM(AM29:AP29) -> -358420 | AR29: =0 -> 0 | AS29: 0 | AT29: 0 | AU29: 0 | AV29: =+SUM(AR29:AU29) -> 0 | AW29: =-34033 -> -34033 | AX29: =-808 -> -808 | AY29: =0 -> 0 | AZ29: =0 -> 0 | BA29: =+SUM(AW29:AZ29) -> -34841 | BB29: 0 | BC29: =0 -> 0 | BD29: =-37198 -> -37198 | BE29: =-103 -> -103 | BF29: =+SUM(BB29:BE29) -> -37301 | BG29: 0 | BI29: =0 -> 0 | BJ29: 0 | BK29: =+SUM(BG29:BJ29) -> 0 | BL29: 0 | BM29: 0 | BN29: 0 | BO29: 0 | BP29: =+SUM(BL29:BO29) -> 0 | BQ29: 0 | BR29: 0 | BS29: 0 | BT29: 0 | BU29: =+SUM(BQ29:BT29) -> 0
A30: x | B30: Purchases of Property and Equipment | H30: -7082 | I30: -573 | J30: -622 | K30: -1644 | L30: -1297 | M30: -4136 | N30: -1092 | O30: -750 | P30: -1465 | Q30: -1192 | R30: -4499 | S30: -1335 | T30: -1243 | U30: -928 | V30: -1318 | W30: =+SUM(S30:V30) -> -4824 | X30: -2147 | Y30: -3503 | Z30: -2754 | AA30: -4409 | AB30: =+SUM(X30:AA30) -> -12813 | AC30: -8463 | AD30: -9249 | AE30: -9341 | AF30: -2375 | AG30: =+SUM(AC30:AF30) -> -29428 | AH30: -2756 | AI30: -1199 | AJ30: =-3170 -> -3170 | AK30: =-6677 -> -6677 | AL30: =+SUM(AH30:AK30) -> -13802 | AM30: =-972 -> -972 | AN30: =-1699 -> -1699 | AO30: =-2164 -> -2164 | AP30: =-4175 -> -4175 | AQ30: =+SUM(AM30:AP30) -> -9010 | AR30: =-3053 -> -3053 | AS30: =-4171 -> -4171 | AT30: =-5863 -> -5863 | AU30: =-7295 -> -7295 | AV30: =+BS!AV83*-1 -> -20382 | AW30: =-2285 -> -2285 | AX30: =-1419 -> -1419 | AY30: =-295 -> -295 | AZ30: =-367 -> -367 | BA30: =+BS!BA83*-1 -> -4366 | BB30: =-620 -> -620 | BC30: =-280 -> -280 | BD30: =-1342 -> -1342 | BE30: =-1183 -> -1183 | BF30: =+BS!BF83*-1 -> -3425 | BG30: =-1361 -> -1361 | BH30: =-948 -> -948 | BI30: =-4137 -> -4137 | BJ30: =-1153 -> -1153 | BK30: =+BS!BK83*-1 -> -7599 | BL30: =+BS!BL83*-1 -> -2079.6973 | BM30: =+BS!BM83*-1 -> -2089.3378 | BN30: =+BS!BN83*-1 -> -2102.491 | BO30: =+BS!BO83*-1 -> -2117.2168 | BP30: =+BS!BP83*-1 -> -8388.7429 | BQ30: =+BS!BQ83*-1 -> -2115.2259 | BR30: =+BS!BR83*-1 -> -2125.1261 | ... BU30: =+BS!BU83*-1 -> -8528.6558
B31: Capitalization of Internal-Use Software Costs | D31: 0 | E31: 0 | F31: 0 | G31: 0 | H31: 0 | I31: 0 | J31: 0 | K31: 0 | L31: 0 | M31: 0 | N31: 0 | O31: 0 | P31: 0 | Q31: 0 | R31: 0 | S31: 0 | T31: -316 | U31: -440 | V31: -406 | W31: =+SUM(S31:V31) -> -1162 | X31: -693 | Y31: -720 | Z31: -1092 | AA31: -760 | AB31: =+SUM(X31:AA31) -> -3265 | AC31: -1601 | AD31: -1551 | AE31: -1534 | AF31: -1401 | AG31: =+SUM(AC31:AF31) -> -6087 | AH31: -1474 | AI31: -1474 | AJ31: =-1459 -> -1459 | AK31: =-1723 -> -1723 | AL31: =+SUM(AH31:AK31) -> -6130 | AM31: =-1758 -> -1758 | AN31: =-2447 -> -2447 | AO31: =-2957 -> -2957 | AP31: =-2692 -> -2692 | AQ31: =+SUM(AM31:AP31) -> -9854 | AR31: =-3522 -> -3522 | AS31: =-4536 -> -4536 | AT31: =-4590 -> -4590 | AU31: =-4497 -> -4497 | AV31: =+SUM(AR31:AU31) -> -17145 | AW31: =-4776 -> -4776 | AX31: =-4305 -> -4305 | AY31: =-3952 -> -3952 | AZ31: =-2845 -> -2845 | BA31: =+SUM(AW31:AZ31) -> -15878 | BB31: =-2916 -> -2916 | BC31: =-3373 -> -3373 | BD31: =-4125 -> -4125 | BE31: =-3748 -> -3748 | BF31: =+SUM(BB31:BE31) -> -14162 | BG31: =-3719 -> -3719 | BH31: =-4314 -> -4314 | BI31: =-3951 -> -3951 | BJ31: =-4122 -> -4122 | BK31: =+SUM(BG31:BJ31) -> -16106 | BL31: =BJ31 -> -4122 | BM31: =BL31 -> -4122 | BN31: =BM31 -> -4122 | BO31: =BN31 -> -4122 | BP31: =+SUM(BL31:BO31) -> -16488 | BQ31: =BO31 -> -4122 | BR31: =BQ31 -> -4122 | BS31: =BR31 -> -4122 | BT31: =BS31 -> -4122 | BU31: =+SUM(BQ31:BT31) -> -16488
B32: Purchases of Investments | H32: 0 | I32: 0 | J32: 0 | K32: 0 | L32: 0 | M32: 0 | N32: 0 | O32: 0 | P32: 0 | Q32: -38976 | R32: -38976 | S32: -7401 | T32: 0 | U32: -5856 | V32: -13506 | W32: =+SUM(S32:V32) -> -26763 | X32: -4460 | Y32: -6195 | Z32: -168290 | AA32: -54476 | AB32: =+SUM(X32:AA32) -> -233421 | AC32: -63029 | AD32: -9403 | AE32: -41776 | AF32: -33839 | AG32: =+SUM(AC32:AF32) -> -148047 | AH32: -24272 | AI32: -24987 | AJ32: =-59451 -> -59451 | AK32: =-68343 -> -68343 | AL32: =+SUM(AH32:AK32) -> -177053 | AM32: =-6394 -> -6394 | AN32: =-52914 -> -52914 | AO32: =0 -> 0 | AP32: 0 | AQ32: =+SUM(AM32:AP32) -> -59308 | AR32: =-32136 -> -32136 | AS32: =-26861-500 -> -27361 | AT32: =-35489-500 -> -35989 | AU32: =-28279 -> -28279 | AV32: =+SUM(AR32:AU32) -> -123765 | AW32: =-4883 -> -4883 | AX32: =-75374 -> -75374 | AY32: =-113756 -> -113756 | AZ32: =-82816 -> -82816 | BA32: =+SUM(AW32:AZ32) -> -276829 | BB32: =-93158 -> -93158 | BC32: =-64808 -> -64808 | BD32: =-84528 -> -84528 | BE32: =0 -> 0 | BF32: =+SUM(BB32:BE32) -> -242494 | BG32: =-144461 -> -144461 | BH32: =-87555 -> -87555 | BI32: =-271022 -> -271022 | BJ32: =-30304-5500 -> -35804 | BK32: =+SUM(BG32:BJ32) -> -538842 | BL32: 0 | BM32: 0 | BN32: 0 | BO32: 0 | BP32: =+SUM(BL32:BO32) -> 0 | BQ32: 0 | BR32: 0 | BS32: 0 | BT32: 0 | BU32: =+SUM(BQ32:BT32) -> 0
B33: Proceeds from Sale of Property and Equipment | H33: 0 | I33: 0 | J33: 0 | K33: 0 | L33: 0 | M33: 0 | N33: 0 | O33: 0 | P33: 0 | Q33: 0 | R33: 0 | S33: 0 | T33: -8427 | U33: 0 | V33: 9150 | W33: =+SUM(S33:V33) -> 723 | X33: 0 | Y33: 0 | Z33: 0 | AA33: 0 | AB33: =+SUM(X33:AA33) -> 0 | AC33: 0 | AD33: =0 -> 0 | AE33: =0 -> 0 | AF33: =0 -> 0 | AG33: =+SUM(AC33:AF33) -> 0 | AH33: =0 -> 0 | AI33: =0 -> 0 | AJ33: =0 -> 0 | AK33: =0 -> 0 | AL33: =+SUM(AH33:AK33) -> 0 | AM33: =0 -> 0 | AO33: 0 | AP33: 0 | AQ33: =+SUM(AM33:AP33) -> 0 | AR33: =2800 -> 2800 | AS33: =57529 -> 57529 | AT33: =26050 -> 26050 | AU33: =34925 -> 34925 | AV33: =+SUM(AR33:AU33) -> 121304 | AW33: =35800 -> 35800 | AX33: =29900 -> 29900 | AY33: =35000 -> 35000 | AZ33: =49750 -> 49750 | BA33: =+SUM(AW33:AZ33) -> 150450 | BB33: =55000 -> 55000 | BC33: =75000 -> 75000 | BD33: =62500 -> 62500 | BE33: =58000 -> 58000 | BF33: =+SUM(BB33:BE33) -> 250500 | BG33: =0 -> 0 | BH33: 0 | BI33: =107000 -> 107000 | BJ33: =123822 -> 123822 | BK33: =+SUM(BG33:BJ33) -> 230822 | BL33: 0 | BM33: 0 | BN33: 0 | BO33: 0 | BP33: =+SUM(BL33:BO33) -> 0 | BQ33: 0 | BR33: 0 | BS33: 0 | BT33: 0 | BU33: =+SUM(BQ33:BT33) -> 0
B34: Increase in Other Investments | H34: 0 | I34: 0 | J34: 0 | K34: 0 | L34: 0 | M34: 0 | N34: 0 | O34: 0 | P34: 0 | Q34: 0 | R34: 0 | S34: 0 | T34: 0 | U34: 0 | V34: -200 | W34: =+SUM(S34:V34) -> -200 | X34: 0 | Y34: 0 | Z34: 0 | AA34: 0 | AB34: =+SUM(X34:AA34) -> 0 | AC34: 0 | AD34: =0 -> 0 | AE34: =0 -> 0 | AF34: =0 -> 0 | AG34: =+SUM(AC34:AF34) -> 0 | AH34: =0 -> 0 | AI34: =0 -> 0 | AJ34: =0 -> 0 | AK34: =0 -> 0 | AL34: =+SUM(AH34:AK34) -> 0 | AM34: =0 -> 0 | AO34: 0 | AQ34: =+SUM(AM34:AP34) -> 0 | AS34: 0 | AT34: 0 | AV34: =+SUM(AR34:AU34) -> 0 | AZ34: =2710 -> 2710 | BA34: =+SUM(AW34:AZ34) -> 2710 | BB34: =0 -> 0 | BC34: =360 -> 360 | BD34: =0 -> 0 | BE34: =0 -> 0 | BF34: =+SUM(BB34:BE34) -> 360 | BG34: =1328 -> 1328 | BH34: 0 | BI34: =0 -> 0 | BJ34: 0 | BK34: =+SUM(BG34:BJ34) -> 1328 | BL34: 0 | BM34: 0 | BN34: 0 | BO34: 0 | BP34: =+SUM(BL34:BO34) -> 0 | BQ34: 0 | BR34: 0 | BS34: 0 | BT34: 0 | BU34: =+SUM(BQ34:BT34) -> 0
B35: Maturities of Investments | H35: 0 | I35: 0 | J35: 0 | K35: 0 | L35: 0 | M35: 0 | N35: 0 | O35: 0 | P35: 0 | Q35: 0 | R35: 0 | S35: 900 | T35: 13705 | U35: 9917 | W35: =+SUM(S35:V35) -> 24522 | X35: 14062 | Y35: 19066 | Z35: 6448 | AA35: 30650 | AB35: =+SUM(X35:AA35) -> 70226 | AC35: 72738 | AD35: 67564 | AE35: 36985 | AF35: 37693 | AG35: =+SUM(AC35:AF35) -> 214980 | AH35: 113924 | AI35: 32675 | AJ35: =9000 -> 9000 | AK35: =10925 -> 10925 | AL35: =+SUM(AH35:AK35) -> 166524 | AM35: =41900-1500 -> 40400 | AN35: =46038 -> 46038 | AO35: =36900-1500 -> 35400 | AP35: =-33784+23160 -> -10624 | AQ35: =+SUM(AM35:AP35) -> 111214 | AT35: 0 | AV35: =+SUM(AR35:AU35) -> 0 | BA35: =+SUM(AW35:AZ35) -> 0 | BB35: =0 -> 0 | BC35: =0 -> 0 | BD35: =0 -> 0 | BE35: =0 -> 0 | BF35: =+SUM(BB35:BE35) -> 0 | BG35: =69000 -> 69000 | BH35: =51500 -> 51500 | BI35: =458 -> 458 | BJ35: 0 | BK35: =+SUM(BG35:BJ35) -> 120958 | BL35: 0 | BM35: 0 | BN35: 0 | BO35: 0 | BP35: =+SUM(BL35:BO35) -> 0 | BQ35: 0 | BR35: 0 | BS35: 0 | BT35: 0 | BU35: =+SUM(BQ35:BT35) -> 0
D36: ______ | E36: ______ | F36: ______ | G36: ______ | H36: ______ | I36: ______ | J36: ______ | K36: ______ | L36: ______ | M36: ______ | N36: ______ | O36: ______ | P36: ______ | Q36: ______ | R36: ______ | S36: ______ | T36: ______ | U36: ______ | V36: ______ | W36: ______ | X36: ______ | Y36: ______ | Z36: ______ | AA36: ______ | AB36: ______ | AC36: ______ | AD36: ______ | AE36: ______ | AF36: ______ | AG36: ______ | AH36: ______ | AI36: ______ | AJ36: ______ | AK36: ______ | AL36: ______ | AM36: ______ | AN36: ______ | AO36: ______ | AP36: ______ | AQ36: ______ | AR36: ______ | AS36: ______ | AT36: ______ | AU36: ______ | AV36: ______ | AW36: ______ | AX36: ______ | AY36: ______ | AZ36: ______ | BA36: ______ | BB36: ______ | BC36: ______ | BD36: ______ | BE36: ______ | BF36: ______ | BG36: ______ | BH36: ______ | BI36: ______ | BJ36: ______ | BK36: ______ | BL36: ______ | BM36: ______ | BN36: ______ | BO36: ______ | BP36: ______ | BQ36: ______ | BR36: ______ | BS36: ______ | BT36: ______ | BU36: ______
B37: Net Cash (Used In)/Provided by Investing Activities | H37: =+SUM(H29:H35) -> -7082 | I37: =+SUM(I29:I35) -> -573 | J37: =+SUM(J29:J35) -> -3966 | K37: =+SUM(K29:K35) -> -1644 | L37: =+SUM(L29:L35) -> -36764 | M37: =+SUM(M29:M35) -> -42947 | N37: =+SUM(N29:N35) -> -1092 | O37: =+SUM(O29:O35) -> -750 | ... BU37: =+SUM(BU29:BU35) -> -25016.656
B39: Cash Flows from Financing Activity
B40: Proceeds from Initial Public Offering and Concurrent Private Placement | H40: 0 | I40: 0 | J40: -1526 | K40: 114442 | L40: -641 | M40: 112275 | N40: 0 | O40: 0 | P40: 0 | Q40: 0 | R40: 0 | S40: 0 | T40: 0 | U40: 0 | V40: 0 | W40: =+SUM(S40:V40) -> 0 | X40: 0 | Y40: 0 | Z40: 0 | AA40: 0 | AB40: =+SUM(X40:AA40) -> 0 | AC40: 0 | AE40: 0 | AG40: =+SUM(AC40:AF40) -> 0 | AL40: =+SUM(AH40:AK40) -> 0 | AQ40: =+SUM(AM40:AP40) -> 0 | AV40: =+SUM(AR40:AU40) -> 0 | BA40: =+SUM(AW40:AZ40) -> 0 | BF40: =+SUM(BB40:BE40) -> 0 | BK40: =+SUM(BG40:BJ40) -> 0 | BP40: =+SUM(BL40:BO40) -> 0 | BU40: =+SUM(BQ40:BT40) -> 0
B41: Proceeds from Issuance of Series D Redeemable Convertible Preferred Stock, net | H41: 30818 | I41: 0 | J41: 0 | K41: 0 | L41: 0 | M41: 0 | N41: 0 | O41: 0 | P41: 0 | Q41: 0 | R41: 0 | S41: 0 | T41: 0 | U41: 0 | V41: 0 | W41: =+SUM(S41:V41) -> 0 | X41: 0 | Y41: 0 | Z41: 0 | AA41: 0 | AB41: =+SUM(X41:AA41) -> 0 | AC41: 0 | AE41: 0 | AG41: =+SUM(AC41:AF41) -> 0 | AL41: =+SUM(AH41:AK41) -> 0 | AQ41: =+SUM(AM41:AP41) -> 0 | AV41: =+SUM(AR41:AU41) -> 0 | BA41: =+SUM(AW41:AZ41) -> 0 | BF41: =+SUM(BB41:BE41) -> 0 | BK41: =+SUM(BG41:BJ41) -> 0 | BP41: =+SUM(BL41:BO41) -> 0 | BU41: =+SUM(BQ41:BT41) -> 0
B42: Proceeds from Issuance of Convertible Senior Notes, net of Issuance Costs Paid of $6,880 | H42: 0 | I42: 0 | J42: 0 | K42: 0 | L42: 0 | M42: 0 | N42: 0 | O42: 0 | P42: 0 | Q42: 0 | R42: 0 | S42: 0 | T42: 0 | U42: 0 | V42: 0 | W42: =+SUM(S42:V42) -> 0 | X42: 0 | Y42: 0 | Z42: =223529 -> 223529 | AA42: -408 | AB42: =+SUM(X42:AA42) -> 223121 | AC42: 0 | AD42: =0 -> 0 | AE42: 0 | AF42: =0 -> 0 | AG42: =+SUM(AC42:AF42) -> 0 | AH42: =0 -> 0 | AI42: =223500-27255-248 -> 195997 | AJ42: =-701 -> -701 | AK42: 0 | AL42: =+SUM(AH42:AK42) -> 195296 | AM42: =587100 -> 587100 | AN42: =-1660 -> -1660 | AO42: =-416 -> -416 | AP42: 0 | AQ42: =+SUM(AM42:AP42) -> 585024 | AR42: 0 | AS42: =0 -> 0 | AV42: =+SUM(AR42:AU42) -> 0 | AY42: =292800 -> 292800 | AZ42: =-709 -> -709 | BA42: =+SUM(AW42:AZ42) -> 292091 | BB42: =0 -> 0 | BC42: =0 -> 0 | BD42: =0 -> 0 | BE42: =0 -> 0 | BF42: =+SUM(BB42:BE42) -> 0 | BG42: =0 -> 0 | BH42: =-45992 -> -45992 | BI42: =-403 -> -403 | BJ42: 0 | BK42: =+SUM(BG42:BJ42) -> -46395 | BL42: =0 -> 0 | BM42: =0 -> 0 | BN42: =0 -> 0 | BO42: =0 -> 0 | BP42: =+SUM(BL42:BO42) -> 0 | BQ42: =0 -> 0 | BR42: =0 -> 0 | BS42: =0 -> 0 | BT42: =0 -> 0 | BU42: =+SUM(BQ42:BT42) -> 0
B43: Purchase of Capped Calls Related to Convertible Senior Notes | H43: 0 | I43: 0 | J43: 0 | K43: 0 | L43: 0 | M43: 0 | N43: 0 | O43: 0 | P43: 0 | Q43: 0 | R43: 0 | S43: 0 | T43: 0 | U43: 0 | V43: 0 | W43: =+SUM(S43:V43) -> 0 | X43: 0 | Y43: 0 | Z43: =+-26910 -> -26910 | AA43: 0 | AB43: =+SUM(X43:AA43) -> -26910 | AC43: 0 | AD43: =0 -> 0 | AE43: 0 | AF43: =0 -> 0 | AG43: =+SUM(AC43:AF43) -> 0 | AH43: =0 -> 0 | AI43: =0 -> 0 | AJ43: =0 -> 0 | AK43: =0 -> 0 | AL43: =+SUM(AH43:AK43) -> 0 | AM43: =-76020 -> -76020 | AN43: =-2002 -> -2002 | AO43: 0 | AP43: 0 | AQ43: =+SUM(AM43:AP43) -> -78022 | AS43: 0 | AV43: =+SUM(AR43:AU43) -> 0 | AY43: =-36570 -> -36570 | BA43: =+SUM(AW43:AZ43) -> -36570 | BB43: =0 -> 0 | BC43: =0 -> 0 | BD43: =0 -> 0 | BE43: =0 -> 0 | BF43: =+SUM(BB43:BE43) -> 0 | BG43: =0 -> 0 | BH43: 0 | BI43: =0 -> 0 | BJ43: 0 | BK43: =+SUM(BG43:BJ43) -> 0 | BL43: =0 -> 0 | BM43: =0 -> 0 | BN43: =0 -> 0 | BO43: =0 -> 0 | BP43: =+SUM(BL43:BO43) -> 0 | BQ43: =0 -> 0 | BR43: =0 -> 0 | BS43: =0 -> 0 | BT43: =0 -> 0 | BU43: =+SUM(BQ43:BT43) -> 0
B44: Proceeds from Secondary Public Offering, net of Offering Costs Paid of $608 | H44: 0 | I44: 0 | J44: 0 | K44: 0 | L44: 0 | M44: 0 | N44: 0 | O44: 0 | P44: 0 | Q44: 0 | R44: 0 | S44: 0 | T44: 0 | U44: 0 | V44: 0 | W44: =+SUM(S44:V44) -> 0 | X44: 31231 | Y44: -324 | Z44: 0 | AA44: 0 | AB44: =+SUM(X44:AA44) -> 30907 | AC44: 0 | AD44: =0 -> 0 | AE44: 0 | AF44: =0 -> 0 | AG44: =+SUM(AC44:AF44) -> 0 | AH44: =0 -> 0 | AI44: =0 -> 0 | AJ44: =0 -> 0 | AK44: =0 -> 0 | AL44: =+SUM(AH44:AK44) -> 0 | AM44: =0 -> 0 | AO44: 0 | AQ44: =+SUM(AM44:AP44) -> 0 | AV44: =+SUM(AR44:AU44) -> 0 | BA44: =+SUM(AW44:AZ44) -> 0 | BF44: =+SUM(BB44:BE44) -> 0 | BI44: =0 -> 0 | BK44: =+SUM(BG44:BJ44) -> 0 | BL44: =0 -> 0 | BM44: =0 -> 0 | BN44: =0 -> 0 | BO44: =0 -> 0 | BP44: =+SUM(BL44:BO44) -> 0 | BQ44: =0 -> 0 | BR44: =0 -> 0 | BS44: =0 -> 0 | BT44: =0 -> 0 | BU44: =+SUM(BQ44:BT44) -> 0
B45: Repayments of Term Loan and Related Termination Fee | H45: 0 | I45: 0 | J45: 0 | K45: -18540 | L45: 0 | M45: -18540 | N45: 0 | O45: 0 | P45: 0 | Q45: 0 | R45: 0 | S45: 0 | T45: 0 | U45: 0 | V45: 0 | W45: =+SUM(S45:V45) -> 0 | X45: 0 | Y45: 0 | Z45: 0 | AA45: 0 | AB45: =+SUM(X45:AA45) -> 0 | AC45: 0 | AD45: =0 -> 0 | AE45: 0 | AF45: =0 -> 0 | AG45: =+SUM(AC45:AF45) -> 0 | AH45: =0 -> 0 | AI45: =0 -> 0 | AL45: =+SUM(AH45:AK45) -> 0 | AQ45: =+SUM(AM45:AP45) -> 0 | AV45: =+SUM(AR45:AU45) -> 0 | AY45: =-199998 -> -199998 | BA45: =+SUM(AW45:AZ45) -> -199998 | BF45: =+SUM(BB45:BE45) -> 0 | BI45: =0 -> 0 | BK45: =+SUM(BG45:BJ45) -> 0 | BL45: =0 -> 0 | BM45: =0 -> 0 | BN45: =0 -> 0 | BO45: =0 -> 0 | BP45: =+SUM(BL45:BO45) -> 0 | BQ45: =0 -> 0 | BR45: =0 -> 0 | BS45: =0 -> 0 | BT45: =0 -> 0 | BU45: =+SUM(BQ45:BT45) -> 0
B46: Borrowings from Line of Credit | H46: 0 | I46: 0 | J46: 0 | K46: 0 | L46: 0 | M46: 0 | N46: 0 | O46: 0 | P46: 0 | Q46: 0 | R46: 0 | S46: 0 | T46: 0 | U46: 0 | V46: 0 | W46: =+SUM(S46:V46) -> 0 | X46: 0 | Y46: 0 | Z46: 0 | AA46: 0 | AB46: =+SUM(X46:AA46) -> 0 | AC46: 0 | AD46: =0 -> 0 | AE46: 0 | AF46: =0 -> 0 | AG46: =+SUM(AC46:AF46) -> 0 | AH46: =0 -> 0 | AI46: =0 -> 0 | AL46: =+SUM(AH46:AK46) -> 0 | AQ46: =+SUM(AM46:AP46) -> 0 | AV46: =+SUM(AR46:AU46) -> 0 | BA46: =+SUM(AW46:AZ46) -> 0 | BF46: =+SUM(BB46:BE46) -> 0 | BI46: =0 -> 0 | BK46: =+SUM(BG46:BJ46) -> 0 | BL46: =0 -> 0 | BM46: =0 -> 0 | BN46: =0 -> 0 | BO46: =0 -> 0 | BP46: =+SUM(BL46:BO46) -> 0 | BQ46: =0 -> 0 | BR46: =0 -> 0 | BS46: =0 -> 0 | BT46: =0 -> 0 | BU46: =+SUM(BQ46:BT46) -> 0
B47: Repayments on Line of Credit | H47: 0 | I47: 0 | J47: 0 | K47: 0 | L47: 0 | M47: 0 | N47: 0 | O47: 0 | P47: 0 | Q47: 0 | R47: 0 | S47: 0 | T47: 0 | U47: 0 | V47: 0 | W47: =+SUM(S47:V47) -> 0 | X47: 0 | Y47: 0 | Z47: 0 | AA47: 0 | AB47: =+SUM(X47:AA47) -> 0 | AC47: 0 | AD47: =0 -> 0 | AE47: 0 | AF47: =0 -> 0 | AG47: =+SUM(AC47:AF47) -> 0 | AH47: =0 -> 0 | AI47: =0 -> 0 | AL47: =+SUM(AH47:AK47) -> 0 | AQ47: =+SUM(AM47:AP47) -> 0 | AV47: =+SUM(AR47:AU47) -> 0 | BA47: =+SUM(AW47:AZ47) -> 0 | BF47: =+SUM(BB47:BE47) -> 0 | BI47: =0 -> 0 | BK47: =+SUM(BG47:BJ47) -> 0 | BL47: =0 -> 0 | BM47: =0 -> 0 | BN47: =0 -> 0 | BO47: =0 -> 0 | BP47: =+SUM(BL47:BO47) -> 0 | BQ47: =0 -> 0 | BR47: =0 -> 0 | BS47: =0 -> 0 | BT47: =0 -> 0 | BU47: =+SUM(BQ47:BT47) -> 0
B48: Business Acquisition Payment | H48: 0 | I48: 0 | J48: 0 | K48: 0 | L48: 0 | M48: 0 | N48: 0 | O48: 0 | P48: 0 | Q48: -1392 | R48: -1392 | S48: 0 | T48: -796 | U48: 0 | V48: 0 | W48: =+SUM(S48:V48) -> -796 | X48: 0 | Y48: 0 | Z48: 0 | AA48: 0 | AB48: =+SUM(X48:AA48) -> 0 | AC48: 0 | AD48: =0 -> 0 | AE48: 0 | AF48: =0 -> 0 | AG48: =+SUM(AC48:AF48) -> 0 | AH48: =0 -> 0 | AI48: =0 -> 0 | AJ48: =-150 -> -150 | AK48: 0 | AL48: =+SUM(AH48:AK48) -> -150 | AM48: =-2431 -> -2431 | AO48: =-9687 -> -9687 | AQ48: =+SUM(AM48:AP48) -> -12118 | AS48: =-300 -> -300 | AV48: =+SUM(AR48:AU48) -> -300 | AW48: =-2250 -> -2250 | BA48: =+SUM(AW48:AZ48) -> -2250 | BB48: =0 -> 0 | BC48: =0 -> 0 | BD48: =0 -> 0 | BE48: =-500 -> -500 | BF48: =+SUM(BB48:BE48) -> -500 | BG48: =0 -> 0 | BH48: 0 | BI48: =0 -> 0 | BJ48: =-4091 -> -4091 | BK48: =+SUM(BG48:BJ48) -> -4091 | BL48: =0 -> 0 | BM48: =0 -> 0 | BN48: =0 -> 0 | BO48: =0 -> 0 | BP48: =+SUM(BL48:BO48) -> 0 | BQ48: =0 -> 0 | BR48: =0 -> 0 | BS48: =0 -> 0 | BT48: =0 -> 0 | BU48: =+SUM(BQ48:BT48) -> 0
B49: Payments of Contingent Consideration Related to Business Acquisitions | H49: -856 | I49: 0 | J49: 0 | K49: 0 | L49: 0 | M49: 0 | N49: 0 | O49: 0 | P49: 0 | Q49: 0 | R49: 0 | S49: 0 | T49: 0 | U49: 0 | V49: 0 | W49: =+SUM(S49:V49) -> 0 | X49: 0 | Y49: 0 | Z49: 0 | AA49: 0 | AB49: =+SUM(X49:AA49) -> 0 | AC49: 0 | AD49: =0 -> 0 | AE49: 0 | AF49: =0 -> 0 | AG49: =+SUM(AC49:AF49) -> 0 | AH49: =0 -> 0 | AI49: =0 -> 0 | AL49: =+SUM(AH49:AK49) -> 0 | AQ49: =+SUM(AM49:AP49) -> 0 | AV49: =+SUM(AR49:AU49) -> 0 | BA49: =+SUM(AW49:AZ49) -> 0 | BF49: =+SUM(BB49:BE49) -> 0 | BI49: =0 -> 0 | BK49: =+SUM(BG49:BJ49) -> 0 | BL49: =0 -> 0 | BM49: =0 -> 0 | BN49: =0 -> 0 | BO49: =0 -> 0 | BP49: =+SUM(BL49:BO49) -> 0 | BQ49: =0 -> 0 | BR49: =0 -> 0 | BS49: =0 -> 0 | BT49: =0 -> 0 | BU49: =+SUM(BQ49:BT49) -> 0
B50: Payments of Debt and Equity Issuance Costs | H50: 0 | I50: 0 | J50: 0 | K50: 0 | L50: 0 | M50: 0 | N50: 0 | O50: 0 | P50: 0 | Q50: 0 | R50: 0 | S50: 0 | T50: 0 | U50: 0 | V50: 0 | W50: =+SUM(S50:V50) -> 0 | X50: 0 | Y50: 0 | Z50: 0 | AA50: 0 | AB50: =+SUM(X50:AA50) -> 0 | AC50: 0 | AD50: =0 -> 0 | AE50: 0 | AF50: =0 -> 0 | AG50: =+SUM(AC50:AF50) -> 0 | AH50: =0 -> 0 | AI50: =0 -> 0 | AJ50: =-163 -> -163 | AK50: =-29 -> -29 | AL50: =+SUM(AH50:AK50) -> -192 | AM50: =-182647 -> -182647 | AO50: 0 | AP50: =-300-45351 -> -45651 | AQ50: =+SUM(AM50:AP50) -> -228298 | AS50: =-71-12 -> -83 | AV50: =+SUM(AR50:AU50) -> -83 | AW50: =0 -> 0 | BA50: =+SUM(AW50:AZ50) -> 0 | BF50: =+SUM(BB50:BE50) -> 0 | BG50: 0 | BH50: =-1290 -> -1290 | BI50: =0 -> 0 | BK50: =+SUM(BG50:BJ50) -> -1290 | BL50: =0 -> 0 | BM50: =0 -> 0 | BN50: =0 -> 0 | BO50: =0 -> 0 | BP50: =+SUM(BL50:BO50) -> 0 | BQ50: =0 -> 0 | BR50: =0 -> 0 | BS50: =0 -> 0 | BT50: =0 -> 0 | BU50: =+SUM(BQ50:BT50) -> 0
B51: Repurchase/Issuance of Common and Preferred Stock | H51: -3526 | I51: 0 | J51: 0 | K51: 0 | L51: 0 | M51: 0 | N51: 0 | O51: 0 | P51: 0 | Q51: 0 | R51: 0 | S51: 0 | T51: 0 | U51: 0 | V51: 0 | W51: =+SUM(S51:V51) -> 0 | X51: 0 | Y51: 0 | Z51: 0 | AA51: 0 | AB51: =+SUM(X51:AA51) -> 0 | AC51: 0 | AE51: 0 | AG51: =+SUM(AC51:AF51) -> 0 | AL51: =+SUM(AH51:AK51) -> 0 | AQ51: =+SUM(AM51:AP51) -> 0 | AV51: =+SUM(AR51:AU51) -> 0 | BA51: =+SUM(AW51:AZ51) -> 0 | BF51: =+SUM(BB51:BE51) -> 0 | BG51: 0 | BH51: =755 -> 755 | BI51: =0 -> 0 | BK51: =+SUM(BG51:BJ51) -> 755 | BL51: =0 -> 0 | BM51: =0 -> 0 | BN51: =0 -> 0 | BO51: =0 -> 0 | BP51: =+SUM(BL51:BO51) -> 0 | BQ51: =0 -> 0 | BR51: =0 -> 0 | BS51: =0 -> 0 | BT51: =0 -> 0 | BU51: =+SUM(BQ51:BT51) -> 0
B52: Payments of Capital Lease Obligations | H52: -256 | I52: -59 | J52: -64 | K52: -64 | L52: -66 | M52: -253 | N52: -68 | O52: 0 | P52: 0 | Q52: 0 | R52: -68 | S52: 0 | T52: 0 | U52: 0 | V52: 0 | W52: =+SUM(S52:V52) -> 0 | X52: 0 | Y52: 0 | Z52: 0 | AA52: 0 | AB52: =+SUM(X52:AA52) -> 0 | AC52: 0 | AE52: 0 | AG52: =+SUM(AC52:AF52) -> 0 | AL52: =+SUM(AH52:AK52) -> 0 | AQ52: =+SUM(AM52:AP52) -> 0 | AV52: =+SUM(AR52:AU52) -> 0 | BA52: =+SUM(AW52:AZ52) -> 0 | BF52: =+SUM(BB52:BE52) -> 0 | BI52: =0 -> 0 | BK52: =+SUM(BG52:BJ52) -> 0 | BL52: =0 -> 0 | BM52: =0 -> 0 | BN52: =0 -> 0 | BO52: =0 -> 0 | BP52: =+SUM(BL52:BO52) -> 0 | BQ52: =0 -> 0 | BR52: =0 -> 0 | BS52: =0 -> 0 | BT52: =0 -> 0 | BU52: =+SUM(BQ52:BT52) -> 0
B53: Taxes Paid Related to Net Share Settlement of Equity Awards | H53: 0 | I53: 0 | J53: 0 | K53: 0 | L53: 0 | M53: 0 | N53: -3087 | O53: -673 | P53: -66 | Q53: -288 | R53: -4114 | S53: -169 | T53: -92 | U53: -207 | V53: -230 | W53: =+SUM(S53:V53) -> -698 | X53: -462 | Y53: -543 | Z53: -707 | AA53: -485 | AB53: =+SUM(X53:AA53) -> -2197 | AC53: -979 | AD53: -1860 | AE53: -2087 | AF53: -2026 | AG53: =+SUM(AC53:AF53) -> -6952 | AH53: -1533 | AI53: -1917 | AJ53: =-2534 -> -2534 | AK53: =-2937 -> -2937 | AL53: =+SUM(AH53:AK53) -> -8921 | AM53: =-3324 -> -3324 | AN53: =-3347 -> -3347 | AO53: =-4701 -> -4701 | AP53: =-4672 -> -4672 | AQ53: =+SUM(AM53:AP53) -> -16044 | AR53: =-3461 -> -3461 | AS53: =-1645 -> -1645 | AT53: =-1637 -> -1637 | AU53: =-719 -> -719 | AV53: =+SUM(AR53:AU53) -> -7462 | AW53: =-1267 -> -1267 | AX53: =-1324 -> -1324 | AY53: =-1421 -> -1421 | AZ53: =-1558 -> -1558 | BA53: =+SUM(AW53:AZ53) -> -5570 | BB53: =-1764 -> -1764 | BC53: =-1325 -> -1325 | BD53: =-794 -> -794 | BE53: =-847 -> -847 | BF53: =+SUM(BB53:BE53) -> -4730 | BG53: =-1303 -> -1303 | BH53: =-595 -> -595 | BI53: =-537 -> -537 | BJ53: =-585 -> -585 | BK53: =+SUM(BG53:BJ53) -> -3020 | BL53: =-1200 -> -1200 | BM53: =-750 -> -750 | BN53: =-750 -> -750 | BO53: =-750 -> -750 | BP53: =+SUM(BL53:BO53) -> -3450 | BQ53: =-1200 -> -1200 | BR53: =-750 -> -750 | BS53: =-750 -> -750 | BT53: =-750 -> -750 | BU53: =+SUM(BQ53:BT53) -> -3450
B54: Borrowings from Term Loan | H54: 0 | I54: 0 | J54: 0 | K54: 0 | L54: 0 | M54: 0 | N54: 0 | O54: 0 | P54: 0 | Q54: 87 | R54: 87 | S54: 0 | T54: 0 | U54: 0 | V54: 0 | W54: =+SUM(S54:V54) -> 0 | X54: 0 | Y54: 0 | Z54: 0 | AA54: 0 | AB54: =+SUM(X54:AA54) -> 0 | AC54: 0 | AG54: =+SUM(AC54:AF54) -> 0 | AL54: =+SUM(AH54:AK54) -> 0 | AQ54: =+SUM(AM54:AP54) -> 0 | AV54: =+SUM(AR54:AU54) -> 0 | BA54: =+SUM(AW54:AZ54) -> 0 | BF54: =+SUM(BB54:BE54) -> 0 | BI54: =0 -> 0 | BK54: =+SUM(BG54:BJ54) -> 0 | BL54: =0 -> 0 | BM54: =0 -> 0 | BN54: =0 -> 0 | BO54: =0 -> 0 | BP54: =+SUM(BL54:BO54) -> 0 | BQ54: =0 -> 0 | BR54: =0 -> 0 | BS54: =0 -> 0 | BT54: =0 -> 0 | BU54: =+SUM(BQ54:BT54) -> 0
B55: Proceeds from Employee Stock Purchase Plan | H55: 0 | I55: 0 | J55: 0 | K55: 0 | L55: 0 | M55: 0 | N55: 2096 | O55: 0 | P55: 1628 | Q55: 0 | R55: 3724 | S55: 1499 | T55: 0 | U55: 1415 | V55: 0 | W55: =+SUM(S55:V55) -> 2914 | X55: 1632 | Y55: 0 | Z55: 2005 | AA55: 0 | AB55: =+SUM(X55:AA55) -> 3637 | AC55: 2634 | AD55: 3340 | AE55: 2887 | AF55: =0 -> 0 | AG55: =+SUM(AC55:AF55) -> 8861 | AH55: 3346 | AI55: =0 -> 0 | AJ55: =3736 -> 3736 | AK55: =0 -> 0 | AL55: =+SUM(AH55:AK55) -> 7082 | AM55: =4467 -> 4467 | AO55: =4809 -> 4809 | AP55: =1036 -> 1036 | AQ55: =+SUM(AM55:AP55) -> 10312 | AR55: =5710 -> 5710 | AT55: =6233 -> 6233 | AV55: =+SUM(AR55:AU55) -> 11943 | AW55: =6174 -> 6174 | AY55: =5149 -> 5149 | BA55: =+SUM(AW55:AZ55) -> 11323 | BB55: =5046 -> 5046 | BC55: =0 -> 0 | BD55: =4200 -> 4200 | BE55: =0 -> 0 | BF55: =+SUM(BB55:BE55) -> 9246 | BG55: =4446 -> 4446 | BH55: 0 | BI55: =3257 -> 3257 | BJ55: 0 | BK55: =+SUM(BG55:BJ55) -> 7703 | BL55: =4500 -> 4500 | BM55: =0 -> 0 | BN55: =4500 -> 4500 | BO55: =0 -> 0 | BP55: =+SUM(BL55:BO55) -> 9000 | BQ55: =4500 -> 4500 | BR55: =0 -> 0 | BS55: =4500 -> 4500 | BT55: =0 -> 0 | BU55: =+SUM(BQ55:BT55) -> 9000
B56: Proceeds from Capped Call Settlement | AY56: =17518 -> 17518 | BA56: =+SUM(AW56:AZ56) -> 17518 | BB56: =0 -> 0 | BC56: =0 -> 0 | BD56: =0 -> 0 | BE56: =0 -> 0 | BF56: =+SUM(BB56:BE56) -> 0 | BG56: =0 -> 0 | BH56: 0 | BI56: =0 -> 0 | BJ56: 0 | BK56: =+SUM(BG56:BJ56) -> 0 | BL56: =0 -> 0 | BM56: =0 -> 0 | BN56: =0 -> 0 | BO56: =0 -> 0 | BP56: =+SUM(BL56:BO56) -> 0 | BQ56: =0 -> 0 | BR56: =0 -> 0 | BS56: =0 -> 0 | BT56: =0 -> 0 | BU56: =+SUM(BQ56:BT56) -> 0
B57: Proceeds from Stock Option Exercises | H57: 489 | I57: 408 | J57: 297 | K57: 570 | L57: 29 | M57: 1304 | N57: 547 | O57: 884 | P57: 1087 | Q57: 406 | R57: 2924 | S57: 775 | T57: 3336 | U57: 884 | V57: 853 | W57: =+SUM(S57:V57) -> 5848 | X57: 1961 | Y57: 2696 | Z57: 1864 | AA57: 1085 | AB57: =+SUM(X57:AA57) -> 7606 | AC57: 2718 | AD57: =0 -> 0 | AE57: 1866 | AF57: 2295 | AG57: =+SUM(AC57:AF57) -> 6879 | AH57: 1561 | AI57: 2167 | AJ57: =2491 -> 2491 | AK57: =1591 -> 1591 | AL57: =+SUM(AH57:AK57) -> 7810 | AM57: =1427 -> 1427 | AN57: =1103 -> 1103 | AO57: =749 -> 749 | AQ57: =+SUM(AM57:AP57) -> 3279 | AR57: =959 -> 959 | AS57: =246 -> 246 | AT57: =416 -> 416 | AU57: =1697 -> 1697 | AV57: =+SUM(AR57:AU57) -> 3318 | AW57: =181 -> 181 | AX57: =2501 -> 2501 | AY57: =302 -> 302 | AZ57: =69 -> 69 | BA57: =+SUM(AW57:AZ57) -> 3053 | BB57: =1080 -> 1080 | BC57: =324 -> 324 | BD57: =32 -> 32 | BE57: =130 -> 130 | BF57: =+SUM(BB57:BE57) -> 1566 | BG57: =1589 -> 1589 | BH57: 0 | BI57: =0 -> 0 | BJ57: 0 | BK57: =+SUM(BG57:BJ57) -> 1589 | BL57: =200 -> 200 | BM57: =200 -> 200 | BN57: =200 -> 200 | BO57: =200 -> 200 | BP57: =+SUM(BL57:BO57) -> 800 | BQ57: =200 -> 200 | BR57: =200 -> 200 | BS57: =200 -> 200 | BT57: =200 -> 200 | BU57: =+SUM(BQ57:BT57) -> 800
D59: ______ | E59: ______ | F59: ______ | G59: ______ | H59: ______ | I59: ______ | J59: ______ | K59: ______ | L59: ______ | M59: ______ | N59: ______ | O59: ______ | P59: ______ | Q59: ______ | R59: ______ | S59: ______ | T59: ______ | U59: ______ | V59: ______ | W59: ______ | X59: ______ | Y59: ______ | Z59: ______ | AA59: ______ | AB59: ______ | AC59: ______ | AD59: ______ | AE59: ______ | AF59: ______ | AG59: ______ | AH59: ______ | AI59: ______ | AJ59: ______ | AK59: ______ | AL59: ______ | AM59: ______ | AN59: ______ | AO59: ______ | AP59: ______ | AQ59: ______ | AR59: ______ | AS59: ______ | AT59: ______ | AU59: ______ | AV59: ______ | AW59: ______ | AX59: ______ | AY59: ______ | AZ59: ______ | BA59: ______ | BB59: ______ | BC59: ______ | BD59: ______ | BE59: ______ | BF59: ______ | BG59: ______ | BH59: ______ | BI59: ______ | BJ59: ______ | BK59: ______ | BL59: ______ | BM59: ______ | BN59: ______ | BO59: ______ | BP59: ______ | BQ59: ______ | BR59: ______ | BS59: ______ | BT59: ______ | BU59: ______
B60: Net Cash (Used In)/Provided by Financing Activities | H60: =SUM(H40:H57) -> 26669 | I60: =SUM(I40:I57) -> 349 | J60: =SUM(J40:J57) -> -1293 | K60: =SUM(K40:K57) -> 96408 | L60: =SUM(L40:L57) -> -678 | M60: =SUM(M40:M57) -> 94786 | N60: =SUM(N40:N57) -> -512 | O60: =SUM(O40:O57) -> 211 | ... BU60: =SUM(BU40:BU57) -> 6350
B62: Effect of Foreign Exchange Rates on Cash | H62: -20 | I62: -244 | J62: 157 | K62: -53 | L62: -62 | M62: -202 | N62: 151 | O62: -77 | P62: -14 | Q62: -263 | R62: -203 | S62: -76 | T62: 220 | U62: 175 | V62: -38 | W62: =+SUM(S62:V62) -> 281 | X62: -36 | Y62: -278 | Z62: -114 | AA62: -266 | AB62: =+SUM(X62:AA62) -> -694 | AC62: -148 | AD62: -3 | AE62: -497 | AF62: 317 | AG62: =+SUM(AC62:AF62) -> -331 | AH62: -560 | AI62: 259 | AJ62: =461 -> 461 | AK62: =519 -> 519 | AL62: =+SUM(AH62:AK62) -> 679 | AM62: =-500 -> -500 | AN62: 207 | AO62: =-556 -> -556 | AP62: =-423 -> -423 | AQ62: =+SUM(AM62:AP62) -> -1272 | AR62: =-800 -> -800 | AS62: =-2871 -> -2871 | AT62: =-2036 -> -2036 | AU62: =2862 -> 2862 | AV62: =+SUM(AR62:AU62) -> -2845 | AW62: =-33 -> -33 | AX62: =-304 -> -304 | AY62: =-1673 -> -1673 | AZ62: =3212 -> 3212 | BA62: =+SUM(AW62:AZ62) -> 1202 | BB62: =-1493 -> -1493 | BC62: =-583 -> -583 | BD62: =2846 -> 2846 | BE62: -3529 | BF62: =+SUM(BB62:BE62) -> -2759 | BG62: =1334 -> 1334 | BH62: =3513 -> 3513 | BI62: =422 -> 422 | BJ62: =410 -> 410 | BK62: =+SUM(BG62:BJ62) -> 5679 | BL62: =0 -> 0 | BM62: =0 -> 0 | BN62: =0 -> 0 | BO62: =0 -> 0 | BP62: =+SUM(BL62:BO62) -> 0 | BQ62: =0 -> 0 | BR62: =0 -> 0 | BS62: =0 -> 0 | BT62: =0 -> 0 | BU62: =+SUM(BQ62:BT62) -> 0
D63: ______ | E63: ______ | F63: ______ | G63: ______ | H63: ______ | I63: ______ | J63: ______ | K63: ______ | L63: ______ | M63: ______ | N63: ______ | O63: ______ | P63: ______ | Q63: ______ | R63: ______ | S63: ______ | T63: ______ | U63: ______ | V63: ______ | W63: ______ | X63: ______ | Y63: ______ | Z63: ______ | AA63: ______ | AB63: ______ | AC63: ______ | AD63: ______ | AE63: ______ | AF63: ______ | AG63: ______ | AH63: ______ | AI63: ______ | AJ63: ______ | AK63: ______ | AL63: ______ | AM63: ______ | AN63: ______ | AO63: ______ | AP63: ______ | AQ63: ______ | AR63: ______ | AS63: ______ | AT63: ______ | AU63: ______ | AV63: ______ | AW63: ______ | AX63: ______ | AY63: ______ | AZ63: ______ | BA63: ______ | BB63: ______ | BC63: ______ | BD63: ______ | BE63: ______ | BF63: ______ | BG63: ______ | BH63: ______ | BI63: ______ | BJ63: ______ | BK63: ______ | BL63: ______ | BM63: ______ | BN63: ______ | BO63: ______ | BP63: ______ | BQ63: ______ | BR63: ______ | BS63: ______ | BT63: ______ | BU63: ______
B64: Net Increase (Decrease) in Cash and Equivalents | H64: =SUM(H60:H62)+H37+H26 -> 16211 | I64: =SUM(I60:I62)+I37+I26 -> -3480 | J64: =SUM(J60:J62)+J37+J26 -> -6343 | K64: =SUM(K60:K62)+K37+K26 -> 96984 | L64: =SUM(L60:L62)+L37+L26 -> -37431 | M64: =SUM(M60:M62)+M37+M26 -> 49730 | N64: =SUM(N60:N62)+N37+N26 -> -3045 | O64: =SUM(O60:O62)+O37+O26 -> 1247 | ... BU64: =SUM(BU60:BU62)+BU37+BU26 -> 137080.35
B67: Cash and Equivalents at Beginning of Period | H67: 20612 | I67: =+H68 -> 36823 | J67: =+I68 -> 33343 | K67: =+J68 -> 27000 | L67: =+K68 -> 123984 | M67: =+H68 -> 36823 | N67: =+M68 -> 86553 | O67: =+N68 -> 83508 | P67: =+O68 -> 84755 | Q67: =+P68 -> 87715 | R67: =+M68 -> 86553 | S67: =+R68 -> 53148 | T67: =+S68 -> 50662 | U67: =+T68 -> 53068 | V67: =+U68 -> 49055 | W67: =+R68 -> 53148 | X67: =+W68 -> 51762 | Y67: =+X68 -> 100146 | Z67: =+Y68 -> 101231 | AA67: =+Z68 -> 131160 | AB67: =+W68 -> 51762 | AC67: =+AB68 -> 99565 | AD67: =+AC68 -> 89869 | AE67: =+AD68 -> 126569 | AF67: =+AE68 -> 114925 | AG67: =+AB68 -> 99565 | AH67: =+AG68 -> 123413 | AI67: =+AH68 -> 204434 | AJ67: =+AI68 -> 280626 | AK67: =+AJ68 -> 239709 | AL67: =+AG68 -> 123413 | AM67: =+AL68 -> 173617 | AN67: =+AM68 -> 503840 | AO67: =+AN68 -> 493605 | AP67: =+AO68 -> 227530 | AQ67: =+AL68 -> 173617 | AR67: =+AQ68 -> 165017 | AS67: =+AR68 -> 141917 | AT67: =+AS68 -> 166174 | AU67: =+AT68 -> 168868 | AV67: =+AQ68 -> 165017 | AW67: =+AV68 -> 207804 | AX67: =+AW68 -> 206274 | AY67: =+AX68 -> 186446 | AZ67: =+AY68 -> 183215 | BA67: =+AV68 -> 207804 | BB67: =+BA68+3 -> 214130 | BC67: =+BB68 -> 206375 | BD67: =+BC68 -> 244548 | BE67: =+BD68 -> 230108 | BF67: =+BA68 -> 214127 | BG67: =+BE68 -> 342101 | BH67: =+BG68 -> 298711 | BI67: =+BH68 -> 261327 | BJ67: =+BI68 -> 130613 | BK67: =+BF68 -> 342098 | BL67: =+BK68 -> 246661 | BM67: =+BL68 -> 271891.32 | BN67: =+BM68 -> 306313.54 | BO67: =+BN68 -> 333933.51 | BP67: =+BK68 -> 246661 | BQ67: =+BP68 -> 383052.41 | BR67: =+BQ68 -> 406981.17 | BS67: =+BR68 -> 437336.4 | BT67: =+BS68 -> 467636.61 | BU67: =+BP68 -> 383052.41
B68: Cash and Equivalents at End of Period | H68: =+H67+H64 -> 36823 | I68: =+I67+I64 -> 33343 | J68: =+J67+J64 -> 27000 | K68: =+K67+K64 -> 123984 | L68: =+L67+L64 -> 86553 | M68: =+M67+M64 -> 86553 | N68: =+N67+N64 -> 83508 | O68: =+O67+O64 -> 84755 | ... V68: =+V67+V64 -> 51562 | W68: 51762 | X68: =+X67+X64 -> 100146 | Y68: =+Y67+Y64 -> 101231 | Z68: =+Z67+Z64 -> 131160 | AA68: =+AA67+AA64 -> 99565 | AB68: =+AB67+AB64 -> 99565 | AC68: =+AC67+AC64 -> 89869 | AD68: =+AD67+AD64 -> 126569 | AE68: =+AE67+AE64 -> 114925 | ... BU68: =+BU67+BU64 -> 520132.76
B70: Free Cash Flow
B71: Cash from Operations | H71: =+H26 -> -3356 | I71: =+I26 -> -3012 | J71: =+J26 -> -1241 | K71: =+K26 -> 2273 | L71: =+L26 -> 73 | M71: =+M26 -> -1907 | N71: =+N26 -> -1592 | O71: =+O26 -> 1863 | ... BU71: =+BU26 -> 155747.01
B72: Capital Expenditures + Capitalized Software | H72: =+H30 -> -7082 | I72: =+I30 -> -573 | J72: =+J30 -> -622 | K72: =+K30 -> -1644 | L72: =+L30 -> -1297 | M72: =+M30 -> -4136 | N72: =+N30 -> -1092 | O72: =+O30 -> -750 | ... AG72: =+AG30 -> -29428 | AH72: =SUM(AH30,,AH31) -> -4230 | AI72: =SUM(AI30,,AI31) -> -2673 | AJ72: =SUM(AJ30,,AJ31) -> -4629 | AK72: =SUM(AK30,,AK31) -> -8400 | AL72: =SUM(AL30,,AL31) -> -19932 | AM72: =SUM(AM30,,AM31) -> -2730 | AN72: =SUM(AN30,,AN31) -> -4146 | AO72: =SUM(AO30,,AO31) -> -5121 | ... BU72: =SUM(BU30,,BU31) -> -25016.656
D73: ______ | E73: ______ | F73: ______ | G73: ______ | H73: ______ | I73: ______ | J73: ______ | K73: ______ | L73: ______ | M73: ______ | N73: ______ | O73: ______ | P73: ______ | Q73: ______ | R73: ______ | S73: ______ | T73: ______ | U73: ______ | V73: ______ | W73: ______ | X73: ______ | Y73: ______ | Z73: ______ | AA73: ______ | AB73: ______ | AC73: ______ | AD73: ______ | AE73: ______ | AF73: ______ | AG73: ______ | AH73: ______ | AI73: ______ | AJ73: ______ | AK73: ______ | AL73: ______ | AM73: ______ | AN73: ______ | AO73: ______ | AP73: ______ | AQ73: ______ | AR73: ______ | AS73: ______ | AT73: ______ | AU73: ______ | AV73: ______ | AW73: ______ | AX73: ______ | AY73: ______ | AZ73: ______ | BA73: ______ | BB73: ______ | BC73: ______ | BD73: ______ | BE73: ______ | BF73: ______ | BG73: ______ | BH73: ______ | BI73: ______ | BJ73: ______ | BK73: ______ | BL73: ______ | BM73: ______ | BN73: ______ | BO73: ______ | BP73: ______ | BQ73: ______ | BR73: ______ | BS73: ______ | BT73: ______ | BU73: ______
B74: Free Cash Flow | H74: =H71+H72 -> -10438 | I74: =I71+I72 -> -3585 | J74: =J71+J72 -> -1863 | K74: =K71+K72 -> 629 | L74: =L71+L72 -> -1224 | M74: =M71+M72 -> -6043 | N74: =N71+N72 -> -2684 | O74: =O71+O72 -> 1113 | ... BU74: =BU71+BU72 -> 130730.35
B75: Yr-Yr Growth | M75: =+M74/H74-1 -> -0.42105767 | N75: =+N74/I74-1 -> -0.25132497 | O75: =+O74/J74-1 -> -1.5974235 | P75: =+P74/K74-1 -> -0.48330684 | Q75: =+Q74/L74-1 -> -5.7867647 | R75: =+R74/M74-1 -> -1.7633626 | S75: =+S74/N74-1 -> -1.7399404 | T75: =+T74/O74-1 -> -5.6936208 | ... BU75: =+BU74/BP74-1 -> 0.0052978997
B76: Q-Q Growth | J76: =+J74/I74-1 -> -0.48033473 | K76: =+K74/J74-1 -> -1.3376275 | L76: =+L74/K74-1 -> -2.9459459 | N76: =+N74/L74-1 -> 1.1928105 | O76: =+O74/N74-1 -> -1.4146796 | P76: =+P74/O74-1 -> -0.70799641 | Q76: =+Q74/P74-1 -> 17.027692 | S76: =+S74/Q74-1 -> -0.66103431 | T76: =+T74/S74-1 -> -3.6304129 | U76: =+U74/T74-1 -> -1.9218989 | V76: =+V74/U74-1 -> 0.42940199 | X76: =+X74/V74-1 -> -0.2520337 | Y76: =+Y74/X74-1 -> -3.4503787 | Z76: =+Z74/Y74-1 -> -0.46072759 | AA76: =+AA74/Z74-1 -> -2.1059671 | AC76: =+AC74/AA74-1 -> -3.9274419 | AD76: =+AD74/AC74-1 -> -0.69285941 | AE76: =+AE74/AD74-1 -> 0.10877919 | AF76: =+AF74/AE74-1 -> -1.7263396 | AH76: =+AH74/AF74-1 -> -3.1003854 | AI76: =+AI74/AH74-1 -> -0.80506772 | AJ76: =+AJ74/AI74-1 -> -3.890632 | AK76: =+AK74/AJ74-1 -> -2.212281 | AM76: =+AM74/AK74-1 -> -3.2851113 | AN76: =+AN74/AM74-1 -> -0.71788413 | AO76: =+AO74/AN74-1 -> 1.8426587 | AP76: =+AP74/AO74-1 -> -1.1520905 | AR76: =+AR74/AP74-1 -> -2.7567692 | AS76: =+AS74/AR74-1 -> -1.3286311 | AT76: =+AT74/AS74-1 -> -8.6764706 | AU76: =+AU74/AT74-1 -> 1.9460495 | AW76: =+AW74/AU74-1 -> -1.0428471 | AX76: =+AX74/AW74-1 -> -21.985234 | AY76: =+AY74/AX74-1 -> -1.0227513 | AZ76: =+AZ74/AY74-1 -> -104.52921 | BB76: =+BB74/AZ74-1 -> -0.54303449 | BC76: =+BC74/BB74-1 -> 0.060688603 | BD76: =+BD74/BC74-1 -> 0.3183359 | BE76: =+BE74/BD74-1 -> 0.52828424 | BG76: =+BG74/BE74-1 -> -0.58062268 | BH76: =+BH74/BG74-1 -> 0.71333631 | BI76: =+BI74/BH74-1 -> -0.2878193 | BJ76: =+BJ74/BI74-1 -> 0.072664475 | BL76: =+BL74/BJ74-1 -> -0.32721396 | BM76: =+BM74/BL74-1 -> 0.60937461 | BN76: =+BN74/BM74-1 -> -0.32317779 | BO76: =+BO74/BN74-1 -> 1.0983925 | BQ76: =+BQ74/BO74-1 -> -0.58870103 | BR76: =+BR74/BQ74-1 -> 0.51282893 | BS76: =+BS74/BR74-1 -> -0.1473866 | BT76: =+BT74/BS74-1 -> 1.0131203
B77: Free Cash Flow Margin | H77: =+H74/H84 -> -0.13577003 | I77: =+I74/I84 -> -0.15209367 | J77: =+J74/J84 -> -0.072237301 | K77: =+K74/K84 -> 0.022216728 | L77: =+L74/L84 -> -0.037256872 | M77: =+M74/M84 -> -0.054674918 | N77: =+N74/N84 -> -0.077135303 | O77: =+O74/O84 -> 0.029864763 | ... BU77: =+BU74/BU84 -> 0.15328365
B78: Rule of 40 | H78: =H77+H85 -> -0.13577003 | I78: =I77+I85 -> 0.25630738 | J78: =J77+J85 -> 0.37015643 | K78: =K77+K85 -> 0.41490697 | L78: =L77+L85 -> 0.46048646 | M78: =M77+M85 -> 0.38296816 | N78: =N77+N85 -> 0.39908548 | O78: =O77+O85 -> 0.47492099 | ... R78: =R77+R85 -> 0.45373468 | S78: ASC 605 | T78: -------------------------------------------------------------------------------------I | X78: ASC 606 | Y78: =Y77+Y85 -> 0.015922068 | Z78: =Z77+Z85 -> 0.12533751 | AA78: =AA77+AA85 -> 0.30063714 | AB78: =AB77+AB85 -> 0.18710436 | AC78: =AC77+AC85 -> 0.041470244 | AD78: =AD77+AD85 -> 0.26539909 | AE78: =AE77+AE85 -> 0.24314299 | AF78: =AF77+AF85 -> 0.39212987 | ... BU78: =BU77+BU85 -> 0.16996232
B80: Source: Rapid7 Inc. financial statements and Needham & Company, LLC estimates
B83: I/S
B84: Revenue | D84: =+IS!D52 -> 16736 | E84: =+IS!E52 -> 17880 | F84: =+IS!F52 -> 20329 | G84: =+IS!G52 -> 21935 | H84: =+IS!H52 -> 76880 | I84: =+IS!I52 -> 23571 | J84: =+IS!J52 -> 25790 | K84: =+IS!K52 -> 28312 | ... BU84: =+IS!BU52 -> 852865.58
B85: Yr-Yr Growth | I85: =+I84/D84-1 -> 0.40840105 | J85: =+J84/E84-1 -> 0.44239374 | K85: =+K84/F84-1 -> 0.39269025 | L85: =+L84/G84-1 -> 0.49774333 | M85: =+M84/H84-1 -> 0.43764308 | N85: =+N84/I84-1 -> 0.47622078 | O85: =+O84/J84-1 -> 0.44505622 | P85: =+P84/K84-1 -> 0.4248022 | ... BU85: =+BU84/BP84-1 -> 0.01667866
B86: Q-Q Growth | E86: =+E84/D84-1 -> 0.068355641 | F86: =+F84/E84-1 -> 0.13696868 | G86: =+G84/F84-1 -> 0.079000443 | I86: =+I84/G84-1 -> 0.074583998 | J86: =+J84/I84-1 -> 0.094141106 | K86: =+K84/J84-1 -> 0.097789841 | L86: =+L84/K84-1 -> 0.16039135 | N86: =+N84/L84-1 -> 0.05914224 | O86: =+O84/N84-1 -> 0.071042649 | P86: =+P84/O84-1 -> 0.082403134 | Q86: =+Q84/P84-1 -> 0.11638861 | S86: =+S84/Q84-1 -> 0.0046853488 | T86: =+T84/S84-1 -> 0.048579954 | U86: =+U84/T84-1 -> 0.064877853 | V86: =+V84/U84-1 -> 0.14271293 | X86: =+X84/V84-1 -> -0.055706639 | Y86: =+Y84/X84-1 -> 0.072016876 | Z86: =+Z84/Y84-1 -> 0.067144642 | AA86: =+AA84/Z84-1 -> 0.10270184 | AC86: =+AC84/AA84-1 -> 0.064199506 | AD86: =+AD84/AC84-1 -> 0.078895949 | AE86: =+AE84/AD84-1 -> 0.053141504 | AF86: =+AF84/AE84-1 -> 0.10213457 | AH86: =+AH84/AF84-1 -> 0.029373254 | AI86: =+AI84/AH84-1 -> 0.048463006 | AJ86: =+AJ84/AI84-1 -> 0.06230791 | AK86: =+AK84/AJ84-1 -> 0.076935522 | AM86: =+AM84/AK84-1 -> 0.037928932 | AN86: =+AN84/AM84-1 -> 0.076372274 | AO86: =+AO84/AN84-1 -> 0.10657248 | AP86: =+AP84/AO84-1 -> 0.083949276 | AR86: =+AR84/AP84-1 -> 0.037892876 | AS86: =+AS84/AR84-1 -> 0.063989986 | AT86: =+AT84/AS84-1 -> 0.049625272 | AU86: =+AU84/AT84-1 -> 0.049577561 | AW86: =+AW84/AU84-1 -> -0.0070739759 | AX86: =+AX84/AW84-1 -> 0.039568934 | AY86: =+AY84/AX84-1 -> 0.044222831 | AZ86: =+AZ84/AY84-1 -> 0.032311924 | BB86: =+BB84/AZ84-1 -> -0.00081357055 | BC86: =+BC84/BB84-1 -> 0.014090619 | BD86: =+BD84/BC84-1 -> 0.03203504 | BE86: =+BE84/BD84-1 -> 0.0074864666 | BG86: =+BG84/BE84-1 -> -0.027781246 | BH86: =+BH84/BG84-1 -> 0.018739328 | BI86: =+BI84/BH84-1 -> 0.017586943 | BJ86: =+BJ84/BI84-1 -> -0.0026243347 | BL86: =+BL84/BJ84-1 -> -0.043324724 | BM86: =+BM84/BL84-1 -> 0.0046355545 | BN86: =+BN84/BM84-1 -> 0.0062953918 | BO86: =+BO84/BN84-1 -> 0.0070039777 | BQ86: =+BQ84/BO84-1 -> -0.00094033119 | BR86: =+BR84/BQ84-1 -> 0.0046804348 | BS86: =+BS84/BR84-1 -> 0.0055176735 | BT86: =+BT84/BS84-1 -> 0.0068325504
B88: Adjusted EBITDA | H88: =+'Billings & Recs'!H92 -> -22842 | I88: =+'Billings & Recs'!I92 -> -4853 | J88: =+'Billings & Recs'!J92 -> -6155 | K88: =+'Billings & Recs'!K92 -> -6698 | L88: =+'Billings & Recs'!L92 -> -10992 | M88: =+'Billings & Recs'!M92 -> -28698 | N88: =+'Billings & Recs'!N92 -> -8389 | O88: =+'Billings & Recs'!O92 -> -7932 | ... BU88: =+'Billings & Recs'!BU92 -> 123828.32
B89: Yr-Yr Growth | M89: =+M88/H88-1 -> 0.25636985 | N89: =+N88/I88-1 -> 0.72862147 | O89: =+O88/J88-1 -> 0.28870837 | P89: =+P88/K88-1 -> -0.38548821 | Q89: =+Q88/L88-1 -> -0.58415211 | R89: =+R88/M88-1 -> -0.12858039 | S89: =+S88/N88-1 -> -0.45559661 | T89: =+T88/O88-1 -> -0.36548159 | ... BU89: =+BU88/BP88-1 -> -0.048643982
B90: Q-Q Growth | J90: =+J88/I88-1 -> 0.26828766 | K90: =+K88/J88-1 -> 0.088220959 | L90: =+L88/K88-1 -> 0.64108689 | N90: =+N88/L88-1 -> -0.23680859 | O90: =+O88/N88-1 -> -0.0544761 | P90: =+P88/O88-1 -> -0.48108926 | Q90: =+Q88/P88-1 -> 0.11054422 | S90: =+S88/Q88-1 -> -0.00087508204 | T90: =+T88/S88-1 -> 0.10203635 | U90: =+U88/T88-1 -> 0.11265647 | V90: =+V88/U88-1 -> 0.1175 | X90: =+X88/V88-1 -> 0.18584212 | Y90: =+Y88/X88-1 -> -0.42770516 | Z90: =+Z88/Y88-1 -> -0.74052272 | AA90: =+AA88/Z88-1 -> -0.40290381 | AC90: =+AC88/AA88-1 -> -4.9620061 | AD90: =+AD88/AC88-1 -> 0.05331799 | AE90: =+AE88/AD88-1 -> 0.25491624 | AF90: =+AF88/AE88-1 -> 0.060359837 | AH90: =+AH88/AF88-1 -> -1.2134647 | AI90: =+AI88/AH88-1 -> -10.687179 | AJ90: =+AJ88/AI88-1 -> -0.2335892 | AK90: =+AK88/AJ88-1 -> -0.48920739 | AM90: =+AM88/AK88-1 -> 0.94624746 | AN90: =+AN88/AM88-1 -> 0.74222685 | AO90: =+AO88/AN88-1 -> -0.011864407 | AP90: =+AP88/AO88-1 -> -1.1920089 | AR90: =+AR88/AP88-1 -> -0.38360483 | AS90: =+AS88/AR88-1 -> -7.8056266 | AT90: =+AT88/AS88-1 -> 1.2460228 | AU90: =+AU88/AT88-1 -> 0.37757948 | AW90: =+AW88/AU88-1 -> -0.31898785 | AX90: =+AX88/AW88-1 -> 0.13245348 | AY90: =+AY88/AX88-1 -> 1.2533991 | AZ90: =+AZ88/AY88-1 -> 0.10453116 | BB90: =+BB88/AZ88-1 -> -0.016725723 | BC90: =+BC88/BB88-1 -> -0.025333019 | BD90: =+BD88/BC88-1 -> 0.10222721 | BE90: =+BE88/BD88-1 -> -0.075334944 | BG90: =+BG88/BE88-1 -> -0.16005182 | BH90: =+BH88/BG88-1 -> 0.096405985 | BI90: =+BI88/BH88-1 -> 0.020305759 | BJ90: =+BJ88/BI88-1 -> -0.1540194 | BL90: =+BL88/BJ88-1 -> -0.29099597 | BM90: =+BM88/BL88-1 -> 0.27030206 | BN90: =+BN88/BM88-1 -> 0.071827816 | BO90: =+BO88/BN88-1 -> -0.0046995951 | BQ90: =+BQ88/BO88-1 -> -0.11934053 | BR90: =+BR88/BQ88-1 -> -0.015408359 | BS90: =+BS88/BR88-1 -> 0.014982932 | BT90: =+BT88/BS88-1 -> -0.0078217196
B93: SBC | AH93: ='Billings & Recs'!AH111 -> 13347 | AI93: ='Billings & Recs'!AI111 -> 16446 | AJ93: ='Billings & Recs'!AJ111 -> 17128 | AK93: ='Billings & Recs'!AK111 -> 16967 | AL93: ='Billings & Recs'!AL111 -> 63888 | AM93: ='Billings & Recs'!AM111 -> 20862 | AN93: ='Billings & Recs'!AN111 -> 23814 | AO93: ='Billings & Recs'!AO111 -> 29196 | ... BU93: ='Billings & Recs'!BU111 -> 117276.06
B94: SBC as % of FCF | AH94: =AH93/AH74 -> -1.1661861 | AI94: =AI93/AI74 -> -7.3715823 | AJ94: =AJ93/AJ74 -> 2.6559156 | AK94: =AK93/AK74 -> -2.1702481 | AL94: =AL93/AL74 -> -4.2464606 | AM94: =AM93/AM74 -> 1.1677582 | AN94: =AN93/AN74 -> 4.725 | AO94: =AO93/AO74 -> 2.0378307 | ... BU94: =BU93/BU74 -> 0.8970836

Sheet IS
B2: Ending ARR | AR2: =Metrics!AR41*1000 -> 627122 | AS2: =Metrics!AS41*1000 -> 658172 | AT2: =Metrics!AT41*1000 -> 683816 | AU2: =Metrics!AU41*1000 -> 714231 | AW2: =Metrics!AW41*1000 -> 727853 | AX2: =Metrics!AX41*1000 -> 750850 | AY2: =Metrics!AY41*1000 -> 776760 | AZ2: =Metrics!AZ41*1000 -> 805670 | BB2: =Metrics!BB41*1000 -> 807196 | BC2: =Metrics!BC41*1000 -> 815630 | BD2: =Metrics!BD41*1000 -> 823104 | BE2: =Metrics!BE41*1000 -> 839819 | BG2: =Metrics!BG41*1000 -> 837220 | BH2: =Metrics!BH41*1000 -> 840610 | BI2: =Metrics!BI41*1000 -> 837730 | BJ2: =Metrics!BJ41*1000 -> 839900 | BL2: =Metrics!BL41*1000 -> 830522.24 | BM2: =Metrics!BM41*1000 -> 831363.29 | BN2: =Metrics!BN41*1000 -> 831865.89 | BO2: =Metrics!BO41*1000 -> 832340.9 | BQ2: =Metrics!BQ41*1000 -> 855437.91 | BR2: =Metrics!BR41*1000 -> 857966.92 | BS2: =Metrics!BS41*1000 -> 860149.33 | BT2: =Metrics!BT41*1000 -> 861472.83
B3: Implied Quarterly Revenue | AR3: =AR2/4 -> 156780.5 | AS3: =AS2/4 -> 164543 | AT3: =AT2/4 -> 170954 | AU3: =AU2/4 -> 178557.75 | AW3: =AW2/4 -> 181963.25 | AX3: =AX2/4 -> 187712.5 | AY3: =AY2/4 -> 194190 | AZ3: =AZ2/4 -> 201417.5 | BB3: =BB2/4 -> 201799 | BC3: =BC2/4 -> 203907.5 | BD3: =BD2/4 -> 205776 | BE3: =BE2/4 -> 209954.75 | BG3: =BG2/4 -> 209305 | BH3: =BH2/4 -> 210152.5 | BI3: =BI2/4 -> 209432.5 | BJ3: =BJ2/4 -> 209975 | BL3: =BL2/4 -> 207630.56 | BM3: =BM2/4 -> 207840.82 | BN3: =BN2/4 -> 207966.47 | BO3: =BO2/4 -> 208085.22 | BQ3: =BQ2/4 -> 213859.48 | BR3: =BR2/4 -> 214491.73 | BS3: =BS2/4 -> 215037.33 | BT3: =BT2/4 -> 215368.21
B4: Implied Go-Get to Achieve High-End | AS4: =AS9-AR3 -> 8219.5 | AT4: =AT9-AS3 -> 12457 | AU4: =AU9-AT3 -> 10046 | AW4: =AW9-AU3 -> 3442.25 | AX4: =AX9-AW3 -> 7036.75 | AY4: =AY9-AX3 -> 10287.5 | AZ4: =AZ9-AY3 -> 7810 | BB4: =BB9-AZ3 -> 3582.5 | BC4: =BC9-BB3 -> 3201 | BD4: =BD9-BC3 -> 7092.5 | BE4: =BE9-BD3 -> 7224 | BG4: =BG9-BE3 -> -954.75 | BH4: =BH9-BG3 -> 3695 | BI4: =BI9-BH3 -> 6847.5 | BJ4: =BJ9-BI3 -> 11567.5 | BL4: =BL9-BJ3 -> -209975 | BM4: =BM9-BL3 -> -207630.56 | BN4: =BN9-BM3 -> -207840.82 | BO4: =BO9-BN3 -> -207966.47 | BQ4: =BQ9-BO3 -> -208085.22 | BR4: =BR9-BQ3 -> -213859.48 | BS4: =BS9-BR3 -> -214491.73 | BT4: =BT9-BS3 -> -215037.33
B6: Achieved Go-Get | AS6: =AS4+AS13 -> 10674.5 | AT6: =AT4+AT13 -> 11222 | AU6: =AU4+AU13 -> 13525 | AW6: =AW4+AW13 -> 4616.25 | AX6: =AX4+AX13 -> 8458.75 | AY6: =AY4+AY13 -> 11130.5 | AZ6: =AZ4+AZ13 -> 11078 | BB6: =BB4+BB13 -> 3683.5 | BC6: =BC4+BC13 -> 6192 | BD6: =BD4+BD13 -> 10746.5 | BE6: =BE4+BE13 -> 10485 | BG6: =BG4+BG13 -> 298.25 | BH6: =BH4+BH13 -> 5195 | BI6: =BI4+BI13 -> 8847.5 | BJ6: =BJ4+BJ13 -> 14167.5 | BL6: =BL4+BL13 -> -207975 | BM6: =BM4+BM13 -> -205630.56 | BN6: =BN4+BN13 -> -205840.82 | BO6: =BO4+BO13 -> -205966.47 | BQ6: =BQ4+BQ13 -> -206085.22 | BR6: =BR4+BR13 -> -211859.48 | BS6: =BS4+BS13 -> -212491.73 | BT6: =BT4+BT13 -> -213037.33
B7: Achieved Go-Get % | AS7: =AS6/AS4 -> 1.29868 | AT7: =AT6/AT4 -> 0.90085895 | AU7: =AU6/AU4 -> 1.346307 | AW7: =AW6/AW4 -> 1.341056 | AX7: =AX6/AX4 -> 1.2020819 | AY7: =AY6/AY4 -> 1.0819441 | AZ7: =AZ6/AZ4 -> 1.4184379 | BB7: =BB6/BB4 -> 1.0281926 | BC7: =BC6/BC4 -> 1.9343955 | BD7: =BD6/BD4 -> 1.5151921 | BE7: =BE6/BE4 -> 1.451412 | BG7: =BG6/BG4 -> -0.31238544 | BH7: =BH6/BH4 -> 1.405954 | BI7: =BI6/BI4 -> 1.2920774 | BJ7: =BJ6/BJ4 -> 1.2247677 | BL7: =BL6/BL4 -> 0.99047506 | BM7: =BM6/BM4 -> 0.99036751 | BN7: =BN6/BN4 -> 0.99037725 | BO7: =BO6/BO4 -> 0.99038307 | BQ7: =BQ6/BQ4 -> 0.99038855 | BR7: =BR6/BR4 -> 0.99064806 | BS7: =BS6/BS4 -> 0.99067563 | BT7: =BT6/BT4 -> 0.99069929
B9: High-End of Next Quarter Guide | AR9: 155000 | AS9: 165000 | AT9: 177000 | AU9: 181000 | AW9: 182000 | AX9: 189000 | AY9: 198000 | AZ9: 202000 | BB9: 205000 | BC9: 205000 | BD9: 211000 | BE9: 213000 | BG9: 209000 | BH9: 213000 | BI9: 217000 | BJ9: 221000
B10: YoY Increase | AW10: =AW9-AR9 -> 27000 | AX10: =AX9-AS9 -> 24000 | AY10: =AY9-AT9 -> 21000 | AZ10: =AZ9-AU9 -> 21000 | BB10: =BB9-AW9 -> 23000 | BC10: =BC9-AX9 -> 16000 | BD10: =BD9-AY9 -> 13000 | BE10: =BE9-AZ9 -> 11000 | BG10: =BG9-BB9 -> 4000 | BH10: =BH9-BC9 -> 8000 | BI10: =BI9-BD9 -> 6000 | BJ10: =BJ9-BE9 -> 8000 | BL10: =BL9-BG9 -> -209000 | BM10: =BM9-BH9 -> -213000 | BN10: =BN9-BI9 -> -217000 | BO10: =BO9-BJ9 -> -221000 | BQ10: =BQ9-BL9 -> 0 | BR10: =BR9-BM9 -> 0 | BS10: =BS9-BN9 -> 0 | BT10: =BT9-BO9 -> 0
B11: QoQ Increase | AW11: =AW9-AU9 -> 1000 | AX11: =AX9-AW9 -> 7000 | AY11: =AY9-AX9 -> 9000 | AZ11: =AZ9-AY9 -> 4000 | BB11: =BB9-AZ9 -> 3000 | BC11: =BC9-BB9 -> 0 | BD11: =BD9-BC9 -> 6000 | BE11: =BE9-BD9 -> 2000 | BG11: =BG9-BE9 -> -4000 | BH11: =BH9-BG9 -> 4000 | BI11: =BI9-BH9 -> 4000 | BJ11: =BJ9-BI9 -> 4000 | BL11: =BL9-BJ9 -> -221000 | BM11: =BM9-BL9 -> 0 | BN11: =BN9-BM9 -> 0 | BO11: =BO9-BN9 -> 0 | BQ11: =BQ9-BO9 -> 0 | BR11: =BR9-BQ9 -> 0 | BS11: =BS9-BR9 -> 0 | BT11: =BT9-BS9 -> 0
B13: Beat High-End $ | AR13: =AR52-AR9 -> 2384 | AS13: =AS52-AS9 -> 2455 | AT13: =AT52-AT9 -> -1235 | AU13: =AU52-AU9 -> 3479 | AW13: =AW52-AW9 -> 1174 | AX13: =AX52-AX9 -> 1422 | AY13: =AY52-AY9 -> 843 | AZ13: =AZ52-AZ9 -> 3268 | BB13: =BB52-BB9 -> 101 | BC13: =BC52-BC9 -> 2991 | BD13: =BD52-BD9 -> 3654 | BE13: =BE52-BE9 -> 3261 | BG13: =BG52-BG9 -> 1253 | BH13: =1500 -> 1500 | BI13: =2000 -> 2000 | BJ13: 2600 | BL13: 2000 | BM13: 2000 | BN13: 2000 | BO13: 2000 | BQ13: 2000 | BR13: 2000 | BS13: 2000 | BT13: 2000
B14: Beat High-End % | AR14: =AR13/AR9 -> 0.015380645 | AS14: =AS13/AS9 -> 0.014878788 | AT14: =AT13/AT9 -> -0.0069774011 | AU14: =AU13/AU9 -> 0.019220994 | AW14: =AW13/AW9 -> 0.0064505495 | AX14: =AX13/AX9 -> 0.0075238095 | AY14: =AY13/AY9 -> 0.0042575758 | AZ14: =AZ13/AZ9 -> 0.016178218 | BB14: =BB13/BB9 -> 0.00049268293 | BC14: =BC13/BC9 -> 0.014590244 | BD14: =BD13/BD9 -> 0.017317536 | BE14: =BE13/BE9 -> 0.015309859 | BG14: =BG13/BG9 -> 0.0059952153 | BH14: =BH13/BH9 -> 0.0070422535 | BI14: =BI13/BI9 -> 0.0092165899 | BJ14: =BJ13/BJ9 -> 0.011764706 | BL14: =BL13/BL9 -> #DIV/0! | BM14: =BM13/BM9 -> #DIV/0! | BN14: =BN13/BN9 -> #DIV/0! | BO14: =BO13/BO9 -> #DIV/0! | BQ14: =BQ13/BQ9 -> #DIV/0! | BR14: =BR13/BR9 -> #DIV/0! | BS14: =BS13/BS9 -> #DIV/0! | BT14: =BT13/BT9 -> #DIV/0!
B20: Rapid7 Inc.—Quarterly Income Statement
B21: (Thousands Of Dollars, Except Per-Share Data)
D22: 2014A | H22: Year | I22: 2015A | M22: Year | N22: 2016A | R22: Year | S22: 2017A | W22: Year | X22: 2018A | AB22: Year | AC22: 2019A | AG22: Year | AH22: 2020A | AL22: Year | AM22: 2021A | AQ22: Year | AR22: 2022A | AV22: Year | AW22: 2023A | BA22: Year | BB22: 2024A | BF22: Year | BG22: 2025E | BK22: Year | BL22: 2026E | BP22: Year | BQ22: 2027E | BU22: Year
D23: 1Q-Mar 14A | E23: 2Q-Jun 14A | F23: 3Q-Sep 14A | G23: 4Q-Dec 14A | H23: 2014A | I23: 1Q-Mar 15 | J23: 2Q-Jun 15 | K23: 3Q-Sep 15 | L23: 4Q-Dec 15 | M23: 2015A | N23: 1Q-Mar 16 | O23: 2Q-Jun 16 | P23: 3Q-Sep 16 | Q23: 4Q-Dec 16 | R23: 2016A | S23: 1Q-Mar 17A | T23: 2Q-Jun 17A | U23: 3Q-Sep 17A | V23: 4Q-Dec 17A | W23: 2017A | X23: 1Q-Mar 18A | Y23: 2Q-Jun 18A | Z23: 3Q-Sep 18A | AA23: 4Q-Dec 18A | AB23: 2018A | AC23: 1Q-Mar 19A | AD23: 2Q-Jun 19A | AE23: 3Q-Sep 19A | AF23: 4Q-Dec 19A | AG23: 2019A | AH23: 1Q-Mar 20A | AI23: 2Q-Jun 20A | AJ23: 3Q-Sep 20A | AK23: 4Q-Dec 20A | AL23: 2020A | AM23: 1Q-Mar 21A | AN23: 2Q-Jun 21A | AO23: 3Q-Sep 21A | AP23: 4Q-Dec 21A | AQ23: 2021A | AR23: 1Q-Mar 22A | AS23: 2Q-Jun 22A | AT23: 3Q-Sep 22A | AU23: 4Q-Dec 22A | AV23: 2022A | AW23: 1Q-Mar 23A | AX23: 2Q-Jun 23A | AY23: 3Q-Sep 23A | AZ23: 4Q-Dec 23A | BA23: 2023A | BB23: 1Q-Mar 24A | BC23: 2Q-Jun 24A | BD23: 3Q-Sep 24A | BE23: 4Q-Dec 24A | BF23: 2024A | BG23: 1Q-Mar 25A | BH23: 2Q-Jun 25A | BI23: 3Q-Sep 25A | BJ23: 4Q-Dec 25A | BK23: 2025A | BL23: 1Q-Mar 26E | BM23: 2Q-Jun 26E | BN23: 3Q-Sep 26E | BO23: 4Q-Dec 26E | BP23: =BL22 -> 2026E | BQ23: 1Q-Mar 27E | BR23: 2Q-Jun 27E | BS23: 3Q-Sep 27E | BT23: 4Q-Dec 27E | BU23: =BQ22 -> 2027E
B25: Calculated Billings | H25: =+'Billings & Recs'!H12 -> 102081 | I25: =+'Billings & Recs'!I12 -> 27158 | J25: =+'Billings & Recs'!J12 -> 34658 | K25: =+'Billings & Recs'!K12 -> 40953 | L25: =+'Billings & Recs'!L12 -> 53018 | M25: =+'Billings & Recs'!M12 -> 155787 | N25: =+'Billings & Recs'!N12 -> 36336 | O25: =+'Billings & Recs'!O12 -> 50133 | ... BU25: =+'Billings & Recs'!BU12 -> 859450.15
B26: % of Revenue | H26: =+H25/H$52 -> 1.3277966 | I26: =+I25/I$52 -> 1.1521785 | J26: =+J25/J$52 -> 1.3438542 | K26: =+K25/K$52 -> 1.4464891 | L26: =+L25/L$52 -> 1.6137948 | M26: =+M25/M$52 -> 1.4095055 | N26: =+N25/N$52 -> 1.044258 | O26: =+O25/O$52 -> 1.3452023 | ... BU26: =+BU25/BU$52 -> 1.0077205
B27: Yr-Yr Growth | M27: =+M25/H25-1 -> 0.52611162 | N27: =+N25/I25-1 -> 0.3379483 | O27: =+O25/J25-1 -> 0.44650586 | P27: =+P25/K25-1 -> 0.095914829 | Q27: =+Q25/L25-1 -> 0.22284884 | R27: =+R25/M25-1 -> 0.25930277 | S27: =+S25/N25-1 -> 0.20621422 | T27: =+T25/O25-1 -> 0.20130453 | ... BU27: =+BU25/BP25-1 -> 0.017103322
