Workbook
Name \M: [1]VALUE2_1.XLS!#REF!
Name _: #REF!
Name __: #REF!
Name ___: #REF!
Name ____: #REF!
Name ____________Z04: #REF!
Name ____________Z05: #REF!
Name ___________Inv1: #REF!
Name ___________TOP10: #REF!
Name _________Inv1: #REF!
Name _________TOP10: #REF!
Name _______Inv1: #REF!
Name _______TOP10: #REF!
Name ______Inv1: #REF!
Name ______TOP10: #REF!
Name ______Z04: #REF!
Name ______Z05: #REF!
Name _____Inv1: #REF!
Name _____TOP10: #REF!
Name _____Z04: #REF!
Name _____Z05: #REF!
Name ____cat2: #REF!
Name ____Inv1: #REF!
Name ____TOP10: #REF!
Name ____USD03: #REF!
Name ____Z04: #REF!
Name ____Z05: #REF!
Name ___cat2: #REF!
Name ___Inv1: #REF!
Name ___nm1: #REF!
Name ___SEC2: #REF!
Name ___SEC4: #REF!
Name ___SEC5: #REF!
Name ___TOP10: #REF!
Name ___USD03: #REF!
Name ___www2: #REF!
Name ___Z04: #REF!
Name ___Z05: #REF!
Name __1__123Graph_ACHART_3: #REF!
Name __123Graph_A: #REF!
Name __123Graph_AChart1: #REF!
Name __123Graph_AChart2: #REF!
Name __123Graph_AChart3: #REF!
Name __123Graph_AChart4: #REF!
Name __123Graph_AChart5: #REF!
Name __123Graph_AChart6: #REF!
Name __123Graph_AChart7: #REF!
Name __123Graph_ACurrent: #REF!
Name __123Graph_B: #REF!
Name __123Graph_BChart1: #REF!
Name __123Graph_BChart2: #REF!
Name __123Graph_BChart3: #REF!
Name __123Graph_BChart4: #REF!
Name __123Graph_BChart5: #REF!
Name __123Graph_BChart6: #REF!
Name __123Graph_BChart7: #REF!
Name __123Graph_BCurrent: #REF!
Name __123Graph_C: #REF!
Name __123Graph_CChart1: #REF!
Name __123Graph_CChart2: #REF!

Sheet __FDSCACHE__
B1: This sheet contains FactSet XML data for use with this workbook's =FDS codes. Modifying the worksheet's contents may damage the workbook's =FDS functionality.

Sheet Income Statement
C2: Mar | D2: Jun | E2: Sep | F2: Dec | H2: Mar | I2: Jun | J2: Sep | K2: Dec | M2: Mar | N2: Jun | O2: Sep | P2: Dec | R2: Mar | S2: Jun | T2: Sep | U2: Dec | W2: Mar | X2: Jun | Y2: Sep | Z2: Dec | AB2: Mar | AC2: Jun | AD2: Sep | AE2: Dec | AG2: Mar | AH2: Jun | AI2: Sep | AJ2: Dec | AL2: Mar | AM2: Jun | AN2: Sep | AO2: Dec | AQ2: Mar | AR2: Jun | AS2: Sep | AT2: Dec | AV2: Mar | AW2: Jun | AX2: Sep | AY2: Dec | BA2: Mar | BB2: Jun | BC2: Sep | BD2: Dec
B3: (Amounts in millions, except per share data) | C3: 1Q16 | D3: 2Q16 | E3: 3Q16 | F3: 4Q16 | G3: 2016 | H3: 1Q17 | I3: 2Q17 | J3: 3Q17 | K3: 4Q17 | L3: 2017 | M3: 1Q18 | N3: 2Q18 | O3: 3Q18 | P3: 4Q18 | Q3: 2018 | R3: 1Q19 | S3: 2Q19 | T3: 3Q19 | U3: 4Q19 | V3: 2019 | W3: 1Q20 | X3: 2Q20 | Y3: 3Q20 | Z3: 4Q20 | AA3: 2020 | AB3: 1Q21 | AC3: 2Q21 | AD3: 3Q21 | AE3: 4Q21 | AF3: 2021 | AG3: 1Q22 | AH3: 2Q22 | AI3: 3Q22 | AJ3: 4Q22 | AK3: 2022 | AL3: 1Q23 | AM3: 2Q23 | AN3: 3Q23 | AO3: 4Q23 | AP3: 2023 | AQ3: 1Q24 | AR3: 2Q24 | AS3: 3Q24 | AT3: 4Q24 | AU3: 2024 | AV3: 1Q25 | AW3: 2Q25 | AX3: 3Q25 | AY3: 4Q25 | AZ3: 2025 | BA3: 1Q26E | BB3: 2Q26E | BC3: 3Q26E | BD3: 4Q26E | BE3: 2026E | BF3: 2027E | BG3: 2028E | BH3: 2029E | BI3: 2030E | BJ3: 2031E
B4: Bookings | C4: =+C5+C13 -> 75.698 | D4: =+D5+D13 -> 81.453 | E4: =+E5+E13 -> 87.269 | F4: =+F5+F13 -> 97.656 | G4: =SUM(G5:G13) -> 342.076 | H4: =+H5+H13 -> 114.548 | I4: =+I5+I13 -> 117.119 | J4: =+J5+J13 -> 120.118 | K4: =+K5+K13 -> 132.198 | L4: =SUM(L5:L13) -> 483.983 | M4: =M136+M157 -> 159.655 | N4: =N136+N157 -> 159.895 | O4: =O136+O157 -> 162.777 | P4: =P136+P157 -> 176.058 | Q4: =SUM(Q5:Q13) -> 658.385 | R4: =R136+R157 -> 200.379 | S4: =S136+S157 -> 199.563 | T4: =T136+T157 -> 205.86 | U4: =U136+U157 -> 226.683 | V4: =SUM(V5:V13) -> 832.485 | W4: =W136+W157 -> 248.858 | X4: =X136+X157 -> 265.851 | Y4: =Y136+Y157 -> 280.941 | Z4: =Z136+Z157 -> 306.381 | AA4: =SUM(AA5:AA13) -> 1102.031 | AB4: =AB136+AB157 -> 351.109 | AC4: =AC136+AC157 -> 342.861 | AD4: =AD136+AD157 -> 373.297 | AE4: =AE136+AE157 -> 351.556 | AF4: =SUM(AF5:AF13) -> 1418.823 | AG4: =AG136+AG157 -> 393.248 | AH4: =AH136+AH157 -> 354.594 | AI4: =AI136+AI157 -> 352.464 | AJ4: =AJ136+AJ157 -> 371.813 | AK4: =SUM(AK5:AK13) -> 1472.119 | AL4: =AL136+AL157 -> 414.905 | AM4: =AM136+AM157 -> 398.496 | AN4: =AN136+AN157 -> 389.095 | AO4: =AO136+AO157 -> 395.004 | AP4: =AP136+AP157 -> 1597.5 | AQ4: =AQ136+AQ157 -> 457.281 | AR4: =AR136+AR157 -> 458.399 | AS4: =AS136+AS157 -> 452.486 | ... BJ4: =BJ136+BJ157 -> 3477.4955
B5: Change in deferred revenue | C5: 14.108 | D5: 12.723 | E5: 11.659 | F5: 13.476 | G5: =SUM(C5:F5) -> 51.966 | H5: 22.008 | I5: 13.599 | J5: 9.088 | K5: 13.658 | L5: =SUM(H5:K5) -> 58.353 | M5: =M4-M13 -> 21.88 | N5: =N4-N13 -> 13.763 | O5: =O4-O13 -> 7.177 | P5: =P4-P13 -> 11.861 | Q5: =SUM(M5:P5) -> 54.681 | R5: =R4-R13 -> 26.089 | S5: =S4-S13 -> 14.144 | T5: =T4-T13 -> 9.069 | U5: =U4-U13 -> 22.095 | V5: =SUM(R5:U5) -> 71.397 | W5: =W4-W13 -> 32.871 | X5: =X4-X13 -> 29.792 | Y5: =Y4-Y13 -> 26.761 | Z5: =Z4-Z13 -> 23.847 | AA5: =SUM(W5:Z5) -> 113.271 | AB5: =AB4-AB13 -> 46.997 | AC5: =AC4-AC13 -> 26.455 | AD5: =AD4-AD13 -> 52.5 | AE5: =AE4-AE13 -> 23.214 | AF5: =SUM(AB5:AE5) -> 149.166 | AG5: =AG4-AG13 -> 51.651 | AH5: =AH4-AH13 -> 9.37 | AI5: =AI4-AI13 -> 6.659 | AJ5: =AJ4-AJ13 -> 16.773 | AK5: =SUM(AG5:AJ5) -> 84.453 | AL5: =AL4-AL13 -> 40.829 | AM5: =AM4-AM13 -> 8.519 | AN5: =AN4-AN13 -> -4.746 | AO5: =AO4-AO13 -> -8.767 | AP5: =AP4-AP13 -> 35.835 | AQ5: =AQ4-AQ13 -> 37.505 | AR5: =AR4-AR13 -> 22.653 | AS5: =AS4-AS13 -> 7.813 | ... BJ5: =BJ4-BJ13 -> 86.177594
B7: Guide
B8: High | AU8: 1832 | AZ8: 2078
B9: Midpoint | AU9: =+AVERAGE(AU8,AU10) -> 1827 | AZ9: =+AVERAGE(AZ8,AZ10) -> 2069
B10: Low | AU10: 1822 | AZ10: 2060
B11: Needham vs Midpoint | AU11: =+AU4/AU9-1 -> 0.0031559934 | AZ11: =+AZ4/AZ9-1 -> -0.0021899468
B13: Revenue | C13: =SUM(C14:C15) -> 61.59 | D13: =SUM(D14:D15) -> 68.73 | E13: =SUM(E14:E15) -> 75.61 | F13: =SUM(F14:F15) -> 84.18 | G13: =SUM(G14:G15) -> 290.11 | H13: =SUM(H14:H15) -> 92.54 | I13: =SUM(I14:I15) -> 103.52 | J13: =SUM(J14:J15) -> 111.03 | ... BJ13: =SUM(BJ14:BJ15) -> 3391.3179
B14: Creative Subscriptions | C14: 61.59 | D14: 68.73 | E14: 75.61 | F14: 84.18 | G14: =SUM(C14:F14) -> 290.11 | H14: 92.54 | I14: 103.52 | J14: 111.03 | K14: 118.54 | L14: =SUM(H14:K14) -> 425.63 | M14: 120.434 | N14: 126.716 | O14: 134.579 | P14: 143.621 | Q14: =SUM(M14:P14) -> 525.35 | R14: 151.364 | S14: 157.012 | T14: 164.761 | U14: 171.355 | V14: =SUM(R14:U14) -> 644.492 | W14: 176.546 | X14: 190.169 | Y14: 202.996 | Z14: 213.745 | AA14: =SUM(W14:Z14) -> 783.456 | AB14: 226.436 | AC14: 235.891 | AD14: 241.303 | AE14: 246.669 | AF14: =SUM(AB14:AE14) -> 950.299 | AG14: 254.968 | AH14: 258.177 | AI14: 261.066 | AJ14: 265.268 | AK14: =SUM(AG14:AJ14) -> 1039.479 | AL14: 278.13 | AM14: 287.089 | AN14: 290.634 | AO14: 296.154 | AP14: =AP143 -> 1152.007 | AQ14: 304.293 | AR14: 312.125 | AS14: 318.825 | AT14: 329.732 | AU14: =AU143 -> 1264.975 | AV14: 337.676 | AW14: 345.456 | AX14: 356.174 | AY14: 370.421 | AZ14: =AZ143 -> 1409.727 | BA14: =BA143 -> 385.06825 | BB14: =BB143 -> 398.07197 | BC14: =BC143 -> 415.8902 | BD14: =BD143 -> 438.7287 | BE14: =BE143 -> 1637.7591 | BF14: =BF143 -> 1834.2902 | BG14: =BG143 -> 2010.3821 | ... BJ14: =BJ143 -> 2412.6726
B15: Business Solutions | M15: 17.341 | N15: 19.416 | O15: 21.021 | P15: 20.576 | Q15: =SUM(M15:P15) -> 78.354 | R15: 22.926 | S15: 28.407 | T15: 32.03 | U15: 33.233 | V15: =SUM(R15:U15) -> 116.596 | W15: 39.441 | X15: 45.89 | Y15: 51.184 | Z15: 68.789 | AA15: =SUM(W15:Z15) -> 205.304 | AB15: 77.676 | AC15: 80.515 | AD15: 79.494 | AE15: 81.673 | AF15: =SUM(AB15:AE15) -> 319.358 | AG15: 86.629 | AH15: 87.047 | AI15: 84.739 | AJ15: 89.772 | AK15: =SUM(AG15:AJ15) -> 348.187 | AL15: 95.946 | AM15: 102.888 | AN15: 103.207 | AO15: 107.617 | AP15: =AP164 -> 409.658 | AQ15: 115.483 | AR15: 123.621 | AS15: 125.848 | AT15: 130.723 | AU15: =AU164 -> 495.675 | AV15: 135.975 | AW15: 144.474 | AX15: 149.02 | AY15: 153.848 | AZ15: =AZ164 -> 583.317 | BA15: =BA164 -> 156.75407 | BB15: =BB164 -> 165.26937 | BC15: =BC164 -> 170.63025 | BD15: =BD164 -> 173.9681 | BE15: =BE164 -> 666.6218 | BF15: =BF164 -> 740.6983 | BG15: =BG164 -> 809.04966 | ... BJ15: =BJ164 -> 978.64523
B17: Guide | AV17: =AV13/AQ13-1 -> 0.12834226 | AW17: =AW18/AR13-1 -> 0.1222134 | AX17: =AX18/AS13-1 -> 0.13341714
B18: High | AG18: 343 | AH18: 346 | AI18: 345 | AJ18: 354 | AL18: 371 | AM18: 385 | AN18: 391 | AO18: 405 | AP18: 1558 | AQ18: 419 | AR18: 435 | AS18: 445 | AT18: 464 | AU18: 1764 | AV18: 473 | AW18: 489 | AX18: 504 | AY18: 531 | AZ18: 2000
B19: Midpoint | AG19: =AVERAGE(AG18,AG20) -> 340.5 | AH19: =AVERAGE(AH18,AH20) -> 344 | AI19: =AVERAGE(AI18,AI20) -> 343 | AJ19: =AVERAGE(AJ18,AJ20) -> 351.5 | AL19: =AVERAGE(AL18,AL20) -> 369 | AM19: =AVERAGE(AM18,AM20) -> 382.5 | AN19: =AVERAGE(AN18,AN20) -> 388.5 | AO19: =AVERAGE(AO18,AO20) -> 402.5 | AP19: =+AVERAGE(AP18,AP20) -> 1560.5 | AQ19: =AVERAGE(AQ18,AQ20) -> 417 | AR19: =AVERAGE(AR18,AR20) -> 433 | AS19: =AVERAGE(AS18,AS20) -> 442.5 | AT19: =AVERAGE(AT18,AT20) -> 460.5 | AU19: =+AVERAGE(AU18,AU20) -> 1760.5 | AV19: =+AVERAGE(AV18,AV20) -> 471 | AW19: =+AVERAGE(AW18,AW20) -> 487 | AX19: =+AVERAGE(AX18,AX20) -> 501 | AY19: =+AVERAGE(AY18,AY20) -> 526 | AZ19: =+AVERAGE(AZ18,AZ20) -> 1995 | BA19: mid teens | BE19: mid teens
B20: Low | AG20: 338 | AH20: 342 | AI20: 341 | AJ20: 349 | AL20: 367 | AM20: 380 | AN20: 386 | AO20: 400 | AP20: 1563 | AQ20: 415 | AR20: 431 | AS20: 440 | AT20: 457 | AU20: 1757 | AV20: 469 | AW20: 485 | AX20: 498 | AY20: 521 | AZ20: 1990 | BA20: =BA13/AV13-1 -> 0.14392733 | BE20: =BE13/AZ13-1 -> 0.15621176
B21: Needham vs Midpoint | AG21: =AG13/AG19-1 -> 0.0032217327 | AH21: =AH13/AH19-1 -> 0.0035581395 | AI21: =AI13/AI19-1 -> 0.0081778426 | AJ21: =AJ13/AJ19-1 -> 0.010071124 | AL21: =AL13/AL19-1 -> 0.013756098 | AM21: =AM13/AM19-1 -> 0.019547712 | AN21: =AN13/AN19-1 -> 0.013747748 | AO21: =AO13/AO19-1 -> 0.003157764 | AP21: =+AP13/AP19-1 -> 0.00074655559 | AQ21: =AQ13/AQ19-1 -> 0.0066570743 | AR21: =AR13/AR19-1 -> 0.0063418014 | AS21: =AS13/AS19-1 -> 0.0049107345 | AT21: =AT13/AT19-1 -> -9.771987e-05 | AU21: =+AU13/AU19-1 -> 8.5203067e-05 | AV21: =+AV13/AV19-1 -> 0.0056284501 | AW21: =+AW13/AW19-1 -> 0.0060164271 | AX21: =+AX13/AX19-1 -> 0.0083712575 | AY21: =+AY13/AY19-1 -> -0.0032908745 | AZ21: =+AZ13/AZ19-1 -> -0.00098045113
B23: Cost of revenue, non GAAP | C23: =10.51-0.428 -> 10.082 | D23: =11.02-0.475 -> 10.545 | E23: =11.02-0.466 -> 10.554 | F23: =12.74-0.429 -> 12.311 | G23: =SUM(C23:F23) -> 43.492 | H23: 14.329 | I23: 16.29 | J23: 17.287 | K23: 18.022 | L23: =SUM(H23:K23) -> 65.928 | M23: =29.044-1.079 -> 27.965 | N23: =30.437-1.087 -> 29.35 | O23: =32.977-1.102 -> 31.875 | P23: =34.489-1.15 -> 33.339 | Q23: =SUM(M23:P23) -> 122.529 | R23: =39.715-1.311 -> 38.404 | S23: =46.662-1.436 -> 45.226 | T23: =53.295-1.525 -> 51.77 | U23: =57.235-1.582 -> 55.653 | V23: =SUM(R23:U23) -> 191.053 | W23: =62.07-1.631 -> 60.439 | X23: =70.482-1.869 -> 68.613 | Y23: =79.84-2.455 -> 77.385 | Z23: =103.307-3.172 -> 100.135 | AA23: =SUM(W23:Z23) -> 306.572 | AB23: =115.832-3.501 -> 112.331 | AC23: =121.419-3.809 -> 117.61 | AD23: =122.529-4.057 -> 118.472 | AE23: =128.799-4.095 -> 124.704 | AF23: =SUM(AB23:AE23) -> 473.117 | AG23: =AG13-AG24 -> 129.676 | AH23: =AH13-AH24 -> 129.484 | AI23: =AI13-AI24 -> 122.68 | AJ23: =AJ13-AJ24 -> 123.468 | AK23: =SUM(AG23:AJ23) -> 505.308 | AL23: =AL13-AL24 -> 124.549 | AM23: =AM13-AM24 -> 123.565 | AN23: =AN13-AN24 -> 124.737 | AO23: =AO13-AO24 -> 121.766 | AP23: =SUM(AL23:AO23) -> 494.617 | AQ23: =AQ13-AQ24 -> 133.04 | AR23: =AR13-AR24 -> 137.49 | AS23: =AS13-AS24 -> 137.787 | AT23: =AT13-AT24 -> 139.503 | AU23: =SUM(AQ23:AT23) -> 547.82 | AV23: =AV13-AV24 -> 147.805 | AW23: =AW13-AW24 -> 149.037 | AX23: =AX13-AX24 -> 155.454 | AY23: =AY13-AY24 -> 165.517 | AZ23: =SUM(AV23:AY23) -> 617.813 | BA23: =BA152+BA182 -> 179.7069 | BB23: =BB152+BB182 -> 183.15036 | BC23: =BC152+BC182 -> 185.95404 | BD23: =BD152+BD182 -> 191.73185 | BE23: =SUM(BA23:BD23) -> 740.54315 | BF23: =BF152+BF182 -> 815.57666 | BG23: =BG152+BG182 -> 881.18877 | BH23: =BH152+BH182 -> 937.32941 | BI23: =BI152+BI182 -> 984.42171 | BJ23: =BJ152+BJ182 -> 1023.4782
B24: Gross profit, non GAAP | C24: =+C13-C23 -> 51.508 | D24: =+D13-D23 -> 58.185 | E24: =+E13-E23 -> 65.056 | F24: =+F13-F23 -> 71.869 | G24: =+G13-G23 -> 246.618 | H24: =+H13-H23 -> 78.211 | I24: =+I13-I23 -> 87.23 | J24: =+J13-J23 -> 93.743 | ... AF24: =+AF13-AF23 -> 796.54 | AG24: 211.921 | AH24: 215.74 | AI24: 223.125 | AJ24: 231.572 | AK24: =+AK13-AK23 -> 882.358 | AL24: 249.527 | AM24: 266.412 | AN24: 269.104 | AO24: 282.005 | AP24: =+AP13-AP23 -> 1067.048 | AQ24: 286.736 | AR24: 298.256 | AS24: 306.886 | AT24: 320.952 | AU24: =+AU13-AU23 -> 1212.83 | AV24: 325.846 | AW24: 340.893 | AX24: 349.74 | AY24: 358.752 | AZ24: =+AZ13-AZ23 -> 1375.231 | BA24: =+BA13-BA23 -> 362.11542 | BB24: =+BB13-BB23 -> 380.19099 | BC24: =+BC13-BC23 -> 400.56641 | BD24: =+BD13-BD23 -> 420.96495 | BE24: =+BE13-BE23 -> 1563.8378 | BF24: =+BF13-BF23 -> 1759.4118 | BG24: =+BG13-BG23 -> 1938.243 | ... BJ24: =+BJ13-BJ23 -> 2367.8396
B26: Sales & marketing, non GAAP | C26: =40.45-0.981-0.05 -> 39.419 | D26: =36.03-1.122-0.136 -> 34.772 | E26: =40.01-1.237-0.138 -> 38.635 | F26: =40.02-1.213-0.136 -> 38.671 | G26: =SUM(C26:F26) -> 151.497 | H26: 52.249 | I26: 46.176 | J26: 49.303 | K26: 47.313 | L26: =SUM(H26:K26) -> 195.041 | M26: =67.011-2.042 -> 64.969 | N26: =58.855-2.352 -> 56.503 | O26: =49.36-2.597 -> 46.763 | P26: =61.065-2.779 -> 58.286 | Q26: =SUM(M26:P26) -> 226.521 | R26: =85.718-4.748 -> 80.97 | S26: =71.329-4.506 -> 66.823 | T26: =75.862-4.59 -> 71.272 | U26: =74.809-4.614 -> 70.195 | V26: =SUM(R26:U26) -> 289.26 | W26: =96.156-4.568 -> 91.588 | X26: =119.333-5.395 -> 113.938 | Y26: =113.092-6.108 -> 106.984 | Z26: =109.629-6.774 -> 102.855 | AA26: =SUM(W26:Z26) -> 415.365 | AB26: =144.455-7.442 -> 137.013 | AC26: =123.021-24.49 -> 98.531 | AD26: =119.991-8.715 -> 111.276 | AE26: =124.56-28.028 -> 96.532 | AF26: =SUM(AB26:AE26) -> 443.352 | AG26: 146.027 | AH26: 109.94 | AI26: 107.367 | AJ26: 87.564 | AK26: =SUM(AG26:AJ26) -> 450.898 | AL26: 88.755 | AM26: 85.564 | AN26: 89.11 | AO26: 91.589 | AP26: =SUM(AL26:AO26) -> 355.018 | AQ26: 95.936 | AR26: 92.496 | AS26: 98.862 | AT26: 95.838 | AU26: =SUM(AQ26:AT26) -> 383.132 | AV26: 101.582 | AW26: 103.519 | AX26: 127.228 | AY26: 142.112 | AZ26: =SUM(AV26:AY26) -> 474.441 | BA26: =AV26+80 -> 181.582 | BB26: =AW26+80 -> 183.519 | BC26: =AX26+50 -> 177.228 | BD26: =AY26+30 -> 172.112 | BE26: =SUM(BA26:BD26) -> 714.441 | BF26: =BF13*BF99 -> 678.58823 | BG26: =BG13*BG99 -> 687.28101 | BH26: =BH13*BH99 -> 684.61424 | BI26: =BI13*BI99 -> 672.78344 | BJ26: =BJ13*BJ99 -> 654.28423 | BL26: =+AZ98 -> 0.49880033
B27: Research and development, non GAAP | C27: =24.472-3.111-1.183-0.137 -> 20.041 | D27: =25.48-3.558-0.397-0.05 -> 21.475 | E27: =26.54-3.718-0.514-0.05 -> 22.258 | F27: =28.88-4.156-0.614-0.05 -> 24.06 | G27: =SUM(C27:F27) -> 87.834 | H27: 26.094 | I27: 29.165 | J27: 32.037 | K27: 33.997 | L27: =SUM(H27:K27) -> 121.293 | M27: =46.502-8.485 -> 38.017 | N27: =48.492-9.47 -> 39.022 | O27: =62.247-10.372 -> 51.875 | P27: =54.558-11.09 -> 43.468 | Q27: =SUM(M27:P27) -> 172.382 | R27: =58.183-12.256 -> 45.927 | S27: =61.486-14.119 -> 47.367 | T27: =64.488-14.886 -> 49.602 | U27: =66.634-14.9 -> 51.734 | V27: =SUM(R27:U27) -> 194.63 | W27: =70.716-16.185 -> 54.531 | X27: =75.464-18.216 -> 57.248 | Y27: =84.473-20.312 -> 64.161 | Z27: =89.625-22.17 -> 67.455 | AA27: =SUM(W27:Z27) -> 243.395 | AB27: =95.086-23.288 -> 71.798 | AC27: =104.199-8.213 -> 95.986 | AD27: =109.323-26.25 -> 83.073 | AE27: =116.329-9.483 -> 106.846 | AF27: =SUM(AB27:AE27) -> 357.703 | AG27: 89.53 | AH27: 90.607 | AI27: 90.193 | AJ27: 87.003 | AK27: =SUM(AG27:AJ27) -> 357.333 | AL27: 86.477 | AM27: 86.656 | AN27: 94.684 | AO27: 93.757 | AP27: =SUM(AL27:AO27) -> 361.574 | AQ27: 93.138 | AR27: 88.474 | AS27: 92.335 | AT27: 94.866 | AU27: =SUM(AQ27:AT27) -> 368.813 | AV27: 96.006 | AW27: 98.389 | AX27: 104.863 | AY27: 104.981 | AZ27: =SUM(AV27:AY27) -> 404.239 | BA27: =+AY27+5 -> 109.981 | BB27: =+BA27 -> 109.981 | BC27: =+BB27 -> 109.981 | BD27: =+BC27 -> 109.981 | BE27: =SUM(BA27:BD27) -> 439.924 | BF27: =+BE27*1.05 -> 461.9202 | BG27: =+BF27*1.05 -> 485.01621 | BH27: =+BG27*1.05 -> 509.26702 | BI27: =+BH27*1.05 -> 534.73037 | BJ27: =+BI27*1.05 -> 561.46689
B28: General & administrative, non GAAP | C28: =5.92-1.617 -> 4.303 | D28: =6.69-1.772 -> 4.918 | E28: =7.07-1.743 -> 5.327 | F28: =7.28-2.022 -> 5.258 | G28: =SUM(C28:F28) -> 19.806 | H28: =11.15-2.331-1.413 -> 7.406 | I28: =11.3-2.92 -> 8.38 | J28: =12.22-3.236 -> 8.984 | K28: =13.52-3.471-0.54 -> 9.509 | L28: =SUM(H28:K28) -> 34.279 | M28: =13.67-4.068 -> 9.602 | N28: =14.855-4.86 -> 9.995 | O28: =14.514-4.689 -> 9.825 | P28: =16.258-5.108 -> 11.15 | Q28: =SUM(M28:P28) -> 40.572 | R28: =18.466-6.592 -> 11.874 | S28: =20.103-7.504 -> 12.599 | T28: =23.751-7.391 -> 16.36 | U28: =23.602-7.377 -> 16.225 | V28: =SUM(R28:U28) -> 57.058 | W28: =25.436-8.334 -> 17.102 | X28: =24.531-9.487 -> 15.044 | Y28: =26.515-10.047 -> 16.468 | Z28: =35.433-10.59 -> 24.843 | AA28: =SUM(W28:Z28) -> 73.457 | AB28: =34.394-12.4 -> 21.994 | AC28: =39.411-13.884 -> 25.527 | AD28: =38.917-14.048 -> 24.869 | AE28: =56.926-29.688 -> 27.238 | AF28: =SUM(AB28:AE28) -> 99.628 | AG28: 27.352 | AH28: 28.12 | AI28: 28.731 | AJ28: 26.305 | AK28: =SUM(AG28:AJ28) -> 110.508 | AL28: 25.777 | AM28: 25.336 | AN28: 27.352 | AO28: 31.957 | AP28: =SUM(AL28:AO28) -> 110.422 | AQ28: 28.241 | AR28: 27.092 | AS28: 27.265 | AT28: 29.712 | AU28: =SUM(AQ28:AT28) -> 112.31 | AV28: 28.421 | AW28: 28.832 | AX28: 27.723 | AY28: 30.475 | AZ28: =SUM(AV28:AY28) -> 115.451 | BA28: =+AY28 -> 30.475 | BB28: =+BA28 -> 30.475 | BC28: =+BB28 -> 30.475 | BD28: =+BC28 -> 30.475 | BE28: =SUM(BA28:BD28) -> 121.9 | BF28: =+BE28*1.02 -> 124.338 | BG28: =+BF28*1.02 -> 126.82476 | BH28: =+BG28*1.02 -> 129.36126 | BI28: =+BH28*1.02 -> 131.94848 | BJ28: =+BI28*1.02 -> 134.58745
B29: Operating Non GAAP adjustments | M29: =-0.588-1.428 -> -2.016 | N29: =-0.731-0.946 -> -1.677 | O29: =-0.733-0.261 -> -0.994 | P29: =-0.732-0.125 -> -0.857 | R29: -0.732 | S29: =-0.738-0.053 -> -0.791 | T29: =-0.733-3.174-0.564 -> -4.471 | U29: =-2.385-2.135-1.868 -> -6.388 | V29: =SUM(R29:U29) -> -12.382 | W29: =-0.566-1.974-0.939 -> -3.479 | X29: =-0.566+0.485-1.697 -> -1.778 | Y29: =-0.826-1.489 -> -2.315 | Z29: =-0.619-2.81-1.686 -> -5.115 | AA29: =SUM(W29:Z29) -> -12.687 | AB29: =-0.599-0.452-1.705 -> -2.756 | AC29: =-0.846-0.579-2.351 -> -3.776 | AD29: =-3.045-0.341-2.579 -> -5.965 | AE29: =-0.462-0.32-2.045 -> -2.827 | AF29: =SUM(AB29:AE29) -> -15.324 | AG29: 0 | AH29: =AG29 -> 0 | AI29: 0 | AJ29: =AI29 -> 0 | AK29: =SUM(AG29:AJ29) -> 0 | AL29: =AJ29 -> 0 | AM29: 0 | AN29: 0 | AO29: 0 | AP29: =SUM(AL29:AO29) -> 0 | AQ29: 0 | AR29: =AQ29 -> 0 | AS29: =AR29 -> 0 | AT29: =AS29 -> 0 | AU29: =SUM(AQ29:AT29) -> 0 | AV29: 0 | AW29: =AV29 -> 0 | AX29: =AW29 -> 0 | AY29: =AX29 -> 0 | AZ29: =SUM(AV29:AY29) -> 0 | BA29: =AY29 -> 0 | BB29: =BA29 -> 0 | BC29: =BB29 -> 0 | BD29: =BC29 -> 0 | BE29: =SUM(BA29:BD29) -> 0 | BF29: =BE29 -> 0 | BG29: =BF29 -> 0 | BH29: =BG29 -> 0 | BI29: =BH29 -> 0 | BJ29: =BI29 -> 0 | BL29: =+SUM(AX27:AY27)*2*1.05 -> 440.6724
B30: Total operating expenses | C30: =SUM(C26:C29) -> 63.763 | D30: =SUM(D26:D29) -> 61.165 | E30: =SUM(E26:E29) -> 66.22 | F30: =SUM(F26:F29) -> 67.989 | G30: =SUM(G26:G29) -> 259.137 | H30: =SUM(H26:H29) -> 85.749 | I30: =SUM(I26:I29) -> 83.721 | J30: =SUM(J26:J29) -> 90.324 | ... BJ30: =SUM(BJ26:BJ29) -> 1350.3386
AP31: =+AP30/AP13 -> 0.52957196
B32: Non-GAAP Operating Income | C32: =C24-C30 -> -12.255 | D32: =D24-D30 -> -2.98 | E32: =E24-E30 -> -1.164 | F32: =F24-F30 -> 3.88 | G32: =G24-G30 -> -12.519 | H32: =H24-H30 -> -7.538 | I32: =I24-I30 -> 3.509 | J32: =J24-J30 -> 3.419 | ... BJ32: =BJ24-BJ30 -> 1017.5011
B33: SBC | W33: =+W45 -> 30.718 | X33: =+X45 -> 34.967 | Y33: =+Y45 -> 38.922 | Z33: =+Z45 -> 42.706 | AA33: =+AA45 -> 147.313 | AB33: =+AB45 -> 46.631 | AC33: =+AC45 -> 50.396 | AD33: =+AD45 -> 53.07 | ... BJ33: =+BJ45 -> 251.97941
B34: Amortization | AG34: 1.574 | AH34: 1.58 | AI34: 1.581 | AJ34: 1.511 | AK34: =+SUM(AG34:AJ34) -> 6.246 | AL34: 1.488 | AM34: 1.489 | AN34: 1.489 | AO34: 1.489 | AP34: =+SUM(AL34:AO34) -> 5.955 | AQ34: 1.483 | AR34: 1.465 | AS34: 1.461 | AT34: 1.834 | AU34: =+SUM(AQ34:AT34) -> 6.243 | AV34: 1.472 | AW34: 1.259 | AX34: 1.355 | AY34: 2.923 | AZ34: =+SUM(AV34:AY34) -> 7.009 | BA34: =+AY34 -> 2.923 | BB34: =+BA34 -> 2.923 | BC34: =+BB34 -> 2.923 | BD34: =+BC34 -> 2.923 | BE34: =+SUM(BA34:BD34) -> 11.692 | BF34: =+BE34 -> 11.692 | BG34: =+BF34 -> 11.692 | BH34: =+BG34 -> 11.692 | BI34: =+BH34 -> 11.692 | BJ34: =+BI34 -> 11.692
B35: Other | AG35: =1.699+0.172 -> 1.871 | AH35: =1.187+0.189 -> 1.376 | AI35: =0.585+0.183 -> 0.768 | AJ35: =1.656+0.219 -> 1.875 | AK35: =+SUM(AG35:AJ35) -> 5.89 | AL35: =0.196+0.308+25.338 -> 25.842 | AM35: =0.244+0.157+0.33 -> 0.731 | AN35: =0.023+0.146+3.843 -> 4.012 | AO35: =0.009+0.137+3.103 -> 3.249 | AP35: =+SUM(AL35:AO35) -> 33.834 | AQ35: =0.005+0.121 -> 0.126 | AR35: 0 | AS35: 0 | AT35: 0.881 | AU35: =+SUM(AQ35:AT35) -> 1.007 | AV35: 0.699 | AW35: =6.087-0.938 -> 5.149 | AX35: =0.945+35.432 -> 36.377 | AY35: =90.044+2.694 -> 92.738 | AZ35: 0 | BA35: 0 | BB35: 0 | BC35: 0 | BD35: 0 | BE35: 0 | BF35: =+BE35 -> 0 | BG35: =+BF35 -> 0 | BH35: =+BG35 -> 0 | BI35: =+BH35 -> 0 | BJ35: =+BI35 -> 0
B36: GAAP Operating Income | AG36: =+AG32-AG33-AG34-AG35 -> -115.417 | AH36: =+AH32-AH33-AH34-AH35 -> -75.022 | AI36: =+AI32-AI33-AI34-AI35 -> -62.311 | AJ36: =+AJ32-AJ33-AJ34-AJ35 -> -32.603 | AK36: =+AK32-AK33-AK34-AK35 -> -285.353 | AL36: =+AL32-AL33-AL34-AL35 -> -33.333 | AM36: =+AM32-AM33-AM34-AM35 -> 12.976 | AN36: =+AN32-AN33-AN34-AN35 -> -5.792 | ... BJ36: =+BJ32-BJ33-BJ34-BJ35 -> 753.82965
B38: GAAP to Non GAAP Adj | M38: =M45+0.588+1.428-0.566 -> 17.124 | N38: =N45+0.731+0.946 -> 19.446 | O38: =O45+0.733+0.261+4.965 -> 24.719 | P38: =P45+0.732+0.125+5.039+0.5 -> 26.523 | Q38: =SUM(M38:P38) -> 87.812 | R38: =R45+0.732+5.117+1.452 -> 32.208 | S38: =S45+0.738+0.053+5.194+0.14 -> 33.69 | T38: =T45+0.733+0.564+5.274+3.174+0.056 -> 38.193 | U38: =U45+2.385+1.868+5.353+2.135+1.257 -> 41.471 | V38: =SUM(R38:U38) -> 145.562 | W38: =W45+0.566+0.939+5.433+1.974-0.873 -> 38.757 | X38: =X45+0.566+1.697+5.516-0.485+1.305 -> 43.566 | Y38: =Y45+0.826+1.489+7.594-0.005 -> 48.826 | Z38: =Z45+0.619+1.686+11.411+2.81-66.709+1.925+15.343 -> 9.791 | AA38: =SUM(W38:Z38) -> 140.94 | AB38: =AB45+0.599+1.705+62.345+0.452-29.513+2.59+6.788 -> 91.597 | AC38: =AC45+0.846+2.351+1.296+0.579-142.348+0.363+32.74 -> -53.777 | AD38: =AD45+3.045+2.579+1.297+0.341-112.165+1.745+21.48 -> -28.608 | AE38: =AE45+0.462+2.045+1.298+0.32+16.195+2.013-3.725 -> 89.902 | AF38: =SUM(AB38:AE38) -> 99.114 | AG38: =AG45+1.574+1.699+1.301+0.172+151.645+4.132-35.612 -> 185.895 | AH38: =AH45+1.58+1.187+1.302+0.189+54.92-2.274-12.632 -> 103.411 | AI38: =AI45+1.581+0.585+1.305+0.183-1.675+2.342-10.182 -> 50.935 | AJ38: =AJ45+1.511+1.656+1.305+0.219+3.955+6.22-0.176 -> 74.607 | AK38: =SUM(AG38:AJ38) -> 414.848 | AL38: =+AL45+1.488+0.196+0.308+25.338 -> 81.851 | AM38: =AM45+1.489+0.244+1.31+0.33+0.157-8.814-1.843-2.022 -> 44.511 | AN38: =AN45+1.489+0.023+0.787+3.843+0.146-8.283-0.552+2.4 -> 58.102 | AO38: =AO45 -> 58.195 | AP38: =SUM(AL38:AO38) -> 242.659 | AQ38: =AQ45 -> 58.142 | AR38: =AR45+AR48 -> 58.183 | AS38: =AS45+AS48 -> 59.206 | AT38: =AT45 -> 61.801 | AU38: =SUM(AQ38:AT38) -> 237.332 | AV38: =AV45 -> 60.261 | AW38: =AW45 -> 59.439 | AX38: =AX45 -> 59.565 | AY38: =AY45 -> 58.111 | AZ38: =SUM(AV38:AY38) -> 237.376 | BA38: =BA45 -> 60.86361 | BB38: =BB45 -> 60.03339 | BC38: =BC45 -> 60.16065 | BD38: =BD45 -> 58.69211 | BE38: =SUM(BA38:BD38) -> 239.74976 | BF38: =BF45 -> 242.14726 | BG38: =BG45 -> 244.56873 | BH38: =BH45 -> 247.01442 | BI38: =BI45 -> 249.48456 | BJ38: =BJ45 -> 251.97941
B39: Non GAAP net Income | M39: =M52+M38 -> -2.689 | N39: =N52+N38 -> 13.806 | O39: =O52+O38 -> 18.803 | P39: =P52+P38 -> 20.77 | Q39: =SUM(M39:P39) -> 50.69 | R39: =R52+R38 -> 1.468 | S39: =S52+S38 -> 16.958 | T39: =T52+T38 -> 20.826 | U39: =U52+U38 -> 19.898 | V39: =SUM(R39:U39) -> 59.15 | W39: =W52+W38 -> -0.396 | X39: =X52+X38 -> -14.17 | Y39: =Y52+Y38 -> -8.016 | Z39: =Z52+Z38 -> -1.632 | AA39: =AA52+AA38 -> -24.214 | AB39: =AB52+AB38 -> -30.155 | AC39: =AC52+AC38 -> -15.82 | AD39: =AD52+AD38 -> -11.941 | ... BJ39: =BJ52+BJ38 -> 1017.8595
B41: Depreciation | C41: 1.2 | D41: 1.2 | E41: 1.2 | F41: 0.9 | G41: =+SUM(C41:F41) -> 4.5 | H41: 1.3 | I41: 1.3 | J41: 1.5 | K41: 1.6 | L41: =+SUM(H41:K41) -> 5.7 | M41: 1.897 | N41: 2.196 | O41: 2.213 | P41: 2.418 | Q41: =+SUM(M41:P41) -> 8.724 | R41: 2.658 | S41: 2.927 | T41: 3.194 | U41: 3.347 | V41: =+SUM(R41:U41) -> 12.126 | W41: 3.572 | X41: 3.537 | Y41: 3.712 | Z41: 3.789 | AA41: =+SUM(W41:Z41) -> 14.61 | AB41: 3.432 | AC41: 3.378 | AD41: =3.595 -> 3.595 | AE41: 3.524 | AF41: =+SUM(AB41:AE41) -> 13.929 | AG41: 3.535 | AH41: 4.022 | AI41: 3.845 | AJ41: 5.209 | AK41: =+SUM(AG41:AJ41) -> 16.611 | AL41: 4.922 | AM41: =AL41 -> 4.922 | AN41: =AM41 -> 4.922 | AO41: =18-SUM(AL41:AN41) -> 3.234 | AP41: =+SUM(AL41:AO41) -> 18 | AQ41: 6.442 | AR41: 4.5 | AS41: 4.5 | AT41: 6.278 | AU41: =+SUM(AQ41:AT41) -> 21.72 | AV41: 6.137 | AW41: 6.099 | AX41: 6.19 | AY41: 6.065 | AZ41: =+SUM(AV41:AY41) -> 24.491 | BA41: =AY41 -> 6.065 | BB41: =BA41 -> 6.065 | BC41: =BB41 -> 6.065 | BD41: =BC41 -> 6.065 | BE41: =+SUM(BA41:BD41) -> 24.26 | BF41: =+BE41 -> 24.26 | BG41: =+BF41 -> 24.26 | BH41: =+BG41 -> 24.26 | BI41: =+BH41 -> 24.26 | BJ41: =+BI41 -> 24.26
B42: Non-GAAP Adjustments | C42: =2.664-C32-C41 -> 13.719 | D42: =10.682-D32-D41 -> 12.462 | E42: =11.365-E32-E41 -> 11.329 | F42: =17.877-F32-F41 -> 13.097 | G42: =+SUM(C42:F42) -> 50.607 | H42: =15-H32-H41 -> 21.238 | I42: =17.3-I32-I41 -> 12.491 | J42: =12.9-J32-J41 -> 7.981 | K42: =23.9-K32-K41 -> 12.601 | L42: =+SUM(H42:K42) -> 54.311 | M42: =+M5 -> 21.88 | N42: =+N5 -> 13.763 | O42: =+O5 -> 7.177 | P42: =+P5 -> 11.861 | Q42: =+SUM(M42:P42) -> 54.681 | R42: =+R5 -> 26.089 | S42: =+S5 -> 14.144 | T42: =+T5 -> 9.069 | U42: =+U5 -> 22.095 | V42: =+SUM(R42:U42) -> 71.397 | W42: =+W5 -> 32.871 | X42: =+X5 -> 29.792 | Y42: =+Y5 -> 26.761 | Z42: =+Z5 -> 23.847 | AA42: =+SUM(W42:Z42) -> 113.271 | AB42: =+AB5 -> 46.997 | AC42: =+AC5 -> 26.455 | AD42: =+AD5 -> 52.5 | AE42: =+AE5 -> 23.214 | AF42: =+SUM(AB42:AE42) -> 149.166 | AG42: =+AG5 -> 51.651 | AH42: =+AH5 -> 9.37 | AI42: =+AI5 -> 6.659 | AJ42: =+AJ5 -> 16.773 | AK42: =+SUM(AG42:AJ42) -> 84.453 | AL42: =+AL5 -> 40.829 | AM42: =+AM5 -> 8.519 | AN42: =+AN5 -> -4.746 | AO42: =+AO5 -> -8.767 | AP42: =+SUM(AL42:AO42) -> 35.835 | AQ42: =+AQ5 -> 37.505 | AR42: =+AR5 -> 22.653 | AS42: =+AS5 -> 7.813 | AT42: =+AT5 -> 4.145 | AU42: =+SUM(AQ42:AT42) -> 72.116 | AV42: =+AV5 -> 37.254 | AW42: =+AW5 -> 19.994 | AX42: =+AX5 -> 9.349 | AY42: =+AY5 -> 4.828 | AZ42: =+SUM(AV42:AY42) -> 71.425 | BA42: =+BA5 -> 34.9723 | BB42: =+BB5 -> 21.3565 | BC42: =+BC5 -> 11.1936 | BD42: =+BD5 -> 0 | BE42: =+SUM(BA42:BD42) -> 67.5224 | BF42: =+BF5 -> 70.89852 | BG42: =+BG5 -> 74.443446 | BH42: =+BH5 -> 78.165618 | BI42: =+BI5 -> 82.073899 | BJ42: =+BJ5 -> 86.177594
B43: Adjusted EBITDA | C43: =C32+SUM(C41:C42) -> 2.664 | D43: =D32+SUM(D41:D42) -> 10.682 | E43: =E32+SUM(E41:E42) -> 11.365 | F43: =F32+SUM(F41:F42) -> 17.877 | G43: =G32+SUM(G41:G42) -> 42.588 | H43: =H32+SUM(H41:H42) -> 15 | I43: =I32+SUM(I41:I42) -> 17.3 | J43: =J32+SUM(J41:J42) -> 12.9 | ... BJ43: =BJ32+SUM(BJ41:BJ42) -> 1127.9386
B45: SBC | M45: 15.674 | N45: 17.769 | O45: 18.76 | P45: 20.127 | Q45: =SUM(M45:P45) -> 72.33 | R45: 24.907 | S45: 27.565 | T45: 28.392 | U45: 28.473 | V45: =SUM(R45:U45) -> 109.337 | W45: 30.718 | X45: 34.967 | Y45: 38.922 | Z45: 42.706 | AA45: =SUM(W45:Z45) -> 147.313 | AB45: 46.631 | AC45: 50.396 | AD45: =53.07 -> 53.07 | AE45: 71.294 | AF45: =SUM(AB45:AE45) -> 221.391 | AG45: 60.984 | AH45: 59.139 | AI45: 56.796 | AJ45: 59.917 | AK45: =SUM(AG45:AJ45) -> 236.836 | AL45: 54.521 | AM45: 53.66 | AN45: 58.249 | AO45: 58.195 | AP45: =SUM(AL45:AO45) -> 224.625 | AQ45: 58.142 | AR45: 59.886 | AS45: 60.892 | AT45: 61.801 | AU45: =SUM(AQ45:AT45) -> 240.721 | AV45: 60.261 | AW45: 59.439 | AX45: 59.565 | AY45: 58.111 | AZ45: =SUM(AV45:AY45) -> 237.376 | BA45: ='Cash Flow'!BA8 -> 60.86361 | BB45: ='Cash Flow'!BB8 -> 60.03339 | BC45: ='Cash Flow'!BC8 -> 60.16065 | BD45: ='Cash Flow'!BD8 -> 58.69211 | BE45: =SUM(BA45:BD45) -> 239.74976 | BF45: ='Cash Flow'!BF8 -> 242.14726 | BG45: ='Cash Flow'!BG8 -> 244.56873 | BH45: ='Cash Flow'!BH8 -> 247.01442 | BI45: ='Cash Flow'!BI8 -> 249.48456 | BJ45: ='Cash Flow'!BJ8 -> 251.97941
B46: Financial income | C46: 0.51 | D46: -0.11 | E46: 0.3 | F46: -0.45 | G46: =SUM(C46:F46) -> 0.25 | H46: 0.15 | I46: -2.04 | J46: -1.98 | K46: -1.14 | L46: =SUM(H46:K46) -> -5.01 | M46: -0.13 | N46: 1.532 | O46: -2.509 | P46: -1.688 | Q46: =SUM(M46:P46) -> -2.795 | R46: -1.73 | S46: -0.58 | T46: =1.242 -> 1.242 | U46: -2.553 | V46: =SUM(R46:U46) -> -3.621 | W46: 1.145 | X46: -3.339 | Y46: =-7.298 -> -7.298 | Z46: 56.551 | AA46: =SUM(W46:Z46) -> 47.059 | AB46: =-28.013 -> -28.013 | AC46: 143.969 | AD46: =111.917 -> 111.917 | AE46: =-16.868 -> -16.868 | AF46: =SUM(AB46:AE46) -> 211.005 | AG46: -144.473 | AH46: -54.92 | AI46: 21.142 | AJ46: -13.256 | AK46: =SUM(AG46:AJ46) -> -191.507 | AL46: 21.377 | AM46: 20.053 | AN46: 14.583 | AO46: 6.461 | AP46: =SUM(AL46:AO46) -> 62.474 | AQ46: 18.884 | AR46: 12.383 | AS46: 4.198 | AT46: 16.355 | AU46: =SUM(AQ46:AT46) -> 51.82 | AV46: 5.832 | AW46: -38.377 | AX46: 14.926 | AY46: 12.604 | AZ46: =SUM(AV46:AY46) -> -5.015 | BA46: =+'Balance Sheet'!BA55 -> 13.08829 | BB46: =+'Balance Sheet'!BB55 -> 12.691698 | BC46: =+'Balance Sheet'!BC55 -> 10.439836 | BD46: =+'Balance Sheet'!BD55 -> 8.3564899 | BE46: =SUM(BA46:BD46) -> 44.576313 | BF46: =+'Balance Sheet'!BE55 -> 25.733221 | BG46: =+'Balance Sheet'!BF55 -> 31.713193 | BH46: =+'Balance Sheet'!BG55 -> 54.163856 | BI46: =+'Balance Sheet'!BH55 -> 80.203281 | BJ46: =+'Balance Sheet'!BI55 -> 109.76984
B47: Other income | C47: 0 | D47: 0 | E47: 0 | F47: -0.01 | G47: =SUM(C47:F47) -> -0.01 | H47: 0 | I47: 0 | J47: 0 | K47: 0.08 | L47: =SUM(H47:K47) -> 0.08 | M47: 0.02 | N47: 0.063 | O47: 0.017 | P47: -0.59 | Q47: =SUM(M47:P47) -> -0.49 | R47: 0.024 | S47: 0.01 | T47: 0.117 | U47: -0.094 | V47: =SUM(R47:U47) -> 0.057 | W47: 0.031 | X47: 0.028 | Y47: 0.025 | Z47: 0.034 | AA47: =SUM(W47:Z47) -> 0.118 | AB47: 0.065 | AC47: 0.041 | AD47: 0.087 | AE47: 0.391 | AF47: =SUM(AB47:AE47) -> 0.584 | AG47: 0.046 | AH47: 0 | AI47: 0 | AJ47: 0.788 | AK47: =SUM(AG47:AJ47) -> 0.834 | AL47: 0.057 | AM47: 0.118 | AN47: -0.474 | AO47: 0.044 | AP47: =SUM(AL47:AO47) -> -0.255 | AQ47: 0.211 | AR47: 0.038 | AS47: -0.191 | AT47: -0.094 | AU47: =SUM(AQ47:AT47) -> -0.036 | AV47: 0.064 | AW47: 0.123 | AX47: 4.136 | AY47: 0.029 | AZ47: =SUM(AV47:AY47) -> 4.352 | BA47: 0 | BB47: 0 | BC47: 0 | BD47: 0 | BE47: =SUM(BA47:BD47) -> 0 | BF47: 0 | BG47: 0 | BH47: 0 | BI47: 0 | BJ47: 0
B48: =B29 -> Operating Non GAAP adjustments | C48: =-12.23-C66-C32-SUM(C46:C47) -> 0.165 | D48: =-3.713-D66-D32-SUM(D46:D47) -> 0.207 | E48: =-1.569-E66-E32-SUM(E46:E47) -> 0.205 | F48: =2.957-F66-F32-SUM(F46:F47) -> 0.261 | G48: =SUM(C48:F48) -> 0.838 | H48: =-7.952-H66-H32-SUM(H46:H47) -> -0.004 | I48: =-0.185-I66-I32-SUM(I46:I47) -> 0.006 | J48: =0.353-J66-J32-SUM(J46:J47) -> -0.006 | K48: =7.235-K66-K32-SUM(K46:K47) -> -3.384 | L48: =SUM(H48:K48) -> -3.388 | M48: =M29 -> -2.016 | N48: =N29 -> -1.677 | O48: =O29 -> -0.994 | P48: =P29 -> -0.857 | Q48: =SUM(M48:P48) -> -5.544 | R48: =R29 -> -0.732 | S48: =S29 -> -0.791 | T48: =T29 -> -4.471 | U48: =U29 -> -6.388 | V48: =SUM(R48:U48) -> -12.382 | W48: =W29 -> -3.479 | X48: =X29 -> -1.778 | Y48: =Y29 -> -2.315 | Z48: =Z29 -> -5.115 | AA48: =SUM(W48:Z48) -> -12.687 | AB48: =AB29 -> -2.756 | AC48: =AC29 -> -3.776 | AD48: =AD29 -> -5.965 | AE48: =-(0.462+0.32+2.045) -> -2.827 | AF48: =SUM(AB48:AE48) -> -15.324 | AG48: =-1.574-0.172-1.699 -> -3.445 | AH48: 5.096 | AI48: -2.22 | AJ48: =-(1.511+0.219+1.656) -> -3.386 | AK48: =SUM(AG48:AJ48) -> -3.955 | AL48: =-(1.488+0.196+0.308)-25.338 -> -27.33 | AM48: =-(1.489+0.244+0.157+0.33) -> -2.22 | AN48: =-1.489-0.023-0.146-3.843 -> -5.501 | AO48: =-3.103-1.489-0.009-0.137 -> -4.738 | AP48: =SUM(AL48:AO48) -> -39.789 | AQ48: =-1.483-0.005-0.121 -> -1.609 | AR48: =-(1.465+0.001+0.237) -> -1.703 | AS48: =-(1.461+0.225) -> -1.686 | AT48: =-(AT35+AT34) -> -2.715 | AU48: =SUM(AQ48:AT48) -> -7.713 | AV48: =-(AV35+AV34) -> -2.171 | AW48: =-(AW35+AW34) -> -6.408 | AX48: =-(AX35+AX34) -> -37.732 | AY48: =-(AY35+AY34) -> -95.661 | AZ48: =SUM(AV48:AY48) -> -141.972 | BA48: 0 | BB48: 0 | BC48: 0 | BD48: 0 | BE48: =SUM(BA48:BD48) -> 0 | BF48: 0 | BG48: 0 | BH48: 0 | BI48: 0 | BJ48: 0
B49: Pretax income | C49: =C32+SUM(C46:C48) -> -11.58 | D49: =D32+SUM(D46:D48) -> -2.883 | E49: =E32+SUM(E46:E48) -> -0.659 | F49: =F32+SUM(F46:F48) -> 3.681 | G49: =G32+SUM(G46:G48) -> -11.441 | H49: =H32+SUM(H46:H48) -> -7.392 | I49: =I32+SUM(I46:I48) -> 1.475 | J49: =J32+SUM(J46:J48) -> 1.433 | ... L49: =L32+SUM(L46:L48) -> 0.771 | M49: =M32-M45+M46+M47+M48 -> -18.562 | N49: =N32-N45+N46+N47+N48 -> -4.912 | O49: =O32-O45+O46+O47+O48 -> -5.99 | P49: =P32-P45+P46+P47+P48 -> -4.451 | Q49: =Q32+SUM(Q46:Q48) -> 32.871 | R49: =R32-R45+R46+R47+R48 -> -29.498 | S49: =S32-S45+S46+S47+S48 -> -14.731 | T49: =T32-T45+T46+T47+T48 -> -19.246 | U49: =U32-U45+U46+U47+U48 -> -20.339 | V49: =V32-V45+V46+V47+V48 -> -83.814 | W49: =W32-W45+W46+W47+W48 -> -37.215 | X49: =X32-X45+X46+X47+X48 -> -57.062 | Y49: =Y32-Y45+Y46+Y47+Y48 -> -57.013 | ... BJ49: =BJ32-BJ45+BJ46+BJ47+BJ48 -> 875.29149
B50: Taxes | M50: 1.251 | N50: 0.728 | O50: -0.074 | P50: 1.302 | Q50: =SUM(M50:P50) -> 3.207 | R50: 1.242 | S50: 2.001 | T50: -1.879 | U50: 1.234 | V50: =SUM(R50:U50) -> 2.598 | W50: 1.938 | X50: 0.674 | Y50: -0.171 | Z50: 12.548 | AA50: =SUM(W50:Z50) -> 14.989 | AB50: 8.149 | AC50: 34.409 | AD50: 25.374 | AE50: -3.73 | AF50: =SUM(AB50:AE50) -> 64.202 | AG50: -32.555 | AH50: -10.652 | AI50: 6.323 | AJ50: -6.096 | AK50: =SUM(AG50:AJ50) -> -42.98 | AL50: -1.53 | AM50: -0.43 | AN50: 1.342 | AO50: 5.32 | AP50: =SUM(AL50:AO50) -> 4.702 | AQ50: 4.763 | AR50: 1.508 | AS50: 3.075 | AT50: 4.257 | AU50: =SUM(AQ50:AT50) -> 13.603 | AV50: 9.535 | AW50: -51.651 | AX50: 12.28 | AY50: -21.211 | AZ50: =SUM(AV50:AY50) -> -51.047 | BA50: =IF(BA49>0,BA49*BA108,0) -> 0 | BB50: =IF(BB49>0,BB49*BB108,0) -> 1.1092868 | BC50: =IF(BC49>0,BC49*BC108,0) -> 4.1451997 | BD50: =IF(BD49>0,BD49*BD108,0) -> 7.2576657 | BE50: =SUM(BA50:BD50) -> 12.512152 | BF50: =IF(BF49>0,BF49*BF108,0) -> 34.768922 | BG50: =IF(BG49>0,BG49*BG108,0) -> 53.283181 | BH50: =IF(BH49>0,BH49*BH108,0) -> 72.848117 | BI50: =IF(BI49>0,BI49*BI108,0) -> 91.562288 | BJ50: =IF(BJ49>0,BJ49*BJ108,0) -> 109.41144
B51: Loss from equity method | AG51: 0 | AH51: 0 | AI51: 0 | AJ51: 0 | AK51: =SUM(AG51:AJ51) -> 0 | AL51: 0 | AM51: 0 | AN51: 0 | AO51: 0 | AP51: =SUM(AL51:AO51) -> 0 | AQ51: 0 | AR51: 0 | AS51: 0 | AT51: 0 | AU51: =SUM(AQ51:AT51) -> 0 | AV51: 0 | AW51: 0 | AX51: 0 | AY51: 1.49 | AZ51: =SUM(AV51:AY51) -> 1.49 | BE51: =SUM(BA51:BD51) -> 0
B52: GAAP Net Income | M52: =M49-M50 -> -19.813 | N52: =N49-N50 -> -5.64 | O52: =O49-O50 -> -5.916 | P52: =P49-P50 -> -5.753 | Q52: =SUM(M52:P52) -> -37.122 | R52: =R49-R50 -> -30.74 | S52: =S49-S50 -> -16.732 | T52: =T49-T50 -> -17.367 | U52: =U49-U50 -> -21.573 | V52: =SUM(R52:U52) -> -86.412 | W52: =W49-W50 -> -39.153 | X52: =X49-X50 -> -57.736 | Y52: =Y49-Y50 -> -56.842 | Z52: =Z49-Z50 -> -11.423 | AA52: =SUM(W52:Z52) -> -165.154 | AB52: =AB49-AB50 -> -121.752 | AC52: =AC49-AC50 -> 37.957 | AD52: =AD49-AD50 -> 16.667 | AE52: =AE49-AE50 -> -111.019 | AF52: =SUM(AB52:AE52) -> -178.147 | AG52: =AG49-AG50 -> -227.289 | AH52: =AH49-AH50 -> -111.238 | AI52: =AI49-AI50 -> -47.363 | AJ52: =AJ49-AJ50 -> -38.975 | AK52: =SUM(AG52:AJ52) -> -424.865 | AL52: =AL49-AL50 -> -10.369 | AM52: =AM49-AM50 -> 33.577 | AN52: =AN49-AN50 -> 6.975 | AO52: =AO49-AO50 -> 2.954 | AP52: =SUM(AL52:AO52) -> 33.137 | AQ52: =AQ49-AQ50 -> 24.002 | AR52: =AR49-AR50 -> 39.518 | AS52: =AS49-AS50 -> 26.778 | AT52: =AT49-AT50 -> 48.024 | AU52: =SUM(AQ52:AT52) -> 138.322 | AV52: =AV49-AV50 -> 33.766 | AW52: =AW49-AW50 -> 57.703 | AX52: =AX49-AX50 -> -0.589 | AY52: =AY49-AY50-AY51 -> -40.234 | AZ52: =SUM(AV52:AY52) -> 50.646 | BA52: =BA49-BA50 -> -7.6978986 | BB52: =BB49-BB50 -> 7.7650079 | BC52: =BC49-BC50 -> 29.016398 | BD52: =BD49-BD50 -> 50.80366 | BE52: =SUM(BA52:BD52) -> 79.887167 | BF52: =BF49-BF50 -> 243.38245 | BG52: =BG49-BG50 -> 372.98227 | BH52: =BH49-BH50 -> 509.93682 | BI52: =BI49-BI50 -> 640.93601 | BJ52: =BJ49-BJ50 -> 765.88006
B62: SBC | AE62: 71.294
B63: Other Non GAAP adj | AE63: =0.462+2.045+1.298+0.32+16.195+2.013-3.725 -> 18.608
B64: GAAP Net Income | AE64: =AE39-SUM(AE62:AE63) -> -111.019
B66: Taxes | C66: -0.65 | D66: -0.83 | E66: -0.91 | F66: -0.724 | G66: =SUM(C66:F66) -> -3.114 | H66: -0.56 | I66: -1.66 | J66: -1.08 | K66: 1.98 | L66: =SUM(H66:K66) -> -1.32 | M66: -1.251 | N66: -0.73 | O66: 0.07 | P66: -1.3 | Q66: =SUM(M66:P66) -> -3.211 | R66: -1.24 | S66: -2 | T66: 1.879 | U66: -1.234 | V66: =SUM(R66:U66) -> -2.595 | W66: -1.938 | X66: -0.674 | Y66: 0.171 | Z66: 2.795 | AA66: =SUM(W66:Z66) -> 0.354 | AB66: -8.149 | AC66: -34.409 | AD66: -25.374 | AE66: -3.73 | AF66: =SUM(AB66:AE66) -> -71.662 | AG66: =AG49*-AG108 -> -32.555 | AH66: =AH49*-AH108 -> -10.652 | AI66: =AI49*-AI108 -> 6.323 | AJ66: =AJ49*-AJ108 -> -6.096 | AK66: =SUM(AG66:AJ66) -> -42.98 | AL66: =AL49*-AL108 -> -1.53 | AM66: =AM49*-AM108 -> -0.43 | AN66: =AN49*-AN108 -> 1.342 | AO66: =AO49*-AO108 -> 5.32 | AP66: =SUM(AL66:AO66) -> 4.702 | AQ66: =AQ49*-AQ108 -> 4.763 | AR66: =AR49*-AR108 -> 1.508 | AS66: =AS49*-AS108 -> 3.075 | AT66: =AT49*-AT108 -> 4.257 | AU66: =SUM(AQ66:AT66) -> 13.603 | AV66: =AV49*-AV108 -> 9.535 | AW66: =AW49*-AW108 -> -51.651 | AX66: =AX49*-AX108 -> 12.28 | AY66: =AY49*-AY108 -> -21.211 | AZ66: =AZ49*-AZ108 -> -51.047 | BA66: =BA49*-BA108 -> 0.96223732 | BB66: =BB49*-BB108 -> -1.1092868 | BC66: =BC49*-BC108 -> -4.1451997 | ... BJ66: =BJ49*-BJ108 -> -109.41144
B68: GAAP Net Income
B69: Non-GAAP Net Income | C69: =C49+C66 -> -12.23 | D69: =D49+D66 -> -3.713 | E69: =E49+E66 -> -1.569 | F69: =F49+F66 -> 2.957 | G69: =G49+G66 -> -14.555 | H69: =H49+H66 -> -7.952 | I69: =I49+I66 -> -0.185 | J69: =J49+J66 -> 0.353 | ... BJ69: =BJ49+BJ66 -> 765.88006
B71: Basic Non-GAAP EPS | C71: =C69/C77 -> -0.30288097 | D71: =D69/D77 -> -0.090194502 | E71: =E69/E77 -> -0.036763552 | F71: =F69/F77 -> 0.067346297 | G71: =G69/G77 -> -0.34627757 | H71: =H69/H77 -> -0.17791321 | I71: =I69/I77 -> -0.0040757446 | J71: =J69/J77 -> 0.0077001286 | ... L71: =L69/L77 -> -0.012052853 | M71: =M39/M77 -> -0.057423614 | N71: =N39/N77 -> 0.28949868 | O71: =O39/O77 -> 0.38770358 | P71: =P39/P77 -> 0.4234144 | Q71: =Q69/Q77 -> 0.61769548 | R71: =R39/R77 -> 0.029619247 | S71: =S39/S77 -> 0.33731813 | T71: =T39/T77 -> 0.40945886 | U71: =U39/U77 -> 0.38771536 | V71: =V39/V77 -> 1.1711782 | W71: =W39/W77 -> -0.0076391373 | X71: =X39/X77 -> -0.25907078 | Y71: =Y39/Y77 -> -0.14480564 | ... BJ71: =BJ39/BJ77 -> 20.609326
B72: Dilluted Non-GAAP EPS | C72: =C69/C78 -> -0.23052744 | D72: =D69/D78 -> -0.070609464 | E72: =E69/E78 -> -0.029536493 | F72: =F69/F78 -> 0.055084436 | G72: =G69/G78 -> -0.27405485 | H72: =H69/H78 -> -0.14328082 | I72: =I69/I78 -> -0.0033110167 | J72: =J69/J78 -> 0.0066623976 | ... L72: =L69/L78 -> -0.0099402809 | M72: =M39/M78 -> -0.057423614 | N72: =N39/N78 -> 0.28949868 | O72: =O39/O78 -> 0.38770358 | P72: =P39/P78 -> 0.4234144 | Q72: =Q69/Q78 -> 0.61769548 | R72: =R39/R78 -> 0.029619247 | S72: =S39/S78 -> 0.33731813 | T72: =T39/T78 -> 0.40945886 | U72: =U39/U78 -> 0.38771536 | V72: =V39/V78 -> 1.1711782 | W72: =W39/W78 -> -0.0076391373 | X72: =X39/X78 -> -0.25907078 | Y72: =Y39/Y78 -> -0.14480564 | ... AA72: =AA39/AA78 -> -0.44490538 | AB72: =IF(AB39>0,AB39/AB78,AB71) -> -0.53579779 | AC72: =IF(AC39>0,AC39/AC78,AC71) -> -0.27607822 | AD72: =IF(AD39>0,AD39/AD78,AD71) -> -0.20834443 | AE72: =IF(AE39>0,AE39/AE78,AE71) -> -0.36882891 | AF72: =IF(AF39>0,AF39/AF78,AF71) -> -1.3856256 | AG72: =IF(AG39>0,AG39/AG78,AG71) -> -0.72015329 | AH72: =IF(AH39>0,AH39/AH78,AH71) -> -0.1350807 | AI72: =IF(AI39>0,AI39/AI78,AI71) -> 0.053940182 | ... BJ72: =IF(BJ39>0,BJ39/BJ78,BJ71) -> 19.156877
B74: Basic GAAP EPS | AB74: =AB52/AB77 -> -2.1633047 | AC74: =AC52/AC77 -> 0.66239577 | AD74: =AD52/AD77 -> 0.29080283 | AE74: =AE52/AE77 -> -1.9390546 | AF74: =AF52/AF77 -> -3.1233161 | AG74: =AG52/AG77 -> -3.9542668 | AH74: =AH52/AH77 -> -1.9197786 | AI74: =AI52/AI77 -> -0.81162814 | ... BJ74: =BJ52/BJ77 -> 15.50732
B75: Dilluted GAAP EPS | AB75: =AB52/AB78 -> -2.1633047 | AC75: =AC52/AC78 -> 0.58441738 | AD75: =AD52/AD78 -> 0.27526078 | AE75: =AE52/AE78 -> -1.7292597 | AF75: =AF52/AF78 -> -2.8969446 | AG75: =AG52/AG78 -> -3.4765606 | AH75: =AH52/AH78 -> -1.6860178 | AI75: =AI52/AI78 -> -0.71522084 | ... BJ75: =BJ52/BJ78 -> 14.414436
B77: Basic Shares | C77: 40.378899 | D77: 41.166589 | E77: 42.67814 | F77: 43.907388 | G77: =AVERAGE(C77:F77) -> 42.032754 | H77: 44.695951 | I77: 45.390479 | J77: 45.84339 | K77: 46.267701 | L77: =AVERAGE(H77:K77) -> 45.54938 | M77: 46.827425 | N77: 47.689337 | O77: 48.498392 | P77: 49.053599 | Q77: =AVERAGE(M77:P77) -> 48.017188 | R77: 49.562367 | S77: 50.273017 | T77: 50.862253 | U77: 51.321155 | V77: =AVERAGE(R77:U77) -> 50.504698 | W77: 51.838314 | X77: 54.695477 | Y77: 55.356961 | Z77: 55.809471 | AA77: =AVERAGE(W77:Z77) -> 54.425056 | AB77: 56.280561 | AC77: 57.3026 | AD77: 57.313747 | AE77: 57.254189 | AF77: =AVERAGE(AB77:AE77) -> 57.037774 | AG77: 57.479429 | AH77: 57.94314 | AI77: 58.355542 | AJ77: 58.189246 | AK77: =AVERAGE(AG77:AJ77) -> 57.991839 | AL77: 56.408677 | AM77: 56.744007 | AN77: 56.837917 | AO77: 57.317815 | AP77: =AVERAGE(AL77:AO77) -> 56.827104 | AQ77: 56.098997 | AR77: 55.631595 | AS77: 55.099939 | AT77: 56.107932 | AU77: =AVERAGE(AQ77:AT77) -> 55.734616 | AV77: 55.70867 | AW77: 55.905451 | AX77: 55.651271 | AY77: 54.944944 | AZ77: =AVERAGE(AV77:AY77) -> 55.552584 | BA77: =+AY77*1.02-'Cash Flow'!BA61 -> 51.337961 | BB77: =+BA77*1.02-'Cash Flow'!BB61 -> 48.154193 | BC77: =+BB77*1.02-'Cash Flow'!BC61 -> 45.307753 | BD77: =+BC77*1.02-'Cash Flow'!BD61 -> 42.735648 | BE77: =AVERAGE(BA77:BD77) -> 46.883889 | BF77: =+BE77*1.025-'Cash Flow'!BF61 -> 44.743357 | BG77: =+BF77*1.025-'Cash Flow'!BG61 -> 45.861941 | BH77: =+BG77*1.025-'Cash Flow'!BH61 -> 47.008489 | BI77: =+BH77*1.025-'Cash Flow'!BI61 -> 48.183701 | BJ77: =+BI77*1.025-'Cash Flow'!BJ61 -> 49.388294
B78: Diluted Shares | C78: 53.052252 | D78: 52.585019 | E78: 53.120727 | F78: 53.681225 | G78: =AVERAGE(C78:F78) -> 53.109806 | H78: 55.499403 | I78: 55.874077 | J78: 52.983929 | K78: 56.561901 | L78: =AVERAGE(H78:K78) -> 55.229828 | M78: 46.827425 | N78: 47.689337 | O78: 48.498392 | P78: 49.053599 | Q78: =AVERAGE(M78:P78) -> 48.017188 | R78: 49.562367 | S78: 50.273017 | T78: 50.862253 | U78: 51.321155 | V78: =AVERAGE(R78:U78) -> 50.504698 | W78: 51.838314 | X78: 54.695477 | Y78: 55.356961 | Z78: 55.809471 | AA78: =AVERAGE(W78:Z78) -> 54.425056 | AB78: =AB77 -> 56.280561 | AC78: 64.948445 | AD78: 60.549853 | AE78: 64.200305 | AF78: =AVERAGE(AB78:AE78) -> 61.494791 | AG78: =AG77+5.099095+2.799022 -> 65.377546 | AH78: =+AH77+5.024271+3.009354 -> 65.976765 | AI78: =+AI77+4.964207+2.901755 -> 66.221504 | AJ78: =AJ77+4.332022+3.123019 -> 65.644287 | AK78: =AVERAGE(AG78:AJ78) -> 65.805025 | AL78: =AL77+4.149981+3.538527 -> 64.097185 | AM78: =62.186985+1.982546+1.263342 -> 65.432873 | AN78: =58.497072+1.940648+1.162995 -> 61.600715 | AO78: =59.085757+2.245872+0.818288 -> 62.149917 | AP78: =AVERAGE(AL78:AO78) -> 63.320172 | AQ78: =58.647238+1.315926+0.406968 -> 60.370132 | AR78: 59.526418 | AS78: 58.166801 | AT78: 62.65857 | AU78: =AVERAGE(AQ78:AT78) -> 60.18048 | AV78: 60.38451 | AW78: 59.650008 | AX78: =+AX77+AW78-AW77 -> 59.395828 | AY78: =+AY77+AX78-AX77 -> 58.689501 | AZ78: =AVERAGE(AV78:AY78) -> 59.529962 | BA78: =+BA77+AY78-AY77 -> 55.082518 | BB78: =+BB77+BA78-BA77 -> 51.89875 | BC78: =+BC77+BB78-BB77 -> 49.05231 | BD78: =+BD77+BC78-BC77 -> 46.480205 | BE78: =AVERAGE(BA78:BD78) -> 50.628446 | BF78: =+BF77+BE78-BE77 -> 48.487914 | BG78: =+BG77+BF78-BF77 -> 49.606498 | BH78: =+BH77+BG78-BG77 -> 50.753046 | BI78: =+BI77+BH78-BH77 -> 51.928258 | BJ78: =+BJ77+BI78-BI77 -> 53.132851
B80: FCF | H80: ='Cash Flow'!C16+'Cash Flow'!C21+'Cash Flow'!C22 -> 14.781 | I80: ='Cash Flow'!D16+'Cash Flow'!D21+'Cash Flow'!D22 -> 17.412 | J80: ='Cash Flow'!E16+'Cash Flow'!E21+'Cash Flow'!E22 -> 18.935 | K80: ='Cash Flow'!F16+'Cash Flow'!F21+'Cash Flow'!F22 -> 19.524 | L80: =SUM(H80:K80) -> 70.652 | M80: ='Cash Flow'!H16+'Cash Flow'!H21+'Cash Flow'!H22 -> 21.421 | N80: ='Cash Flow'!I16+'Cash Flow'!I21+'Cash Flow'!I22 -> 23.857 | O80: ='Cash Flow'!J16+'Cash Flow'!J21+'Cash Flow'!J22 -> 23.691 | P80: ='Cash Flow'!K16+'Cash Flow'!K21+'Cash Flow'!K22 -> 32.664 | Q80: =SUM(M80:P80) -> 101.633 | R80: ='Cash Flow'!M16+'Cash Flow'!M21+'Cash Flow'!M22 -> 30.046 | S80: ='Cash Flow'!N16+'Cash Flow'!N21+'Cash Flow'!N22 -> 30.754 | T80: ='Cash Flow'!O16+'Cash Flow'!O21+'Cash Flow'!O22 -> 29.227 | U80: ='Cash Flow'!P16+'Cash Flow'!P21+'Cash Flow'!P22 -> 37.471 | V80: =SUM(R80:U80) -> 127.498 | W80: ='Cash Flow'!R16+'Cash Flow'!R21+'Cash Flow'!R22 -> 39.952 | X80: ='Cash Flow'!S16+'Cash Flow'!S21+'Cash Flow'!S22 -> 46.694 | Y80: ='Cash Flow'!T16+'Cash Flow'!T21+'Cash Flow'!T22 -> 19.38 | Z80: ='Cash Flow'!U16+'Cash Flow'!U21+'Cash Flow'!U22 -> 23.17 | AA80: =SUM(W80:Z80) -> 129.196 | AB80: ='Cash Flow'!AB16+'Cash Flow'!AB21+'Cash Flow'!AB22 -> 14.639 | AC80: ='Cash Flow'!AC16+'Cash Flow'!AC21+'Cash Flow'!AC22 -> 14.714 | AD80: ='Cash Flow'!AD16+'Cash Flow'!AD21+'Cash Flow'!AD22 -> -8.707 | AE80: ='Cash Flow'!AE16+'Cash Flow'!AE21+'Cash Flow'!AE22 -> 7.339 | AF80: =SUM(AB80:AE80) -> 27.985 | AG80: ='Cash Flow'!AG16+'Cash Flow'!AG21+'Cash Flow'!AG22 -> -33.586 | AH80: ='Cash Flow'!AH16+'Cash Flow'!AH21+'Cash Flow'!AH22 -> -15.886 | AI80: ='Cash Flow'!AI16+'Cash Flow'!AI21+'Cash Flow'!AI22 -> -22.607 | AJ80: ='Cash Flow'!AJ16+'Cash Flow'!AJ21+'Cash Flow'!AJ22 -> 38.585 | AK80: =SUM(AG80:AJ80) -> -33.494 | AL80: ='Cash Flow'!AL16+'Cash Flow'!AL21+'Cash Flow'!AL22 -> 25.029 | AM80: ='Cash Flow'!AM16+'Cash Flow'!AM21+'Cash Flow'!AM22 -> 32.01 | AN80: ='Cash Flow'!AN16+'Cash Flow'!AN21+'Cash Flow'!AN22 -> 44.768 | AO80: ='Cash Flow'!AO16+'Cash Flow'!AO21+'Cash Flow'!AO22 -> 80.39 | AP80: ='Cash Flow'!AP16+'Cash Flow'!AP21+'Cash Flow'!AP22 -> 182.197 | AQ80: ='Cash Flow'!AQ16+'Cash Flow'!AQ21+'Cash Flow'!AQ22 -> 105.711 | AR80: ='Cash Flow'!AR16+'Cash Flow'!AR21+'Cash Flow'!AR22 -> 112.833 | AS80: ='Cash Flow'!AS16+'Cash Flow'!AS21+'Cash Flow'!AS22 -> 127.761 | ... BJ80: ='Cash Flow'!BJ16+'Cash Flow'!BJ21+'Cash Flow'!BJ22 -> 1100.1975
B81: FCF/Share | H81: =H80/H78 -> 0.26632719 | I81: =I80/I78 -> 0.31162931 | J81: =J80/J78 -> 0.35737252 | K81: =K80/K78 -> 0.34517935 | L81: =SUM(H81:K81) -> 1.2805084 | M81: =M80/M78 -> 0.45744561 | N81: =N80/N78 -> 0.50025858 | O81: =O80/O78 -> 0.48849042 | P81: =P80/P78 -> 0.66588386 | Q81: =SUM(M81:P81) -> 2.1120785 | R81: =R80/R78 -> 0.60622609 | S81: =S80/S78 -> 0.61173969 | T81: =T80/T78 -> 0.57463046 | U81: =U80/U78 -> 0.73012776 | V81: =SUM(R81:U81) -> 2.522724 | W81: =W80/W78 -> 0.77070408 | X81: =X80/X78 -> 0.85370862 | Y81: =Y80/Y78 -> 0.35009147 | Z81: =Z80/Z78 -> 0.41516251 | AA81: =SUM(W81:Z81) -> 2.3896667 | AB81: =AB80/AB78 -> 0.26010757 | AC81: =AC80/AC78 -> 0.22654892 | AD81: =AD80/AD78 -> -0.14379886 | AE81: =AE80/AE78 -> 0.1143141 | AF81: =SUM(AB81:AE81) -> 0.45717173 | AG81: =AG80/AG78 -> -0.51372378 | AH81: =AH80/AH78 -> -0.24078174 | AI81: =AI80/AI78 -> -0.34138458 | AJ81: =AJ80/AJ78 -> 0.58778916 | AK81: =SUM(AG81:AJ81) -> -0.50810093 | AL81: =AL80/AL78 -> 0.39048517 | AM81: =AM80/AM78 -> 0.48920365 | AN81: =AN80/AN78 -> 0.72674481 | AO81: =AO80/AO78 -> 1.2934852 | AP81: =AP80/AP78 -> 2.8773927 | AQ81: =AQ80/AQ78 -> 1.751048 | AR81: =AR80/AR78 -> 1.8955113 | AS81: =AS80/AS78 -> 2.1964591 | ... BI81: =BI80/BI78 -> 18.97911 | BJ81: =BJ80/BJ$78 -> 20.70654
B82: FCF ex Build Out and Acq Costs | W82: =+'Cash Flow'!R48 -> 40.435 | X82: =+'Cash Flow'!S48 -> 47.102 | Y82: =+'Cash Flow'!T48 -> 20.159 | Z82: =+'Cash Flow'!U48 -> 23.962 | AA82: =+'Cash Flow'!V48 -> 131.658 | AB82: =+'Cash Flow'!AB48 -> 15.474 | AC82: =+'Cash Flow'!AC48 -> 16.911 | AD82: =+'Cash Flow'!AD48 -> 1.663 | AE82: =+'Cash Flow'!AE48 -> 17.339 | AF82: =+'Cash Flow'!AF48 -> 51.387 | AG82: =+'Cash Flow'!AG48 -> -13.586 | AH82: =+'Cash Flow'!AH48 -> -5.986 | AI82: =+'Cash Flow'!AI48 -> 4.559 | ... BJ82: =+'Cash Flow'!BJ48 -> 1100.1975
B83: FCF ex Build Out/Share | W83: =W82/W$78 -> 0.78002151 | X83: =X82/X$78 -> 0.8611681 | Y83: =Y82/Y$78 -> 0.36416378 | Z83: =Z82/Z$78 -> 0.42935365 | AA83: =AA82/AA$78 -> 2.4190696 | AB83: =AB82/AB$78 -> 0.27494395 | AC83: =AC82/AC$78 -> 0.26037575 | AD83: =AD82/AD$78 -> 0.027464972 | ... BJ83: =BJ82/BJ$78 -> 20.70654
B84: FCF Margin ex Build Out | AA84: =+AA82/AA13 -> 0.13315466 | AF84: =+AF82/AF13 -> 0.040473136 | AK84: =+AK82/AK13 -> 0.026643299 | AL84: =+AL82/AL13 -> 0.11770068 | AM84: =+AM82/AM13 -> 0.12588691 | AN84: =+AN82/AN13 -> 0.15948314 | AO84: =+AO82/AO13 -> 0.2232082 | AP84: =+AP82/AP13 -> 0.15756132 | AQ84: =+AQ82/AQ13 -> 0.26460064 | AR84: =+AR82/AR13 -> 0.2703318 | ... BJ84: =+BJ82/BJ13 -> 0.32441592
B85: Rule of | AK85: =+AK84+AK112 -> 0.11958887 | AP85: =+AP84+AP112 -> 0.282951 | AU85: =+AU84+AU112 -> 0.40481775 | AZ85: =+AZ84+AZ112 -> 0.18201061 | BE85: =+BE84+BE112 -> 0.37567241 | BF85: =+BF84+BF112 -> 0.36634573 | BG85: =+BG84+BG112 -> 0.36035758 | BH85: =+BH84+BH112 -> 0.36276296 | BI85: =+BI84+BI112 -> 0.36793365 | BJ85: =+BJ84+BJ112 -> 0.37577102
B87: FCF ex HQ Guide
B88: High | AJ88: 50 | AP88: 240 | AU88: 488
B89: Midpoint | AJ89: =AVERAGE(AJ88,AJ90) -> 48.5 | AP89: =AVERAGE(AP88,AP90) -> 237.5 | AU89: =AVERAGE(AU88,AU90) -> 485.5 | AZ89: 600
B90: Low | AJ90: 47 | AP90: 235 | AU90: 483
B91: Needham vs Midpoint | AJ91: =AJ82/AJ89-1 -> 0.07185567 | AP91: =AP82/AP89-1 -> 0.036033684 | AU91: =AU82/AU89-1 -> 0.0059794027 | AZ91: =AZ82/AZ89-1 -> -0.83385548
B93: As Percent of Revenue
B94: =+B5 -> Change in deferred revenue | C94: =+C5/C13 -> 0.22906316 | D94: =+D5/D13 -> 0.18511567 | E94: =+E5/E13 -> 0.15419918 | F94: =+F5/F13 -> 0.16008553 | G94: =+G5/G13 -> 0.17912516 | H94: =+H5/H13 -> 0.23782148 | I94: =+I5/I13 -> 0.13136592 | J94: =+J5/J13 -> 0.081851752 | ... AO94: =+AO5/AO13 -> -0.021712803 | AP94: =AP5/AP13 -> 0.022946663 | AQ94: =+AQ5/AQ13 -> 0.08934527 | AR94: =+AR5/AR13 -> 0.051986708 | AS94: =+AS5/AS13 -> 0.017570215 | AT94: =+AT5/AT13 -> 0.0090019654 | AU94: =AU5/AU13 -> 0.040959873 | AV94: =+AV5/AV13 -> 0.078652848 | AW94: =+AW5/AW13 -> 0.040809912 | AX94: =+AX5/AX13 -> 0.018505762 | AY94: =+AY5/AY13 -> 0.0092090129 | AZ94: =AZ5/AZ13 -> 0.035837142 | BA94: =+BA5/BA13 -> 0.064545698 | BB94: =+BB5/BB13 -> 0.037910408 | BC94: =+BC5/BC13 -> 0.019084757 | BD94: =+BD5/BD13 -> 0 | BE94: =BE5/BE13 -> 0.029301753 | BF94: =BF5/BF13 -> 0.027533529 | BG94: =BG5/BG13 -> 0.026403706 | BH94: =BH5/BH13 -> 0.025744492 | BI94: =BI5/BI13 -> 0.025444036 | BJ94: =BJ5/BJ13 -> 0.025411241
B95: =B14 -> Creative Subscriptions | Q95: =Q14/Q13 -> 0.87021123 | R95: =R14/R13 -> 0.86846061 | S95: =S14/S13 -> 0.84679564 | T95: =T14/T13 -> 0.83723849 | U95: =U14/U13 -> 0.83756134 | V95: =V14/V13 -> 0.84680352 | W95: =W14/W13 -> 0.81739179 | X95: =X14/X13 -> 0.80559945 | ... BJ95: =BJ14/BJ13 -> 0.71142627
B96: =B15 -> Business Solutions | Q96: =Q15/Q13 -> 0.12978877 | R96: =R15/R13 -> 0.13153939 | S96: =S15/S13 -> 0.15320436 | T96: =T15/T13 -> 0.16276151 | U96: =U15/U13 -> 0.16243866 | V96: =V15/V13 -> 0.15319648 | W96: =W15/W13 -> 0.18260821 | X96: =X15/X13 -> 0.19440055 | ... BJ96: =BJ15/BJ13 -> 0.28857373
B97: Gross margin, non GAAP | C97: =C24/C13 -> 0.83630459 | D97: =D24/D13 -> 0.84657355 | E97: =E24/E13 -> 0.86041529 | F97: =F24/F13 -> 0.85375386 | G97: =G24/G13 -> 0.85008445 | H97: =H24/H13 -> 0.84515885 | I97: =I24/I13 -> 0.8426391 | J97: =J24/J13 -> 0.84430334 | ... BJ97: =BJ24/BJ13 -> 0.69820634
B98: Opex (of Revenue) | R98: =R30/R13 -> 0.79200757 | S98: =S30/S13 -> 0.67953122 | T98: =T30/T13 -> 0.67463959 | U98: =U30/U13 -> 0.64405537 | V98: =V30/V13 -> 0.69448737 | W98: =W30/W13 -> 0.73959081 | X98: =X30/X13 -> 0.78138093 | Y98: =Y30/Y13 -> 0.72900307 | ... BJ98: =BJ30/BJ13 -> 0.39817517 | BL98: <45%
B99: =+B26 -> Sales & marketing, non GAAP | C99: =C26/C13 -> 0.64002273 | D99: =D26/D13 -> 0.50592172 | E99: =E26/E13 -> 0.51097738 | F99: =F26/F13 -> 0.45938465 | G99: =G26/G13 -> 0.52220537 | H99: =H26/H13 -> 0.5646099 | I99: =I26/I13 -> 0.44605873 | J99: =J26/J13 -> 0.44405116 | ... BE99: =BE26/BE13 -> 0.31003598 | BF99: =MAX(+BE99*0.85,0.15) -> 0.26353058 | BG99: =MAX(+BF99*0.925,0.15) -> 0.24376579 | BH99: =MAX(+BG99*0.925,0.15) -> 0.22548336 | BI99: =MAX(+BH99*0.925,0.15) -> 0.2085721 | BJ99: =MAX(+BI99*0.925,0.15) -> 0.1929292
B100: =+B27 -> Research and development, non GAAP | C100: =C27/C13 -> 0.32539373 | D100: =D27/D13 -> 0.31245453 | E100: =E27/E13 -> 0.29437905 | F100: =F27/F13 -> 0.28581611 | G100: =G27/G13 -> 0.30276102 | H100: =H27/H13 -> 0.28197536 | I100: =I27/I13 -> 0.281733 | J100: =J27/J13 -> 0.28854364 | ... BJ100: =BJ27/BJ13 -> 0.16556009
B101: =+B28 -> General & administrative, non GAAP | C101: =C28/C13 -> 0.069865238 | D101: =D28/D13 -> 0.071555362 | E101: =E28/E13 -> 0.070453644 | F101: =F28/F13 -> 0.062461392 | G101: =G28/G13 -> 0.068270656 | H101: =H28/H13 -> 0.080030257 | I101: =I28/I13 -> 0.080950541 | J101: =J28/J13 -> 0.080915068 | ... BE101: =BE28/BE13 -> 0.05289924 | BF101: =MAX(+BE101*0.95,0.05) -> 0.050254278 | BG101: =MAX(+BF101*0.95,0.05) -> 0.05 | BH101: =MAX(+BG101*0.95,0.05) -> 0.05 | BI101: =MAX(+BH101*0.95,0.05) -> 0.05 | BJ101: =MAX(+BI101*0.95,0.05) -> 0.05
B102: Operating margin | C102: =+C41/C13 -> 0.019483682 | D102: =+D41/D13 -> 0.017459625 | E102: =+E41/E13 -> 0.015870917 | F102: =+F41/F13 -> 0.010691376 | G102: =+G41/G13 -> 0.015511358 | H102: =+H41/H13 -> 0.014047979 | I102: =+I41/I13 -> 0.01255796 | J102: =+J41/J13 -> 0.013509862 | ... Q102: =+Q41/Q13 -> 0.01445079 | R102: =R32/R13 -> -0.012352975 | S102: =S32/S13 -> 0.07655634 | T102: =T32/T13 -> 0.062289434 | U102: =U32/U13 -> 0.083919878 | V102: =V32/V13 -> 0.054486472 | W102: =W32/W13 -> -0.019417835 | X102: =X32/X13 -> -0.072041312 | Y102: =Y32/Y13 -> -0.033452671 | ... BJ102: =BJ32/BJ13 -> 0.30003117
B103: adj EBITDA margin (Bookings) | C103: =C43/C4 -> 0.035192475 | D103: =D43/D4 -> 0.13114311 | E103: =E43/E4 -> 0.13022952 | F103: =F43/F4 -> 0.18306095 | G103: =G43/G4 -> 0.12449865 | H103: =H43/H4 -> 0.13094947 | I103: =I43/I4 -> 0.14771301 | J103: =J43/J4 -> 0.1073944 | ... BJ103: =BJ43/BJ4 -> 0.32435374
B104: adj EBITDA margin (Revenues) | C104: =C43/C13 -> 0.043253775 | D104: =D43/D13 -> 0.15541976 | E104: =E43/E13 -> 0.15031081 | F104: =F43/F13 -> 0.21236636 | G104: =G43/G13 -> 0.14679949 | H104: =H43/H13 -> 0.16209207 | I104: =I43/I13 -> 0.16711747 | J104: =J43/J13 -> 0.11618481 | ... BJ104: =BJ43/BJ13 -> 0.33259597
B105: FCF Margin (Bookings) | H105: =H80/H4 -> 0.12903761 | I105: =I80/I4 -> 0.1486693 | J105: =J80/J4 -> 0.15763666 | K105: =K80/K4 -> 0.14768756 | L105: =L80/L4 -> 0.14598033 | M105: =M80/M4 -> 0.13417056 | N105: =N80/N4 -> 0.14920417 | O105: =O80/O4 -> 0.14554267 | ... BJ105: =BJ80/BJ4 -> 0.3163764
B106: FCF Margin (Revenues) | H106: =H80/H13 -> 0.15972552 | I106: =I80/I13 -> 0.16819938 | J106: =J80/J13 -> 0.17053949 | K106: =K80/K13 -> 0.1647039 | L106: =L80/L13 -> 0.16599394 | M106: =M80/M13 -> 0.15547813 | N106: =N80/N13 -> 0.16325651 | O106: =O80/O13 -> 0.15225578 | ... BJ106: =BJ80/BJ13 -> 0.32441592
B107: FCF Margin ex HQ Build | AB107: =AB82/AB13 -> 0.05088257 | AC107: =AC82/AC13 -> 0.053447153 | AD107: =AD82/AD13 -> 0.0051839637 | AE107: =AE82/AE13 -> 0.052807743 | AF107: =AF82/AF13 -> 0.040473136 | AG107: =AG82/AG13 -> -0.039772012 | AH107: =AH82/AH13 -> -0.017339467 | AI107: =AI82/AI13 -> 0.013183731 | ... BJ107: =BJ82/BJ13 -> 0.32441592
B108: Tax Rate | C108: =-C66/C49 -> -0.056131261 | D108: =-D66/D49 -> -0.28789455 | E108: =-E66/E49 -> -1.3808801 | F108: =-F66/F49 -> 0.19668568 | G108: =-G66/G49 -> -0.27217901 | H108: =-H66/H49 -> -0.075757576 | I108: =-I66/I49 -> 1.1254237 | J108: =-J66/J49 -> 0.75366364 | ... L108: =-L66/L49 -> 1.7120623 | M108: =-M50/M49 -> 0.067395755 | N108: =-N50/N49 -> 0.14820847 | O108: =-O50/O49 -> -0.012353923 | P108: =-P50/P49 -> 0.29251854 | Q108: =-Q66/Q49 -> 0.097684889 | R108: =-R50/R49 -> 0.042104549 | S108: =-S50/S49 -> 0.13583599 | T108: =-T50/T49 -> -0.097630677 | U108: =-U50/U49 -> 0.060671616 | V108: =-V66/V49 -> -0.030961415 | W108: =-W50/W49 -> 0.052075776 | X108: =-X50/X49 -> 0.011811714 | Y108: =-Y50/Y49 -> -0.0029993159 | Z108: =-Z50/Z49 -> -11.153778 | AA108: =-AA66/AA49 -> 0.0023574069 | AB108: =-AB50/AB49 -> 0.071732261 | AC108: =-AC50/AC49 -> -0.47548573 | AD108: =-AD50/AD49 -> -0.60355367 | AE108: =-AE50/AE49 -> -0.03250573 | AF108: =-AF66/AF49 -> -0.62891746 | AG108: =-AG50/AG49 -> -0.12528671 | AH108: =-AH50/AH49 -> -0.08739027 | AI108: =-AI50/AI49 -> 0.1540692 | AJ108: =-AJ50/AJ49 -> -0.13525327 | AK108: =-AK66/AK49 -> -0.091868033 | AL108: =-AL50/AL49 -> -0.12858223 | AM108: =-AM50/AM49 -> 0.012972516 | AN108: =-AN50/AN49 -> -0.16135626 | AO108: =-AO50/AO49 -> -0.642978 | AP108: =-AP66/AP49 -> -0.12426333 | AQ108: =-AQ50/AQ49 -> -0.16558317 | AR108: =-AR50/AR49 -> -0.036757178 | AS108: =-AS50/AS49 -> -0.10300472 | AT108: =-AT50/AT49 -> -0.081425374 | AU108: =-AU50/AU49 -> -0.089537601 | AV108: =-AV50/AV49 -> -0.22020277 | AW108: =-AW50/AW49 -> 8.534534 | AX108: =-AX50/AX49 -> -1.0503806 | ... AZ108: =-AZ50/AZ49 -> 46.875115 | BA108: 0.125 | BB108: 0.125 | BC108: 0.125 | BD108: 0.125 | BE108: =-BE50/BE49 -> -0.1354139 | BF108: 0.125 | BG108: 0.125 | BH108: 0.125 | BI108: 0.125 | BJ108: 0.125
AU109: =+AU104-AP104 -> 0.063100364 | AZ109: =+AZ104-AU104 -> -0.011936659 | BE109: =+BE104-AZ104 -> -0.074716963
B110: Y/Y Growth
B111: Bookings | H111: =H4/C4-1 -> 0.5132236 | I111: =I4/D4-1 -> 0.43787215 | J111: =J4/E4-1 -> 0.37641087 | K111: =K4/F4-1 -> 0.35371099 | L111: =L4/G4-1 -> 0.41484056 | M111: =M4/H4-1 -> 0.39378252 | N111: =N4/I4-1 -> 0.36523536 | O111: =O4/J4-1 -> 0.35514244 | ... BE111: =BE4/AZ4-1 -> 0.14891689 | BF111: =BF4/BE4-1 -> 0.11551218 | BG111: =BG4/BF4-1 -> 0.093725905 | BH111: =BH4/BG4-1 -> 0.076194667 | BI111: =BI4/BH4-1 -> 0.062087761 | BJ111: =BJ4/BI4-1 -> 0.051321477 | BL111: =15%-AU112 -> 0.022581508
B112: Revenue | H112: =H13/C13-1 -> 0.50251664 | I112: =I13/D13-1 -> 0.50618362 | J112: =J13/E13-1 -> 0.46845655 | K112: =K13/F13-1 -> 0.40817296 | L112: =L13/G13-1 -> 0.46713316 | M112: =M13/H13-1 -> 0.48881565 | N112: =N13/I13-1 -> 0.4116306 | O112: =O13/J13-1 -> 0.40142304 | ... BE112: =BE13/AZ13-1 -> 0.15621176 | BF112: =BF13/BE13-1 -> 0.1174318 | BG112: =BG13/BF13-1 -> 0.094929833 | BH112: =BH13/BG13-1 -> 0.076886303 | BI112: =BI13/BH13-1 -> 0.062398954 | BJ112: =BJ13/BI13-1 -> 0.051355101
B113: Creative Subscriptions | R113: =R14/M14-1 -> 0.25682116 | S113: =S14/N14-1 -> 0.23908583 | T113: =T14/O14-1 -> 0.22426976 | U113: =U14/P14-1 -> 0.19310547 | V113: =V14/Q14-1 -> 0.22678595 | W113: =W14/R14-1 -> 0.16636717 | X113: =X14/S14-1 -> 0.21117494 | Y113: =Y14/T14-1 -> 0.23206341 | ... BE113: =BE14/AZ14-1 -> 0.16175622 | BF113: =BF14/BE14-1 -> 0.12 | BG113: =BG14/BF14-1 -> 0.096 | BH113: =BH14/BG14-1 -> 0.0768 | BI113: =BI14/BH14-1 -> 0.06144 | BJ113: =BJ14/BI14-1 -> 0.05
B114: Business Solutions | R114: =R15/M15-1 -> 0.32206908 | S114: =S15/N15-1 -> 0.46307169 | T114: =T15/O15-1 -> 0.52371438 | U114: =U15/P15-1 -> 0.61513414 | V114: =V15/Q15-1 -> 0.48806698 | W114: =W15/R15-1 -> 0.72036116 | X114: =X15/S15-1 -> 0.6154469 | Y114: =Y15/T15-1 -> 0.59800187 | ... BE114: =BE15/AZ15-1 -> 0.14281222 | BF114: =BF15/BE15-1 -> 0.11112223 | BG114: =BG15/BF15-1 -> 0.092279636 | BH114: =BH15/BG15-1 -> 0.077100756 | BI114: =BI15/BH15-1 -> 0.064781164 | BJ114: =BJ15/BI15-1 -> 0.054710844 | BN114: 34
B115: Gross profit | H115: =+H24/C24-1 -> 0.51842432 | I115: =+I24/D24-1 -> 0.49918364 | J115: =+J24/E24-1 -> 0.44095856 | K115: =+K24/F24-1 -> 0.39862806 | L115: =+L24/G24-1 -> 0.45853912 | M115: =+M24/H24-1 -> 0.40402245 | N115: =+N24/I24-1 -> 0.33878253 | O115: =+O24/J24-1 -> 0.31983188 | ... AO115: =+AO24/AJ24-1 -> 0.2177854 | AP115: =AP24/AK24-1 -> 0.20931413 | AQ115: =+AQ24/AL24-1 -> 0.14911813 | AR115: =+AR24/AM24-1 -> 0.11952915 | AS115: =+AS24/AN24-1 -> 0.14039925 | AT115: =+AT24/AO24-1 -> 0.13810748 | AU115: =AU24/AP24-1 -> 0.13662178 | AV115: =+AV24/AQ24-1 -> 0.13639724 | AW115: =+AW24/AR24-1 -> 0.14295437 | AX115: =+AX24/AS24-1 -> 0.13964143 | AY115: =+AY24/AT24-1 -> 0.11777462 | AZ115: =AZ24/AU24-1 -> 0.13390253 | BA115: =+BA24/AV24-1 -> 0.11130848 | BB115: =+BB24/AW24-1 -> 0.11527954 | BC115: =+BC24/AX24-1 -> 0.14532627 | BD115: =+BD24/AY24-1 -> 0.17341491 | BE115: =BE24/AZ24-1 -> 0.13714552 | BF115: =BF24/BE24-1 -> 0.12506033 | BG115: =BG24/BF24-1 -> 0.10164256 | BH115: =BH24/BG24-1 -> 0.08287663 | BI115: =BI24/BH24-1 -> 0.067828557 | BJ115: =BJ24/BI24-1 -> 0.056485536 | BN115: 2000
B116: Sales & marketing | H116: =H26/C26-1 -> 0.32547756 | I116: =I26/D26-1 -> 0.32796503 | J116: =J26/E26-1 -> 0.27612269 | K116: =K26/F26-1 -> 0.22347496 | L116: =L26/G26-1 -> 0.28742483 | M116: =M26/H26-1 -> 0.24344964 | N116: =N26/I26-1 -> 0.22364432 | O116: =O26/J26-1 -> -0.051518163 | ... BE116: =BE26/AZ26-1 -> 0.50585847 | BF116: =BF26/BE26-1 -> -0.050182972 | BG116: =BG26/BF26-1 -> 0.012810096 | BH116: =BH26/BG26-1 -> -0.0038801694 | BI116: =BI26/BH26-1 -> -0.017280967 | BJ116: =BJ26/BI26-1 -> -0.027496532 | BN116: =+BN114/BN115 -> 0.017
B117: R&D | H117: =H27/C27-1 -> 0.30203084 | I117: =I27/D27-1 -> 0.3580908 | J117: =J27/E27-1 -> 0.43934765 | K117: =K27/F27-1 -> 0.41300914 | L117: =L27/G27-1 -> 0.38093449 | M117: =M27/H27-1 -> 0.45692496 | N117: =N27/I27-1 -> 0.3379736 | O117: =O27/J27-1 -> 0.61922153 | ... BE117: =BE27/AZ27-1 -> 0.088276985 | BF117: =BF27/BE27-1 -> 0.05 | BG117: =BG27/BF27-1 -> 0.05 | BH117: =BH27/BG27-1 -> 0.05 | BI117: =BI27/BH27-1 -> 0.05 | BJ117: =BJ27/BI27-1 -> 0.05
B118: G&A | H118: =H28/C28-1 -> 0.7211248 | I118: =I28/D28-1 -> 0.70394469 | J118: =J28/E28-1 -> 0.68650272 | K118: =K28/F28-1 -> 0.80848231 | L118: =L28/G28-1 -> 0.73073816 | M118: =M28/H28-1 -> 0.29651634 | N118: =N28/I28-1 -> 0.19272076 | O118: =O28/J28-1 -> 0.093610864 | ... BE118: =BE28/AZ28-1 -> 0.055859196 | BF118: 0.02 | BG118: 0.02 | BH118: 0.02 | BI118: 0.02 | BJ118: 0.02
B119: D&A | H119: =+H41/C41-1 -> 0.083333333 | I119: =+I41/D41-1 -> 0.083333333 | J119: =+J41/E41-1 -> 0.25 | K119: =+K41/F41-1 -> 0.77777778 | L119: =+L41/G41-1 -> 0.26666667 | M119: =+M41/H41-1 -> 0.45923077 | N119: =+N41/I41-1 -> 0.68923077 | O119: =+O41/J41-1 -> 0.47533333 | ... AO119: =+AO41/AJ41-1 -> -0.37915147 | AP119: =AP41/AK41-1 -> 0.083619288 | AQ119: =+AQ41/AL41-1 -> 0.30881755 | AR119: =+AR41/AM41-1 -> -0.085737505 | AS119: =+AS41/AN41-1 -> -0.085737505 | AT119: =+AT41/AO41-1 -> 0.94124923 | AU119: =AU41/AP41-1 -> 0.20666667 | AV119: =+AV41/AQ41-1 -> -0.047345545 | AW119: =+AW41/AR41-1 -> 0.35533333 | AX119: =+AX41/AS41-1 -> 0.37555556 | AY119: =+AY41/AT41-1 -> -0.033928003 | AZ119: =AZ41/AU41-1 -> 0.12757827 | BA119: =+BA41/AV41-1 -> -0.011732117 | BB119: =+BB41/AW41-1 -> -0.0055746844 | BC119: =+BC41/AX41-1 -> -0.020193861 | BD119: =+BD41/AY41-1 -> 0 | BE119: =BE41/AZ41-1 -> -0.0094320363 | BF119: =BF41/BE41-1 -> 0 | BG119: =BG41/BF41-1 -> 0 | BH119: =BH41/BG41-1 -> 0 | BI119: =BI41/BH41-1 -> 0 | BJ119: =BJ41/BI41-1 -> 0
B120: Adj. EBITDA | H120: =+H43/C43-1 -> 4.6306306 | I120: =+I43/D43-1 -> 0.6195469 | J120: =+J43/E43-1 -> 0.13506379 | K120: =+K43/F43-1 -> 0.33691335 | L120: =+L43/G43-1 -> 0.62252278 | M120: =+M43/H43-1 -> 0.53433333 | N120: =+N43/I43-1 -> 0.67040462 | O120: =+O43/J43-1 -> 0.98806202 | ... AO120: =+AO43/AJ43-1 -> 0.12313504 | AP120: =AP43/AK43-1 -> 3.5432185 | AQ120: =+AQ43/AL43-1 -> 0.20260107 | AR120: =+AR43/AM43-1 -> 0.42589645 | AS120: =+AS43/AN43-1 -> 0.73284137 | AT120: =+AT43/AO43-1 -> 0.87528943 | AU120: =AU43/AP43-1 -> 0.50547012 | AV120: =+AV43/AQ43-1 -> 0.26339002 | AW120: =+AW43/AR43-1 -> 0.16105226 | AX120: =+AX43/AS43-1 -> 0.046934096 | AY120: =+AY43/AT43-1 -> -0.17017096 | AZ120: =AZ43/AU43-1 -> 0.078219122 | BA120: =+BA43/AV43-1 -> -0.43366715 | BB120: =+BB43/AW43-1 -> -0.38612886 | BC120: =+BC43/AX43-1 -> -0.050481095 | BD120: =+BD43/AY43-1 -> 0.24311115 | BE120: =BE43/AZ43-1 -> -0.20473283 | BF120: =BF43/BE43-1 -> 0.55454304 | BG120: =BG43/BF43-1 -> 0.25113531 | BH120: =BH43/BG43-1 -> 0.19006782 | BI120: =BI43/BH43-1 -> 0.14811312 | BJ120: =BJ43/BI43-1 -> 0.11886079
B121: Non-GAAP Net income | H121: =H69/C69-1 -> -0.34979558 | I121: =I69/D69-1 -> -0.95017506 | J121: =J69/E69-1 -> -1.2249841 | K121: =K69/F69-1 -> 1.4467366 | L121: =L69/G69-1 -> -0.962281 | M121: =M69/H69-1 -> 1.4915744 | N121: =N69/I69-1 -> 29.497297 | O121: =O69/J69-1 -> -17.770538 | ... BE121: =BE69/AZ69-1 -> -3.0999934 | BF121: =BF69/BE69-1 -> 1.3198841 | BG121: =BG69/BF69-1 -> 0.53249449 | BH121: =BH69/BG69-1 -> 0.36718782 | BI121: =BI69/BH69-1 -> 0.256893 | BJ121: =BJ69/BI69-1 -> 0.19493996
B122: FCF y/y | M122: =+M80/H80-1 -> 0.44922536 | N122: =+N80/I80-1 -> 0.37014703 | O122: =+O80/J80-1 -> 0.25117507 | P122: =+P80/K80-1 -> 0.67301782 | Q122: =+Q80/L80-1 -> 0.43850139 | R122: =+R80/M80-1 -> 0.40264227 | S122: =+S80/N80-1 -> 0.28909754 | T122: =+T80/O80-1 -> 0.23367524 | ... AO122: =+AO80/AJ80-1 -> 1.0834521 | AP122: =AP80/AK80-1 -> -6.4396907 | AQ122: =+AQ80/AL80-1 -> 3.2235407 | AR122: =+AR80/AM80-1 -> 2.5249297 | AS122: =+AS80/AN80-1 -> 1.8538465 | AT122: =+AT80/AO80-1 -> 0.63917154 | AU122: =AU80/AP80-1 -> 1.6133965 | AV122: =+AV80/AQ80-1 -> 0.34745675 | AW122: =+AW80/AR80-1 -> 0.30870401 | AX122: =+AX80/AS80-1 -> -0.0037491879 | AY122: =+AY80/AT80-1 -> 0.18058328 | AZ122: =AZ80/AU80-1 -> -0.80880996 | BA122: =+BA80/AV80-1 -> -0.30015437 | BB122: =+BB80/AW80-1 -> -0.22581927 | BC122: =+BC80/AX80-1 -> 0.066121271 | BD122: =+BD80/AY80-1 -> 0.002878271 | BE122: =BE80/AZ80-1 -> 4.5551928 | BF122: =BF80/BE80-1 -> 0.26739962 | BG122: =BG80/BF80-1 -> 0.1675713 | BH122: =BH80/BG80-1 -> 0.15985106 | BI122: =BI80/BH80-1 -> 0.13545381 | BJ122: =BJ80/BI80-1 -> 0.11632601
B124: Q/Q Growth
B125: Total Revenue q/q | D125: =D13/C13-1 -> 0.11592791 | E125: =E13/D13-1 -> 0.10010185 | F125: =F13/E13-1 -> 0.1133448 | H125: =H13/F13-1 -> 0.099311 | I125: =I13/H13-1 -> 0.11865139 | J125: =J13/I13-1 -> 0.072546368 | K125: =K13/J13-1 -> 0.067639377 | M125: =M13/K13-1 -> 0.1622659 | N125: =N13/M13-1 -> 0.060656868 | O125: =O13/N13-1 -> 0.064790737 | P125: =P13/O13-1 -> 0.055250643 | R125: =R13/P13-1 -> 0.061468845 | S125: =S13/R13-1 -> 0.063853348 | T125: =T13/S13-1 -> 0.061331363 | U125: =U13/T13-1 -> 0.039620714 | W125: =W13/U13-1 -> 0.055716855 | X125: =X13/W13-1 -> 0.092931519 | Y125: =Y13/X13-1 -> 0.076764707 | Z125: =Z13/Y13-1 -> 0.11155087 | AB125: =AB13/Z13-1 -> 0.076373109 | AC125: =AC13/AB13-1 -> 0.040425896 | AD125: =AD13/AC13-1 -> 0.013877739 | AE125: =AE13/AD13-1 -> 0.023519547 | AG125: =AG13/AF13-1 -> -0.73095332 | AH125: =AH13/AG13-1 -> 0.010617775 | AI125: =AI13/AH13-1 -> 0.0016829653 | AJ125: =AJ13/AI13-1 -> 0.026705802 | AL125: =AL13/AJ13-1 -> 0.053616494 | AM125: =AM13/AL13-1 -> 0.042507405 | AN125: =AN13/AM13-1 -> 0.0099082766 | AO125: =AO13/AN13-1 -> 0.025213221 | AQ125: =AQ13/AO13-1 -> 0.039638805 | AR125: =AR13/AQ13-1 -> 0.0380441 | AS125: =AS13/AR13-1 -> 0.020486706 | AT125: =AT13/AS13-1 -> 0.035491249 | AV125: =AV13/AT13-1 -> 0.028658609 | AW125: =AW13/AV13-1 -> 0.034369187 | AX125: =AX13/AW13-1 -> 0.031155471 | AY125: =AY13/AX13-1 -> 0.037757772 | BA125: =BA13/AY13-1 -> 0.033481523 | BB125: =BB13/BA13-1 -> 0.039716005 | BC125: =BC13/BB13-1 -> 0.041145757 | BD125: =BD13/BC13-1 -> 0.044629899
B126: =+CONCATENATE(B115," q/q") -> Gross profit q/q | D126: =+D24/C24-1 -> 0.12963035 | E126: =+E24/D24-1 -> 0.11808885 | F126: =+F24/E24-1 -> 0.10472516 | H126: =+H24/F24-1 -> 0.088243888 | I126: =+I24/H24-1 -> 0.11531626 | J126: =+J24/I24-1 -> 0.07466468 | K126: =+K24/J24-1 -> 0.072272063 | M126: =+M24/K24-1 -> 0.092441155 | N126: =+N24/M24-1 -> 0.063491485 | O126: =+O24/N24-1 -> 0.059452655 | P126: =+P24/O24-1 -> 0.057652051 | R126: =+R24/P24-1 -> 0.038423329 | S126: =+S24/R24-1 -> 0.031695686 | T126: =+T24/S24-1 -> 0.034438239 | U126: =+U24/T24-1 -> 0.026989195 | W126: =+W24/U24-1 -> 0.04440192 | X126: =+X24/W24-1 -> 0.076490858 | Y126: =+Y24/X24-1 -> 0.055832925 | Z126: =+Z24/Y24-1 -> 0.031697729 | AB126: =+AB24/Z24-1 -> 0.051436686 | AC126: =+AC24/AB24-1 -> 0.03657818 | AD126: =+AD24/AC24-1 -> 0.017751866 | AE126: =+AE24/AD24-1 -> 0.0064895589 | AG126: =+AG24/AF24-1 -> -0.73394808 | AH126: =+AH24/AG24-1 -> 0.018020866 | AI126: =+AI24/AH24-1 -> 0.034231019 | AJ126: =+AJ24/AI24-1 -> 0.037857703 | AL126: =+AL24/AJ24-1 -> 0.077535281 | AM126: =+AM24/AL24-1 -> 0.067668028 | AN126: =+AN24/AM24-1 -> 0.01010465 | AO126: =+AO24/AN24-1 -> 0.047940573 | AQ126: =+AQ24/AO24-1 -> 0.016776298 | AR126: =+AR24/AQ24-1 -> 0.040176329 | AS126: =+AS24/AR24-1 -> 0.028934875 | AT126: =+AT24/AS24-1 -> 0.04583461 | AV126: =+AV24/AT24-1 -> 0.015248386 | AW126: =+AW24/AV24-1 -> 0.046178256 | AX126: =+AX24/AW24-1 -> 0.025952425 | AY126: =+AY24/AX24-1 -> 0.025767713 | BA126: =+BA24/AY24-1 -> 0.0093753396 | BB126: =+BB24/BA24-1 -> 0.049916585 | BC126: =+BC24/BB24-1 -> 0.053592602 | BD126: =+BD24/BC24-1 -> 0.050924225
B127: =+CONCATENATE(B99," q/q") -> Sales & marketing, non GAAP q/q | D127: =D26/C26-1 -> -0.11788731 | E127: =E26/D26-1 -> 0.11109513 | F127: =F26/E26-1 -> 0.00093179759 | H127: =H26/F26-1 -> 0.35111582 | I127: =I26/H26-1 -> -0.11623189 | J127: =J26/I26-1 -> 0.067719161 | K127: =K26/J26-1 -> -0.040362655 | M127: =M26/K26-1 -> 0.37317439 | N127: =N26/M26-1 -> -0.1303083 | O127: =O26/N26-1 -> -0.17238023 | P127: =P26/O26-1 -> 0.24641276 | R127: =R26/P26-1 -> 0.38918437 | S127: =S26/R26-1 -> -0.17471903 | T127: =T26/S26-1 -> 0.066578873 | U127: =U26/T26-1 -> -0.015111124 | W127: =W26/U26-1 -> 0.3047653 | X127: =X26/W26-1 -> 0.2440276 | Y127: =Y26/X26-1 -> -0.061033193 | Z127: =Z26/Y26-1 -> -0.038594556 | AB127: =AB26/Z26-1 -> 0.33209859 | AC127: =AC26/AB26-1 -> -0.28086386 | AD127: =AD26/AC26-1 -> 0.12935015 | AE127: =AE26/AD26-1 -> -0.13249937 | AG127: =AG26/AF26-1 -> -0.67062966 | AH127: =AH26/AG26-1 -> -0.24712553 | AI127: =AI26/AH26-1 -> -0.023403675 | AJ127: =AJ26/AI26-1 -> -0.18444215 | AL127: =AL26/AJ26-1 -> 0.01360148 | AM127: =AM26/AL26-1 -> -0.035952904 | AN127: =AN26/AM26-1 -> 0.041442663 | AO127: =AO26/AN26-1 -> 0.027819549 | AQ127: =AQ26/AO26-1 -> 0.047462031 | AR127: =AR26/AQ26-1 -> -0.035857238 | AS127: =AS26/AR26-1 -> 0.068824598 | AT127: =AT26/AS26-1 -> -0.030588092 | AV127: =AV26/AT26-1 -> 0.059934473 | AW127: =AW26/AV26-1 -> 0.019068339 | AX127: =AX26/AW26-1 -> 0.22903042 | AY127: =AY26/AX26-1 -> 0.11698683 | BA127: =BA26/AY26-1 -> 0.27773868 | BB127: =BB26/BA26-1 -> 0.010667357 | BC127: =BC26/BB26-1 -> -0.034279829 | BD127: =BD26/BC26-1 -> -0.02886677
...

Sheet Core Growth
K2: babd
D5: 2019 | E5: 2020 | F5: 2021 | G5: 2022 | H5: 2023E | I5: 2024E | J5: 2025E | K5: 2026E | L5: 2027E | M5: 2028E | N5: 2029E | O5: 2030E | P5: 2031E | R5: 1Q19 | S5: 2Q19 | T5: 3Q19 | U5: 4Q19 | W5: 1Q20 | X5: 2Q20 | Y5: 3Q20 | Z5: 4Q20 | AB5: 1Q21 | AC5: 2Q21 | AD5: 3Q21 | AE5: 4Q21 | AG5: 1Q22 | AH5: 2Q22 | AI5: 3Q22 | AJ5: 4Q22 | AL5: 1Q23 | AM5: 2Q23 | AN5: 3Q23 | AO5: 4Q23 | AQ5: 1Q24 | AR5: 2Q24 | AS5: 3Q24 | AT5: 4Q24 | AV5: 1Q25 | AW5: 2Q25 | AX5: 3Q25 | AY5: 4Q25 | BA5: 1Q26E | BB5: 2Q26E | BC5: 3Q26E | BD5: 4Q26E
C6: Partner Revenue | D6: 93 | E6: 154 | F6: 270 | G6: =+SUM(AG6:AJ6) -> 348.18 | H6: =+SUM(AL6:AO6) -> 468.6 | I6: =+SUM(AQ6:AT6) -> 610 | J6: =+SUM(AV6:AY6) -> 750.651 | K6: =+SUM(BA6:BD6) -> 900.7812 | L6: =+K6*(1+L8) -> 1044.9062 | M6: =+L6*(1+M8) -> 1178.6542 | N6: =+M6*(1+N8) -> 1299.3484 | O6: =+N6*(1+O8) -> 1405.791 | P6: =+O6*(1+P8) -> 1497.9209 | Q6: =+(J6/G6)^(1/3)-1 -> 0.291848 | R6: =+D6-SUM(S6:U6) -> 21 | S6: =+T6-2.5 -> 21.5 | T6: =+U6-2.5 -> 24 | U6: =+W6-2.5 -> 26.5 | W6: 29 | X6: 32.725 | Y6: 38.145 | Z6: =E6-SUM(W6:Y6) -> 54.13 | AB6: 58 | AC6: =+AH6/1.31 -> 64.80916 | AD6: 71 | AE6: =F6-SUM(AB6:AD6) -> 76.19084 | AF6: =SUM(AB6:AE6) -> 270 | AG6: 82 | AH6: 84.9 | AI6: 86.696 | AJ6: 94.584 | AK6: =SUM(AG6:AJ6) -> 348.18 | AL6: 103.9 | AM6: 115.2 | AN6: 119.4 | AO6: 130.1 | AQ6: 138.4 | AR6: 148.4 | AS6: 155 | AT6: =610-SUM(AQ6:AS6) -> 168.2 | AV6: 172 | AW6: 183.316 | AX6: 192.117 | AY6: 203.218 | BA6: =AV6*(1+BA8) -> 206.4 | BB6: =AW6*(1+BB8) -> 219.9792 | BC6: =AX6*(1+BC8) -> 230.5404 | BD6: =AY6*(1+BD8) -> 243.8616
C7: QoQ Growth | W7: =+W6/U6-1 -> 0.094339623 | X7: =+X6/W6-1 -> 0.12844828 | Y7: =+Y6/X6-1 -> 0.16562261 | Z7: =+Z6/Y6-1 -> 0.41905885 | AB7: =+AB6/Z6-1 -> 0.07149455 | AC7: =+AC6/AB6-1 -> 0.11739932 | AD7: =+AD6/AC6-1 -> 0.095524146 | AE7: =+AE6/AD6-1 -> 0.073110418 | AG7: =+AG6/AE6-1 -> 0.076244865 | AH7: =+AH6/AG6-1 -> 0.035365854 | AI7: =+AI6/AH6-1 -> 0.021154299 | AJ7: =+AJ6/AI6-1 -> 0.09098459 | AL7: =+AL6/AJ6-1 -> 0.09849446 | AM7: =+AM6/AL6-1 -> 0.10875842 | AN7: =+AN6/AM6-1 -> 0.036458333 | AO7: =+AO6/AN6-1 -> 0.08961474 | AQ7: =+AQ6/AO6-1 -> 0.063797079 | AR7: =+AR6/AQ6-1 -> 0.072254335 | AS7: =+AS6/AR6-1 -> 0.044474394 | AT7: =+AT6/AS6-1 -> 0.08516129 | AV7: =+AV6/AT6-1 -> 0.022592152 | AW7: =+AW6/AV6-1 -> 0.065790698 | AX7: =+AX6/AW6-1 -> 0.048009994 | AY7: =+AY6/AX6-1 -> 0.057782497 | BA7: =+BA6/AY6-1 -> 0.015658062 | BB7: =+BB6/BA6-1 -> 0.065790698 | BC7: =+BC6/BB6-1 -> 0.048009994 | BD7: =+BD6/BC6-1 -> 0.057782497
C8: YoY Growth | E8: =+E6/D6-1 -> 0.65591398 | F8: =+F6/E6-1 -> 0.75324675 | G8: =+G6/F6-1 -> 0.28955556 | H8: =+H6/G6-1 -> 0.34585559 | I8: =+I6/H6-1 -> 0.30174989 | J8: =+J6/I6-1 -> 0.23057541 | K8: =+K6/J6-1 -> 0.2 | L8: =+K8*0.8 -> 0.16 | M8: =+L8*0.8 -> 0.128 | N8: =+M8*0.8 -> 0.1024 | O8: =+N8*0.8 -> 0.08192 | P8: =+O8*0.8 -> 0.065536 | AB8: =+AB6/W6-1 -> 1 | AC8: =+AC6/X6-1 -> 0.98041743 | AD8: =+AD6/Y6-1 -> 0.86131865 | AE8: =+AE6/Z6-1 -> 0.40755292 | AG8: =+AG6/AB6-1 -> 0.4137931 | AH8: =+AH6/AC6-1 -> 0.31 | AI8: =+AI6/AD6-1 -> 0.22107042 | AJ8: =+AJ6/AE6-1 -> 0.24140908 | AL8: =+AL6/AG6-1 -> 0.26707317 | AM8: =+AM6/AH6-1 -> 0.35689046 | AN8: =+AN6/AI6-1 -> 0.37722617 | AO8: =+AO6/AJ6-1 -> 0.37549691 | AQ8: =+AQ6/AL6-1 -> 0.33205005 | AR8: =+AR6/AM6-1 -> 0.28819444 | AS8: =+AS6/AN6-1 -> 0.29815745 | AT8: =+AT6/AO6-1 -> 0.29285165 | AV8: =+AV6/AQ6-1 -> 0.24277457 | AW8: =+AW6/AR6-1 -> 0.23528302 | AX8: =+AX6/AS6-1 -> 0.23946452 | AY8: =+AY6/AT6-1 -> 0.20819263 | BA8: 0.2 | BB8: 0.2 | BC8: 0.2 | BD8: 0.2
C9: Partner Revenue - Creative | D9: =+D6*D10 -> 86.49 | E9: =+E6*E10 -> 103.18 | F9: =+F6*F10 -> 139.725 | G9: =+SUM(AG9:AJ9) -> 183.299 | H9: =+SUM(AL9:AO9) -> 246.015 | I9: =+SUM(AQ9:AT9) -> 320.25 | J9: =+SUM(AV9:AY9) -> 382.83201 | K9: =+SUM(BA9:BD9) -> 450.3906 | L9: =+L6*L10 -> 512.00403 | M9: =+M6*M10 -> 565.75401 | N9: =+N6*N10 -> 610.69374 | O9: =+O6*O10 -> 646.66386 | P9: =+P6*P10 -> 674.06441 | R9: =+R6*R10 -> 19.53 | S9: =+S6*S10 -> 19.995 | T9: =+T6*T10 -> 22.32 | U9: =+U6*U10 -> 24.645 | W9: =+W6*W10 -> 23.2 | X9: =+X6*X10 -> 22.9075 | Y9: =+Y6*Y10 -> 24.79425 | Z9: =+E9-SUM(W9:Y9) -> 32.27825 | AB9: =+AB6*AB10 -> 34.8 | AC9: =+AC6*AC10 -> 35.645038 | AD9: =+AD6*AD10 -> 35.5 | AE9: =+F9-SUM(AB9:AD9) -> 33.779962 | AG9: =+AG6*AG10 -> 36.9 | AH9: =+AH6*AH10 -> 46.695 | AI9: =+AI6*AI10 -> 47.6828 | AJ9: =+AJ6*AJ10 -> 52.0212 | AL9: =+AL6*AL10 -> 54.5475 | AM9: =+AM6*AM10 -> 60.48 | AN9: =+AN6*AN10 -> 62.685 | AO9: =+AO6*AO10 -> 68.3025 | AQ9: =+AQ6*AQ10 -> 72.66 | AR9: =+AR6*AR10 -> 77.91 | AS9: =+AS6*AS10 -> 81.375 | AT9: =+AT6*AT10 -> 88.305 | AV9: =+AV6*AV10 -> 87.72 | AW9: =+AW6*AW10 -> 93.49116 | AX9: =+AX6*AX10 -> 97.97967 | AY9: =+AY6*AY10 -> 103.64118 | BA9: =+BA6*BA10 -> 103.2 | BB9: =+BB6*BB10 -> 109.9896 | BC9: =+BC6*BC10 -> 115.2702 | BD9: =+BD6*BD10 -> 121.9308
C10: % CS | D10: 0.93 | E10: 0.67 | F10: 0.5175 | G10: =+G9/G6 -> 0.52644896 | H10: =+H9/H6 -> 0.525 | I10: =+I9/I6 -> 0.525 | J10: =+J9/J6 -> 0.51 | K10: =+K9/K6 -> 0.5 | L10: =+K10-1% -> 0.49 | M10: =+L10-1% -> 0.48 | N10: =+M10-1% -> 0.47 | O10: =+N10-1% -> 0.46 | P10: =+O10-1% -> 0.45 | R10: =+D10 -> 0.93 | S10: =+R10 -> 0.93 | T10: =+S10 -> 0.93 | U10: =+T10 -> 0.93 | W10: 0.8 | X10: 0.7 | Y10: 0.65 | Z10: =+Z9/Z6 -> 0.59630981 | AB10: 0.6 | AC10: 0.55 | AD10: 0.5 | AE10: =+AE9/AE6 -> 0.44335988 | AG10: 0.45 | AH10: 0.55 | AI10: 0.55 | AJ10: 0.55 | AL10: 0.525 | AM10: 0.525 | AN10: 0.525 | AO10: 0.525 | AQ10: 0.525 | AR10: 0.525 | AS10: 0.525 | AT10: 0.525 | AV10: 0.51 | AW10: 0.51 | AX10: 0.51 | AY10: 0.51 | BA10: 0.5 | BB10: 0.5 | BC10: 0.5 | BD10: 0.5
C11: YoY Growth | E11: =+E9/D9-1 -> 0.19297029 | F11: =+F9/E9-1 -> 0.35418686 | G11: =+G9/F9-1 -> 0.31185543 | H11: =+H9/G9-1 -> 0.34215135 | I11: =+I9/H9-1 -> 0.30174989 | J11: =+J9/I9-1 -> 0.19541611 | K11: =+K9/J9-1 -> 0.17647059 | L11: =+L9/K9-1 -> 0.1368 | ... P11: =+P9/O9-1 -> 0.042372174
C12: Partner Revenue - Business | D12: =+D6-D9 -> 6.51 | E12: =+E6-E9 -> 50.82 | F12: =+F6-F9 -> 130.275 | G12: =+SUM(AG12:AJ12) -> 164.881 | H12: =+SUM(AL12:AO12) -> 222.585 | I12: =+SUM(AQ12:AT12) -> 289.75 | J12: =+SUM(AV12:AY12) -> 367.81899 | K12: =+SUM(BA12:BD12) -> 450.3906 | L12: =+L6-L9 -> 532.90216 | M12: =+M6-M9 -> 612.90018 | N12: =+N6-N9 -> 688.65464 | O12: =+O6-O9 -> 759.12714 | P12: =+P6-P9 -> 823.8565 | R12: =+R6-R9 -> 1.47 | S12: =+S6-S9 -> 1.505 | T12: =+T6-T9 -> 1.68 | U12: =+U6-U9 -> 1.855 | W12: =+W6-W9 -> 5.8 | X12: =+X6-X9 -> 9.8175 | Y12: =+Y6-Y9 -> 13.35075 | Z12: =+Z6-Z9 -> 21.85175 | AB12: =+AB6-AB9 -> 23.2 | AC12: =+AC6-AC9 -> 29.164122 | AD12: =+AD6-AD9 -> 35.5 | AE12: =+AE6-AE9 -> 42.410878 | AG12: =+AG6-AG9 -> 45.1 | AH12: =+AH6-AH9 -> 38.205 | AI12: =+AI6-AI9 -> 39.0132 | AJ12: =+AJ6-AJ9 -> 42.5628 | AL12: =+AL6-AL9 -> 49.3525 | AM12: =+AM6-AM9 -> 54.72 | AN12: =+AN6-AN9 -> 56.715 | AO12: =+AO6-AO9 -> 61.7975 | AQ12: =+AQ6-AQ9 -> 65.74 | AR12: =+AR6-AR9 -> 70.49 | AS12: =+AS6-AS9 -> 73.625 | AT12: =+AT6-AT9 -> 79.895 | AV12: =+AV6-AV9 -> 84.28 | AW12: =+AW6-AW9 -> 89.82484 | AX12: =+AX6-AX9 -> 94.13733 | AY12: =+AY6-AY9 -> 99.57682 | BA12: =+BA6-BA9 -> 103.2 | BB12: =+BB6-BB9 -> 109.9896 | BC12: =+BC6-BC9 -> 115.2702 | BD12: =+BD6-BD9 -> 121.9308
C13: % BS | D13: =+D12/D6 -> 0.07 | E13: =+E12/E6 -> 0.33 | F13: =+F12/F6 -> 0.4825 | G13: =+G12/G6 -> 0.47355104 | H13: =+H12/H6 -> 0.475 | I13: =+I12/I6 -> 0.475 | J13: =+J12/J6 -> 0.49 | K13: =+K12/K6 -> 0.5 | ... P13: =+P12/P6 -> 0.55 | R13: =+R12/R6 -> 0.07 | S13: =+S12/S6 -> 0.07 | T13: =+T12/T6 -> 0.07 | U13: =+U12/U6 -> 0.07 | W13: =+W12/W6 -> 0.2 | X13: =+X12/X6 -> 0.3 | Y13: =+Y12/Y6 -> 0.35 | Z13: =+Z12/Z6 -> 0.40369019 | AB13: =+AB12/AB6 -> 0.4 | AC13: =+AC12/AC6 -> 0.45 | AD13: =+AD12/AD6 -> 0.5 | AE13: =+AE12/AE6 -> 0.55664012 | AG13: =+AG12/AG6 -> 0.55 | AH13: =+AH12/AH6 -> 0.45 | AI13: =+AI12/AI6 -> 0.45 | AJ13: =+AJ12/AJ6 -> 0.45 | AL13: =+AL12/AL6 -> 0.475 | AM13: =+AM12/AM6 -> 0.475 | AN13: =+AN12/AN6 -> 0.475 | AO13: =+AO12/AO6 -> 0.475 | AQ13: =+AQ12/AQ6 -> 0.475 | AR13: =+AR12/AR6 -> 0.475 | AS13: =+AS12/AS6 -> 0.475 | AT13: =+AT12/AT6 -> 0.475 | AV13: =+AV12/AV6 -> 0.49 | AW13: =+AW12/AW6 -> 0.49 | AX13: =+AX12/AX6 -> 0.49 | AY13: =+AY12/AY6 -> 0.49 | BA13: =+BA12/BA6 -> 0.5 | BB13: =+BB12/BB6 -> 0.5 | BC13: =+BC12/BC6 -> 0.5 | BD13: =+BD12/BD6 -> 0.5 | CK13: ='Income Statement'!BM15 -> 0
C14: YoY Growth | E14: =+E12/D12-1 -> 6.8064516 | F14: =+F12/E12-1 -> 1.5634593 | G14: =+G12/F12-1 -> 0.26563807 | H14: =+H12/G12-1 -> 0.34997362 | I14: =+I12/H12-1 -> 0.30174989 | J14: =+J12/I12-1 -> 0.26943569 | K14: =+K12/J12-1 -> 0.2244898 | L14: =+L12/K12-1 -> 0.1832 | ... P14: =+P12/O12-1 -> 0.085268148
C16: Transaction Revenue | D16: 11 | E16: 56 | F16: 130 | G16: =+SUM(AG16:AJ16) -> 149.71 | H16: =+SUM(AL16:AO16) -> 177.5 | I16: =+SUM(AQ16:AT16) -> 214.5 | J16: =+SUM(AV16:AY16) -> 254.988 | K16: =+SUM(BA16:BD16) -> 289.04345 | L16: =+'Income Statement'!BF173 -> 314.97871 | M16: =+'Income Statement'!BG173 -> 337.19271 | N16: =+'Income Statement'!BH173 -> 356.10418 | O16: =+'Income Statement'!BI173 -> 372.20596 | P16: =+'Income Statement'!BJ173 -> 385.98773 | R16: =+D16-SUM(S16:U16) -> 2.255 | S16: =+T16-0.5 -> 2.415 | T16: =+U16-0.5 -> 2.915 | U16: =+W16-2.5 -> 3.415 | W16: 5.915 | X16: 10.669 | Y16: 12.432 | Z16: 26.767 | AB16: 29.455 | AC16: 32.438 | AD16: 32.29 | AE16: 36.132 | AG16: 38 | AH16: 36.8 | AI16: 36.04 | AJ16: 38.87 | AL16: 42.3 | AM16: 44.5 | AN16: 44.1 | AO16: 46.6 | AQ16: 49.5 | AR16: 53.9 | AS16: 54 | AT16: 57.1 | AV16: 58.887 | AW16: 63.551 | AX16: 65.268 | AY16: 67.282 | BA16: =+'Income Statement'!BA173 -> 68.102873 | BB16: =+'Income Statement'!BB173 -> 72.207924 | BC16: =+'Income Statement'!BC173 -> 74.31545 | BD16: =+'Income Statement'!BD173 -> 74.4172
C17: QoQ | AB17: =+AB16/Z16-1 -> 0.10042216 | AC17: =+AC16/AB16-1 -> 0.10127313 | AD17: =+AD16/AC16-1 -> -0.0045625501 | AE17: =+AE16/AD16-1 -> 0.11898421 | AG17: =+AG16/AE16-1 -> 0.051699325 | AH17: =+AH16/AG16-1 -> -0.031578947 | AI17: =+AI16/AH16-1 -> -0.020652174 | AJ17: =+AJ16/AI16-1 -> 0.078523862 | AL17: =+AL16/AJ16-1 -> 0.088242861 | AM17: =+AM16/AL16-1 -> 0.052009456 | AN17: =+AN16/AM16-1 -> -0.008988764 | AO17: =+AO16/AN16-1 -> 0.056689342 | AQ17: =+AQ16/AO16-1 -> 0.06223176 | AR17: =+AR16/AQ16-1 -> 0.088888889 | AS17: =+AS16/AR16-1 -> 0.0018552876 | AT17: =+AT16/AS16-1 -> 0.057407407 | AV17: =+AV16/AT16-1 -> 0.031295972 | AW17: =+AW16/AV16-1 -> 0.07920254 | AX17: =+AX16/AW16-1 -> 0.027017671 | AY17: =+AY16/AX16-1 -> 0.030857388 | BA17: =+BA16/AY16-1 -> 0.012200484 | BB17: =+BB16/BA16-1 -> 0.060277213 | BC17: =+BC16/BB16-1 -> 0.029186903 | BD17: =+BD16/BC16-1 -> 0.0013691635
C18: YoY | E18: =+E16/D16-1 -> 4.0909091 | F18: =+F16/E16-1 -> 1.3214286 | G18: =+G16/F16-1 -> 0.15161538 | H18: =+H16/G16-1 -> 0.18562554 | I18: =+I16/H16-1 -> 0.2084507 | J18: =+J16/I16-1 -> 0.18875524 | K18: =+K16/J16-1 -> 0.13355706 | L18: =+L16/K16-1 -> 0.08972789 | ... P18: =+P16/O16-1 -> 0.037027264 | AB18: =+AB16/W16-1 -> 3.9797126 | AC18: =+AC16/X16-1 -> 2.0403974 | AD18: =+AD16/Y16-1 -> 1.5973295 | AE18: =+AE16/Z16-1 -> 0.34987111 | AG18: =+AG16/AB16-1 -> 0.29010355 | AH18: =+AH16/AC16-1 -> 0.13447192 | AI18: =+AI16/AD16-1 -> 0.11613503 | AJ18: =+AJ16/AE16-1 -> 0.075777704 | AL18: =+AL16/AG16-1 -> 0.11315789 | AM18: =+AM16/AH16-1 -> 0.20923913 | AN18: =+AN16/AI16-1 -> 0.2236404 | AO18: =+AO16/AJ16-1 -> 0.19886802 | AQ18: =+AQ16/AL16-1 -> 0.17021277 | AR18: =+AR16/AM16-1 -> 0.21123596 | AS18: =+AS16/AN16-1 -> 0.2244898 | AT18: =+AT16/AO16-1 -> 0.22532189 | AV18: =+AV16/AQ16-1 -> 0.18963636 | AW18: =+AW16/AR16-1 -> 0.1790538 | AX18: =+AX16/AS16-1 -> 0.20866667 | AY18: =+AY16/AT16-1 -> 0.17831874 | BA18: =+BA16/AV16-1 -> 0.15650098 | BB18: =+BB16/AW16-1 -> 0.13622011 | BC18: =+BC16/AX16-1 -> 0.13862 | BD18: =+BD16/AY16-1 -> 0.10604917
C20: Self Creator Revenue | D20: 664 | E20: =+E24-E6 -> 830.907 | F20: =+F24-F6 -> 999.657 | G20: =+SUM(AG20:AJ20) -> 1039.486 | H20: =+SUM(AL20:AO20) -> 1093.065 | I20: =+SUM(AQ20:AT20) -> 1150.65 | J20: =+SUM(AV20:AY20) -> 1242.393 | K20: =+SUM(BA20:BD20) -> 1403.5997 | L20: =+L24-L12-L9 -> 1530.0823 | M20: =+M24-M12-M9 -> 1640.7775 | N20: =+N24-N12-N9 -> 1736.859 | O20: =+O24-O12-O9 -> 1819.8726 | P20: =+P24-P12-P9 -> 1893.397 | R20: =+R24-R12-R9 -> 153.29 | S20: =+S24-S12-S9 -> 163.919 | T20: =+T24-T12-T9 -> 172.791 | U20: =+U24-U12-U9 -> 174 | W20: =+W24-W12-W9 -> 186.987 | X20: =+X24-X12-X9 -> 203.334 | Y20: =+Y24-Y12-Y9 -> 216.035 | Z20: =+Z24-Z12-Z9 -> 224.551 | AB20: =+AB24-AB12-AB9 -> 246.112 | AC20: =+AC24-AC12-AC9 -> 251.59684 | AD20: =+AD24-AD12-AD9 -> 249.797 | AE20: =+AE24-AE12-AE9 -> 252.15116 | AF20: =SUM(AB20:AE20) -> 999.657 | AG20: =+AG24-AG6 -> 259.597 | AH20: =+AH24-AH6 -> 260.324 | AI20: =+AI24-AI6 -> 259.109 | AJ20: =+AJ24-AJ6 -> 260.456 | AK20: =SUM(AG20:AJ20) -> 1039.486 | AL20: =+AL24-AL6 -> 270.176 | AM20: =+AM24-AM6 -> 274.777 | AN20: =+AN24-AN6 -> 274.441 | AO20: =+AO24-AO6 -> 273.671 | AP20: =SUM(AL20:AO20) -> 1093.065 | AQ20: =+AQ24-AQ6 -> 281.376 | AR20: =+AR24-AR6 -> 287.346 | AS20: =+AS24-AS6 -> 289.673 | AT20: =+AT24-AT6 -> 292.255 | AV20: =+AV24-AV6 -> 301.651 | AW20: =+AW24-AW6 -> 306.614 | AX20: =+AX24-AX6 -> 313.077 | AY20: =+AY24-AY6 -> 321.051 | BA20: =+BA24-BA6 -> 335.42232 | BB20: =+BB24-BB6 -> 343.36214 | BC20: =+BC24-BC6 -> 355.98005 | BD20: =+BD24-BD6 -> 368.8352 | BF20: =SUM(AQ20:AT20) -> 1150.65
C21: QoQ Growth | S21: =+S20/R20-1 -> 0.069339161 | T21: =+T20/S20-1 -> 0.054124293 | U21: =+U20/T20-1 -> 0.0069968922 | W21: =+W20/U20-1 -> 0.074637931 | X21: =+X20/W20-1 -> 0.08742319 | Y21: =+Y20/X20-1 -> 0.06246373 | Z21: =+Z20/Y20-1 -> 0.039419539 | AB21: =+AB20/Z20-1 -> 0.096018276 | AC21: =+AC20/AB20-1 -> 0.02228595 | AD21: =+AD20/AC20-1 -> -0.0071536657 | AE21: =+AE20/AD20-1 -> 0.0094242937 | AG21: =+AG20/AE20-1 -> 0.02952927 | AH21: =+AH20/AG20-1 -> 0.0028004946 | AI21: =+AI20/AH20-1 -> -0.0046672608 | AJ21: =+AJ20/AI20-1 -> 0.0051985844 | AL21: =+AL20/AJ20-1 -> 0.037319163 | AM21: =+AM20/AL20-1 -> 0.01702964 | AN21: =+AN20/AM20-1 -> -0.0012228098 | AO21: =+AO20/AN20-1 -> -0.0028057032 | AQ21: =+AQ20/AO20-1 -> 0.028154244 | AR21: =+AR20/AQ20-1 -> 0.021217161 | AS21: =+AS20/AR20-1 -> 0.0080982509 | AT21: =+AT20/AS20-1 -> 0.008913499 | AV21: =+AV20/AT20-1 -> 0.032150006 | AW21: =+AW20/AV20-1 -> 0.016452788 | AX21: =+AX20/AW20-1 -> 0.02107862 | AY21: =+AY20/AX20-1 -> 0.025469773 | BA21: =+BA20/AY20-1 -> 0.04476337 | BB21: =+BB20/BA20-1 -> 0.023671108 | BC21: =+BC20/BB20-1 -> 0.036748098 | BD21: =+BD20/BC20-1 -> 0.036111991
C22: YoY Growth | E22: =+E20/D20-1 -> 0.25136596 | F22: =+F20/E20-1 -> 0.20309132 | G22: =+G20/F20-1 -> 0.039842666 | H22: =+H20/G20-1 -> 0.051543744 | I22: =+I20/H20-1 -> 0.052682137 | J22: =+J20/I20-1 -> 0.079731456 | K22: =+K20/J20-1 -> 0.12975501 | L22: =+L20/K20-1 -> 0.090113014 | ... P22: =+P20/O20-1 -> 0.040400828 | W22: =+W20/R20-1 -> 0.21982517 | X22: =+X20/S20-1 -> 0.24045413 | Y22: =+Y20/T20-1 -> 0.25026766 | Z22: =+Z20/U20-1 -> 0.29052299 | AB22: =+AB20/W20-1 -> 0.31619845 | AC22: =+AC20/X20-1 -> 0.23735745 | AD22: =+AD20/Y20-1 -> 0.15628023 | AE22: =+AE20/Z20-1 -> 0.12291266 | AG22: =+AG20/AB20-1 -> 0.054792127 | AH22: =+AH20/AC20-1 -> 0.034687082 | AI22: =+AI20/AD20-1 -> 0.03727827 | AJ22: =+AJ20/AE20-1 -> 0.032935957 | AK22: =+AK20/AF20-1 -> 0.039842666 | AL22: =+AL20/AG20-1 -> 0.040751627 | AM22: =+AM20/AH20-1 -> 0.055519276 | AN22: =+AN20/AI20-1 -> 0.059172009 | ... AT22: =+AT20/AO20-1 -> 0.067906355 | AV22: =+AV20/AQ20-1 -> 0.072056608 | AW22: =+AW20/AR20-1 -> 0.067055049 | AX22: =+AX20/AS20-1 -> 0.080794551 | AY22: =+AY20/AT20-1 -> 0.098530393 | BA22: =+BA20/AV20-1 -> 0.11195496 | BB22: =+BB20/AW20-1 -> 0.11985148 | BC22: =+BC20/AX20-1 -> 0.13703673 | BD22: =+BD20/AY20-1 -> 0.14883678 | BF22: =+BF20/AP20-1 -> 0.052682137
C24: Total Revenue | D24: =+D20+D6 -> 757 | E24: =213.105+235.337+253.931+282.534 -> 984.907 | F24: =+'Income Statement'!AF13 -> 1269.657 | G24: =+SUM(AG24:AJ24) -> 1387.666 | H24: =+SUM(AL24:AO24) -> 1561.665 | I24: =+SUM(AQ24:AT24) -> 1760.65 | J24: =+SUM(AV24:AY24) -> 1993.044 | K24: =+SUM(BA24:BD24) -> 2304.3809 | L24: =+'Income Statement'!BF13 -> 2574.9885 | M24: =+'Income Statement'!BG13 -> 2819.4317 | N24: =+'Income Statement'!BH13 -> 3036.2074 | O24: =+'Income Statement'!BI13 -> 3225.6636 | P24: =+'Income Statement'!BJ13 -> 3391.3179 | R24: =+'Income Statement'!R13 -> 174.29 | S24: =+'Income Statement'!S13 -> 185.419 | T24: =+'Income Statement'!T13 -> 196.791 | U24: =+D24-SUM(R24:T24) -> 200.5 | W24: =+'Income Statement'!W13 -> 215.987 | X24: =+'Income Statement'!X13 -> 236.059 | Y24: =+'Income Statement'!Y13 -> 254.18 | Z24: =+E24-SUM(W24:Y24) -> 278.681 | AB24: =+'Income Statement'!AB13 -> 304.112 | AC24: =+'Income Statement'!AC13 -> 316.406 | AD24: =+'Income Statement'!AD13 -> 320.797 | AE24: =+'Income Statement'!AE13 -> 328.342 | AG24: =+'Income Statement'!AG13 -> 341.597 | AH24: =+'Income Statement'!AH13 -> 345.224 | AI24: =+'Income Statement'!AI13 -> 345.805 | AJ24: =+'Income Statement'!AJ13 -> 355.04 | AK24: =SUM(AG24:AJ24) -> 1387.666 | AL24: =+'Income Statement'!AL13 -> 374.076 | AM24: =+'Income Statement'!AM13 -> 389.977 | AN24: =+'Income Statement'!AN13 -> 393.841 | AO24: =+'Income Statement'!AO13 -> 403.771 | AQ24: =+'Income Statement'!AQ13 -> 419.776 | AR24: =+'Income Statement'!AR13 -> 435.746 | AS24: =+'Income Statement'!AS13 -> 444.673 | AT24: =+'Income Statement'!AT13 -> 460.455 | AV24: =+'Income Statement'!AV13 -> 473.651 | AW24: =+'Income Statement'!AW13 -> 489.93 | AX24: =+'Income Statement'!AX13 -> 505.194 | AY24: =+'Income Statement'!AY13 -> 524.269 | BA24: =+'Income Statement'!BA13 -> 541.82232 | BB24: =+'Income Statement'!BB13 -> 563.34134 | BC24: =+'Income Statement'!BC13 -> 586.52045 | BD24: =+'Income Statement'!BD13 -> 612.6968
C25: YoY Growth | E25: =+E24/D24-1 -> 0.30106605 | F25: =+F24/E24-1 -> 0.28911359 | G25: =+G24/F24-1 -> 0.092945575 | H25: =+H24/G24-1 -> 0.12538968 | I25: =+I24/H24-1 -> 0.12741849 | J25: =+J24/I24-1 -> 0.1319933 | K25: =+K24/J24-1 -> 0.15621176 | L25: =+L24/K24-1 -> 0.1174318 | ... P25: =+P24/O24-1 -> 0.051355101 | W25: =+W24/R24-1 -> 0.2392392 | X25: =+X24/S24-1 -> 0.27311117 | Y25: =+Y24/T24-1 -> 0.29162411 | Z25: =+Z24/U24-1 -> 0.38993017 | AB25: =+AB24/W24-1 -> 0.40801067 | AC25: =+AC24/X24-1 -> 0.3403683 | AD25: =+AD24/Y24-1 -> 0.26208592 | AE25: =+AE24/Z24-1 -> 0.17820016 | AG25: =+AG24/AB24-1 -> 0.12326051 | AH25: =+AH24/AC24-1 -> 0.091079183 | AI25: =+AI24/AD24-1 -> 0.077955841 | AJ25: =+AJ24/AE24-1 -> 0.081311559 | AL25: =+AL24/AG24-1 -> 0.095079875 | AM25: =+AM24/AH24-1 -> 0.12963467 | AN25: =+AN24/AI24-1 -> 0.13891066 | AO25: =+AO24/AJ24-1 -> 0.13725496 | AQ25: =+AQ24/AL24-1 -> 0.12216769 | AR25: =+AR24/AM24-1 -> 0.11736333 | AS25: =+AS24/AN24-1 -> 0.12906731 | AT25: =+AT24/AO24-1 -> 0.14038651 | AV25: =+AV24/AQ24-1 -> 0.12834226 | AW25: =+AW24/AR24-1 -> 0.12434767 | AX25: =+AX24/AS24-1 -> 0.13610226 | AY25: =+AY24/AT24-1 -> 0.138589 | BA25: =+BA24/AV24-1 -> 0.14392733 | BB25: =+BB24/AW24-1 -> 0.14984047 | BC25: =+BC24/AX24-1 -> 0.16098063 | BD25: =+BD24/AY24-1 -> 0.16866875
C29: Partner BS | D29: =+D12 -> 6.51 | E29: =+E12 -> 50.82 | F29: =+F12 -> 130.275 | G29: =+G12 -> 164.881 | H29: =+H12 -> 222.585 | N29: =+N12 -> 688.65464 | O29: =+O12 -> 759.12714 | P29: =+P12 -> 823.8565 | Q29: =+(J29/G29)^(1/3)-1 -> -1
E30: =+E29/D29-1 -> 6.8064516 | F30: =+F29/E29-1 -> 1.5634593 | G30: =+G29/F29-1 -> 0.26563807 | H30: =+H29/G29-1 -> 0.34997362 | N30: =+N29/M29-1 -> #DIV/0! | O30: =+O29/N29-1 -> 0.10233358 | P30: =+P29/O29-1 -> 0.085268148
C31: Self Creator BS | D31: =+D33-D29 -> 110.086 | E31: =+E33-E29 -> 154.484 | F31: =+F33-F29 -> 189.083 | G31: =+G33-G29 -> 183.306 | H31: =+H33-H29 -> 187.073 | N31: =+N33-N29 -> 182.77337 | O31: =+O33-O29 -> 168.75299 | P31: =+P33-P29 -> 154.78873 | Q31: =+(J31/G31)^(1/3)-1 -> -1 | AO31: 237.5
E32: =+E31/D31-1 -> 0.40330287 | F32: =+F31/E31-1 -> 0.22396494 | G32: =+G31/F31-1 -> -0.03055272 | H32: =+H31/G31-1 -> 0.020550337 | N32: =+N31/M31-1 -> #DIV/0! | O32: =+O31/N31-1 -> -0.076709082 | P32: =+P31/O31-1 -> -0.082749705 | AO32: 205
C33: Business Solutions | D33: ='Income Statement'!V15 -> 116.596 | E33: ='Income Statement'!AA15 -> 205.304 | F33: ='Income Statement'!AF15 -> 319.358 | G33: ='Income Statement'!AK15 -> 348.187 | H33: ='Income Statement'!AP15 -> 409.658 | N33: ='Income Statement'!BH15 -> 871.42801 | O33: ='Income Statement'!BI15 -> 927.88013 | P33: ='Income Statement'!BJ15 -> 978.64523 | AO33: =+AO31/AO32-1 -> 0.15853659
E34: =+E33/D33-1 -> 0.76081512 | F34: =+F33/E33-1 -> 0.55553715 | G34: =+G33/F33-1 -> 0.090271733 | H34: =+H33/G33-1 -> 0.17654594 | N34: =+N33/M33-1 -> #DIV/0! | O34: =+O33/N33-1 -> 0.064781164 | P34: =+P33/O33-1 -> 0.054710844
C36: Partner CS | D36: =+D9 -> 86.49 | E36: =+E9 -> 103.18 | F36: =+F9 -> 139.725 | G36: =+G9 -> 183.299 | H36: =+H9 -> 246.015 | N36: =+N9 -> 610.69374 | O36: =+O9 -> 646.66386 | P36: =+P9 -> 674.06441 | Q36: =+(J36/G36)^(1/3)-1 -> -1
E37: =+E36/D36-1 -> 0.19297029 | F37: =+F36/E36-1 -> 0.35418686 | G37: =+G36/F36-1 -> 0.31185543 | H37: =+H36/G36-1 -> 0.34215135 | N37: =+N36/M36-1 -> #DIV/0! | O37: =+O36/N36-1 -> 0.058900426 | P37: =+P36/O36-1 -> 0.042372174
C38: Self Creator CS | D38: =+D20-D31 -> 553.914 | E38: =+E20-E31 -> 676.423 | F38: =+F20-F31 -> 810.574 | G38: =+G20-G31 -> 856.18 | H38: =+H20-H31 -> 905.992 | N38: =+N20-N31 -> 1554.0857 | O38: =+O20-O31 -> 1651.1196 | P38: =+P20-P31 -> 1738.6082 | Q38: =+(J38/G38)^(1/3)-1 -> -1
E39: =+E38/D38-1 -> 0.22116971 | F39: =+F38/E38-1 -> 0.19832413 | G39: =+G38/F38-1 -> 0.056263833 | H39: =+H38/G38-1 -> 0.058179355 | N39: =+N38/M38-1 -> #DIV/0! | O39: =+O38/N38-1 -> 0.062437952 | P39: =+P38/O38-1 -> 0.052987451
C40: Creative Subscriptions | D40: ='Income Statement'!V14 -> 644.492 | E40: ='Income Statement'!AA14 -> 783.456 | F40: ='Income Statement'!AF14 -> 950.299 | G40: ='Income Statement'!AK14 -> 1039.479 | H40: ='Income Statement'!AP14 -> 1152.007 | N40: ='Income Statement'!BH14 -> 2164.7794 | O40: ='Income Statement'!BI14 -> 2297.7835 | P40: ='Income Statement'!BJ14 -> 2412.6726
E41: =+E40/D40-1 -> 0.21561788 | F41: =+F40/E40-1 -> 0.21295772 | G41: =+G40/F40-1 -> 0.093844148 | H41: =+H40/G40-1 -> 0.10825423 | N41: =+N40/M40-1 -> #DIV/0! | O41: =+O40/N40-1 -> 0.06144 | P41: =+P40/O40-1 -> 0.05
D48: 2019 | E48: 2020 | F48: 2021 | G48: 2022 | H48: 2023E | I48: 2024E | J48: 2025E
C49: Total Users | D49: =+E49-31 -> 169 | E49: 200 | F49: 220 | G49: 243 | H49: 263
C50: YoY Growth | E50: =+E49/D49-1 -> 0.18343195 | F50: =+F49/E49-1 -> 0.1 | G50: =+G49/F49-1 -> 0.10454545 | H50: =+H49/G49-1 -> 0.082304527
C52: Premium Subs | E52: =+F52-0.478 -> 5.537 | F52: =+G52-0.096 -> 6.015 | G52: =+H52-0.189 -> 6.111 | H52: 6.3 | I52: 6.2 | J52: =+I52+0.5 -> 6.7 | K52: =+J52+0.5 -> 7.2
C53: YoY Growth | F53: =+F52/E52-1 -> 0.086328337 | G53: =+G52/F52-1 -> 0.0159601 | H53: =+H52/G52-1 -> 0.030927835 | I53: =+I52/H52-1 -> -0.015873016 | J53: =+J52/I52-1 -> 0.080645161 | K53: =+K52/J52-1 -> 0.074626866
C54: Average Subs | F54: =+AVERAGE(E52:F52) -> 5.776 | G54: =+AVERAGE(F52:G52) -> 6.063 | H54: =+AVERAGE(G52:H52) -> 6.2055 | I54: =+AVERAGE(H52:I52) -> 6.25 | J54: =+AVERAGE(I52:J52) -> 6.45 | K54: =+AVERAGE(J52:K52) -> 6.95
C55: YoY Growth | G55: =+G54/F54-1 -> 0.049688366 | H55: =+H54/G54-1 -> 0.023503216 | I55: =+I54/H54-1 -> 0.0071710579 | J55: =+J54/I54-1 -> 0.032 | K55: =+K54/J54-1 -> 0.07751938
N56: Price increase
C57: CS Revenue | F57: =+'Income Statement'!AF143 -> 950.299 | G57: =+'Income Statement'!AK143 -> 1039.479 | H57: =+'Income Statement'!AP143 -> 1152.007 | I57: =+'Income Statement'!AU143 -> 1264.975 | J57: =+'Income Statement'!AZ143 -> 1409.727 | K57: =+'Income Statement'!BE143 -> 1637.7591 | N57: early in '24
C58: CS ARPU | F58: =+F57/F$54/12 -> 13.710454 | G58: =+G57/G$54/12 -> 14.287193 | H58: =+H57/H$54/12 -> 15.470241 | I58: =+I57/I$54/12 -> 16.866333 | J58: =+J57/J$54/12 -> 18.213527 | K58: =+K57/K$54/12 -> 19.637399 | N58: 1Q22 - most of the impact in '23
C59: YoY Growth | G59: =+G58/F58-1 -> 0.042065611 | H59: =+H58/G58-1 -> 0.082804835 | I59: =+I58/H58-1 -> 0.090243703 | J59: =+J58/I58-1 -> 0.079874729 | N59: 2019
C61: BS Revenue | F61: =+'Income Statement'!AF15 -> 319.358 | G61: =+'Income Statement'!AK15 -> 348.187 | H61: =+'Income Statement'!AP15 -> 409.658 | I61: =+'Income Statement'!AU15 -> 495.675 | J61: =+'Income Statement'!AZ15 -> 583.317 | K61: =+K62*J54*12 -> 601.05551
C62: BS ARPU | F62: =+F61/F$54/12 -> 4.6075427 | G62: =+G61/G$54/12 -> 4.7856809 | H62: =+H61/H$54/12 -> 5.5012758 | I62: =+I61/I$54/12 -> 6.609 | J62: =+J61/J$54/12 -> 7.5363953 | K62: =+I62*1.175 -> 7.765575
G63: =+G62/F62-1 -> 0.0386623 | H63: =+H62/G62-1 -> 0.14952832 | I63: =+I62/H62-1 -> 0.2013577 | J63: =+J62/I62-1 -> 0.1403231
C65: Total Revenue | F65: =+'Income Statement'!AF13 -> 1269.657 | G65: =+'Income Statement'!AK13 -> 1387.666 | H65: =+'Income Statement'!AP13 -> 1561.665 | I65: =+'Income Statement'!AU13 -> 1760.65 | J65: =+'Income Statement'!AZ13 -> 1993.044 | K65: =+K57+K61 -> 2238.8146
C66: Total ARPU | G66: =+G65/G$54/12 -> 19.072874 | H66: =+H65/H$54/12 -> 20.971517 | I66: =+I65/I$54/12 -> 23.475333 | J66: =+J65/J$54/12 -> 25.749922 | K66: =+K65/J54/12 -> 28.925253
H67: =+H66/G66-1 -> 0.099546797 | I67: =+I66/H66-1 -> 0.11939127 | J67: =+J66/I66-1 -> 0.096892731 | K67: =+K66/J66-1 -> 0.1233142
C73: Studio % of Partner | H73: 0.3 | I73: 0.5 | J73: =+J74/J6 -> 0.61400171 | K73: =+K74/K6 -> 0.69441802 | L73: =+L74/L6 -> 0.7497389
C74: Studio Revenue | H74: =+H73*H6 -> 140.58 | I74: =+I73*I6 -> 305 | J74: =+J6-J76 -> 460.901 | K74: =+K6-K76 -> 625.5187 | L74: =+L6-L76 -> 783.40682
C75: YoY Growth | I75: =+I74/H74-1 -> 1.1695832 | J75: =+J74/I74-1 -> 0.51115082 | K75: =+K74/J74-1 -> 0.35716499 | L75: =+L74/K74-1 -> 0.25241151
C76: Non-Studio Revenue | H76: =+H6-H74 -> 328.02 | I76: =+I6-I74 -> 305 | J76: =+I76*(1+J77) -> 289.75 | K76: =+J76*(1+K77) -> 275.2625 | L76: =+K76*(1+L77) -> 261.49937
C77: YoY Growth | I77: =+I76/H76-1 -> -0.070178648 | J77: -0.05 | K77: -0.05 | L77: -0.05

Sheet Balance Sheet
C3: ='Income Statement'!H2 -> Mar | D3: ='Income Statement'!I2 -> Jun | E3: ='Income Statement'!J2 -> Sep | F3: ='Income Statement'!K2 -> Dec | H3: ='Income Statement'!M2 -> Mar | I3: ='Income Statement'!N2 -> Jun | J3: ='Income Statement'!O2 -> Sep | K3: ='Income Statement'!P2 -> Dec | M3: ='Income Statement'!R2 -> Mar | N3: ='Income Statement'!S2 -> Jun | O3: ='Income Statement'!T2 -> Sep | P3: ='Income Statement'!U2 -> Dec | R3: ='Income Statement'!W2 -> Mar | S3: ='Income Statement'!X2 -> Jun | T3: ='Income Statement'!Y2 -> Sep | U3: ='Income Statement'!Z2 -> Dec | AB3: ='Income Statement'!AB2 -> Mar | AC3: ='Income Statement'!AC2 -> Jun | AD3: ='Income Statement'!AD2 -> Sep | AE3: ='Income Statement'!AE2 -> Dec | AG3: ='Income Statement'!AG2 -> Mar | AH3: ='Income Statement'!AH2 -> Jun | AI3: ='Income Statement'!AI2 -> Sep | AJ3: ='Income Statement'!AJ2 -> Dec | AL3: ='Income Statement'!AL2 -> Mar | AM3: ='Income Statement'!AM2 -> Jun | AN3: ='Income Statement'!AN2 -> Sep | AO3: ='Income Statement'!AO2 -> Dec | AQ3: ='Income Statement'!AQ2 -> Mar | AR3: ='Income Statement'!AR2 -> Jun | AS3: ='Income Statement'!AS2 -> Sep | AT3: ='Income Statement'!AT2 -> Dec | AV3: ='Income Statement'!AV2 -> Mar | AW3: ='Income Statement'!AW2 -> Jun | AX3: ='Income Statement'!AX2 -> Sep | AY3: ='Income Statement'!AY2 -> Dec | BA3: ='Income Statement'!BA2 -> Mar | BB3: ='Income Statement'!BB2 -> Jun | BC3: ='Income Statement'!BC2 -> Sep | BD3: ='Income Statement'!BD2 -> Dec
B4: (Amounts in millions, except per share data) | C4: ='Income Statement'!H3 -> 1Q17 | D4: ='Income Statement'!I3 -> 2Q17 | E4: ='Income Statement'!J3 -> 3Q17 | F4: ='Income Statement'!K3 -> 4Q17 | H4: ='Income Statement'!M3 -> 1Q18 | I4: ='Income Statement'!N3 -> 2Q18 | J4: ='Income Statement'!O3 -> 3Q18 | K4: ='Income Statement'!P3 -> 4Q18 | M4: ='Income Statement'!R3 -> 1Q19 | N4: ='Income Statement'!S3 -> 2Q19 | O4: ='Income Statement'!T3 -> 3Q19 | P4: ='Income Statement'!U3 -> 4Q19 | R4: ='Income Statement'!W3 -> 1Q20 | S4: ='Income Statement'!X3 -> 2Q20 | T4: ='Income Statement'!Y3 -> 3Q20 | U4: ='Income Statement'!Z3 -> 4Q20 | AB4: ='Income Statement'!AB3 -> 1Q21 | AC4: ='Income Statement'!AC3 -> 2Q21 | AD4: ='Income Statement'!AD3 -> 3Q21 | AE4: ='Income Statement'!AE3 -> 4Q21 | AG4: ='Income Statement'!AG3 -> 1Q22 | AH4: ='Income Statement'!AH3 -> 2Q22 | AI4: ='Income Statement'!AI3 -> 3Q22 | AJ4: ='Income Statement'!AJ3 -> 4Q22 | AL4: ='Income Statement'!AL3 -> 1Q23 | AM4: ='Income Statement'!AM3 -> 2Q23 | AN4: ='Income Statement'!AN3 -> 3Q23 | AO4: ='Income Statement'!AO3 -> 4Q23 | AQ4: ='Income Statement'!AQ3 -> 1Q24 | AR4: ='Income Statement'!AR3 -> 2Q24 | AS4: ='Income Statement'!AS3 -> 3Q24 | AT4: ='Income Statement'!AT3 -> 4Q24 | AV4: ='Income Statement'!AV3 -> 1Q25 | AW4: ='Income Statement'!AW3 -> 2Q25 | AX4: ='Income Statement'!AX3 -> 3Q25 | AY4: ='Income Statement'!AY3 -> 4Q25 | BA4: ='Income Statement'!BA3 -> 1Q26E | BB4: ='Income Statement'!BB3 -> 2Q26E | BC4: ='Income Statement'!BC3 -> 3Q26E | BD4: ='Income Statement'!BD3 -> 4Q26E | BE4: ='Income Statement'!BF3 -> 2027E | BF4: ='Income Statement'!BG3 -> 2028E | BG4: ='Income Statement'!BH3 -> 2029E | BH4: ='Income Statement'!BI3 -> 2030E | BI4: ='Income Statement'!BJ3 -> 2031E | BK4: =AJ4 -> 4Q22 | BL4: =AO4 -> 4Q23 | BM4: =AT4 -> 4Q24 | BN4: =AZ4 -> 0 | BO4: =BD4 -> 4Q26E | BP4: =BE4 -> 2027E | BQ4: =BF4 -> 2028E | BR4: =BG4 -> 2029E | BS4: =BH4 -> 2030E | BT4: =BI4 -> 2031E
B5: Assets
B6: Cash and cash equivalents | C6: 90.897 | D6: 124.132 | E6: 123.903 | F6: 85.23 | H6: 103.487 | I6: 354.253 | J6: 319.966 | K6: 331.057 | M6: 348.088 | N6: 351.462 | O6: 283.158 | P6: 268.103 | R6: 191.258 | S6: 173.95 | T6: 158.456 | U6: 168.858 | AB6: 415.843 | AC6: 362.253 | AD6: 287.167 | AE6: 451.355 | AG6: 386.609 | AH6: 241.886 | AI6: 299.94 | AJ6: 244.686 | AL6: 350.913 | AM6: 468.037 | AN6: 504.793 | AO6: 609.622 | AQ6: 513.323 | AR6: 276.067 | AS6: 439.434 | AT6: 660.939 | AV6: 653.276 | AW6: 693.042 | AX6: =889.616+9.23 -> 898.846 | AY6: =311.356+5.52 -> 316.876 | BA6: =+AY6+'Cash Flow'!BA36 -> 466.56271 | BB6: =+BA6+'Cash Flow'!BB36 -> 380.88211 | BC6: =+BB6+'Cash Flow'!BC36 -> 316.58016 | BD6: =+BC6+'Cash Flow'!BD36 -> 272.59693 | BE6: =BD6+'Cash Flow'!BF36 -> 513.54744 | BF6: =BE6+'Cash Flow'!BG36 -> 1261.9029 | BG6: =BF6+'Cash Flow'!BH36 -> 2129.8837 | BH6: =BG6+'Cash Flow'!BI36 -> 3115.4358 | BI6: =BH6+'Cash Flow'!BJ36 -> 4215.6333
B7: Short term deposits | C7: 72.674 | D7: 61.055 | E7: 84.8 | F7: 115.382 | H7: 128.739 | I7: 248.948 | J7: 326.425 | K7: 349.619 | M7: 348.355 | N7: 293.25 | O7: 304.113 | P7: 294.096 | R7: 366.048 | S7: 406.033 | T7: 540.069 | U7: 577.138 | AB7: 439.123 | AC7: 565.267 | AD7: 541.324 | AE7: 411.687 | AG7: 456.644 | AH7: 568.84 | AI7: 516.77 | AJ7: 526.328 | AL7: 536.386 | AM7: 176.429 | AN7: 243.384 | AO7: 212.709 | AQ7: 241.987 | AR7: 240.956 | AS7: 176.214 | AT7: 106.844 | AV7: 112.078 | AW7: 111.892 | AX7: 387.408 | AY7: 385.28 | BA7: =+AY7 -> 385.28 | BB7: =+BA7 -> 385.28 | BC7: =+BB7 -> 385.28 | BD7: =+BC7 -> 385.28 | BE7: =BD7 -> 385.28 | BF7: =BE7 -> 385.28 | BG7: =BF7 -> 385.28 | BH7: =BG7 -> 385.28 | BI7: =BH7 -> 385.28
B8: Restricted deposits | C8: 1.085 | D8: 1.093 | E8: 0.949 | F8: 0.949 | H8: 0.949 | I8: 0.949 | J8: 0.949 | K8: 1.149 | M8: 1.149 | N8: 1.149 | O8: 1.149 | P8: 1.149 | R8: 1.15 | S8: 0.925 | T8: 1.135 | U8: 0.925 | AB8: 1.512 | AC8: 6.96 | AD8: 6.96 | AE8: 7.012 | AG8: 7.01 | AH8: 9.737 | AI8: 13.644 | AJ8: 13.669 | AL8: 6.525 | AM8: 3.219 | AN8: 2.893 | AO8: 2.125 | AQ8: 1.306 | AR8: 1.296 | AS8: 2.279 | AT8: 0.773 | AV8: 0.793 | AW8: =11.1+0.901 -> 12.001 | AX8: 0.24 | AY8: 0.222 | BA8: =+AY8 -> 0.222 | BB8: =+BA8 -> 0.222 | BC8: =+BB8 -> 0.222 | BD8: =+BC8 -> 0.222 | BE8: =BD8 -> 0.222 | BF8: =BE8 -> 0.222 | BG8: =BF8 -> 0.222 | BH8: =BG8 -> 0.222 | BI8: =BH8 -> 0.222
B9: Marketable securities | C9: 0 | D9: 0 | E9: 0 | F9: 32.73 | H9: 32.985 | I9: 33.02 | J9: 69.237 | K9: 22.992 | M9: 49.863 | N9: 104.863 | O9: 187.451 | P9: 164.301 | R9: 168.642 | S9: 174.624 | T9: 299.743 | U9: 289.927 | AB9: 269.26 | AC9: 351.624 | AD9: 417.136 | AE9: 456.515 | AG9: 356.38 | AH9: 353.35 | AI9: 400.084 | AJ9: 292.449 | AL9: 273.676 | AM9: 184.458 | AN9: 168.991 | AO9: 140.563 | AQ9: 126.91 | AR9: 270.104 | AS9: 345.538 | AT9: 338.593 | AV9: 304.555 | AW9: 310.061 | AX9: 307.605 | AY9: 483.859 | BA9: =+AY9-100 -> 383.859 | BB9: =+BA9-100 -> 283.859 | BC9: =+BB9-100 -> 183.859 | BD9: =+BC9-100 -> 83.859 | BE9: =BD9 -> 83.859 | BF9: =BE9 -> 83.859 | BG9: =BF9 -> 83.859 | BH9: =BG9 -> 83.859 | BI9: =BH9 -> 83.859
B10: Trade receivables | C10: 9.828 | D10: 8.704 | E10: 11.538 | F10: 11.4 | H10: 11.212 | I10: 8.676 | J10: 14.405 | K10: 13.528 | M10: 18.391 | N10: 18.23 | O10: 16.201 | P10: 16.987 | R10: 17.065 | S10: 18.83 | T10: 23.159 | U10: 23.67 | AB10: 29.915 | AC10: 29.418 | AD10: 27.988 | AE10: 30.367 | AG10: 42.016 | AH10: 40.8 | AI10: 35.796 | AJ10: 42.086 | AL10: 52.56 | AM10: 53.268 | AN10: 54.6 | AO10: 57.394 | AQ10: 56.275 | AR10: 55.784 | AS10: 50.224 | AT10: 46.166 | AV10: 47.328 | AW10: 55.354 | AX10: 54.688 | AY10: 41.525 | BA10: =BA49*BA45/BA47 -> 47.114985 | BB10: =BB49*BB45/BB47 -> 48.986204 | BC10: =BC49*BC45/BC47 -> 51.001778 | BD10: =BD49*BD45/BD47 -> 53.277982 | BE10: =BD10 -> 53.277982 | BF10: =BE10 -> 53.277982 | BG10: =BF10 -> 53.277982 | BH10: =BG10 -> 53.277982 | BI10: =BH10 -> 53.277982
B11: Prepaid expenses and other | C11: 24.229 | D11: 24.414 | E11: 21.939 | F11: 19.246 | H11: 17.595 | I11: 25.453 | J11: 18.304 | K11: 11.939 | M11: 19.53 | N11: 25.774 | O11: 27.229 | P11: 20.859 | R11: 40.56 | S11: 49.888 | T11: 57.481 | U11: 40.666 | AB11: 75.853 | AC11: 37.294 | AD11: 36.373 | AE11: 32.877 | AG11: 55.264 | AH11: 34.059 | AI11: 40.769 | AJ11: 28.519 | AL11: 41.327 | AM11: 38.819 | AN11: 40.452 | AO11: 57.423 | AQ11: 60.075 | AR11: 83.812 | AS11: 55.864 | AT11: 126.887 | AV11: 59.132 | AW11: 95.975 | AX11: 101.862 | AY11: 96.252 | BA11: =+('Income Statement'!BA26+'Income Statement'!BA28)/('Income Statement'!AV26+'Income Statement'!AV28)*AY11 -> 157.00338 | BB11: =+('Income Statement'!BB26+'Income Statement'!BB28)/('Income Statement'!AW26+'Income Statement'!AW28)*BA11 -> 253.85363 | BC11: =+('Income Statement'!BC26+'Income Statement'!BC28)/('Income Statement'!AX26+'Income Statement'!AX28)*BB11 -> 340.27634 | BD11: =+('Income Statement'!BD26+'Income Statement'!BD28)/('Income Statement'!AY26+'Income Statement'!AY28)*BC11 -> 399.42501 | BE11: =BD11 -> 399.42501 | BF11: =BE11 -> 399.42501 | BG11: =BF11 -> 399.42501 | BH11: =BG11 -> 399.42501 | BI11: =BH11 -> 399.42501
B12: Total Current Assets | C12: =SUM(C6:C11) -> 198.713 | D12: =SUM(D6:D11) -> 219.398 | E12: =SUM(E6:E11) -> 243.129 | F12: =SUM(F6:F11) -> 264.937 | H12: =SUM(H6:H11) -> 294.967 | I12: =SUM(I6:I11) -> 671.299 | J12: =SUM(J6:J11) -> 749.286 | K12: =SUM(K6:K11) -> 730.284 | M12: =SUM(M6:M11) -> 785.376 | N12: =SUM(N6:N11) -> 794.728 | O12: =SUM(O6:O11) -> 819.301 | P12: =SUM(P6:P11) -> 765.495 | R12: =SUM(R6:R11) -> 784.723 | S12: =SUM(S6:S11) -> 824.25 | T12: =SUM(T6:T11) -> 1080.043 | U12: =SUM(U6:U11) -> 1101.184 | AB12: =SUM(AB6:AB11) -> 1231.506 | AC12: =SUM(AC6:AC11) -> 1352.816 | AD12: =SUM(AD6:AD11) -> 1316.948 | AE12: =SUM(AE6:AE11) -> 1389.813 | AG12: =SUM(AG6:AG11) -> 1303.923 | AH12: =SUM(AH6:AH11) -> 1248.672 | AI12: =SUM(AI6:AI11) -> 1307.003 | AJ12: =SUM(AJ6:AJ11) -> 1147.737 | AL12: =SUM(AL6:AL11) -> 1261.387 | AM12: =SUM(AM6:AM11) -> 924.23 | AN12: =SUM(AN6:AN11) -> 1015.113 | AO12: =SUM(AO6:AO11) -> 1079.836 | AQ12: =SUM(AQ6:AQ11) -> 999.876 | AR12: =SUM(AR6:AR11) -> 928.019 | AS12: =SUM(AS6:AS11) -> 1069.553 | AT12: =SUM(AT6:AT11) -> 1280.202 | AV12: =SUM(AV6:AV11) -> 1177.162 | AW12: =SUM(AW6:AW11) -> 1278.325 | AX12: =SUM(AX6:AX11) -> 1750.649 | AY12: =SUM(AY6:AY11) -> 1324.014 | BA12: =SUM(BA6:BA11) -> 1440.0421 | BB12: =SUM(BB6:BB11) -> 1353.0829 | BC12: =SUM(BC6:BC11) -> 1277.2193 | BD12: =SUM(BD6:BD11) -> 1194.6609 | BE12: =SUM(BE6:BE11) -> 1435.6114 | BF12: =SUM(BF6:BF11) -> 2183.9668 | BG12: =SUM(BG6:BG11) -> 3051.9477 | BH12: =SUM(BH6:BH11) -> 4037.4998 | BI12: =SUM(BI6:BI11) -> 5137.6973
B14: Prepaid expenses & other | C14: 3.003 | D14: 3.088 | E14: 3.012 | F14: 3.823 | H14: 1.127 | I14: 1.424 | J14: 1.724 | K14: 3.065 | M14: 3.021 | N14: 2.623 | O14: 4.093 | P14: 8.278 | R14: 13.148 | S14: 13.243 | T14: 13.29 | U14: 20.971 | AB14: 118.898 | AC14: 19.585 | AD14: 23.922 | AE14: 41.554 | AG14: 44.045 | AH14: 23.32 | AI14: 33.476 | AJ14: 23.027 | AL14: 36.945 | AM14: 23.766 | AN14: 22.669 | AO14: 25.809 | AQ14: 28.292 | AR14: 25.466 | AS14: 29.221 | AT14: 27.021 | AV14: 31.343 | AW14: =32.934+70.325 -> 103.259 | AX14: 40.156 | AY14: =33.847+4.851+94.549 -> 133.247 | BA14: =AY14 -> 133.247 | BB14: =BA14 -> 133.247 | BC14: =BB14 -> 133.247 | BD14: =BC14 -> 133.247 | BE14: =BD14 -> 133.247 | BF14: =BE14 -> 133.247 | BG14: =BF14 -> 133.247 | BH14: =BG14 -> 133.247 | BI14: =BH14 -> 133.247
B15: PP&E, net | C15: 9.168 | D15: 10.566 | E15: 12.612 | F15: 16.201 | H15: 18.163 | I15: 19.752 | J15: 20.638 | K15: 21.947 | M15: 23.707 | N15: 27.079 | O15: 30.634 | P15: 31.706 | R15: 32.951 | S15: 32.926 | T15: 35.028 | U15: 35.863 | AB15: 37.281 | AC15: 42.522 | AD15: 53.414 | AE15: 50.437 | AG15: 57.081 | AH15: 64.955 | AI15: 72.637 | AJ15: 108.738 | AL15: 112.516 | AM15: 125.401 | AN15: 136.942 | AO15: 136.928 | AQ15: 136.981 | AR15: 136.277 | AS15: 132.627 | AT15: 128.155 | AV15: 125.45 | AW15: 121.715 | AX15: 117.418 | AY15: 114.419 | BA15: =AY15-'Cash Flow'!BQ21 -> 114.419 | BB15: =BA15-'Cash Flow'!BR21 -> 114.419 | BC15: =BB15-'Cash Flow'!BS21 -> 114.419 | BD15: =BC15-'Cash Flow'!BT21 -> 114.419 | BE15: =BD15+10 -> 124.419 | BF15: =BE15+10 -> 134.419 | BG15: =BF15+10 -> 144.419 | BH15: =BG15+10 -> 154.419 | BI15: =BH15+10 -> 164.419
B16: =+B9 -> Marketable securities | C16: 0 | D16: 0 | E16: 0 | F16: 0 | H16: 0 | I16: 0 | J16: 0 | K16: 47.225 | M16: 41.265 | N16: 73.858 | O16: 87.406 | P16: 177.298 | R16: 210.302 | S16: 245.211 | T16: 540.047 | U16: 536.877 | AB16: 463.55 | AC16: 526.84 | AD16: 470.148 | AE16: 387.341 | AG16: 333.853 | AH16: 291.572 | AI16: 235.997 | AJ16: 194.964 | AL16: 140.379 | AM16: 101.52 | AN16: 78.054 | AO16: 64.806 | AQ16: 34.935 | AR16: 13.953 | AS16: 6.168 | AT16: 6.135 | AV16: 6.183 | AW16: 5.259 | AX16: 4.897 | AY16: 474.198 | BA16: =+AY16-100 -> 374.198 | BB16: =+BA16-100 -> 274.198 | BC16: =+BB16-100 -> 174.198 | BD16: =+BC16-100 -> 74.198 | BE16: =BD16 -> 74.198 | BF16: =BE16 -> 74.198 | BG16: =BF16 -> 74.198 | BH16: =BG16 -> 74.198 | BI16: =BH16 -> 74.198
B17: Intangible assets and goodwill | C17: 46.551 | D17: 49.713 | E17: 48.423 | F17: 45.052 | H17: 44.425 | I17: 43.693 | J17: 42.961 | K17: 42.229 | M17: 41.497 | N17: 41.459 | O17: 40.726 | P17: 37.641 | R17: 45.075 | S17: 44.509 | T17: 44.135 | U17: 43.516 | AB17: 49.07 | AC17: 90.228 | AD17: 89.975 | AE17: 89.547 | AG17: 87.964 | AH17: 86.384 | AI17: 84.804 | AJ17: 83.293 | AL17: 81.805 | AM17: 80.316 | AN17: 78.827 | AO17: 77.339 | AQ17: =26.527+49.329 -> 75.856 | AR17: =25.062+49.329 -> 74.391 | AS17: =23.601+49.329 -> 72.93 | AT17: =22.141+49.329 -> 71.47 | AV17: =20.68+49.329 -> 70.009 | AW17: =21.935+72.084 -> 94.019 | AX17: =23.301+150.942 -> 174.243 | AY17: =31.81+135.021 -> 166.831 | BA17: =AY17 -> 166.831 | BB17: =BA17 -> 166.831 | BC17: =BB17 -> 166.831 | BD17: =BC17 -> 166.831 | BE17: =BD17 -> 166.831 | BF17: =BE17 -> 166.831 | BG17: =BF17 -> 166.831 | BH17: =BG17 -> 166.831 | BI17: =BH17 -> 166.831
B18: Operating lease | C18: 0 | D18: 0 | E18: 0 | F18: 0 | H18: 0 | I18: 0 | J18: 0 | K18: 0 | M18: 58.467 | N18: 57.327 | O18: 53.979 | P18: 79.249 | R18: 78.617 | S18: 81.112 | T18: 82.582 | U18: 88.406 | AB18: 84.904 | AC18: 84.813 | AD18: 100.728 | AE18: 101.095 | AG18: 108.929 | AH18: 243.526 | AI18: 235.794 | AJ18: 200.608 | AL18: 169.499 | AM18: 420.073 | AN18: 413.064 | AO18: 420.562 | AQ18: 416.14 | AR18: 412.903 | AS18: 403.981 | AT18: 399.861 | AV18: 395.513 | AW18: 393.46 | AX18: =72.356+398.822 -> 471.178 | AY18: 398.265 | BA18: =AY18 -> 398.265 | BB18: =BA18 -> 398.265 | BC18: =BB18 -> 398.265 | BD18: =BC18 -> 398.265 | BE18: =BD18 -> 398.265 | BF18: =BE18 -> 398.265 | BG18: =BF18 -> 398.265 | BH18: =BG18 -> 398.265 | BI18: =BH18 -> 398.265
B19: Total Assets | C19: =SUM(C12:C18) -> 257.435 | D19: =SUM(D12:D18) -> 282.765 | E19: =SUM(E12:E18) -> 307.176 | F19: =SUM(F12:F18) -> 330.013 | H19: =SUM(H12:H18) -> 358.682 | I19: =SUM(I12:I18) -> 736.168 | J19: =SUM(J12:J18) -> 814.609 | K19: =SUM(K12:K18) -> 844.75 | M19: =SUM(M12:M18) -> 953.333 | N19: =SUM(N12:N18) -> 997.074 | O19: =SUM(O12:O18) -> 1036.139 | P19: =SUM(P12:P18) -> 1099.667 | R19: =SUM(R12:R18) -> 1164.816 | S19: =SUM(S12:S18) -> 1241.251 | T19: =SUM(T12:T18) -> 1795.125 | U19: =SUM(U12:U18) -> 1826.817 | AB19: =SUM(AB12:AB18) -> 1985.209 | AC19: =SUM(AC12:AC18) -> 2116.804 | AD19: =SUM(AD12:AD18) -> 2055.135 | AE19: =SUM(AE12:AE18) -> 2059.787 | AG19: =SUM(AG12:AG18) -> 1935.795 | AH19: =SUM(AH12:AH18) -> 1958.429 | AI19: =SUM(AI12:AI18) -> 1969.711 | AJ19: =SUM(AJ12:AJ18) -> 1758.367 | AL19: =SUM(AL12:AL18) -> 1802.531 | AM19: =SUM(AM12:AM18) -> 1675.306 | AN19: =SUM(AN12:AN18) -> 1744.669 | AO19: =SUM(AO12:AO18) -> 1805.28 | AQ19: =SUM(AQ12:AQ18) -> 1692.08 | AR19: =SUM(AR12:AR18) -> 1591.009 | AS19: =SUM(AS12:AS18) -> 1714.48 | AT19: =SUM(AT12:AT18) -> 1912.844 | AV19: =SUM(AV12:AV18) -> 1805.66 | AW19: =SUM(AW12:AW18) -> 1996.037 | AX19: =SUM(AX12:AX18) -> 2558.541 | AY19: =SUM(AY12:AY18) -> 2610.974 | BA19: =SUM(BA12:BA18) -> 2627.0021 | BB19: =SUM(BB12:BB18) -> 2440.0429 | BC19: =SUM(BC12:BC18) -> 2264.1793 | BD19: =SUM(BD12:BD18) -> 2081.6209 | BE19: =SUM(BE12:BE18) -> 2332.5714 | BF19: =SUM(BF12:BF18) -> 3090.9268 | BG19: =SUM(BG12:BG18) -> 3968.9077 | BH19: =SUM(BH12:BH18) -> 4964.4598 | BI19: =SUM(BI12:BI18) -> 6074.6573
B21: Liabilities and SE
B22: Trade payables | C22: 26.277 | D22: 28.933 | E22: 41.622 | F22: 34.24 | H22: 34.297 | I22: 38.497 | J22: 39.864 | K22: 45.567 | M22: 49.465 | N22: 46.074 | O22: 48.214 | P22: 37.687 | R22: 46.639 | S22: 73.059 | T22: 70.346 | U22: 79.881 | AB22: 77.781 | AC22: 81.334 | AD22: 89.33 | AE22: 114.584 | AG22: 134.754 | AH22: 127.113 | AI22: 118.788 | AJ22: 96.071 | AL22: 49.437 | AM22: 41.467 | AN22: 23.184 | AO22: 39.449 | AQ22: 34.434 | AR22: 18.379 | AS22: 30.891 | AT22: 48.003 | AV22: 38.032 | AW22: 25.237 | AX22: 32.575 | AY22: 74.811 | BA22: =BA46*BA50/BA47 -> 184.71424 | BB22: =BB46*BB50/BB47 -> 125.28215 | BC22: =BC46*BC50/BC47 -> 140.21266 | BD22: =BD46*BD50/BD47 -> 176.1724 | BE22: =BD22*(1+BP22) -> 184.98102 | BF22: =BE22*(1+BQ22) -> 194.23007 | BG22: =BF22*(1+BR22) -> 203.94157 | BH22: =BG22*(1+BS22) -> 214.13865 | BI22: =BH22*(1+BT22) -> 224.84558 | BK22: =AJ22/AE22-1 -> -0.16156706 | BL22: =MAX(BK22-0.15,0.05) -> 0.05 | BM22: =MAX(BL22-0.15,0.05) -> 0.05 | BN22: =MAX(BM22-0.15,0.05) -> 0.05 | BO22: =MAX(BN22-0.15,0.05) -> 0.05 | BP22: =MAX(BO22-0.15,0.05) -> 0.05 | BQ22: =MAX(BP22-0.15,0.05) -> 0.05 | BR22: =MAX(BQ22-0.15,0.05) -> 0.05 | BS22: =MAX(BR22-0.15,0.05) -> 0.05 | BT22: =MAX(BS22-0.15,0.05) -> 0.05
B23: Employees and payroll accruals | C23: 27.978 | D23: 25.938 | E23: 22.987 | F23: 28.067 | H23: 33.188 | I23: 41.564 | J23: 31.101 | K23: 32.036 | M23: 36.145 | N23: 45.452 | O23: 40.725 | P23: 56.464 | R23: 65.665 | S23: 66.306 | T23: 74.642 | U23: 70.814 | AB23: 103.692 | AC23: 86.721 | AD23: 76.379 | AE23: 83.251 | AG23: 78.503 | AH23: 78.169 | AI23: 68.145 | AJ23: 86.113 | AL23: 76.071 | AM23: 58.139 | AN23: 64.888 | AO23: 56.581 | AQ23: 54.152 | AR23: 67.842 | AS23: 75.6 | AT23: 142.007 | AV23: 78.983 | AW23: 100.742 | AX23: 112.068 | AY23: 110.526 | BA23: =+('Income Statement'!BA26+'Income Statement'!BA28)/('Income Statement'!AV26+'Income Statement'!AV28)*'Balance Sheet'!AY23 -> 180.2867 | BB23: =+('Income Statement'!BB26+'Income Statement'!BB28)/('Income Statement'!AW26+'Income Statement'!AW28)*'Balance Sheet'!BA23 -> 291.49967 | BC23: =+('Income Statement'!BC26+'Income Statement'!BC28)/('Income Statement'!AX26+'Income Statement'!AX28)*'Balance Sheet'!BB23 -> 390.73872 | BD23: =+('Income Statement'!BD26+'Income Statement'!BD28)/('Income Statement'!AY26+'Income Statement'!AY28)*'Balance Sheet'!BC23 -> 458.65902 | BE23: =BD23*(1+BP23) -> 481.59197 | BF23: =BE23*(1+BQ23) -> 505.67157 | BG23: =BF23*(1+BR23) -> 530.95515 | BH23: =BG23*(1+BS23) -> 557.50291 | BI23: =BH23*(1+BT23) -> 585.37805 | BK23: =AJ23/AE23-1 -> 0.034377965 | BL23: =MAX(BK23-0.25,0.05) -> 0.05 | BM23: =MAX(BL23-0.25,0.05) -> 0.05 | BN23: =MAX(BM23-0.25,0.05) -> 0.05 | BO23: =MAX(BN23-0.25,0.05) -> 0.05 | BP23: =MAX(BO23-0.25,0.05) -> 0.05 | BQ23: =MAX(BP23-0.25,0.05) -> 0.05 | BR23: =MAX(BQ23-0.25,0.05) -> 0.05 | BS23: =MAX(BR23-0.25,0.05) -> 0.05 | BT23: =MAX(BS23-0.25,0.05) -> 0.05
B24: Deferred revenue | C24: 169.708 | D24: 182.22 | E24: 190.082 | F24: 202.482 | H24: 201.498 | I24: 214.206 | J24: 219.555 | K24: 227.226 | M24: 250.495 | N24: 262.259 | O24: 269.379 | P24: 289.148 | R24: 319.531 | S24: 344.515 | T24: 359.761 | U24: 373.521 | AB24: 412.368 | AC24: 432.606 | AD24: 436.306 | AE24: 484.446 | AG24: 517.55 | AH24: 522.57 | AI24: 526.764 | AJ24: 529.205 | AL24: 577.835 | AM24: 584.028 | AN24: 587.514 | AO24: 592.608 | AQ24: 626.081 | AR24: 650.878 | AS24: 656.671 | AT24: 661.171 | AV24: 698.343 | AW24: 715.705 | AX24: 728.688 | AY24: 737.346 | BA24: ='Income Statement'!BA5*(+AV24/(AV24+AV30))+AY24 -> 768.0739 | BB24: ='Income Statement'!BB5*(+AW24/(AW24+AW30))+BA24 -> 786.69057 | BC24: ='Income Statement'!BC5*(+AX24/(AX24+AX30))+BB24 -> 796.40836 | BD24: ='Income Statement'!BD5*(+AY24/(AY24+AY30))+BC24 -> 796.40836 | BE24: =BD24*(1+BP24) -> 836.22877 | BF24: =BE24*(1+BQ24) -> 878.04021 | BG24: =BF24*(1+BR24) -> 921.94222 | BH24: =BG24*(1+BS24) -> 968.03933 | BI24: =BH24*(1+BT24) -> 1016.4413 | BK24: =AJ24/AE24-1 -> 0.092392135 | BL24: =MAX(BK24-0.15,0.05) -> 0.05 | BM24: =MAX(BL24-0.15,0.05) -> 0.05 | BN24: =MAX(BM24-0.15,0.05) -> 0.05 | BO24: =MAX(BN24-0.15,0.05) -> 0.05 | BP24: =MAX(BO24-0.15,0.05) -> 0.05 | BQ24: =MAX(BP24-0.15,0.05) -> 0.05 | BR24: =MAX(BQ24-0.15,0.05) -> 0.05 | BS24: =MAX(BR24-0.15,0.05) -> 0.05 | BT24: =MAX(BS24-0.15,0.05) -> 0.05
B25: Current portion of conv debt | AB25: 0 | AC25: 0 | AD25: 0 | AE25: 0 | AG25: 0 | AH25: 360.579 | AI25: 361.1 | AJ25: 361.621 | AL25: 362.144 | AM25: 0 | AN25: 0 | AO25: 0 | AQ25: 0 | AR25: =AQ25 -> 0 | AS25: 572.087 | AT25: 572.88 | AV25: 573.674 | AW25: 574.469 | AX25: 0 | AY25: =AX25 -> 0 | BA25: =AY25 -> 0 | BB25: =BA25 -> 0 | BC25: =BB25 -> 0 | BD25: =BC25 -> 0 | BE25: =BD25 -> 0 | BF25: =BE25 -> 0 | BG25: =BF25 -> 0 | BH25: =BG25 -> 0 | BI25: =BH25 -> 0
B26: Accrued expenses and other | C26: 21.877 | D26: 26.65 | E26: 28.407 | F26: 37.592 | H26: 43.668 | I26: 41.047 | J26: 43.444 | K26: 35.564 | M26: 39.509 | N26: 42.972 | O26: =47.41 -> 47.41 | P26: 41.938 | R26: 48.408 | S26: 65.036 | T26: 68.699 | U26: 70.429 | AB26: 85.348 | AC26: 84.075 | AD26: 87.499 | AE26: 62.816 | AG26: 61.334 | AH26: 83.053 | AI26: 86.226 | AJ26: 88.194 | AL26: 97.034 | AM26: 88.414 | AN26: 97.624 | AO26: 76.556 | AQ26: 74.974 | AR26: 85.063 | AS26: 74.021 | AT26: 63.246 | AV26: 79.546 | AW26: 132.938 | AX26: 162.323 | AY26: 146.716 | BA26: =+AY26 -> 146.716 | BB26: =+BA26 -> 146.716 | BC26: =+BB26 -> 146.716 | BD26: =+BC26 -> 146.716 | BE26: =BD26 -> 146.716 | BF26: =BE26 -> 146.716 | BG26: =BF26 -> 146.716 | BH26: =BG26 -> 146.716 | BI26: =BH26 -> 146.716
B27: Operating lease | C27: 0 | D27: 0 | E27: 0 | F27: 0 | H27: 0 | I27: 0 | J27: 0 | K27: 0 | M27: 15.344 | N27: 15.259 | O27: 14.267 | P27: 18.949 | R27: 15.944 | S27: 17.372 | T27: 19.111 | U27: 22.336 | AB27: 22.14 | AC27: 26.667 | AD27: 30.849 | AE27: 29.201 | AG27: 31.477 | AH27: 25.052 | AI27: 29.294 | AJ27: 29.268 | AL27: 48.155 | AM27: 18.461 | AN27: 20.788 | AO27: 24.981 | AQ27: 23.494 | AR27: 26.815 | AS27: 31.287 | AT27: 27.907 | AV27: 29.369 | AW27: 32.806 | AX27: 42.446 | AY27: 43.262 | BA27: =+AY27 -> 43.262 | BB27: =+BA27 -> 43.262 | BC27: =+BB27 -> 43.262 | BD27: =+BC27 -> 43.262 | BE27: =BD27 -> 43.262 | BF27: =BE27 -> 43.262 | BG27: =BF27 -> 43.262 | BH27: =BG27 -> 43.262 | BI27: =BH27 -> 43.262
B28: Total current liabilities | C28: =SUM(C22:C27) -> 245.84 | D28: =SUM(D22:D27) -> 263.741 | E28: =SUM(E22:E27) -> 283.098 | F28: =SUM(F22:F27) -> 302.381 | H28: =SUM(H22:H27) -> 312.651 | I28: =SUM(I22:I27) -> 335.314 | J28: =SUM(J22:J27) -> 333.964 | K28: =SUM(K22:K27) -> 340.393 | M28: =SUM(M22:M27) -> 390.958 | N28: =SUM(N22:N27) -> 412.016 | O28: =SUM(O22:O27) -> 419.995 | P28: =SUM(P22:P27) -> 444.186 | R28: =SUM(R22:R27) -> 496.187 | S28: =SUM(S22:S27) -> 566.288 | T28: =SUM(T22:T27) -> 592.559 | U28: =SUM(U22:U27) -> 616.981 | AB28: =SUM(AB22:AB27) -> 701.329 | AC28: =SUM(AC22:AC27) -> 711.403 | AD28: =SUM(AD22:AD27) -> 720.363 | AE28: =SUM(AE22:AE27) -> 774.298 | AG28: =SUM(AG22:AG27) -> 823.618 | AH28: =SUM(AH22:AH27) -> 1196.536 | AI28: =SUM(AI22:AI27) -> 1190.317 | AJ28: =SUM(AJ22:AJ27) -> 1190.472 | AL28: =SUM(AL22:AL27) -> 1210.676 | AM28: =SUM(AM22:AM27) -> 790.509 | AN28: =SUM(AN22:AN27) -> 793.998 | AO28: =SUM(AO22:AO27) -> 790.175 | AQ28: =SUM(AQ22:AQ27) -> 813.135 | AR28: =SUM(AR22:AR27) -> 848.977 | AS28: =SUM(AS22:AS27) -> 1440.557 | AT28: =SUM(AT22:AT27) -> 1515.214 | AV28: =SUM(AV22:AV27) -> 1497.947 | AW28: =SUM(AW22:AW27) -> 1581.897 | AX28: =SUM(AX22:AX27) -> 1078.1 | AY28: =SUM(AY22:AY27) -> 1112.661 | BA28: =SUM(BA22:BA27) -> 1323.0528 | BB28: =SUM(BB22:BB27) -> 1393.4504 | BC28: =SUM(BC22:BC27) -> 1517.3377 | BD28: =SUM(BD22:BD27) -> 1621.2178 | BE28: =SUM(BE22:BE27) -> 1692.7798 | BF28: =SUM(BF22:BF27) -> 1767.9199 | BG28: =SUM(BG22:BG27) -> 1846.8169 | BH28: =SUM(BH22:BH27) -> 1929.6589 | BI28: =SUM(BI22:BI27) -> 2016.6429
B30: Long term deferred revenue | C30: 12.039 | D30: 13.126 | E30: 14.012 | F30: 14.329 | H30: 9.04 | I30: 10.095 | J30: 11.923 | K30: 12.494 | M30: 15.314 | N30: 17.694 | O30: 19.643 | P30: 21.969 | R30: 24.457 | S30: 29.265 | T30: 40.78 | U30: 50.867 | AB30: 59.059 | AC30: 58.583 | AD30: 60.336 | AE30: 59.966 | AG30: 64.414 | AH30: 67.125 | AI30: 68.954 | AJ30: 70.594 | AL30: 82.939 | AM30: 88.789 | AN30: 85.69 | AO30: 83.384 | AQ30: 91.23 | AR30: 91.859 | AS30: 92.162 | AT30: 89.271 | AV30: 96.461 | AW30: 105.331 | AX30: 110.664 | AY30: 116.991 | BA30: ='Income Statement'!BA5*(+AV30/(AV30+AV24))+AY30 -> 121.2354 | BB30: ='Income Statement'!BB5*(+AW30/(AW30+AW24))+BA30 -> 123.97523 | BC30: ='Income Statement'!BC5*(+AX30/(AX30+AX24))+BB30 -> 125.45104 | BD30: ='Income Statement'!BD5*(+AY30/(AY30+AY24))+BC30 -> 125.45104 | BE30: =BD30*(1+BP30) -> 131.7236 | BF30: =BE30*(1+BQ30) -> 138.30978 | BG30: =BF30*(1+BR30) -> 145.22527 | BH30: =BG30*(1+BS30) -> 152.48653 | BI30: =BH30*(1+BT30) -> 160.11086 | BK30: =AJ30/AE30-1 -> 0.17723377 | BL30: =MAX(BK30-0.05,0.05) -> 0.12723377 | BM30: =MAX(BL30-0.05,0.05) -> 0.077233766 | BN30: =MAX(BM30-0.05,0.05) -> 0.05 | BO30: =MAX(BN30-0.05,0.05) -> 0.05 | BP30: =MAX(BO30-0.05,0.05) -> 0.05 | BQ30: =MAX(BP30-0.05,0.05) -> 0.05 | BR30: =MAX(BQ30-0.05,0.05) -> 0.05 | BS30: =MAX(BR30-0.05,0.05) -> 0.05 | BT30: =MAX(BS30-0.05,0.05) -> 0.05
B31: Long-term deferred tax liabilities | C31: 0.426 | D31: 3.908 | E31: 4.467 | F31: 0.764 | H31: 0.723 | I31: 0.683 | J31: 0.642 | K31: 0.602 | M31: 0.824 | N31: =2.074+0.57 -> 2.644 | O31: =0.425+2.482 -> 2.907 | P31: 1.585 | R31: 1.598 | S31: 1.574 | T31: 0.693 | U31: 0 | AB31: 22.382 | AC31: 55.884 | AD31: 79.718 | AE31: 72.803 | AG31: 37.176 | AH31: 24.509 | AI31: 26.856 | AJ31: 14.902 | AL31: 10.76 | AM31: 8.725 | AN31: 8.155 | AO31: 7.167 | AQ31: 1.595 | AR31: 0.902 | AS31: 1.435 | AT31: 1.965 | AV31: 1.066 | AW31: 5.15 | AX31: 4.992 | AY31: 3.923 | BA31: =AY31 -> 3.923 | BB31: =BA31 -> 3.923 | BC31: =BB31 -> 3.923 | BD31: =BC31 -> 3.923 | BE31: =BD31 -> 3.923 | BF31: =BE31 -> 3.923 | BG31: =BF31 -> 3.923 | BH31: =BG31 -> 3.923 | BI31: =BH31 -> 3.923
B32: Convertible senior note | C32: 0 | D32: 0 | E32: 0 | F32: 0 | H32: 0 | I32: 285.018 | J32: 332.738 | K32: 337.777 | M32: 342.895 | N32: 348.089 | O32: 353.362 | P32: 358.715 | R32: 364.148 | S32: 369.664 | T32: 823.029 | U32: 834.44 | AB32: 919.084 | AC32: 920.379 | AD32: 921.676 | AE32: 922.974 | AG32: 924.275 | AH32: 564.998 | AI32: 565.782 | AJ32: 566.566 | AL32: 567.351 | AM32: 568.138 | AN32: 568.925 | AO32: 569.714 | AQ32: 570.504 | AR32: 571.295 | AS32: 0 | AT32: 0 | AV32: =AT32 -> 0 | AW32: 0 | AX32: 1124.494 | AY32: 1125.769 | BA32: =AY32 -> 1125.769 | BB32: =BA32 -> 1125.769 | BC32: =BB32 -> 1125.769 | BD32: =BC32 -> 1125.769 | BE32: =BD32 -> 1125.769 | BF32: =BE32 -> 1125.769 | BG32: =BF32 -> 1125.769 | BH32: =BG32 -> 1125.769 | BI32: =BH32 -> 1125.769
B33: Long term loan | C33: 1.219 | D33: 1.219 | E33: 1.219 | F33: 1.219 | H33: 1.219 | I33: 1.219 | J33: 1.219 | K33: 1.219 | M33: 1.219 | N33: 1.219 | O33: 1.219 | P33: 1.219 | R33: 1.219 | S33: 1.219 | T33: 1.219 | U33: 0 | AB33: =U33 -> 0 | AC33: 0 | AD33: 0 | AE33: =AD33 -> 0 | AG33: 0 | AH33: 0 | AI33: 0 | AJ33: 0 | AL33: 0 | AM33: =AL33 -> 0 | AN33: =AM33 -> 0 | AO33: 0 | AQ33: 0 | AR33: =AQ33 -> 0 | AS33: =AR33 -> 0 | AT33: 0 | AV33: =AT33 -> 0 | AW33: 0 | AX33: 0 | AY33: =AX33 -> 0 | BA33: =AY33 -> 0 | BB33: =BA33 -> 0 | BC33: =BB33 -> 0 | BD33: =BC33 -> 0 | BE33: =BD33 -> 0 | BF33: =BE33 -> 0 | BG33: =BF33 -> 0 | BH33: =BG33 -> 0 | BI33: =BH33 -> 0
B34: Other long term liabilites | R34: 0 | S34: 0 | T34: 0 | U34: 0 | V34: 0 | AB34: 0 | AC34: 0 | AD34: 0 | AE34: 2.267 | AG34: 2.282 | AH34: 2.09 | AI34: 1.991 | AJ34: 6.093 | AL34: 6.623 | AM34: 9.708 | AN34: 8.202 | AO34: 7.699 | AQ34: 9.759 | AR34: 9.755 | AS34: 11.264 | AT34: 16.021 | AV34: 19.414 | AW34: 28.561 | AX34: 114.995 | AY34: 200.054 | BA34: =AY34 -> 200.054 | BB34: =BA34 -> 200.054 | BC34: =BB34 -> 200.054 | BD34: =BC34 -> 200.054 | BE34: =BD34 -> 200.054 | BF34: =BE34 -> 200.054 | BG34: =BF34 -> 200.054 | BH34: =BG34 -> 200.054 | BI34: =BH34 -> 200.054
B35: Operating lease | C35: 0 | D35: 0 | E35: 0 | F35: 0 | H35: 0 | I35: 0 | J35: 0 | K35: 0 | M35: 43.421 | N35: 42.784 | O35: 40.246 | P35: 64.244 | R35: 66.283 | S35: 68.402 | T35: 69.348 | U35: 74.187 | AB35: 69.527 | AC35: 65.71 | AD35: 77.288 | AE35: 81.764 | AG35: 86.513 | AH35: 192.735 | AI35: 180.227 | AJ35: 172.982 | AL35: 141.115 | AM35: 386.608 | AN35: 374.44 | AO35: 401.626 | AQ35: 400.063 | AR35: 390.931 | AS35: 368.369 | AT35: 369.159 | AV35: 359.389 | AW35: 392.761 | AX35: 404.061 | AY35: 417.578 | BA35: =AY35 -> 417.578 | BB35: =BA35 -> 417.578 | BC35: =BB35 -> 417.578 | BD35: =BC35 -> 417.578 | BE35: =BD35 -> 417.578 | BF35: =BE35 -> 417.578 | BG35: =BF35 -> 417.578 | BH35: =BG35 -> 417.578 | BI35: =BH35 -> 417.578
B36: Total Liabilities | C36: =SUM(C30:C35)+C28 -> 259.524 | D36: =SUM(D30:D35)+D28 -> 281.994 | E36: =SUM(E30:E35)+E28 -> 302.796 | F36: =SUM(F30:F35)+F28 -> 318.693 | H36: =SUM(H30:H35)+H28 -> 323.633 | I36: =SUM(I30:I35)+I28 -> 632.329 | J36: =SUM(J30:J35)+J28 -> 680.486 | K36: =SUM(K30:K35)+K28 -> 692.485 | M36: =SUM(M30:M35)+M28 -> 794.631 | N36: =SUM(N30:N35)+N28 -> 824.446 | O36: =SUM(O30:O35)+O28 -> 837.372 | P36: =SUM(P30:P35)+P28 -> 891.918 | R36: =SUM(R30:R35)+R28 -> 953.892 | S36: =SUM(S30:S35)+S28 -> 1036.412 | T36: =SUM(T30:T35)+T28 -> 1527.628 | U36: =SUM(U30:U35)+U28 -> 1576.475 | AB36: =SUM(AB30:AB35)+AB28 -> 1771.381 | AC36: =SUM(AC30:AC35)+AC28 -> 1811.959 | AD36: =SUM(AD30:AD35)+AD28 -> 1859.381 | AE36: =SUM(AE30:AE35)+AE28 -> 1914.072 | AG36: =SUM(AG30:AG35)+AG28 -> 1938.278 | AH36: =SUM(AH30:AH35)+AH28 -> 2047.993 | AI36: =SUM(AI30:AI35)+AI28 -> 2034.127 | AJ36: =SUM(AJ30:AJ35)+AJ28 -> 2021.609 | AL36: =SUM(AL30:AL35)+AL28 -> 2019.464 | AM36: =SUM(AM30:AM35)+AM28 -> 1852.477 | AN36: =SUM(AN30:AN35)+AN28 -> 1839.41 | AO36: =SUM(AO30:AO35)+AO28 -> 1859.765 | AQ36: =SUM(AQ30:AQ35)+AQ28 -> 1886.286 | AR36: =SUM(AR30:AR35)+AR28 -> 1913.719 | AS36: =SUM(AS30:AS35)+AS28 -> 1913.787 | AT36: =SUM(AT30:AT35)+AT28 -> 1991.63 | AV36: =SUM(AV30:AV35)+AV28 -> 1974.277 | AW36: =SUM(AW30:AW35)+AW28 -> 2113.7 | AX36: =SUM(AX30:AX35)+AX28 -> 2837.306 | AY36: =SUM(AY30:AY35)+AY28 -> 2976.976 | BA36: =SUM(BA30:BA35)+BA28 -> 3191.6122 | BB36: =SUM(BB30:BB35)+BB28 -> 3264.7496 | BC36: =SUM(BC30:BC35)+BC28 -> 3390.1128 | BD36: =SUM(BD30:BD35)+BD28 -> 3493.9928 | BE36: =SUM(BE30:BE35)+BE28 -> 3571.8274 | BF36: =SUM(BF30:BF35)+BF28 -> 3653.5536 | BG36: =SUM(BG30:BG35)+BG28 -> 3739.3662 | BH36: =SUM(BH30:BH35)+BH28 -> 3829.4694 | BI36: =SUM(BI30:BI35)+BI28 -> 3924.0778
B38: Stockholders' Equity | C38: -2.089 | D38: 0.771 | E38: 4.38 | F38: 11.32 | H38: 35.049 | I38: 103.839 | J38: 134.123 | K38: 152.265 | M38: 158.702 | N38: 172.628 | O38: 198.767 | P38: 207.749 | R38: 210.924 | S38: 204.839 | T38: 267.497 | U38: 250.342 | AB38: =AB19-AB36 -> 213.828 | AC38: =AC19-AC36 -> 304.845 | AD38: 195.754 | AE38: 145.715 | AG38: -2.483 | AH38: -89.564 | AI38: -64.416 | AJ38: -262.242 | AL38: -216.933 | AM38: -177.171 | AN38: -94.741 | AO38: -54.485 | AQ38: -194.206 | AR38: -322.71 | AS38: -199.307 | AT38: -78.786 | AV38: -168.617 | AW38: -117.663 | AX38: -278.765 | AY38: =AY19-AY36 -> -366.002 | BA38: =BA19-BA36 -> -564.61017 | BB38: =BB19-BB36 -> -824.70668 | BC38: =BC19-BC36 -> -1125.9335 | BD38: =BD19-BD36 -> -1412.3719 | BE38: =BE19-BE36 -> -1239.2559 | BF38: =BF19-BF36 -> -562.62678 | BG38: =BG19-BG36 -> 229.54147 | BH38: =BH19-BH36 -> 1134.9904 | BI38: =BI19-BI36 -> 2150.5795
B39: Total Liabilities and SE | C39: =C38+C36 -> 257.435 | D39: =D38+D36 -> 282.765 | E39: =E38+E36 -> 307.176 | F39: =F38+F36 -> 330.013 | H39: =H38+H36 -> 358.682 | I39: =I38+I36 -> 736.168 | J39: =J38+J36 -> 814.609 | K39: =K38+K36 -> 844.75 | M39: =M38+M36 -> 953.333 | N39: =N38+N36 -> 997.074 | O39: =O38+O36 -> 1036.139 | P39: =P38+P36 -> 1099.667 | R39: =R38+R36 -> 1164.816 | S39: =S38+S36 -> 1241.251 | T39: =T38+T36 -> 1795.125 | U39: =U38+U36 -> 1826.817 | AB39: =AB38+AB36 -> 1985.209 | AC39: =AC38+AC36 -> 2116.804 | AD39: =AD38+AD36 -> 2055.135 | AE39: =AE38+AE36 -> 2059.787 | AG39: =AG38+AG36 -> 1935.795 | AH39: =AH38+AH36 -> 1958.429 | AI39: =AI38+AI36 -> 1969.711 | AJ39: =AJ38+AJ36 -> 1759.367 | AL39: =AL38+AL36 -> 1802.531 | AM39: =AM38+AM36 -> 1675.306 | AN39: =AN38+AN36 -> 1744.669 | AO39: =AO38+AO36 -> 1805.28 | AQ39: =AQ38+AQ36 -> 1692.08 | AR39: =AR38+AR36 -> 1591.009 | AS39: =AS38+AS36 -> 1714.48 | AT39: =AT38+AT36 -> 1912.844 | AV39: =AV38+AV36 -> 1805.66 | AW39: =AW38+AW36 -> 1996.037 | AX39: =AX38+AX36 -> 2558.541 | AY39: =AY38+AY36 -> 2610.974 | BA39: =BA38+BA36 -> 2627.0021 | BB39: =BB38+BB36 -> 2440.0429 | BC39: =BC38+BC36 -> 2264.1793 | BD39: =BD38+BD36 -> 2081.6209 | BE39: =BE38+BE36 -> 2332.5714 | BF39: =BF38+BF36 -> 3090.9268 | BG39: =BG38+BG36 -> 3968.9077 | BH39: =BH38+BH36 -> 4964.4598 | BI39: =BI38+BI36 -> 6074.6573
B41: Shares | C41: ='Income Statement'!H78 -> 55.499403 | D41: ='Income Statement'!I78 -> 55.874077 | E41: ='Income Statement'!J78 -> 52.983929 | F41: ='Income Statement'!K78 -> 56.561901 | H41: ='Income Statement'!M78 -> 46.827425 | I41: ='Income Statement'!N78 -> 47.689337 | J41: ='Income Statement'!O78 -> 48.498392 | K41: ='Income Statement'!P78 -> 49.053599 | M41: ='Income Statement'!R78 -> 49.562367 | N41: ='Income Statement'!S78 -> 50.273017 | O41: ='Income Statement'!T78 -> 50.862253 | P41: ='Income Statement'!U78 -> 51.321155 | R41: ='Income Statement'!W78 -> 51.838314 | S41: ='Income Statement'!X78 -> 54.695477 | T41: ='Income Statement'!Y78 -> 55.356961 | U41: ='Income Statement'!Z78 -> 55.809471 | AB41: ='Income Statement'!AB78 -> 56.280561 | AC41: ='Income Statement'!AC78 -> 64.948445 | AD41: ='Income Statement'!AD78 -> 60.549853 | AE41: ='Income Statement'!AE78 -> 64.200305 | AG41: ='Income Statement'!AG78 -> 65.377546 | AH41: ='Income Statement'!AH78 -> 65.976765 | AI41: ='Income Statement'!AI78 -> 66.221504 | AJ41: ='Income Statement'!AJ78 -> 65.644287 | AL41: ='Income Statement'!AL78 -> 64.097185 | AM41: ='Income Statement'!AM78 -> 65.432873 | AN41: ='Income Statement'!AN78 -> 61.600715 | AO41: ='Income Statement'!AO78 -> 62.149917 | AQ41: ='Income Statement'!AQ78 -> 60.370132 | AR41: ='Income Statement'!AR78 -> 59.526418 | AS41: ='Income Statement'!AS78 -> 58.166801 | AT41: ='Income Statement'!AT78 -> 62.65857 | AV41: ='Income Statement'!AV78 -> 60.38451 | AW41: ='Income Statement'!AW78 -> 59.650008 | AX41: ='Income Statement'!AX78 -> 59.395828 | AY41: ='Income Statement'!AY78 -> 58.689501 | BA41: ='Income Statement'!BA78 -> 55.082518 | BB41: ='Income Statement'!BB78 -> 51.89875 | BC41: ='Income Statement'!BC78 -> 49.05231 | BD41: ='Income Statement'!BD78 -> 46.480205 | BE41: ='Income Statement'!BF78 -> 48.487914 | BF41: ='Income Statement'!BG78 -> 49.606498 | BG41: ='Income Statement'!BH78 -> 50.753046 | BH41: ='Income Statement'!BI78 -> 51.928258 | BI41: ='Income Statement'!BJ78 -> 53.132851
B42: Net Cash | C42: =C6+C9 -> 90.897 | D42: =D6+D9 -> 124.132 | E42: =E6+E9 -> 123.903 | F42: =F6+F9 -> 117.96 | H42: =H6+H9 -> 136.472 | I42: =I6+I9 -> 387.273 | J42: =J6+J9 -> 389.203 | K42: =K6+K9 -> 354.049 | M42: =M6+M9 -> 397.951 | N42: =N6+N9 -> 456.325 | O42: =O6+O9 -> 470.609 | P42: =P6+P9 -> 432.404 | R42: =R6+R9 -> 359.9 | S42: =S6+S9 -> 348.574 | T42: =T6+T9 -> 458.199 | U42: =U6+U9 -> 458.785 | AB42: =AB6+AB9 -> 685.103 | AC42: =AC6+AC9 -> 713.877 | AD42: =AD6+AD9 -> 704.303 | AE42: =AE6+AE9 -> 907.87 | AG42: =AG6+AG9 -> 742.989 | AH42: =AH6+AH9 -> 595.236 | AI42: =AI6+AI9 -> 700.024 | AJ42: =AJ6+AJ9 -> 537.135 | AL42: =AL6+AL9 -> 624.589 | AM42: =AM6+AM9 -> 652.495 | AN42: =AN6+AN9 -> 673.784 | AO42: =AO6+AO9 -> 750.185 | AQ42: =AQ6+AQ9 -> 640.233 | AR42: =AR6+AR9 -> 546.171 | AS42: =AS6+AS9 -> 784.972 | AT42: =AT6+AT9 -> 999.532 | AV42: =AV6+AV9 -> 957.831 | AW42: =AW6+AW9 -> 1003.103 | AX42: =AX6+AX9 -> 1206.451 | AY42: =AY6+AY9 -> 800.735 | BA42: =BA6+BA9 -> 850.42171 | BB42: =BB6+BB9 -> 664.74111 | BC42: =BC6+BC9 -> 500.43916 | BD42: =BD6+BD9 -> 356.45593 | BE42: =BE6+BE9 -> 597.40644 | BF42: =BF6+BF9 -> 1345.7619 | BG42: =BG6+BG9 -> 2213.7427 | BH42: =BH6+BH9 -> 3199.2948 | BI42: =BI6+BI9 -> 4299.4923
B43: Net Cash/Share | C43: =C42/C41 -> 1.6378014 | D43: =D42/D41 -> 2.2216385 | E43: =E42/E41 -> 2.3385015 | F43: =F42/F41 -> 2.0855027 | H43: =H42/H41 -> 2.9143605 | I43: =I42/I41 -> 8.1207462 | J43: =J42/J41 -> 8.0250702 | K43: =K42/K41 -> 7.2175948 | M43: =M42/M41 -> 8.0292977 | N43: =N42/N41 -> 9.0769368 | O43: =O42/O41 -> 9.252618 | P43: =P42/P41 -> 8.4254534 | R43: =R42/R41 -> 6.9427412 | S43: =S42/S41 -> 6.372995 | T43: =T42/T41 -> 8.2771704 | U43: =U42/U41 -> 8.2205581 | AB43: =AB42/AB41 -> 12.172995 | AC43: =AC42/AC41 -> 10.991441 | AD43: =AD42/AD41 -> 11.631787 | AE43: =AE42/AE41 -> 14.14121 | AG43: =AG42/AG41 -> 11.36459 | AH43: =AH42/AH41 -> 9.0219034 | AI43: =AI42/AI41 -> 10.570947 | AJ43: =AJ42/AJ41 -> 8.1825095 | AL43: =AL42/AL41 -> 9.7444061 | AM43: =AM42/AM41 -> 9.9719754 | AN43: =AN42/AN41 -> 10.937925 | AO43: =AO42/AO41 -> 12.070571 | AQ43: =AQ42/AQ41 -> 10.605128 | AR43: =AR42/AR41 -> 9.1752707 | AS43: =AS42/AS41 -> 13.495189 | AT43: =AT42/AT41 -> 15.95204 | AV43: =AV42/AV41 -> 15.862197 | AW43: =AW42/AW41 -> 16.816477 | AX43: =AX42/AX41 -> 20.31205 | AY43: =AY42/AY41 -> 13.643582 | BA43: =BA42/BA41 -> 15.439049 | BB43: =BB42/BB41 -> 12.808422 | BC43: =BC42/BC41 -> 10.202153 | BD43: =BD42/BD41 -> 7.6689836 | BE43: =BE42/BE41 -> 12.320729 | BF43: =BF42/BF41 -> 27.128742 | BG43: =BG42/BG41 -> 43.617928 | BH43: =BH42/BH41 -> 61.6099 | BI43: =BI42/BI41 -> 80.919662
B45: Revenue | C45: ='Income Statement'!H13 -> 92.54 | D45: ='Income Statement'!I13 -> 103.52 | E45: ='Income Statement'!J13 -> 111.03 | F45: ='Income Statement'!K13 -> 118.54 | H45: ='Income Statement'!M13 -> 137.775 | I45: ='Income Statement'!N13 -> 146.132 | J45: ='Income Statement'!O13 -> 155.6 | K45: ='Income Statement'!P13 -> 164.197 | M45: ='Income Statement'!R13 -> 174.29 | N45: ='Income Statement'!S13 -> 185.419 | O45: ='Income Statement'!T13 -> 196.791 | P45: ='Income Statement'!U13 -> 204.588 | R45: ='Income Statement'!W13 -> 215.987 | S45: ='Income Statement'!X13 -> 236.059 | T45: ='Income Statement'!Y13 -> 254.18 | U45: ='Income Statement'!Z13 -> 282.534 | AB45: ='Income Statement'!AB13 -> 304.112 | AC45: ='Income Statement'!AC13 -> 316.406 | AD45: ='Income Statement'!AD13 -> 320.797 | AE45: ='Income Statement'!AE13 -> 328.342 | AG45: ='Income Statement'!AG13 -> 341.597 | AH45: ='Income Statement'!AH13 -> 345.224 | AI45: ='Income Statement'!AI13 -> 345.805 | AJ45: ='Income Statement'!AJ13 -> 355.04 | AL45: ='Income Statement'!AL13 -> 374.076 | AM45: ='Income Statement'!AM13 -> 389.977 | AN45: ='Income Statement'!AN13 -> 393.841 | AO45: ='Income Statement'!AO13 -> 403.771 | AQ45: ='Income Statement'!AQ13 -> 419.776 | AR45: ='Income Statement'!AR13 -> 435.746 | AS45: ='Income Statement'!AS13 -> 444.673 | AT45: ='Income Statement'!AT13 -> 460.455 | AV45: ='Income Statement'!AV13 -> 473.651 | AW45: ='Income Statement'!AW13 -> 489.93 | AX45: ='Income Statement'!AX13 -> 505.194 | AY45: ='Income Statement'!AY13 -> 524.269 | BA45: ='Income Statement'!BA13 -> 541.82232 | BB45: ='Income Statement'!BB13 -> 563.34134 | BC45: ='Income Statement'!BC13 -> 586.52045 | BD45: ='Income Statement'!BD13 -> 612.6968
B46: Cost of Goods Sold | C46: =+'Income Statement'!H23 -> 14.329 | D46: =+'Income Statement'!I23 -> 16.29 | E46: =+'Income Statement'!J23 -> 17.287 | F46: =+'Income Statement'!K23 -> 18.022 | H46: =+'Income Statement'!M23 -> 27.965 | I46: =+'Income Statement'!N23 -> 29.35 | J46: =+'Income Statement'!O23 -> 31.875 | K46: =+'Income Statement'!P23 -> 33.339 | M46: =+'Income Statement'!R23 -> 38.404 | N46: =+'Income Statement'!S23 -> 45.226 | O46: =+'Income Statement'!T23 -> 51.77 | P46: =+'Income Statement'!U23 -> 55.653 | R46: =+'Income Statement'!W23 -> 60.439 | S46: =+'Income Statement'!X23 -> 68.613 | T46: =+'Income Statement'!Y23 -> 77.385 | U46: =+'Income Statement'!Z23 -> 100.135 | AB46: =+'Income Statement'!AB23 -> 112.331 | AC46: =+'Income Statement'!AC23 -> 117.61 | AD46: =+'Income Statement'!AD23 -> 118.472 | AE46: =+'Income Statement'!AE23 -> 124.704 | AG46: =+'Income Statement'!AG23 -> 129.676 | AH46: =+'Income Statement'!AH23 -> 129.484 | AI46: =+'Income Statement'!AI23 -> 122.68 | AJ46: =+'Income Statement'!AJ23 -> 123.468 | AL46: =+'Income Statement'!AL23 -> 124.549 | AM46: =+'Income Statement'!AM23 -> 123.565 | AN46: =+'Income Statement'!AN23 -> 124.737 | AO46: =+'Income Statement'!AO23 -> 121.766 | AQ46: =+'Income Statement'!AQ23 -> 133.04 | AR46: =+'Income Statement'!AR23 -> 137.49 | AS46: =+'Income Statement'!AS23 -> 137.787 | AT46: =+'Income Statement'!AT23 -> 139.503 | AV46: =+'Income Statement'!AV23 -> 147.805 | AW46: =+'Income Statement'!AW23 -> 149.037 | AX46: =+'Income Statement'!AX23 -> 155.454 | AY46: =+'Income Statement'!AY23 -> 165.517 | BA46: =+'Income Statement'!BA23 -> 179.7069 | BB46: =+'Income Statement'!BB23 -> 183.15036 | BC46: =+'Income Statement'!BC23 -> 185.95404 | BD46: =+'Income Statement'!BD23 -> 191.73185
B47: Days in Quarter | C47: 90 | D47: 91 | E47: 92 | F47: 92 | H47: 90 | I47: 91 | J47: 92 | K47: 92 | M47: 90 | N47: 91 | O47: 92 | P47: 92 | R47: 91 | S47: 91 | T47: 92 | U47: 92 | AB47: 91 | AC47: 91 | AD47: 92 | AE47: 92 | AG47: 91 | AH47: 91 | AI47: 92 | AJ47: 92 | AL47: 91 | AM47: 91 | AN47: 92 | AO47: 92 | AQ47: 91 | AR47: 92 | AS47: 92 | AT47: 92 | AV47: 92 | AW47: 92 | AX47: 92 | AY47: 92 | BA47: 92 | BB47: 92 | BC47: 92 | BD47: 92
B49: DSO | C49: =C10/C45*C47 -> 9.5582451 | D49: =D10/D45*D47 -> 7.6513138 | E49: =E10/E45*E47 -> 9.5604431 | F49: =F10/F45*F47 -> 8.8476464 | H49: =H10/H45*H47 -> 7.3241154 | I49: =I10/I45*I47 -> 5.4027591 | J49: =J10/J45*J47 -> 8.5170951 | K49: =K10/K45*K47 -> 7.5797731 | M49: =M10/M45*M47 -> 9.4967583 | N49: =N10/N45*N47 -> 8.9469256 | O49: =O10/O45*O47 -> 7.5739846 | P49: =P10/P45*P47 -> 7.6387862 | R49: =R10/R45*R47 -> 7.189854 | S49: =S10/S45*S47 -> 7.2589056 | T49: =T10/T45*T47 -> 8.382359 | U49: =U10/U45*U47 -> 7.7075325 | AB49: =AB10/AB45*AB47 -> 8.9515212 | AC49: =AC10/AC45*AC47 -> 8.4607688 | AD49: =AD10/AD45*AD47 -> 8.0265589 | AE49: =AE10/AE45*AE47 -> 8.5087013 | AG49: =AG10/AG45*AG47 -> 11.192885 | AH49: 8 | AI49: 8 | AJ49: 8 | AL49: 8 | AM49: 8 | AN49: 8 | AO49: 8 | AQ49: 8 | AR49: 8 | AS49: 8 | AT49: 8 | AV49: 8 | AW49: 8 | AX49: 8 | AY49: 8 | BA49: 8 | BB49: 8 | BC49: 8 | BD49: 8
B50: Days Payable | C50: =C22/C46*C47 -> 165.04501 | D50: =D22/D46*D47 -> 161.62695 | E50: =E22/E46*E47 -> 221.50888 | F50: =F22/F46*F47 -> 174.79081 | H50: =H22/H46*H47 -> 110.37833 | I50: =I22/I46*I47 -> 119.36037 | J50: =J22/J46*J47 -> 115.05845 | K50: =K22/K46*K47 -> 125.74354 | M50: =M22/M46*M47 -> 115.92152 | N50: =N22/N46*N47 -> 92.706275 | O50: =O22/O46*O47 -> 85.680664 | P50: =P22/P46*P47 -> 62.300397 | R50: =R22/R46*R47 -> 70.222026 | S50: =S22/S46*S47 -> 96.896638 | T50: =T22/T46*T47 -> 83.631608 | U50: =U22/U46*U47 -> 73.391442 | AB50: =AB22/AB46*AB47 -> 63.010843 | AC50: =AC22/AC46*AC47 -> 62.931672 | AD50: =AD22/AD46*AD47 -> 69.36964 | AE50: =AE22/AE46*AE47 -> 84.534001 | AG50: =AG22/AG46*AG47 -> 94.563481 | AH50: =+AC50 -> 62.931672 | AI50: =+AD50 -> 69.36964 | AJ50: =+AE50 -> 84.534001 | AL50: =+AG50 -> 94.563481 | AM50: =+AH50 -> 62.931672 | AN50: =+AI50 -> 69.36964 | AO50: =+AJ50 -> 84.534001 | AQ50: =+AL50 -> 94.563481 | AR50: =+AM50 -> 62.931672 | AS50: =+AN50 -> 69.36964 | AT50: =+AO50 -> 84.534001 | AV50: =+AQ50 -> 94.563481 | AW50: =+AR50 -> 62.931672 | AX50: =+AS50 -> 69.36964 | AY50: =+AT50 -> 84.534001 | BA50: =+AV50 -> 94.563481 | BB50: =+AW50 -> 62.931672 | BC50: =+AX50 -> 69.36964 | BD50: =+AY50 -> 84.534001
B52: Current ratio | C52: =(C6+C7+C9+C10)/C28 -> 0.70533274 | D52: =(D6+D7+D9+D10)/D28 -> 0.73515684 | E52: =(E6+E7+E9+E10)/E28 -> 0.77796735 | F52: =(F6+F7+F9+F10)/F28 -> 0.80938286 | H52: =(H6+H7+H9+H10)/H28 -> 0.88412639 | I52: =(I6+I7+I9+I10)/I28 -> 1.923263 | J52: =(J6+J7+J9+J10)/J28 -> 2.1859632 | K52: =(K6+K7+K9+K10)/K28 -> 2.1069646 | M52: =(M6+M7+M9+M10)/M28 -> 1.9559569 | N52: =(N6+N7+N9+N10)/N28 -> 1.863532 | O52: =(O6+O7+O9+O10)/O28 -> 1.8831724 | P52: =(P6+P7+P9+P10)/P28 -> 1.6738191 | R52: =(R6+R7+R9+R10)/R28 -> 1.4974455 | S52: =(S6+S7+S9+S10)/S28 -> 1.3658015 | T52: =(T6+T7+T9+T10)/T28 -> 1.7237558 | U52: =(U6+U7+U9+U10)/U28 -> 1.7173835 | AB52: =(AB6+AB7+AB9+AB10)/AB28 -> 1.6456485 | AC52: =(AC6+AC7+AC9+AC10)/AC28 -> 1.8394103 | AD52: =(AD6+AD7+AD9+AD10)/AD28 -> 1.7680183 | AE52: =(AE6+AE7+AE9+AE10)/AE28 -> 1.7434166 | AG52: =(AG6+AG7+AG9+AG10)/AG28 -> 1.5075545 | AH52: =(AH6+AH7+AH9+AH10)/AH28 -> 1.0069701 | AI52: =(AI6+AI7+AI9+AI10)/AI28 -> 1.0523163 | AJ52: =(AJ6+AJ7+AJ9+AJ10)/AJ28 -> 0.92866443 | AL52: =(AL6+AL7+AL9+AL10)/AL28 -> 1.0023615 | AM52: =(AM6+AM7+AM9+AM10)/AM28 -> 1.1159797 | AN52: =(AN6+AN7+AN9+AN10)/AN28 -> 1.2238923 | AO52: =(AO6+AO7+AO9+AO10)/AO28 -> 1.2912178 | AQ52: =(AQ6+AQ7+AQ9+AQ10)/AQ28 -> 1.1541687 | AR52: =(AR6+AR7+AR9+AR10)/AR28 -> 0.99285493 | AS52: =(AS6+AS7+AS9+AS10)/AS28 -> 0.70209648 | AT52: =(AT6+AT7+AT9+AT10)/AT28 -> 0.76064635 | AV52: =(AV6+AV7+AV9+AV10)/AV28 -> 0.74584548 | AW52: =(AW6+AW7+AW9+AW10)/AW28 -> 0.73983894 | AX52: =(AX6+AX7+AX9+AX10)/AX28 -> 1.5291225 | AY52: =(AY6+AY7+AY9+AY10)/AY28 -> 1.1032471 | BA52: =(BA6+BA7+BA9+BA10)/BA28 -> 0.9695884 | BB52: =(BB6+BB7+BB9+BB10)/BB28 -> 0.78869497 | BC52: =(BC6+BC7+BC9+BC10)/BC28 -> 0.61734505 | BD52: =(BD6+BD7+BD9+BD10)/BD28 -> 0.4903807
B54: Cash | AL54: =+AJ6+AJ7+AJ8+AJ9+AJ16 -> 1272.096 | AM54: =+AL6+AL7+AL8+AL9+AL16 -> 1307.879 | AN54: =+AM6+AM7+AM8+AM9+AM16 -> 933.663 | AO54: =+AN6+AN7+AN8+AN9+AN16 -> 998.115 | AQ54: =+AO6+AO7+AO8+AO9+AO16 -> 1029.825 | AR54: =+AQ6+AQ7+AQ8+AQ9+AQ16 -> 918.461 | AS54: =+AR6+AR7+AR8+AR9+AR16 -> 802.376 | AT54: =+AS6+AS7+AS8+AS9+AS16 -> 969.633 | AV54: =+AT6+AT7+AT8+AT9+AT16 -> 1113.284 | AW54: =+AV6+AV7+AV8+AV9+AV16 -> 1076.885 | AX54: =+AW6+AW7+AW8+AW9+AW16 -> 1132.255 | AY54: =+AX6+AX7+AX8+AX9+AX16 -> 1598.996 | BA54: =+AY6+AY7+AY8+AY9+AY16 -> 1660.435 | BB54: =+BA6+BA7+BA8+BA9+BA16 -> 1610.1217 | BC54: =+BB6+BB7+BB8+BB9+BB16 -> 1324.4411 | BD54: =+BC6+BC7+BC8+BC9+BC16 -> 1060.1392 | BE54: =+BD6+BD7+BD8+BD9+BD16 -> 816.15593 | BF54: =+BE6+BE7+BE8+BE9+BE16 -> 1057.1064 | BG54: =+BF6+BF7+BF8+BF9+BF16 -> 1805.4619 | BH54: =+BG6+BG7+BG8+BG9+BG16 -> 2673.4427 | BI54: =+BH6+BH7+BH8+BH9+BH16 -> 3658.9948
B55: Interest Income | AL55: =+'Income Statement'!AL46 -> 21.377 | AM55: =+'Income Statement'!AM46 -> 20.053 | AN55: =+'Income Statement'!AN46 -> 14.583 | AO55: =+'Income Statement'!AO46 -> 6.461 | AQ55: =+'Income Statement'!AQ46 -> 18.884 | AR55: =+'Income Statement'!AR46 -> 12.383 | AS55: =+'Income Statement'!AS46 -> 4.198 | AT55: =+'Income Statement'!AT46 -> 16.355 | AV55: =+'Income Statement'!AV46 -> 5.832 | AW55: =+'Income Statement'!AW46 -> -38.377 | AX55: =+'Income Statement'!AX46 -> 14.926 | AY55: =+'Income Statement'!AY46 -> 12.604 | BA55: =+BA54*BA56 -> 13.08829 | BB55: =+BB54*BB56 -> 12.691698 | BC55: =+BC54*BC56 -> 10.439836 | BD55: =+BD54*BD56 -> 8.3564899 | BE55: =+BE54*BE56 -> 25.733221 | BF55: =+BF54*BF56 -> 31.713193 | BG55: =+BG54*BG56 -> 54.163856 | BH55: =+BH54*BH56 -> 80.203281 | BI55: =+BI54*BI56 -> 109.76984
B56: Rate | AL56: =+AL55/AL54 -> 0.016804549 | AM56: =+AM55/AM54 -> 0.015332458 | AN56: =+AN55/AN54 -> 0.015619126 | AO56: =+AO55/AO54 -> 0.006473202 | AQ56: =+AQ55/AQ54 -> 0.018337096 | AR56: =+AR55/AR54 -> 0.013482336 | AS56: =+AS55/AS54 -> 0.0052319611 | AT56: =+AT55/AT54 -> 0.016867206 | AV56: =+AV55/AV54 -> 0.0052385555 | AW56: =+AW55/AW54 -> -0.035637046 | AX56: =+AX55/AX54 -> 0.013182543 | AY56: =+AY55/AY54 -> 0.0078824462 | BA56: =+AY56 -> 0.0078824462 | BB56: =+BA56 -> 0.0078824462 | BC56: =+BB56 -> 0.0078824462 | BD56: =+BC56 -> 0.0078824462 | BE56: =+BD56*4 -> 0.031529785 | BF56: 0.03 | BG56: =BF56 -> 0.03 | BH56: =BG56 -> 0.03 | BI56: =BH56 -> 0.03
AV58: =+SUM(AV55:AY55) -> -5.015

Sheet Cash Flow
C3: ='Income Statement'!H2 -> Mar | D3: ='Income Statement'!I2 -> Jun | E3: ='Income Statement'!J2 -> Sep | F3: ='Income Statement'!K2 -> Dec | H3: ='Income Statement'!M2 -> Mar | I3: ='Income Statement'!N2 -> Jun | J3: ='Income Statement'!O2 -> Sep | K3: ='Income Statement'!P2 -> Dec | M3: ='Income Statement'!R2 -> Mar | N3: ='Income Statement'!S2 -> Jun | O3: ='Income Statement'!T2 -> Sep | P3: ='Income Statement'!U2 -> Dec | R3: ='Income Statement'!W2 -> Mar | S3: ='Income Statement'!X2 -> Jun | T3: ='Income Statement'!Y2 -> Sep | U3: ='Income Statement'!Z2 -> Dec | AB3: ='Income Statement'!AB2 -> Mar | AC3: ='Income Statement'!AC2 -> Jun | AD3: ='Income Statement'!AD2 -> Sep | AE3: ='Income Statement'!AE2 -> Dec | AG3: ='Income Statement'!AG2 -> Mar | AH3: ='Income Statement'!AH2 -> Jun | AI3: ='Income Statement'!AI2 -> Sep | AJ3: ='Income Statement'!AJ2 -> Dec | AL3: ='Income Statement'!AL2 -> Mar | AM3: ='Income Statement'!AM2 -> Jun | AN3: ='Income Statement'!AN2 -> Sep | AO3: ='Income Statement'!AO2 -> Dec | AQ3: ='Income Statement'!AQ2 -> Mar | AR3: ='Income Statement'!AR2 -> Jun | AS3: ='Income Statement'!AS2 -> Sep | AT3: ='Income Statement'!AT2 -> Dec | AV3: ='Income Statement'!AV2 -> Mar | AW3: ='Income Statement'!AW2 -> Jun | AX3: ='Income Statement'!AX2 -> Sep | AY3: ='Income Statement'!AY2 -> Dec | BA3: ='Income Statement'!BA2 -> Mar | BB3: ='Income Statement'!BB2 -> Jun | BC3: ='Income Statement'!BC2 -> Sep | BD3: ='Income Statement'!BD2 -> Dec
B4: (Amounts in millions, except per share data) | C4: ='Income Statement'!H3 -> 1Q17 | D4: ='Income Statement'!I3 -> 2Q17 | E4: ='Income Statement'!J3 -> 3Q17 | F4: ='Income Statement'!K3 -> 4Q17 | G4: ='Income Statement'!L3 -> 2017 | H4: ='Income Statement'!M3 -> 1Q18 | I4: ='Income Statement'!N3 -> 2Q18 | J4: ='Income Statement'!O3 -> 3Q18 | ... V4: ='Income Statement'!AA3 -> 2020 | AB4: ='Income Statement'!AB3 -> 1Q21 | AC4: ='Income Statement'!AC3 -> 2Q21 | AD4: ='Income Statement'!AD3 -> 3Q21 | AE4: ='Income Statement'!AE3 -> 4Q21 | AF4: ='Income Statement'!AF3 -> 2021 | AG4: ='Income Statement'!AG3 -> 1Q22 | AH4: ='Income Statement'!AH3 -> 2Q22 | AI4: ='Income Statement'!AI3 -> 3Q22 | ... BJ4: ='Income Statement'!BJ3 -> 2031E
B5: Operating Activities
B6: Net Income | C6: -20.885 | D6: -14.264 | E6: -14.519 | F6: -6.65 | G6: =SUM(C6:F6) -> -56.318 | H6: -19.811 | I6: -5.64 | J6: -5.916 | K6: -5.753 | L6: =SUM(H6:K6) -> -37.12 | M6: -30.74 | N6: -16.734 | O6: -17.367 | P6: -21.573 | Q6: =SUM(M6:P6) -> -86.414 | R6: -39.153 | S6: -57.736 | T6: -56.842 | U6: -62.789 | V6: =SUM(R6:U6) -> -216.52 | AB6: -121.752 | AC6: 37.957 | AD6: 16.667 | AE6: -111.019 | AF6: =SUM(AB6:AE6) -> -178.147 | AG6: -227.289 | AH6: -111.238 | AI6: -47.361 | AJ6: -38.975 | AK6: =SUM(AG6:AJ6) -> -424.863 | AL6: -10.369 | AM6: 33.577 | AN6: 6.975 | AO6: 2.954 | AP6: =SUM(AL6:AO6) -> 33.137 | AQ6: 24.002 | AR6: 39.518 | AS6: 26.778 | AT6: 48.024 | AU6: =SUM(AQ6:AT6) -> 138.322 | AV6: 33.766 | AW6: 57.703 | AX6: -0.589 | AY6: -40.234 | AZ6: =SUM(AV6:AY6) -> 50.646 | BA6: ='Income Statement'!BA52 -> -7.6978986 | BB6: ='Income Statement'!BB52 -> 7.7650079 | BC6: ='Income Statement'!BC52 -> 29.016398 | BD6: ='Income Statement'!BD52 -> 50.80366 | BE6: =SUM(BA6:BD6) -> 79.887167 | BF6: ='Income Statement'!BF52 -> 243.38245 | BG6: ='Income Statement'!BG52 -> 372.98227 | BH6: ='Income Statement'!BH52 -> 509.93682 | BI6: ='Income Statement'!BI52 -> 640.93601 | BJ6: ='Income Statement'!BJ52 -> 765.88006
B7: Depreciation and Amortization | C7: =1.297+0.32 -> 1.617 | D7: =1.346+1.142 -> 2.488 | E7: =1.451+0.95 -> 2.401 | F7: =1.56-0.341 -> 1.219 | G7: =SUM(C7:F7) -> 7.725 | H7: =1.897+0.588 -> 2.485 | I7: =2.196+0.731 -> 2.927 | J7: =2.213+0.733 -> 2.946 | K7: =2.418+0.732 -> 3.15 | L7: =SUM(H7:K7) -> 11.508 | M7: =2.658+0.732 -> 3.39 | N7: =2.927+0.738 -> 3.665 | O7: =3.194+0.733 -> 3.927 | P7: =3.347+2.385 -> 5.732 | Q7: =SUM(M7:P7) -> 16.714 | R7: =3.572+0.566 -> 4.138 | S7: =3.537+0.566 -> 4.103 | T7: =3.712+0.826 -> 4.538 | U7: =3.789+0.619 -> 4.408 | V7: =SUM(R7:U7) -> 17.187 | AB7: =3.432+0.599 -> 4.031 | AC7: =3.378+0.846 -> 4.224 | AD7: =3.595+3.045 -> 6.64 | AE7: =3.524+0.462 -> 3.986 | AF7: =SUM(AB7:AE7) -> 18.881 | AG7: =3.535+1.574 -> 5.109 | AH7: =4.022+1.58 -> 5.602 | AI7: =3.845+1.581 -> 5.426 | AJ7: =5.209+1.511 -> 6.72 | AK7: =SUM(AG7:AJ7) -> 22.857 | AL7: =4.922+1.488 -> 6.41 | AM7: =4.497+1.489 -> 5.986 | AN7: =4.348+1.489 -> 5.837 | AO7: =6.725+1.489 -> 8.214 | AP7: =SUM(AL7:AO7) -> 26.447 | AQ7: =6.442+1.483 -> 7.925 | AR7: =6.427+1.465 -> 7.892 | AS7: =6.099+1.461 -> 7.56 | AT7: =6.278+1.46 -> 7.738 | AU7: =SUM(AQ7:AT7) -> 31.115 | AV7: =6.137+1.461 -> 7.598 | AW7: =6.099+1.246 -> 7.345 | AX7: =6.19+1.37 -> 7.56 | AY7: =6.065+2.885 -> 8.95 | AZ7: =SUM(AV7:AY7) -> 31.453 | BA7: =+'Income Statement'!BA34+'Income Statement'!BA41 -> 8.988 | BB7: =+'Income Statement'!BB34+'Income Statement'!BB41 -> 8.988 | BC7: =+'Income Statement'!BC34+'Income Statement'!BC41 -> 8.988 | BD7: =+'Income Statement'!BD34+'Income Statement'!BD41 -> 8.988 | BE7: =SUM(BA7:BD7) -> 35.952 | BF7: =+'Income Statement'!BF34+'Income Statement'!BF41 -> 35.952 | BG7: =+'Income Statement'!BG34+'Income Statement'!BG41 -> 35.952 | BH7: =+'Income Statement'!BH34+'Income Statement'!BH41 -> 35.952 | BI7: =+'Income Statement'!BI34+'Income Statement'!BI41 -> 35.952 | BJ7: =+'Income Statement'!BJ34+'Income Statement'!BJ41 -> 35.952
B8: Stock-Based Comp | C8: 8.982 | D8: 11.98 | E8: 13.035 | F8: 13.704 | G8: =SUM(C8:F8) -> 47.701 | H8: 15.674 | I8: 17.769 | J8: 18.76 | K8: 20.127 | L8: =SUM(H8:K8) -> 72.33 | M8: 24.907 | N8: 27.565 | O8: 28.392 | P8: 28.473 | Q8: =SUM(M8:P8) -> 109.337 | R8: 30.718 | S8: 34.967 | T8: 38.922 | U8: 42.706 | V8: =SUM(R8:U8) -> 147.313 | AB8: 46.631 | AC8: 50.396 | AD8: 53.07 | AE8: 71.924 | AF8: =SUM(AB8:AE8) -> 222.021 | AG8: 60.984 | AH8: 59.139 | AI8: 56.796 | AJ8: 59.917 | AK8: =SUM(AG8:AJ8) -> 236.836 | AL8: 54.521 | AM8: 53.66 | AN8: 58.249 | AO8: 58.195 | AP8: =SUM(AL8:AO8) -> 224.625 | AQ8: 58.142 | AR8: 59.886 | AS8: 60.892 | AT8: 61.801 | AU8: =SUM(AQ8:AT8) -> 240.721 | AV8: 60.261 | AW8: 59.439 | AX8: 59.565 | AY8: 58.111 | AZ8: =SUM(AV8:AY8) -> 237.376 | BA8: =+AV8*1.01 -> 60.86361 | BB8: =+AW8*1.01 -> 60.03339 | BC8: =+AX8*1.01 -> 60.16065 | BD8: =+AY8*1.01 -> 58.69211 | BE8: =SUM(BA8:BD8) -> 239.74976 | BF8: =+BE8*1.01 -> 242.14726 | BG8: =+BF8*1.01 -> 244.56873 | BH8: =+BG8*1.01 -> 247.01442 | BI8: =+BH8*1.01 -> 249.48456 | BJ8: =+BI8*1.01 -> 251.97941
B9: Amortization of debt discount | C9: 0 | D9: 0 | E9: 0 | F9: 0 | G9: =SUM(C9:F9) -> 0 | H9: 0 | I9: 0 | J9: 4.965 | K9: 5.039 | L9: =SUM(H9:K9) -> 10.004 | M9: 5.117 | N9: 5.194 | O9: 5.274 | P9: 5.353 | Q9: =SUM(M9:P9) -> 20.938 | R9: 5.433 | S9: 5.516 | T9: 7.594 | U9: 11.411 | V9: =SUM(R9:U9) -> 29.954 | AB9: 62.345 | AC9: 1.296 | AD9: 1.297 | AE9: 1.298 | AF9: =SUM(AB9:AE9) -> 66.236 | AG9: 1.301 | AH9: 1.302 | AI9: 1.305 | AJ9: 1.305 | AK9: =SUM(AG9:AJ9) -> 5.213 | AL9: 1.308 | AM9: 1.31 | AN9: 0.787 | AO9: 0.789 | AP9: =SUM(AL9:AO9) -> 4.194 | AQ9: 0.79 | AR9: 0.791 | AS9: 0.792 | AT9: 0.793 | AU9: =SUM(AQ9:AT9) -> 3.166 | AV9: 0.794 | AW9: 0.795 | AX9: 0.959 | AY9: 1.283 | AZ9: =SUM(AV9:AY9) -> 3.831 | BA9: =AY9 -> 1.283 | BB9: =BA9 -> 1.283 | BC9: =BB9 -> 1.283 | BD9: =BC9 -> 1.283 | BE9: =SUM(BA9:BD9) -> 5.132 | BF9: =+BE9*0.9 -> 4.6188 | BG9: =+BF9*0.9 -> 4.15692 | BH9: =+BG9*0.9 -> 3.741228 | BI9: =+BH9*0.9 -> 3.3671052 | BJ9: =+BI9*0.9 -> 3.0303947
B10: Decrease (increase) in accrued int and FX rate on deposits | C10: -0.114 | D10: -0.053 | E10: 0.007 | F10: -0.395 | G10: =SUM(C10:F10) -> -0.555 | H10: -0.352 | I10: -0.545 | J10: 0.493 | K10: 0.807 | L10: =SUM(H10:K10) -> 0.403 | M10: 0.489 | N10: 0.105 | O10: 0.137 | P10: 0.017 | Q10: =SUM(M10:P10) -> 0.748 | R10: 0.047 | S10: 0.015 | T10: -0.036 | U10: -0.069 | V10: =SUM(R10:U10) -> -0.043 | AB10: 0.015 | AC10: -0.063 | AD10: -0.057 | AE10: 0.085 | AF10: =SUM(AB10:AE10) -> -0.02 | AG10: 0.045 | AH10: -0.21 | AI10: 0.172 | AJ10: -0.093 | AK10: =SUM(AG10:AJ10) -> -0.086 | AL10: =20.834-0.025 -> 20.809 | AM10: =0.133+0.33 -> 0.463 | AN10: -1.937 | AO10: -0.586 | AP10: =SUM(AL10:AO10) -> 18.749 | AQ10: 0.88 | AR10: 0.89 | AS10: -0.283 | AT10: -0.635 | AU10: =SUM(AQ10:AT10) -> 0.852 | AV10: -0.224 | AW10: 0.126 | AX10: -0.504 | AY10: 0.294 | AZ10: =SUM(AV10:AY10) -> -0.308 | BA10: 0 | BB10: 0 | BC10: 0 | BD10: 0 | BE10: =SUM(BA10:BD10) -> 0 | BF10: 0 | BG10: 0 | BH10: 0 | BI10: 0 | BJ10: 0
B11: Non-cash impairment, restructuring, and other | AO11: 3.567 | AP11: =SUM(AL11:AO11) -> 3.567 | AQ11: =5.024-3.652+0.553 -> 1.925 | AR11: 0 | AS11: 0 | AT11: 0 | AV11: 0 | AW11: 0 | AX11: 0 | AY11: 0
B12: Amortization of premium and discount on marketable securities | C12: 0 | D12: 0 | E12: 0 | F12: -0.077 | G12: =SUM(C12:F12) -> -0.077 | H12: 0 | I12: 0 | J12: 0.074 | K12: -0.185 | L12: =SUM(H12:K12) -> -0.111 | M12: 0.051 | N12: 0 | O12: -0.14 | P12: -0.247 | Q12: =SUM(M12:P12) -> -0.336 | R12: 0.279 | S12: 0.438 | T12: 1.222 | U12: 2.532 | V12: =SUM(R12:U12) -> 4.471 | AB12: 2.323 | AC12: 2.082 | AD12: 1.796 | AE12: 1.642 | AF12: =SUM(AB12:AE12) -> 7.843 | AG12: 1.549 | AH12: 1.256 | AI12: 1 | AJ12: 2.447 | AK12: =SUM(AG12:AJ12) -> 6.252 | AL12: 0.54 | AM12: 4.132 | AN12: =1.968-0.563 -> 1.405 | AO12: 4.237 | AP12: =SUM(AL12:AO12) -> 10.314 | AQ12: 0.597 | AR12: 3.937 | AS12: -10.077 | AT12: -7.838 | AU12: =SUM(AQ12:AT12) -> -13.381 | AV12: 3.557 | AW12: -24.409 | AX12: -5.65 | AY12: -14.741 | AZ12: =SUM(AV12:AY12) -> -41.243 | BA12: 0 | BB12: 0 | BC12: 0 | BD12: 0 | BE12: =SUM(BA12:BD12) -> 0 | BF12: 0 | BG12: 0 | BH12: 0 | BI12: 0 | BJ12: 0
B13: Gain on equity securities | R13: 0 | S13: 0 | T13: 0 | U13: 0 | V13: =SUM(R13:U13) -> 0 | AB13: 0 | AC13: -73.186 | AD13: -110.855 | AE13: 17.718 | AF13: =SUM(AB13:AE13) -> -166.323 | AG13: 151.645 | AH13: 54.92 | AI13: -10.182 | AJ13: 3.955 | AK13: =SUM(AG13:AJ13) -> 200.338 | AL13: -13.898 | AM13: -8.814 | AN13: 2.4 | AO13: -10.296 | AP13: =SUM(AL13:AO13) -> -30.608 | AQ13: -3.367 | AR13: 0 | AS13: 0 | AT13: 0 | AU13: =SUM(AQ13:AT13) -> -3.367 | AV13: 0 | AW13: 0 | AX13: -0.042 | AY13: =1.49-0.068 -> 1.422 | AZ13: =SUM(AV13:AY13) -> 1.38 | BA13: 0 | BB13: 0 | BC13: 0 | BD13: 0 | BE13: =SUM(BA13:BD13) -> 0 | BF13: 0 | BG13: 0 | BH13: 0 | BI13: 0 | BJ13: 0
B14: Deferred income taxes, net | C14: -0.213 | D14: -0.184 | E14: 0 | F14: -2.278 | G14: =SUM(C14:F14) -> -2.675 | H14: -0.098 | I14: -0.307 | J14: -0.341 | K14: -0.213 | L14: =SUM(H14:K14) -> -0.959 | M14: 0.131 | N14: 0.402 | O14: -0.346 | P14: 0.748 | Q14: =SUM(M14:P14) -> 0.935 | R14: -1.666 | S14: -0.055 | T14: -1.696 | U14: 0.163 | V14: =SUM(R14:U14) -> -3.254 | AB14: 7.351 | AC14: 32.752 | AD14: 21.111 | AE14: -6.76 | AF14: =SUM(AB14:AE14) -> 54.454 | AG14: -35.575 | AH14: -12.644 | AI14: 2.351 | AJ14: -11.997 | AK14: =SUM(AG14:AJ14) -> -57.865 | AL14: -4.144 | AM14: -6.318 | AN14: 3.713 | AO14: -2.035 | AP14: =SUM(AL14:AO14) -> -8.784 | AQ14: -5.011 | AR14: -0.208 | AS14: 0.03 | AT14: -0.007 | AU14: =SUM(AQ14:AT14) -> -5.196 | AV14: 0.001 | AW14: -64.817 | AX14: -2.097 | AY14: -24.829 | AZ14: =SUM(AV14:AY14) -> -91.742 | BA14: 0 | BB14: 0 | BC14: 0 | BD14: 0 | BE14: =SUM(BA14:BD14) -> 0 | BF14: 0 | BG14: 0 | BH14: 0 | BI14: 0 | BJ14: 0
B15: Changes in Working Capital | C15: =16.397-SUM(C6:C14) -> 27.01 | D15: =19.651-SUM(D6:D14) -> 19.684 | E15: =22.063-SUM(E6:E14) -> 21.139 | F15: =24.91-SUM(F6:F14) -> 19.387 | G15: =SUM(C15:F15) -> 87.22 | H15: =24.779-SUM(H6:H14) -> 26.881 | I15: =27.268-SUM(I6:I14) -> 13.064 | J15: =27.607-SUM(J6:J14) -> 6.626 | K15: =36.055-SUM(K6:K14) -> 13.083 | L15: =SUM(H15:K15) -> 59.654 | M15: =35.074-SUM(M6:M14) -> 31.729 | N15: =37.18-SUM(N6:N14) -> 16.983 | O15: =36.073-SUM(O6:O14) -> 16.196 | P15: =18.225-15.376-0.956+7.656-11.166-4.563+22.095+6.819 -> 22.734 | Q15: =SUM(M15:P15) -> 87.642 | R15: =4.288-5.229+0.148-14.674+8.802+12.109+32.871+6.916 -> 45.231 | S15: =5.158-4.588-1.765-6.931+26.172+11.585+29.792+3.287 -> 62.71 | T15: =3.907-3.377-4.329-7.183-3.331+14.014+26.761+4.35 -> 30.812 | U15: =4.514-2.613-0.511+6.111+10.324-12.382+23.847+0.898 -> 30.188 | V15: =SUM(R15:U15) -> 168.941 | AB15: =4.681-6.035-6.176-73.916-3.262+40.554+46.997+14.701 -> 17.544 | AC15: =8.379-7.578+0.875-30.304+2.234-27.407+21.81-1.634 -> -33.625 | AD15: =SUM(5.907,-6.062,1.43,-0.652,6.727,-0.628,5.336,2.596) -> 14.654 | AE15: =9.474-7.013-2.379+3.029+20.896+6.872+11.593+0.325-0.63 -> 42.167 | AF15: =SUM(AB15:AE15) -> 40.74 | AG15: =8.838-9.647-11.649-12.313+21.686-4.74+37.552-1.158 -> 28.569 | AH15: =9.737-15.525+1.216-15.032-9.573-0.324+7.731+20.974 -> -0.796 | AI15: =8.141-8.675+5.004-5.28-7.96-9.562+6.023+3.069 -> -9.24 | AJ15: =18.724-11.204-6.29+26.713-22.667+17.506+4.081+3.092 -> 29.955 | AK15: =SUM(AG15:AJ15) -> 48.488 | AL15: =5.796-8.121-10.474-10.858-41.67-10.042+60.975+5.178 -> -9.216 | AM15: =5.356-26.208-0.708+8-11.301-17.932+12.043-5.485 -> -36.235 | AN15: =8.905-13.705-1.332-6.402-14.604+6.749+0.387+6.717 -> -13.285 | AO15: =1.492+11.517+-2.794-1.123+16.262-8.307+2.788+5.505 -> 25.34 | AP15: =SUM(AL15:AO15) -> -33.396 | AQ15: =1.119-12.568-2.123-2.429+41.319+2.635 -> 27.953 | AR15: =5.286-7.86+1.598+0.491-28.195-14.502+13.69+25.426+11.389 -> 7.323 | AS15: =9.585-18.753-0.716+5.56+27.484+12.189+7.758+6.096-5.081 -> 44.122 | AT15: =4.351-2.821+2.471+4.058-63.684+17.329+66.407+1.609-5.86 -> 23.86 | AU15: =SUM(AQ15:AT15) -> 103.258 | AV15: =4.803-8.763-2.006-2.654+58.289-9.338-64.148+44.362+19.193 -> 39.738 | AW15: =4.8+34.062-3.832-7.956-6.09-12.581+21.409+26.211+58.13 -> 114.153 | AX15: =4.842+10.736-11.876+0.666-16.673+6.907+11.326+18.316+45.253 -> 69.497 | AY15: =5.476+9.414-0.511+13.163+3.478+41.974-1.542+14.985+81.64 -> 168.077 | AZ15: =SUM(AV15:AY15) -> 391.465 | BA15: 37.5 | BB15: 37.5 | BC15: 37.5 | BD15: 37.5 | BE15: =SUM(BA15:BD15) -> 150 | BF15: 120 | BG15: =+BF15*0.8 -> 96 | BH15: =+BG15*0.8 -> 76.8 | BI15: =+BH15*0.8 -> 61.44 | BJ15: =+BI15*0.8 -> 49.152
B16: Cash from Operations | C16: =SUM(C6:C15) -> 16.397 | D16: =SUM(D6:D15) -> 19.651 | E16: =SUM(E6:E15) -> 22.063 | F16: =SUM(F6:F15) -> 24.91 | G16: =SUM(G6:G15) -> 83.021 | H16: =SUM(H6:H15) -> 24.779 | I16: =SUM(I6:I15) -> 27.268 | J16: =SUM(J6:J15) -> 27.607 | ... V16: =SUM(V6:V15) -> 148.049 | AB16: =SUM(AB6:AB15) -> 18.488 | AC16: =SUM(AC6:AC15) -> 21.833 | AD16: =SUM(AD6:AD15) -> 4.323 | AE16: =SUM(AE6:AE15) -> 21.041 | AF16: =SUM(AF6:AF15) -> 65.685 | AG16: =SUM(AG6:AG15) -> -13.662 | AH16: =SUM(AH6:AH15) -> -2.669 | AI16: =SUM(AI6:AI15) -> 0.267 | ... AY16: =SUM(AY6:AY15) -> 158.333 | AZ16: =SUM(BA6:BA15) -> 100.93671 | BA16: =SUM(BA6:BA15) -> 100.93671 | BB16: =SUM(BB6:BB15) -> 115.5694 | BC16: =SUM(BC6:BC15) -> 136.94805 | BD16: =SUM(BD6:BD15) -> 157.26677 | BE16: =SUM(BE6:BE15) -> 510.72093 | BF16: =SUM(BF6:BF15) -> 646.10051 | BG16: =SUM(BG6:BG15) -> 753.65992 | BH16: =SUM(BH6:BH15) -> 873.44446 | ... BJ16: =SUM(BJ6:BJ15) -> 1105.9939
B18: Investing activies
B19: Proceeds (investments) from/in deposits | C19: =16.386-10.65 -> 5.736 | D19: =16.664-5 -> 11.664 | E19: =17.392-41 -> -23.608 | F19: =1.869-32.056 -> -30.187 | G19: =SUM(C19:F19) -> -36.395 | H19: =13.774-26.779 -> -13.005 | I19: =5.337-125.001 -> -119.664 | J19: =96.015-172.999 -> -76.984 | K19: =88.999-113.2 -> -24.201 | L19: =SUM(H19:K19) -> -233.854 | M19: =26.775-26 -> 0.775 | N19: 55 | O19: =164-175 -> -11 | P19: =103-93 -> 10 | Q19: =SUM(M19:P19) -> 54.775 | R19: =17-89 -> -72 | S19: =9.225-49 -> -39.775 | T19: =175-309.21 -> -134.21 | U19: =93-129.79 -> -36.79 | V19: =SUM(R19:U19) -> -282.775 | AB19: =138.015-0.602 -> 137.413 | AC19: =40-171.529 -> -131.529 | AD19: =269-245 -> 24 | AE19: =285-155.5 -> 129.5 | AF19: =SUM(AB19:AE19) -> 159.384 | AG19: =105-150 -> -45 | AH19: =126.259-240.972 -> -114.713 | AI19: =105.171-57.18 -> 47.991 | AJ19: =308.379-317.869 -> -9.49 | AK19: =SUM(AG19:AJ19) -> -121.212 | AL19: =56.091-58.98 -> -2.889 | AM19: =367.61-4.48 -> 363.13 | AN19: 70.04 | AO19: 131.754 | AP19: =SUM(AL19:AO19) -> 562.035 | AQ19: =0.823-30.162 -> -29.339 | AR19: =0.162-0.011 -> 0.151 | AS19: =178.661-114.619 -> 64.042 | AT19: =97.051-25.54 -> 71.511 | AU19: =SUM(AQ19:AT19) -> 106.365 | AV19: =107.78-112.81 -> -5.03 | AW19: -10.458 | AX19: =70.649-87.032 -> -16.383 | AY19: 10.046 | AZ19: =SUM(AV19:AY19) -> -21.825 | BA19: 0 | BB19: 0 | BC19: 0 | BD19: 0 | BE19: =SUM(BA19:BD19) -> 0 | BF19: 0 | BG19: 0 | BH19: 0 | BI19: 0 | BJ19: 0
B20: Proceeds (investments) from/in marketable securities | C20: 0 | D20: 0 | E20: 0 | F20: =-33.189+0.245 -> -32.944 | G20: =SUM(C20:F20) -> -32.944 | H20: =-3.403+2.94 -> -0.463 | I20: =-11.576+11.496 -> -0.08 | J20: =-37.678+1.357 -> -36.321 | K20: =-6.306+5.261 -> -1.045 | L20: =SUM(H20:K20) -> -37.909 | M20: =-27.923+7.455 -> -20.468 | N20: =-108.693+21.601 -> -87.092 | O20: =-127.967+32.246 -> -95.721 | P20: =-138.191+71.603 -> -66.588 | Q20: =SUM(M20:P20) -> -269.869 | R20: =-129.301+89.255 -> -40.046 | S20: =-100.867+65.656 -> -35.211 | T20: =-468.473+45.104 -> -423.369 | U20: =-64.94+77.32 -> 12.38 | V20: =SUM(R20:U20) -> -486.246 | AB20: =90.097 -> 90.097 | AC20: =90.562 -> 90.562 | AD20: 80.909 | AE20: =-29.377+50.633 -> 21.256 | AF20: =SUM(AB20:AE20) -> 282.824 | AG20: =-72.155+61.38 -> -10.775 | AH20: =-92.408+78.87 -> -13.538 | AI20: =-38.048+51.619 -> 13.571 | AJ20: 98.244 | AK20: =SUM(AG20:AJ20) -> 87.502 | AL20: =58.39 -> 58.39 | AM20: 115.979 | AN20: =+-134.732-4.125+42.901 -> -95.956 | AO20: =-99.725-0.837+31.92 -> -68.642 | AP20: =SUM(AL20:AO20) -> 9.771 | AQ20: =-27.847+52.805 -> 24.958 | AR20: =-163.698+38.35 -> -125.348 | AS20: =-75.664+19.021 -> -56.643 | AT20: 15 | AU20: =SUM(AQ20:AT20) -> -142.033 | AV20: =-27.693+58.292 -> 30.599 | AW20: =20.7-163.313+162.525 -> 19.912 | AX20: =-345+8.51+87.032 -> -249.458 | AY20: =-10.027-639.888+9.111 -> -640.804 | AZ20: =SUM(AV20:AY20) -> -839.751 | BA20: =-('Balance Sheet'!BA16+'Balance Sheet'!BA9-'Balance Sheet'!AY9-'Balance Sheet'!AY16) -> 200 | BB20: =-('Balance Sheet'!BB16+'Balance Sheet'!BB9-'Balance Sheet'!BA9-'Balance Sheet'!BA16) -> 200 | BC20: =-('Balance Sheet'!BC16+'Balance Sheet'!BC9-'Balance Sheet'!BB9-'Balance Sheet'!BB16) -> 200 | BD20: =-('Balance Sheet'!BD16+'Balance Sheet'!BD9-'Balance Sheet'!BC9-'Balance Sheet'!BC16) -> 200 | BE20: =SUM(BA20:BD20) -> 800 | BF20: 0 | BG20: 0 | BH20: 0 | BI20: 0 | BJ20: 0
B21: Purchase of PPE | C21: -1.616 | D21: -2.239 | E21: -3.128 | F21: -5.269 | G21: =SUM(C21:F21) -> -12.252 | H21: -3.211 | I21: -3.296 | J21: -3.865 | K21: -3.312 | L21: =SUM(H21:K21) -> -13.684 | M21: -4.83 | N21: -6.235 | O21: -6.712 | P21: -3.65 | Q21: =SUM(M21:P21) -> -21.427 | R21: -4.943 | S21: -3.264 | T21: -4.928 | U21: -5.268 | V21: =SUM(R21:U21) -> -18.403 | AB21: -3.72 | AC21: -6.657 | AD21: -12.604 | AE21: -12.789 | AF21: =SUM(AB21:AE21) -> -35.77 | AG21: -19.283 | AH21: -12.629 | AI21: =-22.208 -> -22.208 | AJ21: -14.434 | AK21: =SUM(AG21:AJ21) -> -68.554 | AL21: -19.574 | AM21: -15.175 | AN21: -18.69 | AO21: -9.581 | AP21: =SUM(AL21:AO21) -> -63.02 | AQ21: -7.715 | AR21: -6.871 | AS21: -1.665 | AT21: -1.562 | AU21: =SUM(AQ21:AT21) -> -17.813 | AV21: -2.629 | AW21: -2.265 | AX21: -1.144 | AY21: -2.515 | AZ21: =SUM(AV21:AY21) -> -8.553 | BA21: =+BA41-BA22 -> 0.25 | BB21: =+BB41-BB22 -> 0.25 | BC21: =+BC41-BC22 -> 0.25 | BD21: =+BD41-BD22 -> 0.25 | BE21: =SUM(BA21:BD21) -> 1 | BF21: =+BF41-BF22 -> 0.85 | BG21: =+BG41-BG22 -> 0.6955 | BH21: =+BH41-BH22 -> 0.536365 | BI21: =+BI41-BI22 -> 0.37245595 | BJ21: =+BJ41-BJ22 -> 0.20362963
B22: Capitalized website/software | C22: 0 | D22: 0 | E22: 0 | F22: -0.117 | G22: =SUM(C22:F22) -> -0.117 | H22: -0.147 | I22: -0.115 | J22: -0.051 | K22: -0.079 | L22: =SUM(H22:K22) -> -0.392 | M22: -0.198 | N22: -0.191 | O22: -0.134 | P22: -0.116 | Q22: =SUM(M22:P22) -> -0.639 | R22: -0.132 | S22: 0 | T22: -0.206 | U22: -0.112 | V22: =SUM(R22:U22) -> -0.45 | AB22: -0.129 | AC22: -0.462 | AD22: -0.426 | AE22: -0.913 | AF22: =SUM(AB22:AE22) -> -1.93 | AG22: -0.641 | AH22: -0.588 | AI22: -0.666 | AJ22: -0.215 | AK22: =SUM(AG22:AJ22) -> -2.11 | AL22: -1.358 | AM22: -0.576 | AN22: -0.686 | AO22: -0.408 | AP22: =SUM(AL22:AO22) -> -3.028 | AQ22: -0.41 | AR22: -0.325 | AS22: -0.388 | AT22: -0.401 | AU22: =SUM(AQ22:AT22) -> -1.524 | AV22: -0.421 | AW22: -0.405 | AX22: -0.273 | AY22: -0.249 | AZ22: =SUM(AV22:AY22) -> -1.348 | BA22: -1.5 | BB22: -1.5 | BC22: -1.5 | BD22: -1.5 | BE22: =SUM(BA22:BD22) -> -6 | BF22: -6 | BG22: -6 | BH22: -6 | BI22: -6 | BJ22: -6
B23: Payment for business acquired, net of cash | R23: 0 | S23: 0 | T23: 0 | U23: 0 | V23: =SUM(R23:U23) -> 0 | AB23: 0 | AC23: -37.217 | AD23: 0.189 | AE23: -0.115 | AF23: =SUM(AB23:AE23) -> -37.143 | AG23: 0 | AH23: 0 | AI23: 0 | AJ23: 0 | AK23: =SUM(AG23:AJ23) -> 0 | AL23: 0 | AM23: 0 | AN23: 0 | AO23: 0 | AP23: =SUM(AL23:AO23) -> 0 | AQ23: 0 | AR23: -0.46 | AS23: -1.15 | AT23: -1 | AU23: =SUM(AQ23:AT23) -> -2.61 | AV23: -0.75 | AW23: -18.545 | AX23: -1.95 | AY23: -5.335 | AZ23: =SUM(AV23:AY23) -> -26.58 | BA23: 0 | BB23: 0 | BC23: 0 | BD23: 0 | BE23: =SUM(BA23:BD23) -> 0 | BF23: 0 | BG23: 0 | BH23: 0 | BI23: 0 | BJ23: 0
B24: Other investing | C24: -29.834 | D24: -3.257 | E24: 0 | F24: -0.075 | G24: =SUM(C24:F24) -> -33.166 | H24: 0 | I24: -0.5 | J24: 0 | K24: -1.25 | L24: =SUM(H24:K24) -> -1.75 | M24: 0 | N24: -2.8 | O24: -0.262 | P24: =-0.191-3.6 -> -3.791 | Q24: =SUM(M24:P24) -> -6.853 | R24: =-3.5-6.626-1.5-0.1 -> -11.726 | S24: =-0.643-0.685 -> -1.328 | T24: 0 | U24: =1.098-0.4 -> 0.698 | V24: =SUM(R24:U24) -> -12.356 | AB24: -5.586 | AC24: -1.5 | AD24: =18.771-2 -> 16.771 | AE24: -0.181 | AF24: =SUM(AB24:AE24) -> 9.504 | AG24: =-0.16+3.193 -> 3.033 | AH24: -1 | AI24: =-0.58-0.1 -> -0.68 | AJ24: =48.403-0.04 -> 48.363 | AK24: =SUM(AG24:AJ24) -> 49.716 | AL24: =31.861-7.5 -> 24.361 | AM24: =-0.111+17.607 -> 17.496 | AN24: -0.027 | AO24: =19.203+-0.076 -> 19.127 | AP24: =SUM(AL24:AO24) -> 60.957 | AQ24: =22.148-0.55 -> 21.598 | AR24: 0.55 | AS24: 0 | AT24: 0 | AU24: =SUM(AQ24:AT24) -> 22.148 | AV24: 0.417 | AW24: -2.358 | AX24: 0 | AY24: -2.15 | AZ24: =SUM(AV24:AY24) -> -4.091 | BA24: 0 | BB24: 0 | BC24: 0 | BD24: 0 | BE24: =SUM(BA24:BD24) -> 0 | BF24: 0 | BG24: 0 | BH24: 0 | BI24: 0 | BJ24: 0
B25: Cash from Investing | C25: =SUM(C19:C24) -> -25.714 | D25: =SUM(D19:D24) -> 6.168 | E25: =SUM(E19:E24) -> -26.736 | F25: =SUM(F19:F24) -> -68.592 | G25: =SUM(G19:G24) -> -114.874 | H25: =SUM(H19:H24) -> -16.826 | I25: =SUM(I19:I24) -> -123.655 | J25: =SUM(J19:J24) -> -117.221 | ... V25: =SUM(V19:V24) -> -800.23 | AB25: =SUM(AB19:AB24) -> 218.075 | AC25: =SUM(AC19:AC24) -> -86.803 | AD25: =SUM(AD19:AD24) -> 108.839 | AE25: =SUM(AE19:AE24) -> 136.758 | AF25: =SUM(AF19:AF24) -> 376.869 | AG25: =SUM(AG19:AG24) -> -72.666 | AH25: =SUM(AH19:AH24) -> -142.468 | AI25: =SUM(AI19:AI24) -> 38.008 | ... AY25: =SUM(AY19:AY24) -> -641.007 | AZ25: =SUM(BA19:BA24) -> 198.75 | BA25: =SUM(BA19:BA24) -> 198.75 | BB25: =SUM(BB19:BB24) -> 198.75 | BC25: =SUM(BC19:BC24) -> 198.75 | BD25: =SUM(BD19:BD24) -> 198.75 | BE25: =SUM(BE19:BE24) -> 795 | BF25: =SUM(BF19:BF24) -> -5.15 | BG25: =SUM(BG19:BG24) -> -5.3045 | BH25: =SUM(BH19:BH24) -> -5.463635 | ... BJ25: =SUM(BJ19:BJ24) -> -5.7963704
B27: Financing Activities
B28: Process from exercise of options and ESPP shs | C28: =7.32-0.17 -> 7.15 | D28: 7.416 | E28: 4.444 | F28: 4.978 | G28: =SUM(C28:F28) -> 23.988 | H28: 10.304 | I28: =11.587+335.566 -> 347.153 | J28: =6.082+57.75 -> 63.832 | K28: 4.923 | L28: =SUM(H28:K28) -> 426.212 | M28: 6.678 | N28: 7.512 | O28: 9.452 | P28: 7.853 | Q28: =SUM(M28:P28) -> 31.495 | R28: 6.975 | S28: 12.312 | T28: 9.418 | U28: 10.944 | V28: =SUM(R28:U28) -> 39.649 | AB28: 10.422 | AC28: 11.38 | AD28: 11.752 | AE28: 6.389 | AF28: =SUM(AB28:AE28) -> 39.943 | AG28: 21.582 | AH28: 0.432 | AI28: 19.779 | AJ28: 0.917 | AK28: =SUM(AG28:AJ28) -> 42.71 | AL28: 19.655 | AM28: 1.176 | AN28: 17.931 | AO28: 0.898 | AP28: =SUM(AL28:AO28) -> 39.66 | AQ28: 22.628 | AR28: 1.615 | AS28: 28.641 | AT28: 6.692 | AU28: =SUM(AQ28:AT28) -> 59.576 | AV28: 22.654 | AW28: 0.36 | AX28: 31.604 | AY28: 0.2 | AZ28: =SUM(AV28:AY28) -> 54.818 | BA28: 0 | BB28: 0 | BC28: 0 | BD28: 0 | BE28: =SUM(BA28:BD28) -> 0 | BF28: 0 | BG28: 0 | BH28: 0 | BI28: 0 | BJ28: 0
B29: Payments of debt issuance costs | C29: 0 | D29: 0 | E29: 0 | F29: 0 | G29: =SUM(C29:F29) -> 0 | H29: 0 | I29: 0 | J29: -2.591 | K29: 0 | L29: =SUM(H29:K29) -> -2.591 | M29: 0 | N29: 0 | O29: 0 | P29: 0 | Q29: =SUM(M29:P29) -> 0 | R29: 0 | S29: 0 | T29: =575-15.713 -> 559.287 | U29: 0 | V29: =SUM(R29:U29) -> 559.287 | AB29: 0 | AC29: 0 | AD29: 0 | AE29: 0 | AF29: =SUM(AB29:AE29) -> 0 | AG29: 0 | AH29: 0 | AI29: 0 | AJ29: 0 | AK29: =SUM(AG29:AJ29) -> 0 | AL29: 0 | AM29: 0 | AN29: 0 | AO29: 0 | AP29: =SUM(AL29:AO29) -> 0 | AQ29: 0 | AR29: 0 | AS29: 0 | AT29: 0 | AU29: =SUM(AQ29:AT29) -> 0 | AV29: 0 | AW29: 0 | AX29: -25.934 | AY29: -0.008 | AZ29: =SUM(AV29:AY29) -> -25.942 | BA29: 0 | BB29: 0 | BC29: 0 | BD29: 0 | BE29: =SUM(BA29:BD29) -> 0 | BF29: 0 | BG29: 0 | BH29: 0 | BI29: 0 | BJ29: 0
B30: Share repurchase | AB30: 0 | AC30: 0 | AD30: -200 | AE30: 0 | AF30: =SUM(AB30:AE30) -> -200 | AG30: 0 | AH30: 0 | AI30: 0 | AJ30: -231.873 | AK30: =SUM(AG30:AJ30) -> -231.873 | AL30: -18.319 | AM30: -50 | AN30: 0 | AO30: -58.698 | AP30: =SUM(AL30:AO30) -> -127.017 | AQ30: -241.302 | AR30: -225 | AS30: 0 | AT30: 0 | AU30: =SUM(AQ30:AT30) -> -466.302 | AV30: -200 | AW30: -100 | AX30: -175 | AY30: -99.999 | AZ30: =SUM(AV30:AY30) -> -574.999 | BA30: -400 | BB30: -400 | BC30: -400 | BD30: -400 | BE30: =SUM(BA30:BD30) -> -1600 | BF30: -400 | BG30: 0 | BH30: 0 | BI30: 0 | BJ30: 0
B31: Purchase of capped call / Other | C31: 0 | D31: 0 | E31: 0 | F31: 0 | G31: =SUM(C31:F31) -> 0 | H31: 0 | I31: 0 | J31: -5.914 | K31: 0 | L31: =SUM(H31:K31) -> -5.914 | M31: 0 | N31: 0 | O31: 0 | P31: 0 | Q31: =SUM(M31:P31) -> 0 | R31: 0 | S31: 0 | T31: -46 | U31: 0 | V31: =SUM(R31:U31) -> -46 | AB31: 0 | AC31: 0 | AD31: 0 | AE31: 0 | AF31: =SUM(AB31:AE31) -> 0 | AG31: 0 | AH31: 0 | AI31: 0 | AJ31: 0 | AK31: =SUM(AG31:AJ31) -> 0 | AL31: 0 | AM31: -362.667 | AN31: 0 | AO31: 0 | AP31: =SUM(AL31:AO31) -> -362.667 | AQ31: 0 | AR31: 0 | AS31: 0 | AT31: 0 | AU31: =SUM(AQ31:AT31) -> 0 | AV31: 0 | AW31: 0 | AX31: =1150-575-71.875 -> 503.125 | AY31: 0 | AZ31: =SUM(AV31:AY31) -> 503.125 | BA31: 250 | BB31: 0 | BC31: 0 | BD31: 0 | BE31: =SUM(BA31:BD31) -> 250 | BF31: 0 | BG31: 0 | BH31: 0 | BI31: 0 | BJ31: 0
B32: Cash from Financing | C32: =SUM(C28:C31) -> 7.15 | D32: =SUM(D28:D31) -> 7.416 | E32: =SUM(E28:E31) -> 4.444 | F32: =SUM(F28:F31) -> 4.978 | G32: =SUM(G28:G31) -> 23.988 | H32: =SUM(H28:H31) -> 10.304 | I32: =SUM(I28:I31) -> 347.153 | J32: =SUM(J28:J31) -> 55.327 | ... V32: =SUM(V28:V31) -> 552.936 | AB32: =SUM(AB28:AB31) -> 10.422 | AC32: =SUM(AC28:AC31) -> 11.38 | AD32: =SUM(AD28:AD31) -> -188.248 | AE32: =SUM(AE28:AE31) -> 6.389 | AF32: =SUM(AF28:AF31) -> -160.057 | AG32: =SUM(AG28:AG31) -> 21.582 | AH32: =SUM(AH28:AH31) -> 0.432 | AI32: =SUM(AI28:AI31) -> 19.779 | ... AY32: =SUM(AY28:AY31) -> -99.807 | AZ32: =SUM(BA28:BA31) -> -150 | BA32: =SUM(BA28:BA31) -> -150 | BB32: =SUM(BB28:BB31) -> -400 | BC32: =SUM(BC28:BC31) -> -400 | BD32: =SUM(BD28:BD31) -> -400 | BE32: =SUM(BE28:BE31) -> -1350 | BF32: =SUM(BF28:BF31) -> -400 | BG32: =SUM(BG28:BG31) -> 0 | BH32: =SUM(BH28:BH31) -> 0 | ... BJ32: =SUM(BJ28:BJ31) -> 0
B34: Effect of Foreign Exchange | C34: 0 | D34: 0 | E34: 0 | F34: 0 | G34: =SUM(C34:F34) -> 0 | H34: 0 | I34: 0 | J34: 0 | K34: 0 | L34: =SUM(H34:K34) -> 0 | M34: 0 | N34: 0 | O34: 0 | P34: 0 | Q34: =SUM(M34:P34) -> 0 | R34: 0 | S34: 0 | T34: 0 | U34: 0 | V34: =SUM(R34:U34) -> 0 | AB34: 0 | AC34: 0 | AD34: 0 | AE34: 0 | AF34: =SUM(AB34:AE34) -> 0 | AG34: 0 | AH34: 0 | AI34: 0 | AJ34: 0 | AK34: =SUM(AG34:AJ34) -> 0 | AL34: 0 | AM34: 0 | AN34: 0 | AO34: 0 | AP34: =SUM(AL34:AO34) -> 0 | AQ34: -0.553 | AR34: -1.598 | AS34: 0.716 | AT34: -2.471 | AU34: =SUM(AQ34:AT34) -> -3.906 | AV34: 2.006 | AW34: 14.29 | AX34: 1.418 | AY34: 0.511 | AZ34: =SUM(AV34:AY34) -> 18.225 | BA34: 0 | BB34: 0 | BC34: 0 | BD34: 0 | BE34: =SUM(BA34:BD34) -> 0 | BF34: 0 | BG34: 0 | BH34: 0 | BI34: 0 | BJ34: 0
B36: Net Change in Cash | C36: =C16+C25+C32+C34 -> -2.167 | D36: =D16+D25+D32+D34 -> 33.235 | E36: =E16+E25+E32+E34 -> -0.229 | F36: =F16+F25+F32+F34 -> -38.704 | G36: =G16+G25+G32+G34 -> -7.865 | H36: =H16+H25+H32+H34 -> 18.257 | I36: =I16+I25+I32+I34 -> 250.766 | J36: =J16+J25+J32+J34 -> -34.287 | ... V36: =V16+V25+V32+V34 -> -99.245 | AB36: =AB16+AB25+AB32+AB34 -> 246.985 | AC36: =AC16+AC25+AC32+AC34 -> -53.59 | AD36: =AD16+AD25+AD32+AD34 -> -75.086 | AE36: =AE16+AE25+AE32+AE34 -> 164.188 | AF36: =AF16+AF25+AF32+AF34 -> 282.497 | AG36: =AG16+AG25+AG32+AG34 -> -64.746 | AH36: =AH16+AH25+AH32+AH34 -> -144.705 | AI36: =AI16+AI25+AI32+AI34 -> 58.054 | ... AY36: =AY16+AY25+AY32+AY34 -> -581.97 | AZ36: =BA16+BA25+BA32+BA34 -> 149.68671 | BA36: =BA16+BA25+BA32+BA34 -> 149.68671 | BB36: =BB16+BB25+BB32+BB34 -> -85.680602 | BC36: =BC16+BC25+BC32+BC34 -> -64.301952 | BD36: =BD16+BD25+BD32+BD34 -> -43.98323 | BE36: =BE16+BE25+BE32+BE34 -> -44.279073 | BF36: =BF16+BF25+BF32+BF34 -> 240.95051 | BG36: =BG16+BG25+BG32+BG34 -> 748.35542 | BH36: =BH16+BH25+BH32+BH34 -> 867.98083 | ... BJ36: =BJ16+BJ25+BJ32+BJ34 -> 1100.1975
B38: Beg Period Cash | R38: 268.103 | S38: =R39 -> 191.258 | T38: =S39 -> 173.95 | U38: =T39 -> 158.456 | AB38: =U39 -> 168.858 | AC38: =AB39 -> 415.843 | AD38: =AC39 -> 362.253 | AE38: =AD39 -> 287.167 | AG38: =AE39 -> 451.355 | AH38: =AG39 -> 386.609 | AI38: =AH39 -> 241.904 | AJ38: =AI39 -> 299.958 | AL38: =AJ39 -> 244.704 | AM38: =AL39 -> 350.931 | AN38: =AM39 -> 468.055 | AO38: =AN39 -> 504.811 | AP38: =AO39 -> 609.64 | AQ38: =AO39 -> 609.64 | AR38: =AQ39 -> 513.341 | AS38: =AR39 -> 276.084 | AT38: =AS39 -> 439.451 | AU38: =AT39 -> 660.956 | AV38: =AT39 -> 660.956 | AW38: =AV39 -> 653.293 | AX38: =AW39 -> 704.159 | AY38: =AX39 -> 898.863 | AZ38: =AY39 -> 316.893 | BA38: =AY39 -> 316.893 | BB38: =BA39 -> 466.57971 | BC38: =BB39 -> 380.89911 | BD38: =BC39 -> 316.59716 | BE38: =BD39 -> 272.61393 | BF38: =BE39 -> 228.33485 | BG38: =BF39 -> 469.28537 | BH38: =BG39 -> 1217.6408 | BI38: =BH39 -> 2085.6216 | BJ38: =BI39 -> 3071.1737
B39: End Period Cash | R39: =R36+R38 -> 191.258 | S39: =S36+S38 -> 173.95 | T39: =T36+T38 -> 158.456 | U39: =U36+U38 -> 168.858 | AB39: =AB36+AB38 -> 415.843 | AC39: =AC36+AC38 -> 362.253 | AD39: =AD36+AD38 -> 287.167 | AE39: =AE36+AE38 -> 451.355 | AG39: =AG36+AG38 -> 386.609 | AH39: =AH36+AH38 -> 241.904 | AI39: =AI36+AI38 -> 299.958 | AJ39: =AJ36+AJ38 -> 244.704 | AL39: =AL36+AL38 -> 350.931 | AM39: =AM36+AM38 -> 468.055 | AN39: =AN36+AN38 -> 504.811 | AO39: =AO36+AO38 -> 609.64 | AP39: =AP36+AP38 -> 974.576 | AQ39: =AQ36+AQ38 -> 513.341 | AR39: =AR36+AR38 -> 276.084 | AS39: =AS36+AS38 -> 439.451 | ... AY39: =AY36+AY38 -> 316.893 | AZ39: =BA36+BA38 -> 466.57971 | BA39: =BA36+BA38 -> 466.57971 | BB39: =BB36+BB38 -> 380.89911 | BC39: =BC36+BC38 -> 316.59716 | BD39: =BD36+BD38 -> 272.61393 | BE39: =BE36+BE38 -> 228.33485 | BF39: =BF36+BF38 -> 469.28537 | BG39: =BG36+BG38 -> 1217.6408 | BH39: =BH36+BH38 -> 2085.6216 | ... BJ39: =BJ36+BJ38 -> 4171.3712
B41: Total Capex | R41: =SUM(R21:R22) -> -5.075 | S41: =SUM(S21:S22) -> -3.264 | T41: =SUM(T21:T22) -> -5.134 | U41: =SUM(U21:U22) -> -5.38 | V41: =SUM(R41:U41) -> -18.853 | AB41: =SUM(AB21:AB22) -> -3.849 | AC41: =SUM(AC21:AC22) -> -7.119 | AD41: =SUM(AD21:AD22) -> -13.03 | AE41: =SUM(AE21:AE22) -> -13.702 | AF41: =SUM(AB41:AE41) -> -37.7 | AG41: =SUM(AG21:AG22) -> -19.924 | AH41: =SUM(AH21:AH22) -> -13.217 | AI41: =SUM(AI21:AI22) -> -22.874 | AJ41: =SUM(AJ21:AJ22) -> -14.649 | AK41: =SUM(AG41:AJ41) -> -70.664 | AL41: =SUM(AL21:AL22) -> -20.932 | AM41: =SUM(AM21:AM22) -> -15.751 | AN41: =SUM(AN21:AN22) -> -19.376 | AO41: =SUM(AO21:AO22) -> -9.989 | AP41: =SUM(AL41:AO41) -> -66.048 | AQ41: =SUM(AQ21:AQ22) -> -8.125 | AR41: =SUM(AR21:AR22) -> -7.196 | AS41: =SUM(AS21:AS22) -> -2.053 | AT41: =SUM(AT21:AT22) -> -1.963 | AU41: =SUM(AQ41:AT41) -> -19.337 | AV41: =SUM(AV21:AV22) -> -3.05 | AW41: =SUM(AW21:AW22) -> -2.67 | AX41: =SUM(AX21:AX22) -> -1.417 | AY41: =+AY42+AY44 -> -3.5 | AZ41: =SUM(AV41:AY41) -> -10.637 | BA41: =+BA42+BA44 -> -1.25 | BB41: =+BB42+BB44 -> -1.25 | BC41: =+BC42+BC44 -> -1.25 | BD41: =+BD42+BD44 -> -1.25 | BE41: =SUM(BA41:BD41) -> -5 | BF41: =+BF44 -> -5.15 | BG41: =+BG44 -> -5.3045 | BH41: =+BH44 -> -5.463635 | BI41: =+BI44 -> -5.6275441 | BJ41: =+BJ44 -> -5.7963704
B42: HQ Capex | R42: -0.483 | S42: -0.408 | T42: -0.779 | U42: -0.792 | V42: =SUM(R42:U42) -> -2.462 | AB42: -0.835 | AC42: -2.197 | AD42: -10.37 | AE42: -10 | AF42: =SUM(AB42:AE42) -> -23.402 | AG42: -20 | AH42: -9.9 | AI42: -27.166 | AJ42: =-52+38.6 -> -13.4 | AK42: =SUM(AG42:AJ42) -> -70.466 | AL42: -16.949 | AM42: -14.63 | AN42: -18.043 | AO42: -8.324 | AP42: =SUM(AL42:AO42) -> -57.946 | AQ42: -5.362 | AR42: -4.963 | AS42: 0 | AT42: 0 | AU42: =SUM(AQ42:AT42) -> -10.325 | AV42: 0 | AW42: 0 | AX42: 0 | AZ42: =SUM(AV42:AY42) -> 0 | BE42: =SUM(BA42:BD42) -> 0 | BF42: =BE42 -> 0 | BG42: =BF42 -> 0 | BH42: =BG42 -> 0 | BI42: =BH42 -> 0 | BJ42: =BI42 -> 0
B43: Restructuring | AL43: -2.051 | AM43: -2.453 | AN43: 0 | AO43: -1.411 | AP43: =SUM(AL43:AO43) -> -5.915 | AQ43: 0 | AR43: 0 | AS43: 0 | AT43: 0 | AV43: 0 | AW43: 0 | AX43: -32.128 | AZ43: =SUM(AV43:AY43) -> -32.128 | BE43: =SUM(BA43:BD43) -> 0
B44: Net Capex, ex HQ | R44: =R41-R42 -> -4.592 | S44: =S41-S42 -> -2.856 | T44: =T41-T42 -> -4.355 | U44: =U41-U42 -> -4.588 | V44: =SUM(R44:U44) -> -16.391 | AB44: =AB41-AB42 -> -3.014 | AC44: =AC41-AC42 -> -4.922 | AD44: =AD41-AD42 -> -2.66 | AE44: =AE41-AE42 -> -3.702 | AF44: =SUM(AB44:AE44) -> -14.298 | AG44: =AG41-AG42 -> 0.076 | AH44: =AH41-AH42 -> -3.317 | AI44: =AI41-AI42 -> 4.292 | AJ44: =AJ41-AJ42 -> -1.249 | AK44: =SUM(AG44:AJ44) -> -0.198 | AL44: =AL41-AL42 -> -3.983 | AM44: =AM41-AM42 -> -1.121 | AN44: =AN41-AN42 -> -1.333 | AO44: =AO41-AO42 -> -1.665 | AP44: =SUM(AL44:AO44) -> -8.102 | AQ44: =AQ41-AQ42 -> -2.763 | AR44: =AR41-AR42 -> -2.233 | AS44: =AS41-AS42 -> -2.053 | AT44: =AT41-AT42 -> -1.963 | AU44: =SUM(AQ44:AT44) -> -9.012 | AV44: =AV41-AV42 -> -3.05 | AW44: =AW41-AW42 -> -2.67 | AX44: =AX41-AX42 -> -1.417 | AY44: -3.5 | AZ44: =SUM(AV44:AY44) -> -10.637 | BA44: -1.25 | BB44: -1.25 | BC44: -1.25 | BD44: -1.25 | BE44: =SUM(BA44:BD44) -> -5 | BF44: =+BE44*1.03 -> -5.15 | BG44: =+BF44*1.03 -> -5.3045 | BH44: =+BG44*1.03 -> -5.463635 | BI44: =+BH44*1.03 -> -5.6275441 | BJ44: =+BI44*1.03 -> -5.7963704
B46: FCF | R46: =R16+R21+R22 -> 39.952 | S46: =S16+S21+S22 -> 46.694 | T46: =T16+T21+T22 -> 19.38 | U46: =U16+U21+U22 -> 23.17 | V46: =SUM(R46:U46) -> 129.196 | AB46: =AB16+AB21+AB22 -> 14.639 | AC46: =AC16+AC21+AC22 -> 14.714 | AD46: =AD16+AD21+AD22 -> -8.707 | AE46: =AE16+AE21+AE22 -> 7.339 | AF46: =SUM(AB46:AE46) -> 27.985 | AG46: =AG16+AG21+AG22 -> -33.586 | AH46: =AH16+AH21+AH22 -> -15.886 | AI46: =AI16+AI21+AI22 -> -22.607 | AJ46: =AJ16+AJ21+AJ22 -> 38.585 | AK46: =SUM(AG46:AJ46) -> -33.494 | AL46: =AL16+AL21+AL22 -> 25.029 | AM46: =AM16+AM21+AM22 -> 32.01 | AN46: =AN16+AN21+AN22 -> 44.768 | AO46: =AO16+AO21+AO22 -> 80.39 | AP46: =SUM(AL46:AO46) -> 182.197 | AQ46: =AQ16+AQ21+AQ22 -> 105.711 | AR46: =AR16+AR21+AR22 -> 112.833 | AS46: =AS16+AS21+AS22 -> 127.761 | AT46: =AT16+AT21+AT22 -> 131.773 | AU46: =SUM(AQ46:AT46) -> 478.078 | AV46: =AV16+AV21+AV22 -> 142.441 | AW46: =AW16+AW21+AW22 -> 147.665 | AX46: =AX16+AX21+AX22 -> 127.282 | AY46: =AY16+AY21+AY22 -> 155.569 | AZ46: =BA16+BA21+BA22 -> 99.686711 | BA46: =BA16+BA21+BA22 -> 99.686711 | BB46: =BB16+BB21+BB22 -> 114.3194 | BC46: =BC16+BC21+BC22 -> 135.69805 | BD46: =BD16+BD21+BD22 -> 156.01677 | BE46: =BE16+BE21+BE22 -> 505.72093 | BF46: =BF16+BF21+BF22 -> 640.95051 | BG46: =BG16+BG21+BG22 -> 748.35542 | BH46: =BH16+BH21+BH22 -> 867.98083 | ... BJ46: =BJ16+BJ21+BJ22 -> 1100.1975
B47: FCF Margin | AK47: =+AK46/'Income Statement'!AK$13 -> -0.024136932 | AP47: =+AP46/'Income Statement'!AP$13 -> 0.11666843 | AU47: =+AU46/'Income Statement'!AU$13 -> 0.27153494 | AZ47: =+BA46/'Income Statement'!BA$13 -> 0.18398413 | BE47: =+BE46/'Income Statement'!BE$13 -> 0.21946065 | BF47: =+BF46/'Income Statement'!BF$13 -> 0.24891393 | BG47: =+BG46/'Income Statement'!BG$13 -> 0.26542775 | BH47: =+BH46/'Income Statement'!BH$13 -> 0.28587666 | BI47: =+BI46/'Income Statement'!BI$13 -> 0.30553469 | BJ47: =+BJ46/'Income Statement'!BJ$13 -> 0.32441592 | BL47: 35%+
B48: FCF, ex HQ capex | R48: =R46-R42 -> 40.435 | S48: =S46-S42 -> 47.102 | T48: =T46-T42 -> 20.159 | U48: =U46-U42 -> 23.962 | V48: =SUM(R48:U48) -> 131.658 | AB48: =AB46-AB42 -> 15.474 | AC48: =AC46-AC42 -> 16.911 | AD48: =AD46-AD42 -> 1.663 | AE48: =AE46-AE42 -> 17.339 | AF48: =SUM(AB48:AE48) -> 51.387 | AG48: =AG46-AG42 -> -13.586 | AH48: =AH46-AH42 -> -5.986 | AI48: =AI46-AI42 -> 4.559 | AJ48: =AJ46-AJ42 -> 51.985 | AK48: =SUM(AG48:AJ48) -> 36.972 | AL48: =AL46-AL42-AL43 -> 44.029 | AM48: =AM46-AM42-AM43 -> 49.093 | AN48: =AN46-AN42-AN43 -> 62.811 | AO48: =AO46-AO42-AO43 -> 90.125 | AP48: =SUM(AL48:AO48) -> 246.058 | AQ48: =AQ46-AQ42-AQ43 -> 111.073 | AR48: =AR46-AR42-AR43 -> 117.796 | AS48: =AS46-AS42-AS43 -> 127.761 | AT48: =AT46-AT42-AT43 -> 131.773 | AU48: =SUM(AQ48:AT48) -> 488.403 | AV48: =AV46-AV42-AV43 -> 142.441 | AW48: =AW46-AW42-AW43 -> 147.665 | AX48: =AX46-AX42-AX43 -> 159.41 | AY48: =AY46-AY42-AY43 -> 155.569 | AZ48: =BA46-BA42-BA43 -> 99.686711 | BA48: =BA46-BA42-BA43 -> 99.686711 | BB48: =BB46-BB42-BB43 -> 114.3194 | BC48: =BC46-BC42-BC43 -> 135.69805 | BD48: =BD46-BD42-BD43 -> 156.01677 | BE48: =BE46-BE42-BE43 -> 505.72093 | BF48: =BF46-BF42 -> 640.95051 | BG48: =BG46-BG42 -> 748.35542 | BH48: =BH46-BH42 -> 867.98083 | BI48: =BI46-BI42 -> 985.55214 | BJ48: =BJ46-BJ42 -> 1100.1975
B49: FCF Margin | AK49: =+AK48/'Income Statement'!AK$13 -> 0.026643299 | AL49: =+AL48/'Income Statement'!AL$13 -> 0.11770068 | AM49: =+AM48/'Income Statement'!AM$13 -> 0.12588691 | AN49: =+AN48/'Income Statement'!AN$13 -> 0.15948314 | AO49: =+AO48/'Income Statement'!AO$13 -> 0.2232082 | AP49: =+AP48/'Income Statement'!AP$13 -> 0.15756132 | AQ49: =+AQ48/'Income Statement'!AQ$13 -> 0.26460064 | AR49: =+AR48/'Income Statement'!AR$13 -> 0.2703318 | ... AY49: =+AY48/'Income Statement'!AY$13 -> 0.29673507 | AZ49: =+BA48/'Income Statement'!BA$13 -> 0.18398413 | BA49: =+BA48/'Income Statement'!BA$13 -> 0.18398413 | BB49: =+BB48/'Income Statement'!BB$13 -> 0.20293096 | BC49: =+BC48/'Income Statement'!BC$13 -> 0.23136115 | BD49: =+BD48/'Income Statement'!BD$13 -> 0.25463944 | BE49: =+BE48/'Income Statement'!BE$13 -> 0.21946065 | BF49: =+BF48/'Income Statement'!BF$13 -> 0.24891393 | BG49: =+BG48/'Income Statement'!BG$13 -> 0.26542775 | BH49: =+BH48/'Income Statement'!BH$13 -> 0.28587666 | ... BJ49: =+BJ48/'Income Statement'!BJ$13 -> 0.32441592
B52: Increase in ST & LT Deferred Revenues | H52: 21.88 | I52: 13.763 | J52: 7.177 | K52: 11.861 | L52: 54.681 | M52: 26.089 | N52: 14.144 | O52: 9.069 | P52: 22.095 | Q52: 71.397 | R52: 32.871 | S52: 29.792 | T52: 26.761 | U52: 23.847 | V52: 117.664 | AB52: 46.997 | AC52: 21.81 | AD52: 5.336 | AE52: 11.593 | AF52: 82.361 | AG52: 37.5522 | AH52: ='Balance Sheet'!AH24+'Balance Sheet'!AH30-('Balance Sheet'!AG24+'Balance Sheet'!AG30) -> 7.731 | AI52: ='Balance Sheet'!AI24+'Balance Sheet'!AI30-('Balance Sheet'!AH24+'Balance Sheet'!AH30) -> 6.023 | AJ52: ='Balance Sheet'!AJ24+'Balance Sheet'!AJ30-('Balance Sheet'!AI24+'Balance Sheet'!AI30) -> 4.081 | AK52: ='Balance Sheet'!AJ24+'Balance Sheet'!AJ30-('Balance Sheet'!AE24+'Balance Sheet'!AE30) -> 55.387 | AL52: ='Balance Sheet'!AL24+'Balance Sheet'!AL30-('Balance Sheet'!AJ24+'Balance Sheet'!AJ30) -> 60.975 | AM52: ='Balance Sheet'!AM24+'Balance Sheet'!AM30-('Balance Sheet'!AL24+'Balance Sheet'!AL30) -> 12.043 | AN52: ='Balance Sheet'!AN24+'Balance Sheet'!AN30-('Balance Sheet'!AM24+'Balance Sheet'!AM30) -> 0.387 | AO52: ='Balance Sheet'!AO24+'Balance Sheet'!AO30-('Balance Sheet'!AN24+'Balance Sheet'!AN30) -> 2.788 | AP52: ='Balance Sheet'!AO24+'Balance Sheet'!AO30-('Balance Sheet'!AJ24+'Balance Sheet'!AJ30) -> 76.193 | AQ52: ='Balance Sheet'!AQ24+'Balance Sheet'!AQ30-('Balance Sheet'!AO24+'Balance Sheet'!AO30) -> 41.319 | AR52: ='Balance Sheet'!AR24+'Balance Sheet'!AR30-('Balance Sheet'!AQ24+'Balance Sheet'!AQ30) -> 25.426 | AS52: ='Balance Sheet'!AS24+'Balance Sheet'!AS30-('Balance Sheet'!AR24+'Balance Sheet'!AR30) -> 6.096 | AT52: ='Balance Sheet'!AT24+'Balance Sheet'!AT30-('Balance Sheet'!AS24+'Balance Sheet'!AS30) -> 1.609 | AU52: ='Balance Sheet'!AT24+'Balance Sheet'!AT30-('Balance Sheet'!AO24+'Balance Sheet'!AO30) -> 74.45 | AV52: ='Balance Sheet'!AV24+'Balance Sheet'!AV30-('Balance Sheet'!AT24+'Balance Sheet'!AT30) -> 44.362 | AW52: ='Balance Sheet'!AW24+'Balance Sheet'!AW30-('Balance Sheet'!AV24+'Balance Sheet'!AV30) -> 26.232 | AX52: ='Balance Sheet'!AX24+'Balance Sheet'!AX30-('Balance Sheet'!AW24+'Balance Sheet'!AW30) -> 18.316 | AY52: ='Balance Sheet'!AY24+'Balance Sheet'!AY30-('Balance Sheet'!AX24+'Balance Sheet'!AX30) -> 14.985 | AZ52: ='Balance Sheet'!BA24+'Balance Sheet'!BA30-('Balance Sheet'!AT24+'Balance Sheet'!AT30) -> 138.8673 | BA52: ='Balance Sheet'!BA24+'Balance Sheet'!BA30-('Balance Sheet'!AY24+'Balance Sheet'!AY30) -> 34.9723 | BB52: ='Balance Sheet'!BB24+'Balance Sheet'!BB30-('Balance Sheet'!BA24+'Balance Sheet'!BA30) -> 21.3565 | BC52: ='Balance Sheet'!BC24+'Balance Sheet'!BC30-('Balance Sheet'!BB24+'Balance Sheet'!BB30) -> 11.1936 | BD52: ='Balance Sheet'!BD24+'Balance Sheet'!BD30-('Balance Sheet'!BC24+'Balance Sheet'!BC30) -> 0 | BE52: ='Balance Sheet'!BE24+'Balance Sheet'!BE30-('Balance Sheet'!AY24+'Balance Sheet'!AY30) -> 113.61537 | BF52: ='Balance Sheet'!BE24+'Balance Sheet'!BE30-('Balance Sheet'!BD24+'Balance Sheet'!BD30) -> 46.09297 | BG52: ='Balance Sheet'!BF24+'Balance Sheet'!BF30-('Balance Sheet'!BE24+'Balance Sheet'!BE30) -> 48.397619 | BH52: ='Balance Sheet'!BG24+'Balance Sheet'!BG30-('Balance Sheet'!BF24+'Balance Sheet'!BF30) -> 50.817499 | BI52: ='Balance Sheet'!BH24+'Balance Sheet'!BH30-('Balance Sheet'!BG24+'Balance Sheet'!BG30) -> 53.358374 | BJ52: ='Balance Sheet'!BI24+'Balance Sheet'!BI30-('Balance Sheet'!BH24+'Balance Sheet'!BH30) -> 56.026293
B53: Changes in Working Capital, excl Deferred Revenue | H53: =H15-H52 -> 5.001 | I53: =I15-I52 -> -0.699 | J53: =J15-J52 -> -0.551 | K53: =K15-K52 -> 1.222 | L53: =L15-L52 -> 4.973 | M53: =M15-M52 -> 5.64 | N53: =N15-N52 -> 2.839 | O53: =O15-O52 -> 7.127 | ... V53: =V15-V52 -> 51.277 | AB53: =AB15-AB52 -> -29.453 | AC53: =AC15-AC52 -> -55.435 | AD53: =AD15-AD52 -> 9.318 | AE53: =AE15-AE52 -> 30.574 | AF53: =AF15-AF52 -> -41.621 | AG53: =AG15-AG52 -> -8.9832 | AH53: =AH15-AH52 -> -8.527 | AI53: =AI15-AI52 -> -15.263 | ... AY53: =AY15-AY52 -> 153.092 | AZ53: =BA15-BA52 -> 2.5277 | BA53: =BA15-BA52 -> 2.5277 | BB53: =BB15-BB52 -> 16.1435 | BC53: =BC15-BC52 -> 26.3064 | BD53: =BD15-BD52 -> 37.5 | BE53: =BE15-BE52 -> 36.38463 | BF53: =BF15-BF52 -> 73.90703 | BG53: =BG15-BG52 -> 47.602381 | BH53: =BH15-BH52 -> 25.982501 | ... BJ53: =BJ15-BJ52 -> -6.8742931
B54: Changes in WC, % of revenue | H54: =H53/'Income Statement'!M13 -> 0.036298312 | I54: =I53/'Income Statement'!N13 -> -0.0047833466 | J54: =J53/'Income Statement'!O13 -> -0.0035411311 | K54: =K53/'Income Statement'!P13 -> 0.0074422797 | L54: =L53/'Income Statement'!Q13 -> 0.0082374806 | M54: =M53/'Income Statement'!R13 -> 0.03235986 | N54: =N53/'Income Statement'!S13 -> 0.015311268 | O54: =O53/'Income Statement'!T13 -> 0.036216087 | ... V54: =V53/'Income Statement'!AA13 -> 0.051859905 | AB54: =AB53/'Income Statement'!AB13 -> -0.096849187 | AC54: =AC53/'Income Statement'!AC13 -> -0.17520211 | AD54: =AD53/'Income Statement'!AD13 -> 0.029046406 | AE54: =AE53/'Income Statement'!AE13 -> 0.093116324 | AF54: =AF53/'Income Statement'!AF13 -> -0.032781294 | AG54: =AG53/'Income Statement'!AG13 -> -0.026297655 | AH54: =AH53/'Income Statement'!AH13 -> -0.024699905 | AI54: =AI53/'Income Statement'!AI13 -> -0.044137592 | ... AY54: =AY53/'Income Statement'!AY13 -> 0.2920104 | AZ54: =BA53/'Income Statement'!BA13 -> 0.0046651824 | BA54: =BA53/'Income Statement'!BA13 -> 0.0046651824 | BB54: =BB53/'Income Statement'!BB13 -> 0.028656693 | BC54: =BC53/'Income Statement'!BC13 -> 0.044851633 | BD54: =BD53/'Income Statement'!BD13 -> 0.061204825 | BE54: =BE53/'Income Statement'!BE13 -> 0.01578933 | BF54: =BF53/'Income Statement'!BF13 -> 0.028701887 | BG54: =BG53/'Income Statement'!BG13 -> 0.016883679 | BH54: =BH53/'Income Statement'!BH13 -> 0.0085575512 | ... BJ54: =BJ53/'Income Statement'!BJ13 -> -0.0020270271
B56: FCF, % of EBITDA | R56: =R46/'Income Statement'!W43 -> 1.2388601 | S56: =S46/'Income Statement'!X43 -> 2.8606261 | T56: =T46/'Income Statement'!Y43 -> 0.88211197 | U56: =U46/'Income Statement'!Z43 -> 1.1586738 | V56: =V46/'Income Statement'!AA43 -> 1.4269652 | AB56: =AB46/'Income Statement'!AB43 -> 1.0337547 | AC56: =AC46/'Income Statement'!AC43 -> 1.1903568 | AD56: =AD46/'Income Statement'!AD43 -> -0.19277349 | AE56: =AE46/'Income Statement'!AE43 -> 2.8368767 | AF56: =AF46/'Income Statement'!AF43 -> 0.37677042 | AG56: =AG46/'Income Statement'!AG43 -> -8.0004764 | AH56: =AH46/'Income Statement'!AH43 -> -34.163441 | AI56: =AI46/'Income Statement'!AI43 -> -3.0808122 | ... AY56: =AY46/'Income Statement'!AY43 -> 1.6895533 | AZ56: =BA46/'Income Statement'!BA43 -> 1.2289595 | BA56: =BA46/'Income Statement'!BA43 -> 1.2289595 | BB56: =BB46/'Income Statement'!BB43 -> 1.366844 | BC56: =BC46/'Income Statement'!BC43 -> 1.3550697 | BD56: =BD46/'Income Statement'!BD43 -> 1.3630449 | BE56: =BE46/'Income Statement'!BE43 -> 1.3331067 | BF56: =BF46/'Income Statement'!BF43 -> 1.0868654 | BG56: =BG46/'Income Statement'!BG43 -> 1.014273 | BH56: =BH46/'Income Statement'!BH43 -> 0.98851984 | ... BJ56: =BJ46/'Income Statement'!BJ43 -> 0.97540543
B59: Buyback | AJ59: =AJ30 -> -231.873 | AL59: =AL30 -> -18.319 | AM59: =AM30 -> -50 | AN59: =AN30 -> 0 | AO59: =AO30 -> -58.698 | AP59: =AP30 -> -127.017 | AQ59: =AQ30 -> -241.302 | AR59: =AR30 -> -225 | AS59: =AS30 -> 0 | ... AY59: =AY30 -> -99.999 | AZ59: =BA30 -> -400 | BA59: =BA30 -> -400 | BB59: =BB30 -> -400 | BC59: =BC30 -> -400 | BD59: =BD30 -> -400 | BE59: =BE30 -> -1600 | BF59: =BF30 -> -400 | BG59: =BG30 -> 0 | BH59: =BH30 -> 0 | ... BJ59: =BJ30 -> 0
B60: Avg price | AJ60: 85 | AL60: 87.36 | AM60: 83.53 | AN60: 100 | AO60: =+AN60*1.05 -> 105 | AQ60: 125 | AR60: 160 | AS60: =+AR60+8 -> 168 | AT60: 220 | AU60: =AVERAGE(AQ60:AT60) -> 168.25 | AV60: =+AT60*1.02 -> 224.4 | AW60: =+AV60*1.02 -> 228.888 | AX60: 175 | AY60: =+AX60*1.02 -> 178.5 | AZ60: =+AVERAGE(AV60:AY60) -> 201.697 | BA60: 85 | BB60: 95 | BC60: 105 | BD60: 115 | BE60: =+AVERAGE(BA60:BD60) -> 100 | BF60: =+BD60*1.05 -> 120.75 | BG60: =BF60*1.1 -> 132.825 | BH60: =BG60*1.1 -> 146.1075 | BI60: =BH60*1.1 -> 160.71825 | BJ60: =BI60*1.1 -> 176.79008
B61: Shares repurchased | AJ61: =-(AJ59)/AJ60 -> 2.7279176 | AL61: =-(AL59)/AL60 -> 0.20969551 | AM61: =-(AM59)/AM60 -> 0.59858733 | AN61: =-(AN59)/AN60 -> 0 | AO61: =-(AO59)/AO60 -> 0.55902857 | AQ61: =-(AQ59)/AQ60 -> 1.930416 | AR61: =-(AR59)/AR60 -> 1.40625 | AS61: =-(AS59)/AS60 -> 0 | AT61: =-(AT59)/AT60 -> 0 | AU61: =SUM(AQ61:AT61) -> 3.336666 | AV61: =-(AV59)/AV60 -> 0.8912656 | AW61: =-(AW59)/AW60 -> 0.4368949 | AX61: =-(AX59)/AX60 -> 1 | AY61: =-(AY59)/AY60 -> 0.56021849 | AZ61: =-(BA59)/BA60 -> 4.7058824 | BA61: =-(BA59)/BA60 -> 4.7058824 | BB61: =-(BB59)/BB60 -> 4.2105263 | BC61: =-(BC59)/BC60 -> 3.8095238 | BD61: =-(BD59)/BD60 -> 3.4782609 | BE61: =-(BE59)/BE60 -> 16 | BF61: =-(BF59)/BF60 -> 3.3126294 | BG61: =-(BG59)/BG60 -> 0 | BH61: =-(BH59)/BH60 -> 0 | ... BJ61: =-(BJ59)/BJ60 -> 0
B62: Buyback as % of FCF | AP62: =+AP59/AP46 -> -0.69714101 | AU62: =+AU59/AU46 -> -0.97536804 | AZ62: =+BA59/BA46 -> -4.0125709 | BE62: =+BE59/BE46 -> -3.1638003
B64: Stock Comp
B65: % of Revenue | AK65: =+AK8/'Income Statement'!AK13 -> 0.17067219 | AP65: =+AP8/'Income Statement'!AP13 -> 0.14383687 | AU65: =+AU8/'Income Statement'!AU13 -> 0.1367228 | AZ65: =+BA8/'Income Statement'!BA13 -> 0.11233131 | BE65: =+BE8/'Income Statement'!BE13 -> 0.10404085 | BF65: =+BF8/'Income Statement'!BF13 -> 0.09403819 | BG65: =+BG8/'Income Statement'!BG13 -> 0.08674398 | BH65: =+BH8/'Income Statement'!BH13 -> 0.081356239 | BI65: =+BI8/'Income Statement'!BI13 -> 0.07734364 | BJ65: =+BJ8/'Income Statement'!BJ13 -> 0.074301324

Sheet FX
C2: EUR | D2: GBP | E2: JPY
B3: 43466 | C3: =_xll.FDS("EURUSD","FG_PRICE("&B3&")") -> #NAME? | D3: =_xll.FDS("GBPUSD","FG_PRICE("&B3&")") -> #NAME? | E3: =_xll.FDSB("JPYUSD","FG_PRICE("&B3&")") -> #NAME?
B4: =B3+1 -> 43467 | C4: =_xll.FDS("EURUSD","FG_PRICE("&B4&")") -> #NAME? | D4: =_xll.FDS("GBPUSD","FG_PRICE("&B4&")") -> #NAME? | E4: =_xll.FDSB("JPYUSD","FG_PRICE("&B4&")") -> #NAME?
B5: =B4+1 -> 43468 | C5: =_xll.FDS("EURUSD","FG_PRICE("&B5&")") -> #NAME? | D5: =_xll.FDS("GBPUSD","FG_PRICE("&B5&")") -> #NAME? | E5: =_xll.FDSB("JPYUSD","FG_PRICE("&B5&")") -> #NAME?
B6: =B5+1 -> 43469 | C6: =_xll.FDS("EURUSD","FG_PRICE("&B6&")") -> #NAME? | D6: =_xll.FDS("GBPUSD","FG_PRICE("&B6&")") -> #NAME? | E6: =_xll.FDSB("JPYUSD","FG_PRICE("&B6&")") -> #NAME? | H6: ='Income Statement'!R3 -> 1Q19 | I6: ='Income Statement'!S3 -> 2Q19 | J6: ='Income Statement'!T3 -> 3Q19 | K6: ='Income Statement'!U3 -> 4Q19 | L6: ='Income Statement'!W3 -> 1Q20 | M6: ='Income Statement'!X3 -> 2Q20 | N6: ='Income Statement'!Y3 -> 3Q20 | O6: ='Income Statement'!Z3 -> 4Q20 | P6: ='Income Statement'!AB3 -> 1Q21 | Q6: ='Income Statement'!AC3 -> 2Q21 | R6: ='Income Statement'!AD3 -> 3Q21 | S6: ='Income Statement'!AE3 -> 4Q21 | T6: ='Income Statement'!AG3 -> 1Q22 | U6: ='Income Statement'!AH3 -> 2Q22 | V6: ='Income Statement'!AI3 -> 3Q22 | W6: ='Income Statement'!AJ3 -> 4Q22 | X6: ='Income Statement'!AL3 -> 1Q23 | Y6: ='Income Statement'!AM3 -> 2Q23 | Z6: ='Income Statement'!AN3 -> 3Q23 | AA6: ='Income Statement'!AO3 -> 4Q23
B7: =B6+1 -> 43470 | C7: =_xll.FDS("EURUSD","FG_PRICE("&B7&")") -> #NAME? | D7: =_xll.FDS("GBPUSD","FG_PRICE("&B7&")") -> #NAME? | E7: =_xll.FDSB("JPYUSD","FG_PRICE("&B7&")") -> #NAME? | G7: EUR | H7: =AVERAGE(C3:C92) -> #NAME? | I7: =AVERAGE(C93:C182) -> #NAME? | J7: =AVERAGE(C184:C273) -> #NAME? | K7: =AVERAGE(C276:C367) -> #NAME? | L7: =AVERAGE(C368:C458) -> #NAME? | M7: =AVERAGE(C459:C549) -> #NAME? | N7: =AVERAGE(C550:C641) -> #NAME? | O7: =AVERAGE(C642:C733) -> #NAME? | P7: =AVERAGE(C734:C823) -> #NAME? | Q7: =AVERAGE(C824:C914) -> #NAME? | R7: =AVERAGE(C915:C1006) -> #NAME? | S7: =AVERAGE(C1007:C1098) -> #NAME? | T7: =AVERAGE(C1099:C1189) -> #NAME? | U7: =AVERAGE(C1189:C1279) -> #NAME? | V7: =AVERAGE(C1280:C1371) -> #NAME? | W7: =AVERAGE(C1372:C1463) -> #NAME? | X7: =AVERAGE(C1464:C1553) -> #NAME? | Y7: =C1554 -> #NAME? | Z7: =Y7 -> #NAME? | AA7: =Z7 -> #NAME?
B8: =B7+1 -> 43471 | C8: =_xll.FDS("EURUSD","FG_PRICE("&B8&")") -> #NAME? | D8: =_xll.FDS("GBPUSD","FG_PRICE("&B8&")") -> #NAME? | E8: =_xll.FDSB("JPYUSD","FG_PRICE("&B8&")") -> #NAME? | G8: y/y | L8: =L7/H7-1 -> #NAME? | M8: =M7/I7-1 -> #NAME? | N8: =N7/J7-1 -> #NAME? | O8: =O7/K7-1 -> #NAME? | P8: =P7/L7-1 -> #NAME? | Q8: =Q7/M7-1 -> #NAME? | R8: =R7/N7-1 -> #NAME? | S8: =S7/O7-1 -> #NAME? | ... AA8: =AA7/W7-1 -> #NAME?
B9: =B8+1 -> 43472 | C9: =_xll.FDS("EURUSD","FG_PRICE("&B9&")") -> #NAME? | D9: =_xll.FDS("GBPUSD","FG_PRICE("&B9&")") -> #NAME? | E9: =_xll.FDSB("JPYUSD","FG_PRICE("&B9&")") -> #NAME?
B10: =B9+1 -> 43473 | C10: =_xll.FDS("EURUSD","FG_PRICE("&B10&")") -> #NAME? | D10: =_xll.FDS("GBPUSD","FG_PRICE("&B10&")") -> #NAME? | E10: =_xll.FDSB("JPYUSD","FG_PRICE("&B10&")") -> #NAME? | G10: GBP | H10: =AVERAGE(D3:D92) -> #NAME? | I10: =AVERAGE(D93:D182) -> #NAME? | J10: =AVERAGE(D184:D273) -> #NAME? | K10: =AVERAGE(D276:D367) -> #NAME? | L10: =AVERAGE(D368:D458) -> #NAME? | M10: =AVERAGE(D459:D549) -> #NAME? | N10: =AVERAGE(D550:D641) -> #NAME? | O10: =AVERAGE(D642:D733) -> #NAME? | P10: =AVERAGE(D734:D823) -> #NAME? | Q10: =AVERAGE(D824:D914) -> #NAME? | R10: =AVERAGE(D915:D1006) -> #NAME? | S10: =AVERAGE(D1007:D1098) -> #NAME? | T10: =AVERAGE(D1099:D1188) -> #NAME? | U10: =AVERAGE(D1189:D1279) -> #NAME? | V10: =AVERAGE(D1280:D1371) -> #NAME? | W10: =AVERAGE(D1372:D1463) -> #NAME? | X10: =AVERAGE(D1464:D1553) -> #NAME? | Y10: =D1554 -> #NAME? | Z10: =Y10 -> #NAME? | AA10: =Z10 -> #NAME?
B11: =B10+1 -> 43474 | C11: =_xll.FDS("EURUSD","FG_PRICE("&B11&")") -> #NAME? | D11: =_xll.FDS("GBPUSD","FG_PRICE("&B11&")") -> #NAME? | E11: =_xll.FDSB("JPYUSD","FG_PRICE("&B11&")") -> #NAME? | G11: y/y | L11: =L10/H10-1 -> #NAME? | M11: =M10/I10-1 -> #NAME? | N11: =N10/J10-1 -> #NAME? | O11: =O10/K10-1 -> #NAME? | P11: =P10/L10-1 -> #NAME? | Q11: =Q10/M10-1 -> #NAME? | R11: =R10/N10-1 -> #NAME? | S11: =S10/O10-1 -> #NAME? | ... AA11: =AA10/W10-1 -> #NAME?
B12: =B11+1 -> 43475 | C12: =_xll.FDS("EURUSD","FG_PRICE("&B12&")") -> #NAME? | D12: =_xll.FDS("GBPUSD","FG_PRICE("&B12&")") -> #NAME? | E12: =_xll.FDSB("JPYUSD","FG_PRICE("&B12&")") -> #NAME?
B13: =B12+1 -> 43476 | C13: =_xll.FDS("EURUSD","FG_PRICE("&B13&")") -> #NAME? | D13: =_xll.FDS("GBPUSD","FG_PRICE("&B13&")") -> #NAME? | E13: =_xll.FDSB("JPYUSD","FG_PRICE("&B13&")") -> #NAME? | G13: JPY | H13: =AVERAGE(E3:E93) -> #NAME? | I13: =AVERAGE(E94:E184) -> #NAME? | J13: =AVERAGE(E185:E276) -> #NAME? | K13: =AVERAGE(E277:E368) -> #NAME? | L13: =AVERAGE(E369:E459) -> #NAME? | M13: =AVERAGE(E460:E550) -> #NAME? | N13: =AVERAGE(E551:E642) -> #NAME? | O13: =AVERAGE(E643:E734) -> #NAME? | P13: =AVERAGE(E735:E824) -> #NAME? | Q13: =AVERAGE(E825:E915) -> #NAME? | R13: =AVERAGE(E916:E1007) -> #NAME? | S13: =AVERAGE(E1008:E1099) -> #NAME? | T13: =AVERAGE(E1010:E1189) -> #NAME? | U13: =AVERAGE(E1190:E1280) -> #NAME? | V13: =AVERAGE(E1281:E1372) -> #NAME? | W13: =AVERAGE(E1372:E1463) -> #NAME? | X13: =AVERAGE(E1464:E1553) -> #NAME? | Y13: =E1554 -> #NAME? | Z13: =Y13 -> #NAME? | AA13: =Z13 -> #NAME?
B14: =B13+1 -> 43477 | C14: =_xll.FDS("EURUSD","FG_PRICE("&B14&")") -> #NAME? | D14: =_xll.FDS("GBPUSD","FG_PRICE("&B14&")") -> #NAME? | E14: =_xll.FDSB("JPYUSD","FG_PRICE("&B14&")") -> #NAME? | G14: y/y | L14: =L13/H13-1 -> #NAME? | M14: =M13/I13-1 -> #NAME? | N14: =N13/J13-1 -> #NAME? | O14: =O13/K13-1 -> #NAME? | P14: =P13/L13-1 -> #NAME? | Q14: =Q13/M13-1 -> #NAME? | R14: =R13/N13-1 -> #NAME? | S14: =S13/O13-1 -> #NAME? | ... AA14: =AA13/W13-1 -> #NAME?
B15: =B14+1 -> 43478 | C15: =_xll.FDS("EURUSD","FG_PRICE("&B15&")") -> #NAME? | D15: =_xll.FDS("GBPUSD","FG_PRICE("&B15&")") -> #NAME? | E15: =_xll.FDSB("JPYUSD","FG_PRICE("&B15&")") -> #NAME?
