Workbook
Name blank: #REF!
Name blank: #REF!
Name blank: #REF!
Name blank: #REF!
Name Current_Q: #REF!
Name Current_Q: #REF!
Name Current_Q: #REF!
Name Current_Q: #REF!
Name export: #REF!
Name export: #REF!
Name export: #REF!
Name export: #REF!
Name FY_92: #REF!
Name FY_92: #REF!
Name FY_92: #REF!
Name FY_92: #REF!
Name FY_93: #REF!
Name FY_93: #REF!
Name FY_93: #REF!
Name FY_94: #REF!
Name FY_94: #REF!
Name FY_94: #REF!
Name N_A: #REF!
Name N_A: #REF!
Name N_A: #REF!
Name N_A: #REF!
Name N_M: #REF!
Name N_M: #REF!
Name Next_Actual_Period_Range: '[16]Income Statement'!$D$3:$BE$6
Name NM_T: #REF!
Name NM_T: #REF!
Name NM_T: #REF!
Name NM_T: #REF!
Name Prior_Q: #REF!
Name Prior_Q: #REF!
Name Prior_Q: #REF!
Name Prior_Q: #REF!
Name Same_Q_Last_Yr: #REF!
Name Same_Q_Last_Yr: #REF!
Name Same_Q_Last_Yr: #REF!
Name Same_Q_Last_Yr: #REF!
Name source: #REF!
Name source: #REF!
Name source: #REF!
Name source: #REF!
Name SPR01A_18: #REF!
Name SPR01C_18: #REF!
Name WIZARD_3YRATCF: #REF!
Name WIZARD_3YRATCF: #REF!
Name WIZARD_3YRATCF: #REF!
Name WIZARD_3YRATCF: #REF!
Name WIZARD_3YREBITDA: #REF!
Name WIZARD_3YREBITDA: #REF!
Name WIZARD_3YREBITDA: #REF!
Name WIZARD_3YRSECGROWTH: #REF!
Name WIZARD_3YRSECGROWTH: #REF!
Name WIZARD_3YRSECGROWTH: #REF!
Name WIZARD_AVGTRADINGVOLUME: #REF!
Name WIZARD_BKVALSHR: #REF!
Name WIZARD_BURNRATE: #REF!

Sheet __FDSCACHE__
B1: This sheet contains FactSet XML data for use with this workbook's =FDS codes. Modifying the worksheet's contents may damage the workbook's =FDS functionality.

Sheet Comparison
B2: SPS Commerce (SPSC)
D5: =IS!CL3 -> 4Q24 | E5: =K5 -> 4Q25 | F5: % Change | G5: =IS!CP3 -> 3Q25 | H5: =K5 -> 4Q25 | I5: % Change | J5: 4Q25E | K5: =IS!CQ3 -> 4Q25 | L5: % Change
B6: Total Revenue | D6: =IS!CL4 -> 170907 | E6: =K6 -> 192652 | F6: =E6/D6-1 -> 0.12723294 | G6: =IS!CP4 -> 189904 | H6: =K6 -> 192652 | I6: =H6/G6-1 -> 0.014470469 | J6: 193547.39 | K6: =IS!CQ4 -> 192652 | L6: =K6/J6-1 -> -0.0046261819
B7: Cost of Revenue | D7: =IS!CL20 -> 52766 | E7: =K7 -> 55144 | F7: =E7/D7-1 -> 0.045066899 | G7: =IS!CP20 -> 54761 | H7: =K7 -> 55144 | I7: =H7/G7-1 -> 0.0069940286 | J7: 58451.31 | K7: =IS!CQ20 -> 55144 | L7: =K7/J7-1 -> -0.056582314
B8: Gross Profit | D8: =D6-D7 -> 118141 | E8: =E6-E7 -> 137508 | F8: =E8/D8-1 -> 0.16393123 | G8: =G6-G7 -> 135143 | H8: =K8 -> 137508 | I8: =H8/G8-1 -> 0.017499982 | J8: 135096.08 | K8: =K6-K7 -> 137508 | L8: =K8/J8-1 -> 0.017853405
C9: Gross Margins | D9: =D8/D6 -> 0.69125899 | E9: =K9 -> 0.71376368 | G9: =G8/G6 -> 0.71163851 | H9: =K9 -> 0.71376368 | J9: 0.698 | K9: =K8/K6 -> 0.71376368 | N9: =K9-D9*1000 -> -690.54523
B11: Operating Expenses
B12: Sales and marketing | D12: =IS!CL25 -> 36449 | E12: =K12 -> 40067 | F12: =E12/D12-1 -> 0.099261982 | G12: =IS!CP25 -> 38836 | H12: =K12 -> 40067 | I12: =H12/G12-1 -> 0.031697394 | J12: 40064.309 | K12: =IS!CQ25 -> 40067 | L12: =K12/J12-1 -> 6.7172457e-05 | N12: =K12-J12 -> 2.6912181
B13: Research and development | D13: =IS!CL27 -> 15049 | E13: =K13 -> 14797 | F13: =E13/D13-1 -> -0.016745299 | G13: =IS!CP27 -> 14922 | H13: =K13 -> 14797 | I13: =H13/G13-1 -> -0.0083768932 | J13: 16451.528 | K13: =IS!CQ27 -> 14797 | L13: =K13/J13-1 -> -0.10056985 | N13: =K13-J13 -> -1654.5278
B14: General and administrative | D14: =IS!CL29 -> 21744 | E14: =K14 -> 27969 | F14: =E14/D14-1 -> 0.28628587 | G14: =IS!CP29 -> 26248 | H14: =K14 -> 27969 | I14: =H14/G14-1 -> 0.0655669 | J14: 24580.518 | K14: =IS!CQ29 -> 27969 | L14: =K14/J14-1 -> 0.13785235 | N14: =K14-J14 -> 3388.4821
B15: Total Operating Expense | D15: =SUM(D12:D14) -> 73242 | E15: =K15 -> 82833 | F15: =E15/D15-1 -> 0.13094946 | G15: =SUM(G12:G14) -> 80006 | H15: =K15 -> 82833 | I15: =H15/G15-1 -> 0.03533485 | J15: 81096.354 | K15: =SUM(K12:K14) -> 82833 | L15: =K15/J15-1 -> 0.021414594
B17: Proforma Operating Income | D17: =D8-D15 -> 44899 | E17: =K17 -> 54675 | F17: =E17/D17-1 -> 0.21773313 | G17: =G8-G15 -> 55137 | H17: =K17 -> 54675 | I17: =H17/G17-1 -> -0.0083791284 | J17: 53999.721 | K17: =K8-K15 -> 54675 | L17: =K17/J17-1 -> 0.01250524 | N17: =K17-J17 -> 675.27947
C18: Proforma Operating Margins | D18: =D17/D6 -> 0.26271013 | E18: =K18 -> 0.28380188 | F18: =E18/D18-1 -> 0.080285265 | G18: =G17/G6 -> 0.29034144 | H18: =K18 -> 0.28380188 | I18: =H18/G18-1 -> -0.02252367 | J18: 0.279 | K18: =K17/K6 -> 0.28380188 | L18: =K18/J18-1 -> 0.017211043
B20: GAAP Adjustments | D20: =IS!CL40 -> 20155 | E20: =K20 -> 19989 | F20: =E20/D20-1 -> -0.0082361697 | G20: =IS!CP40 -> 23946 | H20: =K20 -> 19989 | I20: =H20/G20-1 -> -0.16524681 | J20: 24500 | K20: =IS!CQ40 -> 19989 | L20: =K20/J20-1 -> -0.18412245
B22: GAAP Operating Income | D22: =D17-D20 -> 24744 | E22: =K22 -> 34686 | F22: =E22/D22-1 -> 0.40179437 | G22: =G17-G20 -> 31191 | H22: =K22 -> 34686 | I22: =H22/G22-1 -> 0.11205155 | J22: 29499.721 | K22: =K17-K20 -> 34686 | L22: =K22/J22-1 -> 0.17580775
C23: GAAP Operating Margins | D23: =D22/D6 -> 0.14478049 | E23: =K23 -> 0.18004485 | F23: =E23/D23-1 -> 0.24357116 | G23: =G22/G6 -> 0.16424615 | H23: =K23 -> 0.18004485 | I23: =H23/G23-1 -> 0.096189181 | J23: 0.15241601 | K23: =K22/K6 -> 0.18004485 | L23: =K23/J23-1 -> 0.18127253
B25: Other Income | D25: =IS!CL47 -> -373 | E25: =K25 -> 1292 | F25: =E25/D25-1 -> -4.463807 | G25: =IS!CP47 -> 1260 | H25: =K25 -> 1292 | I25: =H25/G25-1 -> 0.025396825 | J25: 900 | K25: =IS!CQ47 -> 1292 | L25: =K25/J25-1 -> 0.43555556
B26: Non-GAAP Other Income | D26: =IS!CL50 -> 2234 | E26: =K26 -> 1036 | F26: =E26/D26-1 -> -0.53625783 | G26: =IS!CP50 -> 1065 | H26: =K26 -> 1036 | I26: =H26/G26-1 -> -0.027230047 | J26: 900 | K26: =IS!CQ50 -> 1036 | L26: =K26/J26-1 -> 0.15111111
B28: Proforma Income Before Taxes | D28: =IS!CL55 -> 47133 | E28: =K28 -> 55711 | F28: =E28/D28-1 -> 0.18199563 | G28: =IS!CP55 -> 56202 | H28: =K28 -> 55711 | I28: =H28/G28-1 -> -0.0087363439 | J28: 54899.721 | K28: =IS!CQ55 -> 55711 | L28: =K28/J28-1 -> 0.014777479
B29: Income Tax | D29: =IS!CL56 -> 13183 | E29: =K29 -> 12481 | F29: =E29/D29-1 -> -0.053250398 | G29: =IS!CP56 -> 13247 | H29: =K29 -> 12481 | I29: =H29/G29-1 -> -0.057824413 | J29: 16469.916 | K29: =IS!CQ56 -> 12481 | L29: =K29/J29-1 -> -0.24219408
B30: Proforma Net Income | D30: =D28-D29 -> 33950 | E30: =K30 -> 43230 | F30: =E30/D30-1 -> 0.27334315 | G30: =G28-G29 -> 42955 | H30: =K30 -> 43230 | I30: =H30/G30-1 -> 0.0064020487 | J30: 38429.804 | K30: =K28-K29 -> 43230 | L30: =K30/J30-1 -> 0.12490815
B32: GAAP Income Before Taxes | D32: =D22+D25 -> 24371 | E32: =K32 -> 35978 | F32: =E32/D32-1 -> 0.47626277 | G32: =G22+G25 -> 32451 | H32: =K32 -> 35978 | I32: =H32/G32-1 -> 0.10868694 | J32: 30399.721 | K32: =K22+K25 -> 35978 | L32: =K32/J32-1 -> 0.18349772
B33: Income Tax | D33: =IS!CL62 -> 6812 | E33: =K33 -> 10137 | F33: =E33/D33-1 -> 0.48810922 | G33: =IS!CP62 -> 6882 | H33: =K33 -> 10137 | I33: =H33/G33-1 -> 0.47297297 | J33: 9119.9162 | K33: =IS!CQ62 -> 10137 | L33: =K33/J33-1 -> 0.11152338
B34: GAAP Net Income | D34: =D32-D33 -> 17559 | E34: =K34 -> 25841 | F34: =E34/D34-1 -> 0.47166695 | G34: =G32-G33 -> 25569 | H34: =K34 -> 25841 | I34: =H34/G34-1 -> 0.010637882 | J34: 21279.804 | K34: =K32-K33 -> 25841 | L34: =K34/J34-1 -> 0.21434387
B35: Proforma EPS | D35: =D30/D37 -> 0.89681953 | E35: =K35 -> 1.1447713 | F35: =E35/D35-1 -> 0.27647905 | G35: =G30/G37 -> 1.130603 | H35: =K35 -> 1.1447713 | I35: =H35/G35-1 -> 0.012531659 | J35: 1.0035726 | K35: =K30/K37 -> 1.1447713 | L35: =K35/J35-1 -> 0.14069612 | N35: =K35-J35 -> 0.14119877
B36: GAAP EPS | D36: =D34/D37 -> 0.46383664 | E36: =K36 -> 0.68429415 | F36: =E36/D36-1 -> 0.47529127 | G36: =G34/G37 -> 0.67299239 | H36: =H34/H37 -> 0.68429415 | I36: =H36/G36-1 -> 0.016793291 | J36: 0.55571004 | K36: =K34/K37 -> 0.68429415 | L36: =K36/J36-1 -> 0.23138707
B37: Diluted Shares Outstanding | D37: =IS!CL73 -> 37856 | E37: =K37 -> 37763 | F37: =E37/D37-1 -> -0.0024566779 | G37: =IS!CP73 -> 37993 | H37: =K37 -> 37763 | I37: =H37/G37-1 -> -0.0060537467 | J37: 38293 | K37: =IS!CQ73 -> 37763 | L37: =K37/J37-1 -> -0.01384065
B39: Source: Company reports and Needham & Co estimates

Sheet Guidance
D4: Prior FY26 Guide | E4: New FY26 Guide | F4: Delta | G4: 3Q26 Guide | H4: =LEFT(G4,4)&" Result" -> 3Q26 Result | I4: =LEFT(G4,4)&" Beat" -> 3Q26 Beat | J4: Rest of Year Raise / (Reduce)
C5: Revenue | D5: =IS!CR4*1.075/1000 -> 807.86788 | E5: =AVERAGE(798.5,806.9) -> 802.7 | F5: =E5-D5 -> -5.167875 | G5: =AVERAGE(191.7,193.2) -> 192.45 | H5: =Comparison!K6/1000 -> 192.652 | I5: =H5-G5 -> 0.202 | J5: =F5-I5 -> -5.369875
C6: Growth | D6: =D5/(IS!CR4/1000)-1 -> 0.075 | E6: =E5/(IS!CR4/1000)-1 -> 0.068123299
C7: Adj EBITDA | D7: =D8*D5 -> 264.87688 | E7: 263.25 | F7: =E7-D7 -> -1.6268825 | G7: =AVERAGE(57.9,59.9) -> 58.9 | H7: =IS!CP52/1000 -> 60.48 | I7: =H7-G7 -> 1.58 | J7: =F7-I7 -> -3.2068825
C8: Margin | D8: =IS!CR53+0.02 -> 0.32787154 | E8: =E7/E5 -> 0.32795565
C9: Non-GAAP EPS | D9: N/A | E9: 4.46 | F9: N/A | G9: 0.98 | H9: =Comparison!K35 -> 1.1447713 | I9: =H9-G9 -> 0.16477134 | J9: =F9-I9 -> #VALUE!

Sheet IS
B2: SPS Commerce (SPSC)
B3: Income Statement | D3: 2005 | E3: 2006 | F3: 2007 | G3: 1Q08 | H3: 2Q08 | I3: 2Q08 | J3: 4Q08 | K3: 2008 | L3: 1Q09 | M3: 2Q09 | N3: 2Q09 | O3: 4Q09 | P3: 2009 | Q3: 1QA10 | R3: 2QA10 | S3: 3Q10 | T3: 4Q10 | U3: 2010 | V3: 1Q11 | W3: 2Q11 | X3: 3Q11 | Y3: 4Q11 | Z3: 2011 | AA3: 1Q12 | AB3: 2Q12 | AC3: 3Q12 | AD3: 4Q12 | AE3: 2012 | AF3: 1Q13 | AG3: 2Q13 | AH3: 3Q13 | AI3: 4Q13 | AJ3: 2013 | AK3: 1Q14 | AL3: 2Q14 | AM3: 3Q14 | AN3: 4Q14 | AO3: 2014 | AP3: 1Q15 | AQ3: 2Q15 | AR3: 3Q15 | AS3: 4Q15 | AT3: 2015 | AU3: 1Q16 | AV3: 2Q16 | AW3: 3Q16 | AX3: 4Q16 | AY3: 2016 | AZ3: 1Q17 | BA3: 2Q17 | BB3: 3Q17 | BC3: 4Q17 | BD3: 2017 | BE3: 1Q18 | BF3: 2Q18 | BG3: 3Q18 | BH3: 4Q18 | BI3: 2018 | BJ3: 1Q19 | BK3: 2Q19 | BL3: 3Q19 | BM3: 4Q19 | BN3: 2019 | BO3: 1Q20 | BP3: 2Q20 | BQ3: 3Q20 | BR3: 4Q20 | BS3: 2020 | BT3: 1Q21 | BU3: 2Q21 | BV3: 3Q21 | BW3: 4Q21 | BX3: 2021 | BY3: 1Q22 | BZ3: 2Q22 | CA3: 3Q22 | CB3: 4Q22 | CC3: 2022 | CD3: 1Q23 | CE3: 2Q23 | CF3: 3Q23 | CG3: 4Q23 | CH3: 2023 | CI3: 1Q24 | CJ3: 2Q24 | CK3: 3Q24 | CL3: 4Q24 | CM3: 2024 | CN3: 1Q25 | CO3: 2Q25 | CP3: 3Q25 | CQ3: 4Q25 | CR3: 2025 | CS3: 1Q26E | CT3: 2Q26E | CU3: 3Q26E | CV3: 4Q26E | CW3: 2026E
B4: Total Revenue | D4: 13827 | E4: 19859 | F4: 25198 | G4: 6957 | H4: 7586 | I4: 8074 | J4: 8080 | K4: =SUM(G4:J4) -> 30697 | L4: 8531 | M4: 9600 | N4: 9634 | O4: 9981 | P4: =SUM(L4:O4) -> 37746 | Q4: 10243 | R4: 10944 | S4: 11491 | T4: 11919 | U4: =SUM(Q4:T4) -> 44597 | V4: 12649 | W4: 13937 | X4: 15529 | Y4: 15854 | Z4: =SUM(V4:Y4) -> 57969 | AA4: 16534 | AB4: 17821 | AC4: 20267 | AD4: 22484 | AE4: =SUM(AA4:AD4) -> 77106 | AF4: 23752 | AG4: 25658 | AH4: 27008 | AI4: 27973 | AJ4: =SUM(AF4:AI4) -> 104391 | AK4: 28939 | AL4: 31100 | AM4: 32506 | AN4: 35402 | AO4: =SUM(AK4:AN4) -> 127947 | AP4: 36970 | AQ4: 38846 | AR4: 40354 | AS4: 42348 | AT4: =SUM(AP4:AS4) -> 158518 | AU4: 45599 | AV4: 47351 | AW4: 49284 | AX4: 51061 | AY4: =SUM(AU4:AX4) -> 193295 | AZ4: 51932 | BA4: 54284 | BB4: 56150 | BC4: 58200 | BD4: =SUM(AZ4:BC4) -> 220566 | BE4: 59092 | BF4: 61091 | BG4: 62868 | BH4: 65189 | BI4: =SUM(BE4:BH4) -> 248240 | BJ4: 66934 | BK4: 68529 | BL4: 70928 | BM4: 72733 | BN4: =SUM(BJ4:BM4) -> 279124 | BO4: 74192 | BP4: 75573 | BQ4: =79557 -> 79557 | BR4: 83308 | BS4: =SUM(BO4:BR4) -> 312630 | BT4: 90094 | BU4: 94539 | BV4: 97887 | BW4: 102756 | BX4: =SUM(BT4:BW4) -> 385276 | BY4: 105193 | BZ4: 109178 | CA4: 114486 | CB4: 122018 | CC4: =SUM(BY4:CB4) -> 450875 | CD4: 125868 | CE4: 130416 | CF4: 135661 | CG4: 144965 | CH4: =SUM(CD4:CG4) -> 536910 | CI4: 149576 | CJ4: 153596 | CK4: 163686 | CL4: 170907 | CM4: =SUM(CI4:CL4) -> 637765 | CN4: 181549 | CO4: 187400 | CP4: 189904 | CQ4: 192652 | CR4: =SUM(CN4:CQ4) -> 751505 | CS4: =CS7+CS16 -> 192631.61 | CT4: =CT7+CT16 -> 197698.72 | CU4: =CU7+CU16 -> 204419.39 | CV4: =CV7+CV16 -> 207966.86 | CW4: =SUM(CS4:CV4) -> 802716.59
C5: Y/Y Growth | E5: =E4/D4-1 -> 0.43624792 | F5: =F4/E4-1 -> 0.26884536 | K5: =K4/F4-1 -> 0.21823161 | L5: =L4/G4-1 -> 0.22624695 | M5: =M4/H4-1 -> 0.26548906 | N5: =N4/I4-1 -> 0.19321278 | O5: =O4/J4-1 -> 0.23527228 | P5: =P4/K4-1 -> 0.22963156 | Q5: =Q4/L4-1 -> 0.20067987 | R5: =R4/M4-1 -> 0.14 | ... CW5: =CW4/CR4-1 -> 0.068145371
C6: Q/Q Growth | H6: =H4/G4-1 -> 0.090412534 | I6: =I4/H4-1 -> 0.064329027 | J6: =J4/I4-1 -> 0.00074312608 | L6: =L4/J4-1 -> 0.055816832 | M6: =M4/L4-1 -> 0.1253077 | N6: =N4/M4-1 -> 0.0035416667 | O6: =O4/N4-1 -> 0.036018269 | Q6: =Q4/O4-1 -> 0.026249875 | R6: =R4/Q4-1 -> 0.068436981 | S6: =S4/R4-1 -> 0.049981725 | T6: =T4/S4-1 -> 0.037246541 | V6: =V4/T4-1 -> 0.061246749 | W6: =W4/V4-1 -> 0.10182623 | X6: =X4/W4-1 -> 0.11422831 | Y6: =Y4/X4-1 -> 0.020928585 | AA6: =AA4/Y4-1 -> 0.042891384 | AB6: =AB4/AA4-1 -> 0.077839603 | AC6: =AC4/AB4-1 -> 0.1372538 | AD6: =AD4/AC4-1 -> 0.10938965 | AF6: =AF4/AD4-1 -> 0.056395659 | AG6: =AG4/AF4-1 -> 0.080245874 | AH6: =AH4/AG4-1 -> 0.052615169 | AI6: =AI4/AH4-1 -> 0.035730154 | AK6: =AK4/AI4-1 -> 0.0345333 | AL6: =AL4/AK4-1 -> 0.074674315 | AM6: =AM4/AL4-1 -> 0.045209003 | AN6: =AN4/AM4-1 -> 0.089091245 | AP6: =AP4/AN4-1 -> 0.044291283 | AQ6: =AQ4/AP4-1 -> 0.050743846 | AR6: =AR4/AQ4-1 -> 0.038819956 | AS6: =AS4/AR4-1 -> 0.049412698 | AU6: =AU4/AS4-1 -> 0.076768679 | AV6: =AV4/AU4-1 -> 0.038421895 | AW6: =AW4/AV4-1 -> 0.040822791 | AX6: =AX4/AW4-1 -> 0.036056327 | AZ6: =AZ4/AX4-1 -> 0.017058029 | BA6: =BA4/AZ4-1 -> 0.045289995 | BB6: =BB4/BA4-1 -> 0.03437477 | BC6: =BC4/BB4-1 -> 0.03650935 | BE6: =BE4/BC4-1 -> 0.01532646 | BF6: =BF4/BE4-1 -> 0.033828606 | BG6: =BG4/BF4-1 -> 0.029087754 | BH6: =BH4/BG4-1 -> 0.036918623 | BJ6: =BJ4/BH4-1 -> 0.02676832 | BK6: =BK4/BJ4-1 -> 0.023829444 | BL6: =BL4/BK4-1 -> 0.035007077 | BM6: =BM4/BL4-1 -> 0.025448342 | BO6: =BO4/BM4-1 -> 0.02005967 | BP6: =BP4/BO4-1 -> 0.018613867 | BQ6: =BQ4/BP4-1 -> 0.05271724 | BR6: =BR4/BQ4-1 -> 0.047148585 | BT6: =BT4/BR4-1 -> 0.081456763 | BU6: =BU4/BT4-1 -> 0.049337359 | BV6: =BV4/BU4-1 -> 0.035413956 | BW6: =BW4/BV4-1 -> 0.049741028 | BY6: =BY4/BW4-1 -> 0.023716377 | BZ6: =BZ4/BY4-1 -> 0.037882749 | CA6: =CA4/BZ4-1 -> 0.048617853 | CB6: =CB4/CA4-1 -> 0.065789704 | CD6: =CD4/CB4-1 -> 0.031552722 | CE6: =CE4/CD4-1 -> 0.036133092 | CF6: =CF4/CE4-1 -> 0.040217458 | CG6: =CG4/CF4-1 -> 0.068582717 | CI6: =CI4/CG4-1 -> 0.031807678 | CJ6: =CJ4/CI4-1 -> 0.026875969 | CK6: =CK4/CJ4-1 -> 0.065691815 | CL6: =CL4/CK4-1 -> 0.044114952 | CN6: =CN4/CL4-1 -> 0.062267783 | CO6: =CO4/CN4-1 -> 0.032228214 | CP6: =CP4/CO4-1 -> 0.013361793 | CQ6: =CQ4/CP4-1 -> 0.014470469 | CS6: =CS4/CQ4-1 -> -0.00010581515 | CT6: =CT4/CS4-1 -> 0.026304641 | CU6: =CU4/CT4-1 -> 0.033994498 | CV6: =CV4/CU4-1 -> 0.017353908
C7: Organic Revenue | V7: =V4 -> 12649 | W7: =W4-W9 -> 13687 | X7: =X4-X9 -> 14579 | Y7: =Y4-Y9 -> 14904 | Z7: =SUM(V7:Y7) -> 55819 | AA7: =AA4-AA9 -> 15584 | AB7: =AB4-AB9 -> 17221 | AC7: =AC4-AC9 -> 18467 | AD7: =AD4-AD9 -> 19384 | AE7: =SUM(AA7:AD7) -> 70656 | AF7: =AF4-AF9 -> 20752 | AG7: =AG4-AG9 -> 22658 | AH7: =AH4-AH9 -> 25508 | AI7: =AI4-AI9 -> 27973 | AJ7: =SUM(AF7:AI7) -> 96891 | AK7: =AK4-AK9 -> 28939 | AL7: =AL4-AL9 -> 31100 | AM7: =AM4-AM9 -> 32506 | AN7: =AN4-AN9 -> 35402 | AO7: =SUM(AK7:AN7) -> 127947 | AP7: =AP4-AP9 -> 36970 | AQ7: =AQ4-AQ9 -> 38846 | AR7: =AR4-AR9 -> 40354 | AS7: =AS4-AS9 -> 42348 | AT7: =SUM(AP7:AS7) -> 158518 | AU7: =AU14+AU18 -> 44031.51 | AV7: =AV14+AV18 -> 45500.915 | AW7: =AW14+AW18 -> 46907.624 | AX7: =AX14+AX18 -> 48781.036 | AY7: =SUM(AU7:AX7) -> 185221.08 | AZ7: =AZ14+AZ18 -> 51932 | BA7: =BA14+BA18 -> 54284 | BB7: =BB14+BB18 -> 56150 | BC7: =BC14+BC18 -> 58200 | BD7: =SUM(AZ7:BC7) -> 220566 | BE7: =BE14+BE18 -> 59092 | BF7: =BF14+BF18 -> 61091 | BG7: =BG14+BG18 -> 62868 | BH7: =BH14+BH18 -> 65189 | BI7: =SUM(BE7:BH7) -> 248240 | BJ7: =BJ14+BJ18 -> 65809 | BK7: =BK14+BK18 -> 67404 | BL7: =BL14+BL18 -> 69803 | BM7: =BM14+BM18 -> 71733 | BN7: =SUM(BJ7:BM7) -> 274749 | BO7: =BO14+BO18 -> 74192 | BP7: =BP14+BP18 -> 75573 | BQ7: =BQ14+BQ18 -> 79557 | BR7: =BR14+BR18 -> 83308 | BS7: =SUM(BO7:BR7) -> 312630 | BT7: =BT14+BT18 -> 88644 | BU7: =BU14+BU18 -> 92639 | BV7: =BV14+BV18 -> 95537 | BW7: =BW14+BW18 -> 99406 | BX7: =SUM(BT7:BW7) -> 376226 | BY7: =BY14+BY18 -> 104493 | BZ7: =BZ14+BZ18 -> 108428 | CA7: =CA14+CA18 -> 112736 | CB7: =CB14+CB18 -> 118268 | CC7: =SUM(BY7:CB7) -> 443925 | CD7: =CD14+CD18 -> 122368 | CE7: =CE14+CE18 -> 126641 | CF7: =CF14+CF18 -> 132711 | CG7: =CG14+CG18 -> 138765 | CH7: =SUM(CD7:CG7) -> 520485 | CI7: =CI14+CI18 -> 145576 | CJ7: =CJ14+CJ18 -> 148996 | CK7: =CK14+CK18 -> 160736 | CL7: =CL14+CL18 -> 164707 | CM7: =SUM(CI7:CL7) -> 620015 | CN7: =CN14+CN18 -> 167349 | CO7: =CO14+CO18 -> 170950 | CP7: =CP14+CP18 -> 177654 | CQ7: =CQ14+CQ18 -> 182952 | CR7: =SUM(CN7:CQ7) -> 698905 | CS7: =CS14+CS18 -> 188631.61 | CT7: =CT14+CT18 -> 197698.72 | CU7: =CU14+CU18 -> 204419.39 | CV7: =CV14+CV18 -> 207966.86 | CW7: =SUM(CS7:CV7) -> 798716.59
C8: y/y growth | W8: =W7/R4-1 -> 0.25063962 | X8: =X7/S4-1 -> 0.26873205 | Y8: =Y7/T4-1 -> 0.25044047 | Z8: =Z7/U4-1 -> 0.25163128 | AA8: =AA7/V4-1 -> 0.23203415 | AB8: =AB7/W4-1 -> 0.23563177 | AC8: =AC7/X4-1 -> 0.18919441 | AD8: =AD7/Y4-1 -> 0.22265674 | ... AT8: =AT7/AO4-1 -> 0.23893487 | AU8: =AU7/AP7-1 -> 0.19100649 | AV8: =AV7/AQ7-1 -> 0.17131532 | AW8: =AW7/AR7-1 -> 0.16240333 | AX8: =AX7/AS7-1 -> 0.15190884 | AY8: =AY7/AT4-1 -> 0.16845459 | AZ8: =AZ7/AU4-1 -> 0.13888462 | BA8: =BA7/AV4-1 -> 0.14641718 | BB8: =BB7/AW4-1 -> 0.13931499 | BC8: =BC7/AX4-1 -> 0.13981316 | BD8: =BD7/AY4-1 -> 0.14108487 | BE8: =BE7/AZ4-1 -> 0.1378726 | BF8: =BF7/BA4-1 -> 0.12539607 | ... CW8: =CW7/CR4-1 -> 0.062822719
V9: DirectEDI | W9: 250 | X9: 950 | Y9: 950 | Z9: =SUM(V9:Y9) -> 2150 | AA9: 950 | AB9: 600 | AC9: 1800 | AD9: 3100 | AE9: =SUM(AA9:AD9) -> 6450 | AF9: 3000 | AG9: 3000 | AH9: 1500 | AJ9: =SUM(AF9:AI9) -> 7500 | AO9: =SUM(AK9:AN9) -> 0 | AT9: =SUM(AP9:AS9) -> 0
C10: Recurring revenue | K10: =K11*K4 -> 25478.51 | L10: =L11*L4 -> 6910.11 | M10: =M11*M4 -> 7488 | N10: =N11*N4 -> 7803.54 | O10: =P10-(L10+M10+N10) -> 7995.15 | P10: =P11*P4 -> 30196.8 | Q10: =Q11*Q4 -> 8399.26 | R10: =R11*R4 -> 9083.52 | S10: =S11*S4 -> 9652.44 | T10: =U10-(Q10+R10+S10) -> 10326.26 | U10: =U11*U4 -> 37461.48 | V10: =V11*V4 -> 10498.67 | W10: =W11*W4 -> 11707.08 | X10: =X11*X4 -> 13199.65 | Y10: =Z10-(V10+W10+X10) -> 13868.25 | Z10: =Z11*Z4 -> 49273.65 | AA10: =AA11*AA4 -> 14384.58 | AB10: =AB11*AB4 -> 15326.06 | AC10: =AC11*AC4 -> 17834.96 | AD10: =AE10-(AA10+AB10+AC10) -> 20307.68 | AE10: =AE11*AE4 -> 67853.28 | AF10: =AF4*AF11 -> 21139.28 | AG10: =AG4*AG11 -> 22579.04 | AH10: =AH4*AH11 -> 24037.12 | AI10: =AJ10-(AF10+AG10+AH10) -> 25152.55 | AJ10: =AJ11*AJ4 -> 92907.99 | AK10: =AK4*AK11 -> 26001.314 | AL10: =AL4*AL11 -> 28087.813 | AM10: =AM4*AM11 -> 29325.286 | AN10: =AO10-(AK10+AL10+AM10) -> 31737.887 | AO10: =AO11*AO4 -> 115152.3 | AP10: =AP4*AP11 -> 33273 | AQ10: =AQ4*AQ11 -> 35349.86 | AR10: =AR4*AR11 -> 36722.14 | AS10: =AT10-(AP10+AQ10+AR10) -> 38589.344 | AT10: =AT11*AT4 -> 143934.34 | AU10: =AU11*AU4 -> 41495.09 | AV10: =AV11*AV4 -> 43562.92 | AW10: =AW11*AW4 -> 45341.28 | AX10: =AY10-(AU10+AV10+AW10) -> 46657.71 | AY10: 177057 | AZ10: =AZ11*AZ4 -> 47777.44 | BA10: =BA11*BA4 -> 49941.28 | BB10: =BB11*BB4 -> 51658 | BC10: =BD10-(AZ10+BA10+BB10) -> 54543.28 | BD10: 203920 | BE10: 54860 | BF10: 56430 | BG10: 58644 | BH10: =BI10-(BE10+BF10+BG10) -> 60720 | BI10: =230654 -> 230654 | BJ10: =BJ4*BJ11 -> 62917.96 | BK10: =BK4*BK11 -> 64417.26 | BL10: =BL4*BL11 -> 66672.32 | BM10: =BM4*BM11 -> 68369.02 | BN10: =SUM(BJ10:BM10) -> 262376.56 | BO10: =BO11*BO4 -> 69740.48 | BP10: =BP11*BP4 -> 71038.62 | BQ10: =BQ11*BQ4 -> 75579.15 | BR10: =BR11*BR4 -> 78309.52 | BS10: =SUM(BO10:BR10) -> 294667.77 | BT10: =BT4*BT11 -> 82886.48 | BU10: =BU11*BU4 -> 86975.88 | BV10: =BV11*BV4 -> 90056.04 | BW10: =BW11*BW4 -> 94535.52 | BX10: =SUM(BT10:BW10) -> 354453.92 | BY10: 97567 | BZ10: 101163 | CA10: 106553 | CB10: =419047-SUM(BY10:CA10) -> 113764 | CC10: =SUM(BY10:CB10) -> 419047 | CD10: 117301 | CE10: 121523 | CF10: 127371 | CG10: =502013-SUM(CD10:CF10) -> 135818 | CH10: =SUM(CD10:CG10) -> 502013 | CI10: 139684 | CJ10: =CJ11*CJ4 -> 144380.24 | CK10: =CK4*CK11 -> 153864.84 | CL10: =CG10*1.19 -> 161623.42 | CM10: =SUM(CI10:CL10) -> 599552.5 | CN10: 172329 | CO10: =CO11*CO4 -> 179904 | CP10: =CP11*CP4 -> 182307.84 | CQ10: =CQ11*CQ4 -> 184945.92 | CR10: =SUM(CN10:CQ10) -> 719486.76 | CS10: =CS14+CS16 -> 185031.61 | CT10: =CT14+CT16 -> 189798.72 | CU10: =CU14+CU16 -> 195069.39 | CV10: =CV14+CV16 -> 198816.86 | CW10: =SUM(CS10:CV10) -> 768716.59
C11: % ot total Rev | K11: 0.83 | L11: 0.81 | M11: 0.78 | N11: 0.81 | O11: 0.82 | P11: 0.8 | Q11: 0.82 | R11: 0.83 | S11: 0.84 | T11: =T10/T4 -> 0.86636966 | U11: 0.84 | V11: 0.83 | W11: 0.84 | X11: 0.85 | Y11: =Y10/Y4 -> 0.8747477 | Z11: 0.85 | AA11: 0.87 | AB11: 0.86 | AC11: 0.88 | AD11: =AD10/AD4 -> 0.90320584 | AE11: 0.88 | AF11: 0.89 | AG11: 0.88 | AH11: 0.89 | AI11: =AI10/AI4 -> 0.89917242 | AJ11: 0.89 | AK11: 0.89848697 | AL11: 0.9031451 | AM11: 0.90214995 | AN11: =AN10/AN4 -> 0.89649982 | AO11: 0.9 | AP11: 0.9 | AQ11: 0.91 | AR11: 0.91 | AS11: =AS10/AS4 -> 0.9112436 | AT11: 0.908 | AU11: 0.91 | AV11: 0.92 | AW11: 0.92 | AX11: =AX10/AX4 -> 0.91376413 | AY11: =AY10/AY4 -> 0.91599369 | AZ11: 0.92 | BA11: 0.92 | BB11: 0.92 | BC11: =BC10/BC4 -> 0.93716976 | BD11: =BD10/BD4 -> 0.92453053 | BE11: =BE10/BE4 -> 0.92838286 | BF11: =BF10/BF4 -> 0.92370398 | BG11: =BG10/BG4 -> 0.93281161 | BH11: =BH10/BH4 -> 0.93144549 | BI11: =BI10/BI4 -> 0.92915727 | BJ11: 0.94 | BK11: 0.94 | BL11: 0.94 | BM11: 0.94 | BO11: 0.94 | BP11: 0.94 | BQ11: 0.95 | BR11: 0.94 | BT11: 0.92 | BU11: 0.92 | BV11: 0.92 | BW11: 0.92 | BY11: =BY10/BY4 -> 0.92750468 | BZ11: =BZ10/BZ4 -> 0.92658777 | CA11: =CA10/CA4 -> 0.93070768 | CB11: =CB10/CB4 -> 0.93235424 | CD11: =CD10/CD4 -> 0.93193663 | CE11: =CE10/CE4 -> 0.93181051 | CF11: =CF10/CF4 -> 0.9388918 | CG11: =CG10/CG4 -> 0.93690201 | CI11: =CI10/CI4 -> 0.9338664 | CJ11: 0.94 | CK11: 0.94 | CL11: =CL10/CL4 -> 0.94568052 | CN11: 0.95 | CO11: 0.96 | CP11: 0.96 | CQ11: 0.96 | CS11: =CS10/CS4 -> 0.96054646 | CT11: =CT10/CT4 -> 0.96004021 | CU11: =CU10/CU4 -> 0.9542607 | CV11: =CV10/CV4 -> 0.95600261
C12: Y/Y Growth | K12: =K10/F10-1 -> #DIV/0! | L12: =L10/G10-1 -> #DIV/0! | M12: =M10/H10-1 -> #DIV/0! | N12: =N10/I10-1 -> #DIV/0! | O12: =O10/J10-1 -> #DIV/0! | P12: =P10/K10-1 -> 0.18518705 | Q12: =Q10/L10-1 -> 0.21550308 | R12: =R10/M10-1 -> 0.21307692 | ... CW12: =CW10/CR10-1 -> 0.068423535
C13: Q/Q Growth | L13: =L4/J4-1 -> 0.055816832 | M13: =M4/L4-1 -> 0.1253077 | N13: =N4/M4-1 -> 0.0035416667 | O13: =O4/N4-1 -> 0.036018269 | Q13: =Q4/O4-1 -> 0.026249875 | R13: =R4/Q4-1 -> 0.068436981 | S13: =S4/R4-1 -> 0.049981725 | T13: =T4/S4-1 -> 0.037246541 | V13: =V4/T4-1 -> 0.061246749 | W13: =W4/V4-1 -> 0.10182623 | X13: =X4/W4-1 -> 0.11422831 | Y13: =Y4/X4-1 -> 0.020928585 | AA13: =AA4/Y4-1 -> 0.042891384 | AB13: =AB4/AA4-1 -> 0.077839603 | AC13: =AC4/AB4-1 -> 0.1372538 | AD13: =AD4/AC4-1 -> 0.10938965 | AF13: =AF10/AD10-1 -> 0.040950025 | AG13: =AG10/AF10-1 -> 0.06810828 | AH13: =AH10/AG10-1 -> 0.064576705 | AI13: =AI10/AH10-1 -> 0.046404478 | AK13: =AK10/AI10-1 -> 0.033744666 | AL13: =AL10/AK10-1 -> 0.080245874 | AM13: =AM10/AL10-1 -> 0.044057322 | AN13: =AN10/AM10-1 -> 0.082270303 | AP13: =AP10/AN10-1 -> 0.048368482 | AQ13: =AQ10/AP10-1 -> 0.062418778 | AR13: =AR10/AQ10-1 -> 0.038819956 | AS13: =AS10/AR10-1 -> 0.050846819 | AU13: =AU4/AS4-1 -> 0.076768679 | AV13: =AV4/AU4-1 -> 0.038421895 | AW13: =AW4/AV4-1 -> 0.040822791 | AX13: =AX4/AW4-1 -> 0.036056327 | AZ13: =AZ4/AX4-1 -> 0.017058029 | BA13: =BA4/AZ4-1 -> 0.045289995 | BB13: =BB4/BA4-1 -> 0.03437477 | BC13: =BC4/BB4-1 -> 0.03650935 | BE13: =BE4/BC4-1 -> 0.01532646 | BF13: =BF4/BE4-1 -> 0.033828606 | BG13: =BG4/BF4-1 -> 0.029087754 | BH13: =BH4/BG4-1 -> 0.036918623 | BJ13: =BJ4/BH4-1 -> 0.02676832 | BK13: =BK4/BJ4-1 -> 0.023829444 | BL13: =BL4/BK4-1 -> 0.035007077 | BM13: =BM4/BL4-1 -> 0.025448342 | BO13: =BO4/BM4-1 -> 0.02005967 | BP13: =BP4/BO4-1 -> 0.018613867 | BQ13: =BQ4/BP4-1 -> 0.05271724 | BR13: =BR4/BQ4-1 -> 0.047148585 | BT13: =BT4/BR4-1 -> 0.081456763 | BU13: =BU4/BT4-1 -> 0.049337359 | BV13: =BV4/BU4-1 -> 0.035413956 | BW13: =BW4/BV4-1 -> 0.049741028 | BY13: =BY4/BW4-1 -> 0.023716377 | BZ13: =BZ4/BY4-1 -> 0.037882749 | CA13: =CA4/BZ4-1 -> 0.048617853 | CB13: =CB4/CA4-1 -> 0.065789704 | CD13: =CD4/CB4-1 -> 0.031552722 | CE13: =CE4/CD4-1 -> 0.036133092 | CF13: =CF4/CE4-1 -> 0.040217458 | CG13: =CG4/CF4-1 -> 0.068582717 | CI13: =CI4/CG4-1 -> 0.031807678 | CJ13: =CJ4/CI4-1 -> 0.026875969 | CK13: =CK4/CJ4-1 -> 0.065691815 | CL13: =CL4/CK4-1 -> 0.044114952 | CN13: =CN4/CL4-1 -> 0.062267783 | CO13: =CO4/CN4-1 -> 0.032228214 | CP13: =CP4/CO4-1 -> 0.013361793 | CQ13: =CQ4/CP4-1 -> 0.014470469 | CS13: =CS4/CQ4-1 -> -0.00010581515 | CT13: =CT4/CS4-1 -> 0.026304641 | CU13: =CU4/CT4-1 -> 0.033994498 | CV13: =CV4/CU4-1 -> 0.017353908
C14: Organic Recurring revenue | W14: =R10*(1+W15) -> 11263.565 | X14: =S10*(1+X15) -> 12065.55 | Y14: =T10*(1+Y15) -> 12907.825 | AA14: =V10*(1+AA15) -> 13333.311 | AB14: =W10*(1+AB15) -> 14750.921 | AC14: =X10*(1+AC15) -> 16103.573 | AD14: =Y10*(1+AD15) -> 17196.63 | AE14: =Z10*(1+AE15) -> 61099.326 | AF14: =AA10*(1+AF15) -> 17836.879 | AG14: =AB10*(1+AG15) -> 19310.836 | AH14: =AC10*(1+AH15) -> 22472.05 | AN14: =AI10*(1+AN15) -> 31189.162 | AP14: =AK10*(1+AP15) -> 32241.63 | AQ14: =AL10*(1+AQ15) -> 34267.131 | AR14: =AM10*(1+AR15) -> 35776.849 | AS14: =AN10*(1+AS15) -> 38085.464 | AT14: =SUM(AP14:AS14) -> 140371.07 | AU14: =AP10*(1+AU15) -> 39927.6 | AV14: =AQ10*(1+AV15) -> 41712.835 | AW14: =AR10*(1+AW15) -> 42964.904 | AX14: =AS10*(1+AX15) -> 44377.746 | AY14: =SUM(AU14:AX14) -> 168983.08 | AZ14: =AZ10-AZ16 -> 47777.44 | BA14: =BA10-BA16 -> 49941.28 | BB14: =BB10-BB16 -> 51658 | BC14: =BC10-BC16 -> 54543.28 | BD14: =SUM(AZ14:BC14) -> 203920 | BE14: =BE10-BE16 -> 54860 | BF14: =BF10-BF16 -> 56430 | BG14: =BG10-BG16 -> 58644 | BH14: =BH10-BH16 -> 60720 | BI14: =SUM(BE14:BH14) -> 230654 | BJ14: =BJ10-BJ16 -> 61792.96 | BK14: =BK10-BK16 -> 63292.26 | BL14: =BL10-BL16 -> 65547.32 | BM14: =BM10-BM16 -> 67369.02 | BN14: =SUM(BJ14:BM14) -> 258001.56 | BO14: =BO10-BO16 -> 69740.48 | BP14: =BP10-BP16 -> 71038.62 | BQ14: =BQ10-BQ16 -> 75579.15 | BR14: =BR10-BR16 -> 78309.52 | BS14: =SUM(BO14:BR14) -> 294667.77 | BT14: =BT10-BT16 -> 81436.48 | BU14: =BU10-BU16 -> 85075.88 | BV14: =BV10-BV16 -> 87706.04 | BW14: =BW10-BW16 -> 91185.52 | BX14: =SUM(BT14:BW14) -> 345403.92 | BY14: =BY10-BY16 -> 96867 | BZ14: =BZ10-BZ16 -> 100413 | CA14: =CA10-CA16 -> 104803 | CB14: =CB10-CB16 -> 110014 | CC14: =SUM(BY14:CB14) -> 412097 | CD14: =CD10-CD16 -> 113801 | CE14: =CE10-CE16 -> 117748 | CF14: =CF10-CF16 -> 124421 | CG14: =CG10-CG16 -> 129618 | CH14: =SUM(CD14:CG14) -> 485588 | CI14: =CI10-CI16 -> 135684 | CJ14: =CJ10-CJ16 -> 139780.24 | CK14: =CK10-CK16 -> 150914.84 | CL14: =CL10-CL16 -> 155423.42 | CM14: =SUM(CI14:CL14) -> 581802.5 | CN14: =CN10-CN16 -> 158129 | CO14: =CO10-CO16 -> 163454 | CP14: =CP10-CP16 -> 170057.84 | CQ14: =CQ10-CQ16 -> 175245.92 | CR14: =SUM(CN14:CQ14) -> 666886.76 | CS14: =CN10*(1+CS15) -> 181031.61 | CT14: =CO10*(1+CT15) -> 189798.72 | CU14: =CP10*(1+CU15) -> 195069.39 | CV14: =CQ10*(1+CV15) -> 198816.86 | CW14: =SUM(CS14:CV14) -> 764716.59
C15: Y/Y Growth | W15: 0.24 | X15: 0.25 | Y15: 0.25 | AA15: 0.27 | AB15: 0.26 | AC15: 0.22 | AD15: 0.24 | AE15: 0.24 | AF15: 0.24 | AG15: 0.26 | AH15: 0.26 | AN15: 0.24 | AP15: 0.24 | AQ15: 0.22 | AR15: 0.22 | AS15: 0.2 | AU15: 0.2 | AV15: 0.18 | AW15: 0.17 | AX15: 0.15 | AY15: =AY14/AT14-1 -> 0.20383124 | AZ15: =AZ14/AU10-1 -> 0.15139984 | BA15: =BA14/AV10-1 -> 0.14641718 | BB15: =BB14/AW10-1 -> 0.13931499 | BC15: =BC14/AX10-1 -> 0.16900894 | BD15: =BD14/AY14-1 -> 0.20674801 | BE15: =BE14/AZ10-1 -> 0.14824068 | BF15: =BF14/BA10-1 -> 0.12992699 | BG15: =BG14/BB10-1 -> 0.13523559 | BH15: =BH14/BC10-1 -> 0.11324438 | BI15: =BI14/BD14-1 -> 0.13110043 | BJ15: =BJ14/BE10-1 -> 0.1263755 | BK15: =BK14/BF10-1 -> 0.12160659 | BL15: =BL14/BG10-1 -> 0.11771571 | BM15: =BM14/BH10-1 -> 0.10950296 | BN15: =BN14/BI14-1 -> 0.1185653 | BO15: =BO14/BJ10-1 -> 0.10843517 | BP15: =BP14/BK10-1 -> 0.1027886 | BQ15: =BQ14/BL10-1 -> 0.13359112 | BR15: =BR14/BM10-1 -> 0.1453948 | BS15: =BS14/BN14-1 -> 0.14211623 | BT15: =BT14/BO10-1 -> 0.16770748 | BU15: =BU14/BP10-1 -> 0.1976004 | BV15: =BV14/BQ10-1 -> 0.16045285 | BW15: =BW14/BR10-1 -> 0.16442445 | BX15: =BX14/BS14-1 -> 0.17218086 | BY15: =BY14/BT10-1 -> 0.16867069 | BZ15: =BZ14/BU10-1 -> 0.15449249 | CA15: =CA14/BV10-1 -> 0.16375315 | CB15: =CB14/BW10-1 -> 0.1637319 | CC15: =CC14/BX14-1 -> 0.19308721 | CD15: =CD14/BY10-1 -> 0.16638823 | CE15: =CE14/BZ10-1 -> 0.16394334 | CF15: =CF14/CA10-1 -> 0.1676912 | CG15: =CG14/CB10-1 -> 0.13935867 | CH15: =CH14/CC14-1 -> 0.17833423 | CI15: =CI14/CD10-1 -> 0.15671648 | CJ15: =CJ14/CE10-1 -> 0.15023691 | CK15: =CK14/CF10-1 -> 0.18484459 | CL15: =CL14/CG10-1 -> 0.14435068 | CM15: =CM14/CH14-1 -> 0.19814019 | CN15: =CN14/CI10-1 -> 0.13204805 | CO15: =CO14/CJ10-1 -> 0.13210783 | CP15: =CP14/CK10-1 -> 0.10524172 | CQ15: =CQ14/CL10-1 -> 0.084285433 | CR15: =CR14/CM10-1 -> 0.11230753 | CS15: 0.0505 | CT15: 0.055 | CU15: 0.07 | CV15: 0.075 | CW15: =CW14/CR10-1 -> 0.062864016
C16: Inorganic Recurring revenue | W16: =W10-W14 -> 443.5152 | X16: =X10-X14 -> 1134.1 | Y16: =Y10-Y14 -> 960.425 | AA16: =AA10-AA14 -> 1051.2691 | AB16: 1000 | AC16: 1000 | AD16: =AD10-AD14 -> 3111.05 | AE16: =AE10-AE14 -> 6753.954 | AF16: =AF10-AF14 -> 3302.4008 | AG16: =AG10-AG14 -> 3268.2044 | AH16: =AH10-AH14 -> 1565.0704 | AN16: =AN10-AN14 -> 548.7246 | AP16: =AP10-AP14 -> 1031.3701 | AQ16: =AQ10-AQ14 -> 1082.7286 | AR16: =AR10-AR14 -> 945.29059 | AT16: =SUM(AP16:AS16) -> 3059.3894 | AU16: =AU10-AU14 -> 1567.49 | AV16: =AV10-AV14 -> 1850.0852 | AW16: =AW10-AW14 -> 2376.3762 | AX16: =AX10-AX14 -> 2279.9644 | AY16: =SUM(AU16:AX16) -> 8073.9158 | BD16: =SUM(AZ16:BC16) -> 0 | BI16: =SUM(BE16:BH16) -> 0 | BJ16: 1125 | BK16: 1125 | BL16: 1125 | BM16: 1000 | BN16: =SUM(BJ16:BM16) -> 4375 | BS16: =SUM(BO16:BR16) -> 0 | BT16: 1450 | BU16: 1900 | BV16: 2350 | BW16: =2900+450 -> 3350 | BX16: =SUM(BT16:BW16) -> 9050 | BY16: 700 | BZ16: 750 | CA16: =750+1000 -> 1750 | CB16: =800+1250+1700 -> 3750 | CC16: =SUM(BY16:CB16) -> 6950 | CD16: =1600+1900 -> 3500 | CE16: =1675+2100 -> 3775 | CF16: =750+2200 -> 2950 | CG16: =2300+3900 -> 6200 | CH16: =SUM(CD16:CG16) -> 16425 | CI16: 4000 | CJ16: =4000+600 -> 4600 | CK16: =750+2200 -> 2950 | CL16: =2300+3900 -> 6200 | CM16: =SUM(CI16:CL16) -> 17750 | CN16: =1200+6000+7000 -> 14200 | CO16: 16450 | CP16: =6250-3000+10000-1000 -> 12250 | CQ16: =1000+10000-1300 -> 9700 | CR16: =SUM(CN16:CQ16) -> 52600 | CS16: =5000-500-500 -> 4000 | CT16: 0 | CU16: 0 | CV16: 0 | CW16: =SUM(CS16:CV16) -> 4000
C17: Y/Y Growth | W17: =W12-W15 -> 0.048826358 | X17: =X12-X15 -> 0.11749361 | Y17: =Y12-Y15 -> 0.09300802 | AA17: =AA12-AA15 -> 0.10013355 | AB17: =AB12-AB15 -> 0.049127468 | AC17: =AC12-AC15 -> 0.13116916 | AD17: =AD12-AD15 -> 0.22432895 | AE17: =AE12-AE15 -> 0.1370703 | AF17: =AF12-AF15 -> 0.22957923 | AG17: =AG12-AG15 -> 0.21324492 | AH17: =AH12-AH15 -> 0.087752953 | AN17: =AN12-AN15 -> 0.021815864 | AP17: =AP8-AP15 -> 0.037514772 | AQ17: =AQ8-AQ15 -> 0.029067524 | AR17: =AR8-AR15 -> 0.021432351 | AS17: 0
C18: Non-recurring revenue | K18: =K4-K10 -> 5218.49 | L18: =L4-L10 -> 1620.89 | M18: =M4-M10 -> 2112 | N18: =N4-N10 -> 1830.46 | O18: =O4-O10 -> 1985.85 | P18: =P4-P10 -> 7549.2 | Q18: =Q4-Q10 -> 1843.74 | R18: =R4-R10 -> 1860.48 | ... AX18: =AX4-AX10 -> 4403.29 | AY18: 16096 | AZ18: =AZ4-AZ10 -> 4154.56 | BA18: =BA4-BA10 -> 4342.72 | BB18: =BB4-BB10 -> 4492 | BC18: =BC4-BC10 -> 3656.72 | BD18: 16165 | BE18: =BE4-BE10 -> 4232 | BF18: =BF4-BF10 -> 4661 | BG18: =BG4-BG10 -> 4224 | BH18: =BH4-BH10 -> 4469 | BI18: =SUM(BE18:BH18) -> 17586 | BJ18: =BJ4-BJ10 -> 4016.04 | BK18: =BK4-BK10 -> 4111.74 | BL18: =BL4-BL10 -> 4255.68 | BM18: =BM4-BM10 -> 4363.98 | BN18: =SUM(BJ18:BM18) -> 16747.44 | BO18: =BO4-BO10 -> 4451.52 | BP18: =BP4-BP10 -> 4534.38 | BQ18: =BQ4-BQ10 -> 3977.85 | BR18: =BR4-BR10 -> 4998.48 | BS18: =SUM(BO18:BR18) -> 17962.23 | BT18: =BT4-BT10 -> 7207.52 | BU18: =BU4-BU10 -> 7563.12 | BV18: =BV4-BV10 -> 7830.96 | BW18: =BW4-BW10 -> 8220.48 | BX18: =SUM(BT18:BW18) -> 30822.08 | BY18: =BY4-BY10 -> 7626 | BZ18: =BZ4-BZ10 -> 8015 | CA18: =CA4-CA10 -> 7933 | CB18: =CB4-CB10 -> 8254 | CC18: =SUM(BY18:CB18) -> 31828 | CD18: =CD4-CD10 -> 8567 | CE18: =CE4-CE10 -> 8893 | CF18: =CF4-CF10 -> 8290 | CG18: =CG4-CG10 -> 9147 | CH18: =SUM(CD18:CG18) -> 34897 | CI18: =CI4-CI10 -> 9892 | CJ18: =CJ4-CJ10 -> 9215.76 | CK18: =CK4-CK10 -> 9821.16 | CL18: =CL4-CL10 -> 9283.58 | CM18: =SUM(CI18:CL18) -> 38212.5 | CN18: 9220 | CO18: =CO4-CO10 -> 7496 | CP18: =CP4-CP10 -> 7596.16 | CQ18: =CQ4-CQ10 -> 7706.08 | CR18: =SUM(CN18:CQ18) -> 32018.24 | CS18: 7600 | CT18: 7900 | CU18: 9350 | CV18: 9150 | CW18: =SUM(CS18:CV18) -> 34000
C19: % of total Rev | AK19: =AK18/AK4 -> 0.10151303 | AL19: =AL18/AL4 -> 0.0968549 | AM19: =AM18/AM4 -> 0.097850046 | AN19: =AN18/AN4 -> 0.10350018 | AO19: =AO18/AO4 -> 0.1 | AP19: =AP18/AP4 -> 0.1 | AQ19: =AQ18/AQ4 -> 0.09 | AR19: =AR18/AR4 -> 0.09 | ... AX19: =AX18/AX4 -> 0.086235875 | AZ19: =AZ18/AZ4 -> 0.08 | BA19: =BA18/BA4 -> 0.08 | BB19: =BB18/BB4 -> 0.08 | BC19: =BC18/BC4 -> 0.062830241 | BE19: =BE18/BE4 -> 0.071617139 | BF19: =BF18/BF4 -> 0.076296017 | BG19: =BG18/BG4 -> 0.067188395 | BH19: =BH18/BH4 -> 0.068554511 | BJ19: =BJ18/BJ4 -> 0.06 | BK19: =BK18/BK4 -> 0.06 | BL19: =BL18/BL4 -> 0.06 | BM19: =BM18/BM4 -> 0.06 | BO19: =BO18/BO4 -> 0.06 | BP19: =BP18/BP4 -> 0.06 | BQ19: =BQ18/BQ4 -> 0.05 | BR19: =BR18/BR4 -> 0.06 | BT19: =BT18/BT4 -> 0.08 | BU19: =BU18/BU4 -> 0.08 | BV19: =BV18/BV4 -> 0.08 | BW19: =BW18/BW4 -> 0.08 | BY19: =BY18/BY4 -> 0.072495318 | BZ19: =BZ18/BZ4 -> 0.073412226 | CA19: =CA18/CA4 -> 0.069292315 | CB19: =CB18/CB4 -> 0.067645757 | CC19: =CC18/CC4 -> 0.070591627 | CD19: =CD18/CD4 -> 0.068063368 | CE19: =CE18/CE4 -> 0.068189486 | CF19: =CF18/CF4 -> 0.061108204 | ... CW19: =CW18/CW4 -> 0.04235617
B20: Cost of Revenue | D20: 3823 | E20: 5219 | F20: =6379-2 -> 6377 | G20: =1986-4 -> 1982 | H20: =2199-4 -> 2195 | I20: =2435-4 -> 2431 | J20: =2638-7 -> 2631 | K20: =SUM(G20:J20) -> 9239 | L20: =2837-12 -> 2825 | M20: =2896-11 -> 2885 | N20: =3009-20 -> 2989 | O20: =2973-10 -> 2963 | P20: =SUM(L20:O20) -> 11662 | Q20: =2981-10 -> 2971 | R20: =3101-24 -> 3077 | S20: =3211-31 -> 3180 | T20: =3333-38 -> 3295 | U20: =SUM(Q20:T20) -> 12523 | V20: =3321-46 -> 3275 | W20: =3750-72 -> 3678 | X20: =4076-68 -> 4008 | Y20: =4219-69 -> 4150 | Z20: =SUM(V20:Y20) -> 15111 | AA20: =4448-178 -> 4270 | AB20: =4843-116 -> 4727 | AC20: =5945-122 -> 5823 | AD20: =6804-46 -> 6758 | AE20: =SUM(AA20:AD20) -> 21578 | AF20: =7066-103 -> 6963 | AG20: =7943-122 -> 7821 | AH20: =8249-128 -> 8121 | AI20: =8523-122 -> 8401 | AJ20: =SUM(AF20:AI20) -> 31306 | AK20: =9255-153 -> 9102 | AL20: =9627-152 -> 9475 | AM20: =9970-134 -> 9836 | AN20: =11139-175 -> 10964 | AO20: =SUM(AK20:AN20) -> 39377 | AP20: =11572-172 -> 11400 | AQ20: =12335-288 -> 12047 | AR20: =12700-256 -> 12444 | AS20: =13436-273 -> 13163 | AT20: =SUM(AP20:AS20) -> 49054 | AU20: =14881-280 -> 14601 | AV20: =15972-317 -> 15655 | AW20: =16171-319 -> 15852 | AX20: =17322-393 -> 16929 | AY20: =SUM(AU20:AX20) -> 63037 | AZ20: =17330-451 -> 16879 | BA20: =18191-469 -> 17722 | BB20: =18645-494 -> 18151 | BC20: =19459-473 -> 18986 | BD20: =SUM(AZ20:BC20) -> 71738 | BE20: =19758-548 -> 19210 | BF20: =20402-504 -> 19898 | BG20: =20411-535 -> 19876 | BH20: =21177-581 -> 20596 | BI20: =SUM(BE20:BH20) -> 79580 | BJ20: =21367-587 -> 20780 | BK20: =23700-662 -> 23038 | BL20: =23263-778 -> 22485 | BM20: =23909-792 -> 23117 | BN20: =SUM(BJ20:BM20) -> 89420 | BO20: =23544-808 -> 22736 | BP20: =24326-956 -> 23370 | BQ20: =25045-1003 -> 24042 | BR20: =26921-1181 -> 25740 | BS20: =SUM(BO20:BR20) -> 95888 | BT20: =29970-1503 -> 28467 | BU20: =31730-1746 -> 29984 | BV20: =34343-1696 -> 32647 | BW20: =35635-1815 -> 33820 | BX20: =SUM(BT20:BW20) -> 124918 | BY20: =35389-2179 -> 33210 | BZ20: =37530-2152 -> 35378 | CA20: =38605-2146 -> 36459 | CB20: =41541-2207 -> 39334 | CC20: =SUM(BY20:CB20) -> 144381 | CD20: =42964-2503 -> 40461 | CE20: =44544-2586 -> 41958 | CF20: =45521-2506 -> 43015 | CG20: =49040-2574 -> 46466 | CH20: =SUM(CD20:CG20) -> 171900 | CI20: =51487-4082 -> 47405 | CJ20: =52018-2730 -> 49288 | CK20: =51624-1412 -> 50212 | CL20: =55585-2819 -> 52766 | CM20: =SUM(CI20:CL20) -> 199671 | CN20: =56914-3111 -> 53803 | CO20: =59826-3328 -> 56498 | CP20: =57932-3171 -> 54761 | CQ20: =56957-1813 -> 55144 | CR20: =SUM(CN20:CQ20) -> 220206 | CS20: =CS4*(1-CS22) -> 55477.905 | CT20: =CT4*(1-CT22) -> 56344.135 | CU20: =CU4*(1-CU22) -> 56828.59 | CV20: =CV4*(1-CV22) -> 57606.821 | CW20: =SUM(CS20:CV20) -> 226257.45
B21: Gross Profit | D21: =D4-D20 -> 10004 | E21: =E4-E20 -> 14640 | F21: =F4-F20 -> 18821 | G21: =G4-G20 -> 4975 | H21: =H4-H20 -> 5391 | I21: =I4-I20 -> 5643 | J21: =J4-J20 -> 5449 | K21: =K4-K20 -> 21458 | ... CW21: =CW4-CW20 -> 576459.14
C22: Gross Margin | D22: =D21/D4 -> 0.72351197 | E22: =E21/E4 -> 0.73719724 | F22: =F21/F4 -> 0.74692436 | G22: =G21/G4 -> 0.71510709 | H22: =H21/H4 -> 0.7106512 | I22: =I21/I4 -> 0.69891008 | J22: =J21/J4 -> 0.67438119 | K22: =K21/K4 -> 0.69902596 | ... CR22: =CR21/CR4 -> 0.70697999 | CS22: 0.712 | CT22: 0.715 | CU22: 0.722 | CV22: 0.723 | CW22: =CW21/CW4 -> 0.71813532
B24: Operating Expenses
C25: Sales and marketing | D25: 5034 | E25: 8098 | F25: =11636-33 -> 11603 | G25: =3162-14 -> 3148 | H25: =3240-15 -> 3225 | I25: =3101-15 -> 3086 | J25: =2990-16 -> 2974 | K25: =SUM(G25:J25) -> 12433 | L25: =3075-15 -> 3060 | M25: =3397-17 -> 3380 | N25: =3533-42 -> 3491 | O25: =3501-17 -> 3484 | P25: =SUM(L25:O25) -> 13415 | Q25: =3507-17 -> 3490 | R25: =4122-48 -> 4074 | S25: =4139-64 -> 4075 | T25: =4833-82 -> 4751 | U25: =SUM(Q25:T25) -> 16390 | V25: =5126-89 -> 5037 | W25: =5852-137 -> 5715 | X25: =6404-121 -> 6283 | Y25: =6454-124 -> 6330 | Z25: =SUM(V25:Y25) -> 23365 | AA25: =6447-98 -> 6349 | AB25: =6972-217 -> 6755 | AC25: =7840-232 -> 7608 | AD25: =8778-268 -> 8510 | AE25: =SUM(AA25:AD25) -> 29222 | AF25: =9225-342 -> 8883 | AG25: =9647-386 -> 9261 | AH25: =10291-378 -> 9913 | AI25: =10458-375 -> 10083 | AJ25: =SUM(AF25:AI25) -> 38140 | AK25: =10884-482 -> 10402 | AL25: =11570-472 -> 11098 | AM25: =12046-469 -> 11577 | AN25: =12490-510 -> 11980 | AO25: =SUM(AK25:AN25) -> 45057 | AP25: =13744-542 -> 13202 | AQ25: =14101-482 -> 13619 | AR25: =13795-466 -> 13329 | AS25: =13734-488 -> 13246 | AT25: =SUM(AP25:AS25) -> 53396 | AU25: =15889-654 -> 15235 | AV25: =16677-639 -> 16038 | AW25: =16526-620 -> 15906 | AX25: =16794-499 -> 16295 | AY25: =SUM(AU25:AX25) -> 63474 | AZ25: =17079-517 -> 16562 | BA25: =18741-574 -> 18167 | BB25: =18239-565 -> 17674 | BC25: =19236-541 -> 18695 | BD25: =SUM(AZ25:BC25) -> 71098 | BE25: =18647-653 -> 17994 | BF25: =18424-710 -> 17714 | BG25: =16952-691 -> 16261 | BH25: =17696-621 -> 17075 | BI25: =SUM(BE25:BH25) -> 69044 | BJ25: =17922-730 -> 17192 | BK25: =17545-694 -> 16851 | BL25: =16937-784 -> 16153 | BM25: =17736-738 -> 16998 | BN25: =SUM(BJ25:BM25) -> 67194 | BO25: =18299-846 -> 17453 | BP25: =18611-1010 -> 17601 | BQ25: =19233-1123 -> 18110 | BR25: =19812-1140 -> 18672 | BS25: =SUM(BO25:BR25) -> 71836 | BT25: =21355-1482 -> 19873 | BU25: =21952-1738 -> 20214 | BV25: =22079-1634 -> 20445 | BW25: =22658-1394 -> 21264 | BX25: =SUM(BT25:BW25) -> 81796 | BY25: =24655-2032 -> 22623 | BZ25: =24582-1958 -> 22624 | CA25: =25334-1845 -> 23489 | CB25: =27201-1755 -> 25446 | CC25: =SUM(BY25:CB25) -> 94182 | CD25: =29083-2423 -> 26660 | CE25: =30349-2528 -> 27821 | CF25: =30289-2428 -> 27861 | CG25: =33214-2394 -> 30820 | CH25: =SUM(CD25:CG25) -> 113162 | CI25: =36432-4444 -> 31988 | CJ25: =35691-2512 -> 33179 | CK25: =37577-2820 -> 34757 | CL25: =39220-2771 -> 36449 | CM25: =SUM(CI25:CL25) -> 136373 | CN25: =41634-2427 -> 39207 | CO25: =43434-3357 -> 40077 | CP25: =42322-3486 -> 38836 | CQ25: =41740-1673 -> 40067 | CR25: =SUM(CN25:CQ25) -> 158187 | CS25: =CS26*CS4 -> 41030.534 | CT25: =CT26*CT4 -> 41121.334 | CU25: =CU26*CU4 -> 41905.975 | CV25: =CV26*CV4 -> 41801.34 | CW25: =SUM(CS25:CV25) -> 165859.18
C26: % of Revenue | D26: =D25/D4 -> 0.3640703 | E26: =E25/E4 -> 0.40777481 | F26: =F25/F4 -> 0.46047305 | G26: =G25/G4 -> 0.45249389 | H26: =H25/H4 -> 0.42512523 | I26: =I25/I4 -> 0.38221452 | J26: =J25/J4 -> 0.36806931 | K26: =K25/K4 -> 0.40502329 | ... CR26: =CR25/CR4 -> 0.21049361 | CS26: 0.213 | CT26: 0.208 | CU26: 0.205 | CV26: 0.201 | CW26: =CW25/CW4 -> 0.20662234
C27: Research and development | D27: 2129 | E27: 3190 | F27: =3546-2 -> 3544 | G27: =949-1 -> 948 | H27: =954-1 -> 953 | I27: =875-1 -> 874 | J27: =862-1 -> 861 | K27: =SUM(G27:J27) -> 3636 | L27: =1044-1 -> 1043 | M27: =1059-1 -> 1058 | N27: =1123-1 -> 1122 | O27: =1079-1 -> 1078 | P27: =SUM(L27:O27) -> 4301 | Q27: =1043-1 -> 1042 | R27: =1067-4 -> 1063 | S27: =1108-7 -> 1101 | T27: =1131-8 -> 1123 | U27: =SUM(Q27:T27) -> 4329 | V27: =1240-7 -> 1233 | W27: =1414-16 -> 1398 | X27: =1605-18 -> 1587 | Y27: =1579-15 -> 1564 | Z27: =SUM(V27:Y27) -> 5782 | AA27: =1732-22 -> 1710 | AB27: =1830-29 -> 1801 | AC27: =2088-39 -> 2049 | AD27: =2516-50 -> 2466 | AE27: =SUM(AA27:AD27) -> 8026 | AF27: =2503-61 -> 2442 | AG27: =2657-63 -> 2594 | AH27: =2806-71 -> 2735 | AI27: =2904-71 -> 2833 | AJ27: =SUM(AF27:AI27) -> 10604 | AK27: =2974-93 -> 2881 | AL27: =3365-95 -> 3270 | AM27: =3338-134 -> 3204 | AN27: =3817-122 -> 3695 | AO27: =SUM(AK27:AN27) -> 13050 | AP27: =4069-135 -> 3934 | AQ27: =4495-173 -> 4322 | AR27: =4494-178 -> 4316 | AS27: =4896-154 -> 4742 | AT27: =SUM(AP27:AS27) -> 17314 | AU27: =5069-138 -> 4931 | AV27: =5542-141 -> 5401 | AW27: =5574-143 -> 5431 | AX27: =5796-196 -> 5600 | AY27: =SUM(AU27:AX27) -> 21363 | AZ27: =5105-229 -> 4876 | BA27: =5369-228 -> 5141 | BB27: =6549-241 -> 6308 | BC27: =6160-251 -> 5909 | BD27: =SUM(AZ27:BC27) -> 22234 | BE27: =5132-329 -> 4803 | BF27: =5293-357 -> 4936 | BG27: =5146-287 -> 4859 | BH27: =6516-532 -> 5984 | BI27: =SUM(BE27:BH27) -> 20582 | BJ27: =6192-523 -> 5669 | BK27: =6509-602 -> 5907 | BL27: =7743-697 -> 7046 | BM27: =7861-829 -> 7032 | BN27: =SUM(BJ27:BM27) -> 25654 | BO27: =7568-923 -> 6645 | BP27: =7466-883 -> 6583 | BQ27: =8053-983 -> 7070 | BR27: =7937-837 -> 7100 | BS27: =SUM(BO27:BR27) -> 27398 | BT27: =8706-911 -> 7795 | BU27: =8899-1106 -> 7793 | BV27: =10854-1195 -> 9659 | BW27: =10579-1172 -> 9407 | BX27: =SUM(BT27:BW27) -> 34654 | BY27: =10701-1474 -> 9227 | BZ27: =11432-1380 -> 10052 | CA27: =11135-1396 -> 9739 | CB27: =12480-1384 -> 11096 | CC27: =SUM(BY27:CB27) -> 40114 | CD27: =12563-1777 -> 10786 | CE27: =13318-1812 -> 11506 | CF27: =13558-1798 -> 11760 | CG27: =14216-1813 -> 12403 | CH27: =SUM(CD27:CG27) -> 46455 | CI27: =16009-3242 -> 12767 | CJ27: =14366-1820 -> 12546 | CK27: =15292-1939 -> 13353 | CL27: =17142-2093 -> 15049 | CM27: =SUM(CI27:CL27) -> 53715 | CN27: =17439-2017 -> 15422 | CO27: =17271-2135 -> 15136 | CP27: =17276-2354 -> 14922 | CQ27: =16694-1897 -> 14797 | CR27: =SUM(CN27:CQ27) -> 60277 | CS27: =+CS28*CS4 -> 16181.056 | CT27: =+CT28*CT4 -> 16013.596 | CU27: =+CU28*CU4 -> 15944.712 | CV27: =+CV28*CV4 -> 16221.415 | CW27: =SUM(CS27:CV27) -> 64360.78
C28: % of Revenue | D28: =D27/D4 -> 0.15397411 | E28: =E27/E4 -> 0.16063246 | F28: =F27/F4 -> 0.14064608 | G28: =G27/G4 -> 0.13626563 | H28: =H27/H4 -> 0.12562615 | I28: =I27/I4 -> 0.1082487 | J28: =J27/J4 -> 0.10655941 | K28: =K27/K4 -> 0.11844806 | ... CR28: =CR27/CR4 -> 0.080208382 | CS28: 0.084 | CT28: 0.081 | CU28: 0.078 | CV28: 0.078 | CW28: =CW27/CW4 -> 0.080178709
C29: General and administrative | D29: 3180 | E29: 4199 | F29: =5458-9 -> 5449 | G29: =1639-17 -> 1622 | H29: =1669-17 -> 1652 | I29: =1684-17 -> 1667 | J29: =1724-23 -> 1701 | K29: =SUM(G29:J29) -> 6642 | L29: =1652-20 -> 1632 | M29: =1514-21 -> 1493 | N29: =1505-16 -> 1489 | O29: =1668-23 -> 1645 | P29: =SUM(L29:O29) -> 6259 | Q29: =1665-23 -> 1642 | R29: =1975-99 -> 1876 | S29: =2165-130 -> 2035 | T29: =2180-164 -> 2016 | U29: =SUM(Q29:T29) -> 7569 | V29: =2455-170 -> 2285 | W29: =2839-262 -> 2577 | X29: =2914-280 -> 2634 | Y29: =2943-274 -> 2669 | Z29: =SUM(V29:Y29) -> 10165 | AA29: =3188-314 -> 2874 | AB29: =3165-353 -> 2812 | AC29: =3726-322 -> 3404 | AD29: =3445-349 -> 3096 | AE29: =SUM(AA29:AD29) -> 12186 | AF29: =4047-418 -> 3629 | AG29: =4211-540 -> 3671 | AH29: =4284-508 -> 3776 | AI29: =4647-515 -> 4132 | AJ29: =SUM(AF29:AI29) -> 15208 | AK29: =4511-611 -> 3900 | AL29: =4842-640 -> 4202 | AM29: =5153-556 -> 4597 | AN29: =5727-598 -> 5129 | AO29: =SUM(AK29:AN29) -> 17828 | AP29: =5818-650 -> 5168 | AQ29: =6055-704 -> 5351 | AR29: =6276-710 -> 5566 | AS29: =6668-708 -> 5960 | AT29: =SUM(AP29:AS29) -> 22045 | AU29: =7285-855 -> 6430 | AV29: =7082-968 -> 6114 | AW29: =7149-930 -> 6219 | AX29: =7311-931 -> 6380 | AY29: =SUM(AU29:AX29) -> 25143 | AZ29: =7827-1103 -> 6724 | BA29: =8139-915 -> 7224 | BB29: =8744-1047 -> 7697 | BC29: =12752-4629 -> 8123 | BD29: =SUM(AZ29:BC29) -> 29768 | BE29: =10130-2003 -> 8127 | BF29: =9974-1608 -> 8366 | BG29: =11174-1753 -> 9421 | BH29: =10584-798 -> 9786 | BI29: =SUM(BE29:BH29) -> 35700 | BJ29: =12770-3454+61 -> 9377 | BK29: =10179-917+400 -> 9662 | BL29: =10725-888+22 -> 9859 | BM29: =11045-1015+5 -> 10035 | BN29: =SUM(BJ29:BM29) -> 38933 | BO29: =11909-1767-72 -> 10070 | BP29: =12743-2160-82 -> 10501 | BQ29: =11939-1784-103 -> 10052 | BR29: =13528-1532+583 -> 12579 | BS29: =SUM(BO29:BR29) -> 43202 | BT29: =14737-3029 -> 11708 | BU29: =15758-2909 -> 12849 | BV29: =14691-2324 -> 12367 | BW29: =16119-1920 -> 14199 | BX29: =SUM(BT29:BW29) -> 51123 | BY29: =15468-3330 -> 12138 | BZ29: =17198-3171 -> 14027 | CA29: =16724-2573 -> 14151 | CB29: =17950-2417 -> 15533 | CC29: =SUM(BY29:CB29) -> 55849 | CD29: =20677-5077 -> 15600 | CE29: =21693-5955 -> 15738 | CF29: =21906-4704 -> 17202 | CG29: =20612-2630 -> 17982 | CH29: =SUM(CD29:CG29) -> 66522 | CI29: =25907-8250 -> 17657 | CJ29: =23516-4432 -> 19084 | CK29: =27152-4581 -> 22571 | CL29: =26354-4610 -> 21744 | CM29: =SUM(CI29:CL29) -> 81056 | CN29: =31018-6312 -> 24706 | CO29: =30890-6178 -> 24712 | CP29: =31690-5442 -> 26248 | CQ29: =32996-5027 -> 27969 | CR29: =SUM(CN29:CQ29) -> 103635 | CS29: =CS30*CS4 -> 27931.584 | CT29: =CT30*CT4 -> 25107.737 | CU29: =CU30*CU4 -> 25756.843 | CV29: =CV30*CV4 -> 25787.891 | CW29: =SUM(CS29:CV29) -> 104584.06
C30: % of Revenue | D30: =D29/D4 -> 0.22998481 | E30: =E29/E4 -> 0.21144066 | F30: =F29/F4 -> 0.21624732 | G30: =G29/G4 -> 0.23314647 | H30: =H29/H4 -> 0.21776958 | I30: =I29/I4 -> 0.2064652 | J30: =J29/J4 -> 0.2105198 | K30: =K29/K4 -> 0.21637294 | ... CR30: =CR29/CR4 -> 0.13790327 | CS30: 0.145 | CT30: 0.127 | CU30: 0.126 | CV30: 0.124 | CW30: =CW29/CW4 -> 0.13028765
C31: Total Operating Expenses | D31: =D29+D27+D25 -> 10343 | E31: =E29+E27+E25 -> 15487 | F31: =F29+F27+F25 -> 20596 | G31: =G29+G27+G25 -> 5718 | H31: =H29+H27+H25 -> 5830 | I31: =I29+I27+I25 -> 5627 | J31: =J29+J27+J25 -> 5536 | K31: =K29+K27+K25 -> 22711 | ... CW31: =CW29+CW27+CW25 -> 334804.02
B33: Proforma Operating Income | D33: =D21-D31 -> -339 | E33: =E21-E31 -> -847 | F33: =F21-F31 -> -1775 | G33: =G21-G31 -> -743 | H33: =H21-H31 -> -439 | I33: =I21-I31 -> 16 | J33: =J21-J31 -> -87 | K33: =K21-K31 -> -1253 | ... CW33: =CW21-CW31 -> 241655.12
C34: Proforma Operating Margins | D34: =D33/D4 -> -0.024517249 | E34: =E33/E4 -> -0.042650687 | F34: =F33/F4 -> -0.070442099 | G34: =G33/G4 -> -0.10679891 | H34: =H33/H4 -> -0.05786976 | I34: =I33/I4 -> 0.0019816696 | J34: =J33/J4 -> -0.010767327 | K34: =K33/K4 -> -0.040818321 | ... CW34: =CW33/CW4 -> 0.30104662
C36: Amortization of Intangible assets | W36: 123 | X36: 260 | Y36: 260 | Z36: =SUM(V36:Y36) -> 643 | AA36: 260 | AB36: 260 | AC36: 530 | AD36: 717 | AE36: =SUM(AA36:AD36) -> 1767 | AF36: 717 | AG36: 717 | AH36: 1007 | AI36: 717 | AJ36: =SUM(AF36:AI36) -> 3158 | AK36: 717 | AL36: 682 | AM36: 645 | AN36: 812 | AO36: =SUM(AK36:AN36) -> 2856 | AP36: 845 | AQ36: 833 | AR36: 829 | AS36: 800 | AT36: =SUM(AP36:AS36) -> 3307 | AU36: 1161 | AV36: 1198 | AW36: 1194 | AX36: 1185 | AY36: =SUM(AU36:AX36) -> 4738 | AZ36: 1215 | BA36: 1117 | BB36: 1128 | BC36: 1114 | BD36: =SUM(AZ36:BC36) -> 4574 | BE36: 1125 | BF36: 1033 | BG36: 928 | BH36: 1007 | BI36: =SUM(BE36:BH36) -> 4093 | BJ36: 1304 | BK36: 1266 | BL36: =1327 -> 1327 | BM36: 1418 | BN36: =SUM(BJ36:BM36) -> 5315 | BO36: 1336 | BP36: 1316 | BQ36: 1333 | BR36: 1553 | BS36: =SUM(BO36:BR36) -> 5538 | BT36: 2664 | BU36: 2671 | BV36: 2399 | BW36: 2392 | BX36: =SUM(BT36:BW36) -> 10126 | BY36: 2470 | BZ36: 2468 | CA36: 2998 | CB36: 3832 | CC36: =SUM(BY36:CB36) -> 11768 | CD36: 3851 | CE36: 3479 | CF36: 3788 | CG36: 4998 | CH36: =SUM(CD36:CG36) -> 16116 | CI36: 4338 | CJ36: 4840 | CK36: 6470 | CL36: 7862 | CM36: =SUM(CI36:CL36) -> 23510 | CN36: 8588 | CO36: =9509 -> 9509 | CP36: 9493 | CQ36: 9579 | CR36: =SUM(CN36:CQ36) -> 37169 | CS36: 9600 | CT36: 9600 | CU36: 9550 | CV36: 9550 | CW36: =SUM(CS36:CV36) -> 38300
C37: Stock-based Compensation | F37: 46 | G37: 36 | H37: 37 | I37: 37 | J37: 47 | K37: =SUM(G37:J37) -> 157 | L37: 48 | M37: 50 | N37: 79 | O37: 51 | P37: =SUM(L37:O37) -> 228 | Q37: 51 | R37: 175 | S37: 232 | T37: 292 | U37: =SUM(Q37:T37) -> 750 | V37: 312 | W37: 487 | X37: 487 | Y37: 482 | Z37: =SUM(V37:Y37) -> 1768 | AA37: 612 | AB37: 715 | AC37: 715 | AD37: 713 | AE37: =SUM(AA37:AD37) -> 2755 | AF37: 924 | AG37: 1111 | AH37: 1085 | AI37: 1083 | AJ37: =SUM(AF37:AI37) -> 4203 | AK37: 1339 | AL37: 1359 | AM37: 1293 | AN37: 1405 | AO37: =SUM(AK37:AN37) -> 5396 | AP37: 1499 | AQ37: 1647 | AR37: 1610 | AS37: 1623 | AT37: =SUM(AP37:AS37) -> 6379 | AU37: 1927 | AV37: 2065 | AW37: 2012 | AX37: 2019 | AY37: =SUM(AU37:AX37) -> 8023 | AZ37: 2300 | BA37: 2186 | BB37: 2347 | BC37: 5894 | BD37: =SUM(AZ37:BC37) -> 12727 | BE37: 3533 | BF37: 3179 | BG37: 3266 | BH37: 2532 | BI37: =SUM(BE37:BH37) -> 12510 | BJ37: 5294 | BK37: 2875 | BL37: 3147 | BM37: 3374 | BN37: =SUM(BJ37:BM37) -> 14690 | BO37: 4344 | BP37: 5009 | BQ37: 4893 | BR37: 4690 | BS37: =SUM(BO37:BR37) -> 18936 | BT37: 6925 | BU37: 7499 | BV37: 6849 | BW37: 6301 | BX37: =SUM(BT37:BW37) -> 27574 | BY37: 9015 | BZ37: 8661 | CA37: 7960 | CB37: 7763 | CC37: =SUM(BY37:CB37) -> 33399 | CD37: 11780 | CE37: 12881 | CF37: 11436 | CG37: 9411 | CH37: =SUM(CD37:CG37) -> 45508 | CI37: 20018 | CJ37: 11494 | CK37: 10752 | CL37: 12293 | CM37: =SUM(CI37:CL37) -> 54557 | CN37: 13867 | CO37: 14998 | CP37: 14453 | CQ37: 10410 | CR37: =SUM(CN37:CQ37) -> 53728 | CS37: 17200 | CT37: 16635 | CU37: 16635 | CV37: 16635 | CW37: =SUM(CS37:CV37) -> 67105
C38: % of Revenue | D38: =D37/D4 -> 0 | E38: =E37/E4 -> 0 | F38: =F37/F4 -> 0.0018255417 | G38: =G37/G4 -> 0.0051746442 | H38: =H37/H4 -> 0.0048774057 | I38: =I37/I4 -> 0.0045826108 | J38: =J37/J4 -> 0.0058168317 | K38: =K37/K4 -> 0.0051145063 | ... CW38: =CW37/CW4 -> 0.083597376
C39: Other | AY39: =SUM(AU39:AX39) -> 0 | BH39: 94 | BI39: =SUM(BE39:BH39) -> 94 | BJ39: -61 | BK39: -400 | BL39: -22 | BM39: -5 | BN39: =SUM(BJ39:BM39) -> -488 | BO39: =72 -> 72 | BP39: =82 -> 82 | BQ39: =103 -> 103 | BR39: =-583 -> -583 | BS39: =SUM(BO39:BR39) -> -326 | BX39: =SUM(BT39:BW39) -> 0 | CC39: =SUM(BY39:CB39) -> 0 | CH39: =SUM(CD39:CG39) -> 0 | CM39: =SUM(CI39:CL39) -> 0 | CR39: =SUM(CN39:CQ39) -> 0 | CW39: =SUM(CS39:CV39) -> 0
B40: GAAP Adjustments | F40: =F37 -> 46 | G40: =G37 -> 36 | H40: =H37 -> 37 | I40: =I37 -> 37 | J40: =J37 -> 47 | K40: =SUM(G40:J40) -> 157 | L40: =L37 -> 48 | M40: =M37 -> 50 | N40: =N37 -> 79 | O40: =O37 -> 51 | P40: =SUM(L40:O40) -> 228 | Q40: =Q37 -> 51 | R40: =R37 -> 175 | S40: =S37 -> 232 | T40: =T37 -> 292 | U40: =U37 -> 750 | V40: =V37 -> 312 | W40: =W37+W36 -> 610 | X40: =X37+X36 -> 747 | Y40: =Y37+Y36 -> 742 | Z40: =Z37+Z36 -> 2411 | AA40: =AA37+AA36 -> 872 | AB40: =AB37+AB36 -> 975 | AC40: =AC37+AC36 -> 1245 | AD40: =AD37+AD36 -> 1430 | ... AT40: =AT37+AT36 -> 9686 | AU40: =AU37+AU36+AU39 -> 3088 | AV40: =AV37+AV36+AV39 -> 3263 | AW40: =AW37+AW36+AW39 -> 3206 | AX40: =AX37+AX36+AX39 -> 3204 | AY40: =AY37+AY36+AY39 -> 12761 | AZ40: =AZ37+AZ36+AZ39 -> 3515 | BA40: =BA37+BA36 -> 3303 | BB40: =BB37+BB36 -> 3475 | BC40: =BC37+BC36 -> 7008 | BD40: =BD37+BD36 -> 17301 | BE40: =BE37+BE36+BE39 -> 4658 | BF40: =BF37+BF36 -> 4212 | BG40: =BG37+BG36 -> 4194 | BH40: =BH37+BH36 -> 3539 | BI40: =BI37+BI36 -> 16603 | BJ40: =BJ37+BJ36+BJ39 -> 6537 | BK40: =BK37+BK36+BK39 -> 3741 | BL40: =BL37+BL36+BL39 -> 4452 | BM40: =BM37+BM36+BM39 -> 4787 | BN40: =BN37+BN36 -> 20005 | BO40: =BO37+BO36+BO39 -> 5752 | BP40: =BP37+BP36+BP39 -> 6407 | BQ40: =BQ37+BQ36+BQ39 -> 6329 | BR40: =BR37+BR36+BR39 -> 5660 | BS40: =BS37+BS36+BS39 -> 24148 | BT40: =BT37+BT36+BT39 -> 9589 | BU40: =BU37+BU36+BU39 -> 10170 | BV40: =BV37+BV36+BV39 -> 9248 | ... CW40: =CW37+CW36+CW39 -> 105405
BO41: =11536-BO42 -> 0
B42: GAAP Operating Income | D42: =D33-D40 -> -339 | E42: =E33-E40 -> -847 | F42: =F33-F40 -> -1821 | G42: =G33-G40 -> -779 | H42: =H33-H40 -> -476 | I42: =I33-I40 -> -21 | J42: =J33-J40 -> -134 | K42: =K33-K40 -> -1410 | ... CW42: =CW33-CW40 -> 136250.12
C43: GAAP Operating Margin | D43: =D42/D4 -> -0.024517249 | E43: =E42/E4 -> -0.042650687 | F43: =F42/F4 -> -0.07226764 | G43: =G42/G4 -> -0.11197355 | H43: =H42/H4 -> -0.062747166 | I43: =I42/I4 -> -0.0026009413 | J43: =J42/J4 -> -0.016584158 | K43: =K42/K4 -> -0.045932827 | ... CW43: =CW42/CW4 -> 0.16973627
C45: Investment Income | D45: -314 | E45: -450 | F45: -319 | G45: -133 | H45: -77 | I45: -110 | J45: -71 | K45: -391 | L45: 34 | M45: -77 | N45: -61 | O45: -516 | P45: -620 | Q45: -45 | R45: -13 | S45: 96 | T45: 46 | U45: 84 | V45: 32 | W45: 26 | X45: 16 | Y45: 15 | Z45: 89 | AA45: 15 | AB45: 13 | AC45: 6 | AD45: 12 | AE45: 46 | AF45: 23 | AG45: 22 | AH45: 31 | AI45: 36 | AJ45: 112 | AK45: 49 | AL45: 50 | AM45: 52 | AN45: 36 | AO45: 187 | AP45: 37 | AQ45: 37 | AR45: 49 | AS45: 74 | AT45: 197 | AU45: 145 | AV45: 151 | AW45: 112 | AX45: 193 | AY45: 601 | AZ45: 191 | BA45: 242 | BB45: 272 | BC45: 328 | BD45: 1033 | BE45: 414 | BF45: 547 | BG45: 628 | BH45: 740 | BI45: =SUM(BE45:BH45) -> 2329 | BJ45: 577 | BK45: 813 | BL45: 843 | BM45: 714 | BN45: =SUM(BJ45:BM45) -> 2947 | BO45: 640 | BP45: 332 | BQ45: 107 | BR45: 129 | BS45: =SUM(BO45:BR45) -> 1208 | BT45: 97 | BU45: 79 | BV45: 66 | BW45: 36 | BX45: =SUM(BT45:BW45) -> 278 | BY45: 48 | BZ45: 172 | CA45: 586 | CB45: 864 | CC45: =SUM(BY45:CB45) -> 1670 | CD45: 1127 | CE45: 1611 | CF45: 2635 | CG45: 2288 | CH45: =SUM(CD45:CG45) -> 7661 | CI45: 2879 | CJ45: 2794 | CK45: 2704 | CL45: 2205 | CM45: =SUM(CI45:CL45) -> 10582 | CN45: 1849 | CO45: 688 | CP45: 1076 | CQ45: 1036 | CR45: =SUM(CN45:CQ45) -> 4649 | CS45: 950 | CT45: 820 | CU45: =CT45-45 -> 775 | CV45: =CU45-45 -> 730 | CW45: =SUM(CS45:CV45) -> 3275
C46: Other income | D46: =D47-D45 -> 0 | E46: =E47-E45 -> 0 | F46: =F47-F45 -> 0 | G46: =G47-G45 -> 0 | H46: =H47-H45 -> 0 | I46: =I47-I45 -> 0 | J46: =J47-J45 -> 0 | K46: =SUM(G46:J46) -> 0 | L46: =L47-L45 -> 0 | M46: =M47-M45 -> 0 | N46: =N47-N45 -> -8 | O46: =O47-O45 -> 0 | P46: =SUM(L46:O46) -> -8 | Q46: =Q47-Q45 -> -18 | R46: =R47-R45 -> 10 | S46: =S47-S45 -> -85 | T46: =T47-T45 -> -51 | U46: =SUM(Q46:T46) -> -144 | V46: =V47-V45 -> -18 | W46: =W47-W45 -> -16 | X46: =X47-X45 -> -28 | Y46: =Y47-Y45 -> -78 | Z46: =SUM(V46:Y46) -> -140 | AA46: =AA47-AA45 -> -65 | AB46: =AB47-AB45 -> -38 | AC46: =AC47-AC45 -> -94 | AD46: =AD47-AD45 -> -78 | AE46: =SUM(AA46:AD46) -> -275 | AF46: =AF47-AF45 -> -84 | AG46: =AG47-AG45 -> -48 | AH46: =AH47-AH45 -> 37 | AI46: =AI47-AI45 -> -52 | AJ46: =SUM(AF46:AI46) -> -147 | AK46: =AK47-AK45 -> -56 | AL46: =AL47-AL45 -> 35 | AM46: =AM47-AM45 -> -36 | AN46: =AN47-AN45 -> -401 | AO46: =SUM(AK46:AN46) -> -458 | AP46: =AP47-AP45 -> -112 | AQ46: =AQ47-AQ45 -> -57 | AR46: =AR47-AR45 -> -86 | AS46: =AS47-AS45 -> 110 | AT46: =SUM(AP46:AS46) -> -145 | AU46: =AU47-AU45 -> 293 | AV46: =AV47-AV45 -> -374 | AW46: =AW47-AW45 -> 947 | AX46: =AX47-AX45 -> -134 | AY46: =SUM(AU46:AX46) -> 732 | AZ46: =AZ47-AZ45 -> -60 | BA46: =BA47-BA45 -> -102 | BB46: =BB47-BB45 -> -195 | BC46: =BC47-BC45 -> 36 | BD46: =SUM(AZ46:BC46) -> -321 | BE46: =BE47-BE45 -> -154 | BF46: =BF47-BF45 -> -168 | BG46: =BG47-BG45 -> -219 | BH46: =BH47-BH45 -> -179 | BI46: =SUM(BE46:BH46) -> -720 | BJ46: =BJ47-BJ45 -> -103 | BK46: =BK47-BK45 -> 640 | BL46: =BL47-BL45 -> -143 | BM46: =BM47-BM45 -> 323 | BN46: =SUM(BJ46:BM46) -> 717 | BO46: =BO47-BO45 -> -1313 | BP46: =BP47-BP45 -> 1136 | BQ46: =BQ47-BQ45 -> 316 | BR46: =BR47-BR45 -> 1175 | BS46: =SUM(BO46:BR46) -> 1314 | BT46: =BT47-BT45 -> -422 | BU46: =BU47-BU45 -> -462 | BV46: =BV47-BV45 -> -782 | BW46: =BW47-BW45 -> -156 | BX46: =SUM(BT46:BW46) -> -1822 | BY46: =BY47-BY45 -> 375 | BZ46: =BZ47-BZ45 -> -1510 | CA46: =CA47-CA45 -> -1281 | CB46: =CB47-CB45 -> 888 | CC46: =SUM(BY46:CB46) -> -1528 | CD46: =CD47-CD45 -> 149 | CE46: =CE47-CE45 -> 271 | CF46: =CF47-CF45 -> -933 | CG46: =CG47-CG45 -> 1168 | CH46: =SUM(CD46:CG46) -> 655 | CI46: =CI47-CI45 -> 253 | CJ46: =CJ47-CJ45 -> 1262 | CK46: =CK47-CK45 -> 1074 | CL46: =CL47-CL45 -> -2578 | CM46: =SUM(CI46:CL46) -> 11 | CN46: =CN47-CN45 -> 358 | CO46: =CO47-CO45 -> 85 | CP46: =1260-1076 -> 184 | CQ46: =CQ47-CQ45 -> 256 | CR46: =SUM(CN46:CQ46) -> 883 | CS46: 0 | CT46: 0 | CU46: 0 | CV46: 0 | CW46: =SUM(CS46:CV46) -> 0
B47: Total Other Income | D47: -314 | E47: -450 | F47: -319 | G47: -133 | H47: -77 | I47: -110 | J47: -71 | K47: -391 | L47: 34 | M47: -77 | N47: -69 | O47: -516 | P47: -628 | Q47: -63 | R47: -3 | S47: 11 | T47: -5 | U47: -60 | V47: 14 | W47: 10 | X47: -12 | Y47: -63 | Z47: -51 | AA47: -50 | AB47: -25 | AC47: -88 | AD47: -66 | AE47: -229 | AF47: -61 | AG47: -26 | AH47: 68 | AI47: -16 | AJ47: -35 | AK47: -7 | AL47: 85 | AM47: 16 | AN47: -365 | AO47: -271 | AP47: -75 | AQ47: -20 | AR47: -37 | AS47: 184 | AT47: 52 | AU47: 438 | AV47: -223 | AW47: 1059 | AX47: 59 | AY47: 1333 | AZ47: 131 | BA47: 140 | BB47: 77 | BC47: 364 | BD47: 712 | BE47: 260 | BF47: 379 | BG47: 409 | BH47: 561 | BI47: =SUM(BE47:BH47) -> 1609 | BJ47: 474 | BK47: 1453 | BL47: 700 | BM47: 1037 | BN47: =SUM(BJ47:BM47) -> 3664 | BO47: -673 | BP47: 1468 | BQ47: 423 | BR47: 1304 | BS47: =SUM(BO47:BR47) -> 2522 | BT47: -325 | BU47: -383 | BV47: -716 | BW47: -120 | BX47: =SUM(BT47:BW47) -> -1544 | BY47: 423 | BZ47: -1338 | CA47: -695 | CB47: 1752 | CC47: =SUM(BY47:CB47) -> 142 | CD47: 1276 | CE47: 1882 | CF47: 1702 | CG47: 3456 | CH47: =SUM(CD47:CG47) -> 8316 | CI47: 3132 | CJ47: 4056 | CK47: 3778 | CL47: -373 | CM47: =SUM(CI47:CL47) -> 10593 | CN47: 2207 | CO47: 773 | CP47: =SUM(CP45:CP46) -> 1260 | CQ47: 1292 | CR47: =SUM(CN47:CQ47) -> 5532 | CS47: =SUM(CS45:CS46) -> 950 | CT47: =SUM(CT45:CT46) -> 820 | CU47: =SUM(CU45:CU46) -> 775 | CV47: =SUM(CV45:CV46) -> 730 | CW47: =SUM(CS47:CV47) -> 3275
C48: FX and interest rate impact | K48: 0 | P48: 0 | U48: 0 | Z48: 0 | AE48: 0 | AJ48: 0 | AO48: 0 | AT48: 0 | AY48: 0 | BD48: 0 | BI48: =SUM(BE48:BH48) -> 0 | BN48: =SUM(BJ48:BM48) -> 0 | BO48: 1243 | BP48: -1370 | BQ48: -559 | BR48: -1067 | BS48: =SUM(BO48:BR48) -> -1753 | BT48: -137 | BU48: 562 | BV48: 854 | BW48: -15 | BX48: =SUM(BT48:BW48) -> 1264 | BY48: -468 | BZ48: 1327 | CA48: 1151 | CB48: -984 | CC48: =SUM(BY48:CB48) -> 1026 | CD48: -137 | CE48: -290 | CF48: -98 | CG48: -1173 | CH48: =SUM(CD48:CG48) -> -1698 | CI48: -304 | CJ48: -1255 | CK48: -1077 | CL48: 2521 | CM48: =SUM(CI48:CL48) -> -115 | CN48: -366 | CO48: -107 | CP48: -205 | CQ48: 290 | CR48: =SUM(CN48:CQ48) -> -388 | CS48: 0 | CT48: 0 | CU48: 0 | CW48: =SUM(CS48:CV48) -> 0
C49: Other adjustments | K49: 0 | P49: 0 | U49: 0 | Z49: 0 | AE49: 0 | AJ49: 0 | AO49: 0 | AT49: 0 | AU49: -365 | AV49: 293 | AW49: -1034 | AY49: -1106 | BD49: 0 | BH49: 94 | BI49: =SUM(BE49:BH49) -> 94 | BN49: =SUM(BJ49:BM49) -> 0 | BO49: 0 | BP49: 0 | BQ49: 0 | BR49: 0 | BS49: =SUM(BO49:BR49) -> 0 | BT49: 0 | BU49: 0 | BV49: 0 | BW49: 0 | BX49: =SUM(BT49:BW49) -> 0 | BY49: 0 | BZ49: 0 | CA49: 0 | CB49: 0 | CC49: =SUM(BY49:CB49) -> 0 | CD49: 0 | CE49: 134 | CF49: 1036 | CG49: 0 | CH49: =SUM(CD49:CG49) -> 1170 | CI49: 0 | CJ49: 0 | CK49: 978 | CL49: 86 | CM49: =SUM(CI49:CL49) -> 1064 | CN49: 1013 | CO49: 106 | CP49: 10 | CQ49: -546 | CR49: =SUM(CN49:CQ49) -> 583 | CS49: 0 | CT49: 0 | CU49: 0 | CW49: =SUM(CS49:CV49) -> 0
B50: Non-GAAP other income | D50: =SUM(D47:D49) -> -314 | E50: =SUM(E47:E49) -> -450 | F50: =SUM(F47:F49) -> -319 | G50: =SUM(G47:G49) -> -133 | H50: =SUM(H47:H49) -> -77 | I50: =SUM(I47:I49) -> -110 | J50: =SUM(J47:J49) -> -71 | K50: =SUM(G50:J50) -> -391 | L50: =SUM(L47:L49) -> 34 | M50: =SUM(M47:M49) -> -77 | N50: =SUM(N47:N49) -> -69 | O50: =SUM(O47:O49) -> -516 | P50: =SUM(L50:O50) -> -628 | Q50: =SUM(Q47:Q49) -> -63 | R50: =SUM(R47:R49) -> -3 | S50: =SUM(S47:S49) -> 11 | T50: =SUM(T47:T49) -> -5 | U50: =SUM(Q50:T50) -> -60 | V50: =SUM(V47:V49) -> 14 | W50: =SUM(W47:W49) -> 10 | X50: =SUM(X47:X49) -> -12 | Y50: =SUM(Y47:Y49) -> -63 | Z50: =SUM(V50:Y50) -> -51 | AA50: =SUM(AA47:AA49) -> -50 | AB50: =SUM(AB47:AB49) -> -25 | AC50: =SUM(AC47:AC49) -> -88 | AD50: =SUM(AD47:AD49) -> -66 | AE50: =SUM(AA50:AD50) -> -229 | AF50: =SUM(AF47:AF49) -> -61 | AG50: =SUM(AG47:AG49) -> -26 | AH50: =SUM(AH47:AH49) -> 68 | AI50: =SUM(AI47:AI49) -> -16 | AJ50: =SUM(AF50:AI50) -> -35 | AK50: =SUM(AK47:AK49) -> -7 | AL50: =SUM(AL47:AL49) -> 85 | AM50: =SUM(AM47:AM49) -> 16 | AN50: =SUM(AN47:AN49) -> -365 | AO50: =SUM(AK50:AN50) -> -271 | AP50: =SUM(AP47:AP49) -> -75 | AQ50: =SUM(AQ47:AQ49) -> -20 | AR50: =SUM(AR47:AR49) -> -37 | AS50: =SUM(AS47:AS49) -> 184 | AT50: =SUM(AP50:AS50) -> 52 | AU50: =SUM(AU47:AU49) -> 73 | AV50: =SUM(AV47:AV49) -> 70 | AW50: =SUM(AW47:AW49) -> 25 | AX50: =SUM(AX47:AX49) -> 59 | AY50: =SUM(AU50:AX50) -> 227 | AZ50: =SUM(AZ47:AZ49) -> 131 | BA50: =SUM(BA47:BA49) -> 140 | BB50: =SUM(BB47:BB49) -> 77 | BC50: =SUM(BC47:BC49) -> 364 | BD50: =SUM(AZ50:BC50) -> 712 | BE50: =SUM(BE47:BE49) -> 260 | BF50: =SUM(BF47:BF49) -> 379 | BG50: =SUM(BG47:BG49) -> 409 | BH50: =SUM(BH47:BH49) -> 655 | BI50: =SUM(BE50:BH50) -> 1703 | BJ50: =SUM(BJ47:BJ49) -> 474 | BK50: =SUM(BK47:BK49) -> 1453 | BL50: =SUM(BL47:BL49) -> 700 | BM50: =SUM(BM47:BM49) -> 1037 | BN50: =SUM(BJ50:BM50) -> 3664 | BO50: =SUM(BO47:BO49) -> 570 | BP50: =SUM(BP47:BP49) -> 98 | BQ50: =SUM(BQ47:BQ49) -> -136 | BR50: =SUM(BR47:BR49) -> 237 | BS50: =SUM(BO50:BR50) -> 769 | BT50: =SUM(BT47:BT49) -> -462 | BU50: =SUM(BU47:BU49) -> 179 | BV50: =SUM(BV47:BV49) -> 138 | BW50: =SUM(BW47:BW49) -> -135 | BX50: =SUM(BT50:BW50) -> -280 | BY50: =SUM(BY47:BY49) -> -45 | BZ50: =SUM(BZ47:BZ49) -> -11 | CA50: =SUM(CA47:CA49) -> 456 | CB50: =SUM(CB47:CB49) -> 768 | CC50: =SUM(BY50:CB50) -> 1168 | CD50: =SUM(CD47:CD49) -> 1139 | CE50: =SUM(CE47:CE49) -> 1726 | CF50: =SUM(CF47:CF49) -> 2640 | CG50: =SUM(CG47:CG49) -> 2283 | CH50: =SUM(CD50:CG50) -> 7788 | CI50: =SUM(CI47:CI49) -> 2828 | CJ50: =SUM(CJ47:CJ49) -> 2801 | CK50: =SUM(CK47:CK49) -> 3679 | CL50: =SUM(CL47:CL49) -> 2234 | CM50: =SUM(CI50:CL50) -> 11542 | CN50: =SUM(CN47:CN49) -> 2854 | CO50: =SUM(CO47:CO49) -> 772 | CP50: =SUM(CP47:CP49) -> 1065 | CQ50: =SUM(CQ47:CQ49) -> 1036 | CR50: =SUM(CN50:CQ50) -> 5727 | CS50: =SUM(CS47:CS49) -> 950 | CT50: =SUM(CT47:CT49) -> 820 | CU50: =SUM(CU47:CU49) -> 775 | CV50: =SUM(CV47:CV49) -> 730 | CW50: =SUM(CS50:CV50) -> 3275
B52: Adjusted EBITDA | D52: -354 | E52: -739 | F52: 103 | G52: -259 | H52: 76 | I52: 504 | J52: 442 | K52: 763 | L52: 413 | M52: 1105 | N52: 861 | O52: 1177 | P52: 3556 | Q52: 1422 | R52: 1267 | S52: 1418 | T52: 1068 | U52: 5175 | V52: 1223 | W52: 1026 | X52: 1530 | Y52: 1631 | Z52: 5410 | AA52: 1858 | AB52: 2340 | AC52: 2189 | AD52: 2610 | AE52: =SUM(AA52:AD52) -> 8997 | AF52: 2922 | AG52: 3445 | AH52: 3628 | AI52: 3779 | AJ52: 13774 | AK52: 3902 | AL52: 4540 | AM52: 4686 | AN52: 4694 | AO52: 17891 | AP52: 4695 | AQ52: 5018 | AR52: 6197 | AS52: 6710 | AT52: 22620 | AU52: 5956 | AV52: 5695 | AW52: 7413 | AX52: 7438 | AY52: =SUM(AU52:AX52) -> 26502 | AZ52: =AZ64+AZ62+AZ37+CF!AZ9+CF!AZ13+AZ36+AZ39+AZ48-AZ45+AZ49 -> 8522 | BA52: =BA64+BA62+BA37+CF!BA9+CF!BA13+BA36+BA39+BA48-BA45+BA49 -> 7668 | BB52: =BB64+BB62+BB37+CF!BB9+CF!BB13+BB36+BB39+BB48-BB45+BB49 -> 7955 | BC52: =BC64+BC62+BC37+CF!BC9+CF!BC13+BC36+BC39+BC48-BC45+BC49 -> 8470 | BD52: =SUM(AZ52:BC52) -> 32615 | BE52: =BE64+BE62+BE37+CF!BE9+CF!BE13+BE36+BE39+BE48-BE45+BE49 -> 10887 | BF52: =BF64+BF62+BF37+CF!BF9+CF!BF13+BF36+BF39+BF48-BF45+BF49 -> 12102 | BG52: =BG64+BG62+BG37+CF!BG9+CF!BG13+BG36+BG39+BG48-BG45+BG49 -> 14364 | BH52: =BH64+BH62+BH37+CF!BH9+CF!BH13+BH36+BH39+BH48-BH45+BH49 -> 14042 | BI52: =SUM(BE52:BH52) -> 51395 | BJ52: =BJ64+BJ62+BJ37+CF!BJ9+CF!BJ13+BJ36+BJ39+BJ48-BJ45+BJ49 -> 16450 | BK52: =BK64+BK62+BK37+CF!BK9+CF!BK13+BK36+BK39+BK48-BK45+BK49 -> 16398 | BL52: =BL64+BL62+BL37+CF!BL9+CF!BL13+BL36+BL39+BL48-BL45+BL49 -> 18061 | BM52: =BM64+BM62+BM37+CF!BM9+CF!BM13+BM36+BM39+BM48-BM45+BM49 -> 18854 | BN52: =SUM(BJ52:BM52) -> 69763 | BO52: =BO64+BO62+BO37+CF!BO9+CF!BO13+BO36+BO39+BO48-BO45+BO49 -> 20356 | BP52: =BP64+BP62+BP37+CF!BP9+CF!BP13+BP36+BP39+BP48-BP45+BP49 -> 20422 | BQ52: =BQ64+BQ62+BQ37+CF!BQ9+CF!BQ13+BQ36+BQ39+BQ48-BQ45+BQ49 -> 23238 | BR52: =BR64+BR62+BR37+CF!BR9+CF!BR13+BR36+BR39+BR48-BR45+BR49 -> 22978 | BS52: =SUM(BO52:BR52) -> 86994 | BT52: =BT64+BT62+BT37+CF!BT9+CF!BT13+BT36+BT39+BT48-BT45+BT49 -> 25457 | BU52: =BU64+BU62+BU37+CF!BU9+CF!BU13+BU36+BU39+BU48-BU45+BU49 -> 27328 | BV52: =BV64+BV62+BV37+CF!BV9+CF!BV13+BV36+BV39+BV48-BV45+BV49 -> 26536 | BW52: =BW64+BW62+BW37+CF!BW9+CF!BW13+BW36+BW39+BW48-BW45+BW49 -> 27694 | BX52: =SUM(BT52:BW52) -> 107015 | BY52: =BY64+BY62+BY37+CF!BY9+CF!BY13+BY36+BY39+BY48-BY45+BY49 -> 31766 | BZ52: =BZ64+BZ62+BZ37+CF!BZ9+CF!BZ13+BZ36+BZ39+BZ48-BZ45+BZ49 -> 30864 | CA52: =CA64+CA62+CA37+CF!CA9+CF!CA13+CA36+CA39+CA48-CA45+CA49 -> 34687 | CB52: =CB64+CB62+CB37+CF!CB9+CF!CB13+CB36+CB39+CB48-CB45+CB49 -> 34951 | CC52: =SUM(BY52:CB52) -> 132268 | CD52: =CD64+CD62+CD37+CF!CD9+CF!CD13+CD36+CD39+CD48-CD45+CD49 -> 36999 | CE52: =CE64+CE62+CE37+CF!CE9+CF!CE13+CE36+CE39+CE48-CE45+CE49 -> 38171 | CF52: =CF64+CF62+CF37+CF!CF9+CF!CF13+CF36+CF39+CF48-CF45+CF49 -> 40503 | CG52: =CG64+CG62+CG37+CF!CG9+CF!CG13+CG36+CG39+CG48-CG45+CG49 -> 41956 | CH52: =SUM(CD52:CG52) -> 157629 | CI52: =CI64+CI62+CI37+CF!CI9+CF!CI13+CI36+CI39+CI48-CI45+CI49 -> 44402 | CJ52: =CJ64+CJ62+CJ37+CF!CJ9+CF!CJ13+CJ36+CJ39+CJ48-CJ45+CJ49 -> 44189 | CK52: =CK64+CK62+CK37+CF!CK9+CF!CK13+CK36+CK39+CK48-CK45+CK49 -> 48401 | CL52: =CL64+CL62+CL37+CF!CL9+CF!CL13+CL36+CL39+CL48-CL45+CL49 -> 49639 | CM52: =SUM(CI52:CL52) -> 186631 | CN52: =CN64+CN62+CN37+CF!CN9+CF!CN13+CN36+CN39+CN48-CN45+CN49 -> 54373 | CO52: =CO64+CO62+CO37+CF!CO9+CF!CO13+CO36+CO39+CO48-CO45+CO49 -> 56052 | CP52: =CP64+CP62+CP37+CF!CP9+CF!CP13+CP36+CP39+CP48-CP45+CP49 -> 60480 | CQ52: =CQ64+CQ62+CQ37+CF!CQ9+CF!CQ13+CQ36+CQ39+CQ48-CQ45+CQ49 -> 60462 | CR52: =SUM(CN52:CQ52) -> 231367 | CS52: =CS64+CS62+CS37+CF!CS9+CF!CS13+CS36+CS39+CS48-CS45+CS49 -> 56537.821 | CT52: =CT64+CT62+CT37+CF!CT9+CF!CT13+CT36+CT39+CT48-CT45+CT49 -> 64703.042 | CU52: =CU64+CU62+CU37+CF!CU9+CF!CU13+CU36+CU39+CU48-CU45+CU49 -> 69687.094 | CV52: =CV64+CV62+CV37+CF!CV9+CF!CV13+CV36+CV39+CV48-CV45+CV49 -> 72351.947 | CW52: =SUM(CS52:CV52) -> 263279.9
C53: EBITDA Margins | D53: =D52/D4 -> -0.025602083 | E53: =E52/E4 -> -0.037212347 | F53: =F52/F4 -> 0.004087626 | G53: =G52/G4 -> -0.037228691 | H53: =H52/H4 -> 0.010018455 | I53: =I52/I4 -> 0.062422591 | J53: =J52/J4 -> 0.05470297 | K53: =K52/K4 -> 0.024855849 | ... CW53: =CW52/CW4 -> 0.32798613
N54: =3206-P52 -> -350 | S54: =+S52-1418 -> 0 | CP54: =60480-CP52 -> 0
B55: Proforma Income Before Taxes | D55: =D33+D50 -> -653 | E55: =E33+E50 -> -1297 | F55: =F33+F50 -> -2094 | G55: =G33+G50 -> -876 | H55: =H33+H50 -> -516 | I55: =I33+I50 -> -94 | J55: =J33+J50 -> -158 | K55: =K33+K50 -> -1644 | ... CW55: =CW33+CW50 -> 244930.12
C56: Income Tax | D56: 23 | E56: 4 | F56: 16 | G56: 7 | H56: 2 | I56: 3 | J56: 82 | K56: =SUM(G56:J56) -> 94 | L56: 11 | M56: 0 | N56: 49 | O56: 31 | P56: =SUM(L56:O56) -> 91 | Q56: 65 | R56: 38 | S56: -7 | T56: -4 | U56: =SUM(Q56:T56) -> 92 | V56: 29 | W56: 78 | X56: 81 | Y56: =-12807+12802 -> -5 | Z56: =SUM(V56:Y56) -> 183 | AA56: 153 | AB56: =AB62 -> 300 | AC56: =AC62 -> -124 | AD56: =AD62 -> -208 | AE56: =SUM(AA56:AD56) -> 121 | AF56: =AF62 -> -66 | AG56: 169 | AH56: =AH62 -> 169 | AI56: =AI62 -> 414 | AJ56: =SUM(AF56:AI56) -> 686 | AK56: =AK62 -> 218 | AL56: =AL62 -> 460 | AM56: =AM62 -> 532 | AN56: =AN62 -> 198 | AO56: =SUM(AK56:AN56) -> 1408 | AP56: =AP62 -> 261 | AQ56: =AQ62 -> 356 | AR56: =AR62 -> 953 | AS56: 866 | AT56: =SUM(AP56:AS56) -> 2436 | AU56: 708 | AV56: 305 | AW56: 1220 | AX56: 907 | AY56: =SUM(AU56:AX56) -> 3140 | AZ56: =536+2133 -> 2669 | BA56: =1042+1211 -> 2253 | BB56: =1058+1259 -> 2317 | BC56: =8944+2171-8613 -> 2502 | BD56: =SUM(AZ56:BC56) -> 9741 | BE56: =1306+1153 -> 2459 | BF56: =928+1027 -> 1955 | BG56: =605+3008 -> 3613 | BH56: =1629+1406 -> 3035 | BI56: =SUM(BE56:BH56) -> 11062 | BJ56: =1040+2643 -> 3683 | BK56: =1987+1723 -> 3710 | BL56: =2692+1606 -> 4298 | BM56: =BM62+1332 -> 3971 | BN56: =SUM(BJ56:BM56) -> 15662 | BO56: =1348+3026 -> 4374 | BP56: =BP62+2886 -> 4271 | BQ56: =2970+2929 -> 5899 | BR56: =1391+3444 -> 4835 | BS56: =SUM(BO56:BR56) -> 19379 | BT56: =2137+3975 -> 6112 | BU56: =2963+3999 -> 6962 | BV56: =BV62+4178 -> 5534 | BW56: =2488+4302 -> 6790 | BX56: =SUM(BT56:BW56) -> 25398 | BY56: =4330+3219 -> 7549 | BZ56: =BZ62+3491 -> 7368 | CA56: =CA62+4866 -> 7998 | CB56: =CB62+3063 -> 7914 | CC56: =SUM(BY56:CB56) -> 30829 | CD56: =CD62+5909 -> 8626 | CE56: =CE62+5199 -> 9432 | CF56: =CF62+4981 -> 10440 | CG56: =7330+3906 -> 11236 | CH56: =SUM(CD56:CG56) -> 39734 | CI56: =+CI62+9554 -> 10086 | CJ56: =CJ62+3066 -> 12255 | CK56: =CK62+5514 -> 11403 | CL56: =CL62+6371 -> 13183 | CM56: =SUM(CI56:CL56) -> 46927 | CN56: =CN62+7285 -> 13252 | CO56: =7510+6285 -> 13795 | CP56: =CP62+6365 -> 13247 | CQ56: =CQ62+2344 -> 12481 | CR56: =SUM(CN56:CQ56) -> 52775 | CS56: =CS55*CS57 -> 15888.161 | CT56: =CT55*CT57 -> 17979.575 | CU56: =CU55*CU57 -> 19427.481 | CV56: =CV55*CV57 -> 20183.819 | CW56: =SUM(CS56:CV56) -> 73479.036
C57: Reported Tax Rate % | D57: =D56/D55 -> -0.035222052 | E57: =E56/E55 -> -0.0030840401 | F57: =F56/F55 -> -0.0076408787 | G57: =G56/G55 -> -0.0079908676 | H57: =H56/H55 -> -0.003875969 | I57: =I56/I55 -> -0.031914894 | J57: =J56/J55 -> -0.51898734 | K57: =K56/K55 -> -0.057177616 | ... CH57: =CH56/CH55 -> 0.2709278 | CI57: =CG56/CG55 -> 0.28390227 | CJ57: =CJ56/CJ55 -> 0.28971631 | CK57: =CK56/CK55 -> 0.24537356 | CL57: =CL56/CL55 -> 0.27969788 | CM57: =CM56/CM55 -> 0.26290814 | CN57: =CN56/CN55 -> 0.25849995 | CO57: =CO56/CO55 -> 0.2665752 | CP57: =CP56/CP55 -> 0.23570336 | CQ57: =CQ56/CQ55 -> 0.22403116 | CR57: =CR56/CR55 -> 0.24554849 | CS57: 0.3 | CT57: 0.3 | CU57: 0.3 | CV57: 0.3 | CW57: =CW56/CW55 -> 0.3
B58: Proforma Net Income | D58: =D55-D56 -> -676 | E58: =E55-E56 -> -1301 | F58: =F55-F56 -> -2110 | G58: =G55-G56 -> -883 | H58: =H55-H56 -> -518 | I58: =I55-I56 -> -97 | J58: =J55-J56 -> -240 | K58: =K55-K56 -> -1738 | ... CW58: =CW55-CW56 -> 171451.08
C59: Proforma Net Margin | D59: =D58/D4 -> -0.048889853 | E59: =E58/E4 -> -0.065511859 | F59: =F58/F4 -> -0.083736805 | G59: =G58/G4 -> -0.12692252 | H59: =H58/H4 -> -0.06828368 | I59: =I58/I4 -> -0.012013872 | J59: =J58/J4 -> -0.02970297 | K59: =K58/K4 -> -0.056617911 | ... CW59: =CW58/CW4 -> 0.21358856
B61: GAAP Pre-Tax Income | D61: =D42+D47 -> -653 | E61: =E42+E47 -> -1297 | F61: =F42+F47 -> -2140 | G61: =G42+G47 -> -912 | H61: =H42+H47 -> -553 | I61: =I42+I47 -> -131 | J61: =J42+J47 -> -205 | K61: =K42+K47 -> -1801 | ... CW61: =CW42+CW47 -> 139525.12
C62: Income Tax | D62: 23 | E62: =E56 -> 4 | F62: =F56 -> 16 | G62: =G56 -> 7 | H62: =H56 -> 2 | I62: =I56 -> 3 | J62: =J56 -> 82 | K62: =K56 -> 94 | L62: =L56 -> 11 | ... R62: =R56 -> 38 | S62: -7 | T62: =T56 -> -4 | U62: =U56 -> 92 | V62: =V56 -> 29 | W62: =W56 -> 78 | X62: =X56 -> 81 | Y62: -12807 | Z62: =Z56 -> 183 | AA62: 153 | AB62: 300 | AC62: -124 | AD62: -208 | AE62: =AE56 -> 121 | AF62: -66 | AG62: 169 | AH62: 169 | AI62: 414 | AJ62: =AJ56 -> 686 | AK62: 218 | AL62: 460 | AM62: 532 | AN62: 198 | AO62: =AO56 -> 1408 | AP62: 261 | AQ62: 356 | AR62: 953 | AS62: 866 | AT62: =AT56 -> 2436 | AU62: 708 | AV62: 305 | AW62: 1220 | AX62: 907 | AY62: =AY56 -> 3140 | AZ62: 536 | BA62: 1042 | BB62: 1058 | BC62: 8944 | BD62: =SUM(AZ62:BC62) -> 11580 | BE62: 1306 | BF62: 928 | BG62: 605 | BH62: 1629 | BI62: =SUM(BE62:BH62) -> 4468 | BJ62: 1040 | BK62: 1987 | BL62: 2692 | BM62: 2639 | BN62: =SUM(BJ62:BM62) -> 8358 | BO62: 1348 | BP62: =1385 -> 1385 | BQ62: 2970 | BR62: 1391 | BS62: =SUM(BO62:BR62) -> 7094 | BT62: 2137 | BU62: =2963 -> 2963 | BV62: 1356 | BW62: 2488 | BX62: =SUM(BT62:BW62) -> 8944 | BY62: 4330 | BZ62: 3877 | CA62: 3132 | CB62: 4851 | CC62: =SUM(BY62:CB62) -> 16190 | CD62: 2717 | CE62: 4233 | CF62: 5459 | CG62: 7330 | CH62: =SUM(CD62:CG62) -> 19739 | CI62: 532 | CJ62: 9189 | CK62: 5889 | CL62: 6812 | CM62: =SUM(CI62:CL62) -> 22422 | CN62: 5967 | CO62: 7510 | CP62: 6882 | CQ62: 10137 | CR62: =SUM(CN62:CQ62) -> 30496 | CS62: =CS61*CS63 -> 7848.1608 | CT62: =CT61*CT63 -> 10109.075 | CU62: =CU61*CU63 -> 11571.981 | CV62: =CV61*CV63 -> 12328.319 | CW62: =SUM(CS62:CV62) -> 41857.536
C63: Tax Rate % | D63: =D62/D61 -> -0.035222052 | E63: =E62/E61 -> -0.0030840401 | F63: =F62/F61 -> -0.0074766355 | G63: =G62/G61 -> -0.0076754386 | H63: =H62/H61 -> -0.0036166365 | I63: =I62/I61 -> -0.022900763 | J63: =J62/J61 -> -0.4 | K63: =K62/K61 -> -0.052193226 | ... AG63: =AG62/AG61 -> 0.36980306 | AH63: 0.39 | AI63: 0.39 | AJ63: =AJ62/AJ61 -> 0.39493379 | AK63: =AK62/AK61 -> 0.36886633 | AL63: =AL62/AL61 -> 0.41856233 | AM63: =AM62/AM61 -> 0.38832117 | AN63: =AN62/AN61 -> 0.18821293 | AO63: =AO62/AO61 -> 0.34241245 | AP63: =AP62/AP61 -> 0.3081464 | AQ63: =AQ62/AQ61 -> 0.35352532 | ... CR63: =CR62/CR61 -> 0.24626317 | CS63: 0.3 | CT63: 0.3 | CU63: 0.3 | CV63: 0.3 | CW63: =CW62/CW61 -> 0.3
B64: GAAP Net income | D64: =D61-D62 -> -676 | E64: =E61-E62 -> -1301 | F64: =F61-F62 -> -2156 | G64: =G61-G62 -> -919 | H64: =H61-H62 -> -555 | I64: =I61-I62 -> -134 | J64: =J61-J62 -> -287 | K64: =K61-K62 -> -1895 | ... CW64: =CW61-CW62 -> 97667.583
C65: GAAP Net margin | D65: =D64/D4 -> -0.048889853 | E65: =E64/E4 -> -0.065511859 | F65: =F64/F4 -> -0.085562346 | G65: =G64/G4 -> -0.13209717 | H65: =H64/H4 -> -0.073161086 | I65: =I64/I4 -> -0.016596483 | J65: =J64/J4 -> -0.035519802 | K65: =K64/K4 -> -0.061732417 | ... CW65: =CW64/CW4 -> 0.12167132
B67: Proforma EPS | D67: =D58/D73 -> -6.6930693 | E67: =E58/E73 -> -10.932773 | F67: =F58/F73 -> -11.405405 | G67: =G58/G73 -> #DIV/0! | H67: =H58/H73 -> #DIV/0! | I67: =I58/I73 -> #DIV/0! | J67: =J58/J73 -> #DIV/0! | K67: =K58/K73 -> -5.9115646 | ... CW67: =CW58/CW73 -> 4.4648138
C68: Y/Y Growth % | E68: =E67/D67-1 -> 0.63344687 | F68: =F67/E67-1 -> 0.043230779 | K68: =K67/F67-1 -> -0.48168746 | L68: =L67/G67-1 -> #DIV/0! | M68: =M67/H67-1 -> #DIV/0! | N68: =N67/I67-1 -> #DIV/0! | O68: =O67/J67-1 -> #DIV/0! | P68: =P67/K67-1 -> -1.0253703 | Q68: =Q67/L67-1 -> -6.6180227 | R68: =R67/M67-1 -> -0.12172744 | ... CW68: =CW67/CR67-1 -> 0.046671341
B69: GAAP EPS | D69: =D64/D73 -> -6.6930693 | E69: =E64/E73 -> -10.932773 | F69: =F64/F73 -> -11.654054 | G69: =G64/G73 -> #DIV/0! | H69: =H64/H73 -> #DIV/0! | I69: =I64/I73 -> #DIV/0! | J69: =J64/J73 -> #DIV/0! | K69: =K64/K73 -> -6.4455782 | ... V69: =V64/V73 -> 0.038746259 | W69: =W64/W72 -> -0.0091450625 | X69: =X64/X73 -> 0.013898704 | Y69: =Y64/Y73 -> 1.0174176 | Z69: =Z64/Z73 -> 0.070706873 | AA69: =AA64/AA73 -> 0.019416003 | AB69: =AB64/AB73 -> 0.032703823 | AC69: =AC64/AC73 -> 0.012523391 | AD69: =AD64/AD73 -> 0.023588554 | AE69: =AE64/AE73 -> 0.087880477 | ... CW69: =CW64/CW73 -> 2.5433935
C70: Y/Y Growth % | E70: =E69/D69-1 -> 0.63344687 | F70: =F69/E69-1 -> 0.065974199 | K70: =K69/F69-1 -> -0.44692395 | L70: =L69/G69-1 -> #DIV/0! | M70: =M69/H69-1 -> #DIV/0! | N70: =N69/I69-1 -> #DIV/0! | O70: =O69/J69-1 -> #DIV/0! | P70: =P69/K69-1 -> -1.0194517 | Q70: =Q69/L69-1 -> -1.5914047 | R70: =R69/M69-1 -> -0.25832525 | ... CW70: =CW69/CR69-1 -> 0.035809062
C72: Basic Shares Oustanding | D72: 101 | E72: 119 | F72: 185 | K72: 294 | L72: 331 | M72: 331 | N72: 331 | O72: 329 | P72: 329 | Q72: 327 | R72: 8301 | S72: 11727 | T72: 11727 | U72: =AVERAGE(Q72:T72) -> 8020.5 | V72: 11864 | W72: 11919 | AV72: 16909 | AW72: 17001 | AX72: 17050 | AZ72: 17154 | BA72: 17198 | BB72: 17223 | BC72: 17157 | BE72: 17093 | BG72: 17219 | BH72: 17280
B73: Fully Diluted Share Outstanding | D73: 101 | E73: 119 | F73: 185 | K73: 294 | L73: 331 | M73: 9046 | N73: 9004 | O73: 9428 | P73: 9268 | Q73: 9525 | R73: 11844 | S73: 12413 | T73: 12552 | U73: =AVERAGE(Q73:T73) -> 11583.5 | V73: 12698 | W73: 12620 | X73: 12735 | Y73: 12918 | Z73: =AVERAGE(V73:Y73) -> 12742.75 | AA73: 13185 | AB73: 13026 | AC73: 13894 | AD73: 15516 | AE73: =AVERAGE(AA73:AD73) -> 13905.25 | AF73: 15564 | AG73: 15785 | AH73: 15986 | AI73: 16376 | AJ73: =AVERAGE(AF73:AI73) -> 15927.75 | AK73: 16830 | AL73: 16768 | AM73: 16780 | AN73: 16814 | AO73: =AVERAGE(AK73:AN73) -> 16798 | AP73: 17011 | AQ73: 16998 | AR73: 17054 | AS73: 17110 | AT73: =AVERAGE(AP73:AS73) -> 17043.25 | AU73: 17029 | AV73: 17120 | AW73: 17341 | AX73: 17366 | AY73: =AVERAGE(AU73:AX73) -> 17214 | AZ73: 17393 | BA73: 17378 | BB73: 17410 | BC73: 17325 | BD73: =AVERAGE(AZ73:BC73) -> 17376.5 | BE73: 17307 | BF73: 17549 | BG73: 17741 | BH73: 17722 | BI73: =AVERAGE(BE73:BH73) -> 17579.75 | BJ73: 17992 | BK73: 18010 | BL73: 35932 | BM73: 35967 | BN73: 36200 | BO73: 35926 | BP73: 36016 | BQ73: 36366 | BR73: 36624 | BS73: =AVERAGE(BO73:BR73) -> 36233 | BT73: 36722 | BU73: 36753 | BV73: 37015 | BW73: 37135 | BX73: =AVERAGE(BT73:BW73) -> 36906.25 | BY73: 36989 | BZ73: 36862 | CA73: 36915 | CB73: 36971 | CC73: =AVERAGE(BY73:CB73) -> 36934.25 | CD73: 37155 | CE73: =+CD73+350 -> 37505 | CF73: 37584 | CG73: 37640 | CH73: =AVERAGE(CD73:CG73) -> 37471 | CI73: 37686 | CJ73: 37683 | CK73: 37996 | CL73: 37856 | CM73: =AVERAGE(CI73:CL73) -> 37805.25 | CN73: 38163 | CO73: 38132 | CP73: 37993 | CQ73: 37763 | CR73: =AVERAGE(CN73:CQ73) -> 38012.75 | CS73: =+CQ73+450 -> 38213 | CT73: =+CS73+125 -> 38338 | CU73: =+CT73+125 -> 38463 | CV73: =+CU73+125 -> 38588 | CW73: =AVERAGE(CS73:CV73) -> 38400.5
B75: Deferred Revenue | F75: =BS!F28+BS!F33 -> 0 | G75: =BS!G28+BS!G33 -> 0 | H75: =BS!H28+BS!H33 -> 0 | I75: =BS!I28+BS!I33 -> 0 | J75: =BS!J28+BS!J33 -> 6588 | K75: =BS!K28+BS!K33 -> 0 | L75: =BS!L28+BS!L33 -> 0 | M75: =BS!M28+BS!M33 -> 0 | ... T75: =BS!T28+BS!T33 -> 8587 | V75: =BS!V28+BS!V33 -> 8851 | W75: =BS!W28+BS!W33 -> 9195 | X75: =BS!X28+BS!X33 -> 9910 | Y75: =BS!Y28+BS!Y33 -> 10439 | AA75: =BS!AA28+BS!AA33 -> 11371 | AB75: =BS!AB28+BS!AB33 -> 12239 | AC75: =BS!AC28+BS!AC33 -> 13265 | AD75: =BS!AD28+BS!AD33 -> 13811 | AF75: =BS!AF28+BS!AF33 -> 14166 | AG75: =BS!AG28+BS!AG33 -> 14860 | AH75: =BS!AH28+BS!AH33 -> 15217 | AI75: =BS!AI28+BS!AI33 -> 15120 | AK75: =BS!AK28+BS!AK33 -> 15694 | AL75: =BS!AL28+BS!AL33 -> 16929 | AM75: =BS!AM28+BS!AM33 -> 17198 | AN75: =BS!AN28+BS!AN33 -> 18158 | AP75: =BS!AP28+BS!AP33 -> 18080 | AQ75: =BS!AQ28+BS!AQ33 -> 18829 | AR75: =BS!AR28+BS!AR33 -> 19773 | AS75: =BS!AS28+BS!AS33 -> 18745 | AU75: =BS!AU28+BS!AU33 -> 22210 | AV75: =BS!AV28+BS!AV33 -> 23517 | AW75: =BS!AW28+BS!AW33 -> 23119 | AX75: =BS!AX28+BS!AX33 -> 21902 | AZ75: =BS!AZ28+BS!AZ33 -> 26890 | BA75: =BS!BA28+BS!BA33 -> 27674 | BB75: =BS!BB28+BS!BB33 -> 26834 | BC75: =BS!BC28+BS!BC33 -> 27009 | BE75: =BS!BE28+BS!BE33 -> 24274 | BF75: =BS!BF28+BS!BF33 -> 26831 | BG75: 17741 | BH75: 17741 | BJ75: =BS!BJ28+BS!BJ33 -> 31538 | BK75: =BS!BK28+BS!BK33 -> 33090 | BL75: =BS!BL28+BS!BL33 -> 32952 | BM75: =BS!BM28+BS!BM33 -> 34314 | BO75: =BS!BO28+BS!BO33 -> 37710 | BP75: =BS!BP28+BS!BP33 -> 39019 | BQ75: =BS!BQ28+BS!BQ33 -> 38275 | BR75: =BS!BR28+BS!BR33 -> 40943 | BT75: =BS!BT28+BS!BT33 -> 48508 | BU75: =BS!BU28+BS!BU33 -> 53472 | BV75: =BS!BV28+BS!BV33 -> 54344 | BW75: =BS!BW28+BS!BW33 -> 55572 | BY75: =BS!BY28+BS!BY33 -> 61921 | BZ75: =BS!BZ28+BS!BZ33 -> 64374 | CA75: =BS!CA28+BS!CA33 -> 64095 | CB75: =BS!CB28+BS!CB33 -> 62194 | CD75: =BS!CD28+BS!CD33 -> 68012 | CE75: =BS!CE28+BS!CE33 -> 72105 | CF75: =BS!CF28+BS!CF33 -> 78702 | CG75: =BS!CG28+BS!CG33 -> 76117 | CI75: =BS!CI28+BS!CI33 -> 80174 | CJ75: =BS!CJ28+BS!CJ33 -> 83504 | CK75: =BS!CK28+BS!CK33 -> 85433 | CL75: =BS!CL28+BS!CL33 -> 80445 | CN75: =BS!CN28+BS!CN33 -> 84368 | CO75: =BS!CO28+BS!CO33 -> 84675 | CP75: =BS!CP28+BS!CP33 -> 82716 | CQ75: =BS!CQ28+BS!CQ33 -> 80878
B76: CFO | F76: =CF!F29 -> -803 | G76: =CF!G29 -> 505 | H76: =CF!H29 -> 486 | I76: =CF!I29 -> 494 | J76: =CF!J29 -> 503 | K76: =CF!K29 -> -807 | L76: =CF!L29 -> 1194 | M76: =CF!M29 -> 321 | ... CR76: =CF!CR29 -> 178790
B77: Cash Balance | C77: Cash Balance | F77: =BS!F6 -> 0 | G77: =BS!G6 -> 0 | H77: =BS!H6 -> 0 | I77: =BS!I6 -> 0 | J77: =BS!J6 -> 3715 | K77: =BS!K6 -> 0 | O77: =BS!O6 -> 5931 | P77: =BS!P6 -> 0 | Q77: =BS!Q6 -> 5996 | R77: =BS!R6 -> 37973 | S77: =BS!S6 -> 39113 | T77: =BS!T6 -> 40473 | V77: =BS!V6 -> 40447 | W77: =BS!W6 -> 29788 | X77: =BS!X6 -> 31546 | Y77: =BS!Y6 -> 31985 | AA77: =BS!AA6 -> 33063 | AB77: =BS!AB6 -> 35501 | AC77: =BS!AC6 -> 69715 | AD77: =BS!AD6 -> 66050 | AF77: =BS!AF6 -> 72559 | AG77: =BS!AG6 -> 75134 | AH77: =BS!AH6 -> 80813 | AI77: =BS!AI6 -> 131294 | AK77: =BS!AK6 -> 134603 | AL77: =BS!AL6 -> 136508 | AM77: =BS!AM6 -> 140822 | AN77: =BS!AN6 -> 130795 | AP77: =BS!AP6 -> 133550 | AQ77: =BS!AQ6 -> 121344 | AR77: =BS!AR6 -> 117887 | AS77: =BS!AS6 -> 121538 | AU77: =BS!AU6+BS!AU7+BS!AU16 -> 133428 | AV77: =BS!AV6+BS!AV7+BS!AV16 -> 135726 | AW77: =BS!AW6+BS!AW7+BS!AW16 -> 137780 | AX77: =BS!AX6+BS!AX7+BS!AX16 -> 146447 | AZ77: =BS!AZ6+BS!AZ7+BS!AZ16 -> 156760 | BA77: =BS!BA6+BS!BA7+BS!BA16 -> 163637 | BB77: =BS!BB6+BS!BB7+BS!BB16 -> 166344 | BC77: =BS!BC6+BS!BC7+BS!BC16 -> 168525 | BE77: =BS!BE6+BS!BE7+BS!BE16 -> 168290 | BF77: =BS!BF6+BS!BF7+BS!BF16 -> 177659 | BG77: =BS!BG6+BS!BG7+BS!BG16 -> 194323 | BH77: =BS!BH6+BS!BH7+BS!BH16 -> 178396 | BJ77: =BS!BJ6+BS!BJ7+BS!BJ16 -> 185398 | BK77: =BS!BK6+BS!BK7+BS!BK16 -> 198674 | BL77: =BS!BL6+BS!BL7+BS!BL16 -> 201173 | BM77: =BS!BM6+BS!BM7+BS!BM16 -> 213536 | BO77: =BS!BO6+BS!BO7+BS!BO16 -> 214558 | BP77: =BS!BP6+BS!BP7+BS!BP16 -> 233191 | BQ77: =BS!BQ6+BS!BQ7+BS!BQ16 -> 263706 | BR77: =BS!BR6+BS!BR7+BS!BR16 -> 189978 | BT77: =BS!BT6+BS!BT7+BS!BT16 -> 210948 | BU77: =BS!BU6+BS!BU7+BS!BU16 -> 233366 | BV77: =BS!BV6+BS!BV7+BS!BV16 -> 251986 | BW77: =BS!BW6+BS!BW7+BS!BW16 -> 257310 | BY77: =BS!BY6+BS!BY7+BS!BY16 -> 243056 | BZ77: =BS!BZ6+BS!BZ7+BS!BZ16 -> 259238 | CA77: =BS!CA6+BS!CA7+BS!CA16 -> 237158 | CB77: =BS!CB6+BS!CB7+BS!CB16 -> 214305 | CD77: =BS!CD6+BS!CD7+BS!CD16 -> 233450 | CE77: =BS!CE6+BS!CE7+BS!CE16 -> 270178 | CF77: =BS!CF6+BS!CF7+BS!CF16 -> 239330 | CG77: =BS!CG6+BS!CG7+BS!CG16 -> 275440 | CI77: =BS!CI6+BS!CI7+BS!CI16 -> 290811 | CJ77: =BS!CJ6+BS!CJ7+BS!CJ16 -> 271786 | CK77: =BS!CK6+BS!CK7+BS!CK16 -> 205773 | CL77: =BS!CL6+BS!CL7+BS!CL16 -> 241017 | CN77: =BS!CN6+BS!CN7+BS!CN16 -> 94921 | CO77: =BS!CO6+BS!CO7+BS!CO16 -> 107603 | CP77: =BS!CP6+BS!CP7+BS!CP16 -> 133725 | CQ77: =BS!CQ6+BS!CQ7+BS!CQ16 -> 151355
B78: Cash/Share | F78: =F77/F73 -> 0 | G78: =G77/G73 -> #DIV/0! | H78: =H77/H73 -> #DIV/0! | I78: =I77/I73 -> #DIV/0! | J78: =J77/J73 -> #DIV/0! | K78: =K77/K73 -> 0 | P78: =P77/P73 -> 0 | Q78: =Q77/Q73 -> 0.62950131 | R78: =R77/R73 -> 3.2060959 | S78: =S77/S73 -> 3.1509708 | T78: =T77/T73 -> 3.2244264 | V78: =V77/V73 -> 3.1853048 | W78: =W77/W73 -> 2.3603803 | X78: =X77/X73 -> 2.4771103 | Y78: =Y77/Y73 -> 2.4760025 | AA78: =AA77/AA73 -> 2.5076223 | AB78: =AB77/AB73 -> 2.7253954 | AC78: =AC77/AC73 -> 5.0176335 | AD78: =AD77/AD73 -> 4.2568961 | AF78: =AF77/AF73 -> 4.6619764 | AG78: =AG77/AG73 -> 4.7598353 | AH78: =AH77/AH73 -> 5.0552358 | AI78: =AI77/AI73 -> 8.0174646 | AK78: =AK77/AK73 -> 7.9978015 | AL78: =AL77/AL73 -> 8.1409828 | AM78: =AM77/AM73 -> 8.3922527 | AN78: =AN77/AN73 -> 7.7789342 | AP78: =AP77/AP73 -> 7.8508024 | AQ78: =AQ77/AQ73 -> 7.1387222 | AR78: =AR77/AR73 -> 6.9125718 | AS78: =AS77/AS73 -> 7.1033314 | AU78: =AU77/AU73 -> 7.8353397 | AV78: =AV77/AV73 -> 7.9279206 | AW78: =AW77/AW73 -> 7.9453319 | AX78: =AX77/AX73 -> 8.4329725 | AZ78: =AZ77/AZ73 -> 9.0128212 | BA78: =BA77/BA73 -> 9.416331 | BB78: =BB77/BB73 -> 9.5545089 | BC78: =BC77/BC73 -> 9.7272727 | BE78: =BE77/BE73 -> 9.7238112 | BF78: =BF77/BF73 -> 10.123597 | BG78: =BG77/BG73 -> 10.953328 | BH78: =BH77/BH73 -> 10.066358 | BJ78: =BJ77/BJ73 -> 10.304469 | BK78: =BK77/BK73 -> 11.031316 | BL78: =BL77/BL73 -> 5.5987142 | BM78: =BM77/BM73 -> 5.9369978 | BO78: =BO77/BO73 -> 5.9722207 | BP78: =BP77/BP73 -> 6.4746502 | BQ78: =BQ77/BQ73 -> 7.2514437 | BR78: =BR77/BR73 -> 5.1872543 | BT78: =BT77/BT73 -> 5.7444584 | BU78: =BU77/BU73 -> 6.3495769 | BV78: =BV77/BV73 -> 6.8076726 | BW78: =BW77/BW73 -> 6.9290427 | BY78: =BY77/BY73 -> 6.5710346 | BZ78: =BZ77/BZ73 -> 7.0326624 | CA78: =CA77/CA73 -> 6.4244345 | CB78: =CB77/CB73 -> 5.7965703 | CD78: =CD77/CD73 -> 6.2831382 | CE78: =CE77/CE73 -> 7.2037862 | CF78: =CF77/CF73 -> 6.3678693 | CG78: =CG77/CG73 -> 7.3177471 | CI78: =CI77/CI73 -> 7.7166852 | CJ78: =CJ77/CJ73 -> 7.21243 | CK78: =CK77/CK73 -> 5.415649 | CL78: =CL77/CL73 -> 6.366679 | CN78: =CN77/CN73 -> 2.4872521 | CO78: =CO77/CO73 -> 2.8218557 | CP78: =CP77/CP73 -> 3.5197273 | CQ78: =CQ77/CQ73 -> 4.0080237
B79: Net Cash | AK79: =BS!AK6+BS!AK7+BS!AK16-BS!AK22-BS!AK23-BS!AK32-BS!AK35 -> 134603 | AL79: =BS!AL6+BS!AL7+BS!AL16-BS!AL22-BS!AL23-BS!AL32-BS!AL35 -> 136508 | AM79: =BS!AM6+BS!AM7+BS!AM16-BS!AM22-BS!AM23-BS!AM32-BS!AM35 -> 140822 | AN79: =BS!AN6+BS!AN7+BS!AN16-BS!AN22-BS!AN23-BS!AN32-BS!AN35 -> 130795 | AP79: =BS!AP6+BS!AP7+BS!AP16-BS!AP22-BS!AP23-BS!AP32-BS!AP35 -> 133550 | AQ79: =BS!AQ6+BS!AQ7+BS!AQ16-BS!AQ22-BS!AQ23-BS!AQ32-BS!AQ35 -> 131339 | AR79: =BS!AR6+BS!AR7+BS!AR16-BS!AR22-BS!AR23-BS!AR32-BS!AR35 -> 135415 | AS79: =BS!AS6+BS!AS7+BS!AS16-BS!AS22-BS!AS23-BS!AS32-BS!AS35 -> 144005 | AU79: =AU77-BS!AU21-BS!AU22-BS!AU23-BS!AU32-BS!AU35 -> 133428 | AV79: =AV77-BS!AV21-BS!AV22-BS!AV23-BS!AV32-BS!AV35 -> 135726 | AW79: =AW77-BS!AW21-BS!AW22-BS!AW23-BS!AW32-BS!AW35 -> 137780 | AX79: =AX77-BS!AX21-BS!AX22-BS!AX23-BS!AX32-BS!AX35 -> 146447 | AZ79: =AZ77-BS!AZ21-BS!AZ22-BS!AZ23-BS!AZ32-BS!AZ35 -> 156760 | BA79: =BA77-BS!BA21-BS!BA22-BS!BA23-BS!BA32-BS!BA35 -> 163637 | BB79: =BB77-BS!BB21-BS!BB22-BS!BB23-BS!BB32-BS!BB35 -> 166344 | BC79: =BC77-BS!BC21-BS!BC22-BS!BC23-BS!BC32-BS!BC35 -> 168525 | BE79: =BE77-BS!BE21-BS!BE22-BS!BE23-BS!BE32-BS!BE35 -> 168290 | BF79: =BF77-BS!BF21-BS!BF22-BS!BF23-BS!BF32-BS!BF35 -> 177659 | BG79: =BG77-BS!BG21-BS!BG22-BS!BG23-BS!BG32-BS!BG35 -> 194323 | BH79: =BH77-BS!BH21-BS!BH22-BS!BH23-BS!BH32-BS!BH35 -> 178396 | BJ79: =BJ77-BS!BJ21-BS!BJ22-BS!BJ23-BS!BJ32-BS!BJ35 -> 185398 | BK79: =BK77-BS!BK21-BS!BK22-BS!BK23-BS!BK32-BS!BK35 -> 198674 | BL79: =BL77-BS!BL21-BS!BL22-BS!BL23-BS!BL32-BS!BL35 -> 201173 | BM79: =BM77-BS!BM21-BS!BM22-BS!BM23-BS!BM32-BS!BM35 -> 213536 | BO79: =BO77-BS!BO21-BS!BO22-BS!BO23-BS!BO32-BS!BO35 -> 214558 | BP79: =BP77-BS!BP21-BS!BP22-BS!BP23-BS!BP32-BS!BP35 -> 233191 | BQ79: =BQ77-BS!BQ21-BS!BQ22-BS!BQ23-BS!BQ32-BS!BQ35 -> 263706 | BR79: =BR77-BS!BR21-BS!BR22-BS!BR23-BS!BR32-BS!BR35 -> 189978 | BT79: =BT77-BS!BT21-BS!BT22-BS!BT23-BS!BT32-BS!BT35 -> 210948 | BU79: =BU77-BS!BU21-BS!BU22-BS!BU23-BS!BU32-BS!BU35 -> 233366 | BV79: =BV77-BS!BV21-BS!BV22-BS!BV23-BS!BV32-BS!BV35 -> 251986 | BW79: =BW77-BS!BW21-BS!BW22-BS!BW23-BS!BW32-BS!BW35 -> 257310 | BY79: =BY77-BS!BY21-BS!BY22-BS!BY23-BS!BY32-BS!BY35 -> 243056 | BZ79: =BZ77-BS!BZ21-BS!BZ22-BS!BZ23-BS!BZ32-BS!BZ35 -> 259238 | CA79: =CA77-BS!CA21-BS!CA22-BS!CA23-BS!CA32-BS!CA35 -> 237158 | CB79: =CB77-BS!CB21-BS!CB22-BS!CB23-BS!CB32-BS!CB35 -> 214305 | CD79: =CD77-BS!CD21-BS!CD22-BS!CD23-BS!CD32-BS!CD35 -> 233450 | CE79: =CE77-BS!CE21-BS!CE22-BS!CE23-BS!CE32-BS!CE35 -> 270178 | CF79: =CF77-BS!CF21-BS!CF22-BS!CF23-BS!CF32-BS!CF35 -> 239330 | CG79: =CG77-BS!CG21-BS!CG22-BS!CG23-BS!CG32-BS!CG35 -> 275440 | CI79: =CI77-BS!CI21-BS!CI22-BS!CI23-BS!CI32-BS!CI35 -> 290811 | CJ79: =CJ77-BS!CJ21-BS!CJ22-BS!CJ23-BS!CJ32-BS!CJ35 -> 271786 | CK79: =CK77-BS!CK21-BS!CK22-BS!CK23-BS!CK32-BS!CK35 -> 205773 | CL79: =CL77-BS!CL21-BS!CL22-BS!CL23-BS!CL32-BS!CL35 -> 241017 | CN79: =CN77-BS!CN21-BS!CN22-BS!CN23-BS!CN32-BS!CN35 -> 94921 | CO79: =CO77-BS!CO21-BS!CO22-BS!CO23-BS!CO32-BS!CO35 -> 107603 | CP79: =CP77-BS!CP21-BS!CP22-BS!CP23-BS!CP32-BS!CP35 -> 133725 | CQ79: =CQ77-BS!CQ21-BS!CQ22-BS!CQ23-BS!CQ32-BS!CQ35 -> 151355
B82: Scott Berg, sberg@needhamco.com | CV82: Source: Company Reports and Needham & Company Estimates
B83: 763-350-4027 | CV83: $ in thousands, except per share data
B84: Adjusted EBITDA | D84: -354 | E84: -739 | F84: 103 | G84: -259 | H84: 76 | I84: 504 | J84: 442 | K84: 763 | L84: 413 | M84: 1105 | N84: 861 | O84: 1177 | P84: 3556 | Q84: 1402 | R84: 1267 | S84: 1420 | T84: 1066 | U84: 5175 | V84: 1223 | W84: 1026 | X84: 1530 | Y84: 1631 | Z84: 5410 | AA84: 1858 | AB84: 2340 | AC84: 2189 | AD84: 2610 | AF84: 2922 | AG84: 3445 | AH84: 3628 | AI84: 3779 | AJ84: 13774 | AK84: 3902 | AL84: 4540 | AM84: 4686 | AN84: 4694 | AO84: 17891 | AP84: 4695 | AQ84: 5018 | AR84: 6197 | AS84: 6710 | AT84: 22620 | AU84: 5956 | AV84: 5695 | AW84: 7413 | AX84: 7438 | AY84: 26502 | AZ84: 8522 | BA84: 7668 | BB84: 7955 | BC84: 8470 | BD84: 32615 | BE84: 10887 | BF84: 12102 | BG84: 14364 | BH84: 13948 | BI84: 51301 | BJ84: 16450 | BK84: 16798 | BL84: 18083 | BM84: 18853 | BN84: 69762 | BO84: 20356 | BP84: 20422 | BQ84: 23238 | BR84: 22978 | BS84: 86994 | BT84: 25457 | BU84: 27328 | BV84: 26536 | BW84: 27694 | BX84: 107015 | BY84: 31766 | BZ84: 30864 | CA84: 34687 | CB84: 34951 | CC84: 132268 | CD84: 36999 | CE84: 38171 | CF84: 40503 | CG84: 41956 | CH84: 157629 | CI84: 44402 | CJ84: 44189 | CK84: 48401 | CL84: 49639 | CM84: 186631 | CN84: 50076.982 | CO84: 44189 | CP84: 59359.098 | CQ84: 49639 | CR84: 229442.37 | CS84: 50076.982 | CT84: 56048.569 | CU84: 59359.098 | CV84: 63957.721 | CW84: 229442.37
B85: Proforma Income Before Taxes | D85: -653 | E85: -1297 | F85: -2094 | G85: -876 | H85: -516 | I85: -94 | J85: -158 | K85: -1644 | L85: 5 | M85: 707 | N85: 474 | O85: 295 | P85: 1481 | Q85: 1035 | R85: 851 | S85: 1111 | T85: 729 | U85: 3726 | V85: 833 | W85: 579 | X85: 1005 | Y85: 1078 | Z85: 3495 | AA85: 1281 | AB85: 1701 | AC85: 1295 | AD85: 1588 | AF85: 1774 | AG85: 2285 | AH85: 2531 | AI85: 2508 | AJ85: 9098 | AK85: 2647 | AL85: 3140 | AM85: 3308 | AN85: 3269 | AO85: 12364 | AP85: 3191 | AQ85: 3487 | AR85: 4662 | AS85: 5421 | AT85: 16761 | AU85: 4475 | AV85: 4213 | AW85: 5901 | AX85: 5916 | AY85: 20505 | AZ85: 7022 | BA85: 6170 | BB85: 6397 | BC85: 6851 | BD85: 26440 | BE85: 9218 | BF85: 10556 | BG85: 12860 | BH85: 12403 | BI85: 45037 | BJ85: 14390 | BK85: 14524 | BL85: 16085 | BM85: 16588 | BN85: 61587 | BO85: 17858 | BP85: 17616 | BQ85: 20147 | BR85: 19454 | BS85: 75075 | BT85: 21789 | BU85: 23878 | BV85: 22907 | BW85: 23931 | BX85: 92505 | BY85: 27950 | BZ85: 27086 | CA85: 31104 | CB85: 31377 | CC85: 117517 | CD85: 33500 | CE85: 34985 | CF85: 38463 | CG85: 39577 | CH85: 146525 | CI85: 42587 | CJ85: 42300 | CK85: 46472 | CL85: 47133 | CM85: 178492 | CN85: 46132.667 | CO85: 42300 | CP85: 54842.07 | CQ85: 47133 | CR85: 211946.46 | CS85: 46132.667 | CT85: 51528.345 | CU85: 54842.07 | CV85: 59443.382 | CW85: 211946.46
B86: GAAP Pre-Tax Income | D86: -653 | E86: -1297 | F86: -2140 | G86: -912 | H86: -553 | I86: -131 | J86: -205 | K86: -1801 | L86: -43 | M86: 657 | N86: 395 | O86: 244 | P86: 1253 | Q86: 984 | R86: 676 | S86: 879 | T86: 437 | U86: 2976 | V86: 521 | W86: -31 | X86: 258 | Y86: 336 | Z86: 1084 | AA86: 409 | AB86: 726 | AC86: 50 | AD86: 158 | AF86: 133 | AG86: 457 | AH86: 439 | AI86: 708 | AJ86: 1737 | AK86: 591 | AL86: 1099 | AM86: 1370 | AN86: 1052 | AO86: 4112 | AP86: 847 | AQ86: 1007 | AR86: 2223 | AS86: 2998 | AT86: 7075 | AU86: 1752 | AV86: 657 | AW86: 3729 | AX86: 2712 | AY86: 8850 | AZ86: 3507 | BA86: 2867 | BB86: 2922 | BC86: -157 | BD86: 9139 | BE86: 4560 | BF86: 6344 | BG86: 8666 | BH86: 8864 | BI86: 28434 | BJ86: 7853 | BK86: 10783 | BL86: 11633 | BM86: 11801 | BN86: 41582 | BO86: 10863 | BP86: 12579 | BQ86: 14377 | BR86: 14861 | BS86: 52680 | BT86: 12337 | BU86: 13146 | BV86: 12805 | BW86: 15253 | BX86: 53541 | BY86: 16933 | BZ86: 14630 | CA86: 18995 | CB86: 20766 | CC86: 71324 | CD86: 18006 | CE86: 18915 | CF86: 22301 | CG86: 26341 | CH86: 85563 | CI86: 18535 | CJ86: 27221 | CK86: 29349 | CL86: 24371 | CM86: 99476 | CN86: 21932.667 | CO86: 27221 | CP86: 28642.07 | CQ86: 24371 | CR86: 109146.46 | CS86: 21932.667 | CT86: 26228.345 | CU86: 28642.07 | CV86: 32343.382 | CW86: 109146.46
C88: Recurring Revenue | L88: =L10 -> 6910.11 | M88: =M10 -> 7488 | N88: =N10 -> 7803.54 | O88: =O10 -> 7995.15 | P88: 8184.42 | Q88: =Q10 -> 8399.26 | R88: =R10 -> 9083.52 | S88: =S10 -> 9652.44 | T88: =T10 -> 10326.26 | U88: 9984.9924 | V88: =V10 -> 10498.67 | W88: =W10 -> 11707.08 | X88: =X10 -> 13199.65 | Y88: =Y10 -> 13868.25 | AA88: =AA10 -> 14384.58 | AB88: =AB10 -> 15326.06 | AC88: =AC10 -> 17834.96 | AD88: =AD10 -> 20307.68 | AF88: =AF10 -> 21139.28 | AG88: =AG10 -> 22579.04 | AH88: =AH10 -> 24037.12 | AI88: =AI10 -> 25152.55 | AK88: =AK10 -> 26001.314 | AL88: =AL10 -> 28087.813 | AM88: =AM10 -> 29325.286 | AN88: =AN10 -> 31737.887 | AP88: =AP10 -> 33273 | AQ88: =AQ10 -> 35349.86 | AR88: =AR10 -> 36722.14 | AS88: =AS10 -> 38589.344 | AU88: =AU10 -> 41495.09 | AV88: =AV10 -> 43562.92 | AW88: =AW10 -> 45341.28 | AX88: =AX10 -> 46657.71 | AZ88: =AZ10 -> 47777.44 | BA88: =BA10 -> 49941.28 | BB88: =BB10 -> 51658 | BC88: =BC10 -> 54543.28 | BE88: =BE10 -> 54860 | BF88: =BF10 -> 56430 | BG88: =BG10 -> 58644 | BH88: =BH10 -> 60720 | BJ88: =BJ10 -> 62917.96 | BK88: =BK10 -> 64417.26 | BL88: =BL10 -> 66672.32 | BM88: =BM10 -> 68369.02 | BO88: =BO10 -> 69740.48 | BP88: =BP10 -> 71038.62 | BQ88: =BQ10 -> 75579.15 | BR88: =BR10 -> 78309.52 | BT88: =BT10 -> 82886.48 | BU88: =BU10 -> 86975.88 | BV88: =BV10 -> 90056.04 | BW88: =BW10 -> 94535.52
C89: LTM Rev | K89: =K10 -> 25478.51 | O89: =O88+N88+M88+L88 -> 30196.8 | P89: 30386.07 | Q89: =Q88+O88+N88+M88 -> 31685.95 | R89: =R88+Q88+O88+N88 -> 33281.47 | S89: =S88+R88+Q88+O88 -> 35130.37 | T89: =T88+S88+R88+Q88 -> 37461.48 | U89: 37066.127 | V89: =V88+T88+S88+R88 -> 39560.89 | W89: =W88+V88+T88+S88 -> 42184.45 | X89: =X88+W88+V88+T88 -> 45731.66 | Y89: =Y88+X88+W88+V88 -> 49273.65 | AA89: =AA88+Y88+X88+W88 -> 53159.56 | AB89: =AB88+AA88+Y88+X88 -> 56778.54 | AC89: =AC88+AB88+AA88+Y88 -> 61413.85 | AD89: =AD88+AC88+AB88+AA88 -> 67853.28 | AF89: =AF88+AD88+AC88+AB88 -> 74607.98 | AG89: =AG88+AF88+AD88+AC88 -> 81860.96 | AH89: =AH88+AG88+AF88+AD88 -> 88063.12 | AI89: =AI88+AH88+AG88+AF88 -> 92907.99 | AK89: =AK88+AI88+AH88+AG88 -> 97770.024 | AL89: =AL88+AK88+AI88+AH88 -> 103278.8 | AM89: =AM88+AL88+AK88+AI88 -> 108566.96 | AN89: =AN88+AM88+AL88+AK88 -> 115152.3 | AP89: =AP88+AN88+AM88+AL88 -> 122423.99 | AQ89: =AQ88+AP88+AN88+AM88 -> 129686.03 | AR89: =AR88+AQ88+AP88+AN88 -> 137082.89 | AS89: =AS88+AR88+AQ88+AP88 -> 143934.34 | AU89: =AU88+AS88+AR88+AQ88 -> 152156.43 | AV89: =AV88+AU88+AS88+AR88 -> 160369.49 | AW89: =AW88+AV88+AU88+AS88 -> 168988.63 | AX89: =AX88+AW88+AV88+AU88 -> 177057 | AZ89: =AZ88+AX88+AW88+AV88 -> 183339.35 | BA89: =BA88+AZ88+AX88+AW88 -> 189717.71 | BB89: =BB88+BA88+AZ88+AX88 -> 196034.43 | BC89: =BC88+BB88+BA88+AZ88 -> 203920 | BE89: =BE88+BC88+BB88+BA88 -> 211002.56 | BF89: =BF88+BE88+BC88+BB88 -> 217491.28 | BG89: =BG88+BF88+BE88+BC88 -> 224477.28 | BH89: =BH88+BG88+BF88+BE88 -> 230654 | BJ89: =BJ88+BH88+BG88+BF88 -> 238711.96 | BK89: =BK88+BJ88+BH88+BG88 -> 246699.22 | BL89: =BL88+BK88+BJ88+BH88 -> 254727.54 | BM89: =BM88+BL88+BK88+BJ88 -> 262376.56 | BO89: =BO88+BM88+BL88+BK88 -> 269199.08 | BP89: =BP88+BO88+BM88+BL88 -> 275820.44 | BQ89: =BQ88+BP88+BO88+BM88 -> 284727.27 | BR89: =BR88+BQ88+BP88+BO88 -> 294667.77 | BT89: =BT88+BR88+BQ88+BP88 -> 307813.77 | BU89: =BU88+BT88+BR88+BQ88 -> 323751.03 | BV89: =BV88+BU88+BT88+BR88 -> 338227.92 | BW89: =BW88+BV88+BU88+BT88 -> 354453.92
C90: Change in LTM Recurring Rev | O90: =O89-K10 -> 4718.29 | P90: 4600.59 | T90: =T89-P10 -> 7264.68 | U90: 6869.3266 | V90: =V89-Q89 -> 7874.94 | W90: =W89-R89 -> 8902.98 | X90: =X89-S89 -> 10601.29 | Y90: =Y89-T89 -> 11812.17 | AA90: =AA89-V89 -> 13598.67 | AB90: =AB89-W89 -> 14594.09 | AC90: =AC89-X89 -> 15682.19 | AD90: =AD89-Y89 -> 18579.63 | AF90: =AF89-AA89 -> 21448.42 | AG90: =AG89-AB89 -> 25082.42 | AH90: =AH89-AC89 -> 26649.27 | AI90: =AI89-AD89 -> 25054.71 | AK90: =AK89-AF89 -> 23162.044 | AL90: =AL89-AG89 -> 21417.837 | AM90: =AM89-AH89 -> 20503.843 | AN90: =AN89-AI89 -> 22244.31 | AP90: =AP89-AK89 -> 24653.961 | AQ90: =AQ89-AL89 -> 26407.236 | AR90: =AR89-AM89 -> 28515.923 | AS90: =AS89-AN89 -> 28782.044 | AU90: =AU89-AP89 -> 29732.448 | AV90: =AV89-AQ89 -> 30683.461 | AW90: =AW89-AR89 -> 31905.747 | AX90: =AX89-AS89 -> 33122.656 | AZ90: =AZ89-AU89 -> 31182.916 | BA90: =BA89-AV89 -> 29348.216 | BB90: =BB89-AW89 -> 27045.796 | BC90: =BC89-AX89 -> 26863 | BE90: =BE89-AZ89 -> 27663.21 | BF90: =BF89-BA89 -> 27773.57 | BG90: =BG89-BB89 -> 28442.85 | BH90: =BH89-BC89 -> 26734 | BJ90: =BJ89-BE89 -> 27709.4 | BK90: =BK89-BF89 -> 29207.94 | BL90: =BL89-BG89 -> 30250.26 | BM90: =BM89-BH89 -> 31722.56 | BO90: =BO89-BJ89 -> 30487.12 | BP90: =BP89-BK89 -> 29121.22 | BQ90: =BQ89-BL89 -> 29999.73 | BR90: =BR89-BM89 -> 32291.21 | BT90: =BT89-BO89 -> 38614.69 | BU90: =BU89-BP89 -> 47930.59 | BV90: =BV89-BQ89 -> 53500.65 | BW90: =BW89-BR89 -> 59786.15
C91: Retention Rate | K91: 0.95 | O91: 0.95 | P91: 0.95 | T91: 0.95 | U91: 0.95 | V91: 0.95 | W91: 0.95 | X91: 0.95 | Y91: 0.95 | AA91: 0.95 | AB91: 0.95 | AC91: 0.95 | AD91: 0.95 | AF91: 0.95 | AG91: 0.95 | AH91: 0.95 | AI91: 0.95 | AK91: 0.95 | AL91: 0.95 | AM91: 0.95 | AN91: 0.95 | AP91: 0.95 | AQ91: 0.95 | AR91: 0.95 | AS91: 0.95 | AU91: 0.95 | AV91: 0.95 | AW91: 0.95 | AX91: 0.95 | AZ91: 0.95 | BA91: 0.95 | BB91: 0.95 | BC91: 0.95 | BE91: 0.95 | BF91: 0.95 | BG91: 0.95 | BH91: 0.95 | BJ91: 0.95 | BK91: 0.95 | BL91: 0.95 | BM91: 0.95 | BO91: 0.95 | BP91: 0.95 | BQ91: 0.95 | BR91: 0.95 | BT91: 0.95 | BU91: 0.95 | BV91: 0.95 | BW91: 0.95
C92: Revenue Retention Rate | K92: =K91*K89 -> 24204.584 | O92: =O91*O89 -> 28686.96 | P92: 28866.766 | T92: =T89*T91 -> 35588.406 | U92: 35212.82 | V92: =V91*V89 -> 37582.845 | W92: =W91*W89 -> 40075.227 | X92: =X91*X89 -> 43445.077 | Y92: =Y91*Y89 -> 46809.967 | AA92: =AA91*AA89 -> 50501.582 | AB92: =AB91*AB89 -> 53939.613 | AC92: =AC91*AC89 -> 58343.157 | AD92: =AD91*AD89 -> 64460.616 | AF92: =AF91*AF89 -> 70877.581 | AG92: =AG91*AG89 -> 77767.912 | AH92: =AH91*AH89 -> 83659.964 | AI92: =AI91*AI89 -> 88262.59 | AK92: =AK91*AK89 -> 92881.523 | AL92: =AL91*AL89 -> 98114.857 | AM92: =AM91*AM89 -> 103138.62 | AN92: =AN91*AN89 -> 109394.69 | AP92: =AP91*AP89 -> 116302.79 | AQ92: =AQ91*AQ89 -> 123201.73 | AR92: =AR91*AR89 -> 130228.74 | AS92: =AS91*AS89 -> 136737.63 | AU92: =AU91*AU89 -> 144548.61 | AV92: =AV91*AV89 -> 152351.02 | AW92: =AW91*AW89 -> 160539.2 | AX92: =AX91*AX89 -> 168204.15 | AZ92: =AZ91*AZ89 -> 174172.38 | BA92: =BA91*BA89 -> 180231.82 | BB92: =BB91*BB89 -> 186232.71 | BC92: =BC91*BC89 -> 193724 | BE92: =BE91*BE89 -> 200452.43 | BF92: =BF91*BF89 -> 206616.72 | BG92: =BG91*BG89 -> 213253.42 | BH92: =BH91*BH89 -> 219121.3 | BJ92: =BJ91*BJ89 -> 226776.36 | BK92: =BK91*BK89 -> 234364.26 | BL92: =BL91*BL89 -> 241991.16 | BM92: =BM91*BM89 -> 249257.73 | BO92: =BO91*BO89 -> 255739.13 | BP92: =BP91*BP89 -> 262029.42 | BQ92: =BQ91*BQ89 -> 270490.91 | BR92: =BR91*BR89 -> 279934.38 | BT92: =BT91*BT89 -> 292423.08 | BU92: =BU91*BU89 -> 307563.48 | BV92: =BV91*BV89 -> 321316.52 | BW92: =BW91*BW89 -> 336731.22
C93: NTM Gross Revenue Churn | K93: =K89-K92 -> 1273.9255 | O93: =O89-O92 -> 1509.84 | P93: 1519.3035 | T93: =T89-T92 -> 1873.074 | U93: 1853.3063 | V93: =V89-V92 -> 1978.0445 | W93: =W89-W92 -> 2109.2225 | X93: =X89-X92 -> 2286.583 | Y93: =Y89-Y92 -> 2463.6825 | AA93: =AA89-AA92 -> 2657.978 | AB93: =AB89-AB92 -> 2838.927 | AC93: =AC89-AC92 -> 3070.6925 | AD93: =AD89-AD92 -> 3392.664 | AF93: =AF89-AF92 -> 3730.399 | AG93: =AG89-AG92 -> 4093.048 | AH93: =AH89-AH92 -> 4403.156 | AI93: =AI89-AI92 -> 4645.3995 | AK93: =AK89-AK92 -> 4888.5012 | AL93: =AL89-AL92 -> 5163.9399 | AM93: =AM89-AM92 -> 5428.3482 | AN93: =AN89-AN92 -> 5757.615 | AP93: =AP89-AP92 -> 6121.1993 | AQ93: =AQ89-AQ92 -> 6484.3017 | AR93: =AR89-AR92 -> 6854.1443 | AS93: =AS89-AS92 -> 7196.7172 | AU93: =AU89-AU92 -> 7607.8217 | AV93: =AV89-AV92 -> 8018.4747 | AW93: =AW89-AW92 -> 8449.4317 | AX93: =AX89-AX92 -> 8852.85 | AZ93: =AZ89-AZ92 -> 9166.9675 | BA93: =BA89-BA92 -> 9485.8855 | BB93: =BB89-BB92 -> 9801.7215 | BC93: =BC89-BC92 -> 10196 | BE93: =BE89-BE92 -> 10550.128 | BF93: =BF89-BF92 -> 10874.564 | BG93: =BG89-BG92 -> 11223.864 | BH93: =BH89-BH92 -> 11532.7 | BJ93: =BJ89-BJ92 -> 11935.598 | BK93: =BK89-BK92 -> 12334.961 | BL93: =BL89-BL92 -> 12736.377 | BM93: =BM89-BM92 -> 13118.828 | BO93: =BO89-BO92 -> 13459.954 | BP93: =BP89-BP92 -> 13791.022 | BQ93: =BQ89-BQ92 -> 14236.364 | BR93: =BR89-BR92 -> 14733.389 | BT93: =BT89-BT92 -> 15390.688 | BU93: =BU89-BU92 -> 16187.552 | BV93: =BV89-BV92 -> 16911.396 | BW93: =BW89-BW92 -> 17722.696
C94: Gross New Revenue | O94: =O90+K93 -> 5992.2155 | P94: 5889.864 | T94: =T90+O93 -> 8774.52 | U94: 8388.6301 | Y94: =Y90+T93 -> 13685.244 | AA94: =AA90+V93 -> 15576.715 | AB94: =AB90+W93 -> 16703.313 | AC94: =AC90+X93 -> 17968.773 | AD94: =AD90+Y93 -> 21043.312 | AF94: =AF90+AA93 -> 24106.398 | AG94: =AG90+AB93 -> 27921.347 | AH94: =AH90+AC93 -> 29719.963 | AI94: =AI90+AD93 -> 28447.374 | AK94: =AK90+AF93 -> 26892.443 | AL94: =AL90+AG93 -> 25510.885 | AM94: =AM90+AH93 -> 24906.999 | AN94: =AN90+AI93 -> 26889.71 | AP94: =AP90+AK93 -> 29542.462 | AQ94: =AQ90+AL93 -> 31571.176 | AR94: =AR90+AM93 -> 33944.271 | AS94: =AS90+AN93 -> 34539.659 | AU94: =AU90+AP93 -> 35853.648 | AV94: =AV90+AQ93 -> 37167.763 | AW94: =AW90+AR93 -> 38759.892 | AX94: =AX90+AS93 -> 40319.373 | AZ94: =AZ90+AU93 -> 38790.738 | BA94: =BA90+AV93 -> 37366.691 | BB94: =BB90+AW93 -> 35495.228 | BC94: =BC90+AX93 -> 35715.85 | BE94: =BE90+AZ93 -> 36830.178 | BF94: =BF90+BA93 -> 37259.456 | BG94: =BG90+BB93 -> 38244.572 | BH94: =BH90+BC93 -> 36930 | BJ94: =BJ90+BE93 -> 38259.528 | BK94: =BK90+BF93 -> 40082.504 | BL94: =BL90+BG93 -> 41474.124 | BM94: =BM90+BH93 -> 43255.26 | BO94: =BO90+BJ93 -> 42422.718 | BP94: =BP90+BK93 -> 41456.181 | BQ94: =BQ90+BL93 -> 42736.107 | BR94: =BR90+BM93 -> 45410.038 | BT94: =BT90+BO93 -> 52074.644 | BU94: =BU90+BP93 -> 61721.612 | BV94: =BV90+BQ93 -> 67737.014 | BW94: =BW90+BR93 -> 74519.539
C95: Net New Revenue | AA95: =AA94-V93 -> 13598.67 | AB95: =AB94-W93 -> 14594.09 | AC95: =AC94-X93 -> 15682.19 | AD95: =AD94-Y93 -> 18579.63 | AF95: =AF94-AA93 -> 21448.42 | AG95: =AG94-AB93 -> 25082.42 | AH95: =AH94-AC93 -> 26649.27 | AI95: =AI94-AD93 -> 25054.71 | AK95: =AK94-AF93 -> 23162.044 | AL95: =AL94-AG93 -> 21417.837 | AM95: =AM94-AH93 -> 20503.843 | AN95: =AN94-AI93 -> 22244.31 | AP95: =AP94-AK93 -> 24653.961 | AQ95: =AQ94-AL93 -> 26407.236 | AR95: =AR94-AM93 -> 28515.923 | AS95: =AS94-AN93 -> 28782.044 | AU95: =AU94-AP93 -> 29732.448 | AV95: =AV94-AQ93 -> 30683.461 | AW95: =AW94-AR93 -> 31905.747 | AX95: =AX94-AS93 -> 33122.656 | AZ95: =AZ94-AU93 -> 31182.916 | BA95: =BA94-AV93 -> 29348.216 | BB95: =BB94-AW93 -> 27045.796 | BC95: =BC94-AX93 -> 26863 | BE95: =BE94-AZ93 -> 27663.21 | BF95: =BF94-BA93 -> 27773.57 | BG95: =BG94-BB93 -> 28442.85 | BH95: =BH94-BC93 -> 26734 | BJ95: =BJ94-BE93 -> 27709.4 | BK95: =BK94-BF93 -> 29207.94 | BL95: =BL94-BG93 -> 30250.26 | BM95: =BM94-BH93 -> 31722.56 | BO95: =BO94-BJ93 -> 30487.12 | BP95: =BP94-BK93 -> 29121.22 | BQ95: =BQ94-BL93 -> 29999.73 | BR95: =BR94-BM93 -> 32291.21 | BT95: =BT94-BO93 -> 38614.69 | BU95: =BU94-BP93 -> 47930.59 | BV95: =BV94-BQ93 -> 53500.65 | BW95: =BW94-BR93 -> 59786.15
C97: LTM S&M | O97: =O25+N25+M25+L25 -> 13415 | P97: 13415 | T97: =T25+S25+R25+Q25 -> 16390 | U97: 16390 | Y97: =Y25+X25+W25+V25 -> 23365 | AA97: =AA25+Y25+X25+W25 -> 24677 | AB97: =AB25+AA25+Y25+X25 -> 25717 | AC97: =AC25+AB25+AA25+Y25 -> 27042 | AD97: =AD25+AC25+AB25+AA25 -> 29222 | AF97: =AF25+AD25+AC25+AB25 -> 31756 | AG97: =AG25+AF25+AD25+AC25 -> 34262 | AH97: =AH25+AG25+AF25+AD25 -> 36567 | AI97: =AI25+AH25+AG25+AF25 -> 38140 | AK97: =AK25+AI25+AH25+AG25 -> 39659 | AL97: =AL25+AK25+AI25+AH25 -> 41496 | AM97: =AM25+AL25+AK25+AI25 -> 43160 | AN97: =AN25+AM25+AL25+AK25 -> 45057 | AP97: =AP25+AN25+AM25+AL25 -> 47857 | AQ97: =AQ25+AP25+AN25+AM25 -> 50378 | AR97: =AR25+AQ25+AP25+AN25 -> 52130 | AS97: =AS25+AR25+AQ25+AP25 -> 53396 | AU97: =AU25+AS25+AR25+AQ25 -> 55429 | AV97: =AV25+AU25+AS25+AR25 -> 57848 | AW97: =AW25+AV25+AU25+AS25 -> 60425 | AX97: =AX25+AW25+AV25+AU25 -> 63474 | AZ97: =AZ25+AX25+AW25+AV25 -> 64801 | BA97: =BA25+AZ25+AX25+AW25 -> 66930 | BB97: =BB25+BA25+AZ25+AX25 -> 68698 | BC97: =BC25+BB25+BA25+AZ25 -> 71098 | BE97: =BE25+BC25+BB25+BA25 -> 72530 | BF97: =BF25+BE25+BC25+BB25 -> 72077 | BG97: =BG25+BF25+BE25+BC25 -> 70664 | BH97: =BH25+BG25+BF25+BE25 -> 69044 | BJ97: =BJ25+BH25+BG25+BF25 -> 68242 | BK97: =BK25+BJ25+BH25+BG25 -> 67379 | BL97: =BL25+BK25+BJ25+BH25 -> 67271 | BM97: =BM25+BL25+BK25+BJ25 -> 67194 | BO97: =BO25+BM25+BL25+BK25 -> 67455 | BP97: =BP25+BO25+BM25+BL25 -> 68205 | BQ97: =BQ25+BP25+BO25+BM25 -> 70162 | BR97: =BR25+BQ25+BP25+BO25 -> 71836 | BT97: =BT25+BR25+BQ25+BP25 -> 74256 | BU97: =BU25+BT25+BR25+BQ25 -> 76869 | BV97: =BV25+BU25+BT25+BR25 -> 79204 | BW97: =BW25+BV25+BU25+BT25 -> 81796
C99: Revenue Ratio | O99: =O94/O97 -> 0.44668025 | P99: 0.43905061 | T99: =T94/T97 -> 0.53535815 | U99: 0.51181392 | Y99: =Y97/Y94 -> 1.7073134 | AA99: =AA97/AA94 -> 1.5842237 | AB99: =AB97/AB94 -> 1.5396347 | AC99: =AC97/AC94 -> 1.5049442 | AD99: =AD97/AD94 -> 1.3886597 | AF99: =AF97/AF94 -> 1.3173266 | AG99: =AG97/AG94 -> 1.2270898 | AH99: =AH97/AH94 -> 1.2303851 | AI99: =AI97/AI94 -> 1.3407213 | AK99: =AK97/AK94 -> 1.4747265 | AL99: =AL97/AL94 -> 1.6265998 | AM99: =AM97/AM94 -> 1.7328462 | AN99: =AN97/AN94 -> 1.6756224 | AP99: =AP97/AP94 -> 1.6199394 | AQ99: =AQ97/AQ94 -> 1.595696 | AR99: =AR97/AR94 -> 1.5357525 | AS99: =AS97/AS94 -> 1.545933 | AU99: =AU97/AU94 -> 1.5459794 | AV99: =AV97/AV94 -> 1.5564025 | AW99: =AW97/AW94 -> 1.5589569 | AX99: =AX97/AX94 -> 1.5742804 | AZ99: =AZ97/AZ94 -> 1.6705277 | BA99: =BA97/BA94 -> 1.7911674 | BB99: =BB97/BB94 -> 1.9354151 | BC99: =BC97/BC94 -> 1.9906568 | BE99: =BE97/BE94 -> 1.969309 | BF99: =BF97/BF94 -> 1.934462 | BG99: =BG97/BG94 -> 1.8476871 | BH99: =BH97/BH94 -> 1.8695911 | BJ99: =BJ97/BJ94 -> 1.7836603 | BK99: =BK97/BK94 -> 1.6810078 | BL99: =BL97/BL94 -> 1.6219993 | BM99: =BM97/BM94 -> 1.5534296 | BO99: =BO97/BO94 -> 1.5900678 | BP99: =BP97/BP94 -> 1.6452311 | BQ99: =BQ97/BQ94 -> 1.6417499 | BR99: =BR97/BR94 -> 1.581941 | BT99: =BT97/BT94 -> 1.4259531 | BU99: =BU97/BU94 -> 1.2454147 | BV99: =BV97/BV94 -> 1.1692869 | BW99: =BW97/BW94 -> 1.097645
C101: CAC Ratio | AU101: =AU97/AU90 -> 1.8642595 | AV101: =AV97/AV90 -> 1.8853153 | AW101: =AW97/AW90 -> 1.8938594 | AX101: =AX97/AX90 -> 1.9163318 | AZ101: =AZ97/AZ90 -> 2.078093 | BA101: =BA97/BA90 -> 2.2805475 | BB101: =BB97/BB90 -> 2.540062 | BC101: =BC97/BC90 -> 2.6466888 | BE101: =BE97/BE90 -> 2.6218938 | BF101: =BF97/BF90 -> 2.5951651 | BG101: =BG97/BG90 -> 2.4844205 | BH101: =BH97/BH90 -> 2.5826289 | BJ101: =BJ97/BJ90 -> 2.4627744 | BK101: =BK97/BK90 -> 2.3068727 | BL101: =BL97/BL90 -> 2.2238156 | BM101: =BM97/BM90 -> 2.1181771 | BO101: =BO97/BO90 -> 2.2125737 | BP101: =BP97/BP90 -> 2.3421065 | BQ101: =BQ97/BQ90 -> 2.3387544 | BR101: =BR97/BR90 -> 2.2246302 | BT101: =BT97/BT90 -> 1.9229987 | BU101: =BU97/BU90 -> 1.6037566 | BV101: =BV97/BV90 -> 1.4804306 | BW101: =BW97/BW90 -> 1.368143
AK102: 2014 Billings | AP102: 2015 Billings | AU102: 2016 Billings | AZ102: 2017 Billings | BE102: 2018 Billings | BJ102: 2019 Billings | BO102: 2020 Billings | BT102: 2020 Billings
AK103: =AK3 -> 1Q14 | AL103: =AL3 -> 2Q14 | AM103: =AM3 -> 3Q14 | AN103: =AN3 -> 4Q14 | AO103: =AO3 -> 2014 | AP103: =AP3 -> 1Q15 | AQ103: =AQ3 -> 2Q15 | AR103: =AR3 -> 3Q15 | ... BX103: =BX3 -> 2021
C104: Revenue | AK104: =AK4 -> 28939 | AL104: =AL4 -> 31100 | AM104: =AM4 -> 32506 | AN104: =AN4 -> 35402 | AO104: =AO4 -> 127947 | AP104: =AP4 -> 36970 | AQ104: =AQ4 -> 38846 | AR104: =AR4 -> 40354 | ... BX104: =BX4 -> 385276
C105: Change In Deferred Revenue | AK105: =BS!AK48-BS!AI48 -> 574 | AL105: =BS!AL48-BS!AK48 -> 1235 | AM105: =BS!AM48-BS!AL48 -> 269 | AN105: =BS!AN48-BS!AM48 -> 960 | AP105: =BS!AP48-BS!AN48 -> -78 | AQ105: =BS!AQ48-BS!AP48 -> 749 | AR105: =BS!AR48-BS!AQ48 -> 944 | AS105: =BS!AS48-BS!AR48 -> -1028 | AU105: =BS!AU48-BS!AS48 -> 3465 | AV105: =BS!AV48-BS!AU48 -> 1307 | AW105: =BS!AW48-BS!AV48 -> -398 | AX105: =BS!AX48-BS!AW48 -> -1217 | AZ105: =BS!AZ48-BS!AX48 -> 4988 | BA105: =BS!BA48-BS!AZ48 -> 784 | BB105: =BS!BB48-BS!BA48 -> -840 | BC105: =BS!BC48-BS!BB48 -> 175 | BE105: =BS!BE48-BS!BC48 -> -2735 | BF105: =BS!BF48-BS!BE48 -> 2557 | BG105: =BS!BG48-BS!BF48 -> 802 | BH105: =BS!BH48-BS!BG48 -> 207 | BJ105: =BS!BJ48-BS!BH48 -> 3698 | BK105: =BS!BK48-BS!BJ48 -> 1552 | BL105: =BS!BL48-BS!BK48 -> -138 | BM105: =BS!BM48-BS!BL48 -> 1362 | BO105: =BS!BO48-BS!BM48 -> 3396 | BP105: =BS!BP48-BS!BO48 -> 1309 | BQ105: =BS!BQ48-BS!BP48 -> -744 | BR105: =BS!BR48-BS!BQ48 -> 2668 | BT105: =BS!BT48-BS!BR48 -> 7565 | BU105: =BS!BU48-BS!BT48 -> 4964 | BV105: =BS!BV48-BS!BU48 -> 872 | BW105: =BS!BW48-BS!BV48 -> 1228
C106: Billings | AK106: =AK105+AK104 -> 29513 | AL106: =AL105+AL104 -> 32335 | AM106: =AM105+AM104 -> 32775 | AN106: =AN105+AN104 -> 36362 | AO106: =SUM(AK106:AN106) -> 130985 | AP106: =AP105+AP104 -> 36892 | AQ106: =AQ105+AQ104 -> 39595 | AR106: =AR105+AR104 -> 41298 | AS106: =AS105+AS104 -> 41320 | AT106: =SUM(AP106:AS106) -> 159105 | AU106: =AU104+AU105 -> 49064 | AV106: =AV104+AV105 -> 48658 | AW106: =AW104+AW105 -> 48886 | AX106: =AX104+AX105 -> 49844 | AY106: =SUM(AU106:AX106) -> 196452 | AZ106: =AZ105+AZ104 -> 56920 | BA106: =BA105+BA104 -> 55068 | BB106: =BB105+BB104 -> 55310 | BC106: =BC105+BC104 -> 58375 | BD106: =SUM(AZ106:BC106) -> 225673 | BE106: =BE105+BE104 -> 56357 | BF106: =BF105+BF104 -> 63648 | BG106: =BG105+BG104 -> 63670 | BH106: =BH105+BH104 -> 65396 | BI106: =SUM(BE106:BH106) -> 249071 | BJ106: =BJ105+BJ104 -> 70632 | BK106: =BK105+BK104 -> 70081 | BL106: =BL105+BL104 -> 70790 | BM106: =BM105+BM104 -> 74095 | BN106: =SUM(BJ106:BM106) -> 285598 | BO106: =BO105+BO104 -> 77588 | BP106: =BP105+BP104 -> 76882 | BQ106: =BQ105+BQ104 -> 78813 | BR106: =BR105+BR104 -> 85976 | BS106: =SUM(BO106:BR106) -> 319259 | BT106: =BT105+BT104 -> 97659 | BU106: =BU105+BU104 -> 99503 | BV106: =BV105+BV104 -> 98759 | BW106: =BW105+BW104 -> 103984 | BX106: =SUM(BT106:BW106) -> 399905
C107: % change y/y | AK107: =AK106/AF106-1 -> #DIV/0! | AL107: =AL106/AG106-1 -> #DIV/0! | AM107: =AM106/AH106-1 -> #DIV/0! | AN107: =AN106/AI106-1 -> #DIV/0! | AO107: =AO106/AJ106-1 -> #DIV/0! | AP107: =AP106/AK106-1 -> 0.25002541 | AQ107: =AQ106/AL106-1 -> 0.22452451 | AR107: =AR106/AM106-1 -> 0.26004577 | ... BX107: =BX106/BS106-1 -> 0.25260369
C108: % change q/q | AK108: =AK106/AI106-1 -> #DIV/0! | AL108: =AL106/AK106-1 -> 0.09561888 | AM108: =AM106/AL106-1 -> 0.013607546 | AN108: =AN106/AM106-1 -> 0.10944317 | AP108: =AP106/AN106-1 -> 0.014575656 | AQ108: =AQ106/AP106-1 -> 0.073267917 | AR108: =AR106/AQ106-1 -> 0.043010481 | AS108: =AS106/AR106-1 -> 0.00053271345 | AU108: =AU106/AS106-1 -> 0.1874153 | AV108: =AV106/AU106-1 -> -0.0082749062 | AW108: =AW106/AV106-1 -> 0.004685766 | AX108: =AX106/AW106-1 -> 0.019596613 | AZ108: =AZ106/AX106-1 -> 0.14196292 | BA108: =BA106/AZ106-1 -> -0.032536894 | BB108: =BB106/BA106-1 -> 0.0043945667 | BC108: =BC106/BB106-1 -> 0.055414934 | BE108: =BE106/BC106-1 -> -0.034569593 | BF108: =BF106/BE106-1 -> 0.12937168 | BG108: =BG106/BF106-1 -> 0.00034565108 | BH108: =BH106/BG106-1 -> 0.027108528 | BJ108: =BJ106/BH106-1 -> 0.080066059 | BK108: =BK106/BJ106-1 -> -0.0078009967 | BL108: =BL106/BK106-1 -> 0.010116865 | BM108: =BM106/BL106-1 -> 0.046687385 | BO108: =BO106/BM106-1 -> 0.047142182 | BP108: =BP106/BO106-1 -> -0.0090993453 | BQ108: =BQ106/BP106-1 -> 0.025116412 | BR108: =BR106/BQ106-1 -> 0.090886021 | BT108: =BT106/BR106-1 -> 0.13588676 | BU108: =BU106/BT106-1 -> 0.018882028 | BV108: =BV106/BU106-1 -> -0.0074771615 | BW108: =BW106/BV106-1 -> 0.052906571
C109: Total Billings TTM | AK109: =AK106+AI106+AH106+AG106 -> 29513 | AL109: =AL106+AK106+AI106+AH106 -> 61848 | AM109: =AM106+AL106+AK106+AI106 -> 94623 | AN109: =AN106+AM106+AL106+AK106 -> 130985 | AP109: =AP106+AN106+AM106+AL106 -> 138364 | AQ109: =AQ106+AP106+AN106+AM106 -> 145624 | AR109: =AR106+AQ106+AP106+AN106 -> 154147 | AS109: =AS106+AR106+AQ106+AP106 -> 159105 | AU109: =AU106+AS106+AR106+AQ106 -> 171277 | AV109: =AV106+AU106+AS106+AR106 -> 180340 | AW109: =AW106+AV106+AU106+AS106 -> 187928 | AX109: =AX106+AW106+AV106+AU106 -> 196452 | AZ109: =AZ106+AX106+AW106+AV106 -> 204308 | BA109: =BA106+AZ106+AX106+AW106 -> 210718 | BB109: =BB106+BA106+AZ106+AX106 -> 217142 | BC109: =BC106+BB106+BA106+AZ106 -> 225673 | BE109: =BE106+BC106+BB106+BA106 -> 225110 | BF109: =BF106+BE106+BC106+BB106 -> 233690 | BG109: =BG106+BF106+BE106+BC106 -> 242050 | BH109: =BH106+BG106+BF106+BE106 -> 249071 | BJ109: =BJ106+BH106+BG106+BF106 -> 263346 | BK109: =BK106+BJ106+BH106+BG106 -> 269779 | BL109: =BL106+BK106+BJ106+BH106 -> 276899 | BM109: =BM106+BL106+BK106+BJ106 -> 285598 | BO109: =BO106+BM106+BL106+BK106 -> 292554 | BP109: =BP106+BO106+BM106+BL106 -> 299355 | BQ109: =BQ106+BP106+BO106+BM106 -> 307378 | BR109: =BR106+BQ106+BP106+BO106 -> 319259 | BT109: =BT106+BR106+BQ106+BP106 -> 339330 | BU109: =BU106+BT106+BR106+BQ106 -> 361951 | BV109: =BV106+BU106+BT106+BR106 -> 381897 | BW109: =BW106+BV106+BU106+BT106 -> 399905
C110: % change y/y | AK110: =AK109/AF109-1 -> #DIV/0! | AL110: =AL109/AG109-1 -> #DIV/0! | AM110: =AM109/AH109-1 -> #DIV/0! | AN110: =AN109/AI109-1 -> #DIV/0! | AP110: =AP109/AK109-1 -> 3.6882391 | AQ110: =AQ109/AL109-1 -> 1.3545466 | AR110: =AR109/AM109-1 -> 0.62906482 | AS110: =AS109/AN109-1 -> 0.21468107 | AU110: =AU109/AP109-1 -> 0.23787257 | AV110: =AV109/AQ109-1 -> 0.23839477 | AW110: =AW109/AR109-1 -> 0.21914796 | AX110: =AX109/AS109-1 -> 0.23473178 | AZ110: =AZ109/AU109-1 -> 0.19285135 | BA110: =BA109/AV109-1 -> 0.16844849 | BB110: =BB109/AW109-1 -> 0.15545315 | BC110: =BC109/AX109-1 -> 0.14874371 | BE110: =BE109/AZ109-1 -> 0.10181686 | BF110: =BF109/BA109-1 -> 0.10901774 | BG110: =BG109/BB109-1 -> 0.11470835 | BH110: =BH109/BC109-1 -> 0.10368099 | BJ110: =BJ109/BE109-1 -> 0.16985474 | BK110: =BK109/BF109-1 -> 0.15443108 | BL110: =BL109/BG109-1 -> 0.14397439 | BM110: =BM109/BH109-1 -> 0.14665296 | BO110: =BO109/BJ109-1 -> 0.11091112 | BP110: =BP109/BK109-1 -> 0.10963048 | BQ110: =BQ109/BL109-1 -> 0.11007263 | BR110: =BR109/BM109-1 -> 0.11786147 | BT110: =BT109/BO109-1 -> 0.15988843 | BU110: =BU109/BP109-1 -> 0.2091029 | BV110: =BV109/BQ109-1 -> 0.2424344 | BW110: =BW109/BR109-1 -> 0.25260369
C111: % change q/q | AK111: =AK109/AI109-1 -> #DIV/0! | AL111: =AL109/AK109-1 -> 1.0956189 | AM111: =AM109/AL109-1 -> 0.52992821 | AN111: =AN109/AM109-1 -> 0.38428289 | AP111: =AP109/AN109-1 -> 0.056334695 | AQ111: =AQ109/AP109-1 -> 0.052470296 | AR111: =AR109/AQ109-1 -> 0.058527441 | AS111: =AS109/AR109-1 -> 0.032164103 | AU111: =AU109/AS109-1 -> 0.076502938 | AV111: =AV109/AU109-1 -> 0.052914285 | AW111: =AW109/AV109-1 -> 0.042076079 | AX111: =AX109/AW109-1 -> 0.045357797 | AZ111: =AZ109/AX109-1 -> 0.039989412 | BA111: =BA109/AZ109-1 -> 0.0313742 | BB111: =BB109/BA109-1 -> 0.030486242 | BC111: =BC109/BB109-1 -> 0.039287655 | BE111: =BE109/BC109-1 -> -0.0024947601 | BF111: =BF109/BE109-1 -> 0.038114699 | BG111: =BG109/BF109-1 -> 0.035773888 | BH111: =BH109/BG109-1 -> 0.029006404 | BJ111: =BJ109/BH109-1 -> 0.057312975 | BK111: =BK109/BJ109-1 -> 0.024427939 | BL111: =BL109/BK109-1 -> 0.026391973 | BM111: =BM109/BL109-1 -> 0.031415787 | BO111: =BO109/BM109-1 -> 0.024355913 | BP111: =BP109/BO109-1 -> 0.02324699 | BQ111: =BQ109/BP109-1 -> 0.026800955 | BR111: =BR109/BQ109-1 -> 0.038652734 | BT111: =BT109/BR109-1 -> 0.062867452 | BU111: =BU109/BT109-1 -> 0.06666372 | BV111: =BV109/BU109-1 -> 0.055106907 | BW111: =BW109/BV109-1 -> 0.047154076

Sheet BS
B4: Balance Sheet | D4: =IS!D3 -> 2005 | E4: =IS!E3 -> 2006 | F4: =IS!F3 -> 2007 | G4: =IS!G3 -> 1Q08 | H4: =IS!H3 -> 2Q08 | I4: =IS!I3 -> 2Q08 | J4: =IS!J3 -> 4Q08 | K4: =IS!K3 -> 2008 | ... CW4: =IS!CW3 -> 2026E
B5: Assets
C6: Cash and equivalents | J6: 3715 | O6: 5931 | Q6: 5996 | R6: 37973 | S6: 39113 | T6: 40473 | V6: =T6+CF!V62 -> 40447 | W6: 29788 | X6: 31546 | Y6: 31985 | AA6: 33063 | AB6: 35501 | AC6: 69715 | AD6: 66050 | AE6: =AD6 -> 66050 | AF6: 72559 | AG6: 75134 | AH6: 80813 | AI6: 131294 | AJ6: =AI6 -> 131294 | AK6: 134603 | AL6: =AK6+CF!AL62 -> 136508 | AM6: 140822 | AN6: 130795 | AO6: =AN6 -> 130795 | AP6: 133550 | AQ6: 121344 | AR6: =117887 -> 117887 | AS6: =121538 -> 121538 | AT6: =AS6 -> 121538 | AU6: 110889 | AV6: 107160 | AW6: 109635 | AX6: 115877 | AY6: =AX6 -> 115877 | AZ6: 128707 | BA6: 131744 | BB6: 128984 | BC6: 123127 | BD6: =BC6 -> 123127 | BE6: 120547 | BF6: 125385 | BG6: 144748 | BH6: 133859 | BI6: =BH6 -> 133859 | BJ6: 143715 | BK6: 147023 | BL6: 149727 | BM6: 179252 | BN6: =BM6 -> 179252 | BO6: 184484 | BP6: 174850 | BQ6: 208930 | BR6: 149692 | BS6: =BR6 -> 149692 | BT6: 169274 | BU6: 184367 | BV6: 195803 | BW6: 207552 | BX6: =BW6 -> 207552 | BY6: 203088 | BZ6: 212725 | CA6: 186230 | CB6: 162893 | CC6: =CB6 -> 162893 | CD6: 182304 | CE6: 209264 | CF6: 178702 | CG6: 219081 | CH6: =CG6 -> 219081 | CI6: 234637 | CJ6: 240232 | CK6: 198842 | CL6: 241017 | CM6: =CL6 -> 241017 | CN6: 94921 | CO6: 107603 | CP6: 133725 | CQ6: 151355 | CR6: =CQ6 -> 151355 | CS6: =CR6+CF!CS62 -> 239503.56 | CT6: =CS6+CF!CT62 -> 290198.54 | CU6: =CT6+CF!CU62 -> 342559.1 | CV6: =CU6+CF!CV62 -> 396561.05 | CW6: =CV6 -> 396561.05
C7: Short term marketable securities | AR7: 5014 | AS7: 7517 | AT7: =AS7 -> 7517 | AU7: 10010 | AV7: 21010 | AW7: 15616 | AX7: 23076 | AY7: =AX7 -> 23076 | AZ7: 25550 | BA7: 26896 | BB7: 34869 | BC7: 40192 | BD7: =BC7 -> 40192 | BE7: 45272 | BF7: 47352 | BG7: 44654 | BH7: 44537 | BI7: =BH7 -> 44537 | BJ7: 41683 | BK7: 51651 | BL7: 51446 | BM7: 34284 | BN7: =BM7 -> 34284 | BO7: 30074 | BP7: 50775 | BQ7: 52300 | BR7: 37786 | BS7: =BR7 -> 37786 | BT7: 39174 | BU7: 48999 | BV7: 56183 | BW7: 49758 | BX7: =BW7 -> 49758 | BY7: 39968 | BZ7: 46513 | CA7: 50928 | CB7: 51412 | CC7: =CB7 -> 51412 | CD7: 51146 | CE7: 60914 | CF7: 60628 | CG7: 56359 | CH7: =CG7 -> 56359 | CI7: 56174 | CJ7: 31554 | CK7: 6931 | CL7: 0 | CM7: =CL7 -> 0 | CN7: =CM7 -> 0 | CP7: =CO7 -> 0 | CR7: =CQ7 -> 0 | CS7: =CR7 -> 0 | CT7: =CS7 -> 0 | CU7: =CT7 -> 0 | CV7: =CU7 -> 0 | CW7: =CV7 -> 0
C8: Accounts receivables | J8: 4564 | O8: 4766 | Q8: 5125 | R8: 4987 | S8: 5517 | T8: 5574 | V8: 6356 | W8: 7353 | X8: 7695 | Y8: 7958 | AA8: 7981 | AB8: 9029 | AC8: 10146 | AD8: 10940 | AE8: =AD8 -> 10940 | AF8: 10788 | AG8: 11707 | AH8: 11148 | AI8: 11611 | AJ8: =AI8 -> 11611 | AK8: 12166 | AL8: 13348 | AM8: 13594 | AN8: 15422 | AO8: =AN8 -> 15422 | AP8: 15823 | AQ8: 17255 | AR8: 17945 | AS8: 17615 | AT8: =AS8 -> 17615 | AU8: 20426 | AV8: 20432 | AW8: 21361 | AX8: 20746 | AY8: =AX8 -> 20746 | AZ8: 22683 | BA8: 21545 | BB8: 24175 | BC8: 24897 | BD8: =BC8 -> 24897 | BE8: 25948 | BF8: 28171 | BG8: 27289 | BH8: 27488 | BI8: =BH8 -> 27488 | BJ8: 28301 | BK8: 30747 | BL8: 29383 | BM8: 31532 | BN8: =BM8 -> 31532 | BO8: 33275 | BP8: 37840 | BQ8: 34048 | BR8: =37811-4233 -> 33578 | BS8: =BR8 -> 33578 | BT8: 35270 | BU8: 37936 | BV8: 35330 | BW8: 34562 | BX8: =BW8 -> 34562 | BY8: 38778 | BZ8: =44559-4454 -> 40105 | CA8: 36787 | CB8: =42501-3066 -> 39435 | CC8: =CB8 -> 39435 | CD8: =46654-3217 -> 43437 | CE8: =48092-3100 -> 44992 | CF8: =48218-3077 -> 45141 | CG8: 46840 | CH8: =CG8 -> 46840 | CI8: 52135 | CJ8: 55397 | CK8: 55570 | CL8: 52035 | CM8: =CL8 -> 52035 | CN8: 63390 | CO8: 67512 | CP8: 67439 | CQ8: 68166 | CR8: =CQ8 -> 68166 | CS8: =CS55*IS!CS4 -> 63568.433 | CT8: =CT55*IS!CT4 -> 65240.578 | CU8: =CU55*IS!CU4 -> 67458.398 | CV8: =CV55*IS!CV4 -> 68629.065 | CW8: =CV8 -> 68629.065
C9: Deferred costs, current | J9: 4058 | O9: 4126 | Q9: 4259 | R9: 4569 | S9: 4581 | T9: 4720 | V9: 4887 | W9: 5177 | X9: 5486 | Y9: 5748 | AA9: 6085 | AB9: 6509 | AC9: 6903 | AD9: 7346 | AE9: =AD9 -> 7346 | AF9: 7860 | AG9: 8288 | AH9: 8699 | AI9: 9048 | AJ9: =AI9 -> 9048 | AK9: 9539 | AL9: 10415 | AM9: 11132 | AN9: 12055 | AO9: =AN9 -> 12055 | AP9: 12911 | AQ9: 14003 | AR9: 14761 | AS9: 15086 | AT9: =AS9 -> 15086 | AU9: 15799 | AV9: 17278 | AW9: 18647 | AX9: 19224 | AY9: =AX9 -> 19224 | AZ9: 20908 | BA9: 21917 | BB9: 23326 | BC9: 25091 | BD9: =BC9 -> 25091 | BE9: 31318 | BF9: 32216 | BG9: 33134 | BH9: 34502 | BI9: =BH9 -> 34502 | BJ9: 34692 | BK9: 35087 | BL9: 34583 | BM9: 35274 | BN9: =BM9 -> 35274 | BO9: 35543 | BP9: 35797 | BQ9: 36562 | BR9: 37502 | BS9: =BR9 -> 37502 | BT9: 38666 | BU9: 40149 | BV9: 41593 | BW9: 44529 | BX9: =BW9 -> 44529 | BY9: 46710 | BZ9: 48294 | CA9: 50082 | CB9: 52755 | CC9: =CB9 -> 52755 | CD9: 53844 | CE9: 56250 | CF9: 59525 | CG9: 62403 | CH9: =CG9 -> 62403 | CI9: 63647 | CJ9: 64318 | CK9: 64665 | CL9: 65342 | CM9: =CL9 -> 65342 | CN9: 67107 | CO9: 66809 | CP9: 66510 | CQ9: 66693 | CR9: =CQ9 -> 66693 | CS9: =CS56*IS!CS4 -> 75126.33 | CT9: =CT56*IS!CT4 -> 77102.501 | CU9: =CU56*IS!CU4 -> 79723.562 | CV9: =CV56*IS!CV4 -> 81107.077 | CW9: =CV9 -> 81107.077
C10: Prepaid expenses and other assets | J10: 785 | O10: 1440 | Q10: 2013 | R10: 957 | S10: 991 | T10: 874 | V10: 1234 | W10: 1564 | X10: 1233 | Y10: =783+1765 -> 2548 | AA10: =782+1896 -> 2678 | AB10: =782+1604 -> 2386 | AC10: =782+2398 -> 3180 | AD10: =1732+5443 -> 7175 | AE10: =AD10 -> 7175 | AF10: =1732+2713 -> 4445 | AG10: =1732+2966 -> 4698 | AH10: =1732+2848 -> 4580 | AI10: =1272+2850 -> 4122 | AJ10: =AI10 -> 4122 | AK10: =1272+2797 -> 4069 | AL10: =1272+3346 -> 4618 | AM10: =1272+3824 -> 5096 | AN10: =76+3846 -> 3922 | AO10: =AN10 -> 3922 | AP10: =76+3797 -> 3873 | AQ10: =76+6393 -> 6469 | AR10: =76+5688 -> 5764 | AS10: 5030 | AT10: =AS10 -> 5030 | AU10: 5529 | AV10: 7540 | AW10: 7323 | AX10: 7010 | AY10: =AX10 -> 7010 | AZ10: 6992 | BA10: 6955 | BB10: 5853 | BC10: 6149 | BD10: =BC10 -> 6149 | BE10: 5696 | BF10: 6762 | BG10: 6613 | BH10: 9229 | BI10: =BH10 -> 9229 | BJ10: 8858 | BK10: 8265 | BL10: 8385 | BM10: 11279 | BN10: =BM10 -> 11279 | BO10: =9417-2939 -> 6478 | BP10: =8378-3663 -> 4715 | BQ10: =8927-3759 -> 5168 | BR10: 12312 | BS10: =BR10 -> 12312 | BT10: 14490 | BU10: 11711 | BV10: 14346 | BW10: 16042 | BX10: =BW10 -> 16042 | BY10: 22923 | BZ10: 17912 | CA10: 15246 | CB10: 16319 | CC10: =CB10 -> 16319 | CD10: 15651 | CE10: 13556 | CF10: 15743 | CG10: 16758 | CH10: =CG10 -> 16758 | CI10: 13695 | CJ10: 15437 | CK10: 18639 | CL10: 23513 | CM10: =CL10 -> 23513 | CN10: 26417 | CO10: 27453 | CP10: 47947 | CQ10: 49090 | CR10: =CQ10 -> 49090 | CS10: =CS57*IS!CS4 -> 19263.161 | CT10: =CT57*IS!CT4 -> 19769.872 | CU10: =CU57*IS!CU4 -> 20441.939 | CV10: =CV57*IS!CV4 -> 20796.686 | CW10: =CV10 -> 20796.686
B11: Total Current Assets | J11: =SUM(J6:J10) -> 13122 | L11: =SUM(L6:L10) -> 0 | M11: =SUM(M6:M10) -> 0 | N11: =SUM(N6:N10) -> 0 | O11: =SUM(O6:O10) -> 16263 | Q11: =SUM(Q6:Q10) -> 17393 | R11: =SUM(R6:R10) -> 48486 | S11: =SUM(S6:S10) -> 50202 | T11: =SUM(T6:T10) -> 51641 | V11: =SUM(V6:V10) -> 52924 | W11: =SUM(W6:W10) -> 43882 | X11: =SUM(X6:X10) -> 45960 | Y11: =SUM(Y6:Y10) -> 48239 | AA11: =SUM(AA6:AA10) -> 49807 | AB11: =SUM(AB6:AB10) -> 53425 | AC11: =SUM(AC6:AC10) -> 89944 | AD11: =SUM(AD6:AD10) -> 91511 | AE11: =AD11 -> 91511 | AF11: =SUM(AF6:AF10) -> 95652 | AG11: =SUM(AG6:AG10) -> 99827 | AH11: =SUM(AH6:AH10) -> 105240 | AI11: =SUM(AI6:AI10) -> 156075 | AJ11: =AI11 -> 156075 | AK11: =SUM(AK6:AK10) -> 160377 | AL11: =SUM(AL6:AL10) -> 164889 | AM11: =SUM(AM6:AM10) -> 170644 | AN11: =SUM(AN6:AN10) -> 162194 | AO11: =AN11 -> 162194 | AP11: =SUM(AP6:AP10) -> 166157 | AQ11: =SUM(AQ6:AQ10) -> 159071 | AR11: =SUM(AR6:AR10) -> 161371 | AS11: =SUM(AS6:AS10) -> 166786 | AT11: =AS11 -> 166786 | AU11: =SUM(AU6:AU10) -> 162653 | AV11: =SUM(AV6:AV10) -> 173420 | AW11: =SUM(AW6:AW10) -> 172582 | AX11: =SUM(AX6:AX10) -> 185933 | AY11: =AX11 -> 185933 | AZ11: =SUM(AZ6:AZ10) -> 204840 | BA11: =SUM(BA6:BA10) -> 209057 | BB11: =SUM(BB6:BB10) -> 217207 | BC11: =SUM(BC6:BC10) -> 219456 | BD11: =BC11 -> 219456 | BE11: =SUM(BE6:BE10) -> 228781 | BF11: =SUM(BF6:BF10) -> 239886 | BG11: =SUM(BG6:BG10) -> 256438 | BH11: =SUM(BH6:BH10) -> 249615 | BI11: =BH11 -> 249615 | BJ11: =SUM(BJ6:BJ10) -> 257249 | BK11: =SUM(BK6:BK10) -> 272773 | BL11: =SUM(BL6:BL10) -> 273524 | BM11: =SUM(BM6:BM10) -> 291621 | BN11: =BM11 -> 291621 | BO11: =SUM(BO6:BO10) -> 289854 | BP11: =SUM(BP6:BP10) -> 303977 | BQ11: =SUM(BQ6:BQ10) -> 337008 | BR11: =SUM(BR6:BR10) -> 270870 | BS11: =BR11 -> 270870 | BT11: =SUM(BT6:BT10) -> 296874 | BU11: =SUM(BU6:BU10) -> 323162 | BV11: =SUM(BV6:BV10) -> 343255 | BW11: =SUM(BW6:BW10) -> 352443 | BX11: =BW11 -> 352443 | BY11: =SUM(BY6:BY10) -> 351467 | BZ11: =SUM(BZ6:BZ10) -> 365549 | CA11: =SUM(CA6:CA10) -> 339273 | CB11: =SUM(CB6:CB10) -> 322814 | CC11: =CB11 -> 322814 | CD11: =SUM(CD6:CD10) -> 346382 | CE11: =SUM(CE6:CE10) -> 384976 | CF11: =SUM(CF6:CF10) -> 359739 | CG11: =SUM(CG6:CG10) -> 401441 | CH11: =CG11 -> 401441 | CI11: =SUM(CI6:CI10) -> 420288 | CJ11: =SUM(CJ6:CJ10) -> 406938 | CK11: =SUM(CK6:CK10) -> 344647 | CL11: =SUM(CL6:CL10) -> 381907 | CM11: =CL11 -> 381907 | CN11: =SUM(CN6:CN10) -> 251835 | CO11: =SUM(CO6:CO10) -> 269377 | CP11: =SUM(CP6:CP10) -> 315621 | CQ11: =SUM(CQ6:CQ10) -> 335304 | CR11: =CQ11 -> 335304 | CS11: =SUM(CS6:CS10) -> 397461.48 | CT11: =SUM(CT6:CT10) -> 452311.49 | CU11: =SUM(CU6:CU10) -> 510183 | CV11: =SUM(CV6:CV10) -> 567093.88 | CW11: =CV11 -> 567093.88
C12: Total PP&E | J12: 2809 | O12: 2520 | Q12: 2311 | R12: 2989 | S12: 2602 | T12: 2760 | V12: 2826 | W12: 2896 | X12: 3082 | Y12: 3382 | AA12: 3420 | AB12: 4028 | AC12: 5567 | AD12: 7670 | AE12: =AD12 -> 7670 | AF12: 7589 | AG12: 9319 | AH12: 10557 | AI12: 9922 | AJ12: =AI12 -> 9922 | AK12: 9479 | AL12: 9036 | AM12: 8619 | AN12: 11361 | AO12: =AN12 -> 11361 | AP12: 12088 | AQ12: 12952 | AR12: 13079 | AS12: 13620 | AT12: =AS12 -> 13620 | AU12: 13972 | AV12: 13932 | AW12: 14830 | AX12: 15314 | AY12: =AX12 -> 15314 | AZ12: 15066 | BA12: 15527 | BB12: 15616 | BC12: 16856 | BD12: =BC12 -> 16856 | BE12: 17304 | BF12: 18136 | BG12: 19368 | BH12: 20957 | BI12: =BH12 -> 20957 | BJ12: 20710 | BK12: 20597 | BL12: 20757 | BM12: 23752 | BN12: =BM12 -> 23752 | BO12: =24035 -> 24035 | BP12: 25510 | BQ12: 25053 | BR12: 26432 | BS12: =BR12 -> 26432 | BT12: 26606 | BU12: 29046 | BV12: 31036 | BW12: 31901 | BX12: =BW12 -> 31901 | BY12: 32261 | BZ12: 32000 | CA12: 32923 | CB12: 35458 | CC12: =CB12 -> 35458 | CD12: 35078 | CE12: 35211 | CF12: 36209 | CG12: 36043 | CH12: =CG12 -> 36043 | CI12: 34971 | CJ12: 35083 | CK12: 36148 | CL12: 37547 | CM12: =CL12 -> 37547 | CN12: 38687 | CO12: 40150 | CP12: 41448 | CQ12: 43117 | CR12: =CQ12 -> 43117 | CS12: =CR12-CF!CS33-CF!CS9 -> 45089.715 | CT12: =CS12-CF!CT33-CF!CT9 -> 45998.59 | CU12: =CT12-CF!CU33-CF!CU9 -> 46794.765 | CV12: =CU12-CF!CV33-CF!CV9 -> 47492.214 | CW12: =CV12 -> 47492.214
C13: Operating lease right to use | BJ13: 15234 | BK13: 14038 | BL13: =13648 -> 13648 | BM13: 15744 | BN13: =BM13 -> 15744 | BO13: 15170 | BP13: 14839 | BQ13: 14092 | BR13: 15581 | BS13: =BR13 -> 15581 | BT13: 15296 | BU13: 13352 | BV13: 12665 | BW13: 10851 | BX13: =BW13 -> 10851 | BY13: 10248 | BZ13: 9578 | CA13: 9760 | CB13: 9170 | CC13: =CB13 -> 9170 | CD13: 8451 | CE13: 7973 | CF13: 8315 | CG13: 7862 | CH13: =CG13 -> 7862 | CI13: 7285 | CJ13: 7076 | CK13: 8412 | CL13: 8192 | CM13: =CL13 -> 8192 | CN13: 8424 | CO13: 7395 | CP13: 6723 | CQ13: 5025 | CR13: =CQ13 -> 5025 | CS13: =CR13 -> 5025 | CT13: =CS13 -> 5025 | CU13: =CT13 -> 5025 | CV13: =CU13 -> 5025 | CW13: =CV13 -> 5025
C14: Goodwill | J14: 1166 | O14: 1166 | Q14: 1166 | R14: =Q14 -> 1166 | S14: 1166 | T14: 1166 | V14: 1166 | W14: 5877 | X14: =W14 -> 5877 | Y14: 5853 | AA14: 5853 | AB14: 5853 | AC14: 25487 | AD14: 25487 | AE14: =AD14 -> 25487 | AF14: 25487 | AG14: 25487 | AH14: 25487 | AI14: 25487 | AJ14: =AI14 -> 25487 | AK14: 25487 | AL14: =AK14 -> 25487 | AM14: 25487 | AN14: 34854 | AO14: =AN14 -> 34854 | AP14: 34210 | AQ14: 34303 | AR14: 33527 | AS14: 33848 | AT14: =AS14 -> 33848 | AU14: 50921 | AV14: 50852 | AW14: 51005 | AX14: 49777 | AY14: =AX14 -> 49777 | AZ14: 50289 | BA14: 50766 | BB14: 51783 | BC14: 51613 | BD14: =BC14 -> 51613 | BE14: 51030 | BF14: 50403 | BG14: 50502 | BH14: 69658 | BI14: =BH14 -> 69658 | BJ14: 70075 | BK14: 70300 | BL14: 76366 | BM14: 76845 | BN14: =BM14 -> 76845 | BO14: 74463 | BP14: 75883 | BQ14: 76543 | BR14: 135253 | BS14: =BR14 -> 135253 | BT14: 135263 | BU14: 135354 | BV14: 134680 | BW14: 143663 | BX14: =BW14 -> 143663 | BY14: 144162 | BZ14: 142960 | CA14: 165908 | CB14: 197284 | CC14: =CB14 -> 197284 | CD14: 199001 | CE14: 202786 | CF14: 252045 | CG14: 249176 | CH14: =CG14 -> 249176 | CI14: 248813 | CJ14: 268872 | CK14: 423508 | CL14: 399180 | CM14: =CL14 -> 399180 | CN14: 533940 | CO14: 543514 | CP14: 543035 | CQ14: 541719 | CR14: =CQ14 -> 541719 | CS14: =CR14 -> 541719 | CT14: =CS14 -> 541719 | CU14: =CT14 -> 541719 | CV14: =CU14 -> 541719 | CW14: =CV14 -> 541719
C15: Intangible assets | J15: 446 | O15: 290 | Q15: 290 | R15: =Q15 -> 290 | S15: 290 | T15: =S15 -> 290 | V15: 290 | W15: 6287 | X15: 6027 | Y15: 5767 | AA15: =Y15-IS!AA36 -> 5507 | AB15: 5247 | AC15: 20957 | AD15: 20240 | AE15: =AD15 -> 20240 | AF15: 19523 | AG15: 18806 | AH15: 17799 | AI15: 17082 | AJ15: =AI15 -> 17082 | AK15: 16365 | AL15: =AK15-IS!AL36 -> 15683 | AM15: 15038 | AN15: 18851 | AO15: =AN15 -> 18851 | AP15: 17705 | AQ15: 16915 | AR15: 15766 | AS15: 15081 | AT15: =AS15 -> 15081 | AU15: 23845 | AV15: 22534 | AW15: 21338 | AX15: 19788 | AY15: =AX15 -> 19788 | AZ15: 19389 | BA15: 18484 | BB15: 17720 | BC15: 16529 | BD15: =BC15 -> 16529 | BE15: 15577 | BF15: 14354 | BG15: 13491 | BH15: 22741 | BI15: =BH15 -> 22741 | BJ15: 21572 | BK15: 20379 | BL15: 23844 | BM15: 22668 | BN15: =BM15 -> 22668 | BO15: 20857 | BP15: 19790 | BQ15: 18575 | BR15: 59830 | BS15: =BR15 -> 59830 | BT15: 57594 | BU15: 54950 | BV15: 52471 | BW15: 58587 | BX15: =BW15 -> 58587 | BY15: 56158 | BZ15: 53597 | CA15: 70742 | CB15: 88352 | CC15: =CB15 -> 88352 | CD15: 84536 | CE15: 77633 | CF15: 103597 | CG15: 107344 | CH15: =CG15 -> 107344 | CI15: 99289 | CJ15: 107519 | CK15: 168131 | CL15: 181294 | CM15: =CL15 -> 181294 | CN15: 252280 | CO15: 237105 | CP15: 225262 | CQ15: 215815 | CR15: =CQ15 -> 215815 | CS15: =CR15-IS!CS36 -> 206215 | CT15: =CS15-IS!CT36 -> 196615 | CU15: =CT15-IS!CU36 -> 187065 | CV15: =CU15-IS!CV36 -> 177515 | CW15: =CV15 -> 177515
C16: Marketable securities, non-current | AQ16: 9995 | AR16: 12514 | AS16: 14950 | AT16: =AS16 -> 14950 | AU16: 12529 | AV16: 7556 | AW16: 12529 | AX16: 7494 | AY16: =AX16 -> 7494 | AZ16: 2503 | BA16: 4997 | BB16: 2491 | BC16: 5206 | BD16: =BC16 -> 5206 | BE16: 2471 | BF16: 4922 | BG16: 4921 | BI16: =BH16 -> 0 | BJ16: =BI16 -> 0 | BL16: =BK16 -> 0 | BM16: =BL16 -> 0 | BN16: =BM16 -> 0 | BO16: =BN16 -> 0 | BP16: 7566 | BQ16: 2476 | BR16: 2500 | BS16: =BR16 -> 2500 | BT16: 2500 | BU16: 0 | BV16: 0 | BW16: =BV16 -> 0 | BX16: =BW16 -> 0 | BY16: 0 | BZ16: =BY16 -> 0 | CA16: =BZ16 -> 0 | CB16: =CA16 -> 0 | CC16: =CB16 -> 0 | CD16: =CC16 -> 0 | CE16: =CD16 -> 0 | CF16: =CE16 -> 0 | CG16: =CF16 -> 0 | CH16: =CG16 -> 0 | CM16: =CL16 -> 0 | CR16: =CQ16 -> 0 | CS16: =CR16 -> 0 | CT16: =CS16 -> 0 | CU16: =CT16 -> 0 | CV16: =CU16 -> 0 | CW16: =CV16 -> 0
C17: Other assets | J17: 1654 | O17: 1680 | Q17: =1719+61 -> 1780 | R17: =1662+59 -> 1721 | S17: =1887+80 -> 1967 | T17: =1943+80 -> 2023 | V17: =2031+80 -> 2111 | W17: =2193+80 -> 2273 | X17: =2396+80 -> 2476 | Y17: =2510+11787+80 -> 14377 | AA17: =2670+11646+93 -> 14409 | AB17: =2885+11424+84 -> 14393 | AC17: =3030+11568+191 -> 14789 | AD17: =3202+10853+238 -> 14293 | AE17: =AD17 -> 14293 | AF17: =3396+10925+207 -> 14528 | AG17: =3525+10822+202 -> 14549 | AH17: =3619+10698+190 -> 14507 | AI17: =3684+10870+210 -> 14764 | AJ17: =AI17 -> 14764 | AK17: =3957+10697+197 -> 14851 | AL17: =4578+10294+205 -> 15077 | AM17: =4876+9805+168 -> 14849 | AN17: =5267+11035+213 -> 16515 | AO17: =AN17 -> 16515 | AP17: =5274+11086+350 -> 16710 | AQ17: =5445+10880+365 -> 16690 | AR17: =5465+10758+397 -> 16620 | AS17: =5260+11149+1037 -> 17446 | AT17: =AS17 -> 17446 | AU17: =5311+11451+1043 -> 17805 | AV17: =5660+11588+2213 -> 19461 | AW17: =2130+11967+5893 -> 19990 | AX17: =6086+12446+1527 -> 20059 | AY17: =AX17 -> 20059 | AZ17: =6051+28408+1372 -> 35831 | BA17: =6419+27524+1098 -> 35041 | BB17: =1101+26628+6475 -> 34204 | BC17: =6770+17551+1539 -> 25860 | BD17: =BC17 -> 25860 | BE17: =10239+12596+1598 -> 24433 | BF17: =10328+12061+1583 -> 23972 | BG17: =10597+11433+1710 -> 23740 | BH17: =10973+10456+1723 -> 23152 | BI17: =BH17 -> 23152 | BJ17: =11199+9528+1630 -> 22357 | BK17: =10441+7627+2452 -> 20520 | BL17: =10998+4839+2621 -> 18458 | BM17: =11667+2630+2513 -> 16810 | BN17: =BM17 -> 16810 | BO17: =11393+1837+2210 -> 15440 | BP17: =10852+1030+2216 -> 14098 | BQ17: =11571+140+2228 -> 13939 | BR17: =12160+194+2705 -> 15059 | BS17: =BR17 -> 15059 | BT17: =12874+210+2620 -> 15704 | BU17: =13692+246+2476 -> 16414 | BV17: =14500+189+2487 -> 17176 | BW17: =15191+182+3028 -> 18401 | BX17: =BW17 -> 18401 | BY17: =15900+199+2913 -> 19012 | BZ17: =16371+191+2530 -> 19092 | CA17: =16474+223+1787 -> 18484 | CB17: =17424+227+2185 -> 19836 | CC17: =CB17 -> 19836 | CD17: =17965+3365+2149 -> 23479 | CE17: =19005+6676+1278 -> 26959 | CF17: =19521+6805+1177 -> 27503 | CG17: =20347+505+1126 -> 21978 | CH17: =CG17 -> 21978 | CI17: =1117+7483+20601 -> 29201 | CJ17: =20610+7347+1076 -> 29033 | CK17: =20802+412+1240 -> 22454 | CL17: =20572+505+2033 -> 23110 | CM17: =CL17 -> 23110 | CN17: =21416+562+1906 -> 23884 | CO17: =21095+645+1823 -> 23563 | CP17: =20769+463+5359 -> 26591 | CQ17: =20719+493+7667 -> 28879 | CR17: =CQ17 -> 28879 | CS17: =CR17 -> 28879 | CT17: =CS17 -> 28879 | CU17: =CT17 -> 28879 | CV17: =CU17 -> 28879 | CW17: =CV17 -> 28879
B18: Total Assets | J18: =J11+J12+J14+J15+J17 -> 19197 | L18: =L11+L12+L14+L15+L17 -> 0 | M18: =M11+M12+M14+M15+M17 -> 0 | N18: =N11+N12+N14+N15+N17 -> 0 | O18: =O11+O12+O14+O15+O17 -> 21919 | Q18: =Q11+Q12+Q14+Q15+Q17 -> 22940 | R18: =R11+R12+R14+R15+R17 -> 54652 | S18: =S11+S12+S14+S15+S17 -> 56227 | T18: =T11+T12+T14+T15+T17 -> 57880 | V18: =V11+V12+V14+V15+V17 -> 59317 | W18: =W11+W12+W14+W15+W17 -> 61215 | X18: =X11+X12+X14+X15+X17 -> 63422 | Y18: =Y11+Y12+Y14+Y15+Y17 -> 77618 | AA18: =AA11+AA12+AA14+AA15+AA17 -> 78996 | AB18: =AB11+AB12+AB14+AB15+AB17 -> 82946 | AC18: =AC11+AC12+AC14+AC15+AC17 -> 156744 | AD18: =AD11+AD12+AD14+AD15+AD17 -> 159201 | AE18: =AD18 -> 159201 | AF18: =AF11+AF12+AF14+AF15+AF17 -> 162779 | AG18: =AG11+AG12+AG14+AG15+AG17 -> 167988 | AH18: =AH11+AH12+AH14+AH15+AH17 -> 173590 | AI18: =AI11+AI12+AI14+AI15+AI17 -> 223330 | AJ18: =AI18 -> 223330 | AK18: =AK11+AK12+AK14+AK15+AK17 -> 226559 | AL18: =AL11+AL12+AL14+AL15+AL17 -> 230172 | AM18: =AM11+AM12+AM14+AM15+AM17 -> 234637 | AN18: =AN11+AN12+AN14+AN15+AN17 -> 243775 | AO18: =AN18 -> 243775 | AP18: =AP11+AP12+AP14+AP15+AP17+AP16 -> 246870 | AQ18: =AQ11+AQ12+AQ14+AQ15+AQ17+AQ16 -> 249926 | AR18: =AR11+AR12+AR14+AR15+AR17+AR16 -> 252877 | AS18: =AS11+AS12+AS14+AS15+AS17+AS16 -> 261731 | AT18: =AS18 -> 261731 | AU18: =AU11+AU12+AU14+AU15+AU17+AU16 -> 281725 | AV18: =AV11+AV12+AV14+AV15+AV17+AV16 -> 287755 | AW18: =AW11+AW12+AW14+AW15+AW17+AW16 -> 292274 | AX18: =AX11+AX12+AX14+AX15+AX17+AX16 -> 298365 | AY18: =AX18 -> 298365 | AZ18: =AZ11+AZ12+AZ14+AZ15+AZ17+AZ16 -> 327918 | BA18: =BA11+BA12+BA14+BA15+BA17+BA16 -> 333872 | BB18: =BB11+BB12+BB14+BB15+BB17+BB16 -> 339021 | BC18: =BC11+BC12+BC14+BC15+BC17+BC16 -> 335520 | BD18: =BC18 -> 335520 | BE18: =BE11+BE12+BE14+BE15+BE17+BE16 -> 339596 | BF18: =BF11+BF12+BF14+BF15+BF17+BF16 -> 351673 | BG18: =BG11+BG12+BG14+BG15+BG17+BG16 -> 368460 | BH18: =BH11+BH12+BH14+BH15+BH17+BH16 -> 386123 | BI18: =BH18 -> 386123 | BJ18: =BJ11+BJ12+BJ14+BJ15+BJ17+BJ16+BJ13 -> 407197 | BK18: =BK11+BK12+BK14+BK15+BK17+BK16+BK13 -> 418607 | BL18: =BL11+BL12+BL14+BL15+BL17+BL16+BL13 -> 426597 | BM18: =BM11+BM12+BM14+BM15+BM17+BM16+BM13 -> 447440 | BN18: =BM18 -> 447440 | BO18: =BO11+BO12+BO14+BO15+BO17+BO16+BO13 -> 439819 | BP18: =BP11+BP12+BP14+BP15+BP17+BP16+BP13 -> 461663 | BQ18: =BQ11+BQ12+BQ14+BQ15+BQ17+BQ16+BQ13 -> 487686 | BR18: =BR11+BR12+BR14+BR15+BR17+BR16+BR13 -> 525525 | BS18: =BR18 -> 525525 | BT18: =BT11+BT12+BT14+BT15+BT17+BT16+BT13 -> 549837 | BU18: =BU11+BU12+BU14+BU15+BU17+BU16+BU13 -> 572278 | BV18: =BV11+BV12+BV14+BV15+BV17+BV16+BV13 -> 591283 | BW18: =BW11+BW12+BW14+BW15+BW17+BW16+BW13 -> 615846 | BX18: =BX11+BX12+BX14+BX15+BX17+BX16+BX13 -> 615846 | BY18: =BY11+BY12+BY14+BY15+BY17+BY16+BY13 -> 613308 | BZ18: =BZ11+BZ12+BZ14+BZ15+BZ17+BZ16+BZ13 -> 622776 | CA18: =CA11+CA12+CA14+CA15+CA17+CA16+CA13 -> 637090 | ... CW18: =CW11+CW12+CW14+CW15+CW17+CW16+CW13 -> 1367724.1
AE19: =AD19 -> 0
B20: Liabilities and Equity | AE20: =AD20 -> 0
C21: Current portion of capital lease | J21: 441 | O21: 338 | Q21: 886 | R21: 343 | S21: 122 | T21: 122 | V21: 0 | W21: 0 | X21: 0 | AE21: =AD21 -> 0 | AO21: =AN21 -> 0 | AT21: =AS21 -> 0 | AY21: =AX21 -> 0 | BD21: =BC21 -> 0 | BI21: =BH21 -> 0 | BN21: =BM21 -> 0 | BS21: =BR21 -> 0 | BX21: =BW21 -> 0 | CC21: =CB21 -> 0 | CH21: =CG21 -> 0 | CM21: =CL21 -> 0 | CR21: =CQ21 -> 0 | CW21: =CV21 -> 0
C22: Equipment and term loans | J22: 1409 | O22: 499 | AE22: =AD22 -> 0 | AO22: =AN22 -> 0 | AT22: =AS22 -> 0 | AY22: =AX22 -> 0 | BD22: =BC22 -> 0 | BI22: =BH22 -> 0 | BN22: =BM22 -> 0 | BS22: =BR22 -> 0 | BX22: =BW22 -> 0 | CC22: =CB22 -> 0 | CH22: =CG22 -> 0 | CM22: =CL22 -> 0 | CR22: =CQ22 -> 0 | CW22: =CV22 -> 0
C23: Line of credit | J23: 1300 | O23: 1500 | Q23: 1600 | R23: 0 | S23: 0 | T23: 0 | V23: 0 | W23: 0 | X23: 0 | Y23: 0 | AA23: 0 | AB23: 0 | AC23: 0 | AD23: 0 | AE23: =AD23 -> 0 | AF23: 0 | AG23: 0 | AH23: 0 | AI23: 0 | AJ23: =AI23 -> 0 | AK23: 0 | AL23: 0 | AM23: 0 | AN23: 0 | AO23: =AN23 -> 0 | AP23: 0 | AQ23: 0 | AR23: 0 | AS23: 0 | AT23: =AS23 -> 0 | AU23: 0 | AV23: 0 | AW23: 0 | AX23: 0 | AY23: =AX23 -> 0 | AZ23: 0 | BA23: 0 | BB23: 0 | BC23: 0 | BD23: =BC23 -> 0 | BE23: 0 | BF23: 0 | BG23: 0 | BH23: 0 | BI23: =BH23 -> 0 | BJ23: 0 | BK23: 0 | BL23: 0 | BM23: 0 | BN23: =BM23 -> 0 | BO23: 0 | BP23: 0 | BQ23: 0 | BR23: 0 | BS23: =BR23 -> 0 | BT23: 0 | BU23: 0 | BV23: 0 | BW23: 0 | BX23: =BW23 -> 0 | BY23: 0 | BZ23: 0 | CA23: 0 | CB23: 0 | CC23: =CB23 -> 0 | CD23: 0 | CE23: 0 | CF23: 0 | CG23: 0 | CH23: =CG23 -> 0 | CI23: 0 | CJ23: 0 | CK23: 0 | CL23: 0 | CM23: =CL23 -> 0 | CN23: 0 | CO23: 0 | CP23: 0 | CQ23: 0 | CR23: =CQ23 -> 0 | CS23: 0 | CT23: 0 | CU23: 0 | CV23: 0 | CW23: =CV23 -> 0
C24: Accounts payable | J24: 804 | O24: 1345 | Q24: 1208 | R24: 983 | S24: 1058 | T24: 998 | V24: 1579 | W24: 1821 | X24: 1387 | Y24: 1411 | AA24: 1240 | AB24: 1944 | AC24: 2739 | AD24: 1857 | AE24: =AD24 -> 1857 | AF24: 2034 | AG24: 1650 | AH24: 1685 | AI24: 1798 | AJ24: =AI24 -> 1798 | AK24: 2243 | AL24: 2999 | AM24: 2098 | AN24: 3961 | AO24: =AN24 -> 3961 | AP24: 3444 | AQ24: 3706 | AR24: 2381 | AS24: 2163 | AT24: =AS24 -> 2163 | AU24: 3900 | AV24: 3581 | AW24: 2442 | AX24: 2302 | AY24: =AX24 -> 2302 | AZ24: 3580 | BA24: 2720 | BB24: 3089 | BC24: 4463 | BD24: =BC24 -> 4463 | BE24: 3472 | BF24: 3709 | BG24: 3853 | BH24: 4440 | BI24: =BH24 -> 4440 | BJ24: 4391 | BK24: 3708 | BL24: 4367 | BM24: 4274 | BN24: =BM24 -> 4274 | BO24: 4602 | BP24: 4256 | BQ24: =5036 -> 5036 | BR24: 5354 | BS24: =BR24 -> 5354 | BT24: 5081 | BU24: 5942 | BV24: 3752 | BW24: 8330 | BX24: =BW24 -> 8330 | BY24: 4731 | BZ24: 4442 | CA24: 8200 | CB24: 11256 | CC24: =CB24 -> 11256 | CD24: 5339 | CE24: 6163 | CF24: 6195 | CG24: 7420 | CH24: =CG24 -> 7420 | CI24: 12303 | CJ24: 5877 | CK24: 8107 | CL24: 8577 | CM24: =CL24 -> 8577 | CN24: 11255 | CO24: 11604 | CP24: 12745 | CQ24: 13757 | CR24: =CQ24 -> 13757 | CS24: =CS59*IS!CS4 -> 13484.213 | CT24: =CT59*IS!CT4 -> 13838.91 | CU24: =CU59*IS!CU4 -> 14309.357 | CV24: =CV59*IS!CV4 -> 14557.68 | CW24: =CV24 -> 14557.68
C25: Accrued compensation and benefits | J25: 1884 | O25: 3005 | Q25: 2667 | R25: 3496 | S25: 3719 | T25: 3577 | V25: 3362 | W25: 3836 | X25: 5189 | Y25: 5118 | AA25: 4548 | AB25: 4806 | AC25: 6634 | AD25: 6038 | AE25: =AD25 -> 6038 | AF25: 6697 | AG25: 6511 | AH25: 8404 | AI25: 7981 | AJ25: =AI25 -> 7981 | AK25: 7694 | AL25: 7639 | AM25: 10044 | AN25: 9926 | AO25: =AN25 -> 9926 | AP25: 10303 | AQ25: 9468 | AR25: 9922 | AS25: 11150 | AT25: =AS25 -> 11150 | AU25: 11333 | AV25: 12053 | AW25: 11796 | AX25: 13740 | AY25: =AX25 -> 13740 | AZ25: 12272 | BA25: 13243 | BB25: 12681 | BC25: 15886 | BD25: =BC25 -> 15886 | BE25: 11617 | BF25: 14347 | BG25: 15498 | BH25: 20415 | BI25: =BH25 -> 20415 | BJ25: 11974 | BK25: 15883 | BL25: 17660 | BM25: 22303 | BN25: =BM25 -> 22303 | BO25: 13132 | BP25: 16950 | BQ25: =19374 -> 19374 | BR25: 21939 | BS25: =BR25 -> 21939 | BT25: 20428 | BU25: 27469 | BV25: 30986 | BW25: 31661 | BX25: =BW25 -> 31661 | BY25: 21930 | BZ25: 25855 | CA25: 28779 | CB25: 30235 | CC25: =CB25 -> 30235 | CD25: 26431 | CE25: 28637 | CF25: 41474 | CG25: 41588 | CH25: =CG25 -> 41588 | CI25: 32990 | CJ25: 32236 | CK25: 46010 | CL25: 47160 | CM25: =CL25 -> 47160 | CN25: 40747 | CO25: 38708 | CP25: 51795 | CQ25: 47577 | CR25: =CQ25 -> 47577 | CS25: =CS60*IS!CS4 -> 48157.904 | CT25: =CT60*IS!CT4 -> 51401.667 | CU25: =CU60*IS!CU4 -> 53149.041 | CV25: =CV60*IS!CV4 -> 54071.385 | CW25: =CV25 -> 54071.385
C26: Accrued expenses and other curr. Liab. | J26: 567 | O26: 1071 | Q26: 1457 | R26: 897 | S26: 1021 | T26: 807 | V26: 944 | W26: 1260 | X26: 1126 | Y26: 1097 | AA26: 1311 | AB26: 1560 | AC26: 1276 | AD26: 1077 | AE26: =AD26 -> 1077 | AF26: 1063 | AG26: 3420 | AH26: 2665 | AI26: 2801 | AJ26: =AI26 -> 2801 | AK26: 3069 | AL26: 1805 | AM26: 1801 | AN26: 3168 | AO26: =AN26 -> 3168 | AP26: 2796 | AQ26: 2129 | AR26: 2338 | AS26: 1987 | AT26: =AS26 -> 1987 | AU26: 2926 | AV26: 3887 | AW26: 2509 | AX26: 3508 | AY26: =AX26 -> 3508 | AZ26: 4459 | BA26: 3723 | BB26: 3991 | BC26: 4712 | BD26: =BC26 -> 4712 | BE26: 4111 | BF26: 4758 | BG26: 3976 | BH26: 4558 | BI26: =BH26 -> 4558 | BJ26: 4619 | BK26: 4964 | BL26: 4874 | BM26: 6207 | BN26: =BM26 -> 6207 | BO26: 5374 | BP26: 5067 | BQ26: =6042 -> 6042 | BR26: 11161 | BS26: =BR26 -> 11161 | BT26: 10018 | BU26: 5221 | BV26: 7110 | BW26: 8345 | BX26: =BW26 -> 8345 | BY26: 6632 | BZ26: 7508 | CA26: 5202 | CB26: 7451 | CC26: =CB26 -> 7451 | CD26: 8163 | CE26: 6714 | CF26: 8900 | CG26: 8014 | CH26: =CG26 -> 8014 | CI26: 10744 | CJ26: 9446 | CK26: 8968 | CL26: 12108 | CM26: =CL26 -> 12108 | CN26: 16640 | CO26: 12710 | CP26: 12318 | CQ26: 13074 | CR26: =CQ26 -> 13074 | CS26: =CS61*IS!CS4 -> 13484.213 | CT26: =CT61*IS!CT4 -> 13838.91 | CU26: =CU61*IS!CU4 -> 14309.357 | CV26: =CV61*IS!CV4 -> 14557.68 | CW26: =CV26 -> 14557.68
C27: Deferred rent | J27: 112 | O27: 123 | AE27: =AD27 -> 0 | AJ27: =AI27 -> 0 | AO27: =AN27 -> 0 | AP27: 677 | AQ27: 704 | AR27: 723 | AS27: 1194 | AT27: =AS27 -> 1194 | AU27: 1081 | AV27: 1344 | AW27: 1330 | AX27: 1556 | AY27: =AX27 -> 1556 | AZ27: 1504 | BA27: 1606 | BB27: 1655 | BC27: 1679 | BD27: =BC27 -> 1679 | BE27: 1313 | BF27: 1373 | BG27: 1399 | BH27: 1781 | BI27: =BH27 -> 1781 | BM27: 0 | BN27: =BM27 -> 0 | BS27: =BR27 -> 0 | BX27: =BW27 -> 0 | CC27: =CB27 -> 0 | CH27: =CG27 -> 0 | CM27: =CL27 -> 0 | CR27: =CQ27 -> 0 | CW27: =CV27 -> 0
C28: Current portion of deferred revenues | J28: 2574 | O28: 3407 | Q28: 3593 | R28: 3688 | S28: 3674 | T28: 3585 | V28: 3549 | W28: 3734 | X28: 3806 | Y28: 3840 | AA28: 4077 | AB28: 4366 | AC28: 5262 | AD28: 5499 | AE28: =AD28 -> 5499 | AF28: 5827 | AG28: 6174 | AH28: 6452 | AI28: 6335 | AJ28: =AI28 -> 6335 | AK28: 6493 | AL28: 6912 | AM28: 6961 | AN28: 7505 | AO28: =AN28 -> 7505 | AP28: 7530 | AQ28: 7833 | AR28: 8072 | AS28: 7740 | AT28: =AS28 -> 7740 | AU28: 11334 | AV28: 12281 | AW28: 12157 | AX28: 11055 | AY28: =AX28 -> 11055 | AZ28: 15803 | BA28: 16624 | BB28: 16209 | BC28: 16407 | BD28: =BC28 -> 16407 | BE28: 21583 | BF28: 24191 | BG28: 24948 | BH28: 25328 | BI28: =BH28 -> 25328 | BJ28: 28889 | BK28: 30376 | BL28: 30351 | BM28: 31463 | BN28: =BM28 -> 31463 | BO28: 34929 | BP28: 36273 | BQ28: =35582 -> 35582 | BR28: 37947 | BS28: =BR28 -> 37947 | BT28: 44481 | BU28: 48481 | BV28: 49185 | BW28: 50428 | BX28: =BW28 -> 50428 | BY28: 56798 | BZ28: 59093 | CA28: 58949 | CB28: 57423 | CC28: =CB28 -> 57423 | CD28: 62907 | CE28: 66381 | CF28: 71853 | CG28: 69187 | CH28: =CG28 -> 69187 | CI28: 73701 | CJ28: 76393 | CK28: 78883 | CL28: 74256 | CM28: =CL28 -> 74256 | CN28: 78620 | CO28: 79198 | CP28: 77566 | CQ28: 75590 | CR28: =CQ28 -> 75590 | CS28: =CS62*IS!CS4 -> 94389.491 | CT28: =CT62*IS!CT4 -> 96872.373 | CU28: =CU62*IS!CU4 -> 100165.5 | CV28: =CV62*IS!CV4 -> 101903.76 | CW28: =CV28 -> 101903.76
C29: Operating lease liabilities | BJ29: 3509 | BK29: 3469 | BL29: 3281 | BM29: 5072 | BN29: =BM29 -> 5072 | BO29: 3866 | BP29: 4189 | BQ29: =4355 -> 4355 | BR29: 2798 | BS29: =BR29 -> 2798 | BT29: 3424 | BU29: 3960 | BV29: 3895 | BW29: 4108 | BX29: =BW29 -> 4108 | BY29: 4337 | BZ29: 4341 | CA29: 4336 | CB29: 4277 | CC29: =CB29 -> 4277 | CD29: 4121 | CE29: 4073 | CF29: 4449 | CG29: 4460 | CH29: =CG29 -> 4460 | CI29: 4478 | CJ29: 4594 | CK29: 4363 | CL29: 4583 | CM29: =CL29 -> 4583 | CN29: 6162 | CO29: 5749 | CP29: 5623 | CQ29: 4353 | CR29: =CQ29 -> 4353 | CS29: =CR29 -> 4353 | CT29: =CS29 -> 4353 | CU29: =CT29 -> 4353 | CV29: =CU29 -> 4353 | CW29: =CV29 -> 4353
C30: Interest payable | J30: 36 | O30: 2 | AE30: =AD30 -> 0 | AJ30: =AI30 -> 0 | AO30: =AN30 -> 0 | AT30: =AS30 -> 0 | AY30: =AX30 -> 0 | BD30: =BC30 -> 0 | BI30: =BH30 -> 0 | BN30: =BM30 -> 0 | BS30: =BR30 -> 0 | BX30: =BW30 -> 0 | CC30: =CB30 -> 0 | CH30: =CG30 -> 0 | CM30: =CL30 -> 0 | CR30: =CQ30 -> 0 | CW30: =CV30 -> 0
B31: Total current liabilities | J31: =SUM(J21:J30) -> 9127 | O31: =SUM(O21:O30) -> 11290 | Q31: =SUM(Q21:Q30) -> 11411 | R31: =SUM(R21:R30) -> 9407 | S31: =SUM(S21:S30) -> 9594 | T31: =SUM(T21:T30) -> 9089 | V31: =SUM(V21:V30) -> 9434 | W31: =SUM(W21:W30) -> 10651 | X31: =SUM(X21:X30) -> 11508 | Y31: =SUM(Y21:Y30) -> 11466 | AA31: =SUM(AA21:AA30) -> 11176 | AB31: =SUM(AB21:AB30) -> 12676 | AC31: =SUM(AC21:AC30) -> 15911 | AD31: =SUM(AD21:AD30) -> 14471 | AE31: =AD31 -> 14471 | AF31: =SUM(AF21:AF30) -> 15621 | AG31: =SUM(AG21:AG30) -> 17755 | AH31: =SUM(AH21:AH30) -> 19206 | AI31: =SUM(AI21:AI30) -> 18915 | AJ31: =AI31 -> 18915 | AK31: =SUM(AK21:AK30) -> 19499 | AL31: =SUM(AL21:AL30) -> 19355 | AM31: =SUM(AM21:AM30) -> 20904 | AN31: =SUM(AN21:AN30) -> 24560 | AO31: =AN31 -> 24560 | AP31: =SUM(AP21:AP30) -> 24750 | AQ31: =SUM(AQ21:AQ30) -> 23840 | AR31: =SUM(AR21:AR30) -> 23436 | AS31: =SUM(AS21:AS30) -> 24234 | AT31: =AS31 -> 24234 | AU31: =SUM(AU21:AU30) -> 30574 | AV31: =SUM(AV21:AV30) -> 33146 | AW31: =SUM(AW21:AW30) -> 30234 | AX31: =SUM(AX21:AX30) -> 32161 | AY31: =AX31 -> 32161 | AZ31: =SUM(AZ21:AZ30) -> 37618 | BA31: =SUM(BA21:BA30) -> 37916 | BB31: =SUM(BB21:BB30) -> 37625 | BC31: =SUM(BC21:BC30) -> 43147 | BD31: =BC31 -> 43147 | BE31: =SUM(BE21:BE30) -> 42096 | BF31: =SUM(BF21:BF30) -> 48378 | BG31: =SUM(BG21:BG30) -> 49674 | BH31: =SUM(BH21:BH30) -> 56522 | BI31: =BH31 -> 56522 | BJ31: =SUM(BJ21:BJ30) -> 53382 | BK31: =SUM(BK21:BK30) -> 58400 | BL31: =SUM(BL21:BL30) -> 60533 | BM31: =SUM(BM21:BM30) -> 69319 | BN31: =BM31 -> 69319 | BO31: =SUM(BO21:BO30) -> 61903 | BP31: =SUM(BP21:BP30) -> 66735 | BQ31: =SUM(BQ21:BQ30) -> 70389 | BR31: =SUM(BR21:BR30) -> 79199 | BS31: =BR31 -> 79199 | BT31: =SUM(BT21:BT30) -> 83432 | BU31: =SUM(BU21:BU30) -> 91073 | BV31: =SUM(BV21:BV30) -> 94928 | BW31: =SUM(BW21:BW30) -> 102872 | BX31: =BW31 -> 102872 | BY31: =SUM(BY21:BY30) -> 94428 | BZ31: =SUM(BZ21:BZ30) -> 101239 | CA31: =SUM(CA21:CA30) -> 105466 | CB31: =SUM(CB21:CB30) -> 110642 | CC31: =CB31 -> 110642 | CD31: =SUM(CD21:CD30) -> 106961 | CE31: =SUM(CE21:CE30) -> 111968 | CF31: =SUM(CF21:CF30) -> 132871 | CG31: =SUM(CG21:CG30) -> 130669 | CH31: =CG31 -> 130669 | CI31: =SUM(CI21:CI30) -> 134216 | CJ31: =SUM(CJ21:CJ30) -> 128546 | CK31: =SUM(CK21:CK30) -> 146331 | CL31: =SUM(CL21:CL30) -> 146684 | CM31: =CL31 -> 146684 | CN31: =SUM(CN21:CN30) -> 153424 | CO31: =SUM(CO21:CO30) -> 147969 | CP31: =SUM(CP21:CP30) -> 160047 | CQ31: =SUM(CQ21:CQ30) -> 154351 | CR31: =CQ31 -> 154351 | CS31: =SUM(CS21:CS30) -> 173868.82 | CT31: =SUM(CT21:CT30) -> 180304.86 | CU31: =SUM(CU21:CU30) -> 186286.26 | CV31: =SUM(CV21:CV30) -> 189443.51 | CW31: =CV31 -> 189443.51
C32: Long-term debt | Q32: 146 | R32: 0 | S32: 0 | T32: 0 | V32: 0 | W32: 0 | X32: =W32 -> 0 | Y32: =X32 -> 0 | AA32: 0 | AB32: 0 | AC32: =AB32 -> 0 | AD32: =AC32 -> 0 | AE32: =AD32 -> 0 | AF32: 0 | AG32: 0 | AH32: =AG32 -> 0 | AI32: =AH32 -> 0 | AJ32: =AI32 -> 0 | AK32: 0 | AL32: 0 | AM32: =AL32 -> 0 | AN32: =AM32 -> 0 | AO32: =AN32 -> 0 | AT32: =AS32 -> 0 | AV32: 0 | AW32: =AV32 -> 0 | AX32: =AW32 -> 0 | AY32: =AX32 -> 0 | AZ32: 0 | BA32: 0 | BB32: =BA32 -> 0 | BC32: =BB32 -> 0 | BD32: =BC32 -> 0 | BE32: 0 | BF32: 0 | BG32: =BF32 -> 0 | BH32: =BG32 -> 0 | BI32: =BH32 -> 0 | BJ32: 0 | BK32: 0 | BL32: =BK32 -> 0 | BM32: =BL32 -> 0 | BN32: =BM32 -> 0 | BO32: 0 | BP32: 0 | BQ32: =BP32 -> 0 | BR32: =BQ32 -> 0 | BS32: =BR32 -> 0 | BT32: 0 | BU32: 0 | BV32: =BU32 -> 0 | BW32: =BV32 -> 0 | BX32: =BW32 -> 0 | BY32: 0 | BZ32: 0 | CA32: =BZ32 -> 0 | CB32: =CA32 -> 0 | CC32: =CB32 -> 0 | CD32: 0 | CE32: 0 | CF32: =CE32 -> 0 | CG32: =CF32 -> 0 | CH32: =CG32 -> 0 | CI32: 0 | CK32: =CJ32 -> 0 | CM32: =CL32 -> 0 | CN32: 0 | CP32: =CO32 -> 0 | CR32: =CQ32 -> 0 | CS32: 0 | CT32: 0 | CU32: =CT32 -> 0 | CV32: =CU32 -> 0 | CW32: =CV32 -> 0
C33: Deferred revenue, net of current portion | J33: 4014 | O33: 4025 | Q33: 4158 | R33: 4333 | S33: 4624 | T33: 5002 | V33: 5302 | W33: 5461 | X33: 6104 | Y33: 6599 | AA33: 7294 | AB33: 7873 | AC33: 8003 | AD33: 8312 | AE33: =AD33 -> 8312 | AF33: 8339 | AG33: 8686 | AH33: 8765 | AI33: 8785 | AJ33: =AI33 -> 8785 | AK33: 9201 | AL33: 10017 | AM33: 10237 | AN33: 10653 | AO33: =AN33 -> 10653 | AP33: 10550 | AQ33: 10996 | AR33: 11701 | AS33: 11005 | AT33: =AS33 -> 11005 | AU33: 10876 | AV33: 11236 | AW33: 10962 | AX33: 10847 | AY33: =AX33 -> 10847 | AZ33: 11087 | BA33: 11050 | BB33: 10625 | BC33: 10602 | BD33: =BC33 -> 10602 | BE33: 2691 | BF33: 2640 | BG33: 2685 | BH33: 2512 | BI33: =BH33 -> 2512 | BJ33: 2649 | BK33: 2714 | BL33: 2601 | BM33: 2851 | BN33: =BM33 -> 2851 | BO33: 2781 | BP33: 2746 | BQ33: =2693 -> 2693 | BR33: 2996 | BS33: =BR33 -> 2996 | BT33: 4027 | BU33: 4991 | BV33: 5159 | BW33: 5144 | BX33: =BW33 -> 5144 | BY33: 5123 | BZ33: 5281 | CA33: 5146 | CB33: 4771 | CC33: =CB33 -> 4771 | CD33: 5105 | CE33: 5724 | CF33: 6849 | CG33: 6930 | CH33: =CG33 -> 6930 | CI33: 6473 | CJ33: 7111 | CK33: 6550 | CL33: 6189 | CM33: =CL33 -> 6189 | CN33: 5748 | CO33: 5477 | CP33: 5150 | CQ33: 5288 | CR33: =CQ33 -> 5288 | CS33: =CR33 -> 5288 | CT33: =CS33 -> 5288 | CU33: =CT33 -> 5288 | CV33: =CU33 -> 5288 | CW33: =CV33 -> 5288
C34: Operating lease liabilities, non-current | BJ34: 17723 | BK34: 16890 | BL34: 16224 | BM34: 18796 | BN34: =BM34 -> 18796 | BO34: 18957 | BP34: 17920 | BQ34: =16725 -> 16725 | BR34: 19672 | BS34: =BR34 -> 19672 | BT34: 18743 | BU34: 17733 | BV34: 16697 | BW34: 16426 | BX34: =BW34 -> 16426 | BY34: 15338 | BZ34: 14239 | CA34: 13974 | CB34: 13009 | CC34: =CB34 -> 13009 | CD34: 11994 | CE34: 11058 | CF34: 10563 | CG34: 9569 | CH34: =CG34 -> 9569 | CI34: 8425 | CJ34: 7751 | CK34: 8807 | CL34: 7885 | CM34: =CL34 -> 7885 | CN34: 6101 | CO34: 5049 | CP34: 4021 | CQ34: 2839 | CR34: =CQ34 -> 2839 | CS34: =CR34 -> 2839 | CT34: =CS34 -> 2839 | CU34: =CT34 -> 2839 | CV34: =CU34 -> 2839 | CW34: =CV34 -> 2839
C35: Equipment and terms loans, net of current portion | J35: 732 | O35: 233 | AE35: =AD35 -> 0 | AJ35: =AI35 -> 0 | AO35: =AN35 -> 0 | AT35: =AS35 -> 0 | AY35: =AX35 -> 0 | BD35: =BC35 -> 0 | BI35: =BH35 -> 0 | BN35: =BM35 -> 0 | BS35: =BR35 -> 0 | BX35: =BW35 -> 0 | CC35: =CB35 -> 0 | CH35: =CG35 -> 0 | CM35: =CL35 -> 0 | CR35: =CQ35 -> 0 | CW35: =CV35 -> 0
C36: Capital lease obligations | J36: 553 | O36: 122 | AE36: =AD36 -> 0 | AJ36: =AI36 -> 0 | AO36: =AN36 -> 0 | AT36: =AS36 -> 0 | AY36: =AX36 -> 0 | BD36: =BC36 -> 0 | BI36: =BH36 -> 0 | BN36: =BM36 -> 0 | BS36: =BR36 -> 0 | BX36: =BW36 -> 0 | CC36: =CB36 -> 0 | CH36: =CG36 -> 0 | CM36: =CL36 -> 0 | CR36: =CQ36 -> 0 | CW36: =CV36 -> 0
C37: Convertible preferred stock warrant liability | J37: 188 | O37: 569 | AE37: =AD37 -> 0 | AJ37: =AI37 -> 0 | AO37: =AN37 -> 0 | AT37: =AS37 -> 0 | AY37: =AX37 -> 0 | BD37: =BC37 -> 0 | BI37: =BH37 -> 0 | BN37: =BM37 -> 0 | BS37: =BR37 -> 0 | BX37: =BW37 -> 0 | CC37: =CB37 -> 0 | CH37: =CG37 -> 0 | CM37: =CL37 -> 0 | CR37: =CQ37 -> 0 | CW37: =CV37 -> 0
C38: Deferred tax liability | J38: 82 | O38: 110 | AE38: =AD38 -> 0 | AJ38: =AI38 -> 0 | AO38: =AN38 -> 0 | AT38: =AS38 -> 0 | AU38: 2396 | AV38: 2391 | AW38: 2368 | AX38: 4179 | AY38: =AX38 -> 4179 | AZ38: 1895 | BA38: 1977 | BB38: 2100 | BC38: 1887 | BD38: =BC38 -> 1887 | BE38: 1768 | BF38: 1676 | BG38: 1551 | BH38: 1376 | BI38: =BH38 -> 1376 | BJ38: 1315 | BK38: 1246 | BL38: 1169 | BM38: 1193 | BN38: =BM38 -> 1193 | BO38: 990 | BP38: 952 | BQ38: =2939 -> 2939 | BR38: 2937 | BS38: =BR38 -> 2937 | BT38: 3112 | BU38: 3368 | BV38: 3971 | BW38: 7145 | BX38: =BW38 -> 7145 | BY38: 6898 | BZ38: 4997 | CA38: 4841 | CB38: 7419 | CC38: =CB38 -> 7419 | CD38: 6977 | CE38: 5807 | CF38: 10281 | CG38: 8972 | CH38: =CG38 -> 8972 | CI38: 7536 | CJ38: 7012 | CK38: 11607 | CL38: 15541 | CM38: =CL38 -> 15541 | CN38: 20298 | CO38: 12533 | CP38: 30223 | CQ38: 33201 | CR38: =CQ38 -> 33201 | CS38: =CR38 -> 33201 | CT38: =CS38 -> 33201 | CU38: =CT38 -> 33201 | CV38: =CU38 -> 33201 | CW38: =CV38 -> 33201
C39: Other long-term liabilities | J39: 381 | O39: 258 | Q39: 943 | R39: 317 | S39: 289 | T39: 281 | V39: 244 | W39: 247 | X39: 225 | Y39: 0 | AA39: 250 | AB39: 0 | AC39: 0 | AD39: 1601 | AE39: =AD39 -> 1601 | AF39: 1830 | AG39: 2019 | AH39: 3239 | AI39: 2857 | AJ39: =AI39 -> 2857 | AK39: 2762 | AL39: 2663 | AM39: 2577 | AN39: 3471 | AO39: =AN39 -> 3471 | AP39: 3346 | AQ39: 3178 | AR39: 3015 | AS39: 4307 | AT39: =AS39 -> 4307 | AU39: 4486 | AV39: 4140 | AW39: 3900 | AX39: 1911 | AY39: =AX39 -> 1911 | AZ39: 3912 | BA39: 3899 | BB39: 3498 | BC39: 3064 | BD39: =BC39 -> 3064 | BE39: 4690 | BF39: 4290 | BG39: 3979 | BH39: =5371+1368 -> 6739 | BI39: =BH39 -> 6739 | BJ39: 1424 | BK39: 1024 | BL39: 1002 | BM39: 405 | BN39: =BM39 -> 405 | BO39: 0 | BP39: 0 | BQ39: 0 | BR39: 0 | BS39: =BR39 -> 0 | BT39: 0 | BU39: 0 | BV39: 0 | BW39: 0 | BX39: =BW39 -> 0 | BY39: 0 | BZ39: 0 | CA39: 0 | CB39: 0 | CC39: =CB39 -> 0 | CD39: 0 | CE39: 0 | CF39: 0 | CG39: 229 | CH39: =CG39 -> 229 | CI39: 232 | CJ39: 680 | CK39: 640 | CL39: 241 | CM39: =CL39 -> 241 | CN39: 2558 | CO39: 296 | CP39: 299 | CQ39: 287 | CR39: =CQ39 -> 287 | CS39: 0 | CT39: 0 | CU39: 0 | CV39: 0 | CW39: =CV39 -> 0
B40: Total liabilities | J40: =SUM(J31:J39) -> 15077 | O40: =SUM(O31:O39) -> 16607 | Q40: =SUM(Q31:Q39) -> 16658 | R40: =SUM(R31:R39) -> 14057 | S40: =SUM(S31:S39) -> 14507 | T40: =SUM(T31:T39) -> 14372 | V40: =SUM(V31:V39) -> 14980 | W40: =SUM(W31:W39) -> 16359 | X40: =SUM(X31:X39) -> 17837 | Y40: =SUM(Y31:Y39) -> 18065 | AA40: =SUM(AA31:AA39) -> 18720 | AB40: =SUM(AB31:AB39) -> 20549 | AC40: =SUM(AC31:AC39) -> 23914 | AD40: =SUM(AD31:AD39) -> 24384 | AE40: =AD40 -> 24384 | AF40: =SUM(AF31:AF39) -> 25790 | AG40: =SUM(AG31:AG39) -> 28460 | AH40: =SUM(AH31:AH39) -> 31210 | AI40: =SUM(AI31:AI39) -> 30557 | AJ40: =AI40 -> 30557 | AK40: =SUM(AK31:AK39) -> 31462 | AL40: =SUM(AL31:AL39) -> 32035 | AM40: =SUM(AM31:AM39) -> 33718 | AN40: =SUM(AN31:AN39) -> 38684 | AO40: =AN40 -> 38684 | AP40: =SUM(AP31:AP39) -> 38646 | AQ40: =SUM(AQ31:AQ39) -> 38014 | AR40: =SUM(AR31:AR39) -> 38152 | AS40: =SUM(AS31:AS39) -> 39546 | AT40: =AS40 -> 39546 | AU40: =SUM(AU31:AU39) -> 48332 | AV40: =SUM(AV31:AV39) -> 50913 | AW40: =SUM(AW31:AW39) -> 47464 | AX40: =SUM(AX31:AX39) -> 49098 | AY40: =AX40 -> 49098 | AZ40: =SUM(AZ31:AZ39) -> 54512 | BA40: =SUM(BA31:BA39) -> 54842 | BB40: =SUM(BB31:BB39) -> 53848 | BC40: =SUM(BC31:BC39) -> 58700 | BD40: =BC40 -> 58700 | BE40: =SUM(BE31:BE39) -> 51245 | BF40: =SUM(BF31:BF39) -> 56984 | BG40: =SUM(BG31:BG39) -> 57889 | BH40: =SUM(BH31:BH39) -> 67149 | BI40: =BH40 -> 67149 | BJ40: =SUM(BJ31:BJ39) -> 76493 | BK40: =SUM(BK31:BK39) -> 80274 | BL40: =SUM(BL31:BL39) -> 81529 | BM40: =SUM(BM31:BM39) -> 92564 | BN40: =BM40 -> 92564 | BO40: =SUM(BO31:BO39) -> 84631 | BP40: =SUM(BP31:BP39) -> 88353 | BQ40: =SUM(BQ31:BQ39) -> 92746 | BR40: =SUM(BR31:BR39) -> 104804 | BS40: =BR40 -> 104804 | BT40: =SUM(BT31:BT39) -> 109314 | BU40: =SUM(BU31:BU39) -> 117165 | BV40: =SUM(BV31:BV39) -> 120755 | BW40: =SUM(BW31:BW39) -> 131587 | BX40: =BW40 -> 131587 | BY40: =SUM(BY31:BY39) -> 121787 | BZ40: =SUM(BZ31:BZ39) -> 125756 | CA40: =SUM(CA31:CA39) -> 129427 | CB40: =SUM(CB31:CB39) -> 135841 | CC40: =CB40 -> 135841 | CD40: =SUM(CD31:CD39) -> 131037 | CE40: =SUM(CE31:CE39) -> 134557 | CF40: =SUM(CF31:CF39) -> 160564 | CG40: =SUM(CG31:CG39) -> 156369 | CH40: =CG40 -> 156369 | CI40: =SUM(CI31:CI39) -> 156882 | CJ40: =SUM(CJ31:CJ39) -> 151100 | CK40: =SUM(CK31:CK39) -> 173935 | CL40: =SUM(CL31:CL39) -> 176540 | CM40: =CL40 -> 176540 | CN40: =SUM(CN31:CN39) -> 188129 | CO40: =SUM(CO31:CO39) -> 171324 | CP40: =SUM(CP31:CP39) -> 199740 | CQ40: =SUM(CQ31:CQ39) -> 195966 | CR40: =CQ40 -> 195966 | CS40: =SUM(CS31:CS39) -> 215196.82 | CT40: =SUM(CT31:CT39) -> 221632.86 | CU40: =SUM(CU31:CU39) -> 227614.26 | CV40: =SUM(CV31:CV39) -> 230771.51 | CW40: =CV40 -> 230771.51
AE41: =AD41 -> 0 | AJ41: =AI41 -> 0 | AO41: =AN41 -> 0 | AT41: =AS41 -> 0 | AY41: =AX41 -> 0 | BD41: =BC41 -> 0 | BI41: =BH41 -> 0 | BN41: =BM41 -> 0 | BS41: =BR41 -> 0 | BX41: =BW41 -> 0 | CC41: =CB41 -> 0 | CH41: =CG41 -> 0 | CM41: =CL41 -> 0 | CR41: =CQ41 -> 0 | CW41: =CV41 -> 0
B42: Total stockholders' equity | J42: =65964-61844 -> 4120 | O42: =65778-60466 -> 5312 | Q42: =65778-59496 -> 6282 | R42: 40595 | S42: =S18-S40 -> 41720 | T42: =T18-T40 -> 43508 | V42: 44337 | W42: =W18-W40 -> 44856 | X42: =X18-X40 -> 45585 | Y42: =Y18-Y40 -> 59553 | AA42: =AA18-AA40 -> 60276 | AB42: =AB18-AB40 -> 62397 | AC42: =AC18-AC40 -> 132830 | AD42: =AD18-AD40 -> 134817 | AE42: =AD42 -> 134817 | AF42: =AF18-AF40 -> 136989 | AG42: =AG18-AG40 -> 139528 | AH42: =AH18-AH40 -> 142380 | AI42: =AI18-AI40 -> 192773 | AJ42: =AI42 -> 192773 | AK42: =AK18-AK40 -> 195097 | AL42: =AL18-AL40 -> 198137 | AM42: =AM18-AM40 -> 200919 | AN42: =AN18-AN40 -> 205091 | AO42: =AO18-AO40 -> 205091 | AP42: =AP18-AP40 -> 208224 | AQ42: =AQ18-AQ40 -> 211912 | AR42: =AR18-AR40 -> 214725 | ... CW42: =CW18-CW40 -> 1136952.6
AE43: =AD43 -> 0 | AJ43: =AI43 -> 0 | AO43: =AN43 -> 0 | AT43: =AS43 -> 0 | AY43: =AX43 -> 0 | BD43: =BC43 -> 0 | BI43: =BH43 -> 0 | BN43: =BM43 -> 0 | BS43: =BR43 -> 0 | BX43: =BW43 -> 0 | CC43: =CB43 -> 0 | CH43: =CG43 -> 0 | CM43: =CL43 -> 0 | CR43: =CQ43 -> 0 | CW43: =CV43 -> 0
B44: Total Liabilities and Equity | J44: =+J42+J40 -> 19197 | O44: =O42+O40 -> 21919 | Q44: =Q42+Q40 -> 22940 | R44: =R42+R40 -> 54652 | S44: =S42+S40 -> 56227 | T44: =T42+T40 -> 57880 | V44: =V42+V40 -> 59317 | W44: =W42+W40 -> 61215 | X44: =X42+X40 -> 63422 | Y44: =Y42+Y40 -> 77618 | AA44: =AA42+AA40 -> 78996 | AB44: =AB42+AB40 -> 82946 | AC44: =AC42+AC40 -> 156744 | AD44: =AD42+AD40 -> 159201 | AE44: =AD44 -> 159201 | AF44: =AF42+AF40 -> 162779 | AG44: =AG42+AG40 -> 167988 | AH44: =AH42+AH40 -> 173590 | AI44: =AI42+AI40 -> 223330 | AJ44: =AI44 -> 223330 | AK44: =AK42+AK40 -> 226559 | AL44: =AL42+AL40 -> 230172 | AM44: =AM42+AM40 -> 234637 | AN44: =AN42+AN40 -> 243775 | AO44: =AO42+AO40 -> 243775 | AP44: =AP42+AP40 -> 246870 | AQ44: =AQ42+AQ40 -> 249926 | AR44: =AR42+AR40 -> 252877 | ... CW44: =CW42+CW40 -> 1367724.1
B46: DSO | J46: =J8/(IS!J4*4)*365 -> 51.542698 | O46: =O8/(IS!O4*4)*365 -> 43.572538 | Q46: =Q8/(IS!Q4*4)*365 -> 45.65618 | R46: =R8/(IS!R4*4)*365 -> 41.581118 | S46: =S8/(IS!S4*4)*365 -> 43.810482 | T46: =T8/(IS!T4*4)*365 -> 42.673672 | V46: =V8/(IS!V4*4)*365 -> 45.852241 | W46: =W8/(IS!W4*4)*365 -> 48.142445 | X46: =X8/(IS!X4*4)*365 -> 45.216611 | Y46: =Y8/(IS!Y4*4)*365 -> 45.803425 | AA46: =AA8/(IS!AA4*4)*365 -> 44.046586 | AB46: =AB8/(IS!AB4*4)*365 -> 46.231763 | AC46: =AC8/(IS!AC4*4)*365 -> 45.68128 | AD46: =AD8/(IS!AD4*4)*365 -> 44.399351 | AF46: =AF8/(IS!AF4*4)*365 -> 41.445141 | AG46: =AG8/(IS!AG4*4)*365 -> 41.634724 | AH46: =AH8/(IS!AH4*4)*365 -> 37.664951 | AI46: =AI8/(IS!AI4*4)*365 -> 37.875943 | AK46: =AK8/(IS!AK4*4)*365 -> 38.36164 | AL46: =AL8/(IS!AL4*4)*365 -> 39.164148 | AM46: =AM8/(IS!AM4*4)*365 -> 38.160724 | AN46: =AN8/(IS!AN4*4)*365 -> 39.750791 | AP46: =AP8/(IS!AP4*4)*365 -> 39.054605 | AQ46: =AQ8/(IS!AQ4*4)*365 -> 40.532326 | AR46: =AR8/(IS!AR4*4)*365 -> 40.577917 | AS46: =AS8/(IS!AS4*4)*365 -> 37.95619 | AU46: =AU8/(IS!AU4*4)*365 -> 40.875293 | AV46: =AV8/(IS!AV4*4)*365 -> 39.374459 | AW46: =AW8/(IS!AW4*4)*365 -> 39.550184 | AX46: =AX8/(IS!AX4*4)*365 -> 37.074724 | AZ46: =AZ8/(IS!AZ4*4)*365 -> 39.856423 | BA46: =BA8/(IS!BA4*4)*365 -> 36.216588 | BB46: =BB8/(IS!BB4*4)*365 -> 39.287066 | BC46: =BC8/(IS!BC4*4)*365 -> 39.035245 | BE46: =BE8/(IS!BE4*4)*365 -> 40.06896 | BF46: =BF8/(IS!BF4*4)*365 -> 42.078273 | BG46: =BG8/(IS!BG4*4)*365 -> 39.608724 | BH46: =BH8/(IS!BH4*4)*365 -> 38.477044 | BJ46: =BJ8/(IS!BJ4*4)*365 -> 38.582279 | BK46: =BK8/(IS!BK4*4)*365 -> 40.941262 | BL46: =BL8/(IS!BL4*4)*365 -> 37.801697 | BM46: =BM8/(IS!BM4*4)*365 -> 39.559691 | BO46: =BO8/(IS!BO4*4)*365 -> 40.925487 | BP46: =BP8/(IS!BP4*4)*365 -> 45.689598 | BQ46: =BQ8/(IS!BQ4*4)*365 -> 39.052252 | BR46: =BR8/(IS!BR4*4)*365 -> 36.779091 | BT46: =BT8/(IS!BT4*4)*365 -> 35.722551 | BU46: =BU8/(IS!BU4*4)*365 -> 36.616211 | BV46: =BV8/(IS!BV4*4)*365 -> 32.934532 | BW46: =BW8/(IS!BW4*4)*365 -> 30.691955 | BY46: =BY8/(IS!BY4*4)*365 -> 33.638099 | BZ46: =BZ8/(IS!BZ4*4)*365 -> 33.519402 | CA46: =CA8/(IS!CA4*4)*365 -> 29.320736 | CB46: =CB8/(IS!CB4*4)*365 -> 29.491089 | CD46: =CD8/(IS!CD4*4)*365 -> 31.490341 | CE46: =CE8/(IS!CE4*4)*365 -> 31.480186 | CF46: =CF8/(IS!CF4*4)*365 -> 30.363304 | CG46: =CG8/(IS!CG4*4)*365 -> 29.484013 | CI46: =CI8/(IS!CI4*4)*365 -> 31.805361 | CJ46: =CJ8/(IS!CJ4*4)*365 -> 32.910859 | CK46: =CK8/(IS!CK4*4)*365 -> 30.978596 | CL46: =CL8/(IS!CL4*4)*365 -> 27.782325 | CN46: =CN8/(IS!CN4*4)*365 -> 31.861026 | CO46: =CO8/(IS!CO4*4)*365 -> 32.873372 | CP46: =CP8/(IS!CP4*4)*365 -> 32.40484 | CQ46: =CQ8/(IS!CQ4*4)*365 -> 32.28696 | CS46: =CS8/(IS!CS4*4)*365 -> 30.1125 | CT46: =CT8/(IS!CT4*4)*365 -> 30.1125 | CU46: =CU8/(IS!CU4*4)*365 -> 30.1125 | CV46: =CV8/(IS!CV4*4)*365 -> 30.1125
C48: Deferred Revs | O48: =+O33+O28 -> 7432 | Q48: =+Q33+Q28 -> 7751 | R48: =+R33+R28 -> 8021 | S48: =+S33+S28 -> 8298 | T48: =+T33+T28 -> 8587 | V48: =+V33+V28 -> 8851 | W48: =+W33+W28 -> 9195 | X48: =+X33+X28 -> 9910 | Y48: =+Y33+Y28 -> 10439 | AA48: =+AA33+AA28 -> 11371 | AB48: =+AB33+AB28 -> 12239 | AC48: =+AC33+AC28 -> 13265 | AD48: =+AD33+AD28 -> 13811 | AF48: =+AF33+AF28 -> 14166 | AG48: =+AG33+AG28 -> 14860 | AH48: =+AH33+AH28 -> 15217 | AI48: =+AI33+AI28 -> 15120 | AK48: =+AK33+AK28 -> 15694 | AL48: =+AL33+AL28 -> 16929 | AM48: =+AM33+AM28 -> 17198 | AN48: =+AN33+AN28 -> 18158 | AP48: =+AP33+AP28 -> 18080 | AQ48: =+AQ33+AQ28 -> 18829 | AR48: =+AR33+AR28 -> 19773 | AS48: =+AS33+AS28 -> 18745 | AU48: =+AU33+AU28 -> 22210 | AV48: =+AV33+AV28 -> 23517 | AW48: =+AW33+AW28 -> 23119 | AX48: =+AX33+AX28 -> 21902 | AZ48: =+AZ33+AZ28 -> 26890 | BA48: =+BA33+BA28 -> 27674 | BB48: =+BB33+BB28 -> 26834 | BC48: =+BC33+BC28 -> 27009 | BE48: =+BE33+BE28 -> 24274 | BF48: =+BF33+BF28 -> 26831 | BG48: =+BG33+BG28 -> 27633 | BH48: =+BH33+BH28 -> 27840 | BJ48: =+BJ33+BJ28 -> 31538 | BK48: =+BK33+BK28 -> 33090 | BL48: =+BL33+BL28 -> 32952 | BM48: =+BM33+BM28 -> 34314 | BO48: =+BO33+BO28 -> 37710 | BP48: =+BP33+BP28 -> 39019 | BQ48: =+BQ33+BQ28 -> 38275 | BR48: =+BR33+BR28 -> 40943 | BT48: =+BT33+BT28 -> 48508 | BU48: =+BU33+BU28 -> 53472 | BV48: =+BV33+BV28 -> 54344 | BW48: =+BW33+BW28 -> 55572 | BY48: =+BY33+BY28 -> 61921 | BZ48: =+BZ33+BZ28 -> 64374 | CA48: =+CA33+CA28 -> 64095 | CB48: =+CB33+CB28 -> 62194 | CD48: =+CD33+CD28 -> 68012 | CE48: =+CE33+CE28 -> 72105 | CF48: =+CF33+CF28 -> 78702 | CG48: =+CG33+CG28 -> 76117 | CI48: =+CI33+CI28 -> 80174 | CJ48: =+CJ33+CJ28 -> 83504 | CK48: =+CK33+CK28 -> 85433 | CL48: =+CL33+CL28 -> 80445 | CN48: =+CN33+CN28 -> 84368 | CO48: =+CO33+CO28 -> 84675 | CP48: =+CP33+CP28 -> 82716 | CQ48: =+CQ33+CQ28 -> 80878 | CS48: =+CS33+CS28 -> 99677.491 | CT48: =+CT33+CT28 -> 102160.37 | CU48: =+CU33+CU28 -> 105453.5 | CV48: =+CV33+CV28 -> 107191.76
C49: q/q change | Q49: =Q48/O48-1 -> 0.042922497 | R49: =R48/Q48-1 -> 0.034834215 | S49: =S48/R48-1 -> 0.034534347 | T49: =T48/S48-1 -> 0.034827669 | V49: =V48/T48-1 -> 0.030744148 | W49: =W48/V48-1 -> 0.038865665 | X49: =X48/W48-1 -> 0.077759652 | Y49: =Y48/X48-1 -> 0.053380424 | AA49: =AA48/Y48-1 -> 0.089280582 | AB49: =AB48/AA48-1 -> 0.076334535 | AC49: =AC48/AB48-1 -> 0.083830378 | AD49: =AD48/AC48-1 -> 0.04116095 | AF49: =AF48/AD48-1 -> 0.025704149 | AG49: =AG48/AF48-1 -> 0.048990541 | AH49: =AH48/AG48-1 -> 0.024024226 | AI49: =AI48/AH48-1 -> -0.0063744496 | AK49: =AK48/AI48-1 -> 0.037962963 | AL49: =AL48/AK48-1 -> 0.078692494 | AM49: =AM48/AL48-1 -> 0.015889893 | AN49: =AN48/AM48-1 -> 0.055820444 | AP49: =AP48/AN48-1 -> -0.0042956273 | AQ49: =AQ48/AP48-1 -> 0.041426991 | AR49: =AR48/AQ48-1 -> 0.050135429 | AS49: =AS48/AR48-1 -> -0.051990087 | AU49: =AU48/AS48-1 -> 0.18484929 | AV49: =AV48/AU48-1 -> 0.058847366 | AW49: =AW48/AV48-1 -> -0.016923927 | AX49: =AX48/AW48-1 -> -0.052640685 | AZ49: =AZ48/AX48-1 -> 0.22774176 | BA49: =BA48/AZ48-1 -> 0.02915582 | BB49: =BB48/BA48-1 -> -0.0303534 | BC49: =BC48/BB48-1 -> 0.0065215771 | BE49: =BE48/BC48-1 -> -0.10126254 | BF49: =BF48/BE48-1 -> 0.10533905 | BG49: =BG48/BF48-1 -> 0.029890798 | BH49: =BH48/BG48-1 -> 0.0074910433 | BJ49: =BJ48/BH48-1 -> 0.13283046 | BK49: =BK48/BJ48-1 -> 0.049210476 | BL49: =BL48/BK48-1 -> -0.0041704442 | BM49: =BM48/BL48-1 -> 0.041332848 | BO49: =BO48/BM48-1 -> 0.098968351 | BP49: =BP48/BO48-1 -> 0.034712278 | BQ49: =BQ48/BP48-1 -> -0.019067634 | BR49: =BR48/BQ48-1 -> 0.069706074 | BT49: =BT48/BR48-1 -> 0.18476907 | BU49: =BU48/BT48-1 -> 0.10233364 | BV49: =BV48/BU48-1 -> 0.0163076 | BW49: =BW48/BV48-1 -> 0.022596791 | BY49: =BY48/BW48-1 -> 0.11424818 | BZ49: =BZ48/BY48-1 -> 0.039614993 | CA49: =CA48/BZ48-1 -> -0.0043340479 | CB49: =CB48/CA48-1 -> -0.0296591 | CD49: =CD48/CB48-1 -> 0.093546001 | CE49: =CE48/CD48-1 -> 0.060180556 | CF49: =CF48/CE48-1 -> 0.091491575 | CG49: =CG48/CF48-1 -> -0.032845417 | CI49: =CI48/CG48-1 -> 0.053299526 | CJ49: =CJ48/CI48-1 -> 0.041534662 | CK49: =CK48/CJ48-1 -> 0.02310069 | CL49: =CL48/CK48-1 -> -0.058384933 | CN49: =CN48/CL48-1 -> 0.048766238 | CO49: =CO48/CN48-1 -> 0.0036388204 | CP49: =CP48/CO48-1 -> -0.023135518 | CQ49: =CQ48/CP48-1 -> -0.02222061 | CS49: =CS48/CQ48-1 -> 0.23244258 | CT49: =CT48/CS48-1 -> 0.024909151 | CU49: =CU48/CT48-1 -> 0.032234883 | CV49: =CV48/CU48-1 -> 0.01648369
C50: Y/Y change | V50: =V48/Q48-1 -> 0.14191717 | W50: =W48/R48-1 -> 0.14636579 | X50: =X48/S48-1 -> 0.19426368 | Y50: =Y48/T48-1 -> 0.21567486 | AA50: =AA48/V48-1 -> 0.28471359 | AB50: =AB48/W48-1 -> 0.33104948 | AC50: =AC48/X48-1 -> 0.33854692 | AD50: =AD48/Y48-1 -> 0.32301945 | AF50: =AF48/AA48-1 -> 0.24580072 | AG50: =AG48/AB48-1 -> 0.21415148 | AH50: =AH48/AC48-1 -> 0.14715417 | AI50: =AI48/AD48-1 -> 0.094779524 | AK50: =AK48/AF48-1 -> 0.1078639 | AL50: =AL48/AG48-1 -> 0.13923284 | AM50: =AM48/AH48-1 -> 0.13018335 | AN50: =AN48/AI48-1 -> 0.20092593 | AP50: =AP48/AK48-1 -> 0.15203262 | AQ50: =AQ48/AL48-1 -> 0.11223345 | AR50: =AR48/AM48-1 -> 0.14972671 | AS50: =AS48/AN48-1 -> 0.032327349 | AU50: =AU48/AP48-1 -> 0.2284292 | AV50: =AV48/AQ48-1 -> 0.24897764 | AW50: =AW48/AR48-1 -> 0.16922065 | AX50: =AX48/AS48-1 -> 0.16841824 | AZ50: =AZ48/AU48-1 -> 0.21071589 | BA50: =BA48/AV48-1 -> 0.17676574 | BB50: =BB48/AW48-1 -> 0.16069034 | BC50: =BC48/AX48-1 -> 0.23317505 | BE50: =BE48/AZ48-1 -> -0.097285236 | BF50: =BF48/BA48-1 -> -0.030461805 | BG50: =BG48/BB48-1 -> 0.029775658 | BH50: =BH48/BC48-1 -> 0.030767522 | BJ50: =BJ48/BE48-1 -> 0.29925023 | BK50: =BK48/BF48-1 -> 0.23327494 | BL50: =BL48/BG48-1 -> 0.19248724 | BM50: =BM48/BH48-1 -> 0.2325431 | BO50: =BO48/BJ48-1 -> 0.19570042 | BP50: =BP48/BK48-1 -> 0.179178 | BQ50: =BQ48/BL48-1 -> 0.16153799 | BR50: =BR48/BM48-1 -> 0.19318645 | BT50: =BT48/BO48-1 -> 0.28634315 | BU50: =BU48/BP48-1 -> 0.37040929 | BV50: =BV48/BQ48-1 -> 0.41983018 | BW50: =BW48/BR48-1 -> 0.35730161 | BY50: =BY48/BT48-1 -> 0.27651109 | BZ50: =BZ48/BU48-1 -> 0.20388241 | CA50: =CA48/BV48-1 -> 0.17943103 | CB50: =CB48/BW48-1 -> 0.11916073 | CD50: =CD48/BY48-1 -> 0.098367274 | CE50: =CE48/BZ48-1 -> 0.12009507 | CF50: =CF48/CA48-1 -> 0.22789609 | CG50: =CG48/CB48-1 -> 0.22386404 | CI50: =CI48/CD48-1 -> 0.17882138 | CJ50: =CJ48/CE48-1 -> 0.1580889 | CK50: =CK48/CF48-1 -> 0.085525145 | CL50: =CL48/CG48-1 -> 0.056859834 | CN50: =CN48/CI48-1 -> 0.052311223 | CO50: =CO48/CJ48-1 -> 0.01402328 | CP50: =CP48/CK48-1 -> -0.031802699 | CQ50: =CQ48/CL48-1 -> 0.0053825595 | CS50: =CS48/CN48-1 -> 0.18146088 | CT50: =CT48/CO48-1 -> 0.20649983 | CU50: =CU48/CP48-1 -> 0.27488636 | CV50: =CV48/CQ48-1 -> 0.32535131
C52: LT Def Revs y/y | V52: =V33/Q33-1 -> 0.27513228 | W52: =W33/R33-1 -> 0.26032772 | X52: =X33/S33-1 -> 0.3200692 | Y52: =Y33/T33-1 -> 0.31927229 | AA52: =AA33/V33-1 -> 0.37570728 | AB52: =AB33/W33-1 -> 0.44167735 | AC52: =AC33/X33-1 -> 0.31110747 | AD52: =AD33/Y33-1 -> 0.25958479 | AF52: =AF33/AA33-1 -> 0.14326844 | AG52: =AG33/AB33-1 -> 0.10326432 | AH52: =AH33/AC33-1 -> 0.095214295 | AI52: =AI33/AD33-1 -> 0.056905679 | AK52: =AK33/AF33-1 -> 0.10336971 | AL52: =AL33/AG33-1 -> 0.15323509 | AM52: =AM33/AH33-1 -> 0.16794067 | AN52: =AN33/AI33-1 -> 0.21263517 | AP52: =AP33/AK33-1 -> 0.1466145 | AQ52: =AQ33/AL33-1 -> 0.097733852 | AR52: =AR33/AM33-1 -> 0.14301065 | AS52: =AS33/AN33-1 -> 0.033042335 | AU52: =AU33/AP33-1 -> 0.030900474 | AV52: =AV33/AQ33-1 -> 0.021826119 | AW52: =AW33/AR33-1 -> -0.063156995 | AX52: =AX33/AS33-1 -> -0.01435711 | AZ52: =AZ33/AU33-1 -> 0.019400515 | BA52: =BA33/AV33-1 -> -0.016553934 | BB52: =BB33/AW33-1 -> -0.030742565 | BC52: =BC33/AX33-1 -> -0.02258689 | BE52: =BE33/AZ33-1 -> -0.7572833 | BF52: =BF33/BA33-1 -> -0.76108597 | BG52: =BG33/BB33-1 -> -0.74729412 | BH52: =BH33/BC33-1 -> -0.76306357 | BJ52: =BJ33/BE33-1 -> -0.015607581 | BK52: =BK33/BF33-1 -> 0.028030303 | BL52: =BL33/BG33-1 -> -0.031284916 | BM52: =BM33/BH33-1 -> 0.13495223 | BO52: =BO33/BJ33-1 -> 0.049830125 | BP52: =BP33/BK33-1 -> 0.011790715 | BQ52: =BQ33/BL33-1 -> 0.035371011 | BR52: =BR33/BM33-1 -> 0.050859348 | BT52: =BT33/BO33-1 -> 0.44804027 | BU52: =BU33/BP33-1 -> 0.8175528 | BV52: =BV33/BQ33-1 -> 0.91570739 | BW52: =BW33/BR33-1 -> 0.71695594 | BY52: =BY33/BT33-1 -> 0.2721629 | BZ52: =BZ33/BU33-1 -> 0.058104588 | CA52: =CA33/BV33-1 -> -0.0025198682 | CB52: =CB33/BW33-1 -> -0.072511664 | CD52: =CD33/BY33-1 -> -0.0035135663 | CE52: =CE33/BZ33-1 -> 0.083885628 | CF52: =CF33/CA33-1 -> 0.33093665 | CG52: =CG33/CB33-1 -> 0.45252568 | CI52: =CI33/CD33-1 -> 0.26797258 | CJ52: =CJ33/CE33-1 -> 0.24231307 | CK52: =CK33/CF33-1 -> -0.043656008 | CL52: =CL33/CG33-1 -> -0.10692641 | CN52: =CN33/CI33-1 -> -0.11200371 | CO52: =CO33/CJ33-1 -> -0.22978484 | CP52: =CP33/CK33-1 -> -0.21374046 | CQ52: =CQ33/CL33-1 -> -0.14558087 | CS52: =CS33/CN33-1 -> -0.080027836 | CT52: =CT33/CO33-1 -> -0.034507942 | CU52: =CU33/CP33-1 -> 0.026796117 | CV52: =CV33/CQ33-1 -> 0
C53: q/q | V53: =V33/T33-1 -> 0.05997601 | W53: =W33/V33-1 -> 0.029988684 | X53: =X33/W33-1 -> 0.117744 | Y53: =Y33/X33-1 -> 0.081094364 | AA53: =AA33/Y33-1 -> 0.10531899 | AB53: =AB33/AA33-1 -> 0.079380313 | AC53: =AC33/AB33-1 -> 0.01651213 | AD53: =AD33/AC33-1 -> 0.038610521 | AF53: =AF33/AD33-1 -> 0.0032483157 | AG53: =AG33/AF33-1 -> 0.041611704 | AH53: =AH33/AG33-1 -> 0.0090950956 | AI53: =AI33/AH33-1 -> 0.0022818026 | AK53: =AK33/AI33-1 -> 0.047353443 | AL53: =AL33/AK33-1 -> 0.088686012 | AM53: =AM33/AL33-1 -> 0.021962663 | AN53: =AN33/AM33-1 -> 0.040636905 | AP53: =AP33/AN33-1 -> -0.0096686379 | AQ53: =AQ33/AP33-1 -> 0.042274882 | AR53: =AR33/AQ33-1 -> 0.064114223 | AS53: =AS33/AR33-1 -> -0.059482096 | AU53: =AU33/AS33-1 -> -0.011721945 | AV53: =AV33/AU33-1 -> 0.033100405 | AW53: =AW33/AV33-1 -> -0.024385902 | AX53: =AX33/AW33-1 -> -0.010490786 | AZ53: =AZ33/AX33-1 -> 0.022125933 | BA53: =BA33/AZ33-1 -> -0.0033372418 | BB53: =BB33/BA33-1 -> -0.038461538 | BC53: =BC33/BB33-1 -> -0.0021647059 | BE53: =BE33/BC33-1 -> -0.74617997 | BF53: =BF33/BE33-1 -> -0.018952062 | BG53: =BG33/BF33-1 -> 0.017045455 | BH53: =BH33/BG33-1 -> -0.06443203 | BJ53: =BJ33/BH33-1 -> 0.054538217 | BK53: =BK33/BJ33-1 -> 0.024537561 | BL53: =BL33/BK33-1 -> -0.041635962 | BM53: =BM33/BL33-1 -> 0.096116878 | BO53: =BO33/BM33-1 -> -0.024552788 | BP53: =BP33/BO33-1 -> -0.012585401 | BQ53: =BQ33/BP33-1 -> -0.019300801 | BR53: =BR33/BQ33-1 -> 0.11251392 | BT53: =BT33/BR33-1 -> 0.3441255 | BU53: =BU33/BT33-1 -> 0.23938416 | BV53: =BV33/BU33-1 -> 0.033660589 | BW53: =BW33/BV33-1 -> -0.0029075402 | BY53: =BY33/BW33-1 -> -0.0040824261 | BZ53: =BZ33/BY33-1 -> 0.030841304 | CA53: =CA33/BZ33-1 -> -0.02556334 | CB53: =CB33/CA33-1 -> -0.072872134 | CD53: =CD33/CC33-1 -> 0.070006288 | CE53: =CE33/CD33-1 -> 0.12125367 | CF53: =CF33/CE33-1 -> 0.19654088 | CG53: =CG33/CF33-1 -> 0.011826544 | CI53: =CI33/CH33-1 -> -0.065945166 | CJ53: =CJ33/CI33-1 -> 0.098563263 | CK53: =CK33/CJ33-1 -> -0.078891858 | CL53: =CL33/CK33-1 -> -0.055114504 | CN53: =CN33/CM33-1 -> -0.071255453 | CO53: =CO33/CN33-1 -> -0.047146834 | CP53: =CP33/CO33-1 -> -0.059704218 | CQ53: =CQ33/CP33-1 -> 0.026796117 | CS53: =CS33/CR33-1 -> 0 | CT53: =CT33/CS33-1 -> 0 | CU53: =CU33/CT33-1 -> 0 | CV53: =CV33/CU33-1 -> 0
C55: AR as a % of Rev | J55: =J8/IS!J4 -> 0.56485149 | O55: =O8/IS!O4 -> 0.47750726 | Q55: =Q8/IS!Q4 -> 0.5003417 | R55: =R8/IS!R4 -> 0.45568348 | S55: =S8/IS!S4 -> 0.48011487 | T55: =T8/IS!T4 -> 0.46765668 | V55: =V8/IS!V4 -> 0.50249032 | W55: =W8/IS!W4 -> 0.52758843 | X55: =X8/IS!X4 -> 0.4955245 | Y55: =Y8/IS!Y4 -> 0.50195534 | AA55: =AA8/IS!AA4 -> 0.48270231 | AB55: =AB8/IS!AB4 -> 0.50664946 | AC55: =AC8/IS!AC4 -> 0.50061677 | AD55: =AD8/IS!AD4 -> 0.48656823 | AF55: =AF8/IS!AF4 -> 0.45419333 | AG55: =AG8/IS!AG4 -> 0.45627095 | AH55: =AH8/IS!AH4 -> 0.41276659 | AI55: =AI8/IS!AI4 -> 0.41507883 | AK55: =AK8/IS!AK4 -> 0.42040153 | AL55: =AL8/IS!AL4 -> 0.42919614 | AM55: =AM8/IS!AM4 -> 0.41819972 | AN55: =AN8/IS!AN4 -> 0.43562511 | AP55: =AP8/IS!AP4 -> 0.42799567 | AQ55: =AQ8/IS!AQ4 -> 0.44418988 | AR55: =AR8/IS!AR4 -> 0.4446895 | AS55: =AS8/IS!AS4 -> 0.41595825 | AU55: =AU8/IS!AU4 -> 0.44794842 | AV55: =AV8/IS!AV4 -> 0.43150092 | AW55: =AW8/IS!AW4 -> 0.43342667 | AX55: =AX8/IS!AX4 -> 0.40629835 | AZ55: =AZ8/IS!AZ4 -> 0.43678272 | BA55: =BA8/IS!BA4 -> 0.39689411 | BB55: =BB8/IS!BB4 -> 0.43054319 | BC55: =BC8/IS!BC4 -> 0.42778351 | BE55: =BE8/IS!BE4 -> 0.43911189 | BF55: =BF8/IS!BF4 -> 0.46113175 | BG55: =BG8/IS!BG4 -> 0.43406821 | BH55: =BH8/IS!BH4 -> 0.42166623 | BJ55: =BJ8/IS!BJ4 -> 0.42281949 | BK55: =BK8/IS!BK4 -> 0.44867137 | BL55: =BL8/IS!BL4 -> 0.41426517 | BM55: =BM8/IS!BM4 -> 0.43353086 | BO55: =BO8/IS!BO4 -> 0.44849849 | BP55: =BP8/IS!BP4 -> 0.50070792 | BQ55: =BQ8/IS!BQ4 -> 0.42796988 | BR55: =BR8/IS!BR4 -> 0.40305853 | BT55: =BT8/IS!BT4 -> 0.39148001 | BU55: =BU8/IS!BU4 -> 0.40127355 | BV55: =BV8/IS!BV4 -> 0.36092637 | BW55: =BW8/IS!BW4 -> 0.33635019 | BY55: =BY8/IS!BY4 -> 0.3686367 | BZ55: =BZ8/IS!BZ4 -> 0.36733591 | CA55: =CA8/IS!CA4 -> 0.32132313 | CB55: =CB8/IS!CB4 -> 0.32319002 | CD55: =CD8/IS!CD4 -> 0.34509963 | CE55: =CE8/IS!CE4 -> 0.34498834 | CF55: =CF8/IS!CF4 -> 0.33274854 | CG55: =CG8/IS!CG4 -> 0.32311248 | CI55: =CI8/IS!CI4 -> 0.34855191 | CJ55: =CJ8/IS!CJ4 -> 0.36066694 | CK55: =CK8/IS!CK4 -> 0.33949147 | CL55: =CL8/IS!CL4 -> 0.30446383 | CN55: =CN8/IS!CN4 -> 0.34916193 | CO55: =CO8/IS!CO4 -> 0.36025614 | CP55: 0.33 | CQ55: =CQ8/IS!CQ4 -> 0.3538297 | CS55: 0.33 | CT55: 0.33 | CU55: 0.33 | CV55: 0.33
C56: Deferred Costs of a % of Rev | J56: =J9/IS!J4 -> 0.50222772 | O56: =O9/IS!O4 -> 0.41338543 | Q56: =Q9/IS!Q4 -> 0.41579615 | R56: =R9/IS!R4 -> 0.41748904 | S56: =S9/IS!S4 -> 0.39865982 | T56: =T9/IS!T4 -> 0.39600638 | V56: =V9/IS!V4 -> 0.38635465 | W56: =W9/IS!W4 -> 0.37145727 | X56: =X9/IS!X4 -> 0.35327452 | Y56: =Y9/IS!Y4 -> 0.36255834 | AA56: =AA9/IS!AA4 -> 0.36802951 | AB56: =AB9/IS!AB4 -> 0.36524325 | AC56: =AC9/IS!AC4 -> 0.34060295 | AD56: =AD9/IS!AD4 -> 0.32672122 | AF56: =AF9/IS!AF4 -> 0.3309195 | AG56: =AG9/IS!AG4 -> 0.32301816 | AH56: =AH9/IS!AH4 -> 0.32208975 | AI56: =AI9/IS!AI4 -> 0.32345476 | AK56: =AK9/IS!AK4 -> 0.32962438 | AL56: =AL9/IS!AL4 -> 0.33488746 | AM56: =AM9/IS!AM4 -> 0.34245985 | AN56: =AN9/IS!AN4 -> 0.34051748 | AP56: =AP9/IS!AP4 -> 0.3492291 | AQ56: =AQ9/IS!AQ4 -> 0.36047469 | AR56: =AR9/IS!AR4 -> 0.36578778 | AS56: =AS9/IS!AS4 -> 0.35623878 | AU56: =AU9/IS!AU4 -> 0.3464769 | AV56: =AV9/IS!AV4 -> 0.36489198 | AW56: =AW9/IS!AW4 -> 0.37835809 | AX56: =AX9/IS!AX4 -> 0.37649086 | AZ56: =AZ9/IS!AZ4 -> 0.4026034 | BA56: =BA9/IS!BA4 -> 0.40374696 | BB56: =BB9/IS!BB4 -> 0.41542297 | BC56: =BC9/IS!BC4 -> 0.43111684 | BE56: =BE9/IS!BE4 -> 0.52998714 | BF56: =BF9/IS!BF4 -> 0.52734445 | BG56: =BG9/IS!BG4 -> 0.52704078 | BH56: =BH9/IS!BH4 -> 0.52926107 | BJ56: =BJ9/IS!BJ4 -> 0.51830161 | BK56: =BK9/IS!BK4 -> 0.51200222 | BL56: =BL9/IS!BL4 -> 0.48757895 | BM56: =BM9/IS!BM4 -> 0.48497931 | BO56: =BO9/IS!BO4 -> 0.47906782 | BP56: =BP9/IS!BP4 -> 0.47367446 | BQ56: =BQ9/IS!BQ4 -> 0.45956987 | BR56: =BR9/IS!BR4 -> 0.45016085 | BT56: =BT9/IS!BT4 -> 0.42917397 | BU56: =BU9/IS!BU4 -> 0.42468188 | BV56: =BV9/IS!BV4 -> 0.42490831 | BW56: =BW9/IS!BW4 -> 0.43334696 | BY56: =BY9/IS!BY4 -> 0.44404095 | BZ56: =BZ9/IS!BZ4 -> 0.44234186 | CA56: =CA9/IS!CA4 -> 0.43745087 | CB56: =CB9/IS!CB4 -> 0.43235424 | CD56: =CD9/IS!CD4 -> 0.42778149 | CE56: =CE9/IS!CE4 -> 0.43131211 | CF56: =CF9/IS!CF4 -> 0.43877754 | CG56: =CG9/IS!CG4 -> 0.43046942 | CI56: =CI9/IS!CI4 -> 0.42551613 | CJ56: =CJ9/IS!CJ4 -> 0.41874788 | CK56: =CK9/IS!CK4 -> 0.39505517 | CL56: =CL9/IS!CL4 -> 0.38232489 | CN56: =CN9/IS!CN4 -> 0.36963575 | CO56: =CO9/IS!CO4 -> 0.3565048 | CP56: 0.39 | CQ56: =CQ9/IS!CQ4 -> 0.34618379 | CS56: 0.39 | CT56: 0.39 | CU56: 0.39 | CV56: 0.39
C57: Prepaid expenses as a % of Rev | J57: =J10/IS!J4 -> 0.097153465 | O57: =O10/IS!O4 -> 0.14427412 | Q57: =Q10/IS!Q4 -> 0.19652446 | R57: =R10/IS!R4 -> 0.087445175 | S57: =S10/IS!S4 -> 0.086241406 | T57: =T10/IS!T4 -> 0.073328299 | V57: =V10/IS!V4 -> 0.097557119 | W57: =W10/IS!W4 -> 0.11221927 | X57: =X10/IS!X4 -> 0.079399833 | Y57: =Y10/IS!Y4 -> 0.16071654 | AA57: =AA10/IS!AA4 -> 0.16196928 | AB57: =AB10/IS!AB4 -> 0.13388699 | AC57: =AC10/IS!AC4 -> 0.15690531 | AD57: =AD10/IS!AD4 -> 0.31911582 | AF57: =AF10/IS!AF4 -> 0.18714214 | AG57: =AG10/IS!AG4 -> 0.18310079 | AH57: =AH10/IS!AH4 -> 0.16957938 | AI57: =AI10/IS!AI4 -> 0.14735638 | AK57: =AK10/IS!AK4 -> 0.1406061 | AL57: =AL10/IS!AL4 -> 0.14848875 | AM57: =AM10/IS!AM4 -> 0.15677106 | AN57: =AN10/IS!AN4 -> 0.1107847 | AP57: =AP10/IS!AP4 -> 0.10476062 | AQ57: =AQ10/IS!AQ4 -> 0.16652937 | AR57: =AR10/IS!AR4 -> 0.1428359 | AS57: =AS10/IS!AS4 -> 0.11877775 | AU57: =AU10/IS!AU4 -> 0.12125266 | AV57: =AV10/IS!AV4 -> 0.15923634 | AW57: =AW10/IS!AW4 -> 0.14858778 | AX57: =AX10/IS!AX4 -> 0.13728677 | AZ57: =AZ10/IS!AZ4 -> 0.1346376 | BA57: =BA10/IS!BA4 -> 0.12812247 | BB57: =BB10/IS!BB4 -> 0.10423865 | BC57: =BC10/IS!BC4 -> 0.10565292 | BE57: =BE10/IS!BE4 -> 0.096392067 | BF57: =BF10/IS!BF4 -> 0.11068734 | BG57: =BG10/IS!BG4 -> 0.10518865 | BH57: =BH10/IS!BH4 -> 0.14157296 | BJ57: =BJ10/IS!BJ4 -> 0.13233932 | BK57: =BK10/IS!BK4 -> 0.12060587 | BL57: =BL10/IS!BL4 -> 0.11821848 | BM57: =BM10/IS!BM4 -> 0.15507404 | BO57: =BO10/IS!BO4 -> 0.087313996 | BP57: =BP10/IS!BP4 -> 0.062390007 | BQ57: =BQ10/IS!BQ4 -> 0.064959714 | BR57: =BR10/IS!BR4 -> 0.14778893 | BT57: =BT10/IS!BT4 -> 0.16083202 | BU57: =BU10/IS!BU4 -> 0.1238748 | BV57: =BV10/IS!BV4 -> 0.14655674 | BW57: =BW10/IS!BW4 -> 0.1561174 | BY57: =BY10/IS!BY4 -> 0.21791374 | BZ57: =BZ10/IS!BZ4 -> 0.16406236 | CA57: =CA10/IS!CA4 -> 0.13316912 | CB57: =CB10/IS!CB4 -> 0.13374256 | CD57: =CD10/IS!CD4 -> 0.12434455 | CE57: =CE10/IS!CE4 -> 0.1039443 | CF57: =CF10/IS!CF4 -> 0.11604662 | CG57: =CG10/IS!CG4 -> 0.11560032 | CI57: =CI10/IS!CI4 -> 0.091558806 | CJ57: =CJ10/IS!CJ4 -> 0.10050392 | CK57: =CK10/IS!CK4 -> 0.11387046 | CL57: =CL10/IS!CL4 -> 0.13757775 | CN57: =CN10/IS!CN4 -> 0.14550893 | CO57: =CO10/IS!CO4 -> 0.14649413 | CP57: 0.1 | CQ57: =CQ10/IS!CQ4 -> 0.25481178 | CS57: 0.1 | CT57: 0.1 | CU57: 0.1 | CV57: 0.1
C59: AP as a % of Rev | J59: =J24/IS!J4 -> 0.09950495 | O59: =O24/IS!O4 -> 0.13475604 | Q59: =Q24/IS!Q4 -> 0.1179342 | R59: =R24/IS!R4 -> 0.089820906 | S59: =S24/IS!S4 -> 0.092072056 | T59: =T24/IS!T4 -> 0.083731857 | V59: =V24/IS!V4 -> 0.124832 | W59: =W24/IS!W4 -> 0.1306594 | X59: =X24/IS!X4 -> 0.089316762 | Y59: =Y24/IS!Y4 -> 0.088999622 | AA59: =AA24/IS!AA4 -> 0.074996976 | AB59: =AB24/IS!AB4 -> 0.10908479 | AC59: =AC24/IS!AC4 -> 0.1351458 | AD59: =AD24/IS!AD4 -> 0.082592065 | AF59: =AF24/IS!AF4 -> 0.085634894 | AG59: =AG24/IS!AG4 -> 0.064307428 | AH59: =AH24/IS!AH4 -> 0.062388922 | AI59: =AI24/IS!AI4 -> 0.064276266 | AK59: =AK24/IS!AK4 -> 0.077507861 | AL59: =AL24/IS!AL4 -> 0.096430868 | AM59: =AM24/IS!AM4 -> 0.064541931 | AN59: =AN24/IS!AN4 -> 0.11188633 | AP59: =AP24/IS!AP4 -> 0.093156613 | AQ59: =AQ24/IS!AQ4 -> 0.095402358 | AR59: =AR24/IS!AR4 -> 0.059002825 | AS59: =AS24/IS!AS4 -> 0.051076792 | AU59: =AU24/IS!AU4 -> 0.085528191 | AV59: =AV24/IS!AV4 -> 0.075626703 | AW59: =AW24/IS!AW4 -> 0.04954955 | AX59: =AX24/IS!AX4 -> 0.045083332 | AZ59: =AZ24/IS!AZ4 -> 0.068936301 | BA59: =BA24/IS!BA4 -> 0.050106845 | BB59: =BB24/IS!BB4 -> 0.055013357 | BC59: =BC24/IS!BC4 -> 0.076683849 | BE59: =BE24/IS!BE4 -> 0.058755838 | BF59: =BF24/IS!BF4 -> 0.060712707 | BG59: =BG24/IS!BG4 -> 0.061287141 | BH59: =BH24/IS!BH4 -> 0.06810965 | BJ59: =BJ24/IS!BJ4 -> 0.065601936 | BK59: =BK24/IS!BK4 -> 0.05410848 | BL59: =BL24/IS!BL4 -> 0.061569479 | BM59: =BM24/IS!BM4 -> 0.058762872 | BO59: =BO24/IS!BO4 -> 0.062028251 | BP59: =BP24/IS!BP4 -> 0.056316409 | BQ59: =BQ24/IS!BQ4 -> 0.063300527 | BR59: =BR24/IS!BR4 -> 0.064267537 | BT59: =BT24/IS!BT4 -> 0.056396652 | BU59: =BU24/IS!BU4 -> 0.062852368 | BV59: =BV24/IS!BV4 -> 0.038329911 | BW59: =BW24/IS!BW4 -> 0.081065826 | BY59: =BY24/IS!BY4 -> 0.044974475 | BZ59: =BZ24/IS!BZ4 -> 0.040685852 | CA59: =CA24/IS!CA4 -> 0.071624478 | CB59: =CB24/IS!CB4 -> 0.092248685 | CD59: =CD24/IS!CD4 -> 0.042417453 | CE59: =CE24/IS!CE4 -> 0.047256472 | CF59: =CF24/IS!CF4 -> 0.045665298 | CG59: =CG24/IS!CG4 -> 0.051184769 | CI59: =CI24/IS!CI4 -> 0.0822525 | CJ59: =CJ24/IS!CJ4 -> 0.038262715 | CK59: =CK24/IS!CK4 -> 0.049527754 | CL59: =CL24/IS!CL4 -> 0.050185188 | CN59: =CN24/IS!CN4 -> 0.061994283 | CO59: =CO24/IS!CO4 -> 0.061921025 | CP59: 0.07 | CQ59: =CQ24/IS!CQ4 -> 0.07140855 | CS59: 0.07 | CT59: 0.07 | CU59: 0.07 | CV59: 0.07
C60: Accrued Comp/benefits as a % of Rev | J60: =J25/IS!J4 -> 0.23316832 | O60: =O25/IS!O4 -> 0.30107204 | Q60: =Q25/IS!Q4 -> 0.26037294 | R60: =R25/IS!R4 -> 0.31944444 | S60: =S25/IS!S4 -> 0.32364459 | T60: =T25/IS!T4 -> 0.30010907 | V60: =V25/IS!V4 -> 0.26579176 | W60: =W25/IS!W4 -> 0.27523857 | X60: =X25/IS!X4 -> 0.33414901 | Y60: =Y25/IS!Y4 -> 0.32282074 | AA60: =AA25/IS!AA4 -> 0.27506955 | AB60: =AB25/IS!AB4 -> 0.26968184 | AC60: =AC25/IS!AC4 -> 0.32733014 | AD60: =AD25/IS!AD4 -> 0.26854652 | AF60: =AF25/IS!AF4 -> 0.2819552 | AG60: =AG25/IS!AG4 -> 0.25376101 | AH60: =AH25/IS!AH4 -> 0.31116706 | AI60: =AI25/IS!AI4 -> 0.28531084 | AK60: =AK25/IS!AK4 -> 0.26586959 | AL60: =AL25/IS!AL4 -> 0.24562701 | AM60: =AM25/IS!AM4 -> 0.30898911 | AN60: =AN25/IS!AN4 -> 0.28037964 | AP60: =AP25/IS!AP4 -> 0.27868542 | AQ60: =AQ25/IS!AQ4 -> 0.24373166 | AR60: =AR25/IS!AR4 -> 0.24587401 | AS60: =AS25/IS!AS4 -> 0.26329461 | AU60: =AU25/IS!AU4 -> 0.24853615 | AV60: =AV25/IS!AV4 -> 0.25454584 | AW60: =AW25/IS!AW4 -> 0.23934746 | AX60: =AX25/IS!AX4 -> 0.26908991 | AZ60: =AZ25/IS!AZ4 -> 0.23630902 | BA60: =BA25/IS!BA4 -> 0.2439577 | BB60: =BB25/IS!BB4 -> 0.2258415 | BC60: =BC25/IS!BC4 -> 0.27295533 | BE60: =BE25/IS!BE4 -> 0.19659176 | BF60: =BF25/IS!BF4 -> 0.23484638 | BG60: =BG25/IS!BG4 -> 0.24651651 | BH60: =BH25/IS!BH4 -> 0.31316633 | BJ60: =BJ25/IS!BJ4 -> 0.17889264 | BK60: =BK25/IS!BK4 -> 0.23177049 | BL60: =BL25/IS!BL4 -> 0.24898489 | BM60: =BM25/IS!BM4 -> 0.3066421 | BO60: =BO25/IS!BO4 -> 0.17700022 | BP60: =BP25/IS!BP4 -> 0.22428645 | BQ60: =BQ25/IS!BQ4 -> 0.24352351 | BR60: =BR25/IS!BR4 -> 0.26334806 | BT60: =BT25/IS!BT4 -> 0.22674096 | BU60: =BU25/IS!BU4 -> 0.29055734 | BV60: =BV25/IS!BV4 -> 0.31654867 | BW60: =BW25/IS!BW4 -> 0.30811826 | BY60: =BY25/IS!BY4 -> 0.20847395 | BZ60: =BZ25/IS!BZ4 -> 0.23681511 | CA60: =CA25/IS!CA4 -> 0.25137571 | CB60: =CB25/IS!CB4 -> 0.24779131 | CD60: =CD25/IS!CD4 -> 0.20998983 | CE60: =CE25/IS!CE4 -> 0.21958195 | CF60: =CF25/IS!CF4 -> 0.30571793 | CG60: =CG25/IS!CG4 -> 0.28688304 | CI60: =CI25/IS!CI4 -> 0.22055677 | CJ60: =CJ25/IS!CJ4 -> 0.20987526 | CK60: =CK25/IS!CK4 -> 0.28108696 | CL60: =CL25/IS!CL4 -> 0.27593955 | CN60: =CN25/IS!CN4 -> 0.22444078 | CO60: =CO25/IS!CO4 -> 0.20655283 | CP60: 0.26 | CQ60: =CQ25/IS!CQ4 -> 0.24695825 | CS60: 0.25 | CT60: 0.26 | CU60: 0.26 | CV60: 0.26
C61: Accrued expenses as a % of Rev | J61: =J26/IS!J4 -> 0.070173267 | O61: =O26/IS!O4 -> 0.10730388 | Q61: =Q26/IS!Q4 -> 0.14224348 | R61: =R26/IS!R4 -> 0.081962719 | S61: =S26/IS!S4 -> 0.088852145 | T61: =T26/IS!T4 -> 0.067707022 | V61: =V26/IS!V4 -> 0.074630406 | W61: =W26/IS!W4 -> 0.090406831 | X61: =X26/IS!X4 -> 0.072509498 | Y61: =Y26/IS!Y4 -> 0.069193894 | AA61: =AA26/IS!AA4 -> 0.079291158 | AB61: =AB26/IS!AB4 -> 0.087537175 | AC61: =AC26/IS!AC4 -> 0.062959491 | AD61: =AD26/IS!AD4 -> 0.047900729 | AF61: =AF26/IS!AF4 -> 0.044754126 | AG61: =AG26/IS!AG4 -> 0.13329176 | AH61: =AH26/IS!AH4 -> 0.098674467 | AI61: =AI26/IS!AI4 -> 0.10013227 | AK61: =AK26/IS!AK4 -> 0.10605066 | AL61: =AL26/IS!AL4 -> 0.058038585 | AM61: =AM26/IS!AM4 -> 0.055405156 | AN61: =AN26/IS!AN4 -> 0.08948647 | AP61: =AP26/IS!AP4 -> 0.075628888 | AQ61: =AQ26/IS!AQ4 -> 0.054806158 | AR61: =AR26/IS!AR4 -> 0.057937255 | AS61: =AS26/IS!AS4 -> 0.046920752 | AU61: =AU26/IS!AU4 -> 0.064168074 | AV61: =AV26/IS!AV4 -> 0.082089079 | AW61: =AW26/IS!AW4 -> 0.050909017 | AX61: =AX26/IS!AX4 -> 0.068702141 | AZ61: =AZ26/IS!AZ4 -> 0.085862281 | BA61: =BA26/IS!BA4 -> 0.068583745 | BB61: =BB26/IS!BB4 -> 0.071077471 | BC61: =BC26/IS!BC4 -> 0.080962199 | BE61: =BE26/IS!BE4 -> 0.069569485 | BF61: =BF26/IS!BF4 -> 0.077883813 | BG61: =BG26/IS!BG4 -> 0.063243622 | BH61: =BH26/IS!BH4 -> 0.069919772 | BJ61: =BJ26/IS!BJ4 -> 0.069008277 | BK61: =BK26/IS!BK4 -> 0.072436487 | BL61: =BL26/IS!BL4 -> 0.068717573 | BM61: =BM26/IS!BM4 -> 0.08533953 | BO61: =BO26/IS!BO4 -> 0.072433686 | BP61: =BP26/IS!BP4 -> 0.067047755 | BQ61: =BQ26/IS!BQ4 -> 0.075945548 | BR61: =BR26/IS!BR4 -> 0.13397273 | BT61: =BT26/IS!BT4 -> 0.11119497 | BU61: =BU26/IS!BU4 -> 0.055225886 | BV61: =BV26/IS!BV4 -> 0.072634773 | BW61: =BW26/IS!BW4 -> 0.081211803 | BY61: =BY26/IS!BY4 -> 0.06304602 | BZ61: =BZ26/IS!BZ4 -> 0.068768433 | CA61: =CA26/IS!CA4 -> 0.04543787 | CB61: =CB26/IS!CB4 -> 0.061064761 | CD61: =CD26/IS!CD4 -> 0.064853656 | CE61: =CE26/IS!CE4 -> 0.051481413 | CF61: =CF26/IS!CF4 -> 0.065604706 | CG61: =CG26/IS!CG4 -> 0.05528231 | CI61: =CI26/IS!CI4 -> 0.071829705 | CJ61: =CJ26/IS!CJ4 -> 0.061498997 | CK61: =CK26/IS!CK4 -> 0.054787825 | CL61: =CL26/IS!CL4 -> 0.070845548 | CN61: =CN26/IS!CN4 -> 0.091655696 | CO61: =CO26/IS!CO4 -> 0.067822839 | CP61: 0.07 | CQ61: =CQ26/IS!CQ4 -> 0.067863298 | CS61: 0.07 | CT61: 0.07 | CU61: 0.07 | CV61: 0.07
C62: Current portions of Def. Rev as a % of Rev | J62: =J28/IS!J4 -> 0.31856436 | O62: =O28/IS!O4 -> 0.34134856 | Q62: =Q28/IS!Q4 -> 0.35077614 | R62: =R28/IS!R4 -> 0.3369883 | S62: =S28/IS!S4 -> 0.31972848 | T62: =T28/IS!T4 -> 0.30078027 | V62: =V28/IS!V4 -> 0.28057554 | W62: =W28/IS!W4 -> 0.26791993 | X62: =X28/IS!X4 -> 0.24508983 | Y62: =Y28/IS!Y4 -> 0.24221017 | AA62: =AA28/IS!AA4 -> 0.2465828 | AB62: =AB28/IS!AB4 -> 0.24499186 | AC62: =AC28/IS!AC4 -> 0.25963389 | AD62: =AD28/IS!AD4 -> 0.24457392 | AF62: =AF28/IS!AF4 -> 0.24532671 | AG62: =AG28/IS!AG4 -> 0.24062671 | AH62: =AH28/IS!AH4 -> 0.23889218 | AI62: =AI28/IS!AI4 -> 0.22646838 | AK62: =AK28/IS!AK4 -> 0.2243685 | AL62: =AL28/IS!AL4 -> 0.2222508 | AM62: =AM28/IS!AM4 -> 0.21414508 | AN62: =AN28/IS!AN4 -> 0.21199367 | AP62: =AP28/IS!AP4 -> 0.20367866 | AQ62: =AQ28/IS!AQ4 -> 0.20164238 | AR62: =AR28/IS!AR4 -> 0.20002974 | AS62: =AS28/IS!AS4 -> 0.18277132 | AU62: =AU28/IS!AU4 -> 0.24855808 | AV62: =AV28/IS!AV4 -> 0.25936094 | AW62: =AW28/IS!AW4 -> 0.24667235 | AX62: =AX28/IS!AX4 -> 0.21650575 | AZ62: =AZ28/IS!AZ4 -> 0.30430178 | BA62: =BA28/IS!BA4 -> 0.30624125 | BB62: =BB28/IS!BB4 -> 0.2886732 | BC62: =BC28/IS!BC4 -> 0.28190722 | BE62: =BE28/IS!BE4 -> 0.36524403 | BF62: =BF28/IS!BF4 -> 0.39598304 | BG62: =BG28/IS!BG4 -> 0.39683146 | BH62: =BH28/IS!BH4 -> 0.38853181 | BJ62: =BJ28/IS!BJ4 -> 0.43160427 | BK62: =BK28/IS!BK4 -> 0.4432576 | BL62: =BL28/IS!BL4 -> 0.42791281 | BM62: =BM28/IS!BM4 -> 0.43258218 | BO62: =BO28/IS!BO4 -> 0.470792 | BP62: =BP28/IS!BP4 -> 0.47997301 | BQ62: =BQ28/IS!BQ4 -> 0.44725166 | BR62: =BR28/IS!BR4 -> 0.45550247 | BT62: =BT28/IS!BT4 -> 0.49371767 | BU62: =BU28/IS!BU4 -> 0.51281482 | BV62: =BV28/IS!BV4 -> 0.50246713 | BW62: =BW28/IS!BW4 -> 0.4907548 | BY62: =BY28/IS!BY4 -> 0.53994087 | BZ62: =BZ28/IS!BZ4 -> 0.54125373 | CA62: =CA28/IS!CA4 -> 0.51490139 | CB62: =CB28/IS!CB4 -> 0.47061089 | CD62: =CD28/IS!CD4 -> 0.49978549 | CE62: =CE28/IS!CE4 -> 0.5089943 | CF62: =CF28/IS!CF4 -> 0.52965112 | CG62: =CG28/IS!CG4 -> 0.47726693 | CI62: =CI28/IS!CI4 -> 0.49273279 | CJ62: =CJ28/IS!CJ4 -> 0.49736321 | CK62: =CK28/IS!CK4 -> 0.4819166 | CL62: =CL28/IS!CL4 -> 0.43448191 | CN62: =CN28/IS!CN4 -> 0.43305113 | CO62: =CO28/IS!CO4 -> 0.42261473 | CP62: 0.49 | CQ62: =CQ28/IS!CQ4 -> 0.39236551 | CS62: 0.49 | CT62: 0.49 | CU62: 0.49 | CV62: 0.49
C63: Deferred rent as a % or Rev | AP63: =AP27/IS!AP4 -> 0.018312145 | AQ63: =AQ27/IS!AQ4 -> 0.018122844 | AR63: =AR27/IS!AR4 -> 0.01791644 | AS63: =AS27/IS!AS4 -> 0.028194956 | AU63: =AU27/IS!AU4 -> 0.02370666 | AV63: =AV27/IS!AV4 -> 0.028383772 | AW63: =AW27/IS!AW4 -> 0.026986446 | AX63: =AX27/IS!AX4 -> 0.030473355 | AZ63: =AZ27/IS!AZ4 -> 0.028960949 | BA63: =BA27/IS!BA4 -> 0.029585145 | BB63: =BB27/IS!BB4 -> 0.029474622 | BC63: =BC27/IS!BC4 -> 0.028848797 | BE63: =BE27/IS!BE4 -> 0.02221959 | BF63: =BF27/IS!BF4 -> 0.022474669 | BG63: =BG27/IS!BG4 -> 0.022252974 | BH63: =BH27/IS!BH4 -> 0.02732056 | BJ63: =BJ27/IS!BJ4 -> 0 | BK63: =BK27/IS!BK4 -> 0 | BL63: =BL27/IS!BL4 -> 0 | BM63: =BM27/IS!BM4 -> 0 | BO63: =BO27/IS!BO4 -> 0 | BP63: =BP27/IS!BP4 -> 0 | BQ63: =BQ27/IS!BQ4 -> 0 | BR63: =BR27/IS!BR4 -> 0 | BT63: =BT27/IS!BT4 -> 0 | BU63: =BU27/IS!BU4 -> 0 | BV63: =BV27/IS!BV4 -> 0 | BW63: =BW27/IS!BW4 -> 0 | BY63: =BY27/IS!BY4 -> 0 | BZ63: =BZ27/IS!BZ4 -> 0 | CA63: =CA27/IS!CA4 -> 0 | CB63: =CB27/IS!CB4 -> 0 | CD63: =CD27/IS!CD4 -> 0 | CE63: =CE27/IS!CE4 -> 0 | CF63: =CF27/IS!CF4 -> 0 | CG63: =CG27/IS!CG4 -> 0 | CI63: =CI27/IS!CI4 -> 0 | CJ63: =CJ27/IS!CJ4 -> 0 | CK63: =CK27/IS!CK4 -> 0 | CL63: =CL27/IS!CL4 -> 0 | CN63: =CN27/IS!CN4 -> 0 | CO63: =CO27/IS!CO4 -> 0 | CP63: 0 | CQ63: =CQ27/IS!CQ4 -> 0 | CS63: 0 | CT63: 0 | CU63: 0 | CV63: 0
C65: Def. Rev, net of current, as a % of Rev | J65: =J33/IS!J4 -> 0.49678218 | O65: =O33/IS!O4 -> 0.40326621 | Q65: =Q33/IS!Q4 -> 0.40593576 | R65: =R33/IS!R4 -> 0.39592471 | S65: =S33/IS!S4 -> 0.40240188 | T65: =T33/IS!T4 -> 0.41966608 | V65: =V33/IS!V4 -> 0.41916357 | W65: =W33/IS!W4 -> 0.39183468 | X65: =X33/IS!X4 -> 0.39307103 | Y65: =Y33/IS!Y4 -> 0.41623565 | AA65: =AA33/IS!AA4 -> 0.44115157 | AB65: =AB33/IS!AB4 -> 0.44178217 | AC65: =AC33/IS!AC4 -> 0.39487837 | AD65: =AD33/IS!AD4 -> 0.36968511 | AF65: =AF33/IS!AF4 -> 0.35108622 | AG65: =AG33/IS!AG4 -> 0.33852989 | AH65: =AH33/IS!AH4 -> 0.32453347 | AI65: =AI33/IS!AI4 -> 0.31405284 | AK65: =AK33/IS!AK4 -> 0.31794464 | AL65: =AL33/IS!AL4 -> 0.32209003 | AM65: =AM33/IS!AM4 -> 0.31492648 | AN65: =AN33/IS!AN4 -> 0.3009152 | AP65: =AP33/IS!AP4 -> 0.28536651 | AQ65: =AQ33/IS!AQ4 -> 0.28306647 | AR65: =AR33/IS!AR4 -> 0.28995886 | AS65: =AS33/IS!AS4 -> 0.2598706 | AU65: =AU33/IS!AU4 -> 0.238514 | AV65: =AV33/IS!AV4 -> 0.23729172 | AW65: =AW33/IS!AW4 -> 0.22242513 | AX65: =AX33/IS!AX4 -> 0.21243219 | AZ65: =AZ33/IS!AZ4 -> 0.21349072 | BA65: =BA33/IS!BA4 -> 0.20355906 | BB65: =BB33/IS!BB4 -> 0.18922529 | BC65: =BC33/IS!BC4 -> 0.18216495 | BE65: =BE33/IS!BE4 -> 0.045539159 | BF65: =BF33/IS!BF4 -> 0.043214221 | BG65: =BG33/IS!BG4 -> 0.042708532 | BH65: =BH33/IS!BH4 -> 0.038534109 | BJ65: =BJ33/IS!BJ4 -> 0.039576299 | BK65: =BK33/IS!BK4 -> 0.039603671 | BL65: =BL33/IS!BL4 -> 0.03667099 | BM65: =BM33/IS!BM4 -> 0.039198163 | BO65: =BO33/IS!BO4 -> 0.037483826 | BP65: =BP33/IS!BP4 -> 0.036335728 | BQ65: =BQ33/IS!BQ4 -> 0.033849944 | BR65: =BR33/IS!BR4 -> 0.035962933 | BT65: =BT33/IS!BT4 -> 0.04469776 | BU65: =BU33/IS!BU4 -> 0.052793027 | BV65: =BV33/IS!BV4 -> 0.052703628 | BW65: =BW33/IS!BW4 -> 0.050060337 | BY65: =BY33/IS!BY4 -> 0.048700959 | BZ65: =BZ33/IS!BZ4 -> 0.048370551 | CA65: =CA33/IS!CA4 -> 0.044948727 | CB65: =CB33/IS!CB4 -> 0.039100788 | CD65: =CD33/IS!CD4 -> 0.040558363 | CE65: =CE33/IS!CE4 -> 0.04389032 | CF65: =CF33/IS!CF4 -> 0.050486138 | CG65: =CG33/IS!CG4 -> 0.047804642 | CI65: =CI33/IS!CI4 -> 0.043275659 | CJ65: =CJ33/IS!CJ4 -> 0.046296779 | CK65: =CK33/IS!CK4 -> 0.04001564 | CL65: =CL33/IS!CL4 -> 0.036212677 | CN65: =CN33/IS!CN4 -> 0.031660874 | CO65: =CO33/IS!CO4 -> 0.029226254 | CP65: =CP33/IS!CP4 -> 0.027118965 | CQ65: =CQ33/IS!CQ4 -> 0.027448456 | CS65: =CS33/IS!CS4 -> 0.027451361 | CT65: =CT33/IS!CT4 -> 0.026747771 | CU65: =CU33/IS!CU4 -> 0.025868388 | CV65: =CV33/IS!CV4 -> 0.025427128
CM67: =CF!CM39 -> 137352 | CR67: =CF!CR39 -> 152266 | CW67: =CF!CW39 -> 245206.05

Sheet CF
CO2: =+CO29-CJ29 -> 2881 | CP2: =+CP29-CK29 -> 7283 | CQ2: =+CQ29-CL29 -> 5309
BP3: =BP29-BK29 -> 2667
B4: Cash Flows | D4: =IS!D3 -> 2005 | E4: =IS!E3 -> 2006 | F4: =IS!F3 -> 2007 | G4: =IS!G3 -> 1Q08 | H4: =IS!H3 -> 2Q08 | I4: =IS!I3 -> 2Q08 | J4: =IS!J3 -> 4Q08 | K4: =IS!K3 -> 2008 | ... CW4: =IS!CW3 -> 2026E
B5: Operating activities
C6: Net income (loss) | F6: -2156 | K6: -1895 | L6: =IS!L64 -> -54 | P6: 1162 | Q6: =IS!Q64 -> 919 | R6: =IS!R64 -> 638 | S6: =IS!S64 -> 886 | T6: =U6-SUM(Q6:S6) -> 441 | U6: 2884 | V6: =IS!V64 -> 492 | W6: =IS!W64 -> -109 | X6: =IS!X64 -> 177 | Y6: =IS!Y64 -> 13143 | Z6: =SUM(V6:Y6) -> 13703 | AA6: =IS!AA64 -> 256 | AB6: =IS!AB64 -> 426 | AC6: =IS!AC64 -> 174 | AD6: =IS!AD64 -> 366 | AE6: =SUM(AA6:AD6) -> 1222 | AF6: =IS!AF64 -> 199 | AG6: =IS!AG64 -> 288 | AH6: =IS!AH64 -> 270 | AI6: =IS!AI64 -> 294 | AJ6: =SUM(AF6:AI6) -> 1051 | AK6: =IS!AK64 -> 373 | AL6: =IS!AL64 -> 639 | AM6: =IS!AM64 -> 838 | AN6: =IS!AN64 -> 854 | AO6: =SUM(AK6:AN6) -> 2704 | AP6: =IS!AP64 -> 586 | AQ6: =IS!AQ64 -> 651 | AR6: =IS!AR64 -> 1270 | AS6: =IS!AS64 -> 2132 | AT6: =SUM(AP6:AS6) -> 4639 | AU6: =IS!AU64 -> 1044 | AV6: =IS!AV64 -> 352 | AW6: =IS!AW64 -> 2509 | AX6: =IS!AX64 -> 1805 | AY6: =SUM(AU6:AX6) -> 5710 | AZ6: =IS!AZ64 -> 2971 | BA6: =IS!BA64 -> 1825 | BB6: =IS!BB64 -> 1864 | BC6: =IS!BC64 -> -9101 | BD6: =SUM(AZ6:BC6) -> -2441 | BE6: =IS!BE64 -> 3254 | BF6: =IS!BF64 -> 5416 | BG6: =IS!BG64 -> 8061 | BH6: =23872-BG6-BF6-BE6 -> 7141 | BI6: =SUM(BE6:BH6) -> 23872 | BJ6: =IS!BJ64 -> 6813 | BK6: =IS!BK64 -> 8796 | BL6: =IS!BL64 -> 8941 | BM6: =IS!BM64 -> 9162 | BN6: =SUM(BJ6:BM6) -> 33712 | BO6: =9515 -> 9515 | BP6: =20709-BO6 -> 11194 | BQ6: =32116-BP6-BO6 -> 11407 | BR6: =IS!BR64 -> 13470 | BS6: =SUM(BO6:BR6) -> 45586 | BT6: =IS!BT64 -> 10200 | BU6: =IS!BU64 -> 10183 | BV6: 11449 | BW6: =IS!BW64 -> 12765 | BX6: =SUM(BT6:BW6) -> 44597 | BY6: =IS!BY64 -> 12603 | BZ6: =IS!BZ64 -> 10753 | CA6: =IS!CA64 -> 15863 | CB6: 15915 | CC6: =SUM(BY6:CB6) -> 55134 | CD6: =IS!CD64 -> 15289 | CE6: =IS!CE64 -> 14682 | CF6: =IS!CF64 -> 16842 | CG6: =65824-CF6-CE6-CD6 -> 19011 | CH6: =SUM(CD6:CG6) -> 65824 | CI6: 18003 | CJ6: 18032 | CK6: =IS!CK64 -> 23460 | CL6: =CM6-SUM(CI6:CK6) -> 17559 | CM6: 77054 | CN6: 22196 | CO6: =IS!CO64 -> 19733 | CP6: =67498-CO6-CN6 -> 25569 | CQ6: =CR6-SUM(CN6:CP6) -> 25841 | CR6: 93339 | CS6: =IS!CS64 -> 18312.375 | CT6: =IS!CT64 -> 23587.842 | CU6: =IS!CU64 -> 27001.288 | CV6: =IS!CV64 -> 28766.078 | CW6: =SUM(CS6:CV6) -> 97667.583
C7: Deferred Income taxes | Y7: -12708 | Z7: =SUM(V7:Y7) -> -12708 | AA7: 142 | AB7: 222 | AC7: =220-AB7-AA7 -> -144 | AD7: =-15-AC7-AB7-AA7 -> -235 | AE7: =SUM(AA7:AD7) -> -15 | AF7: -72 | AG7: =31-AF7 -> 103 | AH7: =155-AG7-AF7 -> 124 | AI7: =443-AH7-AG7-AF7 -> 288 | AJ7: =SUM(AF7:AI7) -> 443 | AK7: 173 | AL7: =576-AK7 -> 403 | AM7: =1065-AL7-AK7 -> 489 | AN7: -34 | AO7: =SUM(AK7:AN7) -> 1031 | AP7: -51 | AQ7: =155-AP7 -> 206 | AR7: =277-AQ7-AP7 -> 122 | AS7: =-38-AR7-AQ7-AP7 -> -315 | AT7: =SUM(AP7:AS7) -> -38 | AU7: -302 | AV7: =-439-AU7 -> -137 | AW7: =-818-AV7-AU7 -> -379 | AX7: =-1698-AW7-AV7-AU7 -> -880 | AY7: =SUM(AU7:AX7) -> -1698 | AZ7: 310 | BA7: =1236-AZ7 -> 926 | BB7: =1968-BA7-AZ7 -> 732 | BC7: =10854-BB7-BA7-AZ7 -> 8886 | BD7: =SUM(AZ7:BC7) -> 10854 | BE7: 1020 | BF7: =1498-BE7 -> 478 | BG7: =1934-BF7-BE7 -> 436 | BH7: =2798-BG7-BF7-BE7 -> 864 | BI7: =SUM(BE7:BH7) -> 2798 | BJ7: 838 | BK7: =2634-BJ7 -> 1796 | BL7: =5360-BK7-BJ7 -> 2726 | BM7: 2221 | BN7: =SUM(BJ7:BM7) -> 7581 | BO7: 668 | BP7: =1443-BO7 -> 775 | BQ7: =4324-BP7-BO7 -> 2881 | BR7: =4241-BQ7-BP7-BO7 -> -83 | BS7: =SUM(BO7:BR7) -> 4241 | BT7: 163 | BU7: 188 | BV7: 662 | BW7: =3881-BV7-BU7-BT7 -> 2868 | BX7: =SUM(BT7:BW7) -> 3881 | BY7: -269 | BZ7: -1891 | CA7: =+-2092-BZ7-BY7 -> 68 | CB7: -1640 | CC7: =SUM(BY7:CB7) -> -3732 | CD7: -5147 | CE7: -3507 | CF7: -3252 | CG7: =-10079-CF7-CE7-CD7 -> 1827 | CH7: =SUM(CD7:CG7) -> -10079 | CI7: -7070 | CJ7: -1102 | CK7: -1746 | CL7: =CM7-SUM(CI7:CK7) -> 132 | CM7: -9786 | CN7: -4418 | CO7: -1496 | CP7: =12583-CO7-CN7 -> 18497 | CQ7: =CR7-SUM(CN7:CP7) -> 6326 | CR7: 18909 | CW7: =SUM(CS7:CV7) -> 0
C8: Change in earn-out liability | BK8: =-344-BJ8 -> -344 | BL8: =-366-BK8-BJ8 -> -22 | BM8: -79 | BN8: =SUM(BJ8:BM8) -> -445 | BO8: 72 | BP8: =72-BO8 -> 0 | BQ8: =72-BP8-BO8 -> 0 | BR8: =-85-BO8 -> -157 | BS8: =SUM(BO8:BR8) -> -85 | CL8: =CM8-SUM(CI8:CK8) -> 0 | CQ8: =CR8-SUM(CN8:CP8) -> 0 | CW8: =SUM(CS8:CV8) -> 0
