Workbook
Name \0: #REF!
Name \1: #N/A
Name \2: #N/A
Name \3: #N/A
Name \4: #N/A
Name \5: #N/A
Name \6: #N/A
Name \a: #N/A
Name \b: #REF!
Name \c: #REF!
Name \d: #REF!
Name \e: #REF!
Name \f: #REF!
Name \g: #REF!
Name \h: #REF!
Name \i: #REF!
Name \j: #REF!
Name \k: #N/A
Name \l: #REF!
Name \m: #REF!
Name \n: #REF!
Name \o: #REF!
Name \p: #REF!
Name \PRINJV: #REF!
Name \q: #REF!
Name \r: #REF!
Name \s: #REF!
Name \t: #REF!
Name \u: #REF!
Name \v: #N/A
Name \w: #REF!
Name \x: #REF!
Name \y: #REF!
Name \z: #REF!
Name _: #REF!
Name _.4: #REF!
Name _????_3: #REF!
Name _????1_3: #REF!
Name _????8_3: #REF!
Name _??_3: #REF!
Name _??1???_3: #REF!
Name __: #REF!
Name ___: #REF!
Name ____: #REF!
Name _____: #REF!
Name ______: #REF!
Name ________: #REF!
Name __________: #REF!
Name ____________: #REF!
Name _____________: #REF!
Name ______________: #REF!
Name _______________________________________________tax2: #REF!
Name ______________________________________________tax2: #REF!
Name _____________________________________________tax2: #REF!
Name ____________________________________________tax2: #REF!
Name ___________________________________________tax2: #REF!
Name __________________________________________tax2: #REF!
Name _________________________________________tax2: #REF!
Name ________________________________________tax2: #REF!
Name _______________________________________tax2: #REF!

Sheet Disclaimer
C5: Equity Research
C7: Financial Model
C8: Software
C9: 46083
C12: Varonis Systems, Inc. (VRNS)
C17: Wells Fargo Software Team
C19: Richard Poland | E19: David Unger
C20: Analyst | E20: Associate Analyst
C21: (212) 214-5333 | E21: (212) 214-5317
C22: richard.d.poland@wellsfargo.com | E22: David.Unger@wellsfargo.com
C24: Important Disclaimers:

Sheet Income Statement
A1: Varonis Systems, Inc. (VRNS)
A2: Income Statement | B2: 2017/1F | C2: 2017/2F | D2: 2017/3F | E2: 2017/4F | F2: 2018/1F | G2: 2018/2F | H2: 2018/3F | I2: 2018/4F | J2: 2019/1F | K2: 2019/2F | L2: 2019/3F | M2: 2019/4F | N2: 2019/1F | O2: 2019/2F | P2: 2019/3F | Q2: 2019/4F | R2: 2021/1F | S2: 2021/2F | T2: 2021/3F | U2: 2021/4F | V2: 2022/1F | W2: 2022/2F | X2: 2022/3F | Y2: 2022/4F | Z2: 2023/1F | AA2: 2023/2F | AB2: 2023/3F | AC2: 2023/4F | AD2: 2024/1F | AE2: 2024/2F | AF2: 2024/3F | AG2: 2024/4F | AH2: 2025/1F | AI2: 2025/2F | AJ2: 2025/3F | AK2: 2025/4F | AL2: 2026/1F | AM2: 2026/2F | AN2: 2026/3F | AO2: 2026/4F | AP2: 2027/1F | AQ2: 2027/2F | AR2: 2027/3F | AS2: 2027/4F | AU2: 2017 | AV2: 2018 | AW2: 2019 | AX2: 2020 | AY2: 2021 | AZ2: 2022 | BA2: 2023 | BB2: 2024 | BC2: =BB2+1 -> 2025 | BD2: =BC2+1 -> 2026 | BE2: =BD2+1 -> 2027
B3: 2017 | F3: 2018 | J3: 2019 | N3: 2020 | R3: 2021 | V3: 2022 | Z3: 2023 | AD3: 2024 | AH3: =AD3+1 -> 2025 | AL3: =AH3+1 -> 2026 | AP3: =AL3+1 -> 2027
A4: ($ in millions, unless otherwise stated) | B4: 42825 | C4: 42916 | D4: 43008 | E4: 43100 | F4: 43190 | G4: 43281 | H4: 43373 | I4: 43465 | J4: 43555 | K4: 43646 | L4: 43738 | M4: 43830 | N4: 43921 | O4: 44012 | P4: 44104 | Q4: 44196 | R4: 44286 | S4: 44377 | T4: 44469 | U4: 44561 | V4: 44651 | W4: 44742 | X4: 44834 | Y4: 44926 | Z4: 45016 | AA4: 45107 | AB4: 45199 | AC4: 45291 | AD4: 45382 | AE4: 45473 | AF4: Sep-24 | AG4: Dec-24 | AH4: Mar-25 | AI4: Jun-25 | AJ4: Sep-25 | AK4: Dec-25 | AL4: Mar-26E | AM4: Jun-26E | AN4: Sep-26E | AO4: Dec-26E | AP4: Mar-27E | AQ4: Jun-27E | AR4: Sep-27E | AS4: Dec-27E | AU4: 2017 | AV4: 2018 | AW4: 2019 | AX4: 2020 | AY4: 2021 | AZ4: 2022 | BA4: 2023 | BB4: 2024 | BC4: 2025 | BD4: 2026E | BE4: 2027E
A5: Subscription | B5: =+'Revenue Build'!B13 -> 0 | C5: =+'Revenue Build'!C13 -> 0 | D5: =+'Revenue Build'!D13 -> 0 | E5: =+'Revenue Build'!E13 -> 0 | F5: =+'Revenue Build'!F13 -> 1.071 | G5: =+'Revenue Build'!G13 -> 1.291 | H5: =+'Revenue Build'!H13 -> 2.539 | I5: =+'Revenue Build'!I13 -> 3.849 | ... AI5: =+'Revenue Build'!AI13 -> 138.269 | AJ5: ='Revenue Build'!AJ13 -> 150.636 | AK5: ='Revenue Build'!AK13 -> 163.277 | AL5: ='Revenue Build'!AL13 -> 159.38907 | AM5: ='Revenue Build'!AM13 -> 171.24836 | AN5: ='Revenue Build'!AN13 -> 183.01573 | AO5: ='Revenue Build'!AO13 -> 195.52477 | AP5: ='Revenue Build'!AP13 -> 206.81946 | AQ5: ='Revenue Build'!AQ13 -> 214.59312 | ... AS5: ='Revenue Build'!AS13 -> 231.88418 | AU5: =SUM(B5:E5) -> 0 | AV5: =SUM(F5:I5) -> 8.75 | AW5: =SUM(J5:M5) -> 76.73 | AX5: =SUM(N5:Q5) -> 161.188 | AY5: =SUM(R5:U5) -> 268.942 | AZ5: =SUM(V5:Y5) -> 366.144 | BA5: =SUM(Z5:AC5) -> 400.907 | BB5: =SUM(AD5:AG5) -> 463.022 | BC5: =SUM(AH5:AK5) -> 572.23 | BD5: =SUM(AL5:AO5) -> 709.17794 | BE5: =SUM(AP5:AS5) -> 876.61962
A6: Perpetual Licnese | B6: ='Revenue Build'!B28 -> 18.092 | C6: ='Revenue Build'!C28 -> 27.31 | D6: ='Revenue Build'!D28 -> 29 | E6: ='Revenue Build'!E28 -> 45.939 | F6: ='Revenue Build'!F28 -> 24.086 | G6: ='Revenue Build'!G28 -> 32.27 | H6: ='Revenue Build'!H28 -> 33.432 | I6: ='Revenue Build'!I28 -> 49.79 | ... AS6: ='Revenue Build'!AS28 -> 0 | AU6: =SUM(B6:E6) -> 120.341 | AV6: =SUM(F6:I6) -> 139.578 | AW6: =SUM(J6:M6) -> 42.093 | AX6: =SUM(N6:Q6) -> 1.473 | AY6: =SUM(R6:U6) -> 1.89 | AZ6: =SUM(V6:Y6) -> 0 | BA6: =SUM(Z6:AC6) -> 0 | BB6: =SUM(AD6:AG6) -> 0 | BC6: =SUM(AH6:AK6) -> 0 | BD6: =SUM(AI6:AL6) -> 0 | BE6: =SUM(AM6:AP6) -> 0
A7: Maintenance and Services | B7: =+'Revenue Build'!B33 -> 21.501 | C7: =+'Revenue Build'!C33 -> 22.121 | D7: =+'Revenue Build'!D33 -> 24.365 | E7: =+'Revenue Build'!E33 -> 27.062 | F7: =+'Revenue Build'!F33 -> 28.371 | G7: =+'Revenue Build'!G33 -> 28.629 | H7: =+'Revenue Build'!H33 -> 31.081 | I7: =+'Revenue Build'!I33 -> 33.879 | ... AI7: =+'Revenue Build'!AI33 -> 13.894 | AJ7: ='Revenue Build'!AJ33 -> 10.941 | AK7: ='Revenue Build'!AK33 -> 10.092 | AL7: ='Revenue Build'!AL33 -> 5.9497918 | AM7: ='Revenue Build'!AM33 -> 4.6623359 | AN7: ='Revenue Build'!AN33 -> 3.3456197 | AO7: ='Revenue Build'!AO33 -> 2 | AP7: ='Revenue Build'!AP33 -> 2 | AQ7: ='Revenue Build'!AQ33 -> 2 | ... AS7: ='Revenue Build'!AS33 -> 2 | AU7: =SUM(B7:E7) -> 95.049 | AV7: =SUM(F7:I7) -> 121.96 | AW7: =SUM(J7:M7) -> 135.367 | AX7: =SUM(N7:Q7) -> 130.028 | AY7: =SUM(R7:U7) -> 119.302 | AZ7: =SUM(V7:Y7) -> 107.49 | BA7: =SUM(Z7:AC7) -> 98.253 | BB7: =SUM(AD7:AG7) -> 87.928 | BC7: =SUM(AH7:AK7) -> 51.302 | BD7: =SUM(AL7:AO7) -> 15.957747 | BE7: =SUM(AP7:AS7) -> 8
A8: Total revenue | B8: =+'Revenue Build'!B5 -> 39.593 | C8: =+'Revenue Build'!C5 -> 49.431 | D8: =+'Revenue Build'!D5 -> 53.365 | E8: =+'Revenue Build'!E5 -> 73.001 | F8: =+'Revenue Build'!F5 -> 53.528 | G8: =+'Revenue Build'!G5 -> 62.19 | H8: =+'Revenue Build'!H5 -> 67.052 | I8: =+'Revenue Build'!I5 -> 87.518 | ... AS8: =+'Revenue Build'!AS5 -> 233.88418 | AU8: =SUM(B8:E8) -> 215.39 | AV8: =SUM(F8:I8) -> 270.288 | AW8: =SUM(J8:M8) -> 254.19 | AX8: =SUM(N8:Q8) -> 292.689 | AY8: =SUM(R8:U8) -> 390.134 | AZ8: =SUM(V8:Y8) -> 473.634 | BA8: =SUM(Z8:AC8) -> 499.16 | BB8: =SUM(AD8:AG8) -> 550.95 | BC8: =SUM(AH8:AK8) -> 623.532 | BD8: =SUM(AL8:AO8) -> 725.13568 | BE8: =SUM(AP8:AS8) -> 884.61962
A9: Consensus revenue | B9: ='Revenue Build'!B6 -> 40.38 | C9: ='Revenue Build'!C6 -> 47.532444 | D9: ='Revenue Build'!D6 -> 50.554272 | E9: ='Revenue Build'!E6 -> 66.51052 | F9: ='Revenue Build'!F6 -> 49.838929 | G9: ='Revenue Build'!G6 -> 62.105238 | H9: ='Revenue Build'!H6 -> 64.53161 | I9: ='Revenue Build'!I6 -> 87.408971 | ... AS9: ='Revenue Build'!AS6 -> 230.41508 | AU9: ='Revenue Build'!AU6 -> 210.66552 | AV9: ='Revenue Build'!AV6 -> 270.18211 | AW9: ='Revenue Build'!AW6 -> 253.4685 | AX9: ='Revenue Build'!AX6 -> 281.78387 | AY9: ='Revenue Build'!AY6 -> 385.55766 | AZ9: ='Revenue Build'!AZ6 -> 471.20837 | BA9: ='Revenue Build'!BA6 -> 496.67471 | BB9: ='Revenue Build'!BB6 -> 557.97652 | ... BE9: ='Revenue Build'!BE6 -> 857.74118
A10: Management Guidance - Total Revenue
A11: Low | N11: ='Revenue Build'!N9 -> 53.9 | O11: ='Revenue Build'!O9 -> 56 | P11: ='Revenue Build'!P9 -> 68 | Q11: ='Revenue Build'!Q9 -> 82 | R11: ='Revenue Build'!R9 -> 68 | S11: ='Revenue Build'!S9 -> 82.5 | T11: ='Revenue Build'!T9 -> 96 | U11: ='Revenue Build'!U9 -> 120 | ... AS11: ='Revenue Build'!AS9 | AY11: ='Revenue Build'!AY9 -> 383.5 | AZ11: ='Revenue Build'!AZ9 -> 519 | BA11: ='Revenue Build'!BA9 -> 495 | BB11: ='Revenue Build'!BB9 -> 554.4 | BC11: ='Revenue Build'!BC9 -> 615.2 | BD11: ='Revenue Build'!BD9 -> 722
A12: Mid | N12: ='Revenue Build'!N10 -> 54.1 | O12: ='Revenue Build'!O10 -> 57 | P12: ='Revenue Build'!P10 -> 69.5 | Q12: ='Revenue Build'!Q10 -> 83.5 | R12: ='Revenue Build'!R10 -> 68.75 | S12: ='Revenue Build'!S10 -> 83.25 | T12: ='Revenue Build'!T10 -> 97 | U12: ='Revenue Build'!U10 -> 121.5 | ... AS12: ='Revenue Build'!AS10 | AY12: ='Revenue Build'!AY10 -> 385 | AZ12: ='Revenue Build'!AZ10 -> 496 | BA12: ='Revenue Build'!BA10 -> 497 | BB12: ='Revenue Build'!BB10 -> 556.9 | BC12: ='Revenue Build'!BC10 -> 618.2 | BD12: ='Revenue Build'!BD10 -> 726
A13: High | N13: ='Revenue Build'!N11 -> 54.3 | O13: ='Revenue Build'!O11 -> 58 | P13: ='Revenue Build'!P11 -> 71 | Q13: ='Revenue Build'!Q11 -> 85 | R13: ='Revenue Build'!R11 -> 69.5 | S13: ='Revenue Build'!S11 -> 84 | T13: ='Revenue Build'!T11 -> 98 | U13: ='Revenue Build'!U11 -> 123 | ... AS13: ='Revenue Build'!AS11 | AY13: ='Revenue Build'!AY11 -> 386.5 | AZ13: ='Revenue Build'!AZ11 -> 473 | BA13: ='Revenue Build'!BA11 -> 499 | BB13: ='Revenue Build'!BB11 -> 559.4 | BC13: ='Revenue Build'!BC11 -> 621.2 | BD13: ='Revenue Build'!BD11 -> 730
A15: Total cost of revenue | B15: =B105-B129-B138-B147 -> 4.433 | C15: =C105-C129-C138-C147 -> 4.596 | D15: =D105-D129-D138-D147 -> 5.115 | E15: =E105-E129-E138-E147 -> 5.401 | F15: =F105-F129-F138-F147 -> 5.813 | G15: =G105-G129-G138-G147 -> 5.894 | H15: =H105-H129-H138-H147 -> 6.571 | I15: =I105-I129-I138-I147 -> 7.285 | ... AK15: =AK105-AK129-AK138-AK147 -> 34.685 | AL15: =AL8*(1-AL63) -> 36.374551 | AM15: =AM8*(1-AM63) -> 38.348532 | AN15: =AN8*(1-AN63) -> 40.254052 | AO15: =AO8*(1-AO63) -> 42.270301 | AP15: =AP8*(1-AP63) -> 44.269726 | AQ15: =AQ8*(1-AQ63) -> 45.484555 | AR15: =AR8*(1-AR63) -> 46.867156 | AS15: =AS8*(1-AS63) -> 48.18014 | AU15: =SUM(B15:E15) -> 19.545 | AV15: =SUM(F15:I15) -> 25.563 | AW15: =SUM(J15:M15) -> 32.348 | AX15: =SUM(N15:Q15) -> 38.686 | AY15: =SUM(R15:U15) -> 47.82 | AZ15: =SUM(V15:Y15) -> 56.996 | BA15: =SUM(Z15:AC15) -> 62.6 | BB15: =SUM(AD15:AG15) -> 86.756 | BC15: =SUM(AH15:AK15) -> 124.578 | BD15: =SUM(AL15:AO15) -> 157.24744 | BE15: =SUM(AP15:AS15) -> 184.80158
A16: Gross profit | B16: =B8-B15 -> 35.16 | C16: =C8-C15 -> 44.835 | D16: =D8-D15 -> 48.25 | E16: =E8-E15 -> 67.6 | F16: =F8-F15 -> 47.715 | G16: =G8-G15 -> 56.296 | H16: =H8-H15 -> 60.481 | I16: =I8-I15 -> 80.233 | ... AS16: =AS8-AS15 -> 185.70404 | AU16: =SUM(B16:E16) -> 195.845 | AV16: =SUM(F16:I16) -> 244.725 | AW16: =SUM(J16:M16) -> 221.842 | AX16: =SUM(N16:Q16) -> 254.003 | AY16: =SUM(R16:U16) -> 342.314 | AZ16: =SUM(V16:Y16) -> 416.638 | BA16: =SUM(Z16:AC16) -> 436.56 | BB16: =SUM(AD16:AG16) -> 464.194 | BC16: =SUM(AH16:AK16) -> 498.954 | BD16: =SUM(AL16:AO16) -> 567.88825 | BE16: =SUM(AP16:AS16) -> 699.81804
A17: Consensus gross profit | B17: ='[2]VA Consensus'!C30 -> 35.935 | C17: ='[2]VA Consensus'!D30 -> 42.827976 | D17: ='[2]VA Consensus'!E30 -> 45.832307 | E17: ='[2]VA Consensus'!F30 -> 60.840642 | F17: ='[2]VA Consensus'!G30 -> 44.527167 | G17: ='[2]VA Consensus'!H30 -> 56.212896 | H17: ='[2]VA Consensus'!I30 -> 58.323792 | I17: ='[2]VA Consensus'!J30 -> 80.246522 | ... AS17: ='[2]VA Consensus'!AT30 -> 183.49853 | AU17: ='[2]VA Consensus'!AV30 -> 190.83621 | AV17: ='[2]VA Consensus'!AW30 -> 244.69338 | AW17: ='[2]VA Consensus'!AX30 -> 221.50528 | AX17: ='[2]VA Consensus'!AY30 -> 243.40759 | AY17: ='[2]VA Consensus'!AZ30 -> 336.28952 | AZ17: ='[2]VA Consensus'!BA30 -> 412.79012 | BA17: ='[2]VA Consensus'!BB30 -> 433.41782 | BB17: ='[2]VA Consensus'!BC30 -> 472.21847 | ... BE17: ='[2]VA Consensus'!BF30 -> 682.00556
A19: Operating expenses
A20: Research and development | B20: =B109-B130-B139-B148 -> 9.264 | C20: =C109-C130-C139-C148 -> 10.184 | D20: =D109-D130-D139-D148 -> 10.502 | E20: =E109-E130-E139-E148 -> 12.143 | F20: =F109-F130-F139-F148 -> 13.401 | G20: =G109-G130-G139-G148 -> 14.628 | H20: =H109-H130-H139-H148 -> 15.154 | I20: =I109-I130-I139-I148 -> 16.963 | ... AK20: =AK109-AK130-AK139-AK148 -> 51.862 | AL20: =AL$8*AL65 -> 52.908437 | AM20: =AM$8*AM65 -> 46.792246 | AN20: =AN$8*AN65 -> 51.249371 | AO20: =AO$8*AO65 -> 49.381192 | AP20: =AP$8*AP65 -> 60.557644 | AQ20: =AQ$8*AQ65 -> 57.397176 | AR20: =AR$8*AR65 -> 60.837173 | AS20: =AS$8*AS65 -> 56.132202 | AU20: =SUM(B20:E20) -> 42.093 | AV20: =SUM(F20:I20) -> 60.146 | AW20: =SUM(J20:M20) -> 67.414 | AX20: =SUM(N20:Q20) -> 76.151 | AY20: =SUM(R20:U20) -> 96.238 | AZ20: =SUM(V20:Y20) -> 124.495 | BA20: =SUM(Z20:AC20) -> 133.431 | BB20: =SUM(AD20:AG20) -> 154.395 | BC20: =SUM(AH20:AK20) -> 187.357 | BD20: =SUM(AL20:AO20) -> 200.33125 | BE20: =SUM(AP20:AS20) -> 234.9242
A21: Sales and marketing | B21: =B110-B131-B140-B149 -> 28.536 | C21: =C110-C131-C140-C149 -> 30.052 | D21: =D110-D131-D140-D149 -> 30.389 | E21: =E110-E131-E140-E149 -> 35.465 | F21: =F110-F131-F140-F149 -> 35.401 | G21: =G110-G131-G140-G149 -> 36.644 | H21: =H110-H131-H140-H149 -> 36.798 | I21: =I110-I131-I140-I149 -> 40.25 | ... AK21: =AK110-AK131-AK140-AK149 -> 67.992 | AL21: =AL$8*AL66 -> 71.922407 | AM21: =AM$8*AM66 -> 72.123387 | AN21: =AN$8*AN66 -> 76.408154 | AO21: =AO$8*AO66 -> 80.985155 | AP21: =AP$8*AP66 -> 85.615979 | AQ21: =AQ$8*AQ66 -> 85.554281 | AR21: =AR$8*AR66 -> 86.974626 | AS21: =AS$8*AS66 -> 90.045408 | AU21: =SUM(B21:E21) -> 124.442 | AV21: =SUM(F21:I21) -> 149.093 | AW21: =SUM(J21:M21) -> 153.208 | AX21: =SUM(N21:Q21) -> 151.533 | AY21: =SUM(R21:U21) -> 185.64 | AZ21: =SUM(V21:Y21) -> 220.636 | BA21: =SUM(Z21:AC21) -> 227.874 | BB21: =SUM(AD21:AG21) -> 244.079 | BC21: =SUM(AH21:AK21) -> 259.522 | BD21: =SUM(AL21:AO21) -> 301.4391 | BE21: =SUM(AP21:AS21) -> 348.19029
A22: General and administrative | B22: =B111-B132-B141-B150 -> 4.486 | C22: =C111-C132-C141-C150 -> 5.248 | D22: =D111-D132-D141-D150 -> 5.431 | E22: =E111-E132-E141-E150 -> 6.571 | F22: =F111-F132-F141-F150 -> 5.615 | G22: =G111-G132-G141-G150 -> 6.048 | H22: =H111-H132-H141-H150 -> 6.533 | I22: =I111-I132-I141-I150 -> 7.489 | ... AK22: =AK111-AK132-AK141-AK150 -> 14.277 | AL22: =AL$8*AL67 -> 14.880498 | AM22: =AM$8*AM67 -> 15.831963 | AN22: =AN$8*AN67 -> 15.840715 | AO22: =AO$8*AO67 -> 16.789605 | AP22: =AP$8*AP67 -> 18.793751 | AQ22: =AQ$8*AQ67 -> 18.410415 | AR22: =AR$8*AR67 -> 18.025829 | AS22: =AS$8*AS67 -> 17.541313 | AU22: =SUM(B22:E22) -> 21.736 | AV22: =SUM(F22:I22) -> 25.685 | AW22: =SUM(J22:M22) -> 28.42 | AX22: =SUM(N22:Q22) -> 30.767 | AY22: =SUM(R22:U22) -> 35.195 | AZ22: =SUM(V22:Y22) -> 41.973 | BA22: =SUM(Z22:AC22) -> 46.512 | BB22: =SUM(AD22:AG22) -> 49.809 | BC22: =SUM(AH22:AK22) -> 55.721 | BD22: =SUM(AL22:AO22) -> 63.342781 | BE22: =SUM(AP22:AS22) -> 72.771309
A23: Total operating expenses | B23: =B20+B21+B22 -> 42.286 | C23: =C20+C21+C22 -> 45.484 | D23: =D20+D21+D22 -> 46.322 | E23: =E20+E21+E22 -> 54.179 | F23: =F20+F21+F22 -> 54.417 | G23: =G20+G21+G22 -> 57.32 | H23: =H20+H21+H22 -> 58.485 | I23: =I20+I21+I22 -> 64.702 | ... AS23: =AS20+AS21+AS22 -> 163.71892 | AU23: =SUM(B23:E23) -> 188.271 | AV23: =SUM(F23:I23) -> 234.924 | AW23: =SUM(J23:M23) -> 249.042 | AX23: =SUM(N23:Q23) -> 258.451 | AY23: =SUM(R23:U23) -> 317.073 | AZ23: =SUM(V23:Y23) -> 387.104 | BA23: =SUM(Z23:AC23) -> 407.817 | BB23: =SUM(AD23:AG23) -> 448.283 | BC23: =SUM(AH23:AK23) -> 502.6 | BD23: =SUM(AL23:AO23) -> 565.11313 | BE23: =SUM(AP23:AS23) -> 655.8858
A24: Operating Income | B24: =B16-B23 -> -7.126 | C24: =C16-C23 -> -0.649 | D24: =D16-D23 -> 1.928 | E24: =E16-E23 -> 13.421 | F24: =F16-F23 -> -6.702 | G24: =G16-G23 -> -1.024 | H24: =H16-H23 -> 1.996 | I24: =I16-I23 -> 15.531 | ... AS24: =AS16-AS23 -> 21.985113 | AU24: =SUM(B24:E24) -> 7.574 | AV24: =SUM(F24:I24) -> 9.801 | AW24: =SUM(J24:M24) -> -27.2 | AX24: =SUM(N24:Q24) -> -4.448 | AY24: =SUM(R24:U24) -> 25.241 | AZ24: =SUM(V24:Y24) -> 29.534 | BA24: =SUM(Z24:AC24) -> 28.743 | BB24: =SUM(AD24:AG24) -> 15.911 | BC24: =SUM(AH24:AK24) -> -3.646 | BD24: =SUM(AL24:AO24) -> 2.7751193 | BE24: =SUM(AP24:AS24) -> 43.932244 | BH24: =+BD24/BD8 -> 0.0038270345
A25: Consensus operating income | B25: ='[2]VA Consensus'!C36 -> -6.219 | C25: ='[2]VA Consensus'!D36 -> -1.8211362 | D25: ='[2]VA Consensus'!E36 -> 0.34439955 | E25: ='[2]VA Consensus'!F36 -> 9.5522178 | F25: ='[2]VA Consensus'!G36 -> -8.3391343 | G25: ='[2]VA Consensus'!H36 -> -0.98990951 | H25: ='[2]VA Consensus'!I36 -> 0.35928966 | I25: ='[2]VA Consensus'!J36 -> 11.506609 | ... AS25: ='[2]VA Consensus'!AT36 -> 17.412038 | AU25: ='[2]VA Consensus'!AV36 -> 5.2512178 | AV25: ='[2]VA Consensus'!AW36 -> 5.7860373 | AW25: ='[2]VA Consensus'!AX36 -> -27.555533 | AX25: ='[2]VA Consensus'!AY36 -> -13.076283 | AY25: ='[2]VA Consensus'!AZ36 -> 20.528773 | AZ25: ='[2]VA Consensus'!BA36 -> 26.351861 | BA25: ='[2]VA Consensus'!BB36 -> 27.732461 | BB25: ='[2]VA Consensus'!BC36 -> 22.14059 | ... BE25: ='[2]VA Consensus'!BF36 -> 43.650134 | BH25: =+BD25/BD9 -> 0.0025594523
A26: Management Guidance - Operating Income
A27: Low | N27: -17.6 | O27: -11 | P27: -3 | Q27: 5 | R27: -12 | S27: -2.5 | T27: 3.5 | U27: 16.5 | V27: -10.5 | W27: 0 | X27: 8.5 | Y27: 22 | Z27: -7 | AA27: 0.5 | AB27: 1 | AC27: 25 | AD27: -15 | AE27: -6 | AF27: 7 | AG27: 20 | AH27: -14 | AI27: -5 | AJ27: 1 | AK27: 0 | AL27: -11 | AY27: 19.5 | AZ27: 25.5 | BA27: 26.5 | BB27: 20.6 | BC27: -8.2 | BD27: 0
A28: Mid | N28: =AVERAGE(N27,N29) -> -17.45 | O28: =AVERAGE(O27,O29) -> -10.5 | P28: =AVERAGE(P27,P29) -> -2.5 | Q28: =AVERAGE(Q27,Q29) -> 5.5 | R28: =AVERAGE(R27,R29) -> -11.5 | S28: =AVERAGE(S27,S29) -> -2 | T28: =AVERAGE(T27,T29) -> 4 | U28: =AVERAGE(U27,U29) -> 17.5 | ... AB28: =AVERAGE(AB27,AB29) -> 1.5 | AC28: =IFERROR(AVERAGE(AC27,AC29),"") -> 26 | AD28: =IFERROR(AVERAGE(AD27,AD29),"") -> -14 | AE28: =IFERROR(AVERAGE(AE27,AE29),"") -> -5.5 | AF28: =IFERROR(AVERAGE(AF27,AF29),"") -> 7.5 | AG28: =IFERROR(AVERAGE(AG27,AG29),"") -> 21 | AH28: =IFERROR(AVERAGE(AH27,AH29),"") -> -12.5 | AI28: =IFERROR(AVERAGE(AI27,AI29),"") -> -3.5 | AJ28: =IFERROR(AVERAGE(AJ27,AJ29),"") -> 2.5 | ... AL28: =IFERROR(AVERAGE(AL27,AL29),"") -> -10.5 | AM28: =+'Income Statement'!AM$24-AM24 -> 0 | AN28: =+'Income Statement'!AN$24-AN24 -> 0 | AO28: =+'Income Statement'!AO$24-AO24 -> 0 | AP28: =+'Income Statement'!AP$24-AP24 -> 0 | AQ28: =+'Income Statement'!AQ$24-AQ24 -> 0 | AR28: =+'Income Statement'!AR$24-AR24 -> 0 | AS28: =+'Income Statement'!AS$24-AS24 -> 0 | AY28: =AVERAGE(AY27,AY29) -> 20.5 | AZ28: =AVERAGE(AZ27,AZ29) -> 26.5 | BA28: =AVERAGE(BA27,BA29) -> 27.5 | BB28: =IFERROR(AVERAGE(BB27,BB29),"") -> 21.6 | BC28: =IFERROR(AVERAGE(BC27,BC29),"") -> -6.7 | BD28: =IFERROR(AVERAGE(BD27,BD29),"") -> 2 | BE28: =IFERROR(AVERAGE(BE27,BE29),"")
A29: High | N29: -17.3 | O29: -10 | P29: -2 | Q29: 6 | R29: -11 | S29: -1.5 | T29: 4.5 | U29: 18.5 | V29: -9.5 | W29: 1 | X29: 10 | Y29: 24 | Z29: -6 | AA29: 1.5 | AB29: 2 | AC29: 27 | AD29: -13 | AE29: -5 | AF29: 8 | AG29: 22 | AH29: -11 | AI29: -2 | AJ29: 4 | AK29: 3 | AL29: -10 | AY29: 21.5 | AZ29: 27.5 | BA29: 28.5 | BB29: 22.6 | BC29: -5.2 | BD29: 4
A30: EBITDA | B30: =B24+'Cash Flow'!B7-'Income Statement'!B82 -> 15.04447 | C30: =C24+'Cash Flow'!C7-'Income Statement'!C82 -> -21.53547 | D30: =D24+'Cash Flow'!D7-'Income Statement'!D82 -> 2.614 | E30: =E24+'Cash Flow'!E7-'Income Statement'!E82 -> 14.779 | F30: =F24+'Cash Flow'!F7-'Income Statement'!F82 -> -5.905 | G30: =G24+'Cash Flow'!G7-'Income Statement'!G82 -> -0.195 | H30: =H24+'Cash Flow'!H7-'Income Statement'!H82 -> 2.85 | I30: =I24+'Cash Flow'!I7-'Income Statement'!I82 -> 17.207 | ... AC30: =AC24+'Cash Flow'!AC7-'Income Statement'!AC82 -> 29.703 | AD30: =AD24+'Cash Flow'!AT7-'Income Statement'!AD82 -> -10.953 | AE30: =AE24+'Cash Flow'!AU7-'Income Statement'!AE82 -> 5.015 | AF30: =AF24+'Cash Flow'!AV7-'Income Statement'!AF82 -> 12.848 | AG30: =AG24+'Cash Flow'!AW7-'Income Statement'!AG82 -> 21.544 | AH30: =AH24+'Cash Flow'!AX7-'Income Statement'!AH82 -> 1.459 | AI30: =AI24+'Cash Flow'!AY7-'Income Statement'!AI82 -> 8.454 | AJ30: =AJ24+'Cash Flow'!AZ7-'Income Statement'!AJ82 -> 8.27 | AK30: =AK24+'Cash Flow'!BA7-'Income Statement'!AK82 -> 14.195 | ... AN30: =AN24+'Cash Flow'!BD7-'Income Statement'!AN82 -> 18.721519 | AO30: =AO24+'Cash Flow'!BF7-'Income Statement'!AO82 -> 6.0375155 | AP30: =AP24+'Cash Flow'!BF7-'Income Statement'!AP82 -> -2.4786389 | AQ30: =AQ24+'Cash Flow'!BE7-'Income Statement'!AQ82 -> 29.85616 | AR30: =AR24+'Cash Flow'!BH7-'Income Statement'!AR82 -> 11.84108 | AS30: =AS24+'Cash Flow'!BJ7-'Income Statement'!AS82 -> 23.252113 | AU30: =SUM(B30:E30) -> 10.902 | AV30: =SUM(F30:I30) -> 13.957 | AW30: =SUM(J30:M30) -> -20.879 | AX30: =SUM(N30:Q30) -> 3.966 | AY30: =SUM(R30:U30) -> 29.335 | AZ30: =SUM(V30:Y30) -> 37.95 | BA30: =SUM(Z30:AC30) -> 37.558 | BB30: =SUM(AD30:AG30) -> 28.454 | BC30: =SUM(AH30:AK30) -> 32.378 | BD30: =SUM(AL30:AO30) -> 36.139579 | BE30: =SUM(AP30:AS30) -> 62.470715
A32: Financial income (expenses), net | B32: =B115+B155+B156 -> 0.469 | C32: =C115+C155+C156 -> 0.95 | D32: =D115+D155+D156 -> 0.622 | E32: =E115+E155+E156 -> 0.321 | F32: =F115+F155+F156 -> 0.253 | G32: =G115+G155+G156 -> 0.321 | H32: =H115+H155+H156 -> 0.436 | I32: =I115+I155+I156 -> 0.534 | ... AK32: =AK115+AK155+AK156 -> 9.572 | AL32: =AK32+0.5 -> 10.072 | AM32: =AL32 -> 10.072 | AN32: =AM32 -> 10.072 | AO32: =AN32 -> 10.072 | AP32: =AO32+0.5 -> 10.572 | AQ32: =AP32+0.5 -> 11.072 | AR32: =AQ32+0.5 -> 11.572 | AS32: =AR32+0.5 -> 12.072 | AU32: =SUM(B32:E32) -> 2.362 | AV32: =SUM(F32:I32) -> 1.544 | AW32: =SUM(J32:M32) -> 1.836 | AX32: =SUM(N32:Q32) -> -1.661 | AY32: =SUM(R32:U32) -> -3.577 | AZ32: =SUM(V32:Y32) -> 6.751 | BA32: =SUM(Z32:AC32) -> 30.903 | BB32: =SUM(AD32:AG32) -> 37.615 | BC32: =SUM(AH32:AK32) -> 40.317 | BD32: =SUM(AL32:AO32) -> 40.288 | BE32: =SUM(AP32:AS32) -> 45.288
A33: Pre-tax income | B33: =B24+B32 -> -6.657 | C33: =C24+C32 -> 0.301 | D33: =D24+D32 -> 2.55 | E33: =E24+E32 -> 13.742 | F33: =F24+F32 -> -6.449 | G33: =G24+G32 -> -0.703 | H33: =H24+H32 -> 2.432 | I33: =I24+I32 -> 16.065 | ... AS33: =AS24+AS32 -> 34.057113 | AU33: =AU24-AU32 -> 5.212 | AV33: =AV24-AV32 -> 8.257 | AW33: =AW24-AW32 -> -29.036 | AX33: =AX24-AX32 -> -2.787 | AY33: =AY24-AY32 -> 28.818 | AZ33: =AZ24-AZ32 -> 22.783 | BA33: =BA24-BA32 -> -2.16 | BB33: =SUM(AD33:AG33) -> 53.526 | BC33: =SUM(AH33:AK33) -> 36.671 | BD33: =SUM(AL33:AO33) -> 43.063119 | BE33: =SUM(AP33:AS33) -> 89.220244
A34: Provision for (benefit from) income taxes | B34: =B118-B157 -> 0.2 | C34: =C118-C157 -> 0.58 | D34: =D118-D157 -> 0.759 | E34: =E118-E157 -> 1.248 | F34: =F118-F157 -> 0.527 | G34: =G118-G157 -> 0.567 | H34: =H118-H157 -> 0.583 | I34: =I118-I157 -> -1.264 | ... AK34: =AK118-AK157 -> 2.983 | AL34: 7 | AM34: 7 | AN34: 9 | AO34: 10 | AP34: 9 | AQ34: 8 | AR34: 9 | AS34: 12 | AU34: =SUM(B34:E34) -> 2.787 | AV34: =SUM(F34:I34) -> 0.413 | AW34: =SUM(J34:M34) -> 2.388 | AX34: =SUM(N34:Q34) -> 1.546 | AY34: =SUM(R34:U34) -> 6.022 | AZ34: =SUM(V34:Y34) -> 13.703 | BA34: =SUM(Z34:AC34) -> 13.998 | BB34: =SUM(AD34:AG34) -> 12.758 | BC34: =SUM(AH34:AK34) -> 12.613 | BD34: =SUM(AL34:AO34) -> 33 | BE34: =SUM(AP34:AS34) -> 38
A35: Adjusted tax rate (non-GAAP) | B35: =+B34/B33 -> -0.030043563 | C35: =+C34/C33 -> 1.9269103 | D35: =+D34/D33 -> 0.29764706 | E35: =+E34/E33 -> 0.090816475 | F35: =+F34/F33 -> -0.081718096 | G35: =+G34/G33 -> -0.80654339 | H35: =+H34/H33 -> 0.23972039 | I35: =+I34/I33 -> -0.078680361 | ... S35: =+S34/S33 -> 6.3541667 | T35: =T34/T33 -> 0.21254355 | U35: =U34/U33 -> 0.14046745 | V35: =V34/V33 -> -0.16152616 | W35: =W34/W33 -> 1.0665829 | X35: =X34/X33 -> 0.45259392 | Y35: =Y34/Y33 -> 0.16132139 | Z35: =Z34/Z33 -> 1.026699 | AA35: =AA34/AA33 -> 0.87230553 | ... AK35: =AK34/AK33 -> 0.21118584 | AL35: NA | AM35: =AM34/AM33 -> 0.54320113 | AN35: =AN34/AN33 -> 0.70971991 | AO35: =AO34/AO33 -> 0.55034212 | AP35: NA | AQ35: =AQ34/AQ33 -> 0.38427009 | AR35: =AR34/AR33 -> 0.37205333 | AS35: =AS34/AS33 -> 0.35234931 | AU35: =SUM(B35:E35) -> 2.2853303 | AV35: =SUM(F35:I35) -> -0.72722145 | AW35: =+AW34/AW33 -> -0.082242733 | AX35: =+AX34/AX33 -> -0.55471834 | AY35: =+AY34/AY33 -> 0.20896662 | AZ35: =+AZ34/AZ33 -> 0.60145723 | BA35: =+BA34/BA33 -> -6.4805556 | BB35: =+BB34/BB33 -> 0.23835146 | BC35: =+BC34/BC33 -> 0.34395026 | BD35: =+BD34/BD33 -> 0.76631699 | BE35: =+BE34/BE33 -> 0.42591231
A36: Non-GAAP Net income | B36: =B33-B34 -> -6.857 | C36: =C33-C34 -> -0.279 | D36: =D33-D34 -> 1.791 | E36: =E33-E34 -> 12.494 | F36: =F33-F34 -> -6.976 | G36: =G33-G34 -> -1.27 | H36: =H33-H34 -> 1.849 | I36: =I33-I34 -> 17.329 | ... AS36: =AS33-AS34 -> 22.057113 | AU36: =SUM(B36:E36) -> 7.149 | AV36: =SUM(F36:I36) -> 10.932 | AW36: =SUM(J36:M36) -> -27.752 | AX36: =SUM(N36:Q36) -> -7.655 | AY36: =SUM(R36:U36) -> 15.642 | AZ36: =SUM(V36:Y36) -> 22.582 | BA36: =SUM(Z36:AC36) -> 45.648 | BB36: =SUM(AD36:AG36) -> 40.768 | BC36: =SUM(AH36:AK36) -> 24.058 | BD36: =SUM(AL36:AO36) -> 10.063119 | BE36: =SUM(AP36:AS36) -> 51.220244
A37: Consensus net income | B37: ='[2]VA Consensus'!C38 -> -6.073 | C37: ='[2]VA Consensus'!D38 -> -2.1934727 | D37: ='[2]VA Consensus'!E38 -> -0.18276962 | E37: ='[2]VA Consensus'!F38 -> 9.0058586 | F37: ='[2]VA Consensus'!G38 -> -8.7710332 | G37: ='[2]VA Consensus'!H38 -> -1.4526579 | H37: ='[2]VA Consensus'!I38 -> -0.0065381036 | I37: ='[2]VA Consensus'!J38 -> 10.895775 | ... AS37: ='[2]VA Consensus'!AT38 -> 19.194259 | AU37: ='[2]VA Consensus'!AV38 -> 5.0968586 | AV37: ='[2]VA Consensus'!AW38 -> 3.7547752 | AW37: ='[2]VA Consensus'!AX38 -> -28.186719 | AX37: ='[2]VA Consensus'!AY38 -> -15.724899 | AY37: ='[2]VA Consensus'!AZ38 -> 12.498401 | AZ37: ='[2]VA Consensus'!BA38 -> 17.97807 | BA37: ='[2]VA Consensus'!BB38 -> 40.2844 | BB37: ='[2]VA Consensus'!BC38 -> 35.368007 | ... BE37: ='[2]VA Consensus'!BF38 -> 53.635204
A39: Non-GAAP EPS | B39: =IF(B36<0,B36/B45,B36/B46) -> -0.25442276 | C39: =IF(C36<0,C36/C45,C36/C46) -> -0.010211612 | D39: =IF(D36<0,D36/D45,D36/D46) -> 0.058126419 | E39: =IF(E36<0,E36/E45,E36/E46) -> 0.40145485 | F39: =IF(F36<0,F36/F45,F36/F46) -> -0.24595875 | G39: =IF(G36<0,G36/G45,G36/G46) -> -0.043913769 | H39: =IF(H36<0,H36/H45,H36/H46) -> 0.056848473 | I39: =IF(I36<0,I36/I45,I36/I46) -> 0.53309466 | ... AS39: =IF(AS36<0,AS36/AS45,AS36/AS46) -> 0.14994853 | AU39: =IF(AU36<0,AU36/AU45,AU36/AU46) -> 0.23170088 | AV39: =IF(AV36<0,AV36/AV45,AV36/AV46) -> 0.33863562 | AW39: =IF(AW36<0,AW36/AW45,AW36/AW46) -> -0.91719681 | AX39: =IF(AX36<0,AX36/AX45,AX36/AX46) -> -0.081145348 | AY39: =IF(AY36<0,AY36/AY45,AY36/AY46) -> 0.13378442 | AZ39: =IF(AZ36<0,AZ36/AZ45,AZ36/AZ46) -> 0.17888503 | BA39: =IF(BA36<0,BA36/BA45,BA36/BA46) -> 0.36063612 | BB39: =IF(BB36<0,BB36/BB45,BB36/BB46) -> 0.3108822 | ... BE39: =IF(BE36<0,BE36/BE45,BE36/BE46) -> 0.34981037
A40: Consensus non-GAAP EPS | B40: ='[2]VA Consensus'!C40 -> - | C40: ='[2]VA Consensus'!D40 -> - | D40: ='[2]VA Consensus'!E40 -> - | E40: ='[2]VA Consensus'!F40 -> - | F40: ='[2]VA Consensus'!G40 -> - | G40: ='[2]VA Consensus'!H40 -> - | H40: ='[2]VA Consensus'!I40 -> - | I40: ='[2]VA Consensus'!J40 -> - | ... AS40: ='[2]VA Consensus'!AT40 -> 0.1372202 | AU40: ='[2]VA Consensus'!AV40 -> - | AV40: ='[2]VA Consensus'!AW40 -> - | AW40: ='[2]VA Consensus'!AX40 -> - | AX40: ='[2]VA Consensus'!AY40 -> - | AY40: ='[2]VA Consensus'!AZ40 -> 0.10804504 | AZ40: ='[2]VA Consensus'!BA40 -> 0.14261232 | BA40: ='[2]VA Consensus'!BB40 -> 0.32030295 | BB40: ='[2]VA Consensus'!BC40 -> 0.26695732 | ... BE40: ='[2]VA Consensus'!BF40 -> 0.38567577
A41: Management Guidance - Non-GAAP EPS
A42: Low | N42: -0.19 | O42: -0.12 | P42: -0.05 | Q42: 0.03 | R42: -0.14 | S42: -0.04 | T42: 0.01 | U42: 0.12 | V42: -0.11 | W42: -0.02 | X42: 0.05 | Y42: 0.17 | Z42: -0.05 | AA42: 0.01 | AB42: 0.02 | AC42: 0.22 | AD42: -0.1 | AE42: -0.03 | AF42: 0.07 | AG42: 0.13 | AH42: -0.06 | AI42: 0 | AJ42: 0.04 | AK42: 0.02 | AL42: -0.06 | AY42: 0.1 | AZ42: 0.14 | BA42: 0.31 | BB42: 0.26 | BC42: 0.12 | BD42: 0.06
A43: Mid | N43: =AVERAGE(N42,N44) -> -0.185 | O43: =AVERAGE(O42,O44) -> -0.115 | P43: =AVERAGE(P42,P44) -> -0.045 | Q43: =AVERAGE(Q42,Q44) -> 0.035 | R43: =AVERAGE(R42,R44) -> -0.135 | S43: =AVERAGE(S42,S44) -> -0.035 | T43: =AVERAGE(T42,T44) -> 0.015 | U43: =AVERAGE(U42,U44) -> 0.125 | ... AB43: =AVERAGE(AB42,AB44) -> 0.025 | AC43: =IFERROR(AVERAGE(AC42,AC44),"") -> 0.23 | AD43: =IFERROR(AVERAGE(AD42,AD44),"") -> -0.095 | AE43: =IFERROR(AVERAGE(AE42,AE44),"") -> -0.025 | AF43: =IFERROR(AVERAGE(AF42,AF44),"") -> 0.075 | AG43: =IFERROR(AVERAGE(AG42,AG44),"") -> 0.135 | AH43: =IFERROR(AVERAGE(AH42,AH44),"") -> -0.05 | AI43: =IFERROR(AVERAGE(AI42,AI44),"") -> 0.005 | AJ43: =IFERROR(AVERAGE(AJ42,AJ44),"") -> 0.05 | ... AS43: =IFERROR(AVERAGE(AS42,AS44),"") | AY43: =AVERAGE(AY42,AY44) -> 0.105 | AZ43: =AVERAGE(AZ42,AZ44) -> 0.145 | BA43: =AVERAGE(BA42,BA44) -> 0.32 | BB43: =IFERROR(AVERAGE(BB42,BB44),"") -> 0.265 | BC43: =IFERROR(AVERAGE(BC42,BC44),"") -> 0.125 | BD43: =IFERROR(AVERAGE(BD42,BD44),"") -> 0.08 | BE43: =IFERROR(AVERAGE(BE42,BE44),"")
A44: High | N44: -0.18 | O44: -0.11 | P44: -0.04 | Q44: 0.04 | R44: -0.13 | S44: -0.03 | T44: 0.02 | U44: 0.13 | V44: -0.1 | W44: -0.01 | X44: 0.06 | Y44: 0.18 | Z44: -0.04 | AA44: 0.02 | AB44: 0.03 | AC44: 0.24 | AD44: -0.09 | AE44: -0.02 | AF44: 0.08 | AG44: 0.14 | AH44: -0.04 | AI44: 0.01 | AJ44: 0.06 | AK44: 0.04 | AL44: -0.05 | AY44: 0.11 | AZ44: 0.15 | BA44: 0.33 | BB44: 0.27 | BC44: 0.13 | BD44: 0.1
A45: Basic shares outstanding | B45: =B123 -> 26.951205 | C45: =C123 -> 27.321837 | D45: =D123 -> 27.595461 | E45: =E123 -> 27.987216 | F45: =F123 -> 28.362479 | G45: =G123 -> 28.920314 | H45: =H123 -> 29.281701 | I45: =I123 -> 29.498904 | ... AI45: =AI123 -> 112.05472 | AJ45: =AI45+1.1 -> 113.15471 | AK45: =AK123 -> 117.8548 | AL45: =AK45+1.1 -> 118.9548 | AM45: =AL45+1.1 -> 120.0548 | AN45: =AM45+1.1 -> 121.1548 | AO45: =AN45+1.1 -> 122.2548 | AP45: =AO45+1.1 -> 123.3548 | AQ45: =AP45+1.1 -> 124.4548 | AR45: =AQ45+1.1 -> 125.5548 | AS45: =AR45+1.1 -> 126.6548 | AU45: =AU123 -> 27.46744 | AV45: =AV123 -> 29.020645 | AW45: =AW123 -> 30.25741 | AX45: =AX123 -> 94.336893 | AY45: =AY123 -> 105.30596 | AZ45: =AVERAGE(V45:Y45) -> 109.27289 | BA45: =AVERAGE(Z45:AC45) -> 109.14125 | BB45: =AVERAGE(AD45:AG45) -> 111.658 | BC45: =AVERAGE(AH45:AK45) -> 113.92885 | BD45: =AVERAGE(AL45:AO45) -> 120.6048 | BE45: =AVERAGE(AP45:AS45) -> 125.0048
A46: Diluted shares outstanding | B46: =B124 -> 26.951205 | C46: =C124 -> 30.545216 | D46: =D124 -> 30.812151 | E46: =E124 -> 31.121806 | F46: =F45 -> 28.362479 | G46: =G45 -> 28.920314 | H46: =H124 -> 32.52506 | I46: =I124 -> 32.506422 | J46: =J45 -> 29.827927 | K46: =K45 -> 30.284421 | L46: =L45 -> 30.380154 | M46: =M124 -> 30.524694 | N46: =N124 -> 92.679 | O46: =O124 -> 94.482873 | P46: =P124 -> 106.1335 | Q46: =Q124 -> 108.37172 | R46: 116.5 | S46: 118 | T46: =T124 -> 119.07061 | U46: =U124 -> 118.64997 | V46: 125.1 | W46: 126.9 | X46: =X124 -> 126.93984 | Y46: =Y124 -> 126.01019 | Z46: =Z124 -> 126.2 | AA46: =AA124 -> 127.29488 | AB46: =AB124 -> 126.74861 | AC46: =AC124 -> 126.06187 | AD46: =AD124 -> 126.71187 | AE46: =AE124 -> 128.02364 | ... AI46: =AI124 -> 135.15821 | AJ46: =AI46-1.2 -> 133.95821 | AK46: =AK124 -> 133.29789 | AL46: =AK46-15 -> 118.29789 | AM46: =AL46+15 -> 133.29789 | AN46: =AM46+6 -> 139.29789 | AO46: =AN46+6 -> 145.29789 | AP46: =AO46+0.45 -> 145.74789 | AQ46: =AP46+0.45 -> 146.19789 | AR46: =AQ46+0.45 -> 146.64789 | AS46: =AR46+0.45 -> 147.09789 | AU46: =AU124 -> 30.854436 | AV46: =AV124 -> 32.282487 | AW46: =AW124 -> 30.25741 | AX46: =AX124 -> 94.336893 | AY46: =AY124 -> 116.91945 | AZ46: =AVERAGE(V46:Y46) -> 126.23751 | BA46: =AVERAGE(Z46:AC46) -> 126.57634 | BB46: =AVERAGE(AD46:AG46) -> 131.13649 | BC46: =AVERAGE(AH46:AK46) -> 134.7883 | BD46: =AVERAGE(AL46:AO46) -> 134.04789 | BE46: =AVERAGE(AP46:AS46) -> 146.42289
B48: =B3 -> 2017 | F48: =F3 -> 2018 | J48: =J3 -> 2019 | N48: =N3 -> 2020 | R48: =R3 -> 2021 | V48: =V3 -> 2022 | Z48: =Z3 -> 2023 | AD48: =AD3 -> 2024 | AH48: =AH3 -> 2025 | AL48: =AL3 -> 2026 | AP48: =AP3 -> 2027
B49: =B4 -> 42825 | C49: =C4 -> 42916 | D49: =D4 -> 43008 | E49: =E4 -> 43100 | F49: =F4 -> 43190 | G49: =G4 -> 43281 | H49: =H4 -> 43373 | I49: =I4 -> 43465 | ... AS49: =AS4 -> Dec-27E | AU49: =AU4 -> 2017 | AV49: =AV4 -> 2018 | AW49: =AW4 -> 2019 | AX49: =AX4 -> 2020 | AY49: =AY4 -> 2021 | AZ49: =AZ4 -> 2022 | BA49: =BA4 -> 2023 | BB49: =BB4 -> 2024 | ... BE49: =BE4 -> 2027E
A50: Y/Y %
A51: Total Revenue | F51: =IF(OR(B8<=0,F8<=0),"NM",(F8-B8)/B8) -> 0.35195615 | G51: =IF(OR(C8<=0,G8<=0),"NM",(G8-C8)/C8) -> 0.25811738 | H51: =IF(OR(D8<=0,H8<=0),"NM",(H8-D8)/D8) -> 0.25647897 | I51: =IF(OR(E8<=0,I8<=0),"NM",(I8-E8)/E8) -> 0.19886029 | J51: =IF(OR(F8<=0,J8<=0),"NM",(J8-F8)/F8) -> 0.05290689 | K51: =IF(OR(G8<=0,K8<=0),"NM",(K8-G8)/G8) -> -0.041308892 | L51: =IF(OR(H8<=0,L8<=0),"NM",(L8-H8)/H8) -> -0.020924059 | M51: =IF(OR(I8<=0,M8<=0),"NM",(M8-I8)/I8) -> -0.17091341 | ... AS51: =IF(OR(AO8<=0,AS8<=0),"NM",(AS8-AO8)/AO8) -> 0.18407518 | AV51: =IF(OR(AU8<=0,AV8<=0),"NM",(AV8-AU8)/AU8) -> 0.2548772 | AW51: =IF(OR(AV8<=0,AW8<=0),"NM",(AW8-AV8)/AV8) -> -0.059558693 | AX51: =IF(OR(AW8<=0,AX8<=0),"NM",(AX8-AW8)/AW8) -> 0.15145757 | AY51: =IF(OR(AX8<=0,AY8<=0),"NM",(AY8-AX8)/AX8) -> 0.33293018 | AZ51: =IF(OR(AY8<=0,AZ8<=0),"NM",(AZ8-AY8)/AY8) -> 0.21402903 | BA51: =IF(OR(AZ8<=0,BA8<=0),"NM",(BA8-AZ8)/AZ8) -> 0.053893935 | BB51: =IF(OR(BA8<=0,BB8<=0),"NM",(BB8-BA8)/BA8) -> 0.10375431 | BC51: =IF(OR(BB8<=0,BC8<=0),"NM",(BC8-BB8)/BB8) -> 0.13173972 | ... BE51: =IF(OR(BD8<=0,BE8<=0),"NM",(BE8-BD8)/BD8) -> 0.21993668
A52: Total cost of revenue | F52: =IF(OR(B15<=0,F15<=0),"NM",(F15-B15)/B15) -> 0.3113016 | G52: =IF(OR(C15<=0,G15<=0),"NM",(G15-C15)/C15) -> 0.2824195 | H52: =IF(OR(D15<=0,H15<=0),"NM",(H15-D15)/D15) -> 0.28465298 | I52: =IF(OR(E15<=0,I15<=0),"NM",(I15-E15)/E15) -> 0.34882429 | J52: =IF(OR(F15<=0,J15<=0),"NM",(J15-F15)/F15) -> 0.30483399 | K52: =IF(OR(G15<=0,K15<=0),"NM",(K15-G15)/G15) -> 0.2894469 | L52: =IF(OR(H15<=0,L15<=0),"NM",(L15-H15)/H15) -> 0.23588495 | M52: =IF(OR(I15<=0,M15<=0),"NM",(M15-I15)/I15) -> 0.24118051 | ... AS52: =IF(OR(AO15<=0,AS15<=0),"NM",(AS15-AO15)/AO15) -> 0.13981069 | AV52: =IF(OR(AU15<=0,AV15<=0),"NM",(AV15-AU15)/AU15) -> 0.30790483 | AW52: =IF(OR(AV15<=0,AW15<=0),"NM",(AW15-AV15)/AV15) -> 0.26542268 | AX52: =IF(OR(AW15<=0,AX15<=0),"NM",(AX15-AW15)/AW15) -> 0.19593174 | AY52: =IF(OR(AX15<=0,AY15<=0),"NM",(AY15-AX15)/AX15) -> 0.23610608 | AZ52: =IF(OR(AY15<=0,AZ15<=0),"NM",(AZ15-AY15)/AY15) -> 0.19188624 | BA52: =IF(OR(AZ15<=0,BA15<=0),"NM",(BA15-AZ15)/AZ15) -> 0.098322689 | BB52: =IF(OR(BA15<=0,BB15<=0),"NM",(BB15-BA15)/BA15) -> 0.38587859 | BC52: =IF(OR(BB15<=0,BC15<=0),"NM",(BC15-BB15)/BB15) -> 0.43595832 | ... BE52: =IF(OR(BD15<=0,BE15<=0),"NM",(BE15-BD15)/BD15) -> 0.17522792
A53: Gross profit | F53: =IF(OR(B16<=0,F16<=0),"NM",(F16-B16)/B16) -> 0.35708191 | G53: =IF(OR(C16<=0,G16<=0),"NM",(G16-C16)/C16) -> 0.25562618 | H53: =IF(OR(D16<=0,H16<=0),"NM",(H16-D16)/D16) -> 0.25349223 | I53: =IF(OR(E16<=0,I16<=0),"NM",(I16-E16)/E16) -> 0.1868787 | J53: =IF(OR(F16<=0,J16<=0),"NM",(J16-F16)/F16) -> 0.022215236 | K53: =IF(OR(G16<=0,K16<=0),"NM",(K16-G16)/G16) -> -0.0759379 | L53: =IF(OR(H16<=0,L16<=0),"NM",(L16-H16)/H16) -> -0.048825251 | M53: =IF(OR(I16<=0,M16<=0),"NM",(M16-I16)/I16) -> -0.20833074 | ... AS53: =IF(OR(AO16<=0,AS16<=0),"NM",(AS16-AO16)/AO16) -> 0.19612684 | AV53: =IF(OR(AU16<=0,AV16<=0),"NM",(AV16-AU16)/AU16) -> 0.24958513 | AW53: =IF(OR(AV16<=0,AW16<=0),"NM",(AW16-AV16)/AV16) -> -0.093504955 | AX53: =IF(OR(AW16<=0,AX16<=0),"NM",(AX16-AW16)/AW16) -> 0.14497255 | AY53: =IF(OR(AX16<=0,AY16<=0),"NM",(AY16-AX16)/AX16) -> 0.347677 | AZ53: =IF(OR(AY16<=0,AZ16<=0),"NM",(AZ16-AY16)/AY16) -> 0.21712229 | BA53: =IF(OR(AZ16<=0,BA16<=0),"NM",(BA16-AZ16)/AZ16) -> 0.04781609 | BB53: =IF(OR(BA16<=0,BB16<=0),"NM",(BB16-BA16)/BA16) -> 0.063299432 | BC53: =IF(OR(BB16<=0,BC16<=0),"NM",(BC16-BB16)/BB16) -> 0.074882484 | ... BE53: =IF(OR(BD16<=0,BE16<=0),"NM",(BE16-BD16)/BD16) -> 0.23231647
A54: Research and development | F54: =IF(OR(B20<=0,F20<=0),"NM",(F20-B20)/B20) -> 0.44656736 | G54: =IF(OR(C20<=0,G20<=0),"NM",(G20-C20)/C20) -> 0.43637078 | H54: =IF(OR(D20<=0,H20<=0),"NM",(H20-D20)/D20) -> 0.44296325 | I54: =IF(OR(E20<=0,I20<=0),"NM",(I20-E20)/E20) -> 0.39693651 | J54: =IF(OR(F20<=0,J20<=0),"NM",(J20-F20)/F20) -> 0.19647787 | K54: =IF(OR(G20<=0,K20<=0),"NM",(K20-G20)/G20) -> 0.10623462 | L54: =IF(OR(H20<=0,L20<=0),"NM",(L20-H20)/H20) -> 0.11449122 | M54: =IF(OR(I20<=0,M20<=0),"NM",(M20-I20)/I20) -> 0.079349172 | ... AS54: =IF(OR(AO20<=0,AS20<=0),"NM",(AS20-AO20)/AO20) -> 0.13671217 | AV54: =IF(OR(AU20<=0,AV20<=0),"NM",(AV20-AU20)/AU20) -> 0.42888366 | AW54: =IF(OR(AV20<=0,AW20<=0),"NM",(AW20-AV20)/AV20) -> 0.12083929 | AX54: =IF(OR(AW20<=0,AX20<=0),"NM",(AX20-AW20)/AW20) -> 0.12960216 | AY54: =IF(OR(AX20<=0,AY20<=0),"NM",(AY20-AX20)/AX20) -> 0.26377855 | AZ54: =IF(OR(AY20<=0,AZ20<=0),"NM",(AZ20-AY20)/AY20) -> 0.29361583 | BA54: =IF(OR(AZ20<=0,BA20<=0),"NM",(BA20-AZ20)/AZ20) -> 0.071777983 | BB54: =IF(OR(BA20<=0,BB20<=0),"NM",(BB20-BA20)/BA20) -> 0.15711491 | BC54: =IF(OR(BB20<=0,BC20<=0),"NM",(BC20-BB20)/BB20) -> 0.21349137 | ... BE54: =IF(OR(BD20<=0,BE20<=0),"NM",(BE20-BD20)/BD20) -> 0.17267875
A55: Sales and marketing | F55: =IF(OR(B21<=0,F21<=0),"NM",(F21-B21)/B21) -> 0.24057331 | G55: =IF(OR(C21<=0,G21<=0),"NM",(G21-C21)/C21) -> 0.21935312 | H55: =IF(OR(D21<=0,H21<=0),"NM",(H21-D21)/D21) -> 0.21089868 | I55: =IF(OR(E21<=0,I21<=0),"NM",(I21-E21)/E21) -> 0.13492175 | J55: =IF(OR(F21<=0,J21<=0),"NM",(J21-F21)/F21) -> 0.050252818 | K55: =IF(OR(G21<=0,K21<=0),"NM",(K21-G21)/G21) -> 0.032119856 | L55: =IF(OR(H21<=0,L21<=0),"NM",(L21-H21)/H21) -> 0.033317028 | M55: =IF(OR(I21<=0,M21<=0),"NM",(M21-I21)/I21) -> -0.0016645963 | ... AS55: =IF(OR(AO21<=0,AS21<=0),"NM",(AS21-AO21)/AO21) -> 0.11187548 | AV55: =IF(OR(AU21<=0,AV21<=0),"NM",(AV21-AU21)/AU21) -> 0.19809228 | AW55: =IF(OR(AV21<=0,AW21<=0),"NM",(AW21-AV21)/AV21) -> 0.027600223 | AX55: =IF(OR(AW21<=0,AX21<=0),"NM",(AX21-AW21)/AW21) -> -0.010932849 | AY55: =IF(OR(AX21<=0,AY21<=0),"NM",(AY21-AX21)/AX21) -> 0.22507969 | AZ55: =IF(OR(AY21<=0,AZ21<=0),"NM",(AZ21-AY21)/AY21) -> 0.18851541 | BA55: =IF(OR(AZ21<=0,BA21<=0),"NM",(BA21-AZ21)/AZ21) -> 0.032805163 | BB55: =IF(OR(BA21<=0,BB21<=0),"NM",(BB21-BA21)/BA21) -> 0.071113861 | BC55: =IF(OR(BB21<=0,BC21<=0),"NM",(BC21-BB21)/BB21) -> 0.063270498 | ... BE55: =IF(OR(BD21<=0,BE21<=0),"NM",(BE21-BD21)/BD21) -> 0.15509332
A56: General and administrative | F56: =IF(OR(B22<=0,F22<=0),"NM",(F22-B22)/B22) -> 0.25167187 | G56: =IF(OR(C22<=0,G22<=0),"NM",(G22-C22)/C22) -> 0.15243902 | H56: =IF(OR(D22<=0,H22<=0),"NM",(H22-D22)/D22) -> 0.20290922 | I56: =IF(OR(E22<=0,I22<=0),"NM",(I22-E22)/E22) -> 0.13970476 | J56: =IF(OR(F22<=0,J22<=0),"NM",(J22-F22)/F22) -> 0.19430098 | K56: =IF(OR(G22<=0,K22<=0),"NM",(K22-G22)/G22) -> 0.15195106 | L56: =IF(OR(H22<=0,L22<=0),"NM",(L22-H22)/H22) -> 0.12444512 | M56: =IF(OR(I22<=0,M22<=0),"NM",(M22-I22)/I22) -> -0.011750567 | ... AS56: =IF(OR(AO22<=0,AS22<=0),"NM",(AS22-AO22)/AO22) -> 0.04477222 | AV56: =IF(OR(AU22<=0,AV22<=0),"NM",(AV22-AU22)/AU22) -> 0.18168016 | AW56: =IF(OR(AV22<=0,AW22<=0),"NM",(AW22-AV22)/AV22) -> 0.10648238 | AX56: =IF(OR(AW22<=0,AX22<=0),"NM",(AX22-AW22)/AW22) -> 0.082582688 | AY56: =IF(OR(AX22<=0,AY22<=0),"NM",(AY22-AX22)/AX22) -> 0.14392043 | AZ56: =IF(OR(AY22<=0,AZ22<=0),"NM",(AZ22-AY22)/AY22) -> 0.19258417 | BA56: =IF(OR(AZ22<=0,BA22<=0),"NM",(BA22-AZ22)/AZ22) -> 0.10814095 | BB56: =IF(OR(BA22<=0,BB22<=0),"NM",(BB22-BA22)/BA22) -> 0.070884933 | BC56: =IF(OR(BB22<=0,BC22<=0),"NM",(BC22-BB22)/BB22) -> 0.11869341 | ... BE56: =IF(OR(BD22<=0,BE22<=0),"NM",(BE22-BD22)/BD22) -> 0.14884929
A57: Total operating expenses | F57: =IF(OR(B23<=0,F23<=0),"NM",(F23-B23)/B23) -> 0.28687982 | G57: =IF(OR(C23<=0,G23<=0),"NM",(G23-C23)/C23) -> 0.26022338 | H57: =IF(OR(D23<=0,H23<=0),"NM",(H23-D23)/D23) -> 0.26257502 | I57: =IF(OR(E23<=0,I23<=0),"NM",(I23-E23)/E23) -> 0.19422655 | J57: =IF(OR(F23<=0,J23<=0),"NM",(J23-F23)/F23) -> 0.10112649 | K57: =IF(OR(G23<=0,K23<=0),"NM",(K23-G23)/G23) -> 0.063677599 | L57: =IF(OR(H23<=0,L23<=0),"NM",(L23-H23)/H23) -> 0.064529367 | M57: =IF(OR(I23<=0,M23<=0),"NM",(M23-I23)/I23) -> 0.018407468 | ... AS57: =IF(OR(AO23<=0,AS23<=0),"NM",(AS23-AO23)/AO23) -> 0.11255386 | AV57: =IF(OR(AU23<=0,AV23<=0),"NM",(AV23-AU23)/AU23) -> 0.24779706 | AW57: =IF(OR(AV23<=0,AW23<=0),"NM",(AW23-AV23)/AV23) -> 0.060096031 | AX57: =IF(OR(AW23<=0,AX23<=0),"NM",(AX23-AW23)/AW23) -> 0.037780776 | AY57: =IF(OR(AX23<=0,AY23<=0),"NM",(AY23-AX23)/AX23) -> 0.22682056 | AZ57: =IF(OR(AY23<=0,AZ23<=0),"NM",(AZ23-AY23)/AY23) -> 0.22086712 | BA57: =IF(OR(AZ23<=0,BA23<=0),"NM",(BA23-AZ23)/AZ23) -> 0.053507585 | BB57: =IF(OR(BA23<=0,BB23<=0),"NM",(BB23-BA23)/BA23) -> 0.099225878 | BC57: =IF(OR(BB23<=0,BC23<=0),"NM",(BC23-BB23)/BB23) -> 0.12116676 | ... BE57: =IF(OR(BD23<=0,BE23<=0),"NM",(BE23-BD23)/BD23) -> 0.16062743
A58: Operating income | F58: =IF(OR(B24<=0,F24<=0),"NM",(F24-B24)/B24) -> NM | G58: =IF(OR(C24<=0,G24<=0),"NM",(G24-C24)/C24) -> NM | H58: =IF(OR(D24<=0,H24<=0),"NM",(H24-D24)/D24) -> 0.03526971 | I58: =IF(OR(E24<=0,I24<=0),"NM",(I24-E24)/E24) -> 0.1572163 | J58: =IF(OR(F24<=0,J24<=0),"NM",(J24-F24)/F24) -> NM | K58: =IF(OR(G24<=0,K24<=0),"NM",(K24-G24)/G24) -> NM | L58: =IF(OR(H24<=0,L24<=0),"NM",(L24-H24)/H24) -> NM | M58: =IF(OR(I24<=0,M24<=0),"NM",(M24-I24)/I24) -> NM | ... AS58: =IF(OR(AO24<=0,AS24<=0),"NM",(AS24-AO24)/AO24) -> 1.714709 | AV58: =IF(OR(AU24<=0,AV24<=0),"NM",(AV24-AU24)/AU24) -> 0.29403222 | AW58: =IF(OR(AV24<=0,AW24<=0),"NM",(AW24-AV24)/AV24) -> NM | AX58: =IF(OR(AW24<=0,AX24<=0),"NM",(AX24-AW24)/AW24) -> NM | AY58: =IF(OR(AX24<=0,AY24<=0),"NM",(AY24-AX24)/AX24) -> NM | AZ58: =IF(OR(AY24<=0,AZ24<=0),"NM",(AZ24-AY24)/AY24) -> 0.17008042 | BA58: =IF(OR(AZ24<=0,BA24<=0),"NM",(BA24-AZ24)/AZ24) -> -0.026782691 | BB58: =IF(OR(BA24<=0,BB24<=0),"NM",(BB24-BA24)/BA24) -> -0.44643913 | BC58: =IF(OR(BB24<=0,BC24<=0),"NM",(BC24-BB24)/BB24) -> NM | ... BE58: =IF(OR(BD24<=0,BE24<=0),"NM",(BE24-BD24)/BD24) -> 14.830759
A59: Net income | F59: =IF(OR(B36<=0,F36<=0),"NM",(F36-B36)/B36) -> NM | G59: =IF(OR(C36<=0,G36<=0),"NM",(G36-C36)/C36) -> NM | H59: =IF(OR(D36<=0,H36<=0),"NM",(H36-D36)/D36) -> 0.032384143 | I59: =IF(OR(E36<=0,I36<=0),"NM",(I36-E36)/E36) -> 0.38698575 | J59: =IF(OR(F36<=0,J36<=0),"NM",(J36-F36)/F36) -> NM | K59: =IF(OR(G36<=0,K36<=0),"NM",(K36-G36)/G36) -> NM | L59: =IF(OR(H36<=0,L36<=0),"NM",(L36-H36)/H36) -> NM | M59: =IF(OR(I36<=0,M36<=0),"NM",(M36-I36)/I36) -> NM | ... AK59: =IF(OR(AG36<=0,AK36<=0),"NM",(AK36-AG36)/AG36) -> -0.53398302 | AL59: NM | AM59: =IF(OR(AI36<=0,AM36<=0),"NM",(AM36-AI36)/AI36) -> 0.53736516 | AN59: =IF(OR(AJ36<=0,AN36<=0),"NM",(AN36-AJ36)/AJ36) -> -0.56276768 | AO59: =IF(OR(AK36<=0,AO36<=0),"NM",(AO36-AK36)/AK36) -> -0.2666922 | AP59: NM | AQ59: =IF(OR(AM36<=0,AQ36<=0),"NM",(AQ36-AM36)/AM36) -> 1.1776158 | AR59: =IF(OR(AN36<=0,AR36<=0),"NM",(AR36-AN36)/AN36) -> 3.1265518 | AS59: =IF(OR(AO36<=0,AS36<=0),"NM",(AS36-AO36)/AO36) -> 1.6995986 | AV59: =IF(OR(AU36<=0,AV36<=0),"NM",(AV36-AU36)/AU36) -> 0.52916492 | AW59: =IF(OR(AV36<=0,AW36<=0),"NM",(AW36-AV36)/AV36) -> NM | AX59: =IF(OR(AW36<=0,AX36<=0),"NM",(AX36-AW36)/AW36) -> NM | AY59: =IF(OR(AX36<=0,AY36<=0),"NM",(AY36-AX36)/AX36) -> NM | AZ59: =IF(OR(AY36<=0,AZ36<=0),"NM",(AZ36-AY36)/AY36) -> 0.44367728 | BA59: =IF(OR(AZ36<=0,BA36<=0),"NM",(BA36-AZ36)/AZ36) -> 1.021433 | BB59: =IF(OR(BA36<=0,BB36<=0),"NM",(BB36-BA36)/BA36) -> -0.10690501 | BC59: =IF(OR(BB36<=0,BC36<=0),"NM",(BC36-BB36)/BB36) -> -0.4098803 | ... BE59: =IF(OR(BD36<=0,BE36<=0),"NM",(BE36-BD36)/BD36) -> 4.0898974
A60: EPS | F60: =IF(OR(B39<=0,F39<=0),"NM",(F39-B39)/B39) -> NM | G60: =IF(OR(C39<=0,G39<=0),"NM",(G39-C39)/C39) -> NM | H60: =IF(OR(D39<=0,H39<=0),"NM",(H39-D39)/D39) -> -0.021985629 | I60: =IF(OR(E39<=0,I39<=0),"NM",(I39-E39)/E39) -> 0.32790688 | J60: =IF(OR(F39<=0,J39<=0),"NM",(J39-F39)/F39) -> NM | K60: =IF(OR(G39<=0,K39<=0),"NM",(K39-G39)/G39) -> NM | L60: =IF(OR(H39<=0,L39<=0),"NM",(L39-H39)/H39) -> NM | M60: =IF(OR(I39<=0,M39<=0),"NM",(M39-I39)/I39) -> NM | ... AK60: =IF(OR(AG39<=0,AK39<=0),"NM",(AK39-AG39)/AG39) -> -0.52769186 | AL60: NM | AM60: =IF(OR(AI39<=0,AM39<=0),"NM",(AM39-AI39)/AI39) -> 0.55882088 | AN60: =IF(OR(AJ39<=0,AN39<=0),"NM",(AN39-AJ39)/AJ39) -> -0.579528 | AO60: =IF(OR(AK39<=0,AO39<=0),"NM",(AO39-AK39)/AK39) -> -0.32725532 | AP60: NM | AQ60: =IF(OR(AM39<=0,AQ39<=0),"NM",(AQ39-AM39)/AM39) -> 0.98547043 | AR60: =IF(OR(AN39<=0,AR39<=0),"NM",(AR39-AN39)/AN39) -> 2.9197288 | AS60: =IF(OR(AO39<=0,AS39<=0),"NM",(AS39-AO39)/AO39) -> 1.6665643 | AV60: =IF(OR(AU39<=0,AV39<=0),"NM",(AV39-AU39)/AU39) -> 0.46152064 | AW60: =IF(OR(AV39<=0,AW39<=0),"NM",(AW39-AV39)/AV39) -> NM | AX60: =IF(OR(AW39<=0,AX39<=0),"NM",(AX39-AW39)/AW39) -> NM | AY60: =IF(OR(AX39<=0,AY39<=0),"NM",(AY39-AX39)/AX39) -> NM | AZ60: =IF(OR(AY39<=0,AZ39<=0),"NM",(AZ39-AY39)/AY39) -> 0.33711409 | BA60: =IF(OR(AZ39<=0,BA39<=0),"NM",(BA39-AZ39)/AZ39) -> 1.0160218 | BB60: =IF(OR(BA39<=0,BB39<=0),"NM",(BB39-BA39)/BA39) -> -0.13796155 | BC60: =IF(OR(BB39<=0,BC39<=0),"NM",(BC39-BB39)/BB39) -> -0.4258684 | ... BE60: =IF(OR(BD39<=0,BE39<=0),"NM",(BE39-BD39)/BD39) -> 3.6597223
A62: Margin Analysis | B62: =B49 -> 42825 | C62: =C49 -> 42916 | D62: =D49 -> 43008 | E62: =E49 -> 43100 | F62: =F49 -> 43190 | G62: =G49 -> 43281 | H62: =H49 -> 43373 | I62: =I49 -> 43465 | ... AS62: =AS49 -> Dec-27E | AU62: =AU49 -> 2017 | AV62: =AV49 -> 2018 | AW62: =AW49 -> 2019 | AX62: =AX49 -> 2020 | AY62: =AY49 -> 2021 | AZ62: =AZ49 -> 2022 | BA62: =BA49 -> 2023 | BB62: =BB49 -> 2024 | ... BE62: =BE49 -> 2027E
A63: Total Gross Margin | B63: =+B16/B$8 -> 0.88803576 | C63: =+C16/C$8 -> 0.90702191 | D63: =+D16/D$8 -> 0.90415066 | E63: =+E16/E$8 -> 0.92601471 | F63: =+F16/F$8 -> 0.89140263 | G63: =+G16/G$8 -> 0.90522592 | H63: =+H16/H$8 -> 0.90200143 | I63: =+I16/I$8 -> 0.91675998 | ... AK63: =+AK16/AK$8 -> 0.7999354 | AL63: 0.78 | AM63: =AL63+0.002 -> 0.782 | AN63: =AM63+0.002 -> 0.784 | AO63: =AN63+0.002 -> 0.786 | AP63: =AO63+0.002 -> 0.788 | AQ63: =AP63+0.002 -> 0.79 | AR63: =AQ63+0.002 -> 0.792 | AS63: =AR63+0.002 -> 0.794 | AU63: =+AU16/AU$8 -> 0.90925763 | AV63: =+AV16/AV$8 -> 0.9054231 | AW63: =+AW16/AW$8 -> 0.87274086 | AX63: =+AX16/AX$8 -> 0.86782558 | AY63: =+AY16/AY$8 -> 0.87742673 | AZ63: =+AZ16/AZ$8 -> 0.87966236 | BA63: =+BA16/BA$8 -> 0.87458931 | BB63: =+BB16/BB$8 -> 0.84253381 | ... BE63: =+BE16/BE$8 -> 0.79109487
A64: Consensus Gross Margin | N64: =N17/N9 -> 0.8631939 | O64: =O17/O9 -> 0.85486407 | P64: =P17/P9 -> 0.86564432 | Q64: =Q17/Q9 -> 0.87594062 | R64: =R17/R9 -> 0.85946745 | S64: =S17/S9 -> 0.86866787 | T64: =T17/T9 -> 0.87085603 | U64: =U17/U9 -> 0.88129956 | ... AS64: =AS17/AS9 -> 0.79638248 | AX64: =AX17/AX9 -> 0.86380954 | AY64: =AY17/AY9 -> 0.87221591 | AZ64: =AZ17/AZ9 -> 0.87602458 | BA64: =BA17/BA9 -> 0.87263919 | BB64: =BB17/BB9 -> 0.84630528 | BC64: =BC17/BC9 -> 0.80125994 | BD64: =BD17/BD9 -> 0.79561223 | BE64: =BE17/BE9 -> 0.79511813
A65: Research and development | B65: =+B20/B$8 -> 0.23398075 | C65: =+C20/C$8 -> 0.20602456 | D65: =+D20/D$8 -> 0.19679565 | E65: =+E20/E$8 -> 0.16634019 | F65: =+F20/F$8 -> 0.25035495 | G65: =+G20/G$8 -> 0.23521466 | H65: =+H20/H$8 -> 0.2260037 | I65: =+I20/I$8 -> 0.19382298 | ... AK65: =+AK20/AK$8 -> 0.29914229 | AL65: 0.32 | AM65: 0.266 | AN65: 0.275 | AO65: 0.25 | AP65: 0.29 | AQ65: 0.265 | AR65: 0.27 | AS65: 0.24 | AU65: =+AU20/AU$8 -> 0.1954269 | AV65: =+AV20/AV$8 -> 0.2225256 | AW65: =+AW20/AW$8 -> 0.26521106 | AX65: =+AX20/AX$8 -> 0.26017718 | AY65: =+AY20/AY$8 -> 0.24667935 | AZ65: =+AZ20/AZ$8 -> 0.26285064 | BA65: =+BA20/BA$8 -> 0.26731108 | BB65: =+BB20/BB$8 -> 0.28023414 | ... BE65: =+BE20/BE$8 -> 0.26556521
A66: Sales and Marketing | B66: =+B21/B$8 -> 0.72073346 | C66: =+C21/C$8 -> 0.60795857 | D66: =+D21/D$8 -> 0.56945564 | E66: =+E21/E$8 -> 0.48581526 | F66: =+F21/F$8 -> 0.6613548 | G66: =+G21/G$8 -> 0.58922656 | H66: =+H21/H$8 -> 0.54879795 | I66: =+I21/I$8 -> 0.45990539 | ... AK66: =+AK21/AK$8 -> 0.39218084 | AL66: 0.435 | AM66: 0.41 | AN66: 0.41 | AO66: =+AN66 -> 0.41 | AP66: 0.41 | AQ66: 0.395 | AR66: 0.386 | AS66: 0.385 | AU66: =+AU21/AU$8 -> 0.57775198 | AV66: =+AV21/AV$8 -> 0.55160791 | AW66: =+AW21/AW$8 -> 0.60273024 | AX66: =+AX21/AX$8 -> 0.51772701 | AY66: =+AY21/AY$8 -> 0.47583651 | AZ66: =+AZ21/AZ$8 -> 0.46583649 | BA66: =+BA21/BA$8 -> 0.45651495 | BB66: =+BB21/BB$8 -> 0.44301479 | ... BE66: =+BE21/BE$8 -> 0.39360454
A67: General and administrative | B67: =+B22/B$8 -> 0.11330286 | C67: =+C22/C$8 -> 0.10616819 | D67: =+D22/D$8 -> 0.10177082 | E67: =+E22/E$8 -> 0.090012466 | F67: =+F22/F$8 -> 0.10489837 | G67: =+G22/G$8 -> 0.097250362 | H67: =+H22/H$8 -> 0.097431844 | I67: =+I22/I$8 -> 0.085570968 | ... AK67: =+AK22/AK$8 -> 0.082350363 | AL67: 0.09 | AM67: =+AL67 -> 0.09 | AN67: 0.085 | AO67: 0.085 | AP67: 0.09 | AQ67: 0.085 | AR67: 0.08 | AS67: 0.075 | AU67: =+AU22/AU$8 -> 0.10091462 | AV67: =+AV22/AV$8 -> 0.095028266 | AW67: =+AW22/AW$8 -> 0.11180613 | AX67: =+AX22/AX$8 -> 0.1051184 | AY67: =+AY22/AY$8 -> 0.090212594 | AZ67: =+AZ22/AZ$8 -> 0.08861906 | BA67: =+BA22/BA$8 -> 0.093180543 | BB67: =+BB22/BB$8 -> 0.090405663 | ... BE67: =+BE22/BE$8 -> 0.082262825
A68: Total operating expenses | B68: =+B23/B$8 -> 1.0680171 | C68: =+C23/C$8 -> 0.92015132 | D68: =+D23/D$8 -> 0.86802211 | E68: =+E23/E$8 -> 0.74216792 | F68: =+F23/F$8 -> 1.0166081 | G68: =+G23/G$8 -> 0.92169159 | H68: =+H23/H$8 -> 0.87223349 | I68: =+I23/I$8 -> 0.73929934 | ... AS68: =+AS23/AS$8 -> 0.7 | AU68: =+AU23/AU$8 -> 0.8740935 | AV68: =+AV23/AV$8 -> 0.86916178 | AW68: =+AW23/AW$8 -> 0.97974743 | AX68: =+AX23/AX$8 -> 0.88302259 | AY68: =+AY23/AY$8 -> 0.81272845 | AZ68: =+AZ23/AZ$8 -> 0.81730619 | BA68: =+BA23/BA$8 -> 0.81700657 | BB68: =+BB23/BB$8 -> 0.8136546 | ... BE68: =+BE23/BE$8 -> 0.74143257
A69: Operating margin | B69: =+B24/B$8 -> -0.17998131 | C69: =+C24/C$8 -> -0.013129413 | D69: =+D24/D$8 -> 0.036128549 | E69: =+E24/E$8 -> 0.1838468 | F69: =+F24/F$8 -> -0.1252055 | G69: =+G24/G$8 -> -0.01646567 | H69: =+H24/H$8 -> 0.029767941 | I69: =+I24/I$8 -> 0.17746064 | ... AS69: =+AS24/AS$8 -> 0.094 | AU69: =+AU24/AU$8 -> 0.035164121 | AV69: =+AV24/AV$8 -> 0.036261321 | AW69: =+AW24/AW$8 -> -0.10700657 | AX69: =+AX24/AX$8 -> -0.015197018 | AY69: =+AY24/AY$8 -> 0.064698283 | AZ69: =+AZ24/AZ$8 -> 0.062356165 | BA69: =+BA24/BA$8 -> 0.057582739 | BB69: =+BB24/BB$8 -> 0.028879209 | ... BE69: =+BE24/BE$8 -> 0.049662299
A70: Consensus Operating margin | N70: =N25/N9 -> -0.31855882 | O70: =O25/O9 -> -0.18819801 | P70: =P25/P9 -> -0.039356545 | Q70: =Q25/Q9 -> 0.065673203 | R70: =R25/R9 -> -0.16622485 | S70: =S25/S9 -> -0.023574917 | T70: =T25/T9 -> 0.040870614 | U70: =U25/U9 -> 0.14476856 | ... AS70: =AS25/AS9 -> 0.075568134 | AX70: =AX25/AX9 -> -0.046405365 | AY70: =AY25/AY9 -> 0.053244366 | AZ70: =AZ25/AZ9 -> 0.055924009 | BA70: =BA25/BA9 -> 0.055836266 | BB70: =BB25/BB9 -> 0.039680146 | BC70: =BC25/BC9 -> -0.010715148 | BD70: =BD25/BD9 -> 0.0025594523 | BE70: =BE25/BE9 -> 0.050889632
A71: Net income | B71: =+B36/B$8 -> -0.17318718 | C71: =+C36/C$8 -> -0.0056442314 | D71: =+D36/D$8 -> 0.033561323 | E71: =+E36/E$8 -> 0.17114834 | F71: =+F36/F$8 -> -0.13032432 | G71: =+G36/G$8 -> -0.02042129 | H71: =+H36/H$8 -> 0.027575613 | I71: =+I36/I$8 -> 0.19800498 | ... AS71: =+AS36/AS$8 -> 0.094307845 | AU71: =+AU36/AU$8 -> 0.033190956 | AV71: =+AV36/AV$8 -> 0.040445747 | AW71: =+AW36/AW$8 -> -0.10917817 | AX71: =+AX36/AX$8 -> -0.026154041 | AY71: =+AY36/AY$8 -> 0.040093916 | AZ71: =+AZ36/AZ$8 -> 0.047678165 | BA71: =+BA36/BA$8 -> 0.091449635 | BB71: =+BB36/BB$8 -> 0.073995825 | ... BE71: =+BE36/BE$8 -> 0.057900869
A72: Source: Company data, FactSet, Wells Fargo Securities, LLC estimates
A74: Non-GAAP Reconciliation to GAAP Results | BA74: =BA$4 -> 2023 | BB74: =BB$4 -> 2024 | BC74: =BC$4 -> 2025 | BD74: =BD$4 -> 2026E | BE74: =BE$4 -> 2027E
A75: Adjustments
A76: Share-based compensation | B76: =B77+B78 -> 4.404 | C76: =C77+C78 -> 5.259 | D76: =D77+D78 -> 4.782 | E76: =E77+E78 -> 5.39 | F76: =F77+F78 -> 6.927 | G76: =G77+G78 -> 8.848 | H76: =H77+H78 -> 8.399 | I76: =I77+I78 -> 10.787 | ... AS76: =AS77+AS78 -> 39.271804 | AU76: =SUM(B76:E76) -> 19.835 | AV76: =SUM(F76:I76) -> 34.961 | AW76: =SUM(J76:M76) -> 46.139 | AX76: =SUM(N76:Q76) -> 68.585 | AY76: =SUM(R76:U76) -> 109.779 | AZ76: =SUM(V76:Y76) -> 142.862 | BA76: =SUM(Z76:AC76) -> 139.818 | BB76: =SUM(AD76:AG76) -> 126.682 | BC76: =SUM(AH76:AK76) -> 130.242 | BD76: =SUM(AL76:AO76) -> 144.49023 | BE76: =SUM(AP76:AS76) -> 167.82212
A77: Cost of revenue | B77: =B129 -> 0.227 | C77: =C129 -> 0.273 | D77: =D129 -> 0.283 | E77: =E129 -> 0.295 | F77: =F129 -> 0.362 | G77: =G129 -> 0.468 | H77: =H129 -> 0.47 | I77: =I129 -> 0.457 | ... AS77: =AS129 -> 1.6960964 | AU77: =SUM(B77:E77) -> 1.078 | AV77: =SUM(F77:I77) -> 1.757 | AW77: =SUM(J77:M77) -> 2.561 | AX77: =SUM(N77:Q77) -> 5.013 | AY77: =SUM(R77:U77) -> 8.995 | AZ77: =SUM(V77:Y77) -> 10.72 | BA77: =SUM(Z77:AC77) -> 7.221 | BB77: =SUM(AD77:AG77) -> 5.192 | BC77: =SUM(AH77:AK77) -> 5.924 | BD77: =SUM(AL77:AO77) -> 6.2403385 | BE77: =SUM(AP77:AS77) -> 7.2480118
A78: OpEx | B78: =B133 -> 4.177 | C78: =C133 -> 4.986 | D78: =D133 -> 4.499 | E78: =E133 -> 5.095 | F78: =F133 -> 6.565 | G78: =G133 -> 8.38 | H78: =H133 -> 7.929 | I78: =I133 -> 10.33 | ... AS78: =AS133 -> 37.575708 | AU78: =SUM(B78:E78) -> 18.757 | AV78: =SUM(F78:I78) -> 33.204 | AW78: =SUM(J78:M78) -> 43.578 | AX78: =SUM(N78:Q78) -> 63.572 | AY78: =SUM(R78:U78) -> 100.784 | AZ78: =SUM(V78:Y78) -> 132.142 | BA78: =SUM(Z78:AC78) -> 132.597 | BB78: =SUM(AD78:AG78) -> 121.49 | BC78: =SUM(AH78:AK78) -> 124.318 | BD78: =SUM(AL78:AO78) -> 138.24989 | BE78: =SUM(AP78:AS78) -> 160.57411
A79: Taxes related to share based compensation | B79: =B80+B81 -> 0.402 | C79: =C80+C81 -> 0.199 | D79: =D80+D81 -> 0.273 | E79: =E80+E81 -> 0.284 | F79: =F80+F81 -> 1.868 | G79: =G80+G81 -> 1.433 | H79: =H80+H81 -> 0.43 | I79: =I80+I81 -> 0.244 | ... AS79: =AS80+AS81 -> 1.9635902 | AU79: =SUM(B79:E79) -> 1.158 | AV79: =SUM(F79:I79) -> 3.975 | AW79: =SUM(J79:M79) -> 2.648 | AX79: =SUM(N79:Q79) -> 3.893 | AY79: =SUM(R79:U79) -> 7.362 | AZ79: =SUM(V79:Y79) -> 4.14 | BA79: =SUM(Z79:AC79) -> 3.26 | BB79: =SUM(AD79:AG79) -> 5.618 | BC79: =SUM(AH79:AK79) -> 3.98 | BD79: =SUM(AL79:AO79) -> 7.2245113 | BE79: =SUM(AP79:AS79) -> 8.3911062
A80: Cost of revenue | B80: =B138 -> 0.033 | C80: =C138 -> 0.012 | D80: =D138 -> 0.025 | E80: =E138 -> 0.021 | F80: =F138 -> 0.267 | G80: =G138 -> 0.078 | H80: =H138 -> 0.011 | I80: =I138 -> 0.007 | ... AS80: =AS138 -> 0.08480482 | AU80: =SUM(B80:E80) -> 0.091 | AV80: =SUM(F80:I80) -> 0.363 | AW80: =SUM(J80:M80) -> 0.235 | AX80: =SUM(N80:Q80) -> 0.3 | AY80: =SUM(R80:U80) -> 1.059 | AZ80: =SUM(V80:Y80) -> 0.595 | BA80: =SUM(Z80:AC80) -> 0.405 | BB80: =SUM(AD80:AG80) -> 0.637 | BC80: =SUM(AH80:AK80) -> 0.535 | BD80: =SUM(AL80:AO80) -> 0.31201693 | BE80: =SUM(AP80:AS80) -> 0.36240059
A81: OpEx | B81: =B142 -> 0.369 | C81: =C142 -> 0.187 | D81: =D142 -> 0.248 | E81: =E142 -> 0.263 | F81: =F142 -> 1.601 | G81: =G142 -> 1.355 | H81: =H142 -> 0.419 | I81: =I142 -> 0.237 | ... AS81: =AS142 -> 1.8787854 | AU81: =SUM(B81:E81) -> 1.067 | AV81: =SUM(F81:I81) -> 3.612 | AW81: =SUM(J81:M81) -> 2.413 | AX81: =SUM(N81:Q81) -> 3.593 | AY81: =SUM(R81:U81) -> 6.303 | AZ81: =SUM(V81:Y81) -> 3.545 | BA81: =SUM(Z81:AC81) -> 2.855 | BB81: =SUM(AD81:AG81) -> 4.981 | BC81: =SUM(AH81:AK81) -> 3.445 | BD81: =SUM(AL81:AO81) -> 6.9124944 | BE81: =SUM(AP81:AS81) -> 8.0287056
A82: Amortization of acquired intangible assets | B82: =B83+B84 -> 0 | C82: =C83+C84 -> 0 | D82: =D83+D84 -> 0 | E82: =E83+E84 -> 0 | F82: =F83+F84 -> 0 | G82: =G83+G84 -> 0 | H82: =H83+H84 -> 0 | I82: =I83+I84 -> 0 | ... AS82: =AS83+AS84 -> 2.061 | AU82: =SUM(B82:E82) -> 0 | AV82: =SUM(F82:I82) -> 0 | AW82: =SUM(J82:M82) -> 0 | AX82: =SUM(N82:Q82) -> 1.489 | AY82: =SUM(R82:U82) -> 6.794 | AZ82: =SUM(V82:Y82) -> 3.76 | BA82: =SUM(Z82:AC82) -> 2.888 | BB82: =SUM(AD82:AG82) -> 1.262 | BC82: =SUM(AH82:AK82) -> 8.646 | BD82: =SUM(AL82:AO82) -> 8.244 | BE82: =SUM(AP82:AS82) -> 8.244
A83: Cost of revenue | B83: =B147 -> 0 | C83: =C147 -> 0 | D83: =D147 -> 0 | E83: =E147 -> 0 | F83: =F147 -> 0 | G83: =G147 -> 0 | H83: =H147 -> 0 | I83: =I147 -> 0 | ... AS83: =AS147 -> 0.461 | AU83: =SUM(B83:E83) -> 0 | AV83: =SUM(F83:I83) -> 0 | AW83: =SUM(J83:M83) -> 0 | AX83: =SUM(N83:Q83) -> 0.262 | AY83: =SUM(R83:U83) -> 1.525 | AZ83: =SUM(V83:Y83) -> 1.525 | BA83: =SUM(Z83:AC83) -> 1.525 | BB83: =SUM(AD83:AG83) -> 1.262 | BC83: =SUM(AH83:AK83) -> 0.937 | BD83: =SUM(AL83:AO83) -> 1.844 | BE83: =SUM(AP83:AS83) -> 1.844
A84: OpEx | B84: =B151 -> 0 | C84: =C151 -> 0 | D84: =D151 -> 0 | E84: =E151 -> 0 | F84: =F151 -> 0 | G84: =G151 -> 0 | H84: =H151 -> 0 | I84: =I151 -> 0 | ... AS84: =AS151 -> 1.6 | AU84: =SUM(B84:E84) -> 0 | AV84: =SUM(F84:I84) -> 0 | AW84: =SUM(J84:M84) -> 0 | AX84: =SUM(N84:Q84) -> 1.227 | AY84: =SUM(R84:U84) -> 5.269 | AZ84: =SUM(V84:Y84) -> 2.235 | BA84: =SUM(Z84:AC84) -> 1.363 | BB84: =SUM(AD84:AG84) -> 0 | BC84: =SUM(AH84:AK84) -> 7.709 | BD84: =SUM(AL84:AO84) -> 6.4 | BE84: =SUM(AP84:AS84) -> 6.4
A85: Other Items | B85: =B86+B87+B88 -> 0 | C85: =C86+C87+C88 -> 0 | D85: =D86+D87+D88 -> 0 | E85: =E86+E87+E88 -> 0 | F85: =F86+F87+F88 -> -0.725 | G85: =G86+G87+G88 -> 1.132 | H85: =H86+H87+H88 -> 0.337 | I85: =I86+I87+I88 -> -0.17 | ... AS85: =AS86+AS87+AS88 -> 4.102 | AU85: =SUM(B85:E85) -> 0 | AV85: =SUM(F85:I85) -> 0.574 | AW85: =SUM(J85:M85) -> 2.225 | AX85: =SUM(N85:Q85) -> 12.388 | AY85: =SUM(R85:U85) -> 8.568 | AZ85: =SUM(V85:Y85) -> -3.662 | BA85: =SUM(Z85:AC85) -> 0.598 | BB85: =SUM(AD85:AG85) -> 2.971 | BC85: =SUM(AH85:AK85) -> 10.514 | BD85: =SUM(AL85:AO85) -> 16.408 | BE85: =SUM(AP85:AS85) -> 16.408
A86: Foreign exchange rate differences, net | B86: =B155 -> 0 | C86: =C155 -> 0 | D86: =D155 -> 0 | E86: =E155 -> 0 | F86: =F155 -> -0.725 | G86: =G155 -> 1.132 | H86: =H155 -> 0.337 | I86: =I155 -> -0.17 | ... AS86: =AS155 -> 3.597 | AU86: =SUM(B86:E86) -> 0 | AV86: =SUM(F86:I86) -> 0.574 | AW86: =SUM(J86:M86) -> 2.225 | AX86: =SUM(N86:Q86) -> 1.726 | AY86: =SUM(R86:U86) -> 1.698 | AZ86: =SUM(V86:Y86) -> -5.148 | BA86: =SUM(Z86:AC86) -> -0.916 | BB86: =SUM(AD86:AG86) -> 0.827 | BC86: =SUM(AH86:AK86) -> 7.147 | BD86: =SUM(AL86:AO86) -> 14.388 | BE86: =SUM(AP86:AS86) -> 14.388
A87: Amortization of debt discount and issuance costs | B87: =B156 -> 0 | C87: =C156 -> 0 | D87: =D156 -> 0 | E87: =E156 -> 0 | F87: =F156 -> 0 | G87: =G156 -> 0 | H87: =H156 -> 0 | I87: =I156 -> 0 | ... AS87: =AS156 -> 0.505 | AU87: =SUM(B87:E87) -> 0 | AV87: =SUM(F87:I87) -> 0 | AW87: =SUM(J87:M87) -> 0 | AX87: =SUM(N87:Q87) -> 4.096 | AY87: =SUM(R87:U87) -> 6.87 | AZ87: =SUM(V87:Y87) -> 1.486 | BA87: =SUM(Z87:AC87) -> 1.514 | BB87: =SUM(AD87:AG87) -> 2.144 | BC87: =SUM(AH87:AK87) -> 2.976 | BD87: =SUM(AL87:AO87) -> 2.02 | BE87: =SUM(AP87:AS87) -> 2.02
A88: Acquisition-related taxes | B88: =B157 -> 0 | C88: =C157 -> 0 | D88: =D157 -> 0 | E88: =E157 -> 0 | F88: =F157 -> 0 | G88: =G157 -> 0 | H88: =H157 -> 0 | I88: =I157 -> 0 | ... AS88: =AS157 -> 0 | AU88: =SUM(B88:E88) -> 0 | AV88: =SUM(F88:I88) -> 0 | AW88: =SUM(J88:M88) -> 0 | AX88: =SUM(N88:Q88) -> 6.566 | AY88: =SUM(R88:U88) -> 0 | AZ88: =SUM(V88:Y88) -> 0 | BA88: =SUM(Z88:AC88) -> 0 | BB88: =SUM(AD88:AG88) -> 0 | BC88: =SUM(AH88:AK88) -> 0.391 | BD88: =SUM(AL88:AO88) -> 0 | BE88: =SUM(AP88:AS88) -> 0
A90: GAAP Gross Profit | B90: =B16-B77-B80-B83 -> 34.9 | C90: =C16-C77-C80-C83 -> 44.55 | D90: =D16-D77-D80-D83 -> 47.942 | E90: =E16-E77-E80-E83 -> 67.284 | F90: =F16-F77-F80-F83 -> 47.086 | G90: =G16-G77-G80-G83 -> 55.75 | H90: =H16-H77-H80-H83 -> 60 | I90: =I16-I77-I80-I83 -> 79.769 | ... AS90: =AS16-AS77-AS80-AS83 -> 183.46213 | AU90: =AU16-AU77-AU80-AU83 -> 194.676 | AV90: =AV16-AV77-AV80-AV83 -> 242.605 | AW90: =AW16-AW77-AW80-AW83 -> 219.046 | AX90: =AX16-AX77-AX80-AX83 -> 248.428 | AY90: =AY16-AY77-AY80-AY83 -> 330.735 | AZ90: =AZ16-AZ77-AZ80-AZ83 -> 403.798 | BA90: =BA16-BA77-BA80-BA83 -> 427.409 | BB90: =BB16-BB77-BB80-BB83 -> 457.103 | ... BE90: =BE16-BE77-BE80-BE83 -> 690.36363
A91: GAAP Operating Income | B91: =B24-B76-B79-B82 -> -11.932 | C91: =C24-C76-C79-C82 -> -6.107 | D91: =D24-D76-D79-D82 -> -3.127 | E91: =E24-E76-E79-E82 -> 7.747 | F91: =F24-F76-F79-F82 -> -15.497 | G91: =G24-G76-G79-G82 -> -11.305 | H91: =H24-H76-H79-H82 -> -6.833 | I91: =I24-I76-I79-I82 -> 4.5 | ... AS91: =AS24-AS76-AS79-AS82 -> -21.311282 | AU91: =AU24-AU76-AU79-AU82 -> -13.419 | AV91: =AV24-AV76-AV79-AV82 -> -29.135 | AW91: =AW24-AW76-AW79-AW82 -> -75.987 | AX91: =AX24-AX76-AX79-AX82 -> -78.415 | AY91: =AY24-AY76-AY79-AY82 -> -98.694 | AZ91: =AZ24-AZ76-AZ79-AZ82 -> -121.228 | BA91: =BA24-BA76-BA79-BA82 -> -117.223 | BB91: =BB24-BB76-BB79-BB82 -> -117.651 | ... BE91: =BE24-BE76-BE79-BE82 -> -140.52499
A92: GAAP Net income | B92: =B36-B76-B79-B82-B85 -> -11.663 | C92: =C36-C76-C79-C82-C85 -> -5.737 | D92: =D36-D76-D79-D82-D85 -> -3.264 | E92: =E36-E76-E79-E82-E85 -> 6.82 | F92: =F36-F76-F79-F82-F85 -> -15.046 | G92: =G36-G76-G79-G82-G85 -> -12.683 | H92: =H36-H76-H79-H82-H85 -> -7.317 | I92: =I36-I76-I79-I82-I85 -> 6.468 | ... AS92: =AS36-AS76-AS79-AS82-AS85 -> -25.341282 | AU92: =AU36-AU76-AU79-AU82-AU85 -> -13.844 | AV92: =AV36-AV76-AV79-AV82-AV85 -> -28.578 | AW92: =AW36-AW76-AW79-AW82-AW85 -> -78.764 | AX92: =AX36-AX76-AX79-AX82-AX85 -> -94.01 | AY92: =AY36-AY76-AY79-AY82-AY85 -> -116.861 | AZ92: =AZ36-AZ76-AZ79-AZ82-AZ85 -> -124.518 | BA92: =BA36-BA76-BA79-BA82-BA85 -> -100.916 | BB92: =BB36-BB76-BB79-BB82-BB85 -> -95.765 | ... BE92: =BE36-BE76-BE79-BE82-BE85 -> -149.64499
A93: GAAP EPS | B93: =IF(B92<0,B92/B95,B92/B96) -> -0.43274503 | C93: =IF(C92<0,C92/C95,C92/C96) -> -0.20997856 | D93: =IF(D92<0,D92/D95,D92/D96) -> -0.11828032 | E93: =IF(E92<0,E92/E95,E92/E96) -> 0.21913895 | F93: =IF(F92<0,F92/F95,F92/F96) -> -0.5304896 | G93: =IF(G92<0,G92/G95,G92/G96) -> -0.43854987 | H93: =IF(H92<0,H92/H95,H92/H96) -> -0.24988302 | I93: =IF(I92<0,I92/I95,I92/I96) -> 0.19897607 | ... AS93: =IF(AS92<0,AS92/AS95,AS92/AS96) -> -0.20008149 | AU93: =IF(AU92<0,AU92/AU95,AU92/AU96) -> -0.50401494 | AV93: =IF(AV92<0,AV92/AV95,AV92/AV96) -> -0.98474724 | AW93: =IF(AW92<0,AW92/AW95,AW92/AW96) -> -2.6031309 | AX93: =IF(AX92<0,AX92/AX95,AX92/AX96) -> -0.99653483 | AY93: =IF(AY92<0,AY92/AY95,AY92/AY96) -> -1.1097283 | AZ93: =IF(AZ92<0,AZ92/AZ95,AZ92/AZ96) -> -1.1395141 | BA93: =IF(BA92<0,BA92/BA95,BA92/BA96) -> -0.92463665 | BB93: =IF(BB92<0,BB92/BB95,BB92/BB96) -> -0.85766356 | ... BE93: =IF(BE92<0,BE92/BE95,BE92/BE96) -> -1.1971139
A94: Consensus GAAP EPS | B94: ='[2]VA Consensus'!C42 -> - | C94: ='[2]VA Consensus'!D42 -> - | D94: ='[2]VA Consensus'!E42 -> - | E94: ='[2]VA Consensus'!F42 -> - | F94: ='[2]VA Consensus'!G42 -> - | G94: ='[2]VA Consensus'!H42 -> - | H94: ='[2]VA Consensus'!I42 -> - | I94: ='[2]VA Consensus'!J42 -> - | ... AS94: ='[2]VA Consensus'!AT42 -> -0.12513278 | AU94: ='[2]VA Consensus'!AV42 -> - | AV94: ='[2]VA Consensus'!AW42 -> - | AW94: ='[2]VA Consensus'!AX42 -> - | AX94: ='[2]VA Consensus'!AY42 -> - | AY94: ='[2]VA Consensus'!AZ42 -> -0.92434964 | AZ94: ='[2]VA Consensus'!BA42 -> -1.1045464 | BA94: ='[2]VA Consensus'!BB42 -> -0.94855142 | BB94: ='[2]VA Consensus'!BC42 -> -0.8278336 | ... BE94: ='[2]VA Consensus'!BF42 -> -0.6793602
A95: Basic shares outstanding | B95: =B123 -> 26.951205 | C95: =C123 -> 27.321837 | D95: =D123 -> 27.595461 | E95: =E123 -> 27.987216 | F95: =F123 -> 28.362479 | G95: =G123 -> 28.920314 | H95: =H123 -> 29.281701 | I95: =I123 -> 29.498904 | ... S95: =S123 -> 106.39343 | T95: =T45 -> 107.02802 | U95: =U45 -> 107.40693 | V95: =V45 -> 108.20496 | W95: =W45 -> 109.67531 | X95: =X45 -> 109.99659 | Y95: =Y45 -> 109.2147 | Z95: =Z45 -> 108.3874 | AA95: =AA45 -> 109.74029 | ... AS95: =AS45 -> 126.6548 | AU95: =AU45 -> 27.46744 | AV95: =AV45 -> 29.020645 | AW95: =AW45 -> 30.25741 | AX95: =AX45 -> 94.336893 | AY95: =AY45 -> 105.30596 | AZ95: =AZ45 -> 109.27289 | BA95: =BA45 -> 109.14125 | BB95: =BB45 -> 111.658 | ... BE95: =BE45 -> 125.0048
A96: Diluted shares outstanding | B96: =B124 -> 26.951205 | C96: =C124 -> 30.545216 | D96: =D124 -> 30.812151 | E96: =E124 -> 31.121806 | F96: =F124 -> 28.362479 | G96: =G124 -> 28.920314 | H96: =H124 -> 32.52506 | I96: =I124 -> 32.506422 | ... S96: =S124 -> 106.39343 | T96: =T46 -> 119.07061 | U96: =U46 -> 118.64997 | V96: =V46 -> 125.1 | W96: =W46 -> 126.9 | X96: =X46 -> 126.93984 | Y96: =Y46 -> 126.01019 | Z96: =Z46 -> 126.2 | AA96: =AA46 -> 127.29488 | ... AS96: =AS46 -> 147.09789 | AU96: =AU46 -> 30.854436 | AV96: =AV46 -> 32.282487 | AW96: =AW46 -> 30.25741 | AX96: =AX46 -> 94.336893 | AY96: =AY46 -> 116.91945 | AZ96: =AZ46 -> 126.23751 | BA96: =BA46 -> 126.57634 | BB96: =BB46 -> 131.13649 | ... BE96: =BE46 -> 146.42289
A98: GAAP Inputs | B98: =B3 -> 2017 | F98: =F3 -> 2018 | J98: =J3 -> 2019 | N98: =N3 -> 2020 | R98: =R3 -> 2021 | V98: =V3 -> 2022 | Z98: =Z3 -> 2023 | AD98: =AD3 -> 2024 | AH98: =AH3 -> 2025 | AL98: =AL3 -> 2026 | AP98: =AP3 -> 2027
A99: Revenue | AU99: =AU$4 -> 2017 | AV99: =AV$4 -> 2018 | AW99: =AW$4 -> 2019 | AX99: =AX$4 -> 2020 | AY99: =AY$4 -> 2021 | AZ99: =AZ$4 -> 2022 | BA99: =BA$4 -> 2023 | BB99: =BB$4 -> 2024 | ... BE99: =BE$4 -> 2027E
A100: Subscription | B100: ='Revenue Build'!B13 -> 0 | C100: ='Revenue Build'!C13 -> 0 | D100: ='Revenue Build'!D13 -> 0 | E100: ='Revenue Build'!E13 -> 0 | F100: ='Revenue Build'!F13 -> 1.071 | G100: ='Revenue Build'!G13 -> 1.291 | H100: ='Revenue Build'!H13 -> 2.539 | I100: ='Revenue Build'!I13 -> 3.849 | ... AS100: ='Revenue Build'!AS13 -> 231.88418 | AU100: =SUM(B100:E100) -> 0 | AV100: =SUM(F100:I100) -> 8.75 | AW100: =SUM(J100:M100) -> 76.73 | AX100: =SUM(N100:Q100) -> 161.188 | AY100: =SUM(R100:U100) -> 268.942 | AZ100: =SUM(V100:Y100) -> 366.144 | BA100: =SUM(Z100:AC100) -> 400.907 | BB100: =SUM(AD100:AG100) -> 463.022 | BC100: =SUM(AH100:AK100) -> 572.23 | BD100: =SUM(AL100:AO100) -> 709.17794 | BE100: =SUM(AP100:AS100) -> 876.61962
A101: Perpetual License | B101: ='Revenue Build'!B28 -> 18.092 | C101: ='Revenue Build'!C28 -> 27.31 | D101: ='Revenue Build'!D28 -> 29 | E101: ='Revenue Build'!E28 -> 45.939 | F101: ='Revenue Build'!F28 -> 24.086 | G101: ='Revenue Build'!G28 -> 32.27 | H101: ='Revenue Build'!H28 -> 33.432 | I101: ='Revenue Build'!I28 -> 49.79 | ... AS101: ='Revenue Build'!AS28 -> 0 | AU101: =SUM(B101:E101) -> 120.341 | AV101: =SUM(F101:I101) -> 139.578 | AW101: =SUM(J101:M101) -> 42.093 | AX101: =SUM(N101:Q101) -> 1.473 | AY101: =SUM(R101:U101) -> 1.89 | AZ101: =SUM(V101:Y101) -> 0 | BA101: =SUM(Z101:AC101) -> 0 | BB101: =SUM(AD101:AG101) -> 0 | BC101: =SUM(AH101:AK101) -> 0 | BD101: =SUM(AL101:AO101) -> 0 | BE101: =SUM(AP101:AS101) -> 0
A102: Maintenance and Services | B102: ='Revenue Build'!B33 -> 21.501 | C102: ='Revenue Build'!C33 -> 22.121 | D102: ='Revenue Build'!D33 -> 24.365 | E102: ='Revenue Build'!E33 -> 27.062 | F102: ='Revenue Build'!F33 -> 28.371 | G102: ='Revenue Build'!G33 -> 28.629 | H102: ='Revenue Build'!H33 -> 31.081 | I102: ='Revenue Build'!I33 -> 33.879 | ... AS102: ='Revenue Build'!AS33 -> 2 | AU102: =SUM(B102:E102) -> 95.049 | AV102: =SUM(F102:I102) -> 121.96 | AW102: =SUM(J102:M102) -> 135.367 | AX102: =SUM(N102:Q102) -> 130.028 | AY102: =SUM(R102:U102) -> 119.302 | AZ102: =SUM(V102:Y102) -> 107.49 | BA102: =SUM(Z102:AC102) -> 98.253 | BB102: =SUM(AD102:AG102) -> 87.928 | BC102: =SUM(AH102:AK102) -> 51.302 | BD102: =SUM(AL102:AO102) -> 15.957747 | BE102: =SUM(AP102:AS102) -> 8
A103: Total Revenue | B103: =+'Revenue Build'!B5 -> 39.593 | C103: =+'Revenue Build'!C5 -> 49.431 | D103: =+'Revenue Build'!D5 -> 53.365 | E103: =+'Revenue Build'!E5 -> 73.001 | F103: =+'Revenue Build'!F5 -> 53.528 | G103: =+'Revenue Build'!G5 -> 62.19 | H103: =+'Revenue Build'!H5 -> 67.052 | I103: =+'Revenue Build'!I5 -> 87.518 | ... AS103: =+'Revenue Build'!AS5 -> 233.88418 | AU103: =SUM(B103:E103) -> 215.39 | AV103: =SUM(F103:I103) -> 270.288 | AW103: =SUM(J103:M103) -> 254.19 | AX103: =SUM(N103:Q103) -> 292.689 | AY103: =SUM(R103:U103) -> 390.134 | AZ103: =SUM(V103:Y103) -> 473.634 | BA103: =SUM(Z103:AC103) -> 499.16 | BB103: =SUM(AD103:AG103) -> 550.95 | BC103: =SUM(AH103:AK103) -> 623.532 | BD103: =SUM(AL103:AO103) -> 725.13568 | BE103: =SUM(AP103:AS103) -> 884.61962
A105: Total cost of revenue | B105: 4.693 | C105: 4.881 | D105: 5.423 | E105: 5.717 | F105: 6.442 | G105: 6.44 | H105: 7.052 | I105: 7.749 | J105: 8.326 | K105: 8.398 | L105: 8.768 | M105: 9.652 | N105: 10.18 | O105: 10.335 | P105: 11.284 | Q105: 12.462 | R105: 13.482 | S105: 14.201 | T105: 14.338 | U105: 17.378 | V105: 17.809 | W105: 17.799 | X105: 17.198 | Y105: 17.03 | Z105: 17.637 | AA105: 17.386 | AB105: 17.381 | AC105: 19.347 | AD105: 21.349 | AE105: 22.436 | AF105: 24.007 | AG105: 26.055 | AH105: 29.018 | AI105: 31.249 | AJ105: 35.149 | AK105: 36.558 | AL105: =AL15+AL129+AL138+AL147 -> 38.533306 | AM105: =AM15+AM129+AM138+AM147 -> 40.504834 | AN105: =AN15+AN129+AN138+AN147 -> 42.280733 | AO105: =AO15+AO129+AO138+AO147 -> 44.324918 | AP105: =AP15+AP129+AP138+AP147 -> 46.780259 | AQ105: =AQ15+AQ129+AQ138+AQ147 -> 47.934703 | AR105: =AR15+AR129+AR138+AR147 -> 49.118986 | AS105: =AS15+AS129+AS138+AS147 -> 50.422042 | AU105: =SUM(B105:E105) -> 20.714 | AV105: =SUM(F105:I105) -> 27.683 | AW105: =SUM(J105:M105) -> 35.144 | AX105: =SUM(N105:Q105) -> 44.261 | AY105: =SUM(R105:U105) -> 59.399 | AZ105: =SUM(V105:Y105) -> 69.836 | BA105: =SUM(Z105:AC105) -> 71.751 | BB105: =SUM(AD105:AG105) -> 93.847 | BC105: =SUM(AH105:AK105) -> 131.974 | BD105: =SUM(AL105:AO105) -> 165.64379 | BE105: =SUM(AP105:AS105) -> 194.25599
A106: Gross profit | B106: =B103-B105 -> 34.9 | C106: =C103-C105 -> 44.55 | D106: =D103-D105 -> 47.942 | E106: =E103-E105 -> 67.284 | F106: =F103-F105 -> 47.086 | G106: =G103-G105 -> 55.75 | H106: =H103-H105 -> 60 | I106: =I103-I105 -> 79.769 | ... W106: =W103-W105 -> 93.649 | X106: 106.11 | Y106: =Y103-Y105 -> 125.587 | Z106: =Z103-Z105 -> 89.698 | AA106: =AA103-AA105 -> 98.032 | AB106: =AB103-AB105 -> 104.927 | AC106: =AC103-AC105 -> 134.752 | AD106: =AD103-AD105 -> 92.673 | AE106: =AE103-AE105 -> 107.91 | AF106: =AF103-AF105 -> 124.061 | ... AS106: =AS103-AS105 -> 183.46213 | AU106: =SUM(B106:E106) -> 194.676 | AV106: =SUM(F106:I106) -> 242.605 | AW106: =SUM(J106:M106) -> 219.046 | AX106: =SUM(N106:Q106) -> 248.428 | AY106: =SUM(R106:U106) -> 330.735 | AZ106: =SUM(V106:Y106) -> 403.798 | BA106: =SUM(Z106:AC106) -> 427.409 | BB106: =SUM(AD106:AG106) -> 457.103 | BC106: =SUM(AH106:AK106) -> 491.558 | BD106: =SUM(AL106:AO106) -> 559.49189 | BE106: =SUM(AP106:AS106) -> 690.36363
A108: Operating expenses
A109: Research and development | B109: 10.409 | C109: 11.498 | D109: 11.903 | E109: 13.559 | F109: 15.542 | G109: 17.717 | H109: 17.267 | I109: 19.445 | J109: 18.768 | K109: 19.722 | L109: 20.4 | M109: 21.874 | N109: 22.688 | O109: 24.067 | P109: 24.67 | Q109: 27.938 | R109: 30.062 | S109: 33.333 | T109: 34.344 | U109: 40.143 | V109: 43.57 | W109: 44.815 | X109: 44.478 | Y109: 45.018 | Z109: 44.732 | AA109: 46.144 | AB109: 44.818 | AC109: 48.144 | AD109: 47.827 | AE109: 44.933 | AF109: 53.459 | AG109: 50.546 | AH109: 54.21 | AI109: 56.247 | AJ109: 62.737 | AK109: 64.62 | AL109: =AL20+AL130+AL139+AL148 -> 67.951785 | AM109: =AM20+AM130+AM139+AM148 -> 61.815934 | AN109: =AN20+AN130+AN139+AN148 -> 65.234627 | AO109: =AO20+AO130+AO139+AO148 -> 63.590256 | AP109: =AP20+AP130+AP139+AP148 -> 78.419214 | AQ109: =AQ20+AQ130+AQ139+AQ148 -> 74.774983 | AR109: =AR20+AR130+AR139+AR148 -> 76.626177 | AS109: =AS20+AS130+AS139+AS148 -> 71.841664 | AU109: =SUM(B109:E109) -> 47.369 | AV109: =SUM(F109:I109) -> 69.971 | AW109: =SUM(J109:M109) -> 80.764 | AX109: =SUM(N109:Q109) -> 99.363 | AY109: =SUM(R109:U109) -> 137.882 | AZ109: =SUM(V109:Y109) -> 177.881 | BA109: =SUM(Z109:AC109) -> 183.838 | BB109: =SUM(AD109:AG109) -> 196.765 | BC109: =SUM(AH109:AK109) -> 237.814 | BD109: =SUM(AL109:AO109) -> 258.5926 | BE109: =SUM(AP109:AS109) -> 301.66204
A110: Sales and marketing | B110: 30.914 | C110: 32.58 | D110: 32.458 | E110: 37.973 | F110: 39.972 | G110: 41.349 | H110: 40.792 | I110: 46.196 | J110: 41.996 | K110: 41.656 | L110: 42.117 | M110: 44.129 | N110: 42.58 | O110: 42.983 | P110: 45.435 | Q110: 48.904 | R110: 51.493 | S110: 54.919 | T110: 56.229 | U110: 67.673 | V110: 64.787 | W110: 68.714 | X110: 69.81 | Y110: 71.779 | Z110: 68.393 | AA110: 70.321 | AB110: 68.61 | AC110: 70.569 | AD110: 71.227 | AE110: 70.041 | AF110: 71.378 | AG110: 76.123 | AH110: 72.763 | AI110: 76.578 | AJ110: 74.025 | AK110: 77.976 | AL110: =AL21+AL131+AL140+AL149 -> 83.813261 | AM110: =AM21+AM131+AM140+AM149 -> 83.997176 | AN110: =AN21+AN131+AN140+AN149 -> 87.380592 | AO110: =AO21+AO131+AO140+AO149 -> 92.151858 | AP110: =AP21+AP131+AP140+AP149 -> 99.953026 | AQ110: =AQ21+AQ131+AQ140+AQ149 -> 99.471426 | AR110: =AR21+AR131+AR140+AR149 -> 99.512703 | AS110: =AS21+AS131+AS140+AS149 -> 102.51444 | AU110: =SUM(B110:E110) -> 133.925 | AV110: =SUM(F110:I110) -> 168.309 | AW110: =SUM(J110:M110) -> 169.898 | AX110: =SUM(N110:Q110) -> 179.902 | AY110: =SUM(R110:U110) -> 230.314 | AZ110: =SUM(V110:Y110) -> 275.09 | BA110: =SUM(Z110:AC110) -> 277.893 | BB110: =SUM(AD110:AG110) -> 288.769 | BC110: =SUM(AH110:AK110) -> 301.342 | BD110: =SUM(AL110:AO110) -> 347.34289 | BE110: =SUM(AP110:AS110) -> 401.4516
A111: General and administrative | B111: 5.509 | C111: 6.579 | D111: 6.708 | E111: 8.005 | F111: 7.069 | G111: 7.989 | H111: 8.774 | I111: 9.628 | J111: 9.271 | K111: 13.851 | L111: 10.339 | M111: 10.91 | N111: 11.398 | O111: 11.274 | P111: 11.814 | Q111: 13.092 | R111: 13.823 | S111: 14.196 | T111: 13.997 | U111: 19.217 | V111: 18.18 | W111: 17.688 | X111: 17.404 | Y111: 18.783 | Z111: 19.689 | AA111: 21.283 | AB111: 20.646 | AC111: 21.283 | AD111: 21.252 | AE111: 21.762 | AF111: 22.864 | AG111: 23.342 | AH111: 24.198 | AI111: 24.641 | AJ111: 25.6 | AK111: 24.477 | AL111: =AL22+AL132+AL141+AL150 -> 27.158753 | AM111: =AM22+AM132+AM141+AM150 -> 28.092576 | AN111: =AN22+AN132+AN141+AN150 -> 27.169484 | AO111: =AO22+AO132+AO141+AO150 -> 28.31921 | AP111: =AP22+AP132+AP141+AP150 -> 33.600956 | AQ111: =AQ22+AQ132+AQ141+AQ150 -> 32.783511 | AR111: =AR22+AR132+AR141+AR150 -> 30.973203 | AS111: =AS22+AS132+AS141+AS150 -> 30.41731 | AU111: =SUM(B111:E111) -> 26.801 | AV111: =SUM(F111:I111) -> 33.46 | AW111: =SUM(J111:M111) -> 44.371 | AX111: =SUM(N111:Q111) -> 47.578 | AY111: =SUM(R111:U111) -> 61.233 | AZ111: =SUM(V111:Y111) -> 72.055 | BA111: =SUM(Z111:AC111) -> 82.901 | BB111: =SUM(AD111:AG111) -> 89.22 | BC111: =SUM(AH111:AK111) -> 98.916 | BD111: =SUM(AL111:AO111) -> 110.74002 | BE111: =SUM(AP111:AS111) -> 127.77498
...

Sheet Revenue Build
A1: =+'Income Statement'!A1 -> Varonis Systems, Inc. (VRNS)
A2: Revenue Build | B2: 2017/1F | C2: 2017/2F | D2: 2017/3F | E2: 2017/4F | F2: 2018/1F | G2: 2018/2F | H2: 2018/3F | I2: 2018/4F | J2: 2018/1F | K2: 2018/2F | L2: 2018/3F | M2: 2018/4F | N2: ='Income Statement'!N2 -> 2019/1F | O2: ='Income Statement'!O2 -> 2019/2F | P2: ='Income Statement'!P2 -> 2019/3F | Q2: ='Income Statement'!Q2 -> 2019/4F | R2: ='Income Statement'!R2 -> 2021/1F | S2: ='Income Statement'!S2 -> 2021/2F | T2: ='Income Statement'!T2 -> 2021/3F | U2: ='Income Statement'!U2 -> 2021/4F | ... AS2: ='Income Statement'!AS2 -> 2027/4F | AU2: 2017 | AV2: 2018 | AW2: 2019 | AX2: ='Income Statement'!AX2 -> 2020 | AY2: ='Income Statement'!AY2 -> 2021 | AZ2: ='Income Statement'!AZ2 -> 2022 | BA2: ='Income Statement'!BA2 -> 2023 | BB2: ='Income Statement'!BB2 -> 2024 | BC2: ='Income Statement'!BC2 -> 2025 | BD2: ='Income Statement'!BD2 -> 2026 | BE2: ='Income Statement'!BE2 -> 2027
B3: ='Income Statement'!B$3 -> 2017 | F3: ='Income Statement'!F$3 -> 2018 | J3: ='Income Statement'!J$3 -> 2019 | N3: ='Income Statement'!N$3 -> 2020 | R3: ='Income Statement'!R$3 -> 2021 | V3: ='Income Statement'!V$3 -> 2022 | Z3: ='Income Statement'!Z$3 -> 2023 | AD3: ='Income Statement'!AD$3 -> 2024 | AH3: ='Income Statement'!AH$3 -> 2025 | AL3: ='Income Statement'!AL$3 -> 2026 | AP3: ='Income Statement'!AP$3 -> 2027
A4: ='Income Statement'!A4 -> ($ in millions, unless otherwise stated) | B4: ='Income Statement'!B$4 -> 42825 | C4: ='Income Statement'!C$4 -> 42916 | D4: ='Income Statement'!D$4 -> 43008 | E4: ='Income Statement'!E$4 -> 43100 | F4: ='Income Statement'!F$4 -> 43190 | G4: ='Income Statement'!G$4 -> 43281 | H4: ='Income Statement'!H$4 -> 43373 | I4: ='Income Statement'!I$4 -> 43465 | ... AS4: ='Income Statement'!AS$4 -> Dec-27E | AU4: ='Income Statement'!AU$4 -> 2017 | AV4: ='Income Statement'!AV$4 -> 2018 | AW4: ='Income Statement'!AW$4 -> 2019 | AX4: ='Income Statement'!AX$4 -> 2020 | AY4: ='Income Statement'!AY$4 -> 2021 | AZ4: ='Income Statement'!AZ$4 -> 2022 | BA4: ='Income Statement'!BA$4 -> 2023 | BB4: ='Income Statement'!BB$4 -> 2024 | ... BE4: ='Income Statement'!BE$4 -> 2027E
A5: Total Revenue | B5: =B13+B28+B33 -> 39.593 | C5: =C13+C28+C33 -> 49.431 | D5: =D13+D28+D33 -> 53.365 | E5: =E13+E28+E33 -> 73.001 | F5: =F13+F28+F33 -> 53.528 | G5: =G13+G28+G33 -> 62.19 | H5: =H13+H28+H33 -> 67.052 | I5: =I13+I28+I33 -> 87.518 | ... U5: =U13+U28+U33 -> 126.578 | V5: =V13+V33 -> 96.261 | W5: =W13+W33 -> 111.448 | X5: =X13+X33 -> 123.308 | Y5: =Y13+Y33 -> 142.617 | Z5: =Z13+Z33 -> 107.335 | AA5: =AA13+AA33 -> 115.418 | AB5: =AB13+AB33 -> 122.308 | AC5: =AC13+AC33 -> 154.099 | ... AS5: =AS13+AS33 -> 233.88418 | AU5: =SUM(B5:E5) -> 215.39 | AV5: =SUM(F5:I5) -> 270.288 | AW5: =SUM(J5:M5) -> 254.19 | AX5: =SUM(N5:Q5) -> 292.689 | AY5: =SUM(R5:U5) -> 390.134 | AZ5: =SUM(V5:Y5) -> 473.634 | BA5: =SUM(Z5:AC5) -> 499.16 | BB5: =SUM(AD5:AG5) -> 550.95 | BC5: =SUM(AH5:AK5) -> 623.532 | BD5: =SUM(AL5:AO5) -> 725.13568 | BE5: =SUM(AP5:AS5) -> 884.61962
A6: Consensus revenue | B6: ='[2]VA Consensus'!C28 -> 40.38 | C6: ='[2]VA Consensus'!D28 -> 47.532444 | D6: ='[2]VA Consensus'!E28 -> 50.554272 | E6: ='[2]VA Consensus'!F28 -> 66.51052 | F6: ='[2]VA Consensus'!G28 -> 49.838929 | G6: ='[2]VA Consensus'!H28 -> 62.105238 | H6: ='[2]VA Consensus'!I28 -> 64.53161 | I6: ='[2]VA Consensus'!J28 -> 87.408971 | ... AS6: ='[2]VA Consensus'!AT28 -> 230.41508 | AU6: ='[2]VA Consensus'!AV28 -> 210.66552 | AV6: ='[2]VA Consensus'!AW28 -> 270.18211 | AW6: ='[2]VA Consensus'!AX28 -> 253.4685 | AX6: ='[2]VA Consensus'!AY28 -> 281.78387 | AY6: ='[2]VA Consensus'!AZ28 -> 385.55766 | AZ6: ='[2]VA Consensus'!BA28 -> 471.20837 | BA6: ='[2]VA Consensus'!BB28 -> 496.67471 | BB6: ='[2]VA Consensus'!BC28 -> 557.97652 | ... BE6: ='[2]VA Consensus'!BF28 -> 857.74118
A7: Y/Y % | B7: =IF(ISERROR(B5/#REF!-1),"NA",B5/#REF!-1) -> NA | C7: =IF(ISERROR(C5/#REF!-1),"NA",C5/#REF!-1) -> NA | D7: =IF(ISERROR(D5/#REF!-1),"NA",D5/#REF!-1) -> NA | E7: =IF(ISERROR(E5/#REF!-1),"NA",E5/#REF!-1) -> NA | F7: =IF(ISERROR(F5/B5-1),"NA",F5/B5-1) -> 0.35195615 | G7: =IF(ISERROR(G5/C5-1),"NA",G5/C5-1) -> 0.25811738 | H7: =IF(ISERROR(H5/D5-1),"NA",H5/D5-1) -> 0.25647897 | I7: =IF(ISERROR(I5/E5-1),"NA",I5/E5-1) -> 0.19886029 | J7: =IF(ISERROR(J5/F5-1),"NA",J5/F5-1) -> 0.05290689 | K7: =IF(ISERROR(K5/G5-1),"NA",K5/G5-1) -> -0.041308892 | L7: =IF(ISERROR(L5/H5-1),"NA",L5/H5-1) -> -0.020924059 | M7: =IF(ISERROR(M5/I5-1),"NA",M5/I5-1) -> -0.17091341 | ... AS7: =IF(ISERROR(AS5/AO5-1),"NA",AS5/AO5-1) -> 0.18407518 | AU7: =IF(ISERROR(AU5/#REF!-1),"NA",AU5/#REF!-1) -> NA | AV7: =IF(ISERROR(AV5/AU5-1),"NA",AV5/AU5-1) -> 0.2548772 | AW7: =IF(ISERROR(AW5/AV5-1),"NA",AW5/AV5-1) -> -0.059558693 | AX7: =IF(ISERROR(AX5/AW5-1),"NA",AX5/AW5-1) -> 0.15145757 | AY7: =IF(ISERROR(AY5/AX5-1),"NA",AY5/AX5-1) -> 0.33293018 | AZ7: =IF(ISERROR(AZ5/AY5-1),"NA",AZ5/AY5-1) -> 0.21402903 | BA7: =IF(ISERROR(BA5/AZ5-1),"NA",BA5/AZ5-1) -> 0.053893935 | BB7: =IF(ISERROR(BB5/BA5-1),"NA",BB5/BA5-1) -> 0.10375431 | BC7: =IF(ISERROR(BC5/BB5-1),"NA",BC5/BB5-1) -> 0.13173972 | ... BE7: =IF(ISERROR(BE5/BD5-1),"NA",BE5/BD5-1) -> 0.21993668
A8: Management Guidance - Total Revenue
A9: Low | N9: 53.9 | O9: 56 | P9: 68 | Q9: 82 | R9: 68 | S9: 82.5 | T9: 96 | U9: 120 | V9: 94.5 | W9: 110.5 | X9: 123 | Y9: 139 | Z9: 106 | AA9: 118 | AB9: 123.5 | AC9: 150 | AD9: 111 | AE9: 123 | AF9: 140 | AG9: 162 | AH9: 130 | AI9: 145 | AJ9: 163 | AK9: 165 | AL9: 164 | AY9: 383.5 | AZ9: 519 | BA9: 495 | BB9: 554.4 | BC9: 615.2 | BD9: 722
A10: Mid | N10: =AVERAGE(N9,N11) -> 54.1 | O10: =AVERAGE(O9,O11) -> 57 | P10: =AVERAGE(P9,P11) -> 69.5 | Q10: =AVERAGE(Q9,Q11) -> 83.5 | R10: =AVERAGE(R9,R11) -> 68.75 | S10: =AVERAGE(S9,S11) -> 83.25 | T10: =AVERAGE(T9,T11) -> 97 | U10: =AVERAGE(U9,U11) -> 121.5 | ... AB10: =AVERAGE(AB9,AB11) -> 125.25 | AC10: =IFERROR(AVERAGE(AC9,AC11),"") -> 152 | AD10: =IFERROR(AVERAGE(AD9,AD11),"") -> 113 | AE10: =IFERROR(AVERAGE(AE9,AE11),"") -> 124.5 | AF10: =IFERROR(AVERAGE(AF9,AF11),"") -> 141.5 | AG10: =IFERROR(AVERAGE(AG9,AG11),"") -> 164.5 | AH10: =IFERROR(AVERAGE(AH9,AH11),"") -> 132.5 | AI10: =IFERROR(AVERAGE(AI9,AI11),"") -> 147.5 | AJ10: =IFERROR(AVERAGE(AJ9,AJ11),"") -> 165.5 | ... AS10: =IFERROR(AVERAGE(AS9,AS11),"") | AY10: =AVERAGE(AY9,AY11) -> 385 | AZ10: =AVERAGE(AZ9,AZ11) -> 496 | BA10: =AVERAGE(BA9,BA11) -> 497 | BB10: =IFERROR(AVERAGE(BB9,BB11),"") -> 556.9 | BC10: =IFERROR(AVERAGE(BC9,BC11),"") -> 618.2 | BD10: =IFERROR(AVERAGE(BD9,BD11),"") -> 726 | BE10: =IFERROR(AVERAGE(BE9,BE11),"")
A11: High | N11: 54.3 | O11: 58 | P11: 71 | Q11: 85 | R11: 69.5 | S11: 84 | T11: 98 | U11: 123 | V11: 96.5 | W11: 112 | X11: 125.5 | Y11: 142 | Z11: 108 | AA11: 120 | AB11: 127 | AC11: 154 | AD11: 115 | AE11: 126 | AF11: 143 | AG11: 167 | AH11: 135 | AI11: 150 | AJ11: 168 | AK11: 171 | AL11: 166 | AY11: 386.5 | AZ11: 473 | BA11: 499 | BB11: 559.4 | BC11: 621.2 | BD11: 730
A12: Revenue by Type
A13: Subscription | B13: 0 | C13: 0 | D13: 0 | E13: 0 | F13: 1.071 | G13: 1.291 | H13: 2.539 | I13: 3.849 | J13: 7.005 | K13: 14.837 | L13: 23.327 | M13: 31.561 | N13: 20.365 | O13: 34.086 | P13: 44.084 | Q13: 62.653 | R13: 44.828 | S13: 58.063 | T13: 70.026 | U13: 96.025 | V13: 68.985 | W13: 84.38 | X13: 96.052 | Y13: 116.727 | Z13: 82.974 | AA13: 91.09 | AB13: 97.679 | AC13: 129.164 | AD13: =AD18+AD23 -> 89.965 | AE13: =AE18+AE23 -> 107.514 | AF13: =AF18+AF23 -> 126.556 | AG13: =AG18+AG23 -> 138.987 | AH13: =AH18+AH23 -> 120.048 | AI13: =AI18+AI23 -> 138.269 | AJ13: =+AJ18+AJ23 -> 150.636 | AK13: =+AK18+AK23 -> 163.277 | AL13: =+AL18+AL23 -> 159.38907 | AM13: =+AM18+AM23 -> 171.24836 | AN13: =+AN18+AN23 -> 183.01573 | AO13: =+AO18+AO23 -> 195.52477 | AP13: =+AP18+AP23 -> 206.81946 | AQ13: =+AQ18+AQ23 -> 214.59312 | ... AS13: =+AS18+AS23 -> 231.88418 | AU13: =SUM(B13:E13) -> 0 | AV13: =SUM(F13:I13) -> 8.75 | AW13: =SUM(J13:M13) -> 76.73 | AX13: =SUM(N13:Q13) -> 161.188 | AY13: =SUM(R13:U13) -> 268.942 | AZ13: =SUM(V13:Y13) -> 366.144 | BA13: =SUM(Z13:AC13) -> 400.907 | BB13: =SUM(AD13:AG13) -> 463.022 | BC13: =SUM(AH13:AK13) -> 572.23 | BD13: =SUM(AL13:AO13) -> 709.17794 | BE13: =SUM(AP13:AS13) -> 876.61962
A14: Consensus subscription revenue | B14: ='[2]VA Consensus'!C26 -> - | C14: ='[2]VA Consensus'!D26 -> - | D14: ='[2]VA Consensus'!E26 -> - | E14: ='[2]VA Consensus'!F26 -> - | F14: ='[2]VA Consensus'!G26 -> - | G14: ='[2]VA Consensus'!H26 -> - | H14: ='[2]VA Consensus'!I26 -> - | I14: ='[2]VA Consensus'!J26 -> - | ... AS14: ='[2]VA Consensus'!AT26 -> 228.46285 | AW14: ='[2]VA Consensus'!AX26 -> 73.711943 | AX14: ='[2]VA Consensus'!AY26 -> 150.05446 | AY14: ='[2]VA Consensus'!AZ26 -> 264.88894 | AZ14: ='[2]VA Consensus'!BA26 -> 363.06621 | BA14: ='[2]VA Consensus'!BB26 -> 400.16666 | BB14: ='[2]VA Consensus'!BC26 -> 468.82003 | BC14: ='[2]VA Consensus'!BD26 -> 567.84457 | BD14: ='[2]VA Consensus'!BE26 -> 705.6037 | BE14: ='[2]VA Consensus'!BF26 -> 848.64198
A15: Y/Y % | J15: =J13/F13-1 -> 5.5406162 | K15: =K13/G13-1 -> 10.492641 | L15: =L13/H13-1 -> 8.1874754 | M15: =M13/I13-1 -> 7.1997922 | N15: =N13/J13-1 -> 1.9072091 | O15: =O13/K13-1 -> 1.2973647 | P15: =P13/L13-1 -> 0.88982724 | Q15: =Q13/M13-1 -> 0.98513989 | ... AS15: =AS13/AO13-1 -> 0.18595807 | AU15: =IF(ISERROR(AU13/#REF!-1),"NA",AU13/#REF!-1) -> NA | AV15: =IF(ISERROR(AV13/AU13-1),"NA",AV13/AU13-1) -> NA | AW15: =IF(ISERROR(AW13/AV13-1),"NA",AW13/AV13-1) -> 7.7691429 | AX15: =IF(ISERROR(AX13/AW13-1),"NA",AX13/AW13-1) -> 1.1007168 | AY15: =IF(ISERROR(AY13/AX13-1),"NA",AY13/AX13-1) -> 0.6684989 | AZ15: =IF(ISERROR(AZ13/AY13-1),"NA",AZ13/AY13-1) -> 0.36142365 | BA15: =IF(ISERROR(BA13/AZ13-1),"NA",BA13/AZ13-1) -> 0.094943519 | BB15: =IF(ISERROR(BB13/BA13-1),"NA",BB13/BA13-1) -> 0.15493618 | BC15: =IF(ISERROR(BC13/BB13-1),"NA",BC13/BB13-1) -> 0.2358592 | ... BE15: =IF(ISERROR(BE13/BD13-1),"NA",BE13/BD13-1) -> 0.23610673
A16: % of total revenue | F16: =F13/F5 -> 0.02000822 | G16: =G13/G5 -> 0.020758964 | H16: =H13/H5 -> 0.037866134 | I16: =I13/I5 -> 0.043979524 | J16: =J13/J5 -> 0.12429028 | K16: =K13/K5 -> 0.24885527 | L16: =L13/L5 -> 0.3553291 | M16: =M13/M5 -> 0.43496417 | ... W16: =W13/W5 -> 0.7571244 | X16: 0 | Y16: =Y13/Y5 -> 0.81846484 | Z16: =Z13/Z5 -> 0.77303769 | AA16: =AA13/AA5 -> 0.78921832 | AB16: =AB13/AB5 -> 0.79863132 | AC16: =AC13/AC5 -> 0.83818844 | AD16: =AD13/AD5 -> 0.7890144 | AE16: =AE13/AE5 -> 0.82483544 | AF16: =AF13/AF5 -> 0.8547154 | ... AS16: =AS13/AS5 -> 0.99144876 | AX16: =AX13/AX$5 -> 0.55071424 | AY16: =AY13/AY$5 -> 0.68935802 | AZ16: =AZ13/AZ$5 -> 0.77305261 | BA16: =BA13/BA$5 -> 0.80316331 | BB16: =BB13/BB$5 -> 0.84040657 | BC16: =BC13/BC$5 -> 0.91772355 | BD16: =BD13/BD$5 -> 0.97799343 | BE16: =BE13/BE$5 -> 0.99095657
A18: Term license subscriptions | Z18: 80.906 | AA18: 85.437 | AB18: 83.963 | AC18: 106.2 | AD18: 55.98 | AE18: 62.729 | AF18: 68.751 | AG18: 66.781 | AH18: 31.488 | AI18: 32.374 | AJ18: 24.812 | AK18: 20.961 | BA18: =SUM(Z18:AC18) -> 356.506 | BB18: =SUM(AD18:AG18) -> 254.241 | BC18: =SUM(AH18:AK18) -> 109.635 | BD18: =SUM(AL18:AO18) -> 0
A19: Consensus term license revenue | AE19: ='[2]VA Consensus'!AF25 -> 58.733072 | AF19: ='[2]VA Consensus'!AG25 -> 64.108555 | AG19: ='[2]VA Consensus'!AH25 -> 74.418906 | AH19: ='[2]VA Consensus'!AI25 -> 36.888186 | AI19: ='[2]VA Consensus'!AJ25 -> 35.375066 | AJ19: ='[2]VA Consensus'!AK25 -> 33.219995 | AK19: ='[2]VA Consensus'!AL25 -> 19.857593 | AU19: ='[2]VA Consensus'!AV25 -> 118.22944 | BB19: ='[2]VA Consensus'!BC25 -> 262.44323 | BC19: ='[2]VA Consensus'!BD25 -> 108.53159 | BD19: ='[2]VA Consensus'!BE25 -> 21.360391
A20: Y/Y % | Z20: =IFERROR(Z18/V18-1,"NM") -> NM | AA20: =IFERROR(AA18/W18-1,"NM") -> NM | AB20: =IFERROR(AB18/X18-1,"NM") -> NM | AC20: =IFERROR(AC18/Y18-1,"NM") -> NM | AD20: =IFERROR(AD18/Z18-1,"NM") -> -0.30808593 | AE20: =IFERROR(AE18/AA18-1,"NM") -> -0.26578649 | AF20: =IFERROR(AF18/AB18-1,"NM") -> -0.18117504 | AG20: =IFERROR(AG18/AC18-1,"NM") -> -0.37117702 | ... AK20: =IFERROR(AK18/AG18-1,"NM") -> -0.6861233 | BB20: =BB18/BA18-1 -> -0.28685352 | BC20: =BC18/BB18-1 -> -0.5687753 | BD20: =BD18/BC18-1 -> -1
A21: % of total revenue | Z21: =Z18/Z$5 -> 0.7537709 | AA21: =AA18/AA$5 -> 0.74023982 | AB21: =AB18/AB$5 -> 0.68648821 | AC21: =AC18/AC$5 -> 0.68916735 | AD21: =AD18/AD$5 -> 0.49095789 | AE21: =AE18/AE$5 -> 0.4812499 | AF21: =AF18/AF$5 -> 0.46432045 | AG21: =AG18/AG$5 -> 0.42129402 | ... AK21: =AK18/AK$5 -> 0.12090397 | BA21: =BA18/BA5 -> 0.71421188 | BB21: =BB18/BB5 -> 0.4614593 | BC21: =BC18/BC5 -> 0.17582899 | BD21: =BD18/BD5 -> 0
A23: SaaS | Z23: 2.068 | AA23: 5.653 | AB23: 13.716 | AC23: 23 | AD23: 33.985 | AE23: 44.785 | AF23: 57.805 | AG23: 72.206 | AH23: 88.56 | AI23: 105.895 | AJ23: 125.824 | AK23: 142.316 | AL23: =AL152 -> 159.38907 | AM23: =AM152 -> 171.24836 | AN23: =AN152 -> 183.01573 | AO23: =AO152 -> 195.52477 | AP23: =AP152 -> 206.81946 | AQ23: =AQ152 -> 214.59312 | AR23: =AR152 -> 223.32286 | AS23: =AS152 -> 231.88418 | BA23: =SUM(Z23:AC23) -> 44.437 | BB23: =SUM(AD23:AG23) -> 208.781 | BC23: =SUM(AH23:AK23) -> 462.595 | BD23: =SUM(AL23:AO23) -> 709.17794 | BE23: =SUM(AP23:AS23) -> 876.61962
A24: Consensus SaaS revenue | AE24: ='[2]VA Consensus'!AF24 -> 42.775765 | AF24: ='[2]VA Consensus'!AG24 -> 55.331742 | AG24: ='[2]VA Consensus'!AH24 -> 69.114064 | AH24: ='[2]VA Consensus'!AI24 -> 78.121681 | AI24: ='[2]VA Consensus'!AJ24 -> 96.302924 | AJ24: ='[2]VA Consensus'!AK24 -> 119.18906 | AK24: ='[2]VA Consensus'!AL24 -> 139.88286 | AL24: ='[2]VA Consensus'!AM24 -> 150.40359 | ... AS24: ='[2]VA Consensus'!AT24 -> 226.36455 | AU24: ='[2]VA Consensus'!AV24 -> 118.32642 | BB24: ='[2]VA Consensus'!BC24 -> 205.01188 | BC24: ='[2]VA Consensus'!BD24 -> 460.16186 | BD24: ='[2]VA Consensus'!BE24 -> 684.49882 | BE24: ='[2]VA Consensus'!BF24 -> 843.38756
A25: Y/Y % | Z25: =IFERROR(Z23/V23-1,"NM") -> NM | AA25: =IFERROR(AA23/W23-1,"NM") -> NM | AB25: =IFERROR(AB23/X23-1,"NM") -> NM | AC25: =IFERROR(AC23/Y23-1,"NM") -> NM | AD25: =IFERROR(AD23/Z23-1,"NM") -> 15.433752 | AE25: =IFERROR(AE23/AA23-1,"NM") -> 6.9223421 | AF25: =IFERROR(AF23/AB23-1,"NM") -> 3.2144211 | AG25: =IFERROR(AG23/AC23-1,"NM") -> 2.1393913 | ... AS25: =IFERROR(AS23/AO23-1,"NM") -> 0.18595807 | BB25: =BB23/BA23-1 -> 3.6983595 | BC25: =BC23/BB23-1 -> 1.2156949 | BD25: =BD23/BC23-1 -> 0.53304281 | BE25: =BE23/BD23-1 -> 0.23610673
A26: % of total revenue | Z26: =Z23/Z$5 -> 0.019266782 | AA26: =AA23/AA$5 -> 0.048978496 | AB26: =AB23/AB$5 -> 0.11214311 | AC26: =AC23/AC$5 -> 0.1492547 | AD26: =AD23/AD$5 -> 0.29805652 | AE26: =AE23/AE$5 -> 0.34358553 | AF26: =AF23/AF$5 -> 0.39039495 | AG26: =AG23/AG$5 -> 0.45551812 | AH26: =AH23/AH$5 -> 0.6491574 | AI26: =AI23/AI5 -> 0.69593134 | AJ26: =AJ23/AJ$5 -> 0.77872469 | AK26: =AK23/AK5 -> 0.82088493 | AL26: =AL23/AL5 -> 0.96401456 | AM26: =AM23/AM5 -> 0.97349601 | AN26: =AN23/AN5 -> 0.98204767 | AO26: =AO23/AO5 -> 0.98987469 | AP26: =AP23/AP5 -> 0.99042235 | AQ26: =AQ23/AQ5 -> 0.9907661 | AR26: =AR23/AR5 -> 0.99112385 | AS26: =AS23/AS5 -> 0.99144876 | BA26: =BA23/BA5 -> 0.08902356 | BB26: =BB23/BB5 -> 0.37894727 | BC26: =BC23/BC5 -> 0.74189456 | BD26: =BD23/BD5 -> 0.97799343 | BE26: =BE23/BE5 -> 0.99095657
A28: Perpetual License | B28: 18.092 | C28: 27.31 | D28: 29 | E28: 45.939 | F28: 24.086 | G28: 32.27 | H28: 33.432 | I28: 49.79 | J28: 15.521 | K28: 11.514 | L28: 8.269 | M28: 6.789 | N28: 0.388 | O28: 0.24 | P28: 0.373 | Q28: 0.472 | R28: 0.286 | S28: 0.34 | T28: 0.324 | U28: 0.94 | AU28: =SUM(B28:E28) -> 120.341 | AV28: =SUM(F28:I28) -> 139.578 | AW28: =SUM(J28:M28) -> 42.093 | AX28: =SUM(N28:Q28) -> 1.473 | AY28: =SUM(R28:U28) -> 1.89
A29: Consensus perpetual license revenue | N29: 1.6 | O29: 0.6 | P29: 0.3 | Q29: 0.3 | R29: 0.3 | S29: 0.2 | T29: 0.3 | U29: 0.3 | AX29: 1.3 | AY29: 1.3
A30: Y/Y % | F30: =F28/B28-1 -> 0.33130665 | G30: =G28/C28-1 -> 0.18161845 | H30: =H28/D28-1 -> 0.15282759 | I30: =I28/E28-1 -> 0.083828555 | J30: =J28/F28-1 -> -0.35560076 | K30: =K28/G28-1 -> -0.64319802 | L30: =L28/H28-1 -> -0.75266212 | M30: =M28/I28-1 -> -0.86364732 | ... U30: =U28/Q28-1 -> 0.99152542 | AU30: =IF(ISERROR(AU28/#REF!-1),"NA",AU28/#REF!-1) -> NA | AV30: =IF(ISERROR(AV28/AU28-1),"NA",AV28/AU28-1) -> 0.15985408 | AW30: =IF(ISERROR(AW28/AV28-1),"NA",AW28/AV28-1) -> -0.69842669 | AX30: =IF(ISERROR(AX28/AW28-1),"NA",AX28/AW28-1) -> -0.96500606 | AY30: =IF(ISERROR(AY28/AX28-1),"NA",AY28/AX28-1) -> 0.28309572
A31: % of total revenue | B31: =B28/B5 -> 0.45694946 | C31: =C28/C5 -> 0.55248731 | D31: =D28/D5 -> 0.54342734 | E31: =E28/E5 -> 0.62929275 | F31: =F28/F5 -> 0.44997011 | G31: =G28/G5 -> 0.51889371 | H31: =H28/H5 -> 0.4985981 | I31: =I28/I5 -> 0.56891154 | ... U31: =U28/U5 -> 0.007426251 | AU31: =AU28/AU$5 -> 0.5587121 | AV31: =AV28/AV$5 -> 0.51640472 | AW31: =AW28/AW$5 -> 0.1655966 | AX31: =AX28/AX$5 -> 0.0050326456 | AY31: =AY28/AY$5 -> 0.0048444893
A33: Maintenance and Services | B33: 21.501 | C33: 22.121 | D33: 24.365 | E33: 27.062 | F33: 28.371 | G33: 28.629 | H33: 31.081 | I33: 33.879 | J33: 33.834 | K33: 33.27 | L33: 34.053 | M33: 34.21 | N33: 33.423 | O33: 32.239 | P33: 32.294 | Q33: 32.072 | R33: 29.671 | S33: 30.015 | T33: 30.003 | U33: 29.613 | V33: 27.276 | W33: 27.068 | X33: 27.256 | Y33: 25.89 | Z33: 24.361 | AA33: 24.328 | AB33: 24.629 | AC33: 24.935 | AD33: 24.057 | AE33: 22.832 | AF33: 21.512 | AG33: 19.527 | AH33: 16.375 | AI33: 13.894 | AJ33: 10.941 | AK33: 10.092 | AL33: =+AL164 -> 5.9497918 | AM33: =+AM164 -> 4.6623359 | AN33: =+AN164 -> 3.3456197 | AO33: =+AO164 -> 2 | AP33: =+AP164 -> 2 | AQ33: =+AQ164 -> 2 | AR33: =+AR164 -> 2 | AS33: =+AS164 -> 2 | AU33: =SUM(B33:E33) -> 95.049 | AV33: =SUM(F33:I33) -> 121.96 | AW33: =SUM(J33:M33) -> 135.367 | AX33: =SUM(N33:Q33) -> 130.028 | AY33: =SUM(R33:U33) -> 119.302 | AZ33: =SUM(V33:Y33) -> 107.49 | BA33: =SUM(Z33:AC33) -> 98.253 | BB33: =SUM(AD33:AG33) -> 87.928 | BC33: =SUM(AH33:AK33) -> 51.302 | BD33: =SUM(AL33:AO33) -> 15.957747 | BE33: =SUM(AP33:AS33) -> 8
A34: Consensus professional services revenue | B34: ='[2]VA Consensus'!C27 -> 21.225 | C34: ='[2]VA Consensus'!D27 -> 21.450574 | D34: ='[2]VA Consensus'!E27 -> 22.849497 | E34: ='[2]VA Consensus'!F27 -> 25.265076 | F34: ='[2]VA Consensus'!G27 -> 27.406415 | G34: ='[2]VA Consensus'!H27 -> 28.397139 | H34: ='[2]VA Consensus'!I27 -> 29.973594 | I34: ='[2]VA Consensus'!J27 -> 32.610856 | ... AS34: ='[2]VA Consensus'!AT27 -> 3.2537107 | AU34: ='[2]VA Consensus'!AV27 -> 92.436076 | AV34: ='[2]VA Consensus'!AW27 -> 121.03943 | AW34: ='[2]VA Consensus'!AX27 -> 134.97085 | AX34: ='[2]VA Consensus'!AY27 -> 130.41798 | AY34: ='[2]VA Consensus'!AZ27 -> 119.32442 | AZ34: ='[2]VA Consensus'!BA27 -> 108.09069 | BA34: ='[2]VA Consensus'!BB27 -> 96.918977 | BB34: ='[2]VA Consensus'!BC27 -> 89.156483 | ... BE34: ='[2]VA Consensus'!BF27 -> 15.165337
A35: Y/Y % | F35: =F33/B33-1 -> 0.31952002 | G35: =G33/C33-1 -> 0.29420008 | H35: =H33/D33-1 -> 0.27564129 | I35: =I33/E33-1 -> 0.25190304 | J35: =J33/F33-1 -> 0.19255578 | K35: =K33/G33-1 -> 0.16210835 | L35: =L33/H33-1 -> 0.095621119 | M35: =M33/I33-1 -> 0.0097700641 | ... AK35: =AK33/AG33-1 -> -0.48317714 | AL35: =AK35 -> -0.48317714 | AM35: =AL35 -> -0.48317714 | AN35: =AM35 -> -0.48317714 | AO35: =AN35 -> -0.48317714 | AP35: -0.5 | AQ35: =AP35 -> -0.5 | AR35: =AQ35 -> -0.5 | AS35: =AR35 -> -0.5 | AU35: =IF(ISERROR(AU33/#REF!-1),"NA",AU33/#REF!-1) -> NA | AV35: =IF(ISERROR(AV33/AU33-1),"NA",AV33/AU33-1) -> 0.28312765 | AW35: =IF(ISERROR(AW33/AV33-1),"NA",AW33/AV33-1) -> 0.10992949 | AX35: =IF(ISERROR(AX33/AW33-1),"NA",AX33/AW33-1) -> -0.039440927 | AY35: =IF(ISERROR(AY33/AX33-1),"NA",AY33/AX33-1) -> -0.082489925 | AZ35: =IF(ISERROR(AZ33/AY33-1),"NA",AZ33/AY33-1) -> -0.099009237 | BA35: =IF(ISERROR(BA33/AZ33-1),"NA",BA33/AZ33-1) -> -0.085933575 | BB35: =IF(ISERROR(BB33/BA33-1),"NA",BB33/BA33-1) -> -0.10508585 | BC35: =IF(ISERROR(BC33/BB33-1),"NA",BC33/BB33-1) -> -0.41654536 | ... BE35: =IF(ISERROR(BE33/BD33-1),"NA",BE33/BD33-1) -> -0.49867611
A36: % of total revenue | B36: =B33/B5 -> 0.54305054 | C36: =C33/C5 -> 0.44751269 | D36: =D33/D5 -> 0.45657266 | E36: =E33/E5 -> 0.37070725 | F36: =F33/F5 -> 0.53002167 | G36: =G33/G5 -> 0.46034732 | H36: =H33/H5 -> 0.46353576 | I36: =I33/I5 -> 0.38710894 | ... AS36: =AS33/AS5 -> 0.0085512412 | AU36: =AU33/AU$5 -> 0.4412879 | AV36: =AV33/AV$5 -> 0.4512224 | AW36: =AW33/AW$5 -> 0.53254259 | AX36: =AX33/AX$5 -> 0.44425312 | AY36: =AY33/AY$5 -> 0.3057975 | AZ36: =AZ33/AZ$5 -> 0.22694739 | BA36: =BA33/BA$5 -> 0.19683669 | BB36: =BB33/BB$5 -> 0.15959343 | ... BE36: =BE33/BE$5 -> 0.009043435
B38: ='Income Statement'!B$3 -> 2017 | F38: ='Income Statement'!F$3 -> 2018 | J38: ='Income Statement'!J$3 -> 2019 | N38: ='Income Statement'!N$3 -> 2020 | R38: ='Income Statement'!R$3 -> 2021 | V38: ='Income Statement'!V$3 -> 2022 | Z38: ='Income Statement'!Z$3 -> 2023 | AD38: ='Income Statement'!AD$3 -> 2024 | AH38: ='Income Statement'!AH$3 -> 2025 | AL38: ='Income Statement'!AL$3 -> 2026 | AP38: ='Income Statement'!AP$3 -> 2027
A39: Annual Recurring Revenue (ARR) | B39: ='Income Statement'!B$4 -> 42825 | C39: ='Income Statement'!C$4 -> 42916 | D39: ='Income Statement'!D$4 -> 43008 | E39: ='Income Statement'!E$4 -> 43100 | F39: ='Income Statement'!F$4 -> 43190 | G39: ='Income Statement'!G$4 -> 43281 | H39: ='Income Statement'!H$4 -> 43373 | I39: ='Income Statement'!I$4 -> 43465 | ... AS39: ='Income Statement'!AS$4 -> Dec-27E | AU39: ='Income Statement'!AU$4 -> 2017 | AV39: ='Income Statement'!AV$4 -> 2018 | AW39: ='Income Statement'!AW$4 -> 2019 | AX39: ='Income Statement'!AX$4 -> 2020 | AY39: ='Income Statement'!AY$4 -> 2021 | AZ39: ='Income Statement'!AZ$4 -> 2022 | BA39: ='Income Statement'!BA$4 -> 2023 | BB39: ='Income Statement'!BB$4 -> 2024 | ... BD39: ='Income Statement'!BD$4 -> 2026E | BE39: =BE4 -> 2027E
A40: Total ARR | F40: 103 | G40: 111.9 | H40: 117.9 | I40: 130.3 | J40: 138.7 | K40: 155.2 | L40: 178.9 | M40: 210.5 | N40: 220.5 | O40: 235.7 | P40: 261.1 | Q40: 287.3 | R40: 306.9 | S40: 328.2 | T40: 354.2 | U40: 387.1 | V40: 404.5 | W40: 426.3 | X40: 447.8 | Y40: 465.1 | Z40: 478.1 | AA40: 497 | AB40: 517.5 | AC40: 543 | AD40: 560.3 | AE40: 584.2 | AF40: 610 | AG40: 641.9 | AH40: 664.3 | AI40: 693.2 | AJ40: 718.6 | AK40: 745.4 | AL40: =AL143 -> 755.475 | AM40: =AM143 -> 774.785 | AN40: =AN143 -> 796.3475 | AO40: =AO143 -> 822.4625 | AP40: =AP143 -> 851.915 | AQ40: =AQ143 -> 887.126 | AR40: =AR143 -> 920.41475 | AS40: =AS143 -> 955.96125 | AV40: =I40 -> 130.3 | AW40: =M40 -> 210.5 | AX40: =Q40 -> 287.3 | AY40: =U40 -> 387.1 | AZ40: =Y40 -> 465.1 | BA40: =AC40 -> 543 | BB40: =AG40 -> 641.9 | BC40: =AK40 -> 745.4 | BD40: =AO40 -> 822.4625 | BE40: =AS40 -> 955.96125
A41: Consensus ARR | B41: ='[2]VA Consensus'!C17 -> - | C41: ='[2]VA Consensus'!D17 -> - | D41: ='[2]VA Consensus'!E17 -> - | E41: ='[2]VA Consensus'!F17 -> - | F41: ='[2]VA Consensus'!G17 -> - | G41: ='[2]VA Consensus'!H17 -> - | H41: ='[2]VA Consensus'!I17 -> - | I41: ='[2]VA Consensus'!J17 -> - | ... AS41: ='[2]VA Consensus'!AT17 -> 940.97822 | AW41: ='[2]VA Consensus'!AX17 -> 192.8007 | AX41: ='[2]VA Consensus'!AY17 -> 270.05942 | AY41: ='[2]VA Consensus'!AZ17 -> 380.49017 | AZ41: ='[2]VA Consensus'!BA17 -> 453.5074 | BA41: ='[2]VA Consensus'!BB17 -> 537.31447 | BB41: ='[2]VA Consensus'!BC17 -> 637.73931 | BC41: ='[2]VA Consensus'!BD17 -> 734.46679 | BD41: ='[2]VA Consensus'!BE17 -> 821.1766 | BE41: ='[2]VA Consensus'!BF17 -> 940.97822
A42: Y/Y % | J42: =J40/F40-1 -> 0.34660194 | K42: =K40/G40-1 -> 0.38695264 | L42: =L40/H40-1 -> 0.51738762 | M42: =M40/I40-1 -> 0.61550269 | N42: =N40/J40-1 -> 0.58976208 | O42: =O40/K40-1 -> 0.51868557 | P42: =P40/L40-1 -> 0.45947457 | Q42: =Q40/M40-1 -> 0.36484561 | ... AS42: =AS40/AO40-1 -> 0.16231591 | AW42: NA | AX42: =AX40/AW40-1 -> 0.36484561 | AY42: =AY40/AX40-1 -> 0.34737208 | AZ42: =AZ40/AY40-1 -> 0.20149832 | BA42: =BA40/AZ40-1 -> 0.16749086 | BB42: =BB40/BA40-1 -> 0.18213628 | BC42: =BC40/BB40-1 -> 0.16124007 | BD42: =BD40/BC40-1 -> 0.10338409 | BE42: =BE40/BD40-1 -> 0.16231591
A43: Management Guidance - FY ARR
A44: Low | AC44: 535 | AD44: 617 | AE44: 622 | AF44: 629 | AG44: =BB44 -> 635 | AH44: 737 | AI44: 748 | AJ44: 748 | AK44: =BC44 -> 730 | AO44: =BD44 -> 805 | AZ44: 460 | BA44: 535 | BB44: 635 | BC44: 730 | BD44: 805
A45: Mid | AC45: =AVERAGE(AC44,AC46) -> 537 | AD45: =AVERAGE(AD44,AD46) -> 621 | AE45: =AZ45 -> 461.5 | AF45: =BA45 -> 537 | AG45: =BB45 -> 637 | AH45: =BC45 -> 734 | AI45: =AVERAGE(AI44,AI46) -> 751 | AJ45: =AVERAGE(AJ44,AJ46) -> 751 | AK45: =AVERAGE(AK44,AK46) -> 734 | AO45: =AVERAGE(AO44,AO46) -> 822.5 | AZ45: =AVERAGE(AZ44,AZ46) -> 461.5 | BA45: =AVERAGE(BA44,BA46) -> 537 | BB45: =IFERROR(AVERAGE(BB44,BB46),"") -> 637 | BC45: =IFERROR(AVERAGE(BC44,BC46),"") -> 734 | BD45: =IFERROR(AVERAGE(BD44,BD46),"") -> 822.5 | BE45: =IFERROR(AVERAGE(BE44,BE46),"")
A46: High | AC46: 539 | AD46: 625 | AE46: 628 | AF46: 635 | AG46: =BB46 -> 639 | AH46: 745 | AI46: 754 | AJ46: 754 | AK46: =BC46 -> 738 | AO46: =BD46 -> 840 | AZ46: 463 | BA46: 539 | BB46: 639 | BC46: 738 | BD46: 840
A47: Net New ARR | G47: =G40-F40 -> 8.9 | H47: =H40-G40 -> 6 | I47: =I40-H40 -> 12.4 | J47: =J40-I40 -> 8.4 | K47: =K40-J40 -> 16.5 | L47: =L40-K40 -> 23.7 | M47: =M40-L40 -> 31.6 | N47: =N40-M40 -> 10 | ... AS47: =AS40-AR40 -> 35.5465 | AW47: =+AW40-AV40 -> 80.2 | AX47: =+AX40-AW40 -> 76.8 | AY47: =+AY40-AX40 -> 99.8 | AZ47: =+AZ40-AY40 -> 78 | BA47: =+BA40-AZ40 -> 77.9 | BB47: =+BB40-BA40 -> 98.9 | BC47: =+BC40-BB40 -> 103.5 | BD47: =+BD40-BC40 -> 77.0625 | BE47: =+BE40-BD40 -> 133.49875
A48: Consensus Net New ARR | L48: =L41-K40 -> -1.93 | M48: =M41-L40 -> 13.9007 | N48: =N41-M40 -> -0.73332988 | O48: =O41-N40 -> -6.3139605 | P48: =P41-O40 -> 9.3106414 | Q48: =Q41-P40 -> 18.885996 | R48: =R41-Q40 -> 8.3793562 | S48: =S41-R40 -> 12.396468 | ... AG48: =AG41-AF40 -> 27.73931 | AH48: =AH41-AG41 -> 20.87061 | AI48: =AI41-AH40 -> 23.525473 | AJ48: =AJ41-AI41 -> 32.200829 | AK48: =AK41-AJ41 -> 14.440485 | AL48: =AL41-AK41 -> 14.55675 | AM48: =AM41-AL41 -> 22.244048 | AN48: =AN41-AM41 -> 23.272902 | AO48: =AO41-AN41 -> 26.636109 | AP48: =AP41-AO41 -> 23.18489 | AQ48: =AQ41-AP41 -> 29.133722 | ... AS48: =AS41-AR41 -> 37.13939 | AX48: =AX41-AW40 -> 59.559425 | AY48: =AY41-AX40 -> 93.190172 | AZ48: =AZ41-AY40 -> 66.4074 | BA48: =BA41-AZ40 -> 72.214472 | BB48: =BB41-BA40 -> 94.73931 | BC48: =BC41-BB41 -> 96.727477 | BD48: =BD41-BC41 -> 86.70981 | BE48: =BE41-BD41 -> 119.80162
A49: Y/Y % | J49: NM | K49: =K47/G47-1 -> 0.85393258 | L49: =L47/H47-1 -> 2.95 | M49: =M47/I47-1 -> 1.5483871 | N49: =N47/J47-1 -> 0.19047619 | O49: =O47/K47-1 -> -0.078787879 | P49: =P47/L47-1 -> 0.071729958 | Q49: =Q47/M47-1 -> -0.17088608 | R49: =R47/N47-1 -> 0.96 | ... AS49: =AS47/AO47-1 -> 0.36115259 | AX49: =AX47/AW47-1 -> -0.042394015 | AY49: =AY47/AX47-1 -> 0.29947917 | AZ49: =AZ47/AY47-1 -> -0.21843687 | BA49: =BA47/AZ47-1 -> -0.0012820513 | BB49: =BB47/BA47-1 -> 0.26957638 | BC49: =BC47/BB47-1 -> 0.046511628 | BD49: =BD47/BC47-1 -> -0.25543478 | BE49: =BE47/BD47-1 -> 0.73234388
A50: ARR Contribution Margin | F50: =('Revenue Build'!F40-SUM('Income Statement'!C15:F15,'Income Statement'!C23:F23))/'Revenue Build'!F40 -> -1.1488058 | G50: =('Revenue Build'!G40-SUM('Income Statement'!D15:G15,'Income Statement'!D23:G23))/'Revenue Build'!G40 -> -1.0952726 | H50: =('Revenue Build'!H40-SUM('Income Statement'!E15:H15,'Income Statement'!E23:H23))/'Revenue Build'!H40 -> -1.1041561 | I50: =('Revenue Build'!I40-SUM('Income Statement'!F15:I15,'Income Statement'!F23:I23))/'Revenue Build'!I40 -> -0.99913277 | J50: =('Revenue Build'!J40-SUM('Income Statement'!G15:J15,'Income Statement'!G23:J23))/'Revenue Build'!J40 -> -0.9305119 | K50: =('Revenue Build'!K40-SUM('Income Statement'!H15:K15,'Income Statement'!H23:K23))/'Revenue Build'!K40 -> -0.75978093 | L50: =('Revenue Build'!L40-SUM('Income Statement'!I15:L15,'Income Statement'!I23:L23))/'Revenue Build'!L40 -> -0.5564114 | M50: =('Revenue Build'!M40-SUM('Income Statement'!J15:M15,'Income Statement'!J23:M23))/'Revenue Build'!M40 -> -0.3367696 | ... AS50: =('Revenue Build'!AS40-SUM('Income Statement'!AP15:AS15,'Income Statement'!AP23:AS23))/'Revenue Build'!AS40 -> 0.12058426 | AV50: =0+(('Revenue Build'!AV40-SUM('Income Statement'!AV15,'Income Statement'!AV23))/'Revenue Build'!AV40) -> -0.99913277 | AW50: =0+(('Revenue Build'!AW40-SUM('Income Statement'!AW15,'Income Statement'!AW23))/'Revenue Build'!AW40) -> -0.3367696 | AX50: =0+(('Revenue Build'!AX40-SUM('Income Statement'!AX15,'Income Statement'!AX23))/'Revenue Build'!AX40) -> -0.034239471 | AY50: =0+(('Revenue Build'!AY40-SUM('Income Statement'!AY15,'Income Statement'!AY23))/'Revenue Build'!AY40) -> 0.057367605 | AZ50: =0+(('Revenue Build'!AZ40-SUM('Income Statement'!AZ15,'Income Statement'!AZ23))/'Revenue Build'!AZ40) -> 0.04515158 | BA50: =0+(('Revenue Build'!BA40-SUM('Income Statement'!BA15,'Income Statement'!BA23))/'Revenue Build'!BA40) -> 0.13367035 | BB50: =('Revenue Build'!BB40-SUM('Income Statement'!BB15,'Income Statement'!BB23))/'Revenue Build'!BB40 -> 0.16647609 | BC50: =('Revenue Build'!BC40-SUM('Income Statement'!BC15,'Income Statement'!BC23))/'Revenue Build'!BC40 -> 0.15860209 | BD50: =('Revenue Build'!BD40-SUM('Income Statement'!BD15,'Income Statement'!BD23))/'Revenue Build'!BD40 -> 0.12171003 | BE50: =('Revenue Build'!BE40-SUM('Income Statement'!BE15,'Income Statement'!BE23))/'Revenue Build'!BE40 -> 0.12058426
A52: SaaS ARR | Z52: =Z55*Z40 -> 23.905 | AA52: =AA55*AA40 -> 49.7 | AB52: =AB55*AB40 -> 77.625 | AC52: =AC55*AC40 -> 124.89 | AD52: =AD55*AD40 -> 168.09 | AE52: =AE55*AE40 -> 210.312 | AF52: =AF55*AF40 -> 262.3 | AG52: =AG55*AG40 -> 340.207 | AH52: =+AH60 -> 405.307 | AI52: =+AI60 -> 478.407 | AJ52: =+AJ60 -> 546.207 | AK52: =+AK60 -> 638.607 | AL52: =+AL146 -> 675.382 | AM52: =+AM146 -> 721.392 | AN52: =+AN146 -> 769.6545 | AO52: =+AO146 -> 822.4695 | AP52: =+AP146 -> 851.922 | AQ52: =+AQ146 -> 887.133 | AR52: =+AR146 -> 920.42175 | AS52: =+AS146 -> 955.96825 | BA52: =AC52 -> 124.89 | BB52: =AG52 -> 340.207 | BC52: =AK52 -> 638.607 | BD52: =AO52 -> 822.4695 | BE52: =AS52 -> 955.96825
A53: Consensus SaaS ARR | B53: ='[2]VA Consensus'!C13 -> - | C53: ='[2]VA Consensus'!D13 -> - | D53: ='[2]VA Consensus'!E13 -> - | E53: ='[2]VA Consensus'!F13 -> - | F53: ='[2]VA Consensus'!G13 -> - | G53: ='[2]VA Consensus'!H13 -> - | H53: ='[2]VA Consensus'!I13 -> - | I53: ='[2]VA Consensus'!J13 -> - | ... AS53: ='[2]VA Consensus'!AT13 -> 955.00271 | AU53: ='[2]VA Consensus'!AV13 -> - | AV53: ='[2]VA Consensus'!AW13 -> - | AW53: ='[2]VA Consensus'!AX13 -> - | AX53: ='[2]VA Consensus'!AY13 -> - | AY53: ='[2]VA Consensus'!AZ13 -> - | AZ53: ='[2]VA Consensus'!BA13 -> - | BA53: ='[2]VA Consensus'!BB13 -> - | BB53: ='[2]VA Consensus'!BC13 -> 315.06722 | ... BE53: ='[2]VA Consensus'!BF13 -> 955.00271
A54: Y/Y % | AD54: =AD52/Z52-1 -> 6.0315834 | AE54: =AE52/AA52-1 -> 3.2316298 | AF54: =AF52/AB52-1 -> 2.379066 | AG54: =AG52/AC52-1 -> 1.7240532 | AH54: =AH52/AD52-1 -> 1.4112499 | AI54: =AI52/AE52-1 -> 1.2747489 | AJ54: =AJ52/AF52-1 -> 1.0823751 | AK54: =AK52/AG52-1 -> 0.87711305 | ... AS54: =AS52/AO52-1 -> 0.16231453 | BA54: =IF(ISERROR(BA52/AZ52-1),"NA",BA52/AZ52-1) -> NA | BB54: =IF(ISERROR(BB52/BA52-1),"NA",BB52/BA52-1) -> 1.7240532 | BC54: =IF(ISERROR(BC52/BB52-1),"NA",BC52/BB52-1) -> 0.87711305 | BD54: =IF(ISERROR(BD52/BC52-1),"NA",BD52/BC52-1) -> 0.28791181 | BE54: =IF(ISERROR(BE52/BD52-1),"NA",BE52/BD52-1) -> 0.16231453
A55: % of Total ARR | Z55: 0.05 | AA55: 0.1 | AB55: 0.15 | AC55: 0.23 | AD55: 0.3 | AE55: 0.36 | AF55: 0.43 | AG55: 0.53 | AH55: 0.61 | AI55: 0.69 | AJ55: 0.76 | AK55: 0.86 | AL55: =+AL52/AL40 -> 0.89398326 | AM55: =+AM52/AM40 -> 0.93108669 | AN55: =+AN52/AN40 -> 0.96648071 | AO55: =+AO52/AO40 -> 1.0000085 | AP55: =+AP52/AP40 -> 1.0000082 | AQ55: =+AQ52/AQ40 -> 1.0000079 | AR55: =+AR52/AR40 -> 1.0000076 | AS55: =+AS52/AS40 -> 1.0000073 | BA55: =AC55 -> 0.23 | BB55: =AG55 -> 0.53 | BC55: =AK55 -> 0.86 | BD55: =AO55 -> 1.0000085 | BE55: =AS55 -> 1.0000073
A56: Net New SaaS ARR | AA56: =AA52-Z52 -> 25.795 | AB56: =AB52-AA52 -> 27.925 | AC56: =AC52-AB52 -> 47.265 | AD56: =AD52-AC52 -> 43.2 | AE56: =AE52-AD52 -> 42.222 | AF56: =AF52-AE52 -> 51.988 | AG56: =AG52-AF52 -> 77.907 | AH56: =AH52-AG52 -> 65.1 | ... AS56: =AS52-AR52 -> 35.5465 | BB56: =+BB52-BA52 -> 215.317 | BC56: =+BC52-BB52 -> 298.4 | BD56: =+BD52-BC52 -> 183.8625 | BE56: =+BE52-BD52 -> 133.49875
A57: Y/Y % | AE57: =AE56/AA56-1 -> 0.63682884 | AF57: =AF56/AB56-1 -> 0.86170098 | AG57: =AG56/AC56-1 -> 0.64830213 | AH57: =AH56/AD56-1 -> 0.50694444 | AI57: =AI56/AE56-1 -> 0.7313249 | AJ57: =AJ56/AF56-1 -> 0.30414711 | AK57: =AK56/AG56-1 -> 0.1860295 | AL57: =AL56/AH56-1 -> -0.43509985 | ... AS57: =AS56/AO56-1 -> -0.32696204 | BB57: =IF(ISERROR(BB56/BA56-1),"NA",BB56/BA56-1) -> NA | BC57: =IF(ISERROR(BC56/BB56-1),"NA",BC56/BB56-1) -> 0.38586363 | BD57: =IF(ISERROR(BD56/BC56-1),"NA",BD56/BC56-1) -> -0.38383881 | BE57: =IF(ISERROR(BE56/BD56-1),"NA",BE56/BD56-1) -> -0.27392073
A58: Net New SaaS ARR (+ conversion ARR) | AH58: 39.6 | AI58: 44 | AJ58: 40.9 | AK58: 64.3 | AL58: =+AL169 -> 10 | AM58: =+AM169 -> 14 | AN58: =+AN169 -> 18 | AO58: =+AO169 -> 20.5 | AP58: =+AP169 -> 0 | AQ58: =+AQ169 -> 0 | AR58: =+AR169 -> 0 | AS58: =+AS169 -> 0 | BB58: =+BB60-BA60 -> 340.207 | BC58: =+BC60-BB60 -> 298.4 | BD58: =+BD60-BC60 -> 183.8625 | BE58: =+BE60-BD60 -> 133.49875
A60: SaaS ARR | AH60: =+AG52+AH64+AH58 -> 405.307 | AI60: =+AH52+AI64+AI58 -> 478.407 | AJ60: =+AI52+AJ64+AJ58 -> 546.207 | AK60: =+AJ52+AK64+AK58 -> 638.607 | AL60: =+AK52+AL64+AL58 -> 675.382 | AM60: =+AL52+AM64+AM58 -> 721.392 | AN60: =+AM52+AN64+AN58 -> 769.6545 | AO60: =+AN52+AO64+AO58 -> 822.4695 | ... AS60: =+AR52+AS64+AS58 -> 955.96825 | BA60: =AC60 -> 0 | BB60: =+AG52 -> 340.207 | BC60: =AK60 -> 638.607 | BD60: =AO60 -> 822.4695 | BE60: =AS60 -> 955.96825
A61: Y/Y % | AL61: =AL60/AH60-1 -> 0.66634674 | AM61: =AM60/AI60-1 -> 0.50790436 | AN61: =AN60/AJ60-1 -> 0.40908941 | AO61: =AO60/AK60-1 -> 0.28791181 | AP61: =AP60/AL60-1 -> 0.26139281 | AQ61: =AQ60/AM60-1 -> 0.22975165 | AR61: =AR60/AN60-1 -> 0.19588952 | AS61: =AS60/AO60-1 -> 0.16231453 | BA61: =IF(ISERROR(BA60/AZ60-1),"NA",BA60/AZ60-1) -> NA | BB61: =IF(ISERROR(BB60/BA60-1),"NA",BB60/BA60-1) -> NA | BC61: =IF(ISERROR(BC60/BB60-1),"NA",BC60/BB60-1) -> 0.87711305 | BD61: =IF(ISERROR(BD60/BC60-1),"NA",BD60/BC60-1) -> 0.28791181 | BE61: =IF(ISERROR(BE60/BD60-1),"NA",BE60/BD60-1) -> 0.16231453
A62: SaaS ARR (ex conversions) | AH62: =+AG52+AH64 -> 365.707 | AI62: =+AH62+AI64 -> 394.807 | AJ62: =+AI62+AJ64 -> 421.707 | AK62: =+AJ62+AK64 -> 449.807 | AL62: =+AH52+SUM(AI64:AL64) -> 516.182 | AM62: =+AI52+SUM(AJ64:AM64) -> 592.192 | AN62: =+AJ52+SUM(AK64:AN64) -> 663.3545 | AO62: =+AK52+SUM(AL64:AO64) -> 759.9695 | AP62: =+AL52+SUM(AM64:AP64) -> 799.422 | AQ62: =+AM52+SUM(AN64:AQ64) -> 848.633 | AR62: =+AN52+SUM(AO64:AR64) -> 899.92175 | AS62: =+AO52+SUM(AP64:AS64) -> 955.96825
A63: Y/Y % | AK63: =+(AK62/AG52)-1 -> 0.3221568 | AL63: =+AL62/AH52-1 -> 0.27355807 | AM63: =+AM62/AI52-1 -> 0.23784142 | AN63: =+AN62/AJ52-1 -> 0.21447455 | AO63: =+AO62/AK52-1 -> 0.19004255 | AP63: =+AP62/AL52-1 -> 0.18365903 | AQ63: =+AQ62/AM52-1 -> 0.1763826 | AR63: =+AR62/AN52-1 -> 0.16925419 | AS63: =+AS62/AO52-1 -> 0.16231453
A64: Net New SaaS ARR (ex conversions) | AH64: 25.5 | AI64: 29.1 | AJ64: 26.9 | AK64: 28.1 | AL64: =+AL171 -> 26.775 | AM64: =+AM171 -> 32.01 | AN64: =+AN171 -> 30.2625 | AO64: =+AO171 -> 32.315 | AP64: =+AP171 -> 29.4525 | AQ64: =+AQ171 -> 35.211 | AR64: =+AR171 -> 33.28875 | AS64: =+AS171 -> 35.5465 | BC64: =+SUM(AH64:AK64) -> 109.6 | BD64: =+SUM(AL64:AO64) -> 121.3625 | BE64: =+SUM(AP64:AS64) -> 133.49875
A65: Y/Y % | AL65: =AL64/AH64-1 -> 0.05 | AM65: =AM64/AI64-1 -> 0.1 | AN65: =AN64/AJ64-1 -> 0.125 | AO65: =AO64/AK64-1 -> 0.15 | AP65: =AP64/AL64-1 -> 0.1 | AQ65: =AQ64/AM64-1 -> 0.1 | AR65: =AR64/AN64-1 -> 0.1 | AS65: =AS64/AO64-1 -> 0.1 | BB65: =IF(ISERROR(BB64/BA64-1),"NA",BB64/BA64-1) -> NA | BC65: =IF(ISERROR(BC64/BB64-1),"NA",BC64/BB64-1) -> NA | BD65: =IF(ISERROR(BD64/BC64-1),"NA",BD64/BC64-1) -> 0.10732208 | BE65: =IF(ISERROR(BE64/BD64-1),"NA",BE64/BD64-1) -> 0.1
A66: Non-SaaS ARR | Z66: =Z40-Z52 -> 454.195 | AA66: =AA40-AA52 -> 447.3 | AB66: =AB40-AB52 -> 439.875 | AC66: =AC40-AC52 -> 418.11 | AD66: =AD40-AD52 -> 392.21 | AE66: =AE40-AE52 -> 373.888 | AF66: =AF40-AF52 -> 347.7 | AG66: =AG40-AG52 -> 301.693 | ... AO66: =AO40-AO52 -> -0.007 | BA66: =AC66 -> 418.11 | BB66: =AG66 -> 301.693 | BC66: =AK66 -> 106.793 | BD66: =AO66 -> -0.007 | BE66: =AS66 -> 0
A67: Consensus Non-SaaS ARR | B67: =IFERROR('[2]VA Consensus'!C14+'[2]VA Consensus'!C16,"") | C67: =IFERROR('[2]VA Consensus'!D14+'[2]VA Consensus'!D16,"") | D67: =IFERROR('[2]VA Consensus'!E14+'[2]VA Consensus'!E16,"") | E67: =IFERROR('[2]VA Consensus'!F14+'[2]VA Consensus'!F16,"") | F67: =IFERROR('[2]VA Consensus'!G14+'[2]VA Consensus'!G16,"") | G67: =IFERROR('[2]VA Consensus'!H14+'[2]VA Consensus'!H16,"") | H67: =IFERROR('[2]VA Consensus'!I14+'[2]VA Consensus'!I16,"") | I67: =IFERROR('[2]VA Consensus'!J14+'[2]VA Consensus'!J16,"") | ... AO67: =IFERROR('[2]VA Consensus'!AP14+'[2]VA Consensus'!AP16,"") | AU67: =IFERROR('[2]VA Consensus'!AV14+'[2]VA Consensus'!AV16,"") | AV67: =IFERROR('[2]VA Consensus'!AW14+'[2]VA Consensus'!AW16,"") | AW67: =IFERROR('[2]VA Consensus'!AX14+'[2]VA Consensus'!AX16,"") | AX67: =IFERROR('[2]VA Consensus'!AY14+'[2]VA Consensus'!AY16,"") | AY67: =IFERROR('[2]VA Consensus'!AZ14+'[2]VA Consensus'!AZ16,"") | AZ67: =IFERROR('[2]VA Consensus'!BA14+'[2]VA Consensus'!BA16,"") | BA67: =IFERROR('[2]VA Consensus'!BB14+'[2]VA Consensus'!BB16,"") | BB67: =IFERROR('[2]VA Consensus'!BC14+'[2]VA Consensus'!BC16,"") -> 341.8251 | ... BE67: =IFERROR('[2]VA Consensus'!BF14+'[2]VA Consensus'!BF16,"")
A68: Y/Y % | AD68: =AD66/Z66-1 -> -0.13647222 | AE68: =AE66/AA66-1 -> -0.16412251 | AF68: =AF66/AB66-1 -> -0.20954817 | AG68: =AG66/AC66-1 -> -0.2784363 | AH68: =AH66/AD66-1 -> -0.33965733 | AI68: =AI66/AE66-1 -> -0.42551513 | AJ68: =AJ66/AF66-1 -> -0.50419039 | AK68: =AK66/AG66-1 -> -0.64602096 | ... AO68: =AO66/AK66-1 -> -1.0000655 | BA68: =IF(ISERROR(BA66/AZ66-1),"NA",BA66/AZ66-1) -> NA | BB68: =IF(ISERROR(BB66/BA66-1),"NA",BB66/BA66-1) -> -0.2784363 | BC68: =IF(ISERROR(BC66/BB66-1),"NA",BC66/BB66-1) -> -0.64602096 | BD68: =IF(ISERROR(BD66/BC66-1),"NA",BD66/BC66-1) -> -1.0000655 | BE68: =IF(ISERROR(BE66/BD66-1),"NA",BE66/BD66-1) -> -1
A69: % of Total ARR | Z69: =Z66/Z40 -> 0.95 | AA69: =AA66/AA40 -> 0.9 | AB69: =AB66/AB40 -> 0.85 | AC69: =AC66/AC40 -> 0.77 | AD69: =AD66/AD40 -> 0.7 | AE69: =AE66/AE40 -> 0.64 | AF69: =AF66/AF40 -> 0.57 | AG69: =AG66/AG40 -> 0.47 | ... AO69: =AO66/AO40 -> -8.5110263e-06 | BA69: =AC69 -> 0.77 | BB69: =AG69 -> 0.47 | BC69: =AK69 -> 0.14326939 | BD69: =AO69 -> -8.5110263e-06 | BE69: =AS69 -> 0
A71: Billings & RPO
A72: Revenue | B72: =B5 -> 39.593 | C72: =C5 -> 49.431 | D72: =D5 -> 53.365 | E72: =E5 -> 73.001 | F72: =F5 -> 53.528 | G72: =G5 -> 62.19 | H72: =H5 -> 67.052 | I72: =I5 -> 87.518 | ... AS72: =AS5 -> 233.88418 | AU72: =SUM(B72:E72) -> 215.39 | AV72: =SUM(F72:I72) -> 270.288 | AW72: =SUM(J72:M72) -> 254.19 | AX72: =SUM(N72:Q72) -> 292.689 | AY72: =SUM(R72:U72) -> 390.134 | AZ72: =SUM(V72:Y72) -> 473.634 | BA72: =SUM(Z72:AC72) -> 499.16 | BB72: =SUM(AD72:AG72) -> 550.95 | BC72: =SUM(AH72:AK72) -> 623.532 | BD72: =SUM(AL72:AO72) -> 725.13568 | BE72: =SUM(AP72:AS72) -> 884.61962
A73: Beginning deferred revenue balance | B73: =58.478+3.562 -> 62.04 | C73: =B74 -> 58.837 | D73: =C74 -> 61.346 | E73: =D74 -> 63.43 | F73: =E74 -> 81.3 | G73: =F74 -> 74.728 | H73: =G74 -> 77.937 | I73: =H74 -> 78.918 | J73: =I74 -> 94.216 | ... AS73: =AR74 -> 655.05192 | AX73: =N73 -> 101.435 | AY73: =R73 -> 101.366 | AZ73: =V73 -> 106.787 | BA73: =Z73 -> 112.053 | BB73: =SUM(AD73:AG73) -> 795.488 | BC73: =SUM(AH73:AK73) -> 1168.185 | BD73: =SUM(AL73:AO73) -> 1886.5425 | BE73: =SUM(AP73:AS73) -> 2508.7843
A74: Ending deferred revenue balance | B74: ='Balance Sheet'!B24+'Balance Sheet'!B31 -> 58.837 | C74: ='Balance Sheet'!C24+'Balance Sheet'!C31 -> 61.346 | D74: ='Balance Sheet'!D24+'Balance Sheet'!D31 -> 63.43 | E74: ='Balance Sheet'!E24+'Balance Sheet'!E31 -> 81.3 | F74: ='Balance Sheet'!F24+'Balance Sheet'!F31 -> 74.728 | G74: ='Balance Sheet'!G24+'Balance Sheet'!G31 -> 77.937 | H74: ='Balance Sheet'!H24+'Balance Sheet'!H31 -> 78.918 | I74: ='Balance Sheet'!I24+'Balance Sheet'!I31 -> 94.216 | ... AK74: ='Balance Sheet'!AK24+'Balance Sheet'!AK31 -> 442.217 | AL74: =AL73+AL75 -> 435.84891 | AM74: =AM73+AM75 -> 495.16341 | AN74: =AN73+AN75 -> 513.31317 | AO74: =AO73+AO75 -> 617.27421 | AP74: =AP73+AP75 -> 591.27114 | AQ74: =AQ73+AQ75 -> 645.18701 | AR74: =AR73+AR75 -> 655.05192 | AS74: =AS73+AS75 -> 767.87641 | AX74: =Q74 -> 101.366 | AY74: =U74 -> 106.787 | AZ74: =Y74 -> 112.053 | BA74: =AC74 -> 181.935 | BB74: =SUM(AD74:AG74) -> 866.293 | BC74: =SUM(AH74:AK74) -> 1357.662 | BD74: =SUM(AL74:AO74) -> 2061.5997 | BE74: =SUM(AP74:AS74) -> 2659.3865
A75: Change in deferred revenue | B75: =B74-B73 -> -3.203 | C75: =C74-C73 -> 2.509 | D75: =D74-D73 -> 2.084 | E75: =E74-E73 -> 17.87 | F75: =F74-F73 -> -6.572 | G75: =G74-G73 -> 3.209 | H75: =H74-H73 -> 0.981 | I75: =I74-I73 -> 15.298 | ... AK75: =AK74-AK73 -> 100.709 | AL75: =AL76-AL72 -> -6.368086 | AM75: =AM76-AM72 -> 59.314501 | AN75: =AN76-AN72 -> 18.14976 | AO75: =AO76-AO72 -> 103.96103 | AP75: =AP76-AP72 -> -26.003064 | AQ75: =AQ76-AQ72 -> 53.915863 | AR75: =AR76-AR72 -> 9.864912 | AS75: =AS76-AS72 -> 112.82449 | AV75: =SUM(F75:I75) -> 12.916 | AW75: =SUM(J75:M75) -> 7.219 | AX75: =AX74-AX73 -> -0.069 | AY75: =AY74-AY73 -> 5.421 | AZ75: =AZ74-AZ73 -> 5.266 | BA75: =BA74-BA73 -> 69.882 | BB75: =SUM(AD75:AG75) -> 70.805 | BC75: =SUM(AH75:AK75) -> 189.477 | BD75: =SUM(AL75:AO75) -> 175.05721 | BE75: =SUM(AP75:AS75) -> 150.60221
A76: Total Billings | B76: =B72+B75 -> 36.39 | C76: =C72+C75 -> 51.94 | D76: =D72+D75 -> 55.449 | E76: =E72+E75 -> 90.871 | F76: =F72+F75 -> 46.956 | G76: =G72+G75 -> 65.399 | H76: =H72+H75 -> 68.033 | I76: =I72+I75 -> 102.816 | ... AK76: =AK72+AK75 -> 274.078 | AL76: =AH76*(1+AL78) -> 158.97078 | AM76: =AI76*(1+AM78) -> 235.2252 | AN76: =AJ76*(1+AN78) -> 204.51111 | AO76: =AK76*(1+AO78) -> 301.4858 | AP76: =AL76*(1+AP78) -> 182.8164 | AQ76: =AM76*(1+AQ78) -> 270.50898 | AR76: =AN76*(1+AR78) -> 235.18778 | AS76: =AO76*(1+AS78) -> 346.70867 | AU76: =SUM(B76:E76) -> 234.65 | AV76: =SUM(F76:I76) -> 283.204 | AW76: =SUM(J76:M76) -> 261.409 | AX76: =SUM(N76:Q76) -> 292.62 | AY76: =SUM(R76:U76) -> 395.555 | AZ76: =SUM(V76:Y76) -> 478.9 | BA76: =SUM(Z76:AC76) -> 569.042 | BB76: =SUM(AD76:AG76) -> 621.755 | BC76: =SUM(AH76:AK76) -> 813.009 | BD76: =SUM(AL76:AO76) -> 900.19289 | BE76: =SUM(AP76:AS76) -> 1035.2218
A77: Consensus Billings | J77: 54.4 | K77: 67.6 | L77: 61.1 | M77: 92.1 | N77: 48 | O77: 57.2 | P77: 71.8 | Q77: 104.7 | R77: 58.7 | S77: 78.1 | T77: 100.2 | U77: 142.5 | V77: 85.8 | W77: 105.4 | X77: {=_xll.FDS("VRNS-US","FE_ESTIMATE(NEW_ORDERS_VALUE,MEAN,QTR_ROLL,"&X2&",NOW,,,'')")} -> #Calc | Y77: 162.2 | Z77: ='[2]VA Consensus'!AA20 -> 98.754695 | AA77: ='[2]VA Consensus'!AB20 -> 120.2592 | AB77: ='[2]VA Consensus'!AC20 -> 128.35409 | AC77: ='[2]VA Consensus'!AD20 -> 172.95461 | AD77: ='[2]VA Consensus'!AE20 -> 113.50408 | AE77: ='[2]VA Consensus'!AF20 -> 145.76959 | AF77: ='[2]VA Consensus'!AG20 -> 155.28207 | AG77: ='[2]VA Consensus'!AH20 -> 206.7518 | ... AS77: ='[2]VA Consensus'!AT20 -> 338.24643 | AU77: ='[2]VA Consensus'!AV20 -> 226.75366 | AV77: ='[2]VA Consensus'!AW20 -> 289.34062 | AW77: ='[2]VA Consensus'!AX20 -> 260.42638 | AX77: ='[2]VA Consensus'!AY20 -> 274.89577 | AY77: ='[2]VA Consensus'!AZ20 -> 392.80943 | AZ77: ='[2]VA Consensus'!BA20 -> 481.74902 | BA77: ='[2]VA Consensus'!BB20 -> 551.57061 | BB77: ='[2]VA Consensus'!BC20 -> 636.68397 | ... BE77: ='[2]VA Consensus'!BF20 -> 983.01763
A78: Y/Y % | F78: =F76/B76-1 -> 0.29035449 | G78: =G76/C76-1 -> 0.25912591 | H78: =H76/D76-1 -> 0.22694728 | I78: =I76/E76-1 -> 0.13145008 | J78: =J76/F76-1 -> 0.085612062 | K78: =K76/G76-1 -> -0.14393186 | L78: =L76/H76-1 -> -0.075169403 | M78: =M76/I76-1 -> -0.10978836 | ... AK78: =AK76/AG76-1 -> 0.42660539 | AL78: 0.18 | AM78: 0.05 | AN78: 0.135 | AO78: 0.1 | AP78: 0.15 | AQ78: 0.15 | AR78: 0.15 | AS78: 0.15 | AV78: =IF(ISERROR(AV76/AU76-1),"NA",AV76/AU76-1) -> 0.20692095 | AW78: =IF(ISERROR(AW76/AV76-1),"NA",AW76/AV76-1) -> -0.076958659 | AX78: =IF(ISERROR(AX76/AW76-1),"NA",AX76/AW76-1) -> 0.11939528 | AY78: =IF(ISERROR(AY76/AX76-1),"NA",AY76/AX76-1) -> 0.35177021 | AZ78: =IF(ISERROR(AZ76/AY76-1),"NA",AZ76/AY76-1) -> 0.21070395 | BA78: =IF(ISERROR(BA76/AZ76-1),"NA",BA76/AZ76-1) -> 0.18822719 | BB78: =IF(ISERROR(BB76/BA76-1),"NA",BB76/BA76-1) -> 0.092634639 | BC78: =IF(ISERROR(BC76/BB76-1),"NA",BC76/BB76-1) -> 0.30760348 | ... BE78: =IF(ISERROR(BE76/BD76-1),"NA",BE76/BD76-1) -> 0.15
A80: Revenue | B80: =B5 -> 39.593 | C80: =C5 -> 49.431 | D80: =D5 -> 53.365 | E80: =E5 -> 73.001 | F80: =F5 -> 53.528 | G80: =G5 -> 62.19 | H80: =H5 -> 67.052 | I80: =I5 -> 87.518 | ... AS80: =AS5 -> 233.88418 | AU80: =SUM(B80:E80) -> 215.39 | AV80: =SUM(F80:I80) -> 270.288 | AW80: =SUM(J80:M80) -> 254.19 | AX80: =SUM(N80:Q80) -> 292.689 | AY80: =SUM(R80:U80) -> 390.134 | AZ80: =SUM(V80:Y80) -> 473.634 | BA80: =SUM(Z80:AC80) -> 499.16 | BB80: =SUM(AD80:AG80) -> 550.95 | BC80: =SUM(AH80:AK80) -> 623.532 | BD80: =SUM(AL80:AO80) -> 725.13568 | BE80: =SUM(AP80:AS80) -> 884.61962
A81: Beginning deferred revenue (current) balance | B81: =58.478 -> 58.478 | C81: =B82 -> 54.576 | D81: =C82 -> 57.457 | E81: =D82 -> 58.383 | F81: =E82 -> 73.493 | G81: =F82 -> 68.481 | H81: =G82 -> 71.663 | I81: =H82 -> 72.544 | J81: =I82 -> 87.729 | ... AS81: =AR82 -> 669.64562 | AX81: =N81 -> 95.975 | AY81: =R81 -> 98.588 | AZ81: =V81 -> 104.221 | BA81: =Z81 -> 110.55 | BB81: =SUM(AD81:AG81) -> 792.647 | BC81: =SUM(AH81:AK81) -> 1157.81 | BD81: =SUM(AL81:AO81) -> 1904.3142 | BE81: =SUM(AP81:AS81) -> 2564.6767
A82: Ending deferred revenue (current) balance | B82: ='Balance Sheet'!B24 -> 54.576 | C82: ='Balance Sheet'!C24 -> 57.457 | D82: ='Balance Sheet'!D24 -> 58.383 | E82: ='Balance Sheet'!E24 -> 73.493 | F82: ='Balance Sheet'!F24 -> 68.481 | G82: ='Balance Sheet'!G24 -> 71.663 | H82: ='Balance Sheet'!H24 -> 72.544 | I82: ='Balance Sheet'!I24 -> 87.729 | ... AS82: ='Balance Sheet'!AS24 -> 784.98369 | AX82: =Q82 -> 98.588 | AY82: =U82 -> 104.221 | AZ82: =Y82 -> 110.55 | BA82: =AC82 -> 181.049 | BB82: =SUM(AD82:AG82) -> 862.127 | BC82: =SUM(AH82:AK82) -> 1335.092 | BD82: =SUM(AL82:AO82) -> 2107.5294 | BE82: =SUM(AP82:AS82) -> 2718.6341
A83: Change in deferred revenue (current) | B83: =B82-B81 -> -3.902 | C83: =C82-C81 -> 2.881 | D83: =D82-D81 -> 0.926 | E83: =E82-E81 -> 15.11 | F83: =F82-F81 -> -5.012 | G83: =G82-G81 -> 3.182 | H83: =H82-H81 -> 0.881 | I83: =I82-I81 -> 15.185 | ... AS83: =AS82-AS81 -> 115.33808 | AV83: =SUM(F83:I83) -> 14.236 | AW83: =SUM(J83:M83) -> 8.246 | AX83: =AX82-AX81 -> 2.613 | AY83: =AY82-AY81 -> 5.633 | AZ83: =AZ82-AZ81 -> 6.329 | BA83: =BA82-BA81 -> 70.499 | BB83: =SUM(AD83:AG83) -> 69.48 | BC83: =SUM(AH83:AK83) -> 177.282 | BD83: =SUM(AL83:AO83) -> 203.21527 | BE83: =SUM(AP83:AS83) -> 153.95742
A84: Current Billings | B84: =B80+B83 -> 35.691 | C84: =C80+C83 -> 52.312 | D84: =D80+D83 -> 54.291 | E84: =E80+E83 -> 88.111 | F84: =F80+F83 -> 48.516 | G84: =G80+G83 -> 65.372 | H84: =H80+H83 -> 67.933 | I84: =I80+I83 -> 102.703 | ... AS84: =AS80+AS83 -> 349.22225 | AU84: =SUM(B84:E84) -> 230.405 | AV84: =SUM(F84:I84) -> 284.524 | AW84: =SUM(J84:M84) -> 262.436 | AX84: =SUM(N84:Q84) -> 295.302 | AY84: =SUM(R84:U84) -> 395.767 | AZ84: =SUM(V84:Y84) -> 479.963 | BA84: =SUM(Z84:AC84) -> 569.659 | BB84: =SUM(AD84:AG84) -> 620.43 | BC84: =SUM(AH84:AK84) -> 800.814 | BD84: =SUM(AL84:AO84) -> 928.35095 | BE84: =SUM(AP84:AS84) -> 1038.577
A85: Y/Y % | F85: =F84/B84-1 -> 0.35933429 | G85: =G84/C84-1 -> 0.24965591 | H85: =H84/D84-1 -> 0.25127553 | I85: =I84/E84-1 -> 0.16560929 | J85: =J84/F84-1 -> 0.040378432 | K85: =K84/G84-1 -> -0.13028514 | L85: =L84/H84-1 -> -0.064534173 | M85: =M84/I84-1 -> -0.10852653 | ... AS85: =AS84/AO84-1 -> 0.14950642 | AV85: =IF(ISERROR(AV84/AU84-1),"NA",AV84/AU84-1) -> 0.2348864 | AW85: =IF(ISERROR(AW84/AV84-1),"NA",AW84/AV84-1) -> -0.077631412 | AX85: =IF(ISERROR(AX84/AW84-1),"NA",AX84/AW84-1) -> 0.12523434 | AY85: =IF(ISERROR(AY84/AX84-1),"NA",AY84/AX84-1) -> 0.34021104 | AZ85: =IF(ISERROR(AZ84/AY84-1),"NA",AZ84/AY84-1) -> 0.21274134 | BA85: =IF(ISERROR(BA84/AZ84-1),"NA",BA84/AZ84-1) -> 0.18688107 | BB85: =IF(ISERROR(BB84/BA84-1),"NA",BB84/BA84-1) -> 0.089125249 | BC85: =IF(ISERROR(BC84/BB84-1),"NA",BC84/BB84-1) -> 0.29074029 | ... BE85: =IF(ISERROR(BE84/BD84-1),"NA",BE84/BD84-1) -> 0.11873322
A87: RPO | AA87: 195.752 | AB87: 259.574 | AC87: 378.164 | AD87: 426.168 | AE87: 514.669 | AF87: 581.4 | AG87: 729.7 | AH87: 788.7 | AI87: 870.891 | AJ87: 729.7 | AK87: 1096.662 | BA87: =AC87 -> 378.164
A88: Y/Y % | AE88: =AE87/AA87-1 -> 1.629189 | AF88: =AF87/AB87-1 -> 1.2398237 | AG88: =AG87/AC87-1 -> 0.92958611 | AH88: =AH87/AD87-1 -> 0.85067861 | AI88: =AI87/AE87-1 -> 0.69213805 | AJ88: =AJ87/AF87-1 -> 0.25507396 | AK88: =AK87/AG87-1 -> 0.50289434
A90: CRPO | AA90: =AA87*AA92 -> 137.0264 | AB90: =AB87*AB92 -> 160.93588 | AC90: =AC87*AC92 -> 215.55348 | AD90: =AD87*AD92 -> 234.3924 | AE90: =AE87*AE92 -> 272.77457 | AF90: =AF87*AF92 -> 302.328 | AG90: =AG87*AG92 -> 386.741 | AH90: =AH87*AH92 -> 418.011 | ... AK90: =AK87*AK92 -> 592.19748 | BA90: =BA87*BA92 -> 215.55348
A91: Y/Y % | AE91: =AE90/AA90-1 -> 0.99067165 | AF91: =AF90/AB90-1 -> 0.87856182 | AG91: =AG90/AC90-1 -> 0.79417655 | AH91: =AH90/AD90-1 -> 0.7833812 | AI91: =AI90/AE90-1 -> 0.69213805 | AJ91: =AJ90/AF90-1 -> 0.27921 | AK91: =AK90/AG90-1 -> 0.53125084
A92: Current RPO - % of total | AA92: 0.7 | AB92: 0.62 | AC92: 0.57 | AD92: 0.55 | AE92: 0.53 | AF92: 0.52 | AG92: 0.53 | AH92: 0.53 | AI92: 0.53 | AJ92: 0.53 | AK92: 0.54 | BA92: =AC92 -> 0.57
A94: Backlog (RPO - Deferred Rev) | AA94: =AA87-AA74 -> 64.377 | AB94: =AB87-AB74 -> 113.966 | AC94: =AC87-AC74 -> 196.229 | AD94: =AD87-AD74 -> 240.679 | AE94: =AE87-AE74 -> 305.74 | AF94: =AF87-AF74 -> 362.265 | AG94: =AG87-AG74 -> 476.96 | AH94: =AH87-AH74 -> 537.662 | ... AK94: =AK87-AK74 -> 654.445 | BA94: =BA87-BA74 -> 196.229
A95: Y/Y % | AE95: =AE94/AA94-1 -> 3.7492117 | AF95: =AF94/AB94-1 -> 2.1787112 | AG95: =AG94/AC94-1 -> 1.4306295 | AH95: =AH94/AD94-1 -> 1.2339381 | AI95: =AI94/AE94-1 -> 0.79234644 | AJ95: =AJ94/AF94-1 -> 0.071569155 | AK95: =AK94/AG94-1 -> 0.37211716
A97: CRPO Bookings
A98: Total revenue | AB98: =AB5 -> 122.308 | AC98: =AC5 -> 154.099 | AD98: =AD5 -> 114.022 | AE98: =AE5 -> 130.346 | AF98: =AF5 -> 148.068 | AG98: =AG5 -> 158.514 | AH98: =AH5 -> 136.423 | AI98: =AI5 -> 152.163 | ... AK98: =AK5 -> 173.369
A99: + change in CRPO | AB99: =AB90-AA90 -> 23.90948 | AC99: =AC90-AB90 -> 54.6176 | AD99: =AD90-AC90 -> 18.83892 | AE99: =AE90-AD90 -> 38.38217 | AF99: =AF90-AE90 -> 29.55343 | AG99: =AG90-AF90 -> 84.413 | AH99: =AH90-AG90 -> 31.27 | AI99: =AI90-AH90 -> 43.56123 | ... AK99: =AK90-AJ90 -> 205.45648
A100: Total CRPO Bookings | AB100: =AB98+AB99 -> 146.21748 | AC100: =AC98+AC99 -> 208.7166 | AD100: =AD98+AD99 -> 132.86092 | AE100: =AE98+AE99 -> 168.72817 | AF100: =AF98+AF99 -> 177.62143 | AG100: =AG98+AG99 -> 242.927 | AH100: =AH98+AH99 -> 167.693 | AI100: =AI98+AI99 -> 195.72423 | ... AK100: =AK98+AK99 -> 378.82548
A101: Y/Y % | AF101: =AF100/AB100-1 -> 0.21477562 | AG101: =AG100/AC100-1 -> 0.16390838 | AH101: =AH100/AD100-1 -> 0.26216949 | AI101: =AI100/AE100-1 -> 0.15999735 | AJ101: =AJ100/AF100-1 -> -0.51162554 | AK101: =AK100/AG100-1 -> 0.55942106
A102: Source: Company data, FactSet, Wells Fargo Securities, LLC estimates
B104: ='Income Statement'!B$3 -> 2017 | F104: ='Income Statement'!F$3 -> 2018 | J104: ='Income Statement'!J$3 -> 2019 | N104: ='Income Statement'!N$3 -> 2020 | R104: ='Income Statement'!R$3 -> 2021 | V104: ='Income Statement'!V$3 -> 2022 | Z104: ='Income Statement'!Z$3 -> 2023 | AD104: ='Income Statement'!AD$3 -> 2024 | AH104: ='Income Statement'!AH$3 -> 2025 | AL104: ='Income Statement'!AL$3 -> 2026 | AP104: ='Income Statement'!AP$3 -> 2027
A105: Geographic Mix | B105: ='Income Statement'!B$4 -> 42825 | C105: ='Income Statement'!C$4 -> 42916 | D105: ='Income Statement'!D$4 -> 43008 | E105: ='Income Statement'!E$4 -> 43100 | F105: ='Income Statement'!F$4 -> 43190 | G105: ='Income Statement'!G$4 -> 43281 | H105: ='Income Statement'!H$4 -> 43373 | I105: ='Income Statement'!I$4 -> 43465 | ... AS105: ='Income Statement'!AS$4 -> Dec-27E | AU105: ='Income Statement'!AU$4 -> 2017 | AV105: ='Income Statement'!AV$4 -> 2018 | AW105: ='Income Statement'!AW$4 -> 2019 | AX105: ='Income Statement'!AX$4 -> 2020 | AY105: ='Income Statement'!AY$4 -> 2021 | AZ105: ='Income Statement'!AZ$4 -> 2022 | BA105: ='Income Statement'!BA$4 -> 2023 | BB105: ='Income Statement'!BB$4 -> 2024 | ... BE105: ='Income Statement'!BE$4 -> 2027E
A106: UNITED STATES | B106: 25.437 | C106: 34.428 | D106: 35.307 | E106: =139.72-SUM(B106:D106) -> 44.548 | F106: 31.62 | G106: 38.441 | H106: 44.89 | I106: =167.361-SUM(F106:H106) -> 52.41 | J106: 37.849 | K106: 39.984 | L106: 47.411 | M106: =174.607-SUM(J106:L106) -> 49.363 | N106: 37.874 | O106: 45.815 | P106: 57.14 | Q106: 66.659 | R106: 52.806 | S106: 61.598 | T106: 75.609 | U106: 89.091 | V106: 69.141 | W106: 80.835 | X106: 98.018 | Y106: 104.304 | Z106: 81.249 | AA106: 84.514 | AB106: 94.664 | AC106: =373.806-AB106-AA106-Z106 -> 113.379 | AD106: 80.83 | AE106: 91.957 | AF106: 111.602 | AG106: =400.778-AF106-AE106-AD106 -> 116.389 | AH106: 95.633 | AI106: 108.656 | AJ106: 118.19 | AK106: =440.468-SUM(AH106:AJ106) -> 117.989 | AV106: 192.057 | AW106: =SUM(J106:M106) -> 174.607 | AX106: =SUM(N106:Q106) -> 207.488 | AY106: =SUM(R106:U106) -> 279.104 | AZ106: =SUM(V106:Y106) -> 352.298 | BA106: =SUM(Z106:AC106) -> 373.806
A107: Y/Y % | F107: =F106/B106-1 -> 0.24307112 | G107: =G106/C106-1 -> 0.1165621 | H107: =H106/D106-1 -> 0.27141927 | I107: =I106/E106-1 -> 0.17648379 | J107: =J106/F106-1 -> 0.19699557 | K107: =K106/G106-1 -> 0.040139434 | L107: =L106/H106-1 -> 0.056159501 | M107: =M106/I106-1 -> -0.05813776 | ... AK107: =AK106/AG106-1 -> 0.013747004 | AW107: =AW106/AV106-1 -> -0.090858443 | AX107: =AX106/AW106-1 -> 0.18831433 | AY107: =AY106/AX106-1 -> 0.34515731 | AZ107: =AZ106/AY106-1 -> 0.26224633 | BA107: =BA106/AZ106-1 -> 0.061050588
A108: % of total revenue | C108: =C106/C$5 -> 0.69648601 | D108: =D106/D$5 -> 0.66161342 | E108: =E106/E$5 -> 0.61023822 | F108: =F106/F$5 -> 0.59071888 | G108: =G106/G$5 -> 0.61812188 | H108: =H106/H$5 -> 0.6694804 | I108: =I106/I$5 -> 0.59884824 | J108: =J106/J$5 -> 0.67155784 | ... AK108: =AK106/AK$5 -> 0.68056573 | AW108: =AW106/AW$5 -> 0.6869153 | AX108: =AX106/AX$5 -> 0.70890262 | AY108: =AY106/AY$5 -> 0.71540548 | AZ108: =AZ106/AZ$5 -> 0.74381907 | BA108: =BA106/BA$5 -> 0.7488701
A109: EMEA | B109: 12.695 | C109: 13.406 | D109: 16.449 | E109: =68.998-SUM(B109:D109) -> 26.448 | F109: 20.347 | G109: 21.481 | H109: 19.778 | I109: =93.816-SUM(F109:H109) -> 32.21 | J109: 16.4 | K109: 17.553 | L109: 16.719 | M109: =70.208-SUM(J109:L109) -> 19.536 | N109: 14.611 | O109: 18.721 | P109: 17.827 | Q109: 25.934 | R109: 20.234 | S109: 24.471 | T109: 22.801 | U109: 34.188 | V109: 24.209 | W109: 27.151 | X109: 22.117 | Y109: 34.371 | Z109: 22.918 | AA109: 27.227 | AB109: 24.023 | AC109: =109.587-AB109-AA109-Z109 -> 35.419 | AD109: 24.153 | AE109: 29.07 | AF109: 27.991 | AG109: =114.355-AF109-AE109-AD109 -> 33.141 | AH109: 28.394 | AI109: 31.755 | AJ109: 31.295 | AK109: =133.591-SUM(AH109:AJ109) -> 42.147 | AV109: 29.721 | AW109: =SUM(J109:M109) -> 70.208 | AX109: =SUM(N109:Q109) -> 77.093 | AY109: =SUM(R109:U109) -> 101.694 | AZ109: =SUM(V109:Y109) -> 107.848 | BA109: =SUM(Z109:AC109) -> 109.587
A110: Y/Y % | F110: =F109/B109-1 -> 0.60275699 | G110: =G109/C109-1 -> 0.60234223 | H110: =H109/D109-1 -> 0.20238312 | I110: =I109/E109-1 -> 0.21786146 | J110: =J109/F109-1 -> -0.19398437 | K110: =K109/G109-1 -> -0.18285927 | L110: =L109/H109-1 -> -0.1546668 | M110: =M109/I109-1 -> -0.39348029 | ... AK110: =AK109/AG109-1 -> 0.27174799 | AW110: =AW109/AV109-1 -> 1.3622355 | AX110: =AX109/AW109-1 -> 0.098065747 | AY110: =AY109/AX109-1 -> 0.31910809 | AZ110: =AZ109/AY109-1 -> 0.060514878 | BA110: =BA109/AZ109-1 -> 0.016124546
A111: % of total revenue | C111: =C109/C$5 -> 0.27120633 | D111: =D109/D$5 -> 0.30823574 | E111: =E109/E$5 -> 0.36229641 | F111: =F109/F$5 -> 0.38011882 | G111: =G109/G$5 -> 0.34540923 | H111: =H109/H$5 -> 0.2949651 | I111: =I109/I$5 -> 0.36803857 | J111: =J109/J$5 -> 0.29098652 | ... AK111: =AK109/AK$5 -> 0.24310575 | AW111: =AW109/AW$5 -> 0.27620284 | AX111: =AX109/AX$5 -> 0.26339562 | AY111: =AY109/AY$5 -> 0.26066428 | AZ111: =AZ109/AZ$5 -> 0.22770325 | BA111: =BA109/BA$5 -> 0.21954283
A112: REST OF WORLD | B112: 1.461 | C112: 1.597 | D112: 1.609 | E112: =6.672-SUM(B112:D112) -> 2.005 | F112: 1.561 | G112: 2.268 | H112: 2.384 | I112: =9.111-SUM(F112:H112) -> 2.898 | J112: 2.11 | K112: 2.084 | L112: 1.519 | M112: =9.375-SUM(J112:L112) -> 3.662 | N112: 1.691 | O112: 2.029 | P112: 1.519 | Q112: 2.869 | R112: 1.745 | S112: 2.349 | T112: 1.943 | U112: 3.299 | V112: 2.911 | W112: 3.462 | X112: 3.173 | Y112: 3.942 | Z112: 3.168 | AA112: 3.677 | AB112: 3.621 | AC112: =15.767-AB112-AA112-Z112 -> 5.301 | AD112: 9.039 | AE112: 9.319 | AF112: 8.475 | AG112: =35.817-AF112-AE112-AD112 -> 8.984 | AH112: 12.396 | AI112: 11.752 | AJ112: 12.092 | AK112: =49.473-SUM(AH112:AJ112) -> 13.233 | AV112: 17.213 | AW112: =SUM(J112:M112) -> 9.375 | AX112: =SUM(N112:Q112) -> 8.108 | AY112: =SUM(R112:U112) -> 9.336 | AZ112: =SUM(V112:Y112) -> 13.488 | BA112: =SUM(Z112:AC112) -> 15.767
A113: Y/Y % | F113: =F112/B112-1 -> 0.06844627 | G113: =G112/C112-1 -> 0.42016281 | H113: =H112/D112-1 -> 0.48166563 | I113: =I112/E112-1 -> 0.44538653 | J113: =J112/F112-1 -> 0.35169763 | K113: =K112/G112-1 -> -0.081128748 | L113: =L112/H112-1 -> -0.36283557 | M113: =M112/I112-1 -> 0.26363009 | ... T113: =T112/P112-1 -> 0.27913101 | U113: 0.27 | V113: =V112/R112-1 -> 0.66819484 | W113: =W112/S112-1 -> 0.47381865 | X113: =X112/T112-1 -> 0.63304169 | Y113: =Y112/U112-1 -> 0.19490755 | Z113: =Z112/V112-1 -> 0.088285812 | AA113: =AA112/W112-1 -> 0.062102831 | AB113: =AB112/X112-1 -> 0.1411913 | AC113: =AC112/Y112-1 -> 0.34474886 | ... AK113: =AK112/AG112-1 -> 0.47295191 | AW113: =AW112/AV112-1 -> -0.45535351 | AX113: =AX112/AW112-1 -> -0.13514667 | AY113: =AY112/AX112-1 -> 0.15145535 | AZ113: =AZ112/AY112-1 -> 0.44473008 | BA113: =BA112/AZ112-1 -> 0.16896501
A114: % of total revenue | C114: =C112/C$5 -> 0.032307661 | D114: =D112/D$5 -> 0.030150848 | E114: =E112/E$5 -> 0.027465377 | F114: =F112/F$5 -> 0.029162308 | G114: =G112/G$5 -> 0.036468886 | H114: =H112/H$5 -> 0.035554495 | I114: =I112/I$5 -> 0.033113188 | J114: =J112/J$5 -> 0.037437899 | ... AK114: =AK112/AK$5 -> 0.076328525 | AW114: =AW112/AW$5 -> 0.03688186 | AX114: =AX112/AX$5 -> 0.027701759 | AY114: =AY112/AY$5 -> 0.023930239 | AZ114: =AZ112/AZ$5 -> 0.028477685 | BA114: =BA112/BA$5 -> 0.031587066
...

Sheet Balance Sheet
A1: =+'Income Statement'!A1 -> Varonis Systems, Inc. (VRNS)
A2: Balance Sheet | AU2: =+'Income Statement'!AU2 -> 2017 | AV2: =+'Income Statement'!AV2 -> 2018 | AW2: =+'Income Statement'!AW2 -> 2019 | AX2: =+'Income Statement'!AX2 -> 2020 | AY2: =+'Income Statement'!AY2 -> 2021 | AZ2: =+'Income Statement'!AZ2 -> 2022 | BA2: =+'Income Statement'!BA2 -> 2023 | BB2: =+'Income Statement'!BB2 -> 2024 | ... BE2: =+'Income Statement'!BE2 -> 2027
B3: ='Income Statement'!B$3 -> 2017 | F3: ='Income Statement'!F$3 -> 2018 | J3: ='Income Statement'!J$3 -> 2019 | N3: ='Income Statement'!N$3 -> 2020 | R3: ='Income Statement'!R$3 -> 2021 | V3: ='Income Statement'!V$3 -> 2022 | Z3: ='Income Statement'!Z$3 -> 2023 | AD3: ='Income Statement'!AD$3 -> 2024 | AH3: ='Income Statement'!AH$3 -> 2025 | AL3: ='Income Statement'!AL$3 -> 2026 | AP3: ='Income Statement'!AP$3 -> 2027
A4: ='Income Statement'!A4 -> ($ in millions, unless otherwise stated) | B4: ='Income Statement'!B$4 -> 42825 | C4: ='Income Statement'!C$4 -> 42916 | D4: ='Income Statement'!D$4 -> 43008 | E4: ='Income Statement'!E$4 -> 43100 | F4: ='Income Statement'!F$4 -> 43190 | G4: ='Income Statement'!G$4 -> 43281 | H4: ='Income Statement'!H$4 -> 43373 | I4: ='Income Statement'!I$4 -> 43465 | ... AS4: ='Income Statement'!AS$4 -> Dec-27E | AU4: ='Income Statement'!AU$4 -> 2017 | AV4: ='Income Statement'!AV$4 -> 2018 | AW4: ='Income Statement'!AW$4 -> 2019 | AX4: ='Income Statement'!AX$4 -> 2020 | AY4: ='Income Statement'!AY$4 -> 2021 | AZ4: ='Income Statement'!AZ$4 -> 2022 | BA4: ='Income Statement'!BA$4 -> 2023 | BB4: ='Income Statement'!BB$4 -> 2024 | ... BE4: ='Income Statement'!BE$4 -> 2027E
A5: Current assets
A6: Cash and Cash Equivalents | B6: 51.07 | C6: 53.539 | D6: 53.478 | E6: 56.689 | F6: 70.778 | G6: 73.636 | H6: 67.868 | I6: 48.707 | J6: 64.461 | K6: 69.159 | L6: 52.984 | M6: 68.929 | N6: 77.533 | O6: 239.979 | P6: 231.458 | Q6: 234.092 | R6: 753.606 | S6: 781.357 | T6: 803.144 | U6: 805.761 | V6: 775.719 | W6: 753.172 | X6: 754.245 | Y6: 367.8 | Z6: 248.585 | AA6: 399.196 | AB6: 111.196 | AC6: 230.74 | AD6: 147.051 | AE6: 155.403 | AF6: 282.218 | AG6: 185.585 | AH6: 153.107 | AI6: 199.231 | AJ6: 157.354 | AK6: 202.482 | AL6: =AK6+'Cash Flow'!AL46 -> 261.44757 | AM6: =AL6+'Cash Flow'!AM46 -> 270.9465 | AN6: =AM6+'Cash Flow'!AN46 -> 277.50712 | AO6: =AN6+'Cash Flow'!AO46 -> 249.81498 | AP6: =AO6+'Cash Flow'!AP46 -> 323.67462 | AQ6: =AP6+'Cash Flow'!AQ46 -> 332.05016 | AR6: =AQ6+'Cash Flow'!AR46 -> 347.71623 | AS6: =AR6+'Cash Flow'!AS46 -> 333.3823 | AU6: =E6 -> 56.689 | AV6: =I6 -> 48.707 | AW6: =M6 -> 68.929 | AX6: =Q6 -> 234.092 | AY6: =U6 -> 805.761 | AZ6: =Y6 -> 367.8 | BA6: =AC6 -> 230.74 | BB6: =AG6 -> 185.585 | BC6: =AK6 -> 202.482 | BD6: =AO6 -> 249.81498 | BE6: =AP6 -> 323.67462
A7: Marketable Securities | B7: 0 | C7: 0 | D7: 0 | E7: 0 | F7: 0 | G7: 0 | H7: 0 | I7: 39.77 | J7: 37.842 | K7: 35.845 | L7: 41.397 | M7: 41.531 | N7: 33.737 | O7: 26.116 | P7: 34.112 | Q7: 34.117 | R7: 28.08 | S7: 20.035 | T7: 8.01 | U7: 0 | V7: 28.372 | W7: 28.735 | X7: 25.235 | Y7: 236.338 | Z7: 280.835 | AA7: 277.419 | AB7: 337.705 | AC7: 253.175 | AD7: 355.743 | AE7: 427.065 | AF7: 562.568 | AG7: 343.383 | AH7: 414.524 | AI7: 571.63 | AJ7: 513.935 | AK7: 681.225 | AL7: =AK7 -> 681.225 | AM7: =AL7 -> 681.225 | AN7: =AM7 -> 681.225 | AO7: =AN7 -> 681.225 | AP7: =AO7 -> 681.225 | AQ7: =AP7 -> 681.225 | AR7: =AQ7 -> 681.225 | AS7: =AR7 -> 681.225 | AU7: =E7 -> 0 | AV7: =I7 -> 39.77 | AW7: =M7 -> 41.531 | AX7: =Q7 -> 34.117 | AY7: =U7 -> 0 | AZ7: =Y7 -> 236.338 | BA7: =AC7 -> 253.175 | BB7: =AG7 -> 343.383 | BC7: =AK7 -> 681.225 | BD7: =AO7 -> 681.225 | BE7: =AP7 -> 681.225
A8: Short-Term Bank Deposits | B8: 70.25 | C8: 68.039 | D8: 74.963 | E8: 79.868 | F8: 82.892 | G8: 85.045 | H8: 90.214 | I8: 70.438 | J8: 61.328 | K8: 41.328 | L8: 37 | M8: 10 | N8: 15 | O8: 60 | P8: 60 | Q8: 30.053 | R8: 42.284 | S8: 12.276 | T8: 2.276 | U8: 1.85 | V8: 0 | W8: 6.856 | X8: 10.871 | Y8: 128.35 | Z8: 226.85 | AA8: 77.139 | AB8: 76.186 | AC8: 49.8 | AD8: 45.28 | AE8: 44.846 | AF8: 34.174 | AG8: 39.45 | AH8: 41.588 | AI8: 36.587 | AJ8: 36.632 | AK8: 37.259 | AL8: =AK8 -> 37.259 | AM8: =AL8 -> 37.259 | AN8: =AM8 -> 37.259 | AO8: =AN8 -> 37.259 | AP8: =AO8 -> 37.259 | AQ8: =AP8 -> 37.259 | AR8: =AQ8 -> 37.259 | AS8: =AR8 -> 37.259 | AU8: =E8 -> 79.868 | AV8: =I8 -> 70.438 | AW8: =M8 -> 10 | AX8: =Q8 -> 30.053 | AY8: =U8 -> 1.85 | AZ8: =Y8 -> 128.35 | BA8: =AC8 -> 49.8 | BB8: =AG8 -> 39.45 | BC8: =AK8 -> 37.259 | BD8: =AO8 -> 37.259 | BE8: =AP8 -> 37.259
A9: Trade Receivables, net | B9: 27.466 | C9: 41.313 | D9: 44.68 | E9: 75.596 | F9: 32.468 | G9: 41.393 | H9: 52.938 | I9: 83.223 | J9: 41.796 | K9: 45.563 | L9: 51.866 | M9: 75.05 | N9: 38.265 | O9: 48.766 | P9: 60.111 | Q9: 94.229 | R9: 51.302 | S9: 60.145 | T9: 71.382 | U9: 117.179 | V9: 63.604 | W9: 83.929 | X9: 91.685 | Y9: 135.979 | Z9: 75.393 | AA9: 103.668 | AB9: 111.084 | AC9: 169.116 | AD9: 100.441 | AE9: 122.412 | AF9: 119.203 | AG9: 192.832 | AH9: 123.579 | AI9: 149.703 | AJ9: 142.628 | AK9: 242.822 | AL9: =(AL54*AL61)/(365/4) -> 149.77249 | AM9: =(AM54*AM61)/(365/4) -> 173.06677 | AN9: =(AN54*AN61)/(365/4) -> 164.50576 | AO9: =(AO54*AO61)/(365/4) -> 274.91119 | AP9: =(AP54*AP61)/(365/4) -> 189.15945 | AQ9: =(AQ54*AQ61)/(365/4) -> 213.09148 | AR9: =(AR54*AR61)/(365/4) -> 198.89805 | AS9: =(AS54*AS61)/(365/4) -> 320.38928 | AU9: =E9 -> 75.596 | AV9: =I9 -> 83.223 | AW9: =M9 -> 75.05 | AX9: =Q9 -> 94.229 | AY9: =U9 -> 117.179 | AZ9: =Y9 -> 135.979 | BA9: =AC9 -> 169.116 | BB9: =AG9 -> 192.832 | BC9: =AK9 -> 242.822 | BD9: =AO9 -> 274.91119 | BE9: =AP9 -> 189.15945
A10: Prepaid Expenses & Other Current Assets | B10: 7.792 | C10: 7.571 | D10: 5.5 | E10: 14.346 | F10: 18.933 | G10: 16.927 | H10: 14.665 | I10: 16.952 | J10: 14.899 | K10: 15.235 | L10: 15.05 | M10: 13.047 | N10: 12.764 | O10: 15.568 | P10: 15.45 | Q10: 27.357 | R10: 24.564 | S10: 23.143 | T10: 26.737 | U10: 34.417 | V10: 35.812 | W10: 33.9 | X10: 34.557 | Y10: 37.19 | Z10: 44.381 | AA10: 47.902 | AB10: 49.911 | AC10: 64.326 | AD10: 59.244 | AE10: 66.418 | AF10: 76.206 | AG10: 116.824 | AH10: 85.292 | AI10: 111.212 | AJ10: 110.837 | AK10: 134.767 | AL10: =AL54*AL64 -> 103.37027 | AM10: =AM54*AM64 -> 128.56858 | AN10: =AN54*AN64 -> 127.83832 | AO10: =AO54*AO64 -> 153.54429 | AP10: =AP54*AP64 -> 120.11347 | AQ10: =AQ54*AQ64 -> 147.47265 | AR10: =AR54*AR64 -> 143.29862 | AS10: =AS54*AS64 -> 170.11378 | AU10: =E10 -> 14.346 | AV10: =I10 -> 16.952 | AW10: =M10 -> 13.047 | AX10: =Q10 -> 27.357 | AY10: =U10 -> 34.417 | AZ10: =Y10 -> 37.19 | BA10: =AC10 -> 64.326 | BB10: =AG10 -> 116.824 | BC10: =AK10 -> 134.767 | BD10: =AO10 -> 153.54429 | BE10: =AP10 -> 120.11347
A11: Total current assets | B11: =SUM(B6:B10) -> 156.578 | C11: =SUM(C6:C10) -> 170.462 | D11: =SUM(D6:D10) -> 178.621 | E11: =SUM(E6:E10) -> 226.499 | F11: =SUM(F6:F10) -> 205.071 | G11: =SUM(G6:G10) -> 217.001 | H11: =SUM(H6:H10) -> 225.685 | I11: =SUM(I6:I10) -> 259.09 | ... AS11: =SUM(AS6:AS10) -> 1542.3694 | AU11: =E11 -> 226.499 | AV11: =I11 -> 259.09 | AW11: =M11 -> 208.557 | AX11: =Q11 -> 419.848 | AY11: =U11 -> 959.207 | AZ11: =Y11 -> 905.657 | BA11: =AC11 -> 767.157 | BB11: =AG11 -> 878.074 | BC11: =AK11 -> 1298.555 | BD11: =AO11 -> 1396.7545 | BE11: =AP11 -> 1351.4315
A13: Long-term marketable securities | B13: 0 | C13: 0 | D13: 0 | E13: 0 | F13: 0 | G13: 0 | H13: 0 | I13: 0 | J13: 0 | K13: 0 | L13: 0 | M13: 0 | N13: 0 | O13: 0 | P13: 0 | Q13: 0 | R13: 0 | S13: 0 | T13: 0 | U13: 0 | V13: 0 | W13: 0 | X13: 0 | Y13: 0 | Z13: 0 | AA13: 0 | AB13: 206.44 | AC13: 211.063 | AD13: 226.366 | AE13: 162.972 | AF13: 332.329 | AG13: 658.896 | AH13: 591.702 | AI13: 364.203 | AJ13: 395.651 | AK13: 187.202 | AL13: =AK13 -> 187.202 | AM13: =AL13 -> 187.202 | AN13: =AM13 -> 187.202 | AO13: =AN13 -> 187.202 | AP13: =AO13 -> 187.202 | AQ13: =AP13 -> 187.202 | AR13: =AQ13 -> 187.202 | AS13: =AR13 -> 187.202 | AZ13: =Y13 -> 0 | BA13: =AC13 -> 211.063 | BB13: =AG13 -> 658.896 | BC13: =AK13 -> 187.202 | BD13: =AO13 -> 187.202 | BE13: =AP13 -> 187.202
A14: Operating Lease right-of-use Assets | B14: 0 | C14: 0 | D14: 0 | E14: 0 | F14: 0 | G14: 0 | H14: 0 | I14: 0 | J14: 51.875 | K14: 59.39 | L14: 57.046 | M14: 55.057 | N14: 53.808 | O14: 51.294 | P14: 43.683 | Q14: 47.924 | R14: 54 | S14: 52.554 | T14: 65.223 | U14: 63.749 | V14: 61.351 | W14: 60.512 | X14: 58.757 | Y14: 56.772 | Z14: 55.692 | AA14: 53.919 | AB14: 52.679 | AC14: 51.838 | AD14: 49.22 | AE14: 47.209 | AF14: 45.39 | AG14: 45.593 | AH14: 43.535 | AI14: 41.743 | AJ14: 59.159 | AK14: 57.677 | AL14: =AL54*AL65 -> 52.762566 | AM14: =AM54*AM65 -> 48.257726 | AN14: =AN54*AN65 -> 68.233419 | AO14: =AO54*AO65 -> 65.713225 | AP14: =AP54*AP65 -> 56.197022 | AQ14: =AQ54*AQ65 -> 48.588511 | AR14: =AR54*AR65 -> 71.232451 | AS14: =AS54*AS65 -> 66.11519 | AU14: =E14 -> 0 | AV14: =I14 -> 0 | AW14: =M14 -> 55.057 | AX14: =Q14 -> 47.924 | AY14: =U14 -> 63.749 | AZ14: =Y14 -> 56.772 | BA14: =AC14 -> 51.838 | BB14: =AG14 -> 45.593 | BC14: =AK14 -> 57.677 | BD14: =AO14 -> 65.713225 | BE14: =AP14 -> 56.197022
A15: Property and Equipment, net | B15: 10.786 | C15: 11.16 | D15: 11.512 | E15: 11.896 | F15: 12.18 | G15: 12.342 | H15: 12.593 | I15: 17.323 | J15: 21.065 | K15: 24.351 | L15: 27.188 | M15: 36.338 | N15: 36.849 | O15: 36.566 | P15: 36.019 | Q15: 37.163 | R15: 35.93 | S15: 34.621 | T15: 34.163 | U15: 38.298 | V15: 39.495 | W15: 39.636 | X15: 38.188 | Y15: 39.043 | Z15: 37.643 | AA15: 36.602 | AB15: 34.396 | AC15: 33.964 | AD15: 31.733 | AE15: 30.075 | AF15: 28.908 | AG15: 30.795 | AH15: 31.078 | AI15: 33.088 | AJ15: 34.74 | AK15: 36.032 | AL15: =AK15-'Cash Flow'!AL31-'Cash Flow'!AL81 -> 34.915605 | AM15: =AL15-'Cash Flow'!AM31-'Cash Flow'!AM81 -> 34.92049 | AN15: =AM15-'Cash Flow'!AN31-'Cash Flow'!AN81 -> 32.655427 | AO15: =AN15-'Cash Flow'!AO31-'Cash Flow'!AO81 -> 34.973116 | AP15: =AO15-'Cash Flow'!AP31-'Cash Flow'!AP81 -> 34.162558 | AQ15: =AP15-'Cash Flow'!AQ31-'Cash Flow'!AQ81 -> 34.537259 | AR15: =AQ15-'Cash Flow'!AR31-'Cash Flow'!AR81 -> 32.681359 | AS15: =AR15-'Cash Flow'!AS31-'Cash Flow'!AS81 -> 35.467708 | AU15: =E15 -> 11.896 | AV15: =I15 -> 17.323 | AW15: =M15 -> 36.338 | AX15: =Q15 -> 37.163 | AY15: =U15 -> 38.298 | AZ15: =Y15 -> 39.043 | BA15: =AC15 -> 33.964 | BB15: =AG15 -> 30.795 | BC15: =AK15 -> 36.032 | BD15: =AO15 -> 34.973116 | BE15: =AP15 -> 34.162558
A16: Intangible Assets | B16: 0 | C16: 0 | D16: 0 | E16: 0 | F16: 0 | G16: 0 | H16: 0 | I16: 0 | J16: 0 | K16: 0 | L16: 0 | M16: 0 | N16: 0 | O16: 0 | P16: 0 | Q16: 5.846 | R16: 5.462 | S16: 5.078 | T16: 4.695 | U16: 4.313 | V16: 3.931 | W16: 3.55 | X16: 3.169 | Y16: 2.788 | Z16: 2.406 | AA16: 2.025 | AB16: 1.644 | AC16: 1.263 | AD16: 0.881 | AE16: 0.5 | AF16: 0.119 | AG16: 0 | AH16: 6.014 | AI16: 5.844 | AJ16: 17.332 | AK16: 16.687 | AL16: =AK16-'Cash Flow'!AL80 -> 16.323647 | AM16: =AL16-'Cash Flow'!AM80 -> 15.937062 | AN16: =AM16-'Cash Flow'!AN80 -> 15.527509 | AO16: =AN16-'Cash Flow'!AO80 -> 15.093424 | AP16: =AO16-'Cash Flow'!AP80 -> 14.634517 | AQ16: =AP16-'Cash Flow'!AQ80 -> 14.158527 | AR16: =AQ16-'Cash Flow'!AR80 -> 13.663352 | AS16: =AR16-'Cash Flow'!AS80 -> 13.149362 | AU16: =E16 -> 0 | AV16: =I16 -> 0 | AW16: =M16 -> 0 | AX16: =Q16 -> 5.846 | AY16: =U16 -> 4.313 | AZ16: =Y16 -> 2.788 | BA16: =AC16 -> 1.263 | BB16: =AG16 -> 0 | BC16: =AK16 -> 16.687 | BD16: =AO16 -> 15.093424 | BE16: =AP16 -> 14.634517
A17: Goodwill | B17: 0 | C17: 0 | D17: 0 | E17: 0 | F17: 0 | G17: 0 | H17: 0 | I17: 0 | J17: 0 | K17: 0 | L17: 0 | M17: 0 | N17: 0 | O17: 0 | P17: 0 | Q17: 23.135 | R17: 23.135 | S17: 23.135 | T17: 23.135 | U17: 23.135 | V17: 23.135 | W17: 23.135 | X17: 23.135 | Y17: 23.135 | Z17: 23.135 | AA17: 23.135 | AB17: 23.135 | AC17: 23.135 | AD17: 23.135 | AE17: 23.135 | AF17: 23.135 | AG17: 23.135 | AH17: 39.75 | AI17: 39.75 | AJ17: 135.176 | AK17: 135.276 | AL17: =AK17 -> 135.276 | AM17: =AL17 -> 135.276 | AN17: =AM17 -> 135.276 | AO17: =AN17 -> 135.276 | AP17: =AO17 -> 135.276 | AQ17: =AP17 -> 135.276 | AR17: =AQ17 -> 135.276 | AS17: =AR17 -> 135.276 | AU17: =E17 -> 0 | AV17: =I17 -> 0 | AW17: =M17 -> 0 | AX17: =Q17 -> 23.135 | AY17: =U17 -> 23.135 | AZ17: =Y17 -> 23.135 | BA17: =AC17 -> 23.135 | BB17: =AG17 -> 23.135 | BC17: =AK17 -> 135.276 | BD17: =AO17 -> 135.276 | BE17: =AP17 -> 135.276
A18: Other Long-Term Assets | B18: 0.778 | C18: 0.818 | D18: 0.861 | E18: 7.243 | F18: 7.674 | G18: 7.724 | H18: 7.601 | I18: 8.565 | J18: 12.18 | K18: 13.149 | L18: 15.621 | M18: 18.36 | N18: 19.026 | O18: 20.007 | P18: 21.686 | Q18: 21.566 | R18: 19.444 | S18: 19.988 | T18: 19.717 | U18: 19.835 | V18: 20.143 | W18: 18.862 | X18: 18.666 | Y18: 16.337 | Z18: 16.4 | AA18: 15.888 | AB18: 16.333 | AC18: 15.49 | AD18: 14.56 | AE18: 14.78 | AF18: 16.904 | AG18: 27.782 | AH18: 46.925 | AI18: 62.021 | AJ18: 61.562 | AK18: 60.183 | AL18: =(AL54*AL66) -> 56.871102 | AM18: =(AM54*AM66) -> 71.700462 | AN18: =(AN54*AN66) -> 71.005016 | AO18: =(AO54*AO66) -> 68.56839 | AP18: =(AP54*AP66) -> 61.386015 | AQ18: =(AQ54*AQ66) -> 77.452789 | AR18: =(AR54*AR66) -> 74.58349 | AS18: =(AS54*AS66) -> 69.49592 | AU18: =E18 -> 7.243 | AV18: =I18 -> 8.565 | AW18: =M18 -> 18.36 | AX18: =Q18 -> 21.566 | AY18: =U18 -> 19.835 | AZ18: =Y18 -> 16.337 | BA18: =AC18 -> 15.49 | BB18: =AG18 -> 27.782 | BC18: =AK18 -> 60.183 | BD18: =AO18 -> 68.56839 | BE18: =AP18 -> 61.386015
A19: Total assets | B19: =SUM(B11:B18) -> 168.142 | C19: =SUM(C11:C18) -> 182.44 | D19: =SUM(D11:D18) -> 190.994 | E19: =SUM(E11:E18) -> 245.638 | F19: =SUM(F11:F18) -> 224.925 | G19: =SUM(G11:G18) -> 237.067 | H19: =SUM(H11:H18) -> 245.879 | I19: =SUM(I11:I18) -> 284.978 | ... AS19: =SUM(AS11:AS18) -> 2049.0755 | AU19: =E19 -> 245.638 | AV19: =I19 -> 284.978 | AW19: =M19 -> 318.312 | AX19: =Q19 -> 555.482 | AY19: =U19 -> 1108.537 | AZ19: =Y19 -> 1043.732 | BA19: =AC19 -> 1103.91 | BB19: =AG19 -> 1664.275 | BC19: =AK19 -> 1791.612 | BD19: =AO19 -> 1903.5806 | BE19: =AP19 -> 1840.2897
A21: Current liabilities
A22: Trades Payable | B22: 1.582 | C22: 1.348 | D22: 1.366 | E22: 0.635 | F22: 0.483 | G22: 1.899 | H22: 3.145 | I22: 2.62 | J22: 0.624 | K22: 2.299 | L22: 2.999 | M22: 0.997 | N22: 0.823 | O22: 0.678 | P22: 0.767 | Q22: 0.85 | R22: 0.637 | S22: 3.167 | T22: 3.446 | U22: 5.324 | V22: 4.771 | W22: 4.757 | X22: 5.989 | Y22: 2.962 | Z22: 0.708 | AA22: 0.68 | AB22: 1.328 | AC22: 0.672 | AD22: 2.899 | AE22: 2.532 | AF22: 1.489 | AG22: 4.313 | AH22: 6.274 | AI22: 7.115 | AJ22: 5.261 | AK22: 5.735 | AL22: =(AL55*AL62)/(365/4) -> 8.4529939 | AM22: =(AM55*AM62)/(365/4) -> 9.2222608 | AN22: =(AN55*AN62)/(365/4) -> 6.3579383 | AO22: =(AO55*AO62)/(365/4) -> 6.9891934 | AP22: =(AP55*AP62)/(365/4) -> 10.287735 | AQ22: =(AQ55*AQ62)/(365/4) -> 10.93837 | AR22: =(AR55*AR62)/(365/4) -> 7.402447 | AS22: =(AS55*AS62)/(365/4) -> 7.9663574 | AU22: =E22 -> 0.635 | AV22: =I22 -> 2.62 | AW22: =M22 -> 0.997 | AX22: =Q22 -> 0.85 | AY22: =U22 -> 5.324 | AZ22: =Y22 -> 2.962 | BA22: =AC22 -> 0.672 | BB22: =AG22 -> 4.313 | BC22: =AK22 -> 5.735 | BD22: =AO22 -> 6.9891934 | BE22: =AP22 -> 10.287735
A23: Accrued Expenses & Other Current Liabilities | B23: 21.579 | C23: 30.769 | D23: 32.166 | E23: 42.453 | F23: 36.19 | G23: 45.493 | H23: 46.104 | I23: 55.991 | J23: 50.301 | K23: 53.794 | L23: 53.694 | M23: 62.607 | N23: 59.994 | O23: 65.094 | P23: 66.483 | Q23: 83.198 | R23: 87.026 | S23: 91.973 | T23: 91.917 | U23: 102.226 | V23: 92.56 | W23: 105.782 | X23: 109.25 | Y23: 115.231 | Z23: 107.338 | AA23: 123.343 | AB23: 119.78 | AC23: 125.057 | AD23: 109.202 | AE23: 123.014 | AF23: 123.256 | AG23: 164.93 | AH23: 156.78 | AI23: 190.344 | AJ23: 193.074 | AK23: 225.411 | AL23: =AL54*AL68 -> 190.01068 | AM23: =AM54*AM68 -> 220.05051 | AN23: =AN54*AN68 -> 222.68969 | AO23: =AO54*AO68 -> 256.81786 | AP23: =AP54*AP68 -> 237.89124 | AQ23: =AQ54*AQ68 -> 268.7751 | AR23: =AR54*AR68 -> 266.99293 | AS23: =AS54*AS68 -> 301.75281 | AU23: =E23 -> 42.453 | AV23: =I23 -> 55.991 | AW23: =M23 -> 62.607 | AX23: =Q23 -> 83.198 | AY23: =U23 -> 102.226 | AZ23: =Y23 -> 115.231 | BA23: =AC23 -> 125.057 | BB23: =AG23 -> 164.93 | BC23: =AK23 -> 225.411 | BD23: =AO23 -> 256.81786 | BE23: =AP23 -> 237.89124
A24: Deferred Revenues | B24: 54.576 | C24: 57.457 | D24: 58.383 | E24: 73.493 | F24: 68.481 | G24: 71.663 | H24: 72.544 | I24: 87.729 | J24: 81.844 | K24: 79.078 | L24: 76.978 | M24: 95.975 | N24: 84.331 | O24: 79.129 | P24: 81.192 | Q24: 98.588 | R24: 91.596 | S24: 86.421 | T24: 86.253 | U24: 104.221 | V24: 98.763 | W24: 98.369 | X24: 94.19 | Y24: 110.55 | Z24: 109.297 | AA24: 130.727 | AB24: 145.453 | AC24: 181.049 | AD24: 185.086 | AE24: 208.907 | AF24: 217.605 | AG24: 250.529 | AH24: 250.912 | AI24: 322.791 | AJ24: 333.578 | AK24: 427.811 | AL24: =AL80*AL82 -> 445.55906 | AM24: =AM80*AM82 -> 506.19501 | AN24: =AN80*AN82 -> 524.74912 | AO24: =AO80*AO82 -> 631.02627 | AP24: =AP80*AP82 -> 604.44389 | AQ24: =AQ80*AQ82 -> 659.56093 | AR24: =AR80*AR82 -> 669.64562 | AS24: =AS80*AS82 -> 784.98369 | AU24: =E24 -> 73.493 | AV24: =I24 -> 87.729 | AW24: =M24 -> 95.975 | AX24: =Q24 -> 98.588 | AY24: =U24 -> 104.221 | AZ24: =Y24 -> 110.55 | BA24: =AC24 -> 181.049 | BB24: =AG24 -> 250.529 | BC24: =AK24 -> 427.811 | BD24: =AO24 -> 631.02627 | BE24: =AP24 -> 604.44389
A25: Current Portion of Long-term Debt | B25: 0 | C25: 0 | D25: 0 | E25: 0 | F25: 0 | G25: 0 | H25: 0 | I25: 0 | J25: 0 | K25: 0 | L25: 0 | M25: 0 | N25: 0 | O25: 0 | P25: 0 | Q25: 0 | R25: 0 | S25: 0 | T25: =S25 -> 0 | U25: =T25 -> 0 | V25: 0 | W25: 0 | X25: 0 | Y25: 0 | Z25: 0 | AA25: 0 | AB25: 0 | AC25: 0 | AD25: 0 | AE25: 0 | AF25: 251.625 | AG25: 290.113 | AH25: 296.142 | AI25: 251.148 | AJ25: 0 | AK25: =AJ25 -> 0 | AL25: =AK25 -> 0 | AM25: =AL25 -> 0 | AN25: =AM25 -> 0 | AO25: =AN25 -> 0 | AP25: =AO25 -> 0 | AQ25: =AP25 -> 0 | AR25: =AQ25 -> 0 | AS25: =AR25 -> 0 | AU25: =E25 -> 0 | AV25: =I25 -> 0 | AW25: =M25 -> 0 | AX25: =Q25 -> 0 | AY25: =U25 -> 0 | AZ25: =Y25 -> 0 | BA25: =AC25 -> 0 | BB25: =AG25 -> 290.113 | BC25: =AK25 -> 0 | BD25: =AO25 -> 0 | BE25: =AP25 -> 0
A26: Total current liabilities | B26: =SUM(B22:B25) -> 77.737 | C26: =SUM(C22:C25) -> 89.574 | D26: =SUM(D22:D25) -> 91.915 | E26: =SUM(E22:E25) -> 116.581 | F26: =SUM(F22:F25) -> 105.154 | G26: =SUM(G22:G25) -> 119.055 | H26: =SUM(H22:H25) -> 121.793 | I26: =SUM(I22:I25) -> 146.34 | ... AS26: =SUM(AS22:AS25) -> 1094.7029 | AU26: =E26 -> 116.581 | AV26: =I26 -> 146.34 | AW26: =M26 -> 159.579 | AX26: =Q26 -> 182.636 | AY26: =U26 -> 211.771 | AZ26: =Y26 -> 228.743 | BA26: =AC26 -> 306.778 | BB26: =AG26 -> 709.885 | BC26: =AK26 -> 658.957 | BD26: =AO26 -> 894.83332 | BE26: =AP26 -> 852.62287
A28: Long term liabilities
A29: Convertible Senior Notes | B29: 0 | C29: 0 | D29: 0 | E29: 0 | F29: 0 | G29: 0 | H29: 0 | I29: 0 | J29: 0 | K29: 0 | L29: 0 | M29: 0 | N29: 0 | O29: 215.144 | P29: 216.791 | Q29: 218.46 | R29: 220.149 | S29: 221.857 | T29: 223.584 | U29: 225.33 | V29: 247.846 | W29: 248.216 | X29: 248.589 | Y29: 248.963 | Z29: 249.339 | AA29: 249.716 | AB29: 250.096 | AC29: 250.477 | AD29: 250.86 | AE29: 251.239 | AF29: 449.759 | AG29: 450.243 | AH29: 450.746 | AI29: 451.247 | AJ29: 451.754 | AK29: 452.259 | AL29: =AK29 -> 452.259 | AM29: =AL29 -> 452.259 | AN29: =AM29 -> 452.259 | AO29: =AN29 -> 452.259 | AP29: =AO29 -> 452.259 | AQ29: =AP29 -> 452.259 | AR29: =AQ29 -> 452.259 | AS29: =AR29 -> 452.259 | AU29: =E29 -> 0 | AV29: =I29 -> 0 | AW29: =M29 -> 0 | AX29: =Q29 -> 218.46 | AY29: =U29 -> 225.33 | AZ29: =Y29 -> 248.963 | BA29: =AC29 -> 250.477 | BB29: =AG29 -> 450.243 | BC29: =AK29 -> 452.259 | BD29: =AO29 -> 452.259 | BE29: =AP29 -> 452.259
A30: Operating Lease Liability | B30: 0 | C30: 0 | D30: 0 | E30: 0 | F30: 0 | G30: 0 | H30: 0 | I30: 0 | J30: 52.697 | K30: 59.842 | L30: 58.667 | M30: 57.04 | N30: 54.58 | O30: 53.539 | P30: 48.377 | Q30: 54.54 | R30: 54.383 | S30: 52.72 | T30: 70.318 | U30: 68.694 | V30: 65.786 | W30: 61.982 | X30: 58.867 | Y30: 57.627 | Z30: 55.993 | AA30: 53.565 | AB30: 51.433 | AC30: 51.313 | AD30: 48.009 | AE30: 45.414 | AF30: 43.654 | AG30: 42.789 | AH30: 40.559 | AI30: 39.865 | AJ30: 59.921 | AK30: 59.749 | AL30: =AL54*AL69 -> 49.155781 | AM30: =AM54*AM69 -> 46.086631 | AN30: =AN54*AN69 -> 69.112302 | AO30: =AO54*AO69 -> 68.07392 | AP30: =AP54*AP69 -> 62.082702 | AQ30: =AQ54*AQ69 -> 56.744968 | AR30: =AR54*AR69 -> 83.561221 | AS30: =AS54*AS69 -> 80.604639 | AU30: =E30 -> 0 | AV30: =I30 -> 0 | AW30: =M30 -> 57.04 | AX30: =Q30 -> 54.54 | AY30: =U30 -> 68.694 | AZ30: =Y30 -> 57.627 | BA30: =AC30 -> 51.313 | BB30: =AG30 -> 42.789 | BC30: =AK30 -> 59.749 | BD30: =AO30 -> 68.07392 | BE30: =AP30 -> 62.082702
A31: Deferred Revenues | B31: 4.261 | C31: 3.889 | D31: 5.047 | E31: 7.807 | F31: 6.247 | G31: 6.274 | H31: 6.374 | I31: 6.487 | J31: 6.988 | K31: 6.119 | L31: 5.489 | M31: 5.46 | N31: 4.501 | O31: 3.692 | P31: 3.3 | Q31: 2.778 | R31: 2.152 | S31: 2.052 | T31: 1.872 | U31: 2.566 | V31: 2.378 | W31: 2.277 | X31: 2.125 | Y31: 1.503 | Z31: 1.382 | AA31: 0.648 | AB31: 0.155 | AC31: 0.886 | AD31: 0.403 | AE31: 0.022 | AF31: 1.53 | AG31: 2.211 | AH31: 0.126 | AI31: 0.108 | AJ31: 7.93 | AK31: 14.406 | AL31: =AL80*AL83 -> -9.7101423 | AM31: =AM80*AM83 -> -11.031592 | AN31: =AN80*AN83 -> -11.435944 | AO31: =AO80*AO83 -> -13.75206 | AP31: =AP80*AP83 -> -13.172746 | AQ31: =AQ80*AQ83 -> -14.373921 | AR31: =AR80*AR83 -> -14.593698 | AS31: =AS80*AS83 -> -17.10728 | AU31: =E31 -> 7.807 | AV31: =I31 -> 6.487 | AW31: =M31 -> 5.46 | AX31: =Q31 -> 2.778 | AY31: =U31 -> 2.566 | AZ31: =Y31 -> 1.503 | BA31: =AC31 -> 0.886 | BB31: =AG31 -> 2.211 | BC31: =AK31 -> 14.406 | BD31: =AO31 -> -13.75206 | BE31: =AP31 -> -13.172746
A32: Other Liabilities | B32: =1.445+5.429 -> 6.874 | C32: =1.472+5.273 -> 6.745 | D32: =1.705+5.283 -> 6.988 | E32: 6.608 | F32: 8.045 | G32: 7.933 | H32: 7.651 | I32: 6.781 | J32: 2.997 | K32: 2.694 | L32: 2.555 | M32: 2.701 | N32: 2.712 | O32: 2.49 | P32: 2.689 | Q32: 2.997 | R32: 3.274 | S32: 3.756 | T32: 4.122 | U32: 3.583 | V32: 3.68 | W32: 4.472 | X32: 7.191 | Y32: 4.771 | Z32: 5.985 | AA32: 7.505 | AB32: 7.891 | AC32: 4.808 | AD32: 4.846 | AE32: 5.081 | AF32: 3.676 | AG32: 3.491 | AH32: 7.812 | AI32: 10.895 | AJ32: 8.653 | AK32: 7.585 | AL32: =AL54*AL70 -> 9.4678113 | AM32: =AM54*AM70 -> 12.595355 | AN32: =AN54*AN70 -> 9.9802866 | AO32: =AO54*AO70 -> 8.6418297 | AP32: =AP54*AP70 -> 11.957644 | AQ32: =AQ54*AQ70 -> 15.508251 | AR32: =AR54*AR70 -> 12.066809 | AS32: =AS54*AS70 -> 10.232576 | AU32: =E32 -> 6.608 | AV32: =I32 -> 6.781 | AW32: =M32 -> 2.701 | AX32: =Q32 -> 2.997 | AY32: =U32 -> 3.583 | AZ32: =Y32 -> 4.771 | BA32: =AC32 -> 4.808 | BB32: =AG32 -> 3.491 | BC32: =AK32 -> 7.585 | BD32: =AO32 -> 8.6418297 | BE32: =AP32 -> 11.957644
A33: Total Liabilities | B33: =SUM(B26:B32) -> 88.872 | C33: =SUM(C26:C32) -> 100.208 | D33: =SUM(D26:D32) -> 103.95 | E33: =SUM(E26:E32) -> 130.996 | F33: =SUM(F26:F32) -> 119.446 | G33: =SUM(G26:G32) -> 133.262 | H33: =SUM(H26:H32) -> 135.818 | I33: =SUM(I26:I32) -> 159.608 | ... AS33: =SUM(AS26:AS32) -> 1620.6918 | AU33: =E33 -> 130.996 | AV33: =I33 -> 159.608 | AW33: =M33 -> 224.78 | AX33: =Q33 -> 461.411 | AY33: =U33 -> 511.944 | AZ33: =Y33 -> 541.607 | BA33: =AC33 -> 614.262 | BB33: =AG33 -> 1208.619 | BC33: =AK33 -> 1192.956 | BD33: =AO33 -> 1410.056 | BE33: =AP33 -> 1365.7495
A35: Stockholders' equity
A36: Common Stock | B36: 0.027 | C36: 0.027 | D36: 0.028 | E36: 0.028 | F36: 0.029 | G36: 0.029 | H36: 0.029 | I36: 0.03 | J36: 0.03 | K36: 0.03 | L36: 0.03 | M36: 0.031 | N36: 0.031 | O36: 0.032 | P36: 0.032 | Q36: 0.032 | R36: 0.106 | S36: 0.107 | T36: 0.107 | U36: 0.108 | V36: 0.11 | W36: 0.11 | X36: 0.11 | Y36: 0.108 | Z36: 0.11 | AA36: 0.11 | AB36: 0.109 | AC36: 0.109 | AD36: 0.112 | AE36: 0.112 | AF36: 0.112 | AG36: 0.113 | AH36: 0.113 | AI36: 0.112 | AJ36: 0.118 | AK36: 0.118 | AL36: =AK36 -> 0.118 | AM36: =AL36 -> 0.118 | AN36: =AM36 -> 0.118 | AO36: =AN36 -> 0.118 | AP36: =AO36 -> 0.118 | AQ36: =AP36 -> 0.118 | AR36: =AQ36 -> 0.118 | AS36: =AR36 -> 0.118 | AU36: =E36 -> 0.028 | AV36: =I36 -> 0.03 | AW36: =M36 -> 0.031 | AX36: =Q36 -> 0.032 | AY36: =U36 -> 0.108 | AZ36: =Y36 -> 0.108 | BA36: =AC36 -> 0.109 | BB36: =AG36 -> 0.113 | BC36: =AK36 -> 0.118 | BD36: =AO36 -> 0.118 | BE36: =AP36 -> 0.118
A37: Accumulated Other Comprehensive Income | B37: 1.645 | C37: 2.128 | D37: 1.009 | E37: 0.136 | F37: -1.973 | G37: -2.838 | H37: -1.742 | I37: -3.633 | J37: -0.688 | K37: 0.258 | L37: 0.771 | M37: -0.449 | N37: 0.291 | O37: 3.536 | P37: 3.665 | Q37: 9.371 | R37: 4.191 | S37: 3.093 | T37: 2.528 | U37: 6.083 | V37: 2.894 | W37: -7.919 | X37: -12.357 | Y37: -9.557 | Z37: -14.381 | AA37: -18.019 | AB37: -23.12 | AC37: -8.649 | AD37: -9.105 | AE37: -10.625 | AF37: -4.381 | AG37: 2.676 | AH37: -1.162 | AI37: 14.497 | AJ37: 18.382 | AK37: 23.132 | AL37: =AK37 -> 23.132 | AM37: =AL37 -> 23.132 | AN37: =AM37 -> 23.132 | AO37: =AN37 -> 23.132 | AP37: =AO37 -> 23.132 | AQ37: =AP37 -> 23.132 | AR37: =AQ37 -> 23.132 | AS37: =AR37 -> 23.132 | AU37: =E37 -> 0.136 | AV37: =I37 -> -3.633 | AW37: =M37 -> -0.449 | AX37: =Q37 -> 9.371 | AY37: =U37 -> 6.083 | AZ37: =Y37 -> -9.557 | BA37: =AC37 -> -8.649 | BB37: =AG37 -> 2.676 | BC37: =AK37 -> 23.132 | BD37: =AO37 -> 23.132 | BE37: =AP37 -> 23.132
A38: Additional Paid-In-Capital | B38: 197.237 | C38: 204.751 | D38: 213.995 | E38: 223.868 | F38: 231.86 | G38: 243.733 | H38: 256.21 | I38: 266.941 | J38: 271.26 | K38: 285.001 | L38: 299.051 | M38: 310.682 | N38: 327.881 | O38: 347.447 | P38: 370.933 | Q38: 395.41 | R38: 920.691 | S38: 946.532 | T38: 976.995 | U38: 1018.005 | V38: 1000.493 | W38: 1038.25 | X38: 1077.28 | Y38: 1055.048 | Z38: 1077.327 | AA38: 1109.093 | AB38: 1111.076 | AC38: 1142.578 | AD38: 1146.222 | AE38: 1177.947 | AF38: 1159.99 | AG38: 1193.022 | AH38: 1144.73 | AI38: 1138.652 | AJ38: 1428.039 | AK38: 1444.885 | AL38: =AK38 -> 1444.885 | AM38: =AL38 -> 1444.885 | AN38: =AM38 -> 1444.885 | AO38: =AN38 -> 1444.885 | AP38: =AO38 -> 1444.885 | AQ38: =AP38 -> 1444.885 | AR38: =AQ38 -> 1444.885 | AS38: =AR38 -> 1444.885 | AU38: =E38 -> 223.868 | AV38: =I38 -> 266.941 | AW38: =M38 -> 310.682 | AX38: =Q38 -> 395.41 | AY38: =U38 -> 1018.005 | AZ38: =Y38 -> 1055.048 | BA38: =AC38 -> 1142.578 | BB38: =AG38 -> 1193.022 | BC38: =AK38 -> 1444.885 | BD38: =AO38 -> 1444.885 | BE38: =AP38 -> 1444.885
A39: Accumulated Deficit | B39: -119.639 | C39: -124.674 | D39: -127.988 | E39: -109.39 | F39: -124.437 | G39: -137.119 | H39: -144.436 | I39: -137.968 | J39: -160.607 | K39: -185.095 | L39: -202.082 | M39: -216.732 | N39: -248.162 | O39: -272.485 | P39: -291.71 | Q39: -310.742 | R39: -346.398 | S39: -379.346 | T39: -402.66 | U39: -427.603 | V39: -467.719 | W39: -504.009 | X39: -532.726 | Y39: -543.474 | Z39: -581.778 | AA39: -620.475 | AB39: -643.492 | AC39: -644.39 | AD39: -684.88 | AE39: -708.828 | AF39: -727.161 | AG39: -740.155 | AH39: -775.938 | AI39: -811.762 | AJ39: -841.704 | AK39: -869.479 | AL39: =AL19-AL33-AL36-AL37-AL38 -> -896.90494 | AM39: =AM19-AM33-AM36-AM37-AM38 -> -919.15258 | AN39: =AN19-AN33-AN36-AN37-AN38 -> -943.61281 | AO39: =AO19-AO33-AO36-AO37-AO38 -> -974.61039 | AP39: =AP19-AP33-AP36-AP37-AP38 -> -993.59481 | AQ39: =AQ19-AQ33-AQ36-AQ37-AQ38 -> -1009.2343 | AR39: =AR19-AR33-AR36-AR37-AR38 -> -1022.4338 | AS39: =AS19-AS33-AS36-AS37-AS38 -> -1039.7513 | AU39: =E39 -> -109.39 | AV39: =I39 -> -137.968 | AW39: =M39 -> -216.732 | AX39: =Q39 -> -310.742 | AY39: =U39 -> -427.603 | AZ39: =Y39 -> -543.474 | BA39: =AC39 -> -644.39 | BB39: =AG39 -> -740.155 | BC39: =AK39 -> -869.479 | BD39: =AO39 -> -974.61039 | BE39: =AP39 -> -993.59481
A40: Total stockholders' equity | B40: =SUM(B36:B39) -> 79.27 | C40: =SUM(C36:C39) -> 82.232 | D40: =SUM(D36:D39) -> 87.044 | E40: =SUM(E36:E39) -> 114.642 | F40: =SUM(F36:F39) -> 105.479 | G40: =SUM(G36:G39) -> 103.805 | H40: =SUM(H36:H39) -> 110.061 | I40: =SUM(I36:I39) -> 125.37 | ... AS40: =SUM(AS36:AS39) -> 428.38375 | AU40: =E40 -> 114.642 | AV40: =I40 -> 125.37 | AW40: =M40 -> 93.532 | AX40: =Q40 -> 94.071 | AY40: =U40 -> 596.593 | AZ40: =Y40 -> 502.125 | BA40: =AC40 -> 489.648 | BB40: =AG40 -> 455.656 | BC40: =AK40 -> 598.656 | BD40: =AO40 -> 493.52461 | BE40: =AP40 -> 474.54019
A41: Total liabilities and shareholders' equity | B41: =B40+B33 -> 168.142 | C41: =C40+C33 -> 182.44 | D41: =D40+D33 -> 190.994 | E41: =E40+E33 -> 245.638 | F41: =F40+F33 -> 224.925 | G41: =G40+G33 -> 237.067 | H41: =H40+H33 -> 245.879 | I41: =I40+I33 -> 284.978 | ... AS41: =AS40+AS33 -> 2049.0755 | AU41: =E41 -> 245.638 | AV41: =I41 -> 284.978 | AW41: =M41 -> 318.312 | AX41: =Q41 -> 555.482 | AY41: =U41 -> 1108.537 | AZ41: =Y41 -> 1043.732 | BA41: =AC41 -> 1103.91 | BB41: =AG41 -> 1664.275 | BC41: =AK41 -> 1791.612 | BD41: =AO41 -> 1903.5806 | BE41: =AP41 -> 1840.2897
A43: Net cash | B43: =B6+B7+B8+B13-B29-B25 -> 121.32 | C43: =C6+C7+C8+C13-C29-C25 -> 121.578 | D43: =D6+D7+D8+D13-D29-D25 -> 128.441 | E43: =E6+E7+E8+E13-E29-E25 -> 136.557 | F43: =F6+F7+F8+F13-F29-F25 -> 153.67 | G43: =G6+G7+G8+G13-G29-G25 -> 158.681 | H43: =H6+H7+H8+H13-H29-H25 -> 158.082 | I43: =I6+I7+I8+I13-I29-I25 -> 158.915 | ... AS43: =AS6+AS7+AS8+AS13-AS29-AS25 -> 786.8093 | AU43: =AU6+AU7+AU8+AU13-AU29-AU25 -> 136.557 | AV43: =AV6+AV7+AV8+AV13-AV29-AV25 -> 158.915 | AW43: =AW6+AW7+AW8+AW13-AW29-AW25 -> 120.46 | AX43: =AX6+AX7+AX8+AX13-AX29-AX25 -> 79.802 | AY43: =AY6+AY7+AY8+AY13-AY29-AY25 -> 582.281 | AZ43: =AZ6+AZ7+AZ8+AZ13-AZ29-AZ25 -> 483.525 | BA43: =BA6+BA7+BA8+BA13-BA29-BA25 -> 494.301 | BB43: =BB6+BB7+BB8+BB13-BB29-BB25 -> 486.958 | BC43: =BC6+BC7+BC8+BC13-BC29-BC25 -> 655.909 | BD43: =AO43 -> 703.24198 | BE43: =AS43 -> 786.8093
A44: Y/Y % | F44: =F43/B43-1 -> 0.26665018 | G44: =G43/C43-1 -> 0.30517857 | H44: =H43/D43-1 -> 0.23077522 | I44: =I43/E43-1 -> 0.1637265 | J44: =J43/F43-1 -> 0.06482072 | K44: =K43/G43-1 -> -0.077822802 | L44: =L43/H43-1 -> -0.16890601 | M44: =M43/I43-1 -> -0.24198471 | ... AS44: =AS43/AO43-1 -> 0.11883153 | AU44: =IF(ISERROR(AU43/AT43-1),"NA",AU43/AT43-1) -> NA | AV44: =IF(ISERROR(AV43/AU43-1),"NA",AV43/AU43-1) -> 0.1637265 | AW44: =IF(ISERROR(AW43/AV43-1),"NA",AW43/AV43-1) -> -0.24198471 | AX44: =IF(ISERROR(AX43/AW43-1),"NA",AX43/AW43-1) -> -0.33752283 | AY44: =IF(ISERROR(AY43/AX43-1),"NA",AY43/AX43-1) -> 6.2965715 | AZ44: =IF(ISERROR(AZ43/AY43-1),"NA",AZ43/AY43-1) -> -0.16960196 | BA44: =IF(ISERROR(BA43/AZ43-1),"NA",BA43/AZ43-1) -> 0.022286335 | BB44: =IF(ISERROR(BB43/BA43-1),"NA",BB43/BA43-1) -> -0.014855321 | ... BE44: =IF(ISERROR(BE43/BD43-1),"NA",BE43/BD43-1) -> 0.11883153
A46: Net cash per diluted share | B46: =B43/'Income Statement'!B46 -> 4.5014685 | C46: =C43/'Income Statement'!C46 -> 3.9802632 | D46: =D43/'Income Statement'!D46 -> 4.1685178 | E46: =E43/'Income Statement'!E46 -> 4.3878238 | F46: =F43/'Income Statement'!F46 -> 5.4180736 | G46: =G43/'Income Statement'!G46 -> 5.4868353 | H46: =H43/'Income Statement'!H46 -> 4.8603139 | I46: =I43/'Income Statement'!I46 -> 4.8887263 | ... AS46: =AS43/'Income Statement'!AS46 -> 5.3488824 | AU46: =E46 -> 4.3878238 | AV46: =I46 -> 4.8887263 | AW46: =M46 -> 3.9463131 | AX46: =Q46 -> 0.73637293 | AY46: =+U46 -> 4.9075528 | AZ46: =+Y46 -> 3.8371898 | BA46: =+AC46 -> 3.9210985 | BB46: =AG46 -> 3.604496 | BC46: =AK46 -> 4.9206256 | BD46: =AO46 -> 4.8400015 | BE46: =AS46 -> 5.3488824
A47: Y/Y % | F47: =F46/B46-1 -> 0.20362359 | G47: =G46/C46-1 -> 0.37851067 | H47: =H46/D46-1 -> 0.16595732 | I47: =I46/E46-1 -> 0.11415739 | J47: =J46/F46-1 -> 0.012506008 | K47: =K46/G46-1 -> -0.11936061 | L47: =L46/H46-1 -> -0.11022894 | M47: =M46/I46-1 -> -0.19277275 | ... AS47: =AS46/AO46-1 -> 0.10514066 | AU47: =IF(ISERROR(AU46/AT46-1),"NA",AU46/AT46-1) -> NA | AV47: =IF(ISERROR(AV46/AU46-1),"NA",AV46/AU46-1) -> 0.11415739 | AW47: =IF(ISERROR(AW46/AV46-1),"NA",AW46/AV46-1) -> -0.19277275 | AX47: =IF(ISERROR(AX46/AW46-1),"NA",AX46/AW46-1) -> -0.8134023 | AY47: =IF(ISERROR(AY46/AX46-1),"NA",AY46/AX46-1) -> 5.6644937 | AZ47: =IF(ISERROR(AZ46/AY46-1),"NA",AZ46/AY46-1) -> -0.21810525 | BA47: =IF(ISERROR(BA46/AZ46-1),"NA",BA46/AZ46-1) -> 0.021867225 | BB47: =IF(ISERROR(BB46/BA46-1),"NA",BB46/BA46-1) -> -0.080743297 | ... BE47: =IF(ISERROR(BE46/BD46-1),"NA",BE46/BD46-1) -> 0.10514066
A48: Source: Company data, Wells Fargo Securities, LLC estimates
A50: Check | B50: =IF((B19=B41)*AND(B19>0),"—","X") -> — | C50: =IF((C19=C41)*AND(C19>0),"—","X") -> — | D50: =IF((D19=D41)*AND(D19>0),"—","X") -> — | E50: =IF((E19=E41)*AND(E19>0),"—","X") -> — | F50: =IF((F19=F41)*AND(F19>0),"—","X") -> — | G50: =IF((G19=G41)*AND(G19>0),"—","X") -> — | H50: =IF((H19=H41)*AND(H19>0),"—","X") -> — | I50: =IF((I19=I41)*AND(I19>0),"—","X") -> — | ... AS50: =IF((AS19=AS41)*AND(AS19>0),"—","X") -> — | AU50: =IF((AU19=AU41)*AND(AU19>0),"—","X") -> — | AV50: =IF((AV19=AV41)*AND(AV19>0),"—","X") -> — | AW50: =IF((AW19=AW41)*AND(AW19>0),"—","X") -> — | AX50: =IF((AX19=AX41)*AND(AX19>0),"—","X") -> — | AY50: =IF((AY19=AY41)*AND(AY19>0),"—","X") -> — | AZ50: =IF((AZ19=AZ41)*AND(AZ19>0),"—","X") -> — | BA50: =IF((BA19=BA41)*AND(BA19>0),"—","X") -> — | BB50: =IF((BB19=BB41)*AND(BB19>0),"—","X") -> — | ... BE50: =IF((BE19=BE41)*AND(BE19>0),"—","X") -> —
B51: =+B19-B41 -> 0 | C51: =+C19-C41 -> 0 | D51: =+D19-D41 -> 0 | E51: =+E19-E41 -> 0 | F51: =+F19-F41 -> 0 | G51: =+G19-G41 -> 0 | H51: =+H19-H41 -> 0 | I51: =+I19-I41 -> 0 | ... AS51: =+AS19-AS41 -> 0
A53: Income Statement | AU53: ='Income Statement'!AU$4 -> 2017 | AV53: ='Income Statement'!AV$4 -> 2018 | AW53: ='Income Statement'!AW$4 -> 2019 | AX53: ='Income Statement'!AX$4 -> 2020 | AY53: ='Income Statement'!AY$4 -> 2021 | AZ53: ='Income Statement'!AZ$4 -> 2022 | BA53: ='Income Statement'!BA$4 -> 2023 | BB53: ='Income Statement'!BB$4 -> 2024 | ... BE53: ='Income Statement'!BE$4 -> 2027E
A54: Revenue | B54: =+'Income Statement'!B8 -> 39.593 | C54: =+'Income Statement'!C8 -> 49.431 | D54: =+'Income Statement'!D8 -> 53.365 | E54: =+'Income Statement'!E8 -> 73.001 | F54: =+'Income Statement'!F8 -> 53.528 | G54: =+'Income Statement'!G8 -> 62.19 | H54: =+'Income Statement'!H8 -> 67.052 | I54: =+'Income Statement'!I8 -> 87.518 | ... AS54: =+'Income Statement'!AS8 -> 233.88418
A55: COGS | B55: =+'Income Statement'!B15 -> 4.433 | C55: =+'Income Statement'!C15 -> 4.596 | D55: =+'Income Statement'!D15 -> 5.115 | E55: =+'Income Statement'!E15 -> 5.401 | F55: =+'Income Statement'!F15 -> 5.813 | G55: =+'Income Statement'!G15 -> 5.894 | H55: =+'Income Statement'!H15 -> 6.571 | I55: =+'Income Statement'!I15 -> 7.285 | ... AS55: =+'Income Statement'!AS15 -> 48.18014
A56: R&D | B56: =+'Income Statement'!B20 -> 9.264 | C56: =+'Income Statement'!C20 -> 10.184 | D56: =+'Income Statement'!D20 -> 10.502 | E56: =+'Income Statement'!E20 -> 12.143 | F56: =+'Income Statement'!F20 -> 13.401 | G56: =+'Income Statement'!G20 -> 14.628 | H56: =+'Income Statement'!H20 -> 15.154 | I56: =+'Income Statement'!I20 -> 16.963 | ... AS56: =+'Income Statement'!AS20 -> 56.132202
A57: EBIT | B57: =+'Income Statement'!B24 -> -7.126 | C57: =+'Income Statement'!C24 -> -0.649 | D57: =+'Income Statement'!D24 -> 1.928 | E57: =+'Income Statement'!E24 -> 13.421 | F57: =+'Income Statement'!F24 -> -6.702 | G57: =+'Income Statement'!G24 -> -1.024 | H57: =+'Income Statement'!H24 -> 1.996 | I57: =+'Income Statement'!I24 -> 15.531 | ... AS57: =+'Income Statement'!AS24 -> 21.985113
A58: Net Income | B58: =+'Income Statement'!B36 -> -6.857 | C58: =+'Income Statement'!C36 -> -0.279 | D58: =+'Income Statement'!D36 -> 1.791 | E58: =+'Income Statement'!E36 -> 12.494 | F58: =+'Income Statement'!F36 -> -6.976 | G58: =+'Income Statement'!G36 -> -1.27 | H58: =+'Income Statement'!H36 -> 1.849 | I58: =+'Income Statement'!I36 -> 17.329 | ... AS58: =+'Income Statement'!AS36 -> 22.057113
A60: Working Capital Ratios
A61: Days Sales Outstanding (DSO) | B61: =+(B9/B54)*(365/4) -> 63.300899 | C61: =+(C9/C54)*(365/4) -> 76.264111 | D61: =+(D9/D54)*(365/4) -> 76.399325 | E61: =+(E9/E54)*(365/4) -> 94.493706 | F61: =+(F9/F54)*(365/4) -> 55.348696 | G61: =+(G9/G54)*(365/4) -> 60.735026 | H61: =+(H9/H54)*(365/4) -> 72.042482 | I61: =+(I9/I54)*(365/4) -> 86.77185 | ... AK61: =+(AK9/AK54)*(365/4) -> 127.80548 | AL61: =AH61 -> 82.658963 | AM61: =AI61 -> 89.774773 | AN61: =AJ61 -> 80.548624 | AO61: 127 | AP61: =AL61 -> 82.658963 | AQ61: =AM61 -> 89.774773 | AR61: =AN61 -> 80.548624 | AS61: 125
A62: Days Payable Outstanding (DPO) | B62: =+(B22/B55)*(365/4) -> 32.564291 | C62: =+(C22/C55)*(365/4) -> 26.76349 | D62: =+(D22/D55)*(365/4) -> 24.369013 | E62: =+(E22/E55)*(365/4) -> 10.728337 | F62: =+(F22/F55)*(365/4) -> 7.5819284 | G62: =+(G22/G55)*(365/4) -> 29.400025 | H62: =+(H22/H55)*(365/4) -> 43.673908 | I62: =+(I22/I55)*(365/4) -> 32.817433 | ... AK62: =+(AK22/AK55)*(365/4) -> 15.087754 | AL62: =AH62 -> 21.205367 | AM62: =AI62 -> 21.94429 | AN62: =AJ62 -> 14.412509 | AO62: =AK62 -> 15.087754 | AP62: =AL62 -> 21.205367 | AQ62: =AM62 -> 21.94429 | AR62: =AN62 -> 14.412509 | AS62: =AO62 -> 15.087754
A64: =A10 -> Prepaid Expenses & Other Current Assets | B64: =B10/B54 -> 0.19680247 | C64: =C10/C54 -> 0.15316299 | D64: =D10/D54 -> 0.10306381 | E64: =E10/E54 -> 0.19651786 | F64: =F10/F54 -> 0.35370274 | G64: =G10/G54 -> 0.27218202 | H64: =H10/H54 -> 0.21871085 | I64: =I10/I54 -> 0.1936973 | ... AK64: =AK10/AK54 -> 0.77734197 | AL64: =+AH64 -> 0.6252025 | AM64: =+AI64 -> 0.73087413 | AN64: =+AJ64 -> 0.68597016 | AO64: =+AK64 -> 0.77734197 | AP64: =+AL64-0.05 -> 0.5752025 | AQ64: =+AM64-0.05 -> 0.68087413 | AR64: =+AN64-0.05 -> 0.63597016 | AS64: =+AO64-0.05 -> 0.72734197
A65: =A14 -> Operating Lease right-of-use Assets | B65: =B14/B54 -> 0 | C65: =C14/C54 -> 0 | D65: =D14/D54 -> 0 | E65: =E14/E54 -> 0 | F65: =F14/F54 -> 0 | G65: =G14/G54 -> 0 | H65: =H14/H54 -> 0 | I65: =I14/I54 -> 0 | ... AK65: =AK14/AK54 -> 0.33268347 | AL65: =+AH65 -> 0.31911774 | AM65: =+AI65 -> 0.27433082 | AN65: =+AJ65 -> 0.36613503 | AO65: =+AK65 -> 0.33268347 | AP65: =+AL65-0.05 -> 0.26911774 | AQ65: =+AM65-0.05 -> 0.22433082 | AR65: =+AN65-0.05 -> 0.31613503 | AS65: =+AO65-0.05 -> 0.28268347
A66: =A18 -> Other Long-Term Assets | B66: =+B18/B54 -> 0.019649938 | C66: =+C18/C54 -> 0.01654832 | D66: =+D18/D54 -> 0.01613417 | E66: =+E18/E54 -> 0.099217819 | F66: =+F18/F54 -> 0.14336422 | G66: =+G18/G54 -> 0.12420003 | H66: =+H18/H54 -> 0.11335978 | I66: =+I18/I54 -> 0.097865582 | ... AK66: =+AK18/AK54 -> 0.34713819 | AL66: =+AH66 -> 0.34396693 | AM66: =+AI66 -> 0.4075958 | AN66: =+AJ66 -> 0.3810072 | AO66: =+AK66 -> 0.34713819 | AP66: =+AL66-0.05 -> 0.29396693 | AQ66: =+AM66-0.05 -> 0.3575958 | AR66: =+AN66-0.05 -> 0.3310072 | AS66: =+AO66-0.05 -> 0.29713819
A68: =A23 -> Accrued Expenses & Other Current Liabilities | B68: =+B23/B54 -> 0.54502058 | C68: =+C23/C54 -> 0.62246364 | D68: =+D23/D54 -> 0.60275461 | E68: =+E23/E54 -> 0.58153998 | F68: =+F23/F54 -> 0.67609475 | G68: =+G23/G54 -> 0.73151632 | H68: =+H23/H54 -> 0.68758575 | I68: =+I23/I54 -> 0.63976553 | ... AK68: =+AK23/AK54 -> 1.3001805 | AL68: =+AH68 -> 1.1492197 | AM68: =+AI68 -> 1.2509217 | AN68: =+AJ68 -> 1.1949349 | AO68: =+AK68 -> 1.3001805 | AP68: =+AL68-0.01 -> 1.1392197 | AQ68: =+AM68-0.01 -> 1.2409217 | AR68: =+AN68-0.01 -> 1.1849349 | AS68: =+AO68-0.01 -> 1.2901805
A69: =A30 -> Operating Lease Liability | B69: =B30/B54 -> 0 | C69: =C30/C54 -> 0 | D69: =D30/D54 -> 0 | E69: =E30/E54 -> 0 | F69: =F30/F54 -> 0 | G69: =G30/G54 -> 0 | H69: =H30/H54 -> 0 | I69: =I30/I54 -> 0 | ... AK69: =AK30/AK54 -> 0.34463485 | AL69: =+AH69 -> 0.29730324 | AM69: =+AI69 -> 0.26198879 | AN69: =+AJ69 -> 0.37085105 | AO69: =+AK69 -> 0.34463485 | AP69: =+AL69 -> 0.29730324 | AQ69: =+AM69 -> 0.26198879 | AR69: =+AN69 -> 0.37085105 | AS69: =+AO69 -> 0.34463485
A70: =A32 -> Other Liabilities | B70: =+B32/B54 -> 0.17361655 | C70: =+C32/C54 -> 0.13645283 | D70: =+D32/D54 -> 0.13094725 | E70: =+E32/E54 -> 0.090519308 | F70: =+F32/F54 -> 0.15029517 | G70: =+G32/G54 -> 0.1275607 | H70: =+H32/H54 -> 0.11410547 | I70: =+I32/I54 -> 0.077481204 | ... AK70: =+AK32/AK54 -> 0.043750613 | AL70: =+AH70 -> 0.057263071 | AM70: =+AI70 -> 0.071600849 | AN70: =+AJ70 -> 0.053553414 | AO70: =+AK70 -> 0.043750613 | AP70: =+AL70 -> 0.057263071 | AQ70: =+AM70 -> 0.071600849 | AR70: =+AN70 -> 0.053553414 | AS70: =+AO70 -> 0.043750613
A73: CFFO | B73: ='Cash Flow'!B22 -> 164.28832 | C73: ='Cash Flow'!C22 -> -156.90432 | D73: ='Cash Flow'!D22 -> 3.462 | E73: ='Cash Flow'!E22 -> 5.505 | F73: ='Cash Flow'!F22 -> 17.444 | G73: ='Cash Flow'!G22 -> 2.939 | H73: ='Cash Flow'!H22 -> -4.118 | I73: ='Cash Flow'!I22 -> 7.28 | ... AS73: ='Cash Flow'!AS22 -> 8.8000681 | AU73: =SUM(B73:E73) -> 16.351 | AV73: =SUM(F73:I73) -> 23.545 | AW73: =SUM(J73:M73) -> -10.683 | AX73: =SUM(N73:Q73) -> -5.842 | AY73: =SUM(R73:U73) -> 7.178 | AZ73: =SUM(V73:Y73) -> 11.871 | BA73: =SUM(Z73:AC73) -> 59.416 | BB73: =SUM(AD73:AG73) -> 115.2 | BC73: =SUM(AH73:AK73) -> 147.431 | BD73: =SUM(AL73:AO73) -> 122.85398 | BE73: =SUM(AP73:AS73) -> 164.28832
A74: Free Cash Flow | B74: ='Cash Flow'!B51 -> 143.56732 | C74: ='Cash Flow'!C51 -> -138.71732 | D74: ='Cash Flow'!D51 -> 2.424 | E74: ='Cash Flow'!E51 -> 3.763 | F74: ='Cash Flow'!F51 -> 16.363 | G74: ='Cash Flow'!G51 -> 1.948 | H74: ='Cash Flow'!H51 -> -5.223 | I74: ='Cash Flow'!I51 -> 0.874 | ... AS74: ='Cash Flow'!AS51 -> 0.66606806 | AU74: =SUM(B74:E74) -> 11.037 | AV74: =SUM(F74:I74) -> 13.962 | AW74: =SUM(J74:M74) -> -36.075 | AX74: =SUM(N74:Q74) -> -15.958 | AY74: =SUM(R74:U74) -> -3.312 | AZ74: =SUM(V74:Y74) -> 0.475 | BA74: =SUM(Z74:AC74) -> 54.317 | BB74: =SUM(AD74:AG74) -> 108.506 | BC74: =SUM(AH74:AK74) -> 131.91 | BD74: =SUM(AL74:AO74) -> 107.33298 | BE74: =SUM(AP74:AS74) -> 143.56732
A75: Consensus FCF | J75: ='Cash Flow'!J53 -> 11.064293 | K75: ='Cash Flow'!K53 -> -7.6260627 | L75: ='Cash Flow'!L53 -> -6.2091838 | M75: ='Cash Flow'!M53 -> 0.56065302 | N75: ='Cash Flow'!N53 -> 7.1408154 | O75: ='Cash Flow'!O53 -> -15.645371 | P75: ='Cash Flow'!P53 -> -7.5817996 | Q75: ='Cash Flow'!Q53 -> 7.4436229 | ... AS75: ='Cash Flow'!AS53 -> 34.535039 | AU75: ='Cash Flow'!AU53 -> 11.581281 | AV75: ='Cash Flow'!AV53 -> 16.386978 | AW75: ='Cash Flow'!AW53 -> -18.336755 | AX75: ='Cash Flow'!AX53 -> -14.018677 | AY75: ='Cash Flow'!AY53 -> 7.596519 | AZ75: ='Cash Flow'!AZ53 -> 5.282257 | BA75: ='Cash Flow'!BA53 -> 45.055911 | BB75: ='Cash Flow'!BB53 -> 97.650208 | ... BE75: ='Cash Flow'!BE53 -> 156.74824
A76: Free Cash Flow Margin | R76: ='Cash Flow'!R58 -> 0.25763188 | S76: ='Cash Flow'!S58 -> -0.1161302 | T76: ='Cash Flow'!T58 -> -0.062569131 | U76: ='Cash Flow'!U58 -> -0.047654411 | V76: ='Cash Flow'!V58 -> 0.21864514 | W76: ='Cash Flow'!W58 -> -0.15348862 | X76: ='Cash Flow'!X58 -> -0.02544847 | Y76: ='Cash Flow'!Y58 -> -0.0022998661 | ... AS76: ='Cash Flow'!AS58 -> 0.0028478543 | AY76: ='Cash Flow'!AY58 -> -0.0084893908 | AZ76: ='Cash Flow'!AZ58 -> 0.0010028841 | BA76: ='Cash Flow'!BA58 -> 0.10881681 | BB76: ='Cash Flow'!BB58 -> 0.19694346 | BC76: ='Cash Flow'!BC58 -> 0.2115529 | BD76: ='Cash Flow'!BD58 -> 0.14801779 | BE76: ='Cash Flow'!BE58 -> 0.16229271
A78: Billings | B78: ='[2]Revenue Build_old'!B69 -> 36.39 | C78: ='[2]Revenue Build_old'!C69 -> 51.94 | D78: ='[2]Revenue Build_old'!D69 -> 55.449 | E78: ='[2]Revenue Build_old'!E69 -> 90.871 | F78: ='[2]Revenue Build_old'!F69 -> 46.956 | G78: ='[2]Revenue Build_old'!G69 -> 65.399 | H78: ='[2]Revenue Build_old'!H69 -> 68.033 | I78: ='[2]Revenue Build_old'!I69 -> 102.816 | ... AK78: ='[2]Revenue Build_old'!AK69 -> 249.7547 | AL78: ='Revenue Build'!AL76 -> 158.97078 | AM78: ='Revenue Build'!AM76 -> 235.2252 | AN78: ='Revenue Build'!AN76 -> 204.51111 | AO78: ='Revenue Build'!AO76 -> 301.4858 | AP78: ='Revenue Build'!AP76 -> 182.8164 | AQ78: ='Revenue Build'!AQ76 -> 270.50898 | AR78: ='Revenue Build'!AR76 -> 235.18778 | AS78: ='Revenue Build'!AS76 -> 346.70867
A79: Change in deferred | B79: ='[2]Revenue Build_old'!B68 -> -3.203 | C79: ='[2]Revenue Build_old'!C68 -> 2.509 | D79: ='[2]Revenue Build_old'!D68 -> 2.084 | E79: ='[2]Revenue Build_old'!E68 -> 17.87 | F79: ='[2]Revenue Build_old'!F68 -> -6.572 | G79: ='[2]Revenue Build_old'!G68 -> 3.209 | H79: ='[2]Revenue Build_old'!H68 -> 0.981 | I79: ='[2]Revenue Build_old'!I68 -> 15.298 | ... AK79: ='[2]Revenue Build_old'!AK68 -> 81.813671 | AL79: ='Revenue Build'!AL75 -> -6.368086 | AM79: ='Revenue Build'!AM75 -> 59.314501 | AN79: ='Revenue Build'!AN75 -> 18.14976 | AO79: ='Revenue Build'!AO75 -> 103.96103 | AP79: ='Revenue Build'!AP75 -> -26.003064 | AQ79: ='Revenue Build'!AQ75 -> 53.915863 | AR79: ='Revenue Build'!AR75 -> 9.864912 | AS79: ='Revenue Build'!AS75 -> 112.82449
A80: Ending deferred balance, total deferred revenue | B80: ='[2]Revenue Build_old'!B67 -> 58.837 | C80: ='[2]Revenue Build_old'!C67 -> 61.346 | D80: ='[2]Revenue Build_old'!D67 -> 63.43 | E80: ='[2]Revenue Build_old'!E67 -> 81.3 | F80: ='[2]Revenue Build_old'!F67 -> 74.728 | G80: ='[2]Revenue Build_old'!G67 -> 77.937 | H80: ='[2]Revenue Build_old'!H67 -> 78.918 | I80: ='[2]Revenue Build_old'!I67 -> 94.216 | ... AK80: ='[2]Revenue Build_old'!AK67 -> 418.48764 | AL80: ='Revenue Build'!AL74 -> 435.84891 | AM80: ='Revenue Build'!AM74 -> 495.16341 | AN80: ='Revenue Build'!AN74 -> 513.31317 | AO80: ='Revenue Build'!AO74 -> 617.27421 | AP80: ='Revenue Build'!AP74 -> 591.27114 | AQ80: ='Revenue Build'!AQ74 -> 645.18701 | AR80: ='Revenue Build'!AR74 -> 655.05192 | AS80: ='Revenue Build'!AS74 -> 767.87641
A82: Short term deferred as % of deferred mix | B82: =B24/B80 -> 0.92757958 | C82: =C24/C80 -> 0.93660548 | D82: =D24/D80 -> 0.92043197 | E82: =E24/E80 -> 0.90397294 | F82: =F24/F80 -> 0.91640349 | G82: =G24/G80 -> 0.91949908 | H82: =H24/H80 -> 0.91923262 | I82: =I24/I80 -> 0.93114758 | ... AK82: =AK24/AK80 -> 1.0222787 | AL82: =AK82 -> 1.0222787 | AM82: =AL82 -> 1.0222787 | AN82: =AM82 -> 1.0222787 | AO82: =AN82 -> 1.0222787 | AP82: =AO82 -> 1.0222787 | AQ82: =AP82 -> 1.0222787 | AR82: =AQ82 -> 1.0222787 | AS82: =AR82 -> 1.0222787
A83: Long term deferred as % of deferred mix | B83: =B31/B80 -> 0.072420416 | C83: =C31/C80 -> 0.063394516 | D83: =D31/D80 -> 0.079568028 | E83: =E31/E80 -> 0.09602706 | F83: =F31/F80 -> 0.08359651 | G83: =G31/G80 -> 0.080500917 | H83: =H31/H80 -> 0.080767379 | I83: =I31/I80 -> 0.068852424 | ... AK83: =AK31/AK80 -> 0.034423955 | AL83: =1-AL82 -> -0.022278689 | AM83: =1-AM82 -> -0.022278689 | AN83: =1-AN82 -> -0.022278689 | AO83: =1-AO82 -> -0.022278689 | AP83: =1-AP82 -> -0.022278689 | AQ83: =1-AQ82 -> -0.022278689 | AR83: =1-AR82 -> -0.022278689 | AS83: =1-AS82 -> -0.022278689
A84: Source: Company data, Wells Fargo Securities, LLC estimates

Sheet Cash Flow
A1: =+'Income Statement'!A1 -> Varonis Systems, Inc. (VRNS)
A2: Statement of Cash Flows | N2: ='Income Statement'!N2 -> 2019/1F | O2: ='Income Statement'!O2 -> 2019/2F | P2: ='Income Statement'!P2 -> 2019/3F | Q2: ='Income Statement'!Q2 -> 2019/4F | R2: ='Income Statement'!R2 -> 2021/1F | S2: ='Income Statement'!S2 -> 2021/2F | T2: ='Income Statement'!T2 -> 2021/3F | U2: ='Income Statement'!U2 -> 2021/4F | ... AS2: ='Income Statement'!AS2 -> 2027/4F | AU2: =+'Income Statement'!AU2 -> 2017 | AV2: =+'Income Statement'!AV2 -> 2018 | AW2: =+'Income Statement'!AW2 -> 2019 | AX2: ='Income Statement'!AX2 -> 2020 | AY2: ='Income Statement'!AY2 -> 2021 | AZ2: ='Income Statement'!AZ2 -> 2022 | BA2: ='Income Statement'!BA2 -> 2023 | BB2: ='Income Statement'!BB2 -> 2024 | BC2: ='Income Statement'!BC2 -> 2025 | BD2: ='Income Statement'!BD2 -> 2026 | BE2: ='Income Statement'!BE2 -> 2027 | BG2: INPUTS | BK2: INPUTS | BO2: INPUTS | BS2: INPUTS | BW2: INPUTS | CA2: INPUTS | CE2: INPUTS | CI2: INPUTS | CM2: INPUTS
B3: ='Income Statement'!B3 -> 2017 | F3: ='Income Statement'!F3 -> 2018 | J3: ='Income Statement'!J3 -> 2019 | N3: ='Income Statement'!N3 -> 2020 | R3: ='Income Statement'!R3 -> 2021 | V3: ='Income Statement'!V3 -> 2022 | Z3: ='Income Statement'!Z3 -> 2023 | AD3: ='Income Statement'!AD3 -> 2024 | AH3: ='Income Statement'!AH3 -> 2025 | AL3: ='Income Statement'!AL3 -> 2026 | AP3: ='Income Statement'!AP3 -> 2027 | BG3: 2017 | BK3: 2018 | BO3: 2019 | BS3: 2020 | BW3: 2021 | CA3: 2022 | CE3: 2023 | CI3: 2024 | CM3: 2025
A4: ='Income Statement'!A4 -> ($ in millions, unless otherwise stated) | B4: ='Income Statement'!B4 -> 42825 | C4: ='Income Statement'!C4 -> 42916 | D4: ='Income Statement'!D4 -> 43008 | E4: ='Income Statement'!E4 -> 43100 | F4: ='Income Statement'!F4 -> 43190 | G4: ='Income Statement'!G4 -> 43281 | H4: ='Income Statement'!H4 -> 43373 | ... AS4: ='Income Statement'!AS4 -> Dec-27E | AU4: ='Income Statement'!AU4 -> 2017 | AV4: ='Income Statement'!AV4 -> 2018 | AW4: ='Income Statement'!AW4 -> 2019 | AX4: ='Income Statement'!AX4 -> 2020 | AY4: ='Income Statement'!AY4 -> 2021 | AZ4: ='Income Statement'!AZ4 -> 2022 | BA4: ='Income Statement'!BA4 -> 2023 | BB4: ='Income Statement'!BB4 -> 2024 | ... BE4: ='Income Statement'!BE4 -> 2027E | BG4: =B4 -> 42825 | BH4: =C4 -> 42916 | BI4: =D4 -> 43008 | BJ4: =E4 -> 43100 | BK4: =F4 -> 43190 | BL4: =G4 -> 43281 | BM4: =H4 -> 43373 | BN4: =I4 -> 43465 | ... CP4: =AK4 -> Dec-25
A5: CASH FLOWS FROM OPERATING ACTIVITIES:
A6: Net income (loss) | B6: =BE6 -> -149.64499 | C6: =BH6-BE6 -> 132.24499 | D6: =BI6-BH6 -> -3.264 | E6: =BJ6-BI6 -> 6.82 | F6: =BK6 -> -15.046 | G6: =BL6-BK6 -> -12.683 | H6: =BM6-BL6 -> -7.317 | I6: =BN6-BM6 -> 6.468 | J6: =BO6 -> -22.639 | K6: =BP6-BO6 -> -24.488 | L6: =BQ6-BP6 -> -16.987 | M6: =BR6-BQ6 -> -14.65 | N6: =BS6 -> -31.43 | O6: =BT6-BS6 -> -24.323 | P6: =BU6-BT6 -> -19.225 | Q6: =BV6-BU6 -> -19.032 | R6: =BW6 -> -35.656 | S6: =BX6-BW6 -> -32.948 | T6: =BY6-BX6 -> -23.314 | U6: =BZ6-BY6 -> -24.943 | V6: =CA6 -> -48.763 | W6: =CB6-CA6 -> -36.29 | X6: =CC6-CB6 -> -28.717 | Y6: =CD6-CC6 -> -10.748 | Z6: =CE6 -> -38.304 | AA6: =CF6-CE6 -> -38.697 | AB6: =CG6-CF6 -> -23.017 | AC6: =CH6-CG6 -> -0.898 | AD6: =CI6 -> -40.49 | AE6: =CJ6-CI6 -> -23.948 | AF6: =CK6-CJ6 -> -18.333 | AG6: =CL6-CK6 -> -12.994 | AH6: =CM6 -> -35.783 | AI6: =CN6-CM6 -> -35.824 | AJ6: =CO6-CN6 -> -29.942 | AK6: =CP6-CO6 -> -27.775 | AL6: ='Income Statement'!AL92 -> -53.148239 | AM6: ='Income Statement'!AM92 -> -39.52982 | AN6: ='Income Statement'!AN92 -> -38.734085 | AO6: ='Income Statement'!AO92 -> -34.891474 | AP6: ='Income Statement'!AP92 -> -52.463994 | AQ6: ='Income Statement'!AQ92 -> -39.401505 | AR6: ='Income Statement'!AR92 -> -32.438205 | AS6: ='Income Statement'!AS92 -> -25.341282 | AU6: =SUM(B6:E6) -> -13.844 | AV6: =SUM(F6:I6) -> -28.578 | AW6: =SUM(J6:M6) -> -78.764 | AX6: =SUM(N6:Q6) -> -94.01 | AY6: =SUM(R6:U6) -> -116.861 | AZ6: =SUM(V6:Y6) -> -124.518 | BA6: =SUM(Z6:AC6) -> -100.916 | BB6: =SUM(AD6:AG6) -> -95.765 | BC6: =SUM(AH6:AK6) -> -129.324 | BD6: =SUM(AL6:AO6) -> -166.30362 | BE6: =SUM(AP6:AS6) -> -149.64499 | BG6: -11.663 | BH6: -17.4 | BI6: -20.664 | BJ6: -13.844 | BK6: -15.046 | BL6: -27.729 | BM6: -35.046 | BN6: -28.578 | BO6: -22.639 | BP6: -47.127 | BQ6: -64.114 | BR6: -78.764 | BS6: -31.43 | BT6: -55.753 | BU6: -74.978 | BV6: -94.01 | BW6: -35.656 | BX6: -68.604 | BY6: -91.918 | BZ6: -116.861 | CA6: -48.763 | CB6: -85.053 | CC6: -113.77 | CD6: -124.518 | CE6: -38.304 | CF6: -77.001 | CG6: -100.018 | CH6: -100.916 | CI6: -40.49 | CJ6: -64.438 | CK6: -82.771 | CL6: -95.765 | CM6: -35.783 | CN6: -71.607 | CO6: -101.549 | CP6: -129.324
A7: Depreciation and amortization | B7: =BE7 -> 22.17047 | C7: =BH7-BE7 -> -20.88647 | D7: =BI7-BH7 -> 0.686 | E7: =BJ7-BI7 -> 1.358 | F7: =BK7 -> 0.797 | G7: =BL7-BK7 -> 0.829 | H7: =BM7-BL7 -> 0.854 | I7: =BN7-BM7 -> 1.676 | J7: =BO7 -> 1.337 | K7: =BP7-BO7 -> 1.479 | L7: =BQ7-BP7 -> 1.504 | M7: =BR7-BQ7 -> 2.001 | N7: =BS7 -> 2.098 | O7: =BT7-BS7 -> 2.11 | P7: =BU7-BT7 -> 3.111 | Q7: =BV7-BU7 -> 2.584 | R7: =BW7 -> 2.349 | S7: =BX7-BW7 -> 3.107 | T7: =BY7-BX7 -> 2.815 | U7: =BZ7-BY7 -> 2.617 | V7: =CA7 -> 2.679 | W7: =CB7-CA7 -> 2.498 | X7: =CC7-CB7 -> 2.948 | Y7: =CD7-CC7 -> 4.051 | Z7: =CE7 -> 2.891 | AA7: =CF7-CE7 -> 2.916 | AB7: =CG7-CF7 -> 2.929 | AC7: =CH7-CG7 -> 2.967 | AD7: =CI7 -> 2.909 | AE7: =CJ7-CI7 -> 2.858 | AF7: =CK7-CJ7 -> 2.776 | AG7: =CL7-CK7 -> 2.583 | AH7: =CM7 -> 2.419 | AI7: =CN7-CM7 -> 2.569 | AJ7: =CO7-CN7 -> 2.976 | AK7: =CP7-CO7 -> 4.345 | AL7: =AL79 -> 4.1437476 | AM7: =AM79 -> 4.4087004 | AN7: =AN79 -> 4.6706162 | AO7: =AO79 -> 4.9503955 | AP7: =AP79 -> 5.2334648 | AQ7: =AQ79 -> 5.4282893 | AR7: =AR79 -> 5.6470756 | AS7: =AS79 -> 5.8616405 | AU7: =SUM(B7:E7) -> 3.328 | AV7: =SUM(F7:I7) -> 4.156 | AW7: =SUM(J7:M7) -> 6.321 | AX7: =SUM(N7:Q7) -> 9.903 | AY7: =SUM(R7:U7) -> 10.888 | AZ7: =SUM(V7:Y7) -> 12.176 | BA7: =SUM(Z7:AC7) -> 11.703 | BB7: =SUM(AD7:AG7) -> 11.126 | BC7: =SUM(AH7:AK7) -> 12.309 | BD7: =SUM(AL7:AO7) -> 18.17346 | BE7: =SUM(AP7:AS7) -> 22.17047 | BG7: 0.622 | BH7: 1.284 | BI7: 1.97 | BJ7: 3.328 | BK7: 0.797 | BL7: 1.626 | BM7: 2.48 | BN7: 4.156 | BO7: 1.337 | BP7: 2.816 | BQ7: 4.32 | BR7: 6.321 | BS7: 2.098 | BT7: 4.208 | BU7: 7.319 | BV7: 9.903 | BW7: 2.349 | BX7: 5.456 | BY7: 8.271 | BZ7: 10.888 | CA7: 2.679 | CB7: 5.177 | CC7: 8.125 | CD7: 12.176 | CE7: 2.891 | CF7: 5.807 | CG7: 8.736 | CH7: 11.703 | CI7: 2.909 | CJ7: 5.767 | CK7: 8.543 | CL7: 11.126 | CM7: 2.419 | CN7: 4.988 | CO7: 7.964 | CP7: 12.309
A8: Stock based compensation | B8: =BE8 -> 167.82212 | C8: =BH8-BE8 -> -158.15912 | D8: =BI8-BH8 -> 4.782 | E8: =BJ8-BI8 -> 5.39 | F8: =BK8 -> 6.927 | G8: =BL8-BK8 -> 8.848 | H8: =BM8-BL8 -> 8.399 | I8: =BN8-BM8 -> 10.787 | J8: =BO8 -> 8.961 | K8: =BP8-BO8 -> 14.796 | L8: =BQ8-BP8 -> 11.022 | M8: =BR8-BQ8 -> 11.36 | N8: =BS8 -> 12.883 | O8: =BT8-BS8 -> 17.623 | P8: =BU8-BT8 -> 18.678 | Q8: =BV8-BU8 -> 19.401 | R8: =BW8 -> 21.379 | S8: =BX8-BW8 -> 25.868 | T8: =BY8-BX8 -> 24.422 | U8: =BZ8-BY8 -> 38.11 | V8: =CA8 -> 35.998 | W8: =CB8-CA8 -> 37.758 | X8: =CC8-CB8 -> 34.3 | Y8: =CD8-CC8 -> 34.806 | Z8: =CE8 -> 35.811 | AA8: =CF8-CE8 -> 39.385 | AB8: =CG8-CF8 -> 32.98 | AC8: =CH8-CG8 -> 31.643 | AD8: =CI8 -> 32.093 | AE8: =CJ8-CI8 -> 30.089 | AF8: =CK8-CJ8 -> 31.931 | AG8: =CL8-CK8 -> 32.569 | AH8: =CM8 -> 32.255 | AI8: =CN8-CM8 -> 33.859 | AJ8: =CO8-CN8 -> 31.55 | AK8: =CP8-CO8 -> 32.578 | AL8: ='Income Statement'!AL76 -> 37.438298 | AM8: ='Income Statement'!AM76 -> 37.384183 | AN8: ='Income Statement'!AN76 -> 34.525852 | AO8: ='Income Statement'!AO76 -> 35.141895 | AP8: ='Income Statement'!AP76 -> 45.195577 | AQ8: ='Income Statement'!AQ76 -> 43.863996 | AR8: ='Income Statement'!AR76 -> 39.490748 | AS8: ='Income Statement'!AS76 -> 39.271804 | AU8: =SUM(B8:E8) -> 19.835 | AV8: =SUM(F8:I8) -> 34.961 | AW8: =SUM(J8:M8) -> 46.139 | AX8: =SUM(N8:Q8) -> 68.585 | AY8: =SUM(R8:U8) -> 109.779 | AZ8: =SUM(V8:Y8) -> 142.862 | BA8: =SUM(Z8:AC8) -> 139.819 | BB8: =SUM(AD8:AG8) -> 126.682 | BC8: =SUM(AH8:AK8) -> 130.242 | BD8: =SUM(AL8:AO8) -> 144.49023 | BE8: =SUM(AP8:AS8) -> 167.82212 | BG8: 4.404 | BH8: 9.663 | BI8: 14.445 | BJ8: 19.835 | BK8: 6.927 | BL8: 15.775 | BM8: 24.174 | BN8: 34.961 | BO8: 8.961 | BP8: 23.757 | BQ8: 34.779 | BR8: 46.139 | BS8: 12.883 | BT8: 30.506 | BU8: 49.184 | BV8: 68.585 | BW8: 21.379 | BX8: 47.247 | BY8: 71.669 | BZ8: 109.779 | CA8: 35.998 | CB8: 73.756 | CC8: 108.056 | CD8: 142.862 | CE8: 35.811 | CF8: 75.196 | CG8: 108.176 | CH8: 139.819 | CI8: 32.093 | CJ8: 62.182 | CK8: 94.113 | CL8: 126.682 | CM8: 32.255 | CN8: 66.114 | CO8: 97.664 | CP8: 130.242
A9: Amortization of deferred commissions | B9: =BE9 -> 51.848 | C9: =BH9-BE9 -> -45.807 | D9: =BI9-BH9 -> 3.251 | E9: =BJ9-BI9 -> 3.299 | F9: =BK9 -> 3.325 | G9: =BL9-BK9 -> 3.116 | H9: =BM9-BL9 -> 3.277 | I9: =BN9-BM9 -> 3.467 | J9: =BO9 -> 3.626 | K9: =BP9-BO9 -> 3.51 | L9: =BQ9-BP9 -> 3.394 | M9: =BR9-BQ9 -> 3.1 | N9: =BS9 -> 3.249 | O9: =BT9-BS9 -> 2.534 | P9: =BU9-BT9 -> 3.769 | Q9: =BV9-BU9 -> 3.554 | R9: =BW9 -> 4.157 | S9: =BX9-BW9 -> 3.912 | T9: =BY9-BX9 -> 3.442 | U9: =BZ9-BY9 -> 2.636 | V9: =CA9 -> 6.12 | W9: =CB9-CA9 -> 5.766 | X9: =CC9-CB9 -> 5.312 | Y9: =CD9-CC9 -> 5.066 | Z9: =CE9 -> 3.462 | AA9: =CF9-CE9 -> 9.062 | AB9: =CG9-CF9 -> 5.023 | AC9: =CH9-CG9 -> 3.984 | AD9: =CI9 -> 7.932 | AE9: =CJ9-CI9 -> 6.566 | AF9: =CK9-CJ9 -> 5.408 | AG9: =CL9-CK9 -> 34.486 | AH9: =CM9 -> 11.353 | AI9: =CN9-CM9 -> 13.788 | AJ9: =CO9-CN9 -> 13.817 | AK9: =CP9-CO9 -> 12.962 | AL9: =AK9 -> 12.962 | AM9: =AL9 -> 12.962 | AN9: =AM9 -> 12.962 | AO9: =AN9 -> 12.962 | AP9: =AO9 -> 12.962 | AQ9: =AP9 -> 12.962 | AR9: =AQ9 -> 12.962 | AS9: =AR9 -> 12.962 | AU9: =SUM(B9:E9) -> 12.591 | AV9: =SUM(F9:I9) -> 13.185 | AW9: =SUM(J9:M9) -> 13.63 | AX9: =SUM(N9:Q9) -> 13.106 | AY9: =SUM(R9:U9) -> 14.147 | AZ9: =SUM(V9:Y9) -> 22.264 | BA9: =SUM(Z9:AC9) -> 21.531 | BB9: =SUM(AD9:AG9) -> 54.392 | BC9: =SUM(AH9:AK9) -> 51.92 | BD9: =SUM(AL9:AO9) -> 51.848 | BE9: =SUM(AP9:AS9) -> 51.848 | BG9: 3.027 | BH9: 6.041 | BI9: 9.292 | BJ9: 12.591 | BK9: 3.325 | BL9: 6.441 | BM9: 9.718 | BN9: 13.185 | BO9: 3.626 | BP9: 7.136 | BQ9: 10.53 | BR9: 13.63 | BS9: 3.249 | BT9: 5.783 | BU9: 9.552 | BV9: 13.106 | BW9: 4.157 | BX9: 8.069 | BY9: 11.511 | BZ9: 14.147 | CA9: 6.12 | CB9: 11.886 | CC9: 17.198 | CD9: 22.264 | CE9: 3.462 | CF9: 12.524 | CG9: 17.547 | CH9: 21.531 | CI9: 7.932 | CJ9: 14.498 | CK9: 19.906 | CL9: 54.392 | CM9: 11.353 | CN9: 25.141 | CO9: 38.958 | CP9: 51.92
A10: Noncash operating lease cost | B10: =BE10 -> 10.468 | C10: =BH10-BE10 -> -10.468 | D10: =BI10-BH10 -> 0 | E10: =BJ10-BI10 -> 0 | F10: =BK10 -> 0 | G10: =BL10-BK10 -> 0 | H10: =BM10-BL10 -> 0 | I10: =BN10-BM10 -> 0 | J10: =BO10 -> 1.399 | K10: =BP10-BO10 -> 1.438 | L10: =BQ10-BP10 -> 4.172 | M10: =BR10-BQ10 -> 2.014 | N10: =BS10 -> 1.96 | O10: =BT10-BS10 -> 3.03 | P10: =BU10-BT10 -> 2.236 | Q10: =BV10-BU10 -> 1.511 | R10: =BW10 -> 2.242 | S10: =BX10-BW10 -> 1.969 | T10: =BY10-BX10 -> 1.99 | U10: =BZ10-BY10 -> 2.031 | V10: =CA10 -> 2.326 | W10: =CB10-CA10 -> 2.32 | X10: =CC10-CB10 -> 2.328 | Y10: =CD10-CC10 -> 2.331 | Z10: =CE10 -> 2.367 | AA10: =CF10-CE10 -> 2.364 | AB10: =CG10-CF10 -> 2.356 | AC10: =CH10-CG10 -> 2.381 | AD10: =CI10 -> 2.394 | AE10: =CJ10-CI10 -> 2.328 | AF10: =CK10-CJ10 -> 2.328 | AG10: =CL10-CK10 -> 2.476 | AH10: =CM10 -> 2.476 | AI10: =CN10-CM10 -> 2.476 | AJ10: =CO10-CN10 -> 2.49 | AK10: =CP10-CO10 -> 2.617 | AL10: =AK10 -> 2.617 | AM10: =AL10 -> 2.617 | AN10: =AM10 -> 2.617 | AO10: =AN10 -> 2.617 | AP10: =AO10 -> 2.617 | AQ10: =AP10 -> 2.617 | AR10: =AQ10 -> 2.617 | AS10: =AR10 -> 2.617 | AU10: =SUM(B10:E10) -> 0 | AV10: =SUM(F10:I10) -> 0 | AW10: =SUM(J10:M10) -> 9.023 | AX10: =SUM(N10:Q10) -> 8.737 | AY10: =SUM(R10:U10) -> 8.232 | AZ10: =SUM(V10:Y10) -> 9.305 | BA10: =SUM(Z10:AC10) -> 9.468 | BB10: =SUM(AD10:AG10) -> 9.526 | BC10: =SUM(AH10:AK10) -> 10.059 | BD10: =SUM(AL10:AO10) -> 10.468 | BE10: =SUM(AP10:AS10) -> 10.468 | BG10: 0 | BH10: 0 | BI10: 0 | BJ10: 0 | BK10: 0 | BL10: 0 | BM10: 0 | BN10: 0 | BO10: 1.399 | BP10: 2.837 | BQ10: 7.009 | BR10: 9.023 | BS10: 1.96 | BT10: 4.99 | BU10: 7.226 | BV10: 8.737 | BW10: 2.242 | BX10: 4.211 | BY10: 6.201 | BZ10: 8.232 | CA10: 2.326 | CB10: 4.646 | CC10: 6.974 | CD10: 9.305 | CE10: 2.367 | CF10: 4.731 | CG10: 7.087 | CH10: 9.468 | CI10: 2.394 | CJ10: 4.722 | CK10: 7.05 | CL10: 9.526 | CM10: 2.476 | CN10: 4.952 | CO10: 7.442 | CP10: 10.059
A11: Amortiztion of debt discount and issuance costs | B11: =BE11 -> 2.02 | C11: =BH11-BE11 -> -2.02 | D11: =BI11-BH11 -> 0 | E11: =BJ11-BI11 -> 0 | F11: =BK11 -> 0 | G11: =BL11-BK11 -> 0 | H11: =BM11-BL11 -> 0 | I11: =BN11-BM11 -> 0 | J11: =BO11 -> 0 | K11: =BP11-BO11 -> 0 | L11: =BQ11-BP11 -> 0 | M11: =BR11-BQ11 -> 0 | N11: =BS11 -> 0 | O11: =BT11-BS11 -> 0.78 | P11: =BU11-BT11 -> 1.647 | Q11: =BV11-BU11 -> 1.669 | R11: =BW11 -> 1.689 | S11: =BX11-BW11 -> 1.708 | T11: =BY11-BX11 -> 1.727 | U11: =BZ11-BY11 -> 1.746 | V11: =CA11 -> 0.37 | W11: =CB11-CA11 -> 0.37 | X11: =CC11-CB11 -> 0.373 | Y11: =CD11-CC11 -> 0.373 | Z11: =CE11 -> 0.376 | AA11: =CF11-CE11 -> 0.378 | AB11: =CG11-CF11 -> 0.379 | AC11: =CH11-CG11 -> 0.381 | AD11: =CI11 -> 0.383 | AE11: =CJ11-CI11 -> 0.385 | AF11: =CK11-CJ11 -> 0.496 | AG11: =CL11-CK11 -> 0.88 | AH11: =CM11 -> 0.887 | AI11: =CN11-CM11 -> 0.887 | AJ11: =CO11-CN11 -> 0.697 | AK11: =CP11-CO11 -> 0.505 | AL11: =AK11 -> 0.505 | AM11: =AL11 -> 0.505 | AN11: =AM11 -> 0.505 | AO11: =AN11 -> 0.505 | AP11: =AO11 -> 0.505 | AQ11: =AP11 -> 0.505 | AR11: =AQ11 -> 0.505 | AS11: =AR11 -> 0.505 | AU11: =SUM(B11:E11) -> 0 | AV11: =SUM(F11:I11) -> 0 | AW11: =SUM(J11:M11) -> 0 | AX11: =SUM(N11:Q11) -> 4.096 | AY11: =SUM(R11:U11) -> 6.87 | AZ11: =SUM(V11:Y11) -> 1.486 | BA11: =SUM(Z11:AC11) -> 1.514 | BB11: =SUM(AD11:AG11) -> 2.144 | BC11: =SUM(AH11:AK11) -> 2.976 | BD11: =SUM(AL11:AO11) -> 2.02 | BE11: =SUM(AP11:AS11) -> 2.02 | BG11: 0 | BH11: 0 | BI11: 0 | BJ11: 0 | BK11: 0 | BL11: 0 | BM11: 0 | BN11: 0 | BO11: 0 | BP11: 0 | BQ11: 0 | BR11: 0 | BS11: 0 | BT11: 0.78 | BU11: 2.427 | BV11: 4.096 | BW11: 1.689 | BX11: 3.397 | BY11: 5.124 | BZ11: 6.87 | CA11: 0.37 | CB11: 0.74 | CC11: 1.113 | CD11: 1.486 | CE11: 0.376 | CF11: 0.754 | CG11: 1.133 | CH11: 1.514 | CI11: 0.383 | CJ11: 0.768 | CK11: 1.264 | CL11: 2.144 | CM11: 0.887 | CN11: 1.774 | CO11: 2.471 | CP11: 2.976
A12: Other | B12: =BE12 -> 3.212 | C12: =BH12-BE12 -> -3.214 | D12: =BI12-BH12 -> -0.012 | E12: =BJ12-BI12 -> -0.006 | F12: =BK12 -> 0 | G12: =BL12-BK12 -> -0.002 | H12: =BM12-BL12 -> -0.025 | I12: =BN12-BM12 -> 0 | J12: =BO12 -> 0.024 | K12: =BP12-BO12 -> 0 | L12: =BQ12-BP12 -> 0 | M12: =BR12-BQ12 -> 0.021 | N12: =BS12 -> 0 | O12: =BT12-BS12 -> 0 | P12: =BU12-BT12 -> 0 | Q12: =BV12-BU12 -> 0 | R12: =BW12 -> 0 | S12: =BX12-BW12 -> 0 | T12: =BY12-BX12 -> 0 | U12: =BZ12-BY12 -> 0 | V12: =CA12 -> 0 | W12: =CB12-CA12 -> 0 | X12: =CC12-CB12 -> -0.021 | Y12: =CD12-CC12 -> -0.344 | Z12: =CE12 -> -1.293 | AA12: =CF12-CE12 -> -1.431 | AB12: =CG12-CF12 -> -2.833 | AC12: =CH12-CG12 -> -3.797 | AD12: =CI12 -> -3.743 | AE12: =CJ12-CI12 -> -3.868 | AF12: =CK12-CJ12 -> 2.976 | AG12: =CL12-CK12 -> -1.402 | AH12: =CM12 -> 0.099 | AI12: =CN12-CM12 -> 0.315 | AJ12: =CO12-CN12 -> 0.797 | AK12: =CP12-CO12 -> 0.803 | AL12: =AK12 -> 0.803 | AM12: =AL12 -> 0.803 | AN12: =AM12 -> 0.803 | AO12: =AN12 -> 0.803 | AP12: =AO12 -> 0.803 | AQ12: =AP12 -> 0.803 | AR12: =AQ12 -> 0.803 | AS12: =AR12 -> 0.803 | AU12: =SUM(B12:E12) -> -0.02 | AV12: =SUM(F12:I12) -> -0.027 | AW12: =SUM(J12:M12) -> 0.045 | AX12: =SUM(N12:Q12) -> 0 | AY12: =SUM(R12:U12) -> 0 | AZ12: =SUM(V12:Y12) -> -0.365 | BA12: =SUM(Z12:AC12) -> -9.354 | BB12: =SUM(AD12:AG12) -> -6.037 | BC12: =SUM(AH12:AK12) -> 2.014 | BD12: =SUM(AL12:AO12) -> 3.212 | BE12: =SUM(AP12:AS12) -> 3.212 | BG12: 0 | BH12: -0.002 | BI12: -0.014 | BJ12: -0.02 | BK12: 0 | BL12: -0.002 | BM12: -0.027 | BN12: -0.027 | BO12: 0.024 | BP12: 0.024 | BQ12: 0.024 | BR12: 0.045 | BS12: 0 | BT12: 0 | BU12: 0 | BV12: 0 | BW12: 0 | BX12: 0 | BY12: 0 | CA12: 0 | CB12: 0 | CC12: -0.021 | CD12: =-0.344-0.021 -> -0.365 | CE12: -1.293 | CF12: -2.724 | CG12: -5.557 | CH12: -9.354 | CI12: -3.743 | CJ12: -7.611 | CK12: =-11.288+6.653 -> -4.635 | CL12: =-12.69+6.653 -> -6.037 | CM12: 0.099 | CN12: 0.414 | CO12: 1.211 | CP12: =2.267-0.253 -> 2.014
A13: Changes to assets and liabilities
A14: Trade receivables | B14: =BE14 -> -45.478098 | C14: =BH14-BE14 -> 58.026098 | D14: =BI14-BH14 -> -3.367 | E14: =BJ14-BI14 -> -30.916 | F14: =BK14 -> 43.128 | G14: =BL14-BK14 -> -8.925 | H14: =BM14-BL14 -> -11.545 | I14: =BN14-BM14 -> -30.285 | J14: =BO14 -> 41.427 | K14: =BP14-BO14 -> -3.767 | L14: =BQ14-BP14 -> -6.303 | M14: =BR14-BQ14 -> -23.184 | N14: =BS14 -> 36.785 | O14: =BT14-BS14 -> -10.501 | P14: =BU14-BT14 -> -11.345 | Q14: =BV14-BU14 -> -34.014 | R14: =BW14 -> 42.927 | S14: =BX14-BW14 -> -8.843 | T14: =BY14-BX14 -> -11.237 | U14: =BZ14-BY14 -> -45.797 | V14: =CA14 -> 53.575 | W14: =CB14-CA14 -> -20.325 | X14: =CC14-CB14 -> -7.756 | Y14: =CD14-CC14 -> -44.294 | Z14: =CE14 -> 60.586 | AA14: =CF14-CE14 -> -28.275 | AB14: =CG14-CF14 -> -7.416 | AC14: =CH14-CG14 -> -58.032 | AD14: =CI14 -> 68.675 | AE14: =CJ14-CI14 -> -21.971 | AF14: =CK14-CJ14 -> 3.209 | AG14: =CL14-CK14 -> -73.629 | AH14: =CM14 -> 65.129 | AI14: =CN14-CM14 -> -26.125 | AJ14: =CO14-CN14 -> 7.53 | AK14: =CP14-CO14 -> -99.088 | AL14: ='Balance Sheet'!AK9-'Balance Sheet'!AL9 -> 93.049515 | AM14: ='Balance Sheet'!AL9-'Balance Sheet'!AM9 -> -23.294288 | AN14: ='Balance Sheet'!AM9-'Balance Sheet'!AN9 -> 8.5610164 | AO14: ='Balance Sheet'!AN9-'Balance Sheet'!AO9 -> -110.40543 | AP14: ='Balance Sheet'!AO9-'Balance Sheet'!AP9 -> 85.751732 | AQ14: ='Balance Sheet'!AP9-'Balance Sheet'!AQ9 -> -23.93203 | AR14: ='Balance Sheet'!AQ9-'Balance Sheet'!AR9 -> 14.193438 | AS14: ='Balance Sheet'!AR9-'Balance Sheet'!AS9 -> -121.49124 | AU14: =SUM(B14:E14) -> -21.735 | AV14: =SUM(F14:I14) -> -7.627 | AW14: =SUM(J14:M14) -> 8.173 | AX14: =SUM(N14:Q14) -> -19.075 | AY14: =SUM(R14:U14) -> -22.95 | AZ14: =SUM(V14:Y14) -> -18.8 | BA14: =SUM(Z14:AC14) -> -33.137 | BB14: =SUM(AD14:AG14) -> -23.716 | BC14: =SUM(AH14:AK14) -> -52.554 | BD14: =SUM(AL14:AO14) -> -32.089185 | BE14: =SUM(AP14:AS14) -> -45.478098 | BG14: 26.395 | BH14: 12.548 | BI14: 9.181 | BJ14: -21.735 | BK14: 43.128 | BL14: 34.203 | BM14: 22.658 | BN14: -7.627 | BO14: 41.427 | BP14: 37.66 | BQ14: 31.357 | BR14: 8.173 | BS14: 36.785 | BT14: 26.284 | BU14: 14.939 | BV14: -19.075 | BW14: 42.927 | BX14: 34.084 | BY14: 22.847 | BZ14: -22.95 | CA14: 53.575 | CB14: 33.25 | CC14: 25.494 | CD14: -18.8 | CE14: 60.586 | CF14: 32.311 | CG14: 24.895 | CH14: -33.137 | CI14: 68.675 | CJ14: 46.704 | CK14: 49.913 | CL14: -23.716 | CM14: 65.129 | CN14: 39.004 | CO14: 46.534 | CP14: -52.554
