Workbook
Name \P: #REF!
Name \P: #REF!
Name \P: #REF!
Name \P: #REF!
Name \Q: [1]TSFW!#REF!
Name \Q: [1]TSFW!#REF!
Name \Q: [1]TSFW!#REF!
Name \Q: [1]TSFW!#REF!
Name \S: '[2]US$'!#REF!
Name \S: '[2]US$'!#REF!
Name \X: [1]TSFW!#REF!
Name _1997: #REF!
Name _1997: #REF!
Name _1997: #REF!
Name _1997: #REF!
Name _1998: #REF!
Name _1998: #REF!
Name _1998: #REF!
Name _1999: #REF!
Name _1999: #REF!
Name _1999: #REF!
Name _1st_year: '[3]LINKS&INPUTS'!$D$52
Name _2000: #REF!
Name _2000: #REF!
Name _2000: #REF!
Name _2000: #REF!
Name _2000_EPS: #REF!
Name _2000_EPS: #REF!
Name _2000_EPS: #REF!
Name _2000_Rev: #REF!
Name _2000_Rev: #REF!
Name _2000_Rev: #REF!
Name _2001: #REF!
Name _2001_EPS: #REF!
Name _2001_Rev: #REF!
Name _2002: #REF!
Name _2002_EPS: #REF!
Name _2002_Rev: #REF!
Name _2003: #REF!
Name _2003_EPS: #REF!
Name _2003_Rev: #REF!
Name _2004: #REF!
Name _2004_EPS: #REF!
Name _2004_Rev: #REF!
Name _2005: #REF!
Name _2005_cfps: [4]NAV!#REF!
Name _2005_EPS: #REF!
Name _2005_EPS: #REF!
Name _2005_EPS: #REF!
Name _2005_EPS: #REF!
Name _2005_Rev: #REF!
Name _2005_Rev: #REF!
Name _2005_Rev: #REF!
Name _2006: #REF!
Name _2006: #REF!
Name _2006: #REF!
Name _2006_cfps: [4]NAV!#REF!
Name _2006_cfps: [4]NAV!#REF!
Name _2006_cfps: [4]NAV!#REF!
Name _2006_eps: [4]NAV!#REF!

Sheet __FDSCACHE__
B1: This sheet contains FactSet XML data for use with this workbook's =FDS codes. Modifying the worksheet's contents may damage the workbook's =FDS functionality.

Sheet Comparison
B2: =IS!B2 -> DocuSign, Inc (DOCU)
B4: Variance Analysis | D4: =IS!BO4 -> 3Q25 | E4: =K4 -> 3Q26 | F4: Y/Y Δ | G4: =IS!BS4 -> 2Q26 | H4: =K4 -> 3Q26 | I4: Q/Q Δ | J4: 3Q26E | K4: =IS!BT4 -> 3Q26 | L4: % Δ | N4: Variance | P4: 1Q Cons. | Q4: 2Q Guide | R4: 2Q Cons. | S4: FY G Prev | T4: FY G New | U4: Change | V4: FY Cons.
B5: Subscription Revenues | D5: =IS!BO5 -> 734693 | E5: =K5 -> 800958 | F5: =E5/D5-1 -> 0.090194136 | G5: =IS!BS5 -> 784388 | H5: =K5 -> 800958 | I5: =H5/G5-1 -> 0.021124749 | J5: 788325.59 | K5: =IS!BT5 -> 800958 | L5: =K5/J5-1 -> 0.016024357 | N5: =K5-J5 -> 12632.411 | P5: 564000 | Q5: =(583000+587000)/2 -> 585000 | R5: 581000 | S5: =(2394000+2406000)/2 -> 2400000 | T5: =(2394000+2406000)/2 -> 2400000 | U5: =IF(AND(ISNUMBER(T5), ISNUMBER(S5)), T5-S5, "-") -> 0 | V5: 2401000
B6: Professional Services | D6: =IS!BO9 -> 20127 | E6: =K6 -> 17392 | F6: =E6/D6-1 -> -0.13588712 | G6: =IS!BS9 -> 16248 | H6: =K6 -> 17392 | I6: =H6/G6-1 -> 0.070408666 | J6: 17913.03 | K6: =IS!BT9 -> 17392 | L6: =K6/J6-1 -> -0.029086648 | N6: =K6-J6 -> -521.03 | P6: 17000 | Q6: =Q7-Q5 -> 17000 | R6: 20000 | S6: =S7-S5 -> 76000 | T6: =T7-T5 -> 76000 | U6: =IF(AND(ISNUMBER(T6), ISNUMBER(S6)), T6-S6, "-") -> 0 | V6: 74000
B7: Total Revenue | D7: =D5+D6 -> 754820 | E7: =K7 -> 818350 | F7: =E7/D7-1 -> 0.084165761 | G7: =G5+G6 -> 800636 | H7: =K7 -> 818350 | I7: =H7/G7-1 -> 0.022124911 | J7: 806238.62 | K7: =K5+K6 -> 818350 | L7: =K7/J7-1 -> 0.01502208 | N7: =K7-J7 -> 12111.381 | P7: 583000 | Q7: =(600000+604000)/2 -> 602000 | R7: 601000 | S7: =(2470000+2482000)/2 -> 2476000 | T7: =(2470000+2482000)/2 -> 2476000 | U7: =IF(AND(ISNUMBER(T7), ISNUMBER(S7)), T7-S7, "-") -> 0 | V7: 2476000
B9: Cost of Revenue
B10: Subscription Revenues | D10: =IS!BO18 -> 115585 | E10: =K10 -> 132970 | F10: =E10/D10-1 -> 0.15040879 | G10: =IS!BS18 -> 126890 | H10: =K10 -> 132970 | I10: =H10/G10-1 -> 0.047915517 | J10: 137956.98 | K10: =IS!BT18 -> 132970 | L10: =K10/J10-1 -> -0.036148792
B11: Professional Services | D11: =IS!BO20 -> 16865 | E11: =K11 -> 15891 | F11: =E11/D11-1 -> -0.057752742 | G11: =IS!BS20 -> 16844 | H11: =K11 -> 15891 | I11: =H11/G11-1 -> -0.05657801 | J11: 16838.248 | K11: =IS!BT20 -> 15891 | L11: =K11/J11-1 -> -0.056255745
B12: Total Cost of Revenues | D12: =D10+D11 -> 132450 | E12: =K12 -> 148861 | F12: =E12/D12-1 -> 0.12390336 | G12: =G10+G11 -> 143734 | H12: =K12 -> 148861 | I12: =H12/G12-1 -> 0.035670057 | J12: 154795.23 | K12: =K10+K11 -> 148861 | L12: =K12/J12-1 -> -0.038335977
B14: Gross Profit | D14: =D7-D12 -> 622370 | E14: =K14 -> 669489 | F14: =E14/D14-1 -> 0.075708983 | G14: =G7-G12 -> 656902 | H14: =K14 -> 669489 | I14: =H14/G14-1 -> 0.019161153 | J14: 651443.39 | K14: =K7-K12 -> 669489 | L14: =K14/J14-1 -> 0.02770096 | N14: =K14-J14 -> 18045.607 | P14: 467000 | Q14: =Q15*Q7 -> 481600 | R14: 482000 | S14: =(1951000+2010000)/2 -> 1980500 | T14: =T15*T7 -> 1980800 | U14: =IF(AND(ISNUMBER(T14), ISNUMBER(S14)), T14-S14, "-") -> 300 | V14: 1971000
C15: Gross Margins | D15: =D14/D7 -> 0.8245277 | E15: =K15 -> 0.81809617 | G15: =G14/G7 -> 0.82047522 | H15: =K15 -> 0.81809617 | J15: 0.80800321 | K15: =K14/K7 -> 0.81809617 | N15: =K15-D15 -> -0.0064315328 | P15: =P14/P7 -> 0.80102916 | Q15: 0.8 | R15: =R14/R7 -> 0.80199667 | S15: =S14/S7 -> 0.79987884 | T15: 0.8 | V15: =V14/V7 -> 0.796042
B17: Operating Expenses
B18: S&M | D18: =IS!BO27 -> 236278 | E18: =K18 -> 242764 | F18: =E18/D18-1 -> 0.027450715 | G18: =IS!BS27 -> 250053 | H18: =K18 -> 242764 | I18: =H18/G18-1 -> -0.02914982 | J18: 253965.16 | K18: =IS!BT27 -> 242764 | L18: =K18/J18-1 -> -0.044105124 | N18: =K18-J18 -> -11201.165
B19: R&D | D19: =IS!BO29 -> 96644 | E19: =K19 -> 104902 | F19: =E19/D19-1 -> 0.085447622 | G19: =IS!BS29 -> 105165 | H19: =K19 -> 104902 | I19: =H19/G19-1 -> -0.002500832 | J19: 104811.02 | K19: =IS!BT29 -> 104902 | L19: =K19/J19-1 -> 0.00086803401 | N19: =K19-J19 -> 90.97953
B20: G&A | D20: =IS!BO31 -> 66372 | E20: =K20 -> 64771 | F20: =E20/D20-1 -> -0.024121618 | G20: =IS!BS31 -> 62955 | H20: =K20 -> 64771 | I20: =H20/G20-1 -> 0.028846001 | J20: 63692.851 | K20: =IS!BT31 -> 64771 | L20: =K20/J20-1 -> 0.016927317 | N20: =K20-J20 -> 1078.1491
B21: Total Operating Expenses | D21: =SUM(D18:D20) -> 399294 | E21: =K21 -> 412437 | F21: =E21/D21-1 -> 0.032915596 | G21: =SUM(G18:G20) -> 418173 | H21: =K21 -> 412437 | I21: =H21/G21-1 -> -0.013716811 | J21: 422469.04 | K21: =SUM(K18:K20) -> 412437 | L21: =K21/J21-1 -> -0.023746205 | N21: =K21-J21 -> -10032.036
B23: Non-GAAP Operating Income (Loss) | D23: =D14-D21 -> 223076 | E23: =K23 -> 257052 | F23: =E23/D23-1 -> 0.15230684 | G23: =G14-G21 -> 238729 | H23: =K23 -> 257052 | I23: =H23/G23-1 -> 0.076752301 | J23: 228974.36 | K23: =K14-K21 -> 257052 | L23: =K23/J23-1 -> 0.12262353 | N23: =K23-J23 -> 28077.644 | P23: 98000 | Q23: =Q24*Q7 -> 102340 | R23: 98000 | S23: =(395000+447000)/2 -> 421000 | T23: =T24*T7 -> 420920 | U23: =IF(AND(ISNUMBER(T23), ISNUMBER(S23)), T23-S23, "-") -> -80 | V23: 416000
C24: Non-GAAP Operating Margins | D24: =D23/D7 -> 0.29553536 | E24: =K24 -> 0.3141101 | G24: =G23/G7 -> 0.2981742 | H24: =K24 -> 0.3141101 | J24: 0.28400321 | K24: =K23/K7 -> 0.3141101 | P24: =P23/P7 -> 0.16809605 | Q24: 0.17 | R24: =R23/R7 -> 0.16306156 | S24: =S23/S7 -> 0.17003231 | T24: 0.17 | V24: =V23/V7 -> 0.16801292
B26: GAAP & Non-cash charges | D26: =IS!BO44 -> 164046 | E26: =K26 -> 171697 | F26: =E26/D26-1 -> 0.046639357 | G26: =IS!BS44 -> 173502 | H26: =K26 -> 171697 | I26: =H26/G26-1 -> -0.010403338 | J26: 160916 | K26: =IS!BT44 -> 171697 | L26: =K26/J26-1 -> 0.066997688
B28: GAAP Operating Income | D28: =D23-D26 -> 59030 | E28: =K28 -> 85355 | F28: =E28/D28-1 -> 0.44595968 | G28: =G23-G26 -> 65227 | H28: =K28 -> 85355 | I28: =H28/G28-1 -> 0.30858387 | J28: 68058.356 | K28: =K23-K26 -> 85355 | L28: =K28/J28-1 -> 0.2541443
C29: GAAP Operating Margins | D29: =D28/D7 -> 0.078204075 | E29: =K29 -> 0.10430134 | G29: =G28/G7 -> 0.081468982 | H29: =K29 -> 0.10430134 | J29: 0.084414657 | K29: =K28/K7 -> 0.10430134
B31: Non-GAAP Interest & Other Income (Expense) | D31: =IS!BO54 -> 12544 | E31: =K31 -> 10174 | F31: =E31/D31-1 -> -0.18893495 | G31: =IS!BS54 -> 11233 | H31: =K31 -> 10174 | I31: =H31/G31-1 -> -0.094275795 | J31: 11000 | K31: =IS!BT54 -> 10174 | L31: =K31/J31-1 -> -0.075090909
B32: GAAP Total Other Income (Expense) | D32: =IS!BO55 -> 12544 | E32: =K32 -> 10174 | F32: =E32/D32-1 -> -0.18893495 | G32: =IS!BS55 -> 11233 | H32: =K32 -> 10174 | I32: =H32/G32-1 -> -0.094275795 | J32: 11000 | K32: =IS!BT55 -> 10174 | L32: =K32/J32-1 -> -0.075090909
B34: Non-GAAP Income before Taxes | D34: =D23+D31 -> 235620 | E34: =K34 -> 267226 | F34: =E34/D34-1 -> 0.13413972 | G34: =G23+G31 -> 249962 | H34: =K34 -> 267226 | I34: =H34/G34-1 -> 0.069066498 | J34: 239974.36 | K34: =K23+K31 -> 267226 | L34: =K34/J34-1 -> 0.11356065
B35: Income Tax | D35: =IS!BO61 -> 47124 | E35: =K35 -> 56117 | G35: =IS!BS61 -> 54877 | H35: =K35 -> 56117 | J35: 47994.871 | K35: =IS!BT61 -> 56117 | S35: 6000 | T35: 9000
B36: Non-GAAP Net Income | D36: =D34-D35 -> 188496 | E36: =K36 -> 211109 | F36: =E36/D36-1 -> 0.11996541 | G36: =G34-G35 -> 195085 | H36: =K36 -> 211109 | I36: =H36/G36-1 -> 0.082138555 | J36: 191979.49 | K36: =K34-K35 -> 211109 | L36: =K36/J36-1 -> 0.099643537 | N36: =K36-J36 -> 19129.515
B38: GAAP Income before Taxes | D38: =IS!BO66 -> 71574 | E38: =K38 -> 95529 | F38: =E38/D38-1 -> 0.33468857 | G38: =IS!BS66 -> 76460 | H38: =K38 -> 95529 | I38: =H38/G38-1 -> 0.24939838 | J38: 79058.356 | K38: =IS!BT66 -> 95529 | L38: =K38/J38-1 -> 0.20833527
B39: Income Tax | D39: =IS!BO67 -> 9151 | E39: =K39 -> 11804 | G39: =IS!BS67 -> 13490 | H39: =K39 -> 11804 | J39: 6000 | K39: =IS!BT67 -> 11804
B40: GAAP Net Income | D40: =D38-D39 -> 62423 | E40: =K40 -> 83725 | F40: =E40/D40-1 -> 0.34125242 | G40: =G38-G39 -> 62970 | H40: =K40 -> 83725 | I40: =H40/G40-1 -> 0.3296014 | J40: 73058.356 | K40: =K38-K39 -> 83725 | L40: =K40/J40-1 -> 0.14600169
B42: Non-GAAP EPS | D42: =D36/D46 -> 0.90316522 | E42: =K42 -> 1.0146105 | F42: =E42/D42-1 -> 0.12339417 | G42: =G36/G46 -> 0.9247663 | H42: =K42 -> 1.0146105 | I42: =H42/G42-1 -> 0.097153449 | J42: 0.91047675 | K42: =K36/K46 -> 1.0146105 | L42: =K42/J42-1 -> 0.11437282 | N42: =K42-J42 -> 0.10413379 | P42: 0.46 | R42: 0.46 | V42: 0.54
B43: GAAP EPS | D43: =D40/D45 -> 0.30664597 | E43: =K43 -> 0.41457461 | G43: =G40/G45 -> 0.31074199 | H43: =K43 -> 0.41457461 | J43: 0.36070363 | K43: =K40/K45 -> 0.41457461
B45: Basic Shares Outstanding | D45: =IS!BO79 -> 203567 | E45: =K45 -> 201954 | G45: =IS!BS79 -> 202644 | H45: =K45 -> 201954 | J45: 202544 | K45: =IS!BT79 -> 201954
B46: Diluted Shares Outstanding | D46: =IS!BO80 -> 208706 | E46: =K46 -> 208069 | G46: =IS!BS80 -> 210956 | H46: =K46 -> 208069 | J46: 210856 | K46: =IS!BT80 -> 208069 | Q46: =(205000+210000)/2 -> 207500 | S46: =(205000+210000)/2 -> 207500 | T46: =(205000+210000)/2 -> 207500
X47: 1Q23 | Y47: FY23
B48: Source: Company reports and Needham & Co estimates | W48: Billings | X48: 573 - 583 | Y48: 2706 - 2726
B50: Billings | P50: 581400 | Q50: =(599000+609000)/2 -> 604000 | R50: 677300 | S50: =(2710000+2730000)/2 -> 2720000 | T50: =(2521000+2541000)/2 -> 2531000 | U50: =IF(AND(ISNUMBER(T50), ISNUMBER(S50)), T50-S50, "-") -> -189000 | V50: 2713900

Sheet G CHG
C5: FY26 Guidance | D5: Prior FY26 Guide | E5: Updated FY26 Guide | F5: Delta | G5: 3Q26 Guide | H5: 3Q26 Result | I5: 3Q26 Beat | J5: Rest of Year Raise / (Reduce)
C6: Revenue ($mm) | D6: =AVERAGE(3189,3201) -> 3195 | E6: =AVERAGE(3208,3212) -> 3210 | F6: =E6-D6 -> 15 | G6: =AVERAGE(804,808) -> 806 | H6: =Comparison!K7/1000 -> 818.35 | I6: =H6-G6 -> 12.35 | J6: =F6-I6 -> 2.65
C7: Growth | D7: =D6/(IS!BQ13/1000)-1 -> 0.073322182 | E7: =E6/(IS!BQ13/1000)-1 -> 0.078361254
C8: Subscription Revenue | D8: =AVERAGE(3121,3133) -> 3127 | E8: =AVERAGE(3140,3144) -> 3142 | F8: =E8-D8 -> 15 | G8: =AVERAGE(786,790) -> 788 | H8: =Comparison!K5/1000 -> 800.958 | I8: =H8-G8 -> 12.958 | J8: =F8-I8 -> 2.042
C9: Growth | D9: =D8/(IS!BQ5/1000)-1 -> 0.07778937 | E9: =E8/(IS!BQ5/1000)-1 -> 0.08295945
C10: Billings | D10: =AVERAGE(3325,3355) -> 3340 | E10: =AVERAGE(3379,3389) -> 3384 | F10: =E10-D10 -> 44 | G10: =AVERAGE(785,795) -> 790 | H10: =IS!BO108/1000 -> 752.307 | I10: =H10-G10 -> -37.693 | J10: =F10-I10 -> 81.693
C11: Growth | D11: =D10/(IS!BQ108/1000)-1 -> 0.074107293 | E11: =E10/(IS!BQ108/1000)-1 -> 0.088257209
C12: Non-GAAP Operating Margin | D12: =AVERAGE(28.6%,29.6%) -> 0.291 | E12: =AVERAGE(29.8%,29.9%) -> 0.2985 | F12: =E12-D12 -> 0.0075 | G12: =AVERAGE(28%,29%) -> 0.285 | H12: =Comparison!K24 -> 0.3141101
L14: Guidance History | M14: FY23 | N14: FY24 | O14: FY25 | P14: FY26E
L15: Revenue Growth - Initial Guide | M15: 0.175 | N15: 0.074 | O15: 0.058 | P15: 0.053
L16: Revenue Growth- Actual | M16: =IS!BG14 -> 0.19395381 | N16: =IS!BL14 -> 0.097764432 | O16: =IS!BQ14 -> 0.077793693 | P16: TBD
L17: Difference | M17: =M16-M15 -> 0.018953815 | N17: =N16-N15 -> 0.023764432 | O17: =O16-O15 -> 0.019793693 | P17: TBD
L19: NG Operating Margin - Initial Guide | M19: 0.17 | N19: 0.22 | O19: 0.2725 | P19: 0.283
L20: NG Operating Margin - Actual | M20: =IS!BG36 -> 0.20544812 | N20: =IS!BL36 -> 0.2575664 | O20: =IS!BQ36 -> 0.29764047 | P20: TBD
L21: Difference | M21: =M20-M19 -> 0.035448117 | N21: =N20-N19 -> 0.037566399 | O21: =O20-O19 -> 0.025140472 | P21: TBD

Sheet IS
B2: DocuSign, Inc (DOCU)
B4: Income Statement (FYE January 31) | D4: 2012 | E4: 1Q13 | F4: 2Q13 | G4: 3Q13 | H4: 4Q13 | I4: FY13 | J4: 1Q14 | K4: 2Q14 | L4: 3Q14 | M4: 4Q14 | N4: FY14 | O4: 1Q15 | P4: 2Q15 | Q4: 3Q15 | R4: 4Q15 | S4: FY15 | T4: 1Q16 | U4: 2Q16 | V4: 3Q16 | W4: 4Q16 | X4: FY16 | Y4: 1Q17 | Z4: 2Q17 | AA4: 3Q17 | AB4: 4Q17 | AC4: FY17 | AD4: 1Q18 | AE4: 2Q18 | AF4: 3Q18 | AG4: 4Q18 | AH4: FY18 | AI4: 1Q19 | AJ4: 2Q19 | AK4: 3Q19 | AL4: 4Q19 | AM4: FY19 | AN4: 1Q20 | AO4: 2Q20 | AP4: 3Q20 | AQ4: 4Q20 | AR4: FY20 | AS4: 1Q21 | AT4: 2Q21 | AU4: 3Q21 | AV4: 4Q21 | AW4: FY21 | AX4: 1Q22 | AY4: 2Q22 | AZ4: 3Q22 | BA4: 4Q22 | BB4: FY22 | BC4: 1Q23 | BD4: 2Q23 | BE4: 3Q23 | BF4: 4Q23 | BG4: FY23 | BH4: 1Q24 | BI4: 2Q24 | BJ4: 3Q24 | BK4: 4Q24 | BL4: FY24 | BM4: 1Q25 | BN4: 2Q25 | BO4: 3Q25 | BP4: 4Q25 | BQ4: FY25 | BR4: 1Q26 | BS4: 2Q26 | BT4: 3Q26 | BU4: 4Q26E | BV4: FY26E | BW4: 1Q27E | BX4: 2Q27E | BY4: 3Q27E | BZ4: 4Q27E | CA4: FY27E
B5: Subscription Revenue | X5: =229127 -> 229127 | AC5: =348563 -> 348563 | AD5: 106847 | AE5: 117553 | AF5: 122905 | AG5: 137276 | AH5: =SUM(AD5:AG5) -> 484581 | AI5: 148198 | AJ5: 158461 | AK5: 169426 | AL5: =187572 -> 187572 | AM5: =SUM(AI5:AL5) -> 663657 | AN5: =201458 -> 201458 | AO5: 220811 | AP5: =238072 -> 238072 | AQ5: 258122 | AR5: =SUM(AN5:AQ5) -> 918463 | AS5: 280922 | AT5: =323643 -> 323643 | AU5: =366617 -> 366617 | AV5: 410215 | AW5: =SUM(AS5:AV5) -> 1381397 | AX5: 451935 | AY5: 492758 | AZ5: 528573 | BA5: 564006 | BB5: =SUM(AX5:BA5) -> 2037272 | BC5: 569251 | BD5: 605194 | BE5: 624055 | BF5: 643677 | BG5: =SUM(BC5:BF5) -> 2442177 | BH5: 639307 | BI5: 669367 | BJ5: 682352 | BK5: 695682 | BL5: =SUM(BH5:BK5) -> 2686708 | BM5: 691483 | BN5: 717366 | BO5: 734693 | BP5: 757767 | BQ5: =SUM(BM5:BP5) -> 2901309 | BR5: 746202 | BS5: 784388 | BT5: 800958 | BU5: =BP5*(1+BU6) -> 810280.25 | BV5: =SUM(BR5:BU5) -> 3141828.3 | BW5: =BR5*(1+BW6) -> 790974.12 | BX5: =BS5*(1+BX6) -> 831451.28 | BY5: =BT5*(1+BY6) -> 849015.48 | BZ5: =BU5*(1+BZ6) -> 858897.07 | CA5: =SUM(BW5:BZ5) -> 3330337.9
C6: Y/Y Growth | O6: =O5/J5-1 -> #DIV/0! | P6: =P5/K5-1 -> #DIV/0! | Q6: =Q5/L5-1 -> #DIV/0! | R6: =R5/M5-1 -> #DIV/0! | V6: =V5/Q5-1 -> #DIV/0! | W6: =W5/R5-1 -> #DIV/0! | X6: =X5/S5-1 -> #DIV/0! | Y6: =Y5/T5-1 -> #DIV/0! | Z6: =Z5/U5-1 -> #DIV/0! | AA6: =AA5/V5-1 -> #DIV/0! | AB6: =AB5/W5-1 -> #DIV/0! | AC6: =AC5/X5-1 -> 0.5212655 | ... BT6: =BT5/BO5-1 -> 0.090194136 | BU6: 0.0693 | BV6: =BV5/BQ5-1 -> 0.082900254 | BW6: 0.06 | BX6: 0.06 | BY6: 0.06 | BZ6: 0.06 | CA6: =CA5/BV5-1 -> 0.06
C7: Q/Q Growth | F7: =F5/E5-1 -> #DIV/0! | G7: =G5/F5-1 -> #DIV/0! | H7: =H5/G5-1 -> #DIV/0! | O7: =O5/M5-1 -> #DIV/0! | P7: =P5/O5-1 -> #DIV/0! | Q7: =Q5/P5-1 -> #DIV/0! | R7: =R5/Q5-1 -> #DIV/0! | T7: =T5/R5-1 -> #DIV/0! | U7: =U5/T5-1 -> #DIV/0! | V7: =V5/U5-1 -> #DIV/0! | W7: =W5/V5-1 -> #DIV/0! | Y7: =Y5/W5-1 -> #DIV/0! | Z7: =Z5/Y5-1 -> #DIV/0! | AA7: =AA5/Z5-1 -> #DIV/0! | AB7: =AB5/AA5-1 -> #DIV/0! | AD7: =AD5/AB5-1 -> #DIV/0! | AE7: =AE5/AD5-1 -> 0.10019935 | AF7: =AF5/AE5-1 -> 0.0455284 | AG7: =AG5/AF5-1 -> 0.11692771 | AI7: =AI5/AG5-1 -> 0.079562342 | AJ7: =AJ5/AI5-1 -> 0.069251947 | AK7: =AK5/AJ5-1 -> 0.069196837 | AL7: =AL5/AK5-1 -> 0.10710281 | AN7: =AN5/AL5-1 -> 0.074030239 | AO7: =AO5/AN5-1 -> 0.096064688 | AP7: =AP5/AO5-1 -> 0.078170924 | AQ7: =AQ5/AP5-1 -> 0.08421822 | AS7: =AS5/AQ5-1 -> 0.088330324 | AT7: =AT5/AS5-1 -> 0.15207424 | AU7: =AU5/AT5-1 -> 0.13278211 | AV7: =AV5/AU5-1 -> 0.11891974 | AX7: =AX5/AV5-1 -> 0.10170277 | AY7: =AY5/AX5-1 -> 0.090329362 | AZ7: =AZ5/AY5-1 -> 0.072682737 | BA7: =BA5/AZ5-1 -> 0.067035206 | BC7: =BC5/BA5-1 -> 0.0092995465 | BD7: =BD5/BC5-1 -> 0.063140864 | BE7: =BE5/BD5-1 -> 0.031165213 | BF7: =BF5/BE5-1 -> 0.031442741 | BH7: =BH5/BF5-1 -> -0.0067891194 | BI7: =BI5/BH5-1 -> 0.047019663 | BJ7: =BJ5/BI5-1 -> 0.019398925 | BK7: =BK5/BJ5-1 -> 0.019535372 | BM7: =BM5/BK5-1 -> -0.0060358037 | BN7: =BN5/BM5-1 -> 0.037431144 | BO7: =BO5/BN5-1 -> 0.02415364 | BP7: =BP5/BO5-1 -> 0.031406315 | BR7: =BR5/BP5-1 -> -0.015261947 | BS7: =BS5/BR5-1 -> 0.051173811 | BT7: =BT5/BS5-1 -> 0.021124749 | BU7: =BU5/BT5-1 -> 0.011638879 | BW7: =BW5/BU5-1 -> -0.023826488 | BX7: =BX5/BW5-1 -> 0.051173811 | BY7: =BY5/BX5-1 -> 0.021124749 | BZ7: =BZ5/BY5-1 -> 0.011638879
C8: % of total revenues | D8: =D5/D13 -> #DIV/0! | E8: =E5/E13 -> #DIV/0! | F8: =F5/F13 -> #DIV/0! | G8: =G5/G13 -> #DIV/0! | H8: =H5/H13 -> #DIV/0! | O8: =O5/O13 -> #DIV/0! | P8: =P5/P13 -> #DIV/0! | Q8: =Q5/Q13 -> #DIV/0! | R8: =R5/R13 -> #DIV/0! | S8: =S5/S13 -> #DIV/0! | T8: =T5/T13 -> #DIV/0! | U8: =U5/U13 -> #DIV/0! | V8: =V5/V13 -> #DIV/0! | ... CA8: =CA5/CA13 -> 0.98234282
B9: Professional Services and Other | X9: =21354 -> 21354 | AC9: =32896 -> 32896 | AD9: 6651 | AE9: 7990 | AF9: 7684 | AG9: =11598 -> 11598 | AH9: =SUM(AD9:AG9) -> 33923 | AI9: 7610 | AJ9: 8583 | AK9: 8959 | AL9: =12160 -> 12160 | AM9: =SUM(AI9:AL9) -> 37312 | AN9: =12504 -> 12504 | AO9: 14801 | AP9: =11430 -> 11430 | AQ9: =16773 -> 16773 | AR9: =SUM(AN9:AQ9) -> 55508 | AS9: =16095 -> 16095 | AT9: =18566 -> 18566 | AU9: =16306 -> 16306 | AV9: 20683 | AW9: =SUM(AS9:AV9) -> 71650 | AX9: 17143 | AY9: 19086 | AZ9: 16890 | BA9: 16822 | BB9: =SUM(AX9:BA9) -> 69941 | BC9: 19441 | BD9: 16990 | BE9: 21408 | BF9: 15899 | BG9: =SUM(BC9:BF9) -> 73738 | BH9: 22081 | BI9: 18320 | BJ9: 18069 | BK9: 16704 | BL9: =SUM(BH9:BK9) -> 75174 | BM9: 18157 | BN9: 18661 | BO9: 20127 | BP9: 18485 | BQ9: =SUM(BM9:BP9) -> 75430 | BR9: 17452 | BS9: 16248 | BT9: 17392 | BU9: =BP9*(1+BU10) -> 16932.26 | BV9: =SUM(BR9:BU9) -> 68024.26 | BW9: =BR9*(1+BW10) -> 15357.76 | BX9: =BS9*(1+BX10) -> 14298.24 | BY9: =BT9*(1+BY10) -> 15304.96 | BZ9: =BU9*(1+BZ10) -> 14900.389 | CA9: =SUM(BW9:BZ9) -> 59861.349
C10: Y/Y Growth | O10: =O9/J9-1 -> #DIV/0! | P10: =P9/K9-1 -> #DIV/0! | Q10: =Q9/L9-1 -> #DIV/0! | R10: =R9/M9-1 -> #DIV/0! | V10: =V9/Q9-1 -> #DIV/0! | W10: =W9/R9-1 -> #DIV/0! | X10: =X9/S9-1 -> #DIV/0! | Y10: =Y9/T9-1 -> #DIV/0! | Z10: =Z9/U9-1 -> #DIV/0! | AA10: =AA9/V9-1 -> #DIV/0! | AB10: =AB9/W9-1 -> #DIV/0! | AC10: =AC9/X9-1 -> 0.54050763 | ... BT10: =BT9/BO9-1 -> -0.13588712 | BU10: -0.084 | BV10: =BV9/BQ9-1 -> -0.0981803 | BW10: -0.12 | BX10: -0.12 | BY10: -0.12 | BZ10: -0.12 | CA10: =CA9/BV9-1 -> -0.12
C11: Q/Q Growth | F11: =F9/E9-1 -> #DIV/0! | G11: =G9/F9-1 -> #DIV/0! | H11: =H9/G9-1 -> #DIV/0! | O11: =O9/M9-1 -> #DIV/0! | P11: =P9/O9-1 -> #DIV/0! | Q11: =Q9/P9-1 -> #DIV/0! | R11: =R9/Q9-1 -> #DIV/0! | T11: =T9/R9-1 -> #DIV/0! | U11: =U9/T9-1 -> #DIV/0! | V11: =V9/U9-1 -> #DIV/0! | W11: =W9/V9-1 -> #DIV/0! | Y11: =Y9/W9-1 -> #DIV/0! | Z11: =Z9/Y9-1 -> #DIV/0! | AA11: =AA9/Z9-1 -> #DIV/0! | AB11: =AB9/AA9-1 -> #DIV/0! | AD11: =AD9/AB9-1 -> #DIV/0! | AE11: =AE9/AD9-1 -> 0.20132311 | AF11: =AF9/AE9-1 -> -0.038297872 | AG11: =AG9/AF9-1 -> 0.50937012 | AI11: =AI9/AG9-1 -> -0.34385239 | AJ11: =AJ9/AI9-1 -> 0.12785808 | AK11: =AK9/AJ9-1 -> 0.043807527 | AL11: =AL9/AK9-1 -> 0.35729434 | AN11: =AN9/AL9-1 -> 0.028289474 | AO11: =AO9/AN9-1 -> 0.18370122 | AP11: =AP9/AO9-1 -> -0.22775488 | AQ11: =AQ9/AP9-1 -> 0.46745407 | AS11: =AS9/AQ9-1 -> -0.040422107 | AT11: =AT9/AS9-1 -> 0.15352594 | AU11: =AU9/AT9-1 -> -0.12172789 | AV11: =AV9/AU9-1 -> 0.2684288 | AX11: =AX9/AV9-1 -> -0.17115505 | AY11: =AY9/AX9-1 -> 0.11334072 | AZ11: =AZ9/AY9-1 -> -0.11505816 | BA11: =BA9/AZ9-1 -> -0.0040260509 | BC11: =BC9/BA9-1 -> 0.15568898 | BD11: =BD9/BC9-1 -> -0.12607376 | BE11: =BE9/BD9-1 -> 0.26003531 | BF11: =BF9/BE9-1 -> -0.25733371 | BH11: =BH9/BF9-1 -> 0.38882949 | BI11: =BI9/BH9-1 -> -0.17032743 | BJ11: =BJ9/BI9-1 -> -0.013700873 | BK11: =BK9/BJ9-1 -> -0.075543749 | BM11: =BM9/BK9-1 -> 0.086985153 | BN11: =BN9/BM9-1 -> 0.02775789 | BO11: =BO9/BN9-1 -> 0.078559563 | BP11: =BP9/BO9-1 -> -0.081581955 | BR11: =BR9/BP9-1 -> -0.055883148 | BS11: =BS9/BR9-1 -> -0.068989228 | BT11: =BT9/BS9-1 -> 0.070408666 | BU11: =BU9/BT9-1 -> -0.026433993 | BW11: =BW9/BU9-1 -> -0.092988178 | BX11: =BX9/BW9-1 -> -0.068989228 | BY11: =BY9/BX9-1 -> 0.070408666 | BZ11: =BZ9/BY9-1 -> -0.026433993
C12: % of total revenues | D12: =D9/D13 -> #DIV/0! | E12: =E9/E13 -> #DIV/0! | F12: =F9/F13 -> #DIV/0! | G12: =G9/G13 -> #DIV/0! | H12: =H9/H13 -> #DIV/0! | O12: =O9/O13 -> #DIV/0! | P12: =P9/P13 -> #DIV/0! | Q12: =Q9/Q13 -> #DIV/0! | R12: =R9/R13 -> #DIV/0! | S12: =S9/S13 -> #DIV/0! | T12: =T9/T13 -> #DIV/0! | U12: =U9/U13 -> #DIV/0! | V12: =V9/V13 -> #DIV/0! | ... CA12: =CA9/CA13 -> 0.017657177
B13: Total Revenues | D13: =D5+D9 -> 0 | E13: =E5+E9 -> 0 | F13: =F5+F9 -> 0 | G13: =G5+G9 -> 0 | H13: =H5+H9 -> 0 | O13: =O5+O9 -> 0 | P13: =P5+P9 -> 0 | Q13: =Q5+Q9 -> 0 | R13: =R5+R9 -> 0 | S13: =S5+S9 -> 0 | T13: =T5+T9 -> 0 | U13: =U5+U9 -> 0 | V13: =V5+V9 -> 0 | ... CA13: =CA5+CA9 -> 3390199.3
C14: Y/Y Growth | O14: =O13/J13-1 -> #DIV/0! | P14: =P13/K13-1 -> #DIV/0! | Q14: =Q13/L13-1 -> #DIV/0! | R14: =R13/M13-1 -> #DIV/0! | V14: =V13/Q13-1 -> #DIV/0! | W14: =W13/R13-1 -> #DIV/0! | X14: =X13/S13-1 -> #DIV/0! | Y14: =Y13/T13-1 -> #DIV/0! | Z14: =Z13/U13-1 -> #DIV/0! | AA14: =AA13/V13-1 -> #DIV/0! | AB14: =AB13/W13-1 -> #DIV/0! | AC14: =AC13/X13-1 -> 0.52290593 | ... CA14: =CA13/BV13-1 -> 0.05618538
C15: Q/Q Growth | F15: =F13/E13-1 -> #DIV/0! | G15: =G13/F13-1 -> #DIV/0! | H15: =H13/G13-1 -> #DIV/0! | O15: =O13/M13-1 -> #DIV/0! | P15: =P13/O13-1 -> #DIV/0! | Q15: =Q13/P13-1 -> #DIV/0! | R15: =R13/Q13-1 -> #DIV/0! | T15: =T13/R13-1 -> #DIV/0! | U15: =U13/T13-1 -> #DIV/0! | V15: =V13/U13-1 -> #DIV/0! | W15: =W13/V13-1 -> #DIV/0! | Y15: =Y13/W13-1 -> #DIV/0! | Z15: =Z13/Y13-1 -> #DIV/0! | AA15: =AA13/Z13-1 -> #DIV/0! | AB15: =AB13/AA13-1 -> #DIV/0! | AC15: =AC13-X13 -> 130978 | AD15: =AD13/AB13-1 -> #DIV/0! | AE15: =AE13/AD13-1 -> 0.10612522 | AF15: =AF13/AE13-1 -> 0.0401934 | AG15: =AG13/AF13-1 -> 0.14001945 | AI15: =AI13/AG13-1 -> 0.046576299 | AJ15: =AJ13/AI13-1 -> 0.072114397 | AK15: =AK13/AJ13-1 -> 0.067892292 | AL15: =AL13/AK13-1 -> 0.11966813 | AN15: =AN13/AL13-1 -> 0.071245469 | AO15: =AO13/AN13-1 -> 0.10118619 | AP15: =AP13/AO13-1 -> 0.058952855 | AQ15: =AQ13/AP13-1 -> 0.10177474 | AS15: =AS13/AQ13-1 -> 0.080474363 | AT15: =AT13/AS13-1 -> 0.15215291 | AU15: =AU13/AT13-1 -> 0.11897408 | AV15: =AV13/AU13-1 -> 0.12528628 | AX15: =AX13/AV13-1 -> 0.088605656 | AY15: =AY13/AX13-1 -> 0.091170338 | AZ15: =AZ13/AY13-1 -> 0.065682122 | BA15: =BA13/AZ13-1 -> 0.064834828 | BC15: =BC13/BA13-1 -> 0.013539292 | BD15: =BD13/BC13-1 -> 0.056892229 | BE15: =BE13/BD13-1 -> 0.037414977 | BF15: =BF13/BE13-1 -> 0.021864925 | BH15: =BH13/BF13-1 -> 0.0027472194 | BI15: =BI13/BH13-1 -> 0.039763346 | BJ15: =BJ13/BI13-1 -> 0.018517145 | BK15: =BK13/BJ13-1 -> 0.017082583 | BM15: =BM13/BK13-1 -> -0.0038546518 | BN15: =BN13/BM13-1 -> 0.037183642 | BO15: =BO13/BN13-1 -> 0.025533031 | BP15: =BP13/BO13-1 -> 0.028393524 | BR15: =BR13/BP13-1 -> -0.016229266 | BS15: =BS13/BR13-1 -> 0.048427691 | BT15: =BT13/BS13-1 -> 0.022124911 | BU15: =BU13/BT13-1 -> 0.010829734 | BW15: =BW13/BU13-1 -> -0.025242163 | BX15: =BX13/BW13-1 -> 0.048885132 | BY15: =BY13/BX13-1 -> 0.021957943 | BZ15: =BZ13/BY13-1 -> 0.010964703
B17: Cost of Revenue | AN17: =+((AN9+AO9-AN20-AO20)/(AN9+AO9)) -> -0.15663798
C18: Subscription Revenue | X18: =48656-1074-1965 -> 45617 | AC18: =73363-1190-6940 -> 65233 | AD18: =19293-238-1697 -> 17358 | AE18: =20040-231-1691 -> 18118 | AF18: =22335-228-1691 -> 20416 | AG18: =22166-214-1714 -> 20238 | AH18: =SUM(AD18:AG18) -> 76130 | AI18: =32438-9955-1668 -> 20815 | AJ18: =23057-1588-1003 -> 20466 | AK18: =28709-2398-1632 -> 24679 | AL18: =33560-2241-1778-830 -> 28711 | AM18: =SUM(AI18:AL18) -> 94671 | AN18: =33119-2282-1627-221 -> 28989 | AO18: =39472-3115-1381-211 -> 34765 | AP18: =43178-3534-1348-337 -> 37959 | AQ18: =48162-3951-1348-285 -> 42578 | AR18: =SUM(AN18:AQ18) -> 144291 | AS18: =52010-3864-1348-535 -> 46263 | AT18: =64730-5014-3132-926 -> 55658 | AU18: =69905-5777-3376-722 -> 60030 | AV18: =73347-6138-3196-1454+775 -> 63334 | AW18: =SUM(AS18:AV18) -> 225285 | AX18: =78071-6018-3171-1442 -> 67440 | AY18: =84455-7539-3328-971 -> 72617 | AZ18: =84579-8095-2766-873 -> 72845 | BA18: =96556-9500-2403-417 -> 84236 | BB18: =SUM(AX18:BA18) -> 297138 | BC18: =105159-10613-2403-508 -> 91635 | BD18: =107931-12994-2403-332-194 -> 92008 | BE18: =102524-11665-2425-310-127 -> 87997 | BF18: =110463-11644-2382-243-126 -> 96068 | BG18: =SUM(BC18:BF18) -> 367708 | BH18: =108942-11357-2403-466-299 -> 94417 | BI18: =116185-13081-2314-465-206 -> 100119 | BJ18: =114227-13705-2070-301 -> 98151 | BK18: =120551-13517-2070-232 -> 104732 | BL18: =SUM(BH18:BK18) -> 397419 | BM18: =126602-14181-2070-792 -> 109559 | BN18: =132372-15593-3067-595 -> 113117 | BO18: =134587-14862-3566-574 -> 115585 | BP18: =138884-13712-3564-921 -> 120687 | BQ18: =SUM(BM18:BP18) -> 458948 | BR18: =137343-12996-3565-1445 -> 119337 | BS18: =144097-14425-1220-1562 -> 126890 | BT18: =150372-15018-889-1495 -> 132970 | BU18: =BU5*(1-BU19) -> 140988.76 | BV18: =SUM(BR18:BU18) -> 520185.76 | BW18: =BW5*(1-BW19) -> 134465.6 | BX18: =BX5*(1-BX19) -> 139683.82 | BY18: =BY5*(1-BY19) -> 140087.55 | BZ18: =BZ5*(1-BZ19) -> 140000.22 | CA18: =SUM(BW18:BZ18) -> 554237.19
C19: Gross Margins | D19: =((D5-D18)/(D5)) -> #DIV/0! | E19: =((E5-E18)/(E5)) -> #DIV/0! | F19: =((F5-F18)/(F5)) -> #DIV/0! | G19: =((G5-G18)/(G5)) -> #DIV/0! | H19: =((H5-H18)/(H5)) -> #DIV/0! | O19: =((O5-O18)/(O5)) -> #DIV/0! | P19: =((P5-P18)/(P5)) -> #DIV/0! | Q19: =((Q5-Q18)/(Q5)) -> #DIV/0! | R19: =((R5-R18)/(R5)) -> #DIV/0! | S19: =((S5-S18)/(S5)) -> #DIV/0! | T19: =((T5-T18)/(T5)) -> #DIV/0! | U19: =((U5-U18)/(U5)) -> #DIV/0! | V19: =((V5-V18)/(V5)) -> #DIV/0! | ... BT19: =((BT5-BT18)/(BT5)) -> 0.8339863 | BU19: 0.826 | BV19: =((BV5-BV18)/(BV5)) -> 0.83443215 | BW19: 0.83 | BX19: 0.832 | BY19: 0.835 | BZ19: 0.837 | CA19: =((CA5-CA18)/(CA5)) -> 0.83357929
C20: Professional Services and Other | X20: =25199-1297 -> 23902 | AC20: =29114-1021 -> 28093 | AD20: =7831-235 -> 7596 | AE20: =8418-254 -> 8164 | AF20: =8881-253 -> 8628 | AG20: =9309-234 -> 9075 | AH20: =SUM(AD20:AG20) -> 33463 | AI20: =25856-16045 -> 9811 | AJ20: =13304-2822 -> 10482 | AK20: =16364-3578-108 -> 12678 | AL20: =19133-3413-1119 -> 14601 | AM20: =SUM(AI20:AL20) -> 47572 | AN20: =18900-3440-431 -> 15029 | AO20: =21704-4821-330 -> 16553 | AP20: =18786-3616-378 -> 14792 | AQ20: =19913-3826-383 -> 15704 | AR20: =SUM(AN20:AQ20) -> 62078 | AS20: =22022-4125-501 -> 17396 | AT20: =25885-5225-812 -> 19848 | AU20: =27926-6005-954 -> 20967 | AV20: =28233-6510-775 -> 20948 | AW20: =SUM(AS20:AV20) -> 79159 | AX20: =27171-5535-1332 -> 20304 | AY20: =29325-6446-1150 -> 21729 | AZ20: =31396-7270-927 -> 23199 | BA20: =34898-8096-412 -> 26390 | BB20: =SUM(AX20:BA20) -> 91622 | BC20: =27257-5082-283 -> 21892 | BD20: =28773-6478-198-71 -> 22026 | BE20: =27018-6767-161-286 -> 19804 | BF20: =26963-7431-149-286 -> 19097 | BG20: =SUM(BC20:BF20) -> 82819 | BH20: =27545-6730-209-130 -> 20476 | BI20: =29397-7286-248-86 -> 21777 | BJ20: =28418-7343-236 -> 20839 | BK20: =27356-6977-105 -> 20274 | BL20: =SUM(BH20:BK20) -> 83366 | BM20: =22844-4702-231 -> 17911 | BN20: =23093-4998-221 -> 17874 | BO20: =21950-4765-320 -> 16865 | BP20: =21327-4174-255 -> 16898 | BQ20: =SUM(BM20:BP20) -> 69548 | BR20: =19926-3908-428 -> 15590 | BS20: =21366-4167-355 -> 16844 | BT20: =20174-3992-291 -> 15891 | BU20: =BU9*(1-BU21) -> 16085.647 | BV20: =SUM(BR20:BU20) -> 64410.647 | BW20: =BW9*(1-BW21) -> 15050.605 | BX20: =BX9*(1-BX21) -> 14012.275 | BY20: =BY9*(1-BY21) -> 14845.811 | BZ20: =BZ9*(1-BZ21) -> 14602.381 | CA20: =SUM(BW20:BZ20) -> 58511.072
C21: Gross Margins | D21: =(D9-D20)/D9 -> #DIV/0! | E21: =(E9-E20)/E9 -> #DIV/0! | F21: =(F9-F20)/F9 -> #DIV/0! | G21: =(G9-G20)/G9 -> #DIV/0! | H21: =(H9-H20)/H9 -> #DIV/0! | O21: =(O9-O20)/O9 -> #DIV/0! | P21: =(P9-P20)/P9 -> #DIV/0! | Q21: =(Q9-Q20)/Q9 -> #DIV/0! | R21: =(R9-R20)/R9 -> #DIV/0! | S21: =(S9-S20)/S9 -> #DIV/0! | T21: =(T9-T20)/T9 -> #DIV/0! | U21: =(U9-U20)/U9 -> #DIV/0! | V21: =(V9-V20)/V9 -> #DIV/0! | ... BT21: =(BT9-BT20)/BT9 -> 0.086304048 | BU21: 0.05 | BV21: =(BV9-BV20)/BV9 -> 0.053122415 | BW21: 0.02 | BX21: 0.02 | BY21: 0.03 | BZ21: 0.02 | CA21: =(CA9-CA20)/CA9 -> 0.022556735
B22: Total Cost of Revenues | E22: =E20+E18 -> 0 | F22: =F20+F18 -> 0 | G22: =G20+G18 -> 0 | H22: =H20+H18 -> 0 | O22: =O18+O20 -> 0 | P22: =P18+P20 -> 0 | Q22: =Q18+Q20 -> 0 | R22: =R18+R20 -> 0 | S22: =S20+S18 -> 0 | T22: =T18+T20 -> 0 | U22: =U18+U20 -> 0 | V22: =V18+V20 -> 0 | W22: =W18+W20 -> 0 | X22: =X18+X20 -> 69519 | Y22: =Y18+Y20 -> 0 | Z22: =Z18+Z20 -> 0 | AA22: =AA18+AA20 -> 0 | ... AH22: =AH18+AH20 -> 109593 | AI22: =AI20+AI18 -> 30626 | AJ22: =AJ20+AJ18 -> 30948 | AK22: =AK20+AK18 -> 37357 | AL22: =AL20+AL18 -> 43312 | AM22: =SUM(AI22:AL22) -> 142243 | AN22: =AN20+AN18 -> 44018 | AO22: =AO20+AO18 -> 51318 | AP22: =AP20+AP18 -> 52751 | AQ22: =AQ20+AQ18 -> 58282 | AR22: =SUM(AN22:AQ22) -> 206369 | AS22: =AS20+AS18 -> 63659 | AT22: =AT20+AT18 -> 75506 | AU22: =AU20+AU18 -> 80997 | AV22: =AV20+AV18 -> 84282 | AW22: =SUM(AS22:AV22) -> 304444 | AX22: =AX20+AX18 -> 87744 | AY22: =AY20+AY18 -> 94346 | AZ22: =AZ20+AZ18 -> 96044 | BA22: =BA20+BA18 -> 110626 | BB22: =SUM(AX22:BA22) -> 388760 | BC22: =BC20+BC18 -> 113527 | BD22: =BD20+BD18 -> 114034 | BE22: =BE20+BE18 -> 107801 | BF22: =BF20+BF18 -> 115165 | BG22: =SUM(BC22:BF22) -> 450527 | BH22: =BH20+BH18 -> 114893 | BI22: =BI20+BI18 -> 121896 | BJ22: =BJ20+BJ18 -> 118990 | BK22: =BK20+BK18 -> 125006 | BL22: =SUM(BH22:BK22) -> 480785 | BM22: =BM20+BM18 -> 127470 | BN22: =BN20+BN18 -> 130991 | BO22: =BO20+BO18 -> 132450 | BP22: =BP20+BP18 -> 137585 | BQ22: =SUM(BM22:BP22) -> 528496 | BR22: =BR20+BR18 -> 134927 | BS22: =BS20+BS18 -> 143734 | BT22: =BT20+BT18 -> 148861 | BU22: =BU20+BU18 -> 157074.41 | BV22: =SUM(BR22:BU22) -> 584596.41 | BW22: =BW20+BW18 -> 149516.21 | BX22: =BX20+BX18 -> 153696.09 | BY22: =BY20+BY18 -> 154933.37 | BZ22: =BZ20+BZ18 -> 154602.6 | CA22: =SUM(BW22:BZ22) -> 612748.26
B23: Gross Profit | D23: =D13-D22 -> 0 | E23: =E13-E22 -> 0 | F23: =F13-F22 -> 0 | G23: =G13-G22 -> 0 | H23: =H13-H22 -> 0 | O23: =O13-O22 -> 0 | P23: =P13-P22 -> 0 | Q23: =Q13-Q22 -> 0 | R23: =R13-R22 -> 0 | S23: =S13-S22 -> 0 | T23: =T13-T22 -> 0 | U23: =U13-U22 -> 0 | V23: =V13-V22 -> 0 | ... CA23: =CA13-CA22 -> 2777451
C24: Gross Margin | D24: =D23/D13 -> #DIV/0! | E24: =E23/E13 -> #DIV/0! | F24: =F23/F13 -> #DIV/0! | G24: =G23/G13 -> #DIV/0! | H24: =H23/H13 -> #DIV/0! | O24: =O23/O13 -> #DIV/0! | P24: =P23/P13 -> #DIV/0! | Q24: =Q23/Q13 -> #DIV/0! | R24: =R23/R13 -> #DIV/0! | S24: =S23/S13 -> #DIV/0! | T24: =T23/T13 -> #DIV/0! | U24: =U23/U13 -> #DIV/0! | V24: =V23/V13 -> #DIV/0! | ... CA24: =CA23/CA13 -> 0.81925893
B26: Operating Expenses
C27: Sales and Marketing | X27: =170006-10617-1965 -> 157424 | AC27: =240787-11187-3385 -> 226215 | AD27: =64691-2705-840 -> 61146 | AE27: =68943-2883-665 -> 65395 | AF27: =69666-1959-1015 -> 66692 | AG27: =74630-1839-730 -> 72061 | AH27: =SUM(AD27:AG27) -> 265294 | AI27: =191085-112481-765 -> 77839 | AJ27: =103779-16791-765 -> 86223 | AK27: =117051-22338-2257-68 -> 92388 | AL27: =127691-20505-3234-8051 -> 95901 | AM27: =SUM(AI27:AL27) -> 352351 | AN27: =129936-18102-3106-2351 -> 106377 | AO27: =150886-25942-3039-1577 -> 120328 | AP27: =149231-24649-2957-1682 -> 119943 | AQ27: =161326-26170-2911-1413 -> 130832 | AR27: =SUM(AN27:AQ27) -> 477480 | AS27: =171793-24665-2911-2909 -> 141308 | AT27: =194992-32305-4284-186-3958 -> 154259 | AU27: =209944-36881-3981-4125 -> 164957 | AV27: 178118 | AW27: =SUM(AS27:AV27) -> 638642 | AX27: =239119-38135-3358-6778 -> 190848 | AY27: =262372-46921-3333-5706 -> 206412 | AZ27: =275619-49663-3205-5184 -> 217567 | BA27: =299417-52040-3205-1960 -> 242212 | BB27: =SUM(AX27:BA27) -> 857039 | BC27: =300697-47431-3205-2290 -> 247771 | BD27: =323582-61218-2630-1683-886 -> 257165 | BE27: =313783-57925-2688-1277-1467 -> 250426 | BF27: =304649-55760-2571-910-1467 -> 243941 | BG27: =SUM(BC27:BF27) -> 999303 | BH27: =280605-45326-2629-1670-1356 -> 229624 | BI27: =294838-51563-2630-1400-815 -> 238430 | BJ27: =292473-53715-2629-875 -> 235254 | BK27: =300221-53251-2631-1104 -> 243235 | BL27: =SUM(BH27:BK27) -> 946543 | BM27: =281644-46271-2629-2138 -> 230606 | BN27: 223978 | BO27: 236278 | BP27: =301288-48213-3354-2242 -> 247479 | BQ27: =SUM(BM27:BP27) -> 938341 | BR27: 243034 | BS27: =305450-49081-2962-3354 -> 250053 | BT27: =296516-48018-2356-3378 -> 242764 | BU27: =BU13*BU28 -> 259744.73 | BV27: =SUM(BR27:BU27) -> 995595.73 | BW27: =BW13*BW28 -> 253994.54 | BX27: =BX13*BX28 -> 266411.1 | BY27: =BY13*BY28 -> 267939.34 | BZ27: =BZ13*BZ28 -> 270877.21 | CA27: =SUM(BW27:BZ27) -> 1059222.2
C28: % of Revenue | D28: =D27/D13 -> #DIV/0! | E28: =E27/E13 -> #DIV/0! | F28: =F27/F13 -> #DIV/0! | G28: =G27/G13 -> #DIV/0! | H28: =H27/H13 -> #DIV/0! | O28: =O27/O13 -> #DIV/0! | P28: =P27/P13 -> #DIV/0! | Q28: =Q27/Q13 -> #DIV/0! | R28: =R27/R13 -> #DIV/0! | S28: =S27/S13 -> #DIV/0! | T28: =T27/T13 -> #DIV/0! | U28: =U27/U13 -> #DIV/0! | V28: =V27/V13 -> #DIV/0! | ... BT28: =BT27/BT13 -> 0.29665058 | BU28: 0.314 | BV28: =BV27/BV13 -> 0.31016868 | BW28: 0.315 | BX28: 0.315 | BY28: 0.31 | BZ28: 0.31 | CA28: =CA27/CA13 -> 0.31243655
C29: Research and Development | X29: =62255-8221 -> 54034 | AC29: =89652-10161 -> 79491 | AD29: =22708-1391 -> 21317 | AE29: =23767-1288 -> 22479 | AF29: =22522-1042 -> 21480 | AG29: =23431-1175 -> 22256 | AH29: =SUM(AD29:AG29) -> 87532 | AI29: =70870-47268 -> 23602 | AJ29: =33773-7359 -> 26414 | AK29: =38404-9919-302 -> 28183 | AL29: =42921-9562-2246 -> 31113 | AM29: =SUM(AI29:AL29) -> 109312 | AN29: =37183-7317-1150 -> 28716 | AO29: =47517-11963-1026 -> 34528 | AP29: =48758-11679-712 -> 36367 | AQ29: =52094-12252-636 -> 39206 | AR29: =SUM(AN29:AQ29) -> 138817 | AS29: =54234-11885-1546 -> 40803 | AT29: =63791-14781-2019 -> 46991 | AU29: =73362-18896-1752 -> 52714 | AV29: 57795 | AW29: =SUM(AS29:AV29) -> 198303 | AX29: =85416-20462-4176 -> 60778 | AY29: =94651-26275-2752 -> 65624 | AZ29: =102603-30074-2316 -> 70213 | BA29: =110692-31712-1097 -> 77883 | BB29: =SUM(AX29:BA29) -> 274498 | BC29: =112227-32205-1533 -> 78489 | BD29: =126532-40978-868-385 -> 84301 | BE29: =115934-35506-608-434 -> 79386 | BF29: =125891-41278-460-433 -> 83720 | BG29: =SUM(BC29:BF29) -> 325896 | BH29: =115364-35997-1408-492 -> 77467 | BI29: =135960-45151-1387-381 -> 89041 | BJ29: =136640-48310-876 -> 87454 | BK29: =151524-54753-605 -> 96166 | BL29: =SUM(BH29:BK29) -> 350128 | BM29: =134320-44202-2565 -> 87553 | BN29: 92387 | BO29: 96644 | BP29: =155463-53422-1421 -> 100620 | BQ29: =SUM(BM29:BP29) -> 377204 | BR29: 99935 | BS29: =169630-61865-2600 -> 105165 | BT29: =167626-60806-1918 -> 104902 | BU29: =BU13*BU30 -> 107537.63 | BV29: =SUM(BR29:BU29) -> 417539.63 | BW29: =BW13*BW30 -> 101597.82 | BX29: =BX13*BX30 -> 105718.69 | BY29: =BY13*BY30 -> 108040.06 | BZ29: =BZ13*BZ30 -> 110972.28 | CA29: =SUM(BW29:BZ29) -> 426328.84
C30: % of Revenue | D30: =D29/D13 -> #DIV/0! | E30: =E29/E13 -> #DIV/0! | F30: =F29/F13 -> #DIV/0! | G30: =G29/G13 -> #DIV/0! | H30: =H29/H13 -> #DIV/0! | O30: =O29/O13 -> #DIV/0! | P30: =P29/P13 -> #DIV/0! | Q30: =Q29/Q13 -> #DIV/0! | R30: =R29/R13 -> #DIV/0! | S30: =S29/S13 -> #DIV/0! | T30: =T29/T13 -> #DIV/0! | U30: =U29/U13 -> #DIV/0! | V30: =V29/V13 -> #DIV/0! | ... BT30: =BT29/BT13 -> 0.12818721 | BU30: 0.13 | BV30: =BV29/BV13 -> 0.13008063 | BW30: 0.126 | BX30: 0.125 | BY30: 0.125 | BZ30: 0.127 | CA30: =CA29/CA13 -> 0.12575333
C31: General and Administrative | X31: =63669-11455 -> 52214 | AC31: =64360-11884 -> 52476 | AD31: =18239-3837 -> 14402 | AE31: =18156-3856 -> 14300 | AF31: =19528-3113 -> 16415 | AG31: =25603-2772 -> 22831 | AH31: =SUM(AD31:AG31) -> 67948 | AI31: =103117-84045 -> 19072 | AJ31: =30851-11605 -> 19246 | AK31: =36274-13515-1290 -> 21469 | AL31: =39055-13550-3411 -> 22094 | AM31: =SUM(AI31:AL31) -> 81881 | AN31: =37261-11130-1602 -> 24529 | AO31: =40755-9951-720 -> 30084 | AP31: =33546-9258-735 -> 23553 | AQ31: =35753-9406-540 -> 25807 | AR31: =SUM(AN31:AQ31) -> 103973 | AS31: =38811-9012-1057-694 -> 28048 | AT31: =51446-11442-6746-1544 -> 31714 | AU31: =50256-13361-336-1406 -> 35153 | AV31: 36099 | AW31: =SUM(AS31:AV31) -> 131014 | AX31: =50038-10986-2555 -> 36497 | AY31: =63652-12778-1006-221-3892 -> 45755 | AZ31: =54624-14338-804 -> 39482 | BA31: =64443-16659-334-1207 -> 46243 | BB31: =SUM(AX31:BA31) -> 167977 | BC31: =62578-15392-485 -> 46701 | BD31: =76456-19539-304-1804-292 -> 54517 | BE31: =85553-23384-180-830-363 -> 60796 | BF31: =91641-29810-182-364 -> 61285 | BG31: =SUM(BC31:BF31) -> 223299 | BH31: =104811-40342-431-399 -> 63639 | BI31: =103884-34592-546-296 -> 68450 | BJ31: =108215-36337-564 -> 71314 | BK31: =102711-32502-554 -> 69655 | BL31: =SUM(BH31:BK31) -> 273058 | BM31: =92478-28520-678-1358 -> 61922 | BN31: 51515 | BO31: 66372 | BP31: =98821-30426-1504 -> 66891 | BQ31: =SUM(BM31:BP31) -> 246700 | BR31: 60729 | BS31: =94866-31000-911 -> 62955 | BT31: =98307-32808-728 -> 64771 | BU31: =BU13*BU32 -> 67004.214 | BV31: =SUM(BR31:BU31) -> 255459.21 | BW31: =BW13*BW32 -> 70957.205 | BX31: =BX13*BX32 -> 71042.96 | BY31: =BY13*BY32 -> 73467.237 | BZ31: =BZ13*BZ32 -> 74272.784 | CA31: =SUM(BW31:BZ31) -> 289740.19
C32: % of Revenue | D32: =D31/D13 -> #DIV/0! | E32: =E31/E13 -> #DIV/0! | F32: =F31/F13 -> #DIV/0! | G32: =G31/G13 -> #DIV/0! | H32: =H31/H13 -> #DIV/0! | O32: =O31/O13 -> #DIV/0! | P32: =P31/P13 -> #DIV/0! | Q32: =Q31/Q13 -> #DIV/0! | R32: =R31/R13 -> #DIV/0! | S32: =S31/S13 -> #DIV/0! | T32: =T31/T13 -> #DIV/0! | U32: =U31/U13 -> #DIV/0! | V32: =V31/V13 -> #DIV/0! | ... BT32: =BT31/BT13 -> 0.079148286 | BU32: 0.081 | BV32: =BV31/BV13 -> 0.079585966 | BW32: 0.088 | BX32: 0.084 | BY32: 0.085 | BZ32: 0.085 | CA32: =CA31/CA13 -> 0.085464057
B33: Total Operating Expense | D33: =D27+D29+D31 -> 0 | E33: =E27+E29+E31 -> 0 | F33: =F27+F29+F31 -> 0 | G33: =G27+G29+G31 -> 0 | H33: =H27+H29+H31 -> 0 | O33: =O27+O29+O31 -> 0 | P33: =P27+P29+P31 -> 0 | Q33: =Q27+Q29+Q31 -> 0 | R33: =R27+R29+R31 -> 0 | S33: =S27+S29+S31 -> 0 | T33: =T27+T29+T31 -> 0 | U33: =U27+U29+U31 -> 0 | V33: =V27+V29+V31 -> 0 | ... CA33: =CA27+CA29+CA31 -> 1775291.2
B35: Non-GAAP Operating Income | D35: =D23-D33 -> 0 | E35: =E23-E33 -> 0 | F35: =F23-F33 -> 0 | G35: =G23-G33 -> 0 | H35: =H23-H33 -> 0 | O35: =O23-O33 -> 0 | P35: =P23-P33 -> 0 | Q35: =Q23-Q33 -> 0 | R35: =R23-R33 -> 0 | S35: =S23-S33 -> 0 | T35: =T23-T33 -> 0 | U35: =U23-U33 -> 0 | V35: =V23-V33 -> 0 | ... AG35: =AG23-AG33 -> 2413 | AH35: =SUM(AD35:AG35) -> -11863 | AI35: =AI23-AI33 -> 4669 | AJ35: =AJ23-AJ33 -> 4213 | AK35: =AK23-AK33 -> -1012 | AL35: =AL23-AL33 -> 7312 | AM35: =AM23-AM33 -> 15182 | AN35: =AN23-AN33 -> 10322 | AO35: =AO23-AO33 -> -646 | AP35: =AP23-AP33 -> 16888 | ... CA35: =CA23-CA33 -> 1002159.8
C36: Non-GAAP Operating Margin | D36: =D35/D13 -> #DIV/0! | E36: =E35/E13 -> #DIV/0! | F36: =F35/F13 -> #DIV/0! | G36: =G35/G13 -> #DIV/0! | H36: =H35/H13 -> #DIV/0! | O36: =O35/O13 -> #DIV/0! | P36: =P35/P13 -> #DIV/0! | Q36: =Q35/Q13 -> #DIV/0! | R36: =R35/R13 -> #DIV/0! | S36: =S35/S13 -> #DIV/0! | T36: =T35/T13 -> #DIV/0! | U36: =U35/U13 -> #DIV/0! | V36: =V35/V13 -> #DIV/0! | ... CA36: =CA35/CA13 -> 0.29560499
B38: GAAP Adjustments
C39: Amortization of purchased intangibles | S39: =SUM(O39:R39) -> 0 | X39: =4030+1965 -> 5995 | AC39: =6940+3385 -> 10325 | AD39: 8406 | AE39: 2356 | AF39: 2706 | AG39: 2444 | AH39: =SUM(AD39:AG39) -> 15912 | AI39: 2433 | AJ39: 1768 | AK39: 3889 | AL39: 5012 | AM39: =SUM(AI39:AL39) -> 13102 | AN39: 4733 | AO39: 4420 | AP39: 4305 | AQ39: 4259 | AR39: =SUM(AN39:AQ39) -> 17717 | AS39: 4259 | AT39: 7416 | AU39: 7357 | AV39: 6586 | AW39: =SUM(AS39:AV39) -> 25618 | AX39: 6529 | AY39: 6661 | AZ39: 5971 | BA39: 5608 | BB39: =SUM(AX39:BA39) -> 24769 | BC39: 5608 | BD39: 5033 | BE39: 5113 | BF39: 4953 | BG39: =SUM(BC39:BF39) -> 20707 | BH39: 5032 | BI39: 4944 | BJ39: 4699 | BK39: 4701 | BL39: =SUM(BH39:BK39) -> 19376 | BM39: 4699 | BN39: 6180 | BO39: 6920 | BP39: 6918 | BQ39: =SUM(BM39:BP39) -> 24717 | BR39: 6919 | BS39: 4916 | BT39: 4873 | BU39: =BT39 -> 4873 | BV39: =SUM(BR39:BU39) -> 21581 | BW39: =BU39 -> 4873 | BX39: =BW39 -> 4873 | BY39: =BX39 -> 4873 | BZ39: =BY39 -> 4873 | CA39: =SUM(BW39:BZ39) -> 19492
C40: Stock based compensation | S40: =SUM(O40:R40) -> 0 | X40: =1074+1297+10617+8221+11455 -> 32664 | AC40: =1190+1021+11187+10161+11884 -> 35443 | AD40: 2537 | AE40: 8512 | AF40: 6595 | AG40: 6234 | AH40: =SUM(AD40:AG40) -> 23878 | AI40: 269794 | AJ40: 40165 | AK40: 51748 | AL40: 49271 | AM40: =SUM(AI40:AL40) -> 410978 | AN40: 42271 | AO40: 55792 | AP40: 52736 | AQ40: 55605 | AR40: =SUM(AN40:AQ40) -> 206404 | AS40: 53551 | AT40: 68767 | AU40: 80920 | AV40: =6138+6510+37190+20328+13473 -> 83639 | AW40: =SUM(AS40:AV40) -> 286877 | AX40: 81136 | AY40: 99959 | AZ40: =8095+7270+49663+30074+14338 -> 109440 | BA40: 118007 | BB40: =SUM(AX40:BA40) -> 408542 | BC40: 110723 | BD40: 141207 | BE40: 135247 | BF40: 145923 | BG40: =SUM(BC40:BF40) -> 533100 | BH40: 139752 | BI40: 151673 | BJ40: 159410 | BK40: 161000 | BL40: =SUM(BH40:BK40) -> 611835 | BM40: 137876 | BN40: 164448 | BO40: 153228 | BP40: 149947 | BQ40: =SUM(BM40:BP40) -> 605499 | BR40: 145596 | BS40: 160538 | BT40: 160642 | BU40: 150000 | BV40: =SUM(BR40:BU40) -> 616776 | BW40: 160000 | BX40: 160000 | BY40: 160000 | BZ40: 160000 | CA40: =SUM(BW40:BZ40) -> 640000
C41: Payroll tax on employee stock transactions | S41: =SUM(O41:R41) -> 0 | AC41: 0 | AH41: =SUM(AD41:AG41) -> 0 | AK41: 0 | AL41: 15657 | AM41: =SUM(AI41:AL41) -> 15657 | AN41: 5755 | AO41: 3864 | AP41: 3844 | AQ41: 3257 | AR41: =SUM(AN41:AQ41) -> 16720 | AS41: 6548 | AT41: 9259 | AU41: 8959 | AV41: 9276 | AW41: =SUM(AS41:AV41) -> 34042 | AX41: 16283 | AY41: 11585 | AZ41: 10104 | BA41: 4220 | BB41: =SUM(AX41:BA41) -> 42192 | BC41: 5099 | BD41: 3385 | BE41: 2536 | BF41: 1944 | BG41: =SUM(BC41:BF41) -> 12964 | BH41: 4184 | BI41: 4046 | BJ41: 2852 | BK41: 2600 | BL41: =SUM(BH41:BK41) -> 13682 | BM41: 6404 | BN41: 4772 | BO41: 4274 | BP41: 6343 | BQ41: =SUM(BM41:BP41) -> 21793 | BR41: 12259 | BS41: 8048 | BT41: 6182 | BU41: 6000 | BV41: =SUM(BR41:BU41) -> 32489 | BW41: 6000 | BX41: 6000 | BY41: 6000 | BZ41: 60000 | CA41: =SUM(BW41:BZ41) -> 78000
C42: Acquisition-related expense | S42: =SUM(O42:R42) -> 0 | AC42: 0 | AH42: =SUM(AD42:AG42) -> 0 | AK42: 1768 | AM42: =SUM(AI42:AL42) -> 1768 | AP42: 0 | AR42: =SUM(AN42:AQ42) -> 0 | AS42: 694 | AT42: 6932 | AU42: 336 | AW42: =SUM(AS42:AV42) -> 7962 | AY42: 221 | BB42: =SUM(AX42:BA42) -> 221 | BG42: =SUM(BC42:BF42) -> 0 | BL42: =SUM(BH42:BK42) -> 0 | BM42: 1358 | BN42: 3358 | BO42: -376 | BQ42: =SUM(BM42:BP42) -> 4340 | BV42: =SUM(BR42:BU42) -> 0 | CA42: =SUM(BW42:BZ42) -> 0
C43: Other | S43: =SUM(O43:R43) -> 0 | AC43: =SUM(Y43:AB43) -> 0 | AH43: =SUM(AD43:AG43) -> 0 | AM43: =SUM(AI43:AL43) -> 0 | AR43: =SUM(AN43:AQ43) -> 0 | AW43: =SUM(AS43:AV43) -> 0 | AY43: 3892 | BA43: 1207 | BB43: =SUM(AX43:BA43) -> 5099 | BD43: =1828+1804 -> 3632 | BE43: =28082+830+2677 -> 31589 | BF43: =253+2676 -> 2929 | BG43: =SUM(BC43:BF43) -> 38150 | BH43: =28772+2676 -> 31448 | BI43: =811+1784 -> 2595 | BJ43: =710 -> 710 | BK43: 88 | BL43: =SUM(BH43:BK43) -> 34841 | BM43: =29124 -> 29124 | BN43: 597 | BQ43: =SUM(BM43:BP43) -> 29721 | BV43: =SUM(BR43:BU43) -> 0 | CA43: =SUM(BW43:BZ43) -> 0
B44: Total GAAP and non-cash adjustments | D44: =SUM(D39:D43) -> 0 | E44: =SUM(E39:E43) -> 0 | F44: =SUM(F39:F43) -> 0 | G44: =SUM(G39:G43) -> 0 | H44: =SUM(H39:H43) -> 0 | O44: =SUM(O39:O43) -> 0 | P44: =SUM(P39:P43) -> 0 | Q44: =SUM(Q39:Q43) -> 0 | R44: =SUM(R39:R43) -> 0 | S44: =SUM(S39:S43) -> 0 | T44: =SUM(T39:T43) -> 0 | U44: =SUM(U39:U43) -> 0 | V44: =SUM(V39:V43) -> 0 | ... CA44: =SUM(CA39:CA43) -> 737492
B46: GAAP Operating Income | D46: =D35-D44 -> 0 | E46: =E35-E44 -> 0 | F46: =F35-F44 -> 0 | G46: =G35-G44 -> 0 | H46: =H35-H44 -> 0 | O46: =O35-O44 -> 0 | P46: =P35-P44 -> 0 | Q46: =Q35-Q44 -> 0 | R46: =R35-R44 -> 0 | S46: =S35-S44 -> 0 | T46: =T35-T44 -> 0 | U46: =U35-U44 -> 0 | V46: =V35-V44 -> 0 | ... CA46: =CA35-CA44 -> 264667.82
C47: GAAP Operating Margin | D47: =D46/D13 -> #DIV/0! | E47: =E46/E13 -> #DIV/0! | F47: =F46/F13 -> #DIV/0! | G47: =G46/G13 -> #DIV/0! | H47: =H46/H13 -> #DIV/0! | O47: =O46/O13 -> #DIV/0! | P47: =P46/P13 -> #DIV/0! | Q47: =Q46/Q13 -> #DIV/0! | R47: =R46/R13 -> #DIV/0! | S47: =S46/S13 -> #DIV/0! | T47: =T46/T13 -> #DIV/0! | U47: =U46/U13 -> #DIV/0! | V47: =V46/V13 -> #DIV/0! | ... CA47: =CA46/CA13 -> 0.078068513
C49: Interest expense | S49: =SUM(O49:R49) -> 0 | T49: 0 | U49: 0 | V49: 0 | W49: 0 | X49: -780 | Y49: 0 | Z49: 0 | AA49: 0 | AB49: 0 | AC49: -611 | AD49: -151 | AE49: -169 | AF49: -154 | AG49: -150 | AH49: =SUM(AD49:AG49) -> -624 | AI49: -193 | AJ49: =-47 -> -47 | AK49: =-3503+3147 -> -356 | AL49: =-7101+6360 -> -741 | AM49: =SUM(AI49:AL49) -> -1337 | AN49: =-7156+6454 -> -702 | AO49: =-7273+6548 -> -725 | AP49: =-7364+6645 -> -719 | AQ49: =-7461+6742 -> -719 | AR49: =SUM(AN49:AQ49) -> -2865 | AS49: =-7560+6842 -> -718 | AT49: =-7684+6942 -> -742 | AU49: =-7769+7044 -> -725 | AV49: =-7786+7173 -> -613 | AW49: =SUM(AS49:AV49) -> -2798 | AX49: =-1672+1319 -> -353 | AY49: =-1669+1274 -> -395 | AZ49: =-1485+1255 -> -230 | BA49: =-1617+1250 -> -367 | BB49: =SUM(AX49:BA49) -> -1345 | BC49: =-1649+1284 -> -365 | BD49: =-1632+1198 -> -434 | BE49: =+-1456+1197 -> -259 | BF49: =+-1652+1291 -> -361 | BG49: =SUM(BC49:BF49) -> -1419 | BH49: =-1966+1604 -> -362 | BI49: =-1592+1294 -> -298 | BJ49: -1577 | BK49: -1709 | BL49: =SUM(BH49:BK49) -> -3946 | BM49: -144 | BN49: -544 | BO49: -462 | BP49: -400 | BQ49: =SUM(BM49:BP49) -> -1550 | BR49: -478 | BS49: -828 | BT49: -654 | BU49: -500 | BV49: =SUM(BR49:BU49) -> -2460 | BW49: -500 | BX49: -500 | BY49: -500 | BZ49: -500 | CA49: =SUM(BW49:BZ49) -> -2000
C50: Amortization of debt discount & issuance costs | AG50: 0 | AH50: =SUM(AD50:AG50) -> 0 | AJ50: 0 | AK50: =-3147-71 -> -3218 | AL50: =-6360 -> -6360 | AM50: =SUM(AI50:AL50) -> -9578 | AN50: =-6454 -> -6454 | AO50: -6548 | AP50: =-6645 -> -6645 | AQ50: =-6742 -> -6742 | AR50: =SUM(AN50:AQ50) -> -26389 | AS50: -6842 | AT50: -6942 | AU50: -7044 | AV50: -7173 | AW50: =SUM(AS50:AV50) -> -28001 | AX50: -1319 | AY50: -1274 | AZ50: -1255 | BA50: -1250 | BB50: =SUM(AX50:BA50) -> -5098 | BC50: -1284 | BD50: -1198 | BE50: -1197 | BF50: -1291 | BG50: =SUM(BC50:BF50) -> -4970 | BH50: -1604 | BI50: -1249 | BJ50: =1250+22 -> 1272 | BK50: 1027 | BL50: =SUM(BH50:BK50) -> -554 | BM50: 0 | BP50: 0 | BQ50: =SUM(BM50:BP50) -> 0 | BR50: 0 | BS50: 0 | BT50: 0 | BU50: 0 | BV50: =SUM(BR50:BU50) -> 0 | BW50: 0 | BX50: 0 | BY50: 0 | BZ50: 0 | CA50: =SUM(BW50:BZ50) -> 0
C51: Fair value adj. to strategic investments | AW51: =SUM(AS51:AV51) -> 0 | AX51: 5119 | AY51: 151 | BB51: =SUM(AX51:BA51) -> 5270 | BC51: 340 | BD51: 89 | BE51: -45 | BF51: -4073 | BG51: =SUM(BC51:BF51) -> -3689 | BH51: -119 | BI51: 0 | BK51: -98 | BL51: =SUM(BH51:BK51) -> -217 | BN51: 0 | BQ51: =SUM(BM51:BP51) -> 0 | BV51: =SUM(BR51:BU51) -> 0 | CA51: =SUM(BW51:BZ51) -> 0
C52: Loss on extinguishment of debt | AV52: -33752 | AW52: =SUM(AS52:AV52) -> -33752 | AX52: 0 | BB52: =SUM(AX52:BA52) -> 0 | BG52: =SUM(BC52:BF52) -> 0 | BL52: =SUM(BH52:BK52) -> 0 | BQ52: =SUM(BM52:BP52) -> 0 | BV52: =SUM(BR52:BU52) -> 0 | CA52: =SUM(BW52:BZ52) -> 0
C53: Interest income and other income, net | X53: -3508 | AC53: 1372 | AD53: -110 | AE53: 2034 | AF53: -1225 | AG53: 2436 | AH53: =SUM(AD53:AG53) -> 3135 | AI53: -2228 | AJ53: 2998 | AK53: =3395+71 -> 3466 | AL53: =4794 -> 4794 | AM53: =SUM(AI53:AL53) -> 9030 | AN53: =5217 -> 5217 | AO53: =4531 -> 4531 | AP53: =5801 -> 5801 | AQ53: =3658 -> 3658 | AR53: =SUM(AN53:AQ53) -> 19207 | AS53: =3742 -> 3742 | AT53: 2601 | AU53: -311 | AV53: =2882-33752+33752 -> 2882 | AW53: =SUM(AS53:AV53) -> 8914 | AX53: =6037-5119 -> 918 | AY53: =-1063-151 -> -1214 | AZ53: -940 | BA53: -2621 | BB53: =SUM(AX53:BA53) -> -3857 | BC53: =-4650-340 -> -4990 | BD53: =1003-89 -> 914 | BE53: =820+45 -> 865 | BF53: =7366+4073 -> 11439 | BG53: =SUM(BC53:BF53) -> 8228 | BH53: =12245+119 -> 12364 | BI53: =17455-45 -> 17410 | BJ53: 17673 | BK53: 21516 | BL53: =SUM(BH53:BK53) -> 68963 | BM53: 14109 | BN53: 14630 | BO53: 13006 | BP53: 7818 | BQ53: =SUM(BM53:BP53) -> 49563 | BR53: 14013 | BS53: 12061 | BT53: 10828 | BU53: 10500 | BV53: =SUM(BR53:BU53) -> 47402 | BW53: 10000 | BX53: 9500 | BY53: 9500 | BZ53: 9500 | CA53: =SUM(BW53:BZ53) -> 38500
B54: Non-GAAP Total Other Income (Expense) | D54: =SUM(D49:D53) -> 0 | E54: =SUM(E49:E53) -> 0 | F54: =SUM(F49:F53) -> 0 | G54: =SUM(G49:G53) -> 0 | H54: =SUM(H49:H53) -> 0 | O54: =SUM(O49:O53) -> 0 | P54: =SUM(P49:P53) -> 0 | Q54: =SUM(Q49:Q53) -> 0 | R54: =SUM(R49:R53) -> 0 | S54: =S53 -> 0 | T54: =SUM(T49:T53) -> 0 | U54: =SUM(U49:U53) -> 0 | V54: =SUM(V49:V53) -> 0 | W54: =SUM(W49:W53) -> 0 | X54: =+X49+X53 -> -4288 | Y54: =SUM(Y49:Y53) -> 0 | Z54: =SUM(Z49:Z53) -> 0 | AA54: =SUM(AA49:AA53) -> 0 | AB54: =SUM(AB49:AB53) -> 0 | AC54: =+AC49+AC53 -> 761 | AD54: =+AD49+AD53 -> -261 | AE54: =+AE49+AE53 -> 1865 | AF54: =+AF49+AF53 -> -1379 | AG54: =+AG49+AG53 -> 2286 | AH54: =+AH49+AH53 -> 2511 | AI54: =+AI49+AI53 -> -2421 | AJ54: =+AJ49+AJ53 -> 2951 | ... BI54: =+BI49+BI53 -> 17112 | BJ54: =+BJ49+BJ53+BJ50 -> 17368 | BK54: =SUM(BK49:BK53) -> 20736 | BL54: =SUM(BH54:BK54) -> 67218 | BM54: =+BM49+BM53 -> 13965 | BN54: =+BN49+BN53 -> 14086 | BO54: =+BO49+BO53+BO50 -> 12544 | BP54: =+BP49+BP53 -> 7418 | BQ54: =+BQ49+BQ53 -> 48013 | BR54: =+BR49+BR53 -> 13535 | BS54: =+BS49+BS53 -> 11233 | BT54: =+BT49+BT53 -> 10174 | BU54: =+BU49+BU53 -> 10000 | BV54: =+BV49+BV53 -> 44942 | BW54: =+BW49+BW53 -> 9500 | ... CA54: =+CA49+CA53 -> 36500
B55: GAAP Total Other Income (Expense) | X55: =X49+X50+X53 -> -4288 | AC55: =AC49+AC50+AC53 -> 761 | AD55: =AD49+AD50+AD53 -> -261 | AE55: =AE49+AE50+AE53 -> 1865 | AF55: =AF49+AF50+AF53 -> -1379 | AG55: =AG49+AG50+AG53 -> 2286 | AH55: =AH49+AH50+AH53 -> 2511 | AI55: =AI49+AI50+AI53 -> -2421 | AJ55: =AJ49+AJ50+AJ53 -> 2951 | ... AU55: =AU49+AU50+AU53 -> -8080 | AV55: =AV49+AV50+AV53+AV52 -> -38656 | AW55: =AW49+AW50+AW53+AW52 -> -55637 | AX55: =AX49+AX53+AX52+AX51+AX50 -> 4365 | AY55: =AY49+AY53+AY52+AY51+AY50 -> -2732 | AZ55: =AZ49+AZ53+AZ52+AZ51+AZ50 -> -2425 | BA55: =BA49+BA53+BA52+BA51+BA50 -> -4238 | BB55: =BB49+BB53+BB52+BB51+BB50 -> -5030 | BC55: =BC49+BC53+BC52+BC51+BC50 -> -6299 | BD55: =BD49+BD53+BD52+BD51+BD50 -> -629 | BE55: =BE49+BE53+BE52+BE51+BE50 -> -636 | ... BI55: =BI49+BI53+BI52+BI51+BI50 -> 15863 | BJ55: =BJ49+BJ53+BJ52+BJ51 -> 16096 | BK55: =BK49+BK53 -> 19807 | BL55: =SUM(BH55:BK55) -> 62045 | BM55: =BM49+BM53+BM52+BM51+BM50 -> 13965 | BN55: =BN49+BN53+BN52+BN51+BN50 -> 14086 | BO55: =BO49+BO53+BO52+BO51 -> 12544 | BP55: =BP49+BP53+BP52+BP51+BP50 -> 7418 | BQ55: =BQ49+BQ53+BQ52+BQ51+BQ50 -> 48013 | BR55: =BR49+BR53+BR52+BR51+BR50 -> 13535 | BS55: =BS49+BS53+BS52+BS51+BS50 -> 11233 | BT55: =BT49+BT53+BT52+BT51+BT50 -> 10174 | BU55: =BU49+BU53+BU52+BU51+BU50 -> 10000 | BV55: =BV49+BV53+BV52+BV51+BV50 -> 44942 | BW55: =BW49+BW53+BW52+BW51+BW50 -> 9500 | ... CA55: =CA49+CA53+CA52+CA51+CA50 -> 36500
B57: Adjusted EBITDA | D57: =D66-D49+CF!D7+D40+D39 -> 0 | E57: =E66-E49+CF!E7+E40 -> 0 | F57: =F66-F49+CF!F7+F40 -> 0 | G57: =G66-G49+CF!G7+G40 -> 0 | H57: =H66-H49+CF!H7+H40 -> 0 | O57: =O66-O49+CF!O7+O40+O39 -> 0 | P57: =P66-P49+CF!P7+P40+P39 -> 0 | Q57: =Q66-Q49+CF!Q7+Q40+Q39 -> 0 | R57: =R66-R49+CF!R7+R40+R39 -> 0 | S57: =S66-S53+CF!S7+S40+S39 -> 0 | T57: =T66-T53+CF!T7+T40+T39 -> 0 | U57: =U66-U53+CF!U7+U40+U39+U42+U43 -> 0 | V57: =V66-V53+CF!V7+V40+V39+V42+V43 -> 0 | W57: =W66-W53+CF!W7+W40+W39+W42+W43 -> 0 | X57: =+X35+CF!X8 -> -88705 | Y57: =Y66-Y53+CF!Y7+Y40+Y39+Y43+Y42 -> 0 | Z57: =Z66-Z53+CF!Z7+Z40+Z39+Z43+Z42 -> 0 | AA57: =AA66-AA53+CF!AA7+AA40+AA39+AA43+AA42 -> 0 | AB57: =AB66-AB53+CF!AB7+AB40+AB39+AB43+AB42 -> 0 | AC57: =+AC35+CF!AC8 -> -51903 | AD57: =+AD35+CF!AD8 -> -9041 | AE57: =+AE35+CF!AE8 -> 2430 | AF57: =+AF35+CF!AF8 -> 2570 | AG57: =+AG35+CF!AG8 -> 8016 | AH57: =SUM(AD57:AG57) -> 3975 | AI57: =+AI35+CF!AI8 -> 10836 | AJ57: =+AJ35+CF!AJ8 -> 9526 | AK57: =+AK35+CF!AK8 -> 5442 | AL57: =+AL35+CF!AL8 -> 14303 | AM57: =AM66-AM53+CF!AM7+AM40+AM39+AM42+AM43 -> 36215 | AN57: =+AN35+CF!AN8 -> 17560 | AO57: =+AO35+CF!AO8 -> 7224 | AP57: =+AP35+CF!AP8 -> 25238 | AQ57: =+AQ35+CF!AQ8 -> 29775 | AR57: =AR66-AR53+CF!AR7+AR40+AR39+AR42+AR43 -> 77929 | AS57: =+AS35+CF!AS8 -> 32979 | AT57: =+AT35+CF!AT8 -> 44260 | AU57: =AU66-AU49+CF!AU7+AU40+AU39+AU41-AU50-AU53+AU43-AU51+AU42-AU52 -> 68581 | AV57: =AV66-AV49+CF!AV7+AV40+AV39+AV41-AV50-AV53+AV43-AV51+AV42-AV52 -> 94239 | AW57: =AW66-AW53+CF!AW7+AW40+AW39+AW42+AW43 -> 153141 | AX57: =AX66-AX49+CF!AX7+AX40+AX39+AX41-AX50-AX53+AX43-AX51+AX42 -> 113248 | AY57: =AY66-AY49+CF!AY7+AY40+AY39+AY41-AY50-AY53+AY43-AY51+AY42 -> 120667 | AZ57: =AZ66-AZ49+CF!AZ7+AZ40+AZ39+AZ41-AZ50-AZ53+AZ43-AZ51 -> 142323 | BA57: =BA66-BA49+CF!BA7+BA40+BA39+BA41-BA50-BA53+BA43-BA51 -> 124614 | BB57: =BB66-BB49+CF!BB7+BB40+BB39+BB41-BB50-BB53+BB43-BB51+BB42 -> 500852 | BC57: =BC66-BC49+CF!BC7+BC40+BC39+BC41-BC50-BC53+BC43-BC51 -> 123505 | BD57: =BD66-BD49+CF!BD7+BD40+BD39+BD41-BD50-BD53+BD43-BD51 -> 133310 | BE57: =BE66-BE49+CF!BE7+BE40+BE39+BE41-BE50-BE53+BE43-BE51 -> 168586 | BF57: =BF66-BF49+CF!BF7+BF40+BF39+BF41-BF50-BF53+BF43-BF51 -> 177744 | BG57: =BG66-BG49+CF!BG7+BG40+BG39+BG41-BG50-BG53+BG43-BG51 -> 603145 | BH57: =BH66-BH49+CF!BH7+BH40+BH39+BH41-BH50-BH53+BH43-BH51 -> 198632 | BI57: =BI66-BI49+CF!BI7+BI40+BI39+BI41-BI50-BI53+BI43-BI51-BI52 -> 195108 | BJ57: =BJ66-BJ49+CF!BJ7+BJ40+BJ39+BJ41-BJ53+BJ43-BJ51-BJ52 -> 210733 | BK57: =BK66-BK49+CF!BK7+BK40+BK39+BK41-BK50-BK53+BK43-BK51-BK52 -> 201028 | BL57: =BL66-BL49+CF!BL7+BL40+BL39+BL41-BL50-BL53+BL43-BL51-BL52 -> 804229 | BM57: =BM66-BM49+CF!BM7+BM40+BM39+BM41-BM50-BM53+BM43-BM51 -> 225237 | BN57: =BN66-BN49+CF!BN7+BN40+BN39+BN41-BN50-BN53+BN43-BN51-BN52 -> 260820 | BO57: =BO66-BO49+CF!BO7+BO40+BO39+BO41-BO53+BO43-BO51-BO52 -> 251021 | BP57: =BP66-BP49+CF!BP7+BP40+BP39+BP41-BP50-BP53+BP43-BP51-BP52 -> 252384 | BQ57: =BQ66-BQ49+CF!BQ7+BQ40+BQ39+BQ41-BQ50-BQ53+BQ43-BQ51-BQ52 -> 989462 | BR57: =BR66-BR49+CF!BR7+BR40+BR39+BR41-BR50-BR53+BR43-BR51 -> 255398 | BS57: =BS66-BS49+CF!BS7+BS40+BS39+BS41-BS50-BS53+BS43-BS51-BS52 -> 267609 | BT57: =BT66-BT49+CF!BT7+BT40+BT39+BT41-BT50-BT53+BT43-BT51-BT52 -> 287451 | BU57: =BU66-BU49+CF!BU7+BU40+BU39+BU41-BU50-BU53+BU43-BU51-BU52 -> 285944.48 | BV57: =BV66-BV49+CF!BV7+BV40+BV39+BV41-BV50-BV53+BV43-BV51-BV52 -> 1096402.5 | BW57: =BW66-BW49+CF!BW7+BW40+BW39+BW41-BW50-BW53+BW43-BW51 -> 277870.72 | BX57: =BX66-BX49+CF!BX7+BX40+BX39+BX41-BX50-BX53+BX43-BX51-BX52 -> 295285.35 | BY57: =BY66-BY49+CF!BY7+BY40+BY39+BY41-BY50-BY53+BY43-BY51-BY52 -> 304169.99 | BZ57: =BZ66-BZ49+CF!BZ7+BZ40+BZ39+BZ41-BZ50-BZ53+BZ43-BZ51-BZ52 -> 306258.49 | CA57: =CA66-CA49+CF!CA7+CA40+CA39+CA41-CA50-CA53+CA43-CA51-CA52 -> 1183584.5
C58: EBITDA Margins | D58: =D57/D13 -> #DIV/0! | E58: =E57/E13 -> #DIV/0! | F58: =F57/F13 -> #DIV/0! | G58: =G57/G13 -> #DIV/0! | H58: =H57/H13 -> #DIV/0! | O58: =O57/O13 -> #DIV/0! | P58: =P57/P13 -> #DIV/0! | Q58: =Q57/Q13 -> #DIV/0! | R58: =R57/R13 -> #DIV/0! | S58: =S57/S13 -> #DIV/0! | T58: =T57/T13 -> #DIV/0! | U58: =U57/U13 -> #DIV/0! | V58: =V57/V13 -> #DIV/0! | ... CA58: =CA57/CA13 -> 0.34911946
B60: Non-GAAP Pre-Tax Income | D60: =D35+D54 -> 0 | E60: =E35+E54 -> 0 | F60: =F35+F54 -> 0 | G60: =G35+G54 -> 0 | H60: =H35+H54 -> 0 | O60: =O35+O54 -> 0 | P60: =P35+P54 -> 0 | Q60: =Q35+Q54 -> 0 | R60: =R35+R54 -> 0 | S60: =S35+S54 -> 0 | T60: =T35+T54 -> 0 | U60: =U35+U54 -> 0 | V60: =V35+V54 -> 0 | ... AG60: =AG35+AG54 -> 4699 | AH60: =SUM(AD60:AG60) -> -9352 | AI60: =AI35+AI54 -> 2248 | AJ60: =AJ35+AJ54 -> 7164 | AK60: =+AK35+AK54 -> 2098 | AL60: =AL35+AL54 -> 11365 | AM60: =AM35+AM54 -> 22875 | AN60: =AN35+AN54 -> 14837 | AO60: =AO35+AO54 -> 3160 | AP60: =+AP35+AP54 -> 21970 | AQ60: =AQ35+AQ54 -> 23707 | AR60: =AR35+AR54 -> 63674 | AS60: =AS35+AS54 -> 26223 | AT60: =AT35+AT54 -> 35598 | AU60: =AU35+AU54 -> 48066 | AV60: =AV35+AV54 -> 76873 | AW60: =AW35+AW54 -> 186760 | AX60: =AX35+AX54 -> 93776 | ... CA60: =CA35+CA54 -> 1038659.8
C61: Income Tax | X61: =X67 -> -1033 | AC61: =AC67 -> 356 | AD61: =AD67 -> -143 | AE61: =AE67 -> 121 | AF61: =AF67 -> 783 | AG61: =AG67 -> 2373 | AH61: =SUM(AD61:AG61) -> 3134 | AI61: =AI67 -> 708 | AJ61: =AJ67 -> 1945 | AK61: =AK67+7369 -> 1657 | AL61: =AL67-289 -> 1020 | AM61: =SUM(AI61:AL61) -> 5330 | AN61: =AN67 -> 1346 | AO61: =AO67 -> 1168 | AP61: =AP67 -> 1038 | AQ61: =AQ67 -> 1251 | AR61: =SUM(AN61:AQ61) -> 4803 | AS61: 2133 | AT61: =AT67 -> 842 | AU61: 1941 | AV61: =8859-9294 -> -435 | AW61: =SUM(AS61:AV61) -> 4481 | AX61: 1982 | AY61: 158 | AZ61: -107 | BA61: 1029 | BB61: =SUM(AX61:BA61) -> 3062 | BC61: =BC67+17522 -> 19370 | BD61: =BD67+19171 -> 22530 | BE61: =BE67+27733 -> 29532 | BF61: =BF67+32742 -> 33309 | BG61: =SUM(BC61:BF61) -> 104741 | BH61: =BH67+32464 -> 37553 | BI61: =BI67+22325 -> 37405 | BJ61: =BJ67+43922 -> 40951 | BK61: =BK67+37311 -> 39812 | BL61: =SUM(BH61:BK61) -> 155721 | BM61: =BM67+40378 -> 43211 | BN61: =BN67+866572 -> 50248 | BO61: =BO67+37973 -> 47124 | BP61: =BP67+61823 -> 46219 | BQ61: =SUM(BM61:BP61) -> 186802 | BR61: =BR67+46010 -> 47713 | BS61: =BS67+41387 -> 54877 | BT61: =BT67+44313 -> 56117 | BU61: =BU60*BU62 -> 49170.307 | BV61: =SUM(BR61:BU61) -> 207877.31 | BW61: =BW60*BW62 -> 47953.222 | BX61: =BX60*BX62 -> 51576.136 | BY61: =BY60*BY62 -> 53788.089 | BZ61: =BZ60*BZ62 -> 54414.516 | CA61: =SUM(BW61:BZ61) -> 207731.96
C62: Tax Rate % | D62: =D61/D60 -> #DIV/0! | E62: =E61/E60 -> #DIV/0! | F62: =F61/F60 -> #DIV/0! | G62: =G61/G60 -> #DIV/0! | H62: =H61/H60 -> #DIV/0! | O62: =O61/O60 -> #DIV/0! | P62: =P61/P60 -> #DIV/0! | Q62: =Q61/Q60 -> #DIV/0! | R62: =R61/R60 -> #DIV/0! | S62: =S61/S60 -> #DIV/0! | T62: =T61/T60 -> #DIV/0! | U62: =U61/U60 -> #DIV/0! | V62: =V61/V60 -> #DIV/0! | ... BT62: =BT61/BT60 -> 0.20999828 | BU62: 0.2 | BV62: =BV61/BV60 -> 0.2075445 | BW62: 0.2 | BX62: 0.2 | BY62: 0.2 | BZ62: 0.2 | CA62: =CA61/CA60 -> 0.2
B63: Non-GAAP Net Income (Loss) | D63: =D60-D61 -> 0 | E63: =E60-E61 -> 0 | F63: =F60-F61 -> 0 | G63: =G60-G61 -> 0 | H63: =H60-H61 -> 0 | O63: =O60-O61 -> 0 | P63: =P60-P61 -> 0 | Q63: =Q60-Q61 -> 0 | R63: =R60-R61 -> 0 | S63: =S60-S61 -> 0 | T63: =T60-T61 -> 0 | U63: =U60-U61 -> 0 | V63: =V60-V61 -> 0 | ... CA63: =CA60-CA61 -> 830927.85
C64: Non-GAAP Net Margin | D64: =D63/D13 -> #DIV/0! | E64: =E63/E13 -> #DIV/0! | F64: =F63/F13 -> #DIV/0! | G64: =G63/G13 -> #DIV/0! | H64: =H63/H13 -> #DIV/0! | O64: =O63/O13 -> #DIV/0! | P64: =P63/P13 -> #DIV/0! | Q64: =Q63/Q13 -> #DIV/0! | R64: =R63/R13 -> #DIV/0! | S64: =S63/S13 -> #DIV/0! | T64: =T63/T13 -> #DIV/0! | U64: =U63/U13 -> #DIV/0! | V64: =V63/V13 -> #DIV/0! | ... CA64: =CA63/CA13 -> 0.24509705
B66: GAAP Pre-Tax Income | D66: =D46+D54 -> 0 | E66: =E46+E54 -> 0 | F66: =F46+F54 -> 0 | G66: =G46+G54 -> 0 | H66: =H46+H54 -> 0 | O66: =O46+O54 -> 0 | P66: =P46+P54 -> 0 | Q66: =Q46+Q54 -> 0 | R66: =R46+R54 -> 0 | S66: =S46+S54 -> 0 | T66: =T46+T54 -> 0 | U66: =U46+U54 -> 0 | V66: =V46+V54 -> 0 | ... AJ66: =AJ46+AJ54 -> -34769 | AK66: =+AK46+AK55 -> -58525 | AL66: =+AL46+AL55 -> -64935 | AM66: =AM46+AM54 -> -418630 | AN66: =+AN46+AN55 -> -44376 | AO66: =+AO46+AO55 -> -67464 | AP66: =+AP46+AP55 -> -45560 | AQ66: =+AQ46+AQ55 -> -46156 | AR66: =AR46+AR54 -> -177167 | AS66: =+AS46+AS55 -> -45671 | AT66: =AT46+AT55 -> -63718 | AU66: =AU46+AU55 -> -56550 | AV66: =AV46+AV55 -> -63553 | AW66: =AW46+AW55 -> -229492 | AX66: =AX46+AX55 -> -6372 | AY66: =AY46+AY55 -> -25343 | AZ66: =AZ46+AZ55 -> -5783 | BA66: =BA46+BA55 -> -29416 | ... CA66: =CA46+CA55 -> 301167.82
C67: Income Tax | X67: -1033 | AC67: 356 | AD67: -143 | AE67: 121 | AF67: 783 | AG67: 2373 | AH67: =SUM(AD67:AG67) -> 3134 | AI67: 708 | AJ67: 1945 | AK67: -5712 | AL67: 1309 | AM67: =SUM(AI67:AL67) -> -1750 | AN67: 1346 | AO67: 1168 | AP67: 1038 | AQ67: 1251 | AR67: =SUM(AN67:AQ67) -> 4803 | AS67: =AS61 -> 2133 | AT67: 842 | AU67: =AU61 -> 1941 | AV67: 8859 | AW67: =SUM(AS67:AV67) -> 13775 | AX67: 1982 | AY67: =AY61 -> 158 | AZ67: -107 | BA67: =BA61 -> 1029 | BB67: =SUM(AX67:BA67) -> 3062 | BC67: 1848 | BD67: 3359 | BE67: 1799 | BF67: 567 | BG67: =SUM(BC67:BF67) -> 7573 | BH67: 5089 | BI67: 15080 | BJ67: -2971 | BK67: 2501 | BL67: =SUM(BH67:BK67) -> 19699 | BM67: 2833 | BN67: -816324 | BO67: 9151 | BP67: -15604 | BQ67: =SUM(BM67:BP67) -> -819944 | BR67: 1703 | BS67: 13490 | BT67: 11804 | BU67: 6000 | BV67: =SUM(BR67:BU67) -> 32997 | BW67: 8000 | BX67: 8000 | BY67: 8000 | BZ67: 8000 | CA67: =SUM(BW67:BZ67) -> 32000
C68: Tax Rate % | D68: =D67/D66 -> #DIV/0! | E68: =E67/E66 -> #DIV/0! | F68: =F67/F66 -> #DIV/0! | G68: =G67/G66 -> #DIV/0! | H68: =H67/H66 -> #DIV/0! | O68: =O67/O66 -> #DIV/0! | P68: =P67/P66 -> #DIV/0! | Q68: =Q67/Q66 -> #DIV/0! | R68: =R67/R66 -> #DIV/0! | S68: =S67/S66 -> #DIV/0! | T68: =T67/T66 -> #DIV/0! | U68: =U67/U66 -> #DIV/0! | V68: =V67/V66 -> #DIV/0! | ... AA68: =AA67/AA66 -> #DIV/0! | AB68: -0.3 | AC68: =AC67/AC66 -> -0.0030941455 | AD68: =AD67/AD66 -> 0.0073239437 | AE68: =AE67/AE66 -> -0.010154414 | AF68: =AF67/AF66 -> -0.057061653 | AG68: =AG67/AG66 -> -0.596381 | AH68: =AH67/AH66 -> -0.063774368 | AI68: =AI67/AI66 -> -0.0026224262 | AJ68: =AJ67/AJ66 -> -0.055940637 | ... CA68: =CA67/CA66 -> 0.10625305
C69: NI allocated to participating securities | AG69: -1462 | AH69: =SUM(AD69:AG69) -> -1462 | AI69: -871
C70: Preferred stock accretion | S70: =SUM(O70:R70) -> 0 | AD70: -355 | AE70: -366 | AF70: -376 | AG70: -364 | AH70: =SUM(AD70:AG70) -> -1461 | AI70: -353
B71: GAAP Net Income | D71: =D66-D67 -> 0 | E71: =E66-E67 -> 0 | F71: =F66-F67 -> 0 | G71: =G66-G67 -> 0 | H71: =H66-H67 -> 0 | O71: =O66-O67 -> 0 | P71: =P66-P67+P70 -> 0 | Q71: =Q66-Q67+Q70 -> 0 | R71: =R66-R67+R70 -> 0 | S71: =S66-S67+S70 -> 0 | T71: =T66-T67 -> 0 | U71: =U66-U67 -> 0 | V71: =V66-V67 -> 0 | W71: =W66-W67 -> 0 | X71: =X66-X67 -> -124624 | Y71: =Y66-Y67 -> 0 | Z71: =Z66-Z67 -> 0 | AA71: =AA66-AA67 -> 0 | ... CA71: =CA66-CA67 -> 269167.82
C72: GAAP Net Margin | D72: =D71/D13 -> #DIV/0! | E72: =E71/E13 -> #DIV/0! | F72: =F71/F13 -> #DIV/0! | G72: =G71/G13 -> #DIV/0! | H72: =H71/H13 -> #DIV/0! | O72: =O71/O13 -> #DIV/0! | P72: =P71/P13 -> #DIV/0! | Q72: =Q71/Q13 -> #DIV/0! | R72: =R71/R13 -> #DIV/0! | S72: =S71/S13 -> #DIV/0! | T72: =T71/T13 -> #DIV/0! | U72: =U71/U13 -> #DIV/0! | V72: =V71/V13 -> #DIV/0! | ... CA72: =CA71/CA13 -> 0.079395869
B74: Non-GAAP EPS | D74: =IF(D63>0,D63/D80,D63/D79) -> 0 | E74: =IF(E63>0,E63/E80,E63/E79) -> 0 | F74: =IF(F63>0,F63/F80,F63/F79) -> 0 | G74: =IF(G63>0,G63/G80,G63/G79) -> 0 | H74: =IF(H63>0,H63/H80,H63/H79) -> 0 | O74: =IF(O63>0,O63/O80,O63/O79) -> #DIV/0! | P74: =IF(P63>0,P63/P80,P63/P79) -> #DIV/0! | Q74: =IF(Q63>0,Q63/Q80,Q63/Q79) -> #DIV/0! | R74: =IF(R63>0,R63/R80,R63/R79) -> #DIV/0! | T74: =IF(T63>0,T63/T80,T63/T79) -> #DIV/0! | U74: =IF(U63>0,U63/U80,U63/U79) -> #DIV/0! | V74: =IF(V63>0,V63/V80,V63/V79) -> #DIV/0! | W74: =IF(W63>0,W63/W80,W63/W79) -> #DIV/0! | X74: =IF(X63>0,X63/X80,X63/X79) -> -3.2997467 | Y74: =IF(Y63>0,Y63/Y80,Y63/Y79) -> #DIV/0! | Z74: =IF(Z63>0,Z63/Z80,Z63/Z79) -> #DIV/0! | AA74: =IF(AA63>0,AA63/AA80,AA63/AA79) -> #DIV/0! | ... AC74: =IF(AC63>0,AC63/AC80,AC63/AC79) -> -2.4855265 | AD74: =(AD63+AD70+AD69)/AD80 -> -0.29547745 | AE74: =(AE63+AE70)/AE80 -> -0.048935221 | AF74: =(AF63+AF70)/AF80 -> -0.16730129 | AG74: =(AG63+AG70+AG69)/AG80 -> 0.011785226 | AH74: =IF(AH63>0,AH63/AH80,AH63/AH79) -> -0.38688644 | AI74: =(AI63+AI70+AI69)/AI80 -> 0.0052520485 | AJ74: =IF(AJ63>0,AJ63/AJ80,AJ63/AJ79) -> 0.027264226 | AK74: =IF(AK63>0,AK63/AK80,AK63/AK79) -> 0.0022941746 | AL74: =IF(AL63>0,AL63/AL80,AL63/AL79) -> 0.055126586 | AM74: =IF(AM63>0,AM63/AM80,AM63/AM79) -> 0.11113662 | AN74: =IF(AN63>0,AN63/AN80,AN63/AN79) -> 0.071312658 | AO74: =IF(AO63>0,AO63/AO80,AO63/AO79) -> 0.010520701 | AP74: =IF(AP63>0,AP63/AP80,AP63/AP79) -> 0.1097111 | AQ74: =IF(AQ63>0,AQ63/AQ80,AQ63/AQ79) -> 0.1159151 | ... CA74: =IF(CA63>0,CA63/CA80,CA63/CA79) -> 4.0618464
C75: Y/Y Growth % | O75: N/A | P75: N/A | Q75: N/A | R75: N/A | Y75: =Y74/T74-1 -> #DIV/0! | Z75: =Z74/U74-1 -> #DIV/0! | AA75: =AA74/V74-1 -> #DIV/0! | AB75: =AB74/W74-1 -> #DIV/0! | AC75: =AC74/X74-1 -> -0.24675233 | AD75: =AD74/Y74-1 -> #DIV/0! | AE75: =AE74/Z74-1 -> #DIV/0! | AF75: =AF74/AA74-1 -> #DIV/0! | ... CA75: =CA74/BV74-1 -> 0.071343755
B76: GAAP EPS | D76: =D71/D80 -> 0 | E76: =E71/E80 -> 0 | F76: =F71/F80 -> 0 | G76: =G71/G80 -> 0 | H76: =H71/H80 -> 0 | O76: =O71/O80 -> #DIV/0! | P76: =P71/P80 -> #DIV/0! | Q76: =Q71/Q80 -> #DIV/0! | R76: =R71/R80 -> #DIV/0! | T76: =T71/T80 -> #DIV/0! | U76: =U71/U80 -> #DIV/0! | V76: =V71/V80 -> #DIV/0! | W76: =W71/W80 -> #DIV/0! | X76: =X71/X80 -> -4.7836634 | Y76: =Y71/Y80 -> #DIV/0! | Z76: =Z71/Z80 -> #DIV/0! | AA76: =AA71/AA80 -> #DIV/0! | ... AC76: =AC71/AC80 -> -4.1189418 | AD76: =(AD71+AD70)/AD79 -> -0.66316545 | AE76: =(AE71+AE70)/AE79 -> -0.39202436 | AF76: =(AF71+AF70)/AF79 -> -0.44616676 | AG76: =(AG71+AG70)/AG79 -> -0.19557937 | AH76: =AH71/AH79 -> -1.6198042 | AI76: =(AI71+AI70)/AI79 -> -7.4596796 | AJ76: =AJ71/AJ79 -> -0.22105681 | AK76: =AK71/AK79 -> -0.31485787 | AL76: =AL71/AL79 -> -0.39603274 | AM76: =AM71/AM79 -> -3.1028073 | AN76: =AN71/AN79 -> -0.26566958 | AO76: =AO71/AO79 -> -0.39131302 | AP76: =AP71/AP79 -> -0.26132553 | AQ76: =AQ71/AQ79 -> -0.26212132 | AR76: =IF(AR71>0,AR71/AR80,AR71/AR79) -> -1.0300242 | AS76: =IF(AS71>0,AS71/AS80,AS71/AS79) -> -0.26125545 | AT76: =IF(AT71>0,AT71/AT80,AT71/AT79) -> -0.34923348 | AU76: =IF(AU71>0,AU71/AU80,AU71/AU79) -> -0.3137542 | AV76: =IF(AV71>0,AV71/AV80,AV71/AV79) -> -0.38370682 | AW76: =IF(AW71>0,AW71/AW80,AW71/AW79) -> -1.3096826 | AX76: =IF(AX71>0,AX71/AX80,AX71/AX79) -> -0.042986076 | AY76: =IF(AY71>0,AY71/AY80,AY71/AY79) -> -0.1301098 | ... CA76: =IF(CA71>0,CA71/CA80,CA71/CA79) -> 1.3157801
C77: Y/Y Growth % | O77: N/A | P77: N/A | Q77: N/A | R77: N/A | Y77: =Y76/T76-1 -> #DIV/0! | Z77: =Z76/U76-1 -> #DIV/0! | AA77: =AA76/V76-1 -> #DIV/0! | AB77: =AB76/W76-1 -> #DIV/0! | AC77: =AC76/X76-1 -> -0.1389566 | AD77: =AD76/Y76-1 -> #DIV/0! | AE77: =AE76/Z76-1 -> #DIV/0! | AF77: =AF76/AA76-1 -> #DIV/0! | ... CA77: =CA76/BV76-1 -> -0.074892382
B79: Basic Shares Outstanding | D79: 52876.999 | E79: 54419.498 | F79: 55146.901 | G79: 55688.824 | H79: 54209.685 | X79: 26052 | AC79: 28019.818 | AD79: 29761.804 | AE79: 31638.34 | AF79: 33353 | AG79: 34339 | AH79: =AVERAGE(AD79:AG79) -> 32273.036 | AI79: 36334 | AJ79: 166084 | AK79: 167736 | AL79: 167269 | AM79: =AVERAGE(AI79:AL79) -> 134355.75 | AN79: 172101 | AO79: 175389 | AP79: 178314 | AQ79: 180859 | AR79: =AVERAGE(AN79:AQ79) -> 176665.75 | AS79: 182978 | AT79: 184862 | AU79: 186423 | AV79: 188717 | AW79: =AVERAGE(AS79:AV79) -> 185745 | AX79: 194342 | AY79: 195996 | AZ79: 197597 | BA79: 198687 | BB79: =AVERAGE(AX79:BA79) -> 196655.5 | BC79: 199666 | BD79: 200618 | BE79: 201393 | BF79: 201894 | BG79: =AVERAGE(BC79:BF79) -> 200892.75 | BH79: 202631 | BI79: 203703 | BJ79: 204456 | BK79: 205514 | BL79: =AVERAGE(BH79:BK79) -> 204076 | BM79: 205870 | BN79: 204604 | BO79: 203567 | BP79: 203299 | BQ79: =AVERAGE(BM79:BP79) -> 204335 | BR79: 203280 | BS79: 202644 | BT79: 201954 | BU79: =+BT79-100 -> 201854 | BV79: =AVERAGE(BR79:BU79) -> 202433 | BW79: =+BV79 -> 202433 | BX79: =+BW79 -> 202433 | BY79: =+BX79 -> 202433 | BZ79: =+BY79 -> 202433 | CA79: =AVERAGE(BW79:BZ79) -> 202433
B80: Diluted Shares Outstanding | D80: 55008.742 | E80: 56389.729 | F80: 57150.256 | G80: 57760.868 | H80: 54209.685 | X80: 26052 | AC80: 28019.818 | AD80: 29762 | AE80: 31368 | AF80: 33353 | AG80: 42426 | AH80: =AVERAGE(AD80:AG80) -> 34227.25 | AI80: 60167 | AJ80: 191423 | AK80: 192226 | AL80: 187659 | AM80: =AVERAGE(AI80:AL80) -> 157868.75 | AN80: 189181 | AO80: 189341 | AP80: 190792 | AQ80: 193728 | AR80: =AVERAGE(AN80:AQ80) -> 190760.5 | AS80: 196925 | AT80: 203409 | AU80: 205848 | AV80: 208514 | AW80: =AVERAGE(AS80:AV80) -> 203674 | AX80: 207881 | AY80: 208150 | AZ80: 208105 | BA80: 207161 | BB80: =AVERAGE(AX80:BA80) -> 207824.25 | BC80: 205975 | BD80: 205642 | BE80: 205648 | BF80: 206260 | BG80: =AVERAGE(BC80:BF80) -> 205881.25 | BH80: 208071 | BI80: 208192 | BJ80: 208054 | BK80: 209581 | BL80: =AVERAGE(BH80:BK80) -> 208474.5 | BM80: 209896 | BN80: 208274 | BO80: 208706 | BP80: 214507 | BQ80: =AVERAGE(BM80:BP80) -> 210345.75 | BR80: 212812 | BS80: 210956 | BT80: 208069 | BU80: =+BT80-2500 -> 205569 | BV80: =AVERAGE(BR80:BU80) -> 209351.5 | BW80: =+BU80-1000 -> 204569 | BX80: =+BW80 -> 204569 | BY80: =+BX80 -> 204569 | BZ80: =+BY80 -> 204569 | CA80: =AVERAGE(BW80:BZ80) -> 204569
B82: Deferred Revenue | D82: =BS!D49 -> 0 | E82: =BS!E49 -> 0 | F82: =BS!F49 -> 0 | G82: =BS!G49 -> 0 | H82: =BS!H49 -> 0 | I82: =BS!I49 -> 0 | J82: =BS!J49 -> 0 | K82: =BS!K49 -> 0 | ... Y82: =BS!Y49 -> 23296 | Z82: 70521 | AA82: =BS!AA49 -> 29796 | AB82: =BS!AB49 -> 32712 | AC82: =BS!AC49 -> 32712 | AD82: =BS!AD49 -> 40812 | AE82: =BS!AE49 -> 47762 | AF82: =BS!AF49 -> 50895 | AG82: =BS!AG49 -> 277924 | AH82: =AG82 -> 277924 | AI82: =BS!AI49 -> 290535 | AJ82: =BS!AJ49 -> 297427 | AK82: =BS!AK49 -> 323754 | AL82: =BS!AL49 -> 388772 | AM82: =AL82 -> 388772 | AN82: =BS!AN49 -> 393046 | AO82: =BS!AO49 -> 410518 | AP82: =BS!AP49 -> 433081 | AQ82: =BS!AQ49 -> 519038 | AR82: =AQ82 -> 519038 | AS82: =BS!AS49 -> 563632 | AT82: =BS!AT49 -> 635868 | AU82: =BS!AU49 -> 700902 | AV82: =BS!AV49 -> 796134 | AW82: =AV82 -> 796134 | AX82: =BS!AX49 -> 847782 | AY82: =BS!AY49 -> 932757 | AZ82: =BS!AZ49 -> 957181 | BA82: =BS!BA49 -> 1046616 | BC82: =BS!BC49 -> 1065328 | BD82: =BS!BD49 -> 1088430 | BE82: =BS!BE49 -> 1103439 | BF82: =BS!BF49 -> 1189792 | BH82: =BS!BH49 -> 1208079 | BI82: =BS!BI49 -> 1230250 | BJ82: =BS!BJ49 -> 1226668 | BK82: =BS!BK49 -> 1342039 | BM82: =BS!BM49 -> 1337067 | BN82: =BS!BN49 -> 1330585 | BO82: =BS!BO49 -> 1330680 | BP82: =BS!BP49 -> 1476965 | BR82: =BS!BR49 -> 1447232 | BS82: =BS!BS49 -> 1463461 | BT82: =BS!BT49 -> 1472626
B83: Cash Flow-Operating | D83: =CF!C33 -> 0 | E83: =CF!E33 -> 0 | F83: =CF!F33 -> 0 | G83: =CF!G33 -> 0 | H83: =CF!H33 -> 0 | I83: =CF!I33 -> 0 | J83: =CF!J33 -> 0 | K83: =CF!K33 -> 0 | L83: =CF!L33 -> 0 | ... BK83: =CF!BK33 -> 270698 | BM83: =CF!BM33 -> 254826 | BN83: =CF!BN33 -> 220208 | BO83: =CF!BO33 -> 234326 | BP83: =CF!BP33 -> 307912 | BR83: =CF!BR33 -> 251439 | BS83: =CF!BS33 -> 246073 | BT83: =CF!BT33 -> 290274
B84: Cash & Equivalents | D84: =BS!D6 -> 0 | E84: =BS!E6 -> 0 | F84: =BS!F6 -> 0 | G84: =BS!G6 -> 0 | H84: =BS!H6 -> 0 | S84: =BS!S6 -> 0 | T84: =BS!T6 -> 0 | U84: =BS!U6 -> 0 | V84: =BS!V6 -> 0 | W84: =BS!W6 -> 0 | X84: =BS!X6 -> 228523 | Y84: =BS!Y6 -> 0 | Z84: =BS!Z6 -> 0 | ... AC84: =BS!AC6 -> 190556 | AD84: =(BS!AD6+BS!AD7) -> 0 | AE84: =(BS!AE6+BS!AE7) -> 0 | AF84: =(BS!AF6+BS!AF7) -> 0 | AG84: =(BS!AG6+BS!AG7) -> 256867 | AH84: =AG84 -> 256867 | AI84: =(BS!AI6+BS!AI7) -> 269429 | AJ84: =(BS!AJ6+BS!AJ7) -> 818795 | AK84: =(BS!AK6+BS!AK7) -> 1094133 | AL84: =(BS!AL6+BS!AL7) -> 769014 | AM84: =AL84 -> 769014 | AN84: =(BS!AN6+BS!AN7) -> 752124 | AO84: =(BS!AO6+BS!AO7) -> 750253 | AP84: =(BS!AP6+BS!AP7) -> 653777 | AQ84: =(BS!AQ6+BS!AQ7) -> 656142 | AR84: =AQ84 -> 656142 | AS84: =(BS!AS6+BS!AS7) -> 757949 | AT84: =(BS!AT6+BS!AT7) -> 674039 | AU84: =(BS!AU6+BS!AU7) -> 598574 | AV84: =(BS!AV6+BS!AV7) -> 773505 | AW84: =AV84 -> 773505 | AX84: =(BS!AX6+BS!AX7) -> 780632 | AY84: =(BS!AY6+BS!AY7) -> 822869 | AZ84: =(BS!AZ6+BS!AZ7) -> 818458 | BA84: =(BS!BA6+BS!BA7) -> 802822 | BC84: =(BS!BC6+BS!BC7) -> 967615 | BD84: =(BS!BD6+BS!BD7) -> 994725 | BE84: =(BS!BE6+BS!BE7) -> 975350 | BF84: =(BS!BF6+BS!BF7) -> 1031666 | BH84: =(BS!BH6+BS!BH7) -> 1291257 | BI84: =(BS!BI6+BS!BI7) -> 1444049 | BJ84: =(BS!BJ6+BS!BJ7) -> 1590217 | BK84: =(BS!BK6+BS!BK7) -> 1045462 | BM84: =(BS!BM6+BS!BM7) -> 1086788 | BN84: =(BS!BN6+BS!BN7) -> 938353 | BO84: =(BS!BO6+BS!BO7) -> 942376 | BP84: =(BS!BP6+BS!BP7) -> 963547 | BR84: =(BS!BR6+BS!BR7) -> 948692 | BS84: =(BS!BS6+BS!BS7) -> 844455 | BT84: =(BS!BT6+BS!BT7) -> 839871
B85: Debt | AG85: =BS!AG27+BS!AG33 -> 0 | AH85: =AG85 -> 0 | AI85: =BS!AI27+BS!AI33 -> 0 | AJ85: =BS!AJ27+BS!AJ33 -> 0 | AK85: =BS!AK27+BS!AK33 -> 432572 | AL85: =BS!AL27+BS!AL33 -> 438932 | AM85: =AL85 -> 438932 | AN85: =BS!AN27+BS!AN33 -> 445385 | AO85: =BS!AO27+BS!AO33 -> 451934 | AP85: =BS!AP27+BS!AP33 -> 458578 | AQ85: =BS!AQ27+BS!AQ33 -> 465321 | AR85: =AQ85 -> 465321 | AS85: =BS!AS27+BS!AS33 -> 472162 | AT85: =BS!AT27+BS!AT33 -> 479105 | AU85: =BS!AU27+BS!AU33 -> 486149 | AV85: =BS!AV27+BS!AV33 -> 713688 | AW85: =AV85 -> 713688 | AX85: =BS!AX27+BS!AX33 -> 755920 | AY85: =BS!AY27+BS!AY33 -> 732304 | AZ85: =BS!AZ27+BS!AZ33 -> 730331 | BA85: =BS!BA27+BS!BA33 -> 718487 | BC85: =BS!BC27+BS!BC33 -> 719632 | BD85: =BS!BD27+BS!BD33 -> 720677 | BE85: =BS!BE27+BS!BE33 -> 721782 | BF85: =BS!BF27+BS!BF33 -> 722887 | BH85: =BS!BH27+BS!BH33 -> 723995 | BI85: =BS!BI27+BS!BI33 -> 725105 | BJ85: =BS!BJ27+BS!BJ33 -> 689111 | BK85: =BS!BK27+BS!BK33 -> 0 | BM85: =BS!BM27+BS!BM33 -> 0 | BN85: =BS!BN27+BS!BN33 -> 0 | BO85: =BS!BO27+BS!BO33 -> 0 | BP85: =BS!BP27+BS!BP33 -> 0 | BR85: =BS!BR27+BS!BR33 -> 0 | BS85: =BS!BS27+BS!BS33 -> 0 | BT85: =BS!BT27+BS!BT33 -> 0
B86: Net Cash | D86: =BS!D6 -> 0 | E86: =E84-BS!#REF!-BS!#REF! -> #REF! | F86: =F84-BS!#REF!-BS!#REF! -> #REF! | G86: =G84-BS!#REF!-BS!#REF! -> #REF! | H86: =H84-BS!#REF!-BS!#REF! -> #REF! | S86: =BS!S6 -> 0 | T86: =BS!T6 -> 0 | U86: =BS!U6 -> 0 | V86: =BS!V6 -> 0 | W86: =BS!W6 -> 0 | X86: =BS!X6+BS!X9+BS!X7+BS!X13 -> 228523 | Y86: =BS!Y6+BS!Y9+BS!Y7+BS!Y13 -> 0 | Z86: =BS!Z6+BS!Z9+BS!Z7+BS!Z13 -> 0 | AA86: =BS!AA6+BS!AA9+BS!AA7+BS!AA13 -> 0 | AB86: =BS!AB6+BS!AB9+BS!AB7+BS!AB13 -> 0 | AC86: =BS!AC6+BS!AC9+BS!AC7+BS!AC13 -> 190556 | AD86: =AD84-(BS!AD27+BS!AD33) -> 0 | AE86: =AE84-(BS!AE27+BS!AE33) -> 0 | AF86: =AF84-(BS!AF27+BS!AF33) -> 0 | AG86: =AG84-AG85 -> 256867 | AH86: =AG86 -> 256867 | AI86: =AI84-AI85 -> 269429 | AJ86: =AJ84-AJ85 -> 818795 | AK86: =AK84-AK85 -> 661561 | AL86: =AL84-AL85 -> 330082 | AM86: =AL86 -> 330082 | AN86: =AN84-AN85 -> 306739 | AO86: =AO84-AO85 -> 298319 | AP86: =AP84-AP85 -> 195199 | AQ86: =AQ84-AQ85 -> 190821 | AR86: =AQ86 -> 190821 | AS86: =AS84-AS85 -> 285787 | AT86: =AT84-AT85 -> 194934 | AU86: =AU84-AU85 -> 112425 | AV86: =AV84-AV85 -> 59817 | AW86: =AV86 -> 59817 | AX86: =AX84-AX85 -> 24712 | AY86: =AY84-AY85 -> 90565 | AZ86: =AZ84-AZ85 -> 88127 | BA86: =BA84-BA85 -> 84335 | BC86: =BC84-BC85 -> 247983 | BD86: =BD84-BD85 -> 274048 | BE86: =BE84-BE85 -> 253568 | BF86: =BF84-BF85 -> 308779 | BH86: =BH84-BH85 -> 567262 | BI86: =BI84-BI85 -> 718944 | BJ86: =BJ84-BJ85 -> 901106 | BK86: =BK84-BK85 -> 1045462 | BM86: =BM84-BM85 -> 1086788 | BN86: =BN84-BN85 -> 938353 | BO86: =BO84-BO85 -> 942376 | BP86: =BP84-BP85 -> 963547 | BR86: =BR84-BR85 -> 948692 | BS86: =BS84-BS85 -> 844455 | BT86: =BT84-BT85 -> 839871
B87: Cash/Share | D87: =D86/D80 -> 0 | E87: =E86/E80 -> #REF! | F87: =F86/F80 -> #REF! | G87: =G86/G80 -> #REF! | H87: =H86/H80 -> #REF! | T87: =T86/T80 -> #DIV/0! | U87: =U86/U80 -> #DIV/0! | V87: =V86/V80 -> #DIV/0! | W87: =W86/W80 -> #DIV/0! | X87: =X86/X80 -> 8.7718025 | Y87: =Y86/Y80 -> #DIV/0! | Z87: =Z86/Z80 -> #DIV/0! | AA87: =AA86/AA80 -> #DIV/0! | AB87: =AB86/AB80 -> #DIV/0! | AD87: =AD86/AD80 -> 0 | AE87: =AE86/AE80 -> 0 | AF87: =AF86/AF80 -> 0 | AG87: =AG86/AG80 -> 6.0544713 | AH87: =AG87 -> 6.0544713 | AI87: =AI86/AI80 -> 4.4780195 | AJ87: =AJ86/AJ80 -> 4.2774118 | AK87: =AK86/AK80 -> 3.4415792 | AL87: =AL86/AL80 -> 1.7589457 | AM87: =AL87 -> 1.7589457 | AN87: =AN86/AN80 -> 1.6214049 | AO87: =AO86/AO80 -> 1.5755647 | AP87: =AP86/AP80 -> 1.0230985 | AQ87: =AQ86/AQ80 -> 0.98499443 | AR87: =AQ87 -> 0.98499443 | AS87: =AS86/AS80 -> 1.4512479 | AT87: =AT86/AT80 -> 0.95833518 | AU87: =AU86/AU80 -> 0.54615542 | AV87: =AV86/AV80 -> 0.28687282 | AW87: =AV87 -> 0.28687282 | AX87: =AX86/AX80 -> 0.1188757 | AY87: =AY86/AY80 -> 0.43509488 | AZ87: =AZ86/AZ80 -> 0.42347373 | BA87: =BA86/BA80 -> 0.40709883 | BC87: =BC86/BC80 -> 1.2039471 | BD87: =BD86/BD80 -> 1.3326461 | BE87: =BE86/BE80 -> 1.2330195 | BF87: =BF86/BF80 -> 1.4970377 | BH87: =BH86/BH80 -> 2.7262905 | BI87: =BI86/BI80 -> 3.4532739 | BJ87: =BJ86/BJ80 -> 4.331116 | BK87: =BK86/BK80 -> 4.9883434 | BM87: =BM86/BM80 -> 5.1777452 | BN87: =BN86/BN80 -> 4.5053775 | BO87: =BO86/BO80 -> 4.5153278 | BP87: =BP86/BP80 -> 4.491914 | BR87: =BR86/BR80 -> 4.4578877 | BS87: =BS86/BS80 -> 4.0029911 | BT87: =BT86/BT80 -> 4.0365023
AT90: =34756-AT63 -> 0 | AU90: =AU71--58491 -> 0
C91: Deferred Revenue | S91: =BS!R49 -> 0 | X91: =BS!W49 -> 19572 | AC91: =BS!AB49 -> 32712 | AH91: =BS!AG49 -> 277924
C92: Unbilled Deferred Revenue | S92: =S94-S91 -> 82400 | X92: =X94-X91 -> 112228 | AC92: =AC94-AC91 -> 135488 | AH92: =AH94-AH91 -> -46954
C93: Y/Y growth | X93: =X92/S92-1 -> 0.36199029 | AC93: =AC92/X92-1 -> 0.20725666 | AH93: =AH92/AC92-1 -> -1.3465547
C94: Total Backlog | S94: 82400 | X94: 131800 | AC94: 168200 | AH94: 230970
C95: Y/Y growth | X95: =X94/S94-1 -> 0.59951456 | AC95: =AC94/X94-1 -> 0.27617602 | AH95: =AH94/AC94-1 -> 0.37318668
C96: Net Bookings | X96: =(X94-S94)+X13 -> 299881 | AC96: =(AC94-X94)+AC13 -> 417859 | AH96: =(AH94-AC94)+AH13 -> 581274
C97: Q/Q growth
C98: Y/Y growth
E100: 20123Billings | J100: 2014 Billings | O100: 2015 Billings | T100: 2016 Billings | Y100: 2017 Billings | AD100: 2018 Billings | AI100: 2019 Billings | AN100: 2020 Billings | AS100: 2021 Billings | AX100: 2022 Billings | BC100: 2023 Billings | BH100: ="20"&MID(BL4,3,2)&" Billings" -> 2024 Billings | BM100: ="20"&MID(BQ4,3,2)&" Billings" -> 2025 Billings | BR100: ="20"&MID(BV4,3,2)&" Billings" -> 2026 Billings | BW100: ="20"&MID(CA4,3,2)&" Billings" -> 2027 Billings
P101: 2Q14 | Q101: 3Q14 | R101: 4Q14 | S101: 2015 | T101: 1Q16 | U101: 2Q16 | V101: =V4 -> 3Q16 | W101: =W4 -> 4Q16 | X101: =X4 -> FY16 | Y101: =Y4 -> 1Q17 | Z101: =Z4 -> 2Q17 | AA101: =AA4 -> 3Q17 | AB101: =AB4 -> 4Q17 | AC101: =AC4 -> FY17 | ... CA101: =CA4 -> FY27E
C102: Revenue | T102: =T13 -> 0 | U102: =U13 -> 0 | V102: =V13 -> 0 | W102: =W13 -> 0 | X102: =X13 -> 250481 | Y102: =Y13 -> 0 | Z102: =Z13 -> 0 | AA102: =AA13 -> 0 | ... CA102: =CA13 -> 3390199.3
C103: Change In Deferred Revenue | U103: =U82-T82 -> 0 | V103: =V82-U82 -> 0 | W103: =W82-V82 -> 19572 | Y103: =BS!Y49-BS!X49 -> 3724 | Z103: =BS!Z49-BS!Y49 -> 3677 | AA103: =BS!AA49-BS!Z49 -> 2823 | AB103: =BS!AB49-BS!AA49 -> 2916 | AD103: =208882-195501 -> 13381 | AE103: =214405-208882 -> 5523 | AF103: =226836-214405 -> 12431 | AG103: =282943-226836 -> 56107 | AI103: =293667-282943 -> 10724 | AJ103: 6759 | AK103: =330060-300426 -> 29634 | AL103: =390887-330060 -> 60827 | AN103: =AN82-AM82 -> 4274 | AO103: =AO82-AN82 -> 17472 | AP103: =AP82-AO82 -> 22563 | AQ103: =AQ82-AP82 -> 85957 | AS103: =AS82-AR82 -> 44594 | AT103: =AT82-AS82 -> 72236 | AU103: =AU82-AT82 -> 65034 | AV103: =AV82-AU82 -> 95232 | AX103: =857969-800940 -> 57029 | AY103: =939826-857969 -> 81857 | AZ103: =961243-939826 -> 21417 | BA103: =1049106+-961243 -> 87863 | BC103: =(1074460+-1049106) -> 25354 | BD103: =1094939-1074460 -> 20479 | BE103: =1113131-1094939 -> 18192 | BF103: =1191269-1113131 -> 78138 | BH103: =1210965-1191269 -> 19696 | BI103: =1233894-1210965 -> 22929 | BJ103: =1228174-1233894 -> -5720 | BK103: =1343792-1228174 -> 115618 | BM103: =1340680-1343792 -> -3112 | BN103: =1334461-1340680 -> -6219 | BO103: =1332828-1334461 -> -1633 | BP103: =1479266-1332828 -> 146438 | BR103: =1450718-1479266 -> -28548 | BS103: =1468618-1450718 -> 17900 | BT103: =1479491-1468618 -> 10873 | BU103: =BS!BU49-BS!BT49 -> 170218.05 | BW103: =BS!BW49-BS!BU49 -> -43081.601 | BX103: =BS!BX49-BS!BW49 -> 19002.131 | BY103: =BS!BY49-BS!BX49 -> -2485.3585 | BZ103: =BS!BZ49-BS!BY49 -> 161898.6
C104: Add contract assets and unbilled AR | AD104: 10095 | AE104: 10400 | AF104: 11381 | AG104: 12678 | AI104: 16899 | AJ104: 14555 | AK104: 16196 | AL104: 15229 | AN104: 13436 | AO104: 16810 | AP104: 17757 | AQ104: 20805 | AS104: 15082 | AT104: 16390 | AU104: 20395 | AV104: =26808-21021 -> 5787 | AX104: 21021 | AY104: 19737 | AZ104: 18067 | BA104: 19708 | BC104: 18273 | BD104: 18756 | BE104: 13695 | BF104: 17945 | BH104: 16615 | BI104: 22936 | BJ104: 22358 | BK104: 25253 | BM104: 20189 | BN104: 17179 | BO104: =17461 -> 17461 | BP104: 18341 | BR104: 17825 | BS104: 13319 | BT104: 13824
C105: Less: Contract assets and unbilled AR, end of period | AD105: -10400 | AE105: -11381 | AF105: -12678 | AG105: -16899 | AI105: -14555 | AJ105: -16196 | AK105: -15229 | AL105: -13436 | AN105: -16810 | AO105: -17757 | AP105: -20805 | AQ105: -15082 | AS105: -16390 | AT105: -20395 | AU105: -26808 | AX105: -19737 | AY105: -18067 | AZ105: -19708 | BA105: -18273 | BC105: -18756 | BD105: -13695 | BE105: -17945 | BF105: -16615 | BH105: -22936 | BI105: -22358 | BJ105: -25253 | BK105: -20189 | BM105: -17179 | BN105: -17461 | BO105: -18341 | BP105: -17825 | BR105: -13319 | BS105: -13824 | BT105: -13588
C106: Add: Contract assets and unbilled AR by acquisitions | AJ106: 0 | AK106: -11002 | AT106: 6589 | BN106: 53
C107: Less: Contract liabilities and refund liability | AT107: -9344 | BN107: -5071
C108: Billings | S108: =SUM(O108:R108) -> 0 | V108: 28400 | W108: =W103+W102 -> 19572 | X108: =SUM(T108:W108) -> 47972 | Y108: =Y102+Y103+Y104+Y105+Y106+Y107 -> 3724 | Z108: =Z102+Z103+Z104+Z105+Z106+Z107 -> 3677 | AA108: =AA102+AA103+AA104+AA105+AA106+AA107 -> 2823 | AB108: =AB102+AB103+AB104+AB105+AB106+AB107 -> 2916 | AC108: =SUM(Y108:AB108) -> 13140 | AD108: =AD102+AD103+AD104+AD105+AD106+AD107 -> 126574 | AE108: =AE102+AE103+AE104+AE105+AE106+AE107 -> 130085 | AF108: =AF102+AF103+AF104+AF105+AF106+AF107 -> 141723 | AG108: =AG102+AG103+AG104+AG105+AG106+AG107 -> 200760 | AH108: =SUM(AD108:AG108) -> 599142 | AI108: =AI102+AI103+AI104+AI105+AI106+AI107 -> 168876 | AJ108: =AJ102+AJ103+AJ104+AJ105+AJ106+AJ107 -> 172162 | AK108: =AK102+AK103+AK104+AK105+AK106+AK107 -> 197984 | AL108: =AL102+AL103+AL104+AL105+AL106+AL107 -> 262352 | AM108: =SUM(AI108:AL108) -> 801374 | AN108: =AN102+AN103+AN104+AN105+AN106+AN107 -> 214862 | AO108: =AO102+AO103+AO104+AO105+AO106+AO107 -> 252137 | AP108: =AP102+AP103+AP104+AP105+AP106+AP107 -> 269017 | AQ108: =AQ102+AQ103+AQ104+AQ105+AQ106+AQ107 -> 366575 | AR108: =SUM(AN108:AQ108) -> 1102591 | AS108: =AS102+AS103+AS104+AS105+AS106+AS107 -> 340303 | AT108: =AT102+AT103+AT104+AT105+AT106+AT107 -> 407685 | AU108: =AU102+AU103+AU104+AU105+AU106+AU107 -> 441544 | AV108: =AV102+AV103+AV104+AV105+AV106+AV107 -> 531917 | AW108: =SUM(AS108:AV108) -> 1721449 | AX108: =AX102+AX103+AX104+AX105+AX106+AX107 -> 527391 | AY108: =AY102+AY103+AY104+AY105+AY106+AY107 -> 595371 | AZ108: =AZ102+AZ103+AZ104+AZ105+AZ106+AZ107 -> 565239 | BA108: =BA102+BA103+BA104+BA105+BA106+BA107 -> 670126 | BB108: =SUM(AX108:BA108) -> 2358127 | BC108: =BC102+BC103+BC104+BC105+BC106+BC107 -> 613563 | BD108: =BD102+BD103+BD104+BD105+BD106+BD107 -> 647724 | BE108: =BE102+BE103+BE104+BE105+BE106+BE107 -> 659405 | BF108: =BF102+BF103+BF104+BF105+BF106+BF107 -> 739044 | BG108: =SUM(BC108:BF108) -> 2659736 | BH108: =BH102+BH103+BH104+BH105+BH106+BH107 -> 674763 | BI108: =BI102+BI103+BI104+BI105+BI106+BI107 -> 711194 | BJ108: =BJ102+BJ103+BJ104+BJ105+BJ106+BJ107 -> 691806 | BK108: =BK102+BK103+BK104+BK105+BK106+BK107 -> 833068 | BL108: =SUM(BH108:BK108) -> 2910831 | BM108: =BM102+BM103+BM104+BM105+BM106+BM107 -> 709538 | BN108: =BN102+BN103+BN104+BN105+BN106+BN107 -> 724508 | BO108: =BO102+BO103+BO104+BO105+BO106+BO107 -> 752307 | BP108: =BP102+BP103+BP104+BP105+BP106+BP107 -> 923206 | BQ108: =SUM(BM108:BP108) -> 3109559 | BR108: =BR102+BR103+BR104+BR105+BR106+BR107 -> 739612 | BS108: =BS102+BS103+BS104+BS105+BS106+BS107 -> 818031 | BT108: =BT102+BT103+BT104+BT105+BT106+BT107 -> 829459 | BU108: =BU102+BU103+BU104+BU105+BU106+BU107 -> 997430.56 | BV108: =SUM(BR108:BU108) -> 3384532.6 | BW108: =BW102+BW103+BW104+BW105+BW106+BW107 -> 763250.28 | BX108: =BX102+BX103+BX104+BX105+BX106+BX107 -> 864751.65 | BY108: =BY102+BY103+BY104+BY105+BY106+BY107 -> 861835.08 | BZ108: =BZ102+BZ103+BZ104+BZ105+BZ106+BZ107 -> 1035696.1 | CA108: =SUM(BW108:BZ108) -> 3525533.1
C109: % change y/y | W109: =W108/R108-1 -> #DIV/0! | AA109: =AA108/V108-1 -> -0.90059859 | AB109: =AB108/W108-1 -> -0.85101165 | AC109: =AC108/X108-1 -> -0.72609022 | AD109: =AD108/Y108-1 -> 32.988722 | AE109: =AE108/Z108-1 -> 34.378026 | AF109: =AF108/AA108-1 -> 49.202976 | AG109: =AG108/AB108-1 -> 67.847737 | AH109: =AH108/AC108-1 -> 44.596804 | ... CA109: =CA108/BV108-1 -> 0.04166026
C110: % change q/q | W110: =W108/V108-1 -> -0.31084507 | AB110: =AB108/AA108-1 -> 0.032943677 | AD110: =AD108/AB108-1 -> 42.406722 | AE110: =AE108/AD108-1 -> 0.027738714 | AF110: =AF108/AE108-1 -> 0.089464581 | AG110: =AG108/AF108-1 -> 0.41656612 | AI110: =AI108/AG108-1 -> -0.1588165 | AJ110: =AJ108/AI108-1 -> 0.019458064 | AK110: =AK108/AJ108-1 -> 0.14998664 | AL110: =AL108/AK108-1 -> 0.32511718 | AN110: =AN108/AL108-1 -> -0.18101634 | AO110: =AO108/AN108-1 -> 0.17348345 | AP110: =AP108/AO108-1 -> 0.066947731 | AQ110: =AQ108/AP108-1 -> 0.36264623 | AS110: =AS108/AQ108-1 -> -0.071668826 | AT110: =AT108/AS108-1 -> 0.19800589 | AU110: =AU108/AT108-1 -> 0.083051866 | AV110: =AV108/AU108-1 -> 0.20467496 | AX110: =AX108/AV108-1 -> -0.0085088463 | AY110: =AY108/AX108-1 -> 0.12889867 | AZ110: =AZ108/AY108-1 -> -0.05061046 | BA110: =BA108/AZ108-1 -> 0.18556221 | BC110: =BC108/BA108-1 -> -0.084406515 | BD110: =BD108/BC108-1 -> 0.055676434 | BE110: =BE108/BD108-1 -> 0.018033916 | BF110: =BF108/BE108-1 -> 0.12077403 | BH110: =BH108/BF108-1 -> -0.086978583 | BI110: =BI108/BH108-1 -> 0.053990809 | BJ110: =BJ108/BI108-1 -> -0.027261197 | BK110: =BK108/BJ108-1 -> 0.20419308 | BM110: =BM108/BK108-1 -> -0.14828321 | BN110: =BN108/BM108-1 -> 0.021098236 | BO110: =BO108/BN108-1 -> 0.038369487 | BP110: =BP108/BO108-1 -> 0.22716657 | BR110: =BR108/BP108-1 -> -0.19886569 | BS110: =BS108/BR108-1 -> 0.10602721 | BT110: =BT108/BS108-1 -> 0.013970131 | BU110: =BU108/BT108-1 -> 0.20250737 | BW110: =BW108/BU108-1 -> -0.23478355 | BX110: =BX108/BW108-1 -> 0.1329857 | BY110: =BY108/BX108-1 -> -0.0033727254 | BZ110: =BZ108/BY108-1 -> 0.20173347
C111: Total Billings TTM | AA111: 142800 | AB111: =AB108+AA108+Z108+Y108 -> 13140 | AD111: =AD108+AB108+AA108+Z108 -> 135990 | AE111: =AE108+AD108+AB108+AA108 -> 262398 | AF111: =AF108+AE108+AD108+AB108 -> 401298 | AG111: =AG108+AF108+AE108+AD108-3500 -> 595642 | AI111: =AI108+AG108+AF108+AE108 -> 641444 | AJ111: =AJ108+AI108+AG108+AF108 -> 683521 | AK111: =AK108+AJ108+AI108+AG108 -> 739782 | AL111: =AL108+AK108+AJ108+AI108 -> 801374 | AN111: =AN108+AL108+AK108+AJ108 -> 847360 | AO111: =AO108+AN108+AL108+AK108 -> 927335 | AP111: =AP108+AO108+AN108+AL108 -> 998368 | AQ111: =AQ108+AP108+AO108+AN108 -> 1102591 | AS111: =AS108+AQ108+AP108+AO108 -> 1228032 | AT111: =AT108+AS108+AQ108+AP108 -> 1383580 | AU111: =AU108+AT108+AS108+AQ108 -> 1556107 | AV111: =AV108+AU108+AT108+AS108 -> 1721449 | AX111: =AX108+AV108+AU108+AT108 -> 1908537 | AY111: =AY108+AX108+AV108+AU108 -> 2096223 | AZ111: =AZ108+AY108+AX108+AV108 -> 2219918 | BA111: =BA108+AZ108+AY108+AX108 -> 2358127 | BC111: =BC108+BA108+AZ108+AY108 -> 2444299 | BD111: =BD108+BC108+BA108+AZ108 -> 2496652 | BE111: =BE108+BD108+BC108+BA108 -> 2590818 | BF111: =BF108+BE108+BD108+BC108 -> 2659736 | BH111: =BH108+BF108+BE108+BD108 -> 2720936 | BI111: =BI108+BH108+BF108+BE108 -> 2784406 | BJ111: =BJ108+BI108+BH108+BF108 -> 2816807 | BK111: =BK108+BJ108+BI108+BH108 -> 2910831 | BM111: =BM108+BK108+BJ108+BI108 -> 2945606 | BN111: =BN108+BM108+BK108+BJ108 -> 2958920 | BO111: =BO108+BN108+BM108+BK108 -> 3019421 | BP111: =BP108+BO108+BN108+BM108 -> 3109559 | BR111: =BR108+BP108+BO108+BN108 -> 3139633 | BS111: =BS108+BR108+BP108+BO108 -> 3233156 | BT111: =BT108+BS108+BR108+BP108 -> 3310308 | BU111: =BU108+BT108+BS108+BR108 -> 3384532.6 | BW111: =BW108+BU108+BT108+BS108 -> 3408170.8 | BX111: =BX108+BW108+BU108+BT108 -> 3454891.5 | BY111: =BY108+BX108+BW108+BU108 -> 3487267.6 | BZ111: =BZ108+BY108+BX108+BW108 -> 3525533.1
C112: % change y/y | AF112: =AF111/AA111-1 -> 1.8102101 | AG112: =AG111/AB111-1 -> 44.330441 | AI112: =AI111/AD111-1 -> 3.7168468 | AJ112: =AJ111/AE111-1 -> 1.6049017 | AK112: =AK111/AF111-1 -> 0.84347293 | AL112: =AL111/AG111-1 -> 0.34539539 | AN112: =AN111/AI111-1 -> 0.32101945 | AO112: =AO111/AJ111-1 -> 0.35670301 | AP112: =AP111/AK111-1 -> 0.34954351 | AQ112: =AQ111/AL111-1 -> 0.37587568 | AS112: =AS111/AN111-1 -> 0.44924471 | AT112: =AT111/AO111-1 -> 0.49199588 | AU112: =AU111/AP111-1 -> 0.55865072 | AV112: =AV111/AQ111-1 -> 0.56127612 | AX112: =AX111/AS111-1 -> 0.55414273 | AY112: =AY111/AT111-1 -> 0.51507177 | AZ112: =AZ111/AU111-1 -> 0.42658442 | BA112: =BA111/AV111-1 -> 0.36985005 | BC112: =BC111/AX111-1 -> 0.28071869 | BD112: =BD111/AY111-1 -> 0.19102405 | BE112: =BE111/AZ111-1 -> 0.16707824 | BF112: =BF111/BA111-1 -> 0.12790193 | BH112: =BH111/BC111-1 -> 0.11317642 | BI112: =BI111/BD111-1 -> 0.11525595 | BJ112: =BJ111/BE111-1 -> 0.087226891 | BK112: =BK111/BF111-1 -> 0.094405986 | BM112: =BM111/BH111-1 -> 0.082570851 | BN112: =BN111/BI111-1 -> 0.062675486 | BO112: =BO111/BJ111-1 -> 0.071930381 | BP112: =BP111/BK111-1 -> 0.068271913 | BR112: =BR111/BM111-1 -> 0.065869977 | BS112: =BS111/BN111-1 -> 0.092681113 | BT112: =BT111/BO111-1 -> 0.096338669 | BU112: =BU111/BP111-1 -> 0.088428476 | BW112: =BW111/BR111-1 -> 0.085531603 | BX112: =BX111/BS111-1 -> 0.068581749 | BY112: =BY111/BT111-1 -> 0.053457133 | BZ112: =BZ111/BU111-1 -> 0.04166026
C113: % change q/q | AD113: =AD111/AB111-1 -> 9.3493151 | AE113: =AE111/AD111-1 -> 0.92953894 | AF113: =AF111/AE111-1 -> 0.52934855 | AG113: =AG111/AF111-1 -> 0.48428848 | AI113: =AI111/AG111-1 -> 0.076895182 | AJ113: =AJ111/AI111-1 -> 0.065597309 | AK113: =AK111/AJ111-1 -> 0.082310565 | AL113: =AL111/AK111-1 -> 0.083256959 | AN113: =AN111/AL111-1 -> 0.057383943 | AO113: =AO111/AN111-1 -> 0.094381373 | AP113: =AP111/AO111-1 -> 0.076599072 | AQ113: =AQ111/AP111-1 -> 0.10439337 | AS113: =AS111/AQ111-1 -> 0.11376929 | AT113: =AT111/AS111-1 -> 0.12666445 | AU113: =AU111/AT111-1 -> 0.12469608 | AV113: =AV111/AU111-1 -> 0.10625362 | AX113: =AX111/AV111-1 -> 0.10868054 | AY113: =AY111/AX111-1 -> 0.098340247 | AZ113: =AZ111/AY111-1 -> 0.059008512 | BA113: =BA111/AZ111-1 -> 0.062258606 | BC113: =BC111/BA111-1 -> 0.036542561 | BD113: =BD111/BC111-1 -> 0.021418411 | BE113: =BE111/BD111-1 -> 0.03771691 | BF113: =BF111/BE111-1 -> 0.026600865 | BH113: =BH111/BF111-1 -> 0.023009802 | BI113: =BI111/BH111-1 -> 0.023326532 | BJ113: =BJ111/BI111-1 -> 0.011636593 | BK113: =BK111/BJ111-1 -> 0.033379639 | BM113: =BM111/BK111-1 -> 0.01194676 | BN113: =BN111/BM111-1 -> 0.0045199528 | BO113: =BO111/BN111-1 -> 0.020446987 | BP113: =BP111/BO111-1 -> 0.029852743 | BR113: =BR111/BP111-1 -> 0.0096714679 | BS113: =BS111/BR111-1 -> 0.029787876 | BT113: =BT111/BS111-1 -> 0.023862752 | BU113: =BU111/BT111-1 -> 0.022422253 | BW113: =BW111/BU111-1 -> 0.0069842079 | BX113: =BX111/BW111-1 -> 0.013708424 | BY113: =BY111/BX111-1 -> 0.0093710849 | BZ113: =BZ111/BY111-1 -> 0.010972916
C115: Company provided billings
C116: Non-GAAP billings | X116: 289529 | AC116: 432366 | AD116: 126574 | AE116: 130085 | AF116: 141723 | AG116: 200760 | AH116: =SUM(AD116:AG116) -> 599142 | AI116: 168876 | AJ116: 172162 | AK116: 197984 | AL116: 262352 | AM116: =SUM(AI116:AL116) -> 801374 | AN116: 214955 | AO116: 252364 | AP116: 269399 | AQ116: 366921 | AR116: =SUM(AN116:AQ116) -> 1103639 | AS116: 342052 | AT116: 405695 | AU116: 440411 | AV116: 534934 | AW116: =SUM(AS116:AV116) -> 1723092 | AX116: 527391 | AY116: 595371 | AZ116: 565239 | BA116: 670126 | BB116: =SUM(AX116:BA116) -> 2358127 | BC116: 613563 | BD116: 647724 | BE116: 659405 | BG116: =SUM(BC116:BF116) -> 1920692 | BL116: =SUM(BH116:BK116) -> 0 | BQ116: =SUM(BM116:BP116) -> 0 | BV116: =SUM(BR116:BU116) -> 0 | CA116: =SUM(BW116:BZ116) -> 0
C117: % change y/y | X117: =X116/S116-1 -> #DIV/0! | AC117: =AC116/X116-1 -> 0.49334264 | AD117: =AD116/Y116-1 -> #DIV/0! | AE117: =AE116/Z116-1 -> #DIV/0! | AF117: =AF116/AA116-1 -> #DIV/0! | AG117: =AG116/AB116-1 -> #DIV/0! | AH117: =AH116/AC116-1 -> 0.38572876 | AI117: =AI116/AD116-1 -> 0.33420766 | AJ117: =AJ116/AE116-1 -> 0.32345774 | ... CA117: =CA116/BV116-1 -> #DIV/0!
C118: % change q/q | AD118: =AD116/AB116-1 -> #DIV/0! | AE118: =AE116/AD116-1 -> 0.027738714 | AF118: =AF116/AE116-1 -> 0.089464581 | AG118: =AG116/AF116-1 -> 0.41656612 | AI118: =AI116/AG116-1 -> -0.1588165 | AJ118: =AJ116/AI116-1 -> 0.019458064 | AK118: =AK116/AJ116-1 -> 0.14998664 | AL118: =AL116/AK116-1 -> 0.32511718 | AN118: =AN116/AL116-1 -> -0.18066186 | AO118: =AO116/AN116-1 -> 0.17403177 | AP118: =AP116/AO116-1 -> 0.067501704 | AQ118: =AQ116/AP116-1 -> 0.36199837 | AS118: =AS116/AQ116-1 -> -0.067777532 | AT118: =AT116/AS116-1 -> 0.18606235 | AU118: =AU116/AT116-1 -> 0.085571673 | AV118: =AV116/AU116-1 -> 0.21462452 | AX118: =AX116/AV116-1 -> -0.014100805 | AY118: =AY116/AX116-1 -> 0.12889867 | AZ118: =AZ116/AY116-1 -> -0.05061046 | BA118: =BA116/AZ116-1 -> 0.18556221 | BC118: =BC116/BA116-1 -> -0.084406515 | BD118: =BD116/BC116-1 -> 0.055676434 | BE118: =BE116/BD116-1 -> 0.018033916 | BF118: =BF116/BE116-1 -> -1 | BH118: =BH116/BF116-1 -> #DIV/0! | BI118: =BI116/BH116-1 -> #DIV/0! | BJ118: =BJ116/BI116-1 -> #DIV/0! | BK118: =BK116/BJ116-1 -> #DIV/0! | BM118: =BM116/BK116-1 -> #DIV/0! | BN118: =BN116/BM116-1 -> #DIV/0! | BO118: =BO116/BN116-1 -> #DIV/0! | BP118: =BP116/BO116-1 -> #DIV/0! | BR118: =BR116/BP116-1 -> #DIV/0! | BS118: =BS116/BR116-1 -> #DIV/0! | BT118: =BT116/BS116-1 -> #DIV/0! | BU118: =BU116/BT116-1 -> #DIV/0! | BW118: =BW116/BU116-1 -> #DIV/0! | BX118: =BX116/BW116-1 -> #DIV/0! | BY118: =BY116/BX116-1 -> #DIV/0! | BZ118: =BZ116/BY116-1 -> #DIV/0!
...

Sheet BS
B2: =IS!B2 -> DocuSign, Inc (DOCU)
B4: Balance Sheet | D4: 2012 | E4: 1Q13 | F4: 2Q13 | G4: 3Q13 | H4: 4Q13 | I4: 2013 | J4: 1Q14 | K4: 2Q14 | L4: 3Q14 | M4: 4Q14 | N4: 2014 | O4: 1Q15 | P4: 2Q15 | Q4: 3Q15 | R4: 4Q15 | S4: 2015 | T4: 1Q16 | U4: 2Q16 | V4: 3Q16 | W4: 4Q16 | X4: 2016 | Y4: 1Q17 | Z4: 2Q17 | AA4: 3Q17 | AB4: 4Q17 | AC4: 2017 | AD4: 1Q18 | AE4: 2Q18 | AF4: 3Q18 | AG4: 4Q18 | AH4: 2018 | AI4: 1Q19 | AJ4: 2Q19 | AK4: 3Q19 | AL4: 4Q19 | AM4: 2019 | AN4: 1Q20 | AO4: 2Q20 | AP4: 3Q20 | AQ4: 4Q20 | AR4: 2020 | AS4: 1Q21 | AT4: 2Q21 | AU4: 3Q21 | AV4: 4Q21 | AW4: 2021 | AX4: 1Q22 | AY4: 2Q22 | AZ4: 3Q22 | BA4: 4Q22 | BB4: 2022 | BC4: 1Q23 | BD4: 2Q23 | BE4: 3Q23 | BF4: 4Q23 | BG4: 2023 | BH4: =IS!BH4 -> 1Q24 | BI4: =IS!BI4 -> 2Q24 | BJ4: =IS!BJ4 -> 3Q24 | BK4: =IS!BK4 -> 4Q24 | BL4: =IS!BL4 -> FY24 | BM4: =IS!BM4 -> 1Q25 | BN4: =IS!BN4 -> 2Q25 | BO4: =IS!BO4 -> 3Q25 | ... CA4: =IS!CA4 -> FY27E
B5: Assets: | BP5: 0
C6: Cash and cash equivalents | S6: =R6 -> 0 | X6: 228523 | AC6: 190556 | AG6: 256867 | AH6: =AG6 -> 256867 | AI6: 269429 | AJ6: 818795 | AK6: 1094133 | AL6: 517811 | AM6: =AL6 -> 517811 | AN6: 236476 | AO6: 224290 | AP6: 197697 | AQ6: 241203 | AR6: =AQ6 -> 241203 | AS6: 442237 | AT6: 404262 | AU6: 374984 | AV6: 566055 | AW6: =AV6 -> 566055 | AX6: 518972 | AY6: 518577 | AZ6: 503884 | BA6: 509059 | BB6: =BA6 -> 509059 | BC6: 638190 | BD6: 637186 | BE6: 632620 | BF6: 721895 | BG6: =BF6 -> 721895 | BH6: 940494 | BI6: 1017778 | BJ6: 1188578 | BK6: 797060 | BL6: =BK6 -> 797060 | BM6: 817388 | BN6: 619064 | BO6: 610870 | BP6: 648623 | BQ6: =BP6 -> 648623 | BR6: 657399 | BS6: 599986 | BT6: 583291 | BU6: =BT6+CF!BU70 -> 855072.33 | BV6: =BU6 -> 855072.33 | BW6: =BV6+CF!BW70 -> 1218625.6 | BX6: =BW6+CF!BX70 -> 1487879.3 | BY6: =BX6+CF!BY70 -> 1644676.1 | BZ6: =BY6+CF!BZ70 -> 1939958.5 | CA6: =BZ6 -> 1939958.5
C7: Investments—current | AG7: 0 | AH7: =AG7 -> 0 | AK7: 0 | AL7: 251203 | AM7: =AL7 -> 251203 | AN7: 515648 | AO7: 525963 | AP7: 456080 | AQ7: 414939 | AR7: =AQ7 -> 414939 | AS7: 315712 | AT7: 269777 | AU7: 223590 | AV7: 207450 | AW7: =AV7 -> 207450 | AX7: 261660 | AY7: 304292 | AZ7: 314574 | BA7: 293763 | BB7: =BA7 -> 293763 | BC7: 329425 | BD7: 357539 | BE7: 342730 | BF7: 309771 | BG7: =BF7 -> 309771 | BH7: 350763 | BI7: 426271 | BJ7: 401639 | BK7: 248402 | BL7: =BK7 -> 248402 | BM7: 269400 | BN7: 319289 | BO7: 331506 | BP7: 314924 | BQ7: =BP7 -> 314924 | BR7: 291293 | BS7: 244469 | BT7: 256580 | BU7: =BT7 -> 256580 | BV7: =BU7 -> 256580 | BW7: =BV7 -> 256580 | BX7: =BW7 -> 256580 | BY7: =BX7 -> 256580 | BZ7: =BY7 -> 256580 | CA7: =BZ7 -> 256580
C8: Accounts receivable | S8: =R8 -> 0 | X8: =W8 -> 0 | AG8: 123750 | AH8: =AG8 -> 123750 | AI8: 104128 | AJ8: 108365 | AK8: 130611 | AL8: 174548 | AM8: =AL8 -> 174548 | AN8: 117134 | AO8: 138652 | AP8: 159464 | AQ8: 237841 | AR8: =AQ8 -> 237841 | AS8: 220602 | AT8: 224502 | AU8: 261085 | AV8: 323570 | AW8: =AV8 -> 323570 | AX8: 250365 | AY8: 284730 | AZ8: 305599 | BA8: 440950 | BB8: =BA8 -> 440950 | BC8: 300872 | BD8: 339528 | BE8: 422612 | BF8: 516914 | BG8: =BF8 -> 516914 | BH8: 408632 | BI8: 414740 | BJ8: 360456 | BK8: 439299 | BL8: =BK8 -> 439299 | BM8: 306152 | BN8: 309885 | BO8: 300444 | BP8: 429582 | BQ8: =BP8 -> 429582 | BR8: 307597 | BS8: 356943 | BT8: 354978 | BU8: =BU54*IS!BU13 -> 488055.38 | BV8: =BU8 -> 488055.38 | BW8: =BW54*IS!BW13 -> 362849.35 | BX8: =BX54*IS!BX13 -> 380587.28 | BY8: =BY54*IS!BY13 -> 466733.04 | BZ8: =BZ54*IS!BZ13 -> 524278.47 | CA8: =BZ8 -> 524278.47
C9: Restricted cash | AG9: 569 | AH9: =AG9 -> 569 | AI9: 367 | AJ9: 367 | AK9: 367 | AL9: 367 | AM9: =AL9 -> 367 | AN9: 167 | AO9: 133 | AP9: 414 | AQ9: 280 | AR9: =AQ9 -> 280 | AS9: 280 | AT9: 280 | AU9: 281 | AV9: 0 | AW9: =AV9 -> 0 | AX9: =AW9 -> 0 | AY9: =AX9 -> 0 | AZ9: =AY9 -> 0 | BA9: =AZ9 -> 0 | BB9: =BA9 -> 0 | BC9: =BB9 -> 0 | BD9: =BC9 -> 0 | ... BM9: =BL9 -> 0 | BP9: =BO9 -> 0 | BQ9: =BP9 -> 0 | BS9: =BR9 -> 0 | BT9: =BS9 -> 0 | BU9: =BT9 -> 0 | BV9: =BU9 -> 0 | BW9: =BV9 -> 0 | BX9: =BW9 -> 0 | BY9: =BX9 -> 0 | BZ9: =BY9 -> 0 | CA9: =BZ9 -> 0
C10: Contract assets—current | AG10: 14260 | AH10: =AG10 -> 14260 | AI10: 12030 | AJ10: 13760 | AK10: 12056 | AL10: 10616 | AM10: =AL10 -> 10616 | AN10: 13360 | AO10: 15548 | AP10: 17921 | AQ10: 12502 | AR10: =AQ10 -> 12502 | AS10: 13236 | AT10: 17044 | AU10: 22477 | AV10: 16883 | AW10: =AV10 -> 16883 | AX10: 15267 | AY10: 13993 | AZ10: 14690 | BA10: 12588 | BB10: =BA10 -> 12588 | BC10: 13368 | BD10: 9387 | BE10: 13609 | BF10: 12437 | BG10: =BF10 -> 12437 | BH10: 17454 | BI10: 16188 | BJ10: 19381 | BK10: 15922 | BL10: =BK10 -> 15922 | BM10: 12319 | BN10: 13449 | BO10: 13645 | BP10: 13764 | BQ10: =BP10 -> 13764 | BR10: 9585 | BS10: 9892 | BT10: 8978 | BU10: =BU55*IS!BU13 -> 16544.25 | BV10: =BU10 -> 16544.25 | BW10: =BW55*IS!BW13 -> 16126.638 | BX10: =BX55*IS!BX13 -> 16914.99 | BY10: =BY55*IS!BY13 -> 17286.409 | BZ10: =BZ55*IS!BZ13 -> 17475.949 | CA10: =BZ10 -> 17475.949
C11: Prepaid and other | S11: =R11 -> 0 | X11: =W11 -> 0 | AG11: 23349 | AH11: =AG11 -> 23349 | AI11: 29779 | AJ11: 26776 | AK11: 28344 | AL11: 29976 | AM11: =AL11 -> 29976 | AN11: 39341 | AO11: 38907 | AP11: 37814 | AQ11: 37125 | AR11: =AQ11 -> 37125 | AS11: 51176 | AT11: 52158 | AU11: 47343 | AV11: 48390 | AW11: =AV11 -> 48390 | AX11: 65172 | AY11: 61197 | AZ11: 67842 | BA11: 63236 | BB11: =BA11 -> 63236 | BC11: 80669 | BD11: 79142 | BE11: 68814 | BF11: 69987 | BG11: =BF11 -> 69987 | BH11: 86719 | BI11: 81492 | BJ11: 72629 | BK11: 66984 | BL11: =BK11 -> 66984 | BM11: 84540 | BN11: 81693 | BO11: 75412 | BP11: 82368 | BQ11: =BP11 -> 82368 | BR11: 111204 | BS11: 107760 | BT11: 103328 | BU11: =BU56*IS!BU13 -> 107537.63 | BV11: =BU11 -> 107537.63 | BW11: =BW56*IS!BW13 -> 104823.14 | BX11: =BX56*IS!BX13 -> 101489.94 | BY11: =BY56*IS!BY13 -> 95075.248 | BZ11: =BZ56*IS!BZ13 -> 96117.72 | CA11: =BZ11 -> 96117.72
B12: Total Current Assets | D12: =SUM(D6:D11) -> 0 | E12: =SUM(E6:E11) -> 0 | F12: =SUM(F6:F11) -> 0 | G12: =SUM(G6:G11) -> 0 | H12: =SUM(H6:H11) -> 0 | I12: =SUM(I6:I11) -> 0 | J12: =SUM(J6:J11) -> 0 | K12: =SUM(K6:K11) -> 0 | ... CA12: =SUM(CA6:CA11) -> 2834410.6
C13: Investments—noncurrent | AG13: 0 | AH13: =AG13 -> 0 | AJ13: 0 | AK13: 0 | AL13: 164220 | AM13: =AL13 -> 164220 | AN13: 184683 | AO13: 180146 | AP13: 257783 | AQ13: 239729 | AR13: =AQ13 -> 239729 | AS13: 140117 | AT13: 66265 | AU13: 76782 | AV13: 92717 | AW13: =AV13 -> 92717 | AX13: 94930 | AY13: 64088 | AZ13: 89455 | BA13: 94938 | BB13: =BA13 -> 94938 | BC13: 94751 | BD13: 133238 | BE13: 129783 | BF13: 186049 | BG13: =BF13 -> 186049 | BH13: 206026 | BI13: 85202 | BJ13: 55448 | BK13: 121977 | BL13: =BK13 -> 121977 | BM13: 139108 | BN13: 102537 | BO13: 112805 | BP13: 134105 | BQ13: =BP13 -> 134105 | BR13: 160139 | BS13: 208864 | BT13: 208529 | BU13: =BT13 -> 208529 | BV13: =BU13 -> 208529 | BW13: =BV13 -> 208529 | BX13: =BW13 -> 208529 | BY13: =BX13 -> 208529 | BZ13: =BY13 -> 208529 | CA13: =BZ13 -> 208529
C14: Property and equipment, net | S14: =R14 -> 0 | X14: =W14 -> 0 | AG14: 63019 | AH14: =AG14 -> 63019 | AI14: 60095 | AJ14: 60415 | AK14: 73965 | AL14: 75832 | AM14: =AL14 -> 75832 | AN14: 84094 | AO14: 92078 | AP14: 105917 | AQ14: 128293 | AR14: =AQ14 -> 128293 | AS14: 134811 | AT14: 150646 | AU14: 159652 | AV14: 165039 | AW14: =AV14 -> 165039 | AX14: 164128 | AY14: 173983 | AZ14: 177832 | BA14: 184664 | BB14: =BA14 -> 184664 | BC14: 183704 | BD14: 186229 | BE14: 196127 | BF14: 199892 | BG14: =BF14 -> 199892 | BH14: 120803 | BI14: 220916 | BJ14: 230963 | BK14: 245173 | BL14: =BK14 -> 245173 | BM14: 255736 | BN14: 265544 | BO14: 278623 | BP14: 299370 | BQ14: =BP14 -> 299370 | BR14: 310150 | BS14: 327953 | BT14: 343636 | BU14: =BT14-CF!BU37-CF!BU8 -> 328416.06 | BV14: =BU14 -> 328416.06 | BW14: =BV14-CF!BW37-CF!BW8 -> 310684.45 | BX14: =BW14-CF!BX37-CF!BX8 -> 294152.78 | BY14: =BX14-CF!BY37-CF!BY8 -> 279796.23 | BZ14: =BY14-CF!BZ37-CF!BZ8 -> 271483.33 | CA14: =BZ14 -> 271483.33
C15: Deferred contract acquisition costs—noncurrent | AG15: 75535 | AH15: =AG15 -> 75535 | AI15: 78401 | AJ15: 86199 | AK15: 97091 | AL15: 112583 | AM15: =AL15 -> 112583 | AN15: 115924 | AO15: 124434 | AP15: 136248 | AQ15: 153333 | AR15: =AQ15 -> 153333 | AS15: 169686 | AT15: 198325 | AU15: 225115 | AV15: 260130 | AW15: =AV15 -> 260130 | AX15: 274039 | AY15: 289636 | AZ15: 300073 | BA15: 311835 | BB15: =BA15 -> 311835 | BC15: 313760 | BD15: 322695 | BE15: 329958 | BF15: 350899 | BG15: =BF15 -> 350899 | BH15: 135403 | BI15: 369749 | BJ15: 383205 | BK15: 409627 | BL15: =BK15 -> 409627 | BM15: 415739 | BN15: 427599 | BO15: 445987 | BP15: 467201 | BQ15: =BP15 -> 467201 | BR15: 461969 | BS15: 462928 | BT15: 462552 | BU15: =BU57*IS!BU13 -> 537688.13 | BV15: =BU15 -> 537688.13 | BW15: =BW57*IS!BW13 -> 483799.13 | BX15: =BX57*IS!BX13 -> 507449.71 | BY15: =BY57*IS!BY13 -> 535878.67 | BZ15: =BZ57*IS!BZ13 -> 567968.35 | CA15: =BZ15 -> 567968.35
C16: Operating lease right to use | AG16: 0 | AH16: =AG16 -> 0 | AI16: 0 | AJ16: 0 | AK16: 0 | AL16: 0 | AM16: =AL16 -> 0 | AN16: 143361 | AO16: 137292 | AP16: 136627 | AQ16: 149833 | AR16: =AQ16 -> 149833 | AS16: 161484 | AT16: 168313 | AU16: 160362 | AV16: 159352 | AW16: =AV16 -> 159352 | AX16: 152185 | AY16: 140589 | AZ16: 132608 | BA16: 126021 | BB16: =BA16 -> 126021 | BC16: 116589 | BD16: 100481 | BE16: 92155 | BF16: 141493 | BG16: =BF16 -> 141493 | BH16: 353308 | BI16: 131341 | BJ16: 126198 | BK16: 123188 | BL16: =BK16 -> 123188 | BM16: 119997 | BN16: 117877 | BO16: 113365 | BP16: 109630 | BQ16: =BP16 -> 109630 | BR16: 115412 | BS16: 109953 | BT16: 133183 | BU16: =BU58*IS!BU13 -> 132354 | BV16: =BU16 -> 132354 | BW16: =BW58*IS!BW13 -> 129013.1 | BX16: =BX58*IS!BX13 -> 135319.92 | BY16: =BY58*IS!BY13 -> 138291.27 | BZ16: =BZ58*IS!BZ13 -> 139807.59 | CA16: =BZ16 -> 139807.59
C17: Intangible assets, net | S17: =R17 -> 0 | X17: =W17 -> 0 | AG17: 14148 | AH17: =AG17 -> 14148 | AI17: 11278 | AJ17: 10139 | AK17: 79161 | AL17: 74203 | AM17: =AL17 -> 74203 | AN17: 69490 | AO17: 65070 | AP17: 60759 | AQ17: 56500 | AR17: =AQ17 -> 56500 | AS17: 52241 | AT17: 135825 | AU17: 128414 | AV17: 121828 | AW17: =AV17 -> 121828 | AX17: 115009 | AY17: 110327 | AZ17: 102802 | BA17: 98816 | BB17: =BA17 -> 98816 | BC17: 87277 | BD17: 81246 | BE17: 75232 | BF17: 70280 | BG17: =BF17 -> 70280 | BH17: 65247 | BI17: 60304 | BJ17: 55605 | BK17: 50905 | BL17: =BK17 -> 50905 | BM17: 46206 | BN17: 90227 | BO17: 83307 | BP17: 76388 | BQ17: =BP17 -> 76388 | BR17: 69469 | BS17: 64553 | BT17: 60816 | BU17: =BT17 -> 60816 | BV17: =BU17 -> 60816 | BW17: =BV17 -> 60816 | BX17: =BW17 -> 60816 | BY17: =BX17 -> 60816 | BZ17: =BY17 -> 60816 | CA17: =BZ17 -> 60816
C18: Goodwill | S18: =R18 -> 0 | X18: =W18 -> 0 | AG18: 37306 | AH18: =AG18 -> 37306 | AI18: 36074 | AJ18: 35369 | AK18: 194533 | AL18: 195225 | AM18: =AL18 -> 195225 | AN18: 194775 | AO18: 195427 | AP18: 195024 | AQ18: 194882 | AR18: =AQ18 -> 194882 | AS18: 193594 | AT18: 349254 | AU18: 348504 | AV18: 350151 | AW18: =AV18 -> 350151 | AX18: 351511 | AY18: 355595 | AZ18: 355353 | BA18: 355058 | BB18: =BA18 -> 355058 | BC18: 354056 | BD18: 353326 | BE18: 352423 | BF18: 353619 | BG18: =BF18 -> 353619 | BH18: 359255 | BI18: 353345 | BJ18: 351493 | BK18: 353138 | BL18: =BK18 -> 353138 | BM18: 352450 | BN18: 455519 | BO18: 455678 | BP18: 454477 | BQ18: =BP18 -> 454477 | BR18: 455276 | BS18: 456368 | BT18: 457247 | BU18: =BT18 -> 457247 | BV18: =BU18 -> 457247 | BW18: =BV18 -> 457247 | BX18: =BW18 -> 457247 | BY18: =BX18 -> 457247 | BZ18: =BY18 -> 457247 | CA18: =BZ18 -> 457247
C19: Deferred tax assets - noncurrent | BN19: 822026 | BO19: 816538 | BP19: 840470 | BQ19: =BP19 -> 840470 | BR19: 844837 | BS19: 836641 | BT19: 838694 | BU19: =BS19-IS!BU66*0.1 -> 828143.15 | BW19: =BU19-IS!BW66*0.1 -> 821253.84 | BX19: =BV19-IS!BX66*0.1 -> -8700.7681 | BY19: =BW19-IS!BY66*0.1 -> 811447.09 | BZ19: =BX19-IS!BZ66*0.1 -> -13420.726
C20: Other assets | S20: =R20 -> 0 | X20: =W20 -> 0 | AG20: 11170 | AH20: =AG20 -> 11170 | AI20: 12891 | AJ20: 9513 | AK20: 9175 | AL20: 8833 | AM20: =AL20 -> 8833 | AN20: 23947 | AO20: 23896 | AP20: 24617 | AQ20: 24678 | AR20: =AQ20 -> 24678 | AS20: 26312 | AT20: 16659 | AU20: 22530 | AV20: 24942 | AW20: =AV20 -> 24942 | AX20: 33882 | AY20: 38680 | AZ20: 45791 | BA20: 50337 | BB20: =BA20 -> 50337 | BC20: 61470 | BD20: 67349 | BE20: 75521 | BF20: 79484 | BG20: =BF20 -> 79484 | BH20: 85795 | BI20: 90079 | BJ20: 92032 | BK20: 99615 | BL20: =BK20 -> 99615 | BM20: 107654 | BN20: 129232 | BO20: 132028 | BP20: 141803 | BQ20: =BP20 -> 141803 | BR20: 153073 | BS20: 163613 | BT20: 170227 | BU20: =BU59*IS!BU13 -> 157170.38 | BV20: =BU20 -> 157170.38 | BW20: =BW59*IS!BW13 -> 161266.38 | BX20: =BX59*IS!BX13 -> 153080.66 | BY20: =BY59*IS!BY13 -> 155577.68 | BZ20: =BZ59*IS!BZ13 -> 157283.54 | CA20: =BZ20 -> 157283.54
B21: Total Assets | D21: =D12+SUM(D13:D20) -> 0 | E21: =E12+SUM(E13:E20) -> 0 | F21: =F12+SUM(F13:F20) -> 0 | G21: =G12+SUM(G13:G20) -> 0 | H21: =H12+SUM(H13:H20) -> 0 | I21: =I12+SUM(I13:I20) -> 0 | J21: =J12+SUM(J13:J20) -> 0 | K21: =K12+SUM(K13:K20) -> 0 | ... W21: =W12+SUM(W13:W20) -> 0 | X21: 486487 | Y21: =Y12+SUM(Y13:Y20) -> 0 | Z21: =Z12+SUM(Z13:Z20) -> 0 | AA21: =AA12+SUM(AA13:AA20) -> 0 | AB21: =AB12+SUM(AB13:AB20) -> 0 | AC21: 499638 | AD21: =AD12+SUM(AD13:AD20) -> 0 | AE21: =AE12+SUM(AE13:AE20) -> 0 | AF21: =AF12+SUM(AF13:AF20) -> 0 | AG21: =AG12+SUM(AG13:AG20) -> 619973 | AH21: =AH12+SUM(AH13:AH20) -> 619973 | AI21: =AI12+SUM(AI13:AI20) -> 614472 | AJ21: =AJ12+SUM(AJ13:AJ20) -> 1169698 | AK21: =AK12+SUM(AK13:AK20) -> 1719436 | ... CA21: =CA12+SUM(CA13:CA20) -> 4697545.4
B23: Liabilities:
C24: Accounts payable | S24: =R24 -> 0 | X24: =W24 -> 0 | AG24: 23713 | AH24: =AG24 -> 23713 | AI24: 13269 | AJ24: 16653 | AK24: 22059 | AL24: 19590 | AM24: =AL24 -> 19590 | AN24: 21436 | AO24: 23452 | AP24: 29099 | AQ24: 28144 | AR24: =AQ24 -> 28144 | AS24: 21504 | AT24: 33053 | AU24: 32309 | AV24: 37367 | AW24: =AV24 -> 37367 | AX24: 14870 | AY24: 33612 | AZ24: 47712 | BA24: 52804 | BB24: =BA24 -> 52804 | BC24: 26213 | BD24: 44449 | BE24: 47176 | BF24: 24393 | BG24: =BF24 -> 24393 | BH24: 14688 | BI24: 5803 | BJ24: 14787 | BK24: 19029 | BL24: =BK24 -> 19029 | BM24: 17700 | BN24: 8116 | BO24: 18144 | BP24: 30697 | BQ24: =BP24 -> 30697 | BR24: 24583 | BS24: 10643 | BT24: 22482 | BU24: =BU62*IS!BU13 -> 24816.375 | BV24: =BU24 -> 24816.375 | BW24: =BW62*IS!BW13 -> 24189.956 | BX24: =BX62*IS!BX13 -> 25372.486 | BY24: =BY62*IS!BY13 -> 25929.613 | BZ24: =BZ62*IS!BZ13 -> 26213.924 | CA24: =BZ24 -> 26213.924
C25: Accrued expenses and other current liabilities | S25: =R25 -> 0 | X25: =W25 -> 0 | AG25: =15734+11574 -> 27308 | AH25: =AG25 -> 27308 | AI25: =19023+12017 -> 31040 | AJ25: =18368+11761 -> 30129 | AK25: 22669 | AL25: 35658 | AM25: =AL25 -> 35658 | AN25: =28133+12973 -> 41106 | AO25: =34227+16563 -> 50790 | AP25: =33094+12956 -> 46050 | AQ25: 54344 | AR25: =AQ25 -> 54344 | AS25: 46475 | AT25: 54916 | AU25: 59752 | AV25: 66566 | AW25: =AV25 -> 66566 | AX25: 75438 | AY25: 81817 | AZ25: 81065 | BA25: 91377 | BB25: =BA25 -> 91377 | BC25: 92936 | BD25: 90756 | BE25: 96227 | BF25: 100987 | BG25: =BF25 -> 100987 | BH25: 101685 | BI25: 109349 | BJ25: 99642 | BK25: 104037 | BL25: =BK25 -> 104037 | BM25: 99177 | BN25: 93251 | BO25: 94591 | BP25: 99579 | BQ25: =BP25 -> 99579 | BR25: 101182 | BS25: 100579 | BT25: 119841 | BU25: =BU63*IS!BU13 -> 107537.63 | BV25: =BU25 -> 107537.63 | BW25: =BW63*IS!BW13 -> 129013.1 | BX25: =BX63*IS!BX13 -> 135319.92 | BY25: =BY63*IS!BY13 -> 121004.86 | BZ25: =BZ63*IS!BZ13 -> 122331.64 | CA25: =BZ25 -> 122331.64
C26: Accrued compensation | AG26: 50852 | AH26: =AG26 -> 50852 | AI26: 33905 | AJ26: 51212 | AK26: 53686 | AL26: 77553 | AM26: =AL26 -> 77553 | AN26: 57684 | AO26: 79980 | AP26: 70860 | AQ26: 83189 | AR26: =AQ26 -> 83189 | AS26: 81653 | AT26: 111623 | AU26: 114221 | AV26: 156158 | AW26: =AV26 -> 156158 | AX26: 129640 | AY26: 142599 | AZ26: 144741 | BA26: 160163 | BB26: =BA26 -> 160163 | BC26: 137724 | BD26: 149761 | BE26: 146297 | BF26: 163133 | BG26: =BF26 -> 163133 | BH26: 141990 | BI26: 162243 | BJ26: 159381 | BK26: 195266 | BL26: =BK26 -> 195266 | BM26: 153932 | BN26: 178603 | BO26: 158779 | BP26: 227115 | BQ26: =BP26 -> 227115 | BR26: 170976 | BS26: 208005 | BT26: 180982 | BU26: =BU64*IS!BU13 -> 248163.75 | BV26: =BU26 -> 248163.75 | BW26: =BW64*IS!BW13 -> 209646.29 | BX26: =BX64*IS!BX13 -> 219894.88 | BY26: =BY64*IS!BY13 -> 233366.52 | BZ26: =BZ64*IS!BZ13 -> 244663.29 | CA26: =BZ26 -> 244663.29
C27: Convertible senior notes, net | AR27: =AQ27 -> 0 | AV27: 20469 | AW27: =AV27 -> 20469 | AX27: 13343 | AY27: 2032 | AZ27: 11510 | BA27: 0 | BB27: =BA27 -> 0 | BC27: 16 | BE27: 36921 | BF27: 722887 | BG27: =BF27 -> 722887 | BH27: 723995 | BI27: 725105 | BJ27: 689111 | BK27: 0 | BL27: =BK27 -> 0 | BM27: =BL27 -> 0 | BP27: =BO27 -> 0 | BQ27: =BP27 -> 0 | BS27: =BR27 -> 0 | BT27: =BS27 -> 0 | BU27: =BT27 -> 0 | BV27: =BU27 -> 0 | BW27: =BV27 -> 0 | BX27: =BW27 -> 0 | BY27: =BX27 -> 0 | BZ27: =BY27 -> 0 | CA27: =BZ27 -> 0
C28: Operating lease liabilities | AG28: 0 | AH28: =AG28 -> 0 | AI28: 0 | AJ28: 0 | AK28: 17574 | AL28: 0 | AM28: =AL28 -> 0 | AN28: =16921 -> 16921 | AO28: 17193 | AP28: 18743 | AQ28: 20728 | AR28: =AQ28 -> 20728 | AS28: 27613 | AT28: 30415 | AU28: 30633 | AV28: 32971 | AW28: =AV28 -> 32971 | AX28: 34777 | AY28: 34951 | AZ28: 35228 | BA28: 37404 | BB28: =BA28 -> 37404 | BC28: 37293 | BD28: 43479 | BE28: 34713 | BF28: 24055 | BG28: =BF28 -> 24055 | BH28: 22742 | BI28: 23053 | BJ28: 21701 | BK28: 22230 | BL28: =BK28 -> 22230 | BM28: 20925 | BN28: 19769 | BO28: 19507 | BP28: 19077 | BQ28: =BP28 -> 19077 | BR28: 21815 | BS28: 21185 | BT28: 15840 | BU28: =BU65*IS!BU13 -> 20680.313 | BV28: =BU28 -> 20680.313 | BW28: =BW65*IS!BW13 -> 24189.956 | BX28: =BX65*IS!BX13 -> 25372.486 | BY28: =BY65*IS!BY13 -> 25929.613 | BZ28: =BZ65*IS!BZ13 -> 26213.924 | CA28: =BZ28 -> 26213.924
C29: Deferred rent—current | AG29: 1758 | AH29: =AG29 -> 1758 | AI29: =1811 -> 1811 | AJ29: 1872 | AK29: 2029 | AL29: 2452 | AM29: =AL29 -> 2452 | AN29: 0 | AO29: 0 | AP29: 0 | AR29: =AQ29 -> 0 | AW29: =AV29 -> 0 | BB29: =BA29 -> 0 | BC29: 0 | BG29: =BF29 -> 0 | BL29: =BK29 -> 0 | BQ29: =BP29 -> 0 | BV29: =BU29 -> 0 | CA29: =BZ29 -> 0
C30: Contract liabilities—current | S30: =R30 -> 0 | X30: 130713 | AC30: 190151 | AG30: 270188 | AH30: =AG30 -> 270188 | AI30: 282470 | AJ30: 289724 | AK30: 316619 | AL30: 381060 | AM30: =AL30 -> 381060 | AN30: 385460 | AO30: 402734 | AP30: 423742 | AQ30: 507560 | AR30: =AQ30 -> 507560 | AS30: 552345 | AT30: 624031 | AU30: 686185 | AV30: 779642 | AW30: =AV30 -> 779642 | AX30: 829844 | AY30: 914619 | AZ30: 940111 | BA30: 1029891 | BB30: =BA30 -> 1029891 | BC30: 1049534 | BD30: 1073800 | BE30: 1088197 | BF30: 1172867 | BG30: =BF30 -> 1172867 | BH30: 1190364 | BI30: 1208411 | BJ30: 1204599 | BK30: 1320059 | BL30: =BK30 -> 1320059 | BM30: 1313227 | BN30: 1307565 | BO30: 1307749 | BP30: 1455442 | BQ30: =BP30 -> 1455442 | BR30: 1422878 | BS30: 1436033 | BT30: 1444599 | BU30: =BU66*IS!BU13 -> 1604792.3 | BV30: =BU30 -> 1604792.3 | BW30: =BW66*IS!BW13 -> 1572347.2 | BX30: =BX66*IS!BX13 -> 1590009.1 | BY30: =BY66*IS!BY13 -> 1581706.4 | BZ30: =BZ66*IS!BZ13 -> 1738856.9 | CA30: =BZ30 -> 1738856.9
B31: Total Current Liabilities | D31: =SUM(D24:D30) -> 0 | E31: =SUM(E24:E30) -> 0 | F31: =SUM(F24:F30) -> 0 | G31: =SUM(G24:G30) -> 0 | H31: =SUM(H24:H30) -> 0 | I31: =H31 -> 0 | J31: =SUM(J24:J30) -> 0 | K31: =SUM(K24:K30) -> 0 | L31: =SUM(L24:L30) -> 0 | M31: =SUM(M24:M30) -> 0 | N31: =SUM(N24:N30) -> 0 | O31: =SUM(O24:O30) -> 0 | P31: =SUM(P24:P30) -> 0 | Q31: =SUM(Q24:Q30) -> 0 | ... CA31: =SUM(CA24:CA30) -> 2158279.7
C32: Operating lease liabilities, non current | AH32: =AG32 -> 0 | AI32: 0 | AJ32: 0 | AK32: 0 | AL32: 0 | AM32: =AL32 -> 0 | AN32: 154778 | AO32: 150493 | AP32: 150362 | AQ32: 162432 | AR32: =AQ32 -> 162432 | AS32: 173750 | AT32: 177862 | AU32: 169078 | AV32: 165704 | AW32: =AV32 -> 165704 | AX32: 155998 | AY32: 146025 | AZ32: 136240 | BA32: 126340 | BB32: =BA32 -> 126340 | BC32: 114976 | BD32: 90479 | BE32: 81237 | BF32: 141348 | BG32: =BF32 -> 141348 | BH32: 136243 | BI32: 130746 | BJ32: 124551 | BK32: 120823 | BL32: =BK32 -> 120823 | BM32: 117444 | BN32: 115832 | BO32: 111132 | BP32: 105350 | BQ32: =BP32 -> 105350 | BR32: 111122 | BS32: 105757 | BT32: 134533 | BU32: =BT32 -> 134533 | BV32: =BU32 -> 134533 | BW32: =BV32 -> 134533 | BX32: =BW32 -> 134533 | BY32: =BX32 -> 134533 | BZ32: =BY32 -> 134533 | CA32: =BZ32 -> 134533
C33: Convertible senior notes, net | AG33: 0 | AH33: =AG33 -> 0 | AJ33: 0 | AK33: 432572 | AL33: 438932 | AM33: =AL33 -> 438932 | AN33: 445385 | AO33: 451934 | AP33: 458578 | AQ33: 465321 | AR33: =AQ33 -> 465321 | AS33: 472162 | AT33: 479105 | AU33: 486149 | AV33: 693219 | AW33: =AV33 -> 693219 | AX33: 742577 | AY33: 730272 | AZ33: 718821 | BA33: 718487 | BB33: =BA33 -> 718487 | BC33: 719616 | BD33: 720677 | BE33: 684861 | BG33: =BF33 -> 0 | BI33: 0 | BK33: 0 | BL33: =BK33 -> 0 | BM33: =BL33-IS!BM50 -> 0 | BN33: 0 | BP33: =BO33-IS!BP50 -> 0 | BQ33: =BP33 -> 0 | BS33: =BR33-IS!BS50 -> 0 | BT33: =BS33-IS!BT50 -> 0 | BU33: =BT33-IS!BU50 -> 0 | BV33: =BU33 -> 0 | BW33: =BV33-IS!BW50 -> 0 | BX33: =BW33-IS!BX50 -> 0 | BY33: =BX33-IS!BY50 -> 0 | BZ33: =BY33-IS!BZ50 -> 0 | CA33: =BZ33 -> 0
C34: Contract liabilities—noncurrent | S34: =R34 -> 0 | X34: =W34 -> 0 | AG34: 7736 | AH34: =AG34 -> 7736 | AI34: 8065 | AJ34: 7703 | AK34: 7135 | AL34: 7712 | AM34: =AL34 -> 7712 | AN34: 7586 | AO34: 7784 | AP34: 9339 | AQ34: 11478 | AR34: =AQ34 -> 11478 | AS34: 11287 | AT34: 11837 | AU34: 14717 | AV34: 16492 | AW34: =AV34 -> 16492 | AX34: 17938 | AY34: 18138 | AZ34: 17070 | BA34: 16725 | BB34: =BA34 -> 16725 | BC34: 15794 | BD34: 14630 | BE34: 15242 | BF34: 16925 | BG34: =BF34 -> 16925 | BH34: 17715 | BI34: 21839 | BJ34: 22069 | BK34: 21980 | BL34: =BK34 -> 21980 | BM34: 23840 | BN34: 23020 | BO34: 22931 | BP34: 21523 | BQ34: =BP34 -> 21523 | BR34: 24354 | BS34: 27428 | BT34: 28027 | BU34: =BU68*IS!BU13 -> 38051.776 | BV34: =BU34 -> 38051.776 | BW34: =BW68*IS!BW13 -> 27415.284 | BX34: =BX68*IS!BX13 -> 28755.484 | BY34: =BY68*IS!BY13 -> 34572.818 | BZ34: =BZ68*IS!BZ13 -> 39320.886 | CA34: =BZ34 -> 39320.886
C35: Deferred rent—noncurrent | AG35: 23044 | AH35: =AG35 -> 23044 | AI35: 22862 | AJ35: 22633 | AK35: 23050 | AL35: 24195 | AM35: =AL35 -> 24195 | AN35: 0 | AO35: 0 | AP35: 0 | AR35: =AQ35 -> 0 | AW35: =AV35 -> 0 | BB35: =BA35 -> 0 | BG35: =BF35 -> 0 | BH35: 0 | BI35: 0 | BJ35: 0 | BK35: 0 | BL35: =BK35 -> 0 | BM35: 0 | BN35: 0 | BP35: 0 | BQ35: =BP35 -> 0 | BS35: 0 | BT35: 0 | BU35: 0 | BV35: =BU35 -> 0 | BW35: 0 | BX35: 0 | BY35: 0 | BZ35: 0 | CA35: =BZ35 -> 0
C36: Deferred tax liability—noncurrent | AG36: 2511 | AH36: =AG36 -> 2511 | AI36: 2505 | AJ36: 2499 | AK36: 2500 | AL36: 4207 | AM36: =AL36 -> 4207 | AN36: 4267 | AO36: 4270 | AP36: 4275 | AQ36: 4920 | AR36: =AQ36 -> 4920 | AS36: 4814 | AT36: 8740 | AU36: 7974 | AV36: 6464 | AW36: =AV36 -> 6464 | AX36: 6484 | AY36: 6424 | AZ36: 6379 | BA36: 9316 | BB36: =BA36 -> 9316 | BC36: 9079 | BD36: 10323 | BE36: 10400 | BF36: 10723 | BG36: =BF36 -> 10723 | BH36: 12324 | BI36: 13923 | BJ36: 17160 | BK36: 16795 | BL36: =BK36 -> 16795 | BM36: 18037 | BN36: 18122 | BO36: 19303 | BP36: 20596 | BQ36: =BP36 -> 20596 | BR36: 22381 | BS36: 19064 | BT36: 18497 | BU36: =BT36 -> 18497 | BV36: =BU36 -> 18497 | BW36: =BV36 -> 18497 | BX36: =BW36 -> 18497 | BY36: =BX36 -> 18497 | BZ36: =BY36 -> 18497 | CA36: =BZ36 -> 18497
C37: Other long-term liabilities | S37: =R37 -> 0 | X37: =W37 -> 0 | AG37: 4010 | AH37: =AG37 -> 4010 | AI37: 4419 | AJ37: 3803 | AK37: 9374 | AL37: 9696 | AM37: =AL37 -> 9696 | AN37: 6095 | AO37: 6527 | AP37: 5955 | AQ37: 6695 | AR37: =AQ37 -> 6695 | AS37: 7097 | AT37: 19837 | AU37: 24069 | AV37: 32328 | AW37: =AV37 -> 32328 | AX37: 32974 | AY37: 33322 | AZ37: 32057 | BA37: 23255 | BB37: =BA37 -> 23255 | BC37: 22001 | BD37: 21861 | BE37: 21807 | BF37: 18115 | BG37: =BF37 -> 18115 | BH37: 18661 | BI37: 19174 | BJ37: 19593 | BK37: 21332 | BL37: =BK37 -> 21332 | BM37: 25407 | BN37: 28257 | BO37: 28695 | BP37: 30634 | BQ37: =BP37 -> 30634 | BR37: 33310 | BS37: 33254 | BT37: 35717 | BU37: =BU70*IS!BU13 -> 33088.501 | BV37: =BU37 -> 33088.501 | BW37: =BW70*IS!BW13 -> 32253.275 | BX37: =BX70*IS!BX13 -> 33829.981 | BY37: =BY70*IS!BY13 -> 34572.818 | BZ37: =BZ70*IS!BZ13 -> 34951.898 | CA37: =BZ37 -> 34951.898
B38: Total Liabilities | D38: =D31+SUM(D34:D37) -> 0 | E38: =E31+SUM(E34:E37) -> 0 | F38: =F31+SUM(F34:F37) -> 0 | G38: =G31+SUM(G34:G37) -> 0 | H38: =H31+SUM(H34:H37) -> 0 | I38: =I31+SUM(I34:I37) -> 0 | J38: =J31+SUM(J34:J37) -> 0 | K38: =K31+SUM(K34:K37) -> 0 | ... AH38: =AH31+SUM(AH34:AH37) -> 411120 | AI38: =AI31+SUM(AI32:AI37) -> 400346 | AJ38: =AJ31+SUM(AJ32:AJ37) -> 426228 | AK38: =AK31+SUM(AK32:AK37) -> 909267 | AL38: =AL31+SUM(AL32:AL37) -> 1001055 | AM38: =AM31+SUM(AM34:AM37) -> 562123 | AN38: =AN31+SUM(AN32:AN37) -> 1140718 | AO38: =AO31+SUM(AO32:AO37) -> 1195157 | AP38: =AP31+SUM(AP32:AP37) -> 1217003 | AQ38: =AQ31+SUM(AQ32:AQ37) -> 1344811 | AR38: =AR31+SUM(AR32:AR37) -> 1344811 | AS38: =AS31+SUM(AS32:AS37) -> 1398700 | AT38: =AT31+SUM(AT32:AT37) -> 1551419 | AU38: =AU31+SUM(AU32:AU37) -> 1625087 | ... CA38: =CA31+SUM(CA32:CA37) -> 2385582.5
B40: Shareholders Equity:
C41: Total Shareholder Equity | D41: =D21-D38 -> 0 | E41: =E21-E38 -> 0 | F41: =F21-F38 -> 0 | G41: =G21-G38 -> 0 | H41: =H21-H38 -> 0 | I41: =H41 -> 0 | J41: =J21-J38 -> 0 | K41: =K21-K38 -> 0 | L41: =L21-L38 -> 0 | M41: =M21-M38 -> 0 | N41: =M41 -> 0 | O41: =O21-O38 -> 0 | P41: =P21-P38 -> 0 | Q41: =Q21-Q38 -> 0 | R41: =R21-R38 -> 0 | S41: =R41 -> 0 | T41: =T21-T38 -> 0 | U41: =U21-U38 -> 0 | V41: =V21-V38 -> 0 | W41: =W21-W38 -> 0 | X41: =W41 -> 0 | Y41: =Y21-Y38 -> 0 | Z41: =Z21-Z38 -> 0 | AA41: =AA21-AA38 -> 0 | AB41: =AB21-AB38 -> 0 | AC41: =AC21-AC38 -> 309487 | AD41: =AD21-AD38 -> 0 | AE41: =AE21-AE38 -> 0 | AF41: =AF21-AF38 -> 0 | AG41: =AG21-AG38 -> 208853 | AH41: =AG41 -> 208853 | AI41: =AI21-AI38 -> 214126 | AJ41: =AJ21-AJ38 -> 743470 | AK41: =AK21-AK38 -> 810169 | AL41: =AL21-AL38 -> 614362 | AM41: =AL41 -> 614362 | AN41: =AN21-AN38 -> 597682 | AO41: =AO21-AO38 -> 566679 | AP41: =AP21-AP38 -> 569362 | AQ41: =AQ21-AQ38 -> 546327 | AR41: =AQ41 -> 546327 | AS41: =AS21-AS38 -> 522788 | AT41: =AT21-AT38 -> 501891 | AU41: =AU21-AU38 -> 426032 | AV41: =AV21-AV38 -> 329127 | AW41: =AV41 -> 329127 | AX41: =AX21-AX38 -> 243237 | AY41: =AY21-AY38 -> 211876 | AZ41: =AZ21-AZ38 -> 239569 | BA41: =BA21-BA38 -> 275503 | BB41: =BA41 -> 275503 | BC41: =BC21-BC38 -> 348949 | BD41: =BD21-BD38 -> 407131 | BE41: =BE21-BE38 -> 468506 | BF41: =BF21-BF38 -> 617287 | BG41: =BF41 -> 617287 | BH41: =BH21-BH38 -> 749492 | BI41: =BI21-BI38 -> 847759 | BJ41: =BJ21-BJ38 -> 965033 | BK41: =BK21-BK38 -> 1129739 | BL41: =BK41 -> 1129739 | BM41: =BM21-BM38 -> 1137000 | BN41: =BN21-BN38 -> 1961406 | BO41: =BO21-BO38 -> 1989377 | BP41: =BP21-BP38 -> 2002692 | BQ41: =BP41 -> 2002692 | BR41: =BR21-BR38 -> 2014802 | BS41: =BS21-BS38 -> 1987975 | BT41: =BT21-BT38 -> 1981521 | BU41: =BU21-BU38 -> 2203992.7 | BV41: =BU41 -> 2203992.7 | BW41: =BW21-BW38 -> 2419528.6 | BX41: =BX21-BX38 -> 1839761.5 | BY41: =BY21-BY38 -> 2917821.1 | BZ41: =BZ21-BZ38 -> 2298542.2 | CA41: =BZ41 -> 2298542.2
B42: Total Liabilities & Shareholders Equity | D42: =D41+D38 -> 0 | E42: =E41+E38 -> 0 | F42: =F41+F38 -> 0 | G42: =G41+G38 -> 0 | H42: =H41+H38 -> 0 | I42: =H42 -> 0 | J42: =J41+J38 -> 0 | K42: =K41+K38 -> 0 | L42: =L41+L38 -> 0 | M42: =M41+M38 -> 0 | N42: =M42 -> 0 | O42: =O41+O38 -> 0 | P42: =P41+P38 -> 0 | Q42: =Q41+Q38 -> 0 | R42: =R41+R38 -> 0 | S42: =R42 -> 0 | T42: =T41+T38 -> 0 | U42: =U41+U38 -> 0 | V42: =V41+V38 -> 0 | W42: =W41+W38 -> 0 | X42: =W42 -> 0 | Y42: =Y41+Y38 -> 0 | Z42: =Z41+Z38 -> 0 | AA42: =AA41+AA38 -> 0 | AB42: =AB41+AB38 -> 0 | AC42: =AC41+AC38 -> 499638 | AD42: =AD41+AD38 -> 0 | AE42: =AE41+AE38 -> 0 | AF42: =AF41+AF38 -> 0 | AG42: =AG41+AG38 -> 619973 | AH42: =AG42 -> 619973 | AI42: =AI41+AI38 -> 614472 | AJ42: =AJ41+AJ38 -> 1169698 | AK42: =AK41+AK38 -> 1719436 | AL42: =AL41+AL38 -> 1615417 | AM42: =AL42 -> 1615417 | AN42: =AN41+AN38 -> 1738400 | AO42: =AO41+AO38 -> 1761836 | AP42: =AP41+AP38 -> 1786365 | AQ42: =AQ41+AQ38 -> 1891138 | AR42: =AQ42 -> 1891138 | AS42: =AS41+AS38 -> 1921488 | AT42: =AT41+AT38 -> 2053310 | AU42: =AU41+AU38 -> 2051119 | AV42: =AV41+AV38 -> 2336507 | AW42: =AV42 -> 2336507 | AX42: =AX41+AX38 -> 2297120 | AY42: =AY41+AY38 -> 2355687 | AZ42: =AZ41+AZ38 -> 2410503 | BA42: =BA41+BA38 -> 2541265 | BB42: =BA42 -> 2541265 | BC42: =BC41+BC38 -> 2574131 | BD42: =BD41+BD38 -> 2667346 | BE42: =BE41+BE38 -> 2731584 | BF42: =BF41+BF38 -> 3012720 | BG42: =BF42 -> 3012720 | BH42: =BH41+BH38 -> 3129899 | BI42: =BI41+BI38 -> 3267405 | BJ42: =BJ41+BJ38 -> 3337627 | BK42: =BK41+BK38 -> 2971290 | BL42: =BK42 -> 2971290 | BM42: =BM41+BM38 -> 2926689 | BN42: =BN41+BN38 -> 3753941 | BO42: =BO41+BO38 -> 3770208 | BP42: =BP41+BP38 -> 4012705 | BQ42: =BP42 -> 4012705 | BR42: =BR41+BR38 -> 3947403 | BS42: =BS41+BS38 -> 3949923 | BT42: =BT41+BT38 -> 3982039 | BU42: =BU41+BU38 -> 4434153.3 | BV42: =BU42 -> 4434153.3 | BW42: =BW41+BW38 -> 4591613.6 | BX42: =BX41+BX38 -> 4051345.8 | BY42: =BY41+BY38 -> 5127933.8 | BZ42: =BZ41+BZ38 -> 4684124.7 | CA42: =BZ42 -> 4684124.7
B43: Scott Berg, sberg@needhamco.com
B44: (763) 350-4027
C45: check | D45: =D21-D42 -> 0 | E45: =E21-E42 -> 0 | F45: =F21-F42 -> 0 | G45: =G21-G42 -> 0 | H45: =H21-H42 -> 0 | I45: =I21-I42 -> 0 | J45: =J21-J42 -> 0 | K45: =K21-K42 -> 0 | ... CA45: =CA21-CA42 -> 13420.726
C47: DSO | E47: =((E11+D11)/2)/IS!E13*91 -> #DIV/0! | F47: =((F11+E11)/2)/IS!F13*91 -> #DIV/0! | G47: =((G11+F11)/2)/IS!G13*91 -> #DIV/0! | H47: =((H11+G11)/2)/IS!H13*91 -> #DIV/0! | J47: =((J11+I11)/2)/IS!J13*91 -> #DIV/0! | K47: =((K11+J11)/2)/IS!K13*91 -> #DIV/0! | L47: =((L11+K11)/2)/IS!L13*91 -> #DIV/0! | M47: =((M11+L11)/2)/IS!M13*91 -> #DIV/0! | AB47: =((AB8+AA8)/2)/IS!AB13*91 -> #DIV/0! | AD47: =((AD8+AC8)/2)/IS!AD13*91 -> 0 | AE47: =((AE8+AD8)/2)/IS!AE13*91 -> 0 | AF47: =((AF8+AE8)/2)/IS!AF13*91 -> 0 | AG47: =((AG8+AF8)/2)/IS!AG13*91 -> 37.821413 | AI47: =((AI8+AH8)/2)/IS!AI13*91 -> 66.54632 | AJ47: =((AJ8+AI8)/2)/IS!AJ13*91 -> 57.87955 | AK47: =((AK8+AJ8)/2)/IS!AK13*91 -> 60.954722 | AL47: =((AL8+AK8)/2)/IS!AL13*91 -> 69.516825 | AN47: =((AN8+AM8)/2)/IS!AN13*91 -> 62.027514 | AO47: =((AO8+AN8)/2)/IS!AO13*91 -> 49.395884 | AP47: =((AP8+AO8)/2)/IS!AP13*91 -> 54.365408 | AQ47: =((AQ8+AP8)/2)/IS!AQ13*91 -> 65.761027 | AS47: =((AS8+AR8)/2)/IS!AS13*91 -> 70.22883 | AT47: =((AT8+AS8)/2)/IS!AT13*91 -> 59.180887 | AU47: =((AU8+AT8)/2)/IS!AU13*91 -> 57.698828 | AV47: =((AV8+AU8)/2)/IS!AV13*91 -> 61.73573 | AX47: =((AX8+AW8)/2)/IS!AX13*91 -> 55.671002 | AY47: =((AY8+AX8)/2)/IS!AY13*91 -> 47.566881 | AZ47: =((AZ8+AY8)/2)/IS!AZ13*91 -> 49.242514 | BA47: =((BA8+AZ8)/2)/IS!BA13*91 -> 58.481994 | BC47: =((BC8+BB8)/2)/IS!BC13*91 -> 57.335416 | BD47: =((BD8+BC8)/2)/IS!BD13*91 -> 46.832127 | BE47: =((BE8+BD8)/2)/IS!BE13*91 -> 53.724799 | BF47: =((BF8+BE8)/2)/IS!BF13*91 -> 64.81199 | BH47: =((BH8+BG8)/2)/IS!BH13*91 -> 63.672675 | BI47: =((BI8+BH8)/2)/IS!BI13*91 -> 54.477438 | BJ47: =((BJ8+BI8)/2)/IS!BJ13*91 -> 50.357454 | BK47: =((BK8+BJ8)/2)/IS!BK13*91 -> 51.080247 | BM47: =((BM8+BL8)/2)/IS!BM13*91 -> 47.796094 | BN47: =((BN8+BM8)/2)/IS!BN13*91 -> 38.082412 | BO47: =((BO8+BN8)/2)/IS!BO13*91 -> 36.790188 | BP47: =((BP8+BO8)/2)/IS!BP13*91 -> 42.790464 | BR47: =((BR8+BQ8)/2)/IS!BR13*91 -> 43.922568 | BS47: =((BS8+BR8)/2)/IS!BS13*91 -> 37.765689 | BT47: =((BT8+BS8)/2)/IS!BT13*91 -> 39.582581 | BU47: =((BU8+BT8)/2)/IS!BU13*91 -> 46.370211 | BW47: =((BW8+BV8)/2)/IS!BW13*91 -> 48.015174 | BX47: =((BX8+BW8)/2)/IS!BX13*91 -> 39.995727 | BY47: =((BY8+BX8)/2)/IS!BY13*91 -> 44.605071 | BZ47: =((BZ8+BY8)/2)/IS!BZ13*91 -> 51.603519
C49: Deferred Revs | E49: =E30+E34 -> 0 | F49: =F30+F34 -> 0 | G49: =G30 -> 0 | H49: =H30 -> 0 | J49: =J30 -> 0 | K49: =K30 -> 0 | L49: =L30 -> 0 | M49: =M30 -> 0 | R49: =R30+R34 -> 0 | T49: =T30 -> 0 | U49: =U30 -> 0 | V49: =V30 -> 0 | W49: 19572 | X49: =W49 -> 19572 | Y49: 23296 | Z49: 26973 | AA49: 29796 | AB49: 32712 | AC49: =AB49 -> 32712 | AD49: 40812 | AE49: 47762 | AF49: 50895 | AG49: =AG30+AG34 -> 277924 | AI49: =AI30+AI34 -> 290535 | AJ49: =AJ30+AJ34 -> 297427 | AK49: =AK30+AK34 -> 323754 | AL49: =AL30+AL34 -> 388772 | AN49: =AN30+AN34 -> 393046 | AO49: =AO30+AO34 -> 410518 | AP49: =AP30+AP34 -> 433081 | AQ49: =AQ30+AQ34 -> 519038 | AS49: =AS30+AS34 -> 563632 | AT49: =AT30+AT34 -> 635868 | AU49: =AU30+AU34 -> 700902 | AV49: =AV30+AV34 -> 796134 | AX49: =AX30+AX34 -> 847782 | AY49: =AY30+AY34 -> 932757 | AZ49: =AZ30+AZ34 -> 957181 | BA49: =BA30+BA34 -> 1046616 | BC49: =BC30+BC34 -> 1065328 | BD49: =BD30+BD34 -> 1088430 | BE49: =BE30+BE34 -> 1103439 | BF49: =BF30+BF34 -> 1189792 | BH49: =BH30+BH34 -> 1208079 | BI49: =BI30+BI34 -> 1230250 | BJ49: =BJ30+BJ34 -> 1226668 | BK49: =BK30+BK34 -> 1342039 | BM49: =BM30+BM34 -> 1337067 | BN49: =BN30+BN34 -> 1330585 | BO49: =BO30+BO34 -> 1330680 | BP49: =BP30+BP34 -> 1476965 | BR49: =BR30+BR34 -> 1447232 | BS49: =BS30+BS34 -> 1463461 | BT49: =BT30+BT34 -> 1472626 | BU49: =BU30+BU34 -> 1642844.1 | BW49: =BW30+BW34 -> 1599762.4 | BX49: =BX30+BX34 -> 1618764.6 | BY49: =BY30+BY34 -> 1616279.2 | BZ49: =BZ30+BZ34 -> 1778177.8
C50: % y/y change | J50: =J49/E49-1 -> #DIV/0! | K50: =K49/F49-1 -> #DIV/0! | L50: =L49/G49-1 -> #DIV/0! | M50: =M49/H49-1 -> #DIV/0! | W50: =W49/R49-1 -> #DIV/0! | AB50: =AB49/W49-1 -> 0.67136726 | AD50: =AD49/Y49-1 -> 0.75188874 | AE50: =AE49/Z49-1 -> 0.7707337 | AF50: =AF49/AA49-1 -> 0.70811518 | AG50: =AG49/AB49-1 -> 7.4960871 | AI50: =AI49/AD49-1 -> 6.1188621 | AJ50: =AJ49/AE49-1 -> 5.2272727 | AK50: =AK49/AF49-1 -> 5.3612143 | AL50: =AL49/AG49-1 -> 0.39884285 | AN50: =AN49/AI49-1 -> 0.35283529 | AO50: =AO49/AJ49-1 -> 0.38023112 | AP50: =AP49/AK49-1 -> 0.3376854 | AQ50: =AQ49/AL49-1 -> 0.33507043 | AS50: =AS49/AN49-1 -> 0.43401027 | AT50: =AT49/AO49-1 -> 0.54894061 | AU50: =AU49/AP49-1 -> 0.61840857 | AV50: =AV49/AQ49-1 -> 0.53386457 | AX50: =AX49/AS49-1 -> 0.504141 | AY50: =AY49/AT49-1 -> 0.46690351 | AZ50: =AZ49/AU49-1 -> 0.3656417 | BA50: =BA49/AV49-1 -> 0.31462292 | BC50: =BC49/AX49-1 -> 0.25660606 | BD50: =BD49/AY49-1 -> 0.16689556 | BE50: =BE49/AZ49-1 -> 0.15280078 | BF50: =BF49/BA49-1 -> 0.13679898 | BH50: =BH49/BC49-1 -> 0.13399723 | BI50: =BI49/BD49-1 -> 0.13029777 | BJ50: =BJ49/BE49-1 -> 0.11167722 | BK50: =BK49/BF49-1 -> 0.12796102 | BM50: =BM49/BH49-1 -> 0.10677116 | BN50: =BN49/BI49-1 -> 0.081556594 | BO50: =BO49/BJ49-1 -> 0.084792299 | BP50: =BP49/BK49-1 -> 0.10053806 | BR50: =BR49/BM49-1 -> 0.082393029 | BS50: =BS49/BN49-1 -> 0.099862842 | BT50: =BT49/BO49-1 -> 0.10667178 | BU50: =BU49/BP49-1 -> 0.11231075 | BW50: =BW49/BR49-1 -> 0.10539461 | BX50: =BX49/BS49-1 -> 0.10612075 | BY50: =BY49/BT49-1 -> 0.09754902 | BZ50: =BZ49/BU49-1 -> 0.082377736
C51: % q/q change | F51: =F49/E49-1 -> #DIV/0! | G51: =G49/F49-1 -> #DIV/0! | H51: =H49/G49-1 -> #DIV/0! | J51: =J49/H49-1 -> #DIV/0! | K51: =K49/J49-1 -> #DIV/0! | L51: =L49/K49-1 -> #DIV/0! | M51: =M49/L49-1 -> #DIV/0! | Y51: =Y49/W49-1 -> 0.19027182 | Z51: =Z49/Y49-1 -> 0.15783826 | AA51: =AA49/Z49-1 -> 0.10466022 | AB51: =AB49/AA49-1 -> 0.097865485 | AD51: =AD49/AB49-1 -> 0.24761555 | AE51: =AE49/AD49-1 -> 0.17029305 | AF51: =AF49/AE49-1 -> 0.065596081 | AG51: =AG49/AF49-1 -> 4.4607329 | AI51: =AI49/AG49-1 -> 0.045375714 | AJ51: =AJ49/AI49-1 -> 0.023721755 | AK51: =AK49/AJ49-1 -> 0.088515837 | AL51: =AL49/AK49-1 -> 0.20082532 | AN51: =AN49/AL49-1 -> 0.01099359 | AO51: =AO49/AN49-1 -> 0.044452812 | AP51: =AP49/AO49-1 -> 0.054962267 | AQ51: =AQ49/AP49-1 -> 0.19847788 | AS51: =AS49/AQ49-1 -> 0.085916638 | AT51: =AT49/AS49-1 -> 0.12816164 | AU51: =AU49/AT49-1 -> 0.10227594 | AV51: =AV49/AU49-1 -> 0.13587064 | AX51: =AX49/AV49-1 -> 0.064873501 | AY51: =AY49/AX49-1 -> 0.10023214 | AZ51: =AZ49/AY49-1 -> 0.026184741 | BA51: =BA49/AZ49-1 -> 0.093435829 | BC51: =BC49/BA49-1 -> 0.017878572 | BD51: =BD49/BC49-1 -> 0.02168534 | BE51: =BE49/BD49-1 -> 0.013789587 | BF51: =BF49/BE49-1 -> 0.078258064 | BH51: =BH49/BF49-1 -> 0.015369913 | BI51: =BI49/BH49-1 -> 0.018352277 | BJ51: =BJ49/BI49-1 -> -0.0029116033 | BK51: =BK49/BJ49-1 -> 0.094052343 | BM51: =BM49/BK49-1 -> -0.0037048104 | BN51: =BN49/BM49-1 -> -0.0048479246 | BO51: =BO49/BN49-1 -> 7.1397167e-05 | BP51: =BP49/BO49-1 -> 0.10993252 | BR51: =BR49/BP49-1 -> -0.020131147 | BS51: =BS49/BR49-1 -> 0.011213821 | BT51: =BT49/BS49-1 -> 0.0062625516 | BU51: =BU49/BT49-1 -> 0.11558811 | BW51: =BW49/BU49-1 -> -0.026223792 | BX51: =BX49/BW49-1 -> 0.011878096 | BY51: =BY49/BX49-1 -> -0.0015353428 | BZ51: =BZ49/BY49-1 -> 0.10016747
B53: Drivers of Revenue % - Assets
C54: Accounts receivable | E54: =E11/IS!E13 -> #DIV/0! | F54: =F11/IS!F13 -> #DIV/0! | G54: =G11/IS!G13 -> #DIV/0! | H54: =H11/IS!H13 -> #DIV/0! | J54: =J11/IS!J13 -> #DIV/0! | K54: =K11/IS!K13 -> #DIV/0! | L54: =L11/IS!L13 -> #DIV/0! | M54: =M11/IS!M13 -> #DIV/0! | R54: =R8/IS!R13 -> #DIV/0! | T54: =T8/IS!T13 -> #DIV/0! | U54: =U8/IS!U13 -> #DIV/0! | V54: =V8/IS!V13 -> #DIV/0! | W54: =W8/IS!W13 -> #DIV/0! | Y54: =Y8/IS!Y13 -> #DIV/0! | Z54: =Z8/IS!Z13 -> #DIV/0! | AA54: =AA8/IS!AA13 -> #DIV/0! | AB54: =AB8/IS!AB13 -> #DIV/0! | AD54: =AD8/IS!AD13 -> 0 | AE54: =AE8/IS!AE13 -> 0 | AF54: =AF8/IS!AF13 -> 0 | AG54: =AG8/IS!AG13 -> 0.83123984 | AI54: =AI8/IS!AI13 -> 0.66830971 | AJ54: =AJ8/IS!AJ13 -> 0.64872129 | AK54: =AK8/IS!AK13 -> 0.732186 | AL54: =AL8/IS!AL13 -> 0.87391104 | AN54: =AN8/IS!AN13 -> 0.54745235 | AO54: =AO8/IS!AO13 -> 0.58847597 | AP54: =AP8/IS!AP13 -> 0.63912915 | AQ54: =AQ8/IS!AQ13 -> 0.86520672 | AS54: =AS8/IS!AS13 -> 0.74272516 | AT54: =AT8/IS!AT13 -> 0.65603768 | AU54: =AU8/IS!AU13 -> 0.68182115 | AV54: =AV8/IS!AV13 -> 0.75092017 | AX54: =AX8/IS!AX13 -> 0.53373853 | AY54: =AY8/IS!AY13 -> 0.55628277 | AZ54: =AZ8/IS!AZ13 -> 0.56025615 | BA54: =BA8/IS!BA13 -> 0.75917483 | BC54: =BC8/IS!BC13 -> 0.51108559 | BD54: =BD8/IS!BD13 -> 0.54570352 | BE54: =BE8/IS!BE13 -> 0.65474241 | BF54: =BF8/IS!BF13 -> 0.7837065 | BH54: =BH8/IS!BH13 -> 0.61784006 | BI54: =BI8/IS!BI13 -> 0.60309414 | BJ54: =BJ8/IS!BJ13 -> 0.51462763 | BK54: =BK8/IS!BK13 -> 0.61665867 | BM54: =BM8/IS!BM13 -> 0.43141875 | BN54: =BN8/IS!BN13 -> 0.42102396 | BO54: =BO8/IS!BO13 -> 0.39803397 | BP54: =BP8/IS!BP13 -> 0.55340534 | BR54: =BR8/IS!BR13 -> 0.40279629 | BS54: =BS8/IS!BS13 -> 0.44582432 | BT54: =BT8/IS!BT13 -> 0.43377284 | BU54: 0.59 | BW54: 0.45 | BX54: 0.45 | BY54: 0.54 | BZ54: 0.6
C55: Contract assets - current | AI55: =AI10/IS!AI13 -> 0.077210413 | AJ55: =AJ10/IS!AJ13 -> 0.082373506 | AK55: =AK10/IS!AK13 -> 0.067584158 | AL55: =AL10/IS!AL13 -> 0.053151223 | AN55: =AN10/IS!AN13 -> 0.062440994 | AO55: =AO10/IS!AO13 -> 0.065989848 | AP55: =AP10/IS!AP13 -> 0.07182708 | AQ55: =AQ10/IS!AQ13 -> 0.045479183 | AS55: =AS10/IS!AS13 -> 0.044563106 | AT55: =AT10/IS!AT13 -> 0.04980582 | AU55: =AU10/IS!AU13 -> 0.058698485 | AV55: =AV10/IS!AV13 -> 0.039180966 | AX55: =AX10/IS!AX13 -> 0.032546826 | AY55: =AY10/IS!AY13 -> 0.027338408 | AZ55: =AZ10/IS!AZ13 -> 0.026931249 | BA55: =BA10/IS!BA13 -> 0.021672509 | BC55: =BC10/IS!BC13 -> 0.02270797 | BD55: =BD10/IS!BD13 -> 0.015087177 | BE55: =BE10/IS!BE13 -> 0.02108409 | BF55: =BF10/IS!BF13 -> 0.018856053 | BH55: =BH10/IS!BH13 -> 0.026389956 | BI55: =BI10/IS!BI13 -> 0.023539779 | BJ55: =BJ10/IS!BJ13 -> 0.027670501 | BK55: =BK10/IS!BK13 -> 0.022350243 | BM55: =BM10/IS!BM13 -> 0.017359506 | BN55: =BN10/IS!BN13 -> 0.018272428 | BO55: =BO10/IS!BO13 -> 0.018077157 | BP55: =BP10/IS!BP13 -> 0.017731355 | BR55: =BR10/IS!BR13 -> 0.012551496 | BS55: =BS10/IS!BS13 -> 0.012355178 | BT55: =BT10/IS!BT13 -> 0.010970856 | BU55: 0.02 | BW55: 0.02 | BX55: 0.02 | BY55: 0.02 | BZ55: 0.02
C56: Prepaid expenses & other | E56: =#REF!/IS!E13 -> #REF! | F56: =#REF!/IS!F13 -> #REF! | G56: =#REF!/IS!G13 -> #REF! | H56: =#REF!/IS!H13 -> #REF! | J56: =#REF!/IS!J13 -> #REF! | K56: =#REF!/IS!K13 -> #REF! | L56: =#REF!/IS!L13 -> #REF! | M56: =#REF!/IS!M13 -> #REF! | R56: =R11/IS!R13 -> #DIV/0! | T56: =T11/IS!T13 -> #DIV/0! | U56: =U11/IS!U13 -> #DIV/0! | V56: =V11/IS!V13 -> #DIV/0! | W56: =W11/IS!W13 -> #DIV/0! | Y56: =Y11/IS!Y13 -> #DIV/0! | Z56: =Z11/IS!Z13 -> #DIV/0! | AA56: =AA11/IS!AA13 -> #DIV/0! | AB56: =AB11/IS!AB13 -> #DIV/0! | AD56: =AD11/IS!AD13 -> 0 | AE56: =AE11/IS!AE13 -> 0 | AF56: =AF11/IS!AF13 -> 0 | AG56: =AG11/IS!AG13 -> 0.15683733 | AI56: =AI11/IS!AI13 -> 0.19112626 | AJ56: =AJ11/IS!AJ13 -> 0.1602931 | AK56: =AK11/IS!AK13 -> 0.15889228 | AL56: =AL11/IS!AL13 -> 0.15008111 | AN56: =AN11/IS!AN13 -> 0.1838691 | AO56: =AO11/IS!AO13 -> 0.16513166 | AP56: =AP11/IS!AP13 -> 0.1515579 | AQ56: =AQ11/IS!AQ13 -> 0.13505157 | AS56: =AS11/IS!AS13 -> 0.1722999 | AT56: =AT11/IS!AT13 -> 0.15241563 | AU56: =AU11/IS!AU13 -> 0.12363582 | AV56: =AV11/IS!AV13 -> 0.11230036 | AX56: =AX11/IS!AX13 -> 0.13893638 | AY56: =AY11/IS!AY13 -> 0.11956182 | AZ56: =AZ11/IS!AZ13 -> 0.12437507 | BA56: =BA11/IS!BA13 -> 0.10887216 | BC56: =BC11/IS!BC13 -> 0.13703091 | BD56: =BD11/IS!BD13 -> 0.12720031 | BE56: =BE11/IS!BE13 -> 0.10661184 | BF56: =BF11/IS!BF13 -> 0.10610908 | BH56: =BH11/IS!BH13 -> 0.13111668 | BI56: =BI11/IS!BI13 -> 0.11850159 | BJ56: =BJ11/IS!BJ13 -> 0.10369335 | BK56: =BK11/IS!BK13 -> 0.094027676 | BM56: =BM11/IS!BM13 -> 0.11913083 | BN56: =BN11/IS!BN13 -> 0.11099185 | BO56: =BO11/IS!BO13 -> 0.099907263 | BP56: =BP11/IS!BP13 -> 0.10610987 | BR56: =BR11/IS!BR13 -> 0.14562092 | BS56: =BS11/IS!BS13 -> 0.134593 | BT56: =BT11/IS!BT13 -> 0.12626382 | BU56: 0.13 | BW56: 0.13 | BX56: 0.12 | BY56: 0.11 | BZ56: 0.11
C57: Deferred Contract asset - noncurrent | R57: =#REF!/IS!R13 -> #REF! | T57: =#REF!/IS!T13 -> #REF! | U57: =#REF!/IS!U13 -> #REF! | V57: =#REF!/IS!V13 -> #REF! | W57: =#REF!/IS!W13 -> #REF! | Y57: =#REF!/IS!Y13 -> #REF! | Z57: =#REF!/IS!Z13 -> #REF! | AA57: =#REF!/IS!AA13 -> #REF! | AB57: =#REF!/IS!AB13 -> #REF! | AD57: =AD15/IS!AD13 -> 0 | AE57: =AE15/IS!AE13 -> 0 | AF57: =AF15/IS!AF13 -> 0 | AG57: =AG15/IS!AG13 -> 0.50737536 | AI57: =AI15/IS!AI13 -> 0.50318982 | AJ57: =AJ15/IS!AJ13 -> 0.51602572 | AK57: =AK15/IS!AK13 -> 0.54427783 | AL57: =AL15/IS!AL13 -> 0.56367032 | AN57: =AN15/IS!AN13 -> 0.54179714 | AO57: =AO15/IS!AO13 -> 0.528131 | AP57: =AP15/IS!AP13 -> 0.54607979 | AQ57: =AQ15/IS!AQ13 -> 0.55778752 | AS57: =AS15/IS!AS13 -> 0.57130063 | AT57: =AT15/IS!AT13 -> 0.5795435 | AU57: =AU15/IS!AU13 -> 0.58788582 | AV57: =AV15/IS!AV13 -> 0.60369275 | AX57: =AX15/IS!AX13 -> 0.58420774 | AY57: =AY15/IS!AY13 -> 0.56586773 | AZ57: =AZ15/IS!AZ13 -> 0.55012531 | BA57: =BA15/IS!BA13 -> 0.53688011 | BC57: =BC15/IS!BC13 -> 0.5329782 | BD57: =BD15/IS!BD13 -> 0.51864882 | BE57: =BE15/IS!BE13 -> 0.51119584 | BF57: =BF15/IS!BF13 -> 0.53200693 | BH57: =BH15/IS!BH13 -> 0.20472552 | BI57: =BI15/IS!BI13 -> 0.53767048 | BJ57: =BJ15/IS!BJ13 -> 0.54710667 | BK57: =BK15/IS!BK13 -> 0.57500709 | BM57: =BM15/IS!BM13 -> 0.58584494 | BN57: =BN15/IS!BN13 -> 0.58095559 | BO57: =BO15/IS!BO13 -> 0.59085212 | BP57: =BP15/IS!BP13 -> 0.60186769 | BR57: =BR15/IS!BR13 -> 0.60494543 | BS57: =BS15/IS!BS13 -> 0.57820033 | BT57: =BT15/IS!BT13 -> 0.56522515 | BU57: 0.65 | BW57: 0.6 | BX57: 0.6 | BY57: 0.62 | BZ57: 0.65
C58: Operating lease right to use | AI58: =AI16/IS!AI13 -> 0 | AJ58: =AJ16/IS!AJ13 -> 0 | AK58: =AK16/IS!AK13 -> 0 | AL58: =AL16/IS!AL13 -> 0 | AN58: =AN16/IS!AN13 -> 0.67003019 | AO58: =AO16/IS!AO13 -> 0.58270377 | AP58: =AP16/IS!AP13 -> 0.54759882 | AQ58: =AQ16/IS!AQ13 -> 0.54505538 | AS58: =AS16/IS!AS13 -> 0.54368605 | AT58: =AT16/IS!AT13 -> 0.4918427 | AU58: =AU16/IS!AU13 -> 0.41878393 | AV58: =AV16/IS!AV13 -> 0.36981374 | AX58: =AX16/IS!AX13 -> 0.32443432 | AY58: =AY16/IS!AY13 -> 0.27467158 | AZ58: =AZ16/IS!AZ13 -> 0.2431109 | BA58: =BA16/IS!BA13 -> 0.21696785 | BC58: =BC16/IS!BC13 -> 0.19804754 | BD58: =BD16/IS!BD13 -> 0.16149724 | BE58: =BE16/IS!BE13 -> 0.14277348 | BF58: =BF16/IS!BF13 -> 0.21452115 | BH58: =BH16/IS!BH13 -> 0.53419173 | BI58: =BI16/IS!BI13 -> 0.19098951 | BJ58: =BJ16/IS!BJ13 -> 0.1801745 | BK58: =BK16/IS!BK13 -> 0.17292311 | BM58: =BM16/IS!BM13 -> 0.1690956 | BN58: =BN16/IS!BN13 -> 0.16015309 | BO58: =BO16/IS!BO13 -> 0.15018812 | BP58: =BP16/IS!BP13 -> 0.14122991 | BR58: =BR16/IS!BR13 -> 0.15113127 | BS58: =BS16/IS!BS13 -> 0.13733207 | BT58: =BT16/IS!BT13 -> 0.16274577 | BU58: 0.16 | BW58: 0.16 | BX58: 0.16 | BY58: 0.16 | BZ58: 0.16
C59: Other assets | E59: =E20/IS!E13 -> #DIV/0! | F59: =F20/IS!F13 -> #DIV/0! | G59: =G20/IS!G13 -> #DIV/0! | H59: =H20/IS!H13 -> #DIV/0! | J59: =J20/IS!J13 -> #DIV/0! | K59: =K20/IS!K13 -> #DIV/0! | L59: =L20/IS!L13 -> #DIV/0! | M59: =M20/IS!M13 -> #DIV/0! | R59: =R20/IS!R13 -> #DIV/0! | T59: =T20/IS!T13 -> #DIV/0! | U59: =U20/IS!U13 -> #DIV/0! | V59: =V20/IS!V13 -> #DIV/0! | W59: =W20/IS!W13 -> #DIV/0! | Y59: =Y20/IS!Y13 -> #DIV/0! | Z59: =Z20/IS!Z13 -> #DIV/0! | AA59: =AA20/IS!AA13 -> #DIV/0! | AB59: =AB20/IS!AB13 -> #DIV/0! | AD59: =AD20/IS!AD13 -> 0 | AE59: =AE20/IS!AE13 -> 0 | AF59: =AF20/IS!AF13 -> 0 | AG59: =AG20/IS!AG13 -> 0.075029891 | AI59: =AI20/IS!AI13 -> 0.082736445 | AJ59: =AJ20/IS!AJ13 -> 0.056949067 | AK59: =AK20/IS!AK13 -> 0.051433697 | AL59: =AL20/IS!AL13 -> 0.044224261 | AN59: =AN20/IS!AN13 -> 0.11192174 | AO59: =AO20/IS!AO13 -> 0.10142098 | AP59: =AP20/IS!AP13 -> 0.09866454 | AQ59: =AQ20/IS!AQ13 -> 0.089772459 | AS59: =AS20/IS!AS13 -> 0.088587522 | AT59: =AT20/IS!AT13 -> 0.048680777 | AU59: =AU20/IS!AU13 -> 0.058836894 | AV59: =AV20/IS!AV13 -> 0.057883768 | AX59: =AX20/IS!AX13 -> 0.072231058 | AY59: =AY20/IS!AY13 -> 0.0755699 | AZ59: =AZ20/IS!AZ13 -> 0.083948865 | BA59: =BA20/IS!BA13 -> 0.08666421 | BC59: =BC20/IS!BC13 -> 0.10441793 | BD59: =BD20/IS!BD13 -> 0.10824611 | BE59: =BE20/IS!BE13 -> 0.11700283 | BF59: =BF20/IS!BF13 -> 0.12050772 | BH59: =BH20/IS!BH13 -> 0.12971962 | BI59: =BI20/IS!BI13 -> 0.13098837 | BJ59: =BJ20/IS!BJ13 -> 0.13139526 | BK59: =BK20/IS!BK13 -> 0.1398329 | BM59: =BM20/IS!BM13 -> 0.15170227 | BN59: =BN20/IS!BN13 -> 0.17558052 | BO59: =BO20/IS!BO13 -> 0.17491322 | BP59: =BP20/IS!BP13 -> 0.1826765 | BR59: =BR20/IS!BR13 -> 0.20044811 | BS59: =BS20/IS!BS13 -> 0.20435379 | BT59: =BT20/IS!BT13 -> 0.20801246 | BU59: 0.19 | BW59: 0.2 | BX59: 0.181 | BY59: 0.18 | BZ59: 0.18
B61: Drivers of Revenue % - Liabilities
C62: Accounts payable | E62: =E24/IS!E13 -> #DIV/0! | F62: =F24/IS!F13 -> #DIV/0! | G62: =G24/IS!G13 -> #DIV/0! | H62: =H24/IS!H13 -> #DIV/0! | J62: =J24/IS!J13 -> #DIV/0! | K62: =K24/IS!K13 -> #DIV/0! | L62: =L24/IS!L13 -> #DIV/0! | M62: =M24/IS!M13 -> #DIV/0! | R62: =R24/IS!R13 -> #DIV/0! | T62: =T24/IS!T13 -> #DIV/0! | U62: =U24/IS!U13 -> #DIV/0! | V62: =V24/IS!V13 -> #DIV/0! | W62: =W24/IS!W13 -> #DIV/0! | Y62: =Y24/IS!Y13 -> #DIV/0! | Z62: =Z24/IS!Z13 -> #DIV/0! | AA62: =AA24/IS!AA13 -> #DIV/0! | AB62: =AB24/IS!AB13 -> #DIV/0! | AD62: =AD24/IS!AD13 -> 0 | AE62: =AE24/IS!AE13 -> 0 | AF62: =AF24/IS!AF13 -> 0 | AG62: =AG24/IS!AG13 -> 0.15928235 | AI62: =AI24/IS!AI13 -> 0.085162508 | AJ62: =AJ24/IS!AJ13 -> 0.099692297 | AK62: =AK24/IS!AK13 -> 0.1236595 | AL62: =AL24/IS!AL13 -> 0.098081429 | AN62: =AN24/IS!AN13 -> 0.10018601 | AO62: =AO24/IS!AO13 -> 0.099536526 | AP62: =AP24/IS!AP13 -> 0.11662832 | AQ62: =AQ24/IS!AQ13 -> 0.10238091 | AS62: =AS24/IS!AS13 -> 0.072399896 | AT62: =AT24/IS!AT13 -> 0.096587173 | AU62: =AU24/IS!AU13 -> 0.084374665 | AV62: =AV24/IS!AV13 -> 0.086718899 | AX62: =AX24/IS!AX13 -> 0.031700485 | AY62: =AY24/IS!AY13 -> 0.065668446 | AZ62: =AZ24/IS!AZ13 -> 0.087470644 | BA62: =BA24/IS!BA13 -> 0.090911595 | BC62: =BC24/IS!BC13 -> 0.044527529 | BD62: =BD24/IS!BD13 -> 0.071440281 | BE62: =BE24/IS!BE13 -> 0.07308862 | BF62: =BF24/IS!BF13 -> 0.03698285 | BH62: =BH24/IS!BH13 -> 0.022207842 | BI62: =BI24/IS!BI13 -> 0.008438432 | BJ62: =BJ24/IS!BJ13 -> 0.021111589 | BK62: =BK24/IS!BK13 -> 0.026711642 | BM62: =BM24/IS!BM13 -> 0.024942224 | BN62: =BN24/IS!BN13 -> 0.011026769 | BO62: =BO24/IS!BO13 -> 0.024037519 | BP62: =BP24/IS!BP13 -> 0.039545148 | BR62: =BR24/IS!BR13 -> 0.03219128 | BS62: =BS24/IS!BS13 -> 0.013293182 | BT62: =BT24/IS!BT13 -> 0.027472353 | BU62: 0.03 | BW62: 0.03 | BX62: 0.03 | BY62: 0.03 | BZ62: 0.03
C63: Accrued expenses and other current liabilities | E63: =E25/IS!E13 -> #DIV/0! | F63: =F25/IS!F13 -> #DIV/0! | G63: =G25/IS!G13 -> #DIV/0! | H63: =H25/IS!H13 -> #DIV/0! | J63: =J25/IS!J13 -> #DIV/0! | K63: =K25/IS!K13 -> #DIV/0! | L63: =L25/IS!L13 -> #DIV/0! | M63: =M25/IS!M13 -> #DIV/0! | R63: =R25/IS!R13 -> #DIV/0! | T63: =T25/IS!T13 -> #DIV/0! | U63: =U25/IS!U13 -> #DIV/0! | V63: =V25/IS!V13 -> #DIV/0! | W63: =W25/IS!W13 -> #DIV/0! | Y63: =Y25/IS!Y13 -> #DIV/0! | Z63: =Z25/IS!Z13 -> #DIV/0! | AA63: =AA25/IS!AA13 -> #DIV/0! | AB63: =AB25/IS!AB13 -> #DIV/0! | AD63: =AD25/IS!AD13 -> 0 | AE63: =AE25/IS!AE13 -> 0 | AF63: =AF25/IS!AF13 -> 0 | AG63: =AG25/IS!AG13 -> 0.18343028 | AI63: =AI25/IS!AI13 -> 0.19921955 | AJ63: =AJ25/IS!AJ13 -> 0.18036565 | AK63: =AK25/IS!AK13 -> 0.12707907 | AL63: =AL25/IS!AL13 -> 0.17852923 | AN63: =AN25/IS!AN13 -> 0.19211823 | AO63: =AO25/IS!AO13 -> 0.21556627 | AP63: =AP25/IS!AP13 -> 0.18456766 | AQ63: =AQ25/IS!AQ13 -> 0.19769003 | AS63: =AS25/IS!AS13 -> 0.15647253 | AT63: =AT25/IS!AT13 -> 0.16047503 | AU63: =AU25/IS!AU13 -> 0.15604182 | AV63: =AV25/IS!AV13 -> 0.15448204 | AX63: =AX25/IS!AX13 -> 0.16082187 | AY63: =AY25/IS!AY13 -> 0.15984753 | AZ63: =AZ25/IS!AZ13 -> 0.14861686 | BA63: =BA25/IS!BA13 -> 0.15732196 | BC63: =BC25/IS!BC13 -> 0.15786863 | BD63: =BD25/IS!BD13 -> 0.14586682 | BE63: =BE25/IS!BE13 -> 0.14908213 | BF63: =BF25/IS!BF13 -> 0.15310897 | BH63: =BH25/IS!BH13 -> 0.15374485 | BI63: =BI25/IS!BI13 -> 0.15900984 | BJ63: =BJ25/IS!BJ13 -> 0.14226015 | BK63: =BK25/IS!BK13 -> 0.14604021 | BM63: =BM25/IS!BM13 -> 0.13975678 | BN63: =BN25/IS!BN13 -> 0.12669508 | BO63: =BO25/IS!BO13 -> 0.12531597 | BP63: =BP25/IS!BP13 -> 0.1282818 | BR63: =BR25/IS!BR13 -> 0.13249718 | BS63: =BS25/IS!BS13 -> 0.12562388 | BT63: =BT25/IS!BT13 -> 0.14644223 | BU63: 0.13 | BW63: 0.16 | BX63: 0.16 | BY63: 0.14 | BZ63: 0.14
C64: Accrued compensation | AD64: =AD26/IS!AD13 -> 0 | AE64: =AE26/IS!AE13 -> 0 | AF64: =AF26/IS!AF13 -> 0 | AG64: =AG26/IS!AG13 -> 0.34157744 | AI64: =AI26/IS!AI13 -> 0.21760757 | AJ64: =AJ26/IS!AJ13 -> 0.30657791 | AK64: =AK26/IS!AK13 -> 0.3009558 | AL64: =AL26/IS!AL13 -> 0.3882853 | AN64: =AN26/IS!AN13 -> 0.26959927 | AO64: =AO26/IS!AO13 -> 0.33945639 | AP64: =AP26/IS!AP13 -> 0.28400574 | AQ64: =AQ26/IS!AQ13 -> 0.302621 | AS64: =AS26/IS!AS13 -> 0.27491019 | AT64: =AT26/IS!AT13 -> 0.32618371 | AU64: =AU26/IS!AU13 -> 0.29828712 | AV64: =AV26/IS!AV13 -> 0.36240131 | AX64: =AX26/IS!AX13 -> 0.27637195 | AY64: =AY26/IS!AY13 -> 0.27859856 | AZ64: =AZ26/IS!AZ13 -> 0.26535439 | BA64: =BA26/IS!BA13 -> 0.27574945 | BC64: =BC26/IS!BC13 -> 0.23394916 | BD64: =BD26/IS!BD13 -> 0.24070211 | BE64: =BE26/IS!BE13 -> 0.22665436 | BF64: =BF26/IS!BF13 -> 0.2473301 | BH64: =BH26/IS!BH13 -> 0.21468487 | BI64: =BI26/IS!BI13 -> 0.23592565 | BJ64: =BJ26/IS!BJ13 -> 0.22755029 | BK64: =BK26/IS!BK13 -> 0.2741014 | BM64: =BM26/IS!BM13 -> 0.21691562 | BN64: =BN26/IS!BN13 -> 0.24265822 | BO64: =BO26/IS!BO13 -> 0.21035346 | BP64: =BP26/IS!BP13 -> 0.29257896 | BR64: =BR26/IS!BR13 -> 0.22389197 | BS64: =BS26/IS!BS13 -> 0.25979971 | BT64: =BT26/IS!BT13 -> 0.22115476 | BU64: 0.3 | BW64: 0.26 | BX64: 0.26 | BY64: 0.27 | BZ64: 0.28
C65: Operating lease liabilities | AI65: =AI28/IS!AI13 -> 0 | AJ65: =AJ28/IS!AJ13 -> 0 | AK65: =AK28/IS!AK13 -> 0.098517252 | AL65: =AL28/IS!AL13 -> 0 | AN65: =AN28/IS!AN13 -> 0.079084136 | AO65: =AO28/IS!AO13 -> 0.072971665 | AP65: =AP28/IS!AP13 -> 0.075121642 | AQ65: =AQ28/IS!AQ13 -> 0.075403336 | AS65: =AS28/IS!AS13 -> 0.092967743 | AT65: =AT28/IS!AT13 -> 0.088878434 | AU65: =AU28/IS!AU13 -> 0.079997806 | AV65: =AV28/IS!AV13 -> 0.076516948 | AX65: =AX28/IS!AX13 -> 0.074139056 | AY65: =AY28/IS!AY13 -> 0.068284477 | AZ65: =AZ28/IS!AZ13 -> 0.064583666 | BA65: =BA28/IS!BA13 -> 0.064397722 | BC65: =BC28/IS!BC13 -> 0.063348916 | BD65: =BD28/IS!BD13 -> 0.069881257 | BE65: =BE28/IS!BE13 -> 0.05378 | BF65: =BF28/IS!BF13 -> 0.036470399 | BH65: =BH28/IS!BH13 -> 0.034385263 | BI65: =BI28/IS!BI13 -> 0.033522518 | BJ65: =BJ28/IS!BJ13 -> 0.030982795 | BK65: =BK28/IS!BK13 -> 0.031204993 | BM65: =BM28/IS!BM13 -> 0.029486782 | BN65: =BN28/IS!BN13 -> 0.026859069 | BO65: =BO28/IS!BO13 -> 0.025843247 | BP65: =BP28/IS!BP13 -> 0.024575782 | BR65: =BR28/IS!BR13 -> 0.028566602 | BS65: =BS28/IS!BS13 -> 0.026460214 | BT65: =BT28/IS!BT13 -> 0.019356021 | BU65: 0.025 | BW65: 0.03 | BX65: 0.03 | BY65: 0.03 | BZ65: 0.03
C66: Contract liabilities - current | AI66: =AI30/IS!AI13 -> 1.8129364 | AJ66: =AJ30/IS!AJ13 -> 1.7344173 | AK66: =AK30/IS!AK13 -> 1.7749194 | AL66: =AL30/IS!AL13 -> 1.9078565 | AN66: =AN30/IS!AN13 -> 1.8015349 | AO66: =AO30/IS!AO13 -> 1.7093102 | AP66: =AP30/IS!AP13 -> 1.6983511 | AQ66: =AQ30/IS!AQ13 -> 1.8463777 | AS66: =AS30/IS!AS13 -> 1.859641 | AT66: =AT30/IS!AT13 -> 1.8235377 | AU66: =AU30/IS!AU13 -> 1.791966 | AV66: =AV30/IS!AV13 -> 1.8093424 | AX66: =AX30/IS!AX13 -> 1.769096 | AY66: =AY30/IS!AY13 -> 1.7869097 | AZ66: =AZ30/IS!AZ13 -> 1.7235101 | BA66: =BA30/IS!BA13 -> 1.7731428 | BC66: =BC30/IS!BC13 -> 1.7828236 | BD66: =BD30/IS!BD13 -> 1.725856 | BE66: =BE30/IS!BE13 -> 1.6859169 | BF66: =BF30/IS!BF13 -> 1.7782136 | BH66: =BH30/IS!BH13 -> 1.7997968 | BI66: =BI30/IS!BI13 -> 1.7572108 | BJ66: =BJ30/IS!BJ13 -> 1.7198214 | BK66: =BK30/IS!BK13 -> 1.8530109 | BM66: =BM30/IS!BM13 -> 1.8505538 | BN66: =BN30/IS!BN13 -> 1.7765177 | BO66: =BO30/IS!BO13 -> 1.7325309 | BP66: =BP30/IS!BP13 -> 1.8749607 | BR66: =BR30/IS!BR13 -> 1.8632496 | BS66: =BS30/IS!BS13 -> 1.7936153 | BT66: =BT30/IS!BT13 -> 1.7652581 | BU66: 1.94 | BW66: 1.95 | BX66: 1.88 | BY66: 1.83 | BZ66: 1.99
C67: Operating lease liabilities-noncurrent | AI67: =AI32/IS!AI13 -> 0 | AJ67: =AJ32/IS!AJ13 -> 0 | AK67: =AK32/IS!AK13 -> 0 | AL67: =AL32/IS!AL13 -> 0 | AN67: =AN32/IS!AN13 -> 0.72339013 | AO67: =AO32/IS!AO13 -> 0.63873232 | AP67: =AP32/IS!AP13 -> 0.60264848 | AQ67: =AQ32/IS!AQ13 -> 0.59088743 | AS67: =AS32/IS!AS13 -> 0.58498335 | AT67: =AT32/IS!AT13 -> 0.5197467 | AU67: =AU32/IS!AU13 -> 0.44154569 | AV67: =AV32/IS!AV13 -> 0.38455505 | AX67: =AX32/IS!AX13 -> 0.33256303 | AY67: =AY32/IS!AY13 -> 0.285292 | AZ67: =AZ32/IS!AZ13 -> 0.24976946 | BA67: =BA32/IS!BA13 -> 0.21751706 | BC67: =BC32/IS!BC13 -> 0.19530756 | BD67: =BD32/IS!BD13 -> 0.14542161 | BE67: =BE32/IS!BE13 -> 0.12585849 | BF67: =BF32/IS!BF13 -> 0.21430131 | BH67: =BH32/IS!BH13 -> 0.20599557 | BI67: =BI32/IS!BI13 -> 0.19012429 | BJ67: =BJ32/IS!BJ13 -> 0.17782305 | BK67: =BK32/IS!BK13 -> 0.16960328 | BM67: =BM32/IS!BM13 -> 0.165498 | BN67: =BN32/IS!BN13 -> 0.15737466 | BO67: =BO32/IS!BO13 -> 0.1472298 | BP67: =BP32/IS!BP13 -> 0.13571624 | BR67: =BR32/IS!BR13 -> 0.14551354 | BS67: =BS32/IS!BS13 -> 0.13209124 | BT67: =BT32/IS!BT13 -> 0.16439543 | BU67: 0.145 | BW67: 0.145 | BX67: 0.145 | BY67: 0.145 | BZ67: 0.145
C68: Contract liabilities - noncurrent | AI68: =AI34/IS!AI13 -> 0.051762426 | AJ68: =AJ34/IS!AJ13 -> 0.046113599 | AK68: =AK34/IS!AK13 -> 0.039997758 | AL68: =AL34/IS!AL13 -> 0.03861174 | AN68: =AN34/IS!AN13 -> 0.035454894 | AO68: =AO34/IS!AO13 -> 0.033037367 | AP68: =AP34/IS!AP13 -> 0.037430562 | AQ68: =AQ34/IS!AQ13 -> 0.041754124 | AS68: =AS34/IS!AS13 -> 0.038001192 | AT68: =AT34/IS!AT13 -> 0.034589973 | AU68: =AU34/IS!AU13 -> 0.038433314 | AV68: =AV34/IS!AV13 -> 0.038273559 | AX68: =AX34/IS!AX13 -> 0.038240975 | AY68: =AY34/IS!AY13 -> 0.035436578 | AZ68: =AZ34/IS!AZ13 -> 0.031294515 | BA68: =BA34/IS!BA13 -> 0.028795099 | BC68: =BC34/IS!BC13 -> 0.02682897 | BD68: =BD34/IS!BD13 -> 0.023513944 | BE68: =BE34/IS!BE13 -> 0.023614057 | BF68: =BF34/IS!BF13 -> 0.025660424 | BH68: =BH34/IS!BH13 -> 0.02678458 | BI68: =BI34/IS!BI13 -> 0.03175718 | BJ68: =BJ34/IS!BJ13 -> 0.031508193 | BK68: =BK34/IS!BK13 -> 0.030854059 | BM68: =BM34/IS!BM13 -> 0.033594499 | BN68: =BN34/IS!BN13 -> 0.031276027 | BO68: =BO34/IS!BO13 -> 0.030379428 | BP68: =BP34/IS!BP13 -> 0.027726821 | BR68: =BR34/IS!BR13 -> 0.031891406 | BS68: =BS34/IS!BS13 -> 0.034257765 | BT68: =BT34/IS!BT13 -> 0.034248182 | BU68: 0.046 | BW68: 0.034 | BX68: 0.034 | BY68: 0.04 | BZ68: 0.045
C69: Deferred tax liability | AD69: =#REF!/IS!AD13 -> #REF! | AE69: =#REF!/IS!AE13 -> #REF! | AF69: =#REF!/IS!AF13 -> #REF! | AG69: =#REF!/IS!AG13 -> #REF! | AI69: =AI36/IS!AI13 -> 0.01607748 | AJ69: =AJ36/IS!AJ13 -> 0.01496013 | AK69: =AK36/IS!AK13 -> 0.014014631 | AL69: =AL36/IS!AL13 -> 0.021063225 | AN69: =AN36/IS!AN13 -> 0.019942794 | AO69: =AO36/IS!AO13 -> 0.018123016 | AP69: =AP36/IS!AP13 -> 0.017134131 | AQ69: =AQ36/IS!AQ13 -> 0.017897743 | AS69: =AS36/IS!AS13 -> 0.016207826 | AT69: =AT36/IS!AT13 -> 0.025539948 | AU69: =AU36/IS!AU13 -> 0.02082403 | AV69: =AV36/IS!AV13 -> 0.01500123 | AX69: =AX36/IS!AX13 -> 0.013822861 | AY69: =AY36/IS!AY13 -> 0.012550699 | AZ69: =AZ36/IS!AZ13 -> 0.011694652 | BA69: =BA36/IS!BA13 -> 0.016039172 | BC69: =BC36/IS!BC13 -> 0.015422326 | BD69: =BD36/IS!BD13 -> 0.016591555 | BE69: =BE36/IS!BE13 -> 0.016112465 | BF69: =BF36/IS!BF13 -> 0.016257414 | BH69: =BH36/IS!BH13 -> 0.01863354 | BI69: =BI36/IS!BI13 -> 0.020246129 | BJ69: =BJ36/IS!BJ13 -> 0.024499551 | BK69: =BK36/IS!BK13 -> 0.023575702 | BM69: =BM36/IS!BM13 -> 0.025417113 | BN69: =BN36/IS!BN13 -> 0.024621379 | BO69: =BO36/IS!BO13 -> 0.025572984 | BP69: =BP36/IS!BP13 -> 0.026532621 | BR69: =BR36/IS!BR13 -> 0.029307776 | BS69: =BS36/IS!BS13 -> 0.02381107 | BT69: =BT36/IS!BT13 -> 0.022602798 | BU69: 0.03 | BW69: 0.025 | BX69: 0.025 | BY69: 0.025 | BZ69: 0.025
C70: Other Noncurrent Liabilities | E70: =E37/IS!E13 -> #DIV/0! | F70: =F37/IS!F13 -> #DIV/0! | G70: =G37/IS!G13 -> #DIV/0! | H70: =H37/IS!H13 -> #DIV/0! | J70: =J37/IS!J13 -> #DIV/0! | K70: =K37/IS!K13 -> #DIV/0! | L70: =L37/IS!L13 -> #DIV/0! | M70: =M37/IS!M13 -> #DIV/0! | R70: =R37/IS!R13 -> #DIV/0! | T70: =T37/IS!T13 -> #DIV/0! | U70: =U37/IS!U13 -> #DIV/0! | V70: =V37/IS!V13 -> #DIV/0! | W70: =W37/IS!W13 -> #DIV/0! | Y70: =Y37/IS!Y13 -> #DIV/0! | Z70: =Z37/IS!Z13 -> #DIV/0! | AA70: =AA37/IS!AA13 -> #DIV/0! | AB70: =AB37/IS!AB13 -> #DIV/0! | AD70: =AD37/IS!AD13 -> 0 | AE70: =AE37/IS!AE13 -> 0 | AF70: =AF37/IS!AF13 -> 0 | AG70: =AG37/IS!AG13 -> 0.026935529 | AI70: =AI37/IS!AI13 -> 0.02836183 | AJ70: =AJ37/IS!AJ13 -> 0.022766457 | AK70: =AK37/IS!AK13 -> 0.052549261 | AL70: =AL37/IS!AL13 -> 0.04854505 | AN70: =AN37/IS!AN13 -> 0.028486367 | AO70: =AO37/IS!AO13 -> 0.027702324 | AP70: =AP37/IS!AP13 -> 0.023867544 | AQ70: =AQ37/IS!AQ13 -> 0.024354754 | AS70: =AS37/IS!AS13 -> 0.023894255 | AT70: =AT37/IS!AT13 -> 0.057967499 | AU70: =AU37/IS!AU13 -> 0.062855979 | AV70: =AV37/IS!AV13 -> 0.075024716 | AX70: =AX37/IS!AX13 -> 0.070295345 | AY70: =AY37/IS!AY13 -> 0.065101867 | AZ70: =AZ37/IS!AZ13 -> 0.058770256 | BA70: =BA37/IS!BA13 -> 0.04003767 | BC70: =BC37/IS!BC13 -> 0.037372684 | BD70: =BD37/IS!BD13 -> 0.035135908 | BE70: =BE37/IS!BE13 -> 0.03378505 | BF70: =BF37/IS!BF13 -> 0.027464614 | BH70: =BH37/IS!BH13 -> 0.028214906 | BI70: =BI37/IS!BI13 -> 0.027881871 | BJ70: =BJ37/IS!BJ13 -> 0.027973176 | BK70: =BK37/IS!BK13 -> 0.02994444 | BM70: =BM37/IS!BM13 -> 0.035802661 | BN70: =BN37/IS!BN13 -> 0.038391255 | BO70: =BO37/IS!BO13 -> 0.038015686 | BP70: =BP37/IS!BP13 -> 0.039463988 | BR70: =BR37/IS!BR13 -> 0.043619231 | BS70: =BS37/IS!BS13 -> 0.04153448 | BT70: =BT37/IS!BT13 -> 0.04364514 | BU70: 0.04 | BW70: 0.04 | BX70: 0.04 | BY70: 0.04 | BZ70: 0.04
C73: Free Cash Flow | BM73: =CF!BM48 -> 232073 | BN73: =CF!BN48 -> 197928 | BO73: =CF!BO48 -> 210713 | BP73: =CF!BP48 -> 279570 | BQ73: =CF!BQ48 -> 920284 | BR73: =CF!BR48 -> 227815 | BS73: =CF!BS48 -> 217648 | BT73: =CF!BT48 -> 262900 | ... CA73: =CF!CA48 -> 1084886.2
C74: Margin | AB74: 259000 | BM74: =CF!BM49 -> 0.3270292 | BN74: =CF!BN49 -> 0.26891405 | BO74: =CF!BO49 -> 0.27915662 | BP74: =CF!BP49 -> 0.36015366 | BQ74: =CF!BQ49 -> 0.30915844 | BR74: =CF!BR49 -> 0.29832228 | BS74: =CF!BS49 -> 0.27184388 | BT74: =CF!BT49 -> 0.32125619 | ... CA74: =CF!CA49 -> 0.3200066
AB75: =AB74-AB49 -> 226288

Sheet CF
B2: =IS!B2 -> DocuSign, Inc (DOCU) | BD2: =BD48/AY48-1 -> -0.34783684 | BE2: =BE48/AZ48-1 -> -0.5994179 | BF2: =BE48-AZ48 -> -53959 | BH2: =BH48-BC48 -> 40001 | BI2: =BI33-BD33 -> 90137 | BN2: =BN33-BI33 -> 9192 | BO2: =BO33-BJ33 -> -29851 | BR2: =BR48-BM48 -> -4258 | BV2: 28.3
B4: Cash Flow Statement | D4: 2012 | E4: 1Q13 | F4: 2Q13 | G4: 3Q13 | H4: 4Q13 | I4: 2013 | J4: 1Q14 | K4: 2Q14 | L4: 3Q14 | M4: 4Q14 | N4: 2014 | O4: 1Q15 | P4: 2Q15 | Q4: 3Q15 | R4: 4Q15 | S4: 2015 | T4: 1Q16 | U4: 2Q16 | V4: 3Q16 | W4: 4Q16 | X4: 2016 | Y4: 1Q17 | Z4: 2Q17 | AA4: 3Q17 | AB4: 4Q17 | AC4: 2017 | AD4: 1Q18 | AE4: 2Q18 | AF4: 3Q18 | AG4: 4Q18 | AH4: 2018 | AI4: 1Q19 | AJ4: 2Q19 | AK4: 3Q19 | AL4: 4Q19 | AM4: 2019 | AN4: 1Q20 | AO4: 2Q20 | AP4: 3Q20 | AQ4: 4Q20 | AR4: 2020 | AS4: 1Q21 | AT4: 2Q21 | AU4: 3Q21 | AV4: 4Q21 | AW4: 2021 | AX4: 1Q22 | AY4: 2Q22 | AZ4: 3Q22 | BA4: 4Q22 | BB4: 2022 | BC4: 1Q23 | BD4: 2Q23 | BE4: 3Q23 | BF4: 4Q23 | BG4: 2023 | BH4: =IS!BH4 -> 1Q24 | BI4: =IS!BI4 -> 2Q24 | BJ4: =IS!BJ4 -> 3Q24 | BK4: =IS!BK4 -> 4Q24 | BL4: =IS!BL4 -> FY24 | BM4: =IS!BM4 -> 1Q25 | BN4: =IS!BN4 -> 2Q25 | BO4: =IS!BO4 -> 3Q25 | ... CA4: =IS!CA4 -> FY27E
B5: Operating Activities
B6: Net Income | D6: =IS!D71 -> 0 | E6: =IS!E71 -> 0 | F6: =IS!F71 -> 0 | G6: =IS!G71 -> 0 | H6: =IS!H71 -> 0 | I6: =IS!I71 -> 0 | J6: =IS!J71 -> 0 | K6: =IS!K71 -> 0 | ... P6: =IS!P71 -> 0 | Q6: 0 | R6: 0 | T6: =IS!T71 -> 0 | U6: =IS!U71 -> 0 | V6: =IS!V71 -> 0 | W6: =IS!W71 -> 0 | AC6: -115412 | AD6: -19382 | AE6: -12037 | AF6: -14505 | AG6: -6352 | AH6: =SUM(AD6:AG6) -> -52276 | AI6: -270687 | AJ6: -36714 | AK6: -52813 | AL6: -66244 | AM6: =SUM(AI6:AL6) -> -426458 | AN6: -45722 | AO6: -68632 | AP6: -46598 | AQ6: -47407 | AR6: =SUM(AN6:AQ6) -> -208359 | AS6: =IS!AS71 -> -47804 | AT6: =IS!AT71 -> -64560 | AU6: =IS!AU71 -> -58491 | AV6: =IS!AV71 -> -72412 | AW6: =IS!AW71 -> -243267 | AX6: =IS!AX71 -> -8354 | AY6: =IS!AY71 -> -25501 | AZ6: =IS!AZ71 -> -5676 | ... BI6: =IS!BI71 -> 7395 | BJ6: 38805 | BK6: 27241 | BL6: =SUM(BH6:BK6) -> 73980 | BM6: 33760 | BN6: 888211 | BO6: =IS!BO71 -> 62423 | BP6: 83491 | BQ6: =IS!BQ71 -> 1067885 | BR6: =IS!BR71 -> 72087 | BS6: =IS!BS71 -> 62970 | BT6: =IS!BT71 -> 83725 | BU6: =IS!BU71 -> 78978.533 | BV6: =IS!BV71 -> 297760.53 | BW6: =IS!BW71 -> 60893.11 | BX6: =IS!BX71 -> 79007.681 | ... CA6: =IS!CA71 -> 269167.82
C7: Depreciation of property and equipment | I7: =SUM(E7:H7) -> 0 | N7: =SUM(J7:M7) -> 0 | AC7: 28471 | AD7: 7686 | AE7: 7699 | AF7: 8318 | AG7: 8047 | AH7: =SUM(AD7:AG7) -> 31750 | AI7: 8600 | AJ7: 7081 | AK7: 10343 | AL7: 12003 | AM7: =SUM(AI7:AL7) -> 38027 | AN7: 11971 | AO7: 12290 | AP7: 12655 | AQ7: 13266 | AR7: =SUM(AN7:AQ7) -> 50182 | AS7: 14039 | AT7: 17937 | AU7: 19479 | AV7: 19635 | AW7: =SUM(AS7:AV7) -> 71090 | AX7: 20037 | AY7: 20960 | AZ7: 20166 | BA7: 20750 | BB7: =SUM(AX7:BA7) -> 81913 | BC7: 21301 | BD7: 21143 | BE7: 21532 | BF7: 22279 | BG7: =SUM(BC7:BF7) -> 86255 | BH7: 22867 | BI7: 25238 | BJ7: 23324 | BK7: 23633 | BL7: =SUM(BH7:BK7) -> 95062 | BM7: 24506 | BN7: 27022 | BO7: 27569 | BP7: 28707 | BQ7: =SUM(BM7:BP7) -> 107804 | BR7: 30369 | BS7: 28880 | BT7: 30399 | BU7: =BU8+BU9 -> 50092.944 | BV7: =SUM(BR7:BU7) -> 139740.94 | BW7: =BW8+BW9 -> 47604.606 | BX7: =BX8+BX9 -> 46404.673 | BY7: =BY8+BY9 -> 44229.543 | BZ7: =BZ8+BZ9 -> 43185.904 | CA7: =SUM(BW7:BZ7) -> 181424.73
C8: Depreciation | X8: =X7-X9 -> -5995 | AC8: =AC7-AC9 -> 18146 | AD8: =AD7-AD9 -> -720 | AE8: =AE7-AE9 -> 5343 | AF8: =AF7-AF9 -> 5612 | AG8: =AG7-AG9 -> 5603 | AH8: =SUM(AD8:AG8) -> 15838 | AI8: =AI7-AI9 -> 6167 | AJ8: =AJ7-AJ9 -> 5313 | AK8: =AK7-AK9 -> 6454 | AL8: =AL7-AL9 -> 6991 | AM8: =SUM(AI8:AL8) -> 24925 | AN8: =AN7-AN9 -> 7238 | AO8: =AO7-AO9 -> 7870 | AP8: =AP7-AP9 -> 8350 | AQ8: =AQ7-AQ9 -> 9007 | AR8: =SUM(AN8:AQ8) -> 32465 | AS8: =AS7-AS9 -> 9780 | AT8: =AT7-AT9 -> 10521 | AU8: =AU7-AU9 -> 12122 | AV8: =AV7-AV9 -> 13049 | AW8: =SUM(AS8:AV8) -> 45472 | AX8: =AX7-AX9 -> 13508 | AY8: =AY7-AY9 -> 14299 | AZ8: =AZ7-AZ9 -> 14195 | BA8: =BA7-BA9 -> 15142 | BB8: =SUM(AX8:BA8) -> 57144 | BC8: =BC7-BC9 -> 15693 | BD8: =BD7-BD9 -> 16110 | BE8: =BE7-BE9 -> 16419 | BF8: =BF7-BF9 -> 17326 | BG8: =SUM(BC8:BF8) -> 65548 | BH8: =BH7-BH9 -> 17835 | BI8: =BI7-BI9 -> 20294 | BJ8: =BJ7-BJ9 -> 18625 | BK8: =BK7-BK9 -> 18932 | BL8: =SUM(BH8:BK8) -> 75686 | BM8: =BM7-BM9 -> 19807 | BN8: =BN7-BN9 -> 20842 | BO8: =BO7-BO9 -> 20649 | BP8: =BP7-BP9 -> 21789 | BQ8: =SUM(BM8:BP8) -> 83087 | BR8: =BR7-BR9 -> 23450 | BS8: =BS7-BS9 -> 23964 | BT8: =BT7-BT9 -> 25526 | BU8: =BU77*(BS!BT14+BS!BT20) -> 45219.944 | BV8: =SUM(BR8:BU8) -> 118159.94 | BW8: =BW77*(BS!BV14+BS!BV20) -> 42731.606 | BX8: =BX77*(BS!BW14+BS!BW20) -> 41531.673 | BY8: =BY77*(BS!BX14+BS!BX20) -> 39356.543 | BZ8: =BZ77*(BS!BY14+BS!BY20) -> 38312.904 | CA8: =SUM(BW8:BZ8) -> 161932.73
C9: Amortization | X9: =IS!X39 -> 5995 | AC9: =IS!AC39 -> 10325 | AD9: =IS!AD39 -> 8406 | AE9: =IS!AE39 -> 2356 | AF9: =IS!AF39 -> 2706 | AG9: =IS!AG39 -> 2444 | AH9: =SUM(AD9:AG9) -> 15912 | AI9: =IS!AI39 -> 2433 | AJ9: =IS!AJ39 -> 1768 | AK9: =IS!AK39 -> 3889 | AL9: =IS!AL39 -> 5012 | AM9: =SUM(AI9:AL9) -> 13102 | AN9: =IS!AN39 -> 4733 | AO9: =IS!AO39 -> 4420 | AP9: =IS!AP39 -> 4305 | AQ9: =IS!AQ39 -> 4259 | AR9: =SUM(AN9:AQ9) -> 17717 | AS9: =IS!AS39 -> 4259 | AT9: =IS!AT39 -> 7416 | AU9: =IS!AU39 -> 7357 | AV9: =IS!AV39 -> 6586 | AW9: =SUM(AS9:AV9) -> 25618 | AX9: =IS!AX39 -> 6529 | AY9: =IS!AY39 -> 6661 | AZ9: =IS!AZ39 -> 5971 | BA9: =IS!BA39 -> 5608 | BB9: =SUM(AX9:BA9) -> 24769 | BC9: =IS!BC39 -> 5608 | BD9: =IS!BD39 -> 5033 | BE9: =IS!BE39 -> 5113 | BF9: =IS!BF39 -> 4953 | BG9: =SUM(BC9:BF9) -> 20707 | BH9: =IS!BH39 -> 5032 | BI9: =IS!BI39 -> 4944 | BJ9: =IS!BJ39 -> 4699 | BK9: =IS!BK39 -> 4701 | BL9: =SUM(BH9:BK9) -> 19376 | BM9: =IS!BM39 -> 4699 | BN9: =IS!BN39 -> 6180 | BO9: =IS!BO39 -> 6920 | BP9: =IS!BP39 -> 6918 | BQ9: =SUM(BM9:BP9) -> 24717 | BR9: =IS!BR39 -> 6919 | BS9: =IS!BS39 -> 4916 | BT9: =IS!BT39 -> 4873 | BU9: =IS!BU39 -> 4873 | BV9: =SUM(BR9:BU9) -> 21581 | BW9: =IS!BW39 -> 4873 | BX9: =IS!BX39 -> 4873 | BY9: =IS!BY39 -> 4873 | BZ9: =IS!BZ39 -> 4873 | CA9: =SUM(BW9:BZ9) -> 19492
C10: Amortization of deferred contract acquisition and fulfillment costs | I10: =SUM(E10:H10) -> 0 | N10: =SUM(J10:M10) -> 0 | AC10: 22369 | AD10: 7013 | AE10: 7278 | AF10: 7731 | AG10: 8355 | AH10: =SUM(AD10:AG10) -> 30377 | AI10: 9246 | AJ10: 9900 | AK10: 10743 | AL10: 12223 | AM10: =SUM(AI10:AL10) -> 42112 | AN10: 14260 | AO10: 16889 | AP10: 18211 | AQ10: 20387 | AR10: =SUM(AN10:AQ10) -> 69747 | AS10: 21360 | AT10: 23834 | AU10: 25593 | AV10: 28597 | AW10: =SUM(AS10:AV10) -> 99384 | AX10: 30933 | AY10: 32543 | AZ10: 37283 | BA10: 43683 | BB10: =SUM(AX10:BA10) -> 144442 | BC10: 43990 | BD10: 45585 | BE10: 44806 | BF10: 50664 | BG10: =SUM(BC10:BF10) -> 185045 | BH10: 48230 | BI10: 50152 | BJ10: 49399 | BK10: 52382 | BL10: =SUM(BH10:BK10) -> 200163 | BM10: 54212 | BN10: 57255 | BO10: 61264 | BP10: 64486 | BQ10: =SUM(BM10:BP10) -> 237217 | BR10: 66482 | BS10: 68654 | BT10: 68374 | BU10: 25000 | BV10: =SUM(BR10:BU10) -> 228510 | BW10: 25000 | BX10: 25000 | BY10: 25000 | BZ10: 25000 | CA10: =SUM(BW10:BZ10) -> 100000
C11: Amortization of debt discount and transaction costs | AC11: 0 | AE11: 0 | AF11: 0 | AG11: 0 | AH11: =SUM(AD11:AG11) -> 0 | AI11: 0 | AJ11: 0 | AK11: 3147 | AL11: 6360 | AM11: =SUM(AI11:AL11) -> 9507 | AN11: 6454 | AO11: 6548 | AP11: 6645 | AQ11: 6742 | AR11: =SUM(AN11:AQ11) -> 26389 | AS11: 6842 | AT11: 6942 | AU11: 7044 | AV11: 7173 | AW11: =SUM(AS11:AV11) -> 28001 | AX11: 1319 | AY11: 1274 | AZ11: 1255 | BA11: 1250 | BB11: =SUM(AX11:BA11) -> 5098 | BC11: 1284 | BD11: 1198 | BE11: 1243 | BF11: 1245 | BG11: =SUM(BC11:BF11) -> 4970 | BH11: 1246 | BI11: 1249 | BJ11: 1227 | BK11: 1027 | BL11: =SUM(BH11:BK11) -> 4749 | BM11: 138 | BN11: 139 | BO11: 138 | BP11: 139 | BQ11: =SUM(BM11:BP11) -> 554 | BR11: 138 | BS11: 302 | BT11: 167 | BU11: =-IS!BU50 -> 0 | BV11: =SUM(BR11:BU11) -> 607 | BW11: =-IS!BW50 -> 0 | BX11: =-IS!BX50 -> 0 | BY11: =-IS!BY50 -> 0 | BZ11: =-IS!BZ50 -> 0 | CA11: =SUM(BW11:BZ11) -> 0
C12: Impairment of operating lease right-of-use assets | AH12: =SUM(AD12:AG12) -> 0 | AM12: =SUM(AI12:AL12) -> 0 | AR12: =SUM(AN12:AQ12) -> 0 | AW12: =SUM(AS12:AV12) -> 0 | AY12: 3892 | BB12: =SUM(AX12:BA12) -> 3892 | BG12: =SUM(BC12:BF12) -> 0 | BL12: =SUM(BH12:BK12) -> 0 | BQ12: =SUM(BM12:BP12) -> 0 | BV12: =SUM(BR12:BU12) -> 0 | CA12: =SUM(BW12:BZ12) -> 0
C13: Fair value adjustments to strategic investments | AH13: =SUM(AD13:AG13) -> 0 | AM13: =SUM(AI13:AL13) -> 0 | AR13: =SUM(AN13:AQ13) -> 0 | AW13: =SUM(AS13:AV13) -> 0 | AX13: -5119 | BB13: =SUM(AX13:BA13) -> -5119 | BG13: =SUM(BC13:BF13) -> 0 | BL13: =SUM(BH13:BK13) -> 0 | BQ13: =SUM(BM13:BP13) -> 0 | BV13: =SUM(BR13:BU13) -> 0 | CA13: =SUM(BW13:BZ13) -> 0
C14: Loss on extinguishment of debt | AH14: =SUM(AD14:AG14) -> 0 | AM14: =SUM(AI14:AL14) -> 0 | AR14: =SUM(AN14:AQ14) -> 0 | AV14: 33752 | AW14: =SUM(AS14:AV14) -> 33752 | BB14: =SUM(AX14:BA14) -> 0 | BG14: =SUM(BC14:BF14) -> 0 | BL14: =SUM(BH14:BK14) -> 0 | BQ14: =SUM(BM14:BP14) -> 0 | BV14: =SUM(BR14:BU14) -> 0 | CA14: =SUM(BW14:BZ14) -> 0
C15: Operating cash flow related to repayments of convertible sr notes | AH15: =SUM(AD15:AG15) -> 0 | AM15: =SUM(AI15:AL15) -> 0 | AR15: =SUM(AN15:AQ15) -> 0 | AV15: -75165 | AW15: =SUM(AS15:AV15) -> -75165 | BB15: =SUM(AX15:BA15) -> 0 | BG15: =SUM(BC15:BF15) -> 0 | BL15: =SUM(BH15:BK15) -> 0 | BQ15: =SUM(BM15:BP15) -> 0 | BV15: =SUM(BR15:BU15) -> 0 | CA15: =SUM(BW15:BZ15) -> 0
C16: Stock-based compensation | I16: =SUM(E16:H16) -> 0 | N16: =SUM(J16:M16) -> 0 | AC16: 35443 | AD16: 8406 | AE16: 8512 | AF16: 6595 | AG16: 6234 | AH16: =SUM(AD16:AG16) -> 29747 | AI16: 269794 | AJ16: 40165 | AK16: 51748 | AL16: 49271 | AM16: =SUM(AI16:AL16) -> 410978 | AN16: 42271 | AO16: 55792 | AP16: 52736 | AQ16: 55605 | AR16: =SUM(AN16:AQ16) -> 206404 | AS16: 53551 | AT16: 68767 | AU16: 80920 | AV16: =IS!AV40 -> 83639 | AW16: =SUM(AS16:AV16) -> 286877 | AX16: 81637 | AY16: 99458 | AZ16: 109441 | BA16: 118006 | BB16: =SUM(AX16:BA16) -> 408542 | BC16: 110723 | BD16: 141207 | BE16: 140835 | BF16: 145961 | BG16: =SUM(BC16:BF16) -> 538726 | BH16: 144706 | BI16: 151707 | BJ16: 159418 | BK16: 161016 | BL16: =SUM(BH16:BK16) -> 616847 | BM16: 142504 | BN16: 164656 | BO16: 153228 | BP16: 149947 | BQ16: =SUM(BM16:BP16) -> 610335 | BR16: 145596 | BS16: 160538 | BT16: 160642 | BU16: =IS!BU40 -> 150000 | BV16: =SUM(BR16:BU16) -> 616776 | BW16: =IS!BW40 -> 160000 | BX16: =IS!BX40 -> 160000 | BY16: =IS!BY40 -> 160000 | BZ16: =IS!BZ40 -> 160000 | CA16: =SUM(BW16:BZ16) -> 640000
C17: Non-cash charitable donation | AH17: =SUM(AD17:AG17) -> 0 | AM17: =SUM(AI17:AL17) -> 0 | AR17: =SUM(AN17:AQ17) -> 0 | AW17: =SUM(AS17:AV17) -> 0 | AY17: 3000 | BB17: =SUM(AX17:BA17) -> 3000 | BG17: =SUM(BC17:BF17) -> 0 | BL17: =SUM(BH17:BK17) -> 0 | BQ17: =SUM(BM17:BP17) -> 0 | BV17: =SUM(BR17:BU17) -> 0 | CA17: =SUM(BW17:BZ17) -> 0
C18: Non-cash operating lease costs | I18: =SUM(E18:H18) -> 0 | N18: =SUM(J18:M18) -> 0 | AE18: 0 | AF18: 0 | AH18: =SUM(AD18:AG18) -> 0 | AI18: 0 | AJ18: 0 | AK18: 0 | AL18: 0 | AM18: =SUM(AI18:AL18) -> 0 | AN18: 4128 | AO18: 4735 | AP18: 4980 | AQ18: 5592 | AR18: =SUM(AN18:AQ18) -> 19435 | AS18: 6324 | AT18: 6795 | AU18: 6963 | AV18: 6646 | AW18: =SUM(AS18:AV18) -> 26728 | AX18: 6943 | AY18: 6706 | AZ18: 6527 | BA18: 6643 | BB18: =SUM(AX18:BA18) -> 26819 | BC18: 6442 | BD18: 7024 | BE18: 7002 | BF18: 7033 | BG18: =SUM(BC18:BF18) -> 27501 | BH18: 5980 | BI18: 5751 | BJ18: 4768 | BK18: 4811 | BL18: =SUM(BH18:BK18) -> 21310 | BM18: 4878 | BN18: 4984 | BO18: 4601 | BP18: 4602 | BQ18: =SUM(BM18:BP18) -> 19065 | BR18: 4660 | BS18: 4704 | BT18: 4804 | BU18: 8800 | BV18: =SUM(BR18:BU18) -> 22968 | BW18: 7600 | BX18: 8000 | BY18: 8400 | BZ18: 8800 | CA18: =SUM(BW18:BZ18) -> 32800
C19: Deferred income taxes | AC19: 12 | AD19: -13 | AE19: 13 | AF19: 58 | AG19: -1054 | AH19: =SUM(AD19:AG19) -> -996 | AI19: -6 | AJ19: -6 | AK19: -7335 | AL19: 2346 | AM19: =SUM(AI19:AL19) -> -5001 | AN19: 52 | AO19: -24 | AP19: 14 | AQ19: 1245 | AR19: =SUM(AN19:AQ19) -> 1287 | AS19: -104 | AT19: -180 | AU19: -766 | AV19: -1360 | AW19: =SUM(AS19:AV19) -> -2410 | AX19: 264 | AY19: -1514 | AZ19: -1110 | BA19: 3729 | BB19: =SUM(AX19:BA19) -> 1369 | BC19: 72 | BD19: 2996 | BE19: -23 | BF19: -1348 | BG19: =SUM(BC19:BF19) -> 1697 | BH19: 1623 | BI19: 1797 | BJ19: 3845 | BK19: -973 | BL19: =SUM(BH19:BK19) -> 6292 | BM19: 1477 | BN19: -826038 | BO19: 6675 | BP19: -22103 | BQ19: =SUM(BM19:BP19) -> -839989 | BR19: -3465 | BS19: 4997 | BT19: -2347 | BU19: =BS!BU36-BS!BT36 -> 0 | BV19: =SUM(BR19:BU19) -> -815 | BW19: =BS!BW36-BS!BV36 -> 0 | BX19: =BS!BX36-BS!BW36 -> 0 | BY19: =BS!BY36-BS!BX36 -> 0 | BZ19: =BS!BZ36-BS!BY36 -> 0 | CA19: =SUM(BW19:BZ19) -> 0
C20: Other | AC20: -1767 | AD20: -803 | AE20: -1023 | AF20: 1805 | AG20: -1856 | AH20: =SUM(AD20:AG20) -> -1877 | AI20: 2225 | AJ20: -3100 | AK20: -1204 | AL20: 2879 | AM20: =SUM(AI20:AL20) -> 800 | AN20: -1111 | AO20: -1260 | AP20: 229 | AQ20: 401 | AR20: =SUM(AN20:AQ20) -> -1741 | AS20: 504 | AT20: -997 | AU20: 1699 | AV20: -1416 | AW20: =SUM(AS20:AV20) -> -210 | AX20: -1240 | AY20: 1906 | AZ20: 3159 | BA20: 4274 | BB20: =SUM(AX20:BA20) -> 8099 | BC20: 4907 | BD20: 3192 | BE20: 5441 | BF20: 2183 | BG20: =SUM(BC20:BF20) -> 15723 | BH20: -831 | BI20: 49 | BJ20: -571 | BK20: -551 | BL20: =SUM(BH20:BK20) -> -1904 | BM20: 1472 | BN20: 3851 | BO20: 1149 | BP20: -361 | BQ20: =SUM(BM20:BP20) -> 6111 | BR20: 1723 | BS20: -218 | BT20: 634 | BV20: =SUM(BR20:BU20) -> 2139 | CA20: =SUM(BW20:BZ20) -> 0
B21: Net Change in Working Capital | BB21: =SUM(AX21:BA21) -> 0 | BG21: =SUM(BC21:BF21) -> 0 | BL21: =SUM(BH21:BK21) -> 0 | BQ21: =SUM(BM21:BP21) -> 0 | BV21: =SUM(BR21:BU21) -> 0 | CA21: =SUM(BW21:BZ21) -> 0
C22: AR | I22: =SUM(E22:H22) -> 0 | N22: =SUM(J22:M22) -> 0 | AC22: -17454 | AD22: 11577 | AE22: 1531 | AF22: -146 | AG22: -41039 | AH22: =SUM(AD22:AG22) -> -28077 | AI22: 19622 | AJ22: -4237 | AK22: -14019 | AL22: -43937 | AM22: =SUM(AI22:AL22) -> -42571 | AN22: 57414 | AO22: -21518 | AP22: -20812 | AQ22: -78377 | AR22: =SUM(AN22:AQ22) -> -63293 | AS22: 17239 | AT22: 7915 | AU22: -36583 | AV22: -62484 | AW22: =SUM(AS22:AV22) -> -73913 | AX22: 73205 | AY22: -34365 | AZ22: =BS!AY8-BS!AZ8 -> -20869 | BA22: -135349 | BB22: =SUM(AX22:BA22) -> -117378 | BC22: 140078 | BD22: -38656 | BE22: -83084 | BF22: -94302 | BG22: =SUM(BC22:BF22) -> -75964 | BH22: 108281 | BI22: -8478 | BJ22: 53099 | BK22: -81221 | BL22: =SUM(BH22:BK22) -> 71681 | BM22: 130639 | BN22: -7068 | BO22: 7120 | BP22: -128616 | BQ22: =SUM(BM22:BP22) -> 2075 | BR22: 121003 | BS22: -50674 | BT22: 707 | BU22: =BS!BT8-BS!BU8 -> -133077.38 | BV22: =SUM(BR22:BU22) -> -62041.383 | BW22: =BS!BV8-BS!BW8 -> 125206.04 | BX22: =BS!BW8-BS!BX8 -> -17737.938 | BY22: =BS!BX8-BS!BY8 -> -86145.754 | BZ22: =BS!BY8-BS!BZ8 -> -57545.437 | CA22: =SUM(BW22:BZ22) -> -36223.092
C23: Contract assets | AC23: -7111 | AD23: -38 | AE23: -937 | AF23: -1338 | AG23: -4621 | AH23: =SUM(AD23:AG23) -> -6934 | AI23: 2546 | AJ23: 3113 | AK23: 1625 | AL23: 1430 | AM23: =SUM(AI23:AL23) -> 8714 | AN23: -2701 | AO23: -2204 | AP23: -2318 | AQ23: 5715 | AR23: =SUM(AN23:AQ23) -> -1508 | AS23: -740 | AT23: 2310 | AU23: -5460 | AV23: 5802 | AW23: =SUM(AS23:AV23) -> 1912 | AX23: 1607 | AY23: 1213 | AZ23: -398 | BA23: 2471 | BB23: =SUM(AX23:BA23) -> 4893 | BC23: -808 | BD23: 0 | BE23: 0 | BG23: =SUM(BC23:BF23) -> -808 | BL23: =SUM(BH23:BK23) -> 0 | BQ23: =SUM(BM23:BP23) -> 0 | BU23: =BS!BT10-BS!BU10 -> -7566.2503 | BV23: =SUM(BR23:BU23) -> -7566.2503 | BW23: =BS!BV10-BS!BW10 -> 417.61266 | BX23: =BS!BW10-BS!BX10 -> -788.3528 | BY23: =BS!BX10-BS!BY10 -> -371.4184 | BZ23: =BS!BY10-BS!BZ10 -> -189.54034 | CA23: =SUM(BW23:BZ23) -> -931.69888
C24: Prepaid expenses and other current assets | I24: =SUM(E24:H24) -> 0 | N24: =SUM(J24:M24) -> 0 | AC24: 1630 | AD24: -5570 | AE24: 4914 | AF24: -3472 | AG24: 2621 | AH24: =SUM(AD24:AG24) -> -1507 | AI24: -6519 | AJ24: -1397 | AK24: 1023 | AL24: -900 | AM24: =SUM(AI24:AL24) -> -7793 | AN24: -7107 | AO24: 3950 | AP24: -341 | AQ24: -1106 | AR24: =SUM(AN24:AQ24) -> -4604 | AS24: -9660 | AT24: 4272 | AU24: 3553 | AV24: 680 | AW24: =SUM(AS24:AV24) -> -1155 | AX24: -15670 | AY24: 5303 | AZ24: -2523 | BA24: 5816 | BB24: =SUM(AX24:BA24) -> -7074 | BC24: -16351 | BD24: 323 | BE24: 8435 | BF24: 2555 | BG24: =SUM(BC24:BF24) -> -5038 | BH24: -16803 | BI24: 2383 | BJ24: 6463 | BK24: 7300 | BL24: =SUM(BH24:BK24) -> -657 | BM24: -17061 | BN24: -6 | BO24: 8767 | BP24: -9334 | BQ24: =SUM(BM24:BP24) -> -17634 | BR24: -28551 | BS24: 5544 | BT24: 2928 | BU24: =BS!BT11-BS!BU11 -> -4209.6267 | BV24: =SUM(BR24:BU24) -> -24288.627 | BW24: =BS!BV11-BS!BW11 -> 2714.4823 | BX24: =BS!BW11-BS!BX11 -> 3333.202 | BY24: =BS!BX11-BS!BY11 -> 6414.694 | BZ24: =BS!BY11-BS!BZ11 -> -1042.4719 | CA24: =SUM(BW24:BZ24) -> 11419.906
C25: Deferred contract acquisition and fulfillment costs | I25: =SUM(E25:H25) -> 0 | N25: =SUM(J25:M25) -> 0 | AC25: -34761 | AD25: -9372 | AE25: -10827 | AF25: -12023 | AG25: -20756 | AH25: =SUM(AD25:AG25) -> -52978 | AI25: -12326 | AJ25: -18013 | AK25: -22206 | AL25: -28324 | AM25: =SUM(AI25:AL25) -> -80869 | AN25: -20487 | AO25: -27952 | AP25: -27899 | AQ25: -37923 | AR25: =SUM(AN25:AQ25) -> -114261 | AS25: -41037 | AT25: -51377 | AU25: -52225 | AV25: -63871 | AW25: =SUM(AS25:AV25) -> -208510 | AX25: -46154 | AY25: -49264 | AZ25: -52528 | BA25: -59447 | BB25: =SUM(AX25:BA25) -> -207393 | BC25: -50512 | BD25: -57803 | BE25: -53305 | BF25: -70695 | BG25: =SUM(BC25:BF25) -> -232315 | BH25: -56526 | BI25: -56830 | BJ25: -63154 | BK25: -78649 | BL25: =SUM(BH25:BK25) -> -255159 | BM25: -63072 | BN25: -68183 | BO25: -83293 | BP25: -87618 | BQ25: =SUM(BM25:BP25) -> -302166 | BR25: -56648 | BS25: -71340 | BT25: -67266 | BU25: =BS!BT15-BS!BU15-BU10 -> -100136.13 | BV25: =SUM(BR25:BU25) -> -295390.13 | BW25: =BS!BV15-BS!BW15-BW10 -> 28889.006 | BX25: =BS!BW15-BS!BX15-BX10 -> -48650.584 | BY25: =BS!BX15-BS!BY15-BY10 -> -53428.961 | BZ25: =BS!BY15-BS!BZ15-BZ10 -> -57089.674 | CA25: =SUM(BW25:BZ25) -> -130280.21
C26: Other assets | AC26: 238 | AD26: 884 | AE26: -1052 | AF26: -165 | AG26: -1271 | AH26: =SUM(AD26:AG26) -> -1604 | AI26: 440 | AJ26: 895 | AK26: 667 | AL26: 656 | AM26: =SUM(AI26:AL26) -> 2658 | AN26: 541 | AO26: 418 | AP26: -33 | AQ26: 612 | AR26: =SUM(AN26:AQ26) -> 1538 | AS26: -1364 | AT26: -4768 | AU26: -331 | AV26: 457 | AW26: =SUM(AS26:AV26) -> -6006 | AX26: -3167 | AY26: -3509 | AZ26: -7036 | BA26: -2677 | BB26: =SUM(AX26:BA26) -> -16389 | BC26: -6651 | BD26: 204 | BE26: -8452 | BF26: -6612 | BG26: =SUM(BC26:BF26) -> -21511 | BH26: -7661 | BI26: -772 | BJ26: -5586 | BK26: -1413 | BL26: =SUM(BH26:BK26) -> -15432 | BM26: 1917 | BN26: -16975 | BO26: -1060 | BP26: -5884 | BQ26: =SUM(BM26:BP26) -> -22002 | BR26: 844 | BS26: -2179 | BT26: 1034 | BU26: =BS!BT20-BS!BU20 -> 13056.623 | BV26: =SUM(BR26:BU26) -> 12755.623 | BW26: =BS!BV20-BS!BW20 -> -4095.9985 | BX26: =BS!BW20-BS!BX20 -> 8185.7129 | BY26: =BS!BX20-BS!BY20 -> -2497.0161 | BZ26: =BS!BY20-BS!BZ20 -> -1705.8631 | CA26: =SUM(BW26:BZ26) -> -113.16479
C27: AP | I27: =SUM(E27:H27) -> 0 | N27: =SUM(J27:M27) -> 0 | AC27: 4890 | AD27: -2125 | AE27: -4146 | AF27: 726 | AG27: 8409 | AH27: =SUM(AD27:AG27) -> 2864 | AI27: -7218 | AJ27: 2184 | AK27: -956 | AL27: -1390 | AM27: =SUM(AI27:AL27) -> -7380 | AN27: 282 | AO27: 1306 | AP27: 718 | AQ27: 1543 | AR27: =SUM(AN27:AQ27) -> 3849 | AS27: -2554 | AT27: 8829 | AU27: -2620 | AV27: 8473 | AW27: =SUM(AS27:AV27) -> 12128 | AX27: -21593 | AY27: 12150 | AZ27: 16146 | BA27: 5445 | BB27: =SUM(AX27:BA27) -> 12148 | BC27: -23197 | BD27: 18510 | BE27: 2948 | BF27: -24701 | BG27: =SUM(BC27:BF27) -> -26440 | BH27: -9021 | BI27: -11273 | BJ27: 11205 | BK27: 4263 | BL27: =SUM(BH27:BK27) -> -4826 | BM27: -1163 | BN27: -10412 | BO27: 10061 | BP27: 9152 | BQ27: =SUM(BM27:BP27) -> 7638 | BR27: -6764 | BS27: -14030 | BT27: 12477 | BU27: =BS!BU24-BS!BT24 -> 2334.3754 | BV27: =SUM(BR27:BU27) -> -5982.6246 | BW27: =BS!BW24-BS!BV24 -> -626.41899 | BX27: =BS!BX24-BS!BW24 -> 1182.5292 | BY27: =BS!BY24-BS!BX24 -> 557.1276 | BZ27: =BS!BZ24-BS!BY24 -> 284.31051 | CA27: =SUM(BW27:BZ27) -> 1397.5483
C28: Accrued expenses and other liabilities | I28: =SUM(E28:H28) -> 0 | N28: =SUM(J28:M28) -> 0 | AC28: =-2596-3693 -> -6289 | AD28: =-1046+389 -> -657 | AE28: =529-751 -> -222 | AF28: =1735+1873 -> 3608 | AG28: =4774+2213 -> 6987 | AH28: =SUM(AD28:AG28) -> 9716 | AI28: =3302+309 -> 3611 | AJ28: =-996-379 -> -1375 | AK28: =1304+4030 -> 5334 | AL28: -1122 | AM28: =SUM(AI28:AL28) -> 6448 | AN28: 4710 | AO28: =5997+3795 -> 9792 | AP28: =-5203-4608 -> -9811 | AQ28: 4662 | AR28: =SUM(AN28:AQ28) -> 9353 | AS28: -916 | AT28: 12626 | AU28: 10242 | AV28: 15203 | AW28: =SUM(AS28:AV28) -> 37155 | AX28: 11080 | AY28: 5942 | AZ28: -5136 | BA28: -1058 | BB28: =SUM(AX28:BA28) -> 10828 | BC28: 5148 | BD28: -2181 | BE28: -2094 | BF28: 6467 | BG28: =SUM(BC28:BF28) -> 7340 | BH28: 1095 | BI28: 9069 | BJ28: -7792 | BK28: 4101 | BL28: =SUM(BH28:BK28) -> 6473 | BM28: -3480 | BN28: -4680 | BO28: 1014 | BP28: 10081 | BQ28: =SUM(BM28:BP28) -> 2935 | BR28: 4625 | BS28: 175 | BT28: 19178 | BU28: =BS!BU25-BS!BT25+BS!BU37-BS!BT37 -> -14931.873 | BV28: =SUM(BR28:BU28) -> 9046.1272 | BW28: =BS!BW25-BS!BV25+BS!BW37-BS!BV37 -> 20640.249 | BX28: =BS!BX25-BS!BW25+BS!BX37-BS!BW37 -> 7883.528 | BY28: =BS!BY25-BS!BX25+BS!BY37-BS!BX37 -> -13572.225 | BZ28: =BS!BZ25-BS!BY25+BS!BZ37-BS!BY37 -> 1705.8631 | CA28: =SUM(BW28:BZ28) -> 16657.415
C29: Accrued compensation | AC29: 9532 | AD29: -9128 | AE29: 4148 | AF29: 3227 | AG29: 10921 | AH29: =SUM(AD29:AG29) -> 9168 | AI29: -16947 | AJ29: 17307 | AK29: 1811 | AL29: 23868 | AM29: =SUM(AI29:AL29) -> 26039 | AN29: -19869 | AO29: 22296 | AP29: -9120 | AQ29: 12329 | AR29: =SUM(AN29:AQ29) -> 5636 | AS29: -1536 | AT29: 24401 | AU29: 688 | AV29: 41033 | AW29: =SUM(AS29:AV29) -> 64586 | AX29: -34048 | AY29: 21001 | AZ29: -9734 | BA29: 23909 | BB29: =SUM(AX29:BA29) -> 1128 | BC29: -23220 | BD29: 9201 | BE29: -1808 | BF29: 14046 | BG29: =SUM(BC29:BF29) -> -1781 | BH29: -21582 | BI29: 18270 | BJ29: -1056 | BK29: 38347 | BL29: =SUM(BH29:BK29) -> 33979 | BM29: -45048 | BN29: 25146 | BO29: -21226 | BP29: 70364 | BQ29: =SUM(BM29:BP29) -> 29236 | BR29: -61451 | BS29: 37214 | BT29: -28772 | BU29: =BS!BU26-BS!BT26 -> 67181.754 | BV29: =SUM(BR29:BU29) -> 14172.754 | BW29: =BS!BW26-BS!BV26 -> -38517.465 | BX29: =BS!BX26-BS!BW26 -> 10248.586 | BY29: =BS!BY26-BS!BX26 -> 13471.644 | BZ29: =BS!BZ26-BS!BY26 -> 11296.769 | CA29: =SUM(BW29:BZ29) -> -3500.4659
C30: Contract liabilities | I30: =SUM(E30:H30) -> 0 | N30: =SUM(J30:M30) -> 0 | AC30: =60440 -> 60440 | AD30: 13027 | AE30: 6109 | AF30: 11309 | AG30: 57329 | AH30: =SUM(AD30:AG30) -> 87774 | AI30: 12611 | AJ30: 6892 | AK30: 16353 | AL30: 65018 | AM30: =SUM(AI30:AL30) -> 100874 | AN30: 4274 | AO30: =17472 -> 17472 | AP30: 22563 | AQ30: 85957 | AR30: =SUM(AN30:AQ30) -> 130266 | AS30: 44594 | AT30: 62892 | AU30: 65034 | AV30: 95230 | AW30: =SUM(AS30:AV30) -> 267750 | AX30: 51648 | AY30: 84976 | AZ30: 24423 | BA30: 89435 | BB30: =SUM(AX30:BA30) -> 250482 | BC30: 18712 | BD30: 23102 | BE30: 15010 | BF30: 86353 | BG30: =SUM(BC30:BF30) -> 143177 | BH30: 18287 | BI30: 22171 | BJ30: -3582 | BK30: 115371 | BL30: =SUM(BH30:BK30) -> 152247 | BM30: -4973 | BN30: -11553 | BO30: 95 | BP30: 146285 | BQ30: =SUM(BM30:BP30) -> 129854 | BR30: -34240 | BS30: 15966 | BT30: 8610 | BU30: =BS!BU30-BS!BT30+BS!BU34-BS!BT34 -> 170218.05 | BV30: =SUM(BR30:BU30) -> 160554.05 | BW30: =BS!BW30-BS!BV30+BS!BW34-BS!BV34 -> -43081.601 | BX30: =BS!BX30-BS!BW30+BS!BX34-BS!BW34 -> 19002.131 | BY30: =BS!BY30-BS!BX30+BS!BY34-BS!BX34 -> -2485.3585 | BZ30: =BS!BZ30-BS!BY30+BS!BZ34-BS!BY34 -> 161898.6 | CA30: =SUM(BW30:BZ30) -> 135333.77
C31: Deferred rent | AC31: =14979 -> 14979 | AD31: -2202 | AE31: 2138 | AF31: -110 | AG31: 6 | AH31: =SUM(AD31:AG31) -> -168 | AM31: =SUM(AI31:AL31) -> 0 | AR31: =SUM(AN31:AQ31) -> 0 | AW31: =SUM(AS31:AV31) -> 0 | BB31: =SUM(AX31:BA31) -> 0 | BG31: =SUM(BC31:BF31) -> 0 | BL31: =SUM(BH31:BK31) -> 0 | BQ31: =SUM(BM31:BP31) -> 0 | BV31: =SUM(BR31:BU31) -> 0 | CA31: =SUM(BW31:BZ31) -> 0
C32: Operating lease liabilities | AC32: 0 | AD32: 0 | AE32: 0 | AF32: 0 | AH32: =SUM(AD32:AG32) -> 0 | AI32: 0 | AJ32: 0 | AK32: 0 | AL32: 0 | AM32: =SUM(AI32:AL32) -> 0 | AN32: -3705 | AO32: -3493 | AP32: -3688 | AQ32: -3738 | AR32: =SUM(AN32:AQ32) -> -14624 | AS32: 406 | AT32: -7504 | AU32: -7296 | AV32: -7379 | AW32: =SUM(AS32:AV32) -> -21773 | AX32: -7731 | AY32: -8502 | AZ32: -7979 | BA32: -8642 | BB32: =SUM(AX32:BA32) -> -32854 | BC32: -8259 | BD32: -9088 | BE32: -16083 | BF32: -8934 | BG32: =SUM(BC32:BF32) -> -42364 | BH32: -6795 | BI32: -6862 | BJ32: -5635 | BK32: -5987 | BL32: =SUM(BH32:BK32) -> -25279 | BM32: -5880 | BN32: -6141 | BO32: -4199 | BP32: -5426 | BQ32: =SUM(BM32:BP32) -> -21646 | BR32: -4969 | BS32: -5430 | BT32: -5020 | BU32: =BS!BU28-BS!BT28+BS!BU32-BS!BT32-BU18 -> -3959.6872 | BV32: =SUM(BR32:BU32) -> -19378.687 | BW32: =BS!BW28-BS!BV28+BS!BW32-BS!BV32-BW18 -> -4090.3564 | BX32: =BS!BX28-BS!BW28+BS!BX32-BS!BW32-BX18 -> -6817.4708 | BY32: =BS!BY28-BS!BX28+BS!BY32-BS!BX32-BY18 -> -7842.8724 | BZ32: =BS!BZ28-BS!BY28+BS!BZ32-BS!BY32-BZ18 -> -8515.6895 | CA32: =SUM(BW32:BZ32) -> -27266.389
B33: Cash Flow from Operating Activites | D33: =SUM(D6:D30) -> 0 | E33: =SUM(E6:E30) -> 0 | F33: =SUM(F6:F30) -> 0 | G33: =SUM(G6:G30) -> 0 | H33: =SUM(H6:H30) -> 0 | I33: =SUM(I6:I30) -> 0 | J33: =SUM(J6:J30) -> 0 | K33: =SUM(K6:K30) -> 0 | ... W33: =SUM(W6:W30) -> 0 | X33: =-67995 -> -67995 | AC33: =SUM(AC6:AC32)-AC8-AC9 -> -4790 | AD33: =SUM(AD6:AD32)-AD8-AD9 -> -697 | AE33: =SUM(AE6:AE32)-AE8-AE9 -> 12098 | AF33: =SUM(AF6:AF32)-AF8-AF9 -> 11618 | AG33: =SUM(AG6:AG32)-AG8-AG9 -> 31960 | AH33: =SUM(AD33:AG33) -> 54979 | AI33: =SUM(AI6:AI32)-AI8-AI9 -> 14992 | AJ33: =SUM(AJ6:AJ32)-AJ8-AJ9 -> 22695 | AK33: =SUM(AK6:AK32)-AK8-AK9 -> 4261 | AL33: =SUM(AL6:AL32)-AL8-AL9 -> 34137 | AM33: =SUM(AI33:AL33) -> 76085 | AN33: =SUM(AN6:AN32)-AN8-AN9 -> 45655 | AO33: =SUM(AO6:AO32)-AO8-AO9 -> 26405 | AP33: =SUM(AP6:AP32)-AP8-AP9 -> -1869 | AQ33: =SUM(AQ6:AQ32)-AQ8-AQ9 -> 45505 | AR33: =SUM(AN33:AQ33) -> 115696 | AS33: =SUM(AS6:AS32)-AS8-AS9 -> 59144 | AT33: =SUM(AT6:AT32)-AT8-AT9 -> 118134 | AU33: =SUM(AU6:AU32)-AU8-AU9 -> 57443 | AV33: =SUM(AV6:AV32)-AV8-AV9 -> 62233 | AW33: =SUM(AW6:AW32)-AW8-AW9 -> 296954 | AX33: =SUM(AX6:AX32)-AX8-AX9 -> 135597 | AY33: =SUM(AY6:AY32)-AY8-AY9 -> 177669 | AZ33: =SUM(AZ6:AZ32)-AZ8-AZ9 -> 105411 | ... CA33: =SUM(CA6:CA32)-CA8-CA9 -> 1189886.2
C34: OCF Margins | X34: =X33/IS!X13 -> -0.27145772 | Y34: =Y33/IS!Y13 -> #DIV/0! | Z34: =Z33/IS!Z13 -> #DIV/0! | AA34: =AA33/IS!AA13 -> #DIV/0! | AB34: =AB33/IS!AB13 -> #DIV/0! | AC34: =AC33/IS!AC13 -> -0.012557051 | AD34: =AD33/IS!AD13 -> -0.0061410774 | AE34: =AE33/IS!AE13 -> 0.096365389 | ... CA34: =CA33/IS!CA13 -> 0.35097823
C35: Y/Y growth | AC35: =AC33/X33-1 -> -0.92955364 | AD35: =AD33/Y33-1 -> #DIV/0! | AE35: =AE33/Z33-1 -> #DIV/0! | AF35: =AF33/AA33-1 -> #DIV/0! | AG35: =AG33/AB33-1 -> #DIV/0! | AH35: =AH33/AC33-1 -> -12.477871 | AI35: =AI33/AD33-1 -> -22.509326 | AJ35: =AJ33/AE33-1 -> 0.87592991 | ... CA35: =CA33/BV33-1 -> 0.092072179
B36: Investing Activites
C37: Purchases of property and equipment | I37: =SUM(E37:H37) -> 0 | N37: =SUM(J37:M37) -> 0 | X37: -28305 | Y37: -384 | Z37: -509 | AA37: -298 | AB37: -629 | AC37: -43330 | AD37: -6770 | AE37: -4319 | AF37: -4603 | AG37: -3237 | AH37: =SUM(AD37:AG37) -> -18929 | AI37: -6184 | AJ37: -4336 | AK37: -8576 | AL37: -11317 | AM37: =SUM(AI37:AL37) -> -30413 | AN37: -15237 | AO37: -14554 | AP37: -12280 | AQ37: -29975 | AR37: =SUM(AN37:AQ37) -> -72046 | AS37: -26389 | AT37: -18362 | AU37: -19393 | AV37: -18251 | AW37: =SUM(AS37:AV37) -> -82395 | AX37: -12596 | AY37: -15938 | AZ37: -15392 | BA37: -17470 | BB37: =SUM(AX37:BA37) -> -61396 | BC37: -21709 | BD37: -15404 | BE37: -16477 | BF37: -24064 | BG37: =SUM(BC37:BF37) -> -77654 | BH37: -19057 | BI37: -27379 | BJ37: -23841 | BK37: -22114 | BL37: =SUM(BH37:BK37) -> -92391 | BM37: -22753 | BN37: -22280 | BO37: -23613 | BP37: -28342 | BQ37: =SUM(BM37:BP37) -> -96988 | BR37: -23624 | BS37: -28425 | BT37: -27374 | BU37: -30000 | BV37: =SUM(BR37:BU37) -> -109423 | BW37: -25000 | BX37: -25000 | BY37: -25000 | BZ37: -30000 | CA37: =SUM(BW37:BZ37) -> -105000
C38: Purchases of marketable securities | AH38: =SUM(AD38:AG38) -> 0 | AL38: -415132 | AM38: =SUM(AI38:AL38) -> -415132 | AN38: -375211 | AO38: -155675 | AP38: -223048 | AQ38: -107318 | AR38: =SUM(AN38:AQ38) -> -861252 | AS38: 0 | AT38: -11667 | AU38: -68982 | AV38: -84340 | AW38: =SUM(AS38:AV38) -> -164989 | AX38: -96925 | AY38: -88703 | AZ38: -117134 | BA38: -81366 | BB38: =SUM(AX38:BA38) -> -384128 | BC38: -129735 | BD38: -166558 | BE38: -105956 | BF38: -131461 | BG38: =SUM(BC38:BF38) -> -533710 | BH38: -53830 | BI38: -120542 | BJ38: -28974 | BK38: -132875 | BL38: =SUM(BH38:BK38) -> -336221 | BM38: -119638 | BN38: -103603 | BO38: -110296 | BP38: -77699 | BQ38: =SUM(BM38:BP38) -> -411236 | BR38: -92563 | BS38: -119637 | BT38: -109398 | BV38: =SUM(BR38:BU38) -> -321598 | CA38: =SUM(BW38:BZ38) -> 0
C39: Sales of marketable securities | AH39: =SUM(AD39:AG39) -> 0 | AM39: =SUM(AI39:AL39) -> 0 | AR39: =SUM(AN39:AQ39) -> 0 | AS39: 28986 | AW39: =SUM(AS39:AV39) -> 28986 | AX39: 2002 | AY39: 1000 | AZ39: 68 | BA39: 4499 | BB39: =SUM(AX39:BA39) -> 7569 | BC39: 0 | BD39: 0 | BE39: 0 | BG39: =SUM(BC39:BF39) -> 0 | BL39: =SUM(BH39:BK39) -> 0 | BQ39: =SUM(BM39:BP39) -> 0 | BV39: =SUM(BR39:BU39) -> 0 | CA39: =SUM(BW39:BZ39) -> 0
C40: Maturities of marketable securities | X40: 0 | AH40: =SUM(AD40:AG40) -> 0 | AM40: =SUM(AI40:AL40) -> 0 | AN40: 92457 | AO40: 151992 | AP40: 216261 | AQ40: 166599 | AR40: =SUM(AN40:AQ40) -> 627309 | AS40: 170071 | AT40: 131345 | AU40: 103366 | AV40: 83756 | AW40: =SUM(AS40:AV40) -> 488538 | AX40: 37513 | AY40: 75658 | AZ40: 79900 | BA40: 90113 | BB40: =SUM(AX40:BA40) -> 283184 | BC40: 91055 | BD40: 99124 | BE40: 121590 | BF40: 112148 | BG40: =SUM(BC40:BF40) -> 423917 | BH40: 80699 | BI40: 83318 | BJ40: 87500 | BK40: 222352 | BL40: =SUM(BH40:BK40) -> 473869 | BM40: 82114 | BN40: 93509 | BO40: 90211 | BP40: 74500 | BQ40: =SUM(BM40:BP40) -> 340334 | BR40: 91262 | BS40: 117710 | BT40: 99486 | BV40: =SUM(BR40:BU40) -> 308458 | CA40: =SUM(BW40:BZ40) -> 0
C41: Purchases of strategic investments | X41: 0 | AH41: =SUM(AD41:AG41) -> 0 | AM41: =SUM(AI41:AL41) -> 0 | AN41: -15500 | AR41: =SUM(AN41:AQ41) -> -15500 | AS41: 0 | AU41: -5300 | AW41: =SUM(AS41:AV41) -> -5300 | AX41: -500 | AZ41: -250 | BA41: -1000 | BB41: =SUM(AX41:BA41) -> -1750 | BC41: -2125 | BD41: -500 | BE41: -1000 | BF41: -125 | BG41: =SUM(BC41:BF41) -> -3750 | BI41: -120 | BJ41: -400 | BK41: -125 | BL41: =SUM(BH41:BK41) -> -645 | BM41: -500 | BN41: -125 | BP41: -750 | BQ41: =SUM(BM41:BP41) -> -1375 | BS41: -100 | BT41: -462 | BV41: =SUM(BR41:BU41) -> -562 | CA41: =SUM(BW41:BZ41) -> 0
C42: Purchases of other investments | X42: 0 | AH42: =SUM(AD42:AG42) -> 0 | AM42: =SUM(AI42:AL42) -> 0 | AR42: =SUM(AN42:AQ42) -> 0 | AS42: -3000 | AT42: -241 | AW42: =SUM(AS42:AV42) -> -3241 | BB42: =SUM(AX42:BA42) -> 0 | BG42: =SUM(BC42:BF42) -> 0 | BL42: =SUM(BH42:BK42) -> 0 | BQ42: =SUM(BM42:BP42) -> 0 | BV42: =SUM(BR42:BU42) -> 0 | CA42: =SUM(BW42:BZ42) -> 0
C43: Proceeds from sale of business held for sale | AC43: 665 | AE43: 467 | AH43: =SUM(AD43:AG43) -> 467 | AM43: =SUM(AI43:AL43) -> 0 | AR43: =SUM(AN43:AQ43) -> 0 | AW43: =SUM(AS43:AV43) -> 0 | BB43: =SUM(AX43:BA43) -> 0 | BG43: =SUM(BC43:BF43) -> 0 | BL43: =SUM(BH43:BK43) -> 0 | BQ43: =SUM(BM43:BP43) -> 0 | BV43: =SUM(BR43:BU43) -> 0 | CA43: =SUM(BW43:BZ43) -> 0
C44: Cash paid for acquisition, net of acquired cash | AG44: -299 | AH44: =SUM(AD44:AG44) -> -299 | AK44: -218779 | AM44: =SUM(AI44:AL44) -> -218779 | AR44: =SUM(AN44:AQ44) -> 0 | AT44: -180370 | AW44: =SUM(AS44:AV44) -> -180370 | AY44: -6388 | BB44: =SUM(AX44:BA44) -> -6388 | BG44: =SUM(BC44:BF44) -> 0 | BL44: =SUM(BH44:BK44) -> 0 | BN44: -143611 | BQ44: =SUM(BM44:BP44) -> -143611 | BV44: =SUM(BR44:BU44) -> 0 | CA44: =SUM(BW44:BZ44) -> 0
C45: Other | I45: =SUM(E45:H45) -> 0 | N45: =SUM(J45:M45) -> 0 | AC45: 1785 | AH45: =SUM(AD45:AG45) -> 0 | AM45: =SUM(AI45:AL45) -> 0 | AR45: =SUM(AN45:AQ45) -> 0 | AW45: =SUM(AS45:AV45) -> 0 | BB45: =SUM(AX45:BA45) -> 0 | BG45: =SUM(BC45:BF45) -> 0 | BL45: =SUM(BH45:BK45) -> 0 | BQ45: =SUM(BM45:BP45) -> 0 | BV45: =SUM(BR45:BU45) -> 0 | CA45: =SUM(BW45:BZ45) -> 0
B46: Cash Used in Investing Activites | E46: =SUM(E37:E45) -> 0 | F46: =SUM(F37:F45) -> 0 | G46: =SUM(G37:G45) -> 0 | H46: =SUM(H37:H45) -> 0 | I46: =SUM(I37:I45) -> 0 | J46: =SUM(J37:J45) -> 0 | K46: =SUM(K37:K45) -> 0 | L46: =SUM(L37:L45) -> 0 | ... W46: =SUM(W37:W45) -> 0 | X46: =-80165 -> -80165 | AC46: =SUM(AC37:AC45) -> -40880 | AD46: =SUM(AD37:AD45) -> -6770 | AE46: =SUM(AE37:AE45) -> -3852 | AF46: =SUM(AF37:AF45) -> -4603 | AG46: =SUM(AG37:AG45) -> -3536 | AH46: =SUM(AH37:AH45) -> -18761 | AI46: =SUM(AI37:AI45) -> -6184 | AJ46: =SUM(AJ37:AJ45) -> -4336 | ... CA46: =SUM(CA37:CA45) -> -105000
B48: Free Cash Flow | D48: =D33+D37 -> 0 | E48: =E33+E37 -> 0 | F48: =F33+F37 -> 0 | G48: =G33+G37 -> 0 | H48: =H33+H37 -> 0 | I48: =I33+I37 -> 0 | J48: =J33+J37 -> 0 | K48: =K33+K37 -> 0 | ... W48: =W33+W37 -> 0 | X48: -96300 | Y48: =Y33+Y37+#REF! -> #REF! | Z48: =Z33+Z37+#REF! -> #REF! | AA48: =AA33+AA37+#REF! -> #REF! | AB48: =AB33+AB37+#REF! -> #REF! | AC48: =AC33+AC37 -> -48120 | AD48: =AD33+AD37 -> -7467 | AE48: =AE33+AE37 -> 7779 | AF48: =AF33+AF37 -> 7015 | AG48: =AG33+AG37 -> 28723 | AH48: =AH33+AH37 -> 36050 | AI48: =AI33+AI37 -> 8808 | AJ48: =AJ33+AJ37 -> 18359 | ... CA48: =CA33+CA37 -> 1084886.2
C49: FCF Margin | D49: =D48/IS!D13 -> #DIV/0! | E49: =E48/IS!E13 -> #DIV/0! | F49: =F48/IS!F13 -> #DIV/0! | G49: =G48/IS!G13 -> #DIV/0! | H49: =H48/IS!H13 -> #DIV/0! | I49: =I48/IS!I13 -> #DIV/0! | J49: =J48/IS!J13 -> #DIV/0! | K49: =K48/IS!K13 -> #DIV/0! | ... CA49: =CA48/IS!CA13 -> 0.3200066
B51: Financing Activities
C52: Payment of tax withholding obligation on RSU settlement | I52: =SUM(E52:H52) -> 0 | N52: =SUM(J52:M52) -> 0 | S52: =SUM(O52:R52) -> 0 | X52: 0 | AC52: 0 | AH52: =SUM(AD52:AG52) -> 0 | AL52: -215332 | AM52: =SUM(AI52:AL52) -> -215332 | AN52: -56137 | AO52: -29841 | AP52: -39310 | AQ52: -41216 | AR52: =SUM(AN52:AQ52) -> -166504 | AS52: -46723 | AT52: -87137 | AU52: -113417 | AV52: -125186 | AW52: =SUM(AS52:AV52) -> -372463 | AX52: -106053 | AY52: -122522 | AZ52: -94534 | BA52: -63412 | BB52: =SUM(AX52:BA52) -> -386521 | BC52: -24739 | BD52: -19118 | BE52: -23263 | BF52: -17283 | BG52: =SUM(BC52:BF52) -> -84403 | BH52: -22637 | BI52: -30008 | BJ52: -35615 | BK52: -45922 | BL52: =SUM(BH52:BK52) -> -134182 | BM52: -41637 | BN52: -39446 | BO52: -51051 | BP52: -81148 | BQ52: =SUM(BM52:BP52) -> -213282 | BR52: -62793 | BS52: -69164 | BT52: -74254 | BV52: =SUM(BR52:BU52) -> -206211 | CA52: =SUM(BW52:BZ52) -> 0
C53: Proceeds from the exercise of stock options | I53: =SUM(E53:H53) -> 0 | N53: =SUM(J53:M53) -> 0 | AC53: 8122 | AD53: 5830 | AE53: 7679 | AG53: 4487 | AH53: =SUM(AD53:AG53) -> 17996 | AI53: 7815 | AJ53: 2503 | AK53: 5047 | AL53: 34846 | AM53: =SUM(AI53:AL53) -> 50211 | AN53: 32254 | AO53: 10194 | AP53: 19815 | AQ53: 9914 | AR53: =SUM(AN53:AQ53) -> 72177 | AS53: 7635 | AT53: 5403 | AU53: 1945 | AW53: =SUM(AS53:AV53) -> 14983 | AX53: 6616 | AY53: 5202 | AZ53: 9358 | BA53: 2553 | BB53: =SUM(AX53:BA53) -> 23729 | BC53: 1938 | BD53: 8688 | BE53: 383 | BF53: 1669 | BG53: =SUM(BC53:BF53) -> 12678 | BH53: 127 | BI53: 705 | BJ53: 12375 | BK53: 784 | BL53: =SUM(BH53:BK53) -> 13991 | BM53: 635 | BN53: 454 | BO53: 10257 | BP53: 11359 | BQ53: =SUM(BM53:BP53) -> 22705 | BR53: 699 | BS53: 471 | BT53: 80 | BV53: =SUM(BR53:BU53) -> 1250 | CA53: =SUM(BW53:BZ53) -> 0
C54: Payment of deferred offering costs | AG54: -315 | AH54: =SUM(AD54:AG54) -> -315 | AI54: -2194 | AL54: -319 | AM54: =SUM(AI54:AL54) -> -2513 | AR54: =SUM(AN54:AQ54) -> 0 | AW54: =SUM(AS54:AV54) -> 0 | BB54: =SUM(AX54:BA54) -> 0 | BG54: =SUM(BC54:BF54) -> 0 | BL54: =SUM(BH54:BK54) -> 0 | BQ54: =SUM(BM54:BP54) -> 0 | BV54: =SUM(BR54:BU54) -> 0 | CA54: =SUM(BW54:BZ54) -> 0
C55: Other financing | AH55: =SUM(AD55:AG55) -> 0 | AL55: -250 | AM55: =SUM(AI55:AL55) -> -250 | AR55: =SUM(AN55:AQ55) -> 0 | AW55: =SUM(AS55:AV55) -> 0 | BB55: =SUM(AX55:BA55) -> 0 | BG55: =SUM(BC55:BF55) -> 0 | BL55: =SUM(BH55:BK55) -> 0 | BQ55: =SUM(BM55:BP55) -> 0 | BV55: =SUM(BR55:BU55) -> 0 | CA55: =SUM(BW55:BZ55) -> 0
C56: Proceeds from issuance of convertible senior notes | AC56: -85 | AH56: =SUM(AD56:AG56) -> 0 | AK56: 560756 | AM56: =SUM(AI56:AL56) -> 560756 | AR56: =SUM(AN56:AQ56) -> 0 | AV56: 677370 | AW56: =SUM(AS56:AV56) -> 677370 | BB56: =SUM(AX56:BA56) -> 0 | BG56: =SUM(BC56:BF56) -> 0 | BL56: =SUM(BH56:BK56) -> 0 | BQ56: =SUM(BM56:BP56) -> 0 | BV56: =SUM(BR56:BU56) -> 0 | CA56: =SUM(BW56:BZ56) -> 0
C57: Repurchases of common stock | BD57: -25007 | BE57: -38034 | BG57: =SUM(BC57:BF57) -> -63041 | BH57: -40472 | BI57: -40044 | BJ57: -75035 | BL57: =SUM(BH57:BK57) -> -155551 | BM57: -149062 | BN57: -200076 | BO57: -172665 | BP57: -161725 | BQ57: =SUM(BM57:BP57) -> -683528 | BR57: -183431 | BS57: -201514 | BT57: -215057 | BV57: =SUM(BR57:BU57) -> -600002 | CA57: =SUM(BW57:BZ57) -> 0
C58: Purchase of capped calls related to issuance of convertible senior notes | AH58: =SUM(AD58:AG58) -> 0 | AK58: -67563 | AM58: =SUM(AI58:AL58) -> -67563 | AR58: =SUM(AN58:AQ58) -> 0 | AV58: -31395 | AW58: =SUM(AS58:AV58) -> -31395 | BB58: =SUM(AX58:BA58) -> 0 | BG58: =SUM(BC58:BF58) -> 0 | BL58: =SUM(BH58:BK58) -> 0 | BQ58: =SUM(BM58:BP58) -> 0 | BV58: =SUM(BR58:BU58) -> 0 | CA58: =SUM(BW58:BZ58) -> 0
C59: Settlement of capped calls | BH59: 23688 | BL59: =SUM(BH59:BK59) -> 23688 | BQ59: =SUM(BM59:BP59) -> 0 | BV59: =SUM(BR59:BU59) -> 0 | CA59: =SUM(BW59:BZ59) -> 0
C60: repayment on convertible notes | AH60: =SUM(AD60:AG60) -> 0 | AM60: =SUM(AI60:AL60) -> 0 | AR60: =SUM(AN60:AQ60) -> 0 | AV60: -384199 | AW60: =SUM(AS60:AV60) -> -384199 | AX60: -36684 | AY60: -25030 | AZ60: -3121 | BA60: -13071 | BB60: =SUM(AX60:BA60) -> -77906 | BD60: -16 | BG60: =SUM(BC60:BF60) -> -16 | BJ60: -37083 | BK60: -689896 | BL60: =SUM(BH60:BK60) -> -726979 | BQ60: =SUM(BM60:BP60) -> 0 | BV60: =SUM(BR60:BU60) -> 0 | CA60: =SUM(BW60:BZ60) -> 0
C61: Payment on revolving credit facility costs | AH61: =SUM(AD61:AG61) -> 0 | AM61: =SUM(AI61:AL61) -> 0 | AR61: =SUM(AN61:AQ61) -> 0 | AV61: -2453 | AW61: =SUM(AS61:AV61) -> -2453 | BB61: =SUM(AX61:BA61) -> 0 | BG61: =SUM(BC61:BF61) -> 0 | BL61: =SUM(BH61:BK61) -> 0 | BQ61: =SUM(BM61:BP61) -> 0 | BS61: -3133 | BV61: =SUM(BR61:BU61) -> -3133 | CA61: =SUM(BW61:BZ61) -> 0
C62: Proceeds from issuance of common stock in initial public offering | AH62: =SUM(AD62:AG62) -> 0 | AJ62: 529305 | AM62: =SUM(AI62:AL62) -> 529305 | AR62: =SUM(AN62:AQ62) -> 0 | AW62: =SUM(AS62:AV62) -> 0 | BB62: =SUM(AX62:BA62) -> 0 | BG62: =SUM(BC62:BF62) -> 0 | BL62: =SUM(BH62:BK62) -> 0 | BQ62: =SUM(BM62:BP62) -> 0 | BV62: =SUM(BR62:BU62) -> 0 | CA62: =SUM(BW62:BZ62) -> 0
C63: Payment of deferred offering costs | AF63: 8437 | AH63: =SUM(AD63:AG63) -> 8437 | AJ63: -1328 | AK63: -170 | AM63: =SUM(AI63:AL63) -> -1498 | AR63: =SUM(AN63:AQ63) -> 0 | AW63: =SUM(AS63:AV63) -> 0 | BB63: =SUM(AX63:BA63) -> 0 | BG63: =SUM(BC63:BF63) -> 0 | BL63: =SUM(BH63:BK63) -> 0 | BQ63: =SUM(BM63:BP63) -> 0 | BV63: =SUM(BR63:BU63) -> 0 | CA63: =SUM(BW63:BZ63) -> 0
C64: Payment of holdback on prior acquisition | AF64: -390 | AH64: =SUM(AD64:AG64) -> -390 | AM64: =SUM(AI64:AL64) -> 0 | AR64: =SUM(AN64:AQ64) -> 0 | AW64: =SUM(AS64:AV64) -> 0 | BB64: =SUM(AX64:BA64) -> 0 | BG64: =SUM(BC64:BF64) -> 0 | BL64: =SUM(BH64:BK64) -> 0 | BQ64: =SUM(BM64:BP64) -> 0 | BV64: =SUM(BR64:BU64) -> 0 | CA64: =SUM(BW64:BZ64) -> 0
C65: Proceeds from employee stock purchase plan | X65: 0 | AC65: 0 | AH65: =SUM(AD65:AG65) -> 0 | AL65: 0 | AM65: =SUM(AI65:AL65) -> 0 | AN65: 10563 | AP65: 13309 | AR65: =SUM(AN65:AQ65) -> 23872 | AS65: 13590 | AU65: 16269 | AV65: 9322 | AW65: =SUM(AS65:AV65) -> 39181 | AX65: 23167 | AZ65: 22910 | BB65: =SUM(AX65:BA65) -> 46077 | BC65: 24151 | BD65: 0 | BE65: 12375 | BG65: =SUM(BC65:BF65) -> 36526 | BH65: 18390 | BJ65: 14604 | BL65: =SUM(BH65:BK65) -> 32994 | BM65: 20190 | BO65: 15124 | BQ65: =SUM(BM65:BP65) -> 35314 | BR65: 22010 | BT65: 18770 | BV65: =SUM(BR65:BU65) -> 40780 | CA65: =SUM(BW65:BZ65) -> 0
B66: Cash used in Financing Activites | D66: =SUM(D52:D65) -> 0 | E66: =SUM(E52:E65) -> 0 | F66: =SUM(F52:F65) -> 0 | G66: =SUM(G52:G65) -> 0 | H66: =SUM(H52:H65) -> 0 | I66: =SUM(I52:I65) -> 0 | J66: =SUM(J52:J65) -> 0 | K66: =SUM(K52:K65) -> 0 | ... W66: =SUM(W52:W65) -> 0 | X66: =274856 -> 274856 | Y66: =SUM(Y52:Y65) -> 0 | Z66: =SUM(Z52:Z65) -> 0 | AA66: =SUM(AA52:AA65) -> 0 | AB66: =SUM(AB52:AB65) -> 0 | AC66: =SUM(AC52:AC65) -> 8037 | AD66: =SUM(AD52:AD65) -> 5830 | AE66: =SUM(AE52:AE65) -> 7679 | AF66: =SUM(AF52:AF65) -> 8047 | ... CA66: =SUM(CA52:CA65) -> 0
B68: Effect of foreign currency exchange rate changes | I68: =SUM(E68:H68) -> 0 | N68: =SUM(J68:M68) -> 0 | S68: =SUM(O68:R68) -> 0 | X68: 0 | AC68: -334 | AD68: 484 | AE68: 1659 | AF68: -571 | AG68: 2674 | AH68: =SUM(AD68:AG68) -> 4246 | AI68: -2069 | AJ68: 527 | AK68: 362 | AL68: -2955 | AM68: =SUM(AI68:AL68) -> -4135 | AN68: -379 | AO68: -741 | AP68: 810 | AQ68: -137 | AR68: =SUM(AN68:AQ68) -> -447 | AS68: -2280 | AT68: 4920 | AU68: -1208 | AV68: 4214 | AW68: =SUM(AS68:AV68) -> 5646 | AX68: 779 | AY68: -1342 | AZ68: -1909 | BA68: -3122 | BB68: =SUM(AX68:BA68) -> -5594 | BC68: -5180 | BD68: -2860 | BE68: -6612 | BF68: 10868 | BG68: =SUM(BC68:BF68) -> -3784 | BH68: 1011 | BI68: 1279 | BJ68: -7187 | BK68: 5096 | BL68: =SUM(BH68:BK68) -> 199 | BM68: -2915 | BN68: 238 | BO68: 438 | BP68: -5311 | BQ68: =SUM(BM68:BP68) -> -7550 | BR68: 9923 | BS68: 1529 | BT68: 1922 | BV68: =SUM(BR68:BU68) -> 13374 | CA68: =SUM(BW68:BZ68) -> 0
B70: Net change in cash & cash equivalents | D70: =D68+D66+D46+D33 -> 0 | E70: =E68+E66+E46+E33 -> 0 | F70: =F68+F66+F46+F33 -> 0 | G70: =G68+G66+G46+G33 -> 0 | H70: =H68+H66+H46+H33 -> 0 | I70: =I68+I66+I46+I33 -> 0 | J70: =J68+J66+J46+J33 -> 0 | K70: =K68+K66+K46+K33 -> 0 | ... M70: =M68+M66+M46+M33 -> 0 | N70: =N33+N46+N66+N68 -> 0 | O70: =O33+O46+O66+O68 -> 0 | P70: =P33+P46+P66+P68 -> 0 | Q70: =Q33+Q46+Q66+Q68 -> 0 | R70: =R33+R46+R66+R68 -> 0 | S70: =S33+S46+S66+S68 -> 0 | T70: =T33+T46+T66+T68 -> 0 | U70: =U33+U46+U66+U68 -> 0 | ... CA70: =CA33+CA46+CA66+CA68 -> 1084886.2
B72: Beginning cash & cash equivalents | T72: =S73 -> 0 | U72: =T73 -> 0 | V72: =U73 -> 0 | W72: =V73 -> 0 | Y72: =W73 -> 0 | Z72: =Y73 -> 0 | AA72: =Z73 -> 0 | AB72: =AA73 -> 0 | AC72: 229211 | AD72: 191244 | AE72: 190091 | AF72: 207675 | AG72: =AF73 -> 222166 | AH72: =AC73 -> 191244 | AI72: =AG73 -> 257436 | AJ72: =AI73 -> 269796 | AK72: =AJ73 -> 819162 | AL72: =AK73 -> 1094500 | AM72: =AH73 -> 257436 | AN72: =AL73 -> 518178 | AO72: =AN73 -> 236643 | AP72: =AO73 -> 224423 | AQ72: =AP73 -> 198111 | AR72: =AM73 -> 518178 | AS72: =AQ73 -> 241483 | AT72: =AS73 -> 442517 | AU72: =AT73 -> 404542 | AV72: =AU73 -> 375265 | AW72: =AR73 -> 241483 | AX72: =AV73 -> 566336 | AY72: =AX73 -> 519252 | AZ72: =AY73 -> 518858 | BA72: =AZ73 -> 504165 | BB72: =AW73 -> 566336 | BC72: =BA73 -> 509682 | BD72: =BC73 -> 639624 | BE72: 638849 | BF72: =BE73 -> 634392 | BG72: =BB73 -> 509682 | BH72: =BF73 -> 723201 | BI72: =BH73 -> 944755 | BJ72: =BI73 -> 1022980 | BK72: =BJ73 -> 1193501 | BL72: =BG73 -> 723204 | BM72: =BK73 -> 801499 | BN72: =BM73 -> 822759 | BO72: =BN73 -> 628027 | BP72: =BO73 -> 620758 | BQ72: =BL73 -> 801502 | BR72: =BP73 -> 659554 | BS72: =BR73 -> 672476 | BT72: =BS73 -> 616286 | BU72: =BT73 -> 600273 | BV72: =BQ73 -> 659557 | BW72: =BU73 -> 872054.33 | BX72: =BW73 -> 1235607.6 | BY72: =BX73 -> 1504861.3 | BZ72: =BY73 -> 1661658.1 | CA72: =BV73 -> 872057.33
B73: Ending cash & cash equivalents | S73: =S72+S70 -> 0 | T73: =T70+T72 -> 0 | U73: =U70+U72 -> 0 | V73: =V70+V72 -> 0 | W73: =W70+W72 -> 0 | X73: =X70+X72 -> 126696 | Y73: =Y70+Y72 -> 0 | Z73: =Z70+Z72 -> 0 | AA73: =AA70+AA72 -> 0 | ... CA73: =CA70+CA72 -> 1956943.5
E75: =E73-BS!E6 -> 0 | F75: =F73-BS!F6 -> 0 | G75: =G73-BS!G6 -> 0 | H75: =H73-BS!H6 -> 0 | I75: =I73-BS!I6 -> 0 | J75: =J73-BS!J6 -> 0 | K75: =K73-BS!K6 -> 0 | L75: =L73-BS!L6 -> 0 | ... Q75: =Q73-BS!Q6 -> 0 | R75: 0 | S75: =S73-BS!S6 -> 0 | W75: =W73-BS!W6 -> 0 | X75: =X73-BS!X6 -> -101827 | AA75: =AA73-BS!AA6 -> 0 | AB75: =AB73-BS!AB6 -> 0 | AC75: =AC73-BS!AC6 -> 688 | AD75: =AD73-BS!AD6 -> 190091 | AE75: =AE73-BS!AE6 -> 207675 | AF75: =AF73-BS!AF6 -> 222166 | AG75: =AG73-BS!AG6 -> 569 | AH75: =AH73-BS!AH6 -> 569 | ... CA75: =CA73-BS!CA6 -> 16985
