Workbook
Name _1994: #REF!
Name _1995: #REF!
Name _1996: #REF!
Name _1997: #REF!
Name _1998: #REF!
Name _1999: #REF!
Name _1Q94: #REF!
Name _1Q95: #REF!
Name _2007: #REF!
Name _2008: #REF!
Name _2Q94: #REF!
Name _2Q95: #REF!
Name _3Q94: #REF!
Name _3Q95: #REF!
Name _4Q94: #REF!
Name _4Q95: #REF!
Name _Key1: #REF!
Name _marketsource: #REF!
Name _Order1: 0
Name _Sort: #REF!
Name _strtyr: #REF!
Name a: #REF!
Name Acc_payable: #REF!
Name Acc_payable_growth_fore: #REF!
Name Acc_Rec: #REF!
Name Acc_Rec_growth_fore: #REF!
Name Acc_Rec_turns: #REF!
Name Accel_Ratio: #REF!
Name Accrued_compensation: #REF!
Name Accrued_compensation_growth_fore: #REF!
Name Accrued_expenses: #REF!
Name Accrued_expenses_growth_fore: #REF!
Name Accum_Cap_Expenses: #REF!
Name Accum_Cap_Expenses_growth_fore: #REF!
Name Accum_Goodwill_Amort: #REF!
Name Accum_Goodwill_Amort_growth_fore: #REF!
Name Accum_Other_Amort.: #REF!
Name Adj_net_oper_fore: #REF!
Name Adjusted_Common_Equity: #REF!
Name Adjusted_Income_Available_to_Common: #REF!
Name Adjusted_Net_Operating_Profit: #REF!
Name AEH_qtrly_results: #REF!
Name After_tax_charge: #REF!
Name After_Tax_charges_gains: #REF!
Name Ag: #REF!
Name AHC_CAPEX: #REF!
Name AHC_CAPEX_2004: #REF!
Name AHC_CAPEX_2005: #REF!
Name AHC_CAPEX_2006: #REF!
Name AHC_CAPEX_2007: #REF!
Name AHC_CAPEX_Chems: #REF!
Name AHC_CAPEX_EP: #REF!
Name AHC_CAPEX_EP_2004: #REF!
Name AHC_CAPEX_EP_2005: #REF!
Name AHC_CAPEX_EP_2006: #REF!
Name AHC_CAPEX_EP_2007: #REF!
Name AHC_CAPEX_Other: #REF!
Name AHC_CAPEX_Other_2004: #REF!
Name AHC_CAPEX_Other_2005: #REF!
Name AHC_CAPEX_Other_2006: #REF!

Sheet __FDSCACHE__
B1: This sheet contains FactSet XML data for use with this workbook's =FDS codes. Modifying the worksheet's contents may damage the workbook's =FDS functionality.

Sheet Disclaimer
C5: Equity Research
C7: Financial Model
C8: Life Science Tools & Diagnostics
C9: 46080
C12: Natera, Inc. (NTRA)
C19: Brandon Couillard | E19: Evan Stampler, PhD, CFA | G19: Chris Mercado, CFA
C20: Senior Analyst | E20: Vice President | G20: Vice President
C21: 212.214.5053 | E21: 212.214.5312 | G21: 212.214.8092
C22: brandon.couillard@wellsfargo.com | E22: evan.stampler@wellsfargo.com | G22: chistopher.mercado2@wellsfargo.com
C26: Important Disclaimers:
BN437: 33.6
BN438: 16.1
BN443: 0
BO513: 40 | BW513: 30
BN514: =0.9 -> 0.9 | BO514: 1 | BR514: =+BP514 -> 0

Sheet IS
A1: Natera Inc. (NASDAQ: NTRA)
A2: Income Statement
A3: $ millions except per share data, FY ending Dec
B5: Mar | C5: Jun | D5: Sep | E5: Dec | F5: 41974 | G5: Mar | H5: Jun | I5: Sep | J5: Dec | K5: =+DATE(YEAR(F5)+1,MONTH(F5),DAY(F5)) -> 42339 | L5: Mar | M5: Jun | N5: Sep | O5: Dec | P5: =+DATE(YEAR(K5)+1,MONTH(K5),DAY(K5)) -> 42705 | Q5: Mar | R5: Jun | S5: Sep | T5: Dec | U5: =+DATE(YEAR(P5)+1,MONTH(P5),DAY(P5)) -> 43070 | V5: Mar | W5: Jun | X5: Sep | Y5: Dec | Z5: =+DATE(YEAR(U5)+1,MONTH(U5),DAY(U5)) -> 43435 | AA5: Mar | AB5: Jun | AC5: Sep | AD5: Dec | AE5: =+DATE(YEAR(Z5)+1,MONTH(Z5),DAY(Z5)) -> 43800 | AF5: Mar | AG5: Jun | AH5: Sep | AI5: Dec | AJ5: =+DATE(YEAR(AE5)+1,MONTH(AE5),DAY(AE5)) -> 44166 | AK5: Mar | AL5: Jun | AM5: Sep | AN5: Dec | AO5: =+DATE(YEAR(AJ5)+1,MONTH(AJ5),DAY(AJ5)) -> 44531 | AP5: Mar | AQ5: Jun | AR5: Sep | AS5: Dec | AT5: =+DATE(YEAR(AO5)+1,MONTH(AO5),DAY(AO5)) -> 44896 | AU5: Mar | AV5: Jun | AW5: Sep | AX5: Dec | AY5: =+DATE(YEAR(AT5)+1,MONTH(AT5),DAY(AT5)) -> 45261 | AZ5: Mar | BA5: Jun | BB5: Sep | BC5: Dec | BD5: =+DATE(YEAR(AY5)+1,MONTH(AY5),DAY(AY5)) -> 45627 | BE5: Mar | BF5: Jun | BG5: Sep | BH5: Dec | BI5: =+DATE(YEAR(BD5)+1,MONTH(BD5),DAY(BD5)) -> 45992 | BJ5: Mar | BK5: Jun | BL5: Sep | BM5: Dec | BN5: =+DATE(YEAR(BI5)+1,MONTH(BI5),DAY(BI5)) -> 46357 | BO5: Mar | BP5: Jun | BQ5: Sep | BR5: Dec | BS5: =+DATE(YEAR(BN5)+1,MONTH(BN5),DAY(BN5)) -> 46722 | BT5: Mar | BU5: Jun | BV5: Sep | BW5: Dec | BX5: =+DATE(YEAR(BS5)+1,MONTH(BS5),DAY(BS5)) -> 47088 | BY5: Mar | BZ5: Jun | CA5: Sep | CB5: Dec | CC5: =+DATE(YEAR(BX5)+1,MONTH(BX5),DAY(BX5)) -> 47453 | CD5: Mar | CE5: Jun | CF5: Sep | CG5: Dec | CH5: =+DATE(YEAR(CC5)+1,MONTH(CC5),DAY(CC5)) -> 47818 | CI5: Mar | CJ5: Jun | CK5: Sep | CL5: Dec | CM5: =+DATE(YEAR(CH5)+1,MONTH(CH5),DAY(CH5)) -> 48183 | CN5: Mar | CO5: Jun | CP5: Sep | CQ5: Dec | CR5: =+DATE(YEAR(CM5)+1,MONTH(CM5),DAY(CM5)) -> 48549 | CS5: Mar | CT5: Jun | CU5: Sep | CV5: Dec | CW5: =+DATE(YEAR(CR5)+1,MONTH(CR5),DAY(CR5)) -> 48914 | CX5: Mar | CY5: Jun | CZ5: Sep | DA5: Dec | DB5: =+DATE(YEAR(CW5)+1,MONTH(CW5),DAY(CW5)) -> 49279
B6: 1Q14A | C6: 2Q14A | D6: 3Q14A | E6: 4Q14A | F6: FY14A | G6: 1Q15A | H6: 2Q15A | I6: 3Q15A | J6: 4Q15A | K6: FY15A | L6: 1Q16A | M6: 2Q16A | N6: 3Q16A | O6: 4Q16A | P6: FY16A | Q6: 1Q17A | R6: 2Q17A | S6: 3Q17A | T6: 4Q17A | U6: FY17A | V6: 1Q18A | W6: 2Q18A | X6: 3Q18A | Y6: 4Q18A | Z6: FY18A | AA6: 1Q19A | AB6: 2Q19A | AC6: 3Q19A | AD6: 4Q19A | AE6: FY19A | AF6: 1Q20A | AG6: 2Q20A | AH6: 3Q20A | AI6: 4Q20A | AJ6: FY20A | AK6: 1Q21A | AL6: 2Q21A | AM6: 3Q21A | AN6: 4Q21A | AO6: FY21A | AP6: 1Q22A | AQ6: 2Q22A | AR6: 3Q22A | AS6: 4Q22A | AT6: FY22A | AU6: 1Q23A | AV6: 2Q23A | AW6: 3Q23A | AX6: 4Q23A | AY6: FY23A | AZ6: 1Q24A | BA6: 2Q24A | BB6: 3Q24A | BC6: 4Q24A | BD6: FY24A | BE6: 1Q25A | BF6: 2Q25A | BG6: 3Q25A | BH6: 4Q25 | BI6: FY25 | BJ6: 1Q26E | BK6: 2Q26E | BL6: 3Q26E | BM6: 4Q26E | BN6: FY26E | BO6: 1Q27E | BP6: 2Q27E | BQ6: 3Q27E | BR6: 4Q27E | BS6: FY27E | BT6: 1Q28E | BU6: 2Q28E | BV6: 3Q28E | BW6: 4Q28E | BX6: FY28E | BY6: 1Q29E | BZ6: 2Q29E | CA6: 3Q29E | CB6: 4Q29E | CC6: FY29E | CD6: 1Q30E | CE6: 2Q30E | CF6: 3Q30E | CG6: 4Q30E | CH6: FY30E | CI6: 1Q31E | CJ6: 2Q31E | CK6: 3Q31E | CL6: 4Q31E | CM6: FY31E | CN6: 1Q32E | CO6: 2Q32E | CP6: 3Q32E | CQ6: 4Q32E | CR6: FY32E | CS6: 1Q33E | CT6: 2Q33E | CU6: 3Q33E | CV6: 4Q33E | CW6: FY33E | CX6: 1Q34E | CY6: 2Q34E | CZ6: 3Q34E | DA6: 4Q34E | DB6: FY34E | DD6: 5-yr CAGR | DE6: 3-yr CAGR
A7: Net Sales | B7: =27.209+0.086 -> 27.295 | C7: =35.736+0.1 -> 35.836 | D7: =45.804+0.47 -> 46.274 | E7: =F7-SUM(B7:D7) -> 49.884 | F7: 159.289 | G7: 47.435 | H7: 45.087 | I7: 44.921 | J7: =K7-SUM(G7:I7) -> 52.912 | K7: 190.355 | L7: 61.902 | M7: 51.984 | N7: 53.889 | O7: =P7-SUM(L7:N7) -> 49.299 | P7: 217.074 | Q7: 46.901 | R7: 53.617 | S7: 56.656 | T7: =U7-SUM(Q7:S7) -> 53.765 | U7: 210.939 | V7: 62.34 | W7: 63.069 | X7: 65.28 | Y7: =Z7-SUM(V7:X7) -> 66.965 | Z7: 257.654 | AA7: 66.824 | AB7: 74.355 | AC7: 77.909 | AD7: =AE7-SUM(AA7:AC7) -> 83.24 | AE7: 302.328 | AF7: 94.012 | AG7: 86.472 | AH7: 98.143 | AI7: =AJ7-SUM(AF7:AH7) -> 112.378 | AJ7: 391.005 | AK7: 152.316 | AL7: 142.026 | AM7: 158.116 | AN7: =AO7-SUM(AK7:AM7) -> 173.028 | AO7: 625.486 | AP7: 194.133 | AQ7: 198.2 | AR7: 210.637 | AS7: =AT7-SUM(AP7:AR7) -> 217.252 | AT7: 820.222 | AU7: 241.756 | AV7: 261.404 | AW7: 268.306 | AX7: =AY7-SUM(AU7:AW7) -> 311.105 | AY7: 1082.571 | AZ7: 367.741 | BA7: 413.351 | BB7: 439.758 | BC7: =BD7-SUM(AZ7:BB7) -> 476.061 | BD7: 1696.911 | BE7: 501.83 | BF7: =544.427+2.173 -> 546.6 | BG7: 592.183 | BH7: =2306.113-BE7-BF7-BG7 -> 665.5 | BI7: =SUM(BE7:BH7) -> 2306.113 | BJ7: =+Rev!BJ17 -> 616.53287 | BK7: =+Rev!BK17 -> 650.50782 | BL7: =+Rev!BL17 -> 676.58177 | BM7: =+Rev!BM17 -> 715.30687 | BN7: =SUM(BJ7:BM7) -> 2658.9293 | BO7: =+Rev!BO17 -> 762.14849 | BP7: =+Rev!BP17 -> 763.06913 | BQ7: =+Rev!BQ17 -> 790.7504 | BR7: =+Rev!BR17 -> 813.12422 | BS7: =SUM(BO7:BR7) -> 3129.0922 | BT7: =+Rev!BT17 -> 876.90033 | BU7: =+Rev!BU17 -> 886.05176 | BV7: =+Rev!BV17 -> 913.63859 | BW7: =+Rev!BW17 -> 940.58178 | BX7: =SUM(BT7:BW7) -> 3617.1725 | BY7: =+Rev!BY17 -> 1012.82 | BZ7: =+Rev!BZ17 -> 1016.8898 | CA7: =+Rev!CA17 -> 1051.5164 | CB7: =+Rev!CB17 -> 1076.6057 | CC7: =SUM(BY7:CB7) -> 4157.8319 | CD7: =+Rev!CD17 -> 1155.036 | CE7: =+Rev!CE17 -> 1161.815 | CF7: =+Rev!CF17 -> 1196.7164 | CG7: =+Rev!CG17 -> 1225.5048 | CH7: =SUM(CD7:CG7) -> 4739.0721 | CI7: =+Rev!CI17 -> 1298.4004 | CJ7: =+Rev!CJ17 -> 1301.0288 | CK7: =+Rev!CK17 -> 1332.8348 | CL7: =+Rev!CL17 -> 1358.4264 | CM7: =SUM(CI7:CL7) -> 5290.6903 | CN7: =+Rev!CN17 -> 1435.3246 | CO7: =+Rev!CO17 -> 1437.9537 | CP7: =+Rev!CP17 -> 1470.6387 | CQ7: =+Rev!CQ17 -> 1497.2106 | CR7: =SUM(CN7:CQ7) -> 5841.1277 | CS7: =+Rev!CS17 -> 1578.9497 | CT7: =+Rev!CT17 -> 1582.2801 | CU7: =+Rev!CU17 -> 1616.7881 | CV7: =+Rev!CV17 -> 1645.0622 | CW7: =SUM(CS7:CV7) -> 6423.0801 | CX7: =+Rev!CX17 -> 1717.5517 | CY7: =+Rev!CY17 -> 1717.0667 | CZ7: =+Rev!CZ17 -> 1748.7456 | DA7: =+Rev!DA17 -> 1774.2 | DB7: =SUM(CX7:DA7) -> 6957.564
A8: Cost of Revenues | B8: 15.9 | C8: 19.014 | D8: 20.82 | E8: =F8-SUM(B8:D8) -> 22.662 | F8: 78.396 | G8: 24.843 | H8: 25.732 | I8: 30.456 | J8: =K8-SUM(G8:I8) -> 31.814 | K8: 112.845 | L8: 32.34 | M8: 30.973 | N8: 34.261 | O8: =P8-SUM(L8:N8) -> 38 | P8: 135.574 | Q8: =33.088+0.612 -> 33.7 | R8: =33.709+0.85 -> 34.559 | S8: =33.558+1.054 -> 34.612 | T8: =U8-SUM(Q8:S8) -> 36.725 | U8: =135.508+4.088 -> 139.596 | V8: =39.055+1.537 -> 40.592 | W8: =39.204+1.791 -> 40.995 | X8: =39.477+2.202 -> 41.679 | Y8: =Z8-SUM(V8:X8) -> 42.789 | Z8: =158.081+7.974 -> 166.055 | AA8: =41.605+1.698 -> 43.303 | AB8: =41.382+2.443 -> 43.825 | AC8: =40.138+3.742 -> 43.88 | AD8: =AE8-SUM(AA8:AC8) -> 44.462 | AE8: =162.604+12.866 -> 175.47 | AF8: =41.52+3.458 -> 44.978 | AG8: =42.731+4.208 -> 46.939 | AH8: =46.873+4.948 -> 51.821 | AI8: =AJ8-SUM(AF8:AH8) -> 59.882 | AJ8: =185.865+17.755 -> 203.62 | AK8: =61.322+5.491 -> 66.813 | AL8: =73.227+2.885 -> 76.112 | AM8: =76.838+4.533 -> 81.371 | AN8: =AO8-SUM(AK8:AM8) -> 94.122 | AO8: =302.663+15.755 -> 318.418 | AP8: =102.67+0.545 -> 103.215 | AQ8: =108.756+0.481 -> 109.237 | AR8: =115.436+1.076 -> 116.512 | AS8: =AT8-SUM(AP8:AR8) -> 127.292 | AT8: =453.632+2.624 -> 456.256 | AU8: =147.754+0.37 -> 148.124 | AV8: =142.808+0.341 -> 143.149 | AW8: =146.962+0.349 -> 147.311 | AX8: =AY8-SUM(AU8:AW8) -> 151.247 | AY8: =588.564+1.267 -> 589.831 | AZ8: =158.833+0.307 -> 159.14 | BA8: =169.85+0.329 -> 170.179 | BB8: =167.657+0.354 -> 168.011 | BC8: =BD8-SUM(AZ8:BB8) -> 176.423 | BD8: =672.304+1.449 -> 673.753 | BE8: =184.613+0.452 -> 185.065 | BF8: =199.531+0.465 -> 199.996 | BG8: =207.253+0.548 -> 207.801 | BH8: =810.627+2.306-BE8-BF8-BG8 -> 220.071 | BI8: =SUM(BE8:BH8) -> 812.933 | BJ8: =+BJ7-BJ9 -> 230.4524 | BK8: =+BK7-BK9 -> 239.65354 | BL8: =+BL7-BL9 -> 237.52289 | BM8: =+BM7-BM9 -> 234.83095 | BN8: =SUM(BJ8:BM8) -> 942.45977 | BO8: =+BO7-BO9 -> 267.60622 | BP8: =+BP7-BP9 -> 269.58173 | BQ8: =+BQ7-BQ9 -> 270.51446 | BR8: =+BR7-BR9 -> 261.80974 | BS8: =SUM(BO8:BR8) -> 1069.5122 | BT8: =+BT7-BT9 -> 294.20707 | BU8: =+BU7-BU9 -> 299.97641 | BV8: =+BV7-BV9 -> 298.35836 | BW8: =+BW7-BW9 -> 289.00616 | BX8: =SUM(BT8:BW8) -> 1181.548 | BY8: =+BY7-BY9 -> 326.87003 | BZ8: =+BZ7-BZ9 -> 331.20942 | CA8: =+CA7-CA9 -> 331.20094 | CB8: =+CB7-CB9 -> 319.36444 | CC8: =SUM(BY8:CB8) -> 1308.6448 | CD8: =+CD7-CD9 -> 359.35482 | CE8: =+CE7-CE9 -> 365.13248 | CF8: =+CF7-CF9 -> 364.02375 | CG8: =+CG7-CG9 -> 351.26336 | CH8: =SUM(CD8:CG8) -> 1439.7744 | CI8: =+CI7-CI9 -> 392.38467 | CJ8: =+CJ7-CJ9 -> 398.34097 | CK8: =+CK7-CK9 -> 395.83634 | CL8: =+CL7-CL9 -> 381.01633 | CM8: =SUM(CI8:CL8) -> 1567.5783 | CN8: =+CN7-CN9 -> 424.05992 | CO8: =+CO7-CO9 -> 430.91641 | CP8: =+CP7-CP9 -> 427.59469 | CQ8: =+CQ7-CQ9 -> 411.43563 | CR8: =SUM(CN8:CQ8) -> 1694.0067 | CS8: =+CS7-CS9 -> 456.55124 | CT8: =+CT7-CT9 -> 464.4006 | CU8: =+CU7-CU9 -> 460.41948 | CV8: =+CV7-CV9 -> 442.93284 | CW8: =SUM(CS8:CV8) -> 1824.3042 | CX8: =+CX7-CX9 -> 489.53371 | CY8: =+CY7-CY9 -> 497.75608 | CZ8: =+CZ7-CZ9 -> 492.44631 | DA8: =+DA7-DA9 -> 473.08617 | DB8: =SUM(CX8:DA8) -> 1952.8223
A9: Gross Profit | B9: =B7-B8 -> 11.395 | C9: =C7-C8 -> 16.822 | D9: =D7-D8 -> 25.454 | E9: =E7-E8 -> 27.222 | F9: =F7-F8 -> 80.893 | G9: =G7-G8 -> 22.592 | H9: =H7-H8 -> 19.355 | I9: =I7-I8 -> 14.465 | ... AX9: =AX7-AX8 -> 159.858 | AY9: =SUM(AU9:AX9) -> 492.74 | AZ9: =AZ7-AZ8 -> 208.601 | BA9: =BA7-BA8 -> 243.172 | BB9: =BB7-BB8 -> 271.747 | BC9: =BC7-BC8 -> 299.638 | BD9: =SUM(AZ9:BC9) -> 1023.158 | BE9: =BE7-BE8 -> 316.765 | BF9: =BF7-BF8 -> 346.604 | BG9: =BG7-BG8 -> 384.382 | BH9: =BH7-BH8 -> 445.429 | BI9: =SUM(BE9:BH9) -> 1493.18 | BJ9: =+Rev!BJ479 -> 386.08047 | BK9: =+Rev!BK479 -> 410.85429 | BL9: =+Rev!BL479 -> 439.05889 | BM9: =+Rev!BM479 -> 480.47592 | BN9: =+Rev!BN479 -> 1716.4696 | BO9: =+Rev!BO479 -> 494.54227 | BP9: =+Rev!BP479 -> 493.48739 | BQ9: =+Rev!BQ479 -> 520.23595 | ... DB9: =+Rev!DB479 -> 5004.7417
A10: Research & Development | B10: 4.298 | C10: 4.122 | D10: 4.372 | E10: =F10-SUM(B10:D10) -> 4.5 | F10: 17.292 | G10: 5.63 | H10: 6.741 | I10: 7.336 | J10: =K10-SUM(G10:I10) -> 8.004 | K10: 27.711 | L10: 8.759 | M10: 10.299 | N10: 11.345 | O10: =P10-SUM(L10:N10) -> 11.459 | P10: 41.862 | Q10: 12.65 | R10: 11.786 | S10: 12.609 | T10: =U10-SUM(Q10:S10) -> 13.019 | U10: 50.064 | V10: 14.34 | W10: 11.852 | X10: 12.393 | Y10: =Z10-SUM(V10:X10) -> 12.77 | Z10: 51.355 | AA10: 11.435 | AB10: 12.124 | AC10: 12.796 | AD10: =AE10-SUM(AA10:AC10) -> 15.002 | AE10: 51.357 | AF10: 18.225 | AG10: 23.005 | AH10: 26.421 | AI10: =AJ10-SUM(AF10:AH10) -> 32.384 | AJ10: 100.035 | AK10: 40.188 | AL10: 53.752 | AM10: 98.457 | AN10: =AO10-SUM(AK10:AM10) -> 71.811 | AO10: 264.208 | AP10: 80.414 | AQ10: 82.58 | AR10: 65.51 | AS10: =AT10-SUM(AP10:AR10) -> 87.911 | AT10: 316.415 | AU10: 82.306 | AV10: 78.173 | AW10: 77.235 | AX10: =AY10-SUM(AU10:AW10) -> 82.964 | AY10: 320.678 | AZ10: 88.637 | BA10: 89.109 | BB10: 96.931 | BC10: =BD10-SUM(AZ10:BB10) -> 129.461 | BD10: 404.138 | BE10: 129.078 | BF10: =146.427 -> 146.427 | BG10: 173.412 | BH10: =624.11-BE10-BF10-BG10 -> 175.193 | BI10: =SUM(BE10:BH10) -> 624.11 | BJ10: 198 | BK10: 198 | BL10: 204 | BM10: 208 | BN10: =SUM(BJ10:BM10) -> 808 | BO10: =+BJ10*(1+BO36) -> 215.82 | BP10: =+BK10*(1+BP36) -> 215.82 | BQ10: =+BL10*(1+BQ36) -> 222.36 | BR10: =+BM10*(1+BR36) -> 226.72 | BS10: =SUM(BO10:BR10) -> 880.72 | BT10: =+BO10*(1+BT36) -> 233.0856 | BU10: =+BP10*(1+BU36) -> 233.0856 | BV10: =+BQ10*(1+BV36) -> 240.1488 | BW10: =+BR10*(1+BW36) -> 244.8576 | BX10: =SUM(BT10:BW10) -> 951.1776 | BY10: =+BT10*(1+BY36) -> 250.56702 | BZ10: =+BU10*(1+BZ36) -> 250.56702 | CA10: =+BV10*(1+CA36) -> 258.15996 | CB10: =+BW10*(1+CB36) -> 263.22192 | CC10: =SUM(BY10:CB10) -> 1022.5159 | CD10: =+BY10*(1+CD36) -> 268.10671 | CE10: =+BZ10*(1+CE36) -> 268.10671 | CF10: =+CA10*(1+CF36) -> 276.23116 | CG10: =+CB10*(1+CG36) -> 281.64745 | CH10: =SUM(CD10:CG10) -> 1094.092 | CI10: =+CD10*(1+CI36) -> 286.87418 | CJ10: =+CE10*(1+CJ36) -> 286.87418 | CK10: =+CF10*(1+CK36) -> 295.56734 | CL10: =+CG10*(1+CL36) -> 301.36278 | CM10: =SUM(CI10:CL10) -> 1170.6785 | CN10: =+CI10*(1+CN36) -> 306.95537 | CO10: =+CJ10*(1+CO36) -> 306.95537 | CP10: =+CK10*(1+CP36) -> 316.25705 | CQ10: =+CL10*(1+CQ36) -> 322.45817 | CR10: =SUM(CN10:CQ10) -> 1252.626 | CS10: =+CN10*(1+CS36) -> 328.44225 | CT10: =+CO10*(1+CT36) -> 328.44225 | CU10: =+CP10*(1+CU36) -> 338.39505 | CV10: =+CQ10*(1+CV36) -> 345.03024 | CW10: =SUM(CS10:CV10) -> 1340.3098 | CX10: =+CS10*(1+CX36) -> 351.43321 | CY10: =+CT10*(1+CY36) -> 351.43321 | CZ10: =+CU10*(1+CZ36) -> 362.0827 | DA10: =+CV10*(1+DA36) -> 369.18236 | DB10: =SUM(CX10:DA10) -> 1434.1315
A11: Selling, General & Administrative | B11: 14.379 | C11: 13.905 | D11: 16.303 | E11: =F11-SUM(B11:D11) -> 18.349 | F11: 62.936 | G11: 23.239 | H11: 28.086 | I11: 27.87 | J11: =K11-SUM(G11:I11) -> 30.442 | K11: 109.637 | L11: 30.408 | M11: 33.227 | N11: 34.938 | O11: =P11-SUM(L11:N11) -> 37.553 | P11: 136.126 | Q11: 37.582 | R11: 34.309 | S11: 34.478 | T11: =U11-SUM(Q11:S11) -> 48.937 | U11: 155.306 | V11: 37.925 | W11: 37.44 | X11: 38.374 | Y11: =Z11-SUM(V11:X11) -> 41.133 | Z11: 154.872 | AA11: 43.832 | AB11: 47.042 | AC11: 56.715 | AD11: =AE11-SUM(AA11:AC11) -> 58.587 | AE11: 206.176 | AF11: 65.681 | AG11: 68.188 | AH11: 75.678 | AI11: =AJ11-SUM(AF11:AH11) -> 94.08 | AJ11: 303.627 | AK11: 108.332 | AL11: 127.456 | AM11: 128.485 | AN11: =AO11-SUM(AK11:AM11) -> 146.761 | AO11: 511.034 | AP11: 147.634 | AQ11: 149.468 | AR11: 147.667 | AS11: =AT11-SUM(AP11:AR11) -> 143.822 | AT11: 588.591 | AU11: 149.627 | AV11: 152.508 | AW11: 154.742 | AX11: =AY11-SUM(AU11:AW11) -> 161.43 | AY11: 618.307 | AZ11: 194.278 | BA11: 197.965 | BB11: 214.154 | BC11: =BD11-SUM(AZ11:BB11) -> 234.917 | BD11: 841.314 | BE11: 266.864 | BF11: =310.549 -> 310.549 | BG11: 308.546 | BH11: =1177.261+1.72-BE11-BF11-BG11 -> 293.022 | BI11: =SUM(BE11:BH11) -> 1178.981 | BJ11: 280 | BK11: 290 | BL11: 300 | BM11: 310 | BN11: =SUM(BJ11:BM11) -> 1180 | BO11: =+BJ11*(1+BO37) -> 305.2 | BP11: =+BK11*(1+BP37) -> 316.1 | BQ11: =+BL11*(1+BQ37) -> 327 | BR11: =+BM11*(1+BR37) -> 337.9 | BS11: =SUM(BO11:BR11) -> 1286.2 | BT11: =+BO11*(1+BT37) -> 329.616 | BU11: =+BP11*(1+BU37) -> 341.388 | BV11: =+BQ11*(1+BV37) -> 353.16 | BW11: =+BR11*(1+BW37) -> 364.932 | BX11: =SUM(BT11:BW11) -> 1389.096 | BY11: =+BT11*(1+BY37) -> 354.3372 | BZ11: =+BU11*(1+BZ37) -> 366.9921 | CA11: =+BV11*(1+CA37) -> 379.647 | CB11: =+BW11*(1+CB37) -> 392.3019 | CC11: =SUM(BY11:CB11) -> 1493.2782 | CD11: =+BY11*(1+CD37) -> 379.1408 | CE11: =+BZ11*(1+CE37) -> 392.68155 | CF11: =+CA11*(1+CF37) -> 406.22229 | CG11: =+CB11*(1+CG37) -> 419.76303 | CH11: =SUM(CD11:CG11) -> 1597.8077 | CI11: =+CD11*(1+CI37) -> 401.88925 | CJ11: =+CE11*(1+CJ37) -> 416.24244 | CK11: =+CF11*(1+CK37) -> 430.59563 | CL11: =+CG11*(1+CL37) -> 444.94881 | CM11: =SUM(CI11:CL11) -> 1693.6761 | CN11: =+CI11*(1+CN37) -> 426.00261 | CO11: =+CJ11*(1+CO37) -> 441.21699 | CP11: =+CK11*(1+CP37) -> 456.43137 | CQ11: =+CL11*(1+CQ37) -> 471.64574 | CR11: =SUM(CN11:CQ11) -> 1795.2967 | CS11: =+CN11*(1+CS37) -> 451.56276 | CT11: =+CO11*(1+CT37) -> 467.69001 | CU11: =+CP11*(1+CU37) -> 483.81725 | CV11: =+CQ11*(1+CV37) -> 499.94449 | CW11: =SUM(CS11:CV11) -> 1903.0145 | CX11: =+CS11*(1+CX37) -> 478.65653 | CY11: =+CT11*(1+CY37) -> 495.75141 | CZ11: =+CU11*(1+CZ37) -> 512.84628 | DA11: =+CV11*(1+DA37) -> 529.94116 | DB11: =SUM(CX11:DA11) -> 2017.1954
A12: Gain from Disposal of Business | C12: 0 | D12: 0 | E12: =F12-SUM(C12:D12) -> 0 | F12: 0 | V12: 0 | W12: 0 | X12: 0 | Y12: =Z12-SUM(V12:X12) -> 0 | Z12: 0 | AA12: 0 | AB12: 0 | AC12: -14.388 | AD12: =AE12-SUM(AA12:AC12) -> 0 | AE12: -14.388 | AF12: 0 | AG12: 0 | AH12: 0 | AI12: =AJ12-SUM(AF12:AH12) -> 0 | AJ12: 0 | AK12: 0 | AL12: 0 | AM12: 0 | AN12: =AO12-SUM(AK12:AM12) -> 0 | AO12: 0 | AP12: 0 | AQ12: 0 | AR12: 0 | AS12: =AT12-SUM(AP12:AR12) -> 0 | AT12: 0 | AU12: 0 | AV12: 0 | AW12: 0 | AX12: =AY12-SUM(AU12:AW12) -> 0 | AY12: 0 | AZ12: 0 | BA12: 0 | BB12: 0
A13: Operating Expenses | B13: =+B10+B11 -> 18.677 | C13: =+C10+C11 -> 18.027 | D13: =+D10+D11 -> 20.675 | E13: =+E10+E11 -> 22.849 | F13: =+F10+F11 -> 80.228 | G13: =+G10+G11 -> 28.869 | H13: =+H10+H11 -> 34.827 | I13: =+I10+I11 -> 35.206 | ... DB13: =+DB10+DB11 -> 3451.3268
A14: Operating Income (EBIT) | B14: =+B9-B13 -> -7.282 | C14: =+C9-C13 -> -1.205 | D14: =+D9-D13 -> 4.779 | E14: =+E9-E13 -> 4.373 | F14: =+F9-F13 -> 0.665 | G14: =+G9-G13 -> -6.277 | H14: =+H9-H13 -> -15.472 | I14: =+I9-I13 -> -20.741 | ... DB14: =+DB9-DB13 -> 1553.4149
A15: Interest expense | B15: 0.809 | C15: 0.936 | D15: 1.202 | E15: =F15-SUM(B15:D15) -> 1.272 | F15: 4.219 | G15: 1.01 | H15: 1.203 | I15: 1.177 | J15: =K15-SUM(G15:I15) -> 0.115 | K15: 3.505 | L15: 0.115 | M15: 0.122 | N15: 0.146 | O15: =P15-SUM(L15:N15) -> 0.15 | P15: 0.533 | Q15: 0.183 | R15: 0.218 | S15: 1.477 | T15: =U15-SUM(Q15:S15) -> 2.335 | U15: 4.213 | V15: 2.389 | W15: 2.56 | X15: 2.781 | Y15: =Z15-SUM(V15:X15) -> 2.746 | Z15: 10.476 | AA15: 2.724 | AB15: 2.721 | AC15: 2.672 | AD15: =AE15-SUM(AA15:AC15) -> 2.576 | AE15: 10.693 | AF15: 2.464 | AG15: 4.038 | AH15: 4.27 | AI15: =AJ15-SUM(AF15:AH15) -> 4.31 | AJ15: 15.082 | AK15: 2.073 | AL15: 2.075 | AM15: 2.078 | AN15: =AO15-SUM(AK15:AM15) -> 2.079 | AO15: 8.305 | AP15: 2.087 | AQ15: 2.15 | AR15: 2.33 | AS15: =AT15-SUM(AP15:AR15) -> 2.752 | AT15: 9.319 | AU15: 3.061 | AV15: 3.177 | AW15: 3.252 | AX15: =AY15-SUM(AU15:AW15) -> 3.148 | AY15: 12.638 | AZ15: 3.124 | BA15: 3.127 | BB15: 3.142 | BC15: =BD15-SUM(AZ15:BB15) -> 1.292 | BD15: 10.685 | BE15: 1.005 | BF15: 1.029 | BG15: 1.045 | BH15: =4.069-BE15-BF15-BG15 -> 0.99 | BI15: =SUM(BE15:BH15) -> 4.069 | BJ15: =+'Other Accts'!BJ29 -> 0.963876 | BK15: =+'Other Accts'!BK29 -> 0.722907 | BL15: =+'Other Accts'!BL29 -> 0.48217897 | BM15: =+'Other Accts'!BM29 -> 0.24108948 | BN15: =SUM(BJ15:BM15) -> 2.4100515 | BO15: =+'Other Accts'!BO29 -> 0 | BP15: =+'Other Accts'!BP29 -> 0 | BQ15: =+'Other Accts'!BQ29 -> 0 | BR15: =+'Other Accts'!BR29 -> 0 | BS15: =SUM(BO15:BR15) -> 0 | BT15: =+'Other Accts'!BT29 -> 0 | BU15: =+'Other Accts'!BU29 -> 0 | BV15: =+'Other Accts'!BV29 -> 0 | BW15: =+'Other Accts'!BW29 -> 0 | BX15: =SUM(BT15:BW15) -> 0 | BY15: =+'Other Accts'!BY29 -> 0 | BZ15: =+'Other Accts'!BZ29 -> 0 | CA15: =+'Other Accts'!CA29 -> 0 | CB15: =+'Other Accts'!CB29 -> 0 | CC15: =SUM(BY15:CB15) -> 0 | CD15: =+'Other Accts'!CD29 -> 0 | CE15: =+'Other Accts'!CE29 -> 0 | CF15: =+'Other Accts'!CF29 -> 0 | CG15: =+'Other Accts'!CG29 -> 0 | CH15: =SUM(CD15:CG15) -> 0 | CI15: =+'Other Accts'!CI29 -> 0 | CJ15: =+'Other Accts'!CJ29 -> 0 | CK15: =+'Other Accts'!CK29 -> 0 | CL15: =+'Other Accts'!CL29 -> 0 | CM15: =SUM(CI15:CL15) -> 0 | CN15: =+'Other Accts'!CN29 -> 0 | CO15: =+'Other Accts'!CO29 -> 0 | CP15: =+'Other Accts'!CP29 -> 0 | CQ15: =+'Other Accts'!CQ29 -> 0 | CR15: =SUM(CN15:CQ15) -> 0 | CS15: =+'Other Accts'!CS29 -> 0 | CT15: =+'Other Accts'!CT29 -> 0 | CU15: =+'Other Accts'!CU29 -> 0 | CV15: =+'Other Accts'!CV29 -> 0 | CW15: =SUM(CS15:CV15) -> 0 | CX15: =+'Other Accts'!CX29 -> 0 | CY15: =+'Other Accts'!CY29 -> 0 | CZ15: =+'Other Accts'!CZ29 -> 0 | DA15: =+'Other Accts'!DA29 -> 0 | DB15: =SUM(CX15:DA15) -> 0
A16: Interest income | B16: 0.806 | C16: -1.34 | D16: -0.708 | E16: =F16-SUM(B16:D16) -> 1.124 | F16: -0.118 | G16: 1.8 | H16: 0.322 | I16: -1.81 | J16: =K16-SUM(G16:I16) -> -1.276 | K16: -0.964 | L16: 0 | M16: 0 | N16: 0 | O16: =P16-SUM(L16:N16) -> 0 | P16: 0 | Q16: -1.3 | R16: 0.413 | S16: 0.437 | T16: =U16-SUM(Q16:S16) -> -1.93 | U16: -2.38 | V16: -0.137 | W16: 3.933 | X16: -0.449 | Y16: =Z16-SUM(V16:X16) -> -0.618 | Z16: 2.729 | AA16: -0.453 | AB16: -0.836 | AC16: -0.673 | AD16: =AE16-SUM(AA16:AC16) -> -2.19 | AE16: -4.152 | AF16: -1.987 | AG16: -1.924 | AH16: -1.749 | AI16: =AJ16-SUM(AF16:AH16) -> -1.902 | AJ16: -7.562 | AK16: -1.371 | AL16: -1.585 | AM16: -1.274 | AN16: =AO16-SUM(AK16:AM16) -> -1.151 | AO16: -5.381 | AP16: -0.801 | AQ16: -0.277 | AR16: -0.087 | AS16: =AT16-SUM(AP16:AR16) -> -2.373 | AT16: -3.538 | AU16: -4.585 | AV16: -4.518 | AW16: -5.406 | AX16: =AY16-SUM(AU16:AW16) -> -9.844 | AY16: -24.353 | AZ16: -10.267 | BA16: -10.457 | BB16: -11.618 | BC16: =BD16-SUM(AZ16:BB16) -> -10.906 | BD16: -43.248 | BE16: -13.419 | BF16: -10.738 | BG16: -11.284 | BH16: =-45.891-BE16-BF16-BG16 -> -10.45 | BI16: =SUM(BE16:BH16) -> -45.891 | BJ16: =-'Other Accts'!BJ9 -> -10.22333 | BK16: =-'Other Accts'!BK9 -> -10.614898 | BL16: =-'Other Accts'!BL9 -> -10.033068 | BM16: =-'Other Accts'!BM9 -> -9.6184711 | BN16: =SUM(BJ16:BM16) -> -40.489767 | BO16: =-'Other Accts'!BO9 -> -6.3830883 | BP16: =-'Other Accts'!BP9 -> -5.2179704 | BQ16: =-'Other Accts'!BQ9 -> -5.1821643 | BR16: =-'Other Accts'!BR9 -> -5.2327732 | BS16: =SUM(BO16:BR16) -> -22.015996 | BT16: =-'Other Accts'!BT9 -> -5.3611132 | BU16: =-'Other Accts'!BU9 -> -5.7114312 | BV16: =-'Other Accts'!BV9 -> -5.9356431 | BW16: =-'Other Accts'!BW9 -> -6.2588073 | BX16: =SUM(BT16:BW16) -> -23.266995 | BY16: =-'Other Accts'!BY9 -> -6.6850077 | BZ16: =-'Other Accts'!BZ9 -> -7.3697465 | CA16: =-'Other Accts'!CA9 -> -7.890946 | CB16: =-'Other Accts'!CB9 -> -8.5408551 | CC16: =SUM(BY16:CB16) -> -30.486555 | CD16: =-'Other Accts'!CD9 -> -9.2911588 | CE16: =-'Other Accts'!CE9 -> -10.346495 | CF16: =-'Other Accts'!CF9 -> -11.228513 | CG16: =-'Other Accts'!CG9 -> -12.247067 | CH16: =SUM(CD16:CG16) -> -43.113233 | CI16: =-'Other Accts'!CI9 -> -13.385813 | CJ16: =-'Other Accts'!CJ9 -> -14.826104 | CK16: =-'Other Accts'!CK9 -> -16.051993 | CL16: =-'Other Accts'!CL9 -> -17.408031 | CM16: =SUM(CI16:CL16) -> -61.671941 | CN16: =-'Other Accts'!CN9 -> -18.872947 | CO16: =-'Other Accts'!CO9 -> -20.664821 | CP16: =-'Other Accts'!CP9 -> -22.221129 | CQ16: =-'Other Accts'!CQ9 -> -23.918632 | CR16: =SUM(CN16:CQ16) -> -85.67753 | CS16: =-'Other Accts'!CS9 -> -25.732807 | CT16: =-'Other Accts'!CT9 -> -27.901556 | CU16: =-'Other Accts'!CU9 -> -29.815495 | CV16: =-'Other Accts'!CV9 -> -31.884841 | CW16: =SUM(CS16:CV16) -> -115.3347 | CX16: =-'Other Accts'!CX9 -> -34.081299 | CY16: =-'Other Accts'!CY9 -> -36.590082 | CZ16: =-'Other Accts'!CZ9 -> -38.803301 | DA16: =-'Other Accts'!DA9 -> -41.164611 | DB16: =SUM(CX16:DA16) -> -150.63929
A17: Other expense, net | B17: 0.719 | C17: -0.287 | D17: 0.561 | E17: =F17-SUM(B17:D17) -> 0.723 | F17: 1.716 | G17: 0.917 | H17: 2.684 | I17: -2.478 | J17: =K17-SUM(G17:I17) -> 6.773 | K17: 7.896 | L17: -1.035 | M17: 0.519 | N17: -0.887 | O17: =P17-SUM(L17:N17) -> 0.005 | P17: -1.398 | Q17: 0 | R17: 0 | S17: 0 | T17: =U17-SUM(Q17:S17) -> 0 | U17: 0 | V17: 0 | W17: 0 | X17: 0 | Y17: =Z17-SUM(V17:X17) -> 0 | Z17: 0 | AA17: 0 | AB17: 0 | AC17: 0 | AD17: =AE17-SUM(AA17:AC17) -> 0 | AE17: 0 | AF17: 0 | AG17: 5.848 | AH17: 0 | AI17: =AJ17-SUM(AF17:AH17) -> 0 | AJ17: 5.848 | AK17: 0 | AL17: 0 | AM17: 0 | AN17: =AO17-SUM(AK17:AM17) -> 0 | AO17: 0 | AP17: 0 | AQ17: 0 | AR17: 0 | AS17: =AT17-SUM(AP17:AR17) -> 0 | AT17: 0 | AU17: 0 | AV17: 0 | AW17: 0 | AX17: =AY17-SUM(AU17:AW17) -> 0 | AY17: 0 | AZ17: 0 | BA17: 0 | BB17: 0 | BC17: =BD17-SUM(AZ17:BB17) -> 0 | BD17: 0 | BE17: 0 | BF17: 0 | BG17: 0 | BH17: =0-BE17-BF17-BG17 -> 0 | BI17: =SUM(BE17:BH17) -> 0 | BJ17: 0 | BK17: 0 | BL17: 0 | BM17: 0 | BN17: =SUM(BJ17:BM17) -> 0 | BO17: 0 | BP17: 0 | BQ17: 0 | BR17: 0 | BS17: =SUM(BO17:BR17) -> 0 | BT17: 0 | BU17: 0 | BV17: 0 | BW17: 0 | BX17: =SUM(BT17:BW17) -> 0 | BY17: 0 | BZ17: 0 | CA17: 0 | CB17: 0 | CC17: =SUM(BY17:CB17) -> 0 | CD17: 0 | CE17: 0 | CF17: 0 | CG17: 0 | CH17: =SUM(CD17:CG17) -> 0 | CI17: 0 | CJ17: 0 | CK17: 0 | CL17: 0 | CM17: =SUM(CI17:CL17) -> 0 | CN17: 0 | CO17: 0 | CP17: 0 | CQ17: 0 | CR17: =SUM(CN17:CQ17) -> 0 | CS17: 0 | CT17: 0 | CU17: 0 | CV17: 0 | CW17: =SUM(CS17:CV17) -> 0 | CX17: 0 | CY17: 0 | CZ17: 0 | DA17: 0 | DB17: =SUM(CX17:DA17) -> 0
A18: Income Before Taxes | B18: =+B14-B15-B16-B17 -> -9.616 | C18: =+C14-C15-C16-C17 -> -0.514 | D18: =+D14-D15-D16-D17 -> 3.724 | E18: =+E14-E15-E16-E17 -> 1.254 | F18: =+F14-F15-F16-F17 -> -5.152 | G18: =+G14-G15-G16-G17 -> -10.004 | H18: =+H14-H15-H16-H17 -> -19.681 | I18: =+I14-I15-I16-I17 -> -17.63 | ... DB18: =+DB14-DB15-DB16-DB17 -> 1704.0542
A19: Income Tax | B19: 0 | C19: 0 | D19: 0 | E19: =F19-SUM(B19:D19) -> 0 | F19: 0 | G19: 0 | H19: 0 | I19: 0 | J19: =K19-SUM(G19:I19) -> 0 | K19: 0 | L19: 0 | M19: 0 | N19: 0.103 | O19: =P19-SUM(L19:N19) -> 0.039 | P19: 0.142 | Q19: 0.047 | R19: 0.064 | S19: 0.162 | T19: =U19-SUM(Q19:S19) -> 0.181 | U19: 0.454 | V19: 0.104 | W19: 0.113 | X19: 0.118 | Y19: =Z19-SUM(V19:X19) -> -0.014 | Z19: 0.321 | AA19: 0.074 | AB19: 1.895 | AC19: 0.044 | AD19: =AE19-SUM(AA19:AC19) -> -0.014 | AE19: 1.999 | AF19: 0.023 | AG19: 0.015 | AH19: 0.025 | AI19: =AJ19-SUM(AF19:AH19) -> 0.035 | AJ19: 0.098 | AK19: 0.134 | AL19: 0.242 | AM19: 0.272 | AN19: =AO19-SUM(AK19:AM19) -> -0.03 | AO19: 0.618 | AP19: 0.179 | AQ19: 0.193 | AR19: 0.185 | AS19: =AT19-SUM(AP19:AR19) -> 0.421 | AT19: 0.978 | AU19: 0.16 | AV19: -0.282 | AW19: 0.202 | AX19: =AY19-SUM(AU19:AW19) -> 0.191 | AY19: 0.271 | AZ19: 0.428 | BA19: 0.892 | BB19: 0.73 | BC19: =BD19-SUM(AZ19:BB19) -> -1.355 | BD19: 0.695 | BE19: 0.173 | BF19: 0.275 | BG19: 0.207 | BH19: =-59.929-BE19-BF19-BG19 -> -60.584 | BI19: =SUM(BE19:BH19) -> -59.929 | BJ19: =+BJ20*BJ18 -> 0 | BK19: =+BK20*BK18 -> 0 | BL19: =+BL20*BL18 -> 0 | BM19: =+BM20*BM18 -> 0 | BN19: =SUM(BJ19:BM19) -> 0 | BO19: =+BO20*BO18 -> 0 | BP19: =+BP20*BP18 -> 0 | BQ19: =+BQ20*BQ18 -> 0 | BR19: =+BR20*BR18 -> 0 | BS19: =SUM(BO19:BR19) -> 0 | BT19: =+BT20*BT18 -> 0 | BU19: =+BU20*BU18 -> 0 | BV19: =+BV20*BV18 -> 0 | BW19: =+BW20*BW18 -> 0 | BX19: =SUM(BT19:BW19) -> 0 | BY19: =+BY20*BY18 -> 0 | BZ19: =+BZ20*BZ18 -> 0 | CA19: =+CA20*CA18 -> 0 | CB19: =+CB20*CB18 -> 0 | CC19: =SUM(BY19:CB19) -> 0 | CD19: =+CD20*CD18 -> 0 | CE19: =+CE20*CE18 -> 0 | CF19: =+CF20*CF18 -> 0 | CG19: =+CG20*CG18 -> 0 | CH19: =SUM(CD19:CG19) -> 0 | CI19: =+CI20*CI18 -> 0 | CJ19: =+CJ20*CJ18 -> 0 | CK19: =+CK20*CK18 -> 0 | CL19: =+CL20*CL18 -> 0 | CM19: =SUM(CI19:CL19) -> 0 | CN19: =+CN20*CN18 -> 0 | CO19: =+CO20*CO18 -> 0 | CP19: =+CP20*CP18 -> 0 | CQ19: =+CQ20*CQ18 -> 0 | CR19: =SUM(CN19:CQ19) -> 0 | CS19: =+CS20*CS18 -> 0 | CT19: =+CT20*CT18 -> 0 | CU19: =+CU20*CU18 -> 0 | CV19: =+CV20*CV18 -> 0 | CW19: =SUM(CS19:CV19) -> 0 | CX19: =+CX20*CX18 -> 0 | CY19: =+CY20*CY18 -> 0 | CZ19: =+CZ20*CZ18 -> 0 | DA19: =+DA20*DA18 -> 0 | DB19: =SUM(CX19:DA19) -> 0 | DD19: =SUM(BX19,CC19,CH19,CM19,CR19,CW19,DB19) -> 0
A20: Tax Rate | B20: =+B19/B18 -> 0 | C20: =+C19/C18 -> 0 | D20: =+D19/D18 -> 0 | E20: =+E19/E18 -> 0 | F20: =+F19/F18 -> 0 | G20: =+G19/G18 -> 0 | H20: =+H19/H18 -> 0 | I20: =+I19/I18 -> 0 | ... BI20: =+BI19/BI18 -> 0.22354144 | BJ20: 0 | BK20: 0 | BL20: 0 | BM20: 0 | BN20: =+BN19/BN18 -> 0 | BO20: 0 | BP20: 0 | BQ20: 0 | BR20: 0 | BS20: =+BS19/BS18 -> 0 | BT20: =BX20 -> 0 | BU20: =BX20 -> 0 | BV20: =BX20 -> 0 | BW20: =BX20 -> 0 | BX20: 0 | BY20: =CC20 -> 0 | BZ20: =CC20 -> 0 | CA20: =CC20 -> 0 | CB20: =CC20 -> 0 | CC20: 0 | CD20: =CH20 -> 0 | CE20: =CH20 -> 0 | CF20: =CH20 -> 0 | CG20: =CH20 -> 0 | CH20: 0 | CI20: =CM20 -> 0 | CJ20: =CM20 -> 0 | CK20: =CM20 -> 0 | CL20: =CM20 -> 0 | CM20: 0 | CN20: =CR20 -> 0 | CO20: =CR20 -> 0 | CP20: =CR20 -> 0 | CQ20: =CR20 -> 0 | CR20: 0 | CS20: =CW20 -> 0 | CT20: =CW20 -> 0 | CU20: =CW20 -> 0 | CV20: =CW20 -> 0 | CW20: 0 | CX20: =DB20 -> 0 | CY20: =DB20 -> 0 | CZ20: =DB20 -> 0 | DA20: =DB20 -> 0 | DB20: 0
A21: Net Loss | B21: =+B18-B19 -> -9.616 | C21: =+C18-C19 -> -0.514 | D21: =+D18-D19 -> 3.724 | E21: =+E18-E19 -> 1.254 | F21: =+F18-F19 -> -5.152 | G21: =+G18-G19 -> -10.004 | H21: =+H18-H19 -> -19.681 | I21: =+I18-I19 -> -17.63 | ... DB21: =+DB18-DB19 -> 1704.0542
A22: Unrealized Gain on AFS Securities | B22: 0 | C22: 0 | D22: =2.552+1 -> 3.552 | E22: =F22-SUM(B22:D22) -> -3.552 | F22: 0 | G22: 0 | H22: 0 | I22: -0.036 | J22: =1.416-G22-H22-I22 -> 1.452 | K22: =+G22+H22+I22+J22 -> 1.416 | L22: -1.811 | M22: -0.548 | N22: 0.609 | O22: =-0.691-L22-M22-N22 -> 1.059 | P22: =+L22+M22+N22+O22 -> -0.691 | Q22: -0.2 | R22: -0.062 | S22: -0.067 | T22: =U22-SUM(Q22:S22) -> 0.37 | U22: 0.041 | V22: 0.138 | W22: -0.046 | X22: 0.036 | Y22: =Z22-SUM(V22:X22) -> -0.342 | Z22: -0.214 | AA22: -0.286 | AB22: -1.061 | AC22: -0.063 | AD22: =AE22-SUM(AA22:AC22) -> -0.061 | AE22: -1.471 | AF22: -4.747 | AG22: -0.104 | AH22: 0.6 | AI22: =AJ22-SUM(AF22:AH22) -> 0.911 | AJ22: -3.34 | AK22: 1.062 | AL22: 0.756 | AM22: 0.95 | AN22: =AO22-SUM(AK22:AM22) -> 3.778 | AO22: 6.546 | AP22: 11.617 | AQ22: 2.493 | AR22: 3.212 | AS22: =AT22-SUM(AP22:AR22) -> -3.247 | AT22: =--14.075 -> 14.075 | AU22: -4.564 | AV22: -2.595 | AW22: -3.807 | AX22: =AY22-SUM(AU22:AW22) -> -2.311 | AY22: -13.277 | AZ22: -0.893 | BA22: -0.834 | BB22: -0.593 | BC22: =BD22-SUM(AZ22:BB22) -> -0.421 | BD22: -2.741 | BE22: -0.147 | BF22: 0.09 | BG22: -0.1 | BH22: =-0.086-BE22-BF22-BG22 -> 0.071 | BI22: =+BE22+BF22+BG22+BH22 -> -0.086 | BJ22: -0.1 | BK22: -0.1 | BL22: -0.1 | BM22: -0.1 | BN22: =+BJ22+BK22+BL22+BM22 -> -0.4 | BO22: -0.1 | BP22: -0.1 | BQ22: -0.1 | BR22: -0.1 | BS22: =+BO22+BP22+BQ22+BR22 -> -0.4 | BT22: -0.1 | BU22: -0.1 | BV22: -0.1 | BW22: -0.1 | BX22: =+BT22+BU22+BV22+BW22 -> -0.4 | BY22: -0.1 | BZ22: -0.1 | CA22: -0.1 | CB22: -0.1 | CC22: =+BY22+BZ22+CA22+CB22 -> -0.4 | CD22: -0.1 | CE22: -0.1 | CF22: -0.1 | CG22: -0.1 | CH22: =+CD22+CE22+CF22+CG22 -> -0.4 | CI22: -0.1 | CJ22: -0.1 | CK22: -0.1 | CL22: -0.1 | CM22: =+CI22+CJ22+CK22+CL22 -> -0.4 | CN22: -0.1 | CO22: -0.1 | CP22: -0.1 | CQ22: -0.1 | CR22: =+CN22+CO22+CP22+CQ22 -> -0.4 | CS22: -0.1 | CT22: -0.1 | CU22: -0.1 | CV22: -0.1 | CW22: =+CS22+CT22+CU22+CV22 -> -0.4 | CX22: -0.1 | CY22: -0.1 | CZ22: -0.1 | DA22: -0.1 | DB22: =+CX22+CY22+CZ22+DA22 -> -0.4
A23: Comprehensive Loss | B23: =+B21-B22 -> -9.616 | C23: =+C21-C22 -> -0.514 | D23: =+D21-D22 -> 0.172 | E23: =+E21-E22 -> 4.806 | F23: =+F21-F22 -> -5.152 | G23: =+G21-G22 -> -10.004 | H23: =+H21-H22 -> -19.681 | I23: =+I21-I22 -> -17.594 | ... DB23: =+DB21-DB22 -> 1704.4542
A25: Basic shares outstanding | B25: 4.591 | C25: 4.722 | D25: 4.866 | E25: =F25*4-SUM(B25:D25) -> 5.021 | F25: 4.8 | G25: 5.289 | H25: 5.494 | I25: 44.944 | J25: =K25*4-SUM(G25:I25) -> 49.089 | K25: 26.204 | L25: 50.439 | M25: 51.445 | N25: 52.012 | O25: =P25*4-SUM(L25:N25) -> 52.408 | P25: 51.576 | Q25: 52.758 | R25: 53.088 | S25: 53.447 | T25: =U25*4-SUM(Q25:S25) -> 53.955 | U25: 53.312 | V25: 54.132 | W25: 54.551 | X25: 60.57 | Y25: =Z25*4-SUM(V25:X25) -> 62.139 | Z25: 57.848 | AA25: 62.831 | AB25: 68.224 | AC25: 70.456 | AD25: =AE25*4-SUM(AA25:AC25) -> 76.709 | AE25: 69.555 | AF25: 78.287 | AG25: 79.069 | AH25: 80.908 | AI25: =AJ25*4-SUM(AF25:AH25) -> 85.78 | AJ25: 81.011 | AK25: 86.689 | AL25: 88.077 | AM25: 92.558 | AN25: =AO25*4-SUM(AK25:AM25) -> 94.908 | AO25: 90.558 | AP25: 95.578 | AQ25: 96.579 | AR25: 97.052 | AS25: =AT25*4-SUM(AP25:AR25) -> 104.423 | AT25: 98.408 | AU25: 111.767 | AV25: 113.69 | AW25: 115.171 | AX25: =AY25*4-SUM(AU25:AW25) -> 119.36 | AY25: 114.997 | AZ25: 120.814 | BA25: 122.853 | BB25: 123.775 | BC25: =BD25*4-SUM(AZ25:BB25) -> 131.43 | BD25: 124.718 | BE25: 134.75 | BF25: 136.388 | BG25: 137.187 | BH25: =BI25*4-SUM(BE25:BG25) -> 138.559 | BI25: 136.721 | BJ25: =BH25+BS!BJ55-BS!BJ56 -> 139.59819 | BK25: =BJ25+BS!BK55-BS!BK56 -> 140.63738 | BL25: =BK25+BS!BL55-BS!BL56 -> 141.67658 | BM25: =BL25+BS!BM55-BS!BM56 -> 142.71577 | BN25: =AVERAGE(BJ25:BM25) -> 141.15698 | BO25: =BM25+BS!BO55-BS!BO56 -> 143.78614 | BP25: =BO25+BS!BP55-BS!BP56 -> 144.85651 | BQ25: =BP25+BS!BQ55-BS!BQ56 -> 145.92687 | BR25: =BQ25+BS!BR55-BS!BR56 -> 146.99724 | BS25: =AVERAGE(BO25:BR25) -> 145.39169 | BT25: =BR25+BS!BT55-BS!BT56 -> 148.09972 | BU25: =BT25+BS!BU55-BS!BU56 -> 149.2022 | BV25: =BU25+BS!BV55-BS!BV56 -> 150.30468 | BW25: =BV25+BS!BW55-BS!BW56 -> 151.40716 | BX25: =AVERAGE(BT25:BW25) -> 149.75344 | BY25: =BW25+BS!BY55-BS!BY56 -> 152.54271 | BZ25: =BY25+BS!BZ55-BS!BZ56 -> 153.67827 | CA25: =BZ25+BS!CA55-BS!CA56 -> 154.81382 | CB25: =CA25+BS!CB55-BS!CB56 -> 155.94938 | CC25: =AVERAGE(BY25:CB25) -> 154.24604 | CD25: =CB25+BS!CD55-BS!CD56 -> 157.119 | CE25: =CD25+BS!CE55-BS!CE56 -> 158.28862 | CF25: =CE25+BS!CF55-BS!CF56 -> 159.45824 | CG25: =CF25+BS!CG55-BS!CG56 -> 160.62786 | CH25: =AVERAGE(CD25:CG25) -> 158.87343 | CI25: =CG25+BS!CI55-BS!CI56 -> 161.83257 | CJ25: =CI25+BS!CJ55-BS!CJ56 -> 163.03727 | CK25: =CJ25+BS!CK55-BS!CK56 -> 164.24198 | CL25: =CK25+BS!CL55-BS!CL56 -> 165.44669 | CM25: =AVERAGE(CI25:CL25) -> 163.63963 | CN25: =CL25+BS!CN55-BS!CN56 -> 166.68754 | CO25: =CN25+BS!CO55-BS!CO56 -> 167.92839 | CP25: =CO25+BS!CP55-BS!CP56 -> 169.16924 | CQ25: =CP25+BS!CQ55-BS!CQ56 -> 170.41009 | CR25: =AVERAGE(CN25:CQ25) -> 168.54882 | CS25: =CQ25+BS!CS55-BS!CS56 -> 171.68817 | CT25: =CS25+BS!CT55-BS!CT56 -> 172.96624 | CU25: =CT25+BS!CU55-BS!CU56 -> 174.24432 | CV25: =CU25+BS!CV55-BS!CV56 -> 175.5224 | CW25: =AVERAGE(CS25:CV25) -> 173.60528 | CX25: =CV25+BS!CX55-BS!CX56 -> 176.83881 | CY25: =CX25+BS!CY55-BS!CY56 -> 178.15523 | CZ25: =CY25+BS!CZ55-BS!CZ56 -> 179.47165 | DA25: =CZ25+BS!DA55-BS!DA56 -> 180.78807 | DB25: =AVERAGE(CX25:DA25) -> 178.81344 | DE25: 404 | DF25: 628 | DG25: 675 | DH25: 724 | DI25: 740 | DJ25: 752 | DK25: 801
A26: Diluted shares outstanding | B26: 4.591 | C26: 4.722 | D26: 36.931 | E26: =F26*4-SUM(B26:D26) -> -27.044 | F26: 4.8 | G26: 5.289 | H26: 5.494 | I26: 44.944 | J26: =K26*4-SUM(G26:I26) -> 49.089 | K26: 26.204 | L26: 50.439 | M26: 51.445 | N26: 52.012 | O26: =P26*4-SUM(L26:N26) -> 52.408 | P26: 51.576 | Q26: 53.043 | R26: 53.088 | S26: 53.447 | T26: =U26*4-SUM(Q26:S26) -> 54.838 | U26: 53.604 | V26: 54.132 | W26: 54.551 | X26: 60.57 | Y26: =Z26*4-SUM(V26:X26) -> 62.139 | Z26: 57.848 | AA26: 62.831 | AB26: 68.224 | AC26: 70.456 | AD26: =AE26*4-SUM(AA26:AC26) -> 76.709 | AE26: 69.555 | AF26: 78.287 | AG26: 79.069 | AH26: 80.908 | AI26: =AJ26*4-SUM(AF26:AH26) -> 85.78 | AJ26: 81.011 | AK26: 86.689 | AL26: 88.077 | AM26: 92.558 | AN26: =AO26*4-SUM(AK26:AM26) -> 94.908 | AO26: 90.558 | AP26: 95.578 | AQ26: 96.579 | AR26: 97.052 | AS26: =AT26*4-SUM(AP26:AR26) -> 104.423 | AT26: 98.408 | AU26: 111.767 | AV26: 113.69 | AW26: 115.171 | AX26: =AY26*4-SUM(AU26:AW26) -> 119.36 | AY26: 114.997 | AZ26: 120.814 | BA26: 122.853 | BB26: 123.775 | BC26: =BD26*4-SUM(AZ26:BB26) -> 131.43 | BD26: 124.718 | BE26: 134.75 | BF26: 136.388 | BG26: 137.187 | BH26: =BI26*4-SUM(BE26:BG26) -> 138.559 | BI26: 136.721 | BJ26: =BH26+BS!BJ55-BS!BJ56 -> 139.59819 | BK26: =BJ26+BS!BK55-BS!BK56 -> 140.63738 | BL26: =BK26+BS!BL55-BS!BL56 -> 141.67658 | BM26: =BL26+BS!BM55-BS!BM56 -> 142.71577 | BN26: =AVERAGE(BJ26:BM26) -> 141.15698 | BO26: =BM26+BS!BO55-BS!BO56 -> 143.78614 | BP26: =BO26+BS!BP55-BS!BP56 -> 144.85651 | BQ26: =BP26+BS!BQ55-BS!BQ56 -> 145.92687 | BR26: =BQ26+BS!BR55-BS!BR56 -> 146.99724 | BS26: =AVERAGE(BO26:BR26) -> 145.39169 | BT26: =BR26+BS!BT55-BS!BT56 -> 148.09972 | BU26: =BT26+BS!BU55-BS!BU56 -> 149.2022 | BV26: =BU26+BS!BV55-BS!BV56 -> 150.30468 | BW26: =BV26+BS!BW55-BS!BW56 -> 151.40716 | BX26: =AVERAGE(BT26:BW26) -> 149.75344 | BY26: =BW26+BS!BY55-BS!BY56 -> 152.54271 | BZ26: =BY26+BS!BZ55-BS!BZ56 -> 153.67827 | CA26: =BZ26+BS!CA55-BS!CA56 -> 154.81382 | CB26: =CA26+BS!CB55-BS!CB56 -> 155.94938 | CC26: =AVERAGE(BY26:CB26) -> 154.24604 | CD26: =CB26+BS!CD55-BS!CD56 -> 157.119 | CE26: =CD26+BS!CE55-BS!CE56 -> 158.28862 | CF26: =CE26+BS!CF55-BS!CF56 -> 159.45824 | CG26: =CF26+BS!CG55-BS!CG56 -> 160.62786 | CH26: =AVERAGE(CD26:CG26) -> 158.87343 | CI26: =CG26+BS!CI55-BS!CI56 -> 161.83257 | CJ26: =CI26+BS!CJ55-BS!CJ56 -> 163.03727 | CK26: =CJ26+BS!CK55-BS!CK56 -> 164.24198 | CL26: =CK26+BS!CL55-BS!CL56 -> 165.44669 | CM26: =AVERAGE(CI26:CL26) -> 163.63963 | CN26: =CL26+BS!CN55-BS!CN56 -> 166.68754 | CO26: =CN26+BS!CO55-BS!CO56 -> 167.92839 | CP26: =CO26+BS!CP55-BS!CP56 -> 169.16924 | CQ26: =CP26+BS!CQ55-BS!CQ56 -> 170.41009 | CR26: =AVERAGE(CN26:CQ26) -> 168.54882 | CS26: =CQ26+BS!CS55-BS!CS56 -> 171.68817 | CT26: =CS26+BS!CT55-BS!CT56 -> 172.96624 | CU26: =CT26+BS!CU55-BS!CU56 -> 174.24432 | CV26: =CU26+BS!CV55-BS!CV56 -> 175.5224 | CW26: =AVERAGE(CS26:CV26) -> 173.60528 | CX26: =CV26+BS!CX55-BS!CX56 -> 176.83881 | CY26: =CX26+BS!CY55-BS!CY56 -> 178.15523 | CZ26: =CY26+BS!CZ55-BS!CZ56 -> 179.47165 | DA26: =CZ26+BS!DA55-BS!DA56 -> 180.78807 | DB26: =AVERAGE(CX26:DA26) -> 178.81344 | DF26: =+DF25/DE25-1 -> 0.55445545 | DG26: =+DG25/DF25-1 -> 0.074840764 | DH26: =+DH25/DG25-1 -> 0.072592593 | DI26: =+DI25/DH25-1 -> 0.022099448 | DJ26: =+DJ25/DI25-1 -> 0.016216216 | DK26: =+DK25/DJ25-1 -> 0.065159574
DE27: 841 | DF27: 1105 | DG27: 1204 | DH27: 1278 | DI27: 1336 | DJ27: 1349 | DK27: 1490
A28: GAAP basic E.P.S. | B28: =B23/B25 -> -2.0945328 | C28: =C23/C25 -> -0.10885218 | D28: =D23/D25 -> 0.035347308 | E28: =E23/E25 -> 0.95717984 | F28: =F23/F25 -> -1.0733333 | G28: =G23/G25 -> -1.8914729 | H28: =H23/H25 -> -3.5822716 | I28: =I23/I25 -> -0.39146493 | ... K28: =K23/K25 -> -2.73588 | L28: =L21/L25 -> -0.17218819 | M28: =M21/M25 -> -0.45011177 | N28: =N21/N25 -> -0.50021149 | O28: =O23/O25 -> -0.74351244 | P28: =P21/P25 -> -1.8567745 | Q28: =Q23/Q25 -> -0.67783085 | R28: =R23/R25 -> -0.52121007 | S28: =S21/S25 -> -0.50739985 | T28: =T21/T25 -> -0.84333241 | U28: =U21/U25 -> -2.5569103 | V28: =V21/V25 -> -0.60727481 | W28: =W21/W25 -> -0.62004363 | X28: =X21/X25 -> -0.48895493 | Y28: =Y21/Y25 -> -0.51241571 | Z28: =Z21/Z25 -> -2.2153575 | ... DB28: =DB21/DB25 -> 9.5297881 | DF28: =+DF27/DE27-1 -> 0.31391201 | DG28: =+DG27/DF27-1 -> 0.08959276 | DH28: =+DH27/DG27-1 -> 0.061461794 | DI28: =+DI27/DH27-1 -> 0.045383412 | DJ28: =+DJ27/DI27-1 -> 0.0097305389 | DK28: =+DK27/DJ27-1 -> 0.10452187
A29: GAAP diluted E.P.S. | B29: =B23/B26 -> -2.0945328 | C29: =C23/C26 -> -0.10885218 | D29: =(D23+1)/D26 -> 0.031734857 | E29: =E23/E26 -> -0.1777104 | F29: =F23/F26 -> -1.0733333 | G29: =G23/G26 -> -1.8914729 | H29: =H23/H26 -> -3.5822716 | I29: =I23/I26 -> -0.39146493 | J29: =J23/J26 -> -0.49730082 | K29: =K23/K26 -> -2.73588 | L29: =L21/L26 -> -0.17218819 | M29: =M21/M26 -> -0.45011177 | N29: =N21/N26 -> -0.50021149 | O29: =O23/O26 -> -0.74351244 | P29: =P21/P26 -> -1.8567745 | Q29: =(Q21-1.042)/Q26 -> -0.69760383 | R29: =R23/R26 -> -0.52121007 | S29: =S21/S26 -> -0.50739985 | T29: =(T21-0.106)/T26 -> -0.83168606 | U29: =(U21-1.148)/U26 -> -2.5643982 | V29: =V21/V26 -> -0.60727481 | W29: =W21/W26 -> -0.62004363 | X29: =X21/X26 -> -0.48895493 | Y29: =Y21/Y26 -> -0.51241571 | Z29: =Z21/Z26 -> -2.2153575 | AA29: =AA21/AA26 -> -0.54258248 | AB29: =AB21/AB26 -> -0.47514071 | AC29: =AC21/AC26 -> -0.53260191 | ... DB29: =DB21/DB26 -> 9.5297881
A31: EBITDA | B31: =B14+CF!B9 -> -7.282 | C31: =C14+CF!C9 -> 1.103 | D31: =D14+CF!D9 -> 6.141 | E31: =E14+CF!E9 -> 5.851 | F31: =F14+CF!F9 -> 5.813 | G31: =G14+CF!G9 -> -4.636 | H31: =H14+CF!H9 -> -14.139 | I31: =I14+CF!I9 -> -19.352 | ... DB31: =DB14+CF!DB9 -> 1645.6514
A33: Year-Over-Year
A34: =A7 -> Net Sales | B34: -- | C34: -- | D34: -- | E34: -- | F34: -- | G34: =G7/B7-1 -> 0.73786408 | H34: =H7/C7-1 -> 0.25814823 | I34: =I7/D7-1 -> -0.029238881 | J34: =J7/E7-1 -> 0.060700826 | K34: =K7/F7-1 -> 0.19502916 | L34: =L7/G7-1 -> 0.30498577 | M34: =M7/H7-1 -> 0.15297092 | N34: =N7/I7-1 -> 0.19963937 | ... DB34: =DB7/CW7-1 -> 0.08321302
A35: Gross Profit | B35: -- | C35: -- | D35: -- | E35: -- | F35: -- | G35: =G9/B9-1 -> 0.98262396 | H35: =H9/C9-1 -> 0.15057663 | I35: =I9/D9-1 -> -0.43171997 | J35: =J9/E9-1 -> -0.2249651 | K35: =K9/F9-1 -> -0.041820677 | L35: =L9/G9-1 -> 0.30851629 | M35: =M9/H9-1 -> 0.085559287 | N35: =N9/I9-1 -> 0.35693052 | ... DB35: =DB9/CW9-1 -> 0.08827692
A36: =A10 -> Research & Development | B36: -- | C36: -- | D36: -- | E36: -- | F36: -- | G36: =G10/B10-1 -> 0.30991159 | H36: =H10/C10-1 -> 0.63537118 | I36: =I10/D10-1 -> 0.67795059 | J36: =J10/E10-1 -> 0.77866667 | K36: =K10/F10-1 -> 0.60253296 | L36: =L10/G10-1 -> 0.55577265 | M36: =M10/H10-1 -> 0.52781486 | N36: =N10/I10-1 -> 0.5464831 | ... BN36: =BN10/BI10-1 -> 0.29464357 | BO36: =BS36 -> 0.09 | BP36: =BS36 -> 0.09 | BQ36: =BS36 -> 0.09 | BR36: =BS36 -> 0.09 | BS36: 0.09 | BT36: =BX36 -> 0.08 | BU36: =BX36 -> 0.08 | BV36: =BX36 -> 0.08 | BW36: =BX36 -> 0.08 | BX36: 0.08 | BY36: =CC36 -> 0.075 | BZ36: =CC36 -> 0.075 | CA36: =CC36 -> 0.075 | CB36: =CC36 -> 0.075 | CC36: 0.075 | CD36: =CH36 -> 0.07 | CE36: =CH36 -> 0.07 | CF36: =CH36 -> 0.07 | CG36: =CH36 -> 0.07 | CH36: 0.07 | CI36: =CM36 -> 0.07 | CJ36: =CM36 -> 0.07 | CK36: =CM36 -> 0.07 | CL36: =CM36 -> 0.07 | CM36: 0.07 | CN36: =CR36 -> 0.07 | CO36: =CR36 -> 0.07 | CP36: =CR36 -> 0.07 | CQ36: =CR36 -> 0.07 | CR36: =CM36 -> 0.07 | CS36: =CW36 -> 0.07 | CT36: =CW36 -> 0.07 | CU36: =CW36 -> 0.07 | CV36: =CW36 -> 0.07 | CW36: =CR36 -> 0.07 | CX36: =DB36 -> 0.07 | CY36: =DB36 -> 0.07 | CZ36: =DB36 -> 0.07 | DA36: =DB36 -> 0.07 | DB36: =CW36 -> 0.07
A37: =A11 -> Selling, General & Administrative | B37: -- | C37: -- | D37: -- | E37: -- | F37: -- | G37: =G11/B11-1 -> 0.61617637 | H37: =H11/C11-1 -> 1.019849 | I37: =I11/D11-1 -> 0.70950132 | J37: =J11/E11-1 -> 0.65905499 | K37: =K11/F11-1 -> 0.74203953 | L37: =L11/G11-1 -> 0.30849004 | M37: =M11/H11-1 -> 0.18304493 | N37: =N11/I11-1 -> 0.25360603 | ... BN37: =BN11/BI11-1 -> 0.0008643057 | BO37: =BS37 -> 0.09 | BP37: =BS37 -> 0.09 | BQ37: =BS37 -> 0.09 | BR37: =BS37 -> 0.09 | BS37: 0.09 | BT37: =BX37 -> 0.08 | BU37: =BX37 -> 0.08 | BV37: =BX37 -> 0.08 | BW37: =BX37 -> 0.08 | BX37: 0.08 | BY37: =CC37 -> 0.075 | BZ37: =CC37 -> 0.075 | CA37: =CC37 -> 0.075 | CB37: =CC37 -> 0.075 | CC37: 0.075 | CD37: =CH37 -> 0.07 | CE37: =CH37 -> 0.07 | CF37: =CH37 -> 0.07 | CG37: =CH37 -> 0.07 | CH37: 0.07 | CI37: =CM37 -> 0.06 | CJ37: =CM37 -> 0.06 | CK37: =CM37 -> 0.06 | CL37: =CM37 -> 0.06 | CM37: 0.06 | CN37: =CR37 -> 0.06 | CO37: =CR37 -> 0.06 | CP37: =CR37 -> 0.06 | CQ37: =CR37 -> 0.06 | CR37: 0.06 | CS37: =CW37 -> 0.06 | CT37: =CW37 -> 0.06 | CU37: =CW37 -> 0.06 | CV37: =CW37 -> 0.06 | CW37: 0.06 | CX37: =DB37 -> 0.06 | CY37: =DB37 -> 0.06 | CZ37: =DB37 -> 0.06 | DA37: =DB37 -> 0.06 | DB37: 0.06
A38: Operating Expenses | B38: -- | C38: -- | D38: -- | E38: -- | F38: -- | G38: =G13/B13-1 -> 0.54569792 | H38: =H13/C13-1 -> 0.93193543 | I38: =I13/D13-1 -> 0.7028295 | J38: =J13/E13-1 -> 0.68261193 | K38: =K13/F13-1 -> 0.71197088 | L38: =L13/G13-1 -> 0.35671482 | M38: =M13/H13-1 -> 0.24977747 | N38: =N13/I13-1 -> 0.31463387 | ... DB38: =DB13/CW13-1 -> 0.064132519
A39: Operating Income (EBIT) | B39: -- | C39: -- | D39: -- | E39: -- | F39: -- | G39: =G14/B14-1 -> -0.13801154 | H39: =H14/C14-1 -> 11.839834 | I39: =I14/D14-1 -> -5.3400293 | J39: =J14/E14-1 -> -4.9670707 | K39: =K14/F14-1 -> -90.981955 | L39: =L14/G14-1 -> 0.53018958 | M39: =M14/H14-1 -> 0.45520941 | N39: =N14/I14-1 -> 0.28513572 | ... DB39: =DB14/CW14-1 -> 0.14604964
A40: EBITDA | B40: -- | C40: -- | D40: -- | E40: -- | F40: -- | G40: =G31/B31-1 -> -0.36336171 | H40: =H31/C31-1 -> -13.818676 | I40: =I31/D31-1 -> -4.1512783 | J40: =J31/E31-1 -> -3.7646556 | K40: =K31/F31-1 -> -10.341648 | L40: =L31/G31-1 -> 0.81427955 | M40: =M31/H31-1 -> 0.50512766 | N40: =N31/I31-1 -> 0.28699876 | ... DB40: =DB31/CW31-1 -> 0.14038395
A41: =A18 -> Income Before Taxes | B41: -- | C41: -- | D41: -- | E41: -- | F41: -- | G41: =G18/B18-1 -> 0.040349418 | H41: =H18/C18-1 -> 37.289883 | I41: =I18/D18-1 -> -5.7341568 | J41: =J18/E18-1 -> -19.30941 | K41: =K18/F18-1 -> 12.640334 | L41: =L18/G18-1 -> -0.13184726 | M41: =M18/H18-1 -> 0.17656623 | N41: =N18/I18-1 -> 0.46988088 | ... DB41: =DB18/CW18-1 -> 0.15860075
A42: Net Loss | B42: -- | C42: -- | D42: -- | E42: -- | F42: -- | G42: =G21/B21-1 -> 0.040349418 | H42: =H21/C21-1 -> 37.289883 | I42: =I21/D21-1 -> -5.7341568 | J42: =J21/E21-1 -> -19.30941 | K42: =K21/F21-1 -> 12.640334 | L42: =L21/G21-1 -> -0.13184726 | M42: =M21/H21-1 -> 0.17656623 | N42: =N21/I21-1 -> 0.4757232 | ... DB42: =DB21/CW21-1 -> 0.15860075
A43: Comprehesive Loss | B43: -- | C43: -- | D43: -- | E43: -- | F43: -- | G43: =G23/B23-1 -> 0.040349418 | H43: =H23/C23-1 -> 37.289883 | I43: =I23/D23-1 -> -103.2907 | J43: =J23/E23-1 -> -6.079484 | K43: =K23/F23-1 -> 12.915179 | L43: =L23/G23-1 -> -0.31287485 | M43: =M23/H23-1 -> 0.14872212 | N43: =N23/I23-1 -> 0.51335683 | ... DB43: =DB23/CW23-1 -> 0.15855762
A45: GAAP diluted EPS | B45: -- | C45: -- | D45: -- | E45: -- | F45: -- | G45: =G29/B29-1 -> -0.096947594 | H45: =H29/C29-1 -> 31.909507 | I45: =I29/D29-1 -> -13.335488 | J45: =J29/E29-1 -> 1.7983777 | K45: =K29/F29-1 -> 1.5489565 | L45: =L29/G29-1 -> -0.90896608 | M45: =M29/H29-1 -> -0.87435018 | N45: =N29/I29-1 -> 0.27779386 | ... DB45: =DB29/CW29-1 -> 0.12485509
A47: % of Revenue | BJ47: =BJ53*100 -> -14.909105 | BK47: =BK53*100 -> -11.859306 | BL47: =BL53*100 -> -9.5984131 | BM47: =BM53*100 -> -5.2458713
A48: Gross margin | B48: =B9/B$7 -> 0.41747573 | C48: =C9/C$7 -> 0.46941623 | D48: =D9/D$7 -> 0.55007131 | E48: =E9/E$7 -> 0.54570604 | F48: =F9/F$7 -> 0.50783795 | G48: =G9/G$7 -> 0.47627279 | H48: =H9/H$7 -> 0.42928117 | I48: =I9/I$7 -> 0.32200975 | ... DB48: =DB9/DB$7 -> 0.71932385
A49: Margin Chg yoy | B49: -- | C49: -- | D49: -- | E49: -- | F49: -- | G49: =+(G48-B48)*10000 -> 587.97066 | H49: =+(H48-C48)*10000 -> -401.35062 | I49: =+(I48-D48)*10000 -> -2280.6156 | J49: =+(J48-E48)*10000 -> -1469.6851 | K49: =+(K48-F48)*10000 -> -1006.5138 | L49: =+(L48-G48)*10000 -> 12.885122 | M49: =+(M48-H48)*10000 -> -250.99112 | N49: =+(N48-I48)*10000 -> 422.20426 | ... DB49: =+(DB48-CW48)*10000 -> 33.471113
A50: Research & Development | B50: =B10/B$7 -> 0.15746474 | C50: =C10/C$7 -> 0.115024 | D50: =D10/D$7 -> 0.094480702 | E50: =E10/E$7 -> 0.090209286 | F50: =F10/F$7 -> 0.1085574 | G50: =G10/G$7 -> 0.11868873 | H50: =H10/H$7 -> 0.14951095 | I50: =I10/I$7 -> 0.16330892 | ... DB50: =DB10/DB$7 -> 0.20612552
A51: =A11 -> Selling, General & Administrative | B51: =B11/B$7 -> 0.52679978 | C51: =C11/C$7 -> 0.38801764 | D51: =D11/D$7 -> 0.35231447 | E51: =E11/E$7 -> 0.36783337 | F51: =F11/F$7 -> 0.39510575 | G51: =G11/G$7 -> 0.48991251 | H51: =H11/H$7 -> 0.622929 | I51: =I11/I$7 -> 0.62042252 | ... DB51: =DB11/DB$7 -> 0.2899284
A52: Operating Expenses | B52: =B13/B7 -> 0.68426452 | C52: =C13/C7 -> 0.50304163 | D52: =D13/D7 -> 0.44679518 | E52: =E13/E7 -> 0.45804266 | F52: =F13/F7 -> 0.50366315 | G52: =G13/G7 -> 0.60860124 | H52: =H13/H7 -> 0.77243995 | I52: =I13/I7 -> 0.78373144 | ... DB52: =DB13/DB7 -> 0.49605391
A53: Operating Income | B53: =B14/B7 -> -0.26678879 | C53: =C14/C7 -> -0.033625405 | D53: =D14/D7 -> 0.10327614 | E53: =E14/E7 -> 0.087663379 | F53: =F14/F7 -> 0.0041748018 | G53: =G14/G7 -> -0.13232845 | H53: =H14/H7 -> -0.34315878 | I53: =I14/I7 -> -0.46172169 | ... DB53: =DB14/DB7 -> 0.22326994
A54: Margin Chg yoy | B54: -- | C54: -- | D54: -- | E54: -- | F54: -- | G54: =+(G53-B53)*10000 -> 1344.6034 | H54: =+(H53-C53)*10000 -> -3095.3338 | I54: =+(I53-D53)*10000 -> -5649.9783 | J54: =+(J53-E53)*10000 -> -4155.2851 | K54: =+(K53-F53)*10000 -> -3185.2431 | L54: =+(L53-G53)*10000 -> -228.36166 | M54: =+(M53-H53)*10000 -> -899.55253 | N54: =+(N53-I53)*10000 -> -329.06157 | ... DB54: =+(DB53-CW53)*10000 -> 122.4164
A55: Incremental margin | B55: -- | C55: -- | D55: -- | E55: -- | F55: -- | G55: =(G14-B14)/(G7-B7) -> 0.049900695 | H55: =(H14-C14)/(H7-C7) -> -1.5422117 | I55: =(I14-D14)/(I7-D7) -> 18.861789 | J55: =(J14-E14)/(J7-E7) -> -7.1733818 | K55: =(K14-F14)/(K7-F7) -> -1.9475633 | L55: =(L14-G14)/(L7-G7) -> -0.23004078 | M55: =(M14-H14)/(M7-H7) -> -1.0211686 | N55: =(N14-I14)/(N7-I7) -> -0.65945584 | ... DB55: =(DB14-CW14)/(DB7-CW7) -> 0.37038202
A56: EBITDA | B56: =B31/B$7 -> -0.26678879 | C56: =C31/C$7 -> 0.030779105 | D56: =D31/D$7 -> 0.13270951 | E56: =E31/E$7 -> 0.11729212 | F56: =F31/F$7 -> 0.036493418 | G56: =G31/G$7 -> -0.097733741 | H56: =H31/H$7 -> -0.31359372 | I56: =I31/I$7 -> -0.43080074 | ... DB56: =DB31/DB$7 -> 0.23652695
A57: Margin Chg yoy | B57: -- | C57: -- | D57: -- | E57: -- | F57: -- | G57: =+(G56-B56)*10000 -> 1690.5505 | H57: =+(H56-C56)*10000 -> -3443.7282 | I57: =+(I56-D56)*10000 -> -5635.1025 | J57: =+(J56-E56)*10000 -> -4230.0727 | K57: =+(K56-F56)*10000 -> -3217.6567 | L57: =+(L56-G56)*10000 -> -381.42321 | M57: =+(M56-H56)*10000 -> -957.82243 | N57: =+(N56-I56)*10000 -> -313.71504 | ... DB57: =+(DB56-CW56)*10000 -> 118.57818
A58: Income Before Taxes | B58: =B7/B18 -> -2.8384983 | C58: =C7/C18 -> -69.719844 | D58: =D7/D18 -> 12.425886 | E58: =E7/E18 -> 39.779904 | F58: =F7/F18 -> -30.917896 | G58: =G7/G18 -> -4.7416034 | H58: =H7/H18 -> -2.2908897 | I58: =I7/I18 -> -2.5479864 | ... DB58: =DB7/DB18 -> 4.0829476
A59: Income Tax | B59: =+B19/B18 -> 0 | C59: =+C19/C18 -> 0 | D59: =+D19/D18 -> 0 | E59: =+E19/E18 -> 0 | F59: =+F19/F18 -> 0 | G59: =+G19/G18 -> 0 | H59: =+H19/H18 -> 0 | I59: =+I19/I18 -> 0 | ... DB59: =+DB19/DB18 -> 0
A60: Net Loss | B60: =+B21/B7 -> -0.35229896 | C60: =+C21/C7 -> -0.014343119 | D60: =+D21/D7 -> 0.080477158 | E60: =+E21/E7 -> 0.025138321 | F60: =+F21/F7 -> -0.032343727 | G60: =+G21/G7 -> -0.21089913 | H60: =+H21/H7 -> -0.43651163 | I60: =+I21/I7 -> -0.39246678 | ... DB60: =+DB21/DB7 -> 0.24492109
A61: Comprehensive Loss | B61: =+B23/B7 -> -0.35229896 | C61: =+C23/C7 -> -0.014343119 | D61: =+D23/D7 -> 0.0037169901 | E61: =+E23/E7 -> 0.096343517 | F61: =+F23/F7 -> -0.032343727 | G61: =+G23/G7 -> -0.21089913 | H61: =+H23/H7 -> -0.43651163 | I61: =+I23/I7 -> -0.39166537 | ... DB61: =+DB23/DB7 -> 0.24497859
A65: Source: Natera and Wells Fargo Securities, LLC estimates.
P66: =+P50+P51 -> 0.81994159 | U66: =+U50+U51 -> 0.973599 | Z66: =+Z50+Z51 -> 0.80040287 | AE66: =+AE50+AE51 -> 0.85183311 | AJ66: =+AJ50+AJ51 -> 1.0323704 | AO66: =+AO50+AO51 -> 1.2394234 | AT66: =+AT50+AT51 -> 1.1033671 | AY66: =+AY50+AY51 -> 0.86736574 | BD66: =+BD50+BD51 -> 0.73395246 | BI66: =+BI50+BI51 -> 0.78187452 | BN66: =+BN50+BN51 -> 0.74766936 | BS66: =+BS50+BS51 -> 0.69250755 | BX66: =+BX50+BX51 -> 0.64698978 | CC66: =+CC50+CC51 -> 0.60507355 | CH66: =+CH50+CH51 -> 0.56802252 | CM66: =+CM50+CM51 -> 0.54139525 | CR66: =+CR50+CR51 -> 0.52180381 | CW66: =+CW50+CW51 -> 0.50494844 | DB66: =+DB50+DB51 -> 0.49605391
A67: Stock-based comp expense | C67: 6M | U67: =+[1]IS!F62+[1]IS!F63+[1]IS!F64 -> 1.8145741 | Z67: =+[1]IS!K62+[1]IS!K63+[1]IS!K64 -> 1.4787454 | AE67: =+[1]IS!P62+[1]IS!P63+[1]IS!P64 -> 0.97929329 | AJ67: =+[1]IS!U62+[1]IS!U63+[1]IS!U64 -> 1.0296551 | AO67: =+[1]IS!Z62+[1]IS!Z63+[1]IS!Z64 -> 1.3562798 | AT67: =+[1]IS!AE62+[1]IS!AE63+[1]IS!AE64 -> 1.6386468 | AY67: =+[1]IS!AJ62+[1]IS!AJ63+[1]IS!AJ64 -> 1.2930359 | BD67: =+[1]IS!AO62+[1]IS!AO63+[1]IS!AO64 -> 1.0247167 | BI67: =+[1]IS!AT62+[1]IS!AT63+[1]IS!AT64 -> 0.92028786 | BN67: =+[1]IS!AY62+[1]IS!AY63+[1]IS!AY64 -> 0.79772772 | BS67: =+[1]IS!BD62+[1]IS!BD63+[1]IS!BD64 -> 0.64003094 | BX67: =+[1]IS!BI62+[1]IS!BI63+[1]IS!BI64 -> 0.53668797 | CC67: =+[1]IS!BN62+[1]IS!BN63+[1]IS!BN64 -> 0.48527073
A68: COGS | C68: 0.101 | D68: 0.114 | E68: =F68-SUM(C68:D68) -> 0.076 | F68: 0.291 | G68: 0.083 | H68: 0.271 | I68: 0.41 | J68: =K68-SUM(G68:I68) -> -0.172 | K68: 0.592 | L68: 0.133 | M68: 0.189 | N68: 0.16 | O68: =P68-SUM(L68:N68) -> 0.159 | P68: 0.641 | Q68: 0.131 | R68: 0.152 | S68: 0.147 | T68: =U68-SUM(Q68:S68) -> 0.114 | U68: 0.544 | V68: 0.142 | W68: 0.153 | X68: 0.191 | Y68: =Z68-SUM(V68:X68) -> 0.083 | Z68: 0.569 | AA68: 0.168 | AB68: 0.225 | AC68: 0.269 | AD68: =AE68-SUM(AA68:AC68) -> 0.275 | AE68: 0.937 | AF68: 0.314 | AG68: 0.441 | AH68: 0.458 | AI68: =AJ68-SUM(AF68:AH68) -> 0.478 | AJ68: 1.691 | AK68: 0.708 | AL68: 1.275 | AM68: 1.262 | AN68: =AO68-SUM(AK68:AM68) -> 1.566 | AO68: 4.811 | AP68: 1.716 | AQ68: 2.063 | AR68: 2.124 | AS68: =AT68-SUM(AP68:AR68) -> 2.002 | AT68: 7.905 | AU68: 2.556 | AV68: 2.838 | AW68: 3.299 | AX68: =AY68-SUM(AU68:AW68) -> 3.059 | AY68: 11.752 | AZ68: 3.777 | BA68: 4.046 | BB68: 4.174 | BC68: =BD68-SUM(AZ68:BB68) -> 4.471 | BD68: 16.468 | BE68: =11.466-BF68 -> 5.27 | BF68: 6.196 | BG68: 6.158
A69: R&D | C69: 1.15 | D69: 0.251 | E69: =F69-SUM(C69:D69) -> 0.192 | F69: 1.593 | G69: 0.261 | H69: 0.32 | I69: 0.268 | J69: =K69-SUM(G69:I69) -> 0.726 | K69: 1.575 | L69: 0.605 | M69: 0.717 | N69: 0.783 | O69: =P69-SUM(L69:N69) -> 0.748 | P69: 2.853 | Q69: 0.65 | R69: 0.73 | S69: 0.943 | T69: =U69-SUM(Q69:S69) -> 0.891 | U69: 3.214 | V69: 0.903 | W69: 1.013 | X69: 1.047 | Y69: =Z69-SUM(V69:X69) -> 1.08 | Z69: 4.043 | AA69: 0.894 | AB69: 1.264 | AC69: 1.58 | AD69: =AE69-SUM(AA69:AC69) -> 1.616 | AE69: 5.354 | AF69: 1.842 | AG69: 2.913 | AH69: 3.098 | AI69: =AJ69-SUM(AF69:AH69) -> 3.571 | AJ69: 11.424 | AK69: 3.874 | AL69: 6.616 | AM69: 6.652 | AN69: =AO69-SUM(AK69:AM69) -> 8.726 | AO69: 25.868 | AP69: 9.421 | AQ69: 12.458 | AR69: 13.469 | AS69: =AT69-SUM(AP69:AR69) -> 11.197 | AT69: 46.545 | AU69: 14.858 | AV69: 15.495 | AW69: 18.784 | AX69: =AY69-SUM(AU69:AW69) -> 17.189 | AY69: 66.326 | AZ69: 20.649 | BA69: 21.957 | BB69: 22.549 | BC69: =BD69-SUM(AZ69:BB69) -> 23.55 | BD69: 88.705 | BE69: =57.283-BF69 -> 26.511 | BF69: 30.772 | BG69: 30.797
A70: SG&A | C70: 1.777 | D70: 0.7 | E70: =F70-SUM(C70:D70) -> 0.796 | F70: 3.273 | G70: 0.803 | H70: 1 | I70: 1.488 | J70: =K70-SUM(G70:I70) -> 1.868 | K70: 5.159 | L70: 1.658 | M70: 1.991 | N70: 1.73 | O70: =P70-SUM(L70:N70) -> 1.728 | P70: 7.107 | Q70: 1.762 | R70: 1.995 | S70: 1.896 | T70: =U70-SUM(Q70:S70) -> 1.991 | U70: 7.644 | V70: 2.109 | W70: 2.202 | X70: 2.378 | Y70: =Z70-SUM(V70:X70) -> 2.897 | Z70: 9.586 | AA70: 2.989 | AB70: 4.315 | AC70: 8.398 | AD70: =AE70-SUM(AA70:AC70) -> 6.631 | AE70: 22.333 | AF70: 5.261 | AG70: 8.603 | AH70: 11.476 | AI70: =AJ70-SUM(AF70:AH70) -> 11.716 | AJ70: 37.056 | AK70: 18.65 | AL70: 27.212 | AM70: 18.544 | AN70: =AO70-SUM(AK70:AM70) -> 20.134 | AO70: 84.54 | AP70: 23.95 | AQ70: 26.452 | AR70: 24.745 | AS70: =AT70-SUM(AP70:AR70) -> 22.787 | AT70: 97.934 | AU70: 23.281 | AV70: 26.137 | AW70: 35.504 | AX70: =AY70-SUM(AU70:AW70) -> 28.808 | AY70: 113.73 | AZ70: 40.021 | BA70: 41.408 | BB70: 43.921 | BC70: =BD70-SUM(AZ70:BB70) -> 43.905 | BD70: 169.255 | BE70: =102.436-BF70 -> 46.046 | BF70: 56.39 | BG70: 53.682
A71: Total | C71: =SUM(C68:C70) -> 3.028 | D71: =SUM(D68:D70) -> 1.065 | E71: =SUM(E68:E70) -> 1.064 | F71: =SUM(F68:F70) -> 5.157 | G71: =SUM(G68:G70) -> 1.147 | H71: =SUM(H68:H70) -> 1.591 | I71: =SUM(I68:I70) -> 2.166 | J71: =SUM(J68:J70) -> 2.422 | ... BG71: =SUM(BG68:BG70) -> 90.637
A72: % of revenue | C72: =C71/C7 -> 0.084496038 | D72: =D71/D7 -> 0.023015084 | E72: =E71/E7 -> 0.021329484 | F72: =F71/F7 -> 0.032375117 | G72: =G71/G7 -> 0.024180457 | H72: =H71/H7 -> 0.035287333 | I72: =I71/I7 -> 0.048217983 | J72: =J71/J7 -> 0.045774116 | ... BG72: =BG71/BG7 -> 0.15305573
F73: =+F71/F13 -> 0.064279304 | K73: =+K71/K13 -> 0.053338964 | P73: =+P71/P13 -> 0.059560195 | U73: =+U71/U13 -> 0.055519307 | Z73: =+Z71/Z13 -> 0.068846465 | AE73: =+AE71/AE13 -> 0.11114692 | AJ73: =+AJ71/AJ13 -> 0.12428963 | AO73: =+AO71/AO13 -> 0.14862327 | AT73: =+AT71/AT13 -> 0.16837899 | AY73: =+AY71/AY13 -> 0.20427163 | BD73: =+BD71/BD13 -> 0.2203441 | BI73: =+BI71/BI13 -> 0
F75: =+F9/(F10+F11) -> 1.0082889 | K75: =+K9/(K10+K11) -> 0.56433294 | P75: =+P9/(P10+P11) -> 0.45789604 | U75: =+U9/(U10+U11) -> 0.34738764 | Z75: =+Z9/(Z10+Z11) -> 0.44416589 | AE75: =+AE9/(AE10+AE11) -> 0.4925893 | AJ75: =+AJ9/(AJ10+AJ11) -> 0.46421263 | AO75: =+AO9/(AO10+AO11) -> 0.39609309 | AT75: =+AT9/(AT10+AT11) -> 0.40216971 | AU75: =+AU9/(AU10+AU11) -> 0.40370279 | AY75: =+AY9/(AY10+AY11) -> 0.52475812 | BD75: =+BD9/(BD10+BD11) -> 0.8215154 | BI75: =+BI9/(BI10+BI11) -> 0.82812237 | BN75: =+BN9/(BN10+BN11) -> 0.86341527 | BS75: =+BS9/(BS10+BS11) -> 0.9504643 | BX75: =+BX9/(BX10+BX11) -> 1.0407435 | CC75: =+CC9/(CC10+CC11) -> 1.13252 | CH75: =+CH9/(CH10+CH11) -> 1.2256392 | CM75: =+CM9/(CM10+CM11) -> 1.2998083 | CR75: =+CR9/(CR10+CR11) -> 1.3606385 | CW75: =+CW9/(CW10+CW11) -> 1.4179205 | DB75: =+DB9/(DB10+DB11) -> 1.4500921
F77: =+F70/F11 -> 0.052005212 | K77: =+K70/K11 -> 0.047055282 | P77: =+P70/P11 -> 0.052208983 | U77: =+U70/U11 -> 0.049218961 | Z77: =+Z70/Z11 -> 0.061896276 | AE77: =+AE70/AE11 -> 0.10832008 | AJ77: =+AJ70/AJ11 -> 0.12204448 | AO77: =+AO70/AO11 -> 0.16542931 | AT77: =+AT70/AT11 -> 0.16638719 | AU77: =+AU70/AU11 -> 0.15559358 | AV77: =+AV70/AV11 -> 0.17138117 | AW77: =+AW70/AW11 -> 0.22943997 | AX77: =+AX70/AX11 -> 0.17845506 | AY77: =+AY70/AY11 -> 0.18393775 | AZ77: =+AZ70/AZ11 -> 0.20599862 | BA77: =+BA70/BA11 -> 0.20916829 | ... BF77: =+BF70/BF11 -> 0.18158165
U79: =+U9+U68 -> 71.887 | Z79: =+Z9+Z68 -> 92.168 | AE79: =+AE9+AE68 -> 127.795 | AJ79: =+AJ9+AJ68 -> 189.076 | AO79: =+AO9+AO68 -> 311.879 | AT79: =+AT9+AT68 -> 371.871 | AY79: =+AY9+AY68 -> 504.492 | BD79: =+BD9+BD68 -> 1039.626
U80: =+U10+U11-U69-U70 -> 194.512 | Z80: =+Z10+Z11-Z69-Z70 -> 192.598 | AE80: =+AE10+AE11-AE69-AE70 -> 229.846 | AJ80: =+AJ10+AJ11-AJ69-AJ70 -> 355.182 | AO80: =+AO10+AO11-AO69-AO70 -> 664.834 | AT80: =+AT10+AT11-AT69-AT70 -> 760.527 | AY80: =+AY10+AY11-AY69-AY70 -> 758.929 | BD80: =+BD10+BD11-BD69-BD70 -> 987.492

Sheet Rev
A1: =+IS!A1 -> Natera Inc. (NASDAQ: NTRA)
A2: Revenue Build
A3: =+IS!A3 -> $ millions except per share data, FY ending Dec
B5: =+IS!B5 -> Mar | C5: =+IS!C5 -> Jun | D5: =+IS!D5 -> Sep | E5: =+IS!E5 -> Dec | F5: =+IS!F5 -> 41974 | G5: =+IS!G5 -> Mar | H5: =+IS!H5 -> Jun | I5: =+IS!I5 -> Sep | ... DB5: =+IS!DB5 -> 49279
B6: =+IS!B6 -> 1Q14A | C6: =+IS!C6 -> 2Q14A | D6: =+IS!D6 -> 3Q14A | E6: =+IS!E6 -> 4Q14A | F6: =+IS!F6 -> FY14A | G6: =+IS!G6 -> 1Q15A | H6: =+IS!H6 -> 2Q15A | I6: =+IS!I6 -> 3Q15A | ... DB6: =+IS!DB6 -> FY34E
A7: Revenue Build
A8: Consolidated
A9: Product Revenues | G9: =+G31 -> 46.899 | H9: =+H31 -> 44.519 | I9: =+I31 -> 44.423 | J9: =+J31 -> 52.327 | K9: =+G9+H9+I9+J9 -> 188.168 | L9: =+L31 -> 61.136 | M9: =+M31 -> 51.231 | N9: =+N31 -> 53.09 | O9: =+O31 -> 48.511 | P9: =+L9+M9+N9+O9 -> 213.968 | Q9: =+Q31 -> 45.913 | R9: =+R31 -> 52.276 | S9: =+S31 -> 55.331 | T9: =+T31 -> 51.969 | U9: =+Q9+R9+S9+T9 -> 205.489 | V9: =+V31 -> 54.269 | W9: =+W31 -> 60.353 | X9: =+X31 -> 62.662 | Y9: =+Y31 -> 63.082 | Z9: =+V9+W9+X9+Y9 -> 240.366 | AA9: =+AA31 -> 63.364 | AB9: =+AB31 -> 65.099 | AC9: =+AC31 -> 66.936 | AD9: =+AD31 -> 74.482 | AE9: =+AA9+AB9+AC9+AD9 -> 269.881 | AF9: =+AF31 -> 87.046 | AG9: =+AG31 -> 80.414 | AH9: =+AH31 -> 93.286 | AI9: =+AI31 -> 106.465 | AJ9: =+AF9+AG9+AH9+AI9 -> 367.211 | AK9: =+AK31 -> 118.382 | AL9: =+AL31 -> 137.232 | AM9: =+AM31 -> 150.651 | AN9: =+AN31 -> 160.884 | AO9: =+AK9+AL9+AM9+AN9 -> 567.149 | AP9: =+AP31 -> 190.002 | AQ9: =+AQ31 -> 194.582 | AR9: =+AR31 -> 199.831 | AS9: =+AS31 -> 212.892 | AT9: =+AP9+AQ9+AR9+AS9 -> 797.307 | AU9: =+AU31 -> 237.797 | AV9: =+AV31 -> 258.256 | AW9: =+AW31 -> 265.218 | AX9: =+AX31 -> 307.251 | AY9: =+AU9+AV9+AW9+AX9 -> 1068.522 | AZ9: =+AZ31 -> 364.672 | BA9: =+BA31 -> 411.364 | BB9: =+BB31 -> 436.127 | BC9: =+BC31 -> 472.911 | BD9: =+AZ9+BA9+BB9+BC9 -> 1685.074 | BE9: =+BE31 -> 500.036 | BF9: =+BF31 -> 544.427 | BG9: =+BG31 -> 590.197 | BH9: =+BH31 -> 661.16 | BI9: =+BE9+BF9+BG9+BH9 -> 2295.82 | BJ9: =+BJ31 -> 614.64917 | BK9: =+BK31 -> 648.22617 | BL9: =+BL31 -> 674.49647 | BM9: =+BM31 -> 710.74987 | BN9: =+BJ9+BK9+BL9+BM9 -> 2648.1217 | BO9: =+BO31 -> 760.17061 | BP9: =+BP31 -> 760.6734 | BQ9: =+BQ31 -> 788.56084 | BR9: =+BR31 -> 808.33937 | BS9: =+BO9+BP9+BQ9+BR9 -> 3117.7442 | BT9: =+BT31 -> 874.82355 | BU9: =+BU31 -> 883.53624 | BV9: =+BV31 -> 911.33955 | BW9: =+BW31 -> 935.55769 | BX9: =+BT9+BU9+BV9+BW9 -> 3605.257 | BY9: =+BY31 -> 1010.6394 | BZ9: =+BZ31 -> 1014.2485 | CA9: =+CA31 -> 1049.1024 | CB9: =+CB31 -> 1071.3304 | CC9: =+BY9+BZ9+CA9+CB9 -> 4145.3207 | CD9: =+CD31 -> 1152.7464 | CE9: =+CE31 -> 1159.0417 | CF9: =+CF31 -> 1194.1817 | CG9: =+CG31 -> 1219.9657 | CH9: =+CD9+CE9+CF9+CG9 -> 4725.9354 | CI9: =+CI31 -> 1295.9962 | CJ9: =+CJ31 -> 1298.1168 | CK9: =+CK31 -> 1330.1733 | CL9: =+CL31 -> 1352.6104 | CM9: =+CI9+CJ9+CK9+CL9 -> 5276.8967 | CN9: =+CN31 -> 1432.8003 | CO9: =+CO31 -> 1434.8961 | CP9: =+CP31 -> 1467.8442 | CQ9: =+CQ31 -> 1491.1037 | CR9: =+CN9+CO9+CP9+CQ9 -> 5826.6444 | CS9: =+CS31 -> 1576.2991 | CT9: =+CT31 -> 1579.0696 | CU9: =+CU31 -> 1613.8538 | CV9: =+CV31 -> 1638.6501 | CW9: =+CS9+CT9+CU9+CV9 -> 6407.8727 | CX9: =+CX31 -> 1714.7687 | CY9: =+CY31 -> 1713.6956 | CZ9: =+CZ31 -> 1745.6647 | DA9: =+DA31 -> 1767.4672 | DB9: =+CX9+CY9+CZ9+DA9 -> 6941.5962
A10: % yoy | G10: -- | H10: -- | I10: -- | J10: -- | K10: -- | L10: =+L9/G9-1 -> 0.30356724 | M10: =+M9/H9-1 -> 0.15076709 | N10: =+N9/I9-1 -> 0.19510164 | O10: =+O9/J9-1 -> -0.072926023 | P10: =+P9/K9-1 -> 0.13711152 | Q10: =+Q9/L9-1 -> -0.24900222 | R10: =+R9/M9-1 -> 0.020397806 | S10: =+S9/N9-1 -> 0.042211339 | ... DB10: =+DB9/CW9-1 -> 0.083291843
A11: % seq | G11: -- | H11: =+H9/G9-1 -> -0.050747351 | I11: =+I9/H9-1 -> -0.0021563827 | J11: =+J9/I9-1 -> 0.17792585 | K11: -- | L11: =+L9/J9-1 -> 0.16834521 | M11: =+M9/L9-1 -> -0.16201583 | N11: =+N9/M9-1 -> 0.036286623 | O11: =+O9/N9-1 -> -0.086249765 | P11: -- | Q11: =+Q9/O9-1 -> -0.053554864 | R11: =+R9/Q9-1 -> 0.1385882 | S11: =+S9/R9-1 -> 0.058439819 | T11: =+T9/S9-1 -> -0.060761598 | U11: -- | V11: =+V9/T9-1 -> 0.044257153 | W11: =+W9/V9-1 -> 0.1121082 | X11: =+X9/W9-1 -> 0.038258247 | Y11: =+Y9/X9-1 -> 0.0067026268 | Z11: -- | AA11: =+AA9/Y9-1 -> 0.0044703719 | AB11: =+AB9/AA9-1 -> 0.027381478 | AC11: =+AC9/AB9-1 -> 0.028218559 | AD11: =+AD9/AC9-1 -> 0.11273455 | AE11: -- | AF11: =+AF9/AD9-1 -> 0.16868505 | AG11: =+AG9/AF9-1 -> -0.076189601 | AH11: =+AH9/AG9-1 -> 0.16007163 | AI11: =+AI9/AH9-1 -> 0.14127522 | AJ11: -- | AK11: =+AK9/AI9-1 -> 0.1119335 | AL11: =+AL9/AK9-1 -> 0.15923029 | AM11: =+AM9/AL9-1 -> 0.097783316 | AN11: =+AN9/AM9-1 -> 0.067925205 | AO11: -- | AP11: =+AP9/AN9-1 -> 0.18098754 | AQ11: =+AQ9/AP9-1 -> 0.024105009 | AR11: =+AR9/AQ9-1 -> 0.026975774 | AS11: =+AS9/AR9-1 -> 0.065360229 | AT11: -- | AU11: =+AU9/AS9-1 -> 0.1169842 | AV11: =+AV9/AU9-1 -> 0.086035568 | AW11: =+AW9/AV9-1 -> 0.026957747 | AX11: =+AX9/AW9-1 -> 0.15848472 | AY11: -- | AZ11: =+AZ9/AX9-1 -> 0.18688629 | BA11: =+BA9/AZ9-1 -> 0.12803835 | BB11: =+BB9/BA9-1 -> 0.060197295 | BC11: =+BC9/BB9-1 -> 0.084342405 | BD11: -- | BE11: =+BE9/BC9-1 -> 0.057357515 | BF11: =+BF9/BE9-1 -> 0.088775608 | BG11: =+BG9/BF9-1 -> 0.084070041 | BH11: =+BH9/BG9-1 -> 0.12023612 | BI11: -- | BJ11: =+BJ9/BH9-1 -> -0.070347315 | BK11: =+BK9/BJ9-1 -> 0.054627917 | BL11: =+BL9/BK9-1 -> 0.040526439 | BM11: =+BM9/BL9-1 -> 0.05374883 | BN11: -- | BO11: =+BO9/BM9-1 -> 0.069533238 | BP11: =+BP9/BO9-1 -> 0.00066141344 | BQ11: =+BQ9/BP9-1 -> 0.03666152 | BR11: =+BR9/BQ9-1 -> 0.025081806 | BS11: -- | BT11: =+BT9/BR9-1 -> 0.082247863 | BU11: =+BU9/BT9-1 -> 0.0099593647 | BV11: =+BV9/BU9-1 -> 0.031468212 | BW11: =+BW9/BV9-1 -> 0.026574228 | BX11: -- | BY11: =+BY9/BW9-1 -> 0.080253458 | BZ11: =+BZ9/BY9-1 -> 0.0035710435 | CA11: =+CA9/BZ9-1 -> 0.034364266 | CB11: =+CB9/CA9-1 -> 0.021187683 | CC11: -- | CD11: =+CD9/CB9-1 -> 0.075995163 | CE11: =+CE9/CD9-1 -> 0.0054611374 | CF11: =+CF9/CE9-1 -> 0.03031815 | CG11: =+CG9/CF9-1 -> 0.021591392 | CH11: -- | CI11: =+CI9/CG9-1 -> 0.062321859 | CJ11: =+CJ9/CI9-1 -> 0.0016362308 | CK11: =+CK9/CJ9-1 -> 0.024694656 | CL11: =+CL9/CK9-1 -> 0.016867762 | CM11: -- | CN11: =+CN9/CL9-1 -> 0.059285304 | CO11: =+CO9/CN9-1 -> 0.0014627348 | CP11: =+CP9/CO9-1 -> 0.022962045 | CQ11: =+CQ9/CP9-1 -> 0.015846027 | CR11: -- | CS11: =+CS9/CQ9-1 -> 0.057135771 | CT11: =+CT9/CS9-1 -> 0.00175761 | CU11: =+CU9/CT9-1 -> 0.022028299 | CV11: =+CV9/CU9-1 -> 0.015364617 | CW11: -- | CX11: =+CX9/CV9-1 -> 0.046451995 | CY11: =+CY9/CX9-1 -> -0.00062575125 | CZ11: =+CZ9/CY9-1 -> 0.018655023 | DA11: =+DA9/CZ9-1 -> 0.012489547 | DB11: --
A13: Licensing and Other Revenues | G13: 0.536 | H13: 0.568 | I13: 0.498 | J13: 0.585 | K13: =+G13+H13+I13+J13 -> 2.187 | L13: 0.766 | M13: 0.753 | N13: 0.799 | O13: 0.788 | P13: =+L13+M13+N13+O13 -> 3.106 | Q13: 0.988 | R13: 1.341 | S13: 1.325 | T13: 1.796 | U13: =+Q13+R13+S13+T13 -> 5.45 | V13: 8.071 | W13: 2.716 | X13: 2.618 | Y13: 3.883 | Z13: =+V13+W13+X13+Y13 -> 17.288 | AA13: 3.46 | AB13: 9.256 | AC13: 10.973 | AD13: 8.758 | AE13: =+AA13+AB13+AC13+AD13 -> 32.447 | AF13: 6.966 | AG13: 6.058 | AH13: 4.857 | AI13: 5.913 | AJ13: =+AF13+AG13+AH13+AI13 -> 23.794 | AK13: 33.934 | AL13: 4.794 | AM13: 7.465 | AN13: 12.144 | AO13: =+AK13+AL13+AM13+AN13 -> 58.337 | AP13: 4.131 | AQ13: 3.618 | AR13: 10.806 | AS13: 4.36 | AT13: =+AP13+AQ13+AR13+AS13 -> 22.915 | AU13: 3.959 | AV13: 3.148 | AW13: 3.088 | AX13: 3.854 | AY13: =+AU13+AV13+AW13+AX13 -> 14.049 | AZ13: 3.069 | BA13: 1.987 | BB13: 3.631 | BC13: 3.15 | BD13: =+AZ13+BA13+BB13+BC13 -> 11.837 | BE13: 1.794 | BF13: 2.173 | BG13: 1.986 | BH13: =10.293-BE13-BF13-BG13 -> 4.34 | BI13: =+BE13+BF13+BG13+BH13 -> 10.293 | BJ13: =+BE13*(1+BJ14) -> 1.8837 | BK13: =+BF13*(1+BK14) -> 2.28165 | BL13: =+BG13*(1+BL14) -> 2.0853 | BM13: =+BH13*(1+BM14) -> 4.557 | BN13: =+BJ13+BK13+BL13+BM13 -> 10.80765 | BO13: =+BJ13*(1+BO14) -> 1.977885 | BP13: =+BK13*(1+BP14) -> 2.3957325 | BQ13: =+BL13*(1+BQ14) -> 2.189565 | BR13: =+BM13*(1+BR14) -> 4.78485 | BS13: =+BO13+BP13+BQ13+BR13 -> 11.348033 | BT13: =+BO13*(1+BT14) -> 2.0767793 | BU13: =+BP13*(1+BU14) -> 2.5155191 | BV13: =+BQ13*(1+BV14) -> 2.2990433 | BW13: =+BR13*(1+BW14) -> 5.0240925 | BX13: =+BT13+BU13+BV13+BW13 -> 11.915434 | BY13: =+BT13*(1+BY14) -> 2.1806182 | BZ13: =+BU13*(1+BZ14) -> 2.6412951 | CA13: =+BV13*(1+CA14) -> 2.4139954 | CB13: =+BW13*(1+CB14) -> 5.2752971 | CC13: =+BY13+BZ13+CA13+CB13 -> 12.511206 | CD13: =+BY13*(1+CD14) -> 2.2896491 | CE13: =+BZ13*(1+CE14) -> 2.7733598 | CF13: =+CA13*(1+CF14) -> 2.5346952 | CG13: =+CB13*(1+CG14) -> 5.539062 | CH13: =+CD13+CE13+CF13+CG13 -> 13.136766 | CI13: =+CD13*(1+CI14) -> 2.4041316 | CJ13: =+CE13*(1+CJ14) -> 2.9120278 | CK13: =+CF13*(1+CK14) -> 2.6614299 | CL13: =+CG13*(1+CL14) -> 5.8160151 | CM13: =+CI13+CJ13+CK13+CL13 -> 13.793604 | CN13: =+CI13*(1+CN14) -> 2.5243382 | CO13: =+CJ13*(1+CO14) -> 3.0576292 | CP13: =+CK13*(1+CP14) -> 2.7945014 | CQ13: =+CL13*(1+CQ14) -> 6.1068158 | CR13: =+CN13+CO13+CP13+CQ13 -> 14.483285 | CS13: =+CN13*(1+CS14) -> 2.6505551 | CT13: =+CO13*(1+CT14) -> 3.2105107 | CU13: =+CP13*(1+CU14) -> 2.9342265 | CV13: =+CQ13*(1+CV14) -> 6.4121566 | CW13: =+CS13+CT13+CU13+CV13 -> 15.207449 | CX13: =+CS13*(1+CX14) -> 2.7830828 | CY13: =+CT13*(1+CY14) -> 3.3710362 | CZ13: =+CU13*(1+CZ14) -> 3.0809378 | DA13: =+CV13*(1+DA14) -> 6.7327645 | DB13: =+CX13+CY13+CZ13+DA13 -> 15.967821
A14: % yoy | G14: -- | H14: -- | I14: -- | J14: -- | K14: -- | L14: =+L13/G13-1 -> 0.42910448 | M14: =+M13/H13-1 -> 0.32570423 | N14: =+N13/I13-1 -> 0.60441767 | O14: =+O13/J13-1 -> 0.34700855 | P14: =+P13/K13-1 -> 0.42021033 | Q14: =+Q13/L13-1 -> 0.28981723 | R14: =+R13/M13-1 -> 0.78087649 | S14: =+S13/N13-1 -> 0.6583229 | ... BI14: =+BI13/BD13-1 -> -0.13043846 | BJ14: 0.05 | BK14: 0.05 | BL14: 0.05 | BM14: 0.05 | BN14: =+BN13/BI13-1 -> 0.05 | BO14: 0.05 | BP14: 0.05 | BQ14: 0.05 | BR14: 0.05 | BS14: =+BS13/BN13-1 -> 0.05 | BT14: 0.05 | BU14: 0.05 | BV14: 0.05 | BW14: 0.05 | BX14: =+BX13/BS13-1 -> 0.05 | BY14: 0.05 | BZ14: 0.05 | CA14: 0.05 | CB14: 0.05 | CC14: =+CC13/BX13-1 -> 0.05 | CD14: 0.05 | CE14: 0.05 | CF14: 0.05 | CG14: 0.05 | CH14: =+CH13/CC13-1 -> 0.05 | CI14: 0.05 | CJ14: 0.05 | CK14: 0.05 | CL14: 0.05 | CM14: =+CM13/CH13-1 -> 0.05 | CN14: 0.05 | CO14: 0.05 | CP14: 0.05 | CQ14: 0.05 | CR14: =+CR13/CM13-1 -> 0.05 | CS14: 0.05 | CT14: 0.05 | CU14: 0.05 | CV14: 0.05 | CW14: =+CW13/CR13-1 -> 0.05 | CX14: 0.05 | CY14: 0.05 | CZ14: 0.05 | DA14: 0.05 | DB14: =+DB13/CW13-1 -> 0.05
A15: % seq | G15: -- | H15: =+H13/G13-1 -> 0.059701493 | I15: =+I13/H13-1 -> -0.12323944 | J15: =+J13/I13-1 -> 0.1746988 | K15: -- | L15: =+L13/J13-1 -> 0.30940171 | M15: =+M13/L13-1 -> -0.016971279 | N15: =+N13/M13-1 -> 0.061088977 | O15: =+O13/N13-1 -> -0.013767209 | P15: -- | Q15: =+Q13/O13-1 -> 0.25380711 | R15: =+R13/Q13-1 -> 0.35728745 | S15: =+S13/R13-1 -> -0.011931394 | T15: =+T13/S13-1 -> 0.3554717 | U15: -- | V15: =+V13/T13-1 -> 3.4938753 | W15: =+W13/V13-1 -> -0.66348656 | X15: =+X13/W13-1 -> -0.036082474 | Y15: =+Y13/X13-1 -> 0.48319328 | Z15: -- | AA15: =+AA13/Y13-1 -> -0.10893639 | AB15: =+AB13/AA13-1 -> 1.6751445 | AC15: =+AC13/AB13-1 -> 0.1855013 | AD15: =+AD13/AC13-1 -> -0.20185911 | AE15: -- | AF15: =+AF13/AD13-1 -> -0.20461293 | AG15: =+AG13/AF13-1 -> -0.1303474 | AH15: =+AH13/AG13-1 -> -0.19825025 | AI15: =+AI13/AH13-1 -> 0.21741816 | AJ15: -- | AK15: =+AK13/AJ13-1 -> 0.42615785 | AL15: =+AL13/AK13-1 -> -0.85872576 | AM15: =+AM13/AL13-1 -> 0.55715478 | AN15: =+AN13/AM13-1 -> 0.62679169 | AO15: -- | AP15: =+AP13/AO13-1 -> -0.92918731 | AQ15: =+AQ13/AP13-1 -> -0.12418301 | AR15: =+AR13/AQ13-1 -> 1.986733 | AS15: =+AS13/AR13-1 -> -0.59652045 | AT15: -- | AU15: =+AU13/AT13-1 -> -0.82723107 | AV15: =+AV13/AU13-1 -> -0.20484971 | AW15: =+AW13/AV13-1 -> -0.01905972 | AX15: =+AX13/AW13-1 -> 0.24805699 | AY15: -- | AZ15: =+AZ13/AY13-1 -> -0.78155029 | BA15: =+BA13/AZ13-1 -> -0.35255784 | BB15: =+BB13/BA13-1 -> 0.82737796 | BC15: =+BC13/BB13-1 -> -0.13247039 | BD15: -- | BE15: =+BE13/BC13-1 -> -0.43047619 | BF15: =+BF13/BE13-1 -> 0.21125975 | BG15: =+BG13/BF13-1 -> -0.086056144 | BH15: =+BH13/BG13-1 -> 1.1852971 | BI15: -- | BJ15: =+BJ13/BH13-1 -> -0.56596774 | BK15: =+BK13/BJ13-1 -> 0.21125975 | BL15: =+BL13/BK13-1 -> -0.086056144 | BM15: =+BM13/BL13-1 -> 1.1852971 | BN15: -- | BO15: =+BO13/BN13-1 -> -0.81699213 | BP15: =+BP13/BO13-1 -> 0.21125975 | BQ15: =+BQ13/BP13-1 -> -0.086056144 | BR15: =+BR13/BQ13-1 -> 1.1852971 | BS15: -- | BT15: =+BT13/BS13-1 -> -0.81699213 | BU15: =+BU13/BT13-1 -> 0.21125975 | BV15: =+BV13/BU13-1 -> -0.086056144 | BW15: =+BW13/BV13-1 -> 1.1852971 | BX15: -- | BY15: =+BY13/BX13-1 -> -0.81699213 | BZ15: =+BZ13/BY13-1 -> 0.21125975 | CA15: =+CA13/BZ13-1 -> -0.086056144 | CB15: =+CB13/CA13-1 -> 1.1852971 | CC15: -- | CD15: =+CD13/CC13-1 -> -0.81699213 | CE15: =+CE13/CD13-1 -> 0.21125975 | CF15: =+CF13/CE13-1 -> -0.086056144 | CG15: =+CG13/CF13-1 -> 1.1852971 | CH15: -- | CI15: =+CI13/CH13-1 -> -0.81699213 | CJ15: =+CJ13/CI13-1 -> 0.21125975 | CK15: =+CK13/CJ13-1 -> -0.086056144 | CL15: =+CL13/CK13-1 -> 1.1852971 | CM15: -- | CN15: =+CN13/CM13-1 -> -0.81699213 | CO15: =+CO13/CN13-1 -> 0.21125975 | CP15: =+CP13/CO13-1 -> -0.086056144 | CQ15: =+CQ13/CP13-1 -> 1.1852971 | CR15: -- | CS15: =+CS13/CR13-1 -> -0.81699213 | CT15: =+CT13/CS13-1 -> 0.21125975 | CU15: =+CU13/CT13-1 -> -0.086056144 | CV15: =+CV13/CU13-1 -> 1.1852971 | CW15: -- | CX15: =+CX13/CW13-1 -> -0.81699213 | CY15: =+CY13/CX13-1 -> 0.21125975 | CZ15: =+CZ13/CY13-1 -> -0.086056144 | DA15: =+DA13/CZ13-1 -> 1.1852971 | DB15: --
A17: Total Revenues | G17: =+G9+G13 -> 47.435 | H17: =+H9+H13 -> 45.087 | I17: =+I9+I13 -> 44.921 | J17: =+J9+J13 -> 52.912 | K17: =+K9+K13 -> 190.355 | L17: =+L9+L13 -> 61.902 | M17: =+M9+M13 -> 51.984 | N17: =+N9+N13 -> 53.889 | ... DB17: =+DB9+DB13 -> 6957.564
A18: % yoy | G18: -- | H18: -- | I18: -- | J18: -- | K18: -- | L18: =+L17/G17-1 -> 0.30498577 | M18: =+M17/H17-1 -> 0.15297092 | N18: =+N17/I17-1 -> 0.19963937 | O18: =+O17/J17-1 -> -0.068283187 | P18: =+P17/K17-1 -> 0.14036406 | Q18: =+Q17/L17-1 -> -0.24233466 | R18: =+R17/M17-1 -> 0.031413512 | S18: =+S17/N17-1 -> 0.051346286 | ... DB18: =+DB17/CW17-1 -> 0.08321302
A19: % seq | G19: -- | H19: =+H17/G17-1 -> -0.049499315 | I19: =+I17/H17-1 -> -0.0036817708 | J19: =+J17/I17-1 -> 0.17789007 | K19: -- | L19: =+L17/J17-1 -> 0.16990475 | M19: =+M17/L17-1 -> -0.16022099 | N19: =+N17/M17-1 -> 0.036645891 | O19: =+O17/N17-1 -> -0.085175082 | P19: -- | Q19: =+Q17/O17-1 -> -0.04864196 | R19: =+R17/Q17-1 -> 0.14319524 | S19: =+S17/R17-1 -> 0.056679784 | T19: =+T17/S17-1 -> -0.051027252 | U19: -- | V19: =+V17/T17-1 -> 0.15949037 | W19: =+W17/V17-1 -> 0.011693936 | X19: =+X17/W17-1 -> 0.035056843 | Y19: =+Y17/X17-1 -> 0.025811887 | Z19: -- | AA19: =+AA17/Y17-1 -> -0.0021055775 | AB19: =+AB17/AA17-1 -> 0.11269903 | AC19: =+AC17/AB17-1 -> 0.047797727 | AD19: =+AD17/AC17-1 -> 0.068425984 | AE19: -- | AF19: =+AF17/AD17-1 -> 0.12940894 | AG19: =+AG17/AF17-1 -> -0.080202527 | AH19: =+AH17/AG17-1 -> 0.13496854 | AI19: =+AI17/AH17-1 -> 0.14504346 | AJ19: -- | AK19: =+AK17/AI17-1 -> 0.35538984 | AL19: =+AL17/AK17-1 -> -0.067556921 | AM19: =+AM17/AL17-1 -> 0.11328912 | AN19: =+AN17/AM17-1 -> 0.094310506 | AO19: -- | AP19: =+AP17/AN17-1 -> 0.12197448 | AQ19: =+AQ17/AP17-1 -> 0.020949555 | AR19: =+AR17/AQ17-1 -> 0.062749748 | AS19: =+AS17/AR17-1 -> 0.031404739 | AT19: -- | AU19: =+AU17/AS17-1 -> 0.11279068 | AV19: =+AV17/AU17-1 -> 0.081272026 | AW19: =+AW17/AV17-1 -> 0.026403575 | AX19: =+AX17/AW17-1 -> 0.15951563 | AY19: -- | AZ19: =+AZ17/AX17-1 -> 0.18204786 | BA19: =+BA17/AZ17-1 -> 0.12402751 | BB19: =+BB17/BA17-1 -> 0.063885173 | BC19: =+BC17/BB17-1 -> 0.082552222 | BD19: -- | BE19: =+BE17/BC17-1 -> 0.054129618 | BF19: =+BF17/BE17-1 -> 0.089213479 | BG19: =+BG17/BF17-1 -> 0.083393707 | BH19: =+BH17/BG17-1 -> 0.12380801 | BI19: -- | BJ19: =+BJ17/BH17-1 -> -0.07357946 | BK19: =+BK17/BJ17-1 -> 0.055106476 | BL19: =+BL17/BK17-1 -> 0.040082452 | BM19: =+BM17/BL17-1 -> 0.057236388 | BN19: -- | BO19: =+BO17/BM17-1 -> 0.065484657 | BP19: =+BP17/BO17-1 -> 0.0012079464 | BQ19: =+BQ17/BP17-1 -> 0.036276235 | BR19: =+BR17/BQ17-1 -> 0.028294409 | BS19: -- | BT19: =+BT17/BR17-1 -> 0.078433421 | BU19: =+BU17/BT17-1 -> 0.010436108 | BV19: =+BV17/BU17-1 -> 0.031134558 | BW19: =+BW17/BV17-1 -> 0.029489991 | BX19: -- | BY19: =+BY17/BW17-1 -> 0.076801685 | BZ19: =+BZ17/BY17-1 -> 0.0040182007 | CA19: =+CA17/BZ17-1 -> 0.034051483 | CB19: =+CB17/CA17-1 -> 0.023860161 | CC19: -- | CD19: =+CD17/CB17-1 -> 0.072849587 | CE19: =+CE17/CD17-1 -> 0.0058690958 | CF19: =+CF17/CE17-1 -> 0.030040354 | CG19: =+CG17/CF17-1 -> 0.02405617 | CH19: -- | CI19: =+CI17/CG17-1 -> 0.059482103 | CJ19: =+CJ17/CI17-1 -> 0.0020243719 | CK19: =+CK17/CJ17-1 -> 0.024446768 | CL19: =+CL17/CK17-1 -> 0.019200904 | CM19: -- | CN19: =+CN17/CL17-1 -> 0.056608323 | CO19: =+CO17/CN17-1 -> 0.0018317096 | CP19: =+CP17/CO17-1 -> 0.022730231 | CQ19: =+CQ17/CP17-1 -> 0.018068213 | CR19: -- | CS19: =+CS17/CQ17-1 -> 0.054594259 | CT19: =+CT17/CS17-1 -> 0.0021092976 | CU19: =+CU17/CT17-1 -> 0.021808992 | CV19: =+CV17/CU17-1 -> 0.017487868 | CW19: -- | CX19: =+CX17/CV17-1 -> 0.044064893 | CY19: =+CY17/CX17-1 -> -0.00028241667 | CZ19: =+CZ17/CY17-1 -> 0.018449449 | DA19: =+DA17/CZ17-1 -> 0.014555798 | DB19: --
A20: % of total | L20: =L17/IS!L7 -> 1 | M20: =M17/IS!M7 -> 1 | N20: =N17/IS!N7 -> 1 | O20: =O17/IS!O7 -> 1 | P20: =P17/IS!P7 -> 1 | U20: =U17/IS!U7 -> 1 | V20: =V17/IS!V7 -> 1 | W20: =W17/IS!W7 -> 1 | X20: =X17/IS!X7 -> 1 | Y20: =Y17/IS!Y7 -> 1 | Z20: =Z17/IS!Z7 -> 1 | AA20: =AA17/IS!AA7 -> 1 | AB20: =AB17/IS!AB7 -> 1 | ... DB20: =DB17/IS!DB7 -> 1
BE21: =BE17/$BI$17 -> 0.21760859 | BF21: =BF17/$BI$17 -> 0.23702221 | BG21: =BG17/$BI$17 -> 0.25678837 | BH21: =BH17/$BI$17 -> 0.28858083
A22: Product Revenues
A23: Total Tests Processed | B23: 44000 | C23: 54000 | D23: 57000 | E23: 60000 | F23: =+B23+C23+D23+E23 -> 215000 | G23: 64000 | H23: 69000 | I23: 84000 | J23: 96000 | K23: =+SUM(G23:J23) -> 313000 | L23: 105000 | M23: 103000 | N23: 109000 | O23: 117000 | P23: =+SUM(L23:O23) -> 434000 | Q23: 121300 | R23: 125700 | S23: 130400 | T23: 137800 | U23: =+SUM(Q23:T23) -> 515200 | V23: 164355 | W23: 162807 | X23: 167172 | Y23: 174200 | Z23: =+SUM(V23:Y23) -> 668534 | AA23: 200200 | AB23: 194200 | AC23: 200200 | AD23: 209400 | AE23: =+SUM(AA23:AD23) -> 804000 | AF23: 235500 | AG23: 234100 | AH23: 262000 | AI23: 295000 | AJ23: =+SUM(AF23:AI23) -> 1026600 | AK23: 348200 | AL23: 375700 | AM23: 407300 | AN23: 438800 | AO23: =+SUM(AK23:AN23) -> 1570000 | AP23: 489300 | AQ23: 499900 | AR23: 517500 | AS23: 559700 | AT23: =+SUM(AP23:AS23) -> 2066400 | AU23: 626200 | AV23: 617200 | AW23: 626000 | AX23: 626800 | AY23: =+SUM(AU23:AX23) -> 2496200 | AZ23: 735800 | BA23: 760300 | BB23: 775800 | BC23: 792800 | BD23: =SUM(AZ23:BC23) -> 3064700 | BE23: 855100 | BF23: 853100 | BG23: 893600 | BH23: 923600 | BI23: =SUM(BE23:BH23) -> 3525400 | BJ23: =+BJ52+BJ187+BJ303 -> 972433.11 | BK23: =+BK52+BK187+BK303 -> 973583.43 | BL23: =+BL52+BL187+BL303 -> 1001384.4 | BM23: =+BM52+BM187+BM303 -> 1037415.7 | BN23: =SUM(BJ23:BM23) -> 3984816.7 | BO23: =+BO52+BO187+BO303 -> 1152255.1 | BP23: =+BP52+BP187+BP303 -> 1117515.9 | BQ23: =+BQ52+BQ187+BQ303 -> 1163750.2 | BR23: =+BR52+BR187+BR303 -> 1180204.4 | BS23: =SUM(BO23:BR23) -> 4613725.5 | BT23: =+BT52+BT187+BT303 -> 1279588.5 | BU23: =+BU52+BU187+BU303 -> 1256073.8 | BV23: =+BV52+BV187+BV303 -> 1296499.3 | BW23: =+BW52+BW187+BW303 -> 1315962 | BX23: =SUM(BT23:BW23) -> 5148123.6 | BY23: =+BY52+BY187+BY303 -> 1421648.8 | BZ23: =+BZ52+BZ187+BZ303 -> 1386854 | CA23: =+CA52+CA187+CA303 -> 1439214.9 | CB23: =+CB52+CB187+CB303 -> 1454195.5 | CC23: =SUM(BY23:CB23) -> 5701913.2 | CD23: =+CD52+CD187+CD303 -> 1562934.2 | CE23: =+CE52+CE187+CE303 -> 1528898.1 | CF23: =+CF52+CF187+CF303 -> 1581844.5 | CG23: =+CG52+CG187+CG303 -> 1599444.2 | CH23: =SUM(CD23:CG23) -> 6273121 | CI23: =+CI52+CI187+CI303 -> 1706590.3 | CJ23: =+CJ52+CJ187+CJ303 -> 1667950 | CK23: =+CK52+CK187+CK303 -> 1720084.4 | CL23: =+CL52+CL187+CL303 -> 1734921.5 | CM23: =SUM(CI23:CL23) -> 6829546.1 | CN23: =+CN52+CN187+CN303 -> 1844354.7 | CO23: =+CO52+CO187+CO303 -> 1804351.3 | CP23: =+CP52+CP187+CP303 -> 1858088.5 | CQ23: =+CQ52+CQ187+CQ303 -> 1873432.9 | CR23: =SUM(CN23:CQ23) -> 7380227.3 | CS23: =+CS52+CS187+CS303 -> 1985668.5 | CT23: =+CT52+CT187+CT303 -> 1944557.7 | CU23: =+CU52+CU187+CU303 -> 2000726.7 | CV23: =+CV52+CV187+CV303 -> 2016852.4 | CW23: =SUM(CS23:CV23) -> 7947805.3 | CX23: =+CX52+CX187+CX303 -> 2129118.5 | CY23: =+CY52+CY187+CY303 -> 2084225.2 | CZ23: =+CZ52+CZ187+CZ303 -> 2139897.5 | DA23: =+DA52+DA187+DA303 -> 2154152.7 | DB23: =SUM(CX23:DA23) -> 8507393.9
A24: % yoy | B24: -- | C24: -- | D24: -- | E24: -- | F24: -- | G24: =+G23/B23-1 -> 0.45454545 | H24: =+H23/C23-1 -> 0.27777778 | I24: =+I23/D23-1 -> 0.47368421 | J24: =+J23/E23-1 -> 0.6 | K24: =+K23/F23-1 -> 0.45581395 | L24: =+L23/G23-1 -> 0.640625 | M24: =+M23/H23-1 -> 0.49275362 | N24: =+N23/I23-1 -> 0.29761905 | ... DB24: =+DB23/CW23-1 -> 0.070407931
A25: % seq | B25: -- | C25: =+C23/B23-1 -> 0.22727273 | D25: =+D23/C23-1 -> 0.055555556 | E25: =+E23/D23-1 -> 0.052631579 | F25: -- | G25: =+G23/E23-1 -> 0.066666667 | H25: =+H23/G23-1 -> 0.078125 | I25: =+I23/H23-1 -> 0.2173913 | J25: =+J23/I23-1 -> 0.14285714 | K25: -- | L25: =+L23/J23-1 -> 0.09375 | M25: =+M23/L23-1 -> -0.019047619 | N25: =+N23/M23-1 -> 0.058252427 | O25: =+O23/N23-1 -> 0.073394495 | P25: -- | Q25: =+Q23/O23-1 -> 0.036752137 | R25: =+R23/Q23-1 -> 0.036273702 | S25: =+S23/R23-1 -> 0.037390613 | T25: =+T23/S23-1 -> 0.056748466 | U25: -- | V25: =+V23/T23-1 -> 0.19270682 | W25: =+W23/V23-1 -> -0.0094186365 | X25: =+X23/W23-1 -> 0.026810887 | Y25: =+Y23/X23-1 -> 0.042040533 | Z25: -- | AA25: =+AA23/Y23-1 -> 0.14925373 | AB25: =+AB23/AA23-1 -> -0.02997003 | AC25: =+AC23/AB23-1 -> 0.030895984 | AD25: =+AD23/AC23-1 -> 0.045954046 | AE25: -- | AF25: =+AF23/AD23-1 -> 0.12464183 | AG25: =+AG23/AF23-1 -> -0.0059447983 | AH25: =+AH23/AG23-1 -> 0.11917984 | AI25: =+AI23/AH23-1 -> 0.1259542 | AJ25: -- | AK25: =+AK23/AI23-1 -> 0.18033898 | AL25: =+AL23/AK23-1 -> 0.078977599 | AM25: =+AM23/AL23-1 -> 0.084109662 | AN25: =+AN23/AM23-1 -> 0.077338571 | AO25: -- | AP25: =+AP23/AN23-1 -> 0.1150866 | AQ25: =+AQ23/AP23-1 -> 0.021663601 | AR25: =+AR23/AQ23-1 -> 0.035207041 | AS25: =+AS23/AR23-1 -> 0.081545894 | AT25: -- | AU25: =+AU23/AS23-1 -> 0.11881365 | AV25: =+AV23/AU23-1 -> -0.014372405 | AW25: =+AW23/AV23-1 -> 0.014257939 | AX25: =+AX23/AW23-1 -> 0.0012779553 | AY25: -- | AZ25: =+AZ23/AX23-1 -> 0.17389917 | BA25: =+BA23/AZ23-1 -> 0.033297092 | BB25: =+BB23/BA23-1 -> 0.020386689 | BC25: =+BC23/BB23-1 -> 0.021912864 | BD25: -- | BE25: =+BE23/BC23-1 -> 0.07858224 | BF25: =+BF23/BE23-1 -> -0.0023389077 | BG25: =+BG23/BF23-1 -> 0.047473919 | BH25: =+BH23/BG23-1 -> 0.033572068 | BI25: -- | BJ25: =+BJ23/BH23-1 -> 0.052872574 | BK25: =+BK23/BJ23-1 -> 0.0011829319 | BL25: =+BL23/BK23-1 -> 0.028555288 | BM25: =+BM23/BL23-1 -> 0.035981534 | BN25: -- | BO25: =+BO23/BM23-1 -> 0.11069749 | BP25: =+BP23/BO23-1 -> -0.030148819 | BQ25: =+BQ23/BP23-1 -> 0.041372344 | BR25: =+BR23/BQ23-1 -> 0.014138949 | BS25: -- | BT25: =+BT23/BR23-1 -> 0.084209242 | BU25: =+BU23/BT23-1 -> -0.018376754 | BV25: =+BV23/BU23-1 -> 0.032184028 | BW25: =+BW23/BV23-1 -> 0.015011676 | BX25: -- | BY25: =+BY23/BW23-1 -> 0.08031148 | BZ25: =+BZ23/BY23-1 -> -0.02447498 | CA25: =+CA23/BZ23-1 -> 0.037755177 | CB25: =+CB23/CA23-1 -> 0.010408843 | CC25: -- | CD25: =+CD23/CB23-1 -> 0.074775877 | CE25: =+CE23/CD23-1 -> -0.021777079 | CF25: =+CF23/CE23-1 -> 0.034630478 | CG25: =+CG23/CF23-1 -> 0.011126013 | CH25: -- | CI25: =+CI23/CG23-1 -> 0.066989584 | CJ25: =+CJ23/CI23-1 -> -0.022641771 | CK25: =+CK23/CJ23-1 -> 0.031256535 | CL25: =+CL23/CK23-1 -> 0.0086258045 | CM25: -- | CN25: =+CN23/CL23-1 -> 0.063076766 | CO25: =+CO23/CN23-1 -> -0.021689653 | CP25: =+CP23/CO23-1 -> 0.029781983 | CQ25: =+CQ23/CP23-1 -> 0.0082581615 | CR25: -- | CS25: =+CS23/CQ23-1 -> 0.059909096 | CT25: =+CT23/CS23-1 -> -0.020703777 | CU25: =+CU23/CT23-1 -> 0.028885246 | CV25: =+CV23/CU23-1 -> 0.0080599118 | CW25: -- | CX25: =+CX23/CV23-1 -> 0.055664006 | CY25: =+CY23/CX23-1 -> -0.021085394 | CZ25: =+CZ23/CY23-1 -> 0.026711293 | DA25: =+DA23/CZ23-1 -> 0.0066616009 | DB25: --
A27: Average Selling Price ($ / test) | G27: =+G31/G23*1000000 -> 732.79688 | H27: =+H31/H23*1000000 -> 645.2029 | I27: =+I31/I23*1000000 -> 528.84524 | J27: =+J31/J23*1000000 -> 545.07292 | K27: =+K31/K23*1000000 -> 601.17572 | L27: =+L31/L23*1000000 -> 582.24762 | M27: =+M31/M23*1000000 -> 497.38835 | N27: =+N31/N23*1000000 -> 487.06422 | ... DB27: =+DB31/DB23*1000000 -> 815.94861
A28: % yoy | G28: -- | H28: -- | I28: -- | J28: -- | K28: -- | L28: =+L27/G27-1 -> -0.20544473 | M28: =+M27/H27-1 -> -0.22909778 | N28: =+N27/I27-1 -> -0.079004243 | O28: =+O27/J27-1 -> -0.23932392 | P28: =+P27/K27-1 -> -0.17991727 | Q28: =+Q27/L27-1 -> -0.34991949 | R28: =+R27/M27-1 -> -0.16387451 | S28: =+S27/N27-1 -> -0.12882641 | ... DB28: =+DB27/CW27-1 -> 0.01203645
A29: % seq | G29: -- | H29: =+H27/G27-1 -> -0.11953377 | I29: =+I27/H27-1 -> -0.18034274 | J29: =+J27/I27-1 -> 0.030685118 | K29: -- | L29: =+L27/J27-1 -> 0.068201338 | M29: =+M27/L27-1 -> -0.1457443 | N29: =+N27/M27-1 -> -0.020756677 | O29: =+O27/N27-1 -> -0.14872841 | P29: -- | Q29: =+Q27/O27-1 -> -0.087105681 | R29: =+R27/Q27-1 -> 0.098733083 | S29: =+S27/R27-1 -> 0.020290531 | T29: =+T27/S27-1 -> -0.11119965 | U29: -- | V29: =+V27/T27-1 -> -0.12446451 | W29: =+W27/V27-1 -> 0.12268234 | X29: =+X27/W27-1 -> 0.011148461 | Y29: =+Y27/X27-1 -> -0.033912219 | Z29: -- | AA29: =+AA27/Y27-1 -> -0.12598033 | AB29: =+AB27/AA27-1 -> 0.05912344 | AC29: =+AC27/AB27-1 -> -0.0025971816 | AD29: =+AD27/AC27-1 -> 0.063846501 | AE29: -- | AF29: =+AF27/AD27-1 -> 0.039161995 | AG29: =+AG27/AF27-1 -> -0.070664891 | AH29: =+AH27/AG27-1 -> 0.036537284 | AI29: =+AI27/AH27-1 -> 0.013607143 | AJ29: -- | AK29: =+AK27/AI27-1 -> -0.0579541 | AL29: =+AL27/AK27-1 -> 0.074378457 | AM29: =+AM27/AL27-1 -> 0.012612796 | AN29: =+AN27/AM27-1 -> -0.008737612 | AO29: -- | AP29: =+AP27/AN27-1 -> 0.059099396 | AQ29: =+AQ27/AP27-1 -> 0.0023896401 | AR29: =+AR27/AQ27-1 -> -0.0079513251 | AS29: =+AS27/AR27-1 -> -0.014965305 | AT29: -- | AU29: =+AU27/AS27-1 -> -0.001635171 | AV29: =+AV27/AU27-1 -> 0.10187212 | AW29: =+AW27/AV27-1 -> 0.012521281 | AX29: =+AX27/AW27-1 -> 0.15700612 | AY29: -- | AZ29: =+AZ27/AX27-1 -> 0.011063234 | BA29: =+BA27/AZ27-1 -> 0.091688301 | BB29: =+BB27/BA27-1 -> 0.039015214 | BC29: =+BC27/BB27-1 -> 0.061090865 | BD29: -- | BE29: =+BE27/BC27-1 -> -0.019678355 | BF29: =+BF27/BE27-1 -> 0.091328124 | BG29: =+BG27/BF27-1 -> 0.034937502 | BH29: =+BH27/BG27-1 -> 0.08384907 | BI29: -- | BJ29: =+BJ27/BH27-1 -> -0.1170321 | BK29: =+BK27/BJ27-1 -> 0.053381838 | BL29: =+BL27/BK27-1 -> 0.011638802 | BM29: =+BM27/BL27-1 -> 0.017150206 | BN29: -- | BO29: =+BO27/BM27-1 -> -0.037061627 | BP29: =+BP27/BO27-1 -> 0.031768001 | BQ29: =+BQ27/BP27-1 -> -0.0045236697 | BR29: =+BR27/BQ27-1 -> 0.010790294 | BS29: -- | BT29: =+BT27/BR27-1 -> -0.0018090416 | BU29: =+BU27/BT27-1 -> 0.028866593 | BV29: =+BV27/BU27-1 -> -0.00069349678 | BW29: =+BW27/BV27-1 -> 0.011391545 | BX29: -- | BY29: =+BY27/BW27-1 -> -5.3708479e-05 | BZ29: =+BZ27/BY27-1 -> 0.028749671 | CA29: =+CA27/BZ27-1 -> -0.0032675442 | CB29: =+CB27/CA27-1 -> 0.0106678 | CC29: -- | CD29: =+CD27/CB27-1 -> 0.0011344564 | CE29: =+CE27/CD27-1 -> 0.02784459 | CF29: =+CF27/CE27-1 -> -0.0041679878 | CG29: =+CG27/CF27-1 -> 0.010350223 | CH29: -- | CI29: =+CI27/CG27-1 -> -0.0043746673 | CJ29: =+CJ27/CI27-1 -> 0.024840433 | CK29: =+CK27/CJ27-1 -> -0.0063629929 | CL29: =+CL27/CK27-1 -> 0.0081714719 | CM29: -- | CN29: =+CN27/CL27-1 -> -0.0035664985 | CO29: =+CO27/CN27-1 -> 0.023665688 | CP29: =+CP27/CO27-1 -> -0.0066227007 | CQ29: =+CQ27/CP27-1 -> 0.0075257167 | CR29: -- | CS29: =+CS27/CQ27-1 -> -0.002616569 | CT29: =+CT27/CS27-1 -> 0.022936254 | CU29: =+CU27/CT27-1 -> -0.0066644429 | CV29: =+CV27/CU27-1 -> 0.0072463005 | CW29: -- | CX29: =+CX27/CV27-1 -> -0.0087262718 | CY29: =+CY27/CX27-1 -> 0.020900334 | CZ29: =+CZ27/CY27-1 -> -0.0078466749 | DA29: =+DA27/CZ27-1 -> 0.0057893801 | DB29: --
A31: Total Product Revenues | G31: 46.899 | H31: 44.519 | I31: 44.423 | J31: 52.327 | K31: =+G31+H31+I31+J31 -> 188.168 | L31: 61.136 | M31: 51.231 | N31: 53.09 | O31: 48.511 | P31: =+L31+M31+N31+O31 -> 213.968 | Q31: 45.913 | R31: 52.276 | S31: 55.331 | T31: 51.969 | U31: =+Q31+R31+S31+T31 -> 205.489 | V31: 54.269 | W31: 60.353 | X31: 62.662 | Y31: 63.082 | Z31: =+V31+W31+X31+Y31 -> 240.366 | AA31: 63.364 | AB31: 65.099 | AC31: 66.936 | AD31: 74.482 | AE31: =+AA31+AB31+AC31+AD31 -> 269.881 | AF31: 87.046 | AG31: 80.414 | AH31: 93.286 | AI31: 106.465 | AJ31: =+AF31+AG31+AH31+AI31 -> 367.211 | AK31: 118.382 | AL31: 137.232 | AM31: 150.651 | AN31: 160.884 | AO31: =+AK31+AL31+AM31+AN31 -> 567.149 | AP31: 190.002 | AQ31: 194.582 | AR31: 199.831 | AS31: 212.892 | AT31: =+AP31+AQ31+AR31+AS31 -> 797.307 | AU31: 237.797 | AV31: 258.256 | AW31: 265.218 | AX31: 307.251 | AY31: =+AU31+AV31+AW31+AX31 -> 1068.522 | AZ31: 364.672 | BA31: 411.364 | BB31: 436.127 | BC31: 472.911 | BD31: =SUM(AZ31:BC31) -> 1685.074 | BE31: 500.036 | BF31: 544.427 | BG31: 590.197 | BH31: =2295.82-BE31-BF31-BG31 -> 661.16 | BI31: =+BE31+BF31+BG31+BH31 -> 2295.82 | BJ31: =+BJ61+BJ195+BJ312 -> 614.64917 | BK31: =+BK61+BK195+BK312 -> 648.22617 | BL31: =+BL61+BL195+BL312 -> 674.49647 | BM31: =+BM61+BM195+BM312 -> 710.74987 | BN31: =+BJ31+BK31+BL31+BM31 -> 2648.1217 | BO31: =+BO61+BO195+BO312 -> 760.17061 | BP31: =+BP61+BP195+BP312 -> 760.6734 | BQ31: =+BQ61+BQ195+BQ312 -> 788.56084 | BR31: =+BR61+BR195+BR312 -> 808.33937 | BS31: =+BO31+BP31+BQ31+BR31 -> 3117.7442 | BT31: =+BT61+BT195+BT312 -> 874.82355 | BU31: =+BU61+BU195+BU312 -> 883.53624 | BV31: =+BV61+BV195+BV312 -> 911.33955 | BW31: =+BW61+BW195+BW312 -> 935.55769 | BX31: =+BT31+BU31+BV31+BW31 -> 3605.257 | BY31: =+BY61+BY195+BY312 -> 1010.6394 | BZ31: =+BZ61+BZ195+BZ312 -> 1014.2485 | CA31: =+CA61+CA195+CA312 -> 1049.1024 | CB31: =+CB61+CB195+CB312 -> 1071.3304 | CC31: =+BY31+BZ31+CA31+CB31 -> 4145.3207 | CD31: =+CD61+CD195+CD312 -> 1152.7464 | CE31: =+CE61+CE195+CE312 -> 1159.0417 | CF31: =+CF61+CF195+CF312 -> 1194.1817 | CG31: =+CG61+CG195+CG312 -> 1219.9657 | CH31: =+CD31+CE31+CF31+CG31 -> 4725.9354 | CI31: =+CI61+CI195+CI312 -> 1295.9962 | CJ31: =+CJ61+CJ195+CJ312 -> 1298.1168 | CK31: =+CK61+CK195+CK312 -> 1330.1733 | CL31: =+CL61+CL195+CL312 -> 1352.6104 | CM31: =+CI31+CJ31+CK31+CL31 -> 5276.8967 | CN31: =+CN61+CN195+CN312 -> 1432.8003 | CO31: =+CO61+CO195+CO312 -> 1434.8961 | CP31: =+CP61+CP195+CP312 -> 1467.8442 | CQ31: =+CQ61+CQ195+CQ312 -> 1491.1037 | CR31: =+CN31+CO31+CP31+CQ31 -> 5826.6444 | CS31: =+CS61+CS195+CS312 -> 1576.2991 | CT31: =+CT61+CT195+CT312 -> 1579.0696 | CU31: =+CU61+CU195+CU312 -> 1613.8538 | CV31: =+CV61+CV195+CV312 -> 1638.6501 | CW31: =+CS31+CT31+CU31+CV31 -> 6407.8727 | CX31: =+CX61+CX195+CX312 -> 1714.7687 | CY31: =+CY61+CY195+CY312 -> 1713.6956 | CZ31: =+CZ61+CZ195+CZ312 -> 1745.6647 | DA31: =+DA61+DA195+DA312 -> 1767.4672 | DB31: =+CX31+CY31+CZ31+DA31 -> 6941.5962
A32: % yoy | G32: -- | H32: -- | I32: -- | J32: -- | K32: -- | L32: =+L31/G31-1 -> 0.30356724 | M32: =+M31/H31-1 -> 0.15076709 | N32: =+N31/I31-1 -> 0.19510164 | O32: =+O31/J31-1 -> -0.072926023 | P32: =+P31/K31-1 -> 0.13711152 | Q32: =+Q31/L31-1 -> -0.24900222 | R32: =+R31/M31-1 -> 0.020397806 | S32: =+S31/N31-1 -> 0.042211339 | ... DB32: =+DB31/CW31-1 -> 0.083291843
A33: % seq | G33: -- | H33: =+H31/G31-1 -> -0.050747351 | I33: =+I31/H31-1 -> -0.0021563827 | J33: =+J31/I31-1 -> 0.17792585 | K33: -- | L33: =+L31/J31-1 -> 0.16834521 | M33: =+M31/L31-1 -> -0.16201583 | N33: =+N31/M31-1 -> 0.036286623 | O33: =+O31/N31-1 -> -0.086249765 | P33: -- | Q33: =+Q31/O31-1 -> -0.053554864 | R33: =+R31/Q31-1 -> 0.1385882 | S33: =+S31/R31-1 -> 0.058439819 | T33: =+T31/S31-1 -> -0.060761598 | U33: -- | V33: =+V31/T31-1 -> 0.044257153 | W33: =+W31/V31-1 -> 0.1121082 | X33: =+X31/W31-1 -> 0.038258247 | Y33: =+Y31/X31-1 -> 0.0067026268 | Z33: -- | AA33: =+AA31/Y31-1 -> 0.0044703719 | AB33: =+AB31/AA31-1 -> 0.027381478 | AC33: =+AC31/AB31-1 -> 0.028218559 | AD33: =+AD31/AC31-1 -> 0.11273455 | AE33: -- | AF33: =+AF31/AD31-1 -> 0.16868505 | AG33: =+AG31/AF31-1 -> -0.076189601 | AH33: =+AH31/AG31-1 -> 0.16007163 | AI33: =+AI31/AH31-1 -> 0.14127522 | AJ33: -- | AK33: =+AK31/AI31-1 -> 0.1119335 | AL33: =+AL31/AK31-1 -> 0.15923029 | AM33: =+AM31/AL31-1 -> 0.097783316 | AN33: =+AN31/AM31-1 -> 0.067925205 | AO33: -- | AP33: =+AP31/AN31-1 -> 0.18098754 | AQ33: =+AQ31/AP31-1 -> 0.024105009 | AR33: =+AR31/AQ31-1 -> 0.026975774 | AS33: =+AS31/AR31-1 -> 0.065360229 | AT33: -- | AU33: =+AU31/AS31-1 -> 0.1169842 | AV33: =+AV31/AU31-1 -> 0.086035568 | AW33: =+AW31/AV31-1 -> 0.026957747 | AX33: =+AX31/AW31-1 -> 0.15848472 | AY33: -- | AZ33: =+AZ31/AX31-1 -> 0.18688629 | BA33: =+BA31/AZ31-1 -> 0.12803835 | BB33: =+BB31/BA31-1 -> 0.060197295 | BC33: =+BC31/BB31-1 -> 0.084342405 | BD33: -- | BE33: =+BE31/BC31-1 -> 0.057357515 | BF33: =+BF31/BE31-1 -> 0.088775608 | BG33: =+BG31/BF31-1 -> 0.084070041 | BH33: =+BH31/BG31-1 -> 0.12023612 | BI33: -- | BJ33: =+BJ31/BH31-1 -> -0.070347315 | BK33: =+BK31/BJ31-1 -> 0.054627917 | BL33: =+BL31/BK31-1 -> 0.040526439 | BM33: =+BM31/BL31-1 -> 0.05374883 | BN33: -- | BO33: =+BO31/BM31-1 -> 0.069533238 | BP33: =+BP31/BO31-1 -> 0.00066141344 | BQ33: =+BQ31/BP31-1 -> 0.03666152 | BR33: =+BR31/BQ31-1 -> 0.025081806 | BS33: -- | BT33: =+BT31/BR31-1 -> 0.082247863 | BU33: =+BU31/BT31-1 -> 0.0099593647 | BV33: =+BV31/BU31-1 -> 0.031468212 | BW33: =+BW31/BV31-1 -> 0.026574228 | BX33: -- | BY33: =+BY31/BW31-1 -> 0.080253458 | BZ33: =+BZ31/BY31-1 -> 0.0035710435 | CA33: =+CA31/BZ31-1 -> 0.034364266 | CB33: =+CB31/CA31-1 -> 0.021187683 | CC33: -- | CD33: =+CD31/CB31-1 -> 0.075995163 | CE33: =+CE31/CD31-1 -> 0.0054611374 | CF33: =+CF31/CE31-1 -> 0.03031815 | CG33: =+CG31/CF31-1 -> 0.021591392 | CH33: -- | CI33: =+CI31/CG31-1 -> 0.062321859 | CJ33: =+CJ31/CI31-1 -> 0.0016362308 | CK33: =+CK31/CJ31-1 -> 0.024694656 | CL33: =+CL31/CK31-1 -> 0.016867762 | CM33: -- | CN33: =+CN31/CL31-1 -> 0.059285304 | CO33: =+CO31/CN31-1 -> 0.0014627348 | CP33: =+CP31/CO31-1 -> 0.022962045 | CQ33: =+CQ31/CP31-1 -> 0.015846027 | CR33: -- | CS33: =+CS31/CQ31-1 -> 0.057135771 | CT33: =+CT31/CS31-1 -> 0.00175761 | CU33: =+CU31/CT31-1 -> 0.022028299 | CV33: =+CV31/CU31-1 -> 0.015364617 | CW33: -- | CX33: =+CX31/CV31-1 -> 0.046451995 | CY33: =+CY31/CX31-1 -> -0.00062575125 | CZ33: =+CZ31/CY31-1 -> 0.018655023 | DA33: =+DA31/CZ31-1 -> 0.012489547 | DB33: --
A35: Product Revenue by Channel
A36: Women's Health | AO36: =AO61 -> 468.78082 | AT36: =AT61 -> 574.44075 | AY36: =AY61 -> 656.85197 | AZ36: =AZ61 -> 224.02792 | BA36: =BA61 -> 243.10682 | BB36: =BB61 -> 251.22979 | BC36: =BC61 -> 264.68278 | BD36: =BD61 -> 983.0473 | BE36: =BE61 -> 276.76529 | BF36: =BF61 -> 282.29169 | ... BH36: =BH61 -> 327.08478 | BI36: =SUM(BE36:BH36) -> 1180.8793 | BJ36: =BJ61 -> 274.71691 | BK36: =BK61 -> 280.61299 | BL36: =BL61 -> 284.30877 | BM36: =BM61 -> 288.52941 | BN36: =SUM(BJ36:BM36) -> 1128.1681 | BO36: =BO61 -> 315.94803 | BP36: =BP61 -> 291.64043 | BQ36: =BQ61 -> 305.63239 | BR36: =BR61 -> 303.10166 | BS36: =SUM(BO36:BR36) -> 1216.3225 | BT36: =BT61 -> 344.44575 | BU36: =BU61 -> 323.90828 | BV36: =BV61 -> 334.13457 | BW36: =BW61 -> 331.62929 | BX36: =SUM(BT36:BW36) -> 1334.1179
A37: % yoy | BD37: =+BD36/AY36-1 -> 0.49660403 | BE37: =+BE36/AZ36-1 -> 0.23540535 | BF37: =+BF36/BA36-1 -> 0.16118375 | BG37: =+BG36/BB36-1 -> 0.17317913 | BH37: =+BH36/BC36-1 -> 0.23576147 | BI37: =+BI36/BD36-1 -> 0.20124362 | BJ37: =+BJ36/BE36-1 -> -0.0074011532 | BK37: =+BK36/BF36-1 -> -0.0059466612 | ... BX37: =+BX36/BS36-1 -> 0.09684551
A38: % seq | BE38: =+BE36/BC36-1 -> 0.045649016 | BF38: =+BF36/BE36-1 -> 0.01996781 | BG38: =+BG36/BF36-1 -> 0.044088639 | BH38: =+BH36/BG36-1 -> 0.1097493 | BI38: -- | BJ38: =+BJ36/BH36-1 -> -0.1601049 | BK38: =+BK36/BJ36-1 -> 0.021462407 | BL38: =+BL36/BK36-1 -> 0.013170377 | BM38: =+BM36/BL36-1 -> 0.014845253 | BN38: -- | BO38: =+BO36/BM36-1 -> 0.095028872 | BP38: =+BP36/BO36-1 -> -0.076935441 | BQ38: =+BQ36/BP36-1 -> 0.047976736 | BR38: =+BR36/BQ36-1 -> -0.0082803024 | BS38: -- | BT38: =+BT36/BS36-1 -> -0.7168138 | BU38: =+BU36/BT36-1 -> -0.059624688 | BV38: =+BV36/BU36-1 -> 0.031571559 | BW38: =+BW36/BV36-1 -> -0.007497797
A39: % of total | BD39: =BD36/BD31 -> 0.58338524 | BE39: =BE36/BE31 -> 0.55349073 | BF39: =BF36/BF31 -> 0.51851155 | BG39: =BG36/BG31 -> 0.49938841 | BH39: =BH36/BH31 -> 0.49471351 | BI39: =BI36/BI31 -> 0.51436058 | BJ39: =BJ36/BJ31 -> 0.44694912 | BK39: =BK36/BK31 -> 0.43289365 | ... BX39: =BX36/BX31 -> 0.37004792
A41: Organ Health / Transplant | AY41: =AY195 -> 84.13563 | AZ41: =AZ195 -> 21.465081 | BA41: =BA195 -> 29.551863 | BB41: =BB195 -> 34.221293 | BC41: =BC195 -> 38.274379 | BD41: =BD195 -> 123.51262 | BE41: =BE195 -> 30.60881 | BF41: =BF195 -> 39.970462 | ... BH41: =BH195 -> 49.310994 | BI41: =SUM(BE41:BH41) -> 163.18621 | BJ41: =BJ195 -> 34.188329 | BK41: =BK195 -> 43.92856 | BL41: =BL195 -> 47.132957 | BM41: =BM195 -> 53.280998 | BN41: =SUM(BJ41:BM41) -> 178.53084 | BO41: =BO195 -> 41.558267 | BP41: =BP195 -> 51.90393 | BQ41: =BQ195 -> 55.243587 | BR41: =BR195 -> 61.765412 | BS41: =SUM(BO41:BR41) -> 210.4712 | BT41: =BT195 -> 48.648055 | BU41: =BU195 -> 59.479506 | BV41: =BV195 -> 62.941267 | BW41: =BW195 -> 69.764787 | BX41: =SUM(BT41:BW41) -> 240.83362
A42: % yoy | BD42: =+BD41/AY41-1 -> 0.46801796 | BE42: =+BE41/AZ41-1 -> 0.4259816 | BF42: =+BF41/BA41-1 -> 0.35255302 | BG42: =+BG41/BB41-1 -> 0.26517563 | BH42: =+BH41/BC41-1 -> 0.28835517 | BI42: =+BI41/BD41-1 -> 0.32121088 | BJ42: =+BJ41/BE41-1 -> 0.11694406 | BK42: =+BK41/BF41-1 -> 0.099025582 | ... BX42: =+BX41/BS41-1 -> 0.14425926
A43: % seq | BE43: =+BE41/BC41-1 -> -0.20027937 | BF43: =+BF41/BE41-1 -> 0.30584825 | BG43: =+BG41/BF41-1 -> 0.083198532 | BH43: =+BH41/BG41-1 -> 0.13892868 | BI43: -- | BJ43: =+BJ41/BH41-1 -> -0.30667937 | BK43: =+BK41/BJ41-1 -> 0.28489929 | BL43: =+BL41/BK41-1 -> 0.072945651 | BM43: =+BM41/BL41-1 -> 0.13044038 | BN43: -- | BO43: =+BO41/BM41-1 -> -0.22001711 | BP43: =+BP41/BO41-1 -> 0.24894355 | BQ43: =+BQ41/BP41-1 -> 0.064343052 | BR43: =+BR41/BQ41-1 -> 0.11805579 | BS43: -- | BT43: =+BT41/BS41-1 -> -0.76886122 | BU43: =+BU41/BT41-1 -> 0.22264921 | BV43: =+BV41/BU41-1 -> 0.05820089 | BW43: =+BW41/BV41-1 -> 0.10841092
A44: % of total | BD44: =BD41/BD31 -> 0.073298036 | BE44: =BE41/BE31 -> 0.061213214 | BF44: =BF41/BF31 -> 0.073417486 | BG44: =BG41/BG31 -> 0.073358464 | BH44: =BH41/BH31 -> 0.074582543 | BI44: =BI41/BI31 -> 0.071079706 | BJ44: =BJ41/BJ31 -> 0.055622509 | BK44: =BK41/BK31 -> 0.067767334 | ... BX44: =BX41/BX31 -> 0.066800678
A46: Oncology | AY46: =AY312 -> 327.5344 | AZ46: =AZ312 -> 119.179 | BA46: =BA312 -> 138.70532 | BB46: =BB312 -> 150.67592 | BC46: =BC312 -> 169.95384 | BD46: =BD312 -> 566.00327 | BE46: =BE312 -> 192.6619 | BF46: =BF312 -> 222.16485 | ... BH46: =BH312 -> 284.76422 | BI46: =SUM(BE46:BH46) -> 951.75449 | BJ46: =BJ312 -> 305.74393 | BK46: =BK312 -> 323.68462 | BL46: =BL312 -> 343.05474 | BM46: =BM312 -> 368.93946 | BN46: =SUM(BJ46:BM46) -> 1341.4228 | BO46: =BO312 -> 402.66431 | BP46: =BP312 -> 417.12903 | BQ46: =BQ312 -> 427.68486 | BR46: =BR312 -> 443.4723 | BS46: =SUM(BO46:BR46) -> 1690.9505 | BT46: =BT312 -> 481.72975 | BU46: =BU312 -> 500.14846 | BV46: =BV312 -> 514.26371 | BW46: =BW312 -> 534.16361 | BX46: =SUM(BT46:BW46) -> 2030.3055
A47: % yoy | BD47: =+BD46/AY46-1 -> 0.72807276 | BE47: =+BE46/AZ46-1 -> 0.61657591 | BF47: =+BF46/BA46-1 -> 0.6017039 | BG47: =+BG46/BB46-1 -> 0.67354885 | BH47: =+BH46/BC46-1 -> 0.67553863 | BI47: =+BI46/BD46-1 -> 0.68153531 | BJ47: =+BJ46/BE46-1 -> 0.58694549 | BK47: =+BK46/BF46-1 -> 0.45695693 | ... BX47: =+BX46/BS46-1 -> 0.20068892
A48: % seq | BE48: =+BE46/BC46-1 -> 0.1336131 | BF48: =+BF46/BE46-1 -> 0.1531333 | BG48: =+BG46/BF46-1 -> 0.13502883 | BH48: =+BH46/BG46-1 -> 0.12928402 | BI48: -- | BJ48: =+BJ46/BI46-1 -> -0.67875756 | BK48: =+BK46/BJ46-1 -> 0.058678799 | BL48: =+BL46/BK46-1 -> 0.059842579 | BM48: =+BM46/BL46-1 -> 0.075453615 | BN48: -- | BO48: =+BO46/BM46-1 -> 0.091410245 | BP48: =+BP46/BO46-1 -> 0.035922542 | BQ48: =+BQ46/BP46-1 -> 0.025305909 | BR48: =+BR46/BQ46-1 -> 0.036913706 | BS48: -- | BT48: =+BT46/BS46-1 -> -0.71511304 | BU48: =+BU46/BT46-1 -> 0.03823452 | BV48: =+BV46/BU46-1 -> 0.028222133 | BW48: =+BW46/BV46-1 -> 0.0386959
A49: % of total | BD49: =BD46/BD31 -> 0.33589224 | BE49: =BE46/BE31 -> 0.38529606 | BF49: =BF46/BF31 -> 0.40807097 | BG49: =BG46/BG31 -> 0.42725312 | BH49: =BH46/BH31 -> 0.43070395 | BI49: =BI46/BI31 -> 0.41455972 | BJ49: =BJ46/BJ31 -> 0.49742837 | BK49: =BK46/BK31 -> 0.49933902 | ... BX49: =BX46/BX31 -> 0.5631514
A51: Women's Health
A52: Total Women's Health Volumes | B52: =+B23-B187-B303 -> 44000 | C52: =+C23-C187-C303 -> 54000 | D52: =+D23-D187-D303 -> 57000 | E52: =+E23-E187-E303 -> 60000 | F52: =+F23-F187-F303 -> 215000 | G52: =+G23-G187-G303 -> 64000 | H52: =+H23-H187-H303 -> 69000 | I52: =+I23-I187-I303 -> 84000 | ... BH52: =+BH23-BH187-BH303 -> 644264.18 | BI52: =+BE52+BF52+BG52+BH52 -> 2569849.2 | BJ52: =+BJ67+BJ160+BJ174 -> 688245.28 | BK52: =+BK67+BK160+BK174 -> 667472.13 | BL52: =+BL67+BL160+BL174 -> 678591.02 | BM52: =+BM67+BM160+BM174 -> 690214.7 | BN52: =+BJ52+BK52+BL52+BM52 -> 2724523.1 | BO52: =+BO67+BO160+BO174 -> 801024.57 | BP52: =+BP67+BP160+BP174 -> 745139.6 | BQ52: =+BQ67+BQ160+BQ174 -> 780084.44 | BR52: =+BR67+BR160+BR174 -> 778103.55 | BS52: =+BO52+BP52+BQ52+BR52 -> 3104352.2 | BT52: =+BT67+BT160+BT174 -> 874657.64 | BU52: =+BU67+BU160+BU174 -> 826972.74 | BV52: =+BV67+BV160+BV174 -> 853715.45 | BW52: =+BW67+BW160+BW174 -> 851828.59 | BX52: =+BT52+BU52+BV52+BW52 -> 3407174.4 | BY52: =+BY67+BY160+BY174 -> 952487.86 | BZ52: =+BZ67+BZ160+BZ174 -> 893963.11 | CA52: =+CA67+CA160+CA174 -> 931559.43 | CB52: =+CB67+CB160+CB174 -> 925743.75 | CC52: =+BY52+BZ52+CA52+CB52 -> 3703754.1 | CD52: =+CD67+CD160+CD174 -> 1028406.3 | CE52: =+CE67+CE160+CE174 -> 968654.25 | CF52: =+CF67+CF160+CF174 -> 1007470.3 | CG52: =+CG67+CG160+CG174 -> 1002403.2 | CH52: =+CD52+CE52+CF52+CG52 -> 4006934 | CI52: =+CI67+CI160+CI174 -> 1107112.6 | CJ52: =+CJ67+CJ160+CJ174 -> 1045045.4 | CK52: =+CK67+CK160+CK174 -> 1086176.1 | CL52: =+CL67+CL160+CL174 -> 1080787.2 | CM52: =+CI52+CJ52+CK52+CL52 -> 4319121.4 | CN52: =+CN67+CN160+CN174 -> 1187579.9 | CO52: =+CO67+CO160+CO174 -> 1123704.7 | CP52: =+CP67+CP160+CP174 -> 1166643.7 | CQ52: =+CQ67+CQ160+CQ174 -> 1161478.8 | CR52: =+CN52+CO52+CP52+CQ52 -> 4639407 | CS52: =+CS67+CS160+CS174 -> 1270395.7 | CT52: =+CT67+CT160+CT174 -> 1204408.8 | CU52: =+CU67+CU160+CU174 -> 1249464 | CV52: =+CV67+CV160+CV174 -> 1244248.1 | CW52: =+CS52+CT52+CU52+CV52 -> 4968516.6 | CX52: =+CX67+CX160+CX174 -> 1355328.8 | CY52: =+CY67+CY160+CY174 -> 1287337.8 | CZ52: =+CZ67+CZ160+CZ174 -> 1334404.3 | DA52: =+DA67+DA160+DA174 -> 1329279.4 | DB52: =+CX52+CY52+CZ52+DA52 -> 5306350.4
A53: % yoy | B53: -- | C53: -- | D53: -- | E53: -- | F53: -- | G53: =+G52/B52-1 -> 0.45454545 | H53: =+H52/C52-1 -> 0.27777778 | I53: =+I52/D52-1 -> 0.47368421 | J53: =+J52/E52-1 -> 0.6 | K53: =+K52/F52-1 -> 0.45581395 | L53: =+L52/G52-1 -> 0.640625 | M53: =+M52/H52-1 -> 0.49275362 | N53: =+N52/I52-1 -> 0.29761905 | ... DB53: =+DB52/CW52-1 -> 0.067994915
A54: % seq | B54: -- | C54: =+C52/B52-1 -> 0.22727273 | D54: =+D52/C52-1 -> 0.055555556 | E54: =+E52/D52-1 -> 0.052631579 | F54: -- | G54: =+G52/E52-1 -> 0.066666667 | H54: =+H52/G52-1 -> 0.078125 | I54: =+I52/H52-1 -> 0.2173913 | J54: =+J52/I52-1 -> 0.14285714 | K54: -- | L54: =+L52/J52-1 -> 0.09375 | M54: =+M52/L52-1 -> -0.019047619 | N54: =+N52/M52-1 -> 0.058252427 | O54: =+O52/N52-1 -> 0.073394495 | P54: -- | Q54: =+Q52/O52-1 -> 0.036752137 | R54: =+R52/Q52-1 -> 0.036273702 | S54: =+S52/R52-1 -> 0.037390613 | T54: =+T52/S52-1 -> 0.056748466 | U54: -- | V54: =+V52/T52-1 -> 0.18726415 | W54: =+W52/V52-1 -> -0.010378656 | X54: =+X52/W52-1 -> 0.027886379 | Y54: =+Y52/X52-1 -> 0.041929553 | Z54: -- | AA54: =+AA52/Y52-1 -> 0.14417532 | AB54: =+AB52/AA52-1 -> -0.026612903 | AC54: =+AC52/AB52-1 -> 0.031224109 | AD54: =+AD52/AC52-1 -> 0.046045694 | AE54: -- | AF54: =+AF52/AD52-1 -> 0.11984927 | AG54: =+AG52/AF52-1 -> -0.018732291 | AH54: =+AH52/AG52-1 -> 0.10294853 | AI54: =+AI52/AH52-1 -> 0.11533684 | AJ54: -- | AK54: =+AK52/AI52-1 -> 0.16684259 | AL54: =+AL52/AK52-1 -> 0.054638968 | AM54: =+AM52/AL52-1 -> 0.078894156 | AN54: =+AN52/AM52-1 -> 0.062133213 | AO54: -- | AP54: =+AP52/AN52-1 -> 0.11933476 | AQ54: =+AQ52/AP52-1 -> -0.016052841 | AR54: =+AR52/AQ52-1 -> 0.018115263 | AS54: =+AS52/AR52-1 -> 0.068935006 | AT54: -- | AU54: =+AU52/AS52-1 -> 0.12970367 | AV54: =+AV52/AU52-1 -> -0.044941438 | AW54: =+AW52/AV52-1 -> 0.0032537834 | AX54: =+AX52/AW52-1 -> -0.01962436 | AY54: -- | AZ54: =+AZ52/AX52-1 -> 0.18751693 | BA54: =+BA52/AZ52-1 -> 0.011062398 | BB54: =+BB52/BA52-1 -> 0.00027231382 | BC54: =+BC52/BB52-1 -> -0.0021184913 | BD54: -- | BE54: =+BE52/BC52-1 -> 0.086356096 | BF54: =+BF52/BE52-1 -> -0.047919102 | BG54: =+BG52/BF52-1 -> 0.02513214 | BH54: =+BH52/BG52-1 -> 0.0037648007 | BI54: -- | BJ54: =+BJ52/BH52-1 -> 0.068265626 | BK54: =+BK52/BJ52-1 -> -0.030182763 | BL54: =+BL52/BK52-1 -> 0.016658206 | BM54: =+BM52/BL52-1 -> 0.01712913 | BN54: -- | BO54: =+BO52/BM52-1 -> 0.16054407 | BP54: =+BP52/BO52-1 -> -0.069766856 | BQ54: =+BQ52/BP52-1 -> 0.046897038 | BR54: =+BR52/BQ52-1 -> -0.0025393361 | BS54: -- | BT54: =+BT52/BR52-1 -> 0.124089 | BU54: =+BU52/BT52-1 -> -0.054518364 | BV54: =+BV52/BU52-1 -> 0.032338082 | BW54: =+BW52/BV52-1 -> -0.0022101701 | BX54: -- | BY54: =+BY52/BW52-1 -> 0.11816845 | BZ54: =+BZ52/BY52-1 -> -0.061444089 | CA54: =+CA52/BZ52-1 -> 0.042055779 | CB54: =+CB52/CA52-1 -> -0.0062429473 | CC54: -- | CD54: =+CD52/CB52-1 -> 0.11089739 | CE54: =+CE52/CD52-1 -> -0.058101617 | CF54: =+CF52/CE52-1 -> 0.040072144 | CG54: =+CG52/CF52-1 -> -0.005029568 | CH54: -- | CI54: =+CI52/CG52-1 -> 0.10445845 | CJ54: =+CJ52/CI52-1 -> -0.056062276 | CK54: =+CK52/CJ52-1 -> 0.03935787 | CL54: =+CL52/CK52-1 -> -0.0049613812 | CM54: -- | CN54: =+CN52/CL52-1 -> 0.098810055 | CO54: =+CO52/CN52-1 -> -0.053786013 | CP54: =+CP52/CO52-1 -> 0.038212004 | CQ54: =+CQ52/CP52-1 -> -0.0044270983 | CR54: -- | CS54: =+CS52/CQ52-1 -> 0.093774288 | CT54: =+CT52/CS52-1 -> -0.051942025 | CU54: =+CU52/CT52-1 -> 0.0374086 | CV54: =+CV52/CU52-1 -> -0.0041744954 | CW54: -- | CX54: =+CX52/CV52-1 -> 0.089275382 | CY54: =+CY52/CX52-1 -> -0.050165736 | CZ54: =+CZ52/CY52-1 -> 0.036561166 | DA54: =+DA52/CZ52-1 -> -0.0038405902 | DB54: --
A55: % of Total Volumes | AY55: =AY52/AY23 -> 0.82990986 | AZ55: =AZ52/AZ23 -> 0.8152131 | BA55: =BA52/BA23 -> 0.79767118 | BB55: =BB52/BB23 -> 0.78194709 | BC55: =BC52/BC23 -> 0.76355878 | BD55: =BD52/BD23 -> 0.78907794 | BE55: =BE52/BE23 -> 0.76906211 | BF55: =BF52/BF23 -> 0.73392593 | ... CC55: =CC52/CC23 -> 0.64956341
A57: Average Selling Price ($ / test) | B57: =+B61/B52*1000000 -> 618.38636 | C57: =+C61/C52*1000000 -> 661.77778 | D57: =+D61/D52*1000000 -> 803.57895 | E57: =+E61/E52*1000000 -> 809.31667 | F57: =+F61/F52*1000000 -> 731.66512 | G57: =+G61/G52*1000000 -> 732.79688 | H57: =+H61/H52*1000000 -> 645.2029 | I57: =+I61/I52*1000000 -> 528.84524 | ... DB57: =+DB61/DB52*1000000 -> 392.39826
A58: % yoy | B58: -- | C58: -- | D58: -- | E58: -- | F58: -- | G58: =+G57/B57-1 -> 0.18501461 | H58: =+H57/C57-1 -> -0.025045989 | I58: =+I57/D57-1 -> -0.34188764 | J58: =+J57/E57-1 -> -0.3265023 | K58: =+K57/F57-1 -> -0.1783458 | L58: =+L57/G57-1 -> -0.20544473 | M58: =+M57/H57-1 -> -0.22909778 | N58: =+N57/I57-1 -> -0.079004243 | ... DB58: =+DB57/CW57-1 -> 0.0012422306
A59: % seq | B59: -- | C59: =+C57/B57-1 -> 0.070168776 | D59: =+D57/C57-1 -> 0.21427309 | E59: =+E57/D57-1 -> 0.0071402061 | F59: -- | G59: =+G57/E57-1 -> -0.094548642 | H59: =+H57/G57-1 -> -0.11953377 | I59: =+I57/H57-1 -> -0.18034274 | J59: =+J57/I57-1 -> 0.030685118 | K59: -- | L59: =+L57/J57-1 -> 0.068201338 | M59: =+M57/L57-1 -> -0.1457443 | N59: =+N57/M57-1 -> -0.020756677 | O59: =+O57/N57-1 -> -0.14872841 | P59: -- | Q59: =+Q57/O57-1 -> -0.087105681 | R59: =+R57/Q57-1 -> 0.098733083 | S59: =+S57/R57-1 -> 0.020290531 | T59: =+T57/S57-1 -> -0.11119965 | U59: -- | V59: =+V57/T57-1 -> -0.13868398 | W59: =+W57/V57-1 -> 0.12189135 | X59: =+X57/W57-1 -> 0.014651998 | Y59: =+Y57/X57-1 -> -0.034861445 | Z59: -- | AA59: =+AA57/Y57-1 -> -0.14321052 | AB59: =+AB57/AA57-1 -> 0.075012338 | AC59: =+AC57/AB57-1 -> -0.0015287747 | AD59: =+AD57/AC57-1 -> 0.065692094 | AE59: -- | AF59: =+AF57/AE57-1 -> 0.093812415 | AG59: =+AG57/AF57-1 -> -0.067694115 | AH59: =+AH57/AG57-1 -> 0.032359992 | AI59: =+AI57/AH57-1 -> 0.0079777729 | AJ59: -- | AK59: =+AK57/AJ57-1 -> -0.084671553 | AL59: =+AL57/AK57-1 -> -0.021595263 | AM59: =+AM57/AL57-1 -> 0.088568022 | AN59: =+AN57/AM57-1 -> -0.031908614 | AO59: -- | AP59: =+AP57/AO57-1 -> 0.034235085 | AQ59: =+AQ57/AP57-1 -> -0.03361878 | AR59: =+AR57/AQ57-1 -> -0.025501436 | AS59: =+AS57/AR57-1 -> -0.047631109 | AT59: -- | AU59: =+AU57/AT57-1 -> -0.053646379 | AV59: =+AV57/AU57-1 -> 0.029622832 | AW59: =+AW57/AV57-1 -> 0.027558443 | AX59: =+AX57/AW57-1 -> 0.061178571 | AY59: -- | AZ59: =+AZ57/AY57-1 -> 0.17791515 | BA59: =+BA57/AZ57-1 -> 0.073289878 | BB59: =+BB57/BA57-1 -> 0.033131838 | BC59: =+BC57/BB57-1 -> 0.055785232 | BD59: -- | BE59: =+BE57/BC57-1 -> -0.037471212 | BF59: =+BF57/BE57-1 -> 0.071303723 | BG59: =+BG57/BF57-1 -> 0.018491761 | BH59: =+BH57/BG57-1 -> 0.10558699 | BI59: -- | BJ59: =+BJ57/BI57-1 -> -0.13135111 | BK59: =+BK57/BJ57-1 -> 0.053252477 | BL59: =+BL57/BK57-1 -> -0.00343068 | BM59: =+BM57/BL57-1 -> -0.0022454157 | BN59: -- | BO59: =+BO57/BN57-1 -> -0.047452793 | BP59: =+BP57/BO57-1 -> -0.0077062238 | BQ59: =+BQ57/BP57-1 -> 0.0010313316 | BR59: =+BR57/BQ57-1 -> -0.0057555816 | BS59: -- | BT59: =+BT57/BS57-1 -> 0.005090044 | BU59: =+BU57/BT57-1 -> -0.0054007651 | BV59: =+BV57/BU57-1 -> -0.00074251129 | BW59: =+BW57/BV57-1 -> -0.0052993393 | BX59: -- | BY59: =+BY57/BX57-1 -> 0.0052064693 | BZ59: =+BZ57/BY57-1 -> -0.0069554791 | CA59: =+CA57/BZ57-1 -> 0.0013433755 | CB59: =+CB57/CA57-1 -> -0.005640892 | CC59: -- | CD59: =+CD57/CC57-1 -> 0.0052839939 | CE59: =+CE57/CD57-1 -> -0.0066470102 | CF59: =+CF57/CE57-1 -> 0.0014614642 | CG59: =+CG57/CF57-1 -> -0.0051348637 | CH59: -- | CI59: =+CI57/CH57-1 -> 0.0054802582 | CJ59: =+CJ57/CI57-1 -> -0.0065192204 | CK59: =+CK57/CJ57-1 -> 0.0017325419 | CL59: =+CL57/CK57-1 -> -0.0048559915 | CM59: -- | CN59: =+CN57/CM57-1 -> 0.0055395066 | CO59: =+CO57/CN57-1 -> -0.0063102091 | CP59: =+CP57/CO57-1 -> 0.0018855264 | CQ59: =+CQ57/CP57-1 -> -0.0045220349 | CR59: -- | CS59: =+CS57/CR57-1 -> 0.0056034741 | CT59: =+CT57/CS57-1 -> -0.0061477065 | CU59: =+CU57/CT57-1 -> 0.0020573757 | CV59: =+CV57/CU57-1 -> -0.0042595545 | CW59: -- | CX59: =+CX57/CW57-1 -> 0.0056201009 | CY59: =+CY57/CX57-1 -> -0.0059725109 | CZ59: =+CZ57/CY57-1 -> 0.0021893245 | DA59: =+DA57/CZ57-1 -> -0.00400232 | DB59: --
A61: Total Women's Health Revenues | B61: 27.209 | C61: 35.736 | D61: 45.804 | E61: =157.308-B61-C61-D61 -> 48.559 | F61: =+F75+F169+F182 -> 157.308 | G61: =+G31-G195-G312 -> 46.899 | H61: =+H31-H195-H312 -> 44.519 | I61: =+I31-I195-I312 -> 44.423 | J61: =+J31-J195-J312 -> 52.327 | K61: =+K31-K195-K312 -> 188.168 | L61: =+L31-L195-L312 -> 61.136 | M61: =+M31-M195-M312 -> 51.231 | N61: =+N31-N195-N312 -> 53.09 | ... BC61: =+BC31-BC195-BC312 -> 264.68278 | BD61: =+AZ61+BA61+BB61+BC61 -> 983.0473 | BE61: =+BE31-BE195-BE312 -> 276.76529 | BF61: =+BF31-BF195-BF312 -> 282.29169 | BG61: =+BG31-BG195-BG312 -> 294.73754 | BH61: =+BH31-BH195-BH312 -> 327.08478 | BI61: =+BE61+BF61+BG61+BH61 -> 1180.8793 | BJ61: =+BJ75+BJ169+BJ182 -> 274.71691 | BK61: =+BK75+BK169+BK182 -> 280.61299 | BL61: =+BL75+BL169+BL182 -> 284.30877 | BM61: =+BM75+BM169+BM182 -> 288.52941 | BN61: =+BJ61+BK61+BL61+BM61 -> 1128.1681 | BO61: =+BO75+BO169+BO182 -> 315.94803 | BP61: =+BP75+BP169+BP182 -> 291.64043 | BQ61: =+BQ75+BQ169+BQ182 -> 305.63239 | BR61: =+BR75+BR169+BR182 -> 303.10166 | BS61: =+BO61+BP61+BQ61+BR61 -> 1216.3225 | BT61: =+BT75+BT169+BT182 -> 344.44575 | BU61: =+BU75+BU169+BU182 -> 323.90828 | BV61: =+BV75+BV169+BV182 -> 334.13457 | BW61: =+BW75+BW169+BW182 -> 331.62929 | BX61: =+BT61+BU61+BV61+BW61 -> 1334.1179 | BY61: =+BY75+BY169+BY182 -> 374.89924 | BZ61: =+BZ75+BZ169+BZ182 -> 349.41652 | CA61: =+CA75+CA169+CA182 -> 364.60064 | CB61: =+CB75+CB169+CB182 -> 360.28062 | CC61: =+BY61+BZ61+CA61+CB61 -> 1449.197 | CD61: =+CD75+CD169+CD182 -> 404.51887 | CE61: =+CE75+CE169+CE182 -> 378.48306 | CF61: =+CF75+CF169+CF182 -> 394.22499 | CG61: =+CG75+CG169+CG182 -> 390.2281 | CH61: =+CD61+CE61+CF61+CG61 -> 1567.455 | CI61: =+CI75+CI169+CI182 -> 435.45998 | CJ61: =+CJ75+CJ169+CJ182 -> 408.3674 | CK61: =+CK75+CK169+CK182 -> 425.17523 | CL61: =+CL75+CL169+CL182 -> 421.01137 | CM61: =+CI61+CJ61+CK61+CL61 -> 1690.014 | CN61: =+CN75+CN169+CN182 -> 467.25811 | CO61: =+CO75+CO169+CO182 -> 439.33625 | CP61: =+CP75+CP169+CP182 -> 456.9842 | CQ61: =+CQ75+CQ169+CQ182 -> 452.90374 | CR61: =+CN61+CO61+CP61+CQ61 -> 1816.4823 | CS61: =+CS75+CS169+CS182 -> 500.18938 | CT61: =+CT75+CT169+CT182 -> 471.29324 | CU61: =+CU75+CU169+CU182 -> 489.92956 | CV61: =+CV75+CV169+CV182 -> 485.80618 | CW61: =+CS61+CT61+CU61+CV61 -> 1947.2184 | CX61: =+CX75+CX169+CX182 -> 534.15407 | CY61: =+CY75+CY169+CY182 -> 504.32764 | CZ61: =+CZ75+CZ169+CZ182 -> 523.91095 | DA61: =+DA75+DA169+DA182 -> 519.81001 | DB61: =+CX61+CY61+CZ61+DA61 -> 2082.2027
A62: % yoy | B62: -- | C62: -- | D62: -- | E62: -- | F62: -- | G62: =+G61/B61-1 -> 0.72365761 | H62: =+H61/C61-1 -> 0.24577457 | I62: =+I61/D61-1 -> -0.030150205 | J62: =+J61/E61-1 -> 0.077596326 | K62: =+K61/F61-1 -> 0.19617566 | L62: =+L61/G61-1 -> 0.30356724 | M62: =+M61/H61-1 -> 0.15076709 | N62: =+N61/I61-1 -> 0.19510164 | ... DB62: =+DB61/CW61-1 -> 0.069321611
A63: % seq | B63: -- | C63: =+C61/B61-1 -> 0.31338895 | D63: =+D61/C61-1 -> 0.28173271 | E63: =+E61/D61-1 -> 0.060147585 | F63: -- | G63: =+G61/E61-1 -> -0.034185218 | H63: =+H61/G61-1 -> -0.050747351 | I63: =+I61/H61-1 -> -0.0021563827 | J63: =+J61/I61-1 -> 0.17792585 | K63: -- | L63: =+L61/J61-1 -> 0.16834521 | M63: =+M61/L61-1 -> -0.16201583 | N63: =+N61/M61-1 -> 0.036286623 | O63: =+O61/N61-1 -> -0.086249765 | P63: -- | Q63: =+Q61/O61-1 -> -0.053554864 | R63: =+R61/Q61-1 -> 0.1385882 | S63: =+S61/R61-1 -> 0.058439819 | T63: =+T61/S61-1 -> -0.060761598 | U63: -- | V63: =+V61/T61-1 -> 0.022609633 | W63: =+W61/V61-1 -> 0.11024763 | X63: =+X61/W61-1 -> 0.042946969 | Y63: =+Y61/X61-1 -> 0.0056063832 | Z63: -- | AA63: =+AA61/Y61-1 -> -0.019682622 | AB63: =+AB61/AA61-1 -> 0.046403139 | AC63: =+AC61/AB61-1 -> 0.0296476 | AD63: =+AD61/AC61-1 -> 0.11476263 | AE63: -- | AF63: =+AF61/AE61-1 -> -0.68063153 | AG63: =+AG61/AF61-1 -> -0.08515834 | AH63: =+AH61/AG61-1 -> 0.13863993 | AI63: =+AI61/AH61-1 -> 0.12423474 | AJ63: -- | AK63: =+AK61/AJ61-1 -> -0.69811473 | AL63: =+AL61/AK61-1 -> 0.031863762 | AM63: =+AM61/AL61-1 -> 0.17444968 | AN63: =+AN61/AM61-1 -> 0.028242014 | AO63: -- | AP63: =+AP61/AO61-1 -> -0.6821025 | AQ63: =+AQ61/AP61-1 -> -0.049131944 | AR63: =+AR61/AQ61-1 -> -0.0078481381 | AS63: =+AS61/AR61-1 -> 0.018020447 | AT63: -- | AU63: =+AU61/AT61-1 -> -0.71778412 | AV63: =+AV61/AU61-1 -> -0.016649899 | AW63: =+AW61/AV61-1 -> 0.030901896 | AX63: =+AX61/AW61-1 -> 0.040353621 | AY63: -- | AZ63: =+AZ61/AX61-1 -> 0.31029467 | BA63: =+BA61/AZ61-1 -> 0.085163037 | BB63: =+BB61/BA61-1 -> 0.033413175 | BC63: =+BC61/BB61-1 -> 0.053548561 | BD63: -- | BE63: =+BE61/BC61-1 -> 0.045649016 | BF63: =+BF61/BE61-1 -> 0.01996781 | BG63: =+BG61/BF61-1 -> 0.044088639 | BH63: =+BH61/BG61-1 -> 0.1097493 | BI63: -- | BJ63: =+BJ61/BH61-1 -> -0.1601049 | BK63: =+BK61/BJ61-1 -> 0.021462407 | BL63: =+BL61/BK61-1 -> 0.013170377 | BM63: =+BM61/BL61-1 -> 0.014845253 | BN63: -- | BO63: =+BO61/BM61-1 -> 0.095028872 | BP63: =+BP61/BO61-1 -> -0.076935441 | BQ63: =+BQ61/BP61-1 -> 0.047976736 | BR63: =+BR61/BQ61-1 -> -0.0082803024 | BS63: -- | BT63: =+BT61/BR61-1 -> 0.13640337 | BU63: =+BU61/BT61-1 -> -0.059624688 | BV63: =+BV61/BU61-1 -> 0.031571559 | BW63: =+BW61/BV61-1 -> -0.007497797 | BX63: -- | BY63: =+BY61/BW61-1 -> 0.13047686 | BZ63: =+BZ61/BY61-1 -> -0.067972195 | CA63: =+CA61/BZ61-1 -> 0.043455651 | CB63: =+CB61/CA61-1 -> -0.011848623 | CC63: -- | CD63: =+CD61/CB61-1 -> 0.1227883 | CE63: =+CE61/CD61-1 -> -0.064362425 | CF63: =+CF61/CE61-1 -> 0.041592172 | CG63: =+CG61/CF61-1 -> -0.010138606 | CH63: -- | CI63: =+CI61/CG61-1 -> 0.1159114 | CJ63: =+CJ61/CI61-1 -> -0.062216014 | CK63: =+CK61/CJ61-1 -> 0.041158601 | CL63: =+CL61/CK61-1 -> -0.0097932802 | CM63: -- | CN63: =+CN61/CL61-1 -> 0.10984678 | CO63: =+CO61/CN61-1 -> -0.059756821 | CP63: =+CP61/CO61-1 -> 0.04016958 | CQ63: =+CQ61/CP61-1 -> -0.0089291137 | CR63: -- | CS63: =+CS61/CQ61-1 -> 0.1044055 | CT63: =+CT61/CS61-1 -> -0.057770407 | CU63: =+CU61/CT61-1 -> 0.039542939 | CV63: =+CV61/CU61-1 -> -0.0084162684 | CW63: -- | CX63: =+CX61/CV61-1 -> 0.099520945 | CY63: =+CY61/CX61-1 -> -0.055838631 | CZ63: =+CZ61/CY61-1 -> 0.038830534 | DA63: =+DA61/CZ61-1 -> -0.007827539 | DB63: --
A64: % of Total Revenues | AY64: =AY61/AY$17 -> 0.60675186 | AZ64: =AZ61/AZ$17 -> 0.60920028 | BA64: =BA61/BA$17 -> 0.58813652 | BB64: =BB61/BB$17 -> 0.571291 | BC64: =BC61/BC$17 -> 0.55598501 | BD64: =BD61/BD$17 -> 0.57931577 | BE64: =BE61/BE$17 -> 0.55151204 | BF64: =BF61/BF$17 -> 0.51645021 | ... DB64: =DB61/DB$17 -> 0.29927179
A66: Panorama (NIPT)
A67: Total Panorama Tests | B67: 39600 | C67: 46800 | D67: 49000 | E67: 50000 | F67: =+B67+C67+D67+E67 -> 185400 | G67: 55000 | H67: 58000 | I67: 67000 | J67: 73000 | K67: =+G67+H67+I67+J67 -> 253000 | L67: 81000 | M67: 80000 | N67: 84000 | O67: 84000 | P67: =+L67+M67+N67+O67 -> 329000 | Q67: 84100 | R67: 83900 | S67: 83500 | T67: 90600 | U67: =+Q67+R67+S67+T67 -> 342100 | V67: 107200 | W67: 105700 | X67: 98200 | Y67: 111300 | Z67: =+V67+W67+X67+Y67 -> 422400 | AA67: 127000 | AB67: 123500 | AC67: 126100 | AD67: =+AD95+AD124+AD146 -> 130424.09 | AE67: =+AA67+AB67+AC67+AD67 -> 507024.09 | AF67: =+AF95+AF124+AF146 -> 147635.74 | AG67: =+AG95+AG124+AG146 -> 147238.75 | AH67: =+AH95+AH124+AH146 -> 164391.57 | AI67: =+AI95+AI124+AI146 -> 175055.17 | AJ67: =+AF67+AG67+AH67+AI67 -> 634321.22 | AK67: =+AK95+AK124+AK146 -> 209794.84 | AL67: =+AL95+AL124+AL146 -> 224693.76 | AM67: =+AM95+AM124+AM146 -> 243379.56 | AN67: =+AN95+AN124+AN146 -> 251720.48 | AO67: =+AK67+AL67+AM67+AN67 -> 929588.64 | AP67: =+AP95+AP124+AP146 -> 287257.53 | AQ67: =+AQ95+AQ124+AQ146 -> 284885.07 | AR67: =+AR95+AR124+AR146 -> 288640.05 | AS67: =+AS95+AS124+AS146 -> 302273.86 | AT67: =+AP67+AQ67+AR67+AS67 -> 1163056.5 | AU67: =+AU95+AU124+AU146 -> 313499.69 | AV67: =+AV95+AV124+AV146 -> 307366.53 | AW67: =+AW95+AW124+AW146 -> 309496.55 | AX67: =+AX95+AX124+AX146 -> 314409.21 | AY67: =+AU67+AV67+AW67+AX67 -> 1244772 | AZ67: =+AZ95+AZ124+AZ146 -> 346225.96 | BA67: =+BA95+BA124+BA146 -> 348952.43 | BB67: =+BB95+BB124+BB146 -> 349062.56 | BC67: =+BC95+BC124+BC146 -> 348564.3 | BD67: =+AZ67+BA67+BB67+BC67 -> 1392805.3 | BE67: =+BE95+BE124+BE146 -> 380116.5 | BF67: =+BF95+BF124+BF146 -> 372514.21 | BG67: =+BG95+BG124+BG146 -> 372635.45 | BH67: =+BH95+BH124+BH146 -> 369985.77 | BI67: =+BE67+BF67+BG67+BH67 -> 1495251.9 | BJ67: =+BJ95+BJ124+BJ146 -> 398568.37 | BK67: =+BK95+BK124+BK146 -> 398216.19 | BL67: =+BL95+BL124+BL146 -> 393630.23 | BM67: =+BM95+BM124+BM146 -> 398828.52 | BN67: =+BJ67+BK67+BL67+BM67 -> 1589243.3 | BO67: =+BO95+BO124+BO146 -> 462296.54 | BP67: =+BP95+BP124+BP146 -> 441302.03 | BQ67: =+BQ95+BQ124+BQ146 -> 451441.29 | BR67: =+BR95+BR124+BR146 -> 448404.42 | BS67: =+BO67+BP67+BQ67+BR67 -> 1803444.3 | BT67: =+BT95+BT124+BT146 -> 503796.84 | BU67: =+BU95+BU124+BU146 -> 488903.88 | BV67: =+BV95+BV124+BV146 -> 492848.67 | BW67: =+BW95+BW124+BW146 -> 489772.3 | BX67: =+BT67+BU67+BV67+BW67 -> 1975321.7 | BY67: =+BY95+BY124+BY146 -> 547326.31 | BZ67: =+BZ95+BZ124+BZ146 -> 526746.22 | CA67: =+CA95+CA124+CA146 -> 536285.53 | CB67: =+CB95+CB124+CB146 -> 530747.37 | CC67: =+BY67+BZ67+CA67+CB67 -> 2141105.4 | CD67: =+CD95+CD124+CD146 -> 589168 | CE67: =+CE95+CE124+CE146 -> 568838.85 | CF67: =+CF95+CF124+CF146 -> 578034.94 | CG67: =+CG95+CG124+CG146 -> 572862.27 | CH67: =+CD67+CE67+CF67+CG67 -> 2308904.1 | CI67: =+CI95+CI124+CI146 -> 632166.14 | CJ67: =+CJ95+CJ124+CJ146 -> 611444.83 | CK67: =+CK95+CK124+CK146 -> 620941.16 | CL67: =+CL95+CL124+CL146 -> 615491.01 | CM67: =+CI67+CJ67+CK67+CL67 -> 2480043.1 | CN67: =+CN95+CN124+CN146 -> 675688.55 | CO67: =+CO95+CO124+CO146 -> 654898.97 | CP67: =+CP95+CP124+CP146 -> 664372.06 | CQ67: =+CQ95+CQ124+CQ146 -> 658968.4 | CR67: =+CN67+CO67+CP67+CQ67 -> 2653928 | CS67: =+CS95+CS124+CS146 -> 720073.45 | CT67: =+CT95+CT124+CT146 -> 699051.18 | CU67: =+CU95+CU124+CU146 -> 708665.89 | CV67: =+CV95+CV124+CV146 -> 703144.38 | CW67: =+CS67+CT67+CU67+CV67 -> 2830934.9 | CX67: =+CX95+CX124+CX146 -> 765169.33 | CY67: =+CY95+CY124+CY146 -> 743996.59 | CZ67: =+CZ95+CZ124+CZ146 -> 753671.18 | DA67: =+DA95+DA124+DA146 -> 748114.09 | DB67: =+CX67+CY67+CZ67+DA67 -> 3010951.2
A68: % yoy | B68: -- | C68: -- | D68: -- | E68: -- | F68: -- | G68: =+G67/B67-1 -> 0.38888889 | H68: =+H67/C67-1 -> 0.23931624 | I68: =+I67/D67-1 -> 0.36734694 | J68: =+J67/E67-1 -> 0.46 | K68: =+K67/F67-1 -> 0.36461704 | L68: =+L67/G67-1 -> 0.47272727 | M68: =+M67/H67-1 -> 0.37931034 | N68: =+N67/I67-1 -> 0.25373134 | ... DB68: =+DB67/CW67-1 -> 0.06358899
A69: % seq | B69: -- | C69: =+C67/B67-1 -> 0.18181818 | D69: =+D67/C67-1 -> 0.047008547 | E69: =+E67/D67-1 -> 0.020408163 | F69: -- | G69: =+G67/E67-1 -> 0.1 | H69: =+H67/G67-1 -> 0.054545455 | I69: =+I67/H67-1 -> 0.15517241 | J69: =+J67/I67-1 -> 0.089552239 | K69: -- | L69: =+L67/J67-1 -> 0.10958904 | M69: =+M67/L67-1 -> -0.012345679 | N69: =+N67/M67-1 -> 0.05 | O69: =+O67/N67-1 -> 0 | P69: -- | Q69: =+Q67/O67-1 -> 0.0011904762 | R69: =+R67/Q67-1 -> -0.0023781213 | S69: =+S67/R67-1 -> -0.0047675805 | T69: =+T67/S67-1 -> 0.08502994 | U69: -- | V69: =+V67/T67-1 -> 0.18322296 | W69: =+W67/V67-1 -> -0.013992537 | X69: =+X67/W67-1 -> -0.070955535 | Y69: =+Y67/X67-1 -> 0.13340122 | Z69: -- | AA69: =+AA67/Y67-1 -> 0.1410602 | AB69: =+AB67/AA67-1 -> -0.027559055 | AC69: =+AC67/AB67-1 -> 0.021052632 | AD69: =+AD67/AC67-1 -> 0.034290934 | AE69: -- | AF69: =+AF67/AD67-1 -> 0.13196679 | AG69: =+AG67/AF67-1 -> -0.0026889844 | AH69: =+AH67/AG67-1 -> 0.11649671 | AI69: =+AI67/AH67-1 -> 0.064867036 | AJ69: -- | AK69: =+AK67/AI67-1 -> 0.19844988 | AL69: =+AL67/AK67-1 -> 0.071016581 | AM69: =+AM67/AL67-1 -> 0.083161212 | AN69: =+AN67/AM67-1 -> 0.034271225 | AO69: -- | AP69: =+AP67/AN67-1 -> 0.14117665 | AQ69: =+AQ67/AP67-1 -> -0.0082590256 | AR69: =+AR67/AQ67-1 -> 0.013180701 | AS69: =+AS67/AR67-1 -> 0.047234647 | AT69: -- | AU69: =+AU67/AS67-1 -> 0.037137934 | AV69: =+AV67/AU67-1 -> -0.019563516 | AW69: =+AW67/AV67-1 -> 0.0069298929 | AX69: =+AX67/AW67-1 -> 0.01587308 | AY69: -- | AZ69: =+AZ67/AX67-1 -> 0.10119535 | BA69: =+BA67/AZ67-1 -> 0.0078748222 | BB69: =+BB67/BA67-1 -> 0.00031561113 | BC69: =+BC67/BB67-1 -> -0.0014274286 | BD69: -- | BE69: =+BE67/BC67-1 -> 0.09052044 | BF69: =+BF67/BE67-1 -> -0.019999873 | BG69: =+BG67/BF67-1 -> 0.00032545009 | BH69: =+BH67/BG67-1 -> -0.0071106562 | BI69: -- | BJ69: =+BJ67/BH67-1 -> 0.077253252 | BK69: =+BK67/BJ67-1 -> -0.0008836047 | BL69: =+BL67/BK67-1 -> -0.011516253 | BM69: =+BM67/BL67-1 -> 0.013206022 | BN69: -- | BO69: =+BO67/BM67-1 -> 0.15913611 | BP69: =+BP67/BO67-1 -> -0.045413522 | BQ69: =+BQ67/BP67-1 -> 0.022975789 | BR69: =+BR67/BQ67-1 -> -0.00672706 | BS69: -- | BT69: =+BT67/BR67-1 -> 0.12353228 | BU69: =+BU67/BT67-1 -> -0.029561427 | BV69: =+BV67/BU67-1 -> 0.0080686369 | BW69: =+BW67/BV67-1 -> -0.0062420311 | BX69: -- | BY69: =+BY67/BW67-1 -> 0.11751178 | BZ69: =+BZ67/BY67-1 -> -0.037601137 | CA69: =+CA67/BZ67-1 -> 0.018109881 | CB69: =+CB67/CA67-1 -> -0.010326884 | CC69: -- | CD69: =+CD67/CB67-1 -> 0.11007239 | CE69: =+CE67/CD67-1 -> -0.034504844 | CF69: =+CF67/CE67-1 -> 0.016166418 | CG69: =+CG67/CF67-1 -> -0.0089487169 | CH69: -- | CI69: =+CI67/CG67-1 -> 0.10352205 | CJ69: =+CJ67/CI67-1 -> -0.032778262 | CK69: =+CK67/CJ67-1 -> 0.015530966 | CL69: =+CL67/CK67-1 -> -0.0087772525 | CM69: -- | CN69: =+CN67/CL67-1 -> 0.097804107 | CO69: =+CO67/CN67-1 -> -0.030768001 | CP69: =+CP67/CO67-1 -> 0.014464972 | CQ69: =+CQ67/CP67-1 -> -0.0081334921 | CR69: -- | CS69: =+CS67/CQ67-1 -> 0.092728354 | CT69: =+CT67/CS67-1 -> -0.029194624 | CU69: =+CU67/CT67-1 -> 0.013753945 | CV69: =+CV67/CU67-1 -> -0.0077914113 | CW69: -- | CX69: =+CX67/CV67-1 -> 0.088210833 | CY69: =+CY67/CX67-1 -> -0.027670669 | CZ69: =+CZ67/CY67-1 -> 0.013003545 | DA69: =+DA67/CZ67-1 -> -0.00737336 | DB69: --
A71: Average Selling Price ($ / test) | B71: =+B75/B67*1000000 -> 515.15152 | C71: =+C75/C67*1000000 -> 572.64957 | D71: =+D75/D67*1000000 -> 702.04082 | E71: =+E75/E67*1000000 -> 728 | F71: =+F75/F67*1000000 -> 636.4617 | G71: =+G75/G67*1000000 -> 636.36364 | H71: =+H75/H67*1000000 -> 593.10345 | I71: =+I75/I67*1000000 -> 504.47761 | ... DB71: =+DB75/DB67*1000000 -> 370.71805
A72: % yoy | B72: -- | C72: -- | D72: -- | E72: -- | F72: -- | G72: =+G71/B71-1 -> 0.23529412 | H72: =+H71/C71-1 -> 0.035717962 | I72: =+I71/D71-1 -> -0.2814127 | J72: =+J71/E71-1 -> -0.34141201 | K72: =+K71/F71-1 -> -0.14174717 | L72: =+L71/G71-1 -> -0.25114638 | M72: =+M71/H71-1 -> -0.32347384 | N72: =+N71/I71-1 -> -0.098548887 | ... DB72: =+DB71/CW71-1 -> -0.004118011
A73: % seq | B73: -- | C73: =+C71/B71-1 -> 0.11161388 | D73: =+D71/C71-1 -> 0.22595187 | E73: =+E71/D71-1 -> 0.036976744 | F73: -- | G73: =+G71/E71-1 -> -0.12587413 | H73: =+H71/G71-1 -> -0.067980296 | I73: =+I71/H71-1 -> -0.14942728 | J73: =+J71/I71-1 -> -0.049606874 | K73: -- | L73: =+L71/J71-1 -> -0.0060670194 | M73: =+M71/L71-1 -> -0.1579987 | N73: =+N71/M71-1 -> 0.133363 | O73: =+O71/N71-1 -> -0.09947644 | P73: -- | Q73: =+Q71/O71-1 -> -0.088294666 | R73: =+R71/Q71-1 -> 0.050268366 | S73: =+S71/R71-1 -> 0.090304497 | T73: =+T71/S71-1 -> -0.17388589 | U73: -- | V73: =+V71/T71-1 -> -0.12051656 | W73: =+W71/V71-1 -> 0.087285961 | X73: =+X71/W71-1 -> 0.085419911 | Y73: =+Y71/X71-1 -> -0.11769991 | Z73: -- | AA73: =+AA71/Y71-1 -> -0.094409449 | AB73: =+AB71/AA71-1 -> 0.0089895956 | AC73: =+AC71/AB71-1 -> 0.0088970484 | AD73: =+AD71/AC71-1 -> 0.094930365 | AE73: -- | AF73: =+AF71/AD71-1 -> -0.031384894 | AG73: =+AG71/AF71-1 -> -0.066281059 | AH73: =+AH71/AG71-1 -> 0.064171764 | AI73: =+AI71/AH71-1 -> -0.0068917091 | AJ73: -- | AK73: =+AK71/AI71-1 -> -0.039854529 | AL73: =+AL71/AK71-1 -> -0.063983776 | AM73: =+AM71/AL71-1 -> 0.063309416 | AN73: =+AN71/AM71-1 -> -0.0086691506 | AO73: -- | AP73: =+AP71/AN71-1 -> 0.020773781 | AQ73: =+AQ71/AP71-1 -> -0.00093777452 | AR73: =+AR71/AQ71-1 -> 0.0011785868 | AS73: =+AS71/AR71-1 -> 0.0041706689 | AT73: -- | AU73: =+AU71/AS71-1 -> 0.024332219 | AV73: =+AV71/AU71-1 -> -0.0025457156 | AW73: =+AW71/AV71-1 -> 0.00061264074 | AX73: =+AX71/AW71-1 -> 0.0014755846 | AY73: -- | AZ73: =+AZ71/AX71-1 -> 0.094611825 | BA73: =+BA71/AZ71-1 -> 0.16168519 | BB73: =+BB71/BA71-1 -> 0.044489487 | BC73: =+BC71/BB71-1 -> 0.042696343 | BD73: -- | BE73: =+BE71/BC71-1 -> 0.0050003343 | BF73: =+BF71/BE71-1 -> 0.028316167 | BG73: =+BG71/BF71-1 -> 0.00073045008 | BH73: =+BH71/BG71-1 -> 0.067121627 | BI73: -- | BJ73: =+BJ71/BH71-1 -> -0.14740694 | BK73: =+BK71/BJ71-1 -> -0.033611334 | BL73: =+BL71/BK71-1 -> -0.010689901 | BM73: =+BM71/BL71-1 -> -0.0051801694 | BN73: -- | BO73: =+BO71/BM71-1 -> 0.024104059 | BP73: =+BP71/BO71-1 -> -0.017561249 | BQ73: =+BQ71/BP71-1 -> -0.0021336743 | BR73: =+BR71/BQ71-1 -> -0.0088666822 | BS73: -- | BT73: =+BT71/BR71-1 -> 0.018812309 | BU73: =+BU71/BT71-1 -> -0.013799693 | BV73: =+BV71/BU71-1 -> -0.0048319646 | BW73: =+BW71/BV71-1 -> -0.0083054642 | BX73: -- | BY73: =+BY71/BW71-1 -> 0.0191497 | BZ73: =+BZ71/BY71-1 -> -0.015676481 | CA73: =+CA71/BZ71-1 -> -0.0018631935 | CB73: =+CB71/CA71-1 -> -0.0089554232 | CC73: -- | CD73: =+CD71/CB71-1 -> 0.018908231 | CE73: =+CE71/CD71-1 -> -0.014882393 | CF73: =+CF71/CE71-1 -> -0.0018093906 | CG73: =+CG71/CF71-1 -> -0.0082937021 | CH73: -- | CI73: =+CI71/CG71-1 -> 0.018554527 | CJ73: =+CJ71/CI71-1 -> -0.014386761 | CK73: =+CK71/CJ71-1 -> -0.0015064978 | CL73: =+CL71/CK71-1 -> -0.0079680854 | CM73: -- | CN73: =+CN71/CL71-1 -> 0.018172469 | CO73: =+CO71/CN71-1 -> -0.013791416 | CP73: =+CP71/CO71-1 -> -0.0013786203 | CQ73: =+CQ71/CP71-1 -> -0.0075369288 | CR73: -- | CS73: =+CS71/CQ71-1 -> 0.017756274 | CT73: =+CT71/CS71-1 -> -0.013290574 | CU73: =+CU71/CT71-1 -> -0.0012091365 | CV73: =+CV71/CU71-1 -> -0.0072070299 | CW73: -- | CX73: =+CX71/CV71-1 -> 0.01733087 | CY73: =+CY71/CX71-1 -> -0.012788787 | CZ73: =+CZ71/CY71-1 -> -0.0010943707 | DA73: =+DA71/CZ71-1 -> -0.0068725358 | DB73: --
A75: Total Panorama Revenues | B75: 20.4 | C75: 26.8 | D75: 34.4 | E75: 36.4 | F75: =+B75+C75+D75+E75 -> 118 | G75: 35 | H75: 34.4 | I75: 33.8 | J75: 35 | K75: =+G75+H75+I75+J75 -> 138.2 | L75: 38.6 | M75: 32.1 | N75: 38.2 | O75: 34.4 | P75: =+L75+M75+N75+O75 -> 143.3 | Q75: 31.4 | R75: 32.9 | S75: 35.7 | T75: 32 | U75: =+Q75+R75+S75+T75 -> 132 | V75: 33.3 | W75: 35.7 | X75: 36 | Y75: 36 | Z75: =+V75+W75+X75+Y75 -> 141 | AA75: 37.2 | AB75: 36.5 | AC75: 37.6 | AD75: =+AD103+AD132+AD155 -> 42.581118 | AE75: =+AA75+AB75+AC75+AD75 -> 153.88112 | AF75: =+AF103+AF132+AF155 -> 46.687647 | AG75: =+AG103+AG132+AG155 -> 43.475919 | AH75: =+AH103+AH132+AH155 -> 51.655664 | AI75: =+AI103+AI132+AI155 -> 54.627326 | AJ75: =+AF75+AG75+AH75+AI75 -> 196.44656 | AK75: =+AK103+AK132+AK155 -> 62.858911 | AL75: =+AL103+AL132+AL155 -> 63.01536 | AM75: =+AM103+AM132+AM155 -> 72.577029 | AN75: =+AN103+AN132+AN155 -> 74.413588 | AO75: =+AK75+AL75+AM75+AN75 -> 272.86489 | AP75: =+AP103+AP132+AP155 -> 86.683139 | AQ75: =+AQ103+AQ132+AQ155 -> 85.886603 | AR75: =+AR103+AR132+AR155 -> 87.121208 | AS75: =+AS103+AS132+AS155 -> 91.616864 | AT75: =+AP75+AQ75+AR75+AS75 -> 351.30781 | AU75: =+AU103+AU132+AU155 -> 97.331356 | AV75: =+AV103+AV132+AV155 -> 95.184282 | AW75: =+AW103+AW132+AW155 -> 95.902617 | AX75: =+AX103+AX132+AX155 -> 97.568645 | AY75: =+AU75+AV75+AW75+AX75 -> 385.9869 | AZ75: =+AZ103+AZ132+AZ155 -> 117.60744 | BA75: =+BA103+BA132+BA155 -> 137.6987 | BB75: =+BB103+BB132+BB155 -> 143.87023 | BC75: =+BC103+BC132+BC155 -> 149.79883 | BD75: =+AZ75+BA75+BB75+BC75 -> 548.9752 | BE75: =+BE103+BE132+BE155 -> 164.17554 | BF75: =+BF103+BF132+BF155 -> 165.44789 | BG75: =+BG103+BG132+BG155 -> 165.62263 | BH75: =+BH103+BH132+BH155 -> 175.48276 | BI75: =+BE75+BF75+BG75+BH75 -> 670.72882 | BJ75: =+BJ103+BJ132+BJ155 -> 161.17365 | BK75: =+BK103+BK132+BK155 -> 155.61877 | BL75: =+BL103+BL132+BL155 -> 152.18223 | BM75: =+BM103+BM132+BM155 -> 153.39321 | BN75: =+BJ75+BK75+BL75+BM75 -> 622.36786 | BO75: =+BO103+BO132+BO155 -> 182.0894 | BP75: =+BP103+BP132+BP155 -> 170.76758 | BQ75: =+BQ103+BQ132+BQ155 -> 174.31837 | BR75: =+BR103+BR132+BR155 -> 171.61049 | BS75: =+BO75+BP75+BQ75+BR75 -> 698.78583 | BT75: =+BT103+BT132+BT155 -> 196.43712 | BU75: =+BU103+BU132+BU155 -> 187.99952 | BV75: =+BV103+BV132+BV155 -> 188.60069 | BW75: =+BW103+BW132+BW155 -> 185.8668 | BX75: =+BT75+BU75+BV75+BW75 -> 758.90412 | BY75: =+BY103+BY132+BY155 -> 211.68589 | BZ75: =+BZ103+BZ132+BZ155 -> 200.53255 | CA75: =+CA103+CA132+CA155 -> 203.78377 | CB75: =+CB103+CB132+CB155 -> 199.87319 | CC75: =+BY75+BZ75+CA75+CB75 -> 815.87539 | CD75: =+CD103+CD132+CD155 -> 226.06895 | CE75: =+CE103+CE132+CE155 -> 215.02012 | CF75: =+CF103+CF132+CF155 -> 218.10088 | CG75: =+CG103+CG132+CG155 -> 214.35648 | CH75: =+CD75+CE75+CF75+CG75 -> 873.54644 | CI75: =+CI103+CI132+CI155 -> 240.93612 | CJ75: =+CJ103+CJ132+CJ155 -> 229.68598 | CK75: =+CK103+CK132+CK155 -> 232.90183 | CL75: =+CL103+CL132+CL155 -> 229.0181 | CM75: =+CI75+CJ75+CK75+CL75 -> 932.54204 | CN75: =+CN103+CN132+CN155 -> 255.98588 | CO75: =+CO103+CO132+CO155 -> 244.68792 | CP75: =+CP103+CP132+CP155 -> 247.88512 | CQ75: =+CQ103+CQ132+CQ155 -> 244.01585 | CR75: =+CN75+CO75+CP75+CQ75 -> 992.57477 | CS75: =+CS103+CS132+CS155 -> 271.37762 | CT75: =+CT103+CT132+CT155 -> 259.95339 | CU75: =+CU103+CU132+CU155 -> 263.21013 | CV75: =+CV103+CV132+CV155 -> 259.27717 | CW75: =+CS75+CT75+CU75+CV75 -> 1053.8183 | CX75: =+CX103+CX132+CX155 -> 287.0381 | CY75: =+CY103+CY132+CY155 -> 275.52627 | CZ75: =+CZ103+CZ132+CZ155 -> 278.80364 | DA75: =+DA103+DA132+DA155 -> 274.84596 | DB75: =+CX75+CY75+CZ75+DA75 -> 1116.214
A76: % yoy | B76: -- | C76: -- | D76: -- | E76: -- | F76: -- | G76: =+G75/B75-1 -> 0.71568627 | H76: =+H75/C75-1 -> 0.28358209 | I76: =+I75/D75-1 -> -0.01744186 | J76: =+J75/E75-1 -> -0.038461538 | K76: =+K75/F75-1 -> 0.17118644 | L76: =+L75/G75-1 -> 0.10285714 | M76: =+M75/H75-1 -> -0.066860465 | N76: =+N75/I75-1 -> 0.13017751 | ... DB76: =+DB75/CW75-1 -> 0.059209119
A77: % seq | B77: -- | C77: =+C75/B75-1 -> 0.31372549 | D77: =+D75/C75-1 -> 0.28358209 | E77: =+E75/D75-1 -> 0.058139535 | F77: -- | G77: =+G75/E75-1 -> -0.038461538 | H77: =+H75/G75-1 -> -0.017142857 | I77: =+I75/H75-1 -> -0.01744186 | J77: =+J75/I75-1 -> 0.035502959 | K77: -- | L77: =+L75/J75-1 -> 0.10285714 | M77: =+M75/L75-1 -> -0.16839378 | N77: =+N75/M75-1 -> 0.19003115 | O77: =+O75/N75-1 -> -0.09947644 | P77: -- | Q77: =+Q75/O75-1 -> -0.087209302 | R77: =+R75/Q75-1 -> 0.047770701 | S77: =+S75/R75-1 -> 0.085106383 | T77: =+T75/S75-1 -> -0.10364146 | U77: -- | V77: =+V75/T75-1 -> 0.040625 | W77: =+W75/V75-1 -> 0.072072072 | X77: =+X75/W75-1 -> 0.0084033613 | Y77: =+Y75/X75-1 -> 0 | Z77: -- | AA77: =+AA75/Y75-1 -> 0.033333333 | AB77: =+AB75/AA75-1 -> -0.018817204 | AC77: =+AC75/AB75-1 -> 0.030136986 | AD77: =+AD75/AC75-1 -> 0.13247655 | AE77: -- | AF77: =+AF75/AD75-1 -> 0.096440137 | AG77: =+AG75/AF75-1 -> -0.068791815 | AH77: =+AH75/AG75-1 -> 0.18814427 | AI77: =+AI75/AH75-1 -> 0.057528282 | AJ77: -- | AK77: =+AK75/AI75-1 -> 0.15068622 | AL77: =+AL75/AK75-1 -> 0.0024888958 | AM77: =+AM75/AL75-1 -> 0.15173552 | AN77: =+AN75/AM75-1 -> 0.025304972 | AO77: -- | AP77: =+AP75/AN75-1 -> 0.16488321 | AQ77: =+AQ75/AP75-1 -> -0.009189055 | AR77: =+AR75/AQ75-1 -> 0.014374822 | AS77: =+AS75/AR75-1 -> 0.051602316 | AT77: -- | AU77: =+AU75/AS75-1 -> 0.062373802 | AV77: =+AV75/AU75-1 -> -0.022059429 | AW77: =+AW75/AV75-1 -> 0.0075467792 | AX77: =+AX75/AW75-1 -> 0.017372086 | AY77: -- | AZ77: =+AZ75/AX75-1 -> 0.20538146 | BA77: =+BA75/AZ75-1 -> 0.17083326 | BB77: =+BB75/BA75-1 -> 0.044819139 | BC77: =+BC75/BB75-1 -> 0.041207968 | BD77: -- | BE77: =+BE75/BC75-1 -> 0.095973407 | BF77: =+BF75/BE75-1 -> 0.007749974 | BG77: =+BG75/BF75-1 -> 0.0010561379 | BH77: =+BH75/BG75-1 -> 0.059533692 | BI77: -- | BJ77: =+BJ75/BH75-1 -> -0.081541359 | BK77: =+BK75/BJ75-1 -> -0.03446524 | BL77: =+BL75/BK75-1 -> -0.022083046 | BM77: =+BM75/BL75-1 -> 0.0079574436 | BN77: -- | BO77: =+BO75/BM75-1 -> 0.18707599 | BP77: =+BP75/BO75-1 -> -0.062177253 | BQ77: =+BQ75/BP75-1 -> 0.020793092 | BR77: =+BR75/BQ75-1 -> -0.015534096 | BS77: -- | BT77: =+BT75/BR75-1 -> 0.14466851 | BU77: =+BU75/BT75-1 -> -0.042953181 | BV77: =+BV75/BU75-1 -> 0.0031976849 | BW77: =+BW75/BV75-1 -> -0.014495652 | BX77: -- | BY77: =+BY75/BW75-1 -> 0.1389118 | BZ77: =+BZ75/BY75-1 -> -0.052688165 | CA77: =+CA75/BZ75-1 -> 0.016212945 | CB77: =+CB75/CA75-1 -> -0.019189826 | CC77: -- | CD77: =+CD75/CB75-1 -> 0.13106189 | CE77: =+CE75/CD75-1 -> -0.048873722 | CF77: =+CF75/CE75-1 -> 0.014327776 | CG77: =+CG75/CF75-1 -> -0.017168201 | CH77: -- | CI77: =+CI75/CG75-1 -> 0.12399738 | CJ77: =+CJ75/CI75-1 -> -0.046693451 | CK77: =+CK75/CJ75-1 -> 0.01400107 | CL77: =+CL75/CK75-1 -> -0.0166754 | CM77: -- | CN77: =+CN75/CL75-1 -> 0.11775392 | CO77: =+CO75/CN75-1 -> -0.044135083 | CP77: =+CP75/CO75-1 -> 0.01306641 | CQ77: =+CQ75/CP75-1 -> -0.015609119 | CR77: -- | CS77: =+CS75/CQ75-1 -> 0.11213114 | CT77: =+CT75/CS75-1 -> -0.042097185 | CU77: =+CU75/CT75-1 -> 0.012528179 | CV77: =+CV75/CU75-1 -> -0.014942288 | CW77: -- | CX77: =+CX75/CV75-1 -> 0.10707047 | CY77: =+CY75/CX75-1 -> -0.040105581 | CZ77: =+CZ75/CY75-1 -> 0.011894944 | DA77: =+DA75/CZ75-1 -> -0.014195222 | DB77: --
A79: United States
A80: High Risk Pregnancies | B80: =+F80/4 -> 225535 | C80: =+F80/4 -> 225535 | D80: =+F80/4 -> 225535 | E80: =+F80/4 -> 225535 | F80: 902140 | G80: =+B80*(1+G81) -> 227790.35 | H80: =+C80*(1+H81) -> 227790.35 | I80: =+D80*(1+I81) -> 227790.35 | J80: =+E80*(1+J81) -> 227790.35 | K80: =+G80+H80+I80+J80 -> 911161.4 | L80: =+G80*(1+L81) -> 230068.25 | M80: =+H80*(1+M81) -> 230068.25 | N80: =+I80*(1+N81) -> 230068.25 | O80: =+J80*(1+O81) -> 230068.25 | P80: =+L80+M80+N80+O80 -> 920273.01 | Q80: =+L80*(1+Q81) -> 232368.94 | R80: =+M80*(1+R81) -> 232368.94 | S80: =+N80*(1+S81) -> 232368.94 | T80: =+O80*(1+T81) -> 232368.94 | U80: =+Q80+R80+S80+T80 -> 929475.74 | V80: =+Q80*(1+V81) -> 234692.63 | W80: =+R80*(1+W81) -> 234692.63 | X80: =+S80*(1+X81) -> 234692.63 | Y80: =+T80*(1+Y81) -> 234692.63 | Z80: =+V80+W80+X80+Y80 -> 938770.5 | AA80: =+V80*(1+AA81) -> 237039.55 | AB80: =+W80*(1+AB81) -> 237039.55 | AC80: =+X80*(1+AC81) -> 237039.55 | AD80: =+Y80*(1+AD81) -> 237039.55 | AE80: =+AA80+AB80+AC80+AD80 -> 948158.21 | AF80: =+AA80*(1+AF81) -> 239409.95 | AG80: =+AB80*(1+AG81) -> 239409.95 | AH80: =+AC80*(1+AH81) -> 239409.95 | AI80: =+AD80*(1+AI81) -> 239409.95 | AJ80: =+AF80+AG80+AH80+AI80 -> 957639.79 | AK80: =+AF80*(1+AK81) -> 241804.05 | AL80: =+AG80*(1+AL81) -> 241804.05 | AM80: =+AH80*(1+AM81) -> 241804.05 | AN80: =+AI80*(1+AN81) -> 241804.05 | AO80: =+AK80+AL80+AM80+AN80 -> 967216.19 | AP80: =+AK80*(1+AP81) -> 244222.09 | AQ80: =+AL80*(1+AQ81) -> 244222.09 | AR80: =+AM80*(1+AR81) -> 244222.09 | AS80: =+AN80*(1+AS81) -> 244222.09 | AT80: =+AP80+AQ80+AR80+AS80 -> 976888.35 | AU80: =+AP80*(1+AU81) -> 246664.31 | AV80: =+AQ80*(1+AV81) -> 246664.31 | AW80: =+AR80*(1+AW81) -> 246664.31 | AX80: =+AS80*(1+AX81) -> 246664.31 | AY80: =+AU80+AV80+AW80+AX80 -> 986657.23 | AZ80: =+AU80*(1+AZ81) -> 249130.95 | BA80: =+AV80*(1+BA81) -> 249130.95 | BB80: =+AW80*(1+BB81) -> 249130.95 | BC80: =+AX80*(1+BC81) -> 249130.95 | BD80: =+AZ80+BA80+BB80+BC80 -> 996523.8 | BE80: =+AZ80*(1+BE81) -> 251622.26 | BF80: =+BA80*(1+BF81) -> 251622.26 | BG80: =+BB80*(1+BG81) -> 251622.26 | BH80: =+BC80*(1+BH81) -> 251622.26 | BI80: =+BE80+BF80+BG80+BH80 -> 1006489 | BJ80: =+BE80*(1+BJ81) -> 254138.48 | BK80: =+BF80*(1+BK81) -> 254138.48 | BL80: =+BG80*(1+BL81) -> 254138.48 | BM80: =+BH80*(1+BM81) -> 254138.48 | BN80: =+BI80*(1+BN81) -> 1016553.9 | BO80: =+BJ80*(1+BO81) -> 256679.87 | BP80: =+BK80*(1+BP81) -> 256679.87 | BQ80: =+BL80*(1+BQ81) -> 256679.87 | ... BW80: =+BR80*(1+BW81) -> 259246.67 | BX80: =+BT80+BU80+BV80+BW80 -> 1036986.7 | BY80: =+BT80*(1+BY81) -> 261839.13 | BZ80: =+BU80*(1+BZ81) -> 261839.13 | CA80: =+BV80*(1+CA81) -> 261839.13 | CB80: =+BW80*(1+CB81) -> 261839.13 | CC80: =+BY80+BZ80+CA80+CB80 -> 1047356.5 | CD80: =+BY80*(1+CD81) -> 264457.52 | CE80: =+BZ80*(1+CE81) -> 264457.52 | CF80: =+CA80*(1+CF81) -> 264457.52 | CG80: =+CB80*(1+CG81) -> 264457.52 | CH80: =+CD80+CE80+CF80+CG80 -> 1057830.1 | CI80: =+CD80*(1+CI81) -> 267102.1 | CJ80: =+CE80*(1+CJ81) -> 267102.1 | CK80: =+CF80*(1+CK81) -> 267102.1 | CL80: =+CG80*(1+CL81) -> 267102.1 | CM80: =+CI80+CJ80+CK80+CL80 -> 1068408.4 | CN80: =+CI80*(1+CN81) -> 269773.12 | CO80: =+CJ80*(1+CO81) -> 269773.12 | CP80: =+CK80*(1+CP81) -> 269773.12 | CQ80: =+CL80*(1+CQ81) -> 269773.12 | CR80: =+CN80+CO80+CP80+CQ80 -> 1079092.5 | CS80: =+CN80*(1+CS81) -> 272470.85 | CT80: =+CO80*(1+CT81) -> 272470.85 | CU80: =+CP80*(1+CU81) -> 272470.85 | CV80: =+CQ80*(1+CV81) -> 272470.85 | CW80: =+CS80+CT80+CU80+CV80 -> 1089883.4 | CX80: =+CS80*(1+CX81) -> 275195.56 | CY80: =+CT80*(1+CY81) -> 275195.56 | CZ80: =+CU80*(1+CZ81) -> 275195.56 | DA80: =+CV80*(1+DA81) -> 275195.56 | DB80: =+CX80+CY80+CZ80+DA80 -> 1100782.2
A81: % yoy | B81: -- | C81: -- | D81: -- | E81: -- | F81: -- | G81: 0.01 | H81: 0.01 | I81: 0.01 | J81: 0.01 | K81: =+K80/F80-1 -> 0.01 | L81: 0.01 | M81: 0.01 | N81: 0.01 | O81: 0.01 | P81: =+P80/K80-1 -> 0.01 | Q81: 0.01 | R81: 0.01 | S81: 0.01 | T81: 0.01 | U81: =+U80/P80-1 -> 0.01 | V81: 0.01 | W81: 0.01 | X81: 0.01 | Y81: 0.01 | Z81: =+Z80/U80-1 -> 0.01 | AA81: 0.01 | AB81: 0.01 | AC81: 0.01 | AD81: 0.01 | AE81: =+AE80/Z80-1 -> 0.01 | AF81: 0.01 | AG81: 0.01 | AH81: 0.01 | AI81: 0.01 | AJ81: =+AJ80/AE80-1 -> 0.01 | AK81: 0.01 | AL81: 0.01 | AM81: 0.01 | AN81: 0.01 | AO81: =+AO80/AJ80-1 -> 0.01 | AP81: 0.01 | AQ81: 0.01 | AR81: 0.01 | AS81: 0.01 | AT81: =+AT80/AO80-1 -> 0.01 | AU81: 0.01 | AV81: 0.01 | AW81: 0.01 | AX81: 0.01 | AY81: =+AY80/AT80-1 -> 0.01 | AZ81: 0.01 | BA81: 0.01 | BB81: 0.01 | BC81: 0.01 | BD81: =+BD80/AY80-1 -> 0.01 | BE81: 0.01 | BF81: 0.01 | BG81: 0.01 | BH81: 0.01 | BI81: =+BI80/BD80-1 -> 0.01 | BJ81: 0.01 | BK81: 0.01 | BL81: 0.01 | BM81: 0.01 | BN81: 0.01 | BO81: 0.01 | BP81: 0.01 | BQ81: 0.01 | BR81: 0.01 | BS81: 0.01 | BT81: 0.01 | BU81: 0.01 | BV81: 0.01 | BW81: 0.01 | BX81: =+BX80/BS80-1 -> 0.01 | BY81: 0.01 | BZ81: 0.01 | CA81: 0.01 | CB81: 0.01 | CC81: =+CC80/BX80-1 -> 0.01 | CD81: 0.01 | CE81: 0.01 | CF81: 0.01 | CG81: 0.01 | CH81: =+CH80/CC80-1 -> 0.01 | CI81: 0.01 | CJ81: 0.01 | CK81: 0.01 | CL81: 0.01 | CM81: =+CM80/CH80-1 -> 0.01 | CN81: 0.01 | CO81: 0.01 | CP81: 0.01 | CQ81: 0.01 | CR81: =+CR80/CM80-1 -> 0.01 | CS81: 0.01 | CT81: 0.01 | CU81: 0.01 | CV81: 0.01 | CW81: =+CW80/CR80-1 -> 0.01 | CX81: 0.01 | CY81: 0.01 | CZ81: 0.01 | DA81: 0.01 | DB81: =+DB80/CW80-1 -> 0.01
A82: % total | B82: =+B80/B86 -> 0.17910623 | C82: =+C80/C86 -> 0.17910623 | D82: =+D80/D86 -> 0.17910623 | E82: =+E80/E86 -> 0.17910623 | F82: =+F80/F86 -> 0.17910623 | G82: =+G80/G86 -> 0.17910623 | H82: =+H80/H86 -> 0.17910623 | I82: =+I80/I86 -> 0.17910623 | ... DB82: =+DB80/DB86 -> 0.17910623
A83: Average / Low Risk Pregnancies | B83: =+F83/4 -> 1033689.8 | C83: =+F83/4 -> 1033689.8 | D83: =+F83/4 -> 1033689.8 | E83: =+F83/4 -> 1033689.8 | F83: 4134759 | G83: =+B83*(1+G84) -> 1044026.6 | H83: =+C83*(1+H84) -> 1044026.6 | I83: =+D83*(1+I84) -> 1044026.6 | J83: =+E83*(1+J84) -> 1044026.6 | K83: =+G83+H83+I83+J83 -> 4176106.6 | L83: =+G83*(1+L84) -> 1054466.9 | M83: =+H83*(1+M84) -> 1054466.9 | N83: =+I83*(1+N84) -> 1054466.9 | O83: =+J83*(1+O84) -> 1054466.9 | P83: =+L83+M83+N83+O83 -> 4217867.7 | Q83: =+L83*(1+Q84) -> 1065011.6 | R83: =+M83*(1+R84) -> 1065011.6 | S83: =+N83*(1+S84) -> 1065011.6 | T83: =+O83*(1+T84) -> 1065011.6 | U83: =+Q83+R83+S83+T83 -> 4260046.3 | V83: =+Q83*(1+V84) -> 1075661.7 | W83: =+R83*(1+W84) -> 1075661.7 | X83: =+S83*(1+X84) -> 1075661.7 | Y83: =+T83*(1+Y84) -> 1075661.7 | Z83: =+V83+W83+X83+Y83 -> 4302646.8 | AA83: =+V83*(1+AA84) -> 1086418.3 | AB83: =+W83*(1+AB84) -> 1086418.3 | AC83: =+X83*(1+AC84) -> 1086418.3 | AD83: =+Y83*(1+AD84) -> 1086418.3 | AE83: =+AA83+AB83+AC83+AD83 -> 4345673.3 | AF83: =+AA83*(1+AF84) -> 1097282.5 | AG83: =+AB83*(1+AG84) -> 1097282.5 | AH83: =+AC83*(1+AH84) -> 1097282.5 | AI83: =+AD83*(1+AI84) -> 1097282.5 | AJ83: =+AF83+AG83+AH83+AI83 -> 4389130 | AK83: =+AF83*(1+AK84) -> 1108255.3 | AL83: =+AG83*(1+AL84) -> 1108255.3 | AM83: =+AH83*(1+AM84) -> 1108255.3 | AN83: =+AI83*(1+AN84) -> 1108255.3 | AO83: =+AK83+AL83+AM83+AN83 -> 4433021.3 | AP83: =+AK83*(1+AP84) -> 1119337.9 | AQ83: =+AL83*(1+AQ84) -> 1119337.9 | AR83: =+AM83*(1+AR84) -> 1119337.9 | AS83: =+AN83*(1+AS84) -> 1119337.9 | AT83: =+AP83+AQ83+AR83+AS83 -> 4477351.5 | AU83: =+AP83*(1+AU84) -> 1130531.3 | AV83: =+AQ83*(1+AV84) -> 1130531.3 | AW83: =+AR83*(1+AW84) -> 1130531.3 | AX83: =+AS83*(1+AX84) -> 1130531.3 | AY83: =+AU83+AV83+AW83+AX83 -> 4522125 | AZ83: =+AU83*(1+AZ84) -> 1141836.6 | BA83: =+AV83*(1+BA84) -> 1141836.6 | BB83: =+AW83*(1+BB84) -> 1141836.6 | BC83: =+AX83*(1+BC84) -> 1141836.6 | BD83: =+AZ83+BA83+BB83+BC83 -> 4567346.3 | BE83: =+AZ83*(1+BE84) -> 1153254.9 | BF83: =+BA83*(1+BF84) -> 1153254.9 | BG83: =+BB83*(1+BG84) -> 1153254.9 | BH83: =+BC83*(1+BH84) -> 1153254.9 | BI83: =+BE83+BF83+BG83+BH83 -> 4613019.7 | BJ83: =+BE83*(1+BJ84) -> 1164787.5 | BK83: =+BF83*(1+BK84) -> 1164787.5 | BL83: =+BG83*(1+BL84) -> 1164787.5 | BM83: =+BH83*(1+BM84) -> 1164787.5 | BN83: =+BI83*(1+BN84) -> 4659149.9 | BO83: =+BJ83*(1+BO84) -> 1176435.4 | BP83: =+BK83*(1+BP84) -> 1176435.4 | BQ83: =+BL83*(1+BQ84) -> 1176435.4 | ... BW83: =+BR83*(1+BW84) -> 1188199.7 | BX83: =+BT83+BU83+BV83+BW83 -> 4752798.8 | BY83: =+BT83*(1+BY84) -> 1200081.7 | BZ83: =+BU83*(1+BZ84) -> 1200081.7 | CA83: =+BV83*(1+CA84) -> 1200081.7 | CB83: =+BW83*(1+CB84) -> 1200081.7 | CC83: =+BY83+BZ83+CA83+CB83 -> 4800326.8 | CD83: =+BY83*(1+CD84) -> 1212082.5 | CE83: =+BZ83*(1+CE84) -> 1212082.5 | CF83: =+CA83*(1+CF84) -> 1212082.5 | CG83: =+CB83*(1+CG84) -> 1212082.5 | CH83: =+CD83+CE83+CF83+CG83 -> 4848330.1 | CI83: =+CD83*(1+CI84) -> 1224203.4 | CJ83: =+CE83*(1+CJ84) -> 1224203.4 | CK83: =+CF83*(1+CK84) -> 1224203.4 | CL83: =+CG83*(1+CL84) -> 1224203.4 | CM83: =+CI83+CJ83+CK83+CL83 -> 4896813.4 | CN83: =+CI83*(1+CN84) -> 1236445.4 | CO83: =+CJ83*(1+CO84) -> 1236445.4 | CP83: =+CK83*(1+CP84) -> 1236445.4 | CQ83: =+CL83*(1+CQ84) -> 1236445.4 | CR83: =+CN83+CO83+CP83+CQ83 -> 4945781.5 | CS83: =+CN83*(1+CS84) -> 1248809.8 | CT83: =+CO83*(1+CT84) -> 1248809.8 | CU83: =+CP83*(1+CU84) -> 1248809.8 | CV83: =+CQ83*(1+CV84) -> 1248809.8 | CW83: =+CS83+CT83+CU83+CV83 -> 4995239.4 | CX83: =+CS83*(1+CX84) -> 1261297.9 | CY83: =+CT83*(1+CY84) -> 1261297.9 | CZ83: =+CU83*(1+CZ84) -> 1261297.9 | DA83: =+CV83*(1+DA84) -> 1261297.9 | DB83: =+CX83+CY83+CZ83+DA83 -> 5045191.7
A84: % yoy | B84: -- | C84: -- | D84: -- | E84: -- | F84: -- | G84: 0.01 | H84: 0.01 | I84: 0.01 | J84: 0.01 | K84: =+K83/F83-1 -> 0.01 | L84: 0.01 | M84: 0.01 | N84: 0.01 | O84: 0.01 | P84: =+P83/K83-1 -> 0.01 | Q84: 0.01 | R84: 0.01 | S84: 0.01 | T84: 0.01 | U84: =+U83/P83-1 -> 0.01 | V84: 0.01 | W84: 0.01 | X84: 0.01 | Y84: 0.01 | Z84: =+Z83/U83-1 -> 0.01 | AA84: 0.01 | AB84: 0.01 | AC84: 0.01 | AD84: 0.01 | AE84: =+AE83/Z83-1 -> 0.01 | AF84: 0.01 | AG84: 0.01 | AH84: 0.01 | AI84: 0.01 | AJ84: =+AJ83/AE83-1 -> 0.01 | AK84: 0.01 | AL84: 0.01 | AM84: 0.01 | AN84: 0.01 | AO84: =+AO83/AJ83-1 -> 0.01 | AP84: 0.01 | AQ84: 0.01 | AR84: 0.01 | AS84: 0.01 | AT84: =+AT83/AO83-1 -> 0.01 | AU84: 0.01 | AV84: 0.01 | AW84: 0.01 | AX84: 0.01 | AY84: =+AY83/AT83-1 -> 0.01 | AZ84: 0.01 | BA84: 0.01 | BB84: 0.01 | BC84: 0.01 | BD84: =+BD83/AY83-1 -> 0.01 | BE84: 0.01 | BF84: 0.01 | BG84: 0.01 | BH84: 0.01 | BI84: =+BI83/BD83-1 -> 0.01 | BJ84: 0.01 | BK84: 0.01 | BL84: 0.01 | BM84: 0.01 | BN84: 0.01 | BO84: 0.01 | BP84: 0.01 | BQ84: 0.01 | BR84: 0.01 | BS84: 0.01 | BT84: 0.01 | BU84: 0.01 | BV84: 0.01 | BW84: 0.01 | BX84: =+BX83/BS83-1 -> 0.01 | BY84: 0.01 | BZ84: 0.01 | CA84: 0.01 | CB84: 0.01 | CC84: =+CC83/BX83-1 -> 0.01 | CD84: 0.01 | CE84: 0.01 | CF84: 0.01 | CG84: 0.01 | CH84: =+CH83/CC83-1 -> 0.01 | CI84: 0.01 | CJ84: 0.01 | CK84: 0.01 | CL84: 0.01 | CM84: =+CM83/CH83-1 -> 0.01 | CN84: 0.01 | CO84: 0.01 | CP84: 0.01 | CQ84: 0.01 | CR84: =+CR83/CM83-1 -> 0.01 | CS84: 0.01 | CT84: 0.01 | CU84: 0.01 | CV84: 0.01 | CW84: =+CW83/CR83-1 -> 0.01 | CX84: 0.01 | CY84: 0.01 | CZ84: 0.01 | DA84: 0.01 | DB84: =+DB83/CW83-1 -> 0.01
A85: % total | B85: =+B83/B86 -> 0.82089377 | C85: =+C83/C86 -> 0.82089377 | D85: =+D83/D86 -> 0.82089377 | E85: =+E83/E86 -> 0.82089377 | F85: =+F83/F86 -> 0.82089377 | G85: =+G83/G86 -> 0.82089377 | H85: =+H83/H86 -> 0.82089377 | I85: =+I83/I86 -> 0.82089377 | ... DB85: =+DB83/DB86 -> 0.82089377
A86: Total Market | B86: =+B80+B83 -> 1259224.8 | C86: =+C80+C83 -> 1259224.8 | D86: =+D80+D83 -> 1259224.8 | E86: =+E80+E83 -> 1259224.8 | F86: =+F80+F83 -> 5036899 | G86: =+G80+G83 -> 1271817 | H86: =+H80+H83 -> 1271817 | I86: =+I80+I83 -> 1271817 | ... DB86: =+DB80+DB83 -> 6145974
A87: % yoy | B87: -- | C87: -- | D87: -- | E87: -- | F87: -- | G87: =+G86/B86-1 -> 0.01 | H87: =+H86/C86-1 -> 0.01 | I87: =+I86/D86-1 -> 0.01 | J87: =+J86/E86-1 -> 0.01 | K87: =+K86/F86-1 -> 0.01 | L87: =+L86/G86-1 -> 0.01 | M87: =+M86/H86-1 -> 0.01 | N87: =+N86/I86-1 -> 0.01 | ... DB87: =+DB86/CW86-1 -> 0.01
A89: High Risk Tests | B89: =+B91*B80 -> 21876.895 | C89: =+C91*C80 -> 25485.455 | D89: =+D91*D80 -> 22102.43 | E89: =+E91*E80 -> 18719.405 | F89: =+B89+C89+D89+E89 -> 88184.185 | G89: =+G91*G80 -> 17084.276 | H89: =+H91*H80 -> 17084.276 | I89: =+I91*I80 -> 15945.325 | J89: =+J91*J80 -> 15945.325 | K89: =+G89+H89+I89+J89 -> 66059.201 | L89: =+L91*L80 -> 20015.938 | M89: =+M91*M80 -> 17255.119 | N89: =+N91*N80 -> 20476.075 | O89: =+O91*O80 -> 20476.075 | P89: =+L89+M89+N89+O89 -> 78223.206 | Q89: =+Q91*Q80 -> 20216.097 | R89: =+R91*R80 -> 18821.884 | S89: =+S91*S80 -> 18845.121 | T89: =+T91*T80 -> 20239.334 | U89: =+Q89+R89+S89+T89 -> 78122.436 | V89: =+V91*V80 -> 21591.722 | W89: =+W91*W80 -> 21063.663 | X89: =+X91*X80 -> 21122.336 | Y89: =+Y91*Y80 -> 21873.353 | Z89: =+V89+W89+X89+Y89 -> 85651.074 | AA89: =+AA91*AA80 -> 22828.568 | AB89: =+AB91*AB80 -> 18442.862 | AC89: =+AC91*AC80 -> 18370.565 | AD89: =+AD91*AD80 -> 18489.085 | AE89: =+AA89+AB89+AC89+AD89 -> 78131.081 | AF89: =+AF91*AF80 -> 22504.535 | AG89: =+AG91*AG80 -> 23510.057 | AH89: =+AH91*AH80 -> 23462.175 | AI89: =+AI91*AI80 -> 23940.995 | AJ89: =+AF89+AG89+AH89+AI89 -> 93417.761 | AK89: =+AK91*AK80 -> 30950.918 | AL89: =+AL91*AL80 -> 32633.149 | AM89: =+AM91*AM80 -> 35113.575 | AN89: =+AN91*AN80 -> 36270.607 | AO89: =+AK89+AL89+AM89+AN89 -> 134968.25 | AP89: =+AP91*AP80 -> 37121.757 | AQ89: =+AQ91*AQ80 -> 38867.945 | AR89: =+AR91*AR80 -> 40025.558 | AS89: =+AS91*AS80 -> 47623.307 | AT89: =+AP89+AQ89+AR89+AS89 -> 163638.57 | AU89: =+AU91*AU80 -> 49332.862 | AV89: =+AV91*AV80 -> 47359.547 | AW89: =+AW91*AW80 -> 46866.219 | AX89: =+AX91*AX80 -> 46126.226 | AY89: =+AU89+AV89+AW89+AX89 -> 189684.85 | AZ89: =+AZ91*AZ80 -> 46714.545 | BA89: =+BA91*BA80 -> 54808.809 | BB89: =+BB91*BB80 -> 52815.762 | BC89: =+BC91*BC80 -> 52317.5 | BD89: =+AZ89+BA89+BB89+BC89 -> 206656.62 | BE89: =+BE91*BE80 -> 53406.825 | BF89: =+BF91*BF80 -> 52214.135 | BG89: =+BG91*BG80 -> 59131.231 | BH89: =+BH91*BH80 -> 57369.875 | BI89: =+BE89+BF89+BG89+BH89 -> 222122.07 | BJ89: =+BJ91*BJ80 -> 54639.774 | BK89: =+BK91*BK80 -> 54893.912 | BL89: =+BL91*BL80 -> 57181.159 | BM89: =+BM91*BM80 -> 62263.928 | BN89: =SUM(BJ89:BM89) -> 228978.77 | BO89: =+BO91*BO80 -> 66223.406 | BP89: =+BP91*BP80 -> 63464.097 | BQ89: =+BQ91*BQ80 -> 68790.205 | BR89: =+BR91*BR80 -> 69175.224 | BS89: =+BS91*BS80 -> 290561.61 | BT89: =+BT91*BT80 -> 72459.443 | BU89: =+BU91*BU80 -> 75959.273 | BV89: =+BV91*BV80 -> 75051.91 | BW89: =+BW91*BW80 -> 75440.78 | BX89: =+BT89+BU89+BV89+BW89 -> 298911.41 | BY89: =+BY91*BY80 -> 80122.775 | BZ89: =+BZ91*BZ80 -> 78093.522 | CA89: =+CA91*CA80 -> 82741.166 | CB89: =+CB91*CB80 -> 80711.913 | CC89: =+BY89+BZ89+CA89+CB89 -> 321669.38 | CD89: =+CD91*CD80 -> 85485.895 | CE89: =+CE91*CE80 -> 83866.093 | CF89: =+CF91*CF80 -> 88130.47 | CG89: =+CG91*CG80 -> 86510.668 | CH89: =+CD89+CE89+CF89+CG89 -> 343993.13 | CI89: =+CI91*CI80 -> 91382.306 | CJ89: =+CJ91*CJ80 -> 89529.285 | CK89: =+CK91*CK80 -> 94053.327 | CL89: =+CL91*CL80 -> 92200.306 | CM89: =+CI89+CJ89+CK89+CL89 -> 367165.22 | CN89: =+CN91*CN80 -> 97168.906 | CO89: =+CO91*CO80 -> 95406.95 | CP89: =+CP91*CP80 -> 99866.637 | CQ89: =+CQ91*CQ80 -> 98104.682 | CR89: =+CN89+CO89+CP89+CQ89 -> 390547.18 | CS89: =+CS91*CS80 -> 103172.79 | CT89: =+CT91*CT80 -> 101337.87 | CU89: =+CU91*CU80 -> 105897.5 | CV89: =+CV91*CV80 -> 104062.58 | CW89: =+CS89+CT89+CU89+CV89 -> 414470.74 | CX89: =+CX91*CX80 -> 109231.14 | CY89: =+CY91*CY80 -> 107405.82 | CZ89: =+CZ91*CZ80 -> 111983.09 | DA89: =+DA91*DA80 -> 110157.77 | DB89: =+CX89+CY89+CZ89+DA89 -> 438777.82
A90: % yoy | B90: -- | C90: -- | D90: -- | E90: -- | F90: -- | G90: =+G89/B89-1 -> -0.21907216 | H90: =+H89/C89-1 -> -0.32964602 | I90: =+I89/D89-1 -> -0.27857143 | J90: =+J89/E89-1 -> -0.14819277 | K90: =+K89/F89-1 -> -0.25089514 | L90: =+L89/G89-1 -> 0.1716 | M90: =+M89/H89-1 -> 0.01 | N90: =+N89/I89-1 -> 0.28414286 | ... DB90: =+DB89/CW89-1 -> 0.058646075
A91: % HR Pregnancies | B91: 0.097 | C91: 0.113 | D91: 0.098 | E91: 0.083 | F91: =+F89/F80 -> 0.09775 | G91: 0.075 | H91: 0.075 | I91: 0.07 | J91: 0.07 | K91: =+K89/K80 -> 0.0725 | L91: 0.087 | M91: 0.075 | N91: 0.089 | O91: 0.089 | P91: =+P89/P80 -> 0.085 | Q91: 0.087 | R91: 0.081 | S91: =+R91+0.0001 -> 0.0811 | T91: =+S91+0.006 -> 0.0871 | U91: =+U89/U80 -> 0.08405 | V91: 0.092 | W91: 0.08975 | X91: 0.09 | Y91: =X91+0.0015+0.0017 -> 0.0932 | Z91: =+Z89/Z80 -> 0.0912375 | AA91: 0.096307 | AB91: 0.077805 | AC91: 0.0775 | AD91: 0.078 | AE91: =+AE89/AE80 -> 0.082403 | AF91: 0.094 | AG91: 0.0982 | AH91: 0.098 | AI91: 0.1 | AJ91: =+AJ89/AJ80 -> 0.09755 | AK91: 0.128 | AL91: 0.134957 | AM91: 0.145215 | AN91: 0.15 | AO91: =+AO89/AO80 -> 0.139543 | AP91: 0.152 | AQ91: 0.15915 | AR91: 0.16389 | AS91: 0.195 | AT91: =+AT89/AT80 -> 0.16751 | AU91: 0.2 | AV91: 0.192 | AW91: 0.19 | AX91: 0.187 | AY91: =+AY89/AY80 -> 0.19225 | AZ91: =+AT91+0.02 -> 0.18751 | BA91: =+AU91+0.02 -> 0.22 | BB91: =+AV91+0.02 -> 0.212 | BC91: =+AW91+0.02 -> 0.21 | BD91: =+BD89/BD80 -> 0.2073775 | BE91: =+AY91+0.02 -> 0.21225 | BF91: =+AZ91+0.02 -> 0.20751 | BG91: =+BA91+0.015 -> 0.235 | BH91: 0.228 | BI91: =+BI89/BI80 -> 0.22069 | BJ91: 0.215 | BK91: 0.216 | BL91: 0.225 | BM91: 0.245 | BN91: =+BN89/BN80 -> 0.22525 | BO91: =+BM91+0.013 -> 0.258 | BP91: =+BN91+0.022 -> 0.24725 | BQ91: =+BO91+0.01 -> 0.268 | BR91: =+BQ91+0.0015 -> 0.2695 | BS91: =+BQ91+0.015 -> 0.283 | BT91: =+BR91+0.01 -> 0.2795 | BU91: =+BS91+0.01 -> 0.293 | BV91: =+BT91+0.01 -> 0.2895 | BW91: =+BV91+0.0015 -> 0.291 | BX91: =+BX89/BX80 -> 0.28825 | BY91: =+BW91+0.015 -> 0.306 | BZ91: =+BX91+0.01 -> 0.29825 | CA91: =+BY91+0.01 -> 0.316 | CB91: =+BZ91+0.01 -> 0.30825 | CC91: =+CC89/CC80 -> 0.307125 | CD91: =+CB91+0.015 -> 0.32325 | CE91: =+CC91+0.01 -> 0.317125 | CF91: =+CD91+0.01 -> 0.33325 | CG91: =+CE91+0.01 -> 0.327125 | CH91: =+CH89/CH80 -> 0.3251875 | CI91: =+CG91+0.015 -> 0.342125 | CJ91: =+CH91+0.01 -> 0.3351875 | CK91: =+CI91+0.01 -> 0.352125 | CL91: =+CJ91+0.01 -> 0.3451875 | CM91: =+CM89/CM80 -> 0.34365625 | CN91: =+CL91+0.015 -> 0.3601875 | CO91: =+CM91+0.01 -> 0.35365625 | CP91: =+CN91+0.01 -> 0.3701875 | CQ91: =+CO91+0.01 -> 0.36365625 | CR91: =+CR89/CR80 -> 0.36192188 | CS91: =+CQ91+0.015 -> 0.37865625 | CT91: =+CR91+0.01 -> 0.37192188 | CU91: =+CS91+0.01 -> 0.38865625 | CV91: =+CT91+0.01 -> 0.38192188 | CW91: =+CW89/CW80 -> 0.38028906 | CX91: =+CV91+0.015 -> 0.39692188 | CY91: =+CW91+0.01 -> 0.39028906 | CZ91: =+CX91+0.01 -> 0.40692188 | DA91: =+CY91+0.01 -> 0.40028906 | DB91: =+DB89/DB80 -> 0.39860547
A92: Average / Low Risk Tests | B92: =+B94*B83 -> 10336.898 | C92: =+C94*C83 -> 13437.967 | D92: =+D94*D83 -> 17572.726 | E92: =+E94*E83 -> 20673.795 | F92: =+B92+C92+D92+E92 -> 62021.385 | G92: =+G94*G83 -> 26100.666 | H92: =+H94*H83 -> 29232.746 | I92: =+I94*I83 -> 31320.799 | J92: =+J94*J83 -> 40717.039 | K92: =+G92+H92+I92+J92 -> 127371.25 | L92: =+L94*L83 -> 45342.077 | M92: =+M94*M83 -> 44287.61 | N92: =+N94*N83 -> 46396.544 | O92: =+O94*O83 -> 46396.544 | P92: =+L92+M92+N92+O92 -> 182422.78 | Q92: =+Q94*Q83 -> 44730.486 | R92: =+R94*R83 -> 42600.463 | S92: =+S94*S83 -> 42600.463 | T92: =+T94*T83 -> 45795.498 | U92: =+Q92+R92+S92+T92 -> 175726.91 | V92: =+V94*V83 -> 57547.901 | W92: =+W94*W83 -> 59376.526 | X92: =+X94*X83 -> 59161.393 | Y92: =+Y94*Y83 -> 59645.441 | Z92: =+V92+W92+X92+Y92 -> 235731.26 | AA92: =+AA94*AA83 -> 69096.205 | AB92: =+AB94*AB83 -> 65619.666 | AC92: =+AC94*AC83 -> 64247.52 | AD92: =+AD94*AD83 -> 64098.681 | AE92: =+AA92+AB92+AC92+AD92 -> 263062.07 | AF92: =+AF94*AF83 -> 72420.645 | AG92: =+AG94*AG83 -> 75712.492 | AH92: =+AH94*AH83 -> 89977.165 | AI92: =+AI94*AI83 -> 98755.425 | AJ92: =+AF92+AG92+AH92+AI92 -> 336865.73 | AK92: =+AK94*AK83 -> 124124.6 | AL92: =+AL94*AL83 -> 134098.89 | AM92: =+AM94*AM83 -> 144073.19 | AN92: =+AN94*AN83 -> 141856.68 | AO92: =+AK92+AL92+AM92+AN92 -> 544153.36 | AP92: =+AP94*AP83 -> 170139.36 | AQ92: =+AQ94*AQ83 -> 165662.01 | AR92: =+AR94*AR83 -> 167900.68 | AS92: =+AS94*AS83 -> 173497.37 | AT92: =+AP92+AQ92+AR92+AS92 -> 677199.42 | AU92: =+AU94*AU83 -> 173536.55 | AV92: =+AV94*AV83 -> 169014.42 | AW92: =+AW94*AW83 -> 171275.49 | AX92: =+AX94*AX83 -> 176928.14 | AY92: =+AU92+AV92+AW92+AX92 -> 690754.6 | AZ92: =+AZ94*AZ83 -> 198108.64 | BA92: =+BA94*BA83 -> 194112.22 | BB92: =+BB94*BB83 -> 194112.22 | BC92: =+BC94*BC83 -> 194112.22 | BD92: =+AZ92+BA92+BB92+BC92 -> 780445.29 | BE92: =+BE94*BE83 -> 219118.44 | BF92: =+BF94*BF83 -> 207585.89 | BG92: =+BG94*BG83 -> 196053.34 | BH92: =+BH94*BH83 -> 191440.32 | BI92: =+BE92+BF92+BG92+BH92 -> 814197.98 | BJ92: =+BJ94*BJ83 -> 215485.68 | BK92: =+BK94*BK83 -> 209661.75 | BL92: =+BL94*BL83 -> 198013.87 | BM92: =+BM94*BM83 -> 193354.72 | BN92: =SUM(BJ92:BM92) -> 816516.03 | BO92: =+BO94*BO83 -> 247051.43 | BP92: =+BP94*BP83 -> 223522.72 | BQ92: =+BQ94*BQ83 -> 223522.72 | BR92: =+BR94*BR83 -> 215287.67 | BS92: =+BS94*BS83 -> 918796.02 | BT92: =+BT94*BT83 -> 261403.94 | BU92: =+BU94*BU83 -> 237639.94 | BV92: =+BV94*BV83 -> 237639.94 | BW92: =+BW94*BW83 -> 229322.54 | BX92: =+BT92+BU92+BV92+BW92 -> 966006.37 | BY92: =+BY94*BY83 -> 276018.79 | BZ92: =+BZ94*BZ83 -> 252017.16 | CA92: =+CA94*CA83 -> 252017.16 | CB92: =+CB94*CB83 -> 243616.59 | CC92: =+BY92+BZ92+CA92+CB92 -> 1023669.7 | CD92: =+CD94*CD83 -> 290899.81 | CE92: =+CE94*CE83 -> 266658.16 | CF92: =+CF94*CF83 -> 266658.16 | CG92: =+CG94*CG83 -> 258173.58 | CH92: =+CD92+CE92+CF92+CG92 -> 1082389.7 | CI92: =+CI94*CI83 -> 306050.84 | CJ92: =+CJ94*CJ83 -> 281566.77 | CK92: =+CK94*CK83 -> 281566.77 | CL92: =+CL94*CL83 -> 272997.35 | CM92: =+CI92+CJ92+CK92+CL92 -> 1142181.7 | CN92: =+CN94*CN83 -> 321475.8 | CO92: =+CO94*CO83 -> 296746.89 | CP92: =+CP94*CP83 -> 296746.89 | CQ92: =+CQ94*CQ83 -> 288091.77 | CR92: =+CN92+CO92+CP92+CQ92 -> 1203061.4 | CS92: =+CS94*CS83 -> 337178.66 | CT92: =+CT94*CT83 -> 312202.46 | CU92: =+CU94*CU83 -> 312202.46 | CV92: =+CV94*CV83 -> 303460.79 | CW92: =+CS92+CT92+CU92+CV92 -> 1265044.4 | CX92: =+CX94*CX83 -> 353163.42 | CY92: =+CY94*CY83 -> 327937.46 | CZ92: =+CZ94*CZ83 -> 327937.46 | DA92: =+DA94*DA83 -> 319108.38 | DB92: =+CX92+CY92+CZ92+DA92 -> 1328146.7
A93: % yoy | B93: -- | C93: -- | D93: -- | E93: -- | F93: -- | G93: =+G92/B92-1 -> 1.525 | H93: =+H92/C92-1 -> 1.1753846 | I93: =+I92/D92-1 -> 0.78235294 | J93: =+J92/E92-1 -> 0.9695 | K93: =+K92/F92-1 -> 1.0536667 | L93: =+L92/G92-1 -> 0.7372 | M93: =+M92/H92-1 -> 0.515 | N93: =+N92/I92-1 -> 0.48133333 | ... DB93: =+DB92/CW92-1 -> 0.04988154
A94: % A/L RP Pregnancies | B94: 0.01 | C94: 0.013 | D94: 0.017 | E94: 0.02 | F94: =+F92/F83 -> 0.015 | G94: 0.025 | H94: 0.028 | I94: 0.03 | J94: 0.039 | K94: =+K92/K83 -> 0.0305 | L94: 0.043 | M94: 0.042 | N94: 0.044 | O94: 0.044 | P94: =+P92/P83 -> 0.04325 | Q94: 0.042 | R94: 0.04 | S94: =+R94 -> 0.04 | T94: =+S94+0.003 -> 0.043 | U94: =+U92/U83 -> 0.04125 | V94: 0.0535 | W94: 0.0552 | X94: 0.055 | Y94: 0.05545 | Z94: =+Z92/Z83 -> 0.0547875 | AA94: 0.0636 | AB94: 0.0604 | AC94: 0.059137 | AD94: 0.059 | AE94: =+AE92/AE83 -> 0.06053425 | AF94: 0.066 | AG94: 0.069 | AH94: 0.082 | AI94: 0.09 | AJ94: =+AJ92/AJ83 -> 0.07675 | AK94: 0.112 | AL94: 0.121 | AM94: 0.13 | AN94: 0.128 | AO94: =+AO92/AO83 -> 0.12275 | AP94: 0.152 | AQ94: 0.148 | AR94: 0.15 | AS94: 0.155 | AT94: =+AT92/AT83 -> 0.15125 | AU94: =+AP94+0.0015 -> 0.1535 | AV94: =+AQ94+0.0015 -> 0.1495 | AW94: =+AR94+0.0015 -> 0.1515 | AX94: =+AS94+0.0015 -> 0.1565 | AY94: =+AY92/AY83 -> 0.15275 | AZ94: =+AU94+0.02 -> 0.1735 | BA94: 0.17 | BB94: 0.17 | BC94: 0.17 | BD94: =+BD92/BD83 -> 0.170875 | BE94: 0.19 | BF94: 0.18 | BG94: 0.17 | BH94: 0.166 | BI94: =+BI92/BI83 -> 0.1765 | BJ94: 0.185 | BK94: 0.18 | BL94: 0.17 | BM94: 0.166 | BN94: =+BN92/BN83 -> 0.17525 | BO94: 0.21 | BP94: =+BK94+0.01 -> 0.19 | BQ94: 0.19 | BR94: 0.183 | BS94: =+BN94+0.02 -> 0.19525 | BT94: =+BO94+0.01 -> 0.22 | BU94: =+BP94+0.01 -> 0.2 | BV94: =+BQ94+0.01 -> 0.2 | BW94: =+BR94+0.01 -> 0.193 | BX94: =+BX92/BX83 -> 0.20325 | BY94: =+BT94+0.01 -> 0.23 | BZ94: =+BU94+0.01 -> 0.21 | CA94: =+BV94+0.01 -> 0.21 | CB94: =+BW94+0.01 -> 0.203 | CC94: =+CC92/CC83 -> 0.21325 | CD94: =+BY94+0.01 -> 0.24 | CE94: =+BZ94+0.01 -> 0.22 | CF94: =+CA94+0.01 -> 0.22 | CG94: =+CB94+0.01 -> 0.213 | CH94: =+CH92/CH83 -> 0.22325 | CI94: =+CD94+0.01 -> 0.25 | CJ94: =+CE94+0.01 -> 0.23 | CK94: =+CF94+0.01 -> 0.23 | CL94: =+CG94+0.01 -> 0.223 | CM94: =+CM92/CM83 -> 0.23325 | CN94: =+CI94+0.01 -> 0.26 | CO94: =+CJ94+0.01 -> 0.24 | CP94: =+CK94+0.01 -> 0.24 | CQ94: =+CL94+0.01 -> 0.233 | CR94: =+CR92/CR83 -> 0.24325 | CS94: =+CN94+0.01 -> 0.27 | CT94: =+CO94+0.01 -> 0.25 | CU94: =+CP94+0.01 -> 0.25 | CV94: =+CQ94+0.01 -> 0.243 | CW94: =+CW92/CW83 -> 0.25325 | CX94: =+CS94+0.01 -> 0.28 | CY94: =+CT94+0.01 -> 0.26 | CZ94: =+CU94+0.01 -> 0.26 | DA94: =+CV94+0.01 -> 0.253 | DB94: =+DB92/DB83 -> 0.26325
A95: Total Natera Tests | B95: =+B89+B92 -> 32213.793 | C95: =+C89+C92 -> 38923.422 | D95: =+D89+D92 -> 39675.156 | E95: =+E89+E92 -> 39393.2 | F95: =+F89+F92 -> 150205.57 | G95: =+G89+G92 -> 43184.942 | H95: =+H89+H92 -> 46317.022 | I95: =+I89+I92 -> 47266.124 | ... BM95: =+BM89+BM92 -> 255618.65 | BN95: =SUM(BJ95:BM95) -> 1045494.8 | BO95: =+BO89+BO92 -> 313274.83 | BP95: =+BP89+BP92 -> 286986.82 | BQ95: =+BQ89+BQ92 -> 292312.92 | BR95: =+BR89+BR92 -> 284462.9 | BS95: =SUM(BO95:BR95) -> 1177037.5 | BT95: =+BT89+BT92 -> 333863.38 | BU95: =+BU89+BU92 -> 313599.22 | BV95: =+BV89+BV92 -> 312691.85 | BW95: =+BW89+BW92 -> 304763.32 | BX95: =SUM(BT95:BW95) -> 1264917.8 | BY95: =+BY89+BY92 -> 356141.57 | BZ95: =+BZ89+BZ92 -> 330110.68 | CA95: =+CA89+CA92 -> 334758.33 | CB95: =+CB89+CB92 -> 324328.5 | CC95: =SUM(BY95:CB95) -> 1345339.1 | CD95: =+CD89+CD92 -> 376385.7 | CE95: =+CE89+CE92 -> 350524.25 | CF95: =+CF89+CF92 -> 354788.63 | CG95: =+CG89+CG92 -> 344684.25 | CH95: =SUM(CD95:CG95) -> 1426382.8 | CI95: =+CI89+CI92 -> 397433.14 | CJ95: =+CJ89+CJ92 -> 371096.06 | CK95: =+CK89+CK92 -> 375620.1 | CL95: =+CL89+CL92 -> 365197.65 | CM95: =SUM(CI95:CL95) -> 1509347 | CN95: =+CN89+CN92 -> 418644.71 | CO95: =+CO89+CO92 -> 392153.84 | CP95: =+CP89+CP92 -> 396613.53 | CQ95: =+CQ89+CQ92 -> 386196.46 | CR95: =SUM(CN95:CQ95) -> 1593608.5 | CS95: =+CS89+CS92 -> 440351.45 | CT95: =+CT89+CT92 -> 413540.33 | CU95: =+CU89+CU92 -> 418099.96 | CV95: =+CV89+CV92 -> 407523.37 | CW95: =SUM(CS95:CV95) -> 1679515.1 | CX95: =+CX89+CX92 -> 462394.56 | CY95: =+CY89+CY92 -> 435343.28 | CZ95: =+CZ89+CZ92 -> 439920.56 | DA95: =+DA89+DA92 -> 429266.15 | DB95: =SUM(CX95:DA95) -> 1766924.5
A96: % yoy | B96: -- | C96: -- | D96: -- | E96: -- | F96: -- | G96: =+G95/B95-1 -> 0.34057306 | H96: =+H95/C95-1 -> 0.18995248 | I96: =+I95/D95-1 -> 0.191328 | J96: =+J95/E95-1 -> 0.43837931 | K96: =+K95/F95-1 -> 0.2877715 | L96: =+L95/G95-1 -> 0.51344454 | M96: =+M95/H95-1 -> 0.32872811 | N96: =+N95/I95-1 -> 0.41481072 | ... DB96: =+DB95/CW95-1 -> 0.052044452
A97: % seq | B97: -- | C97: =+C95/B95-1 -> 0.20828436 | D97: =+D95/C95-1 -> 0.019313153 | E97: =+E95/D95-1 -> -0.0071066073 | F97: -- | G97: =+G95/E95-1 -> 0.09625373 | H97: =+H95/G95-1 -> 0.07252713 | I97: =+I95/H95-1 -> 0.02049142 | J97: =+J95/I95-1 -> 0.19879438 | K97: -- | L97: =+L95/J95-1 -> 0.15346433 | M97: =+M95/L95-1 -> -0.058375181 | N97: =+N95/M95-1 -> 0.086604696 | O97: =+O95/N95-1 -> 0 | P97: -- | Q97: =+Q95/O95-1 -> -0.028801547 | R97: =+R95/Q95-1 -> -0.05426362 | S97: =+S95/R95-1 -> 0.00037831334 | T97: =+T95/S95-1 -> 0.07468801 | U97: -- | V97: =+V95/T95-1 -> 0.19845269 | W97: =+W95/V95-1 -> 0.016433822 | X97: =+X95/W95-1 -> -0.0019450375 | Y97: =+Y95/X95-1 -> 0.015383742 | Z97: -- | AA97: =+AA95/Y95-1 -> 0.12765129 | AB97: =+AB95/AA95-1 -> -0.085529114 | AC97: =+AC95/AB95-1 -> -0.017182964 | AD97: =+AD95/AC95-1 -> -0.00036698422 | AE97: -- | AF97: =+AF95/AD95-1 -> 0.1493855 | AG97: =+AG95/AF95-1 -> 0.045271121 | AH97: =+AH95/AG95-1 -> 0.14328185 | AI97: =+AI95/AH95-1 -> 0.081603788 | AJ97: -- | AK97: =+AK95/AI95-1 -> 0.263896 | AL97: =+AL95/AK95-1 -> 0.07516679 | AM97: =+AM95/AL95-1 -> 0.074699042 | AN97: =+AN95/AM95-1 -> -0.0059127038 | AO97: -- | AP97: =+AP95/AN95-1 -> 0.16355622 | AQ97: =+AQ95/AP95-1 -> -0.013177405 | AR97: =+AR95/AQ95-1 -> 0.016605335 | AS97: =+AS95/AR95-1 -> 0.063457304 | AT97: -- | AU97: =+AU95/AS95-1 -> 0.0079084935 | AV97: =+AV95/AU95-1 -> -0.029144599 | AW97: =+AW95/AV95-1 -> 0.0081698085 | AX97: =+AX95/AW95-1 -> 0.022520514 | AY97: -- | AZ97: =+AZ95/AX95-1 -> 0.097594243 | BA97: =+BA95/AZ95-1 -> 0.016737943 | BB97: =+BB95/BA95-1 -> -0.0080067467 | BC97: =+BC95/BB95-1 -> -0.002017843 | BD97: -- | BE97: =+BE95/BC95-1 -> 0.10589448 | BF97: =+BF95/BE95-1 -> -0.046693795 | BG97: =+BG95/BF95-1 -> -0.017765408 | BH97: =+BH95/BG95-1 -> -0.024979471 | BI97: -- | BJ97: =+BJ95/BH95-1 -> 0.085668772 | BK97: =+BK95/BJ95-1 -> -0.020619304 | BL97: =+BL95/BK95-1 -> -0.035382454 | BM97: =+BM95/BL95-1 -> 0.0016599842 | BN97: -- | BO97: =+BO95/BN95-1 -> -0.70035735 | BP97: =+BP95/BO95-1 -> -0.08391359 | BQ97: =+BQ95/BP95-1 -> 0.018558718 | BR97: =+BR95/BQ95-1 -> -0.026854877 | BS97: -- | BT97: =+BT95/BS95-1 -> -0.7163528 | BU97: =+BU95/BT95-1 -> -0.060695978 | BV97: =+BV95/BU95-1 -> -0.0028933852 | BW97: =+BW95/BV95-1 -> -0.025355723 | BX97: -- | BY97: =+BY95/BW95-1 -> 0.16858408 | BZ97: =+BZ95/BY95-1 -> -0.073091405 | CA97: =+CA95/BZ95-1 -> 0.01407905 | CB97: =+CB95/CA95-1 -> -0.031156283 | CC97: -- | CD97: =+CD95/CB95-1 -> 0.16050764 | CE97: =+CE95/CD95-1 -> -0.068709977 | CF97: =+CF95/CE95-1 -> 0.012165714 | CG97: =+CG95/CF95-1 -> -0.02848 | CH97: -- | CI97: =+CI95/CG95-1 -> 0.15303542 | CJ97: =+CJ95/CI95-1 -> -0.06626797 | CK97: =+CK95/CJ95-1 -> 0.012191026 | CL97: =+CL95/CK95-1 -> -0.027747302 | CM97: -- | CN97: =+CN95/CL95-1 -> 0.14635103 | CO97: =+CO95/CN95-1 -> -0.063277674 | CP97: =+CP95/CO95-1 -> 0.011372289 | CQ97: =+CQ95/CP95-1 -> -0.026265048 | CR97: -- | CS97: =+CS95/CQ95-1 -> 0.14022654 | CT97: =+CT95/CS95-1 -> -0.060885726 | CU97: =+CU95/CT95-1 -> 0.01102584 | CV97: =+CV95/CU95-1 -> -0.025296797 | CW97: -- | CX97: =+CX95/CV95-1 -> 0.13464551 | CY97: =+CY95/CX95-1 -> -0.05850259 | CZ97: =+CZ95/CY95-1 -> 0.010514177 | DA97: =+DA95/CZ95-1 -> -0.024218932 | DB97: --
A99: Average Selling Price ($ / test) | B99: 502 | C99: 582 | D99: 699 | E99: 721 | F99: =+F103/F95*1000000 -> 632.2015 | G99: 657 | H99: 630 | I99: 513 | J99: 504 | K99: =+K103/K95*1000000 -> 570.52849 | L99: 500 | M99: 411 | N99: 485 | O99: 425 | P99: =+P103/P95*1000000 -> 455.89482 | Q99: 395 | R99: 435 | S99: 485 | T99: 360 | U99: =+U103/U95*1000000 -> 417.35884 | V99: 317 | W99: 370 | X99: 370 | Y99: 370 | Z99: =+Z103/Z95*1000000 -> 356.94888 | AA99: 325 | AB99: 325 | AC99: 320 | AD99: 350 | AE99: =+AE103/AE95*1000000 -> 329.84067 | AF99: 325 | AG99: 300 | AH99: 330 | AI99: 325 | AJ99: =+AJ103/AJ95*1000000 -> 320.55324 | AK99: 325 | AL99: 300 | AM99: 325 | AN99: 325 | AO99: =+AO103/AO95*1000000 -> 318.86222 | AP99: 335 | AQ99: 335 | AR99: 335 | AS99: 335 | AT99: =+AT103/AT95*1000000 -> 335 | AU99: 350 | AV99: 350 | AW99: 350 | AX99: 350 | AY99: =+AY103/AY95*1000000 -> 350 | AZ99: 380 | BA99: 450 | BB99: 475 | BC99: 500 | BD99: =+BD103/BD95*1000000 -> 451.37479 | BE99: 500 | BF99: 525 | BG99: 530 | BH99: 580 | BI99: =+BI103/BI95*1000000 -> 532.86181 | BJ99: 490 | BK99: 475 | BL99: 475 | BM99: 475 | BN99: =+BN103/BN95*1000000 -> 478.87556 | BO99: 475 | BP99: 475 | BQ99: 475 | BR99: 475 | BS99: =+BS103/BS95*1000000 -> 475 | BT99: 475 | BU99: 475 | BV99: 475 | BW99: 475 | BX99: =+BX103/BX95*1000000 -> 475 | BY99: 475 | BZ99: 475 | CA99: 475 | CB99: 475 | CC99: =+CC103/CC95*1000000 -> 475 | CD99: 475 | CE99: 475 | CF99: 475 | CG99: 475 | CH99: =+CH103/CH95*1000000 -> 475 | CI99: 475 | CJ99: 475 | CK99: 475 | CL99: 475 | CM99: =+CM103/CM95*1000000 -> 475 | CN99: 475 | CO99: 475 | CP99: 475 | CQ99: 475 | CR99: =+CR103/CR95*1000000 -> 475 | CS99: 475 | CT99: 475 | CU99: 475 | CV99: 475 | CW99: =+CW103/CW95*1000000 -> 475 | CX99: 475 | CY99: 475 | CZ99: 475 | DA99: 475 | DB99: =+DB103/DB95*1000000 -> 475
A100: % yoy | B100: -- | C100: -- | D100: -- | E100: -- | F100: -- | G100: =+G99/B99-1 -> 0.30876494 | H100: =+H99/C99-1 -> 0.082474227 | I100: =+I99/D99-1 -> -0.26609442 | J100: =+J99/E99-1 -> -0.30097087 | K100: =+K99/F99-1 -> -0.097552769 | L100: =+L99/G99-1 -> -0.23896499 | M100: =+M99/H99-1 -> -0.34761905 | N100: =+N99/I99-1 -> -0.054580897 | ... DB100: =+DB99/CW99-1 -> 0
A101: % seq | B101: -- | C101: =+C99/B99-1 -> 0.15936255 | D101: =+D99/C99-1 -> 0.20103093 | E101: =+E99/D99-1 -> 0.031473534 | F101: -- | G101: =+G99/E99-1 -> -0.088765603 | H101: =+H99/G99-1 -> -0.04109589 | I101: =+I99/H99-1 -> -0.18571429 | J101: =+J99/I99-1 -> -0.01754386 | K101: -- | L101: =+L99/J99-1 -> -0.0079365079 | M101: =+M99/L99-1 -> -0.178 | N101: =+N99/M99-1 -> 0.18004866 | O101: =+O99/N99-1 -> -0.12371134 | P101: -- | Q101: =+Q99/O99-1 -> -0.070588235 | R101: =+R99/Q99-1 -> 0.10126582 | S101: =+S99/R99-1 -> 0.11494253 | T101: =+T99/S99-1 -> -0.25773196 | U101: -- | V101: =+V99/T99-1 -> -0.11944444 | W101: =+W99/V99-1 -> 0.16719243 | X101: =+X99/W99-1 -> 0 | Y101: =+Y99/X99-1 -> 0 | Z101: -- | AA101: =+AA99/Y99-1 -> -0.12162162 | AB101: =+AB99/AA99-1 -> 0 | AC101: =+AC99/AB99-1 -> -0.015384615 | AD101: =+AD99/AC99-1 -> 0.09375 | AE101: -- | AF101: =+AF99/AD99-1 -> -0.071428571 | AG101: =+AG99/AF99-1 -> -0.076923077 | AH101: =+AH99/AG99-1 -> 0.1 | AI101: =+AI99/AH99-1 -> -0.015151515 | AJ101: -- | AK101: =+AK99/AI99-1 -> 0 | AL101: =+AL99/AK99-1 -> -0.076923077 | AM101: =+AM99/AL99-1 -> 0.083333333 | AN101: =+AN99/AM99-1 -> 0 | AO101: -- | AP101: =+AP99/AN99-1 -> 0.030769231 | AQ101: =+AQ99/AP99-1 -> 0 | AR101: =+AR99/AQ99-1 -> 0 | AS101: =+AS99/AR99-1 -> 0 | AT101: -- | AU101: =+AU99/AS99-1 -> 0.044776119 | AV101: =+AV99/AU99-1 -> 0 | AW101: =+AW99/AV99-1 -> 0 | AX101: =+AX99/AW99-1 -> 0 | AY101: -- | AZ101: =+AZ99/AX99-1 -> 0.085714286 | BA101: =+BA99/AZ99-1 -> 0.18421053 | BB101: =+BB99/BA99-1 -> 0.055555556 | BC101: =+BC99/BB99-1 -> 0.052631579 | BD101: -- | BE101: =+BE99/BC99-1 -> 0 | BF101: =+BF99/BE99-1 -> 0.05 | BG101: =+BG99/BF99-1 -> 0.0095238095 | BH101: =+BH99/BG99-1 -> 0.094339623 | BI101: -- | BJ101: =+BJ99/BH99-1 -> -0.15517241 | BK101: =+BK99/BJ99-1 -> -0.030612245 | BL101: =+BL99/BK99-1 -> 0 | BM101: =+BM99/BL99-1 -> 0 | BN101: =+BN99/BL99-1 -> 0.0081590818 | BO101: =+BO99/BN99-1 -> -0.00809305 | BP101: =+BP99/BO99-1 -> 0 | BQ101: =+BQ99/BP99-1 -> 0 | BR101: =+BR99/BQ99-1 -> 0 | BS101: =+BS99/BQ99-1 -> 0 | BT101: =+BT99/BS99-1 -> 0 | BU101: =+BU99/BT99-1 -> 0 | BV101: =+BV99/BU99-1 -> 0 | BW101: =+BW99/BV99-1 -> 0 | BX101: -- | BY101: =+BY99/BW99-1 -> 0 | BZ101: =+BZ99/BY99-1 -> 0 | CA101: =+CA99/BZ99-1 -> 0 | CB101: =+CB99/CA99-1 -> 0 | CC101: -- | CD101: =+CD99/CB99-1 -> 0 | CE101: =+CE99/CD99-1 -> 0 | CF101: =+CF99/CE99-1 -> 0 | CG101: =+CG99/CF99-1 -> 0 | CH101: -- | CI101: =+CI99/CG99-1 -> 0 | CJ101: =+CJ99/CI99-1 -> 0 | CK101: =+CK99/CJ99-1 -> 0 | CL101: =+CL99/CK99-1 -> 0 | CM101: -- | CN101: =+CN99/CL99-1 -> 0 | CO101: =+CO99/CN99-1 -> 0 | CP101: =+CP99/CO99-1 -> 0 | CQ101: =+CQ99/CP99-1 -> 0 | CR101: -- | CS101: =+CS99/CQ99-1 -> 0 | CT101: =+CT99/CS99-1 -> 0 | CU101: =+CU99/CT99-1 -> 0 | CV101: =+CV99/CU99-1 -> 0 | CW101: -- | CX101: =+CX99/CV99-1 -> 0 | CY101: =+CY99/CX99-1 -> 0 | CZ101: =+CZ99/CY99-1 -> 0 | DA101: =+DA99/CZ99-1 -> 0 | DB101: --
A103: US Panorama Revenues | B103: =+B95*B99/1000000 -> 16.171324 | C103: =+C95*C99/1000000 -> 22.653431 | D103: =+D95*D99/1000000 -> 27.732934 | E103: =+E95*E99/1000000 -> 28.402497 | F103: =+B103+C103+D103+E103 -> 94.960186 | G103: =+G95*G99/1000000 -> 28.372507 | H103: =+H95*H99/1000000 -> 29.179724 | I103: =+I95*I99/1000000 -> 24.247522 | J103: =+J95*J99/1000000 -> 28.557831 | K103: =+G103+H103+I103+J103 -> 110.35758 | L103: =+L95*L99/1000000 -> 32.679008 | M103: =+M95*M99/1000000 -> 25.294062 | N103: =+N95*N99/1000000 -> 32.43322 | O103: =+O95*O99/1000000 -> 28.420863 | P103: =+L103+M103+N103+O103 -> 118.82715 | Q103: =+Q95*Q99/1000000 -> 25.653901 | R103: =+R95*R99/1000000 -> 26.718721 | S103: =+S95*S99/1000000 -> 29.801108 | T103: =+T95*T99/1000000 -> 23.77254 | U103: =+Q103+R103+S103+T103 -> 105.94627 | V103: =+V95*V99/1000000 -> 25.08726 | W103: =+W95*W99/1000000 -> 29.76287 | X103: =+X95*X99/1000000 -> 29.70498 | Y103: =+Y95*Y99/1000000 -> 30.161954 | Z103: =+V103+W103+X103+Y103 -> 114.71706 | AA103: =+AA95*AA99/1000000 -> 29.875551 | AB103: =+AB95*AB99/1000000 -> 27.320322 | AC103: =+AC95*AC99/1000000 -> 26.437787 | AD103: =+AD95*AD99/1000000 -> 28.905718 | AE103: =+AA103+AB103+AC103+AD103 -> 112.53938 | AF103: =+AF95*AF99/1000000 -> 30.850683 | AG103: =+AG95*AG99/1000000 -> 29.766765 | AH103: =+AH95*AH99/1000000 -> 37.434982 | AI103: =+AI95*AI99/1000000 -> 39.876336 | AJ103: =+AF103+AG103+AH103+AI103 -> 137.92877 | AK103: =+AK95*AK99/1000000 -> 50.399542 | AL103: =+AL95*AL99/1000000 -> 50.019613 | AM103: =+AM95*AM99/1000000 -> 58.235699 | AN103: =+AN95*AN99/1000000 -> 57.891369 | AO103: =+AK103+AL103+AM103+AN103 -> 216.54622 | AP103: =+AP95*AP99/1000000 -> 69.432473 | AQ103: =+AQ95*AQ99/1000000 -> 68.517534 | AR103: =+AR95*AR99/1000000 -> 69.65529 | AS103: =+AS95*AS99/1000000 -> 74.075427 | AT103: =+AP103+AQ103+AR103+AS103 -> 281.68072 | AU103: =+AU95*AU99/1000000 -> 78.004293 | AV103: =+AV95*AV99/1000000 -> 75.730889 | AW103: =+AW95*AW99/1000000 -> 76.349596 | AX103: =+AX95*AX99/1000000 -> 78.069029 | AY103: =+AU103+AV103+AW103+AX103 -> 308.15381 | AZ103: =+AZ95*AZ99/1000000 -> 93.032812 | BA103: =+BA95*BA99/1000000 -> 112.01446 | BB103: =+BB95*BB99/1000000 -> 117.29079 | BC103: =+BC95*BC99/1000000 -> 123.21486 | BD103: =+AZ103+BA103+BB103+BC103 -> 445.55292 | BE103: =+BE95*BE99/1000000 -> 136.26263 | BF103: =+BF95*BF99/1000000 -> 136.39501 | BG103: =+BG95*BG99/1000000 -> 135.24782 | BH103: =+BH95*BH99/1000000 -> 144.30991 | BI103: =+BE103+BF103+BG103+BH103 -> 552.21538 | BJ103: =+BJ95*BJ99/1000000 -> 132.36147 | BK103: =+BK95*BK99/1000000 -> 125.66394 | BL103: =+BL95*BL99/1000000 -> 121.21764 | BM103: =+BM95*BM99/1000000 -> 121.41886 | BN103: =SUM(BJ103:BM103) -> 500.66191 | BO103: =+BO95*BO99/1000000 -> 148.80554 | BP103: =+BP95*BP99/1000000 -> 136.31874 | BQ103: =+BQ95*BQ99/1000000 -> 138.84864 | BR103: =+BR95*BR99/1000000 -> 135.11988 | BS103: =SUM(BO103:BR103) -> 559.0928 | BT103: =+BT95*BT99/1000000 -> 158.58511 | BU103: =+BU95*BU99/1000000 -> 148.95963 | BV103: =+BV95*BV99/1000000 -> 148.52863 | BW103: =+BW95*BW99/1000000 -> 144.76258 | BX103: =SUM(BT103:BW103) -> 600.83594 | BY103: =+BY95*BY99/1000000 -> 169.16724 | BZ103: =+BZ95*BZ99/1000000 -> 156.80257 | CA103: =+CA95*CA99/1000000 -> 159.0102 | CB103: =+CB95*CB99/1000000 -> 154.05604 | CC103: =+BY103+BZ103+CA103+CB103 -> 639.03606 | CD103: =+CD95*CD99/1000000 -> 178.78321 | CE103: =+CE95*CE99/1000000 -> 166.49902 | CF103: =+CF95*CF99/1000000 -> 168.5246 | CG103: =+CG95*CG99/1000000 -> 163.72502 | CH103: =+CD103+CE103+CF103+CG103 -> 677.53184 | CI103: =+CI95*CI99/1000000 -> 188.78074 | CJ103: =+CJ95*CJ99/1000000 -> 176.27063 | CK103: =+CK95*CK99/1000000 -> 178.41955 | CL103: =+CL95*CL99/1000000 -> 173.46889 | CM103: =+CI103+CJ103+CK103+CL103 -> 716.9398 | CN103: =+CN95*CN99/1000000 -> 198.85624 | CO103: =+CO95*CO99/1000000 -> 186.27308 | CP103: =+CP95*CP99/1000000 -> 188.39143 | CQ103: =+CQ95*CQ99/1000000 -> 183.44332 | CR103: =+CN103+CO103+CP103+CQ103 -> 756.96405 | CS103: =+CS95*CS99/1000000 -> 209.16694 | CT103: =+CT95*CT99/1000000 -> 196.43166 | CU103: =+CU95*CU99/1000000 -> 198.59748 | CV103: =+CV95*CV99/1000000 -> 193.5736 | CW103: =+CS103+CT103+CU103+CV103 -> 797.76968 | CX103: =+CX95*CX99/1000000 -> 219.63742 | CY103: =+CY95*CY99/1000000 -> 206.78806 | CZ103: =+CZ95*CZ99/1000000 -> 208.96226 | DA103: =+DA95*DA99/1000000 -> 203.90142 | DB103: =+CX103+CY103+CZ103+DA103 -> 839.28916
A104: % yoy | B104: -- | C104: -- | D104: -- | E104: -- | F104: -- | G104: =+G103/B103-1 -> 0.75449502 | H104: =+H103/C103-1 -> 0.28809289 | I104: =+I103/D103-1 -> -0.12567773 | J104: =+J103/E103-1 -> 0.0054690308 | K104: =+K103/F103-1 -> 0.16214583 | L104: =+L103/G103-1 -> 0.15178428 | M104: =+M103/H103-1 -> -0.13316309 | N104: =+N103/I103-1 -> 0.33758908 | ... DB104: =+DB103/CW103-1 -> 0.052044452
A105: % seq | B105: -- | C105: =+C103/B103-1 -> 0.40083964 | D105: =+D103/C103-1 -> 0.22422662 | E105: =+E103/D103-1 -> 0.024143256 | F105: -- | G105: =+G103/E103-1 -> -0.0010558937 | H105: =+H103/G103-1 -> 0.028450673 | I105: =+I103/H103-1 -> -0.16902842 | J105: =+J103/I103-1 -> 0.1777629 | K105: -- | L105: =+L103/J103-1 -> 0.14430985 | M105: =+M103/L103-1 -> -0.2259844 | N105: =+N103/M103-1 -> 0.28224642 | O105: =+O103/N103-1 -> -0.12371134 | P105: -- | Q105: =+Q103/O103-1 -> -0.097356732 | R105: =+R103/Q103-1 -> 0.041507152 | S105: =+S103/R103-1 -> 0.11536433 | T105: =+T103/S103-1 -> -0.20229344 | U105: -- | V105: =+V103/T103-1 -> 0.055304173 | W105: =+W103/V103-1 -> 0.18637386 | X105: =+X103/W103-1 -> -0.0019450375 | Y105: =+Y103/X103-1 -> 0.015383742 | Z105: -- | AA105: =+AA103/Y103-1 -> -0.0094954896 | AB105: =+AB103/AA103-1 -> -0.085529114 | AC105: =+AC103/AB103-1 -> -0.032303226 | AD105: =+AD103/AC103-1 -> 0.093348611 | AE105: -- | AF105: =+AF103/AD103-1 -> 0.067286532 | AG105: =+AG103/AF103-1 -> -0.03513435 | AH105: =+AH103/AG103-1 -> 0.25761004 | AI105: =+AI103/AH103-1 -> 0.065215852 | AJ105: -- | AK105: =+AK103/AI103-1 -> 0.263896 | AL105: =+AL103/AK103-1 -> -0.0075383474 | AM105: =+AM103/AL103-1 -> 0.1642573 | AN105: =+AN103/AM103-1 -> -0.0059127038 | AO105: -- | AP105: =+AP103/AN103-1 -> 0.19935795 | AQ105: =+AQ103/AP103-1 -> -0.013177405 | AR105: =+AR103/AQ103-1 -> 0.016605335 | AS105: =+AS103/AR103-1 -> 0.063457304 | AT105: -- | AU105: =+AU103/AS103-1 -> 0.053038725 | AV105: =+AV103/AU103-1 -> -0.029144599 | AW105: =+AW103/AV103-1 -> 0.0081698085 | AX105: =+AX103/AW103-1 -> 0.022520514 | AY105: -- | AZ105: =+AZ103/AX103-1 -> 0.19167375 | BA105: =+BA103/AZ103-1 -> 0.20403177 | BB105: =+BB103/BA103-1 -> 0.04710399 | BC105: =+BC103/BB103-1 -> 0.050507534 | BD105: -- | BE105: =+BE103/BC103-1 -> 0.10589448 | BF105: =+BF103/BE103-1 -> 0.00097151476 | BG105: =+BG103/BF103-1 -> -0.0084107928 | BH105: =+BH103/BG103-1 -> 0.067003598 | BI105: -- | BJ105: =+BJ103/BH103-1 -> -0.082797072 | BK105: =+BK103/BJ103-1 -> -0.050600346 | BL105: =+BL103/BK103-1 -> -0.035382454 | BM105: =+BM103/BL103-1 -> 0.0016599842 | BN105: =+BN103/BL103-1 -> 3.1302727 | BO105: =+BO103/BN103-1 -> -0.70278237 | BP105: =+BP103/BO103-1 -> -0.08391359 | BQ105: =+BQ103/BP103-1 -> 0.018558718 | BR105: =+BR103/BQ103-1 -> -0.026854877 | BS105: =+BS103/BQ103-1 -> 3.0266351 | BT105: =+BT103/BS103-1 -> -0.7163528 | BU105: =+BU103/BT103-1 -> -0.060695978 | BV105: =+BV103/BU103-1 -> -0.0028933852 | BW105: =+BW103/BV103-1 -> -0.025355723 | BX105: -- | BY105: =+BY103/BW103-1 -> 0.16858408 | BZ105: =+BZ103/BY103-1 -> -0.073091405 | CA105: =+CA103/BZ103-1 -> 0.01407905 | CB105: =+CB103/CA103-1 -> -0.031156283 | CC105: -- | CD105: =+CD103/CB103-1 -> 0.16050764 | CE105: =+CE103/CD103-1 -> -0.068709977 | CF105: =+CF103/CE103-1 -> 0.012165714 | CG105: =+CG103/CF103-1 -> -0.02848 | CH105: -- | CI105: =+CI103/CG103-1 -> 0.15303542 | CJ105: =+CJ103/CI103-1 -> -0.06626797 | CK105: =+CK103/CJ103-1 -> 0.012191026 | CL105: =+CL103/CK103-1 -> -0.027747302 | CM105: -- | CN105: =+CN103/CL103-1 -> 0.14635103 | CO105: =+CO103/CN103-1 -> -0.063277674 | CP105: =+CP103/CO103-1 -> 0.011372289 | CQ105: =+CQ103/CP103-1 -> -0.026265048 | CR105: -- | CS105: =+CS103/CQ103-1 -> 0.14022654 | CT105: =+CT103/CS103-1 -> -0.060885726 | CU105: =+CU103/CT103-1 -> 0.01102584 | CV105: =+CV103/CU103-1 -> -0.025296797 | CW105: -- | CX105: =+CX103/CV103-1 -> 0.13464551 | CY105: =+CY103/CX103-1 -> -0.05850259 | CZ105: =+CZ103/CY103-1 -> 0.010514177 | DA105: =+DA103/CZ103-1 -> -0.024218932 | DB105: --
A107: Europe
A108: High Risk Pregnancies | B108: =+F108/4 -> 375000 | C108: =+F108/4 -> 375000 | D108: =+F108/4 -> 375000 | E108: =+F108/4 -> 375000 | F108: 1500000 | G108: =+B108*(1+G109) -> 382500 | H108: =+C108*(1+H109) -> 382500 | I108: =+D108*(1+I109) -> 382500 | J108: =+E108*(1+J109) -> 382500 | K108: =+G108+H108+I108+J108 -> 1530000 | L108: =+G108*(1+L109) -> 390150 | M108: =+H108*(1+M109) -> 390150 | N108: =+I108*(1+N109) -> 390150 | O108: =+J108*(1+O109) -> 390150 | P108: =+L108+M108+N108+O108 -> 1560600 | Q108: =+L108*(1+Q109) -> 397953 | R108: =+M108*(1+R109) -> 397953 | S108: =+N108*(1+S109) -> 397953 | T108: =+O108*(1+T109) -> 397953 | U108: =+Q108+R108+S108+T108 -> 1591812 | V108: =+Q108*(1+V109) -> 405912.06 | W108: =+R108*(1+W109) -> 405912.06 | X108: =+S108*(1+X109) -> 405912.06 | Y108: =+T108*(1+Y109) -> 405912.06 | Z108: =+V108+W108+X108+Y108 -> 1623648.2 | AA108: =+V108*(1+AA109) -> 414030.3 | AB108: =+W108*(1+AB109) -> 414030.3 | AC108: =+X108*(1+AC109) -> 414030.3 | AD108: =+Y108*(1+AD109) -> 414030.3 | AE108: =+AA108+AB108+AC108+AD108 -> 1656121.2 | AF108: =+AA108*(1+AF109) -> 422310.91 | AG108: =+AB108*(1+AG109) -> 422310.91 | AH108: =+AC108*(1+AH109) -> 422310.91 | AI108: =+AD108*(1+AI109) -> 422310.91 | AJ108: =+AF108+AG108+AH108+AI108 -> 1689243.6 | AK108: =+AF108*(1+AK109) -> 430757.13 | AL108: =+AG108*(1+AL109) -> 430757.13 | AM108: =+AH108*(1+AM109) -> 430757.13 | AN108: =+AI108*(1+AN109) -> 430757.13 | AO108: =+AK108+AL108+AM108+AN108 -> 1723028.5 | AP108: =+AK108*(1+AP109) -> 439372.27 | AQ108: =+AL108*(1+AQ109) -> 439372.27 | AR108: =+AM108*(1+AR109) -> 439372.27 | AS108: =+AN108*(1+AS109) -> 439372.27 | AT108: =+AP108+AQ108+AR108+AS108 -> 1757489.1 | AU108: =+AP108*(1+AU109) -> 448159.71 | AV108: =+AQ108*(1+AV109) -> 448159.71 | AW108: =+AR108*(1+AW109) -> 448159.71 | AX108: =+AS108*(1+AX109) -> 448159.71 | AY108: =+AU108+AV108+AW108+AX108 -> 1792638.9 | AZ108: =+AU108*(1+AZ109) -> 457122.91 | BA108: =+AV108*(1+BA109) -> 457122.91 | BB108: =+AW108*(1+BB109) -> 457122.91 | BC108: =+AX108*(1+BC109) -> 457122.91 | BD108: =+AZ108+BA108+BB108+BC108 -> 1828491.6 | BE108: =+AZ108*(1+BE109) -> 461694.14 | BF108: =+BA108*(1+BF109) -> 466265.37 | BG108: =+BB108*(1+BG109) -> 466265.37 | BH108: =+BC108*(1+BH109) -> 466265.37 | BI108: =+BE108+BF108+BG108+BH108 -> 1860490.2 | BJ108: =+BE108*(1+BJ109) -> 470928.02 | BK108: =+BF108*(1+BK109) -> 475590.67 | BL108: =+BG108*(1+BL109) -> 475590.67 | BM108: =+BH108*(1+BM109) -> 475590.67 | BN108: =+BJ108+BK108+BL108+BM108 -> 1897700 | BO108: =+BJ108*(1+BO109) -> 480346.58 | BP108: =+BK108*(1+BP109) -> 485102.49 | BQ108: =+BL108*(1+BQ109) -> 485102.49 | BR108: =+BM108*(1+BR109) -> 485102.49 | BS108: =+BO108+BP108+BQ108+BR108 -> 1935654 | BT108: =+BO108*(1+BT109) -> 489953.51 | BU108: =+BP108*(1+BU109) -> 494804.54 | BV108: =+BQ108*(1+BV109) -> 494804.54 | BW108: =+BR108*(1+BW109) -> 494804.54 | BX108: =+BT108+BU108+BV108+BW108 -> 1974367.1 | BY108: =+BT108*(1+BY109) -> 499752.58 | BZ108: =+BU108*(1+BZ109) -> 504700.63 | CA108: =+BV108*(1+CA109) -> 504700.63 | CB108: =+BW108*(1+CB109) -> 504700.63 | CC108: =+BY108+BZ108+CA108+CB108 -> 2013854.5 | CD108: =+BY108*(1+CD109) -> 509747.63 | CE108: =+BZ108*(1+CE109) -> 514794.64 | CF108: =+CA108*(1+CF109) -> 514794.64 | CG108: =+CB108*(1+CG109) -> 514794.64 | CH108: =+CD108+CE108+CF108+CG108 -> 2054131.6 | CI108: =+CD108*(1+CI109) -> 519942.59 | CJ108: =+CE108*(1+CJ109) -> 525090.53 | CK108: =+CF108*(1+CK109) -> 525090.53 | CL108: =+CG108*(1+CL109) -> 525090.53 | CM108: =+CI108+CJ108+CK108+CL108 -> 2095214.2 | CN108: =+CI108*(1+CN109) -> 530341.44 | CO108: =+CJ108*(1+CO109) -> 535592.34 | CP108: =+CK108*(1+CP109) -> 535592.34 | CQ108: =+CL108*(1+CQ109) -> 535592.34 | CR108: =+CN108+CO108+CP108+CQ108 -> 2137118.5 | CS108: =+CN108*(1+CS109) -> 540948.27 | CT108: =+CO108*(1+CT109) -> 546304.19 | CU108: =+CP108*(1+CU109) -> 546304.19 | CV108: =+CQ108*(1+CV109) -> 546304.19 | CW108: =+CS108+CT108+CU108+CV108 -> 2179860.8 | CX108: =+CS108*(1+CX109) -> 551767.23 | CY108: =+CT108*(1+CY109) -> 557230.27 | CZ108: =+CU108*(1+CZ109) -> 557230.27 | DA108: =+CV108*(1+DA109) -> 557230.27 | DB108: =+CX108+CY108+CZ108+DA108 -> 2223458.1
A109: % yoy | B109: -- | C109: -- | D109: -- | E109: -- | F109: -- | G109: 0.02 | H109: 0.02 | I109: 0.02 | J109: 0.02 | K109: =+K108/F108-1 -> 0.02 | L109: 0.02 | M109: 0.02 | N109: 0.02 | O109: 0.02 | P109: =+P108/K108-1 -> 0.02 | Q109: 0.02 | R109: 0.02 | S109: 0.02 | T109: 0.02 | U109: =+U108/P108-1 -> 0.02 | V109: 0.02 | W109: 0.02 | X109: 0.02 | Y109: 0.02 | Z109: =+Z108/U108-1 -> 0.02 | AA109: 0.02 | AB109: 0.02 | AC109: 0.02 | AD109: 0.02 | AE109: =+AE108/Z108-1 -> 0.02 | AF109: 0.02 | AG109: 0.02 | AH109: 0.02 | AI109: 0.02 | AJ109: =+AJ108/AE108-1 -> 0.02 | AK109: 0.02 | AL109: 0.02 | AM109: 0.02 | AN109: 0.02 | AO109: =+AO108/AJ108-1 -> 0.02 | AP109: 0.02 | AQ109: 0.02 | AR109: 0.02 | AS109: 0.02 | AT109: =+AT108/AO108-1 -> 0.02 | AU109: 0.02 | AV109: 0.02 | AW109: 0.02 | AX109: 0.02 | AY109: =+AY108/AT108-1 -> 0.02 | AZ109: 0.02 | BA109: 0.02 | BB109: 0.02 | BC109: 0.02 | BD109: =+BD108/AY108-1 -> 0.02 | BE109: 0.01 | BF109: 0.02 | BG109: 0.02 | BH109: 0.02 | BI109: =+BI108/BD108-1 -> 0.0175 | BJ109: 0.02 | BK109: 0.02 | BL109: 0.02 | BM109: 0.02 | BN109: =+BN108/BI108-1 -> 0.02 | BO109: 0.02 | BP109: 0.02 | BQ109: 0.02 | BR109: 0.02 | BS109: =+BS108/BN108-1 -> 0.02 | BT109: 0.02 | BU109: 0.02 | BV109: 0.02 | BW109: 0.02 | BX109: =+BX108/BS108-1 -> 0.02 | BY109: 0.02 | BZ109: 0.02 | CA109: 0.02 | CB109: 0.02 | CC109: =+CC108/BX108-1 -> 0.02 | CD109: 0.02 | CE109: 0.02 | CF109: 0.02 | CG109: 0.02 | CH109: =+CH108/CC108-1 -> 0.02 | CI109: 0.02 | CJ109: 0.02 | CK109: 0.02 | CL109: 0.02 | CM109: =+CM108/CH108-1 -> 0.02 | CN109: 0.02 | CO109: 0.02 | CP109: 0.02 | CQ109: 0.02 | CR109: =+CR108/CM108-1 -> 0.02 | CS109: 0.02 | CT109: 0.02 | CU109: 0.02 | CV109: 0.02 | CW109: =+CW108/CR108-1 -> 0.02 | CX109: 0.02 | CY109: 0.02 | CZ109: 0.02 | DA109: 0.02 | DB109: =+DB108/CW108-1 -> 0.02
A110: % total | B110: =+B108/B114 -> 0.22058824 | C110: =+C108/C114 -> 0.22058824 | D110: =+D108/D114 -> 0.22058824 | E110: =+E108/E114 -> 0.22058824 | F110: =+F108/F114 -> 0.22058824 | G110: =+G108/G114 -> 0.22228679 | H110: =+H108/H114 -> 0.22228679 | I110: =+I108/I114 -> 0.22228679 | ... DB110: =+DB108/DB114 -> 0.25585029
A111: Average / Low Risk Pregnancies | B111: =+F111/4 -> 1325000 | C111: =+F111/4 -> 1325000 | D111: =+F111/4 -> 1325000 | E111: =+F111/4 -> 1325000 | F111: 5300000 | G111: =+B111*(1+G112) -> 1338250 | H111: =+C111*(1+H112) -> 1338250 | I111: =+D111*(1+I112) -> 1338250 | J111: =+E111*(1+J112) -> 1338250 | K111: =+G111+H111+I111+J111 -> 5353000 | L111: =+G111*(1+L112) -> 1351632.5 | M111: =+H111*(1+M112) -> 1351632.5 | N111: =+I111*(1+N112) -> 1351632.5 | O111: =+J111*(1+O112) -> 1351632.5 | P111: =+L111+M111+N111+O111 -> 5406530 | Q111: =+L111*(1+Q112) -> 1365148.8 | R111: =+M111*(1+R112) -> 1365148.8 | S111: =+N111*(1+S112) -> 1365148.8 | T111: =+O111*(1+T112) -> 1365148.8 | U111: =+Q111+R111+S111+T111 -> 5460595.3 | V111: =+Q111*(1+V112) -> 1378800.3 | W111: =+R111*(1+W112) -> 1378800.3 | X111: =+S111*(1+X112) -> 1378800.3 | Y111: =+T111*(1+Y112) -> 1378800.3 | Z111: =+V111+W111+X111+Y111 -> 5515201.3 | AA111: =+V111*(1+AA112) -> 1392588.3 | AB111: =+W111*(1+AB112) -> 1392588.3 | AC111: =+X111*(1+AC112) -> 1392588.3 | AD111: =+Y111*(1+AD112) -> 1392588.3 | AE111: =+AA111+AB111+AC111+AD111 -> 5570353.3 | AF111: =+AA111*(1+AF112) -> 1406514.2 | AG111: =+AB111*(1+AG112) -> 1406514.2 | AH111: =+AC111*(1+AH112) -> 1406514.2 | AI111: =+AD111*(1+AI112) -> 1406514.2 | AJ111: =+AF111+AG111+AH111+AI111 -> 5626056.8 | AK111: =+AF111*(1+AK112) -> 1420579.3 | AL111: =+AG111*(1+AL112) -> 1420579.3 | AM111: =+AH111*(1+AM112) -> 1420579.3 | AN111: =+AI111*(1+AN112) -> 1420579.3 | AO111: =+AK111+AL111+AM111+AN111 -> 5682317.4 | AP111: =+AK111*(1+AP112) -> 1434785.1 | AQ111: =+AL111*(1+AQ112) -> 1434785.1 | AR111: =+AM111*(1+AR112) -> 1434785.1 | AS111: =+AN111*(1+AS112) -> 1434785.1 | AT111: =+AP111+AQ111+AR111+AS111 -> 5739140.5 | AU111: =+AP111*(1+AU112) -> 1449133 | AV111: =+AQ111*(1+AV112) -> 1449133 | AW111: =+AR111*(1+AW112) -> 1449133 | AX111: =+AS111*(1+AX112) -> 1449133 | AY111: =+AU111+AV111+AW111+AX111 -> 5796531.9 | AZ111: =+AU111*(1+AZ112) -> 1463624.3 | BA111: =+AV111*(1+BA112) -> 1463624.3 | BB111: =+AW111*(1+BB112) -> 1463624.3 | BC111: =+AX111*(1+BC112) -> 1463624.3 | BD111: =+AZ111+BA111+BB111+BC111 -> 5854497.3 | BE111: =+AZ111*(1+BE112) -> 1478260.6 | BF111: =+BA111*(1+BF112) -> 1478260.6 | BG111: =+BB111*(1+BG112) -> 1478260.6 | BH111: =+BC111*(1+BH112) -> 1478260.6 | BI111: =+BE111+BF111+BG111+BH111 -> 5913042.2 | BJ111: =+BE111*(1+BJ112) -> 1493043.2 | BK111: =+BF111*(1+BK112) -> 1493043.2 | BL111: =+BG111*(1+BL112) -> 1493043.2 | BM111: =+BH111*(1+BM112) -> 1493043.2 | BN111: =+BJ111+BK111+BL111+BM111 -> 5972172.7 | BO111: =+BJ111*(1+BO112) -> 1507973.6 | BP111: =+BK111*(1+BP112) -> 1507973.6 | BQ111: =+BL111*(1+BQ112) -> 1507973.6 | BR111: =+BM111*(1+BR112) -> 1507973.6 | BS111: =+BO111+BP111+BQ111+BR111 -> 6031894.4 | BT111: =+BO111*(1+BT112) -> 1523053.3 | BU111: =+BP111*(1+BU112) -> 1523053.3 | BV111: =+BQ111*(1+BV112) -> 1523053.3 | BW111: =+BR111*(1+BW112) -> 1523053.3 | BX111: =+BT111+BU111+BV111+BW111 -> 6092213.3 | BY111: =+BT111*(1+BY112) -> 1538283.9 | BZ111: =+BU111*(1+BZ112) -> 1538283.9 | CA111: =+BV111*(1+CA112) -> 1538283.9 | CB111: =+BW111*(1+CB112) -> 1538283.9 | CC111: =+BY111+BZ111+CA111+CB111 -> 6153135.5 | CD111: =+BY111*(1+CD112) -> 1553666.7 | CE111: =+BZ111*(1+CE112) -> 1553666.7 | CF111: =+CA111*(1+CF112) -> 1553666.7 | CG111: =+CB111*(1+CG112) -> 1553666.7 | CH111: =+CD111+CE111+CF111+CG111 -> 6214666.8 | CI111: =+CD111*(1+CI112) -> 1569203.4 | CJ111: =+CE111*(1+CJ112) -> 1569203.4 | CK111: =+CF111*(1+CK112) -> 1569203.4 | CL111: =+CG111*(1+CL112) -> 1569203.4 | CM111: =+CI111+CJ111+CK111+CL111 -> 6276813.5 | CN111: =+CI111*(1+CN112) -> 1584895.4 | CO111: =+CJ111*(1+CO112) -> 1584895.4 | CP111: =+CK111*(1+CP112) -> 1584895.4 | CQ111: =+CL111*(1+CQ112) -> 1584895.4 | CR111: =+CN111+CO111+CP111+CQ111 -> 6339581.6 | CS111: =+CN111*(1+CS112) -> 1600744.4 | CT111: =+CO111*(1+CT112) -> 1600744.4 | CU111: =+CP111*(1+CU112) -> 1600744.4 | CV111: =+CQ111*(1+CV112) -> 1600744.4 | CW111: =+CS111+CT111+CU111+CV111 -> 6402977.4 | CX111: =+CS111*(1+CX112) -> 1616751.8 | CY111: =+CT111*(1+CY112) -> 1616751.8 | CZ111: =+CU111*(1+CZ112) -> 1616751.8 | DA111: =+CV111*(1+DA112) -> 1616751.8 | DB111: =+CX111+CY111+CZ111+DA111 -> 6467007.2
A112: % yoy | B112: -- | C112: -- | D112: -- | E112: -- | F112: -- | G112: 0.01 | H112: 0.01 | I112: 0.01 | J112: 0.01 | K112: =+K111/F111-1 -> 0.01 | L112: 0.01 | M112: 0.01 | N112: 0.01 | O112: 0.01 | P112: =+P111/K111-1 -> 0.01 | Q112: 0.01 | R112: 0.01 | S112: 0.01 | T112: 0.01 | U112: =+U111/P111-1 -> 0.01 | V112: 0.01 | W112: 0.01 | X112: 0.01 | Y112: 0.01 | Z112: =+Z111/U111-1 -> 0.01 | AA112: 0.01 | AB112: 0.01 | AC112: 0.01 | AD112: 0.01 | AE112: =+AE111/Z111-1 -> 0.01 | AF112: 0.01 | AG112: 0.01 | AH112: 0.01 | AI112: 0.01 | AJ112: =+AJ111/AE111-1 -> 0.01 | AK112: 0.01 | AL112: 0.01 | AM112: 0.01 | AN112: 0.01 | AO112: =+AO111/AJ111-1 -> 0.01 | AP112: 0.01 | AQ112: 0.01 | AR112: 0.01 | AS112: 0.01 | AT112: =+AT111/AO111-1 -> 0.01 | AU112: 0.01 | AV112: 0.01 | AW112: 0.01 | AX112: 0.01 | AY112: =+AY111/AT111-1 -> 0.01 | AZ112: 0.01 | BA112: 0.01 | BB112: 0.01 | BC112: 0.01 | BD112: =+BD111/AY111-1 -> 0.01 | BE112: 0.01 | BF112: 0.01 | BG112: 0.01 | BH112: 0.01 | BI112: =+BI111/BD111-1 -> 0.01 | BJ112: 0.01 | BK112: 0.01 | BL112: 0.01 | BM112: 0.01 | BN112: =+BN111/BI111-1 -> 0.01 | BO112: 0.01 | BP112: 0.01 | BQ112: 0.01 | BR112: 0.01 | BS112: =+BS111/BN111-1 -> 0.01 | BT112: 0.01 | BU112: 0.01 | BV112: 0.01 | BW112: 0.01 | BX112: =+BX111/BS111-1 -> 0.01 | BY112: 0.01 | BZ112: 0.01 | CA112: 0.01 | CB112: 0.01 | CC112: =+CC111/BX111-1 -> 0.01 | CD112: 0.01 | CE112: 0.01 | CF112: 0.01 | CG112: 0.01 | CH112: =+CH111/CC111-1 -> 0.01 | CI112: 0.01 | CJ112: 0.01 | CK112: 0.01 | CL112: 0.01 | CM112: =+CM111/CH111-1 -> 0.01 | CN112: 0.01 | CO112: 0.01 | CP112: 0.01 | CQ112: 0.01 | CR112: =+CR111/CM111-1 -> 0.01 | CS112: 0.01 | CT112: 0.01 | CU112: 0.01 | CV112: 0.01 | CW112: =+CW111/CR111-1 -> 0.01 | CX112: 0.01 | CY112: 0.01 | CZ112: 0.01 | DA112: 0.01 | DB112: =+DB111/CW111-1 -> 0.01
A113: % total | B113: =+B111/B114 -> 0.77941176 | C113: =+C111/C114 -> 0.77941176 | D113: =+D111/D114 -> 0.77941176 | E113: =+E111/E114 -> 0.77941176 | F113: =+F111/F114 -> 0.77941176 | G113: =+G111/G114 -> 0.77771321 | H113: =+H111/H114 -> 0.77771321 | I113: =+I111/I114 -> 0.77771321 | ... DB113: =+DB111/DB114 -> 0.74414971
A114: Total Market | B114: =+B108+B111 -> 1700000 | C114: =+C108+C111 -> 1700000 | D114: =+D108+D111 -> 1700000 | E114: =+E108+E111 -> 1700000 | F114: =+F108+F111 -> 6800000 | G114: =+G108+G111 -> 1720750 | H114: =+H108+H111 -> 1720750 | I114: =+I108+I111 -> 1720750 | ... DB114: =+DB108+DB111 -> 8690465.3
A115: % yoy | B115: -- | C115: -- | D115: -- | E115: -- | F115: -- | G115: =+G114/B114-1 -> 0.012205882 | H115: =+H114/C114-1 -> 0.012205882 | I115: =+I114/D114-1 -> 0.012205882 | J115: =+J114/E114-1 -> 0.012205882 | K115: =+K114/F114-1 -> 0.012205882 | L115: =+L114/G114-1 -> 0.012222868 | M115: =+M114/H114-1 -> 0.012222868 | N115: =+N114/I114-1 -> 0.012222868 | ... DB115: =+DB114/CW114-1 -> 0.01253979
A117: High Risk Tests | B117: =+B67-B95 -> 7386.2075 | C117: =+C67-C95 -> 7876.5782 | D117: =+D67-D95 -> 9324.8442 | E117: =+E67-E95 -> 10606.8 | F117: =+B117+C117+D117+E117 -> 35194.43 | G117: =+G67-G95 -> 11815.058 | H117: =+H67-H95 -> 11682.978 | I117: =+I67-I95 -> 19733.876 | J117: =+J119*J108 -> 13005 | K117: =+G117+H117+I117+J117 -> 56236.911 | L117: =+L119*L108 -> 13265.1 | M117: =+M119*M108 -> 12484.8 | N117: =+N119*N108 -> 9753.75 | O117: =+O119*O108 -> 8388.225 | P117: =+L117+M117+N117+O117 -> 43891.875 | Q117: =+Q119*Q108 -> 8953.9425 | R117: =+R119*R108 -> 9152.919 | S117: =+S119*S108 -> 9431.4861 | T117: =+T119*T108 -> 9829.4391 | U117: =+Q117+R117+S117+T117 -> 37367.787 | V117: =+V119*V108 -> 10553.714 | W117: =+W119*W108 -> 10350.758 | X117: =+X119*X108 -> 9376.5686 | Y117: =+Y119*Y108 -> 8930.0653 | Z117: =+V117+W117+X117+Y117 -> 39211.105 | AA117: =+AA119*AA108 -> 13248.97 | AB117: =+AB119*AB108 -> 19045.394 | AC117: =+AC119*AC108 -> 21613.624 | AD117: =+AD119*AD108 -> 21943.606 | AE117: =+AA117+AB117+AC117+AD117 -> 75851.593 | AF117: =+AF119*AF108 -> 23015.944 | AG117: =+AG119*AG108 -> 22804.789 | AH117: =+AH119*AH108 -> 22804.789 | AI117: =+AI119*AI108 -> 22804.789 | AJ117: =+AF117+AG117+AH117+AI117 -> 91430.311 | AK117: =+AK119*AK108 -> 24983.913 | AL117: =+AL119*AL108 -> 25845.428 | AM117: =+AM119*AM108 -> 29291.485 | AN117: =+AN119*AN108 -> 32737.542 | AO117: =+AK117+AL117+AM117+AN117 -> 112858.37 | AP117: =+AP119*AP108 -> 33831.665 | AQ117: =+AQ119*AQ108 -> 33831.665 | AR117: =+AR119*AR108 -> 33831.665 | AS117: =+AS119*AS108 -> 34271.037 | AT117: =+AP117+AQ117+AR117+AS117 -> 135766.03 | AU117: =+AU119*AU108 -> 35852.777 | AV117: =+AV119*AV108 -> 35852.777 | AW117: =+AW119*AW108 -> 35852.777 | AX117: =+AX119*AX108 -> 35852.777 | AY117: =+AU117+AV117+AW117+AX117 -> 143411.11 | AZ117: =+AZ119*AZ108 -> 37941.201 | BA117: =+BA119*BA108 -> 36569.833 | BB117: =+BB119*BB108 -> 37941.201 | BC117: =+BC119*BC108 -> 37941.201 | BD117: =+AZ117+BA117+BB117+BC117 -> 150393.44 | BE117: =+BE119*BE108 -> 39013.155 | BF117: =+BF119*BF108 -> 40098.821 | BG117: =+BG119*BG108 -> 40798.219 | BH117: =+BH119*BH108 -> 41963.883 | BI117: =+BE117+BF117+BG117+BH117 -> 161874.08 | BJ117: =+BJ119*BJ108 -> 44738.162 | BK117: =+BK119*BK108 -> 45894.5 | BL117: =+BL119*BL108 -> 46607.886 | BM117: =+BM119*BM108 -> 47321.272 | BN117: =+BJ117+BK117+BL117+BM117 -> 184561.82 | BO117: =+BO119*BO108 -> 48515.005 | BP117: =+BP119*BP108 -> 49723.005 | BQ117: =+BQ119*BQ108 -> 50450.659 | BR117: =+BR119*BR108 -> 51178.312 | BS117: =+BO117+BP117+BQ117+BR117 -> 199866.98 | BT117: =+BT119*BT108 -> 52425.026 | BU117: =+BU119*BU108 -> 53686.292 | BV117: =+BV119*BV108 -> 54428.499 | BW117: =+BW119*BW108 -> 55170.706 | BX117: =+BT117+BU117+BV117+BW117 -> 215710.52 | BY117: =+BY119*BY108 -> 56472.042 | BZ117: =+BZ119*BZ108 -> 57788.222 | CA117: =+CA119*CA108 -> 58545.273 | CB117: =+CB119*CB108 -> 59302.324 | CC117: =+BY117+BZ117+CA117+CB117 -> 232107.86 | CD117: =+CD119*CD108 -> 60659.968 | CE117: =+CE119*CE108 -> 62032.754 | CF117: =+CF119*CF108 -> 62804.946 | CG117: =+CG119*CG108 -> 63577.138 | CH117: =+CD117+CE117+CF117+CG117 -> 249074.81 | CI117: =+CI119*CI108 -> 64992.823 | CJ117: =+CJ119*CJ108 -> 66423.952 | CK117: =+CK119*CK108 -> 67211.588 | CL117: =+CL119*CL108 -> 67999.224 | CM117: =+CI117+CJ117+CK117+CL117 -> 266627.59 | CN117: =+CN119*CN108 -> 69474.728 | CO117: =+CO119*CO108 -> 70965.985 | CP117: =+CP119*CP108 -> 71769.374 | CQ117: =+CQ119*CQ108 -> 72572.762 | CR117: =+CN117+CO117+CP117+CQ117 -> 284782.85 | CS117: =+CS119*CS108 -> 74109.912 | CT117: =+CT119*CT108 -> 75663.13 | CU117: =+CU119*CU108 -> 76482.587 | CV117: =+CV119*CV108 -> 77302.043 | CW117: =+CS117+CT117+CU117+CV117 -> 303557.67 | CX117: =+CX119*CX108 -> 78902.714 | CY117: =+CY119*CY108 -> 80519.775 | CZ117: =+CZ119*CZ108 -> 81355.62 | DA117: =+DA119*DA108 -> 82191.465 | DB117: =+CX117+CY117+CZ117+DA117 -> 322969.57
A118: % yoy | B118: -- | C118: -- | D118: -- | E118: -- | F118: -- | G118: =+G117/B117-1 -> 0.59961084 | H118: =+H117/C117-1 -> 0.48325545 | I118: =+I117/D117-1 -> 1.1162687 | J118: =+J117/E117-1 -> 0.22610024 | K118: =+K117/F117-1 -> 0.59789237 | L118: =+L117/G117-1 -> 0.12272834 | M118: =+M117/H117-1 -> 0.06863168 | N118: =+N117/I117-1 -> -0.50573572 | ... DB118: =+DB117/CW117-1 -> 0.063947986
A119: % HR Pregnancies | B119: =+B117/B108 -> 0.019696553 | C119: =+C117/C108 -> 0.021004209 | D119: =+D117/D108 -> 0.024866251 | E119: =+E117/E108 -> 0.0282848 | F119: =+F117/F108 -> 0.023462953 | G119: =+G117/G108 -> 0.030889039 | H119: =+H117/H108 -> 0.030543732 | I119: =+I117/I108 -> 0.051591833 | J119: 0.034 | K119: =+K117/K108 -> 0.036756151 | L119: 0.034 | M119: 0.032 | N119: 0.025 | O119: 0.0215 | P119: =+P117/P108 -> 0.028125 | Q119: 0.0225 | R119: 0.023 | S119: 0.0237 | T119: 0.0247 | U119: =+U117/U108 -> 0.023475 | V119: 0.026 | W119: 0.0255 | X119: 0.0231 | Y119: 0.022 | Z119: =+Z117/Z108 -> 0.02415 | AA119: 0.032 | AB119: 0.046 | AC119: 0.052203 | AD119: 0.053 | AE119: =+AE117/AE108 -> 0.04580075 | AF119: 0.0545 | AG119: 0.054 | AH119: 0.054 | AI119: 0.054 | AJ119: =+AJ117/AJ108 -> 0.054125 | AK119: 0.058 | AL119: 0.06 | AM119: 0.068 | AN119: 0.076 | AO119: =+AO117/AO108 -> 0.0655 | AP119: 0.077 | AQ119: 0.077 | AR119: 0.077 | AS119: 0.078 | AT119: =+AT117/AT108 -> 0.07725 | AU119: 0.08 | AV119: 0.08 | AW119: 0.08 | AX119: 0.08 | AY119: =+AY117/AY108 -> 0.08 | AZ119: 0.083 | BA119: 0.08 | BB119: 0.083 | BC119: 0.083 | BD119: =+BD117/BD108 -> 0.08225 | BE119: =+BC119+0.0015 -> 0.0845 | BF119: =+BE119+0.0015 -> 0.086 | BG119: =+BF119+0.0015 -> 0.0875 | BH119: 0.09 | BI119: =+BI117/BI108 -> 0.087006143 | BJ119: =+BH119+0.005 -> 0.095 | BK119: =+BJ119+0.0015 -> 0.0965 | BL119: =+BK119+0.0015 -> 0.098 | BM119: =+BL119+0.0015 -> 0.0995 | BN119: =+BN117/BN108 -> 0.097255528 | BO119: =+BM119+0.0015 -> 0.101 | BP119: =+BO119+0.0015 -> 0.1025 | BQ119: =+BP119+0.0015 -> 0.104 | BR119: =+BQ119+0.0015 -> 0.1055 | BS119: =+BS117/BS108 -> 0.10325553 | BT119: =+BR119+0.0015 -> 0.107 | BU119: =+BT119+0.0015 -> 0.1085 | BV119: =+BU119+0.0015 -> 0.11 | BW119: =+BV119+0.0015 -> 0.1115 | BX119: =+BX117/BX108 -> 0.10925553 | BY119: =+BW119+0.0015 -> 0.113 | BZ119: =+BY119+0.0015 -> 0.1145 | CA119: =+BZ119+0.0015 -> 0.116 | CB119: =+CA119+0.0015 -> 0.1175 | CC119: =+CC117/CC108 -> 0.11525553 | CD119: =+CB119+0.0015 -> 0.119 | CE119: =+CD119+0.0015 -> 0.1205 | CF119: =+CE119+0.0015 -> 0.122 | CG119: =+CF119+0.0015 -> 0.1235 | CH119: =+CH117/CH108 -> 0.12125553 | CI119: =+CG119+0.0015 -> 0.125 | CJ119: =+CI119+0.0015 -> 0.1265 | CK119: =+CJ119+0.0015 -> 0.128 | CL119: =+CK119+0.0015 -> 0.1295 | CM119: =+CM117/CM108 -> 0.12725553 | CN119: =+CL119+0.0015 -> 0.131 | CO119: =+CN119+0.0015 -> 0.1325 | CP119: =+CO119+0.0015 -> 0.134 | CQ119: =+CP119+0.0015 -> 0.1355 | CR119: =+CR117/CR108 -> 0.13325553 | CS119: =+CQ119+0.0015 -> 0.137 | CT119: =+CS119+0.0015 -> 0.1385 | CU119: =+CT119+0.0015 -> 0.14 | CV119: =+CU119+0.0015 -> 0.1415 | CW119: =+CW117/CW108 -> 0.13925553 | CX119: =+CV119+0.0015 -> 0.143 | CY119: =+CX119+0.0015 -> 0.1445 | CZ119: =+CY119+0.0015 -> 0.146 | DA119: =+CZ119+0.0015 -> 0.1475 | DB119: =+DB117/DB108 -> 0.14525553
