Workbook

Sheet Revenue Model
A1: Veracyte Inc. | BS1: Needham & Company, LLC
A2: Quarterly Revenue Model | BS2: Michael Matson ● (617) 457-0949
A3: ($ In Millions)
B5: 41699 | C5: 41791 | D5: 41883 | E5: 41974 | F5: 2014 | G5: 42064 | H5: 42156 | I5: 42248 | J5: 42339 | K5: 2015 | L5: 42430 | M5: 42522 | N5: 42614 | O5: 42705 | P5: 2016 | Q5: 42795 | R5: 42887 | S5: 42979 | T5: 43070 | U5: 2017 | V5: 43160 | W5: 43252 | X5: 43344 | Y5: 43435 | Z5: 2018 | AA5: 43525 | AB5: 43617 | AC5: 43709 | AD5: 43800 | AE5: 2019 | AF5: 43891 | AG5: 43983 | AH5: 44075 | AI5: 44166 | AJ5: 2020 | AK5: 44256 | AL5: 44348 | AM5: 44440 | AN5: 44531 | AO5: 2021 | AP5: 44621 | AQ5: 44713 | AR5: 44805 | AS5: 44896 | AT5: 2022 | AU5: 44986 | AV5: 45078 | AW5: 45170 | AX5: 45261 | AY5: 2023 | AZ5: 45352 | BA5: 45444 | BB5: 45536 | BC5: 45627 | BD5: 2024 | BE5: 45717 | BF5: 45809 | BG5: 45901 | BH5: 45992 | BI5: 2025 | BJ5: =DATE(YEAR(BE5)+1,MONTH(BE5),DAY(BE5)) -> 46082 | BK5: =DATE(YEAR(BF5)+1,MONTH(BF5),DAY(BF5)) -> 46174 | BL5: =DATE(YEAR(BG5)+1,MONTH(BG5),DAY(BG5)) -> 46266 | BM5: =DATE(YEAR(BH5)+1,MONTH(BH5),DAY(BH5)) -> 46357 | BN5: 2026E | BO5: =DATE(YEAR(BJ5)+1,MONTH(BJ5),DAY(BJ5)) -> 46447 | BP5: =DATE(YEAR(BK5)+1,MONTH(BK5),DAY(BK5)) -> 46539 | BQ5: =DATE(YEAR(BL5)+1,MONTH(BL5),DAY(BL5)) -> 46631 | BR5: =DATE(YEAR(BM5)+1,MONTH(BM5),DAY(BM5)) -> 46722 | BS5: 2027E
B6: Q114A | C6: Q214A | D6: Q314A | E6: Q414A | F6: Annual | G6: Q115A | H6: Q215A | I6: Q315A | J6: Q415A | K6: Annual | L6: Q116A | M6: Q216A | N6: Q316A | O6: Q416A | P6: Annual | Q6: Q117A | R6: Q217A | S6: Q317A | T6: Q417A | U6: Annual | V6: Q118A | W6: Q218A | X6: Q318A | Y6: Q418A | Z6: Annual | AA6: Q119A | AB6: Q219A | AC6: Q319A | AD6: Q419A | AE6: Annual | AF6: Q120A | AG6: Q220A | AH6: Q320A | AI6: Q420A | AJ6: Annual | AK6: Q121A | AL6: Q221A | AM6: Q321A | AN6: Q421A | AO6: Annual | AP6: Q122A | AQ6: Q222A | AR6: Q322A | AS6: Q422A | AT6: Annual | AU6: Q123A | AV6: Q223A | AW6: Q323A | AX6: Q423A | AY6: Annual | AZ6: Q124A | BA6: Q224A | BB6: Q324A | BC6: Q424A | BD6: Annual | BE6: Q125A | BF6: Q225A | BG6: Q325A | BH6: Q425A | BI6: Annual | BJ6: Q126E | BK6: Q226E | BL6: Q326E | BM6: Q426E | BN6: Annual | BO6: Q127E | BP6: Q227E | BQ6: Q327E | BR6: Q427E | BS6: Annual
A7: Revenue
A8: Testing Revenue | B8: 7.476 | C8: 8.677 | D8: 9.838 | E8: 12.199 | F8: =SUM(B8:E8) -> 38.19 | G8: 11.218 | H8: 11.908 | I8: 12.335 | J8: 14.042 | K8: =SUM(G8:J8) -> 49.503 | L8: 13.55 | M8: 14.675 | N8: 18.603 | O8: 18.257 | P8: =SUM(L8:O8) -> 65.085 | Q8: 16.432 | R8: 18.406 | S8: 17.519 | T8: 19.596 | U8: =SUM(Q8:T8) -> 71.953 | V8: 20.041 | W8: 22.301 | X8: 23.216 | Y8: 25.5 | Z8: =SUM(V8:Y8) -> 91.058 | AA8: 25.389 | AB8: 26.686 | AC8: 26.723 | AD8: 28.557 | AE8: =SUM(AA8:AD8) -> 107.355 | AF8: 26.991 | AG8: 15.212 | AH8: 28.27 | AI8: 31.497 | AJ8: =SUM(AF8:AI8) -> 101.97 | AK8: 33.078 | AL8: 50.793 | AM8: 50.897 | AN8: 53.414 | AO8: =SUM(AK8:AN8) -> 188.182 | AP8: 55.98 | AQ8: 59.718 | AR8: 64.577 | AS8: 70.269 | AT8: =SUM(AP8:AS8) -> 250.544 | AU8: 72.396 | AV8: 81.749 | AW8: 82.012 | AX8: 90.385 | AY8: =SUM(AU8:AX8) -> 326.542 | AZ8: 90.303 | BA8: 106.97 | BB8: 109.536 | BC8: 112.152 | BD8: =SUM(AZ8:BC8) -> 418.961 | BE8: 107.309 | BF8: 122.263 | BG8: 127.756 | BH8: 135.826 | BI8: =SUM(BE8:BH8) -> 493.154 | BJ8: =BJ28*BJ40/1000000 -> 126.5009 | BK8: =BK28*BK40/1000000 -> 143.52642 | BL8: =BL28*BL40/1000000 -> 142.9207 | BM8: =BM28*BM40/1000000 -> 149.698 | BN8: =SUM(BJ8:BM8) -> 562.64602 | BO8: =BO28*BO40/1000000 -> 140.28431 | BP8: =BP28*BP40/1000000 -> 159.27291 | BQ8: =BQ28*BQ40/1000000 -> 158.77311 | BR8: =BR28*BR40/1000000 -> 166.09808 | BS8: =SUM(BO8:BR8) -> 624.42842
A9: Product Revenue | B9: 0 | C9: 0 | D9: 0 | E9: 0 | F9: =SUM(B9:E9) -> 0 | G9: 0 | H9: 0 | I9: 0 | J9: 0 | K9: =SUM(G9:J9) -> 0 | L9: 0 | M9: 0 | N9: 0 | O9: 0 | P9: =SUM(L9:O9) -> 0 | Q9: 0 | R9: 0 | S9: 0 | T9: 0 | U9: =SUM(Q9:T9) -> 0 | V9: 0 | W9: 0 | X9: 0 | Y9: 0 | Z9: =SUM(V9:Y9) -> 0 | AA9: 0 | AB9: 0 | AC9: 0 | AD9: 0.923 | AE9: =SUM(AA9:AD9) -> 0.923 | AF9: 3.409 | AG9: 1.713 | AH9: 2.027 | AI9: 2.696 | AJ9: =SUM(AF9:AI9) -> 9.845 | AK9: 3.059 | AL9: 2.688 | AM9: 2.959 | AN9: 2.758 | AO9: =SUM(AK9:AN9) -> 11.464 | AP9: 2.979 | AQ9: 3.108 | AR9: 3.314 | AS9: 3.231 | AT9: =SUM(AP9:AS9) -> 12.632 | AU9: 3.892 | AV9: 4.011 | AW9: 4.02 | AX9: 3.665 | AY9: =SUM(AU9:AX9) -> 15.588 | AZ9: 3.537 | BA9: 3.906 | BB9: 3.188 | BC9: 3.019 | BD9: =SUM(AZ9:BC9) -> 13.65 | BE9: 3.58 | BF9: 3.598 | BG9: 3.301 | BH9: 3.848 | BI9: =SUM(BE9:BH9) -> 14.327 | BJ9: =BJ29*BJ41/1000000 -> 3.763765 | BK9: =BK29*BK41/1000000 -> 3.6978625 | BL9: =BL29*BL41/1000000 -> 3.204326 | BM9: =BM29*BM41/1000000 -> 3.6656435 | BN9: =SUM(BJ9:BM9) -> 14.331597 | BO9: =BO29*BO41/1000000 -> 3.8390403 | BP9: =BP29*BP41/1000000 -> 3.7718198 | BQ9: =BQ29*BQ41/1000000 -> 3.2684125 | BR9: =BR29*BR41/1000000 -> 3.7389564 | BS9: =SUM(BO9:BR9) -> 14.618229
A10: Biopharma and Other Revenue | B10: 0 | C10: 0 | D10: 0 | E10: 0 | F10: =SUM(B10:E10) -> 0 | G10: 0 | H10: 0 | I10: 0 | J10: 0 | K10: =SUM(G10:J10) -> 0 | L10: 0 | M10: 0 | N10: 0 | O10: 0 | P10: =SUM(L10:O10) -> 0 | Q10: 0 | R10: 0 | S10: 0 | T10: 0 | U10: =SUM(Q10:T10) -> 0 | V10: 0 | W10: 0.45 | X10: 0.25 | Y10: 0.25 | Z10: =SUM(V10:Y10) -> 0.95 | AA10: 4.14 | AB10: =1.45+2 -> 3.45 | AC10: =2.25+2 -> 4.25 | AD10: 0.25 | AE10: =SUM(AA10:AD10) -> 12.09 | AF10: 0.722 | AG10: 3.779 | AH10: 0.824 | AI10: 0.343 | AJ10: =SUM(AF10:AI10) -> 5.668 | AK10: 0.566 | AL10: 1.624 | AM10: 6.514 | AN10: 11.164 | AO10: =SUM(AK10:AN10) -> 19.868 | AP10: 8.824 | AQ10: 10.038 | AR10: 7.701 | AS10: 6.797 | AT10: =SUM(AP10:AS10) -> 33.36 | AU10: 6.134 | AV10: 4.562 | AW10: 4.076 | AX10: 4.149 | AY10: =SUM(AU10:AX10) -> 18.921 | AZ10: 3.004 | BA10: 3.552 | BB10: 3.136 | BC10: 3.461 | BD10: =SUM(AZ10:BC10) -> 13.153 | BE10: 3.584 | BF10: 4.303 | BG10: 0.815 | BH10: 0.962 | BI10: =SUM(BE10:BH10) -> 9.664 | BJ10: =BE10*(1+BJ16) -> 0 | BK10: =BF10*(1+BK16) -> 0 | BL10: =BG10*(1+BL16) -> 0 | BM10: =BH10*(1+BM16) -> 0 | BN10: =SUM(BJ10:BM10) -> 0 | BO10: =BJ10*(1+BO16) -> 0 | BP10: =BK10*(1+BP16) -> 0 | BQ10: =BL10*(1+BQ16) -> 0 | BR10: =BM10*(1+BR16) -> 0 | BS10: =SUM(BO10:BR10) -> 0
A11: Total Revenue | B11: =SUM(B8:B10) -> 7.476 | C11: =SUM(C8:C10) -> 8.677 | D11: =SUM(D8:D10) -> 9.838 | E11: =SUM(E8:E10) -> 12.199 | F11: =SUM(B11:E11) -> 38.19 | G11: =SUM(G8:G10) -> 11.218 | H11: =SUM(H8:H10) -> 11.908 | I11: =SUM(I8:I10) -> 12.335 | J11: =SUM(J8:J10) -> 14.042 | K11: =SUM(G11:J11) -> 49.503 | L11: =SUM(L8:L10) -> 13.55 | M11: =SUM(M8:M10) -> 14.675 | N11: =SUM(N8:N10) -> 18.603 | O11: =SUM(O8:O10) -> 18.257 | P11: =SUM(L11:O11) -> 65.085 | Q11: =SUM(Q8:Q10) -> 16.432 | R11: =SUM(R8:R10) -> 18.406 | S11: =SUM(S8:S10) -> 17.519 | T11: =SUM(T8:T10) -> 19.596 | U11: =SUM(Q11:T11) -> 71.953 | V11: =SUM(V8:V10) -> 20.041 | W11: =SUM(W8:W10) -> 22.751 | X11: =SUM(X8:X10) -> 23.466 | Y11: =SUM(Y8:Y10) -> 25.75 | Z11: =SUM(V11:Y11) -> 92.008 | AA11: =SUM(AA8:AA10) -> 29.529 | AB11: =SUM(AB8:AB10) -> 30.136 | AC11: =SUM(AC8:AC10) -> 30.973 | AD11: =SUM(AD8:AD10) -> 29.73 | AE11: =SUM(AA11:AD11) -> 120.368 | AF11: =SUM(AF8:AF10) -> 31.122 | AG11: =SUM(AG8:AG10) -> 20.704 | AH11: =SUM(AH8:AH10) -> 31.121 | AI11: =SUM(AI8:AI10) -> 34.536 | AJ11: =SUM(AF11:AI11) -> 117.483 | AK11: =SUM(AK8:AK10) -> 36.703 | AL11: =SUM(AL8:AL10) -> 55.105 | AM11: =SUM(AM8:AM10) -> 60.37 | AN11: =SUM(AN8:AN10) -> 67.336 | AO11: =SUM(AK11:AN11) -> 219.514 | AP11: =SUM(AP8:AP10) -> 67.783 | AQ11: =SUM(AQ8:AQ10) -> 72.864 | AR11: =SUM(AR8:AR10) -> 75.592 | AS11: =SUM(AS8:AS10) -> 80.297 | AT11: =SUM(AP11:AS11) -> 296.536 | AU11: =SUM(AU8:AU10) -> 82.422 | AV11: =SUM(AV8:AV10) -> 90.322 | AW11: =SUM(AW8:AW10) -> 90.108 | AX11: =SUM(AX8:AX10) -> 98.199 | AY11: =SUM(AU11:AX11) -> 361.051 | AZ11: =SUM(AZ8:AZ10) -> 96.844 | BA11: =SUM(BA8:BA10) -> 114.428 | BB11: =SUM(BB8:BB10) -> 115.86 | BC11: =SUM(BC8:BC10) -> 118.632 | BD11: =SUM(AZ11:BC11) -> 445.764 | BE11: =SUM(BE8:BE10) -> 114.473 | BF11: =SUM(BF8:BF10) -> 130.164 | BG11: =SUM(BG8:BG10) -> 131.872 | BH11: =SUM(BH8:BH10) -> 140.636 | BI11: =SUM(BE11:BH11) -> 517.145 | BJ11: =SUM(BJ8:BJ10) -> 130.26467 | BK11: =SUM(BK8:BK10) -> 147.22429 | BL11: =SUM(BL8:BL10) -> 146.12503 | BM11: =SUM(BM8:BM10) -> 153.36364 | BN11: =SUM(BJ11:BM11) -> 576.97762 | BO11: =SUM(BO8:BO10) -> 144.12335 | BP11: =SUM(BP8:BP10) -> 163.04473 | BQ11: =SUM(BQ8:BQ10) -> 162.04153 | BR11: =SUM(BR8:BR10) -> 169.83704 | BS11: =SUM(BO11:BR11) -> 639.04665
A13: Year/Year Changes
A14: Testing Revenue | B14: NA | C14: NA | D14: NA | E14: NA | F14: NA | G14: =IFERROR(G8/B8-1,"NA") -> 0.50053505 | H14: =IFERROR(H8/C8-1,"NA") -> 0.37236372 | I14: =IFERROR(I8/D8-1,"NA") -> 0.25381175 | J14: =IFERROR(J8/E8-1,"NA") -> 0.15107796 | K14: =IFERROR(K8/F8-1,"NA") -> 0.29622938 | L14: =IFERROR(L8/G8-1,"NA") -> 0.20788019 | M14: =IFERROR(M8/H8-1,"NA") -> 0.2323648 | N14: =IFERROR(N8/I8-1,"NA") -> 0.50814755 | ... BS14: =IFERROR(BS8/BN8-1,"NA") -> 0.10980687
A15: Product Revenue | B15: NA | C15: NA | D15: NA | E15: NA | F15: NA | G15: =IFERROR(G9/B9-1,"NA") -> NA | H15: =IFERROR(H9/C9-1,"NA") -> NA | I15: =IFERROR(I9/D9-1,"NA") -> NA | J15: =IFERROR(J9/E9-1,"NA") -> NA | K15: =IFERROR(K9/F9-1,"NA") -> NA | L15: =IFERROR(L9/G9-1,"NA") -> NA | M15: =IFERROR(M9/H9-1,"NA") -> NA | N15: =IFERROR(N9/I9-1,"NA") -> NA | ... BS15: =IFERROR(BS9/BN9-1,"NA") -> 0.02
A16: Biopharma and Other Revenue | B16: NA | C16: NA | D16: NA | E16: NA | F16: NA | G16: =IFERROR(G10/B10-1,"NA") -> NA | H16: =IFERROR(H10/C10-1,"NA") -> NA | I16: =IFERROR(I10/D10-1,"NA") -> NA | J16: =IFERROR(J10/E10-1,"NA") -> NA | K16: =IFERROR(K10/F10-1,"NA") -> NA | L16: =IFERROR(L10/G10-1,"NA") -> NA | M16: =IFERROR(M10/H10-1,"NA") -> NA | N16: =IFERROR(N10/I10-1,"NA") -> NA | ... BI16: =IFERROR(BI10/BD10-1,"NA") -> -0.26526268 | BJ16: -1 | BK16: -1 | BL16: -1 | BM16: -1 | BN16: =IFERROR(BN10/BI10-1,"NA") -> -1 | BO16: -0.1 | BP16: -0.1 | BQ16: -0.1 | BR16: -0.1 | BS16: =IFERROR(BS10/BN10-1,"NA") -> NA
A17: Total Revenue | B17: NA | C17: NA | D17: NA | E17: NA | F17: NA | G17: =IFERROR(G11/B11-1,"NA") -> 0.50053505 | H17: =IFERROR(H11/C11-1,"NA") -> 0.37236372 | I17: =IFERROR(I11/D11-1,"NA") -> 0.25381175 | J17: =IFERROR(J11/E11-1,"NA") -> 0.15107796 | K17: =IFERROR(K11/F11-1,"NA") -> 0.29622938 | L17: =IFERROR(L11/G11-1,"NA") -> 0.20788019 | M17: =IFERROR(M11/H11-1,"NA") -> 0.2323648 | N17: =IFERROR(N11/I11-1,"NA") -> 0.50814755 | ... BS17: =IFERROR(BS11/BN11-1,"NA") -> 0.10757615
A19: % of Revenue
A20: Testing Revenue | B20: =B8/B$11 -> 1 | C20: =C8/C$11 -> 1 | D20: =D8/D$11 -> 1 | E20: =E8/E$11 -> 1 | F20: =F8/F$11 -> 1 | G20: =G8/G$11 -> 1 | H20: =H8/H$11 -> 1 | I20: =I8/I$11 -> 1 | ... BS20: =BS8/BS$11 -> 0.97712494
A21: Product Revenue | B21: =B9/B$11 -> 0 | C21: =C9/C$11 -> 0 | D21: =D9/D$11 -> 0 | E21: =E9/E$11 -> 0 | F21: =F9/F$11 -> 0 | G21: =G9/G$11 -> 0 | H21: =H9/H$11 -> 0 | I21: =I9/I$11 -> 0 | ... BS21: =BS9/BS$11 -> 0.022875058
A22: Biopharma and Other Revenue | B22: =B10/B$11 -> 0 | C22: =C10/C$11 -> 0 | D22: =D10/D$11 -> 0 | E22: =E10/E$11 -> 0 | F22: =F10/F$11 -> 0 | G22: =G10/G$11 -> 0 | H22: =H10/H$11 -> 0 | I22: =I10/I$11 -> 0 | ... BS22: =BS10/BS$11 -> 0
A23: Total Revenue | B23: =B11/B$11 -> 1 | C23: =C11/C$11 -> 1 | D23: =D11/D$11 -> 1 | E23: =E11/E$11 -> 1 | F23: =F11/F$11 -> 1 | G23: =G11/G$11 -> 1 | H23: =H11/H$11 -> 1 | I23: =I11/I$11 -> 1 | ... BS23: =BS11/BS$11 -> 1
A25: Test Volume
A26: Afirma | B26: 3098 | C26: 3451 | D26: 3441 | E26: 4071 | F26: =SUM(B26:E26) -> 14061 | G26: 4020 | H26: 4758 | I26: 5034 | J26: 5609 | K26: =SUM(G26:J26) -> 19421 | L26: 5352 | M26: 5832 | N26: 5740 | O26: 6313 | P26: =SUM(L26:O26) -> 23237 | Q26: 5834 | R26: 6506 | S26: 6533 | T26: 7153 | U26: =SUM(Q26:T26) -> 26026 | V26: 6864 | W26: 7686 | X26: 8006 | Y26: 9154 | Z26: =SUM(V26:Y26) -> 31710 | AA26: 9162 | AB26: 9663 | AC26: 9941 | AD26: 10846 | AE26: =SUM(AA26:AD26) -> 39612 | AF26: 10559 | AG26: 5379 | AH26: 10242 | AI26: 11221 | AJ26: =SUM(AF26:AI26) -> 37401 | AK26: 10743 | AL26: 12013 | AM26: 11342 | AN26: 12622 | AO26: =SUM(AK26:AN26) -> 46720 | AP26: =AP28-AP27 -> 12239 | AQ26: =AQ28-AQ27 -> 12604 | AR26: =AR28-AR27 -> 12974 | AS26: =AS28-AS27 -> 13701 | AT26: =SUM(AP26:AS26) -> 51518 | AU26: =AU28-AU27 -> 13388 | AV26: =AV28-AV27 -> 14009 | AW26: =AW28-AW27 -> 14194 | AX26: =AX28-AX27 -> 15736 | AY26: =SUM(AU26:AX26) -> 57327 | AZ26: 14000 | BA26: 15700 | BB26: 15100 | BC26: 16300 | BD26: =SUM(AZ26:BC26) -> 61100 | BE26: 15500 | BF26: =42441-BF27 -> 16941 | BG26: 17000 | BH26: 18250 | BI26: =SUM(BE26:BH26) -> 67691 | BJ26: =BE26*(1+BJ33) -> 16275 | BK26: =BF26*(1+BK33) -> 18126.87 | BL26: =BG26*(1+BL33) -> 17510 | BM26: =BH26*(1+BM33) -> 18980 | BN26: =SUM(BJ26:BM26) -> 70891.87 | BO26: =BJ26*(1+BO33) -> 16926 | BP26: =BK26*(1+BP33) -> 18851.945 | BQ26: =BL26*(1+BQ33) -> 18210.4 | BR26: =BM26*(1+BR33) -> 19739.2 | BS26: =SUM(BO26:BR26) -> 73727.545
A27: Decipher | B27: 0 | C27: 0 | D27: 0 | E27: 0 | F27: =SUM(B27:E27) -> 0 | G27: 0 | H27: 0 | I27: 0 | J27: 0 | K27: =SUM(G27:J27) -> 0 | L27: 0 | M27: 0 | N27: 0 | O27: 0 | P27: =SUM(L27:O27) -> 0 | Q27: 0 | R27: 0 | S27: 0 | T27: 0 | U27: =SUM(Q27:T27) -> 0 | V27: 0 | W27: 0 | X27: 0 | Y27: 0 | Z27: =SUM(V27:Y27) -> 0 | AA27: 0 | AB27: 0 | AC27: 0 | AD27: 0 | AE27: =SUM(AA27:AD27) -> 0 | AF27: 0 | AG27: 0 | AH27: 0 | AI27: 0 | AJ27: =SUM(AF27:AI27) -> 0 | AK27: 1560 | AL27: 6967 | AM27: 7500 | AN27: 7700 | AO27: =SUM(AK27:AN27) -> 23727 | AP27: 8800 | AQ27: 10000 | AR27: 11000 | AS27: 12000 | AT27: =SUM(AP27:AS27) -> 41800 | AU27: 12500 | AV27: 15050 | AW27: 15500 | AX27: 15500 | AY27: =SUM(AU27:AX27) -> 58550 | AZ27: 16500 | BA27: 19900 | BB27: 21250 | BC27: 22400 | BD27: =SUM(AZ27:BC27) -> 80050 | BE27: 22600 | BF27: 25500 | BG27: 26700 | BH27: 27200 | BI27: =SUM(BE27:BH27) -> 102000 | BJ27: =BE27*(1+BJ34) -> 27346 | BK27: =BF27*(1+BK34) -> 31365 | BL27: =BG27*(1+BL34) -> 31773 | BM27: =BH27*(1+BM34) -> 32640 | BN27: =SUM(BJ27:BM27) -> 123124 | BO27: =BJ27*(1+BO34) -> 31447.9 | BP27: =BK27*(1+BP34) -> 36069.75 | BQ27: =BL27*(1+BQ34) -> 36538.95 | BR27: =BM27*(1+BR34) -> 37536 | BS27: =SUM(BO27:BR27) -> 141592.6
A28: Total Testing Volume | B28: =SUM(B26:B27) -> 3098 | C28: =SUM(C26:C27) -> 3451 | D28: =SUM(D26:D27) -> 3441 | E28: =SUM(E26:E27) -> 4071 | F28: =SUM(B28:E28) -> 14061 | G28: =SUM(G26:G27) -> 4020 | H28: =SUM(H26:H27) -> 4758 | I28: =SUM(I26:I27) -> 5034 | J28: =SUM(J26:J27) -> 5609 | K28: =SUM(G28:J28) -> 19421 | L28: =SUM(L26:L27) -> 5352 | M28: =SUM(M26:M27) -> 5832 | N28: =SUM(N26:N27) -> 5740 | O28: =SUM(O26:O27) -> 6313 | P28: =SUM(L28:O28) -> 23237 | Q28: =SUM(Q26:Q27) -> 5834 | R28: =SUM(R26:R27) -> 6506 | S28: =SUM(S26:S27) -> 6533 | T28: =SUM(T26:T27) -> 7153 | U28: =SUM(Q28:T28) -> 26026 | V28: =SUM(V26:V27) -> 6864 | W28: =SUM(W26:W27) -> 7686 | X28: =SUM(X26:X27) -> 8006 | Y28: =SUM(Y26:Y27) -> 9154 | Z28: =SUM(V28:Y28) -> 31710 | AA28: =SUM(AA26:AA27) -> 9162 | AB28: =SUM(AB26:AB27) -> 9663 | AC28: =SUM(AC26:AC27) -> 9941 | AD28: =SUM(AD26:AD27) -> 10846 | AE28: =SUM(AA28:AD28) -> 39612 | AF28: =SUM(AF26:AF27) -> 10559 | AG28: =SUM(AG26:AG27) -> 5379 | AH28: =SUM(AH26:AH27) -> 10242 | AI28: =SUM(AI26:AI27) -> 11221 | AJ28: =SUM(AF28:AI28) -> 37401 | AK28: =SUM(AK26:AK27) -> 12303 | AL28: =SUM(AL26:AL27) -> 18980 | AM28: =SUM(AM26:AM27) -> 18842 | AN28: =SUM(AN26:AN27) -> 20322 | AO28: =SUM(AK28:AN28) -> 70447 | AP28: =21039 -> 21039 | AQ28: 22604 | AR28: 23974 | AS28: 25701 | AT28: =SUM(AP28:AS28) -> 93318 | AU28: =28788-AU29 -> 25888 | AV28: =31809-AV29 -> 29059 | AW28: =32544-AW29 -> 29694 | AX28: 31236 | AY28: =SUM(AU28:AX28) -> 115877 | AZ28: 30924 | BA28: 36000 | BB28: 36792 | BC28: 39107 | BD28: =SUM(AZ28:BC28) -> 142823 | BE28: =SUM(BE26:BE27) -> 38100 | BF28: =SUM(BF26:BF27) -> 42441 | BG28: =SUM(BG26:BG27) -> 43700 | BH28: =SUM(BH26:BH27) -> 45450 | BI28: =SUM(BE28:BH28) -> 169691 | BJ28: =SUM(BJ26:BJ27) -> 43621 | BK28: =SUM(BK26:BK27) -> 49491.87 | BL28: =SUM(BL26:BL27) -> 49283 | BM28: =SUM(BM26:BM27) -> 51620 | BN28: =SUM(BJ28:BM28) -> 194015.87 | BO28: =SUM(BO26:BO27) -> 48373.9 | BP28: =SUM(BP26:BP27) -> 54921.695 | BQ28: =SUM(BQ26:BQ27) -> 54749.35 | BR28: =SUM(BR26:BR27) -> 57275.2 | BS28: =SUM(BO28:BR28) -> 215320.14
A29: Total Product Volume | B29: 0 | C29: 0 | D29: 0 | E29: 0 | F29: =SUM(B29:E29) -> 0 | G29: 0 | H29: 0 | I29: 0 | J29: 0 | K29: =SUM(G29:J29) -> 0 | L29: 0 | M29: 0 | N29: 0 | O29: 0 | P29: =SUM(L29:O29) -> 0 | Q29: 0 | R29: 0 | S29: 0 | T29: 0 | U29: =SUM(Q29:T29) -> 0 | V29: 0 | W29: 0 | X29: 0 | Y29: 0 | Z29: =SUM(V29:Y29) -> 0 | AA29: 0 | AB29: 0 | AC29: 0 | AD29: 680 | AE29: =SUM(AA29:AD29) -> 680 | AF29: 2482 | AG29: 1249 | AH29: 1448 | AI29: 1909 | AJ29: =SUM(AF29:AI29) -> 7088 | AK29: 2134 | AL29: 1876 | AM29: 2130 | AN29: 1978 | AO29: =SUM(AK29:AN29) -> 8118 | AP29: 2206 | AQ29: 2300 | AR29: 2400 | AS29: 2300 | AT29: =SUM(AP29:AS29) -> 9206 | AU29: 2900 | AV29: 2750 | AW29: 2850 | AX29: 2600 | AY29: =SUM(AU29:AX29) -> 11100 | AZ29: 2500 | BA29: 3023 | BB29: 2240 | BC29: 2200 | BD29: =SUM(AZ29:BC29) -> 9963 | BE29: 2570 | BF29: =44966-42441 -> 2525 | BG29: 2188 | BH29: =48019-45516 -> 2503 | BI29: =SUM(BE29:BH29) -> 9786 | BJ29: =BE29*(1+BJ36) -> 2595.7 | BK29: =BF29*(1+BK36) -> 2550.25 | BL29: =BG29*(1+BL36) -> 2209.88 | BM29: =BH29*(1+BM36) -> 2528.03 | BN29: =SUM(BJ29:BM29) -> 9883.86 | BO29: =BJ29*(1+BO36) -> 2647.614 | BP29: =BK29*(1+BP36) -> 2601.255 | BQ29: =BL29*(1+BQ36) -> 2254.0776 | BR29: =BM29*(1+BR36) -> 2578.5906 | BS29: =SUM(BO29:BR29) -> 10081.537
A30: Total Volume | B30: =SUM(B28:B29) -> 3098 | C30: =SUM(C28:C29) -> 3451 | D30: =SUM(D28:D29) -> 3441 | E30: =SUM(E28:E29) -> 4071 | F30: =SUM(B30:E30) -> 14061 | G30: =SUM(G28:G29) -> 4020 | H30: =SUM(H28:H29) -> 4758 | I30: =SUM(I28:I29) -> 5034 | J30: =SUM(J28:J29) -> 5609 | K30: =SUM(G30:J30) -> 19421 | L30: =SUM(L28:L29) -> 5352 | M30: =SUM(M28:M29) -> 5832 | N30: =SUM(N28:N29) -> 5740 | O30: =SUM(O28:O29) -> 6313 | P30: =SUM(L30:O30) -> 23237 | Q30: =SUM(Q28:Q29) -> 5834 | R30: =SUM(R28:R29) -> 6506 | S30: =SUM(S28:S29) -> 6533 | T30: =SUM(T28:T29) -> 7153 | U30: =SUM(Q30:T30) -> 26026 | V30: =SUM(V28:V29) -> 6864 | W30: =SUM(W28:W29) -> 7686 | X30: =SUM(X28:X29) -> 8006 | Y30: =SUM(Y28:Y29) -> 9154 | Z30: =SUM(V30:Y30) -> 31710 | AA30: =SUM(AA28:AA29) -> 9162 | AB30: =SUM(AB28:AB29) -> 9663 | AC30: =SUM(AC28:AC29) -> 9941 | AD30: =SUM(AD28:AD29) -> 11526 | AE30: =SUM(AA30:AD30) -> 40292 | AF30: =SUM(AF28:AF29) -> 13041 | AG30: =SUM(AG28:AG29) -> 6628 | AH30: =SUM(AH28:AH29) -> 11690 | AI30: =SUM(AI28:AI29) -> 13130 | AJ30: =SUM(AF30:AI30) -> 44489 | AK30: =SUM(AK28:AK29) -> 14437 | AL30: =SUM(AL28:AL29) -> 20856 | AM30: =SUM(AM28:AM29) -> 20972 | AN30: =SUM(AN28:AN29) -> 22300 | AO30: =SUM(AK30:AN30) -> 78565 | AP30: =SUM(AP28:AP29) -> 23245 | AQ30: =SUM(AQ28:AQ29) -> 24904 | AR30: =SUM(AR28:AR29) -> 26374 | AS30: =SUM(AS28:AS29) -> 28001 | AT30: =SUM(AP30:AS30) -> 102524 | AU30: =SUM(AU28:AU29) -> 28788 | AV30: =SUM(AV28:AV29) -> 31809 | AW30: =SUM(AW28:AW29) -> 32544 | AX30: =SUM(AX28:AX29) -> 33836 | AY30: =SUM(AU30:AX30) -> 126977 | AZ30: =SUM(AZ28:AZ29) -> 33424 | BA30: =SUM(BA28:BA29) -> 39023 | BB30: =SUM(BB28:BB29) -> 39032 | BC30: 41271 | BD30: =SUM(AZ30:BC30) -> 152750 | BE30: 40655 | BF30: =SUM(BF28:BF29) -> 44966 | BG30: =SUM(BG28:BG29) -> 45888 | BH30: =SUM(BH28:BH29) -> 47953 | BI30: =SUM(BE30:BH30) -> 179462 | BJ30: =SUM(BJ28:BJ29) -> 46216.7 | BK30: =SUM(BK28:BK29) -> 52042.12 | BL30: =SUM(BL28:BL29) -> 51492.88 | BM30: =SUM(BM28:BM29) -> 54148.03 | BN30: =SUM(BJ30:BM30) -> 203899.73 | BO30: =SUM(BO28:BO29) -> 51021.514 | BP30: =SUM(BP28:BP29) -> 57522.95 | BQ30: =SUM(BQ28:BQ29) -> 57003.428 | BR30: =SUM(BR28:BR29) -> 59853.791 | BS30: =SUM(BO30:BR30) -> 225401.68
A32: Year/Year Changes
A33: Afirma | B33: NA | C33: NA | D33: NA | E33: NA | F33: NA | G33: =IFERROR(G26/B26-1,"NA") -> 0.29761136 | H33: =IFERROR(H26/C26-1,"NA") -> 0.3787308 | I33: =IFERROR(I26/D26-1,"NA") -> 0.46294682 | J33: =IFERROR(J26/E26-1,"NA") -> 0.37779415 | K33: =IFERROR(K26/F26-1,"NA") -> 0.38119622 | L33: =IFERROR(L26/G26-1,"NA") -> 0.33134328 | M33: =IFERROR(M26/H26-1,"NA") -> 0.22572509 | N33: =IFERROR(N26/I26-1,"NA") -> 0.14024632 | ... AM33: =IFERROR(AM26/AH26-1,"NA") -> 0.1074009 | AN33: 0.1146912 | AO33: =IFERROR(AO26/AJ26-1,"NA") -> 0.24916446 | AP33: =IFERROR(AP26/AK26-1,"NA") -> 0.13925347 | AQ33: =IFERROR(AQ26/AL26-1,"NA") -> 0.049196704 | AR33: =IFERROR(AR26/AM26-1,"NA") -> 0.14388997 | AS33: =IFERROR(AS26/AN26-1,"NA") -> 0.08548566 | AT33: =IFERROR(AT26/AO26-1,"NA") -> 0.10269692 | AU33: =IFERROR(AU26/AP26-1,"NA") -> 0.093880219 | AV33: =IFERROR(AV26/AQ26-1,"NA") -> 0.11147255 | ... BI33: =IFERROR(BI26/BD26-1,"NA") -> 0.10787234 | BJ33: 0.05 | BK33: 0.07 | BL33: 0.03 | BM33: 0.04 | BN33: =IFERROR(BN26/BI26-1,"NA") -> 0.047286493 | BO33: 0.04 | BP33: 0.04 | BQ33: 0.04 | BR33: 0.04 | BS33: =IFERROR(BS26/BN26-1,"NA") -> 0.04
A34: Decipher | B34: NA | C34: NA | D34: NA | E34: NA | F34: NA | G34: =IFERROR(G27/B27-1,"NA") -> NA | H34: =IFERROR(H27/C27-1,"NA") -> NA | I34: =IFERROR(I27/D27-1,"NA") -> NA | J34: =IFERROR(J27/E27-1,"NA") -> NA | K34: =IFERROR(K27/F27-1,"NA") -> NA | L34: =IFERROR(L27/G27-1,"NA") -> NA | M34: =IFERROR(M27/H27-1,"NA") -> NA | N34: =IFERROR(N27/I27-1,"NA") -> NA | ... BI34: =IFERROR(BI27/BD27-1,"NA") -> 0.27420362 | BJ34: 0.21 | BK34: 0.23 | BL34: 0.19 | BM34: 0.2 | BN34: =IFERROR(BN27/BI27-1,"NA") -> 0.20709804 | BO34: 0.15 | BP34: 0.15 | BQ34: 0.15 | BR34: 0.15 | BS34: =IFERROR(BS27/BN27-1,"NA") -> 0.15
A35: Total Testing Volume | B35: NA | C35: NA | D35: NA | E35: NA | F35: NA | G35: =IFERROR(G28/B28-1,"NA") -> 0.29761136 | H35: =IFERROR(H28/C28-1,"NA") -> 0.3787308 | I35: =IFERROR(I28/D28-1,"NA") -> 0.46294682 | J35: =IFERROR(J28/E28-1,"NA") -> 0.37779415 | K35: =IFERROR(K28/F28-1,"NA") -> 0.38119622 | L35: =IFERROR(L28/G28-1,"NA") -> 0.33134328 | M35: =IFERROR(M28/H28-1,"NA") -> 0.22572509 | N35: =IFERROR(N28/I28-1,"NA") -> 0.14024632 | ... BS35: =IFERROR(BS28/BN28-1,"NA") -> 0.10980687
A36: Total Product Volume | B36: NA | C36: NA | D36: NA | E36: NA | F36: NA | G36: =IFERROR(G29/B29-1,"NA") -> NA | H36: =IFERROR(H29/C29-1,"NA") -> NA | I36: =IFERROR(I29/D29-1,"NA") -> NA | J36: =IFERROR(J29/E29-1,"NA") -> NA | K36: =IFERROR(K29/F29-1,"NA") -> NA | L36: =IFERROR(L29/G29-1,"NA") -> NA | M36: =IFERROR(M29/H29-1,"NA") -> NA | N36: =IFERROR(N29/I29-1,"NA") -> NA | ... AM36: =IFERROR(AM29/AH29-1,"NA") -> 0.47099448 | AN36: 0.3 | AO36: =IFERROR(AO29/AJ29-1,"NA") -> 0.14531603 | AP36: =IFERROR(AP29/AK29-1,"NA") -> 0.033739456 | AQ36: =IFERROR(AQ29/AL29-1,"NA") -> 0.22601279 | AR36: =IFERROR(AR29/AM29-1,"NA") -> 0.12676056 | AS36: =IFERROR(AS29/AN29-1,"NA") -> 0.1627907 | AT36: =IFERROR(AT29/AO29-1,"NA") -> 0.13402316 | AU36: =IFERROR(AU29/AP29-1,"NA") -> 0.31459655 | AV36: =IFERROR(AV29/AQ29-1,"NA") -> 0.19565217 | ... BI36: =IFERROR(BI29/BD29-1,"NA") -> -0.017765733 | BJ36: 0.01 | BK36: 0.01 | BL36: 0.01 | BM36: 0.01 | BN36: =IFERROR(BN29/BI29-1,"NA") -> 0.01 | BO36: 0.02 | BP36: 0.02 | BQ36: 0.02 | BR36: 0.02 | BS36: =IFERROR(BS29/BN29-1,"NA") -> 0.02
A37: Total Volume | B37: NA | C37: NA | D37: NA | E37: NA | F37: NA | G37: =IFERROR(G30/B30-1,"NA") -> 0.29761136 | H37: =IFERROR(H30/C30-1,"NA") -> 0.3787308 | I37: =IFERROR(I30/D30-1,"NA") -> 0.46294682 | J37: =IFERROR(J30/E30-1,"NA") -> 0.37779415 | K37: =IFERROR(K30/F30-1,"NA") -> 0.38119622 | L37: =IFERROR(L30/G30-1,"NA") -> 0.33134328 | M37: =IFERROR(M30/H30-1,"NA") -> 0.22572509 | N37: =IFERROR(N30/I30-1,"NA") -> 0.14024632 | ... BS37: =IFERROR(BS30/BN30-1,"NA") -> 0.10545356
A39: Revenue Per Test
A40: Testing | B40: =IFERROR(B8/(B26+B27)*1000000,"NA") -> 2413.1698 | C40: =IFERROR(C8/(C26+C27)*1000000,"NA") -> 2514.3437 | D40: =IFERROR(D8/(D26+D27)*1000000,"NA") -> 2859.0526 | E40: =IFERROR(E8/(E26+E27)*1000000,"NA") -> 2996.561 | F40: =IFERROR(F8/(F26+F27)*1000000,"NA") -> 2716.023 | G40: =IFERROR(G8/(G26+G27)*1000000,"NA") -> 2790.5473 | H40: =IFERROR(H8/(H26+H27)*1000000,"NA") -> 2502.7322 | I40: =IFERROR(I8/(I26+I27)*1000000,"NA") -> 2450.3377 | ... AJ40: =IFERROR(AJ8/(AJ26+AJ27)*1000000,"NA") -> 2726.3977 | AK40: =IFERROR(AK8/(AK28)*1000000,"NA") -> 2688.6125 | AL40: =IFERROR(AL8/(AL28)*1000000,"NA") -> 2676.1328 | AM40: =IFERROR(AM8/(AM28)*1000000,"NA") -> 2701.2525 | AN40: =IFERROR(AN8/(AN28)*1000000,"NA") -> 2628.383 | AO40: =IFERROR(AO8/(AO26+AO27)*1000000,"NA") -> 2671.2564 | AP40: =IFERROR(AP8/(AP28)*1000000,"NA") -> 2660.7729 | AQ40: =IFERROR(AQ8/(AQ28)*1000000,"NA") -> 2641.9218 | AR40: =IFERROR(AR8/(AR28)*1000000,"NA") -> 2693.6264 | AS40: =IFERROR(AS8/(AS28)*1000000,"NA") -> 2734.0959 | AT40: =IFERROR(AT8/(AT26+AT27)*1000000,"NA") -> 2684.8411 | AU40: =IFERROR(AU8/(AU28)*1000000,"NA") -> 2796.508 | AV40: =IFERROR(AV8/(AV28)*1000000,"NA") -> 2813.2076 | AW40: =IFERROR(AW8/(AW28)*1000000,"NA") -> 2761.9048 | AX40: =IFERROR(AX8/(AX28)*1000000,"NA") -> 2893.6163 | AY40: =IFERROR(AY8/(AY26+AY27)*1000000,"NA") -> 2818.0053 | AZ40: =IFERROR(AZ8/(AZ28)*1000000,"NA") -> 2920.1591 | BA40: =IFERROR(BA8/(BA28)*1000000,"NA") -> 2971.3889 | BB40: =IFERROR(BB8/(BB28)*1000000,"NA") -> 2977.1689 | BC40: =IFERROR(BC8/(BC28)*1000000,"NA") -> 2867.8242 | BD40: =IFERROR(BD8/(BD26+BD27)*1000000,"NA") -> 2968.197 | BE40: =IFERROR(BE8/(BE28)*1000000,"NA") -> 2816.5092 | BF40: =IFERROR(BF8/(BF28)*1000000,"NA") -> 2880.7757 | BG40: =IFERROR(BG8/(BG28)*1000000,"NA") -> 2923.4783 | BH40: =IFERROR(BH8/(BH28)*1000000,"NA") -> 2988.4708 | BI40: =IFERROR(BI8/(BI26+BI27)*1000000,"NA") -> 2906.1883 | BJ40: 2900 | BK40: =BJ40 -> 2900 | BL40: =BK40 -> 2900 | BM40: =BL40 -> 2900 | BN40: =IFERROR(BN8/(BN26+BN27)*1000000,"NA") -> 2900 | BO40: =BM40 -> 2900 | BP40: =BO40 -> 2900 | BQ40: =BP40 -> 2900 | BR40: =BQ40 -> 2900 | BS40: =IFERROR(BS8/(BS26+BS27)*1000000,"NA") -> 2900
A41: Products | B41: =IFERROR(B9/B29*1000000,"NA") -> NA | C41: =IFERROR(C9/C29*1000000,"NA") -> NA | D41: =IFERROR(D9/D29*1000000,"NA") -> NA | E41: =IFERROR(E9/E29*1000000,"NA") -> NA | F41: =IFERROR(F9/F29*1000000,"NA") -> NA | G41: =IFERROR(G9/G29*1000000,"NA") -> NA | H41: =IFERROR(H9/H29*1000000,"NA") -> NA | I41: =IFERROR(I9/I29*1000000,"NA") -> NA | ... BI41: =IFERROR(BI9/BI29*1000000,"NA") -> 1464.0302 | BJ41: 1450 | BK41: =BJ41 -> 1450 | BL41: =BK41 -> 1450 | BM41: =BL41 -> 1450 | BN41: =IFERROR(BN9/BN29*1000000,"NA") -> 1450 | BO41: =BM41 -> 1450 | BP41: =BO41 -> 1450 | BQ41: =BP41 -> 1450 | BR41: =BQ41 -> 1450 | BS41: =IFERROR(BS9/BS29*1000000,"NA") -> 1450
A42: Average Revenue Per Test | B42: =IFERROR((B8+B9)/B30*1000000,"NA") -> 2413.1698 | C42: =IFERROR((C8+C9)/C30*1000000,"NA") -> 2514.3437 | D42: =IFERROR((D8+D9)/D30*1000000,"NA") -> 2859.0526 | E42: =IFERROR((E8+E9)/E30*1000000,"NA") -> 2996.561 | F42: =IFERROR((F8+F9)/F30*1000000,"NA") -> 2716.023 | G42: =IFERROR((G8+G9)/G30*1000000,"NA") -> 2790.5473 | H42: =IFERROR((H8+H9)/H30*1000000,"NA") -> 2502.7322 | I42: =IFERROR((I8+I9)/I30*1000000,"NA") -> 2450.3377 | ... BS42: =IFERROR((BS8+BS9)/BS30*1000000,"NA") -> 2835.1459
A44: Year/Year Changes
A45: Testing | B45: NA | C45: NA | D45: NA | E45: NA | F45: NA | G45: =IFERROR(G40/B40-1,"NA") -> 0.15638248 | H45: =IFERROR(H40/C40-1,"NA") -> -0.0046180752 | I45: =IFERROR(I40/D40-1,"NA") -> -0.14295466 | J45: =IFERROR(J40/E40-1,"NA") -> -0.16455012 | K45: =IFERROR(K40/F40-1,"NA") -> -0.061516848 | L45: =IFERROR(L40/G40-1,"NA") -> -0.09273573 | M45: =IFERROR(M40/H40-1,"NA") -> 0.0054169587 | N45: =IFERROR(N40/I40-1,"NA") -> 0.32265065 | ... BS45: =IFERROR(BS40/BN40-1,"NA") -> -1.110223e-16
A46: Products | B46: NA | C46: NA | D46: NA | E46: NA | F46: NA | G46: =IFERROR(G41/B41-1,"NA") -> NA | H46: =IFERROR(H41/C41-1,"NA") -> NA | I46: =IFERROR(I41/D41-1,"NA") -> NA | J46: =IFERROR(J41/E41-1,"NA") -> NA | K46: =IFERROR(K41/F41-1,"NA") -> NA | L46: =IFERROR(L41/G41-1,"NA") -> NA | M46: =IFERROR(M41/H41-1,"NA") -> NA | N46: =IFERROR(N41/I41-1,"NA") -> NA | ... BS46: =IFERROR(BS41/BN41-1,"NA") -> 2.220446e-16
A47: Average Revenue Per Test | B47: NA | C47: NA | D47: NA | E47: NA | F47: NA | G47: =IFERROR(G42/B42-1,"NA") -> 0.15638248 | H47: =IFERROR(H42/C42-1,"NA") -> -0.0046180752 | I47: =IFERROR(I42/D42-1,"NA") -> -0.14295466 | J47: =IFERROR(J42/E42-1,"NA") -> -0.16455012 | K47: =IFERROR(K42/F42-1,"NA") -> -0.061516848 | L47: =IFERROR(L42/G42-1,"NA") -> -0.09273573 | M47: =IFERROR(M42/H42-1,"NA") -> 0.0054169587 | N47: =IFERROR(N42/I42-1,"NA") -> 0.32265065 | ... BS47: =IFERROR(BS42/BN42-1,"NA") -> 0.0019201063
A49: Organic Growth Calculations
A50: Total Reported Revenue | B50: NA | C50: NA | D50: NA | E50: NA | F50: NA | G50: =G17 -> 0.50053505 | H50: =H17 -> 0.37236372 | I50: =I17 -> 0.25381175 | J50: =J17 -> 0.15107796 | K50: =K17 -> 0.29622938 | L50: =L17 -> 0.20788019 | M50: =M17 -> 0.2323648 | N50: =N17 -> 0.50814755 | ... BS50: =BS17 -> 0.10757615
A51: Currency Impact | B51: NA | C51: NA | D51: NA | E51: NA | F51: NA | G51: 0 | H51: 0 | I51: 0 | J51: 0 | K51: =SUMPRODUCT(G51:J51,G11:J11)/K11 -> 0 | L51: 0 | M51: 0 | N51: 0 | O51: 0 | P51: =SUMPRODUCT(L51:O51,L11:O11)/P11 -> 0 | Q51: 0 | R51: 0 | S51: 0 | T51: 0 | U51: =SUMPRODUCT(Q51:T51,Q11:T11)/U11 -> 0 | V51: 0 | W51: 0 | X51: 0 | Y51: 0 | Z51: =SUMPRODUCT(V51:Y51,V11:Y11)/Z11 -> 0 | AA51: 0 | AB51: 0 | AC51: 0 | AD51: 0 | AE51: =SUMPRODUCT(AA51:AD51,AA11:AD11)/AE11 -> 0 | AF51: 0 | AG51: 0 | AH51: 0 | AI51: 0 | AJ51: =SUMPRODUCT(AF51:AI51,AF11:AI11)/AJ11 -> 0 | AK51: 0 | AL51: 0 | AM51: 0 | AN51: 0 | AO51: =SUMPRODUCT(AK51:AN51,AK11:AN11)/AO11 -> 0 | AP51: 0 | AQ51: 0 | AR51: 0 | AS51: 0 | AT51: =SUMPRODUCT(AP51:AS51,AP11:AS11)/AT11 -> 0 | AU51: 0 | AV51: 0 | AW51: 0 | AX51: 0 | AY51: =SUMPRODUCT(AU51:AX51,AU11:AX11)/AY11 -> 0 | AZ51: 0 | BA51: 0 | BB51: 0 | BC51: 0 | BD51: =SUMPRODUCT(AZ51:BC51,AZ11:BC11)/BD11 -> 0 | BE51: 0 | BF51: 0 | BG51: 0 | BH51: 0 | BI51: =SUMPRODUCT(BE51:BH51,BE11:BH11)/BI11 -> 0 | BJ51: 0 | BK51: 0 | BL51: 0 | BM51: 0 | BN51: =SUMPRODUCT(BJ51:BM51,BJ11:BM11)/BN11 -> 0 | BO51: 0 | BP51: 0 | BQ51: 0 | BR51: 0 | BS51: =SUMPRODUCT(BO51:BR51,BO11:BR11)/BS11 -> 0
A52: Constant Currency Revenue | B52: NA | C52: NA | D52: NA | E52: NA | F52: NA | G52: =G50-G51 -> 0.50053505 | H52: =H50-H51 -> 0.37236372 | I52: =I50-I51 -> 0.25381175 | J52: =J50-J51 -> 0.15107796 | K52: =K50-K51 -> 0.29622938 | L52: =L50-L51 -> 0.20788019 | M52: =M50-M51 -> 0.2323648 | N52: =N50-N51 -> 0.50814755 | ... BS52: =BS50-BS51 -> 0.10757615
A53: Acquisition Impact | B53: NA | C53: NA | D53: NA | E53: NA | F53: NA | G53: 0 | H53: 0 | I53: 0 | J53: 0 | K53: =SUMPRODUCT(G53:J53,G11:J11)/K11 -> 0 | L53: 0 | M53: 0 | N53: 0 | O53: 0 | P53: =SUMPRODUCT(L53:O53,L11:O11)/P11 -> 0 | Q53: 0 | R53: 0 | S53: 0 | T53: 0 | U53: =SUMPRODUCT(Q53:T53,Q11:T11)/U11 -> 0 | V53: 0 | W53: 0 | X53: 0 | Y53: 0 | Z53: =SUMPRODUCT(V53:Y53,V11:Y11)/Z11 -> 0 | AA53: 0 | AB53: 0 | AC53: 0 | AD53: 0 | AE53: =SUMPRODUCT(AA53:AD53,AA11:AD11)/AE11 -> 0 | AF53: 0 | AG53: 0 | AH53: 0 | AI53: 0 | AJ53: =SUMPRODUCT(AF53:AI53,AF11:AI11)/AJ11 -> 0 | AK53: =3.8/AF11 -> 0.12210012 | AL53: =18.5/AG11 -> 0.89354714 | AM53: =(20.3+4.7)/AH11 -> 0.80331609 | AN53: =(20.2+7+4)/AI11 -> 0.90340514 | AO53: =SUMPRODUCT(AK53:AN53,AF11:AI11)/AJ11 -> 0.66818178 | AP53: =(20+7.6)/AK11 -> 0.75198213 | AQ53: =8.4/AL11 -> 0.15243626 | AR53: =2.6/AM11 -> 0.043067749 | AS53: 0 | AT53: =SUMPRODUCT(AP53:AS53,AK11:AN11)/AO11 -> 0.175843 | AU53: 0 | AV53: 0 | AW53: 0 | AX53: 0 | AY53: =SUMPRODUCT(AU53:AX53,AP11:AS11)/AT11 -> 0 | AZ53: 0 | BA53: 0 | BB53: 0 | BC53: 0 | BD53: =SUMPRODUCT(AZ53:BC53,AU11:AX11)/AY11 -> 0 | BE53: 0 | BF53: 0 | BG53: 0 | BH53: 0 | BI53: =SUMPRODUCT(BE53:BH53,AZ11:BC11)/BD11 -> 0 | BJ53: 0 | BK53: 0 | BL53: 0 | BM53: 0 | BN53: =SUMPRODUCT(BJ53:BM53,BE11:BH11)/BI11 -> 0 | BO53: 0 | BP53: 0 | BQ53: 0 | BR53: 0 | BS53: =SUMPRODUCT(BO53:BR53,BJ11:BM11)/BN11 -> 0
A54: Constant Currency, Organic Revenue | B54: NA | C54: NA | D54: NA | E54: NA | F54: NA | G54: =G52-G53 -> 0.50053505 | H54: =H52-H53 -> 0.37236372 | I54: =I52-I53 -> 0.25381175 | J54: =J52-J53 -> 0.15107796 | K54: =K52-K53 -> 0.29622938 | L54: =L52-L53 -> 0.20788019 | M54: =M52-M53 -> 0.2323648 | N54: =N52-N53 -> 0.50814755 | ... BS54: =BS52-BS53 -> 0.10757615
A55: Source: Company reports and Needham & Company estimates

Sheet Income Statement
A1: Veracyte Inc. | BS1: Needham & Company, LLC
A2: Quarterly Income Statement | BS2: Michael Matson ● (617) 457-0949
A3: ($ In Millions Except Per Share Data) | AH3: NG EPS | AI3: -0.11
B5: ='Revenue Model'!B5 -> 41699 | C5: ='Revenue Model'!C5 -> 41791 | D5: ='Revenue Model'!D5 -> 41883 | E5: ='Revenue Model'!E5 -> 41974 | F5: ='Revenue Model'!F5 -> 2014 | G5: ='Revenue Model'!G5 -> 42064 | H5: ='Revenue Model'!H5 -> 42156 | I5: ='Revenue Model'!I5 -> 42248 | ... BS5: ='Revenue Model'!BS5 -> 2027E
B6: ='Revenue Model'!B6 -> Q114A | C6: ='Revenue Model'!C6 -> Q214A | D6: ='Revenue Model'!D6 -> Q314A | E6: ='Revenue Model'!E6 -> Q414A | F6: ='Revenue Model'!F6 -> Annual | G6: ='Revenue Model'!G6 -> Q115A | H6: ='Revenue Model'!H6 -> Q215A | I6: ='Revenue Model'!I6 -> Q315A | ... BS6: ='Revenue Model'!BS6 -> Annual
A7: Testing Revenue | B7: ='Revenue Model'!B8 -> 7.476 | C7: ='Revenue Model'!C8 -> 8.677 | D7: ='Revenue Model'!D8 -> 9.838 | E7: ='Revenue Model'!E8 -> 12.199 | F7: =SUM(B7:E7) -> 38.19 | G7: ='Revenue Model'!G8 -> 11.218 | H7: ='Revenue Model'!H8 -> 11.908 | I7: ='Revenue Model'!I8 -> 12.335 | J7: ='Revenue Model'!J8 -> 14.042 | K7: =SUM(G7:J7) -> 49.503 | L7: ='Revenue Model'!L8 -> 13.55 | M7: ='Revenue Model'!M8 -> 14.675 | N7: ='Revenue Model'!N8 -> 18.603 | O7: ='Revenue Model'!O8 -> 18.257 | P7: =SUM(L7:O7) -> 65.085 | Q7: ='Revenue Model'!Q8 -> 16.432 | R7: ='Revenue Model'!R8 -> 18.406 | S7: ='Revenue Model'!S8 -> 17.519 | T7: ='Revenue Model'!T8 -> 19.596 | U7: =SUM(Q7:T7) -> 71.953 | V7: ='Revenue Model'!V8 -> 20.041 | W7: ='Revenue Model'!W8 -> 22.301 | X7: ='Revenue Model'!X8 -> 23.216 | Y7: ='Revenue Model'!Y8 -> 25.5 | Z7: =SUM(V7:Y7) -> 91.058 | AA7: ='Revenue Model'!AA8 -> 25.389 | AB7: ='Revenue Model'!AB8 -> 26.686 | AC7: ='Revenue Model'!AC8 -> 26.723 | AD7: ='Revenue Model'!AD8 -> 28.557 | AE7: =SUM(AA7:AD7) -> 107.355 | AF7: ='Revenue Model'!AF8 -> 26.991 | AG7: ='Revenue Model'!AG8 -> 15.212 | AH7: ='Revenue Model'!AH8 -> 28.27 | AI7: ='Revenue Model'!AI8 -> 31.497 | AJ7: =SUM(AF7:AI7) -> 101.97 | AK7: ='Revenue Model'!AK8 -> 33.078 | AL7: ='Revenue Model'!AL8 -> 50.793 | AM7: ='Revenue Model'!AM8 -> 50.897 | AN7: ='Revenue Model'!AN8 -> 53.414 | AO7: =SUM(AK7:AN7) -> 188.182 | AP7: ='Revenue Model'!AP8 -> 55.98 | AQ7: ='Revenue Model'!AQ8 -> 59.718 | AR7: ='Revenue Model'!AR8 -> 64.577 | AS7: ='Revenue Model'!AS8 -> 70.269 | AT7: =SUM(AP7:AS7) -> 250.544 | AU7: ='Revenue Model'!AU8 -> 72.396 | AV7: ='Revenue Model'!AV8 -> 81.749 | AW7: ='Revenue Model'!AW8 -> 82.012 | AX7: ='Revenue Model'!AX8 -> 90.385 | AY7: =SUM(AU7:AX7) -> 326.542 | AZ7: ='Revenue Model'!AZ8 -> 90.303 | BA7: ='Revenue Model'!BA8 -> 106.97 | BB7: ='Revenue Model'!BB8 -> 109.536 | BC7: ='Revenue Model'!BC8 -> 112.152 | BD7: =SUM(AZ7:BC7) -> 418.961 | BE7: ='Revenue Model'!BE8 -> 107.309 | BF7: ='Revenue Model'!BF8 -> 122.263 | BG7: ='Revenue Model'!BG8 -> 127.756 | BH7: ='Revenue Model'!BH8 -> 135.826 | BI7: =SUM(BE7:BH7) -> 493.154 | BJ7: ='Revenue Model'!BJ8 -> 126.5009 | BK7: ='Revenue Model'!BK8 -> 143.52642 | BL7: ='Revenue Model'!BL8 -> 142.9207 | BM7: ='Revenue Model'!BM8 -> 149.698 | BN7: =SUM(BJ7:BM7) -> 562.64602 | BO7: ='Revenue Model'!BO8 -> 140.28431 | BP7: ='Revenue Model'!BP8 -> 159.27291 | BQ7: ='Revenue Model'!BQ8 -> 158.77311 | BR7: ='Revenue Model'!BR8 -> 166.09808 | BS7: =SUM(BO7:BR7) -> 624.42842
A8: Product Revenue | B8: ='Revenue Model'!B9 -> 0 | C8: ='Revenue Model'!C9 -> 0 | D8: ='Revenue Model'!D9 -> 0 | E8: ='Revenue Model'!E9 -> 0 | F8: =SUM(B8:E8) -> 0 | G8: ='Revenue Model'!G9 -> 0 | H8: ='Revenue Model'!H9 -> 0 | I8: ='Revenue Model'!I9 -> 0 | J8: ='Revenue Model'!J9 -> 0 | K8: =SUM(G8:J8) -> 0 | L8: ='Revenue Model'!L9 -> 0 | M8: ='Revenue Model'!M9 -> 0 | N8: ='Revenue Model'!N9 -> 0 | O8: ='Revenue Model'!O9 -> 0 | P8: =SUM(L8:O8) -> 0 | Q8: ='Revenue Model'!Q9 -> 0 | R8: ='Revenue Model'!R9 -> 0 | S8: ='Revenue Model'!S9 -> 0 | T8: ='Revenue Model'!T9 -> 0 | U8: =SUM(Q8:T8) -> 0 | V8: ='Revenue Model'!V9 -> 0 | W8: ='Revenue Model'!W9 -> 0 | X8: ='Revenue Model'!X9 -> 0 | Y8: ='Revenue Model'!Y9 -> 0 | Z8: =SUM(V8:Y8) -> 0 | AA8: ='Revenue Model'!AA9 -> 0 | AB8: ='Revenue Model'!AB9 -> 0 | AC8: ='Revenue Model'!AC9 -> 0 | AD8: ='Revenue Model'!AD9 -> 0.923 | AE8: =SUM(AA8:AD8) -> 0.923 | AF8: ='Revenue Model'!AF9 -> 3.409 | AG8: ='Revenue Model'!AG9 -> 1.713 | AH8: ='Revenue Model'!AH9 -> 2.027 | AI8: ='Revenue Model'!AI9 -> 2.696 | AJ8: =SUM(AF8:AI8) -> 9.845 | AK8: ='Revenue Model'!AK9 -> 3.059 | AL8: ='Revenue Model'!AL9 -> 2.688 | AM8: ='Revenue Model'!AM9 -> 2.959 | AN8: ='Revenue Model'!AN9 -> 2.758 | AO8: =SUM(AK8:AN8) -> 11.464 | AP8: ='Revenue Model'!AP9 -> 2.979 | AQ8: ='Revenue Model'!AQ9 -> 3.108 | AR8: ='Revenue Model'!AR9 -> 3.314 | AS8: ='Revenue Model'!AS9 -> 3.231 | AT8: =SUM(AP8:AS8) -> 12.632 | AU8: ='Revenue Model'!AU9 -> 3.892 | AV8: ='Revenue Model'!AV9 -> 4.011 | AW8: ='Revenue Model'!AW9 -> 4.02 | AX8: ='Revenue Model'!AX9 -> 3.665 | AY8: =SUM(AU8:AX8) -> 15.588 | AZ8: ='Revenue Model'!AZ9 -> 3.537 | BA8: ='Revenue Model'!BA9 -> 3.906 | BB8: ='Revenue Model'!BB9 -> 3.188 | BC8: ='Revenue Model'!BC9 -> 3.019 | BD8: =SUM(AZ8:BC8) -> 13.65 | BE8: ='Revenue Model'!BE9 -> 3.58 | BF8: ='Revenue Model'!BF9 -> 3.598 | BG8: ='Revenue Model'!BG9 -> 3.301 | BH8: ='Revenue Model'!BH9 -> 3.848 | BI8: =SUM(BE8:BH8) -> 14.327 | BJ8: ='Revenue Model'!BJ9 -> 3.763765 | BK8: ='Revenue Model'!BK9 -> 3.6978625 | BL8: ='Revenue Model'!BL9 -> 3.204326 | BM8: ='Revenue Model'!BM9 -> 3.6656435 | BN8: =SUM(BJ8:BM8) -> 14.331597 | BO8: ='Revenue Model'!BO9 -> 3.8390403 | BP8: ='Revenue Model'!BP9 -> 3.7718198 | BQ8: ='Revenue Model'!BQ9 -> 3.2684125 | BR8: ='Revenue Model'!BR9 -> 3.7389564 | BS8: =SUM(BO8:BR8) -> 14.618229
A9: Biopharma and Other Revenue | B9: ='Revenue Model'!B10 -> 0 | C9: ='Revenue Model'!C10 -> 0 | D9: ='Revenue Model'!D10 -> 0 | E9: ='Revenue Model'!E10 -> 0 | F9: =SUM(B9:E9) -> 0 | G9: ='Revenue Model'!G10 -> 0 | H9: ='Revenue Model'!H10 -> 0 | I9: ='Revenue Model'!I10 -> 0 | J9: ='Revenue Model'!J10 -> 0 | K9: =SUM(G9:J9) -> 0 | L9: ='Revenue Model'!L10 -> 0 | M9: ='Revenue Model'!M10 -> 0 | N9: ='Revenue Model'!N10 -> 0 | O9: ='Revenue Model'!O10 -> 0 | P9: =SUM(L9:O9) -> 0 | Q9: ='Revenue Model'!Q10 -> 0 | R9: ='Revenue Model'!R10 -> 0 | S9: ='Revenue Model'!S10 -> 0 | T9: ='Revenue Model'!T10 -> 0 | U9: =SUM(Q9:T9) -> 0 | V9: ='Revenue Model'!V10 -> 0 | W9: ='Revenue Model'!W10 -> 0.45 | X9: ='Revenue Model'!X10 -> 0.25 | Y9: ='Revenue Model'!Y10 -> 0.25 | Z9: =SUM(V9:Y9) -> 0.95 | AA9: ='Revenue Model'!AA10 -> 4.14 | AB9: ='Revenue Model'!AB10 -> 3.45 | AC9: ='Revenue Model'!AC10 -> 4.25 | AD9: ='Revenue Model'!AD10 -> 0.25 | AE9: =SUM(AA9:AD9) -> 12.09 | AF9: ='Revenue Model'!AF10 -> 0.722 | AG9: ='Revenue Model'!AG10 -> 3.779 | AH9: ='Revenue Model'!AH10 -> 0.824 | AI9: ='Revenue Model'!AI10 -> 0.343 | AJ9: =SUM(AF9:AI9) -> 5.668 | AK9: ='Revenue Model'!AK10 -> 0.566 | AL9: ='Revenue Model'!AL10 -> 1.624 | AM9: ='Revenue Model'!AM10 -> 6.514 | AN9: ='Revenue Model'!AN10 -> 11.164 | AO9: =SUM(AK9:AN9) -> 19.868 | AP9: ='Revenue Model'!AP10 -> 8.824 | AQ9: ='Revenue Model'!AQ10 -> 10.038 | AR9: ='Revenue Model'!AR10 -> 7.701 | AS9: ='Revenue Model'!AS10 -> 6.797 | AT9: =SUM(AP9:AS9) -> 33.36 | AU9: ='Revenue Model'!AU10 -> 6.134 | AV9: ='Revenue Model'!AV10 -> 4.562 | AW9: ='Revenue Model'!AW10 -> 4.076 | AX9: ='Revenue Model'!AX10 -> 4.149 | AY9: =SUM(AU9:AX9) -> 18.921 | AZ9: ='Revenue Model'!AZ10 -> 3.004 | BA9: ='Revenue Model'!BA10 -> 3.552 | BB9: ='Revenue Model'!BB10 -> 3.136 | BC9: ='Revenue Model'!BC10 -> 3.461 | BD9: =SUM(AZ9:BC9) -> 13.153 | BE9: ='Revenue Model'!BE10 -> 3.584 | BF9: ='Revenue Model'!BF10 -> 4.303 | BG9: ='Revenue Model'!BG10 -> 0.815 | BH9: ='Revenue Model'!BH10 -> 0.962 | BI9: =SUM(BE9:BH9) -> 9.664 | BJ9: ='Revenue Model'!BJ10 -> 0 | BK9: ='Revenue Model'!BK10 -> 0 | BL9: ='Revenue Model'!BL10 -> 0 | BM9: ='Revenue Model'!BM10 -> 0 | BN9: =SUM(BJ9:BM9) -> 0 | BO9: ='Revenue Model'!BO10 -> 0 | BP9: ='Revenue Model'!BP10 -> 0 | BQ9: ='Revenue Model'!BQ10 -> 0 | BR9: ='Revenue Model'!BR10 -> 0 | BS9: =SUM(BO9:BR9) -> 0
A10: Total Revenue | B10: =SUM(B7:B9) -> 7.476 | C10: =SUM(C7:C9) -> 8.677 | D10: =SUM(D7:D9) -> 9.838 | E10: =SUM(E7:E9) -> 12.199 | F10: =SUM(B10:E10) -> 38.19 | G10: =SUM(G7:G9) -> 11.218 | H10: =SUM(H7:H9) -> 11.908 | I10: =SUM(I7:I9) -> 12.335 | J10: =SUM(J7:J9) -> 14.042 | K10: =SUM(G10:J10) -> 49.503 | L10: =SUM(L7:L9) -> 13.55 | M10: =SUM(M7:M9) -> 14.675 | N10: =SUM(N7:N9) -> 18.603 | O10: =SUM(O7:O9) -> 18.257 | P10: =SUM(L10:O10) -> 65.085 | Q10: =SUM(Q7:Q9) -> 16.432 | R10: =SUM(R7:R9) -> 18.406 | S10: =SUM(S7:S9) -> 17.519 | T10: =SUM(T7:T9) -> 19.596 | U10: =SUM(Q10:T10) -> 71.953 | V10: =SUM(V7:V9) -> 20.041 | W10: =SUM(W7:W9) -> 22.751 | X10: =SUM(X7:X9) -> 23.466 | Y10: =SUM(Y7:Y9) -> 25.75 | Z10: =SUM(V10:Y10) -> 92.008 | AA10: =SUM(AA7:AA9) -> 29.529 | AB10: =SUM(AB7:AB9) -> 30.136 | AC10: =SUM(AC7:AC9) -> 30.973 | AD10: =SUM(AD7:AD9) -> 29.73 | AE10: =SUM(AA10:AD10) -> 120.368 | AF10: =SUM(AF7:AF9) -> 31.122 | AG10: =SUM(AG7:AG9) -> 20.704 | AH10: =SUM(AH7:AH9) -> 31.121 | AI10: =SUM(AI7:AI9) -> 34.536 | AJ10: =SUM(AF10:AI10) -> 117.483 | AK10: =SUM(AK7:AK9) -> 36.703 | AL10: =SUM(AL7:AL9) -> 55.105 | AM10: =SUM(AM7:AM9) -> 60.37 | AN10: =SUM(AN7:AN9) -> 67.336 | AO10: =SUM(AK10:AN10) -> 219.514 | AP10: =SUM(AP7:AP9) -> 67.783 | AQ10: =SUM(AQ7:AQ9) -> 72.864 | AR10: =SUM(AR7:AR9) -> 75.592 | AS10: =SUM(AS7:AS9) -> 80.297 | AT10: =SUM(AP10:AS10) -> 296.536 | AU10: =SUM(AU7:AU9) -> 82.422 | AV10: =SUM(AV7:AV9) -> 90.322 | AW10: =SUM(AW7:AW9) -> 90.108 | AX10: =SUM(AX7:AX9) -> 98.199 | AY10: =SUM(AU10:AX10) -> 361.051 | AZ10: =SUM(AZ7:AZ9) -> 96.844 | BA10: =SUM(BA7:BA9) -> 114.428 | BB10: =SUM(BB7:BB9) -> 115.86 | BC10: =SUM(BC7:BC9) -> 118.632 | BD10: =SUM(AZ10:BC10) -> 445.764 | BE10: =SUM(BE7:BE9) -> 114.473 | BF10: =SUM(BF7:BF9) -> 130.164 | BG10: =SUM(BG7:BG9) -> 131.872 | BH10: =SUM(BH7:BH9) -> 140.636 | BI10: =SUM(BE10:BH10) -> 517.145 | BJ10: =SUM(BJ7:BJ9) -> 130.26467 | BK10: =SUM(BK7:BK9) -> 147.22429 | BL10: =SUM(BL7:BL9) -> 146.12503 | BM10: =SUM(BM7:BM9) -> 153.36364 | BN10: =SUM(BJ10:BM10) -> 576.97762 | BO10: =SUM(BO7:BO9) -> 144.12335 | BP10: =SUM(BP7:BP9) -> 163.04473 | BQ10: =SUM(BQ7:BQ9) -> 162.04153 | BR10: =SUM(BR7:BR9) -> 169.83704 | BS10: =SUM(BO10:BR10) -> 639.04665
A11: Cost of Testing Revenue | B11: 3.607 | C11: 3.966 | D11: 4.168 | E11: 4.865 | F11: =+B11+C11+D11+E11 -> 16.606 | G11: 4.566 | H11: 5.139 | I11: 5.618 | J11: 6.175 | K11: =+G11+H11+I11+J11 -> 21.498 | L11: 6.279 | M11: 6.301 | N11: 6.367 | O11: 6.515 | P11: =+L11+M11+N11+O11 -> 25.462 | Q11: 6.297 | R11: 6.96 | S11: 7.169 | T11: 7.769 | U11: =+Q11+R11+S11+T11 -> 28.195 | V11: 7.867 | W11: 8.246 | X11: 8.261 | Y11: 8.704 | Z11: =+V11+W11+X11+Y11 -> 33.078 | AA11: 8.513 | AB11: 8.777 | AC11: 9.114 | AD11: =9.673 -> 9.673 | AE11: =+AA11+AB11+AC11+AD11 -> 36.077 | AF11: =10.568-1.088 -> 9.48 | AG11: 6.471 | AH11: 9.118 | AI11: 9.756 | AJ11: =+AF11+AG11+AH11+AI11 -> 34.825 | AK11: 10.832 | AL11: 15.589 | AM11: 16.073 | AN11: 16.366 | AO11: =+AK11+AL11+AM11+AN11 -> 58.86 | AP11: 17.47 | AQ11: 18.533 | AR11: 19.749 | AS11: 19.394 | AT11: =+AP11+AQ11+AR11+AS11 -> 75.146 | AY11: =+AU11+AV11+AW11+AX11 -> 0 | BD11: =+AZ11+BA11+BB11+BC11 -> 0 | BI11: =+BE11+BF11+BG11+BH11 -> 0 | BN11: =+BJ11+BK11+BL11+BM11 -> 0 | BS11: =+BO11+BP11+BQ11+BR11 -> 0
A12: Cost of Product Revenue | B12: 0 | C12: 0 | D12: 0 | E12: 0 | F12: =+B12+C12+D12+E12 -> 0 | G12: 0 | H12: 0 | I12: 0 | J12: 0 | K12: =+G12+H12+I12+J12 -> 0 | L12: 0 | M12: 0 | N12: 0 | O12: 0 | P12: =+L12+M12+N12+O12 -> 0 | Q12: 0 | R12: 0 | S12: 0 | T12: 0 | U12: =+Q12+R12+S12+T12 -> 0 | V12: 0 | W12: 0 | X12: 0 | Y12: 0 | Z12: =+V12+W12+X12+Y12 -> 0 | AA12: 0 | AB12: 0 | AC12: 0 | AD12: 0.466 | AE12: =+AA12+AB12+AC12+AD12 -> 0.466 | AF12: 1.559 | AG12: 0.932 | AH12: 1.048 | AI12: 1.382 | AJ12: =+AF12+AG12+AH12+AI12 -> 4.921 | AK12: 1.49 | AL12: 1.323 | AM12: 1.491 | AN12: 1.583 | AO12: =+AK12+AL12+AM12+AN12 -> 5.887 | AP12: 1.575 | AQ12: 1.646 | AR12: 1.978 | AS12: 2.618 | AT12: =+AP12+AQ12+AR12+AS12 -> 7.817 | AY12: =+AU12+AV12+AW12+AX12 -> 0 | BD12: =+AZ12+BA12+BB12+BC12 -> 0 | BI12: =+BE12+BF12+BG12+BH12 -> 0 | BN12: =+BJ12+BK12+BL12+BM12 -> 0 | BS12: =+BO12+BP12+BQ12+BR12 -> 0
A13: Cost of Biopharma Revenue | B13: 0 | C13: 0 | D13: 0 | E13: 0 | F13: =SUM(B13:E13) -> 0 | G13: 0 | H13: 0 | I13: 0 | J13: 0 | K13: =SUM(G13:J13) -> 0 | L13: 0 | M13: 0 | N13: 0 | O13: 0 | P13: =SUM(L13:O13) -> 0 | Q13: 0 | R13: 0 | S13: 0 | T13: 0 | U13: =SUM(Q13:T13) -> 0 | V13: 0 | W13: 0 | X13: 0 | Y13: 0 | Z13: =SUM(V13:Y13) -> 0 | AA13: 0 | AB13: 0 | AC13: 0 | AD13: 0 | AE13: =+AA13+AB13+AC13+AD13 -> 0 | AF13: 0.116 | AG13: 0.252 | AH13: 0.204 | AI13: 0.049 | AJ13: =+AF13+AG13+AH13+AI13 -> 0.621 | AK13: 0.081 | AL13: 0.56 | AM13: 4.079 | AN13: 4.933 | AO13: =+AK13+AL13+AM13+AN13 -> 9.653 | AP13: 4.482 | AQ13: 4.735 | AR13: 4.149 | AS13: 4.755 | AT13: =+AP13+AQ13+AR13+AS13 -> 18.121 | AY13: =+AU13+AV13+AW13+AX13 -> 0 | BD13: =+AZ13+BA13+BB13+BC13 -> 0 | BI13: =+BE13+BF13+BG13+BH13 -> 0 | BN13: =+BJ13+BK13+BL13+BM13 -> 0 | BS13: =+BO13+BP13+BQ13+BR13 -> 0
A14: Total Cost of Sales | B14: =SUM(B11:B13) -> 3.607 | C14: =SUM(C11:C13) -> 3.966 | D14: =SUM(D11:D13) -> 4.168 | E14: =SUM(E11:E13) -> 4.865 | F14: =+B14+C14+D14+E14 -> 16.606 | G14: =SUM(G11:G13) -> 4.566 | H14: =SUM(H11:H13) -> 5.139 | I14: =SUM(I11:I13) -> 5.618 | J14: =SUM(J11:J13) -> 6.175 | K14: =+G14+H14+I14+J14 -> 21.498 | L14: =SUM(L11:L13) -> 6.279 | M14: =SUM(M11:M13) -> 6.301 | N14: =SUM(N11:N13) -> 6.367 | O14: =SUM(O11:O13) -> 6.515 | P14: =+L14+M14+N14+O14 -> 25.462 | Q14: =SUM(Q11:Q13) -> 6.297 | R14: =SUM(R11:R13) -> 6.96 | S14: =SUM(S11:S13) -> 7.169 | T14: =SUM(T11:T13) -> 7.769 | U14: =+Q14+R14+S14+T14 -> 28.195 | V14: =SUM(V11:V13) -> 7.867 | W14: =SUM(W11:W13) -> 8.246 | X14: =SUM(X11:X13) -> 8.261 | Y14: =SUM(Y11:Y13) -> 8.704 | Z14: =+V14+W14+X14+Y14 -> 33.078 | AA14: =SUM(AA11:AA13) -> 8.513 | AB14: =SUM(AB11:AB13) -> 8.777 | AC14: =SUM(AC11:AC13) -> 9.114 | AD14: =SUM(AD11:AD13) -> 10.139 | AE14: =+AA14+AB14+AC14+AD14 -> 36.543 | AF14: =SUM(AF11:AF13) -> 11.155 | AG14: =SUM(AG11:AG13) -> 7.655 | AH14: =SUM(AH11:AH13) -> 10.37 | AI14: =SUM(AI11:AI13) -> 11.187 | AJ14: =+AF14+AG14+AH14+AI14 -> 40.367 | AK14: =SUM(AK11:AK13) -> 12.403 | AL14: =SUM(AL11:AL13) -> 17.472 | AM14: =SUM(AM11:AM13) -> 21.643 | AN14: =SUM(AN11:AN13) -> 22.882 | AO14: =+AK14+AL14+AM14+AN14 -> 74.4 | AP14: =SUM(AP11:AP13) -> 23.527 | AQ14: =SUM(AQ11:AQ13) -> 24.914 | AR14: =SUM(AR11:AR13) -> 25.876 | AS14: =SUM(AS11:AS13) -> 26.767 | AT14: =+AP14+AQ14+AR14+AS14 -> 101.084 | AU14: 25.768 | AV14: 29.191 | AW14: 27.108 | AX14: 28.904 | AY14: =+AU14+AV14+AW14+AX14 -> 110.971 | AZ14: 30.908 | BA14: 33.002 | BB14: 33.346 | BC14: 36.426 | BD14: =+AZ14+BA14+BB14+BC14 -> 133.682 | BE14: 31.86 | BF14: =31.865+1.716+3.507 -> 37.088 | BG14: =33.222+1.597+1.106 -> 35.925 | BH14: =32.502+2.34+0.215 -> 35.057 | BI14: =+BE14+BF14+BG14+BH14 -> 139.93 | BJ14: =(1-BJ61)*BJ10 -> 35.822783 | BK14: =(1-BK61)*BK10 -> 40.486679 | BL14: =(1-BL61)*BL10 -> 39.453757 | BM14: =(1-BM61)*BM10 -> 40.641366 | BN14: =+BJ14+BK14+BL14+BM14 -> 156.40458 | BO14: =(1-BO61)*BO10 -> 39.633921 | BP14: =(1-BP61)*BP10 -> 44.837302 | BQ14: =(1-BQ61)*BQ10 -> 43.751212 | BR14: =(1-BR61)*BR10 -> 45.006815 | BS14: =+BO14+BP14+BQ14+BR14 -> 173.22925
A15: Gross Profit | B15: =+B10-B14 -> 3.869 | C15: =+C10-C14 -> 4.711 | D15: =+D10-D14 -> 5.67 | E15: =+E10-E14 -> 7.334 | F15: =+F10-F14 -> 21.584 | G15: =+G10-G14 -> 6.652 | H15: =+H10-H14 -> 6.769 | I15: =+I10-I14 -> 6.717 | ... BS15: =+BS10-BS14 -> 465.8174
A16: Research & Development | B16: 2.126 | C16: 2.243 | D16: 2.233 | E16: 3.202 | F16: =SUM(B16:E16) -> 9.804 | G16: 2.787 | H16: 3.103 | I16: 3.563 | J16: 3.343 | K16: =SUM(G16:J16) -> 12.796 | L16: 3.461 | M16: 4.267 | N16: 4.006 | O16: 3.59 | P16: =SUM(L16:O16) -> 15.324 | Q16: 4.03 | R16: 3.603 | S16: 3.046 | T16: 3.202 | U16: =SUM(Q16:T16) -> 13.881 | V16: 3.675 | W16: 4.601 | X16: 3.419 | Y16: 3.125 | Z16: =SUM(V16:Y16) -> 14.82 | AA16: 3.435 | AB16: 3.33 | AC16: 3.643 | AD16: 4.443 | AE16: =SUM(AA16:AD16) -> 14.851 | AF16: 4.407 | AG16: 4.169 | AH16: 4.042 | AI16: 4.586 | AJ16: =SUM(AF16:AI16) -> 17.204 | AK16: 5.336 | AL16: 6.249 | AM16: 8.006 | AN16: 10.252 | AO16: =SUM(AK16:AN16) -> 29.843 | AP16: 8.524 | AQ16: 9.084 | AR16: 10.522 | AS16: 11.055 | AT16: =SUM(AP16:AS16) -> 39.185 | AU16: 11.513 | AV16: 11.102 | AW16: 12.187 | AX16: 17.178 | AY16: =SUM(AU16:AX16) -> 51.98 | AZ16: 13.504 | BA16: 14.595 | BB16: 16.081 | BC16: 17.394 | BD16: =SUM(AZ16:BC16) -> 61.574 | BE16: 15.654 | BF16: 14.256 | BG16: 14.032 | BH16: 18.954 | BI16: =SUM(BE16:BH16) -> 62.896 | BJ16: =BJ62*BJ$10 -> 17.194936 | BK16: =BK62*BK$10 -> 19.58083 | BL16: =BL62*BL$10 -> 19.288503 | BM16: =BM62*BM$10 -> 18.863728 | BN16: =SUM(BJ16:BM16) -> 74.927997 | BO16: =BO62*BO$10 -> 18.880159 | BP16: =BP62*BP$10 -> 21.521905 | BQ16: =BQ62*BQ$10 -> 21.22744 | BR16: =BR62*BR$10 -> 20.720118 | BS16: =SUM(BO16:BR16) -> 82.349622
A17: Selling & Marketing | B17: 4.336 | C17: 5.101 | D17: 5.533 | E17: 6.962 | F17: =SUM(B17:E17) -> 21.932 | G17: 5.62 | H17: 6.937 | I17: 6.048 | J17: 6.687 | K17: =SUM(G17:J17) -> 25.292 | L17: 7.066 | M17: 8.263 | N17: 7.087 | O17: 5.832 | P17: =SUM(L17:O17) -> 28.248 | Q17: 7.336 | R17: 7.994 | S17: 7.885 | T17: 9.045 | U17: =SUM(Q17:T17) -> 32.26 | V17: 11.543 | W17: 9.623 | X17: 10.081 | Y17: 10.066 | Z17: =SUM(V17:Y17) -> 41.313 | AA17: 12.477 | AB17: 13.943 | AC17: 13.088 | AD17: 14.183 | AE17: =SUM(AA17:AD17) -> 53.691 | AF17: 17.584 | AG17: 10.701 | AH17: 10.955 | AI17: 13.149 | AJ17: =SUM(AF17:AI17) -> 52.389 | AK17: 16.296 | AL17: 19.662 | AM17: 21.67 | AN17: 22.212 | AO17: =SUM(AK17:AN17) -> 79.84 | AP17: 22.538 | AQ17: 23.143 | AR17: 24.262 | AS17: 23.21 | AT17: =SUM(AP17:AS17) -> 93.153 | AU17: 23.428 | AV17: 22.695 | AW17: 21.614 | AX17: 22.762 | AY17: =SUM(AU17:AX17) -> 90.499 | AZ17: 21.665 | BA17: 21.88 | BB17: 20.829 | BC17: 22.952 | BD17: =SUM(AZ17:BC17) -> 87.326 | BE17: 22.496 | BF17: 23.118 | BG17: 22.353 | BH17: 23.88 | BI17: =SUM(BE17:BH17) -> 91.847 | BJ17: =BJ63*BJ$10 -> 24.098963 | BK17: =BK63*BK$10 -> 26.647596 | BL17: =BL63*BL$10 -> 27.179255 | BM17: =BM63*BM$10 -> 29.139092 | BN17: =SUM(BJ17:BM17) -> 107.06491 | BO17: =BO63*BO$10 -> 26.374573 | BP17: =BP63*BP$10 -> 29.185008 | BQ17: =BQ63*BQ$10 -> 29.815641 | BR17: =BR63*BR$10 -> 31.929363 | BS17: =SUM(BO17:BR17) -> 117.30458
A18: General & Administrative | B18: 3.982 | C18: 3.928 | D18: 5.715 | E18: 5.229 | F18: =SUM(B18:E18) -> 18.854 | G18: 5.798 | H18: 5.536 | I18: 5.728 | J18: 5.521 | K18: =SUM(G18:J18) -> 22.583 | L18: 6.228 | M18: 6.071 | N18: 5.763 | O18: 5.725 | P18: =SUM(L18:O18) -> 23.787 | Q18: 6.019 | R18: 6.192 | S18: 5.52 | T18: 5.357 | U18: =SUM(Q18:T18) -> 23.088 | V18: 5.644 | W18: 5.932 | X18: 5.742 | Y18: 6.645 | Z18: =SUM(V18:Y18) -> 23.963 | AA18: 6.904 | AB18: 6.92 | AC18: 6.624 | AD18: 8.581 | AE18: =SUM(AA18:AD18) -> 29.029 | AF18: 7.813 | AG18: 7.957 | AH18: 8.546 | AI18: 12.413 | AJ18: =SUM(AF18:AI18) -> 36.729 | AK18: =46.282-35.1 -> 11.182 | AL18: =15.473 -> 15.473 | AM18: 20.749 | AN18: 18.849 | AO18: =SUM(AK18:AN18) -> 66.253 | AP18: 18.022 | AQ18: 16.765 | AR18: 16.328 | AS18: 16.84 | AT18: =SUM(AP18:AS18) -> 67.955 | AU18: 16.281 | AV18: 17.894 | AW18: 17.95 | AX18: 17.935 | AY18: =SUM(AU18:AX18) -> 70.06 | AZ18: 17.799 | BA18: 22.562 | BB18: 20.732 | BC18: 17.569 | BD18: =SUM(AZ18:BC18) -> 78.662 | BE18: 22.348 | BF18: 22.941 | BG18: 22.254 | BH18: 22.294 | BI18: =SUM(BE18:BH18) -> 89.837 | BJ18: =BJ64*BJ$10 -> 23.44764 | BK18: =BK64*BK$10 -> 25.911474 | BL18: =BL64*BL$10 -> 25.718005 | BM18: =BM64*BM$10 -> 26.838638 | BN18: =SUM(BJ18:BM18) -> 101.91576 | BO18: =BO64*BO$10 -> 25.653956 | BP18: =BP64*BP$10 -> 28.369784 | BQ18: =BQ64*BQ$10 -> 28.195226 | BR18: =BR64*BR$10 -> 29.381807 | BS18: =SUM(BO18:BR18) -> 111.60077
A19: Total Operating Expenses | B19: =SUM(B16:B18) -> 10.444 | C19: =SUM(C16:C18) -> 11.272 | D19: =SUM(D16:D18) -> 13.481 | E19: =SUM(E16:E18) -> 15.393 | F19: =SUM(F16:F18) -> 50.59 | G19: =SUM(G16:G18) -> 14.205 | H19: =SUM(H16:H18) -> 15.576 | I19: =SUM(I16:I18) -> 15.339 | ... BS19: =SUM(BS16:BS18) -> 311.25498
A20: Operating Income | B20: =+B15-B19 -> -6.575 | C20: =+C15-C19 -> -6.561 | D20: =+D15-D19 -> -7.811 | E20: =+E15-E19 -> -8.059 | F20: =+F15-F19 -> -29.006 | G20: =+G15-G19 -> -7.553 | H20: =+H15-H19 -> -8.807 | I20: =+I15-I19 -> -8.622 | ... BS20: =+BS15-BS19 -> 154.56242
A21: Interest Expense | B21: -0.111 | C21: -0.113 | D21: -0.114 | E21: -0.101 | F21: =SUM(B21:E21) -> -0.439 | G21: -0.089 | H21: -0.09 | I21: -0.092 | J21: -0.096 | K21: =SUM(G21:J21) -> -0.367 | L21: -0.367 | M21: -0.785 | N21: -0.799 | O21: -0.806 | P21: =SUM(L21:O21) -> -2.757 | Q21: -0.8 | R21: -0.808 | S21: -0.815 | T21: -2.518 | U21: =SUM(Q21:T21) -> -4.941 | V21: -0.448 | W21: -0.481 | X21: -0.498 | Y21: -0.536 | Z21: =SUM(V21:Y21) -> -1.963 | AA21: -0.303 | AB21: -0.235 | AC21: -0.058 | AD21: -0.081 | AE21: =SUM(AA21:AD21) -> -0.677 | AF21: -0.055 | AG21: -0.065 | AH21: -0.055 | AI21: -0.054 | AJ21: =SUM(AF21:AI21) -> -0.229 | AK21: -0.053 | AL21: -0.063 | AM21: 1.202 | AN21: 1.016 | AO21: =SUM(AK21:AN21) -> 2.102 | AP21: 0 | AQ21: 0 | AR21: 0 | AS21: 0 | AT21: =SUM(AP21:AS21) -> 0 | AU21: 0 | AW21: 0 | AX21: 0 | AY21: =SUM(AU21:AX21) -> 0 | AZ21: 0 | BB21: 0 | BC21: 0 | BD21: =SUM(AZ21:BC21) -> 0 | BE21: 0 | BG21: 0 | BH21: 0 | BI21: =SUM(BE21:BH21) -> 0 | BJ21: 0 | BK21: 0 | BL21: 0 | BM21: 0 | BN21: =SUM(BJ21:BM21) -> 0 | BO21: 0 | BP21: 0 | BQ21: 0 | BR21: 0 | BS21: =SUM(BO21:BR21) -> 0
A22: Other Income (Expense) | B22: 0.012 | C22: 0.019 | D22: 0.023 | E22: 0.018 | F22: =SUM(B22:E22) -> 0.072 | G22: 0.032 | H22: 0.028 | I22: 0.035 | J22: 0.034 | K22: =SUM(G22:J22) -> 0.129 | L22: 0.043 | M22: 0.036 | N22: 0.048 | O22: 0.075 | P22: =SUM(L22:O22) -> 0.202 | Q22: 0.1 | R22: 0.119 | S22: 0.134 | T22: 0.123 | U22: =SUM(Q22:T22) -> 0.476 | V22: 0.226 | W22: 0.15 | X22: 0.333 | Y22: 0.488 | Z22: =SUM(V22:Y22) -> 1.197 | AA22: 0.453 | AB22: 0.841 | AC22: 1.091 | AD22: 0.82 | AE22: =SUM(AA22:AD22) -> 3.205 | AF22: 0.539 | AG22: 0.091 | AH22: -0.003 | AI22: 0.082 | AJ22: =SUM(AF22:AI22) -> 0.709 | AK22: -0.195 | AL22: -1.653 | AM22: 0 | AN22: 0 | AO22: =SUM(AK22:AN22) -> -1.848 | AP22: 0.784 | AQ22: 1.086 | AR22: 0.805 | AS22: 1.979 | AT22: =SUM(AP22:AS22) -> 4.654 | AU22: 2.407 | AV22: -0.226 | AW22: 1.967 | AX22: 5.035 | AY22: =SUM(AU22:AX22) -> 9.183 | AZ22: 2.748 | BA22: 2.755 | BB22: 3.042 | BC22: =-0.732+1.89 -> 1.158 | BD22: =SUM(AZ22:BC22) -> 9.703 | BE22: 3.421 | BF22: 3.984 | BG22: =-4.057+8.138-1.308 -> 2.773 | BH22: =3.439 -> 3.439 | BI22: =SUM(BE22:BH22) -> 13.617 | BJ22: 0.1 | BK22: 0.1 | BL22: 0.1 | BM22: 0.1 | BN22: =SUM(BJ22:BM22) -> 0.4 | BO22: 0.1 | BP22: 0.1 | BQ22: 0.1 | BR22: 0.1 | BS22: =SUM(BO22:BR22) -> 0.4
A23: Pretax Income | B23: =B20+B22+B21 -> -6.674 | C23: =C20+C22+C21 -> -6.655 | D23: =D20+D22+D21 -> -7.902 | E23: =E20+E22+E21 -> -8.142 | F23: =F20+F22+F21 -> -29.373 | G23: =G20+G22+G21 -> -7.61 | H23: =H20+H22+H21 -> -8.869 | I23: =I20+I22+I21 -> -8.679 | ... BS23: =BS20+BS22+BS21 -> 154.96242
A24: Provision for Income Taxes | B24: 0 | C24: 0 | D24: 0 | E24: 0 | F24: =SUM(B24:E24) -> 0 | G24: 0 | H24: 0 | I24: 0 | J24: 0 | K24: =SUM(G24:J24) -> 0 | L24: 0 | M24: 0 | N24: 0 | O24: 0 | P24: =SUM(L24:O24) -> 0 | Q24: 0 | R24: 0 | S24: 0 | T24: 0 | U24: =SUM(Q24:T24) -> 0 | V24: 0 | W24: 0 | X24: 0 | Y24: 0 | Z24: =SUM(V24:Y24) -> 0 | AA24: 0 | AB24: 0 | AC24: 0 | AD24: 0 | AE24: =SUM(AA24:AD24) -> 0 | AF24: 0 | AG24: 0 | AH24: 0 | AI24: 0 | AJ24: =SUM(AF24:AI24) -> 0 | AK24: =-3.795+0.27 -> -3.525 | AL24: -0.152 | AM24: -1.35 | AN24: -0.789 | AO24: =SUM(AK24:AN24) -> -5.816 | AP24: =-0.003 -> -0.003 | AQ24: -0.115 | AR24: -0.152 | AS24: 0.403 | AT24: =SUM(AP24:AS24) -> 0.133 | AU24: 0.576 | AV24: 0.676 | AW24: 0.97 | AX24: 1.208 | AY24: =SUM(AU24:AX24) -> 3.43 | AZ24: 1.088 | BA24: 1.741 | BB24: =BB25*BB23 -> 1.926066 | BC24: =-1.67-1.83 -> -3.5 | BD24: =SUM(AZ24:BC24) -> 1.255066 | BE24: 1.06 | BF24: =2.23-0.437 -> 1.793 | BG24: =-0.248-0.565 -> -0.813 | BH24: =-0.515+1.59 -> 1.075 | BI24: =SUM(BE24:BH24) -> 3.115 | BJ24: =BJ25*BJ23 -> 1.4900172 | BK24: =BK25*BK23 -> 1.7348854 | BL24: =BL25*BL23 -> 1.7292753 | BM24: =BM25*BM23 -> 1.899041 | BN24: =SUM(BJ24:BM24) -> 6.8532188 | BO24: =BO25*BO23 -> 1.684037 | BP24: =BP25*BP23 -> 1.9615368 | BQ24: =BQ25*BQ23 -> 1.9576004 | BR24: =BR25*BR23 -> 2.1449467 | BS24: =SUM(BO24:BR24) -> 7.7481209
A25: Tax Rate | B25: =B24/B23 -> 0 | C25: =C24/C23 -> 0 | D25: =D24/D23 -> 0 | E25: =E24/E23 -> 0 | F25: =F24/F23 -> 0 | G25: =G24/G23 -> 0 | H25: =H24/H23 -> 0 | I25: =I24/I23 -> 0 | ... BA25: =BA24/BA23 -> 0.069241171 | BB25: 0.069 | BC25: =BC24/BC23 -> -0.13752996 | BD25: =BD24/BD23 -> 0.013320166 | BE25: =BE24/BE23 -> 0.041510025 | BF25: =BF24/BF23 -> 0.048795755 | BG25: 0.069 | BH25: =BH24/BH23 -> 0.024493051 | BI25: =BI24/BI23 -> 0.021298854 | BJ25: 0.05 | BK25: 0.05 | BL25: 0.05 | BM25: 0.05 | BN25: =BN24/BN23 -> 0.05 | BO25: 0.05 | BP25: 0.05 | BQ25: 0.05 | BR25: 0.05 | BS25: =BS24/BS23 -> 0.05
A26: Income Before Non-Recurring | B26: =+B23-B24 -> -6.674 | C26: =+C23-C24 -> -6.655 | D26: =+D23-D24 -> -7.902 | E26: =+E23-E24 -> -8.142 | F26: =+F23-F24 -> -29.373 | G26: =+G23-G24 -> -7.61 | H26: =+H23-H24 -> -8.869 | I26: =+I23-I24 -> -8.679 | ... BS26: =+BS23-BS24 -> 147.2143
A27: Intangible Asset Amortization | B27: 0 | C27: 0 | D27: 0 | E27: 0 | F27: =SUM(B27:E27) -> 0 | G27: 0 | H27: -0.267 | I27: -0.266 | J27: -0.267 | K27: =SUM(G27:J27) -> -0.8 | L27: -0.267 | M27: -0.267 | N27: -0.266 | O27: -0.267 | P27: =SUM(L27:O27) -> -1.067 | Q27: -0.267 | R27: -0.266 | S27: -0.267 | T27: -0.267 | U27: =SUM(Q27:T27) -> -1.067 | V27: -0.267 | W27: -0.266 | X27: -0.267 | Y27: -0.267 | Z27: =SUM(V27:Y27) -> -1.067 | AA27: -0.267 | AB27: -0.266 | AC27: -0.267 | AD27: -0.601 | AE27: =SUM(AA27:AD27) -> -1.401 | AF27: -1.275 | AG27: -1.273 | AH27: -1.274 | AI27: -1.273 | AJ27: =SUM(AF27:AI27) -> -5.095 | AK27: -1.801 | AL27: -3.723 | AM27: -4.983 | AN27: -5.474 | AO27: =SUM(AK27:AN27) -> -15.981 | AP27: -5.486 | AQ27: -5.391 | AR27: -5.213 | AS27: -5.264 | AT27: =SUM(AP27:AS27) -> -21.354 | AY27: =SUM(AU27:AX27) -> 0 | BD27: =SUM(AZ27:BC27) -> 0 | BI27: =SUM(BE27:BH27) -> 0 | BN27: =SUM(BJ27:BM27) -> 0 | BS27: =SUM(BO27:BR27) -> 0
A28: Net Other Items | B28: 0 | C28: 0 | D28: 0 | E28: 0 | F28: =SUM(B28:E28) -> 0 | G28: 0 | H28: 0 | I28: 0 | J28: 0 | K28: =SUM(G28:J28) -> 0 | L28: 0 | M28: 0 | N28: 0 | O28: 0 | P28: =SUM(L28:O28) -> 0 | Q28: 0 | R28: 0 | S28: 0 | T28: 0 | U28: =SUM(Q28:T28) -> 0 | V28: 0 | W28: 0 | X28: 0 | Y28: 0 | Z28: =SUM(V28:Y28) -> 0 | AA28: 0 | AB28: 0 | AC28: 0 | AD28: 0 | AE28: =SUM(AA28:AD28) -> 0 | AF28: -1.088 | AG28: 0 | AH28: 0 | AI28: 0 | AJ28: =SUM(AF28:AI28) -> -1.088 | AK28: -34.83 | AL28: 0 | AM28: 0 | AN28: 0 | AO28: =SUM(AK28:AN28) -> -34.83 | AP28: =-4.934 -> -4.934 | AQ28: =-0.982-3.318 -> -4.3 | AR28: =-2.557-0.514 -> -3.071 | AS28: -2.631 | AT28: =SUM(AP28:AS28) -> -14.936 | AY28: =SUM(AU28:AX28) -> 0 | BD28: =SUM(AZ28:BC28) -> 0 | BI28: =SUM(BE28:BH28) -> 0 | BN28: =SUM(BJ28:BM28) -> 0 | BS28: =SUM(BO28:BR28) -> 0
A29: Non-GAAP Net Income | B29: =SUM(B26:B28) -> -6.674 | C29: =SUM(C26:C28) -> -6.655 | D29: =SUM(D26:D28) -> -7.902 | E29: =SUM(E26:E28) -> -8.142 | F29: =SUM(F26:F28) -> -29.373 | G29: =SUM(G26:G28) -> -7.61 | H29: =SUM(H26:H28) -> -9.136 | I29: =SUM(I26:I28) -> -8.945 | ... AT29: =SUM(AT26:AT28) -> -36.61 | AU29: =+AU23-AU24 -> 7.263 | AV29: =+AV23-AV24 -> 8.538 | AW29: =+AW23-AW24 -> 12.246 | AX29: =+AX23-AX24 -> 15.247 | AY29: =+AY23-AY24 -> 43.294 | AZ29: =+AZ23-AZ24 -> 14.628 | BA29: =+BA23-BA24 -> 23.403 | BB29: =+BB23-BB24 -> 25.987934 | ... BS29: =+BS23-BS24 -> 147.2143
A31: Weighted Average Shares (Basic) | B31: 21.148342 | C31: 21.237196 | D31: 21.64866 | E31: 22.50825 | F31: 21.639374 | G31: 22.539723 | H31: 26.048934 | I31: 27.640806 | J31: 27.672806 | K31: 25.944193 | L31: 27.817993 | M31: 27.859918 | N31: 27.916819 | O31: 31.705603 | P31: 28.830472 | Q31: 33.823889 | R31: 33.873128 | S31: 33.946748 | T31: 34.055524 | U31: 33.925617 | V31: 34.271254 | W31: 34.314234 | X31: 38.620036 | Y31: 40.731334 | Z31: 37.020246 | AA31: 41.168593 | AB31: 45.586081 | AC31: 48.588296 | AD31: 49.095703 | AE31: 46.138177 | AF31: 49.792631 | AG31: 50.212123 | AH31: 54.858052 | AI31: 58.023753 | AJ31: =AVERAGE(AF31:AI31) -> 53.22164 | AK31: 63.331702 | AL31: 67.316065 | AM31: 69.743733 | AN31: 71.064467 | AO31: =AVERAGE(AK31:AN31) -> 67.863992 | AP31: 71.229672 | AQ31: 71.476966 | AR31: 71.656694 | AS31: 71.825754 | AT31: =AVERAGE(AP31:AS31) -> 71.547272 | AU31: 72.175457 | AV31: 72.478662 | AW31: 72.80477 | AX31: 73.107059 | AY31: =AVERAGE(AU31:AX31) -> 72.641487 | AZ31: 74.759789 | BA31: 77.163149 | BB31: 78.464654 | BC31: 77.608924 | BD31: =AVERAGE(AZ31:BC31) -> 76.999129 | BE31: 80.056024 | BF31: 78.391502 | BG31: 78.725139 | BH31: 79.178087 | BI31: =AVERAGE(BE31:BH31) -> 79.087688 | BJ31: =+BH31+0.4 -> 79.578087 | BK31: =+BJ31+0.4 -> 79.978087 | BL31: =+BK31+0.4 -> 80.378087 | BM31: =+BL31+0.4 -> 80.778087 | BN31: =AVERAGE(BJ31:BM31) -> 80.178087 | BO31: =+BM31+0.4 -> 81.178087 | BP31: =+BO31+0.4 -> 81.578087 | BQ31: =+BP31+0.4 -> 81.978087 | BR31: =+BQ31+0.4 -> 82.378087 | BS31: =AVERAGE(BO31:BR31) -> 81.778087
A32: Effect of Dilutive Securities | B32: =+B33-B31 -> 0 | C32: =+C33-C31 -> 0 | D32: =+D33-D31 -> 0 | E32: =+E33-E31 -> 0 | F32: =+F33-F31 -> 0 | G32: =+G33-G31 -> 0 | H32: =+H33-H31 -> 0 | I32: =+I33-I31 -> 0 | ... R32: =+R33-R31 -> 0 | S32: 0.9 | T32: =+T33-T31 -> 0 | U32: =+U33-U31 -> 0 | V32: =+V33-V31 -> 0 | W32: =+W33-W31 -> 0 | X32: =+X33-X31 -> 0 | Y32: 0 | Z32: =+Z33-Z31 -> 0 | AA32: 0 | AB32: 0 | AC32: 0 | AD32: 0 | AE32: =+AE33-AE31 -> 0 | AF32: =+AF33-AF31 -> 0 | AG32: =+AG33-AG31 -> 0 | AH32: =+AH33-AH31 -> 0 | AI32: 0 | AJ32: =+AJ33-AJ31 -> 0 | AK32: 0 | AL32: 0 | AM32: 0 | AN32: 0 | AO32: =+AO33-AO31 -> 0 | AP32: 0 | AQ32: 0 | AR32: 0 | AS32: 0 | AT32: =+AT33-AT31 -> 0 | AU32: 0 | AV32: 0 | AW32: 0 | AX32: 0 | AY32: =+AX32 -> 0 | AZ32: 0 | BA32: 0 | BB32: 0 | BC32: 0 | BD32: =+BC32 -> 0 | BE32: 0 | BF32: 0 | BG32: 0 | BH32: 0 | BI32: =+BH32 -> 0 | BJ32: 0 | BK32: 0 | BL32: 0 | BM32: 0 | BN32: =+BM32 -> 0 | BO32: 0 | BP32: 0 | BQ32: 0 | BR32: 0 | BS32: =+BR32 -> 0
A33: Weighted Average Shares (Diluted) | B33: 21.148342 | C33: 21.237196 | D33: 21.64866 | E33: 22.50825 | F33: 21.639374 | G33: 22.539723 | H33: 26.048934 | I33: 27.640806 | J33: 27.672806 | K33: 25.944193 | L33: 27.817993 | M33: 27.859918 | N33: 27.916819 | O33: 31.705603 | P33: 28.830472 | Q33: 33.823889 | R33: 33.873128 | S33: 33.946748 | T33: 34.055524 | U33: 33.925617 | V33: 34.271254 | W33: 34.314234 | X33: 38.620036 | Y33: 40.731334 | Z33: 37.020246 | AA33: 41.168593 | AB33: 45.586081 | AC33: 48.588296 | AD33: 49.095703 | AE33: 46.138177 | AF33: 49.792631 | AG33: 50.212123 | AH33: 54.858052 | AI33: =+AI32+AI31 -> 58.023753 | AJ33: =AVERAGE(AF33:AI33) -> 53.22164 | AK33: =+AK32+AK31 -> 63.331702 | AL33: =+AL32+AL31 -> 67.316065 | AM33: =+AM32+AM31 -> 69.743733 | AN33: =+AN32+AN31 -> 71.064467 | AO33: =+AO31 -> 67.863992 | AP33: =+AP32+AP31 -> 71.229672 | AQ33: =+AQ32+AQ31 -> 71.476966 | AR33: =+AR32+AR31 -> 71.656694 | AS33: =+AS32+AS31 -> 71.825754 | AT33: =+AT31 -> 71.547272 | AU33: 73.512773 | AV33: 73.700383 | AW33: 74.130913 | AX33: 74.224254 | AY33: =AVERAGE(AU33:AX33) -> 73.892081 | AZ33: 75.877075 | BA33: 77.163149 | BB33: 78.464654 | BC33: 79.905412 | BD33: =AVERAGE(AZ33:BC33) -> 77.852573 | BE33: 80.056024 | BF33: 79.449213 | BG33: 79.691703 | BH33: 81.387089 | BI33: =AVERAGE(BE33:BH33) -> 80.146007 | BJ33: =+BJ32+BJ31 -> 79.578087 | BK33: =+BK32+BK31 -> 79.978087 | BL33: =+BL32+BL31 -> 80.378087 | BM33: =+BM32+BM31 -> 80.778087 | BN33: =AVERAGE(BJ33:BM33) -> 80.178087 | BO33: =+BO32+BO31 -> 81.178087 | BP33: =+BP32+BP31 -> 81.578087 | BQ33: =+BQ32+BQ31 -> 81.978087 | BR33: =+BR32+BR31 -> 82.378087 | BS33: =AVERAGE(BO33:BR33) -> 81.778087
A35: Non-GAAP EPS | AU35: =AU29/AU33 -> 0.098799157 | AV35: =AV29/AV33 -> 0.11584743 | AW35: =AW29/AW33 -> 0.16519424 | AX35: =AX29/AX33 -> 0.20541803 | AY35: =+AY29/AY33 -> 0.58590852 | AZ35: =AZ29/AZ33 -> 0.1927855 | BA35: =BA29/BA33 -> 0.30329244 | BB35: =BB29/BB33 -> 0.33120562 | BC35: =BC29/BC33 -> 0.36229085 | BD35: =+BD29/BD33 -> 1.1941537 | BE35: =BE29/BE33 -> 0.30573589 | BF35: =BF29/BF33 -> 0.43992884 | BG35: =BG29/BG33 -> 0.51315254 | BH35: =BH29/BH33 -> 0.52606624 | BI35: =+BI29/BI33 -> 1.785953 | BJ35: =BJ29/BJ33 -> 0.3557553 | BK35: =BK29/BK33 -> 0.41214816 | BL35: =BL29/BL33 -> 0.408771 | BM35: =BM29/BM33 -> 0.44667781 | BN35: =+BN29/BN33 -> 1.6240243 | BO35: =BO29/BO33 -> 0.39415444 | BP35: =BP29/BP33 -> 0.45685307 | BQ35: =BQ29/BQ33 -> 0.45371158 | BR35: =BR29/BR33 -> 0.49471878 | BS35: =+BS29/BS33 -> 1.800168
A36: Amortization of Intangible Assets | AU36: =10.67-AV36 -> 5.329 | AV36: 5.341 | AW36: 5.337 | AX36: 4.563 | AY36: =SUM(AU36:AX36) -> 20.57 | AZ36: =7.443-BA36 -> 3.653 | BA36: 3.79 | BB36: 3.797 | BC36: 3.609 | BD36: =SUM(AZ36:BC36) -> 14.849 | BE36: 3.207 | BF36: 3.288 | BG36: 3.329 | BH36: 3.329 | BI36: =SUM(BE36:BH36) -> 13.153 | BJ36: 3.8 | BK36: =BJ36 -> 3.8 | BL36: =BK36 -> 3.8 | BM36: =BL36 -> 3.8 | BN36: =SUM(BJ36:BM36) -> 15.2 | BO36: 3.8 | BP36: =BO36 -> 3.8 | BQ36: =BP36 -> 3.8 | BR36: =BQ36 -> 3.8 | BS36: =SUM(BO36:BR36) -> 15.2
A37: Stock-Based Comp Expense | AU37: =18.55-AV37 -> 8.101 | AV37: 10.449 | AW37: 7.332 | AX37: 7.607 | AY37: =SUM(AU37:AX37) -> 33.489 | AZ37: =17.873-BA37 -> 8.019 | BA37: 9.854 | BB37: 8.747 | BC37: 9.629 | BD37: =SUM(AZ37:BC37) -> 36.249 | BE37: 10.958 | BF37: 10.985 | BG37: 10.757 | BH37: 10.901 | BI37: =SUM(BE37:BH37) -> 43.601 | BJ37: 9.9 | BK37: =BJ37 -> 9.9 | BL37: =BK37 -> 9.9 | BM37: =BL37 -> 9.9 | BN37: =SUM(BJ37:BM37) -> 39.6 | BO37: 9.9 | BP37: =BO37 -> 9.9 | BQ37: =BP37 -> 9.9 | BR37: =BQ37 -> 9.9 | BS37: =SUM(BO37:BR37) -> 39.6
A38: Acquisition-Related Expenses | AU38: =2.856-AV38 -> 1.155 | AV38: 1.701 | AW38: -4.581 | AX38: 2.718 | AY38: =SUM(AU38:AX38) -> 0.993 | AZ38: =5.596-BA38 -> 4.503 | BA38: 1.093 | BB38: 0.075 | BC38: 0.961 | BD38: =SUM(AZ38:BC38) -> 6.632 | BE38: 1.352 | BF38: -0.925 | BG38: 0.166 | BH38: -12.564 | BI38: =SUM(BE38:BH38) -> -11.971 | BJ38: 1 | BK38: =BJ38 -> 1 | BL38: =BK38 -> 1 | BM38: =BL38 -> 1 | BN38: =SUM(BJ38:BM38) -> 4 | BO38: 1 | BP38: =BO38 -> 1 | BQ38: =BP38 -> 1 | BR38: =BQ38 -> 1 | BS38: =SUM(BO38:BR38) -> 4
A39: Other Adjustments | AU39: =1.344-AV39 -> 1.344 | AV39: 0 | AW39: 34.9 | AX39: 32.039 | AY39: =SUM(AU39:AX39) -> 68.283 | AZ39: =4.496-BA39 -> 1.45 | BA39: 3.046 | BB39: -0.853 | BC39: 7.807 | BD39: =SUM(AZ39:BC39) -> 11.45 | BE39: 2.591 | BF39: 22.147 | BG39: 8.138 | BH39: 1.59 | BI39: =SUM(BE39:BH39) -> 34.466 | BJ39: 1 | BK39: =BJ39 -> 1 | BL39: =BK39 -> 1 | BM39: =BL39 -> 1 | BN39: =SUM(BJ39:BM39) -> 4 | BO39: 1 | BP39: =BO39 -> 1 | BQ39: =BP39 -> 1 | BR39: =BQ39 -> 1 | BS39: =SUM(BO39:BR39) -> 4
A40: Tax | AU40: =-1.126-AV40 -> -0.575 | AV40: -0.551 | AW40: -1.124 | AX40: -3.387 | AY40: =SUM(AU40:AX40) -> -5.637 | AZ40: =-1.247-BA40 -> -1.133 | BA40: -0.114 | BB40: -0.933 | BC40: 1.83 | BD40: =SUM(AZ40:BC40) -> -0.35 | BE40: -0.679 | BF40: 0.437 | BG40: -0.565 | BH40: -1.59 | BI40: =SUM(BE40:BH40) -> -2.397 | BJ40: 0 | BK40: =BJ40 -> 0 | BL40: =BK40 -> 0 | BM40: =BL40 -> 0 | BN40: =SUM(BJ40:BM40) -> 0 | BO40: 0 | BP40: =BO40 -> 0 | BQ40: =BP40 -> 0 | BR40: =BQ40 -> 0 | BS40: =SUM(BO40:BR40) -> 0
A41: GAAP Net Income | B41: =B29 -> -6.674 | C41: =C29 -> -6.655 | D41: =D29 -> -7.902 | E41: =E29 -> -8.142 | F41: =F29 -> -29.373 | G41: =G29 -> -7.61 | H41: =H29 -> -9.136 | I41: =I29 -> -8.945 | ... AT41: =AT29 -> -36.61 | AU41: =(AU29-SUM(AU36:AU40)) -> -8.091 | AV41: =(AV29-SUM(AV36:AV40)) -> -8.402 | AW41: =(AW29-SUM(AW36:AW40)) -> -29.618 | AX41: =(AX29-SUM(AX36:AX40)) -> -28.293 | AY41: =(AY29-SUM(AY36:AY40)) -> -74.404 | AZ41: =(AZ29-SUM(AZ36:AZ40)) -> -1.864 | BA41: =(BA29-SUM(BA36:BA40)) -> 5.734 | BB41: =(BB29-SUM(BB36:BB40)) -> 15.154934 | ... BS41: =(BS29-SUM(BS36:BS40)) -> 84.414297
A42: GAAP EPS | B42: =B29/B33 -> -0.31558029 | C42: =C29/C33 -> -0.31336529 | D42: =D29/D33 -> -0.36501104 | E42: =E29/E33 -> -0.36173403 | F42: =+F29/F33 -> -1.3573868 | G42: =G29/G33 -> -0.33762615 | H42: =H29/H33 -> -0.35072452 | I42: =I29/I33 -> -0.32361574 | J42: =J29/J33 -> -0.28956225 | K42: =+K29/K33 -> -1.2990961 | L42: =L29/L33 -> -0.36217566 | M42: =M29/M33 -> -0.40355467 | N42: =N29/N33 -> -0.20192129 | O42: =O29/O33 -> -0.13887135 | P42: =+P29/P33 -> -1.0876686 | Q42: =Q29/Q33 -> -0.24293481 | R42: =R29/R33 -> -0.21545102 | S42: =S29/S31 -> -0.20764876 | T42: =T29/T33 -> -0.24780121 | U42: =+U29/U33 -> -0.91385221 | V42: =V29/V31 -> -0.26777544 | W42: =W29/W33 -> -0.18208187 | X42: =X29/X33 -> -0.11571714 | Y42: =Y29/Y33 -> -0.076231238 | Z42: =+Z29/Z33 -> -0.62125465 | AA42: =AA29/AA33 -> -0.046564623 | AB42: =AB29/AB33 -> -0.054709682 | AC42: =AC29/AC33 -> -0.015024194 | AD42: =AD29/AD33 -> -0.15231476 | AE42: =+AE29/AE33 -> -0.27350452 | AF42: =AF29/AF33 -> -0.23529586 | AG42: =AG29/AG33 -> -0.21956849 | AH42: =AH29/AH33 -> -0.075175837 | AI42: =AI29/AI33 -> -0.13863288 | AJ42: =+AJ29/AJ33 -> -0.65591741 | AK42: =AK29/AK33 -> -0.66109071 | AL42: =AL29/AL33 -> -0.13426216 | AM42: =AM29/AM33 -> -0.20258451 | AN42: =AN29/AN33 -> -0.14814717 | AO42: =+AO29/AO33 -> -1.1134476 | AP42: =AP29/AP33 -> -0.20301933 | AQ42: =AQ29/AQ33 -> -0.13335765 | AR42: =AR29/AR33 -> -0.12173322 | AS42: =AS29/AS33 -> -0.054214537 | AT42: =+AT29/AT33 -> -0.51168967 | AU42: =AU41/AU31 -> -0.11210182 | AV42: =AV41/AV31 -> -0.11592377 | AW42: =AW41/AW31 -> -0.406814 | AX42: =AX41/AX31 -> -0.38700777 | AY42: =AY41/AY31 -> -1.0242632 | AZ42: =AZ41/AZ31 -> -0.02493319 | BA42: =BA41/BA31 -> 0.074310083 | BB42: =BB41/BB31 -> 0.19314345 | ... BS42: =BS41/BS31 -> 1.0322361
A43: Amortization of Intangible Assets | AU43: =10.67-AV43 -> 5.329 | AV43: 5.341 | AW43: 5.337 | AX43: 4.563 | AY43: =SUM(AU43:AX43) -> 20.57 | AZ43: =7.443-BA43 -> 3.653 | BA43: 3.79 | BB43: 3.797 | BC43: 3.609 | BD43: =SUM(AZ43:BC43) -> 14.849 | BE43: 3.207 | BF43: 3.288 | BG43: 3.329 | BH43: 3.329 | BI43: =SUM(BE43:BH43) -> 13.153 | BJ43: =BJ36 -> 3.8 | BK43: =BK36 -> 3.8 | BL43: =BL36 -> 3.8 | BM43: =BM36 -> 3.8 | BN43: =SUM(BJ43:BM43) -> 15.2 | BO43: =BO36 -> 3.8 | BP43: =BP36 -> 3.8 | BQ43: =BQ36 -> 3.8 | BR43: =BR36 -> 3.8 | BS43: =SUM(BO43:BR43) -> 15.2
A44: Depreciation Expense | AU44: =2.859-AV44 -> 1.341 | AV44: 1.518 | AW44: 1.985 | AX44: 1.773 | AY44: =SUM(AU44:AX44) -> 6.617 | AZ44: =3.885-BA44 -> 1.937 | BA44: 1.948 | BB44: 2.081 | BC44: 2.643 | BD44: =SUM(AZ44:BC44) -> 8.609 | BE44: 2.155 | BF44: 2.201 | BG44: 1.938 | BH44: 1.968 | BI44: =SUM(BE44:BH44) -> 8.262 | BJ44: 1.9 | BK44: 1.9 | BL44: 1.9 | BM44: 1.9 | BN44: =SUM(BJ44:BM44) -> 7.6 | BO44: 1.9 | BP44: 1.9 | BQ44: 1.9 | BR44: 1.9 | BS44: =SUM(BO44:BR44) -> 7.6
A45: Stock-Based Comp Expense | AU45: =18.55-AV45 -> 8.101 | AV45: 10.449 | AW45: 7.332 | AX45: 7.607 | AY45: =SUM(AU45:AX45) -> 33.489 | AZ45: =17.873-BA45 -> 8.019 | BA45: 9.854 | BB45: 8.747 | BC45: 9.629 | BD45: =SUM(AZ45:BC45) -> 36.249 | BE45: 10.958 | BF45: 10.958 | BG45: 10.757 | BH45: 10.901 | BI45: =SUM(BE45:BH45) -> 43.574 | BJ45: =BJ37 -> 9.9 | BK45: =BK37 -> 9.9 | BL45: =BL37 -> 9.9 | BM45: =BM37 -> 9.9 | BN45: =SUM(BJ45:BM45) -> 39.6 | BO45: =BO37 -> 9.9 | BP45: =BP37 -> 9.9 | BQ45: =BQ37 -> 9.9 | BR45: =BR37 -> 9.9 | BS45: =SUM(BO45:BR45) -> 39.6
A46: Acquisition-Related Expenses | AU46: =2.856-AV46 -> 1.155 | AV46: 1.701 | AW46: -4.581 | AX46: 2.718 | AY46: =SUM(AU46:AX46) -> 0.993 | AZ46: =5.596-BA46 -> 4.503 | BA46: 1.093 | BB46: 0.075 | BC46: 0.961 | BD46: =SUM(AZ46:BC46) -> 6.632 | BE46: 1.352 | BF46: -0.925 | BG46: 0.166 | BH46: -12.564 | BI46: =SUM(BE46:BH46) -> -11.971 | BJ46: 0 | BK46: 0 | BL46: 0 | BM46: 0 | BN46: =SUM(BJ46:BM46) -> 0 | BO46: 0 | BP46: 0 | BQ46: 0 | BR46: 0 | BS46: =SUM(BO46:BR46) -> 0
A47: Other Expense (Income) | AU47: =-1.902-AV47 -> -2.189 | AV47: 0.287 | AW47: -2.62 | AX47: -3.399 | AY47: =SUM(AU47:AX47) -> -7.921 | AZ47: =-6.313-BA47 -> -3.261 | BA47: -3.052 | BB47: -3.366 | BC47: -1.967 | BD47: =SUM(AZ47:BC47) -> -11.646 | BE47: -2.976 | BF47: -3.17 | BG47: -3.484 | BH47: -3.546 | BI47: =SUM(BE47:BH47) -> -13.176 | BJ47: 0 | BK47: 0 | BL47: 0 | BM47: 0 | BN47: =SUM(BJ47:BM47) -> 0 | BO47: 0 | BP47: 0 | BQ47: 0 | BR47: 0 | BS47: =SUM(BO47:BR47) -> 0
A48: Other Adjustments | AU48: =1.344-AV48 -> 1.344 | AV48: 0 | AW48: 34.9 | AX48: 32.039 | AY48: =SUM(AU48:AX48) -> 68.283 | AZ48: =4.496-BA48 -> 1.45 | BA48: 3.046 | BB48: -0.853 | BC48: 7.801 | BD48: =SUM(AZ48:BC48) -> 11.444 | BE48: 2.591 | BF48: 22.147 | BG48: 8.138 | BH48: 1.59 | BI48: =SUM(BE48:BH48) -> 34.466 | BJ48: 2 | BK48: 2 | BL48: 2 | BM48: 2 | BN48: =SUM(BJ48:BM48) -> 8 | BO48: 2 | BP48: 2 | BQ48: 2 | BR48: 2 | BS48: =SUM(BO48:BR48) -> 8
A49: Tax | AU49: =0.125-AV49 -> 0 | AV49: 0.125 | AW49: -0.154 | AX49: -2.179 | AY49: =SUM(AU49:AX49) -> -2.208 | AZ49: =1.584-BA49 -> -0.043 | BA49: 1.627 | BB49: 1.693 | BC49: -1.67 | BD49: =SUM(AZ49:BC49) -> 1.607 | BE49: 0.381 | BF49: 2.23 | BG49: -0.248 | BH49: -0.515 | BI49: =SUM(BE49:BH49) -> 1.848 | BJ49: =BJ24 -> 1.4900172 | BK49: =BK24 -> 1.7348854 | BL49: =BL24 -> 1.7292753 | BM49: =BM24 -> 1.899041 | BN49: =SUM(BJ49:BM49) -> 6.8532188 | BO49: =BO24 -> 1.684037 | BP49: =BP24 -> 1.9615368 | BQ49: =BQ24 -> 1.9576004 | BR49: =BR24 -> 2.1449467 | BS49: =SUM(BO49:BR49) -> 7.7481209
A50: Adjusted EBITDA | B50: =+B20+'Cash Flow'!B9+'Cash Flow'!B10+B27 -> -6.575 | C50: =+C20+'Cash Flow'!C9+'Cash Flow'!C10+C27 -> -6.561 | D50: =+D20+'Cash Flow'!D9+'Cash Flow'!D10+D27 -> -7.811 | E50: =+E20+'Cash Flow'!E9+'Cash Flow'!E10+E27 -> -8.059 | F50: =SUM(B50:E50) -> -29.006 | G50: =+G20+'Cash Flow'!G9+'Cash Flow'!G10+G27 -> -7.553 | H50: =+H20+'Cash Flow'!H9+'Cash Flow'!H10+H27 -> -9.074 | I50: =+I20+'Cash Flow'!I9+'Cash Flow'!I10+I27 -> -8.888 | J50: =+J20+'Cash Flow'!J9+'Cash Flow'!J10+J27 -> -7.951 | K50: =SUM(G50:J50) -> -33.466 | L50: =+L20+'Cash Flow'!L9+'Cash Flow'!L10+L27 -> -9.751 | M50: =+M20+'Cash Flow'!M9+'Cash Flow'!M10+M27 -> -10.494 | N50: =+N20+'Cash Flow'!N9+'Cash Flow'!N10+N27 -> -4.886 | O50: =+O20+'Cash Flow'!O9+'Cash Flow'!O10+O27 -> -3.672 | P50: =SUM(L50:O50) -> -28.803 | Q50: =+Q20+'Cash Flow'!Q9+'Cash Flow'!Q10+Q27 -> -5.043 | R50: =+R20+'Cash Flow'!R9+'Cash Flow'!R10+R27 -> -4.023 | S50: =+S20+'Cash Flow'!S9+'Cash Flow'!S10+S27 -> -3.764 | T50: =+T20+'Cash Flow'!T9+'Cash Flow'!T10+T27 -> -3.25 | U50: =SUM(Q50:T50) -> -16.08 | V50: =+V20+'Cash Flow'!V9+'Cash Flow'!V10+V27 -> -6.8 | W50: =+W20+'Cash Flow'!W9+'Cash Flow'!W10+W27 -> -3.197 | X50: =+X20+'Cash Flow'!X9+'Cash Flow'!X10+X27 -> -1.804 | Y50: =+Y20+'Cash Flow'!Y9+'Cash Flow'!Y10+Y27 -> -0.554 | Z50: =SUM(V50:Y50) -> -12.355 | AA50: =+AA20+'Cash Flow'!AA9+'Cash Flow'!AA10+AA27 -> 0.637 | AB50: =+AB20+'Cash Flow'!AB9+'Cash Flow'!AB10+AB27 -> 0.39 | AC50: =+AC20+'Cash Flow'!AC9+'Cash Flow'!AC10+AC27 -> 1.844 | AD50: =+AD20+'Cash Flow'!AD9+'Cash Flow'!AD10+AD27 -> -4.094 | AE50: =SUM(AA50:AD50) -> -1.223 | AF50: =+AF20+'Cash Flow'!AF9+'Cash Flow'!AF10+AF27 -> -6.235 | AG50: =+AG20+'Cash Flow'!AG9+'Cash Flow'!AG10+AG27 -> -5.734 | AH50: =+AH20+'Cash Flow'!AH9+'Cash Flow'!AH10+AH27 -> 1.013 | AI50: =+AI20+'Cash Flow'!AI9+'Cash Flow'!AI10+AI27 -> -2.406 | AJ50: =SUM(AF50:AI50) -> -13.362 | AK50: =+AK20+'Cash Flow'!AK9+'Cash Flow'!AK10+AK27 -> -3.91 | AL50: =+AL20+'Cash Flow'!AL9+'Cash Flow'!AL10+AL27 -> 1.09 | AM50: =+AM20+'Cash Flow'!AM9+'Cash Flow'!AM10+AM27 -> -2.674 | AN50: =+AN20+'Cash Flow'!AN9+'Cash Flow'!AN10+AN27 -> 0.803 | AO50: =SUM(AK50:AN50) -> -4.691 | AP50: =+AP20+'Cash Flow'!AP9+'Cash Flow'!AP10+AP27 -> 2.887 | AQ50: =+AQ20+'Cash Flow'!AQ9+'Cash Flow'!AQ10+AQ27 -> 5.998 | AR50: =+AR20+'Cash Flow'!AR9+'Cash Flow'!AR10+AR27 -> 6.998 | AS50: =+AS20+'Cash Flow'!AS9+'Cash Flow'!AS10+AS27 -> 10.584 | AT50: =SUM(AP50:AS50) -> 26.467 | AU50: =AU41+SUM(AU43:AU49) -> 6.99 | AV50: =AV41+SUM(AV43:AV49) -> 11.019 | AW50: =AW41+SUM(AW43:AW49) -> 12.581 | AX50: =AX41+SUM(AX43:AX49) -> 14.829 | AY50: =SUM(AU50:AX50) -> 45.419 | AZ50: =AZ41+SUM(AZ43:AZ49) -> 14.394 | BA50: =BA41+SUM(BA43:BA49) -> 24.04 | BB50: =BB41+SUM(BB43:BB49) -> 27.328934 | BC50: =BC41+SUM(BC43:BC49) -> 26.119 | BD50: =SUM(AZ50:BC50) -> 91.881934 | BE50: =BE41+SUM(BE43:BE49) -> 24.715 | BF50: =BF41+SUM(BF43:BF49) -> 35.749 | BG50: =BG41+SUM(BG43:BG49) -> 39.665 | BH50: =BH41+SUM(BH43:BH49) -> 42.312 | BI50: =SUM(BE50:BH50) -> 142.441 | BJ50: =BJ41+SUM(BJ43:BJ49) -> 31.700344 | BK50: =BK41+SUM(BK43:BK49) -> 36.597707 | BL50: =BL41+SUM(BL43:BL49) -> 36.485506 | BM50: =BM41+SUM(BM43:BM49) -> 39.88082 | BN50: =SUM(BJ50:BM50) -> 144.66438 | BO50: =BO41+SUM(BO43:BO49) -> 35.580741 | BP50: =BP41+SUM(BP43:BP49) -> 41.130736 | BQ50: =BQ41+SUM(BQ43:BQ49) -> 41.052008 | BR50: =BR41+SUM(BR43:BR49) -> 44.798933 | BS50: =SUM(BO50:BR50) -> 162.56242
A51: Adjusted EBITDA per Share | B51: =B50/B33 -> -0.31089908 | C51: =C50/C33 -> -0.30893909 | D51: =D50/D33 -> -0.36080755 | E51: =E50/E33 -> -0.35804649 | F51: =F50/F33 -> -1.3404269 | G51: =G50/G33 -> -0.33509729 | H51: =H50/H33 -> -0.34834439 | I51: =I50/I33 -> -0.32155358 | ... BS51: =BS50/BS33 -> 1.9878481
A53: % of Revenue
A54: Testing Revenue | B54: =B7/B$10 -> 1 | C54: =C7/C$10 -> 1 | D54: =D7/D$10 -> 1 | E54: =E7/E$10 -> 1 | F54: =F7/F$10 -> 1 | G54: =G7/G$10 -> 1 | H54: =H7/H$10 -> 1 | I54: =I7/I$10 -> 1 | ... BS54: =BS7/BS$10 -> 0.97712494
A55: Product Revenue | B55: =B8/B$10 -> 0 | C55: =C8/C$10 -> 0 | D55: =D8/D$10 -> 0 | E55: =E8/E$10 -> 0 | F55: =F8/F$10 -> 0 | G55: =G8/G$10 -> 0 | H55: =H8/H$10 -> 0 | I55: =I8/I$10 -> 0 | ... BS55: =BS8/BS$10 -> 0.022875058
A56: Biopharma Revenue | B56: =B9/B$10 -> 0 | C56: =C9/C$10 -> 0 | D56: =D9/D$10 -> 0 | E56: =E9/E$10 -> 0 | F56: =F9/F$10 -> 0 | G56: =G9/G$10 -> 0 | H56: =H9/H$10 -> 0 | I56: =I9/I$10 -> 0 | ... BS56: =BS9/BS$10 -> 0
A57: Total Revenue | B57: =B10/B$10 -> 1 | C57: =C10/C$10 -> 1 | D57: =D10/D$10 -> 1 | E57: =E10/E$10 -> 1 | F57: =F10/F$10 -> 1 | G57: =G10/G$10 -> 1 | H57: =H10/H$10 -> 1 | I57: =I10/I$10 -> 1 | ... BS57: =BS10/BS$10 -> 1
A58: Gross Profit - Testing Revenue | B58: =+(B7-B11)/B7 -> 0.51752274 | C58: =+(C7-C11)/C7 -> 0.54292958 | D58: =+(D7-D11)/D7 -> 0.57633665 | E58: =+(E7-E11)/E7 -> 0.60119682 | F58: =+(F7-F11)/F7 -> 0.56517413 | G58: =+(G7-G11)/G7 -> 0.59297557 | H58: =+(H7-H11)/H7 -> 0.56844138 | I58: =+(I7-I11)/I7 -> 0.54454803 | ... AT58: =+(AT7-AT11)/AT7 -> 0.70006865
A59: Gross Profit - Product Revenue | B59: NA | C59: NA | D59: NA | E59: NA | F59: NA | G59: NA | H59: NA | I59: NA | J59: NA | K59: NA | L59: NA | M59: NA | N59: NA | O59: NA | P59: NA | Q59: NA | R59: NA | S59: NA | T59: NA | U59: NA | V59: NA | W59: NA | X59: NA | Y59: NA | Z59: NA | AA59: NA | AB59: NA | AC59: NA | AD59: =+(AD8-AD12)/AD8 -> 0.49512459 | AE59: =+(AE8-AE12)/AE8 -> 0.49512459 | AF59: =+(AF8-AF12)/AF8 -> 0.54268114 | AG59: =+(AG8-AG12)/AG8 -> 0.45592528 | AH59: =+(AH8-AH12)/AH8 -> 0.48297977 | AI59: =+(AI8-AI12)/AI8 -> 0.48738872 | AJ59: =+(AJ8-AJ12)/AJ8 -> 0.50015236 | AK59: =+(AK8-AK12)/AK8 -> 0.51291272 | ... AT59: =+(AT8-AT12)/AT8 -> 0.38117479
A60: Gross Profit - Biopharma Revenue | B60: NA | C60: NA | D60: NA | E60: NA | F60: NA | G60: NA | H60: NA | I60: NA | J60: NA | K60: NA | L60: NA | M60: NA | N60: NA | O60: NA | P60: NA | Q60: NA | R60: NA | S60: NA | T60: NA | U60: NA | V60: NA | W60: NA | X60: NA | Y60: NA | Z60: NA | AA60: =+(AA9-AA13)/AA9 -> 1 | AB60: =+(AB9-AB13)/AB9 -> 1 | AC60: =+(AC9-AC13)/AC9 -> 1 | AD60: =+(AD9-AD13)/AD9 -> 1 | AE60: =+(AE9-AE13)/AE9 -> 1 | AF60: =+(AF9-AF13)/AF9 -> 0.83933518 | AG60: =+(AG9-AG13)/AG9 -> 0.93331569 | AH60: =+(AH9-AH13)/AH9 -> 0.75242718 | ... AT60: =+(AT9-AT13)/AT9 -> 0.45680456
A61: Gross Profit | B61: =+B15/B10 -> 0.51752274 | C61: =+C15/C10 -> 0.54292958 | D61: =+D15/D10 -> 0.57633665 | E61: =+E15/E10 -> 0.60119682 | F61: =+F15/F10 -> 0.56517413 | G61: =+G15/G10 -> 0.59297557 | H61: =+H15/H10 -> 0.56844138 | I61: =+I15/I10 -> 0.54454803 | ... BI61: =+BI15/BI10 -> 0.72941825 | BJ61: 0.725 | BK61: 0.725 | BL61: 0.73 | BM61: 0.735 | BN61: =+BN15/BN10 -> 0.72892435 | BO61: 0.725 | BP61: 0.725 | BQ61: 0.73 | BR61: 0.735 | BS61: =+BS15/BS10 -> 0.7289255
A62: Research & Development | B62: =B16/B$10 -> 0.28437667 | C62: =C16/C$10 -> 0.25849948 | D62: =D16/D$10 -> 0.22697703 | E62: =E16/E$10 -> 0.26248053 | F62: =F16/F$10 -> 0.25671642 | G62: =G16/G$10 -> 0.24844001 | H62: =H16/H$10 -> 0.26058112 | I62: =I16/I$10 -> 0.28885286 | ... BI62: =BI16/BI$10 -> 0.1216216 | BJ62: 0.132 | BK62: 0.133 | BL62: 0.132 | BM62: 0.123 | BN62: =BN16/BN$10 -> 0.12986292 | BO62: 0.131 | BP62: 0.132 | BQ62: 0.131 | BR62: 0.122 | BS62: =BS16/BS$10 -> 0.12886324
A63: Selling & Marketing | B63: =B17/B$10 -> 0.5799893 | C63: =C17/C$10 -> 0.58787599 | D63: =D17/D$10 -> 0.56241106 | E63: =E17/E$10 -> 0.57070252 | F63: =F17/F$10 -> 0.57428646 | G63: =G17/G$10 -> 0.50098057 | H63: =H17/H$10 -> 0.58254955 | I63: =I17/I$10 -> 0.49031212 | ... BI63: =BI17/BI$10 -> 0.17760396 | BJ63: 0.185 | BK63: 0.181 | BL63: 0.186 | BM63: 0.19 | BN63: =BN17/BN$10 -> 0.18556163 | BO63: 0.183 | BP63: 0.179 | BQ63: 0.184 | BR63: 0.188 | BS63: =BS17/BS$10 -> 0.18356185
A64: General & Administrative | B64: =B18/B$10 -> 0.53263777 | C64: =C18/C$10 -> 0.45269102 | D64: =D18/D$10 -> 0.58091075 | E64: =E18/E$10 -> 0.42864169 | F64: =F18/F$10 -> 0.49368945 | G64: =G18/G$10 -> 0.51684792 | H64: =H18/H$10 -> 0.46489755 | I64: =I18/I$10 -> 0.46436968 | ... BI64: =BI18/BI$10 -> 0.17371724 | BJ64: 0.18 | BK64: 0.176 | BL64: 0.176 | BM64: 0.175 | BN64: =BN18/BN$10 -> 0.17663728 | BO64: 0.178 | BP64: 0.174 | BQ64: 0.174 | BR64: 0.173 | BS64: =BS18/BS$10 -> 0.17463635
A65: Total Operating Expenses | B65: =B19/B$10 -> 1.3970037 | C65: =C19/C$10 -> 1.2990665 | D65: =D19/D$10 -> 1.3702988 | E65: =E19/E$10 -> 1.2618247 | F65: =F19/F$10 -> 1.3246923 | G65: =G19/G$10 -> 1.2662685 | H65: =H19/H$10 -> 1.3080282 | I65: =I19/I$10 -> 1.2435347 | ... BS65: =BS19/BS$10 -> 0.48706144
A66: Operating Income | B66: =B20/B$10 -> -0.87948101 | C66: =C20/C$10 -> -0.75613691 | D66: =D20/D$10 -> -0.79396219 | E66: =E20/E$10 -> -0.66062792 | F66: =F20/F$10 -> -0.7595182 | G66: =G20/G$10 -> -0.67329292 | H66: =H20/H$10 -> -0.73958683 | I66: =I20/I$10 -> -0.69898662 | ... BS66: =BS20/BS$10 -> 0.24186406
A67: Pretax Income | B67: =B23/B$10 -> -0.89272338 | C67: =C23/C$10 -> -0.76697015 | D67: =D23/D$10 -> -0.80321203 | E67: =E23/E$10 -> -0.66743176 | F67: =F23/F$10 -> -0.76912804 | G67: =G23/G$10 -> -0.67837404 | H67: =H23/H$10 -> -0.74479342 | I67: =I23/I$10 -> -0.70360762 | ... BS67: =BS23/BS$10 -> 0.24248999
A68: Adjusted EBITDA | B68: =B50/B$10 -> -0.87948101 | C68: =C50/C$10 -> -0.75613691 | D68: =D50/D$10 -> -0.79396219 | E68: =E50/E$10 -> -0.66062792 | F68: =F50/F$10 -> -0.7595182 | G68: =G50/G$10 -> -0.67329292 | H68: =H50/H$10 -> -0.76200873 | I68: =I50/I$10 -> -0.72055128 | ... BS68: =BS50/BS$10 -> 0.25438271
A69: Net Income | B69: =B26/B$10 -> -0.89272338 | C69: =C26/C$10 -> -0.76697015 | D69: =D26/D$10 -> -0.80321203 | E69: =E26/E$10 -> -0.66743176 | F69: =F26/F$10 -> -0.76912804 | G69: =G26/G$10 -> -0.67837404 | H69: =H26/H$10 -> -0.74479342 | I69: =I26/I$10 -> -0.70360762 | ... BS69: =BS26/BS$10 -> 0.23036549
A71: Yr/Yr Changes
A72: Testing Revenue | B72: NA | C72: NA | D72: NA | E72: NA | F72: NA | G72: =IFERROR(G7/B7-1,"NA") -> 0.50053505 | H72: =IFERROR(H7/C7-1,"NA") -> 0.37236372 | I72: =IFERROR(I7/D7-1,"NA") -> 0.25381175 | J72: =IFERROR(J7/E7-1,"NA") -> 0.15107796 | K72: =IFERROR(K7/F7-1,"NA") -> 0.29622938 | L72: =IFERROR(L7/G7-1,"NA") -> 0.20788019 | M72: =IFERROR(M7/H7-1,"NA") -> 0.2323648 | N72: =IFERROR(N7/I7-1,"NA") -> 0.50814755 | ... BS72: =IFERROR(BS7/BN7-1,"NA") -> 0.10980687
A73: Product Revenue | B73: NA | C73: NA | D73: NA | E73: NA | F73: NA | G73: =IFERROR(G8/B8-1,"NA") -> NA | H73: =IFERROR(H8/C8-1,"NA") -> NA | I73: =IFERROR(I8/D8-1,"NA") -> NA | J73: =IFERROR(J8/E8-1,"NA") -> NA | K73: =IFERROR(K8/F8-1,"NA") -> NA | L73: =IFERROR(L8/G8-1,"NA") -> NA | M73: =IFERROR(M8/H8-1,"NA") -> NA | N73: =IFERROR(N8/I8-1,"NA") -> NA | ... BS73: =IFERROR(BS8/BN8-1,"NA") -> 0.02
A74: Biopharma Revenue | B74: NA | C74: NA | D74: NA | E74: NA | F74: NA | G74: =IFERROR(G9/B9-1,"NA") -> NA | H74: =IFERROR(H9/C9-1,"NA") -> NA | I74: =IFERROR(I9/D9-1,"NA") -> NA | J74: =IFERROR(J9/E9-1,"NA") -> NA | K74: =IFERROR(K9/F9-1,"NA") -> NA | L74: =IFERROR(L9/G9-1,"NA") -> NA | M74: =IFERROR(M9/H9-1,"NA") -> NA | N74: =IFERROR(N9/I9-1,"NA") -> NA | ... BS74: =IFERROR(BS9/BN9-1,"NA") -> NA
A75: Total Revenue | B75: NA | C75: NA | D75: NA | E75: NA | F75: NA | G75: =IFERROR(G10/B10-1,"NA") -> 0.50053505 | H75: =IFERROR(H10/C10-1,"NA") -> 0.37236372 | I75: =IFERROR(I10/D10-1,"NA") -> 0.25381175 | J75: =IFERROR(J10/E10-1,"NA") -> 0.15107796 | K75: =IFERROR(K10/F10-1,"NA") -> 0.29622938 | L75: =IFERROR(L10/G10-1,"NA") -> 0.20788019 | M75: =IFERROR(M10/H10-1,"NA") -> 0.2323648 | N75: =IFERROR(N10/I10-1,"NA") -> 0.50814755 | ... BS75: =IFERROR(BS10/BN10-1,"NA") -> 0.10757615
A76: Gross Profit | B76: NA | C76: NA | D76: NA | E76: NA | F76: NA | G76: =IFERROR(G15/B15-1,"NA") -> 0.71930731 | H76: =IFERROR(H15/C15-1,"NA") -> 0.43684993 | I76: =IFERROR(I15/D15-1,"NA") -> 0.18465608 | J76: =IFERROR(J15/E15-1,"NA") -> 0.072675211 | K76: =IFERROR(K15/F15-1,"NA") -> 0.29748888 | L76: =IFERROR(L15/G15-1,"NA") -> 0.09305472 | M76: =IFERROR(M15/H15-1,"NA") -> 0.23711036 | N76: =IFERROR(N15/I15-1,"NA") -> 0.82164657 | ... BS76: =IFERROR(BS15/BN15-1,"NA") -> 0.1075779
A77: Research & Development | B77: NA | C77: NA | D77: NA | E77: NA | F77: NA | G77: =IFERROR(G16/B16-1,"NA") -> 0.31091251 | H77: =IFERROR(H16/C16-1,"NA") -> 0.38341507 | I77: =IFERROR(I16/D16-1,"NA") -> 0.59561129 | J77: =IFERROR(J16/E16-1,"NA") -> 0.044034978 | K77: =IFERROR(K16/F16-1,"NA") -> 0.30518156 | L77: =IFERROR(L16/G16-1,"NA") -> 0.2418371 | M77: =IFERROR(M16/H16-1,"NA") -> 0.37512085 | N77: =IFERROR(N16/I16-1,"NA") -> 0.12433343 | ... BS77: =IFERROR(BS16/BN16-1,"NA") -> 0.099050093
A78: Selling & Marketing | B78: NA | C78: NA | D78: NA | E78: NA | F78: NA | G78: =IFERROR(G17/B17-1,"NA") -> 0.29612546 | H78: =IFERROR(H17/C17-1,"NA") -> 0.35992943 | I78: =IFERROR(I17/D17-1,"NA") -> 0.093077896 | J78: =IFERROR(J17/E17-1,"NA") -> -0.039500144 | K78: =IFERROR(K17/F17-1,"NA") -> 0.1532008 | L78: =IFERROR(L17/G17-1,"NA") -> 0.25729537 | M78: =IFERROR(M17/H17-1,"NA") -> 0.19114891 | N78: =IFERROR(N17/I17-1,"NA") -> 0.17179233 | ... BS78: =IFERROR(BS17/BN17-1,"NA") -> 0.095639917
A79: General & Administrative | B79: NA | C79: NA | D79: NA | E79: NA | F79: NA | G79: =IFERROR(G18/B18-1,"NA") -> 0.45605224 | H79: =IFERROR(H18/C18-1,"NA") -> 0.40936864 | I79: =IFERROR(I18/D18-1,"NA") -> 0.0022747157 | J79: =IFERROR(J18/E18-1,"NA") -> 0.055842417 | K79: =IFERROR(K18/F18-1,"NA") -> 0.19778296 | L79: =IFERROR(L18/G18-1,"NA") -> 0.074163505 | M79: =IFERROR(M18/H18-1,"NA") -> 0.096640173 | N79: =IFERROR(N18/I18-1,"NA") -> 0.0061103352 | ... BS79: =IFERROR(BS18/BN18-1,"NA") -> 0.095029635
A80: Total Operating Expenses | B80: NA | C80: NA | D80: NA | E80: NA | F80: NA | G80: =IFERROR(G19/B19-1,"NA") -> 0.36011107 | H80: =IFERROR(H19/C19-1,"NA") -> 0.38183109 | I80: =IFERROR(I19/D19-1,"NA") -> 0.1378236 | J80: =IFERROR(J19/E19-1,"NA") -> 0.010264406 | K80: =IFERROR(K19/F19-1,"NA") -> 0.19926863 | L80: =IFERROR(L19/G19-1,"NA") -> 0.17951426 | M80: =IFERROR(M19/H19-1,"NA") -> 0.19420904 | N80: =IFERROR(N19/I19-1,"NA") -> 0.098898233 | ... BS80: =IFERROR(BS19/BN19-1,"NA") -> 0.096320841
A81: Operating Income | B81: NA | C81: NA | D81: NA | E81: NA | F81: NA | G81: =IFERROR(G20/B20-1,"NA") -> 0.14874525 | H81: =IFERROR(H20/C20-1,"NA") -> 0.34232586 | I81: =IFERROR(I20/D20-1,"NA") -> 0.10382793 | J81: =IFERROR(J20/E20-1,"NA") -> -0.046531828 | K81: =IFERROR(K20/F20-1,"NA") -> 0.12618079 | L81: =IFERROR(L20/G20-1,"NA") -> 0.25566 | M81: =IFERROR(M20/H20-1,"NA") -> 0.16123538 | N81: =IFERROR(N20/I20-1,"NA") -> -0.46416145 | ... AU81: =IFERROR(AU20/AP20-1,"NA") -> -2.1251036 | AV81: NM | AW81: NM | AX81: =IFERROR(AX20/AS20-1,"NA") -> 3.7092784 | AY81: =IFERROR(AY20/AT20-1,"NA") -> -8.7548027 | AZ81: =IFERROR(AZ20/AU20-1,"NA") -> 1.3873343 | BA81: =IFERROR(BA20/AV20-1,"NA") -> 1.3717161 | BB81: =IFERROR(BB20/AW20-1,"NA") -> 1.211041 | BC81: =IFERROR(BC20/AX20-1,"NA") -> 1.1270578 | BD81: =IFERROR(BD20/AY20-1,"NA") -> 1.2514051 | BE81: =IFERROR(BE20/AZ20-1,"NA") -> 0.70535163 | ... BS81: =IFERROR(BS20/BN20-1,"NA") -> 0.13096347
A82: Pretax Income | B82: NA | C82: NA | D82: NA | E82: NA | F82: NA | G82: =IFERROR(G23/B23-1,"NA") -> 0.14024573 | H82: =IFERROR(H23/C23-1,"NA") -> 0.33268219 | I82: =IFERROR(I23/D23-1,"NA") -> 0.098329537 | J82: =IFERROR(J23/E23-1,"NA") -> -0.048636699 | K82: =IFERROR(K23/F23-1,"NA") -> 0.12021244 | L82: =IFERROR(L23/G23-1,"NA") -> 0.28883049 | M82: =IFERROR(M23/H23-1,"NA") -> 0.23756906 | N82: =IFERROR(N23/I23-1,"NA") -> -0.3811499 | ... AU82: =IFERROR(AU23/AP23-1,"NA") -> -2.9384273 | AV82: NM | AW82: NM | AX82: =IFERROR(AX23/AS23-1,"NA") -> 2.736376 | AY82: NM | AZ82: =IFERROR(AZ23/AU23-1,"NA") -> 1.0048476 | BA82: =IFERROR(BA23/AV23-1,"NA") -> 1.7288908 | BB82: =IFERROR(BB23/AW23-1,"NA") -> 1.1121368 | BC82: =IFERROR(BC23/AX23-1,"NA") -> 0.54658159 | BD82: =IFERROR(BD23/AY23-1,"NA") -> 1.0165868 | BE82: =IFERROR(BE23/AZ23-1,"NA") -> 0.62484093 | BF82: =IFERROR(BF23/BA23-1,"NA") -> 0.46138244 | BG82: =IFERROR(BG23/BB23-1,"NA") -> 0.43587447 | ... BS82: =IFERROR(BS23/BN23-1,"NA") -> 0.13058128
A83: Adjusted EBITDA | B83: NA | C83: NA | D83: NA | E83: NA | F83: NA | G83: =IFERROR(G50/B50-1,"NA") -> 0.14874525 | H83: =IFERROR(H50/C50-1,"NA") -> 0.38302088 | I83: =IFERROR(I50/D50-1,"NA") -> 0.13788247 | J83: =IFERROR(J50/E50-1,"NA") -> -0.013401166 | K83: =IFERROR(K50/F50-1,"NA") -> 0.15376129 | L83: =IFERROR(L50/G50-1,"NA") -> 0.29101019 | M83: =IFERROR(M50/H50-1,"NA") -> 0.15649107 | N83: =IFERROR(N50/I50-1,"NA") -> -0.45027003 | ... AE83: =IFERROR(AE50/Z50-1,"NA") -> -0.90101174 | AF83: NM | AG83: NM | AH83: =IFERROR(AH50/AC50-1,"NA") -> -0.45065076 | AI83: =IFERROR(AI50/AD50-1,"NA") -> -0.4123107 | AJ83: =IFERROR(AJ50/AE50-1,"NA") -> 9.9255928 | AK83: =IFERROR(AK50/AF50-1,"NA") -> -0.37289495 | AL83: =IFERROR(AL50/AG50-1,"NA") -> -1.1900942 | AM83: =IFERROR(AM50/AH50-1,"NA") -> -3.6396841 | AN83: =IFERROR(AN50/AI50-1,"NA") -> -1.333749 | AO83: =IFERROR(AO50/AJ50-1,"NA") -> -0.6489298 | ... BS83: =IFERROR(BS50/BN50-1,"NA") -> 0.12372114
A84: Net Income | B84: NA | C84: NA | D84: NA | E84: NA | F84: NA | G84: =IFERROR(G26/B26-1,"NA") -> 0.14024573 | H84: =IFERROR(H26/C26-1,"NA") -> 0.33268219 | I84: =IFERROR(I26/D26-1,"NA") -> 0.098329537 | J84: =IFERROR(J26/E26-1,"NA") -> -0.048636699 | K84: =IFERROR(K26/F26-1,"NA") -> 0.12021244 | L84: =IFERROR(L26/G26-1,"NA") -> 0.28883049 | M84: =IFERROR(M26/H26-1,"NA") -> 0.23756906 | N84: =IFERROR(N26/I26-1,"NA") -> -0.3811499 | ... AU84: =IFERROR(AU26/AP26-1,"NA") -> -2.7973274 | AV84: NM | AW84: NM | AX84: =IFERROR(AX26/AS26-1,"NA") -> 2.8107973 | AY84: NM | AZ84: =IFERROR(AZ26/AU26-1,"NA") -> 1.0140438 | BA84: =IFERROR(BA26/AV26-1,"NA") -> 1.7410401 | BB84: =IFERROR(BB26/AW26-1,"NA") -> 1.1221569 | BC84: =IFERROR(BC26/AX26-1,"NA") -> 0.89866859 | BD84: =IFERROR(BD26/AY26-1,"NA") -> 1.147363 | BE84: =IFERROR(BE26/AZ26-1,"NA") -> 0.67322942 | BF84: =IFERROR(BF26/BA26-1,"NA") -> 0.49348374 | BG84: =IFERROR(BG26/BB26-1,"NA") -> 0.57357641 | ... BS84: =IFERROR(BS26/BN26-1,"NA") -> 0.13058128
A85: Adjusted EPS | B85: NA | C85: NA | D85: NA | E85: NA | F85: NA | G85: =IFERROR(#REF!/#REF!-1,"NA") -> NA | H85: =IFERROR(#REF!/#REF!-1,"NA") -> NA | I85: =IFERROR(#REF!/#REF!-1,"NA") -> NA | J85: =IFERROR(#REF!/#REF!-1,"NA") -> NA | K85: =IFERROR(#REF!/#REF!-1,"NA") -> NA | L85: =IFERROR(#REF!/#REF!-1,"NA") -> NA | M85: =IFERROR(#REF!/#REF!-1,"NA") -> NA | N85: =IFERROR(#REF!/#REF!-1,"NA") -> NA | ... AY85: =IFERROR(#REF!/#REF!-1,"NA") -> NA | AZ85: =IFERROR(AZ35/AU35-1,"NA") -> 0.95128691 | BA85: =IFERROR(BA35/AV35-1,"NA") -> 1.6180334 | BB85: =IFERROR(BB35/AW35-1,"NA") -> 1.0049465 | BC85: =IFERROR(BC35/AX35-1,"NA") -> 0.76367603 | BD85: =IFERROR(BD35/AY35-1,"NA") -> 1.038123 | BE85: =IFERROR(BE35/AZ35-1,"NA") -> 0.58588633 | BF85: =IFERROR(BF35/BA35-1,"NA") -> 0.45051038 | BG85: =IFERROR(BG35/BB35-1,"NA") -> 0.54934735 | ... BS85: =IFERROR(BS35/BN35-1,"NA") -> 0.10846129
A86: Revenue Seasonality | B86: =B15/F15 -> 0.17925315 | C86: =C15/F15 -> 0.21826353 | D86: =D15/F15 -> 0.26269459 | E86: =E15/F15 -> 0.33978873 | G86: =G15/K15 -> 0.23752901 | H86: =H15/K15 -> 0.24170684 | I86: =I15/K15 -> 0.23985003 | J86: =J15/K15 -> 0.28091412 | L86: =L15/P15 -> 0.18350453 | M86: =M15/P15 -> 0.2113419 | N86: =N15/P15 -> 0.30881054 | O86: =O15/P15 -> 0.29634303 | Q86: =Q15/U15 -> 0.23161479 | R86: =R15/U15 -> 0.26157503 | S86: =S15/U15 -> 0.23652818 | T86: =T15/U15 -> 0.27028201 | V86: =V15/Z15 -> 0.20658408 | W86: =W15/Z15 -> 0.24613949 | X86: =X15/Z15 -> 0.25801799 | Y86: =Y15/Z15 -> 0.28925844 | AA86: =AA15/AE15 -> 0.25071279 | AB86: =AB15/AE15 -> 0.25480465 | AC86: =AC15/AE15 -> 0.26076946 | AD86: =AD15/AE15 -> 0.23371309 | AF86: =AF15/AJ15 -> 0.25892162 | AG86: =AG15/AJ15 -> 0.16921261 | AH86: =AH15/AJ15 -> 0.26908813 | AI86: =AI15/AJ15 -> 0.30277763 | AK86: =AK15/AO15 -> 0.16745455 | AL86: =AL15/AO15 -> 0.25933404 | AM86: =AM15/AO15 -> 0.26687294 | AN86: =AN15/AO15 -> 0.30633846 | AP86: =AP15/AT15 -> 0.226429 | AQ86: =AQ15/AT15 -> 0.24532878 | AR86: =AR15/AT15 -> 0.25436424 | AS86: =AS15/AT15 -> 0.27387799 | AU86: =AU15/AY15 -> 0.22654351 | AV86: =AV15/AY15 -> 0.24444578 | AW86: =AW15/AY15 -> 0.25191939 | AX86: =AX15/AY15 -> 0.27709133 | AZ86: =AZ15/BD15 -> 0.21127781 | BA86: =BA15/BD15 -> 0.2609122 | BB86: =BB15/BD15 -> 0.26439846 | BC86: =BC15/BD15 -> 0.26341154 | BE86: =BE15/BI15 -> 0.21900773 | BF86: =BF15/BI15 -> 0.24674522 | BG86: =BG15/BI15 -> 0.25435627 | BH86: =BH15/BI15 -> 0.27989078 | BJ86: =BJ15/BN15 -> 0.22455525 | BK86: =BK15/BN15 -> 0.25379089 | BL86: =BL15/BN15 -> 0.25363316 | BM86: =BM15/BN15 -> 0.2680207 | BO86: =BO15/BS15 -> 0.22431414 | BP86: =BP15/BS15 -> 0.25376346 | BQ86: =BQ15/BS15 -> 0.25394138 | BR86: =BR15/BS15 -> 0.26798102
A87: Earnings Seasonality | B87: =B42/F42 -> 0.23249106 | C87: =C42/F42 -> 0.23085925 | D87: =D42/F42 -> 0.26890718 | E87: =E42/F42 -> 0.26649297 | G87: =G42/K42 -> 0.25989313 | H87: =H42/K42 -> 0.26997581 | I87: =I42/K42 -> 0.24910839 | J87: =J42/K42 -> 0.22289517 | L87: =L42/P42 -> 0.33298346 | M87: =M42/P42 -> 0.37102722 | N87: =N42/P42 -> 0.18564596 | O87: =O42/P42 -> 0.127678 | Q87: =Q42/U42 -> 0.26583599 | R87: =R42/U42 -> 0.23576134 | S87: =S42/U42 -> 0.22722356 | T87: =T42/U42 -> 0.27116114 | V87: =V42/Z42 -> 0.43102363 | W87: =W42/Z42 -> 0.29308734 | X87: =X42/Z42 -> 0.18626361 | Y87: =Y42/Z42 -> 0.1227053 | AA87: =AA42/AE42 -> 0.17025175 | AB87: =AB42/AE42 -> 0.20003209 | AC87: =AC42/AE42 -> 0.054932161 | AD87: =AD42/AE42 -> 0.55690032 | AF87: =AF42/AJ42 -> 0.35872788 | AG87: =AG42/AJ42 -> 0.33475021 | AH87: =AH42/AJ42 -> 0.11461174 | AI87: =AI42/AJ42 -> 0.21135722 | AK87: =AK42/AO42 -> 0.59373311 | AL87: =AL42/AO42 -> 0.12058237 | AM87: =AM42/AO42 -> 0.18194346 | AN87: =AN42/AO42 -> 0.13305267 | AP87: =AP42/AT42 -> 0.3967626 | AQ87: =AQ42/AT42 -> 0.26062212 | AR87: =AR42/AT42 -> 0.23790439 | AS87: =AS42/AT42 -> 0.10595199 | AU87: =AU35/AY35 -> 0.16862557 | AV87: =AV35/AY35 -> 0.19772273 | AW87: =AW35/AY35 -> 0.28194545 | AX87: =AX35/AY35 -> 0.35059744 | AZ87: =AZ35/BD35 -> 0.16144112 | BA87: =BA35/BD35 -> 0.25398109 | BB87: =BB35/BD35 -> 0.27735594 | BC87: =BC35/BD35 -> 0.30338713 | BE87: =BE35/BI35 -> 0.17118922 | BF87: =BF35/BI35 -> 0.24632722 | BG87: =BG35/BI35 -> 0.28732702 | BH87: =BH35/BI35 -> 0.29455772 | BJ87: =BJ42/BN42 -> 0.1884763 | BK87: =BK42/BN42 -> 0.25672294 | BL87: =BL42/BN42 -> 0.25386809 | BM87: =BM42/BN42 -> 0.30010444 | BO87: =BO42/BS42 -> 0.19448311 | BP87: =BP42/BS42 -> 0.25614238 | BQ87: =BQ42/BS42 -> 0.25400873 | BR87: =BR42/BS42 -> 0.29463618
A88: Source: Company reports and Needham & Company estimates

Sheet Balance Sheet
A1: Veracyte Inc. | BR1: Needham & Company, LLC
A2: Quarterly Balance Sheet | BR2: Michael Matson ● (617) 457-0949
A3: ($ In Millions)
B5: ='Revenue Model'!B5 -> 41699 | C5: ='Revenue Model'!C5 -> 41791 | D5: ='Revenue Model'!D5 -> 41883 | E5: ='Revenue Model'!E5 -> 41974 | G5: ='Revenue Model'!G5 -> 42064 | H5: ='Revenue Model'!H5 -> 42156 | I5: ='Revenue Model'!I5 -> 42248 | J5: ='Revenue Model'!J5 -> 42339 | L5: ='Revenue Model'!L5 -> 42430 | M5: ='Revenue Model'!M5 -> 42522 | N5: ='Revenue Model'!N5 -> 42614 | O5: ='Revenue Model'!O5 -> 42705 | Q5: ='Revenue Model'!Q5 -> 42795 | R5: ='Revenue Model'!R5 -> 42887 | S5: ='Revenue Model'!S5 -> 42979 | T5: ='Revenue Model'!T5 -> 43070 | V5: ='Revenue Model'!V5 -> 43160 | W5: ='Revenue Model'!W5 -> 43252 | X5: ='Revenue Model'!X5 -> 43344 | Y5: ='Revenue Model'!Y5 -> 43435 | AA5: ='Revenue Model'!AA5 -> 43525 | AB5: ='Revenue Model'!AB5 -> 43617 | AC5: ='Revenue Model'!AC5 -> 43709 | AD5: ='Revenue Model'!AD5 -> 43800 | AF5: ='Revenue Model'!AF5 -> 43891 | AG5: ='Revenue Model'!AG5 -> 43983 | AH5: ='Revenue Model'!AH5 -> 44075 | AI5: ='Revenue Model'!AI5 -> 44166 | AK5: ='Revenue Model'!AK5 -> 44256 | AL5: ='Revenue Model'!AL5 -> 44348 | AM5: ='Revenue Model'!AM5 -> 44440 | AN5: ='Revenue Model'!AN5 -> 44531 | AP5: ='Revenue Model'!AP5 -> 44621 | AQ5: ='Revenue Model'!AQ5 -> 44713 | AR5: ='Revenue Model'!AR5 -> 44805 | AS5: ='Revenue Model'!AS5 -> 44896 | AU5: ='Revenue Model'!AU5 -> 44986 | AV5: ='Revenue Model'!AV5 -> 45078 | AW5: ='Revenue Model'!AW5 -> 45170 | AX5: ='Revenue Model'!AX5 -> 45261 | AZ5: ='Revenue Model'!AZ5 -> 45352 | BA5: ='Revenue Model'!BA5 -> 45444 | BB5: ='Revenue Model'!BB5 -> 45536 | BC5: ='Revenue Model'!BC5 -> 45627 | BE5: ='Revenue Model'!BE5 -> 45717 | BF5: ='Revenue Model'!BF5 -> 45809 | BG5: ='Revenue Model'!BG5 -> 45901 | BH5: ='Revenue Model'!BH5 -> 45992 | BJ5: ='Revenue Model'!BJ5 -> 46082 | BK5: ='Revenue Model'!BK5 -> 46174 | BL5: ='Revenue Model'!BL5 -> 46266 | BM5: ='Revenue Model'!BM5 -> 46357 | BO5: ='Revenue Model'!BO5 -> 46447 | BP5: ='Revenue Model'!BP5 -> 46539 | BQ5: ='Revenue Model'!BQ5 -> 46631 | BR5: ='Revenue Model'!BR5 -> 46722
A6: Assets | B6: ='Revenue Model'!B6 -> Q114A | C6: ='Revenue Model'!C6 -> Q214A | D6: ='Revenue Model'!D6 -> Q314A | E6: ='Revenue Model'!E6 -> Q414A | G6: ='Revenue Model'!G6 -> Q115A | H6: ='Revenue Model'!H6 -> Q215A | I6: ='Revenue Model'!I6 -> Q315A | J6: ='Revenue Model'!J6 -> Q415A | L6: ='Revenue Model'!L6 -> Q116A | M6: ='Revenue Model'!M6 -> Q216A | N6: ='Revenue Model'!N6 -> Q316A | O6: ='Revenue Model'!O6 -> Q416A | Q6: ='Revenue Model'!Q6 -> Q117A | R6: ='Revenue Model'!R6 -> Q217A | S6: ='Revenue Model'!S6 -> Q317A | T6: ='Revenue Model'!T6 -> Q417A | V6: ='Revenue Model'!V6 -> Q118A | W6: ='Revenue Model'!W6 -> Q218A | X6: ='Revenue Model'!X6 -> Q318A | Y6: ='Revenue Model'!Y6 -> Q418A | AA6: ='Revenue Model'!AA6 -> Q119A | AB6: ='Revenue Model'!AB6 -> Q219A | AC6: ='Revenue Model'!AC6 -> Q319A | AD6: ='Revenue Model'!AD6 -> Q419A | AF6: ='Revenue Model'!AF6 -> Q120A | AG6: ='Revenue Model'!AG6 -> Q220A | AH6: ='Revenue Model'!AH6 -> Q320A | AI6: ='Revenue Model'!AI6 -> Q420A | AK6: ='Revenue Model'!AK6 -> Q121A | AL6: ='Revenue Model'!AL6 -> Q221A | AM6: ='Revenue Model'!AM6 -> Q321A | AN6: ='Revenue Model'!AN6 -> Q421A | AP6: ='Revenue Model'!AP6 -> Q122A | AQ6: ='Revenue Model'!AQ6 -> Q222A | AR6: ='Revenue Model'!AR6 -> Q322A | AS6: ='Revenue Model'!AS6 -> Q422A | AU6: ='Revenue Model'!AU6 -> Q123A | AV6: ='Revenue Model'!AV6 -> Q223A | AW6: ='Revenue Model'!AW6 -> Q323A | AX6: ='Revenue Model'!AX6 -> Q423A | AZ6: ='Revenue Model'!AZ6 -> Q124A | BA6: ='Revenue Model'!BA6 -> Q224A | BB6: ='Revenue Model'!BB6 -> Q324A | BC6: ='Revenue Model'!BC6 -> Q424A | BE6: ='Revenue Model'!BE6 -> Q125A | BF6: ='Revenue Model'!BF6 -> Q225A | BG6: ='Revenue Model'!BG6 -> Q325A | BH6: ='Revenue Model'!BH6 -> Q425A | BJ6: ='Revenue Model'!BJ6 -> Q126E | BK6: ='Revenue Model'!BK6 -> Q226E | BL6: ='Revenue Model'!BL6 -> Q326E | BM6: ='Revenue Model'!BM6 -> Q426E | BO6: ='Revenue Model'!BO6 -> Q127E | BP6: ='Revenue Model'!BP6 -> Q227E | BQ6: ='Revenue Model'!BQ6 -> Q327E | BR6: ='Revenue Model'!BR6 -> Q427E
A7: Cash & Equivalents | O7: 59.219 | Q7: 51.506 | R7: 46.463 | S7: 41.195 | T7: 33.891 | V7: 27.152 | W7: 23.758 | X7: 77.846 | Y7: 77.995 | AA7: 67.841 | AB7: 192.647 | AC7: 195.662 | AD7: 159.317 | AF7: 153.132 | AG7: 147.45 | AH7: 345.08 | AI7: 349.364 | AK7: 324.062 | AL7: 327.545 | AM7: 164.029 | AN7: 173.197 | AP7: 163.615 | AQ7: 153.447 | AR7: 170.112 | AS7: 154.247 | AU7: 177.89 | AV7: 191.142 | AW7: 202.463 | AX7: 216.454 | AZ7: 209.188 | BA7: 235.915 | BB7: 274.079 | BC7: =239.087+50.354 -> 289.441 | BE7: =186.12+101.235 -> 287.355 | BF7: =219.499+101.22 -> 320.719 | BG7: =315.573+50.855 -> 366.428 | BH7: =+'Cash Flow'!BH52-BH17 -> 375.45808 | BJ7: =+'Cash Flow'!BJ52-BJ17 -> 403.51263 | BK7: =+'Cash Flow'!BK52-BK17 -> 449.45859 | BL7: =+'Cash Flow'!BL52-BL17 -> 491.92662 | BM7: =+'Cash Flow'!BM52-BM17 -> 540.81016 | BO7: =+'Cash Flow'!BO52-BO17 -> 570.06639 | BP7: =+'Cash Flow'!BP52-BP17 -> 619.63198 | BQ7: =+'Cash Flow'!BQ52-BQ17 -> 665.56226 | BR7: =+'Cash Flow'!BR52-BR17 -> 718.94131
A8: Accounts Receivable | O8: 8.756 | Q8: 9.125 | R8: 11.027 | S8: 11.635 | T8: 12.716 | V8: 13.198 | W8: 13.006 | X8: 12.262 | Y8: 13.168 | AA8: 16.615 | AB8: =19.626-AB9 -> 17.626 | AC8: =23.613-AC9 -> 17.613 | AD8: =19.329-AD9 -> 17.329 | AF8: 19.091 | AG8: =15.306-AG9 -> 13.406 | AH8: =17.629-AH9 -> 16.829 | AI8: =18.461-AI9 -> 16.461 | AK8: 27.877 | AL8: 31.864 | AM8: 40.309 | AN8: 41.461 | AP8: 42.481 | AQ8: 40.448 | AR8: 40.068 | AS8: 44.021 | AU8: 45.489 | AV8: 42.365 | AW8: 39.297 | AX8: 40.378 | AZ8: 46.665 | BA8: 50.304 | BB8: 48.807 | BC8: 46.525 | BE8: 53.781 | BF8: 50.814 | BG8: 47.826 | BH8: =+BH69*('Income Statement'!BH10-'[1]Old Revenue Model'!BH44) -> 84.3816 | BJ8: =+BJ69*('Income Statement'!BJ10-'[1]Old Revenue Model'!BJ44) -> 78.158799 | BK8: =+BK69*('Income Statement'!BK10-'[1]Old Revenue Model'!BK44) -> 88.334571 | BL8: =+BL69*('Income Statement'!BL10-'[1]Old Revenue Model'!BL44) -> 87.675016 | BM8: =+BM69*('Income Statement'!BM10-'[1]Old Revenue Model'!BM44) -> 92.018186 | BO8: =+BO69*('Income Statement'!BO10-'[1]Old Revenue Model'!BO44) -> 86.47401 | BP8: =+BP69*('Income Statement'!BP10-'[1]Old Revenue Model'!BP44) -> 97.826841 | BQ8: =+BQ69*('Income Statement'!BQ10-'[1]Old Revenue Model'!BQ44) -> 97.224917 | BR8: =+BR69*('Income Statement'!BR10-'[1]Old Revenue Model'!BR44) -> 101.90222
A9: J&J & Acerto Receivable | O9: 0 | Q9: 0 | R9: 0 | S9: 0 | T9: 0 | V9: 0 | W9: 0 | X9: 0 | Y9: 0 | AA9: 0 | AB9: 2 | AC9: 6 | AD9: 2 | AF9: 0 | AG9: =0.5+1.4 -> 1.9 | AH9: 0.8 | AI9: 2 | AK9: 0 | AL9: =+AK9 -> 0 | AM9: =+AL9 -> 0 | AN9: =+AM9 -> 0 | AP9: 0 | AQ9: =+AP9 -> 0 | AR9: =+AQ9 -> 0 | AS9: =+AR9 -> 0 | AU9: =+AS9 -> 0 | AV9: =+AU9 -> 0 | AW9: =+AV9 -> 0 | AX9: =+AW9 -> 0 | AZ9: =+AX9 -> 0 | BA9: =+AZ9 -> 0 | BB9: =+BA9 -> 0 | BC9: =+BB9 -> 0 | BE9: =+BC9 -> 0 | BF9: =+BE9 -> 0 | BG9: =+BF9 -> 0 | BH9: =+BG9 -> 0 | BJ9: =+BH9 -> 0 | BK9: =+BJ9 -> 0 | BL9: =+BK9 -> 0 | BM9: =+BL9 -> 0 | BO9: =+BM9 -> 0 | BP9: =+BO9 -> 0 | BQ9: =+BP9 -> 0 | BR9: =+BQ9 -> 0
A10: Supplies Inventory | O10: 3.475 | Q10: 3.443 | R10: 3.317 | S10: 3.76 | T10: 5.324 | V10: 4.557 | W10: 3.049 | X10: 3.463 | Y10: 3.402 | AA10: 3.768 | AB10: 5.104 | AC10: 6.608 | AD10: 6.806 | AF10: 6.094 | AG10: 7.041 | AH10: 4.456 | AI10: 4.657 | AK10: 6.308 | AL10: 6.674 | AM10: 9.824 | AN10: 11.225 | AP10: 12.372 | AQ10: 14.6 | AR10: 13.798 | AS10: 14.294 | AU10: 13.306 | AV10: 11.572 | AW10: 15.887 | AX10: 16.128 | AZ10: 18.328 | BA10: 19.258 | BB10: 20.364 | BC10: 21.75 | BE10: 24.254 | BF10: 25.02 | BG10: 20.327 | BH10: =+BG10 -> 20.327 | BJ10: =+BH10 -> 20.327 | BK10: =+BJ10 -> 20.327 | BL10: =+BK10 -> 20.327 | BM10: =+BL10 -> 20.327 | BO10: =+BM10 -> 20.327 | BP10: =+BO10 -> 20.327 | BQ10: =+BP10 -> 20.327 | BR10: =+BQ10 -> 20.327
A11: Prepaid Expenses & Other Current Assets | O11: 2.057 | Q11: 2.101 | R11: 1.933 | S11: 1.617 | T11: 1.997 | V11: 2.142 | W11: 1.822 | X11: 1.803 | Y11: 2.387 | AA11: 2.392 | AB11: 2.573 | AC11: 2.196 | AD11: 2.235 | AF11: 3.045 | AG11: 2.891 | AH11: 3.15 | AI11: 3.197 | AK11: 3.845 | AL11: 5.263 | AM11: 15.146 | AN11: 17.219 | AP11: 20.015 | AQ11: =10.551+15.999 -> 26.55 | AR11: 14.538 | AS11: =24.605+11.469 -> 36.074 | AU11: 14.818 | AV11: 14.401 | AW11: 13.516 | AX11: 12.661 | AZ11: 16.237 | BA11: 15.629 | BB11: 13.604 | BC11: 14.551 | BE11: 17.762 | BF11: 18.128 | BG11: 14.643 | BH11: =BH70*'Income Statement'!BH10 -> 14.0636 | BJ11: =BJ70*'Income Statement'!BJ10 -> 13.026467 | BK11: =BK70*'Income Statement'!BK10 -> 14.722429 | BL11: =BL70*'Income Statement'!BL10 -> 14.612503 | BM11: =BM70*'Income Statement'!BM10 -> 15.336364 | BO11: =BO70*'Income Statement'!BO10 -> 14.412335 | BP11: =BP70*'Income Statement'!BP10 -> 16.304473 | BQ11: =BQ70*'Income Statement'!BQ10 -> 16.204153 | BR11: =BR70*'Income Statement'!BR10 -> 16.983704
A12: Current Assets | O12: =SUM(O7:O11) -> 73.507 | Q12: =SUM(Q7:Q11) -> 66.175 | R12: =SUM(R7:R11) -> 62.74 | S12: =SUM(S7:S11) -> 58.207 | T12: =SUM(T7:T11) -> 53.928 | V12: =SUM(V7:V11) -> 47.049 | W12: =SUM(W7:W11) -> 41.635 | X12: =SUM(X7:X11) -> 95.374 | Y12: =SUM(Y7:Y11) -> 96.952 | AA12: =SUM(AA7:AA11) -> 90.616 | AB12: =SUM(AB7:AB11) -> 219.95 | AC12: =SUM(AC7:AC11) -> 228.079 | AD12: =SUM(AD7:AD11) -> 187.687 | AF12: =SUM(AF7:AF11) -> 181.362 | AG12: =SUM(AG7:AG11) -> 172.688 | AH12: =SUM(AH7:AH11) -> 370.315 | AI12: =SUM(AI7:AI11) -> 375.679 | AK12: =SUM(AK7:AK11) -> 362.092 | AL12: =SUM(AL7:AL11) -> 371.346 | AM12: =SUM(AM7:AM11) -> 229.308 | AN12: =SUM(AN7:AN11) -> 243.102 | AP12: =SUM(AP7:AP11) -> 238.483 | AQ12: =SUM(AQ7:AQ11) -> 235.045 | AR12: =SUM(AR7:AR11) -> 238.516 | AS12: =SUM(AS7:AS11) -> 248.636 | AU12: =SUM(AU7:AU11) -> 251.503 | AV12: =SUM(AV7:AV11) -> 259.48 | AW12: =SUM(AW7:AW11) -> 271.163 | AX12: =SUM(AX7:AX11) -> 285.621 | AZ12: =SUM(AZ7:AZ11) -> 290.418 | BA12: =SUM(BA7:BA11) -> 321.106 | BB12: =SUM(BB7:BB11) -> 356.854 | BC12: =SUM(BC7:BC11) -> 372.267 | BE12: =SUM(BE7:BE11) -> 383.152 | BF12: =SUM(BF7:BF11) -> 414.681 | BG12: =SUM(BG7:BG11) -> 449.224 | BH12: =SUM(BH7:BH11) -> 494.23028 | BJ12: =SUM(BJ7:BJ11) -> 515.0249 | BK12: =SUM(BK7:BK11) -> 572.84259 | BL12: =SUM(BL7:BL11) -> 614.54114 | BM12: =SUM(BM7:BM11) -> 668.49171 | BO12: =SUM(BO7:BO11) -> 691.27973 | BP12: =SUM(BP7:BP11) -> 754.0903 | BQ12: =SUM(BQ7:BQ11) -> 799.31833 | BR12: =SUM(BR7:BR11) -> 858.15423
A13: Property, Plant & Equipment | O13: 11.48 | Q13: 10.657 | R13: 10.093 | S13: 10.281 | T13: 9.688 | V13: 9.215 | W13: 9.035 | X13: 8.939 | Y13: 8.94 | AA13: 8.114 | AB13: 8.15 | AC13: 8.488 | AD13: 8.933 | AF13: 8.788 | AG13: 8.64 | AH13: 8.914 | AI13: 8.99 | AK13: 10.562 | AL13: 11.813 | AM13: 14.868 | AN13: 15.098 | AP13: 16.299 | AQ13: 17.188 | AR13: 17.237 | AS13: 17.702 | AU13: 18.072 | AV13: 18.51 | AW13: 19.288 | AX13: 20.584 | AZ13: 21.566 | BA13: 22.291 | BB13: 21.194 | BC13: 22.953 | BE13: 22.529 | BF13: 18.552 | BG13: 18.9 | BH13: =+BG13-'Cash Flow'!BH32-'Cash Flow'!BH9-'Income Statement'!BH27 -> 22.191 | BJ13: =+BH13-'Cash Flow'!BJ32-'Cash Flow'!BJ9-'Income Statement'!BJ27 -> 23.16 | BK13: =+BJ13-'Cash Flow'!BK32-'Cash Flow'!BK9-'Income Statement'!BK27 -> 23.596 | BL13: =+BK13-'Cash Flow'!BL32-'Cash Flow'!BL9-'Income Statement'!BL27 -> 25.538 | BM13: =+BL13-'Cash Flow'!BM32-'Cash Flow'!BM9-'Income Statement'!BM27 -> 29.079 | BO13: =+BM13-'Cash Flow'!BO32-'Cash Flow'!BO9-'Income Statement'!BO27 -> 31.398 | BP13: =+BO13-'Cash Flow'!BP32-'Cash Flow'!BP9-'Income Statement'!BP27 -> 33.184 | BQ13: =+BP13-'Cash Flow'!BQ32-'Cash Flow'!BQ9-'Income Statement'!BQ27 -> 36.476 | BR13: =+BQ13-'Cash Flow'!BR32-'Cash Flow'!BR9-'Income Statement'!BR27 -> 41.367
A14: Intangible Assets | O14: 14.133 | Q14: 13.867 | R14: 13.6 | S14: 13.333 | T14: 13.067 | V14: 12.8 | W14: 12.533 | X14: 12.267 | Y14: 12 | AA14: 11.733 | AB14: 11.467 | AC14: 11.2 | AD14: 65.019 | AF14: 63.744 | AG14: 62.471 | AH14: 61.197 | AI14: 59.924 | AK14: 159.423 | AL14: 155.7 | AM14: 209.521 | AN14: 202.731 | AP14: 196.228 | AQ14: 184.367 | AR14: 176.542 | AS14: 174.866 | AU14: 170.226 | AV14: 164.744 | AW14: 123.567 | AX14: 88.593 | AZ14: 116.348 | BA14: 112.532 | BB14: 108.873 | BC14: 102.301 | BE14: 99.094 | BF14: 95.806 | BG14: 92.477 | BH14: =+BG14+'Income Statement'!BH27 -> 92.477 | BJ14: =+BH14+'Income Statement'!BJ27 -> 92.477 | BK14: =+BJ14+'Income Statement'!BK27 -> 92.477 | BL14: =+BK14+'Income Statement'!BL27 -> 92.477 | BM14: =+BL14+'Income Statement'!BM27 -> 92.477 | BO14: =+BM14+'Income Statement'!BO27 -> 92.477 | BP14: =+BO14+'Income Statement'!BP27 -> 92.477 | BQ14: =+BP14+'Income Statement'!BQ27 -> 92.477 | BR14: =+BQ14+'Income Statement'!BR27 -> 92.477
A15: Goodwill | O15: 1.057 | Q15: 1.057 | R15: 1.057 | S15: 1.057 | T15: 1.057 | V15: 1.057 | W15: 1.057 | X15: 1.057 | Y15: 1.057 | AA15: 1.057 | AB15: 1.057 | AC15: 1.057 | AD15: 2.725 | AF15: 2.725 | AG15: 2.725 | AH15: 2.725 | AI15: 2.725 | AK15: 474.838 | AL15: 471.764 | AM15: 714.273 | AN15: 707.904 | AP15: 704.368 | AQ15: 690.04 | AR15: 676.885 | AS15: 695.891 | AU15: 699.718 | AV15: 698.92 | AW15: 693.176 | AX15: 702.984 | AZ15: 753.853 | BA15: 752.107 | BB15: 762.117 | BC15: 745.8 | BE15: 754.272 | BF15: 773.255 | BG15: 767.154 | BH15: =+BG15 -> 767.154 | BJ15: =+BH15 -> 767.154 | BK15: =+BJ15 -> 767.154 | BL15: =+BK15 -> 767.154 | BM15: =+BL15 -> 767.154 | BO15: =+BM15 -> 767.154 | BP15: =+BO15 -> 767.154 | BQ15: =+BP15 -> 767.154 | BR15: =+BQ15 -> 767.154
A16: Deferred Tax Asset | Q16: 0 | R16: 0 | S16: 0 | T16: 0 | V16: 0 | W16: 0 | X16: 0 | Y16: 0 | AA16: 0 | AB16: 0 | AC16: 0 | AD16: 0 | AF16: 0 | AG16: 0 | AH16: =+AG16 -> 0 | AI16: =+AH16 -> 0 | AK16: =+AI16 -> 0 | AL16: =+AK16 -> 0 | AM16: =+AL16 -> 0 | AN16: =+AM16 -> 0 | AP16: =+AN16 -> 0 | AQ16: =+AP16 -> 0 | AR16: =+AQ16 -> 0 | AS16: =+AR16 -> 0 | AU16: =+AS16 -> 0 | AV16: =+AU16 -> 0 | AW16: =+AV16 -> 0 | AX16: =+AW16 -> 0 | AZ16: =+AX16 -> 0 | BA16: =+AZ16 -> 0 | BB16: =+BA16 -> 0 | BC16: =+BB16 -> 0 | BE16: =+BC16 -> 0 | BF16: =+BE16 -> 0 | BG16: =+BF16 -> 0 | BH16: =+BG16 -> 0 | BJ16: =+BH16 -> 0 | BK16: =+BJ16 -> 0 | BL16: =+BK16 -> 0 | BM16: =+BL16 -> 0 | BO16: =+BM16 -> 0 | BP16: =+BO16 -> 0 | BQ16: =+BP16 -> 0 | BR16: =+BQ16 -> 0
A17: Restricted Cash | O17: =0.603+0.12 -> 0.723 | Q17: =0.603+0.12 -> 0.723 | R17: =0.603+0.12 -> 0.723 | S17: 0.603 | T17: 0.603 | V17: 0.603 | W17: 0.603 | X17: 0.603 | Y17: 0.603 | AA17: 0.603 | AB17: 0.603 | AC17: 0.603 | AD17: 0.603 | AF17: 0.603 | AG17: 0.603 | AH17: 0.603 | AI17: 0.603 | AK17: 0.749 | AL17: 0.749 | AM17: 0.749 | AN17: 0.749 | AP17: 0.749 | AQ17: 0.749 | AR17: 0.749 | AS17: 0.749 | AU17: 0.749 | AV17: 0.889 | AW17: 0.87 | AX17: 0.876 | AZ17: 1.082 | BA17: 1.088 | BB17: 1.08 | BC17: 1.544 | BE17: 1.645 | BF17: 1.654 | BG17: 1.637 | BH17: =+BG17 -> 1.637 | BJ17: =+BH17 -> 1.637 | BK17: =+BJ17 -> 1.637 | BL17: =+BK17 -> 1.637 | BM17: =+BL17 -> 1.637 | BO17: =+BM17 -> 1.637 | BP17: =+BO17 -> 1.637 | BQ17: =+BP17 -> 1.637 | BR17: =+BQ17 -> 1.637
A18: Lease Assets | V18: 0 | W18: 0 | X18: 0 | Y18: 0 | AA18: =0.735+9.63 -> 10.365 | AB18: =0.677+9.412 -> 10.089 | AC18: =0.619+9.033 -> 9.652 | AD18: 8.808 | AF18: 8.576 | AG18: 8.339 | AH18: 8.094 | AI18: 7.843 | AK18: 15.186 | AL18: 14.559 | AM18: 16.001 | AN18: 16.043 | AP18: 15.663 | AQ18: 14.816 | AR18: 13.885 | AS18: 13.16 | AU18: 11.308 | AV18: 12.455 | AW18: 11.297 | AX18: 10.277 | AZ18: 11.167 | BA18: 18.116 | BB18: 17.031 | BC18: 48.189 | BE18: 47.624 | BF18: 38.679 | BG18: 37.301 | BH18: =+BG18 -> 37.301 | BJ18: =+BH18 -> 37.301 | BK18: =+BJ18 -> 37.301 | BL18: =+BK18 -> 37.301 | BM18: =+BL18 -> 37.301 | BO18: =+BM18 -> 37.301 | BP18: =+BO18 -> 37.301 | BQ18: =+BP18 -> 37.301 | BR18: =+BQ18 -> 37.301
A19: Other Assets | O19: 0.134 | Q19: 0.127 | R19: 0.134 | S19: 0.178 | T19: 0.326 | V19: 0.466 | W19: 0.598 | X19: 0.837 | Y19: 1.086 | AA19: =1.049 -> 1.049 | AB19: 1.061 | AC19: 1.228 | AD19: 1.437 | AF19: 1.302 | AG19: 1.271 | AH19: 2.303 | AI19: 1.399 | AK19: 2.286 | AL19: 1.504 | AM19: 1.636 | AN19: 2.198 | AP19: 1.799 | AQ19: 1.993 | AR19: 2.143 | AS19: 5.418 | AU19: 5.543 | AV19: 6.116 | AW19: 5.582 | AX19: 5.971 | AZ19: 5.639 | BA19: 7.087 | BB19: 7.872 | BC19: 6.981 | BE19: 7.095 | BF19: 1.477 | BG19: 1.094 | BH19: =+BG19 -> 1.094 | BJ19: =+BH19 -> 1.094 | BK19: =+BJ19 -> 1.094 | BL19: =+BK19 -> 1.094 | BM19: =+BL19 -> 1.094 | BO19: =+BM19 -> 1.094 | BP19: =+BO19 -> 1.094 | BQ19: =+BP19 -> 1.094 | BR19: =+BQ19 -> 1.094
A20: Total Assets | O20: =SUM(O12:O19) -> 101.034 | Q20: =SUM(Q12:Q19) -> 92.606 | R20: =SUM(R12:R19) -> 88.347 | S20: =SUM(S12:S19) -> 83.659 | T20: =SUM(T12:T19) -> 78.669 | V20: =SUM(V12:V19) -> 71.19 | W20: =SUM(W12:W19) -> 65.461 | X20: =SUM(X12:X19) -> 119.077 | Y20: =SUM(Y12:Y19) -> 120.638 | AA20: =SUM(AA12:AA19) -> 123.537 | AB20: =SUM(AB12:AB19) -> 252.377 | AC20: =SUM(AC12:AC19) -> 260.307 | AD20: =SUM(AD12:AD19) -> 275.212 | AF20: =SUM(AF12:AF19) -> 267.1 | AG20: =SUM(AG12:AG19) -> 256.737 | AH20: =SUM(AH12:AH19) -> 454.151 | AI20: =SUM(AI12:AI19) -> 457.163 | AK20: =SUM(AK12:AK19) -> 1025.136 | AL20: =SUM(AL12:AL19) -> 1027.435 | AM20: =SUM(AM12:AM19) -> 1186.356 | AN20: =SUM(AN12:AN19) -> 1187.825 | AP20: =SUM(AP12:AP19) -> 1173.589 | AQ20: =SUM(AQ12:AQ19) -> 1144.198 | AR20: =SUM(AR12:AR19) -> 1125.957 | AS20: =SUM(AS12:AS19) -> 1156.422 | AU20: =SUM(AU12:AU19) -> 1157.119 | AV20: =SUM(AV12:AV19) -> 1161.114 | AW20: =SUM(AW12:AW19) -> 1124.943 | AX20: =SUM(AX12:AX19) -> 1114.906 | AZ20: =SUM(AZ12:AZ19) -> 1200.073 | BA20: =SUM(BA12:BA19) -> 1234.327 | BB20: =SUM(BB12:BB19) -> 1275.021 | BC20: =SUM(BC12:BC19) -> 1300.035 | BE20: =SUM(BE12:BE19) -> 1315.411 | BF20: =SUM(BF12:BF19) -> 1344.104 | BG20: =SUM(BG12:BG19) -> 1367.787 | BH20: =SUM(BH12:BH19) -> 1416.0843 | BJ20: =SUM(BJ12:BJ19) -> 1437.8479 | BK20: =SUM(BK12:BK19) -> 1496.1016 | BL20: =SUM(BL12:BL19) -> 1539.7421 | BM20: =SUM(BM12:BM19) -> 1597.2337 | BO20: =SUM(BO12:BO19) -> 1622.3407 | BP20: =SUM(BP12:BP19) -> 1686.9373 | BQ20: =SUM(BQ12:BQ19) -> 1735.4573 | BR20: =SUM(BR12:BR19) -> 1799.1842
A22: Liabilities and Equity
A23: Accounts Payable | O23: 2.424 | Q23: 2.611 | R23: 2.349 | S23: 3.161 | T23: 3.853 | V23: 3.356 | W23: 1.962 | X23: 1.175 | Y23: 2.516 | AA23: 4.064 | AB23: 4.061 | AC23: 5.568 | AD23: 2.328 | AF23: 7.665 | AG23: 2.224 | AH23: 1.932 | AI23: 3.116 | AK23: 7.137 | AL23: 8.472 | AM23: 11.201 | AN23: 12.36 | AP23: 11.273 | AQ23: 10.328 | AR23: 11.114 | AS23: 11.911 | AU23: 15.655 | AV23: 12.895 | AW23: 12.531 | AX23: 12.943 | AZ23: 12.152 | BA23: 12.084 | BB23: 9.67 | BC23: 8.634 | BE23: 15.709 | BF23: 11.447 | BG23: 5.509 | BH23: =+BH71*'Income Statement'!BH10 -> 11.25088 | BJ23: =+BJ71*'Income Statement'!BJ10 -> 10.421173 | BK23: =+BK71*'Income Statement'!BK10 -> 11.777943 | BL23: =+BL71*'Income Statement'!BL10 -> 11.690002 | BM23: =+BM71*'Income Statement'!BM10 -> 12.269091 | BO23: =+BO71*'Income Statement'!BO10 -> 11.529868 | BP23: =+BP71*'Income Statement'!BP10 -> 13.043579 | BQ23: =+BQ71*'Income Statement'!BQ10 -> 12.963322 | BR23: =+BR71*'Income Statement'!BR10 -> 13.586963
A24: J&J Deferred Revenue | O24: 0 | Q24: 0 | R24: 0 | S24: 0 | T24: 0 | V24: 0 | W24: 0 | X24: 0 | Y24: 0 | AA24: 1.2 | AB24: 0 | AC24: 0 | AD24: 0 | AF24: 0 | AG24: 0 | AH24: 0 | AI24: 0 | AK24: 0 | AL24: =+AK24 -> 0 | AM24: 0 | AN24: =+AM24 -> 0 | AP24: =+AN24 -> 0 | AQ24: =+AP24 -> 0 | AR24: =+AQ24 -> 0 | AS24: =+AR24 -> 0 | AU24: =+AS24 -> 0 | AV24: =+AU24 -> 0 | AW24: =+AV24 -> 0 | AX24: =+AW24 -> 0 | AZ24: =+AX24 -> 0 | BA24: =+AZ24 -> 0 | BB24: =+BA24 -> 0 | BC24: =+BB24 -> 0 | BE24: =+BC24 -> 0 | BF24: =+BE24 -> 0 | BG24: =+BF24 -> 0 | BH24: =+BG24 -> 0 | BJ24: =+BH24 -> 0 | BK24: =+BJ24 -> 0 | BL24: =+BK24 -> 0 | BM24: =+BL24 -> 0 | BO24: =+BM24 -> 0 | BP24: =+BO24 -> 0 | BQ24: =+BP24 -> 0 | BR24: =+BQ24 -> 0
A25: Accrued Expenses | O25: 9.11 | Q25: 6.8 | R25: 8.45 | S25: 8.058 | T25: 8.175 | V25: 8.483 | W25: 8.429 | X25: 9.261 | Y25: 9.186 | AA25: =8.788-AA24 -> 7.588 | AB25: 9.82 | AC25: 9.76 | AD25: 13.734 | AF25: 10.079 | AG25: 9.386 | AH25: 10.445 | AI25: =11.705+0.371 -> 12.076 | AK25: =16.254+0.454+5.986 -> 22.694 | AL25: =20.756+0.566 -> 21.322 | AM25: =29.044+3.44 -> 32.484 | AN25: =39.475+1.127+4.646+2.682 -> 47.93 | AP25: =38.543+1.079+4.878+2.703 -> 47.203 | AQ25: =33.565+1.133+4.193+5.998 -> 44.889 | AR25: =32.137+1.187+3.863+5.913 -> 43.1 | AS25: =37.774+2.613+6.06 -> 46.447 | AU25: =30.641+2.194+3.3 -> 36.135 | AV25: =34.427+2.378+3.359 -> 40.164 | AW25: =34.828+2.214+2.574 -> 39.616 | AX25: =38.427+2.008+2.657 -> 43.092 | AZ25: =30.293+2.602+6.934 -> 39.829 | BA25: =43.455+2.195+7.348+7.185+0.072 -> 60.255 | BB25: =43.872+2.033+7.391+7.294+0.053 -> 60.643 | BC25: =43.826+1.673+16.981 -> 62.48 | BE25: =35.928+1.712+14.36 -> 52 | BF25: =43.707+1.45+13.415 -> 58.572 | BG25: =48.373+0.417+13.571+4.282 -> 66.643 | BH25: =BH72*'Income Statement'!BH10 -> 56.2544 | BJ25: =BJ72*'Income Statement'!BJ10 -> 39.0794 | BK25: =BK72*'Income Statement'!BK10 -> 51.5285 | BL25: =BL72*'Income Statement'!BL10 -> 51.143759 | BM25: =BM72*'Income Statement'!BM10 -> 61.345457 | BO25: =BO72*'Income Statement'!BO10 -> 43.237005 | BP25: =BP72*'Income Statement'!BP10 -> 57.065657 | BQ25: =BQ72*'Income Statement'!BQ10 -> 56.714535 | BR25: =BR72*'Income Statement'!BR10 -> 67.934815
A26: Current Liabilities | O26: =SUM(O23:O25) -> 11.534 | Q26: =SUM(Q23:Q25) -> 9.411 | R26: =SUM(R23:R25) -> 10.799 | S26: =SUM(S23:S25) -> 11.219 | T26: =SUM(T23:T25) -> 12.028 | V26: =SUM(V23:V25) -> 11.839 | W26: =SUM(W23:W25) -> 10.391 | X26: =SUM(X23:X25) -> 10.436 | Y26: =SUM(Y23:Y25) -> 11.702 | AA26: =SUM(AA23:AA25) -> 12.852 | AB26: =SUM(AB23:AB25) -> 13.881 | AC26: =SUM(AC23:AC25) -> 15.328 | AD26: =SUM(AD23:AD25) -> 16.062 | AF26: =SUM(AF23:AF25) -> 17.744 | AG26: =SUM(AG23:AG25) -> 11.61 | AH26: =SUM(AH23:AH25) -> 12.377 | AI26: =SUM(AI23:AI25) -> 15.192 | AK26: =SUM(AK23:AK25) -> 29.831 | AL26: =SUM(AL23:AL25) -> 29.794 | AM26: =SUM(AM23:AM25) -> 43.685 | AN26: =SUM(AN23:AN25) -> 60.29 | AP26: =SUM(AP23:AP25) -> 58.476 | AQ26: =SUM(AQ23:AQ25) -> 55.217 | AR26: =SUM(AR23:AR25) -> 54.214 | AS26: =SUM(AS23:AS25) -> 58.358 | AU26: =SUM(AU23:AU25) -> 51.79 | AV26: =SUM(AV23:AV25) -> 53.059 | AW26: =SUM(AW23:AW25) -> 52.147 | AX26: =SUM(AX23:AX25) -> 56.035 | AZ26: =SUM(AZ23:AZ25) -> 51.981 | BA26: =SUM(BA23:BA25) -> 72.339 | BB26: =SUM(BB23:BB25) -> 70.313 | BC26: =SUM(BC23:BC25) -> 71.114 | BE26: =SUM(BE23:BE25) -> 67.709 | BF26: =SUM(BF23:BF25) -> 70.019 | BG26: =SUM(BG23:BG25) -> 72.152 | BH26: =SUM(BH23:BH25) -> 67.50528 | BJ26: =SUM(BJ23:BJ25) -> 49.500573 | BK26: =SUM(BK23:BK25) -> 63.306443 | BL26: =SUM(BL23:BL25) -> 62.833761 | BM26: =SUM(BM23:BM25) -> 73.614549 | BO26: =SUM(BO23:BO25) -> 54.766873 | BP26: =SUM(BP23:BP25) -> 70.109236 | BQ26: =SUM(BQ23:BQ25) -> 69.677857 | BR26: =SUM(BR23:BR25) -> 81.521777
A27: Long-Term Debt | O27: 24.918 | Q27: 24.944 | R27: 24.971 | S27: 24.997 | T27: 24.938 | V27: 25.016 | W27: 25.103 | X27: 25.192 | Y27: =1.357+23.925 -> 25.282 | AA27: 12.854 | AB27: 0.585 | AC27: 0.639 | AD27: 0.694 | AF27: 0.748 | AG27: 0.801 | AH27: 0.756 | AI27: 0.81 | AK27: 0.863 | AL27: 0.917 | AM27: 1.075 | AN27: 0 | AP27: 0 | AQ27: 0 | AR27: 0 | AS27: 0 | AU27: 0 | AV27: 0 | AW27: 0 | AX27: 0 | AZ27: =+AX27+'Cash Flow'!AZ42-'Income Statement'!AZ21 -> 0 | BA27: 0 | BB27: =+BA27+'Cash Flow'!BB42-'Income Statement'!BB21 -> 0 | BC27: =+BB27+'Cash Flow'!BC42-'Income Statement'!BC21 -> 0 | BE27: =+BC27+'Cash Flow'!BE42-'Income Statement'!BE21 -> 0 | BF27: =+BE27+'Cash Flow'!BF42-'Income Statement'!BF21 -> 0 | BG27: =+BF27+'Cash Flow'!BG42-'Income Statement'!BG21 -> 0 | BH27: =+BG27+'Cash Flow'!BH42-'Income Statement'!BH21 -> 0 | BJ27: =+BH27+'Cash Flow'!BJ42-'Income Statement'!BJ21 -> 0 | BK27: =+BJ27+'Cash Flow'!BK42-'Income Statement'!BK21 -> 0 | BL27: =+BK27+'Cash Flow'!BL42-'Income Statement'!BL21 -> 0 | BM27: =+BL27+'Cash Flow'!BM42-'Income Statement'!BM21 -> 0 | BO27: =+BM27+'Cash Flow'!BO42-'Income Statement'!BO21 -> 0 | BP27: =+BO27+'Cash Flow'!BP42-'Income Statement'!BP21 -> 0 | BQ27: =+BP27+'Cash Flow'!BQ42-'Income Statement'!BQ21 -> 0 | BR27: =+BQ27+'Cash Flow'!BR42-'Income Statement'!BR21 -> 0
A28: Lease Liability | O28: 0.599 | Q28: 0.528 | R28: 0.456 | S28: 0.382 | T28: 0.308 | V28: 0.233 | W28: 0.156 | X28: 0.079 | Y28: 0 | AA28: =0.233+1.244+12.582 -> 14.059 | AB28: =0.156+1.284+12.231 -> 13.671 | AC28: =0.079+1.365+11.872 -> 13.316 | AD28: =1.407+11.506 -> 12.913 | AF28: =1.45+11.132 -> 12.582 | AG28: =1.495+10.736 -> 12.231 | AH28: =1.542+10.331 -> 11.873 | AI28: =1.589+9.917 -> 11.506 | AK28: =2.878+14.036 -> 16.914 | AL28: =3.375+2.936+13.334 -> 19.645 | AM28: =3.465+14.236+1.891+0.241 -> 19.833 | AN28: =3.63+0.231+14.096+1.407 -> 19.364 | AP28: =3.849+0.218+13.485+1.378 -> 18.93 | AQ28: =3.93+0.198+12.529+1.21 -> 17.867 | AR28: =3.958+0.18+11.527+1.148 -> 16.813 | AS28: =4.07+0.186+10.648+0.931 -> 15.835 | AU28: =4.076+0.127+9.709+0.791 -> 14.703 | AV28: =4.973+0.119+9.891+0.792 -> 15.775 | AW28: =5.007+0.106+8.72+0.776 -> 14.609 | AX28: =7.525+0.786+5.105+0.101 -> 13.517 | AZ28: =8.058+0.528+5.982+0.089 -> 14.657 | BA28: =1.483+13.553 -> 15.036 | BB28: =12.4+0.571 -> 12.971 | BC28: =7.5+0.019+43.237+0.411 -> 51.167 | BE28: =7.409+0.007+43.092+0.446 -> 50.954 | BF28: =6.414+44.232+0.508 -> 51.154 | BG28: =36.171 -> 36.171 | BH28: =+BG28 -> 36.171 | BJ28: =+BH28 -> 36.171 | BK28: =+BJ28 -> 36.171 | BL28: =+BK28 -> 36.171 | BM28: =+BL28 -> 36.171 | BO28: =+BM28 -> 36.171 | BP28: =+BO28 -> 36.171 | BQ28: =+BP28 -> 36.171 | BR28: =+BQ28 -> 36.171
A29: Contingent Consideration | O29: 0 | Q29: 0 | R29: 0 | S29: 0 | T29: 0 | V29: 0 | W29: 0 | X29: 0 | Y29: 0 | AA29: 0 | AB29: 0 | AC29: 0 | AD29: 6.088 | AF29: 5.604 | AG29: 5.948 | AH29: 6.42 | AI29: 7.594 | AK29: 1.8 | AL29: 4.467 | AM29: =5.251+2.646 -> 7.897 | AN29: 5.722 | AP29: 5.732 | AQ29: 2.358 | AR29: 2.411 | AS29: 2.498 | AU29: 4.773 | AV29: 4.855 | AW29: 0.484 | AX29: 0.518 | AZ29: 13.446 | BA29: 13.889 | BB29: 14.225 | BC29: 0.561 | BE29: 0.57 | BF29: 0.573 | BG29: 0.583 | BH29: =+BG29 -> 0.583 | BJ29: =+BH29 -> 0.583 | BK29: =+BJ29 -> 0.583 | BL29: =+BK29 -> 0.583 | BM29: =+BL29 -> 0.583 | BO29: =+BM29 -> 0.583 | BP29: =+BO29 -> 0.583 | BQ29: =+BP29 -> 0.583 | BR29: =+BQ29 -> 0.583
A30: Deferred Rent | O30: 4.402 | Q30: 4.373 | R30: 4.277 | S30: 4.245 | T30: 4.17 | V30: 4.094 | W30: 4.005 | X30: 3.953 | Y30: 3.899 | AA30: 0 | AB30: 0 | AC30: 0 | AD30: 0 | AF30: 0 | AG30: 0 | AH30: =+AG30 -> 0 | AI30: 0 | AK30: =+AI30 -> 0 | AL30: =+AK30 -> 0 | AM30: 0 | AN30: =+AM30 -> 0 | AP30: =+AN30 -> 0 | AQ30: =+AP30 -> 0 | AR30: =+AQ30 -> 0 | AS30: =+AR30 -> 0 | AU30: =+AS30 -> 0 | AV30: =+AU30 -> 0 | AW30: =+AV30 -> 0 | AX30: =+AW30 -> 0 | AZ30: 0 | BA30: =+AZ30 -> 0 | BB30: =+BA30 -> 0 | BC30: =+BB30 -> 0 | BE30: =+BC30 -> 0 | BF30: =+BE30 -> 0 | BG30: =+BF30 -> 0 | BH30: =+BG30 -> 0 | BJ30: =+BH30 -> 0 | BK30: =+BJ30 -> 0 | BL30: =+BK30 -> 0 | BM30: =+BL30 -> 0 | BO30: =+BM30 -> 0 | BP30: =+BO30 -> 0 | BQ30: =+BP30 -> 0 | BR30: =+BQ30 -> 0
A31: Deferred Tax Liability | Q31: 0 | R31: 0 | S31: 0 | T31: 0 | V31: 0 | W31: 0 | X31: 0 | Y31: 0 | AA31: 0 | AB31: 0 | AC31: 0 | AD31: =+AC31 -> 0 | AF31: =+AD31 -> 0 | AG31: 0 | AH31: =+AG31 -> 0 | AI31: 0 | AK31: =+AI31 -> 0 | AL31: =+AK31 -> 0 | AM31: 6.234 | AN31: 5.592 | AP31: 4.983 | AQ31: 4.605 | AR31: 4.342 | AS31: 4.531 | AU31: 4.594 | AV31: 4.707 | AW31: 3.644 | AX31: 0.734 | AZ31: 1.34 | BA31: 0.54 | BB31: 1.47 | BC31: 1.227 | BE31: 1.242 | BF31: 1.301 | BG31: 1.214 | BH31: =+BG31 -> 1.214 | BJ31: =+BH31 -> 1.214 | BK31: =+BJ31 -> 1.214 | BL31: =+BK31 -> 1.214 | BM31: =+BL31 -> 1.214 | BO31: =+BM31 -> 1.214 | BP31: =+BO31 -> 1.214 | BQ31: =+BP31 -> 1.214 | BR31: =+BQ31 -> 1.214
A32: Deferred Genzyme Co-Promotion Fee | Q32: 0 | R32: 0 | S32: 0 | T32: 0 | V32: 0 | W32: 0 | X32: 0 | Y32: 0 | AA32: 0 | AB32: 0 | AC32: 0 | AD32: 0 | AF32: =+AD32 -> 0 | AG32: 0 | AH32: 0 | AI32: 0 | AK32: =+AI32 -> 0 | AL32: =+AK32 -> 0 | AM32: 0 | AN32: =+AM32 -> 0 | AP32: =+AN32 -> 0 | AQ32: =+AP32 -> 0 | AR32: =+AQ32 -> 0 | AS32: =+AR32 -> 0 | AU32: =+AS32 -> 0 | AV32: =+AU32 -> 0 | AW32: =+AV32 -> 0 | AX32: =+AW32 -> 0 | AZ32: =+AX32 -> 0 | BA32: =+AZ32 -> 0 | BB32: =+BA32 -> 0 | BC32: =+BB32 -> 0 | BE32: =+BC32 -> 0 | BF32: =+BE32 -> 0 | BG32: =+BF32 -> 0 | BH32: =+BG32 -> 0 | BJ32: =+BH32 -> 0 | BK32: =+BJ32 -> 0 | BL32: =+BK32 -> 0 | BM32: =+BL32 -> 0 | BO32: =+BM32 -> 0 | BP32: =+BO32 -> 0 | BQ32: =+BP32 -> 0 | BR32: =+BQ32 -> 0
A33: Deferred revenue, net | AI33: 0.829 | AK33: =0.747+0.75 -> 1.497 | AL33: =0.662+0.773 -> 1.435 | AM33: 0.552 | AN33: 0.343 | AP33: 0.278 | AQ33: 0 | AR33: 0 | AS33: 0 | AU33: =+AS33 -> 0 | AV33: =+AU33 -> 0 | AW33: =+AV33 -> 0 | AX33: =+AW33 -> 0 | AZ33: =+AX33 -> 0 | BA33: =+AZ33 -> 0 | BB33: =+BA33 -> 0 | BC33: =+BB33 -> 0 | BE33: =+BC33 -> 0 | BF33: =+BE33 -> 0 | BG33: =+BF33 -> 0 | BH33: =+BG33 -> 0 | BJ33: =+BH33 -> 0 | BK33: =+BJ33 -> 0 | BL33: =+BK33 -> 0 | BM33: =+BL33 -> 0 | BO33: =+BM33 -> 0 | BP33: =+BO33 -> 0 | BQ33: =+BP33 -> 0 | BR33: =+BQ33 -> 0
A34: Preferred Stock | O34: 0 | Q34: 0 | R34: 0 | S34: 0 | T34: 0 | V34: 0 | W34: 0 | X34: 0 | Y34: 0 | AA34: 0 | AB34: 0 | AC34: 0 | AD34: 0 | AF34: 0 | AG34: 0 | AH34: 0 | AI34: 0 | AK34: =+AI34 -> 0 | AL34: =+AK34 -> 0 | AM34: 0 | AN34: =+AM34 -> 0 | AP34: =+AN34 -> 0 | AQ34: =+AP34 -> 0 | AR34: =+AQ34 -> 0 | AS34: =+AR34 -> 0 | AU34: =+AS34 -> 0 | AV34: =+AU34 -> 0 | AW34: =+AV34 -> 0 | AX34: =+AW34 -> 0 | AZ34: =+AX34 -> 0 | BA34: =+AZ34 -> 0 | BB34: =+BA34 -> 0 | BC34: =+BB34 -> 0 | BE34: =+BC34 -> 0 | BF34: =+BE34 -> 0 | BG34: =+BF34 -> 0 | BH34: =+BG34 -> 0 | BJ34: =+BH34 -> 0 | BK34: =+BJ34 -> 0 | BL34: =+BK34 -> 0 | BM34: =+BL34 -> 0 | BO34: =+BM34 -> 0 | BP34: =+BO34 -> 0 | BQ34: =+BP34 -> 0 | BR34: =+BQ34 -> 0
A35: Common Stock | O35: 0.034 | Q35: 0.034 | R35: 0.034 | S35: 0.034 | T35: 0.034 | V35: 0.034 | W35: 0.034 | X35: 0.041 | Y35: 0.041 | AA35: 0.042 | AB35: 0.048 | AC35: 0.049 | AD35: 0.05 | AF35: 0.05 | AG35: 0.05 | AH35: 0.058 | AI35: 0.058 | AK35: 0.067 | AL35: 0.067 | AM35: 0.071 | AN35: 0.071 | AP35: 0.071 | AQ35: 0.072 | AR35: 0.072 | AS35: 0.072 | AU35: 0.072 | AV35: 0.073 | AW35: 0.073 | AX35: 0.073 | AZ35: 0.076 | BA35: 0.077 | BB35: 0.077 | BC35: 0.078 | BE35: 0.078 | BF35: 0.079 | BG35: 0.079 | BH35: =+BG35 -> 0.079 | BJ35: =+BH35 -> 0.079 | BK35: =+BJ35 -> 0.079 | BL35: =+BK35 -> 0.079 | BM35: =+BL35 -> 0.079 | BO35: =+BM35 -> 0.079 | BP35: =+BO35 -> 0.079 | BQ35: =+BP35 -> 0.079 | BR35: =+BQ35 -> 0.079
A36: APIC | O36: 239.631 | Q36: 241.617 | R36: 243.409 | S36: 245.43 | T36: 248.278 | V36: 250.238 | W36: 252.284 | X36: 310.357 | Y36: 313.8 | AA36: 319.733 | AB36: 462.689 | AC36: 470.202 | AD36: =239.455-AD37-AD35 -> 486.09 | AF36: =+AD36+'Cash Flow'!AF10 -> 488.995 | AG36: 495.523 | AH36: 696.217 | AI36: 702.768 | AK36: 1297.626 | AL36: 1303.61 | AM36: 1461.778 | AN36: 1468.683 | AP36: 1477.418 | AQ36: 1483.279 | AR36: 1492.044 | AS36: 1500.191 | AU36: 1509.861 | AV36: 1520.638 | AW36: 1528.011 | AX36: 1536.168 | AZ36: 1617.465 | BA36: 1627.307 | BB36: 1646.343 | BC36: 1655.961 | BE36: 1660.435 | BF36: 1670.853 | BG36: 1684.587 | BH36: =+BG36+'Cash Flow'!BH10 -> 1694.716 | BJ36: =+BH36+'Cash Flow'!BJ10 -> 1706.174 | BK36: =+BJ36+'Cash Flow'!BK10 -> 1717.659 | BL36: =+BK36+'Cash Flow'!BL10 -> 1728.916 | BM36: =+BL36+'Cash Flow'!BM10 -> 1739.545 | BO36: =+BM36+'Cash Flow'!BO10 -> 1751.503 | BP36: =+BO36+'Cash Flow'!BP10 -> 1763.488 | BQ36: =+BP36+'Cash Flow'!BQ10 -> 1775.245 | BR36: =+BQ36+'Cash Flow'!BR10 -> 1786.374
A37: Accumulated Deficit | O37: -180.084 | Q37: -188.301 | R37: -195.599 | S37: -202.648 | T37: -211.087 | V37: -220.264 | W37: -226.512 | X37: -230.981 | Y37: -234.086 | AA37: -236.003 | AB37: -238.497 | AC37: -239.227 | AD37: =+AC37+'Cash Flow'!AD8 -> -246.685 | AF37: =230.422-AF36-AF35-AF34 -> -258.623 | AG37: -269.426 | AH37: -273.55 | AI37: -281.594 | AK37: -323.462 | AL37: -332.5 | AM37: =-346.629-8.14 -> -354.769 | AN37: =-357.157-15.083 -> -372.24 | AP37: =-371.618-20.681 -> -392.299 | AQ37: =-381.15-38.05 -> -419.2 | AR37: =-389.873-54.066 -> -443.939 | AS37: =-393.717-31.346 -> -425.063 | AU37: =-401.808-26.866 -> -428.674 | AV37: =-410.21-27.783 -> -437.993 | AW37: =-439.828-34.197 -> -474.025 | AX37: =-468.121-24.018 -> -492.139 | AZ37: =-469.985-28.907 -> -498.892 | BA37: =-464.251-30.61 -> -494.861 | BB37: =-449.096-21.282 -> -470.378 | BC37: =-443.983-36.09 -> -480.073 | BE37: =-436.936-28.641 -> -465.577 | BF37: =-437.916-11.959 -> -449.875 | BG37: =-418.779-8.22 -> -426.999 | BH37: =+BG37+'Cash Flow'!BH8 -> -384.184 | BJ37: =+BH37+'Cash Flow'!BJ8 -> -355.87367 | BK37: =+BJ37+'Cash Flow'!BK8 -> -322.91085 | BL37: =+BK37+'Cash Flow'!BL8 -> -290.05462 | BM37: =+BL37+'Cash Flow'!BM8 -> -253.97284 | BO37: =+BM37+'Cash Flow'!BO8 -> -221.97614 | BP37: =+BO37+'Cash Flow'!BP8 -> -184.70694 | BQ37: =+BP37+'Cash Flow'!BQ8 -> -147.51253 | BR37: =+BQ37+'Cash Flow'!BR8 -> -106.75854
A38: Shareholders Equity | O38: =SUM(O34:O37) -> 59.581 | Q38: =SUM(Q34:Q37) -> 53.35 | R38: =SUM(R34:R37) -> 47.844 | S38: =SUM(S34:S37) -> 42.816 | T38: =SUM(T34:T37) -> 37.225 | V38: =SUM(V34:V37) -> 30.008 | W38: =SUM(W34:W37) -> 25.806 | X38: =SUM(X34:X37) -> 79.417 | Y38: =SUM(Y34:Y37) -> 79.755 | AA38: =SUM(AA34:AA37) -> 83.772 | AB38: =SUM(AB34:AB37) -> 224.24 | AC38: =SUM(AC34:AC37) -> 231.024 | AD38: =SUM(AD34:AD37) -> 239.455 | AF38: =SUM(AF34:AF37) -> 230.422 | AG38: =SUM(AG34:AG37) -> 226.147 | AH38: =SUM(AH34:AH37) -> 422.725 | AI38: =SUM(AI33:AI37) -> 422.061 | AK38: =SUM(AK33:AK37) -> 975.728 | AL38: =SUM(AL33:AL37) -> 972.612 | AM38: =SUM(AM33:AM37) -> 1107.632 | AN38: =SUM(AN33:AN37) -> 1096.857 | AP38: =SUM(AP33:AP37) -> 1085.468 | AQ38: =SUM(AQ33:AQ37) -> 1064.151 | AR38: =SUM(AR33:AR37) -> 1048.177 | AS38: =SUM(AS33:AS37) -> 1075.2 | AU38: =SUM(AU33:AU37) -> 1081.259 | AV38: =SUM(AV33:AV37) -> 1082.718 | AW38: =SUM(AW33:AW37) -> 1054.059 | AX38: =SUM(AX33:AX37) -> 1044.102 | AZ38: =SUM(AZ33:AZ37) -> 1118.649 | BA38: =SUM(BA33:BA37) -> 1132.523 | BB38: =SUM(BB33:BB37) -> 1176.042 | BC38: =SUM(BC33:BC37) -> 1175.966 | BE38: =SUM(BE33:BE37) -> 1194.936 | BF38: =SUM(BF33:BF37) -> 1221.057 | BG38: =SUM(BG33:BG37) -> 1257.667 | BH38: =SUM(BH33:BH37) -> 1310.611 | BJ38: =SUM(BJ33:BJ37) -> 1350.3793 | BK38: =SUM(BK33:BK37) -> 1394.8271 | BL38: =SUM(BL33:BL37) -> 1438.9404 | BM38: =SUM(BM33:BM37) -> 1485.6512 | BO38: =SUM(BO33:BO37) -> 1529.6059 | BP38: =SUM(BP33:BP37) -> 1578.8601 | BQ38: =SUM(BQ33:BQ37) -> 1627.8115 | BR38: =SUM(BR33:BR37) -> 1679.6945
A39: Total Liabilities & Stockholders Equity | O39: =+O38+O26+O30+O27+O28 -> 101.034 | Q39: =+Q38+Q26+Q30+Q27+Q28 -> 92.606 | R39: =+R38+R26+R30+R27+R28 -> 88.347 | S39: =+S38+S26+S30+S27+S28 -> 83.659 | T39: =+T38+T26+T30+T27+T28 -> 78.669 | V39: =+V38+V26+V30+V27+V28+V29 -> 71.19 | W39: =+W38+W26+W30+W27+W28+W29 -> 65.461 | X39: =+X38+X26+X30+X27+X28+X29 -> 119.077 | Y39: =+Y38+Y26+Y30+Y27+Y28+Y29 -> 120.638 | AA39: =+AA38+AA26+AA30+AA27+AA28+AA29 -> 123.537 | AB39: =+AB38+AB26+AB30+AB27+AB28+AB29 -> 252.377 | AC39: =+AC38+AC26+AC30+AC27+AC28+AC29 -> 260.307 | AD39: =+AD38+AD26+AD30+AD27+AD28+AD29 -> 275.212 | AF39: =+AF38+AF26+AF30+AF27+AF28+AF29 -> 267.1 | AG39: =+AG38+AG26+AG30+AG27+AG28+AG29 -> 256.737 | AH39: =+AH38+AH26+AH30+AH27+AH28+AH29 -> 454.151 | AI39: =+AI38+AI26+AI30+AI27+AI28+AI29 -> 457.163 | AK39: =+AK38+AK26+AK30+AK27+AK28+AK29 -> 1025.136 | AL39: =+AL38+AL26+AL30+AL27+AL28+AL29 -> 1027.435 | AM39: =+AM38+AM26+AM30+AM27+AM28+AM29+AM31 -> 1186.356 | AN39: =+AN38+AN26+AN30+AN27+AN28+AN29+AN31 -> 1187.825 | AP39: =+AP38+AP26+AP30+AP27+AP28+AP29+AP31 -> 1173.589 | AQ39: =+AQ38+AQ26+AQ30+AQ27+AQ28+AQ29+AQ31 -> 1144.198 | AR39: =+AR38+AR26+AR30+AR27+AR28+AR29+AR31 -> 1125.957 | AS39: =+AS38+AS26+AS30+AS27+AS28+AS29+AS31 -> 1156.422 | AT39: =+AT38+AT26+AT30+AT27+AT28+AT29+AT31 -> 0 | AU39: =+AU38+AU26+AU30+AU27+AU28+AU29+AU31 -> 1157.119 | AV39: =+AV38+AV26+AV30+AV27+AV28+AV29+AV31 -> 1161.114 | AW39: =+AW38+AW26+AW30+AW27+AW28+AW29+AW31 -> 1124.943 | ... BR39: =+BR38+BR26+BR30+BR27+BR28+BR29+BR31 -> 1799.1842
AT40: =AT39-AT20 -> 0 | AU40: =AU39-AU20 -> 0 | AV40: =AV39-AV20 -> 0 | AW40: =AW39-AW20 -> 0 | AX40: =AX39-AX20 -> 0 | AY40: =AY39-AY20 -> 0 | AZ40: =AZ39-AZ20 -> 0 | BA40: =BA39-BA20 -> 0 | ... BR40: =BR39-BR20 -> 0
A41: Balance Sheet Analysis
A42: Current Ratio | O42: =O12/O26 -> 6.3730709 | Q42: =Q12/Q26 -> 7.0316651 | R42: =R12/R26 -> 5.8097972 | S42: =S12/S26 -> 5.1882521 | T42: =T12/T26 -> 4.4835384 | V42: =V12/V26 -> 3.9740688 | W42: =W12/W26 -> 4.0068328 | X42: =X12/X26 -> 9.1389421 | Y42: =Y12/Y26 -> 8.2850795 | AA42: =AA12/AA26 -> 7.0507314 | AB42: =AB12/AB26 -> 15.8454 | AC42: =AC12/AC26 -> 14.879893 | AD42: =AD12/AD26 -> 11.685158 | AF42: =AF12/AF26 -> 10.221032 | AG42: =AG12/AG26 -> 14.874074 | AH42: =AH12/AH26 -> 29.919609 | AI42: =AI12/AI26 -> 24.728739 | AK42: =AK12/AK26 -> 12.138111 | AL42: =AL12/AL26 -> 12.463785 | AM42: =AM12/AM26 -> 5.2491244 | AN42: =AN12/AN26 -> 4.032211 | AP42: =AP12/AP26 -> 4.0783056 | AQ42: =AQ12/AQ26 -> 4.2567506 | AR42: =AR12/AR26 -> 4.3995278 | AS42: =AS12/AS26 -> 4.2605298 | AU42: =AU12/AU26 -> 4.8562078 | AV42: =AV12/AV26 -> 4.890405 | AW42: =AW12/AW26 -> 5.1999732 | AX42: =AX12/AX26 -> 5.0971893 | AZ42: =AZ12/AZ26 -> 5.5870029 | BA42: =BA12/BA26 -> 4.4389057 | BB42: =BB12/BB26 -> 5.0752208 | BC42: =BC12/BC26 -> 5.234792 | BE42: =BE12/BE26 -> 5.6588046 | BF42: =BF12/BF26 -> 5.9224068 | BG42: =BG12/BG26 -> 6.2260783 | BH42: =BH12/BH26 -> 7.3213574 | BJ42: =BJ12/BJ26 -> 10.404423 | BK42: =BK12/BK26 -> 9.048725 | BL42: =BL12/BL26 -> 9.780429 | BM42: =BM12/BM26 -> 9.0809727 | BO42: =BO12/BO26 -> 12.622224 | BP42: =BP12/BP26 -> 10.755934 | BQ42: =BQ12/BQ26 -> 11.471626 | BR42: =BR12/BR26 -> 10.526687
A43: Working Capital | O43: =+O8+O10+O11-O26 -> 2.754 | Q43: =+Q8+Q10+Q11-Q26 -> 5.258 | R43: =+R8+R10+R11-R26 -> 5.478 | S43: =+S8+S10+S11-S26 -> 5.793 | T43: =+T8+T10+T11-T26 -> 8.009 | V43: =+V8+V10+V11-V26 -> 8.058 | W43: =+W8+W10+W11-W26 -> 7.486 | X43: =+X8+X10+X11-X26 -> 7.092 | Y43: =+Y8+Y10+Y11-Y26 -> 7.255 | AA43: =+AA8+AA10+AA11-AA26 -> 9.923 | AB43: =+AB8+AB10+AB11-AB26 -> 11.422 | AC43: =+AC8+AC10+AC11-AC26 -> 11.089 | AD43: =+AD8+AD10+AD11-AD26 -> 10.308 | AF43: =+AF8+AF10+AF11-AF26 -> 10.486 | AG43: =+AG8+AG10+AG11-AG26 -> 11.728 | AH43: =+AH8+AH10+AH11-AH26 -> 12.058 | AI43: =+AI8+AI10+AI11-AI26 -> 9.123 | AK43: =+AK8+AK10+AK11-AK26 -> 8.199 | AL43: =+AL8+AL10+AL11-AL26 -> 14.007 | AM43: =+AM8+AM10+AM11-AM26 -> 21.594 | AN43: =+AN8+AN10+AN11-AN26 -> 9.615 | AP43: =+AP8+AP10+AP11-AP26 -> 16.392 | AQ43: =+AQ8+AQ10+AQ11-AQ26 -> 26.381 | AR43: =+AR8+AR10+AR11-AR26 -> 14.19 | AS43: =+AS8+AS10+AS11-AS26 -> 36.031 | AU43: =+AU8+AU10+AU11-AU26 -> 21.823 | AV43: =+AV8+AV10+AV11-AV26 -> 15.279 | AW43: =+AW8+AW10+AW11-AW26 -> 16.553 | AX43: =+AX8+AX10+AX11-AX26 -> 13.132 | AZ43: =+AZ8+AZ10+AZ11-AZ26 -> 29.249 | BA43: =+BA8+BA10+BA11-BA26 -> 12.852 | BB43: =+BB8+BB10+BB11-BB26 -> 12.462 | BC43: =+BC8+BC10+BC11-BC26 -> 11.712 | BE43: =+BE8+BE10+BE11-BE26 -> 28.088 | BF43: =+BF8+BF10+BF11-BF26 -> 23.943 | BG43: =+BG8+BG10+BG11-BG26 -> 10.644 | BH43: =+BH8+BH10+BH11-BH26 -> 51.26692 | BJ43: =+BJ8+BJ10+BJ11-BJ26 -> 62.011693 | BK43: =+BK8+BK10+BK11-BK26 -> 60.077557 | BL43: =+BL8+BL10+BL11-BL26 -> 59.780757 | BM43: =+BM8+BM10+BM11-BM26 -> 54.067002 | BO43: =+BO8+BO10+BO11-BO26 -> 66.446472 | BP43: =+BP8+BP10+BP11-BP26 -> 64.349078 | BQ43: =+BQ8+BQ10+BQ11-BQ26 -> 64.078212 | BR43: =+BR8+BR10+BR11-BR26 -> 57.691148
A44: Days Sales Outstanding | O44: NA | Q44: =45*(Q8+O8)/'Income Statement'!Q10 -> 48.968172 | R44: =45*(R8+Q8)/'Income Statement'!R10 -> 49.268717 | S44: =45*(S8+R8)/'Income Statement'!S10 -> 58.210514 | T44: =45*(T8+S8)/'Income Statement'!T10 -> 55.91932 | V44: =45*(V8+T8)/'Revenue Model'!V8 -> 58.187216 | W44: =45*(W8+V8)/'Revenue Model'!W8 -> 52.875656 | X44: =45*(X8+W8)/'Revenue Model'!X8 -> 48.977429 | Y44: =45*(Y8+X8)/'Revenue Model'!Y8 -> 44.876471 | AA44: =45*(AA8+Y8)/'Revenue Model'!AA8 -> 52.788018 | AB44: =45*(AB8+AA8)/'Revenue Model'!AB8 -> 57.739826 | AC44: =45*(AC8+AB8)/'Revenue Model'!AC8 -> 59.340456 | AD44: =45*(AD8+AC8)/'Revenue Model'!AD8 -> 55.061456 | AF44: =45*(AF8+AD8)/'Revenue Model'!AF8 -> 60.72024 | AG44: =45*(AG8+AF8)/'Revenue Model'!AG8 -> 96.13233 | AH44: =45*(AH8+AG8)/'Revenue Model'!AH8 -> 48.127874 | AI44: =45*(AI8+AH8)/'Revenue Model'!AI8 -> 47.561673 | AK44: =45*(AK8+AI8)/'Revenue Model'!AK8 -> 60.318338 | AL44: =45*(AL8+AK8)/'Revenue Model'!AL8 -> 52.92747 | AM44: =45*(AM8+AL8)/'Revenue Model'!AM8 -> 63.810932 | AN44: =45*(AN8+AM8)/'Revenue Model'!AN8 -> 68.889243 | AP44: =45*(AP8+AN8)/'Revenue Model'!AP8 -> 67.477492 | AQ44: =45*(AQ8+AP8)/'Revenue Model'!AQ8 -> 62.490455 | AR44: =45*(AR8+AQ8)/'Revenue Model'!AR8 -> 56.106973 | AS44: =45*(AS8+AR8)/'Revenue Model'!AS8 -> 53.850275 | AU44: =45*(AU8+AS8)/'Revenue Model'!AU8 -> 55.637742 | AV44: =45*(AV8+AU8)/'Revenue Model'!AV8 -> 48.360592 | AW44: =45*(AW8+AV8)/'Revenue Model'!AW8 -> 44.807955 | AX44: =45*(AX8+AW8)/'Revenue Model'!AX8 -> 39.66781 | AZ44: =45*(AZ8+AX8)/'Revenue Model'!AZ8 -> 43.375469 | BA44: =45*(BA8+AZ8)/'Revenue Model'!BA8 -> 40.792792 | BB44: =45*(BB8+BA8)/'Revenue Model'!BB8 -> 40.717161 | BC44: =45*(BC8+BB8)/'Revenue Model'!BC8 -> 38.251123 | BE44: =45*(BE8+BC8)/'Revenue Model'!BE8 -> 42.063294 | BF44: =45*(BF8+BE8)/'Revenue Model'!BF8 -> 38.497133 | BG44: =45*(BG8+BF8)/'Revenue Model'!BG8 -> 34.744356 | BH44: =45*(BH8+BG8)/'Revenue Model'!BH8 -> 43.801202 | BJ44: =45*(BJ8+BH8)/'Revenue Model'!BJ8 -> 57.820284 | BK44: =45*(BK8+BJ8)/'Revenue Model'!BK8 -> 52.200853 | BL44: =45*(BL8+BK8)/'Revenue Model'!BL8 -> 55.418364 | BM44: =45*(BM8+BL8)/'Revenue Model'!BM8 -> 54.016714 | BO44: =45*(BO8+BM8)/'Revenue Model'!BO8 -> 57.256217 | BP44: =45*(BP8+BO8)/'Revenue Model'!BP8 -> 52.071241 | BQ44: =45*(BQ8+BP8)/'Revenue Model'!BQ8 -> 55.282212 | BR44: =45*(BR8+BQ8)/'Revenue Model'!BR8 -> 53.948373
A45: Days Sales Out (Rolling 4 Qtr) | O45: NA | Q45: NA | R45: NA | S45: NA | T45: =(+T8+O8)/('Income Statement'!T10+'Income Statement'!S10+'Income Statement'!R10+'Income Statement'!Q10)*180 -> 53.715064 | V45: =(+V8+Q8)/('Revenue Model'!V8+'Revenue Model'!T8+'Revenue Model'!S8+'Revenue Model'!R8)*180 -> 53.176729 | W45: =(+W8+R8)/('Revenue Model'!W8+'Revenue Model'!V8+'Revenue Model'!T8+'Revenue Model'!S8)*180 -> 54.443787 | X45: =(+X8+S8)/('Revenue Model'!X8+'Revenue Model'!W8+'Revenue Model'!V8+'Revenue Model'!T8)*180 -> 50.513892 | Y45: =(+Y8+T8)/('Revenue Model'!Y8+'Revenue Model'!X8+'Revenue Model'!W8+'Revenue Model'!V8)*180 -> 51.166509 | AA45: =(+AA8+V8)/('Revenue Model'!AA8+'Revenue Model'!Y8+'Revenue Model'!X8+'Revenue Model'!W8)*180 -> 55.663963 | AB45: =(+AB8+W8)/('Revenue Model'!AB8+'Revenue Model'!AA8+'Revenue Model'!Y8+'Revenue Model'!X8)*180 -> 54.704884 | AC45: =(+AC8+X8)/('Revenue Model'!AC8+'Revenue Model'!AB8+'Revenue Model'!AA8+'Revenue Model'!Y8)*180 -> 51.558994 | AD45: =(+AD8+Y8)/('Revenue Model'!AD8+'Revenue Model'!AC8+'Revenue Model'!AB8+'Revenue Model'!AA8)*180 -> 51.133715 | AF45: =(+AF8+AA8)/('Revenue Model'!AF8+'Revenue Model'!AD8+'Revenue Model'!AC8+'Revenue Model'!AB8)*180 -> 58.987307 | AG45: =(+AG8+AB8)/('Revenue Model'!AG8+'Revenue Model'!AF8+'Revenue Model'!AD8+'Revenue Model'!AC8)*180 -> 57.299837 | AH45: =(+AH8+AC8)/('Revenue Model'!AH8+'Revenue Model'!AG8+'Revenue Model'!AF8+'Revenue Model'!AD8)*180 -> 62.602848 | AI45: =(+AI8+AD8)/('Revenue Model'!AI8+'Revenue Model'!AH8+'Revenue Model'!AG8+'Revenue Model'!AF8)*180 -> 59.646955 | AK45: =(+AK8+AF8)/('Revenue Model'!AK8+'Revenue Model'!AI8+'Revenue Model'!AH8+'Revenue Model'!AG8)*180 -> 78.238707 | AL45: =(+AL8+AG8)/('Revenue Model'!AL8+'Revenue Model'!AK8+'Revenue Model'!AI8+'Revenue Model'!AH8)*180 -> 56.730113 | AM45: =(+AM8+AH8)/('Revenue Model'!AM8+'Revenue Model'!AL8+'Revenue Model'!AK8+'Revenue Model'!AI8)*180 -> 61.858118 | AN45: =(+AN8+AI8)/('Revenue Model'!AN8+'Revenue Model'!AM8+'Revenue Model'!AL8+'Revenue Model'!AK8)*180 -> 55.403599 | AP45: =(+AP8+AK8)/('Revenue Model'!AP8+'Revenue Model'!AN8+'Revenue Model'!AM8+'Revenue Model'!AL8)*180 -> 59.997158 | AQ45: =(+AQ8+AL8)/('Revenue Model'!AQ8+'Revenue Model'!AP8+'Revenue Model'!AN8+'Revenue Model'!AM8)*180 -> 59.161943 | AR45: =(+AR8+AM8)/('Revenue Model'!AR8+'Revenue Model'!AQ8+'Revenue Model'!AP8+'Revenue Model'!AN8)*180 -> 61.910745 | AS45: =(+AS8+AN8)/('Revenue Model'!AS8+'Revenue Model'!AR8+'Revenue Model'!AQ8+'Revenue Model'!AP8)*180 -> 61.413404 | AU45: =(+AU8+AP8)/('Revenue Model'!AU8+'Revenue Model'!AS8+'Revenue Model'!AR8+'Revenue Model'!AQ8)*180 -> 59.314504 | AV45: =(+AV8+AQ8)/('Revenue Model'!AV8+'Revenue Model'!AU8+'Revenue Model'!AS8+'Revenue Model'!AR8)*180 -> 51.580637 | AW45: =(+AW8+AR8)/('Revenue Model'!AW8+'Revenue Model'!AV8+'Revenue Model'!AU8+'Revenue Model'!AS8)*180 -> 46.620391 | AX45: =(+AX8+AS8)/('Revenue Model'!AX8+'Revenue Model'!AW8+'Revenue Model'!AV8+'Revenue Model'!AU8)*180 -> 46.523326 | AZ45: =(+AZ8+AU8)/('Revenue Model'!AZ8+'Revenue Model'!AX8+'Revenue Model'!AW8+'Revenue Model'!AV8)*180 -> 48.15726 | BA45: =(+BA8+AV8)/('Revenue Model'!BA8+'Revenue Model'!AZ8+'Revenue Model'!AX8+'Revenue Model'!AW8)*180 -> 45.122461 | BB45: =(+BB8+AW8)/('Revenue Model'!BB8+'Revenue Model'!BA8+'Revenue Model'!AZ8+'Revenue Model'!AX8)*180 -> 39.926887 | BC45: =(+BC8+AX8)/('Revenue Model'!BC8+'Revenue Model'!BB8+'Revenue Model'!BA8+'Revenue Model'!AZ8)*180 -> 37.336506 | BE45: =(+BE8+AZ8)/('Revenue Model'!BE8+'Revenue Model'!BC8+'Revenue Model'!BB8+'Revenue Model'!BA8)*180 -> 41.471671 | BF45: =(+BF8+BA8)/('Revenue Model'!BF8+'Revenue Model'!BE8+'Revenue Model'!BC8+'Revenue Model'!BB8)*180 -> 40.334264 | BG45: =(+BG8+BB8)/('Revenue Model'!BG8+'Revenue Model'!BF8+'Revenue Model'!BE8+'Revenue Model'!BC8)*180 -> 37.049374 | BH45: =(+BH8+BC8)/('Revenue Model'!BH8+'Revenue Model'!BG8+'Revenue Model'!BF8+'Revenue Model'!BE8)*180 -> 47.780588 | BJ45: =(+BJ8+BE8)/('Revenue Model'!BJ8+'Revenue Model'!BH8+'Revenue Model'!BG8+'Revenue Model'!BF8)*180 -> 46.35377 | BK45: =(+BK8+BF8)/('Revenue Model'!BK8+'Revenue Model'!BJ8+'Revenue Model'!BH8+'Revenue Model'!BG8)*180 -> 46.938353 | BL45: =(+BL8+BG8)/('Revenue Model'!BL8+'Revenue Model'!BK8+'Revenue Model'!BJ8+'Revenue Model'!BH8)*180 -> 44.444857 | BM45: =(+BM8+BH8)/('Revenue Model'!BM8+'Revenue Model'!BL8+'Revenue Model'!BK8+'Revenue Model'!BJ8)*180 -> 56.433282 | BO45: =(+BO8+BJ8)/('Revenue Model'!BO8+'Revenue Model'!BM8+'Revenue Model'!BL8+'Revenue Model'!BK8)*180 -> 51.409425 | BP45: =(+BP8+BK8)/('Revenue Model'!BP8+'Revenue Model'!BO8+'Revenue Model'!BM8+'Revenue Model'!BL8)*180 -> 56.586316 | BQ45: =(+BQ8+BL8)/('Revenue Model'!BQ8+'Revenue Model'!BP8+'Revenue Model'!BO8+'Revenue Model'!BM8)*180 -> 54.73756 | BR45: =(+BR8+BM8)/('Revenue Model'!BR8+'Revenue Model'!BQ8+'Revenue Model'!BP8+'Revenue Model'!BO8)*180 -> 55.9002
A47: Book Value/Share | O47: =O38/'Income Statement'!O33 -> 1.8791947 | Q47: =Q38/'Income Statement'!Q33 -> 1.5772876 | R47: =R38/'Income Statement'!R33 -> 1.4124471 | S47: =S38/'Income Statement'!S33 -> 1.2612696 | T47: =T38/'Income Statement'!T33 -> 1.0930679 | V47: =V38/'Income Statement'!V33 -> 0.87560263 | W47: =W38/'Income Statement'!W33 -> 0.75204943 | X47: =X38/'Income Statement'!X33 -> 2.0563678 | Y47: =Y38/'Income Statement'!Y33 -> 1.9580748 | AA47: =AA38/'Income Statement'!AA33 -> 2.0348522 | AB47: =AB38/'Income Statement'!AB33 -> 4.9190454 | AC47: =AC38/'Income Statement'!AC33 -> 4.7547253 | AD47: =AD38/'Income Statement'!AD33 -> 4.8773107 | AF47: =AF38/'Income Statement'!AF33 -> 4.6276326 | AG47: =AG38/'Income Statement'!AG33 -> 4.5038327 | AH47: =AH38/'Income Statement'!AH33 -> 7.7057968 | AI47: =AI38/'Income Statement'!AI33 -> 7.2739349 | AK47: =AK38/'Income Statement'!AK33 -> 15.406628 | AL47: =AL38/'Income Statement'!AL33 -> 14.448438 | AM47: =AM38/'Income Statement'!AM33 -> 15.881456 | AN47: =AN38/'Income Statement'!AN33 -> 15.434676 | AP47: =AP38/'Income Statement'!AP33 -> 15.238986 | AQ47: =AQ38/'Income Statement'!AQ33 -> 14.888027 | AR47: =AR38/'Income Statement'!AR33 -> 14.627761 | AS47: =AS38/'Income Statement'!AS33 -> 14.969561 | AU47: =AU38/'Income Statement'!AU33 -> 14.708451 | AV47: =AV38/'Income Statement'!AV33 -> 14.690806 | AW47: =AW38/'Income Statement'!AW33 -> 14.218886 | AX47: =AX38/'Income Statement'!AX33 -> 14.066857 | AZ47: =AZ38/'Income Statement'!AZ33 -> 14.742911 | BA47: =BA38/'Income Statement'!BA33 -> 14.676993 | BB47: =BB38/'Income Statement'!BB33 -> 14.988175 | BC47: =BC38/'Income Statement'!BC33 -> 14.716976 | BE47: =BE38/'Income Statement'!BE33 -> 14.926247 | BF47: =BF38/'Income Statement'!BF33 -> 15.369026 | BG47: =BG38/'Income Statement'!BG33 -> 15.781655 | BH47: =BH38/'Income Statement'!BH33 -> 16.103426 | BJ47: =BJ38/'Income Statement'!BJ33 -> 16.969236 | BK47: =BK38/'Income Statement'!BK33 -> 17.440116 | BL47: =BL38/'Income Statement'!BL33 -> 17.902148 | BM47: =BM38/'Income Statement'!BM33 -> 18.39176 | BO47: =BO38/'Income Statement'!BO33 -> 18.842596 | BP47: =BP38/'Income Statement'!BP33 -> 19.353973 | BQ47: =BQ38/'Income Statement'!BQ33 -> 19.856666 | BR47: =BR38/'Income Statement'!BR33 -> 20.390064
A48: Return on Equity | O48: NA | Q48: NM | R48: NM | S48: NM | T48: NM | V48: NM | W48: NM | X48: NM | Y48: NM | AA48: NM | AB48: NM | AC48: NM | AD48: NM | AF48: NM | AG48: NM | AH48: NM | AI48: NM | AK48: =4*'Income Statement'!AK26/((AI38+AK38)/2) -> -0.02997305 | AL48: =4*'Income Statement'!AL26/((AK38+AL38)/2) -> -0.021823706 | AM48: =4*'Income Statement'!AM26/((AL38+AM38)/2) -> -0.035172797 | AN48: =4*'Income Statement'!AN26/((AM38+AN38)/2) -> -0.018340758 | AP48: =4*'Income Statement'!AP26/((AN38+AP38)/2) -> -0.014813559 | AQ48: =4*'Income Statement'!AQ26/((AP38+AQ38)/2) -> 0.00059173277 | AR48: =4*'Income Statement'!AR26/((AQ38+AR38)/2) -> -0.0016626206 | AS48: =4*'Income Statement'!AS26/((AR38+AS38)/2) -> 0.015074101 | AU48: =4*'Income Statement'!AU26/((AS38+AU38)/2) -> 0.026944171 | AV48: =4*'Income Statement'!AV26/((AU38+AV38)/2) -> 0.031564106 | AW48: =4*'Income Statement'!AW26/((AV38+AW38)/2) -> 0.045848491 | AX48: =4*'Income Statement'!AX26/((AW38+AX38)/2) -> 0.058134719 | AZ48: =4*'Income Statement'!AZ26/((AX38+AZ38)/2) -> 0.054108864 | BA48: =4*'Income Statement'!BA26/((AZ38+BA38)/2) -> 0.083167346 | BB48: =4*'Income Statement'!BB26/((BA38+BB38)/2) -> 0.090057448 | BC48: =4*'Income Statement'!BC26/((BB38+BC38)/2) -> 0.098465651 | BE48: =4*'Income Statement'!BE26/((BC38+BE38)/2) -> 0.082587977 | BF48: =4*'Income Statement'!BF26/((BE38+BF38)/2) -> 0.11573543 | BG48: =4*'Income Statement'!BG26/((BF38+BG38)/2) -> 0.13198404 | BH48: =4*'Income Statement'!BH26/((BG38+BH38)/2) -> 0.13336562 | BJ48: =4*'Income Statement'!BJ26/((BH38+BJ38)/2) -> 0.085112151 | BK48: =4*'Income Statement'!BK26/((BJ38+BK38)/2) -> 0.096059286 | BL48: =4*'Income Statement'!BL26/((BK38+BL38)/2) -> 0.09275632 | BM48: =4*'Income Statement'!BM26/((BL38+BM38)/2) -> 0.09869899 | BO48: =4*'Income Statement'!BO26/((BM38+BO38)/2) -> 0.084892806 | BP48: =4*'Income Statement'!BP26/((BO38+BP38)/2) -> 0.095916637 | BQ48: =4*'Income Statement'!BQ26/((BP38+BQ38)/2) -> 0.09279256 | BR48: =4*'Income Statement'!BR26/((BQ38+BR38)/2) -> 0.098573336
A49: Return on Equity (Rolling 4 Qtr) | O49: NA | Q49: NM | R49: NM | S49: NM | T49: NM | V49: NM | W49: NM | X49: NM | Y49: NM | AA49: NM | AB49: NM | AC49: NM | AD49: NM | AF49: NM | AG49: NM | AH49: NM | AI49: NM | AK49: =(+'Income Statement'!AK26+'Income Statement'!AI26+'Income Statement'!AH26+'Income Statement'!AG26)/((AK38+AF38)/2) -> -0.040807528 | AL49: =(+'Income Statement'!AL26+'Income Statement'!AK26+'Income Statement'!AI26+'Income Statement'!AH26)/((AL38+AG38)/2) -> -0.033656473 | AM49: =(+'Income Statement'!AM26+'Income Statement'!AL26+'Income Statement'!AK26+'Income Statement'!AI26)/((AM38+AH38)/2) -> -0.034591929 | AN49: =(+'Income Statement'!AN26+'Income Statement'!AM26+'Income Statement'!AL26+'Income Statement'!AK26)/((AN38+AI38)/2) -> -0.032591621 | AP49: =(+'Income Statement'!AP26+'Income Statement'!AN26+'Income Statement'!AM26+'Income Statement'!AL26)/((AP38+AK38)/2) -> -0.022856633 | AQ49: =(+'Income Statement'!AQ26+'Income Statement'!AP26+'Income Statement'!AN26+'Income Statement'!AM26)/((AQ38+AL38)/2) -> -0.017755625 | AR49: =(+'Income Statement'!AR26+'Income Statement'!AQ26+'Income Statement'!AP26+'Income Statement'!AN26)/((AR38+AM38)/2) -> -0.008697431 | AS49: =(+'Income Statement'!AS26+'Income Statement'!AR26+'Income Statement'!AQ26+'Income Statement'!AP26)/((AS38+AN38)/2) -> -0.00029465157 | AU49: =(+'Income Statement'!AU26+'Income Statement'!AS26+'Income Statement'!AR26+'Income Statement'!AQ26)/((AU38+AP38)/2) -> 0.010138795 | AV49: =(+'Income Statement'!AV26+'Income Statement'!AU26+'Income Statement'!AS26+'Income Statement'!AR26)/((AV38+AQ38)/2) -> 0.018038362 | AW49: =(+'Income Statement'!AW26+'Income Statement'!AV26+'Income Statement'!AU26+'Income Statement'!AS26)/((AW38+AR38)/2) -> 0.030489441 | AX49: =(+'Income Statement'!AX26+'Income Statement'!AW26+'Income Statement'!AV26+'Income Statement'!AU26)/((AX38+AS38)/2) -> 0.040856848 | AZ49: =(+'Income Statement'!AZ26+'Income Statement'!AX26+'Income Statement'!AW26+'Income Statement'!AV26)/((AZ38+AU38)/2) -> 0.046055562 | BA49: =(+'Income Statement'!BA26+'Income Statement'!AZ26+'Income Statement'!AX26+'Income Statement'!AW26)/((BA38+AV38)/2) -> 0.059157446 | BB49: =(+'Income Statement'!BB26+'Income Statement'!BA26+'Income Statement'!AZ26+'Income Statement'!AX26)/((BB38+AW38)/2) -> 0.071087304 | BC49: =(+'Income Statement'!BC26+'Income Statement'!BB26+'Income Statement'!BA26+'Income Statement'!AZ26)/((BC38+AX38)/2) -> 0.08375233 | BE49: =(+'Income Statement'!BE26+'Income Statement'!BC26+'Income Statement'!BB26+'Income Statement'!BA26)/((BE38+AZ38)/2) -> 0.088880187 | BF49: =(+'Income Statement'!BF26+'Income Statement'!BE26+'Income Statement'!BC26+'Income Statement'!BB26)/((BF38+BA38)/2) -> 0.097183808 | BG49: =(+'Income Statement'!BG26+'Income Statement'!BF26+'Income Statement'!BE26+'Income Statement'!BC26)/((BG38+BB38)/2) -> 0.10623374 | BH49: =(+'Income Statement'!BH26+'Income Statement'!BG26+'Income Statement'!BF26+'Income Statement'!BE26)/((BH38+BC38)/2) -> 0.11512774 | BJ49: =(+'Income Statement'!BJ26+'Income Statement'!BH26+'Income Statement'!BG26+'Income Statement'!BF26)/((BJ38+BE38)/2) -> 0.11548379 | BK49: =(+'Income Statement'!BK26+'Income Statement'!BJ26+'Income Statement'!BH26+'Income Statement'!BG26)/((BK38+BF38)/2) -> 0.11084753 | BL49: =(+'Income Statement'!BL26+'Income Statement'!BK26+'Income Statement'!BJ26+'Income Statement'!BH26)/((BL38+BG38)/2) -> 0.1015679 | BM49: =(+'Income Statement'!BM26+'Income Statement'!BL26+'Income Statement'!BK26+'Income Statement'!BJ26)/((BM38+BH38)/2) -> 0.093132296 | BO49: =(+'Income Statement'!BO26+'Income Statement'!BM26+'Income Statement'!BL26+'Income Statement'!BK26)/((BO38+BJ38)/2) -> 0.092984878 | BP49: =(+'Income Statement'!BP26+'Income Statement'!BO26+'Income Statement'!BM26+'Income Statement'!BL26)/((BP38+BK38)/2) -> 0.09295121 | BQ49: =(+'Income Statement'!BQ26+'Income Statement'!BP26+'Income Statement'!BO26+'Income Statement'!BM26)/((BQ38+BL38)/2) -> 0.09295965 | BR49: =(+'Income Statement'!BR26+'Income Statement'!BQ26+'Income Statement'!BP26+'Income Statement'!BO26)/((BR38+BM38)/2) -> 0.093016255
A50: Long-Term Debt/Total Capital | O50: =+O27/(O38+O27) -> 0.29489106 | Q50: =+Q27/(Q38+Q27) -> 0.31859402 | R50: =+R27/(R38+R27) -> 0.34293758 | S50: =+S27/(S38+S27) -> 0.36861664 | T50: =+T27/(T38+T27) -> 0.40117111 | V50: =+V27/(V38+V27) -> 0.45463798 | W50: =+W27/(W38+W27) -> 0.49309552 | X50: =+X27/(X38+X27) -> 0.24082058 | Y50: =+Y27/(Y38+Y27) -> 0.24069614 | AA50: =+AA27/(AA38+AA27) -> 0.13302838 | AB50: =+AB27/(AB38+AB27) -> 0.0026020238 | AC50: =+AC27/(AC38+AC27) -> 0.002758317 | AD50: =+AD27/(AD38+AD27) -> 0.0028898725 | AF50: =+AF27/(AF38+AF27) -> 0.003235714 | AG50: =+AG27/(AG38+AG27) -> 0.0035294429 | AH50: =+AH27/(AH38+AH27) -> 0.0017852041 | AI50: =+AI27/(AI38+AI27) -> 0.0019154778 | AK50: =+AK27/(AK38+AK27) -> 0.00088368621 | AL50: =+AL27/(AL38+AL27) -> 0.00094193393 | AM50: =+AM27/(AM38+AM27) -> 0.00096959792 | AN50: =+AN27/(AN38+AN27) -> 0 | AP50: =+AP27/(AP38+AP27) -> 0 | AQ50: =+AQ27/(AQ38+AQ27) -> 0 | AR50: =+AR27/(AR38+AR27) -> 0 | AS50: =+AS27/(AS38+AS27) -> 0 | AU50: =+AU27/(AU38+AU27) -> 0 | AV50: =+AV27/(AV38+AV27) -> 0 | AW50: =+AW27/(AW38+AW27) -> 0 | AX50: =+AX27/(AX38+AX27) -> 0 | AZ50: =+AZ27/(AZ38+AZ27) -> 0 | BA50: =+BA27/(BA38+BA27) -> 0 | BB50: =+BB27/(BB38+BB27) -> 0 | BC50: =+BC27/(BC38+BC27) -> 0 | BE50: =+BE27/(BE38+BE27) -> 0 | BF50: =+BF27/(BF38+BF27) -> 0 | BG50: =+BG27/(BG38+BG27) -> 0 | BH50: =+BH27/(BH38+BH27) -> 0 | BJ50: =+BJ27/(BJ38+BJ27) -> 0 | BK50: =+BK27/(BK38+BK27) -> 0 | BL50: =+BL27/(BL38+BL27) -> 0 | BM50: =+BM27/(BM38+BM27) -> 0 | BO50: =+BO27/(BO38+BO27) -> 0 | BP50: =+BP27/(BP38+BP27) -> 0 | BQ50: =+BQ27/(BQ38+BQ27) -> 0 | BR50: =+BR27/(BR38+BR27) -> 0
A51: EBIT | O51: =+'Income Statement'!O20+'Income Statement'!O22 -> -3.33 | Q51: =+'Income Statement'!Q20+'Income Statement'!Q22 -> -7.15 | R51: =+'Income Statement'!R20+'Income Statement'!R22 -> -6.224 | S51: =+'Income Statement'!S20+'Income Statement'!S22 -> -5.967 | T51: =+'Income Statement'!T20+'Income Statement'!T22 -> -5.654 | V51: =+'Income Statement'!V20+'Income Statement'!V22 -> -8.462 | W51: =+'Income Statement'!W20+'Income Statement'!W22 -> -5.501 | X51: =+'Income Statement'!X20+'Income Statement'!X22 -> -3.704 | Y51: =+'Income Statement'!Y20+'Income Statement'!Y22 -> -2.302 | AA51: =+'Income Statement'!AA20+'Income Statement'!AA22 -> -1.347 | AB51: =+'Income Statement'!AB20+'Income Statement'!AB22 -> -1.993 | AC51: =+'Income Statement'!AC20+'Income Statement'!AC22 -> -0.405 | AD51: =+'Income Statement'!AD20+'Income Statement'!AD22 -> -6.796 | AF51: =+'Income Statement'!AF20+'Income Statement'!AF22 -> -9.298 | AG51: =+'Income Statement'!AG20+'Income Statement'!AG22 -> -9.687 | AH51: =+'Income Statement'!AH20+'Income Statement'!AH22 -> -2.795 | AI51: =+'Income Statement'!AI20+'Income Statement'!AI22 -> -6.717 | AK51: =+'Income Statement'!AK20+'Income Statement'!AK22 -> -8.709 | AL51: =+'Income Statement'!AL20+'Income Statement'!AL22 -> -5.404 | AM51: =+'Income Statement'!AM20+'Income Statement'!AM22 -> -11.698 | AN51: =+'Income Statement'!AN20+'Income Statement'!AN22 -> -6.859 | AP51: =+'Income Statement'!AP20+'Income Statement'!AP22 -> -4.044 | AQ51: =+'Income Statement'!AQ20+'Income Statement'!AQ22 -> 0.044 | AR51: =+'Income Statement'!AR20+'Income Statement'!AR22 -> -0.591 | AS51: =+'Income Statement'!AS20+'Income Statement'!AS22 -> 4.404 | AU51: =+'Income Statement'!AU20+'Income Statement'!AU22 -> 7.839 | AV51: =+'Income Statement'!AV20+'Income Statement'!AV22 -> 9.214 | AW51: =+'Income Statement'!AW20+'Income Statement'!AW22 -> 13.216 | AX51: =+'Income Statement'!AX20+'Income Statement'!AX22 -> 16.455 | AZ51: =+'Income Statement'!AZ20+'Income Statement'!AZ22 -> 15.716 | BA51: =+'Income Statement'!BA20+'Income Statement'!BA22 -> 25.144 | BB51: =+'Income Statement'!BB20+'Income Statement'!BB22 -> 27.914 | BC51: =+'Income Statement'!BC20+'Income Statement'!BC22 -> 25.449 | BE51: =+'Income Statement'!BE20+'Income Statement'!BE22 -> 25.536 | BF51: =+'Income Statement'!BF20+'Income Statement'!BF22 -> 36.745 | BG51: =+'Income Statement'!BG20+'Income Statement'!BG22 -> 40.081 | BH51: =+'Income Statement'!BH20+'Income Statement'!BH22 -> 43.89 | BJ51: =+'Income Statement'!BJ20+'Income Statement'!BJ22 -> 29.800344 | BK51: =+'Income Statement'!BK20+'Income Statement'!BK22 -> 34.697707 | BL51: =+'Income Statement'!BL20+'Income Statement'!BL22 -> 34.585506 | BM51: =+'Income Statement'!BM20+'Income Statement'!BM22 -> 37.98082 | BO51: =+'Income Statement'!BO20+'Income Statement'!BO22 -> 33.680741 | BP51: =+'Income Statement'!BP20+'Income Statement'!BP22 -> 39.230736 | BQ51: =+'Income Statement'!BQ20+'Income Statement'!BQ22 -> 39.152008 | BR51: =+'Income Statement'!BR20+'Income Statement'!BR22 -> 42.898933
A52: Total Operating Assets | O52: =+O20-O7 -> 41.815 | Q52: =+Q20-Q7 -> 41.1 | R52: =+R20-R7 -> 41.884 | S52: =+S20-S7 -> 42.464 | T52: =+T20-T7 -> 44.778 | V52: =+V20-V7 -> 44.038 | W52: =+W20-W7 -> 41.703 | X52: =+X20-X7 -> 41.231 | Y52: =+Y20-Y7 -> 42.643 | AA52: =+AA20-AA7 -> 55.696 | AB52: =+AB20-AB7 -> 59.73 | AC52: =+AC20-AC7 -> 64.645 | AD52: =+AD20-AD7 -> 115.895 | AF52: =+AF20-AF7 -> 113.968 | AG52: =+AG20-AG7 -> 109.287 | AH52: =+AH20-AH7 -> 109.071 | AI52: =+AI20-AI7 -> 107.799 | AK52: =+AK20-AK7 -> 701.074 | AL52: =+AL20-AL7 -> 699.89 | AM52: =+AM20-AM7 -> 1022.327 | AN52: =+AN20-AN7 -> 1014.628 | AP52: =+AP20-AP7 -> 1009.974 | AQ52: =+AQ20-AQ7 -> 990.751 | AR52: =+AR20-AR7 -> 955.845 | AS52: =+AS20-AS7 -> 1002.175 | AU52: =+AU20-AU7 -> 979.229 | AV52: =+AV20-AV7 -> 969.972 | AW52: =+AW20-AW7 -> 922.48 | AX52: =+AX20-AX7 -> 898.452 | AZ52: =+AZ20-AZ7 -> 990.885 | BA52: =+BA20-BA7 -> 998.412 | BB52: =+BB20-BB7 -> 1000.942 | BC52: =+BC20-BC7 -> 1010.594 | BE52: =+BE20-BE7 -> 1028.056 | BF52: =+BF20-BF7 -> 1023.385 | BG52: =+BG20-BG7 -> 1001.359 | BH52: =+BH20-BH7 -> 1040.6262 | BJ52: =+BJ20-BJ7 -> 1034.3353 | BK52: =+BK20-BK7 -> 1046.643 | BL52: =+BL20-BL7 -> 1047.8155 | BM52: =+BM20-BM7 -> 1056.4236 | BO52: =+BO20-BO7 -> 1052.2743 | BP52: =+BP20-BP7 -> 1067.3053 | BQ52: =+BQ20-BQ7 -> 1069.8951 | BR52: =+BR20-BR7 -> 1080.2429
A53: Return on Assets | O53: NA | Q53: NM | R53: NM | S53: NM | T53: NM | V53: NM | W53: NM | X53: NM | Y53: NM | AA53: NM | AB53: NM | AC53: NM | AD53: NM | AF53: NM | AG53: NM | AH53: NM | AI53: NM | AK53: =4*AK51/((AI52+AK52)/2) -> -0.086134659 | AL53: =4*AL51/((AK52+AL52)/2) -> -0.030858752 | AM53: =4*AM51/((AL52+AM52)/2) -> -0.054339262 | AN53: =4*AN51/((AM52+AN52)/2) -> -0.026938249 | AP53: =4*AP51/((AN52+AP52)/2) -> -0.015979437 | AQ53: =4*AQ51/((AP52+AQ52)/2) -> 0.00017593622 | AR53: =4*AR51/((AQ52+AR52)/2) -> -0.0024288553 | AS53: =4*AS51/((AR52+AS52)/2) -> 0.017993688 | AU53: =4*AU51/((AS52+AU52)/2) -> 0.031650284 | AV53: =4*AV51/((AU52+AV52)/2) -> 0.037816521 | AW53: =4*AW51/((AV52+AW52)/2) -> 0.05586826 | AX53: =4*AX51/((AW52+AX52)/2) -> 0.07229265 | AZ53: =4*AZ51/((AX52+AZ52)/2) -> 0.066546095 | BA53: =4*BA51/((AZ52+BA52)/2) -> 0.10111713 | BB53: =4*BB51/((BA52+BB52)/2) -> 0.11169208 | BC53: =4*BC51/((BB52+BC52)/2) -> 0.10121221 | BE53: =4*BE51/((BC52+BE52)/2) -> 0.10020749 | BF53: =4*BF51/((BE52+BF52)/2) -> 0.1432944 | BG53: =4*BG51/((BF52+BG52)/2) -> 0.15836471 | BH53: =4*BH51/((BG52+BH52)/2) -> 0.17195032 | BJ53: =4*BJ51/((BH52+BJ52)/2) -> 0.11489502 | BK53: =4*BK51/((BJ52+BK52)/2) -> 0.13338998 | BL53: =4*BL51/((BK52+BL52)/2) -> 0.1321029 | BM53: =4*BM51/((BL52+BM52)/2) -> 0.14439736 | BO53: =4*BO51/((BM52+BO52)/2) -> 0.12777834 | BP53: =4*BP51/((BO52+BP52)/2) -> 0.14806987 | BQ53: =4*BQ51/((BP52+BQ52)/2) -> 0.14655437 | BR53: =4*BR51/((BQ52+BR52)/2) -> 0.15961369
A54: Return on Assets (Rolling 4 Qtr) | O54: NA | Q54: NM | R54: NM | S54: NM | T54: NM | V54: NM | W54: NM | X54: NM | Y54: NM | AA54: NM | AB54: NM | AC54: NM | AD54: NM | AF54: NM | AG54: NM | AH54: NM | AI54: NM | AK54: =+(AK51+AI51+AH51+AG51)/((AK52+AF52)/2) -> -0.06848236 | AL54: =+(AL51+AK51+AI51+AH51)/((AL52+AG52)/2) -> -0.058392663 | AM54: =+(AM51+AL51+AK51+AI51)/((AM52+AH52)/2) -> -0.057500544 | AN54: =+(AN51+AM51+AL51+AK51)/((AN52+AI52)/2) -> -0.05821314 | AP54: =+(AP51+AN51+AM51+AL51)/((AP52+AK52)/2) -> -0.032734324 | AQ54: =+(AQ51+AP51+AN51+AM51)/((AQ52+AL52)/2) -> -0.026684553 | AR54: =+(AR51+AQ51+AP51+AN51)/((AR52+AM52)/2) -> -0.011576344 | AS54: =+(AS51+AR51+AQ51+AP51)/((AS52+AN52)/2) -> -0.00018544201 | AU54: =+(AU51+AS51+AR51+AQ51)/((AU52+AP52)/2) -> 0.011759484 | AV54: =+(AV51+AU51+AS51+AR51)/((AV52+AQ52)/2) -> 0.021283986 | AW54: =+(AW51+AV51+AU51+AS51)/((AW52+AR52)/2) -> 0.036919064 | AX54: =+(AX51+AW51+AV51+AU51)/((AX52+AS52)/2) -> 0.049166933 | AZ54: =+(AZ51+AX51+AW51+AV51)/((AZ52+AU52)/2) -> 0.05542928 | BA54: =+(BA51+AZ51+AX51+AW51)/((BA52+AV52)/2) -> 0.071663862 | BB54: =+(BB51+BA51+AZ51+AX51)/((BB52+AW52)/2) -> 0.088622258 | BC54: =+(BC51+BB51+BA51+AZ51)/((BC52+AX52)/2) -> 0.098712132 | BE54: =+(BE51+BC51+BB51+BA51)/((BE52+AZ52)/2) -> 0.1030669 | BF54: =+(BF51+BE51+BC51+BB51)/((BF52+BA52)/2) -> 0.11439724 | BG54: =+(BG51+BF51+BE51+BC51)/((BG52+BB52)/2) -> 0.12766412 | BH54: =+(BH51+BG51+BF51+BE51)/((BH52+BC52)/2) -> 0.1426 | BJ54: =+(BJ51+BH51+BG51+BF51)/((BJ52+BE52)/2) -> 0.14596294 | BK54: =+(BK51+BJ51+BH51+BG51)/((BK52+BF52)/2) -> 0.14344642 | BL54: =+(BL51+BK51+BJ51+BH51)/((BL52+BG52)/2) -> 0.13954259 | BM54: =+(BM51+BL51+BK51+BJ51)/((BM52+BH52)/2) -> 0.13072115 | BO54: =+(BO51+BM51+BL51+BK51)/((BO52+BJ52)/2) -> 0.13509453 | BP54: =+(BP51+BO51+BM51+BL51)/((BP52+BK52)/2) -> 0.1376361 | BQ54: =+(BQ51+BP51+BO51+BM51)/((BQ52+BL52)/2) -> 0.14170426 | BR54: =+(BR51+BQ51+BP51+BO51)/((BR52+BM52)/2) -> 0.14505064
A55: Capital Employed | O55: =+O38+O27 -> 84.499 | Q55: =+Q38+Q27 -> 78.294 | R55: =+R38+R27 -> 72.815 | S55: =+S38+S27 -> 67.813 | T55: =+T38+T27 -> 62.163 | V55: =+V38+V27 -> 55.024 | W55: =+W38+W27 -> 50.909 | X55: =+X38+X27 -> 104.609 | Y55: =+Y38+Y27 -> 105.037 | AA55: =+AA38+AA27 -> 96.626 | AB55: =+AB38+AB27 -> 224.825 | AC55: =+AC38+AC27 -> 231.663 | AD55: =+AD38+AD27 -> 240.149 | AF55: =+AF38+AF27 -> 231.17 | AG55: =+AG38+AG27 -> 226.948 | AH55: =+AH38+AH27 -> 423.481 | AI55: =+AI38+AI27 -> 422.871 | AK55: =+AK38+AK27 -> 976.591 | AL55: =+AL38+AL27 -> 973.529 | AM55: =+AM38+AM27 -> 1108.707 | AN55: =+AN38+AN27 -> 1096.857 | AP55: =+AP38+AP27 -> 1085.468 | AQ55: =+AQ38+AQ27 -> 1064.151 | AR55: =+AR38+AR27 -> 1048.177 | AS55: =+AS38+AS27 -> 1075.2 | AU55: =+AU38+AU27 -> 1081.259 | AV55: =+AV38+AV27 -> 1082.718 | AW55: =+AW38+AW27 -> 1054.059 | AX55: =+AX38+AX27 -> 1044.102 | AZ55: =+AZ38+AZ27 -> 1118.649 | BA55: =+BA38+BA27 -> 1132.523 | BB55: =+BB38+BB27 -> 1176.042 | BC55: =+BC38+BC27 -> 1175.966 | BE55: =+BE38+BE27 -> 1194.936 | BF55: =+BF38+BF27 -> 1221.057 | BG55: =+BG38+BG27 -> 1257.667 | BH55: =+BH38+BH27 -> 1310.611 | BJ55: =+BJ38+BJ27 -> 1350.3793 | BK55: =+BK38+BK27 -> 1394.8271 | BL55: =+BL38+BL27 -> 1438.9404 | BM55: =+BM38+BM27 -> 1485.6512 | BO55: =+BO38+BO27 -> 1529.6059 | BP55: =+BP38+BP27 -> 1578.8601 | BQ55: =+BQ38+BQ27 -> 1627.8115 | BR55: =+BR38+BR27 -> 1679.6945
A56: NOPAT | O56: =+('Income Statement'!O20+'Income Statement'!Y22)*(1-'Income Statement'!O25) -> -2.917 | Q56: =+('Income Statement'!Q20+'Income Statement'!AA22)*(1-'Income Statement'!Q25) -> -6.797 | R56: =+('Income Statement'!R20+'Income Statement'!AB22)*(1-'Income Statement'!R25) -> -5.502 | S56: =+('Income Statement'!S20+'Income Statement'!AC22)*(1-'Income Statement'!S25) -> -5.01 | T56: =+('Income Statement'!T20+'Income Statement'!AD22)*(1-'Income Statement'!T25) -> -4.957 | V56: =+('Income Statement'!V20+'Income Statement'!AF22)*(1-'Income Statement'!V25) -> -8.149 | W56: =+('Income Statement'!W20+'Income Statement'!AG22)*(1-'Income Statement'!W25) -> -5.56 | X56: =+('Income Statement'!X20+'Income Statement'!AH22)*(1-'Income Statement'!X25) -> -4.04 | Y56: =+('Income Statement'!Y20+'Income Statement'!AI22)*(1-'Income Statement'!Y25) -> -2.708 | AA56: =+('Income Statement'!AA20+'Income Statement'!AK22)*(1-'Income Statement'!AA25) -> -1.995 | AB56: =+('Income Statement'!AB20+'Income Statement'!AL22)*(1-'Income Statement'!AB25) -> -4.487 | AC56: =+('Income Statement'!AC20+'Income Statement'!AM22)*(1-'Income Statement'!AC25) -> -1.496 | AD56: =+('Income Statement'!AD20+'Income Statement'!AN22)*(1-'Income Statement'!AD25) -> -7.616 | AF56: =+('Income Statement'!AF20+'Income Statement'!AP22)*(1-'Income Statement'!AF25) -> -9.053 | AG56: =+('Income Statement'!AG20+'Income Statement'!AQ22)*(1-'Income Statement'!AG25) -> -8.692 | AH56: =+('Income Statement'!AH20+'Income Statement'!AR22)*(1-'Income Statement'!AH25) -> -1.987 | AI56: =+('Income Statement'!AI20+'Income Statement'!AS22)*(1-'Income Statement'!AI25) -> -4.82 | AK56: =+('Income Statement'!AK20+'Income Statement'!AU22)*(1-'Income Statement'!AK25) -> -3.6501209 | AL56: =+('Income Statement'!AL20+'Income Statement'!AV22)*(1-'Income Statement'!AL25) -> -3.8664267 | AM56: =+('Income Statement'!AM20+'Income Statement'!AW22)*(1-'Income Statement'!AM25) -> -8.4793946 | AN56: =+('Income Statement'!AN20+'Income Statement'!AX22)*(1-'Income Statement'!AN25) -> -1.5776991 | AP56: =+('Income Statement'!AP20+'Income Statement'!BT22)*(1-'Income Statement'!AP25) -> -4.8244184 | AQ56: =+('Income Statement'!AQ20+'Income Statement'!BU22)*(1-'Income Statement'!AQ25) -> -3.7654091 | AR56: =+('Income Statement'!AR20+'Income Statement'!BV22)*(1-'Income Statement'!AR25) -> -1.0369611 | AS56: =+('Income Statement'!AS20+'Income Statement'!BW22)*(1-'Income Statement'!AS25) -> 2.2030938 | AU56: =+('Income Statement'!AU20+'Income Statement'!BY22)*(1-'Income Statement'!AU25) -> 5.0328634 | AV56: =+('Income Statement'!AV20+'Income Statement'!BZ22)*(1-'Income Statement'!AV25) -> 8.7474191 | AW56: =+('Income Statement'!AW20+'Income Statement'!CA22)*(1-'Income Statement'!AW25) -> 10.42337 | AX56: =+('Income Statement'!AX20+'Income Statement'!CB22)*(1-'Income Statement'!AX25) -> 10.581631 | AZ56: =+('Income Statement'!AZ20+'Income Statement'!CD22)*(1-'Income Statement'!AZ25) -> 12.070241 | BA56: =+('Income Statement'!BA20+'Income Statement'!CE22)*(1-'Income Statement'!BA25) -> 20.838759 | BB56: =+('Income Statement'!BB20+'Income Statement'!CF22)*(1-'Income Statement'!BB25) -> 23.155832 | BC56: =+('Income Statement'!BC20+'Income Statement'!CG22)*(1-'Income Statement'!BC25) -> 27.63174 | BE56: =+('Income Statement'!BE20+'Income Statement'!CI22)*(1-'Income Statement'!BE25) -> 21.197006 | BF56: =+('Income Statement'!BF20+'Income Statement'!CJ22)*(1-'Income Statement'!BF25) -> 31.162402 | BG56: =+('Income Statement'!BG20+'Income Statement'!CK22)*(1-'Income Statement'!BG25) -> 34.733748 | BH56: =+('Income Statement'!BH20+'Income Statement'!CL22)*(1-'Income Statement'!BH25) -> 39.460232 | BJ56: =+('Income Statement'!BJ20+'Income Statement'!CN22)*(1-'Income Statement'!BJ25) -> 28.215326 | BK56: =+('Income Statement'!BK20+'Income Statement'!CO22)*(1-'Income Statement'!BK25) -> 32.867822 | BL56: =+('Income Statement'!BL20+'Income Statement'!CP22)*(1-'Income Statement'!BL25) -> 32.761231 | BM56: =+('Income Statement'!BM20+'Income Statement'!CQ22)*(1-'Income Statement'!BM25) -> 35.986779 | BO56: =+('Income Statement'!BO20+'Income Statement'!CS22)*(1-'Income Statement'!BO25) -> 31.901704 | BP56: =+('Income Statement'!BP20+'Income Statement'!CT22)*(1-'Income Statement'!BP25) -> 37.1742 | BQ56: =+('Income Statement'!BQ20+'Income Statement'!CU22)*(1-'Income Statement'!BQ25) -> 37.099408 | BR56: =+('Income Statement'!BR20+'Income Statement'!CV22)*(1-'Income Statement'!BR25) -> 40.658987
A57: Return on Contributed Capital | O57: NA | Q57: NM | R57: NM | S57: NM | T57: NM | V57: NM | W57: NM | X57: NM | Y57: NM | AA57: NM | AB57: NM | AC57: NM | AD57: NM | AF57: NM | AG57: NM | AH57: NM | AI57: NM | AK57: =4*AK56/((AI55+AK55)/2) -> -0.020865852 | AL57: =4*AL56/((AK55+AL55)/2) -> -0.015861287 | AM57: =4*AM56/((AL55+AM55)/2) -> -0.032578035 | AN57: =4*AN56/((AM55+AN55)/2) -> -0.0057226147 | AP57: =4*AP56/((AN55+AP55)/2) -> -0.017685426 | AQ57: =4*AQ56/((AP55+AQ55)/2) -> -0.014013308 | AR57: =4*AR56/((AQ55+AR55)/2) -> -0.003927273 | AS57: =4*AS56/((AR55+AS55)/2) -> 0.0083003396 | AU57: =4*AU56/((AS55+AU55)/2) -> 0.018670843 | AV57: =4*AV56/((AU55+AV55)/2) -> 0.032338307 | AW57: =4*AW56/((AV55+AW55)/2) -> 0.039024642 | AX57: =4*AX56/((AW55+AX55)/2) -> 0.040346308 | AZ57: =4*AZ56/((AX55+AZ55)/2) -> 0.044647732 | BA57: =4*BA56/((AZ55+BA55)/2) -> 0.074054793 | BB57: =4*BB56/((BA55+BB55)/2) -> 0.080243206 | BC57: =4*BC56/((BB55+BC55)/2) -> 0.093985192 | BE57: =4*BE56/((BC55+BE55)/2) -> 0.071523853 | BF57: =4*BF56/((BE55+BF55)/2) -> 0.10318706 | BG57: =4*BG56/((BF55+BG55)/2) -> 0.11210203 | BH57: =4*BH56/((BG55+BH55)/2) -> 0.12291576 | BJ57: =4*BJ56/((BH55+BJ55)/2) -> 0.084826543 | BK57: =4*BK56/((BJ55+BK55)/2) -> 0.09578244 | BL57: =4*BL56/((BK55+BL55)/2) -> 0.092488125 | BM57: =4*BM56/((BL55+BM55)/2) -> 0.098439125 | BO57: =4*BO56/((BM55+BO55)/2) -> 0.084640754 | BP57: =4*BP56/((BO55+BP55)/2) -> 0.095672143 | BQ57: =4*BQ56/((BP55+BQ55)/2) -> 0.092555555 | BR57: =4*BR56/((BQ55+BR55)/2) -> 0.098343555
A58: ROIC (Rolling 4 Qtr) | O58: NA | Q58: NM | R58: NM | S58: NM | T58: NM | V58: NM | W58: NM | X58: NM | Y58: NM | AA58: NM | AB58: NM | AC58: NM | AD58: NM | AF58: NM | AG58: NM | AH58: NM | AI58: NM | AK58: =+(AK56+AI56+AH56+AG56)/((AK55+AF55)/2) -> -0.031710116 | AL58: =+(AL56+AK56+AI56+AH56)/((AL55+AG55)/2) -> -0.023863094 | AM58: =+(AM56+AL56+AK56+AI56)/((AM55+AH55)/2) -> -0.027171525 | AN58: =+(AN56+AM56+AL56+AK56)/((AN55+AI55)/2) -> -0.023127351 | AP58: =+(AP56+AN56+AM56+AL56)/((AP55+AK55)/2) -> -0.018183708 | AQ58: =+(AQ56+AP56+AN56+AM56)/((AQ55+AL55)/2) -> -0.018302109 | AR58: =+(AR56+AQ56+AP56+AN56)/((AR55+AM55)/2) -> -0.010389513 | AS58: =+(AS56+AR56+AQ56+AP56)/((AS55+AN55)/2) -> -0.0068356353 | AU58: =+(AU56+AS56+AR56+AQ56)/((AU55+AP55)/2) -> 0.0022463254 | AV58: =+(AV56+AU56+AS56+AR56)/((AV55+AQ55)/2) -> 0.013923919 | AW58: =+(AW56+AV56+AU56+AS56)/((AW55+AR55)/2) -> 0.025122532 | AX58: =+(AX56+AW56+AV56+AU56)/((AX55+AS55)/2) -> 0.032827113 | AZ58: =+(AZ56+AX56+AW56+AV56)/((AZ55+AU55)/2) -> 0.038022191 | BA58: =+(BA56+AZ56+AX56+AW56)/((BA55+AV55)/2) -> 0.048675517 | BB58: =+(BB56+BA56+AZ56+AX56)/((BB55+AW55)/2) -> 0.059769906 | BC58: =+(BC56+BB56+BA56+AZ56)/((BC55+AX55)/2) -> 0.075400008 | BE58: =+(BE56+BC56+BB56+BA56)/((BE55+AZ55)/2) -> 0.080241995 | BF58: =+(BF56+BE56+BC56+BB56)/((BF55+BA55)/2) -> 0.087651136 | BG58: =+(BG56+BF56+BE56+BC56)/((BG55+BB55)/2) -> 0.09427988 | BH58: =+(BH56+BG56+BF56+BE56)/((BH55+BC55)/2) -> 0.10178924 | BJ58: =+(BJ56+BH56+BG56+BF56)/((BJ55+BE55)/2) -> 0.10495494 | BK58: =+(BK56+BJ56+BH56+BG56)/((BK55+BF55)/2) -> 0.10342746 | BL58: =+(BL56+BK56+BJ56+BH56)/((BL55+BG55)/2) -> 0.098868387 | BM58: =+(BM56+BL56+BK56+BJ56)/((BM55+BH55)/2) -> 0.092860505 | BO58: =+(BO56+BM56+BL56+BK56)/((BO55+BJ55)/2) -> 0.092720987 | BP58: =+(BP56+BO56+BM56+BL56)/((BP55+BK55)/2) -> 0.092695636 | BQ58: =+(BQ56+BP56+BO56+BM56)/((BQ55+BL55)/2) -> 0.092711831 | BR58: =+(BR56+BQ56+BP56+BO56)/((BR55+BM55)/2) -> 0.092776155
A59: EBIT w/o FAS Stock Compensation Expense | O59: =+O51+'Cash Flow'!O10 -> -3.33 | Q59: =+Q51+'Cash Flow'!Q10 -> -5.578 | R59: =+R51+'Cash Flow'!R10 -> -4.582 | S59: =+S51+'Cash Flow'!S10 -> -4.356 | T59: =+T51+'Cash Flow'!T10 -> -3.862 | V59: =+V51+'Cash Flow'!V10 -> -7.287 | W59: =+W51+'Cash Flow'!W10 -> -3.77 | X59: =+X51+'Cash Flow'!X10 -> -2.185 | Y59: =+Y51+'Cash Flow'!Y10 -> -0.769 | AA59: =+AA51+'Cash Flow'!AA10 -> 0.412 | AB59: =+AB51+'Cash Flow'!AB10 -> 0.573 | AC59: =+AC51+'Cash Flow'!AC10 -> 2.235 | AD59: =+AD51+'Cash Flow'!AD10 -> -3.954 | AF59: =+AF51+'Cash Flow'!AF10 -> -6.393 | AG59: =+AG51+'Cash Flow'!AG10 -> -6.327 | AH59: =+AH51+'Cash Flow'!AH10 -> 0.294 | AI59: =+AI51+'Cash Flow'!AI10 -> -3.076 | AK59: =+AK51+'Cash Flow'!AK10 -> -4.854 | AL59: =+AL51+'Cash Flow'!AL10 -> -1.34 | AM59: =+AM51+'Cash Flow'!AM10 -> -3.83 | AN59: =+AN51+'Cash Flow'!AN10 -> -0.127 | AP59: =+AP51+'Cash Flow'!AP10 -> 2.601 | AQ59: =+AQ51+'Cash Flow'!AQ10 -> 5.983 | AR59: =+AR51+'Cash Flow'!AR10 -> 6.692 | AS59: =+AS51+'Cash Flow'!AS10 -> 11.271 | AU59: =+AU51+'Cash Flow'!AU10 -> 15.824 | AV59: =+AV51+'Cash Flow'!AV10 -> 19.595 | AW59: =+AW51+'Cash Flow'!AW10 -> 20.479 | AX59: =+AX51+'Cash Flow'!AX10 -> 23.967 | AZ59: =+AZ51+'Cash Flow'!AZ10 -> 23.735 | BA59: =+BA51+'Cash Flow'!BA10 -> 34.998 | BB59: =+BB51+'Cash Flow'!BB10 -> 36.661 | BC59: =+BC51+'Cash Flow'!BC10 -> 35.078 | BE59: =+BE51+'Cash Flow'!BT10 -> 25.536 | BF59: =+BF51+'Cash Flow'!BU10 -> 36.745 | BG59: =+BG51+'Cash Flow'!BV10 -> 40.081 | BH59: =+BH51+'Cash Flow'!BW10 -> 43.89 | BJ59: =+BJ51+'Cash Flow'!BY10 -> 29.800344 | BK59: =+BK51+'Cash Flow'!BZ10 -> 34.697707 | BL59: =+BL51+'Cash Flow'!CA10 -> 34.585506 | BM59: =+BM51+'Cash Flow'!CB10 -> 37.98082 | BO59: =+BO51+'Cash Flow'!CD10 -> 33.680741 | BP59: =+BP51+'Cash Flow'!CE10 -> 39.230736 | BQ59: =+BQ51+'Cash Flow'!CF10 -> 39.152008 | BR59: =+BR51+'Cash Flow'!CG10 -> 42.898933
A60: EBIT Growth | O60: NA | Q60: NM | R60: NM | S60: NM | T60: NM | V60: NM | W60: NM | X60: NM | Y60: NM | AA60: NM | AB60: NM | AC60: NM | AD60: NM | AF60: NM | AG60: NM | AH60: NM | AI60: NM | AK60: NM | AL60: NM | AM60: NM | AN60: NM | AP60: =+AP59/AK59-1 -> -1.5358467 | AQ60: =+AQ59/AL59-1 -> -5.4649254 | AR60: =+AR59/AM59-1 -> -2.7472585 | AS60: =+AS59/AN59-1 -> -89.748031 | AU60: =+AU59/AP59-1 -> 5.0838139 | AV60: =+AV59/AQ59-1 -> 2.2751128 | AW60: =+AW59/AR59-1 -> 2.0602212 | AX60: =+AX59/AS59-1 -> 1.1264307 | AZ60: =+AZ59/AU59-1 -> 0.4999368 | BA60: =+BA59/AV59-1 -> 0.78606787 | BB60: =+BB59/AW59-1 -> 0.7901753 | BC60: =+BC59/AX59-1 -> 0.46359578 | BE60: =+BE59/AZ59-1 -> 0.075879503 | BF60: =+BF59/BA59-1 -> 0.049917138 | BG60: =+BG59/BB59-1 -> 0.093287144 | BH60: =+BH59/BC59-1 -> 0.25121159 | BJ60: =+BJ59/BE59-1 -> 0.16699341 | BK60: =+BK59/BF59-1 -> -0.055716231 | BL60: =+BL59/BG59-1 -> -0.1371097 | BM60: =+BM59/BH59-1 -> -0.13463614 | BO60: =+BO59/BJ59-1 -> 0.13021316 | BP60: =+BP59/BK59-1 -> 0.13064348 | BQ60: =+BQ59/BL59-1 -> 0.13203514 | BR60: =+BR59/BM59-1 -> 0.12948939
A61: LTM EBIT Growth | O61: NA | Q61: NM | R61: NM | S61: NM | T61: NM | V61: NM | W61: NM | X61: NM | Y61: NM | AA61: NM | AB61: NM | AC61: NM | AD61: NM | AF61: NM | AG61: NM | AH61: NM | AI61: NM | AK61: NM | AL61: NM | AM61: NM | AN61: NM | AP61: =(AP59+AL59+AN59+AM59)/(AK59+AG59+AI59+AH59)-1 -> -0.80691828 | AQ61: =(AQ59+AM59+AP59+AN59)/(AL59+AH59+AK59+AI59)-1 -> -1.5154857 | AR61: =(AR59+AN59+AQ59+AP59)/(AM59+AI59+AL59+AK59)-1 -> -2.1564122 | AS61: =(AS59+AR59+AQ59+AP59)/(AN59+AM59+AL59+AK59)-1 -> -3.6152103 | AU61: =(AU59+AQ59+AS59+AR59)/(AP59+AL59+AN59+AM59)-1 -> -15.751484 | AV61: =(AV59+AR59+AU59+AS59)/(AQ59+AM59+AP59+AN59)-1 -> 10.537065 | AW61: =(AW59+AS59+AV59+AU59)/(AR59+AN59+AQ59+AP59)-1 -> 3.43389 | AX61: =(AX59+AW59+AV59+AU59)/(AS59+AR59+AQ59+AP59)-1 -> 2.0084379 | AZ61: =(AZ59+AV59+AX59+AW59)/(AU59+AQ59+AS59+AR59)-1 -> 1.2070908 | BA61: =(BA59+AW59+AZ59+AX59)/(AV59+AR59+AU59+AS59)-1 -> 0.93284253 | BB61: =(BB59+AX59+BA59+AZ59)/(AW59+AS59+AV59+AU59)-1 -> 0.77702512 | BC61: =(BC59+BB59+BA59+AZ59)/(AX59+AW59+AV59+AU59)-1 -> 0.6336568 | BE61: =(BE59+BA59+BC59+BB59)/(AZ59+AV59+AX59+AW59)-1 -> 0.50693812 | BF61: =(BF59+BB59+BE59+BC59)/(BA59+AW59+AZ59+AX59)-1 -> 0.29890772 | BG61: =(BG59+BC59+BF59+BE59)/(BB59+AX59+BA59+AZ59)-1 -> 0.15146488 | BH61: =(BH59+BG59+BF59+BE59)/(BC59+BB59+BA59+AZ59)-1 -> 0.12094549 | BJ61: =(BJ59+BF59+BH59+BG59)/(BE59+BA59+BC59+BB59)-1 -> 0.1379219 | BK61: =(BK59+BG59+BJ59+BH59)/(BF59+BB59+BE59+BC59)-1 -> 0.10781265 | BL61: =(BL59+BH59+BK59+BJ59)/(BG59+BC59+BF59+BE59)-1 -> 0.040261619 | BM61: =(BM59+BL59+BK59+BJ59)/(BH59+BG59+BF59+BE59)-1 -> -0.062820496 | BO61: =(BO59+BK59+BM59+BL59)/(BJ59+BF59+BH59+BG59)-1 -> -0.063591565 | BP61: =(BP59+BL59+BO59+BM59)/(BK59+BG59+BJ59+BH59)-1 -> -0.020147281 | BQ61: =(BQ59+BM59+BP59+BO59)/(BL59+BH59+BK59+BJ59)-1 -> 0.049454936 | BR61: =(BR59+BQ59+BP59+BO59)/(BM59+BL59+BK59+BJ59)-1 -> 0.13058128
A62: Taxes | O62: =+'Income Statement'!O26/'Income Statement'!O23 -> 1 | Q62: =+'Income Statement'!Q26/'Income Statement'!Q23 -> 1 | R62: =+'Income Statement'!R26/'Income Statement'!R23 -> 1 | S62: =+'Income Statement'!S26/'Income Statement'!S23 -> 1 | T62: =+'Income Statement'!T26/'Income Statement'!T23 -> 1 | V62: =+'Income Statement'!V26/'Income Statement'!V23 -> 1 | W62: =+'Income Statement'!W26/'Income Statement'!W23 -> 1 | X62: =+'Income Statement'!X26/'Income Statement'!X23 -> 1 | Y62: =+'Income Statement'!Y26/'Income Statement'!Y23 -> 1 | AA62: =+'Income Statement'!AA26/'Income Statement'!AA23 -> 1 | AB62: =+'Income Statement'!AB26/'Income Statement'!AB23 -> 1 | AC62: =+'Income Statement'!AC26/'Income Statement'!AC23 -> 1 | AD62: =+'Income Statement'!AD26/'Income Statement'!AD23 -> 1 | AF62: =+'Income Statement'!AF26/'Income Statement'!AF23 -> 1 | AG62: =+'Income Statement'!AG26/'Income Statement'!AG23 -> 1 | AH62: =+'Income Statement'!AH26/'Income Statement'!AH23 -> 1 | AI62: =+'Income Statement'!AI26/'Income Statement'!AI23 -> 1 | AK62: =+'Income Statement'!AK26/'Income Statement'!AK23 -> 0.59769459 | AL62: =+'Income Statement'!AL26/'Income Statement'!AL23 -> 0.97219682 | AM62: =+'Income Statement'!AM26/'Income Statement'!AM23 -> 0.87137957 | AN62: =+'Income Statement'!AN26/'Income Statement'!AN23 -> 0.86496663 | AP62: =+'Income Statement'!AP26/'Income Statement'!AP23 -> 0.99925816 | AQ62: =+'Income Statement'!AQ26/'Income Statement'!AQ23 -> 3.6136364 | AR62: =+'Income Statement'!AR26/'Income Statement'!AR23 -> 0.7428088 | AS62: =+'Income Statement'!AS26/'Income Statement'!AS23 -> 0.90849228 | AU62: =+'Income Statement'!AU26/'Income Statement'!AU23 -> 0.92652124 | AV62: =+'Income Statement'!AV26/'Income Statement'!AV23 -> 0.92663338 | AW62: =+'Income Statement'!AW26/'Income Statement'!AW23 -> 0.92660412 | AX62: =+'Income Statement'!AX26/'Income Statement'!AX23 -> 0.92658766 | AZ62: =+'Income Statement'!AZ26/'Income Statement'!AZ23 -> 0.93077119 | BA62: =+'Income Statement'!BA26/'Income Statement'!BA23 -> 0.93075883 | BB62: =+'Income Statement'!BB26/'Income Statement'!BB23 -> 0.931 | BC62: =+'Income Statement'!BC26/'Income Statement'!BC23 -> 1.13753 | BE62: =+'Income Statement'!BE26/'Income Statement'!BE23 -> 0.95848997 | BF62: =+'Income Statement'!BF26/'Income Statement'!BF23 -> 0.95120425 | BG62: =+'Income Statement'!BG26/'Income Statement'!BG23 -> 1.0202839 | BH62: =+'Income Statement'!BH26/'Income Statement'!BH23 -> 0.97550695 | BJ62: =+'Income Statement'!BJ26/'Income Statement'!BJ23 -> 0.95 | BK62: =+'Income Statement'!BK26/'Income Statement'!BK23 -> 0.95 | BL62: =+'Income Statement'!BL26/'Income Statement'!BL23 -> 0.95 | BM62: =+'Income Statement'!BM26/'Income Statement'!BM23 -> 0.95 | BO62: =+'Income Statement'!BO26/'Income Statement'!BO23 -> 0.95 | BP62: =+'Income Statement'!BP26/'Income Statement'!BP23 -> 0.95 | BQ62: =+'Income Statement'!BQ26/'Income Statement'!BQ23 -> 0.95 | BR62: =+'Income Statement'!BR26/'Income Statement'!BR23 -> 0.95
A63: Financing | O63: =+('Income Statement'!O23-'Income Statement'!O22)/'Income Statement'!O20 -> 1.2367107 | Q63: =+('Income Statement'!Q23-'Income Statement'!Q22)/'Income Statement'!Q20 -> 1.1103448 | R63: =+('Income Statement'!R23-'Income Statement'!R22)/'Income Statement'!R20 -> 1.1273845 | S63: =+('Income Statement'!S23-'Income Statement'!S22)/'Income Statement'!S20 -> 1.1335847 | T63: =+('Income Statement'!T23-'Income Statement'!T22)/'Income Statement'!T20 -> 1.4358664 | V63: =+('Income Statement'!V23-'Income Statement'!V22)/'Income Statement'!V20 -> 1.0515654 | W63: =+('Income Statement'!W23-'Income Statement'!W22)/'Income Statement'!W20 -> 1.0851177 | X63: =+('Income Statement'!X23-'Income Statement'!X22)/'Income Statement'!X20 -> 1.1233589 | Y63: =+('Income Statement'!Y23-'Income Statement'!Y22)/'Income Statement'!Y20 -> 1.1921147 | AA63: =+('Income Statement'!AA23-'Income Statement'!AA22)/'Income Statement'!AA20 -> 1.1683333 | AB63: =+('Income Statement'!AB23-'Income Statement'!AB22)/'Income Statement'!AB20 -> 1.0829217 | AC63: =+('Income Statement'!AC23-'Income Statement'!AC22)/'Income Statement'!AC20 -> 1.0387701 | AD63: =+('Income Statement'!AD23-'Income Statement'!AD22)/'Income Statement'!AD20 -> 1.0106355 | AF63: =+('Income Statement'!AF23-'Income Statement'!AF22)/'Income Statement'!AF20 -> 1.0055911 | AG63: =+('Income Statement'!AG23-'Income Statement'!AG22)/'Income Statement'!AG20 -> 1.0066476 | AH63: =+('Income Statement'!AH23-'Income Statement'!AH22)/'Income Statement'!AH20 -> 1.0196991 | AI63: =+('Income Statement'!AI23-'Income Statement'!AI22)/'Income Statement'!AI20 -> 1.0079423 | AK63: =+('Income Statement'!AK23-'Income Statement'!AK22)/'Income Statement'!AK20 -> 1.006225 | AL63: =+('Income Statement'!AL23-'Income Statement'!AL22)/'Income Statement'!AL20 -> 1.0167955 | AM63: =+('Income Statement'!AM23-'Income Statement'!AM22)/'Income Statement'!AM20 -> 0.89724739 | AN63: =+('Income Statement'!AN23-'Income Statement'!AN22)/'Income Statement'!AN20 -> 0.85187345 | AP63: =+('Income Statement'!AP23-'Income Statement'!AP22)/'Income Statement'!AP20 -> 1 | AQ63: =+('Income Statement'!AQ23-'Income Statement'!AQ22)/'Income Statement'!AQ20 -> 1 | AR63: =+('Income Statement'!AR23-'Income Statement'!AR22)/'Income Statement'!AR20 -> 1 | AS63: =+('Income Statement'!AS23-'Income Statement'!AS22)/'Income Statement'!AS20 -> 1 | AU63: =+('Income Statement'!AU23-'Income Statement'!AU22)/'Income Statement'!AU20 -> 1 | AV63: =+('Income Statement'!AV23-'Income Statement'!AV22)/'Income Statement'!AV20 -> 1 | AW63: =+('Income Statement'!AW23-'Income Statement'!AW22)/'Income Statement'!AW20 -> 1 | AX63: =+('Income Statement'!AX23-'Income Statement'!AX22)/'Income Statement'!AX20 -> 1 | AZ63: =+('Income Statement'!AZ23-'Income Statement'!AZ22)/'Income Statement'!AZ20 -> 1 | BA63: =+('Income Statement'!BA23-'Income Statement'!BA22)/'Income Statement'!BA20 -> 1 | BB63: =+('Income Statement'!BB23-'Income Statement'!BB22)/'Income Statement'!BB20 -> 1 | BC63: =+('Income Statement'!BC23-'Income Statement'!BC22)/'Income Statement'!BC20 -> 1 | BE63: =+('Income Statement'!BE23-'Income Statement'!BE22)/'Income Statement'!BE20 -> 1 | BF63: =+('Income Statement'!BF23-'Income Statement'!BF22)/'Income Statement'!BF20 -> 1 | BG63: =+('Income Statement'!BG23-'Income Statement'!BG22)/'Income Statement'!BG20 -> 1 | BH63: =+('Income Statement'!BH23-'Income Statement'!BH22)/'Income Statement'!BH20 -> 1 | BJ63: =+('Income Statement'!BJ23-'Income Statement'!BJ22)/'Income Statement'!BJ20 -> 1 | BK63: =+('Income Statement'!BK23-'Income Statement'!BK22)/'Income Statement'!BK20 -> 1 | BL63: =+('Income Statement'!BL23-'Income Statement'!BL22)/'Income Statement'!BL20 -> 1 | BM63: =+('Income Statement'!BM23-'Income Statement'!BM22)/'Income Statement'!BM20 -> 1 | BO63: =+('Income Statement'!BO23-'Income Statement'!BO22)/'Income Statement'!BO20 -> 1 | BP63: =+('Income Statement'!BP23-'Income Statement'!BP22)/'Income Statement'!BP20 -> 1 | BQ63: =+('Income Statement'!BQ23-'Income Statement'!BQ22)/'Income Statement'!BQ20 -> 1 | BR63: =+('Income Statement'!BR23-'Income Statement'!BR22)/'Income Statement'!BR20 -> 1
A64: Operations | O64: =+('Income Statement'!O20+'Income Statement'!Y22)/'Income Statement'!O10 -> -0.15977433 | Q64: =+('Income Statement'!Q20+'Income Statement'!AA22)/'Income Statement'!Q10 -> -0.41364411 | R64: =+('Income Statement'!R20+'Income Statement'!AB22)/'Income Statement'!R10 -> -0.29892426 | S64: =+('Income Statement'!S20+'Income Statement'!AC22)/'Income Statement'!S10 -> -0.28597523 | T64: =+('Income Statement'!T20+'Income Statement'!AD22)/'Income Statement'!T10 -> -0.25295979 | V64: =+('Income Statement'!V20+'Income Statement'!V22)/'Income Statement'!V10 -> -0.42223442 | W64: =+('Income Statement'!W20+'Income Statement'!W22)/'Income Statement'!W10 -> -0.24179157 | X64: =+('Income Statement'!X20+'Income Statement'!X22)/'Income Statement'!X10 -> -0.15784539 | Y64: =+('Income Statement'!Y20+'Income Statement'!Y22)/'Income Statement'!Y10 -> -0.089398058 | AA64: =+('Income Statement'!AA20+'Income Statement'!AA22)/'Income Statement'!AA10 -> -0.045616174 | AB64: =+('Income Statement'!AB20+'Income Statement'!AB22)/'Income Statement'!AB10 -> -0.066133528 | AC64: =+('Income Statement'!AC20+'Income Statement'!AC22)/'Income Statement'!AC10 -> -0.013075905 | AD64: =+('Income Statement'!AD20+'Income Statement'!AD22)/'Income Statement'!AD10 -> -0.22859065 | AF64: =+('Income Statement'!AF20+'Income Statement'!AF22)/'Income Statement'!AF10 -> -0.29875972 | AG64: =+('Income Statement'!AG20+'Income Statement'!AG22)/'Income Statement'!AG10 -> -0.4678806 | AH64: =+('Income Statement'!AH20+'Income Statement'!AH22)/'Income Statement'!AH10 -> -0.089810739 | AI64: =+('Income Statement'!AI20+'Income Statement'!AI22)/'Income Statement'!AI10 -> -0.1944927 | AK64: =+('Income Statement'!AK20+'Income Statement'!AK22)/'Income Statement'!AK10 -> -0.23728306 | AL64: =+('Income Statement'!AL20+'Income Statement'!AL22)/'Income Statement'!AL10 -> -0.098067326 | AM64: =+('Income Statement'!AM20+'Income Statement'!AM22)/'Income Statement'!AM10 -> -0.19377174 | AN64: =+('Income Statement'!AN20+'Income Statement'!AN22)/'Income Statement'!AN10 -> -0.1018623 | AP64: =+('Income Statement'!AP20+'Income Statement'!AP22)/'Income Statement'!AP10 -> -0.059660977 | AQ64: =+('Income Statement'!AQ20+'Income Statement'!AQ22)/'Income Statement'!AQ10 -> 0.00060386473 | AR64: =+('Income Statement'!AR20+'Income Statement'!AR22)/'Income Statement'!AR10 -> -0.0078182876 | AS64: =+('Income Statement'!AS20+'Income Statement'!AS22)/'Income Statement'!AS10 -> 0.054846383 | AU64: =+('Income Statement'!AU20+'Income Statement'!AU22)/'Income Statement'!AU10 -> 0.095108102 | AV64: =+('Income Statement'!AV20+'Income Statement'!AV22)/'Income Statement'!AV10 -> 0.1020128 | AW64: =+('Income Statement'!AW20+'Income Statement'!AW22)/'Income Statement'!AW10 -> 0.14666844 | AX64: =+('Income Statement'!AX20+'Income Statement'!AX22)/'Income Statement'!AX10 -> 0.1675679 | AZ64: =+('Income Statement'!AZ20+'Income Statement'!AZ22)/'Income Statement'!AZ10 -> 0.16228161 | BA64: =+('Income Statement'!BA20+'Income Statement'!BA22)/'Income Statement'!BA10 -> 0.21973643 | BB64: =+('Income Statement'!BB20+'Income Statement'!BB22)/'Income Statement'!BB10 -> 0.24092871 | BC64: =+('Income Statement'!BC20+'Income Statement'!BC22)/'Income Statement'!BC10 -> 0.21452053 | BE64: =+('Income Statement'!BE20+'Income Statement'!BE22)/'Income Statement'!BE10 -> 0.22307444 | BF64: =+('Income Statement'!BF20+'Income Statement'!BF22)/'Income Statement'!BF10 -> 0.28229772 | BG64: =+('Income Statement'!BG20+'Income Statement'!BG22)/'Income Statement'!BG10 -> 0.30393867 | BH64: =+('Income Statement'!BH20+'Income Statement'!BH22)/'Income Statement'!BH10 -> 0.31208225 | BJ64: =+('Income Statement'!BJ20+'Income Statement'!BJ22)/'Income Statement'!BJ10 -> 0.22876767 | BK64: =+('Income Statement'!BK20+'Income Statement'!BK22)/'Income Statement'!BK10 -> 0.23567924 | BL64: =+('Income Statement'!BL20+'Income Statement'!BL22)/'Income Statement'!BL10 -> 0.23668435 | BM64: =+('Income Statement'!BM20+'Income Statement'!BM22)/'Income Statement'!BM10 -> 0.24765205 | BO64: =+('Income Statement'!BO20+'Income Statement'!BO22)/'Income Statement'!BO10 -> 0.23369385 | BP64: =+('Income Statement'!BP20+'Income Statement'!BP22)/'Income Statement'!BP10 -> 0.24061333 | BQ64: =+('Income Statement'!BQ20+'Income Statement'!BQ22)/'Income Statement'!BQ10 -> 0.24161713 | BR64: =+('Income Statement'!BR20+'Income Statement'!BR22)/'Income Statement'!BR10 -> 0.2525888
A65: Turnover | O65: NA | Q65: =+'Income Statement'!Q10*4/(('Balance Sheet'!Q20+'Balance Sheet'!O20)/2) -> 0.678868 | R65: =+'Income Statement'!R10*4/(('Balance Sheet'!R20+'Balance Sheet'!Q20)/2) -> 0.81373616 | S65: =+'Income Statement'!S10*4/(('Balance Sheet'!S20+'Balance Sheet'!R20)/2) -> 0.81480879 | T65: =+'Income Statement'!T10*4/(('Balance Sheet'!T20+'Balance Sheet'!S20)/2) -> 0.96574836 | V65: =+'Income Statement'!V10*4/(('Balance Sheet'!V20+'Balance Sheet'!T20)/2) -> 1.069859 | W65: =+'Income Statement'!W10*4/(('Balance Sheet'!W20+'Balance Sheet'!V20)/2) -> 1.3319185 | X65: =+'Income Statement'!X10*4/(('Balance Sheet'!X20+'Balance Sheet'!W20)/2) -> 1.0172864 | Y65: =+'Income Statement'!Y10*4/(('Balance Sheet'!Y20+'Balance Sheet'!X20)/2) -> 0.85935382 | AA65: =+'Income Statement'!AA10*4/(('Balance Sheet'!AA20+'Balance Sheet'!Y20)/2) -> 0.96747005 | AB65: =+'Income Statement'!AB10*4/(('Balance Sheet'!AB20+'Balance Sheet'!AA20)/2) -> 0.64133818 | AC65: =+'Income Statement'!AC10*4/(('Balance Sheet'!AC20+'Balance Sheet'!AB20)/2) -> 0.48330746 | AD65: =+'Income Statement'!AD10*4/(('Balance Sheet'!AD20+'Balance Sheet'!AC20)/2) -> 0.4441299 | AF65: =+'Income Statement'!AF10*4/(('Balance Sheet'!AF20+'Balance Sheet'!AD20)/2) -> 0.45910103 | AG65: =+'Income Statement'!AG10*4/(('Balance Sheet'!AG20+'Balance Sheet'!AF20)/2) -> 0.31618996 | AH65: =+'Income Statement'!AH10*4/(('Balance Sheet'!AH20+'Balance Sheet'!AG20)/2) -> 0.35022113 | AI65: =+'Income Statement'!AI10*4/(('Balance Sheet'!AI20+'Balance Sheet'!AH20)/2) -> 0.30317541 | AK65: =+'Income Statement'!AK10*4/(('Balance Sheet'!AK20+'Balance Sheet'!AI20)/2) -> 0.19808689 | AL65: =+'Income Statement'!AL10*4/(('Balance Sheet'!AL20+'Balance Sheet'!AK20)/2) -> 0.21477454 | AM65: =+'Income Statement'!AM10*4/(('Balance Sheet'!AM20+'Balance Sheet'!AL20)/2) -> 0.21815971 | AN65: =+'Income Statement'!AN10*4/(('Balance Sheet'!AN20+'Balance Sheet'!AM20)/2) -> 0.22689424 | AP65: =+'Income Statement'!AP10*4/(('Balance Sheet'!AP20+'Balance Sheet'!AN20)/2) -> 0.22963529 | AQ65: =+'Income Statement'!AQ10*4/(('Balance Sheet'!AQ20+'Balance Sheet'!AP20)/2) -> 0.25149507 | AR65: =+'Income Statement'!AR10*4/(('Balance Sheet'!AR20+'Balance Sheet'!AQ20)/2) -> 0.26638533 | AS65: =+'Income Statement'!AS10*4/(('Balance Sheet'!AS20+'Balance Sheet'!AR20)/2) -> 0.28145019 | AU65: =+'Income Statement'!AU10*4/(('Balance Sheet'!AU20+'Balance Sheet'!AS20)/2) -> 0.28500727 | AV65: =+'Income Statement'!AV10*4/(('Balance Sheet'!AV20+'Balance Sheet'!AU20)/2) -> 0.31169257 | AW65: =+'Income Statement'!AW10*4/(('Balance Sheet'!AW20+'Balance Sheet'!AV20)/2) -> 0.31533072 | AX65: =+'Income Statement'!AX10*4/(('Balance Sheet'!AX20+'Balance Sheet'!AW20)/2) -> 0.35073436 | AZ65: =+'Income Statement'!AZ10*4/(('Balance Sheet'!AZ20+'Balance Sheet'!AX20)/2) -> 0.33466913 | BA65: =+'Income Statement'!BA10*4/(('Balance Sheet'!BA20+'Balance Sheet'!AZ20)/2) -> 0.37603681 | BB65: =+'Income Statement'!BB10*4/(('Balance Sheet'!BB20+'Balance Sheet'!BA20)/2) -> 0.36937085 | BC65: =+'Income Statement'!BC10*4/(('Balance Sheet'!BC20+'Balance Sheet'!BB20)/2) -> 0.36855742 | BE65: =+'Income Statement'!BE10*4/(('Balance Sheet'!BE20+'Balance Sheet'!BC20)/2) -> 0.35014449 | BF65: =+'Income Statement'!BF10*4/(('Balance Sheet'!BF20+'Balance Sheet'!BE20)/2) -> 0.39154207 | BG65: =+'Income Statement'!BG10*4/(('Balance Sheet'!BG20+'Balance Sheet'!BF20)/2) -> 0.38901859 | BH65: =+'Income Statement'!BH10*4/(('Balance Sheet'!BH20+'Balance Sheet'!BG20)/2) -> 0.40414512 | BJ65: =+'Income Statement'!BJ10*4/(('Balance Sheet'!BJ20+'Balance Sheet'!BH20)/2) -> 0.3651514 | BK65: =+'Income Statement'!BK10*4/(('Balance Sheet'!BK20+'Balance Sheet'!BJ20)/2) -> 0.40143646 | BL65: =+'Income Statement'!BL10*4/(('Balance Sheet'!BL20+'Balance Sheet'!BK20)/2) -> 0.385066 | BM65: =+'Income Statement'!BM10*4/(('Balance Sheet'!BM20+'Balance Sheet'!BL20)/2) -> 0.39111208 | BO65: =+'Income Statement'!BO10*4/(('Balance Sheet'!BO20+'Balance Sheet'!BM20)/2) -> 0.35811776 | BP65: =+'Income Statement'!BP10*4/(('Balance Sheet'!BP20+'Balance Sheet'!BO20)/2) -> 0.3941518 | BQ65: =+'Income Statement'!BQ10*4/(('Balance Sheet'!BQ20+'Balance Sheet'!BP20)/2) -> 0.37877929 | BR65: =+'Income Statement'!BR10*4/(('Balance Sheet'!BR20+'Balance Sheet'!BQ20)/2) -> 0.38439436
A66: Leverage | O66: NA | Q66: =+((Q20+O20)/2)/((Q38+O38)/2) -> 1.7146753 | R66: =+((R20+Q20)/2)/((R38+Q38)/2) -> 1.7881791 | S66: =+((S20+R20)/2)/((S38+R38)/2) -> 1.8972645 | T66: =+((T20+S20)/2)/((T38+S38)/2) -> 2.0280606 | V66: =+((V20+T20)/2)/((V38+T38)/2) -> 2.2289501 | W66: =+((W20+V20)/2)/((W38+V38)/2) -> 2.4483284 | X66: =+((X20+W20)/2)/((X38+W38)/2) -> 1.7537801 | Y66: =+((Y20+X20)/2)/((Y38+X38)/2) -> 1.5060124 | AA66: =+((AA20+Y20)/2)/((AA38+Y38)/2) -> 1.4931785 | AB66: =+((AB20+AA20)/2)/((AB38+AA38)/2) -> 1.2204524 | AC66: =+((AC20+AB20)/2)/((AC38+AB38)/2) -> 1.1261246 | AD66: =+((AD20+AC20)/2)/((AD38+AC38)/2) -> 1.1382421 | AF66: =+((AF20+AD20)/2)/((AF38+AD38)/2) -> 1.1541574 | AG66: =+((AG20+AF20)/2)/((AG38+AF38)/2) -> 1.1473337 | AH66: =+((AH20+AG20)/2)/((AH38+AG38)/2) -> 1.0955751 | AI66: =+((AI20+AH20)/2)/((AI38+AH38)/2) -> 1.0787513 | AK66: =+((AK20+AI20)/2)/((AK38+AI38)/2) -> 1.0604598 | AL66: =+((AL20+AK20)/2)/((AL38+AK38)/2) -> 1.0534973 | AM66: =+((AM20+AL20)/2)/((AM38+AL38)/2) -> 1.0641978 | AN66: =+((AN20+AM20)/2)/((AN38+AM38)/2) -> 1.0769757 | AP66: =+((AP20+AN20)/2)/((AP38+AN38)/2) -> 1.0820634 | AQ66: =+((AQ20+AP20)/2)/((AQ38+AP38)/2) -> 1.0782315 | AR66: =+((AR20+AQ20)/2)/((AR38+AQ38)/2) -> 1.0747171 | AS66: =+((AS20+AR20)/2)/((AS38+AR38)/2) -> 1.0748817 | AU66: =+((AU20+AS20)/2)/((AU38+AS38)/2) -> 1.0728426 | AV66: =+((AV20+AU20)/2)/((AV38+AU38)/2) -> 1.0712836 | AW66: =+((AW20+AV20)/2)/((AW38+AV38)/2) -> 1.0698622 | AX66: =+((AX20+AW20)/2)/((AX38+AW38)/2) -> 1.0675296 | AZ66: =+((AZ20+AX20)/2)/((AZ38+AX38)/2) -> 1.0703863 | BA66: =+((BA20+AZ20)/2)/((BA38+AZ38)/2) -> 1.0813923 | BB66: =+((BB20+BA20)/2)/((BB38+BA38)/2) -> 1.0869731 | BC66: =+((BC20+BB20)/2)/((BC38+BB38)/2) -> 1.094833 | BE66: =+((BE20+BC20)/2)/((BE38+BC38)/2) -> 1.1031439 | BF66: =+((BF20+BE20)/2)/((BF38+BE38)/2) -> 1.1007958 | BG66: =+((BG20+BF20)/2)/((BG38+BF38)/2) -> 1.0940674 | BH66: =+((BH20+BG20)/2)/((BH38+BG38)/2) -> 1.0839447 | BJ66: =+((BJ20+BH20)/2)/((BJ38+BH38)/2) -> 1.0725075 | BK66: =+((BK20+BJ20)/2)/((BK38+BJ38)/2) -> 1.0687537 | BL66: =+((BL20+BK20)/2)/((BL38+BK38)/2) -> 1.0713101 | BM66: =+((BM20+BL20)/2)/((BM38+BL38)/2) -> 1.0726202 | BO66: =+((BO20+BM20)/2)/((BO38+BM38)/2) -> 1.0677612 | BP66: =+((BP20+BO20)/2)/((BP38+BO38)/2) -> 1.0646017 | BQ66: =+((BQ20+BP20)/2)/((BQ38+BP38)/2) -> 1.0672732 | BR66: =+((BR20+BQ20)/2)/((BR38+BQ38)/2) -> 1.0686728
A67: ROE | O67: NM | Q67: NM | R67: NM | S67: NM | T67: NM | V67: NM | W67: NM | X67: NM | Y67: NM | AA67: NM | AB67: NM | AC67: NM | AD67: NM | AF67: NM | AG67: NM | AH67: NM | AI67: NM | AK67: =+AK66*AK65*AK64*AK63*AK62 -> -0.029977203 | AL67: =+AL66*AL65*AL64*AL63*AL62 -> -0.021934533 | AM67: =+AM66*AM65*AM64*AM63*AM62 -> -0.035172797 | AN67: =+AN66*AN65*AN64*AN63*AN62 -> -0.018340758 | AP67: =+AP66*AP65*AP64*AP63*AP62 -> -0.014813559 | AQ67: =+AQ66*AQ65*AQ64*AQ63*AQ62 -> 0.00059173277 | AR67: =+AR66*AR65*AR64*AR63*AR62 -> -0.0016626206 | AS67: =+AS66*AS65*AS64*AS63*AS62 -> 0.015074101 | AU67: =+AU66*AU65*AU64*AU63*AU62 -> 0.026944171 | AV67: =+AV66*AV65*AV64*AV63*AV62 -> 0.031564106 | AW67: =+AW66*AW65*AW64*AW63*AW62 -> 0.045848491 | AX67: =+AX66*AX65*AX64*AX63*AX62 -> 0.058134719 | AZ67: =+AZ66*AZ65*AZ64*AZ63*AZ62 -> 0.054108864 | BA67: =+BA66*BA65*BA64*BA63*BA62 -> 0.083167346 | BB67: =+BB66*BB65*BB64*BB63*BB62 -> 0.090057448 | BC67: =+BC66*BC65*BC64*BC63*BC62 -> 0.098465651 | BE67: =+BE66*BE65*BE64*BE63*BE62 -> 0.082587977 | BF67: =+BF66*BF65*BF64*BF63*BF62 -> 0.11573543 | BG67: =+BG66*BG65*BG64*BG63*BG62 -> 0.13198404 | BH67: =+BH66*BH65*BH64*BH63*BH62 -> 0.13336562 | BJ67: =+BJ66*BJ65*BJ64*BJ63*BJ62 -> 0.085112151 | BK67: =+BK66*BK65*BK64*BK63*BK62 -> 0.096059286 | BL67: =+BL66*BL65*BL64*BL63*BL62 -> 0.09275632 | BM67: =+BM66*BM65*BM64*BM63*BM62 -> 0.09869899 | BO67: =+BO66*BO65*BO64*BO63*BO62 -> 0.084892806 | BP67: =+BP66*BP65*BP64*BP63*BP62 -> 0.095916637 | BQ67: =+BQ66*BQ65*BQ64*BQ63*BQ62 -> 0.09279256 | BR67: =+BR66*BR65*BR64*BR63*BR62 -> 0.098573336
A69: Receivables as % of Revenue | O69: =O8/'Income Statement'!O10 -> 0.47959687 | Q69: =Q8/'Income Statement'!Q10 -> 0.55531889 | R69: =R8/'Income Statement'!R10 -> 0.59909812 | S69: =S8/'Income Statement'!S10 -> 0.66413608 | T69: =T8/'Income Statement'!T10 -> 0.64890794 | V69: =V8/('Income Statement'!V10-'[1]Old Revenue Model'!V44) -> 0.65854997 | W69: =W8/('Income Statement'!W10-'[1]Old Revenue Model'!W44) -> 0.57166718 | X69: =X8/('Income Statement'!X10-'[1]Old Revenue Model'!X44) -> 0.52254325 | Y69: =Y8/('Income Statement'!Y10-'[1]Old Revenue Model'!Y44) -> 0.51137864 | AA69: =AA8/('Income Statement'!AA10-'[1]Old Revenue Model'!AA44) -> 0.56266721 | AB69: =AB8/('Income Statement'!AB10-'[1]Old Revenue Model'!AB44) -> 0.62645721 | AC69: =AC8/('Income Statement'!AC10-'[1]Old Revenue Model'!AC44) -> 0.60791081 | AD69: =AD8/('Income Statement'!AD10-'[1]Old Revenue Model'!AD44) -> 0.58287925 | AF69: =AF8/('Income Statement'!AF10-'[1]Old Revenue Model'!AF44) -> 0.61342459 | AG69: =AG8/('Income Statement'!AG10-'[1]Old Revenue Model'!AG44) -> 0.64750773 | AH69: =AH8/('Income Statement'!AH10-'[1]Old Revenue Model'!AH44) -> 0.54076026 | AI69: 0.6 | AK69: 0.6 | AL69: 0.6 | AM69: 0.6 | AN69: 0.6 | AP69: 0.6 | AQ69: 0.6 | AR69: 0.6 | AS69: 0.6 | AU69: 0.6 | AV69: 0.6 | AW69: 0.6 | AX69: 0.6 | AZ69: 0.6 | BA69: 0.6 | BB69: 0.6 | BC69: 0.6 | BE69: 0.6 | BF69: 0.6 | BG69: 0.6 | BH69: 0.6 | BJ69: 0.6 | BK69: 0.6 | BL69: 0.6 | BM69: 0.6 | BO69: 0.6 | BP69: 0.6 | BQ69: 0.6 | BR69: 0.6
A70: Other Current Assets as a % of Revenue | O70: =+O11/'Income Statement'!O10 -> 0.11266911 | Q70: =+Q11/'Income Statement'!Q10 -> 0.12786027 | R70: =+R11/'Income Statement'!R10 -> 0.1050201 | S70: =+S11/'Income Statement'!S10 -> 0.092299789 | T70: =+T11/'Income Statement'!T10 -> 0.10190855 | V70: =+V11/'Income Statement'!V10 -> 0.10688089 | W70: =+W11/'Income Statement'!W10 -> 0.080084392 | X70: =+X11/'Income Statement'!X10 -> 0.076834569 | Y70: =+Y11/'Income Statement'!Y10 -> 0.092699029 | AA70: =+AA11/'Income Statement'!AA10 -> 0.081005114 | AB70: =+AB11/'Income Statement'!AB10 -> 0.085379612 | AC70: =+AC11/'Income Statement'!AC10 -> 0.070900462 | AD70: =+AD11/'Income Statement'!AD10 -> 0.075176589 | AF70: =+AF11/'Income Statement'!AF10 -> 0.097840756 | AG70: =+AG11/'Income Statement'!AG10 -> 0.13963485 | AH70: =+AH11/'Income Statement'!AH10 -> 0.10121783 | AI70: 0.1 | AK70: 0.1 | AL70: 0.1 | AM70: 0.1 | AN70: 0.1 | AP70: 0.1 | AQ70: 0.1 | AR70: 0.1 | AS70: 0.1 | AU70: 0.1 | AV70: 0.1 | AW70: 0.1 | AX70: 0.1 | AZ70: 0.1 | BA70: 0.1 | BB70: 0.1 | BC70: 0.1 | BE70: 0.1 | BF70: 0.1 | BG70: 0.1 | BH70: 0.1 | BJ70: 0.1 | BK70: 0.1 | BL70: 0.1 | BM70: 0.1 | BO70: 0.1 | BP70: 0.1 | BQ70: 0.1 | BR70: 0.1
A71: A/P as % of Revenue | O71: =+O23/'Income Statement'!O10 -> 0.13277099 | Q71: =+Q23/'Income Statement'!Q10 -> 0.15889727 | R71: =+R23/'Income Statement'!R10 -> 0.12762143 | S71: =+S23/'Income Statement'!S10 -> 0.18043267 | T71: =+T23/'Income Statement'!T10 -> 0.19662176 | V71: =+V23/'Income Statement'!V10 -> 0.16745671 | W71: =+W23/'Income Statement'!W10 -> 0.086237968 | X71: =+X23/'Income Statement'!X10 -> 0.050072445 | Y71: =+Y23/'Income Statement'!Y10 -> 0.097708738 | AA71: =+AA23/'Income Statement'!AA10 -> 0.13762742 | AB71: =+AB23/'Income Statement'!AB10 -> 0.13475577 | AC71: =+AC23/'Income Statement'!AC10 -> 0.17976948 | AD71: =+AD23/'Income Statement'!AD10 -> 0.078304743 | AF71: =+AF23/'Income Statement'!AF10 -> 0.2462888 | AG71: =+AG23/'Income Statement'!AG10 -> 0.10741886 | AH71: =+AH23/'Income Statement'!AH10 -> 0.062080267 | AI71: 0.08 | AK71: 0.08 | AL71: 0.08 | AM71: 0.08 | AN71: 0.08 | AP71: 0.08 | AQ71: 0.08 | AR71: 0.08 | AS71: 0.08 | AU71: 0.08 | AV71: 0.08 | AW71: 0.08 | AX71: 0.08 | AZ71: 0.08 | BA71: 0.08 | BB71: 0.08 | BC71: 0.08 | BE71: 0.08 | BF71: 0.08 | BG71: 0.08 | BH71: 0.08 | BJ71: 0.08 | BK71: 0.08 | BL71: 0.08 | BM71: 0.08 | BO71: 0.08 | BP71: 0.08 | BQ71: 0.08 | BR71: 0.08
