Workbook

Sheet __FDSCACHE__
B1: This sheet contains FactSet XML data for use with this workbook's =FDS codes. Modifying the worksheet's contents may damage the workbook's =FDS functionality.

Sheet Comparison
B2: Bill.com, Inc. (BILL)
B4: Variance Analysis | D4: =IS!AN4 -> 2Q25 | E4: =K4 -> 2Q26 | F4: Y/Y Change | G4: =IS!AR4 -> 1Q26 | H4: =K4 -> 2Q26 | I4: Q/Q Change | J4: 2Q26E | K4: =IS!AS4 -> 2Q26 | L4: % Difference
B5: Subscription and transaction fees | C5: Subscription Revenue | D5: =IS!AN5 -> 67721 | E5: =K5 -> 72100 | F5: =E5/D5-1 -> 0.064662365 | G5: =IS!AR5 -> 70823 | H5: =K5 -> 72100 | I5: =H5/G5-1 -> 0.018030866 | J5: 73051.39 | K5: =IS!AS5 -> 72100 | L5: =K5/J5-1 -> -0.013023566
C6: Transaction Revenue | D6: =IS!AN8 -> 251895 | E6: =K6 -> 303028 | F6: =E6/D6-1 -> 0.20299331 | G6: =IS!AR8 -> 287182 | H6: =K6 -> 303028 | I6: =H6/G6-1 -> 0.055177553 | J6: 290999.86 | K6: =IS!AS8 -> 303028 | L6: =K6/J6-1 -> 0.041333831
C7: Float Revenue | D7: =IS!AN14 -> 42938 | E7: =K7 -> 39543 | F7: =E7/D7-1 -> -0.079067493 | G7: =IS!AR14 -> 37736 | H7: =K7 -> 39543 | I7: =H7/G7-1 -> 0.047885308 | J7: 33802.488 | K7: =IS!AS14 -> 39543 | L7: =K7/J7-1 -> 0.16982514
B8: Total Revenue | D8: =IS!AN17 -> 362554 | E8: =K8 -> 414671 | F8: =E8/D8-1 -> 0.14374962 | G8: =IS!AR17 -> 395741 | H8: =K8 -> 414671 | I8: =H8/G8-1 -> 0.047834316 | J8: 397853.74 | K8: =IS!AS17 -> 414671 | L8: =K8/J8-1 -> 0.04226996
B10: Cost of Revenue | D10: =IS!AN21 -> 53644 | E10: =K10 -> 66892 | F10: =E10/D10-1 -> 0.24696145 | G10: =IS!AR21 -> 63661 | H10: =K10 -> 66892 | I10: =H10/G10-1 -> 0.050753208 | J10: 61547.973 | K10: =IS!AS21 -> 66892 | L10: =K10/J10-1 -> 0.086827013
B11: Gross Profit | D11: =D8-D10 -> 308910 | E11: =K11 -> 347779 | F11: =E11/D11-1 -> 0.12582629 | G11: =G8-G10 -> 332080 | H11: =K11 -> 347779 | I11: =H11/G11-1 -> 0.047274753 | J11: 336305.77 | K11: =K8-K10 -> 347779 | L11: =K11/J11-1 -> 0.034115487
C12: Gross Margin | D12: =D11/D8 -> 0.85203859 | E12: =K12 -> 0.83868657 | G12: =G11/G8 -> 0.83913469 | H12: =K12 -> 0.83868657 | J12: 0.8453 | K12: =K11/K8 -> 0.83868657
B14: Operating Expenses
C15: =IS!C26 -> Research & Development | D15: =IS!AN26 -> 55010 | E15: =K15 -> 53256 | F15: =E15/D15-1 -> -0.031885112 | G15: =IS!AR26 -> 53860 | H15: =K15 -> 53256 | I15: =H15/G15-1 -> -0.011214259 | J15: 65248.013 | K15: =IS!AS26 -> 53256 | L15: =K15/J15-1 -> -0.18379124
C16: =IS!C32 -> Sales & Marketing | D16: =IS!AN32 -> 121878 | E16: =K16 -> 145251 | F16: =E16/D16-1 -> 0.19177374 | G16: =IS!AR32 -> 139415 | H16: =K16 -> 145251 | I16: =H16/G16-1 -> 0.041860632 | J16: 135270.27 | K16: =IS!AS32 -> 145251 | L16: =K16/J16-1 -> 0.07378361
C17: =IS!C38 -> General & Administrative | D17: =IS!AN38 -> 69216 | E17: =K17 -> 75187 | F17: =E17/D17-1 -> 0.086266181 | G17: =IS!AR38 -> 70569 | H17: =K17 -> 75187 | I17: =H17/G17-1 -> 0.065439499 | J17: 70817.965 | K17: =IS!AS38 -> 75187 | L17: =K17/J17-1 -> 0.061693873
B18: Total Operating Expenses | D18: =SUM(D15:D17) -> 246104 | E18: =K18 -> 273694 | F18: =E18/D18-1 -> 0.11210708 | G18: =SUM(G15:G17) -> 263844 | H18: =K18 -> 273694 | I18: =H18/G18-1 -> 0.037332666 | J18: 271336.25 | K18: =SUM(K15:K17) -> 273694 | L18: =K18/J18-1 -> 0.0086894043
B20: Non-GAAP Operating Income | D20: =D11-D18 -> 62806 | E20: =K20 -> 74085 | F20: =E20/D20-1 -> 0.17958475 | G20: =G11-G18 -> 68236 | H20: =K20 -> 74085 | I20: =H20/G20-1 -> 0.085717217 | J20: 64969.515 | K20: =K11-K18 -> 74085 | L20: =K20/J20-1 -> 0.14030402
C21: Non-GAAP Operating Margin | D21: =D20/D8 -> 0.17323213 | E21: =K21 -> 0.17865971 | G21: =G20/G8 -> 0.1724259 | H21: =K21 -> 0.17865971 | J21: 0.1633 | K21: =K20/K8 -> 0.17865971
B23: GAAP Adjustments | D23: =IS!AN52 -> 84516 | E23: =K23 -> 92161 | F23: =E23/D23-1 -> 0.090456245 | G23: =IS!AR52 -> 88955 | H23: =K23 -> 92161 | I23: =H23/G23-1 -> 0.036040695 | J23: 89000 | K23: =IS!AS52 -> 92161 | L23: =K23/J23-1 -> 0.035516854
B25: GAAP Operating Income | D25: =D20-D23 -> -21710 | E25: =K25 -> -18076 | F25: =E25/D25-1 -> -0.1673883 | G25: =G20-G23 -> -20719 | H25: =K25 -> -18076 | I25: =H25/G25-1 -> -0.12756407 | J25: -24030.485 | K25: =K20-K23 -> -18076 | L25: =K25/J25-1 -> -0.24778878
C26: GAAP Operating Margin | D26: =D25/D8 -> -0.059880735 | E26: =K26 -> -0.043591184 | G26: =G25/G8 -> -0.052354949 | H26: =K26 -> -0.043591184 | J26: -0.060400298 | K26: =K25/K8 -> -0.043591184
B28: Non-GAAP Other Income | D28: =IS!AN61 -> 15832 | E28: =K28 -> 17635 | F28: =E28/D28-1 -> 0.11388327 | G28: =IS!AR61 -> 19516 | H28: =K28 -> 17635 | I28: =H28/G28-1 -> -0.096382455 | J28: 15650 | K28: =IS!AS61 -> 17635 | L28: =K28/J28-1 -> 0.12683706
B30: Non-GAAP Income before Taxes | D30: =IS!AN66 -> 78638 | E30: =K30 -> 91720 | F30: =E30/D30-1 -> 0.16635723 | G30: =IS!AR66 -> 87752 | H30: =K30 -> 91720 | I30: =H30/G30-1 -> 0.045218343 | J30: 80619.515 | K30: =IS!AS66 -> 91720 | L30: =K30/J30-1 -> 0.13768979
B31: Income Tax | D31: =IS!AN67 -> 15728 | E31: =K31 -> 18344 | G31: =IS!AR67 -> 17550 | H31: =K31 -> 18344 | J31: 16123.903 | K31: =IS!AS67 -> 18344
B32: Non-GAAP Net Income | D32: =D30-D31 -> 62910 | E32: =K32 -> 73376 | F32: =E32/D32-1 -> 0.16636465 | G32: =G30-G31 -> 70202 | H32: =K32 -> 73376 | I32: =H32/G32-1 -> 0.045212387 | J32: 64495.612 | K32: =K30-K31 -> 73376 | L32: =K32/J32-1 -> 0.13768979
B34: GAAP Income before Taxes | D34: =D25+D28 -> -5878 | E34: =K34 -> -441 | F34: =E34/D34-1 -> -0.92497448 | G34: =G25+G28 -> -1203 | H34: =K34 -> -441 | I34: =H34/G34-1 -> -0.63341646 | J34: -8380.4845 | K34: =K25+K28 -> -441 | L34: =K34/J34-1 -> -0.94737774
B35: Income Tax | D35: =IS!AN73 -> 45 | E35: =K35 -> 522 | F35: =E35/D35-1 -> 10.6 | G35: =IS!AR73 -> 149 | H35: =K35 -> 522 | I35: =H35/G35-1 -> 2.5033557 | J35: 500 | K35: =IS!AS73 -> 522 | L35: =K35/J35-1 -> 0.044
B36: GAAP Net Income | D36: =D34-D35 -> -5923 | E36: =K36 -> -963 | F36: =E36/D36-1 -> -0.83741347 | G36: =G34-G35 -> -1352 | H36: =K36 -> -963 | I36: =H36/G36-1 -> -0.28772189 | J36: -8880.4845 | K36: =K34-K35 -> -963 | L36: =K36/J36-1 -> -0.89155997
B38: Non- GAAP EPS | D38: =IS!AN79 -> 0.56210295 | E38: =K38 -> 0.64031276 | G38: =IS!AR79 -> 0.60787794 | H38: =K38 -> 0.64031276 | J38: 0.55513561 | K38: =IS!AS79 -> 0.64031276
B39: GAAP EPS | D39: =IS!AN81 -> 0.2997525 | E39: =K39 -> -0.025743047 | G39: =IS!AR81 -> -0.029061439 | H39: =K39 -> -0.025743047 | J39: -0.1024265 | K39: =IS!AS81 -> -0.025743047
B41: Basic Shares Outstanding | D41: =IS!AN84 -> 104480 | E41: =K41 -> 100532 | G41: =IS!AR84 -> 101922 | H41: =K41 -> 100532 | J41: 102322 | K41: =IS!AS84 -> 100532
B42: Diluted Shares Outstanding | D42: =IS!AN85 -> 111919 | E42: =K42 -> 114594 | G42: =IS!AR85 -> 115487 | H42: =K42 -> 114594 | J42: 116179.92 | K42: =IS!AS85 -> 114594
B44: AP/AR Variance Analysis | D44: =IS!AN$4 -> 2Q25 | E44: =K44 -> 2Q26 | F44: Y/Y Change | G44: =IS!AR$4 -> 1Q26 | H44: =K44 -> 2Q26 | I44: Q/Q Change | J44: 2Q26E | K44: =IS!AS$4 -> 2Q26 | L44: % Difference
B45: Customer Count | D45: ='Revenue Build'!AN4 -> 160600 | E45: =K45 -> 177500 | F45: =E45/D45-1 -> 0.10523039 | G45: ='Revenue Build'!AR4 -> 173500 | H45: =K45 -> 177500 | I45: =H45/G45-1 -> 0.023054755 | J45: 177500 | K45: ='Revenue Build'!AS4 -> 177500 | L45: =K45/J45-1 -> 0
C46: Quarterly Adds | D46: ='Revenue Build'!AN5 -> 4500 | E46: =K46 -> 4000 | F46: =E46/D46-1 -> -0.11111111 | G46: ='Revenue Build'!AR5 -> 4000 | H46: =K46 -> 4000 | I46: =H46/G46-1 -> 0 | J46: 4000 | K46: ='Revenue Build'!AS5 -> 4000 | L46: =K46/J46-1 -> 0
C47: Sub. Revenue/Customer | D47: ='Revenue Build'!AN8 -> 339.35243 | E47: =K47 -> 325.07042 | F47: =E47/D47-1 -> -0.042086058 | G47: ='Revenue Build'!AR8 -> 323.34294 | H47: =K47 -> 325.07042 | I47: =H47/G47-1 -> 0.0053425724 | J47: 335.9589 | K47: ='Revenue Build'!AS8 -> 325.07042 | L47: =K47/J47-1 -> -0.032410159
B49: Total Payment Volume | D49: ='Revenue Build'!AN20*1000 -> 71900 | E49: =K49 -> 79900 | F49: =E49/D49-1 -> 0.11126565 | G49: ='Revenue Build'!AR20*1000 -> 74700 | H49: =K49 -> 79900 | I49: =H49/G49-1 -> 0.06961178 | J49: 76933 | K49: ='Revenue Build'!AS20*1000 -> 79900 | L49: =K49/J49-1 -> 0.038566025
C50: Transactions | D50: ='Revenue Build'!AN14 -> 12.2 | E50: =K50 -> 12.8 | F50: =E50/D50-1 -> 0.049180328 | G50: ='Revenue Build'!AR14 -> 12.5 | H50: =K50 -> 12.8 | I50: =H50/G50-1 -> 0.024 | J50: 13.054 | K50: ='Revenue Build'!AS14 -> 12.8 | L50: =K50/J50-1 -> -0.019457638
C51: Average Transaction Size | D51: ='Revenue Build'!AN17 -> 5893.4426 | E51: =K51 -> 6242.1875 | F51: =E51/D51-1 -> 0.05917507 | G51: ='Revenue Build'!AR17 -> 5976 | H51: =K51 -> 6242.1875 | I51: =H51/G51-1 -> 0.044542754 | J51: 5893.4426 | K51: ='Revenue Build'!AS17 -> 6242.1875 | L51: =K51/J51-1 -> 0.05917507
B53: Take Rate (BPs) | D53: ='Revenue Build'!AN23 -> 15.624757 | E53: =K53 -> 16.036045 | F53: =E53/D53-1 -> 0.026322871 | G53: ='Revenue Build'!AR23 -> 16.398394 | H53: =K53 -> 16.036045 | I53: =H53/G53-1 -> -0.022096586 | J53: 16.2 | K53: ='Revenue Build'!AS23 -> 16.036045 | L53: =K53/J53-1 -> -0.010120676
B55: Segment Revenue | D55: ='Revenue Build'!AN29 -> 166842 | E55: =K55 -> 185828 | F55: =E55/D55-1 -> 0.11379629 | G55: ='Revenue Build'!AR29 -> 178596 | H55: =K55 -> 185828 | I55: =H55/G55-1 -> 0.040493628 | J55: 184264.17 | K55: ='Revenue Build'!AS29 -> 185828 | L55: =K55/J55-1 -> 0.0084869161
C56: Subscription Revenue | D56: ='Revenue Build'!AN11 -> 54500 | E56: =K56 -> 57700 | F56: =E56/D56-1 -> 0.058715596 | G56: ='Revenue Build'!AR11 -> 56100 | H56: =K56 -> 57700 | I56: =H56/G56-1 -> 0.028520499 | J56: 59632.705 | K56: ='Revenue Build'!AS11 -> 57700 | L56: =K56/J56-1 -> -0.032410159
C57: Transaction Revenue | D57: ='Revenue Build'!AN26 -> 112342 | E57: =K57 -> 128128 | F57: =E57/D57-1 -> 0.14051735 | G57: ='Revenue Build'!AR26 -> 122496 | H57: =K57 -> 128128 | I57: =H57/G57-1 -> 0.045977011 | J57: 124631.46 | K57: ='Revenue Build'!AS26 -> 128128 | L57: =K57/J57-1 -> 0.028055035
B59: S&E Variance Analysis | D59: =IS!AN$4 -> 2Q25 | E59: =K59 -> 2Q26 | F59: Y/Y Change | G59: =IS!AR$4 -> 1Q26 | H59: =K59 -> 2Q26 | I59: Q/Q Change | J59: 2Q26E | K59: =IS!AS$4 -> 2Q26 | L59: % Difference
B60: Customer Count | D60: ='Revenue Build'!AN35 -> 37800 | E60: =K60 -> 44000 | F60: =E60/D60-1 -> 0.16402116 | G60: ='Revenue Build'!AR35 -> 42500 | H60: =K60 -> 44000 | I60: =H60/G60-1 -> 0.035294118 | J60: 43775 | K60: ='Revenue Build'!AS35 -> 44000 | L60: =K60/J60-1 -> 0.00513992
C61: Quarterly Adds | D61: ='Revenue Build'!AN36 -> 1400 | E61: =K61 -> 1500 | F61: =E61/D61-1 -> 0.071428571 | G61: ='Revenue Build'!AR36 -> 1400 | H61: =K61 -> 1500 | I61: =H61/G61-1 -> 0.071428571 | J61: 1275 | K61: ='Revenue Build'!AS36 -> 1500 | L61: =K61/J61-1 -> 0.17647059
B63: Total Payment Volume | D63: ='Revenue Build'!AN45*1000 -> 5200 | E63: =K63 -> 6500 | F63: =E63/D63-1 -> 0.25 | G63: ='Revenue Build'!AR45*1000 -> 6200 | H63: =K63 -> 6500 | I63: =H63/G63-1 -> 0.048387097 | J63: 6273.124 | K63: ='Revenue Build'!AS45*1000 -> 6500 | L63: =K63/J63-1 -> 0.03616635
C64: Transactions | D64: ='Revenue Build'!AN39 -> 16.1 | E64: =K64 -> 19.8 | F64: =E64/D64-1 -> 0.22981366 | G64: ='Revenue Build'!AR39 -> 18.8 | H64: =K64 -> 19.8 | I64: =H64/G64-1 -> 0.053191489 | J64: 19.481 | K64: ='Revenue Build'!AS39 -> 19.8 | L64: =K64/J64-1 -> 0.016374929
C65: Average Transaction Size | D65: ='Revenue Build'!AN42 -> 322.98137 | E65: =K65 -> 328.28283 | F65: =E65/D65-1 -> 0.016414141 | G65: ='Revenue Build'!AR42 -> 329.78723 | H65: =K65 -> 328.28283 | I65: =H65/G65-1 -> -0.0045617465 | J65: 322.01242 | K65: ='Revenue Build'!AS42 -> 328.28283 | L65: =K65/J65-1 -> 0.019472559
B67: Take Rate (BPs) | D67: ='Revenue Build'!AN48 -> 257.40962 | E67: =K67 -> 256.15385 | F67: =E67/D67-1 -> -0.0048784861 | G67: ='Revenue Build'!AR48 -> 253.6871 | H67: =K67 -> 256.15385 | I67: =H67/G67-1 -> 0.0097235902 | J67: 252.5 | K67: ='Revenue Build'!AS48 -> 256.15385 | L67: =K67/J67-1 -> 0.014470678
B69: Segment Revenue | D69: ='Revenue Build'!AN51 -> 133853 | E69: =K69 -> 166500 | F69: =E69/D69-1 -> 0.24390189 | G69: ='Revenue Build'!AR51 -> 157286 | H69: =K69 -> 166500 | I69: =H69/G69-1 -> 0.058581183 | J69: 158396.38 | K69: ='Revenue Build'!AS51 -> 166500 | L69: =K69/J69-1 -> 0.05116038
C70: Rewards - % of Revenue | D70: ='Revenue Build'!AN55 -> 0.48336608 | E70: =K70 -> 0.52252252 | F70: =E70/D70-1 -> 0.081007839 | G70: ='Revenue Build'!AR55 -> 0.51689279 | H70: =K70 -> 0.52252252 | I70: =H70/G70-1 -> 0.010891482 | K70: ='Revenue Build'!AS55 -> 0.52252252
B72: Embedded Variance Analysis | D72: =IS!AN$4 -> 2Q25 | E72: =K72 -> 2Q26 | F72: Y/Y Change | G72: =IS!AR$4 -> 1Q26 | H72: =K72 -> 2Q26 | I72: Q/Q Change | J72: 2Q26E | K72: =IS!AS$4 -> 2Q26 | L72: % Difference
B73: Customer Count | D73: ='Revenue Build'!AN60 -> 282900 | E73: =K73 -> 277000 | F73: =E73/D73-1 -> -0.020855426 | G73: ='Revenue Build'!AR60 -> 282500 | H73: =K73 -> 277000 | I73: =H73/G73-1 -> -0.019469027 | J73: 281500 | K73: ='Revenue Build'!AS60 -> 277000 | L73: =K73/J73-1 -> -0.01598579
C74: Quarterly Adds | D74: ='Revenue Build'!AN61 -> -800 | E74: =K74 -> -5500 | F74: =E74/D74-1 -> 5.875 | G74: ='Revenue Build'!AR61 -> -700 | H74: =K74 -> -5500 | I74: =H74/G74-1 -> 6.8571429 | J74: -1000 | K74: ='Revenue Build'!AS61 -> -5500 | L74: =K74/J74-1 -> 4.5
C75: Sub. Revenue/Customer | D75: ='Revenue Build'!AN64 -> 46.733828 | E75: =K75 -> 51.98556 | F75: =E75/D75-1 -> 0.11237537 | G75: ='Revenue Build'!AR64 -> 52.116814 | H75: =K75 -> 51.98556 | I75: =H75/G75-1 -> -0.0025184692 | J75: 47.668505 | K75: ='Revenue Build'!AS64 -> 51.98556 | L75: =K75/J75-1 -> 0.090564091
B77: Total Payment Volume | D77: ='Revenue Build'!AN76*1000 -> 7400 | E77: =K77 -> 8700 | F77: =E77/D77-1 -> 0.17567568 | G77: ='Revenue Build'!AR76*1000 -> 8400 | H77: =K77 -> 8700 | I77: =H77/G77-1 -> 0.035714286 | J77: 8857.8 | K77: ='Revenue Build'!AS76*1000 -> 8700 | L77: =K77/J77-1 -> -0.017814807
C78: Transactions | D78: ='Revenue Build'!AN70 -> 1.7 | E78: =K78 -> 2.1 | F78: =E78/D78-1 -> 0.23529412 | G78: ='Revenue Build'!AR70 -> 2 | H78: =K78 -> 2.1 | I78: =H78/G78-1 -> 0.05 | J78: 2.142 | K78: ='Revenue Build'!AS70 -> 2.1 | L78: =K78/J78-1 -> -0.019607843
C79: Average Transaction Size | D79: ='Revenue Build'!AN73 -> 4352.9412 | E79: =K79 -> 4142.8571 | F79: =E79/D79-1 -> -0.048262548 | G79: ='Revenue Build'!AR73 -> 4200 | H79: =K79 -> 4142.8571 | I79: =H79/G79-1 -> -0.013605442 | J79: 4135.2941 | K79: ='Revenue Build'!AS73 -> 4142.8571 | L79: =K79/J79-1 -> 0.0018288966
B81: Take Rate (BPs) | D81: ='Revenue Build'!AN79 -> 7.7027027 | E81: =K81 -> 9.6551724 | F81: =E81/D81-1 -> 0.25347852 | G81: ='Revenue Build'!AR79 -> 8.8095238 | H81: =K81 -> 9.6551724 | I81: =H81/G81-1 -> 0.095992544 | J81: 9 | K81: ='Revenue Build'!AS79 -> 9.6551724 | L81: =K81/J81-1 -> 0.072796935
B83: Segment Revenue | D83: ='Revenue Build'!AN85 -> 18921 | E83: =K83 -> 22800 | F83: =E83/D83-1 -> 0.20501031 | G83: ='Revenue Build'!AR85 -> 22123 | H83: =K83 -> 22800 | I83: =H83/G83-1 -> 0.030601636 | J83: 21390.704 | K83: ='Revenue Build'!AS85 -> 22800 | L83: =K83/J83-1 -> 0.065883568
C84: Subscription Revenue | D84: ='Revenue Build'!AN67 -> 13221 | E84: =K84 -> 14400 | F84: =E84/D84-1 -> 0.08917631 | G84: ='Revenue Build'!AR67 -> 14723 | H84: =K84 -> 14400 | I84: =H84/G84-1 -> -0.021938464 | J84: 13418.684 | K84: ='Revenue Build'!AS67 -> 14400 | L84: =K84/J84-1 -> 0.073130562
C85: Transaction Revenue | D85: ='Revenue Build'!AK82 -> 5500 | E85: =K85 -> 8400 | F85: =E85/D85-1 -> 0.52727273 | G85: ='Revenue Build'!AR82 -> 7400 | H85: =K85 -> 8400 | I85: =H85/G85-1 -> 0.13513514 | J85: 7972.02 | K85: ='Revenue Build'!AS82 -> 8400 | L85: =K85/J85-1 -> 0.053685264

Sheet Guide
C4: FY26 Guide Midpoint | D4: FY26 Prior Guide | E4: FY26 Updated Guidance | F4: Upside/ Downside | G4: 2Q Results | H4: 2Q Guide | I4: 2Q Beat | J4: Rest of Year Raise / (Reduce)
C5: Total Revenue | D5: 1612 | E5: 1641 | F5: =E5-D5 -> 29 | G5: =Comparison!K8/1000 -> 414.671 | H5: 399.5 | I5: =G5-H5 -> 15.171 | J5: =F5-I5 -> 13.829
C6: Growth | D6: =1000*D5/IS!AQ17-1 -> 0.10216947 | E6: =1000*E5/IS!AQ17-1 -> 0.12199758
C7: Non-GAAP Operating Income | D7: 267 | E7: 280.25 | F7: =E7-D7 -> 13.25 | G7: =Comparison!K20/1000 -> 74.085 | H7: 65 | I7: =G7-H7 -> 9.085 | J7: =F7-I7 -> 4.165
C8: Margin | D8: =D7/D5 -> 0.16563275 | E8: =E7/E5 -> 0.17078001
C9: Non-GAAP EPS | D9: 2.18 | E9: 2.37 | F9: =E9-D9 -> 0.19 | G9: =Comparison!K38 -> 0.64031276 | H9: 0.555 | I9: =G9-H9 -> 0.085312756 | J9: =F9-I9 -> 0.10468724
C17: FY26 Guide Midpoint | D17: FY26 Guide | E17: FY26E Street | F17: Upside/Downside
C18: Total Revenue | D18: =AVERAGE(1589.5,1629.5) -> 1609.5 | E18: 1634.2 | F18: =D18-E18 -> -24.7
C19: Growth | D19: =D18/(IS!AQ17/1000)-1 -> 0.10046015 | E19: =1000*E18/IS!AQ17-1 -> 0.11734823
C20: Non-GAAP Net Income | D20: 255 | E20: 259 | F20: =D20-E20 -> -4
C21: Margin | D21: =D20/D18 -> 0.1584343 | E21: =E20/E18 -> 0.15848733
C22: Non-GAAP EPS | D22: 2.1 | E22: 2.18 | F22: =D22-E22 -> -0.08
E24: =AVERAGE(1450.5,1490.5) -> 1470.5
E25: =E18-E24 -> 163.7

Sheet IS
B2: Bill.com, Inc. (BILL) | D2: ="Sep. " &C4 -> Sep. | E2: ="Dec. " &C4 -> Dec. | F2: ="Mar. " &H4 -> Mar. 2018 | G2: ="Jun. " &H4 -> Jun. 2018 | I2: ="Sep. " &H4 -> Sep. 2018 | J2: ="Dec. " &H4 -> Dec. 2018 | K2: ="Mar. " &M4 -> Mar. 2019 | L2: ="Jun. " &M4 -> Jun. 2019 | N2: ="Sep. " &M4 -> Sep. 2019 | O2: ="Dec. " &M4 -> Dec. 2019 | P2: ="Mar. " &R4 -> Mar. 2020 | Q2: ="Jun. " &R4 -> Jun. 2020 | S2: ="Sep. " &R4 -> Sep. 2020 | T2: ="Dec. " &R4 -> Dec. 2020 | U2: ="Mar. " &W4 -> Mar. 2021 | V2: ="Jun. " &W4 -> Jun. 2021 | X2: ="Sep. " &W4 -> Sep. 2021 | Y2: ="Dec. " &W4 -> Dec. 2021 | Z2: ="Mar. " &AB4 -> Mar. 2022 | AA2: ="Jun. " &AB4 -> Jun. 2022 | AC2: ="Sep. " &AB4 -> Sep. 2022 | AD2: ="Dec. " &AB4 -> Dec. 2022 | AE2: ="Mar. " &AG4 -> Mar. 2023 | AF2: ="Jun. " &AG4 -> Jun. 2023 | AH2: ="Sep. " &AG4 -> Sep. 2023 | AI2: ="Dec. " &AG4 -> Dec. 2023 | AJ2: ="Mar. " &AL4 -> Mar. 2024 | AK2: ="Jun. " &AL4 -> Jun. 2024 | AM2: ="Sep. " &AL4 -> Sep. 2024 | AN2: ="Dec. " &AL4 -> Dec. 2024 | AO2: ="Mar. " &AQ4 -> Mar. 2025 | AP2: ="Jun. " &AQ4 -> Jun. 2025 | AR2: ="Sep. " &AQ4 -> Sep. 2025 | AS2: ="Dec. " &AQ4 -> Dec. 2025 | AT2: ="Mar. " &AV4 -> Mar. 2026E | AU2: ="Jun. " &AV4 -> Jun. 2026E | AW2: ="Sep. " &AV4 -> Sep. 2026E | AX2: ="Dec. " &AV4 -> Dec. 2026E | AY2: ="Mar. " &BA4 -> Mar. 2027E | AZ2: ="Jun. " &BA4 -> Jun. 2027E
B4: Income Statement | D4: 1Q18 | E4: 2Q18 | F4: 3Q18 | G4: 4Q18 | H4: 2018 | I4: 1Q19 | J4: 2Q19 | K4: 3Q19 | L4: 4Q19 | M4: 2019 | N4: 1Q20 | O4: 2Q20 | P4: 3Q20 | Q4: 4Q20 | R4: 2020 | S4: 1Q21 | T4: 2Q21 | U4: 3Q21 | V4: 4Q21 | W4: 2021 | X4: 1Q22 | Y4: 2Q22 | Z4: 3Q22 | AA4: 4Q22 | AB4: 2022 | AC4: 1Q23 | AD4: 2Q23 | AE4: 3Q23 | AF4: 4Q23 | AG4: 2023 | AH4: 1Q24 | AI4: 2Q24 | AJ4: 3Q24 | AK4: 4Q24 | AL4: 2024 | AM4: 1Q25 | AN4: 2Q25 | AO4: 3Q25 | AP4: 4Q25 | AQ4: 2025 | AR4: 1Q26 | AS4: 2Q26 | AT4: 3Q26E | AU4: 4Q26E | AV4: 2026E | AW4: 1Q27E | AX4: 2Q27E | AY4: 3Q27E | AZ4: 4Q27E | BA4: 2027E
B5: Subscription Revenue | H5: 42000 | I5: 13070.323 | J5: 14316.547 | K5: 15400 | L5: 16813.13 | M5: =SUM(I5:L5) -> 59600 | N5: 18047.775 | O5: 19900 | P5: 22292 | Q5: 23600 | R5: =SUM(N5:Q5) -> 83839.775 | S5: 24600 | T5: 26600 | U5: 29300 | V5: 31200 | W5: =SUM(S5:V5) -> 111700 | X5: 36900 | Y5: 49200 | Z5: 52200 | AA5: ='Revenue Build'!AA143 -> 55300 | AB5: =SUM(X5:AA5) -> 193600 | AC5: 58100 | AD5: ='Revenue Build'!AD143 -> 61500 | AE5: ='Revenue Build'!AE143 -> 66700 | AF5: ='Revenue Build'!AF143 -> 66900 | AG5: =SUM(AC5:AF5) -> 253200 | AH5: ='Revenue Build'!AH143 -> 62400 | AI5: ='Revenue Build'!AI143 -> 63400 | AJ5: ='Revenue Build'!AJ143 -> 65600 | AK5: ='Revenue Build'!AK143 -> 65800 | AL5: =SUM(AH5:AK5) -> 257200 | AM5: ='Revenue Build'!AM143 -> 67383 | AN5: ='Revenue Build'!AN143 -> 67721 | AO5: ='Revenue Build'!AO143 -> 68115 | AP5: ='Revenue Build'!AP143 -> 68787 | AQ5: =SUM(AM5:AP5) -> 272006 | AR5: ='Revenue Build'!AR143 -> 70823 | AS5: ='Revenue Build'!AS143 -> 72100 | AT5: ='Revenue Build'!AT143 -> 72361.685 | AU5: ='Revenue Build'!AU143 -> 73465.459 | AV5: =SUM(AR5:AU5) -> 288750.14 | AW5: ='Revenue Build'!AW143 -> 76928.96 | AX5: ='Revenue Build'!AX143 -> 78464.912 | AY5: ='Revenue Build'!AY143 -> 78779.436 | AZ5: ='Revenue Build'!AZ143 -> 80148.65 | BA5: =SUM(AW5:AZ5) -> 314321.96
C6: Y/Y Growth | M6: =M5/H5-1 -> 0.41904762 | N6: =N5/I5-1 -> 0.38082086 | O6: =O5/J5-1 -> 0.39 | P6: =P5/K5-1 -> 0.44753247 | Q6: =Q5/L5-1 -> 0.40366485 | R6: =R5/M5-1 -> 0.40670763 | S6: =S5/N5-1 -> 0.36304894 | T6: =T5/O5-1 -> 0.33668342 | ... BA6: =BA5/AV5-1 -> 0.088560354
C7: Q/Q Growth | J7: =J5/I5-1 -> 0.095347595 | K7: =K5/J5-1 -> 0.075678392 | L7: =L5/K5-1 -> 0.09176171 | N7: =N5/L5-1 -> 0.073433335 | O7: =O5/N5-1 -> 0.10262902 | P7: =P5/O5-1 -> 0.12020101 | Q7: =Q5/P5-1 -> 0.058675758 | S7: =S5/Q5-1 -> 0.042372881 | T7: =T5/S5-1 -> 0.081300813 | U7: =U5/T5-1 -> 0.10150376 | V7: =V5/U5-1 -> 0.064846416 | X7: =X5/V5-1 -> 0.18269231 | Y7: =Y5/X5-1 -> 0.33333333 | Z7: =Z5/Y5-1 -> 0.06097561 | AA7: =AA5/Z5-1 -> 0.059386973 | AC7: =AC5/AA5-1 -> 0.050632911 | AD7: =AD5/AC5-1 -> 0.058519793 | AE7: =AE5/AD5-1 -> 0.084552846 | AF7: =AF5/AE5-1 -> 0.0029985007 | AH7: =AH5/AF5-1 -> -0.067264574 | AI7: =AI5/AH5-1 -> 0.016025641 | AJ7: =AJ5/AI5-1 -> 0.034700315 | AK7: =AK5/AJ5-1 -> 0.0030487805 | AM7: =AM5/AK5-1 -> 0.024057751 | AN7: =AN5/AM5-1 -> 0.005016102 | AO7: =AO5/AN5-1 -> 0.0058179885 | AP7: =AP5/AO5-1 -> 0.0098656684 | AR7: =AR5/AP5-1 -> 0.029598616 | AS7: =AS5/AR5-1 -> 0.018030866 | AT7: =AT5/AS5-1 -> 0.0036294789 | AU7: =AU5/AT5-1 -> 0.01525356 | AW7: =AW5/AU5-1 -> 0.047144624 | AX7: =AX5/AW5-1 -> 0.019965851 | AY7: =AY5/AX5-1 -> 0.0040084665 | AZ7: =AZ5/AY5-1 -> 0.017380346
B8: Transaction Revenue | I8: 5100 | J8: 6040 | K8: 6700 | L8: 8560 | M8: =SUM(I8:L8) -> 26400 | N8: 10500 | O8: 13100 | P8: 13800 | Q8: 15200 | R8: =SUM(N8:Q8) -> 52600 | S8: 19200 | T8: 25700 | U8: 29300 | V8: 46300 | W8: =SUM(S8:V8) -> 120500 | X8: 80600 | Y8: 106300 | Z8: 113300 | AA8: ='Revenue Build'!AA139 -> 139600 | AB8: =SUM(X8:AA8) -> 439800 | AC8: 156500 | AD8: ='Revenue Build'!AD139 -> 169600 | AE8: ='Revenue Build'!AE139 -> 172700 | AF8: ='Revenue Build'!AF139 -> 192600 | AG8: =SUM(AC8:AF8) -> 691400 | AH8: ='Revenue Build'!AH139 -> 202800 | AI8: ='Revenue Build'!AI139 -> 211600 | AJ8: ='Revenue Build'!AJ139-6 -> 215694 | AK8: ='Revenue Build'!AK139+6 -> 235506 | AL8: =SUM(AH8:AK8) -> 865600 | AM8: ='Revenue Build'!AM139 -> 247560 | AN8: ='Revenue Build'!AN139 -> 251895 | AO8: ='Revenue Build'!AO139 -> 252183 | AP8: ='Revenue Build'!AP139 -> 277160 | AQ8: =SUM(AM8:AP8) -> 1028798 | AR8: ='Revenue Build'!AR139 -> 287182 | AS8: ='Revenue Build'!AS139 -> 303028 | AT8: ='Revenue Build'!AT139 -> 296693.21 | AU8: ='Revenue Build'!AU139 -> 324479.68 | AV8: =SUM(AR8:AU8) -> 1211382.9 | AW8: ='Revenue Build'!AW139 -> 329854.59 | AX8: ='Revenue Build'!AX139 -> 345160.53 | AY8: ='Revenue Build'!AY139 -> 340465.02 | AZ8: ='Revenue Build'!AZ139 -> 370738.9 | BA8: =SUM(AW8:AZ8) -> 1386219
C9: Y/Y Growth | N9: =N8/I8-1 -> 1.0588235 | O9: =O8/J8-1 -> 1.1688742 | P9: =P8/K8-1 -> 1.0597015 | Q9: =Q8/L8-1 -> 0.77570093 | R9: =R8/M8-1 -> 0.99242424 | S9: =S8/N8-1 -> 0.82857143 | T9: =T8/O8-1 -> 0.96183206 | U9: =U8/P8-1 -> 1.1231884 | ... BA9: =BA8/AV8-1 -> 0.14432773
C10: Q/Q Growth | J10: =J8/I8-1 -> 0.18431373 | K10: =K8/J8-1 -> 0.10927152 | L10: =L8/K8-1 -> 0.27761194 | N10: =N8/L8-1 -> 0.22663551 | O10: =O8/N8-1 -> 0.24761905 | P10: =P8/O8-1 -> 0.053435115 | Q10: =Q8/P8-1 -> 0.10144928 | S10: =S8/Q8-1 -> 0.26315789 | T10: =T8/S8-1 -> 0.33854167 | U10: =U8/T8-1 -> 0.14007782 | V10: =V8/U8-1 -> 0.58020478 | X10: =X8/V8-1 -> 0.74082073 | Y10: =Y8/X8-1 -> 0.31885856 | Z10: =Z8/Y8-1 -> 0.065851364 | AA10: =AA8/Z8-1 -> 0.2321271 | AC10: =AC8/AA8-1 -> 0.12106017 | AD10: =AD8/AC8-1 -> 0.08370607 | AE10: =AE8/AD8-1 -> 0.018278302 | AF10: =AF8/AE8-1 -> 0.11522872 | AH10: =AH8/AF8-1 -> 0.052959502 | AI10: =AI8/AH8-1 -> 0.043392505 | AJ10: =AJ8/AI8-1 -> 0.019347826 | AK10: =AK8/AJ8-1 -> 0.091852346 | AM10: =AM8/AK8-1 -> 0.051183409 | AN10: =AN8/AM8-1 -> 0.017510906 | AO10: =AO8/AN8-1 -> 0.0011433335 | AP10: =AP8/AO8-1 -> 0.099043155 | AR10: =AR8/AP8-1 -> 0.036159619 | AS10: =AS8/AR8-1 -> 0.055177553 | AT10: =AT8/AS8-1 -> -0.020904953 | AU10: =AU8/AT8-1 -> 0.093653857 | AW10: =AW8/AU8-1 -> 0.0165647 | AX10: =AX8/AW8-1 -> 0.046402082 | AY10: =AY8/AX8-1 -> -0.01360383 | AZ10: =AZ8/AY8-1 -> 0.0889192
B11: Subscription & Transaction Fee Revenue | D11: 12365.458 | E11: 13337.97 | F11: 14920.695 | G11: 16367.558 | H11: =SUM(D11:G11) -> 56991.681 | I11: 18170.323 | J11: 20443.823 | K11: 22111.762 | L11: 25224.916 | M11: =SUM(I11:L11) -> 85950.823 | N11: 28547.775 | O11: 32964 | P11: 36092 | Q11: 38801 | R11: =SUM(N11:Q11) -> 136404.77 | S11: 43788 | T11: 52333 | U11: 58622 | V11: 77512 | W11: =SUM(S11:V11) -> 232255 | X11: =115600+1946 -> 117546 | Y11: =Y8+Y5 -> 155500 | Z11: =Z8+Z5 -> 165500 | AA11: 194820 | AB11: =AB8+AB5 -> 633400 | AC11: =AC8+AC5 -> 214600 | AD11: =AD8+AD5 -> 231100 | AE11: =AE8+AE5 -> 239400 | AF11: 259510 | AG11: 944710 | AH11: 265142 | AI11: 274992 | AJ11: =AJ8+AJ5 -> 281294 | AK11: =AK8+AK5 -> 301306 | AL11: =SUM(AH11:AK11) -> 1122734 | AM11: =AM5+AM8 -> 314943 | AN11: =AN8+AN5 -> 319616 | AO11: =AO8+AO5 -> 320298 | AP11: =AP8+AP5 -> 345947 | AQ11: =SUM(AM11:AP11) -> 1300804 | AR11: =AR5+AR8 -> 358005 | AS11: =AS8+AS5 -> 375128 | AT11: =AT8+AT5 -> 369054.9 | AU11: =AU8+AU5 -> 397945.14 | AV11: =SUM(AR11:AU11) -> 1500133 | AW11: =AW8+AW5 -> 406783.55 | AX11: =AX8+AX5 -> 423625.44 | AY11: =AY8+AY5 -> 419244.46 | AZ11: =AZ8+AZ5 -> 450887.55 | BA11: =SUM(AW11:AZ11) -> 1700541
C12: Y/Y Growth | I12: =I11/D11-1 -> 0.46944192 | J12: =J11/E11-1 -> 0.53275369 | K12: =K11/F11-1 -> 0.48195254 | L12: =L11/G11-1 -> 0.54115331 | M12: =M11/H11-1 -> 0.50812929 | N12: =N11/I11-1 -> 0.57112093 | O12: =O11/J11-1 -> 0.61241861 | P12: =P11/K11-1 -> 0.63225349 | ... BA12: =BA11/AV11-1 -> 0.13359345
C13: Q/Q Growth | J13: =J11/I11-1 -> 0.12512159 | K13: =K11/J11-1 -> 0.081586452 | L13: =L11/K11-1 -> 0.14079177 | N13: =N11/L11-1 -> 0.13172924 | O13: =O11/N11-1 -> 0.15469596 | P13: =P11/O11-1 -> 0.094891397 | Q13: =Q11/P11-1 -> 0.075058185 | S13: =S11/Q11-1 -> 0.12852762 | T13: =T11/S11-1 -> 0.19514479 | U13: =U11/T11-1 -> 0.12017274 | V13: =V11/U11-1 -> 0.32223397 | X13: =X11/V11-1 -> 0.51648777 | Y13: =Y11/X11-1 -> 0.32288636 | Z13: =Z11/Y11-1 -> 0.064308682 | AA13: =AA11/Z11-1 -> 0.17716012 | AC13: =AC11/AA11-1 -> 0.10152962 | AD13: =AD11/AC11-1 -> 0.076887232 | AE13: =AE11/AD11-1 -> 0.035915188 | AF13: =AF11/AE11-1 -> 0.084001671 | AH13: =AH11/AF11-1 -> 0.021702439 | AI13: =AI11/AH11-1 -> 0.037149905 | AJ13: =AJ11/AI11-1 -> 0.02291703 | AK13: =AK11/AJ11-1 -> 0.071142648 | AM13: =AM11/AK11-1 -> 0.045259636 | AN13: =AN11/AM11-1 -> 0.014837606 | AO13: =AO11/AN11-1 -> 0.0021338106 | AP13: =AP11/AO11-1 -> 0.080078552 | AR13: =AR11/AP11-1 -> 0.03485505 | AS13: =AS11/AR11-1 -> 0.047828941 | AT13: =AT11/AS11-1 -> -0.016189409 | AU13: =AU11/AT11-1 -> 0.078281679 | AW13: =AW11/AU11-1 -> 0.022210122 | AX13: =AX11/AW11-1 -> 0.041402588 | AY13: =AY11/AX11-1 -> -0.010341639 | AZ13: =AZ11/AY11-1 -> 0.075476469
B14: Interest on Client Funds Held | D14: 737.17115 | E14: 1825.148 | F14: 2177.0098 | G14: 3133.1164 | H14: =SUM(D14:G14) -> 7872.4454 | I14: ='Revenue Build'!I150 -> 4253.8067 | J14: ='Revenue Build'!J150 -> 5554.8275 | K14: ='Revenue Build'!K150 -> 6131.9238 | L14: ='Revenue Build'!L150 -> 6459.412 | M14: =SUM(I14:L14) -> 22399.97 | N14: ='Revenue Build'!N150 -> 6631.7051 | O14: ='Revenue Build'!O150 -> 6116 | P14: ='Revenue Build'!P150 -> 5138 | Q14: ='Revenue Build'!Q150 -> 3309 | R14: =SUM(N14:Q14) -> 21194.705 | S14: ='Revenue Build'!S150 -> 2421 | T14: ='Revenue Build'!T150 -> 1712 | U14: ='Revenue Build'!U150 -> 1116 | V14: ='Revenue Build'!V150 -> 761 | W14: =SUM(S14:V14) -> 6010 | X14: ='Revenue Build'!X150 -> 803 | Y14: ='Revenue Build'!Y150 -> 978 | Z14: ='Revenue Build'!Z150 -> 1411 | AA14: ='Revenue Build'!AA150 -> 5401 | AB14: =SUM(X14:AA14) -> 8593 | AC14: ='Revenue Build'!AC150 -> 15324 | AD14: ='Revenue Build'!AD150 -> 28900 | AE14: ='Revenue Build'!AE150 -> 33100 | AF14: ='Revenue Build'!AF150 -> 36473 | AG14: =SUM(AC14:AF14) -> 113797 | AH14: ='Revenue Build'!AH150 -> 39843 | AI14: ='Revenue Build'!AI150 -> 43503 | AJ14: ='Revenue Build'!AJ150 -> 41734 | AK14: ='Revenue Build'!AK150 -> 42359 | AL14: =SUM(AH14:AK14) -> 167439 | AM14: ='Revenue Build'!AM150 -> 43507 | AN14: 42938 | AO14: ='Revenue Build'!AO150 -> 37919 | AP14: ='Revenue Build'!AP150 -> 37402 | AQ14: =SUM(AM14:AP14) -> 161766 | AR14: ='Revenue Build'!AR150 -> 37736 | AS14: ='Revenue Build'!AS150 -> 39543 | AT14: ='Revenue Build'!AT150 -> 33804.176 | AU14: ='Revenue Build'!AU150 -> 31902.473 | AV14: =SUM(AR14:AU14) -> 142985.65 | AW14: ='Revenue Build'!AW150 -> 32443.469 | AX14: ='Revenue Build'!AX150 -> 31564.844 | AY14: ='Revenue Build'!AY150 -> 30314.432 | AZ14: ='Revenue Build'!AZ150 -> 32126.365 | BA14: =SUM(AW14:AZ14) -> 126449.11
C15: Y/Y Growth | I15: =I14/D14-1 -> 4.7704465 | J15: =J14/E14-1 -> 2.0434943 | K15: =K14/F14-1 -> 1.8166725 | L15: =L14/G14-1 -> 1.0616572 | M15: =M14/H14-1 -> 1.8453637 | N15: =N14/I14-1 -> 0.55900481 | O15: =O14/J14-1 -> 0.10102428 | P15: =P14/K14-1 -> -0.16209005 | ... BA15: =BA14/AV14-1 -> -0.11565173
C16: Q/Q Growth | E16: =E14/D14-1 -> 1.4758809 | F16: =F14/E14-1 -> 0.19278538 | G16: =G14/F14-1 -> 0.43918339 | I16: =I14/G14-1 -> 0.35769187 | J16: =J14/I14-1 -> 0.30584862 | K16: =K14/J14-1 -> 0.10389094 | L16: =L14/K14-1 -> 0.053407084 | N16: =N14/L14-1 -> 0.02667318 | O16: =O14/N14-1 -> -0.07776357 | P16: =P14/O14-1 -> -0.15990844 | Q16: =Q14/P14-1 -> -0.35597509 | S16: =S14/Q14-1 -> -0.26835902 | T16: =T14/S14-1 -> -0.29285419 | U16: =U14/T14-1 -> -0.34813084 | V16: =V14/U14-1 -> -0.31810036 | X16: =X14/V14-1 -> 0.055190539 | Y16: =Y14/X14-1 -> 0.21793275 | Z16: =Z14/Y14-1 -> 0.44274029 | AA16: =AA14/Z14-1 -> 2.8277817 | AC16: =AC14/AA14-1 -> 1.8372524 | AD16: =AD14/AC14-1 -> 0.88593057 | AE16: =AE14/AD14-1 -> 0.14532872 | AF16: =AF14/AE14-1 -> 0.10190332 | AH16: =AH14/AF14-1 -> 0.092397116 | AI16: =AI14/AH14-1 -> 0.091860553 | AJ16: =AJ14/AI14-1 -> -0.040663862 | AK16: =AK14/AJ14-1 -> 0.014975799 | AM16: =AM14/AK14-1 -> 0.027101679 | AN16: =AN14/AM14-1 -> -0.013078355 | AO16: =AO14/AN14-1 -> -0.11688947 | AP16: =AP14/AO14-1 -> -0.013634326 | AR16: =AR14/AP14-1 -> 0.0089300037 | AS16: =AS14/AR14-1 -> 0.047885308 | AT16: =AT14/AS14-1 -> -0.14512869 | AU16: =AU14/AT14-1 -> -0.056256468 | AW16: =AW14/AU14-1 -> 0.016957828 | AX16: =AX14/AW14-1 -> -0.027081721 | AY16: =AY14/AX14-1 -> -0.039614085 | AZ16: =AZ14/AY14-1 -> 0.059771303
B17: Total Revenues | D17: =D11+D14 -> 13102.63 | E17: =E11+E14 -> 15163.118 | F17: =F11+F14 -> 17097.705 | G17: =G11+G14 -> 19500.674 | H17: =H11+H14 -> 64864.126 | I17: =I11+I14 -> 22424.13 | J17: =J11+J14 -> 25998.65 | K17: =K11+K14 -> 28243.685 | ... X17: =X11+X14 -> 118349 | Y17: 156478 | Z17: 166911 | AA17: 200221 | AB17: =SUM(X17:AA17) -> 641959 | AC17: =AC11+AC14 -> 229924 | AD17: 260006 | AE17: 272555 | AF17: 295983 | AG17: =SUM(AC17:AF17) -> 1058468 | AH17: =AH11+AH14 -> 304985 | AI17: =AI11+AI14 -> 318495 | AJ17: =AJ11+AJ14 -> 323028 | AK17: =AK11+AK14 -> 343665 | AL17: =SUM(AH17:AK17) -> 1290173 | AM17: =AM11+AM14 -> 358450 | AN17: =AN11+AN14 -> 362554 | AO17: =AO11+AO14 -> 358217 | AP17: =AP11+AP14 -> 383349 | AQ17: =SUM(AM17:AP17) -> 1462570 | AR17: =AR11+AR14 -> 395741 | AS17: =AS11+AS14 -> 414671 | AT17: =AT11+AT14 -> 402859.08 | AU17: =AU11+AU14 -> 429847.61 | AV17: =SUM(AR17:AU17) -> 1643118.7 | AW17: =AW11+AW14 -> 439227.02 | AX17: =AX11+AX14 -> 455190.28 | AY17: =AY11+AY14 -> 449558.89 | AZ17: =AZ11+AZ14 -> 483013.91 | BA17: =SUM(AW17:AZ17) -> 1826990.1
C18: Y/Y Growth | I18: =I17/D17-1 -> 0.71142209 | J18: =J17/E17-1 -> 0.71459791 | K18: =K17/F17-1 -> 0.65189924 | L18: =L17/G17-1 -> 0.62478115 | M18: =M17/H17-1 -> 0.67042708 | N18: =N17/I17-1 -> 0.56882253 | O18: =O17/J17-1 -> 0.50315496 | P18: =P17/K17-1 -> 0.45979533 | ... BA18: =BA17/AV17-1 -> 0.11190392
C19: Q/Q Growth | E19: =E17/D17-1 -> 0.15725762 | F19: =F17/E17-1 -> 0.12758503 | G19: =G17/F17-1 -> 0.14054339 | I19: =I17/G17-1 -> 0.14991562 | J19: =J17/I17-1 -> 0.1594051 | K19: =K17/J17-1 -> 0.086351992 | L19: =L17/K17-1 -> 0.12181987 | N19: =N17/L17-1 -> 0.1103117 | O19: =O17/N17-1 -> 0.11087487 | P19: =P17/O17-1 -> 0.055015353 | Q19: =Q17/P17-1 -> 0.021343682 | S19: =S17/Q17-1 -> 0.097340299 | T19: =T17/S17-1 -> 0.16957736 | U19: =U17/T17-1 -> 0.10533814 | V19: =V17/U17-1 -> 0.31027152 | X19: =X17/V17-1 -> 0.51200286 | Y19: =Y17/X17-1 -> 0.32217425 | Z19: =Z17/Y17-1 -> 0.066673909 | AA19: =AA17/Z17-1 -> 0.19956743 | AC19: =AC17/AA17-1 -> 0.14835107 | AD19: =AD17/AC17-1 -> 0.13083454 | AE19: =AE17/AD17-1 -> 0.048264271 | AF19: =AF17/AE17-1 -> 0.085956963 | AH19: =AH17/AF17-1 -> 0.030413909 | AI19: =AI17/AH17-1 -> 0.044297261 | AJ19: =AJ17/AI17-1 -> 0.014232563 | AK19: =AK17/AJ17-1 -> 0.063886103 | AM19: =AM17/AK17-1 -> 0.043021547 | AN19: =AN17/AM17-1 -> 0.011449296 | AO19: =AO17/AN17-1 -> -0.011962356 | AP19: =AP17/AO17-1 -> 0.070158591 | AR19: =AR17/AP17-1 -> 0.032325635 | AS19: =AS17/AR17-1 -> 0.047834316 | AT19: =AT17/AS17-1 -> -0.028485051 | AU19: =AU17/AT17-1 -> 0.066992492 | AW19: =AW17/AU17-1 -> 0.021820307 | AX19: =AX17/AW17-1 -> 0.036344 | AY19: =AY17/AX17-1 -> -0.012371515 | AZ19: =AZ17/AY17-1 -> 0.074417446
B21: Cost of Revenue | D21: 3903.0364 | E21: 4027.9458 | F21: 4565.125 | G21: 4973.4755 | H21: =SUM(D21:G21) -> 17469.583 | I21: 5577 | J21: 6289 | K21: 6770.564 | L21: 7560 | M21: =SUM(I21:L21) -> 26196.564 | N21: 8010.4169 | O21: =9787-211-982 -> 8594 | P21: =10110-422-956 -> 8732 | Q21: =10100-476-608 -> 9016 | R21: =SUM(N21:Q21) -> 34352.417 | S21: =10605+400 -> 11005 | T21: =12246+400 -> 12646 | U21: =15434-728-119-800 -> 13787 | V21: =20293-967-2653-108-709 -> 15856 | W21: =SUM(S21:V21) -> 53294 | X21: =29835-1127-8401-163-721 -> 19423 | Y21: =34386-9285-1285-89-763 -> 22964 | Z21: =37342-1401-9285-881 -> 25775 | AA21: =43441-10172-1534 -> 31735 | AB21: =SUM(X21:AA21) -> 99897 | AC21: =34820-2066 -> 32754 | AD21: =47467-10502-2353 -> 34612 | AE21: =37897-2514 -> 35383 | AF21: =52552-11225-2495 -> 38832 | AG21: =SUM(AC21:AF21) -> 141581 | AH21: =44904-2628 -> 42276 | AI21: =47239-2446 -> 44793 | AJ21: =43845-2277 -> 41568 | AK21: =53905+11295-11295-2243 -> 51662 | AL21: =SUM(AH21:AK21) -> 180299 | AM21: =53602+11094-11094-2183 -> 51419 | AN21: =56298+10310-10310-2654 -> 53644 | AO21: =56733-2530 -> 54203 | AP21: =63172-2553 -> 60619 | AQ21: =SUM(AM21:AP21) -> 219885 | AR21: =66066-2405 -> 63661 | AS21: =69190-2298 -> 66892 | AT21: =AT17*(1-AT23) -> 65666.029 | AU21: =AU17*(1-AU23) -> 72644.246 | AV21: =SUM(AR21:AU21) -> 268863.28 | AW21: =AW17*(1-AW23) -> 67640.96 | AX21: =AX17*(1-AX23) -> 70099.303 | AY21: =AY17*(1-AY23) -> 71929.422 | AZ21: =AZ17*(1-AZ23) -> 81146.337 | BA21: =SUM(AW21:AZ21) -> 290816.02
B22: Gross Profit | D22: =D17-D21 -> 9199.5931 | E22: =E17-E21 -> 11135.172 | F22: =F17-F21 -> 12532.58 | G22: =G17-G21 -> 14527.198 | H22: =H17-H21 -> 47394.543 | I22: =I17-I21 -> 16847.13 | J22: =J17-J21 -> 19709.65 | K22: =K17-K21 -> 21473.121 | ... BA22: =BA17-BA21 -> 1536174.1
C23: Gross Margin | D23: =D22/D17 -> 0.70211808 | E23: =E22/E17 -> 0.734359 | F23: =F22/F17 -> 0.73299779 | G23: =G22/G17 -> 0.74495879 | H23: =H22/H17 -> 0.7306742 | I23: =I22/I17 -> 0.75129469 | J23: =J22/J17 -> 0.75810283 | K23: =K22/K17 -> 0.76028043 | ... AS23: =AS22/AS17 -> 0.83868657 | AT23: 0.837 | AU23: 0.831 | AV23: =AV22/AV17 -> 0.83637014 | AW23: 0.846 | AX23: 0.846 | AY23: 0.84 | AZ23: 0.832 | BA23: =BA22/BA17 -> 0.84082233
B25: Operating Expenses
C26: Research & Development | D26: 4598.3355 | E26: 4806.1979 | F26: 5245.8858 | G26: 5549.8605 | H26: =SUM(D26:G26) -> 20200.28 | I26: 6159.1792 | J26: 6542 | K26: 8050 | L26: 9102 | M26: =SUM(I26:L26) -> 29853.179 | N26: 10942.971 | O26: =12992-1084+74 -> 11982 | P26: =13969-1466+280 -> 12783 | Q26: =14929-2274+67 -> 12722 | R26: =SUM(N26:Q26) -> 48429.971 | S26: =15484-700 -> 14784 | T26: =17848-500 -> 17348 | U26: 18031 | V26: 22792 | W26: =SUM(S26:V26) -> 72955 | X26: =42472-10560-582-588 -> 30742 | Y26: =51954-14280-659-577 -> 36438 | Z26: =60230-14998-581 -> 44651 | AA26: =66908-16681 -> 50227 | AB26: =SUM(X26:AA26) -> 162058 | AC26: 53764 | AD26: =78910-27310 -> 51600 | AE26: =78761-23274 -> 55487 | AF26: =81841-23935 -> 57906 | AG26: =SUM(AC26:AF26) -> 218757 | AH26: =89065-27887 -> 61178 | AI26: =86489-26550 -> 59939 | AJ26: 55532 | AK26: 54348 | AL26: =SUM(AH26:AK26) -> 230997 | AM26: 54709 | AN26: =84784-29774 -> 55010 | AO26: 57987 | AP26: 62098 | AQ26: =SUM(AM26:AP26) -> 229804 | AR26: 53860 | AS26: 53256 | AT26: =AT17*AT27 -> 53983.116 | AU26: =AU17*AU27 -> 55880.189 | AV26: =SUM(AR26:AU26) -> 216979.31 | AW26: =AW17*AW27 -> 60613.328 | AX26: =AX17*AX27 -> 61905.878 | AY26: =AY17*AY27 -> 61140.009 | AZ26: =AZ17*AZ27 -> 65689.892 | BA26: =SUM(AW26:AZ26) -> 249349.11
C27: % of Revenue | D27: =D26/D17 -> 0.35094753 | E27: =E26/E17 -> 0.31696633 | F27: =F26/F17 -> 0.30681813 | G27: =G26/G17 -> 0.2845984 | H27: =H26/H17 -> 0.31142453 | I27: =I26/I17 -> 0.27466748 | J27: =J26/J17 -> 0.25162845 | K27: =K26/K17 -> 0.28501946 | ... AS27: =AS26/AS17 -> 0.12842953 | AT27: 0.134 | AU27: 0.13 | AV27: =AV26/AV17 -> 0.13205334 | AW27: 0.138 | AX27: 0.136 | AY27: 0.136 | AZ27: 0.136 | BA27: =BA26/BA17 -> 0.13648082
C28: Rewards Expense | X28: =AC28-23400 -> 15600 | Y28: =AE28-21500 -> 21500 | Z28: =AE28-18400 -> 24600 | AA28: ='Revenue Build'!AA54 -> 34400 | AB28: =AG28-78700 -> 96000 | AC28: ='Revenue Build'!AC54 -> 39000 | AD28: ='Revenue Build'!AD54 -> 44000 | AE28: ='Revenue Build'!AE54 -> 43000 | AF28: ='Revenue Build'!AF54 -> 48700 | AG28: =SUM(AC28:AF28) -> 174700 | AH28: ='Revenue Build'!AH54 -> 51800 | AI28: ='Revenue Build'!AI54 -> 53700 | AJ28: ='Revenue Build'!AJ54 -> 53800 | AK28: ='Revenue Build'!AK54 -> 60500 | AL28: =SUM(AH28:AK28) -> 219800 | AM28: ='Revenue Build'!AM54 -> 62100 | AN28: ='Revenue Build'!AN54 -> 64700 | AO28: ='Revenue Build'!AO54 -> 68400 | AP28: ='Revenue Build'!AP54 -> 76800 | AQ28: =SUM(AM28:AP28) -> 272000 | AR28: ='Revenue Build'!AR54 -> 81300 | AS28: ='Revenue Build'!AS54 -> 87000
C29: % of Revenue | X29: =X28/X17 -> 0.13181353 | Y29: =Y28/Y17 -> 0.13739951 | Z29: =Z28/Z17 -> 0.14738394 | AA29: =AA28/AA17 -> 0.17181015 | AB29: =AB28/AB17 -> 0.14954226 | AC29: =AC28/AC17 -> 0.16962127 | AD29: =AD28/AD17 -> 0.16922686 | AE29: =AE28/AE17 -> 0.15776632 | ... AS29: =AS28/AS17 -> 0.20980488
C30: Other S&M | X30: =X32-X28 -> 29719 | Y30: =Y32-Y28 -> 37070 | Z30: =Z32-Z28 -> 38363 | AA30: =AA32-AA28 -> 44533 | AB30: =SUM(X30:AA30) -> 149685 | AC30: =AC32-AC28 -> 49441 | AD30: =AD32-AD28 -> 50865 | AE30: =AE32-AE28 -> 53748 | AF30: =AF32-AF28 -> 54697 | AG30: =SUM(AC30:AF30) -> 208751 | AH30: =AH32-AH28 -> 52516 | AI30: =AI32-AI28 -> 51596 | AJ30: =AJ32-AJ28 -> 52888 | AK30: =AK32-AK28 -> 51667 | AL30: =SUM(AH30:AK30) -> 208667 | AM30: =AM32-AM28 -> 53328 | AN30: =AN32-AN28 -> 57178 | AO30: =AO32-AO28 -> 58489 | AP30: =AP32-AP28 -> 61916 | AQ30: =SUM(AM30:AP30) -> 230911 | AR30: =AR32-AR28 -> 58115 | AS30: =AS32-AS28 -> 58251
C31: % of Revenue | X31: =X30/X17 -> 0.25111323 | Y31: =Y30/Y17 -> 0.23690231 | Z31: =Z30/Z17 -> 0.22984105 | AA31: =AA30/AA17 -> 0.22241923 | AB31: =AB30/AB17 -> 0.2331691 | AC31: =AC30/AC17 -> 0.21503192 | AD31: =AD30/AD17 -> 0.1956301 | AE31: =AE30/AE17 -> 0.19720057 | ... AS31: =AS30/AS17 -> 0.14047522 | BA31: =BA30/BA15 -> 0
C32: Sales & Marketing | D32: 4279.077 | E32: 4654.7802 | F32: 4808.867 | G32: 6245.3872 | H32: =SUM(D32:G32) -> 19988.111 | I32: 5763.5565 | J32: 7226.2048 | K32: 7414 | L32: 10155.767 | M32: =SUM(I32:L32) -> 30559.528 | N32: 10344.749 | O32: =11491-494+682 -> 11679 | P32: =11802-767+506 -> 11541 | Q32: =11796-1134+1306 -> 11968 | R32: =SUM(N32:Q32) -> 45532.749 | S32: =11940-1100 -> 10840 | T32: =12592-1000 -> 11592 | U32: 13156 | V32: 22254 | W32: =SUM(S32:V32) -> 57842 | X32: =62312-8114-195-8271-413 -> 45319 | Y32: =80817-10483-11039-288-437 -> 58570 | Z32: =92065-18179-10484-439 -> 62963 | AA32: =102484-23551 -> 78933 | AB32: =SUM(X32:AA32) -> 245785 | AC32: 88441 | AD32: =164683-69818 -> 94865 | AE32: =115350-18602 -> 96748 | AF32: =117199-13802 -> 103397 | AG32: =SUM(AC32:AF32) -> 383451 | AH32: =118398-14082 -> 104316 | AI32: =118305-13009 -> 105296 | AJ32: 106688 | AK32: 112167 | AL32: =SUM(AH32:AK32) -> 428467 | AM32: 115428 | AN32: =132534-10656 -> 121878 | AO32: 126889 | AP32: 138716 | AQ32: =SUM(AM32:AP32) -> 502911 | AR32: 139415 | AS32: 145251 | AT32: =AT17*AT33 -> 144827.84 | AU32: =AU17*AU33 -> 153756.49 | AV32: =SUM(AR32:AU32) -> 583250.33 | AW32: =AW17*AW33 -> 155925.59 | AX32: =AX17*AX33 -> 160226.98 | AY32: =AY17*AY33 -> 159143.85 | AZ32: =AZ17*AZ33 -> 170503.91 | BA32: =SUM(AW32:AZ32) -> 645800.33
C33: % of Revenue | D33: =D32/D17 -> 0.32658155 | E33: =E32/E17 -> 0.30698042 | F33: =F32/F17 -> 0.28125804 | G33: =G32/G17 -> 0.3202652 | H33: =H32/H17 -> 0.30815356 | I33: =I32/I17 -> 0.25702476 | J33: =J32/J17 -> 0.27794539 | K33: =K32/K17 -> 0.26250115 | ... AS33: =AS32/AS17 -> 0.3502801 | AT33: 0.3595 | AU33: 0.3577 | AV33: =AV32/AV17 -> 0.35496543 | AW33: 0.355 | AX33: 0.352 | AY33: 0.354 | AZ33: 0.353 | BA33: =BA32/BA17 -> 0.35347774
C34: Provision for expected credit losses | X34: 4035 | Y34: 5190 | Z34: 6085 | AA34: =19566-SUM(X34:Z34) -> 4256 | AB34: =SUM(X34:AA34) -> 19566 | AC34: 6583 | AD34: 8520 | AE34: 8425 | AF34: =32224-SUM(AC34:AE34) -> 8696 | AG34: =SUM(AC34:AF34) -> 32224 | AH34: 11975 | AI34: 14354 | AJ34: 15104 | AK34: =60105-SUM(AH34:AJ34) -> 18672 | AL34: =SUM(AH34:AK34) -> 60105 | AM34: 20661 | AN34: 21358 | AO34: 14945 | AP34: 15785 | AQ34: =SUM(AM34:AP34) -> 72749 | AR34: 16096 | AS34: 22624
C35: % of Revenue | X35: =X34/X17 -> 0.034094078 | Y35: =Y34/Y17 -> 0.033167602 | Z35: =Z34/Z17 -> 0.036456555 | AA35: =AA34/AA17 -> 0.021256512 | AB35: =AB34/AB17 -> 0.030478582 | AC35: =AC34/AC17 -> 0.0286312 | AD35: =AD34/AD17 -> 0.032768475 | AE35: =AE34/AE17 -> 0.030911192 | ... AS35: =AS34/AS17 -> 0.054558915
C36: Other G&A | X36: =X38-X34 -> 28028 | Y36: =Y38-Y34 -> 29934 | Z36: =Z38-Z34 -> 33115 | AA36: =AA38-AA34 -> 38239 | AB36: =SUM(X36:AA36) -> 129316 | AC36: =AC38-AC34 -> 39237 | AD36: =AD38-AD34 -> 39657 | AE36: =AE38-AE34 -> 41671 | AF36: =AF38-AF34 -> 44804 | AG36: =SUM(AC36:AF36) -> 165369 | AH36: =AH38-AH34 -> 51867 | AI36: =AI38-AI34 -> 49810 | AJ36: =AJ38-AJ34 -> 45603 | AK36: =AK38-AK34 -> 46845 | AL36: =SUM(AH36:AK36) -> 194125 | AM36: =AM38-AM34 -> 49145 | AN36: =AN38-AN34 -> 47858 | AO36: =AO38-AO34 -> 50894 | AP36: =AP38-AP34 -> 49779 | AQ36: =SUM(AM36:AP36) -> 197676 | AR36: =AR38-AR34 -> 54473 | AS36: =AS38-AS34 -> 52563
C37: % of Revenue | X37: =X36/X17 -> 0.23682498 | Y37: =Y36/Y17 -> 0.19129846 | Z37: =Z36/Z17 -> 0.19839915 | AA37: =AA36/AA17 -> 0.19098396 | AB37: =AB36/AB17 -> 0.20143966 | AC37: =AC36/AC17 -> 0.17065204 | AD37: =AD36/AD17 -> 0.1525234 | AE37: =AE36/AE17 -> 0.15289024 | ... AS37: =AS36/AS17 -> 0.12675832
C38: General & Administrative | D38: 3199.584 | E38: 3278.035 | F38: 4268.4498 | G38: 4436.5703 | H38: =SUM(D38:G38) -> 15182.639 | I38: 5698.7928 | J38: 6010 | K38: 7117 | L38: 8048 | M38: =SUM(I38:L38) -> 26873.793 | N38: 9395.2055 | O38: =12748-1286-127 -> 11335 | P38: =15064-2430-133 -> 12501 | Q38: =15546-3744-789 -> 11013 | R38: =SUM(N38:Q38) -> 44244.205 | S38: 11857 | T38: 14017 | U38: 16894 | V38: 23569 | W38: =SUM(S38:V38) -> 66337 | X38: =57935-18086-1042-6325-419 -> 32063 | Y38: =65396-23080-2343-432-4417 -> 35124 | Z38: =60457-20565-243-449 -> 39200 | AA38: =58686-16191 -> 42495 | AB38: =SUM(X38:AA38) -> 148882 | AC38: 45820 | AD38: =69381-20989-215 -> 48177 | AE38: =71719-21334-289 -> 50096 | AF38: =73441-18937-1004 -> 53500 | AG38: =SUM(AC38:AF38) -> 197593 | AH38: =85326-21387-97 -> 63842 | AI38: =85583-20547-872 -> 64164 | AJ38: 60707 | AK38: =50732+14785 -> 65517 | AL38: =SUM(AH38:AK38) -> 254230 | AM38: =49145+20661 -> 69806 | AN38: =71122+21358-23264 -> 69216 | AO38: =50894+14945 -> 65839 | AP38: =49779+15785 -> 65564 | AQ38: =SUM(AM38:AP38) -> 270425 | AR38: =54473+16096 -> 70569 | AS38: =52563+22624 -> 75187 | AT38: =AT17*AT39 -> 73320.352 | AU38: =AU17*AU39 -> 74363.636 | AV38: =SUM(AR38:AU38) -> 293439.99 | AW38: =AW17*AW39 -> 79500.09 | AX38: =AX17*AX39 -> 81479.061 | AY38: =AY17*AY39 -> 81370.159 | AZ38: =AZ17*AZ39 -> 84044.421 | BA38: =SUM(AW38:AZ38) -> 326393.73
C39: % of Revenue | D39: =D38/D17 -> 0.24419404 | E39: =E38/E17 -> 0.21618476 | F39: =F38/F17 -> 0.24965046 | G39: =G38/G17 -> 0.22750856 | H39: =H38/H17 -> 0.23406835 | I39: =I38/I17 -> 0.25413663 | J39: =J38/J17 -> 0.23116585 | K39: =K38/K17 -> 0.25198553 | ... AS39: =AS38/AS17 -> 0.18131724 | AT39: 0.182 | AU39: 0.173 | AV39: =AV38/AV17 -> 0.17858721 | AW39: 0.181 | AX39: 0.179 | AY39: 0.181 | AZ39: 0.174 | BA39: =BA38/BA17 -> 0.17865107
B40: Total Operating Expense | D40: =D26+D32+D38 -> 12076.996 | E40: =E26+E32+E38 -> 12739.013 | F40: =F26+F32+F38 -> 14323.203 | G40: =G26+G32+G38 -> 16231.818 | H40: =H26+H32+H38 -> 55371.03 | I40: =I26+I32+I38 -> 17621.528 | J40: =J26+J32+J38 -> 19778.205 | K40: =K26+K32+K38 -> 22581 | ... BA40: =BA26+BA32+BA38 -> 1221543.2
B42: Non-GAAP Operating Income | D42: =D22-D40 -> -2877.4033 | E42: =E22-E40 -> -1603.841 | F42: =F22-F40 -> -1790.623 | G42: =G22-G40 -> -1704.6195 | H42: =H22-H40 -> -7976.4868 | I42: =I22-I40 -> -774.39889 | J42: =J22-J40 -> -68.55468 | K42: =K22-K40 -> -1107.8786 | ... BA42: =BA22-BA40 -> 314630.91
C43: Non-GAAP Operating Margin | D43: =D42/D17 -> -0.21960503 | E43: =E42/E17 -> -0.1057725 | F43: =F42/F17 -> -0.10472885 | G43: =G42/G17 -> -0.087413365 | H43: =H42/H17 -> -0.12297224 | I43: =I42/I17 -> -0.034534178 | J43: =J42/J17 -> -0.0026368554 | K43: =K42/K17 -> -0.03922571 | ... BA43: =BA42/BA17 -> 0.17221271
B45: GAAP Adjustments
C46: Amortization of intangibles | V46: 5659 | W46: =SUM(S46:V46) -> 5659 | X46: =8401+8271 -> 16672 | Y46: 19768 | Z46: =9285+10484 -> 19769 | AA46: 19769 | AB46: =SUM(X46:AA46) -> 75978 | AC46: 19769 | AD46: 19994 | AE46: 20220 | AF46: 20221 | AG46: =SUM(AC46:AF46) -> 80204 | AH46: =23939-AH47 -> 20221 | AI46: =23462-AI47 -> 20222 | AJ46: 23429 | AK46: 22965 | AL46: =SUM(AH46:AK46) -> 86837 | AM46: 20107 | AN46: 18168 | AO46: 18336 | AP46: 18325 | AQ46: =SUM(AM46:AP46) -> 74936 | AR46: 19004 | AS46: 22779 | AT46: 20000 | AU46: 20000 | AV46: =SUM(AR46:AU46) -> 81783 | AW46: 20000 | AX46: 20000 | AY46: 20000 | AZ46: 20000 | BA46: =SUM(AW46:AZ46) -> 80000
C47: Depreciation | H47: =SUM(D47:G47) -> 0 | M47: =SUM(I47:L47) -> 0 | R47: =SUM(N47:Q47) -> 0 | S47: =-400+1600 -> 1200 | T47: =-400+1500 -> 1100 | U47: 1314 | V47: 1694 | W47: =SUM(S47:V47) -> 5308 | X47: 2141 | Y47: 2209 | Z47: 2350 | AA47: 2460 | AB47: =SUM(X47:AA47) -> 9160 | AC47: =22306-AC46 -> 2537 | AD47: 2536 | AE47: 2826 | AF47: 3351 | AG47: =SUM(AC47:AF47) -> 11250 | AH47: 3718 | AI47: 3240 | AL47: =SUM(AH47:AK47) -> 6958 | AQ47: =SUM(AM47:AP47) -> 0 | AV47: =SUM(AR47:AU47) -> 0 | BA47: =SUM(AW47:AZ47) -> 0
C48: Acquisition and integration expense | Y48: 4417 | Z48: 243 | AB48: =SUM(X48:AA48) -> 4660 | AD48: 215 | AE48: 289 | AF48: 1004 | AG48: =SUM(AC48:AF48) -> 1508 | AH48: 97 | AI48: 872 | AL48: =SUM(AH48:AK48) -> 969 | AQ48: =SUM(AM48:AP48) -> 0 | AV48: =SUM(AR48:AU48) -> 0 | BA48: =SUM(AW48:AZ48) -> 0
C49: Other | D49: -297.24736 | E49: -310.55432 | F49: -696.34339 | G49: -401.40482 | H49: =SUM(D49:G49) -> -1705.5499 | I49: -159.82793 | J49: -365.27411 | K49: 519.21715 | L49: 594.46884 | M49: =SUM(I49:L49) -> 588.58395 | N49: 660.29886 | O49: 905 | P49: 303 | Q49: 24 | R49: =SUM(N49:Q49) -> 1892.2989 | S49: =925-1671 -> -746 | V49: 15471 | W49: =SUM(S49:V49) -> 14725 | X49: 6325 | Y49: 3379 | AB49: =SUM(X49:AA49) -> 9704 | AF49: 1 | AG49: =SUM(AC49:AF49) -> 1 | AI49: 25091 | AJ49: 2107 | AK49: 392 | AL49: =SUM(AH49:AK49) -> 27590 | AM49: -92 | AQ49: =SUM(AM49:AP49) -> -92 | AR49: =8870+1844 -> 10714 | AS49: =412+4521 -> 4933 | AV49: =SUM(AR49:AU49) -> 15647 | BA49: =SUM(AW49:AZ49) -> 0
C50: Stock based compensation | D50: 370.23185 | E50: 364.32182 | F50: 369.674 | G50: 440.53721 | H50: =SUM(D50:G50) -> 1544.7649 | I50: 786.37353 | J50: 414.58766 | K50: 1376.3449 | L50: 1505.167 | M50: =SUM(I50:L50) -> 4082.4731 | N50: 2275.6994 | O50: 3075 | P50: 5085 | Q50: 7628 | R50: =SUM(N50:Q50) -> 18063.699 | S50: =9894+956 -> 10850 | T50: =10689+1105 -> 11794 | U50: =10680+1172 -> 11852 | V50: =40724+973 -> 41697 | W50: =SUM(S50:V50) -> 76193 | X50: =37887+163+582+195+1042 -> 39869 | Y50: 49684 | Z50: 55143 | AA50: 57957 | AB50: =SUM(X50:AA50) -> 202653 | AC50: 74533 | AD50: 120470 | AE50: 65724 | AF50: 59169 | AG50: =SUM(AC50:AF50) -> 319896 | AH50: 65984 | AI50: 62552 | AJ50: 60619 | AK50: 58837 | AL50: =SUM(AH50:AK50) -> 247992 | AM50: 54771 | AN50: 66348 | AO50: 63909 | AP50: 60277 | AQ50: =SUM(AM50:AP50) -> 245305 | AR50: 59237 | AS50: 64449 | AT50: 64350 | AU50: 67000 | AV50: =SUM(AR50:AU50) -> 255036 | AW50: 67000 | AX50: 71000 | AY50: 74000 | AZ50: 77000 | BA50: =SUM(AW50:AZ50) -> 289000
C51: % of Revenue | D51: =D50/D17 -> 0.028256302 | E51: =E50/E17 -> 0.024026841 | F51: =F50/F17 -> 0.021621265 | G51: =G50/G17 -> 0.022590871 | H51: =H50/H17 -> 0.023815396 | I51: =I50/I17 -> 0.035068185 | J51: =J50/J17 -> 0.015946507 | K51: =K50/K17 -> 0.048731065 | ... BA51: =BA50/BA17 -> 0.15818367
B52: GAAP Adjustments | D52: =SUM(D47:D50) -> 72.98449 | E52: =SUM(E47:E50) -> 53.7675 | F52: =SUM(F47:F50) -> -326.66939 | G52: =SUM(G47:G50) -> 39.13239 | H52: =SUM(H47:H50) -> -160.78501 | I52: =SUM(I47:I50) -> 626.5456 | J52: =SUM(J47:J50) -> 49.31355 | K52: =SUM(K47:K50) -> 1895.562 | ... U52: =SUM(U47:U50) -> 13166 | V52: =SUM(V46:V50) -> 64521 | W52: =SUM(W46:W50) -> 101885 | X52: =SUM(X46:X50) -> 65007 | Y52: =SUM(Y46:Y50) -> 79457 | Z52: =SUM(Z46:Z50) -> 77505 | AA52: =SUM(AA46:AA50) -> 80186 | AB52: =SUM(AB46:AB50) -> 302155 | AC52: =SUM(AC46:AC50) -> 96839 | ... BA52: =SUM(BA46:BA50) -> 369000
B54: GAAP Operating Income | D54: =D42-D52 -> -2950.3878 | E54: =E42-E52 -> -1657.6085 | F54: =F42-F52 -> -1463.9536 | G54: =G42-G52 -> -1743.7519 | H54: =H42-H52 -> -7815.7018 | I54: =I42-I52 -> -1400.9445 | J54: =J42-J52 -> -117.86823 | K54: =K42-K52 -> -3003.4406 | ... BA54: =BA42-BA52 -> -54369.089
C55: GAAP Operating Margin | D55: =D54/D17 -> -0.22517524 | E55: =E54/E17 -> -0.10931844 | F55: =F54/F17 -> -0.085622814 | G55: =G54/G17 -> -0.089420085 | H55: =H54/H17 -> -0.12049344 | I55: =I54/I17 -> -0.062474866 | J55: =J54/J17 -> -0.0045336288 | K55: =K54/K17 -> -0.10634025 | ... BA55: =BA54/BA17 -> -0.029758831
C57: Amortization of debt discount | S57: 0 | T57: -3905 | U57: -11819 | V57: -11807 | W57: =SUM(S57:V57) -> -27531 | X57: -556 | Y57: -1399 | Z57: -1407 | AA57: -1415 | AB57: =SUM(X57:AA57) -> -4777 | AC57: -1712 | AD57: -1771 | AE57: -1734 | AF57: -1747 | AG57: =SUM(AC57:AF57) -> -6964 | AH57: -1761 | AI57: -1762 | AJ57: -1651 | AK57: -1064 | AL57: =SUM(AH57:AK57) -> -6238 | AM57: -894 | AN57: -1001 | AO57: -1384 | AP57: -1459 | AQ57: =SUM(AM57:AP57) -> -4738 | AR57: -1610 | AS57: -1625 | AT57: -1600 | AU57: -1600 | AV57: =SUM(AR57:AU57) -> -6435 | AW57: -1600 | AX57: -1600 | AY57: -1600 | AZ57: -1600 | BA57: =SUM(AW57:AZ57) -> -6400
C58: Other income, net | D58: =D59-D57 -> -37.62095 | E58: =E59-E57 -> 70.246 | F58: =F59-F57 -> 273.88174 | G58: =G59-G57 -> 324.3554 | H58: =SUM(D58:G58) -> 630.86219 | I58: =I59-I57 -> 316.6156 | J58: =J59-J57 -> 392.9108 | K58: =K59-K57 -> 901.24214 | L58: =L59-L57 -> 721.96713 | M58: =SUM(I58:L58) -> 2332.7357 | N58: =N59-N57 -> 804.74402 | O58: =O59-O57 -> 912 | P58: =P59-P57 -> 1397 | Q58: =Q59-Q57 -> 764 | R58: =SUM(N58:Q58) -> 3877.744 | S58: =S59-S57 -> 830 | T58: =T59-T57 -> 564 | U58: =U59-U57 -> 387 | V58: =V59-V57 -> 380 | W58: =SUM(S58:V58) -> 2161 | X58: =X59-X57 -> -2919 | Y58: =Y59-Y57 -> -3601 | Z58: =Z59-Z57 -> -3009 | AA58: =AA59-AA57 -> 445 | AB58: =SUM(X58:AA58) -> -9084 | AC58: =AC59-AC57 -> 7659 | AD58: =AD59-AD57 -> 18793 | AE58: =AE59-AE57 -> 25356 | AF58: =AF59-AF57 -> 28011 | AG58: =SUM(AC58:AF58) -> 79819 | AH58: =AH59-AH57 -> 31069 | AI58: =AI59-AI57 -> 30681 | AJ58: =AJ59-AJ57 -> 61452 | AK58: =AK59-AK57 -> 30883 | AL58: =SUM(AH58:AK58) -> 154085 | AM58: =AM59-AM57 -> 18772 | AN58: =AN59-AN57 -> 56304 | AO58: =AO59-AO57 -> 20034 | AP58: =AP59-AP57 -> 20639 | AQ58: =SUM(AM58:AP58) -> 115749 | AR58: =AR59-AR57 -> 19516 | AS58: =AS59-AS57 -> 17635 | AT58: 16200 | AU58: 16000 | AV58: =SUM(AR58:AU58) -> 69351 | AW58: 15000 | AX58: 15000 | AY58: 15000 | AZ58: 15000 | BA58: =SUM(AW58:AZ58) -> 60000
B59: Total Other Income | D59: -37.62095 | E59: 70.246 | F59: 273.88174 | G59: 324.3554 | H59: =SUM(D59:G59) -> 630.86219 | I59: 316.6156 | J59: 392.9108 | K59: 901.24214 | L59: 721.96713 | M59: =SUM(I59:L59) -> 2332.7357 | N59: 804.74402 | O59: 912 | P59: 1397 | Q59: 764 | R59: =SUM(N59:Q59) -> 3877.744 | S59: 830 | T59: -3341 | U59: -11432 | V59: -11427 | W59: =SUM(S59:V59) -> -25370 | X59: -3475 | Y59: -5000 | Z59: -4416 | AA59: -970 | AB59: =SUM(X59:AA59) -> -13861 | AC59: 5947 | AD59: 17022 | AE59: 23622 | AF59: 26264 | AG59: =SUM(AC59:AF59) -> 72855 | AH59: 29308 | AI59: 28919 | AJ59: 59801 | AK59: 29819 | AL59: =SUM(AH59:AK59) -> 147847 | AM59: 17878 | AN59: 55303 | AO59: 18650 | AP59: 19180 | AQ59: =SUM(AM59:AP59) -> 111011 | AR59: 17906 | AS59: 16010 | AT59: =+AT58+AT57 -> 14600 | AU59: =+AU58+AU57 -> 14400 | AV59: =+AV58+AV57 -> 62916 | AW59: =+AW58+AW57 -> 13400 | AX59: =+AX58+AX57 -> 13400 | AY59: =+AY58+AY57 -> 13400 | AZ59: =+AZ58+AZ57 -> 13400 | BA59: =+BA58+BA57 -> 53600
C60: Non-GAAP adjustments | AA60: -566 | AB60: =SUM(X60:AA60) -> -566 | AJ60: -34297 | AK60: -10974 | AL60: =SUM(AH60:AK60) -> -45271 | AM60: -78 | AN60: -40472 | AO60: 0 | AP60: 0 | AQ60: =SUM(AM60:AP60) -> -40550 | AV60: =SUM(AR60:AU60) -> 0 | BA60: =SUM(AW60:AZ60) -> 0
B61: Total Non-GAAP Other Income | D61: =SUM(D58,D60) -> -37.62095 | E61: =SUM(E58,E60) -> 70.246 | F61: =SUM(F58,F60) -> 273.88174 | G61: =SUM(G58,G60) -> 324.3554 | H61: =SUM(D61:G61) -> 630.86219 | I61: =SUM(I58,I60) -> 316.6156 | J61: =SUM(J58,J60) -> 392.9108 | K61: =SUM(K58,K60) -> 901.24214 | L61: =SUM(L58,L60) -> 721.96713 | M61: =SUM(I61:L61) -> 2332.7357 | N61: =SUM(N58,N60) -> 804.74402 | O61: =SUM(O58,O60) -> 912 | P61: =SUM(P58,P60) -> 1397 | Q61: =SUM(Q58,Q60) -> 764 | R61: =SUM(N61:Q61) -> 3877.744 | S61: =SUM(S58,S60) -> 830 | T61: =SUM(T58,T60) -> 564 | U61: =SUM(U58,U60) -> 387 | V61: =SUM(V58,V60) -> 380 | W61: =SUM(S61:V61) -> 2161 | X61: =SUM(X58,X60) -> -2919 | Y61: =SUM(Y58,Y60) -> -3601 | Z61: =SUM(Z58,Z60) -> -3009 | AA61: =SUM(AA58,AA60) -> -121 | AB61: =SUM(X61:AA61) -> -9650 | AC61: =SUM(AC58,AC60) -> 7659 | AD61: =SUM(AD58,AD60) -> 18793 | AE61: =SUM(AE58,AE60) -> 25356 | AF61: =SUM(AF58,AF60) -> 28011 | AG61: =SUM(AC61:AF61) -> 79819 | AH61: =SUM(AH58,AH60) -> 31069 | AI61: =SUM(AI58,AI60) -> 30681 | AJ61: =SUM(AJ58,AJ60) -> 27155 | AK61: =SUM(AK58,AK60) -> 19909 | AL61: =SUM(AH61:AK61) -> 108814 | AM61: =SUM(AM58,AM60) -> 18694 | AN61: =SUM(AN58,AN60) -> 15832 | AO61: =SUM(AO58,AO60) -> 20034 | AP61: =SUM(AP58,AP60) -> 20639 | AQ61: =SUM(AM61:AP61) -> 75199 | AR61: =SUM(AR58,AR60) -> 19516 | AS61: =SUM(AS58,AS60) -> 17635 | AT61: =SUM(AT58,AT60) -> 16200 | AU61: =SUM(AU58,AU60) -> 16000 | AV61: =SUM(AR61:AU61) -> 69351 | AW61: =SUM(AW58,AW60) -> 15000 | AX61: =SUM(AX58,AX60) -> 15000 | AY61: =SUM(AY58,AY60) -> 15000 | AZ61: =SUM(AZ58,AZ60) -> 15000 | BA61: =SUM(AW61:AZ61) -> 60000
B63: Adjusted EBITDA | D63: -2356.4033 | E63: -1090.841 | F63: -1204.623 | G63: -1010.6195 | H63: =H76+CF!H8+IS!H73+H52-H58 -> -7976.4868 | I63: =I76+CF!I8+IS!I73+I52-I58 -> -774.39889 | J63: =J76+CF!J8+IS!J73+J52-J58 -> -68.55468 | K63: =K76+CF!K8+IS!K73+K52-K58 -> -1107.8786 | L63: =L76+CF!L8+IS!L73+L52-L58 -> -3181.4389 | M63: =M76+CF!M8+IS!M73+M52-M58 -> -5132.2711 | N63: =N76+CF!N8+IS!N73+N52-N58 -> -3513.8629 | O63: =O76+CF!O8+IS!O73+O52-O58 -> -4510 | ... BA63: =BA76+CF!BA8+IS!BA73+BA52-BA58 -> 308230.91
C64: EBITDA Margins | D64: =D63/D17 -> -0.17984202 | E64: =E63/E17 -> -0.071940413 | F64: =F63/F17 -> -0.070455245 | G64: =G63/G17 -> -0.051824852 | H64: =H63/H17 -> -0.12297224 | I64: =I63/I17 -> -0.034534178 | J64: =J63/J17 -> -0.0026368554 | K64: =K63/K17 -> -0.03922571 | ... BA64: =BA63/BA17 -> 0.16870968
V65: =+V66+5818 -> 0
B66: Non-GAAP Pre-Tax Income | D66: =D42+D59 -> -2915.0243 | E66: =E42+E59 -> -1533.595 | F66: =F42+F59 -> -1516.7412 | G66: =G42+G59 -> -1380.2641 | H66: =H42+H59 -> -7345.6246 | I66: =I42+I59 -> -457.78329 | J66: =J42+J59 -> 324.35612 | K66: =K42+K59 -> -206.63646 | ... R66: =R42+R59 -> -11082.119 | S66: =S42+S61 -> -1447 | T66: =T42+T61 -> -994 | U66: =U42+U61 -> -1743 | V66: =V42+V61 -> -5818 | W66: =W42+W61 -> -10002 | X66: =X42+X61 -> -12117 | Y66: =Y42+Y61 -> -219 | Z66: =Z42+Z61 -> -8687 | ... BA66: =BA42+BA61 -> 374630.91
C67: Income Tax | D67: 6.725 | E67: 0 | F67: 0.411 | G67: 2.70373 | H67: =SUM(D67:G67) -> 9.83973 | I67: -21.03259 | J67: -6.12929 | K67: -69.60653 | L67: -59 | M67: =SUM(I67:L67) -> -155.76841 | N67: 51.16343 | O67: 0 | P67: 1 | Q67: 1 | R67: =SUM(N67:Q67) -> 53.16343 | S67: 0 | T67: 0 | U67: 0 | V67: 0 | W67: =SUM(S67:V67) -> 0 | X67: =-3941+3943 -> 2 | Y67: 0 | Z67: 0 | AA67: 1 | AB67: =SUM(X67:AA67) -> 3 | AC67: -107 | AD67: =AD73+526 -> 161 | AE67: =AE73+966 -> 1508 | AF67: =AF73+193 -> 930 | AG67: =SUM(AC67:AF67) -> 2492 | AH67: =AH73+42 -> 564 | AI67: =AI73+94 -> 1760 | AJ67: 17138 | AK67: 15976 | AL67: =SUM(AH67:AK67) -> 35438 | AM67: 17156 | AN67: 15728 | AO67: 14667 | AP67: 15398 | AQ67: =SUM(AM67:AP67) -> 62949 | AR67: 17550 | AS67: 18344 | AT67: =AT66*AT68 -> 16252.348 | AU67: =AU66*AU68 -> 17840.61 | AV67: =SUM(AR67:AU67) -> 69986.958 | AW67: =AW66*AW68 -> 18109.409 | AX67: =AX66*AX68 -> 19295.812 | AY67: =AY66*AY68 -> 18195.09 | AZ67: =AZ66*AZ68 -> 19325.87 | BA67: =SUM(AW67:AZ67) -> 74926.182
C68: Tax Rate % | D68: =D67/D66 -> -0.0023070134 | E68: =E67/E66 -> 0 | F68: =F67/F66 -> -0.00027097569 | G68: =G67/G66 -> -0.0019588497 | H68: =H67/H66 -> -0.0013395362 | I68: =I67/I66 -> 0.045944425 | J68: =J67/J66 -> -0.018896792 | K68: =K67/K66 -> 0.33685503 | ... AS68: =AS67/AS66 -> 0.2 | AT68: 0.2 | AU68: 0.2 | AV68: =AV67/AV66 -> 0.19999886 | AW68: 0.2 | AX68: 0.2 | AY68: 0.2 | AZ68: 0.2 | BA68: =BA67/BA66 -> 0.2
B69: Non-GAAP Net Income (Loss) | D69: =D66-D67 -> -2921.7493 | E69: =E66-E67 -> -1533.595 | F69: =F66-F67 -> -1517.1522 | G69: =G66-G67 -> -1382.9679 | H69: =H66-H67 -> -7355.4643 | I69: =I66-I67 -> -436.7507 | J69: =J66-J67 -> 330.48541 | K69: =K66-K67 -> -137.02993 | ... BA69: =BA66-BA67 -> 299704.73
C70: Non-GAAP Net Margin | D70: =D69/D17 -> -0.22298954 | E70: =E69/E17 -> -0.10113982 | F70: =F69/F17 -> -0.088734264 | G70: =G69/G17 -> -0.070918978 | H70: =H69/H17 -> -0.11339803 | I70: =I69/I17 -> -0.019476818 | J70: =J69/J17 -> 0.012711637 | K70: =K69/K17 -> -0.0048517015 | ... BA70: =BA69/BA17 -> 0.16404289
B72: GAAP Pre-Tax Income | D72: =D54+D59 -> -2988.0087 | E72: =E54+E59 -> -1587.3625 | F72: =F54+F59 -> -1190.0718 | G72: =G54+G59 -> -1419.3965 | H72: =H54+H59 -> -7184.8396 | I72: =I54+I59 -> -1084.3289 | J72: =J54+J59 -> 275.04257 | K72: =K54+K59 -> -2102.1985 | ... BA72: =BA54+BA59 -> -769.0893
C73: Income Tax | D73: 6.725 | E73: 0 | F73: 0.411 | G73: 2.70373 | H73: =SUM(D73:G73) -> 9.83973 | I73: -21.03259 | J73: -6.12929 | K73: -69.60653 | L73: -59 | M73: =SUM(I73:L73) -> -155.76841 | N73: 51.16343 | O73: 0 | P73: 1 | Q73: 1 | R73: =SUM(N73:Q73) -> 53.16343 | S73: 0 | T73: -333 | U73: 0 | V73: -40284 | W73: =SUM(S73:V73) -> -40617 | X73: -3941 | Y73: -635 | Z73: -879 | AA73: 617 | AB73: =SUM(X73:AA73) -> -4838 | AC73: -107 | AD73: -365 | AE73: 542 | AF73: 737 | AG73: =SUM(AC73:AF73) -> 807 | AH73: 522 | AI73: 1666 | AJ73: 370 | AK73: 0 | AL73: =SUM(AH73:AK73) -> 2558 | AM73: 1268 | AN73: 45 | AO73: 1293 | AP73: 4004 | AQ73: =SUM(AM73:AP73) -> 6610 | AR73: 149 | AS73: 522 | AT73: 500 | AU73: 500 | AV73: =SUM(AR73:AU73) -> 1671 | AW73: 500 | AX73: 500 | AY73: 500 | AZ73: 500 | BA73: =SUM(AW73:AZ73) -> 2000
C74: Tax Rate % | D74: =D73/D72 -> -0.0022506628 | E74: =E73/E72 -> 0 | F74: =F73/F72 -> -0.0003453573 | G74: =G73/G72 -> -0.0019048447 | H74: =H73/H72 -> -0.0013695128 | I74: =I73/I72 -> 0.019396873 | J74: =J73/J72 -> -0.022284878 | K74: =K73/K72 -> 0.033111302 | ... BA74: =BA73/BA72 -> -2.6004783
B76: GAAP Net Income | D76: =D72-D73 -> -2994.7337 | E76: =E72-E73 -> -1587.3625 | F76: =F72-F73 -> -1190.4828 | G76: =G72-G73 -> -1422.1003 | H76: =H72-H73 -> -7194.6793 | I76: =I72-I73 -> -1063.2963 | J76: =J72-J73 -> 281.17186 | K76: =K72-K73 -> -2032.592 | L76: =L72-L73 -> -4500.1077 | M76: =SUM(I76:L76) -> -7314.8241 | N76: =N72-N73 -> -5696.2805 | O76: =O72-O73 -> -7578 | P76: =P72-P73 -> -8319 | Q76: =Q72-Q73 -> -9498 | R76: =R72-R73 -> -31091.28 | S76: =S72-S73 -> -12751 | T76: =T72-T73 -> -17460 | U76: =U72-U73 -> -26728 | ... BA76: =BA72-BA73 -> -2769.0893
C77: GAAP Net Margin | D77: =D76/D17 -> -0.22855975 | E77: =E76/E17 -> -0.10468576 | F77: =F76/F17 -> -0.069628226 | G77: =G76/G17 -> -0.072925698 | H77: =H76/H17 -> -0.11091924 | I77: =I76/I17 -> -0.047417506 | J77: =J76/J17 -> 0.010814864 | K77: =K76/K17 -> -0.071966244 | ... BA77: =BA76/BA17 -> -0.0015156564
O78: =-7578-O76 -> 0
B79: Non-GAAP EPS | D79: =IF(D69>0,D69/D85,D69/D84) -> -0.060082446 | E79: =IF(E69>0,E69/E85,E69/E84) -> -0.028385977 | F79: =IF(F69>0,F69/F85,F69/F84) -> -0.02793093 | G79: =IF(G69>0,G69/G85,G69/G84) -> -0.025393263 | H79: =IF(H69>0,H69/H85,H69/H84) -> -0.13915287 | I79: =I69/I85 -> -0.0080059153 | J79: =IF(J69>0,J69/J85,J69/J84) -> 0.0059681877 | K79: =IF(K69>0,K69/K85,K69/K84) -> -0.0022827288 | L79: =IF(L69>0,L69/L85,L69/L84) -> -0.03966247 | M79: =IF(M69>0,M69/M85,M69/M84) -> -0.045882901 | N79: =IF(N69>0,N69/N85,N69/N84) -> -0.045500033 | O79: =IF(O69>0,O69/O85,O69/O84) -> -0.057319463 | P79: =IF(P69>0,P69/P85,P69/P84) -> -0.040495171 | Q79: =IF(Q69>0,Q69/Q85,Q69/Q84) -> -0.024898504 | R79: =SUM(N79:Q79) -> -0.16821317 | S79: =IF(S69>0,S69/S85,S69/S84) -> -0.018038795 | T79: =IF(T69>0,T69/T85,T69/T84) -> -0.012193476 | U79: =IF(U69>0,U69/U85,U69/U84) -> -0.0210948 | V79: =IF(V69>0,V69/V85,V69/V84) -> -0.066900477 | W79: =IF(W69>0,W69/W85,W69/W84) -> -0.1207508 | X79: =IF(X69>0,X69/X85,X69/X84) -> -0.12638176 | Y79: =IF(Y69>0,Y69/Y85,Y69/Y84) -> -0.0021280731 | Z79: =IF(Z69>0,Z69/Z85,Z69/Z84) -> -0.083665607 | ... BA79: =IF(BA69>0,BA69/BA85,BA69/BA84) -> 2.5408992
C80: Y/Y Growth % | I80: =I79/D79-1 -> -0.86675118 | J80: =J79/E79-1 -> -1.2102513 | K80: =K79/F79-1 -> -0.91827236 | L80: =L79/G79-1 -> 0.56192886 | M80: =M79/H79-1 -> -0.67026982 | N80: =N79/I79-1 -> 4.6833019 | O80: =O79/J79-1 -> -10.604166 | P80: =P79/K79-1 -> 16.739808 | ... BA80: =BA79/AV79-1 -> 0.044712152
B81: GAAP EPS | D81: =D76/D86 -> -0.42889134 | E81: =E76/E86 -> -0.22283463 | F81: =F76/F86 -> -0.16564392 | G81: =G76/G86 -> -0.19399772 | H81: =H76/H85 -> -0.13611109 | I81: =I76/I86 -> -0.14325312 | J81: =J76/J86 -> 0.036329461 | K81: =K76/K86 -> -0.25581675 | L81: =L76/L86 -> -0.55639314 | M81: =M76/M85 -> -0.12694967 | N81: =N76/N86 -> -0.69205206 | O81: =O76/O86 -> -0.33972922 | P81: =P76/P86 -> -0.11493665 | Q81: =Q76/Q86 -> -0.12810726 | R81: =R76/R86 -> -0.74810588 | S81: =IF(S76>0,S76/S85,S76/S84) -> -0.15895831 | T81: =IF(T76>0,T76/T85,T76/T84) -> -0.2141832 | U81: =IF(U76>0,U76/U85,U76/U84) -> -0.3234778 | V81: =IF(V76>0,V76/V85,V76/V84) -> -0.48136607 | W81: =IF(W76>0,W76/W85,W76/W84) -> -1.1927914 | X81: =IF(X76>0,X76/X85,X76/X84) -> -0.76897969 | Y81: =IF(Y76>0,Y76/Y85,Y76/Y84) -> -0.78165387 | Z81: =IF(Z76>0,Z76/Z85,Z76/Z84) -> -0.8352114 | ... BA81: =IF(BA76>0,BA76/BA85,BA76/BA84) -> -0.026760139
C82: Y/Y Growth % | I82: =I81/D81-1 -> -0.66599203 | J82: =J81/E81-1 -> -1.1630333 | K82: =K81/F81-1 -> 0.54437754 | L82: =L81/G81-1 -> 1.8680396 | M82: =M81/H81-1 -> -0.067308435 | N82: =N81/I81-1 -> 3.8309737 | O82: =O81/J81-1 -> -10.351342 | P82: =P81/K81-1 -> -0.55070708 | ... BA82: =BA81/AV81-1 -> -0.74553632
B84: Basic Shares Outstanding | D84: 48629 | E84: 54026.5 | F84: 54318 | G84: 54462 | H84: =AVERAGE(D84:G84) -> 52858.875 | I84: 54553.5 | J84: 55374.5 | K84: 60029 | L84: 60522.5 | M84: =AVERAGE(I84:L84) -> 57619.875 | N84: 60665.5 | O84: 62771 | P84: 72379 | Q84: 74141 | R84: =AVERAGE(N84:Q84) -> 67489.125 | S84: 80216 | T84: 81519 | U84: 82627 | V84: 86965 | W84: =AVERAGE(S84:V84) -> 82831.75 | X84: 95892 | Y84: 102910 | Z84: 103830 | AA84: 104439 | AB84: =AVERAGE(X84:AA84) -> 101767.75 | AC84: 105086 | AD84: 105906 | AE84: 106597 | AF84: 106414 | AG84: =AVERAGE(AC84:AF84) -> 106000.75 | AH84: 106817 | AI84: 105914 | AJ84: 105436 | AK84: 106289 | AL84: =AVERAGE(AH84:AK84) -> 106114 | AM84: 107322 | AN84: 104480 | AO84: 102219 | AP84: 103231 | AQ84: =AVERAGE(AM84:AP84) -> 104313 | AR84: 101922 | AS84: 100532 | AT84: =(AT85/AS85)*AS84 -> 100532 | AU84: =(AU85/AT85)*AT84 -> 101537.32 | AV84: =AVERAGE(AR84:AU84) -> 101130.83 | AW84: =(AW85/AU85)*AU84 -> 102654.23 | AX84: =(AX85/AW85)*AW84 -> 103270.16 | AY84: =(AY85/AX85)*AX84 -> 103786.51 | AZ84: =(AZ85/AY85)*AY84 -> 104201.65 | BA84: =AVERAGE(AW84:AZ84) -> 103478.14
B85: Diluted Shares Outstanding | D85: =D84 -> 48629 | E85: =E84 -> 54026.5 | F85: =F84 -> 54318 | G85: =G84 -> 54462 | H85: =AVERAGE(D85:G85) -> 52858.875 | I85: =I84 -> 54553.5 | J85: =J84 -> 55374.5 | K85: =K84 -> 60029 | L85: =L84 -> 60522.5 | M85: =AVERAGE(I85:L85) -> 57619.875 | N85: =N84 -> 60665.5 | O85: 66000 | P85: 81900 | Q85: 85000 | R85: =AVERAGE(N85:Q85) -> 73391.375 | S85: 80216 | T85: 81519 | U85: 82627 | V85: 86965 | W85: =AVERAGE(S85:V85) -> 82831.75 | X85: 95892 | Y85: 102910 | Z85: 103830 | AA85: =AA84 -> 104439 | AB85: =AVERAGE(X85:AA85) -> 101767.75 | AC85: 117500 | AD85: 117258 | AE85: 117213 | AF85: 117022 | AG85: =AVERAGE(AC85:AF85) -> 117248.25 | AH85: 117948 | AI85: 116712 | AJ85: 111176 | AK85: 111399 | AL85: =AVERAGE(AH85:AK85) -> 114308.75 | AM85: 109749 | AN85: 111919 | AO85: 117667 | AP85: 116754 | AQ85: =AVERAGE(AM85:AP85) -> 114022.25 | AR85: 115487 | AS85: 114594 | AT85: =+AS85*1 -> 114594 | AU85: =+AT85*1.01 -> 115739.94 | AV85: =AVERAGE(AR85:AU85) -> 115103.74 | AW85: =+AU85*1.011 -> 117013.08 | AX85: =+AW85*1.006 -> 117715.16 | AY85: =+AX85*1.005 -> 118303.73 | AZ85: =+AY85*1.004 -> 118776.95 | BA85: =AVERAGE(AW85:AZ85) -> 117952.23
C86: Historical GAAP Shares | D86: 6982.5 | E86: 7123.5 | F86: 7187 | G86: 7330.5 | H86: 7155 | I86: 7422.5 | J86: 7739.5 | K86: 7945.5 | L86: 8088 | M86: 7797 | N86: 8231 | O86: 22306 | P86: =P84 -> 72379 | Q86: =Q84 -> 74141 | R86: 41560
B88: Deferred revenue | H88: 5208 | I88: 5095 | J88: 5642 | K88: 5471.9016 | L88: 5254.1441 | N88: 5248.0812 | O88: 6365 | P88: 8199 | Q88: 8513 | S88: 8951 | T88: 8545 | U88: 11437 | V88: 16576.34 | X88: 23968 | Y88: 32809 | Z88: 30370 | AA88: 34027 | AC88: 32724 | AD88: 32371 | AE88: 29341 | AF88: 35497.708 | AH88: 37268.569 | AI88: 39231.429 | AJ88: 40414.934 | AK88: 35497.708 | AM88: 37268.569 | AN88: 39231.429 | AO88: 40414.934 | AP88: 35497.708 | AR88: 37268.569 | AS88: 39231.429
B89: Cash Flow - Operating | H89: -8355.6793 | I89: -2255.2963 | J89: 76.17186 | K89: 102.40804 | L89: -1873.1077 | M89: -3949.8241 | N89: -2380.2805 | O89: -1769 | P89: 822 | Q89: -1103 | R89: -4430.2805 | S89: -2156 | T89: -8403 | U89: -408 | V89: 17786 | W89: 6819 | X89: -17206 | Y89: -12930 | Z89: 26445 | AA89: -10474 | AB89: -10786 | AC89: 20065 | AD89: 55230 | AE89: 34031 | AF89: 116893.2 | AG89: 233079.2 | AH89: 31999.314 | AI89: 35970.231 | AJ89: 34723.734 | AK89: 116893.2 | AL89: 233079.2 | AM89: 31999.314 | AN89: 35970.231 | AO89: 34723.734 | AP89: 116893.2 | AR89: 31999.314 | AS89: 35970.231
B91: Net Cash | H91: 92268 | I91: 89403 | J91: 158512 | K91: 175368.96 | L91: 162274.74 | M91: 162274.74 | N91: 157641.84 | O91: 383029 | P91: 382423 | Q91: 697617 | S91: 700324 | T91: 848220 | U91: 838373 | V91: 175548 | X91: 1063057 | Y91: 1016010 | Z91: 1038416 | AA91: 931953 | AC91: 868730 | AD91: 869329 | AE91: 825432 | AF91: 1051383.2 | AH91: 1070882.5 | AI91: 1094352.7 | AJ91: 1116576.5 | AK91: 1051383.2 | AM91: 1070882.5 | AN91: 1094352.7 | AO91: 1116576.5 | AP91: 1051383.2 | AR91: 1070882.5 | AS91: 1094352.7
B92: Cash/share | H92: =H91/H85 -> 1.7455536 | I92: =I91/I85 -> 1.6388133 | J92: =J91/J85 -> 2.862545 | K92: =K91/K85 -> 2.9214041 | L92: =L91/L85 -> 2.6812299 | M92: =M91/M85 -> 2.816298 | N92: =N91/N85 -> 2.5985419 | O92: =O91/O85 -> 5.8034697 | ... Q92: =Q91/Q85 -> 8.2072588 | S92: =S91/S85 -> 8.7304777 | T92: =T91/T85 -> 10.405182 | U92: =U91/U85 -> 10.146478 | V92: =V91/V85 -> 2.0186052 | X92: =X91/X85 -> 11.085982 | Y92: =Y91/Y85 -> 9.8728015 | Z92: =Z91/Z85 -> 10.001117 | AA92: =AA91/AA85 -> 8.9234194 | AC92: =AC91/AC85 -> 7.3934468 | AD92: =AD91/AD85 -> 7.413814 | AE92: =AE91/AE85 -> 7.042154 | AF92: =AF91/AF85 -> 8.9844918 | AH92: =AH91/AH85 -> 9.0792766 | AI92: =AI91/AI85 -> 9.3765229 | AJ92: =AJ91/AJ85 -> 10.043323 | AK92: =AK91/AK85 -> 9.4379949 | AM92: =AM91/AM85 -> 9.7575605 | AN92: =AN91/AN85 -> 9.7780783 | AO92: =AO91/AO85 -> 9.4892916 | AP92: =AP91/AP85 -> 9.005115 | AR92: =AR91/AR85 -> 9.2727537 | AS92: =AS91/AS85 -> 9.5498258
B93: Scott Berg, sberg@needhamco.com | BA93: Source: Company Reports and Needham & Company, LLC Estimates
B94: 763.350.4027
U106: switched
C107: Total RPO | O107: 46200 | P107: 43700 | Q107: 152300 | S107: 151200 | T107: 148700 | Y107: 155000 | Z107: 148000
C108: Y/Y Change in Total RPO | T108: =T107-P107 -> 105000 | Y108: =Y107-U107 -> 155000 | Z108: =Z107-V107 -> 148000
C109: Total RPO Bookings | T109: =T108+T17 -> 159045 | Y109: =Y108+Y17 -> 311478 | Z109: =Z108+Z17 -> 314911
C110: % change y/y
C111: % change q/q
C113: Short-term RPO (24 months) | O113: 8100 | P113: 7500 | Q113: 13000 | S113: 17900 | T113: 17800 | Y113: =Y107*0.6 -> 93000 | Z113: =Z107*0.63 -> 93240
C114: Y/Y Change in Short-term RPO | T114: =T113-P113 -> 10300 | Y114: =Y113-U113 -> 93000 | Z114: =Z113-V113 -> 93240
C115: Short-term RPO Bookings | T115: =T114+#REF! -> #REF! | Y115: =Y114+#REF! -> #REF! | Z115: =Z114+#REF! -> #REF!
C116: % change y/y
C117: % change q/q
C119: Change in TTM Rev | L119: =L17+K17+J17+I17-G17-F17-E17-D17 -> 43486.667 | N119: =N17+L17+K17+J17-I17-G17-F17-E17 -> 46920.517 | O119: =+O17+N17+L17+K17-J17-I17-G17-F17 -> 49166.334 | P119: =+P17+O17+N17+L17-K17-J17-I17-G17 -> 51006.668 | Q119: =Q17+P17+O17+N17-L17-K17-J17-I17 -> 49248.687 | S119: =S17+Q17+P17+O17-N17-L17-K17-J17 -> 47522.857 | T119: =+T17+S17+Q17+P17-O17-N17-L17-K17 -> 49406.507 | U119: =+U17+T17+S17+Q17-P17-O17-N17-L17 -> 54928.193 | V119: =V17+U17+T17+S17-Q17-P17-O17-N17 -> 80665.52 | X119: =X17+V17+U17+T17-S17-Q17-P17-O17 -> 141776 | Y119: =+Y17+X17+V17+U17-T17-S17-Q17-P17 -> 229244 | Z119: =+Z17+Y17+X17+V17-U17-T17-S17-Q17 -> 317909 | AA119: =AA17+Z17+Y17+X17-V17-U17-T17-S17 -> 403694
C120: TTM S&M | L120: =L32+K32+J32+I32 -> 30559.528 | N120: =+N32+L32+K32+J32 -> 35140.72 | O120: =+O32+N32+L32+K32 -> 39593.515 | P120: =+P32+O32+N32+L32 -> 43720.515 | Q120: =Q32+P32+O32+N32 -> 45532.749 | S120: =+S32+Q32+P32+O32 -> 46028 | T120: =+T32+S32+Q32+P32 -> 45941 | U120: =+U32+T32+S32+Q32 -> 47556 | V120: =V32+U32+T32+S32 -> 57842 | X120: =+X32+V32+U32+T32 -> 92321 | Y120: =+Y32+X32+V32+U32 -> 139299 | Z120: =+Z32+Y32+X32+V32 -> 189106 | AA120: =AA32+Z32+Y32+X32 -> 245785
C121: CAC Total Revenues | L121: =L120/L119 -> 0.70273328 | N121: =N120/N119 -> 0.74894145 | O121: =O120/O119 -> 0.80529728 | P121: =P120/P119 -> 0.85715293 | Q121: =Q120/Q119 -> 0.92454746 | S121: =S120/S119 -> 0.96854446 | T121: =T120/T119 -> 0.92985727 | U121: =U120/U119 -> 0.8657849 | V121: =V120/V119 -> 0.71705978 | X121: =X120/X119 -> 0.65117509 | Y121: =Y120/Y119 -> 0.60764513 | Z121: =Z120/Z119 -> 0.59484318 | AA121: =AA120/AA119 -> 0.60883986
C123: Change in TTM Subs Revs | L123: =+#REF!+#REF!+#REF!+#REF!-#REF!-#REF!-#REF!-#REF! -> #REF! | N123: =+#REF!+#REF!+#REF!+#REF!-#REF!-#REF!-#REF!-#REF! -> #REF! | O123: =+#REF!+#REF!+#REF!+#REF!-#REF!-#REF!-#REF!-#REF! -> #REF! | P123: =+#REF!+#REF!+#REF!+#REF!-#REF!-#REF!-#REF!-#REF! -> #REF! | Q123: =+#REF!+#REF!+#REF!+#REF!-#REF!-#REF!-#REF!-#REF! -> #REF! | S123: =+#REF!+#REF!+#REF!+#REF!-#REF!-#REF!-#REF!-#REF! -> #REF! | T123: =+#REF!+#REF!+#REF!+#REF!-#REF!-#REF!-#REF!-#REF! -> #REF! | U123: =+#REF!+#REF!+#REF!+#REF!-#REF!-#REF!-#REF!-#REF! -> #REF! | V123: =+#REF!+#REF!+#REF!+#REF!-#REF!-#REF!-#REF!-#REF! -> #REF! | X123: =+#REF!+#REF!+#REF!+#REF!-#REF!-#REF!-#REF!-#REF! -> #REF! | Y123: =+#REF!+#REF!+#REF!+#REF!-#REF!-#REF!-#REF!-#REF! -> #REF! | Z123: =+#REF!+#REF!+#REF!+#REF!-#REF!-#REF!-#REF!-#REF! -> #REF! | AA123: =+#REF!+#REF!+#REF!+#REF!-#REF!-#REF!-#REF!-#REF! -> #REF!
C124: CAC Subs Revs | L124: =L120/L123 -> #REF! | N124: =N120/N123 -> #REF! | O124: =O120/O123 -> #REF! | P124: =P120/P123 -> #REF! | Q124: =Q120/Q123 -> #REF! | S124: =S120/S123 -> #REF! | T124: =T120/T123 -> #REF! | U124: =U120/U123 -> #REF! | V124: =V120/V123 -> #REF! | X124: =X120/X123 -> #REF! | Y124: =Y120/Y123 -> #REF! | Z124: =Z120/Z123 -> #REF! | AA124: =AA120/AA123 -> #REF!
C126: Total RPO | O126: 46200 | P126: 43700 | Q126: 152300 | S126: 151200 | T126: 148700
C127: Y/Y Change | T127: =T126-O126 -> 102500
C128: Total RPO Billings | T128: =T127+T17 -> 156545
C130: ST RPO | O130: 8100 | P130: 7500 | Q130: 13000 | S130: 17900 | T130: 17800
...

Sheet BS
B2: Bill.com, Inc. (BILL)
B4: Balance Sheet | D4: 1Q18 | E4: 2Q18 | F4: 3Q18 | G4: 4Q18 | H4: 2018 | I4: 1Q19 | J4: 2Q19 | K4: 3Q19 | L4: 4Q19 | M4: 2019 | N4: 1Q20 | O4: 2Q20 | P4: 3Q20 | Q4: 4Q20 | R4: 2020 | S4: 1Q21 | T4: 2Q21 | U4: 3Q21 | V4: 4Q21 | W4: 2021 | X4: 1Q22 | Y4: 2Q22 | Z4: 3Q22 | AA4: 4Q22 | AB4: 2022 | AC4: 1Q23 | AD4: 2Q23 | AE4: 3Q23 | AF4: 4Q23 | AG4: 2023 | AH4: =IS!AH4 -> 1Q24 | AI4: =IS!AI4 -> 2Q24 | AJ4: =IS!AJ4 -> 3Q24 | AK4: 4Q24 | AL4: =IS!AL4 -> 2024 | AM4: =IS!AM4 -> 1Q25 | AN4: =IS!AN4 -> 2Q25 | AO4: =IS!AO4 -> 3Q25 | AP4: =IS!AP4 -> 4Q25 | AQ4: =IS!AQ4 -> 2025 | AR4: =IS!AR4 -> 1Q26 | AS4: =IS!AS4 -> 2Q26 | ... BA4: =IS!BA4 -> 2027E
B5: Assets:
C6: Cash and Cash Equivalents | D6: 89333 | E6: 56616 | F6: 22642 | G6: 22401 | H6: =G6 -> 22401 | I6: 15308 | J6: 84134 | K6: 100727 | L6: 90306.147 | M6: =L6 -> 90306.147 | N6: 86249.027 | O6: 314894 | P6: 228585 | Q6: 573643 | R6: =Q6 -> 573643 | S6: 564153 | T6: 1568684 | U6: 1223724 | V6: 509615 | W6: =V6 -> 509615 | X6: 2013433 | Y6: 1672166 | Z6: 1639371 | AA6: 1596542 | AB6: =AA6 -> 1596542 | AC6: 1608966 | AD6: 1616758 | AE6: 1590560 | AF6: 1617151 | AG6: =AF6 -> 1617151 | AH6: 1527182 | AI6: 1579633 | AJ6: 952474 | AK6: 985941 | AL6: =AK6 -> 985941 | AM6: 853470 | AN6: 1566271 | AO6: 1047737 | AP6: 1038346 | AQ6: =AP6 -> 1038346 | AR6: 1099628 | AS6: 1094530 | AT6: =AS6+CF!AT76 -> 1066357.3 | AU6: =AT6+CF!AU76 -> 1158573.3 | AV6: =AU6 -> 1158573.3 | AW6: =AV6+CF!AW76 -> 1218031.2 | AX6: =AW6+CF!AX76 -> 1309480.7 | AY6: =AX6+CF!AY76 -> 1384554.1 | AZ6: =AY6+CF!AZ76 -> 1485378 | BA6: =AZ6 -> 1485378
C7: Short Term Investments | D7: 0 | E7: 38675 | F7: 69156 | G7: 69867 | H7: =G7 -> 69867 | I7: 74095 | J7: 74378 | K7: 74641.964 | L7: 71968.59 | M7: =L7 -> 71968.59 | N7: 71392.815 | O7: 68135 | P7: 153838 | Q7: 123974 | R7: =Q7 -> 123974 | S7: 136171 | T7: 165588 | U7: 512520 | V7: 655314 | W7: =V7 -> 655314 | X7: 821544 | Y7: 1117170 | Z7: 1143408 | AA7: 1108493 | AB7: =AA7 -> 1108493 | AC7: 1034537 | AD7: 1066538 | AE7: 1073013 | AF7: 1043110 | AG7: =AF7 -> 1043110 | AH7: 1119456 | AI7: 972621 | AJ7: 837140 | AK7: 601535 | AL7: =AK7 -> 601535 | AM7: 619596 | AN7: 644672 | AO7: 1125349 | AP7: 1180110 | AQ7: =AP7 -> 1180110 | AR7: 1215339 | AS7: 1146970 | AT7: =AS7 -> 1146970 | AU7: =AT7 -> 1146970 | AV7: =AU7 -> 1146970 | AW7: =AV7 -> 1146970 | AX7: =AW7 -> 1146970 | AY7: =AX7 -> 1146970 | AZ7: =AY7 -> 1146970 | BA7: =AZ7 -> 1146970
C8: Restricted Cash | D8: 246.15925 | E8: 246.15925 | F8: 256.19744 | G8: 256.20246 | H8: =G8 -> 256.20246 | I8: 256.20753 | J8: 256.2126 | K8: 256.22012 | L8: 256.23266 | M8: =L8 -> 256.23266 | N8: 256.24536 | P8: =O8 -> 0 | Q8: =P8 -> 0 | R8: =Q8 -> 0 | S8: =R8 -> 0 | T8: =S8 -> 0 | U8: =T8 -> 0 | V8: =U8 -> 0 | W8: =V8 -> 0 | ... AC8: =AB8 -> 0 | AD8: 0 | AE8: =AD8 -> 0 | AF8: =AE8 -> 0 | AG8: =AF8 -> 0 | AH8: =AG8 -> 0 | AI8: 0 | AJ8: =AI8 -> 0 | AL8: =AK8 -> 0 | AQ8: =AP8 -> 0 | AT8: =AS8 -> 0 | AU8: =AT8 -> 0 | AV8: =AU8 -> 0 | AW8: =AV8 -> 0 | AX8: 0 | AY8: =AX8 -> 0 | AZ8: =AY8 -> 0 | BA8: =AZ8 -> 0
C9: Accounts Receivable, net | D9: 1818 | E9: 1687 | F9: 1605 | G9: 2300 | H9: =G9 -> 2300 | I9: 3396 | J9: 4672 | K9: 4004.4258 | L9: 4397.6445 | M9: =L9 -> 4397.6445 | N9: 3690.5937 | O9: 4791 | P9: 3440 | Q9: 4252 | R9: =Q9 -> 4252 | S9: 5042 | T9: 7037 | U9: 9584 | V9: 18222 | W9: =V9 -> 18222 | X9: 19815 | Y9: 24433 | Z9: 26859 | AA9: 24045 | AB9: =AA9 -> 24045 | AC9: 29060 | AD9: 31261 | AE9: 34065 | AF9: 28233 | AG9: =AF9 -> 28233 | AH9: 24100 | AI9: 26652 | AJ9: 29891 | AK9: 28049 | AL9: =AK9 -> 28049 | AM9: 31934 | AN9: 28911 | AO9: 26663 | AP9: 32341 | AQ9: =AP9 -> 32341 | AR9: 32113 | AS9: 41163 | AT9: =AT60*IS!AT$17 -> 42300.203 | AU9: =AU60*IS!AU$17 -> 45133.999 | AV9: =AU9 -> 45133.999 | AW9: =AW60*IS!AW$17 -> 46118.837 | AX9: =AX60*IS!AX$17 -> 47794.98 | AY9: =AY60*IS!AY$17 -> 47203.683 | AZ9: =AZ60*IS!AZ$17 -> 50716.461 | BA9: =AZ9 -> 50716.461
C10: Acquired card receivables | V10: 147093 | W10: =V10 -> 147093 | X10: 174338 | Y10: 213414 | Z10: 237511 | AA10: 256392 | AB10: =AA10 -> 256392 | AC10: 357741 | AD10: 380895 | AE10: 431114 | AF10: 458650 | AG10: =AF10 -> 458650 | AH10: 552827 | AI10: 516980 | AJ10: 641861 | AK10: 697216 | AL10: =AK10 -> 697216 | AM10: 628274 | AN10: 581661 | AO10: 705535 | AP10: 685108 | AQ10: =AP10 -> 685108 | AR10: 738765 | AS10: 732084 | AT10: =AS10 -> 732084 | AU10: =AT10 -> 732084 | AV10: =AU10 -> 732084 | AW10: =AV10 -> 732084 | AX10: =AW10 -> 732084 | AY10: =AX10 -> 732084 | AZ10: =AY10 -> 732084 | BA10: =AZ10 -> 732084
C11: Unbilled Revenue | D11: 2327 | E11: 2538 | F11: 2908 | G11: 3047.1751 | H11: =G11 -> 3047.1751 | I11: 3565 | J11: 3929.8569 | K11: 4431.7575 | L11: 4795.0972 | M11: =L11 -> 4795.0972 | N11: 5415.5627 | O11: 5909 | P11: 6151 | Q11: 6549 | R11: =Q11 -> 6549 | S11: 6925 | T11: 7370 | U11: 7865 | V11: 8118 | W11: =V11 -> 8118 | X11: 0 | Y11: 0 | AA11: 0 | AB11: =AA11 -> 0 | AD11: 0 | AE11: 0 | AF11: 0 | AG11: =AF11 -> 0 | AH11: 0 | AI11: 0 | AJ11: 0 | AL11: =AK11 -> 0 | AQ11: =AP11 -> 0 | AT11: 0 | AU11: 0 | AV11: =AU11 -> 0 | AW11: 0 | AX11: 0 | AY11: 0 | AZ11: 0 | BA11: =AZ11 -> 0
C12: Prepaid Expenses and Other Current Assets | D12: 2616.7855 | E12: 4624.1662 | F12: 5205.0669 | G12: 5825.6531 | H12: =G12 -> 5825.6531 | I12: 7066.4629 | J12: 8957.9617 | K12: 10544.122 | L12: 12070.415 | M12: =L12 -> 12070.415 | N12: 13654.68 | O12: 15768 | P12: 25137 | Q12: 26781 | R12: =Q12 -> 26781 | S12: 15421 | T12: 18748 | U12: 18268 | V12: 59077 | W12: =V12 -> 59077 | X12: 71551 | Y12: 84718 | Z12: 91865 | AA12: 151258 | AB12: =AA12 -> 151258 | AC12: 140019 | AD12: 178688 | AE12: 170120 | AF12: 170111 | AG12: =AF12 -> 170111 | AH12: 195027 | AI12: 204726 | AJ12: 256199 | AK12: 297169 | AL12: =AK12 -> 297169 | AM12: 283756 | AN12: 251877 | AO12: 241332 | AP12: 258418 | AQ12: =AP12 -> 258418 | AR12: 269326 | AS12: 278473 | AT12: =AT62*IS!AT$17 -> 261858.4 | AU12: =AU62*IS!AU$17 -> 279400.95 | AV12: =AU12 -> 279400.95 | AW12: =AW62*IS!AW$17 -> 285497.56 | AX12: =AX62*IS!AX$17 -> 295873.68 | AY12: =AY62*IS!AY$17 -> 292213.28 | AZ12: =AZ62*IS!AZ$17 -> 313959.04 | BA12: =AZ12 -> 313959.04
C13: Funds Held for Customers | D13: 709298 | E13: 902871 | F13: 786615 | G13: 915013.13 | H13: =G13 -> 915013.13 | I13: 1013736 | J13: 1212826 | K13: 1179910 | L13: 1329306.1 | M13: =L13 -> 1329306.1 | N13: 1466491.8 | O13: 1481763 | P13: 1353552 | Q13: 1644250 | R13: =Q13 -> 1644250 | S13: 1668903 | T13: 2217680 | U13: 1929840 | V13: 2208598 | W13: =V13 -> 2208598 | X13: 2432521 | Y13: 3380395 | Z13: 3043540 | AA13: 3142660 | AB13: =AA13 -> 3142660 | AC13: 3121654 | AD13: 3474048 | AE13: 3106360 | AF13: 3355909 | AG13: =AF13 -> 3355909 | AH13: 3263528 | AI13: 3655435 | AJ13: 3510918 | AK13: 3704907 | AL13: =AK13 -> 3704907 | AM13: 3787171 | AN13: 3766541 | AO13: 3657218 | AP13: 4044470 | AQ13: =AP13 -> 4044470 | AR13: 3974674 | AS13: 4032211 | AT13: ='Revenue Build'!AT94*1000 -> 4147751.7 | AU13: ='Revenue Build'!AU94*1000 -> 4218508.8 | AV13: =AU13 -> 4218508.8 | AW13: ='Revenue Build'!AW94*1000 -> 4399114.5 | AX13: ='Revenue Build'!AX94*1000 -> 4676273.2 | AY13: ='Revenue Build'!AY94*1000 -> 4491027 | AZ13: ='Revenue Build'!AZ94*1000 -> 4759461.5 | BA13: =AZ13 -> 4759461.5
B14: Total Current Assets | D14: =SUM(D6:D13) -> 805638.94 | E14: =SUM(E6:E13) -> 1007257.3 | F14: =SUM(F6:F13) -> 888387.26 | G14: =SUM(G6:G13) -> 1018710.2 | H14: =SUM(H6:H13) -> 1018710.2 | I14: =SUM(I6:I13) -> 1117422.7 | J14: =SUM(J6:J13) -> 1389154 | K14: =SUM(K6:K13) -> 1374515.5 | ... BA14: =SUM(BA6:BA13) -> 8488569
C15: Operating lease right of use | S15: 43400 | T15: 44771 | U15: 44125 | V15: 71925 | W15: =V15 -> 71925 | X15: 78930 | Y15: 76807 | Z15: 78739 | AA15: 76445 | AB15: =AA15 -> 76445 | AC15: 75106 | AD15: 72725 | AE15: 70331 | AF15: 68988 | AG15: =AF15 -> 68988 | AH15: 66600 | AI15: 63505 | AJ15: 61466 | AK15: 59414 | AL15: =AK15 -> 59414 | AM15: 57370 | AN15: 60144 | AO15: 58076 | AP15: 56086 | AQ15: =AP15 -> 56086 | AR15: 54066 | AS15: 52017 | AT15: =AS15 -> 52017 | AU15: =AT15 -> 52017 | AV15: =AU15 -> 52017 | AW15: =AV15 -> 52017 | AX15: =AW15 -> 52017 | AY15: =AX15 -> 52017 | AZ15: =AY15 -> 52017 | BA15: =AZ15 -> 52017
C16: PP&E | D16: 4269.6683 | E16: 4532 | F16: 4109 | G16: 5948.2619 | H16: =G16 -> 5948.2619 | I16: 6315 | J16: 6449.8386 | K16: 6649.5243 | L16: 6556.5475 | M16: =L16 -> 6556.5475 | N16: 7607.4852 | O16: 7511 | P16: 12317 | Q16: 13866 | R16: =Q16 -> 13866 | S16: 21709 | T16: 30572 | U16: 31740 | V16: 48902 | W16: =V16 -> 48902 | X16: 51142 | Y16: 52691 | Z16: 53279 | AA16: 56985 | AB16: =AA16 -> 56985 | AC16: 62025 | AD16: 69383 | AE16: 77465 | AF16: 81564 | AG16: =AF16 -> 81564 | AH16: 85294 | AI16: 86577 | AJ16: 87300 | AK16: 88034 | AL16: =AK16 -> 88034 | AM16: 90016 | AN16: 94467 | AO16: 104837 | AP16: 116611 | AQ16: =AP16 -> 116611 | AR16: 128957 | AS16: 127028 | AT16: =AS16-CF!AT45-CF!AT11 -> 128228 | AU16: =AT16-CF!AU45-CF!AU11 -> 129428 | AV16: =AU16 -> 129428 | AW16: =AV16-CF!AW45-CF!AW11 -> 130628 | AX16: =AW16-CF!AX45-CF!AX11 -> 131828 | AY16: =AX16-CF!AY45-CF!AY11 -> 133028 | AZ16: =AY16-CF!AZ45-CF!AZ11 -> 134228 | BA16: =AZ16 -> 134228
C17: Intangible assets | V17: 417341 | W17: =V17 -> 417341 | X17: 491888 | Y17: 472120 | Z17: 452351 | AA17: 432583 | AB17: =AA17 -> 432583 | AC17: 412814 | AD17: 401869 | AE17: 381648 | AF17: 361427 | AG17: =AF17 -> 361427 | AH17: 341206 | AI17: 320985 | AJ17: 300764 | AK17: 281471 | AL17: =AK17 -> 281471 | AM17: 264914 | AN17: 253134 | AO17: 237970 | AP17: 222805 | AQ17: =AP17 -> 222805 | AR17: 207640 | AS17: 192475 | AT17: =AS17 -> 192475 | AU17: =AT17 -> 192475 | AV17: =AU17 -> 192475 | AW17: =AV17 -> 192475 | AX17: =AW17 -> 192475 | AY17: =AX17 -> 192475 | AZ17: =AY17 -> 192475 | BA17: =AZ17 -> 192475
C18: Goodwill | V18: 1772043 | W18: =V18 -> 1772043 | X18: 2354812 | Y18: 2363109 | Z18: 2363109 | AA18: 2362893 | AB18: =AA18 -> 2362893 | AC18: 2362330 | AD18: 2396509 | AE18: 2396509 | AF18: 2396509 | AG18: =AF18 -> 2396509 | AH18: 2396509 | AI18: 2396509 | AJ18: 2396509 | AK18: 2396509 | AL18: =AK18 -> 2396509 | AM18: 2396509 | AN18: 2396509 | AO18: 2396509 | AP18: 2396509 | AQ18: =AP18 -> 2396509 | AR18: 2396509 | AS18: 2396509 | AT18: =AS18 -> 2396509 | AU18: =AT18 -> 2396509 | AV18: =AU18 -> 2396509 | AW18: =AV18 -> 2396509 | AX18: =AW18 -> 2396509 | AY18: =AX18 -> 2396509 | AZ18: =AY18 -> 2396509 | BA18: =AZ18 -> 2396509
C19: Other assets | D19: 2552.1855 | E19: 2802 | F19: 3691 | G19: 4626.4705 | H19: =G19 -> 4626.4705 | I19: 5476 | J19: 5227.0558 | K19: 5979.866 | L19: 6640.8056 | M19: =L19 -> 6640.8056 | N19: 7398.4897 | O19: 6353 | P19: 6819 | Q19: 10700 | R19: =Q19 -> 10700 | S19: 17484 | T19: 21967 | U19: 22499 | V19: 52925 | W19: =V19 -> 52925 | X19: 54221 | Y19: 53935 | Z19: 53804 | AA19: 47730 | AB19: =AA19 -> 47730 | AC19: 48847 | AD19: 49600 | AE19: 49700 | AF19: 54366 | AG19: =AF19 -> 54366 | AH19: 48654 | AI19: 48788 | AJ19: 47736 | AK19: 38568 | AL19: =AK19 -> 38568 | AM19: 32051 | AN19: 30019 | AO19: 31410 | AP19: 33178 | AQ19: =AP19 -> 33178 | AR19: 34228 | AS19: 32974 | AT19: =AT64*IS!AT$17 -> 98249.206 | AU19: =AU64*IS!AU$17 -> 94987.657 | AV19: =AU19 -> 94987.657 | AW19: =AW64*IS!AW$17 -> 107118.61 | AX19: =AX64*IS!AX$17 -> 111011.73 | AY19: =AY64*IS!AY$17 -> 109638.35 | AZ19: =AZ64*IS!AZ$17 -> 106736.34 | BA19: =AZ19 -> 106736.34
B20: Total Assets | D20: =D14+SUM(D16:D19) -> 812460.8 | E20: =E14+SUM(E16:E19) -> 1014591.3 | F20: =F14+SUM(F16:F19) -> 896187.26 | G20: =G14+SUM(G16:G19) -> 1029284.9 | H20: =H14+SUM(H16:H19) -> 1029284.9 | I20: =I14+SUM(I16:I19) -> 1129213.7 | J20: =J14+SUM(J16:J19) -> 1400830.9 | K20: =K14+SUM(K16:K19) -> 1387144.9 | ... R20: =R14+SUM(R16:R19) -> 2404015 | S20: =S14+SUM(S16:S19)+S15 -> 2479208 | T20: =T14+SUM(T16:T19)+T15 -> 4082417 | U20: =U14+SUM(U16:U19)+U15 -> 3800165 | V20: =V14+SUM(V16:V19)+V15 -> 5969173 | W20: =W14+SUM(W16:W19)+W15 -> 5969173 | X20: =X14+SUM(X16:X19)+X15 -> 8564195 | Y20: =Y14+SUM(Y16:Y19)+Y15 -> 9510958 | Z20: =Z14+SUM(Z16:Z19)+Z15 -> 9183836 | ... BA20: =BA14+SUM(BA16:BA19)+BA15 -> 11370534
B22: Liabilities:
C23: Accounts Payable | D23: 1467 | E23: 2420 | F23: 1319 | G23: 1532 | H23: =G23 -> 1532 | I23: 2580 | J23: 3791 | K23: 4672.2937 | L23: 5063.3075 | M23: =L23 -> 5063.3075 | N23: 5686.3045 | O23: 6018 | P23: 6477 | Q23: 3478 | R23: =Q23 -> 3478 | S23: 6566 | T23: 5076 | U23: 4320 | V23: 11904 | W23: =V23 -> 11904 | X23: 13142 | Y23: 11770 | Z23: 9433 | AA23: 9948 | AB23: =AA23 -> 9948 | AC23: 11508 | AD23: 14262 | AE23: 9144 | AF23: 8519 | AG23: =AF23 -> 8519 | AH23: 6491 | AI23: 8772 | AJ23: 6824 | AK23: 7447 | AL23: =AK23 -> 7447 | AM23: 11181 | AN23: 5723 | AO23: 9302 | AP23: 16293 | AQ23: =AP23 -> 16293 | AR23: 6999 | AS23: 5044 | AT23: =AT67*IS!AT$17 -> 14100.068 | AU23: =AU67*IS!AU$17 -> 15044.666 | AV23: =AU23 -> 15044.666 | AW23: =AW67*IS!AW$17 -> 15372.946 | AX23: =AX67*IS!AX$17 -> 15931.66 | AY23: =AY67*IS!AY$17 -> 15734.561 | AZ23: =AZ67*IS!AZ$17 -> 16905.487 | BA23: =AZ23 -> 16905.487
C24: Accrued Compensation and Benefits | D24: 2245 | E24: 2625 | F24: 2541 | G24: 3425 | H24: =G24 -> 3425 | I24: 2872 | J24: 3304 | K24: 3487.386 | L24: 4333.4786 | M24: =L24 -> 4333.4786 | N24: 4408.9414 | O24: 6379 | P24: 6723 | Q24: 12387 | R24: =Q24 -> 12387 | S24: 7605 | T24: 14304 | U24: 11632 | V24: 20287 | W24: =V24 -> 20287 | X24: 18176 | Y24: 21146 | Z24: 18478 | AA24: 29004 | AB24: =AA24 -> 29004 | AC24: 20649 | AD24: 31021 | AE24: 20639 | AF24: 32901 | AG24: =AF24 -> 32901 | AH24: 23030 | AI24: 33228 | AJ24: 27619 | AK24: 34158 | AL24: =AK24 -> 34158 | AM24: 23305 | AN24: 29249 | AO24: 32998 | AP24: 39581 | AQ24: =AP24 -> 39581 | AR24: 35950 | AS24: 33081 | AT24: =AT68*IS!AT$17 -> 34243.021 | AU24: =AU68*IS!AU$17 -> 42984.761 | AV24: =AU24 -> 42984.761 | AW24: =AW68*IS!AW$17 -> 37334.296 | AX24: =AX68*IS!AX$17 -> 45519.028 | AY24: =AY68*IS!AY$17 -> 38212.506 | AZ24: =AZ68*IS!AZ$17 -> 48301.391 | BA24: =AZ24 -> 48301.391
C25: Deferred Revenue, current portion | D25: 2655 | E25: 2662 | F25: 2745 | G25: 3277 | H25: =G25 -> 3277 | I25: 2846 | J25: 3801 | K25: 3341.1347 | L25: 3468.5765 | M25: =L25 -> 3468.5765 | N25: 3706.4395 | O25: 4274 | P25: 6101 | Q25: 5891 | R25: =Q25 -> 5891 | S25: 6166 | T25: 5379 | U25: 8371 | V25: 12848 | W25: =V25 -> 12848 | X25: 21328 | Y25: 30487 | Z25: 30370 | AA25: 31868 | AB25: =AA25 -> 31868 | AC25: 30401 | AD25: 30358 | AE25: 28084 | AF25: 26328 | AG25: =AF25 -> 26328 | AH25: 19489 | AI25: 17327 | AJ25: 17547 | AK25: 17006 | AL25: =AK25 -> 17006 | AM25: 21730 | AN25: 21775 | AO25: 21740 | AP25: 22435 | AQ25: =AP25 -> 22435 | AR25: 20782 | AS25: 20887 | AT25: =AT70*IS!AT$17 -> 28200.135 | AU25: =AU70*IS!AU$17 -> 30089.333 | AV25: =AU25 -> 30089.333 | AW25: =AW70*IS!AW$17 -> 30745.891 | AX25: =AX70*IS!AX$17 -> 31863.32 | AY25: =AY70*IS!AY$17 -> 31469.122 | AZ25: =AZ70*IS!AZ$17 -> 33810.974 | BA25: =AZ25 -> 33810.974
C26: Other Accrued Liabilities | D26: 1511 | E26: 1454 | F26: 1789 | G26: 3001 | H26: =G26 -> 3001 | I26: 3793 | J26: 6683 | K26: 7462 | L26: 6550.8679 | M26: =L26 -> 6550.8679 | N26: 7730.7311 | O26: 9872 | P26: 10894 | Q26: 8541 | R26: =Q26 -> 8541 | S26: 8335 | T26: 6600 | U26: 9281 | V26: 72022 | W26: =V26 -> 72022 | X26: 79296 | Y26: 87578 | Z26: 155127 | AA26: 120080 | AB26: =AA26 -> 120080 | AC26: 141806 | AD26: 181551 | AE26: 171234 | AF26: 194733 | AG26: =AF26 -> 194733 | AH26: 252932 | AI26: 268409 | AJ26: 263603 | AK26: 299506 | AL26: =AK26 -> 299506 | AM26: 212327 | AN26: 265548 | AO26: 262921 | AP26: 252455 | AQ26: =AP26 -> 252455 | AR26: 306405 | AS26: 339017 | AT26: =AT69*IS!AT$17 -> 261858.4 | AU26: =AU69*IS!AU$17 -> 279400.95 | AV26: =AU26 -> 279400.95 | AW26: =AW69*IS!AW$17 -> 285497.56 | AX26: =AX69*IS!AX$17 -> 295873.68 | AY26: =AY69*IS!AY$17 -> 292213.28 | AZ26: =AZ69*IS!AZ$17 -> 313959.04 | BA26: =AZ26 -> 313959.04
C27: Convertible Preferred Stock Warrant Liabilities | D27: 490 | E27: 492 | F27: 496 | G27: 663 | H27: =G27 -> 663 | I27: 652 | J27: 358 | K27: 523.62413 | L27: 688.36132 | M27: =L27 -> 688.36132 | N27: 853.41269 | P27: =O27 -> 0 | Q27: =P27 -> 0 | R27: =Q27 -> 0 | S27: =R27 -> 0 | T27: =S27 -> 0 | U27: =T27 -> 0 | V27: =U27 -> 0 | W27: =V27 -> 0 | ... AJ27: =AI27 -> 0 | AL27: =AK27 -> 0 | AQ27: =AP27 -> 0 | AT27: =AS27 -> 0 | AU27: =AT27 -> 0 | AV27: =AU27 -> 0 | AW27: =AV27 -> 0 | AX27: =AW27 -> 0 | AY27: =AX27 -> 0 | AZ27: =AY27 -> 0 | BA27: =AZ27 -> 0
C28: Bank Borrowings, current portion | D28: 3044 | E28: 2417 | F28: 3042 | G28: 3667 | H28: =G28 -> 3667 | I28: 4292 | J28: 4500 | K28: 4500 | L28: 9.3132257e-13 | M28: =L28 -> 9.3132257e-13 | N28: 0 | O28: 0 | P28: 2300 | Q28: 2300 | R28: =Q28 -> 2300 | S28: 2300 | T28: 2300 | U28: 0 | V28: =U28 -> 0 | W28: =V28 -> 0 | Y28: =X28 -> 0 | Z28: =Y28 -> 0 | AA28: =Z28 -> 0 | AB28: =AA28 -> 0 | AD28: =AC28 -> 0 | AE28: =AD28 -> 0 | AF28: 135046 | AG28: =AF28 -> 135046 | AH28: 135033 | AI28: 135021 | AJ28: 0 | AL28: =AK28 -> 0 | AP28: 180005 | AQ28: =AP28 -> 180005 | AT28: =AS28 -> 0 | AU28: =AT28 -> 0 | AV28: =AU28 -> 0 | AW28: =AV28 -> 0 | AX28: =AW28 -> 0 | AY28: =AX28 -> 0 | AZ28: =AY28 -> 0 | BA28: =AZ28 -> 0
C29: Operating lease liabilities | S29: 2485 | T29: 4727 | U29: 6388
C30: Convertible notes | X30: 1132793 | Y30: 1133825 | Z30: 1134835 | AA30: 75097 | AB30: =AA30 -> 75097 | AN30: 33373 | AO30: 33397 | AP30: 33421 | AQ30: =AP30 -> 33421 | AR30: 33446 | AS30: 0 | AT30: =AS30 -> 0 | AU30: =AT30 -> 0 | AV30: =AU30 -> 0 | AW30: =AV30 -> 0 | AX30: =AW30 -> 0 | AY30: =AX30 -> 0 | AZ30: =AY30 -> 0 | BA30: =AZ30 -> 0
C31: Customer Fund Deposits | D31: 709298 | E31: 902871 | F31: 786615 | G31: 915013 | H31: =G31 -> 915013 | I31: 1013736 | J31: 1212826 | K31: 1179910 | L31: 1329310 | M31: =L31 -> 1329310 | N31: 1466491.8 | O31: 1491763 | P31: 1353552 | Q31: 1644250 | R31: =Q31 -> 1644250 | S31: 1668903 | T31: 2217680 | U31: 1929840 | V31: 2208598 | W31: =V31 -> 2208598 | X31: 2432521 | Y31: 3380395 | Z31: 3043540 | AA31: 3142660 | AB31: =AA31 -> 3142660 | AC31: 3121654 | AD31: 3474048 | AE31: 3106630 | AF31: 3355909 | AG31: =AF31 -> 3355909 | AH31: 3263528 | AI31: 3655435 | AJ31: 3510918 | AK31: 3704907 | AL31: =AK31 -> 3704907 | AM31: 3787171 | AN31: 3766541 | AO31: 3657218 | AP31: 4044470 | AQ31: =AP31 -> 4044470 | AR31: 3974674 | AS31: 4032211 | AT31: =AT13 -> 4147751.7 | AU31: =AU13 -> 4218508.8 | AV31: =AU31 -> 4218508.8 | AW31: =AW13 -> 4399114.5 | AX31: =AX13 -> 4676273.2 | AY31: =AY13 -> 4491027 | AZ31: =AZ13 -> 4759461.5 | BA31: =AZ31 -> 4759461.5
B32: Total Current Liabilities | D32: =SUM(D23:D31) -> 720710 | E32: =SUM(E23:E31) -> 914941 | F32: =SUM(F23:F31) -> 798547 | G32: =SUM(G23:G31) -> 930578 | H32: =SUM(H23:H31) -> 930578 | I32: =SUM(I23:I31) -> 1030771 | J32: =SUM(J23:J31) -> 1235263 | K32: =SUM(K23:K31) -> 1203896.4 | ... BA32: =SUM(BA23:BA31) -> 5172438.4
C33: Deferred Revenue, long-term portion | D33: 1760 | E33: 1514 | F33: 1195.1717 | G33: 1931 | H33: =G33 -> 1931 | I33: 2249 | J33: 1841 | K33: 2130.7668 | L33: 1785.5677 | M33: =L33 -> 1785.5677 | N33: 1541.6417 | O33: 2091 | P33: 2098 | Q33: 2622 | R33: =Q33 -> 2622 | S33: 2785 | T33: 3166 | U33: 3066 | V33: 3728 | W33: =V33 -> 3728 | X33: 2640 | Y33: 2322 | AA33: 2159 | AB33: =AA33 -> 2159 | AC33: 2323 | AD33: 2013 | AE33: 1257 | AF33: 410 | AG33: =AF33 -> 410 | AH33: 4800 | AI33: 4174 | AJ33: 4156 | AK33: 4167 | AL33: =AK33 -> 4167 | AM33: 100 | AN33: 202 | AO33: 245 | AP33: 285 | AQ33: =AP33 -> 285 | AR33: 346 | AS33: 424 | AT33: =AT72*IS!AT$17 -> 4028.5908 | AU33: =AU72*IS!AU$17 -> 4298.4761 | AV33: =AU33 -> 4298.4761 | AW33: =AW72*IS!AW$17 -> 4392.2702 | AX33: =AX72*IS!AX$17 -> 4551.9028 | AY33: =AY72*IS!AY$17 -> 4495.5889 | AZ33: =AZ72*IS!AZ$17 -> 4830.1391 | BA33: =AZ33 -> 4830.1391
C34: Operating lease liabilities | S34: 52934 | T34: 54141 | U34: 53644 | V34: 86639 | W34: =V34 -> 86639 | X34: 85722 | Y34: 83547 | Z34: 84931 | AA34: 82728 | AB34: =AA34 -> 82728 | AC34: 80440 | AD34: 78207 | AE34: 75631 | AF34: 72477 | AG34: =AF34 -> 72477 | AH34: 69969 | AI34: 67725 | AJ34: 65023 | AK34: 62847 | AL34: =AK34 -> 62847 | AM34: 60571 | AN34: 63400 | AO34: 60694 | AP34: 58372 | AQ34: =AP34 -> 58372 | AR34: 55947 | AS34: 53490 | AT34: =AS34 -> 53490 | AU34: =AT34 -> 53490 | AV34: =AU34 -> 53490 | AW34: =AV34 -> 53490 | AX34: =AW34 -> 53490 | AY34: =AX34 -> 53490 | AZ34: =AY34 -> 53490 | BA34: =AZ34 -> 53490
C35: Borrowings from credit facilities | V35: 79534 | W35: =V35 -> 79534 | X35: 79014 | Y35: 78713 | Z35: 48071 | AA35: 0 | AB35: =AA35 -> 0 | AC35: 75083 | AD35: 112570 | AE35: 135058 | AF35: 0 | AG35: =AF35 -> 0 | AH35: =AG35 -> 0 | AI35: =AH35 -> 0 | AJ35: 180011 | AK35: 180009 | AL35: =AK35 -> 180009 | AM35: 180008 | AN35: 180007 | AO35: 180006 | AP35: 0 | AQ35: =AP35 -> 0 | AR35: 330003 | AS35: 330000 | AT35: =AS35 -> 330000 | AU35: =AT35 -> 330000 | AV35: =AU35 -> 330000 | AW35: =AV35 -> 330000 | AX35: =AW35 -> 330000 | AY35: =AX35 -> 330000 | AZ35: =AY35 -> 330000 | BA35: =AZ35 -> 330000
C36: Convertible senior notes | D36: 127 | E36: 7083 | F36: 6458.3333 | G36: 5833 | H36: =G36 -> 5833 | I36: 5208 | J36: 4583 | K36: 4166.6667 | L36: -4.6566129e-13 | M36: =L36 -> -4.6566129e-13 | N36: 0 | O36: =N36 -> 0 | P36: =O36 -> 0 | Q36: =P36 -> 0 | R36: =Q36 -> 0 | S36: =R36 -> 0 | T36: 886052 | U36: 897871 | V36: 909847 | W36: =V36 -> 909847 | X36: 560113 | Y36: 560788 | Z36: 561457 | AA36: 1697985 | AB36: =AA36 -> 1697985 | AC36: 1699690 | AD36: 1701397 | AE36: 1703083 | AF36: 1704782 | AG36: =AF36 -> 1704782 | AH36: 1706494 | AI36: 1708208 | AJ36: 966242 | AK36: 733991 | AL36: =AK36 -> 733991 | AM36: 734814 | AN36: 1498490 | AO36: 1499780 | AP36: 1501044 | AQ36: =AP36 -> 1501044 | AR36: 1502321 | AS36: 1503600 | AT36: =AS36 -> 1503600 | AU36: =AT36 -> 1503600 | AV36: =AU36 -> 1503600 | AW36: =AV36 -> 1503600 | AX36: =AW36 -> 1503600 | AY36: =AX36 -> 1503600 | AZ36: =AY36 -> 1503600 | BA36: =AZ36 -> 1503600
C37: Deferred income tax liability | T37: 1832 | U37: 1832 | V37: 9090 | W37: =V37 -> 9090 | X37: 3877 | AB37: =AA37 -> 0 | AG37: =AF37 -> 0 | AL37: =AK37 -> 0 | AQ37: =AP37 -> 0 | AV37: =AU37 -> 0 | BA37: =AZ37 -> 0
C38: Other Long-term Liabilities | D38: 420 | E38: 392 | F38: 334.67993 | G38: 1698 | H38: =G38 -> 1698 | I38: 1404 | J38: 1254 | K38: 1023.3871 | L38: 1446.7353 | M38: =L38 -> 1446.7353 | N38: 1412.2348 | O38: 1375 | P38: 11745 | Q38: 13827 | R38: =Q38 -> 13827 | S38: 2361 | T38: 4412 | U38: 3459 | V38: 25888 | W38: =V38 -> 25888 | X38: 26372 | Y38: 27060 | Z38: 29278 | AA38: 20803 | AB38: =AA38 -> 20803 | AC38: 22014 | AD38: 28970 | AE38: 26058 | AF38: 18944 | AG38: =AF38 -> 18944 | AH38: 20504 | AI38: 22267 | AJ38: 21582 | AK38: 574 | AL38: =AK38 -> 574 | AM38: 609 | AN38: 504 | AO38: 3874 | AP38: 1581 | AQ38: =AP38 -> 1581 | AR38: 1661 | AS38: 1871 | AT38: =AT73*IS!AT$17 -> 8057.1815 | AU38: =AU73*IS!AU$17 -> 8596.9522 | AV38: =AU38 -> 8596.9522 | AW38: =AW73*IS!AW$17 -> 8784.5403 | AX38: =AX73*IS!AX$17 -> 9103.8056 | AY38: =AY73*IS!AY$17 -> 8991.1778 | AZ38: =AZ73*IS!AZ$17 -> 9660.2783 | BA38: =AZ38 -> 9660.2783
B39: Total Liabilities | D39: =D32+SUM(D33:D38) -> 723017 | E39: =E32+SUM(E33:E38) -> 923930 | F39: =F32+SUM(F33:F38) -> 806535.18 | G39: =G32+SUM(G33:G38) -> 940040 | H39: =H32+SUM(H33:H38) -> 940040 | I39: =I32+SUM(I33:I38) -> 1039632 | J39: =J32+SUM(J33:J38) -> 1242941 | K39: =K32+SUM(K33:K38) -> 1211217.3 | ... BA39: =BA32+SUM(BA33:BA38) -> 7074018.8
C41: Convertible preferred stock | D41: 188702 | E41: 191150 | F41: 191147 | G41: 191146.58 | H41: =G41 -> 191146.58 | I41: 191147 | J41: 258248.27 | K41: 276293.21 | L41: 276307.09 | M41: =L41 -> 276307.09 | N41: =M41 -> 276307.09 | O41: =N41 -> 276307.09 | P41: =O41 -> 276307.09 | Q41: =P41 -> 276307.09 | R41: =Q41 -> 276307.09 | S41: =R41 -> 276307.09 | T41: =S41 -> 276307.09 | ... Y41: =X41 -> 276307.09 | Z41: 0 | AA41: =Z41 -> 0 | AB41: =AA41 -> 0 | AC41: =AB41 -> 0 | AD41: =AC41 -> 0 | AE41: =AD41 -> 0 | AF41: =AE41 -> 0 | AG41: =AF41 -> 0 | AH41: =AG41 -> 0 | ... BA41: =AZ41 -> 0
B43: Shareholders Equity:
C44: Total Shareholder Equity | D44: =D20-D39 -> 89443.799 | E44: =E20-E39 -> 90661.325 | F44: =F20-F39 -> 89652.079 | G44: =G20-G39 -> 89244.895 | H44: =G44 -> 89244.895 | I44: =I20-I39 -> 89581.67 | J44: =J20-J39 -> 157889.93 | K44: =K20-K39 -> 175927.62 | L44: =L20-L39 -> 173650.73 | M44: =L44 -> 173650.73 | N44: =N20-N39 -> 170325.19 | O44: =O20-O39 -> 383352 | P44: =P20-P39 -> 389949 | Q44: =Q20-Q39 -> 710719 | R44: =Q44 -> 710719 | S44: =S20-S39 -> 718768 | T44: =T20-T39 -> 876748 | U44: =U20-U39 -> 870461 | V44: =V20-V39 -> 2528788 | W44: =V44 -> 2528788 | X44: =X20-X39 -> 4109201 | Y44: =Y20-Y39 -> 4093327 | Z44: =Z20-Z39 -> 4068316 | AA44: =AA20-AA39 -> 4043694 | AB44: =AA44 -> 4043694 | AC44: =AC20-AC39 -> 4047531 | AD44: =AD20-AD39 -> 4083877 | AE44: =AE20-AE39 -> 4104067 | AF44: =AF20-AF39 -> 4085969 | AG44: =AF44 -> 4085969 | AH44: =AH20-AH39 -> 4118113 | AI44: =AI20-AI39 -> 3951845 | AJ44: =AJ20-AJ39 -> 4058733 | AK44: =AK20-AK39 -> 4134201 | AL44: =AK44 -> 4134201 | AM44: =AM20-AM39 -> 4013245 | AN44: =AN20-AN39 -> 3809394 | AO44: =AO20-AO39 -> 3870461 | AP44: =AP20-AP39 -> 3914040 | AQ44: =AP44 -> 3914040 | AR44: =AR20-AR39 -> 3882711 | AS44: =AS20-AS39 -> 3806809 | AT44: =AT20-AT39 -> 3879470.7 | AU44: =AU20-AU39 -> 3960073.8 | AV44: =AU44 -> 3960073.8 | AW44: =AW20-AW39 -> 4038231.7 | AX44: =AX20-AX39 -> 4126110.7 | AY44: =AY20-AY39 -> 4208486.2 | AZ44: =AZ20-AZ39 -> 4296515.5 | BA44: =AZ44 -> 4296515.5
B45: Total Liabilities & Shareholders Equity | D45: =D44+D39 -> 812460.8 | E45: =E44+E39 -> 1014591.3 | F45: =F44+F39 -> 896187.26 | G45: =G44+G39 -> 1029284.9 | H45: =G45 -> 1029284.9 | I45: =I44+I39 -> 1129213.7 | J45: =J44+J39 -> 1400830.9 | K45: =K44+K39 -> 1387144.9 | L45: =L44+L39 -> 1526297.6 | M45: =L45 -> 1526297.6 | N45: =N44+N39 -> 1662156.7 | O45: =O44+O39 -> 1905124 | P45: =P44+P39 -> 1789839 | Q45: =Q44+Q39 -> 2404015 | R45: =Q45 -> 2404015 | S45: =S44+S39 -> 2479208 | T45: =T44+T39 -> 4082417 | U45: =U44+U39 -> 3800165 | V45: =V44+V39 -> 5969173 | W45: =V45 -> 5969173 | X45: =X44+X39 -> 8564195 | Y45: =Y44+Y39 -> 9510958 | Z45: =Z44+Z39 -> 9183836 | AA45: =AA44+AA39 -> 9256026 | AB45: =AA45 -> 9256026 | AC45: =AC44+AC39 -> 9253099 | AD45: =AD44+AD39 -> 9738274 | AE45: =AE44+AE39 -> 9380885 | AF45: =AF44+AF39 -> 9636018 | AG45: =AF45 -> 9636018 | AH45: =AH44+AH39 -> 9620383 | AI45: =AI44+AI39 -> 9872411 | AJ45: =AJ44+AJ39 -> 9122258 | AK45: =AK44+AK39 -> 9178813 | AL45: =AK45 -> 9178813 | AM45: =AM44+AM39 -> 9045061 | AN45: =AN44+AN39 -> 9674206 | AO45: =AO44+AO39 -> 9632636 | AP45: =AP44+AP39 -> 10063982 | AQ45: =AP45 -> 10063982 | AR45: =AR44+AR39 -> 10151245 | AS45: =AS44+AS39 -> 10126434 | AT45: =AT44+AT39 -> 10264800 | AU45: =AU44+AU39 -> 10446088 | AV45: =AU45 -> 10446088 | AW45: =AW44+AW39 -> 10706564 | AX45: =AX44+AX39 -> 11092317 | AY45: =AY44+AY39 -> 10977719 | AZ45: =AZ44+AZ39 -> 11370534 | BA45: =AZ45 -> 11370534
B46: Scott Berg, sberg@needhamco.com | AG46: Source: Company Reports and Needham & Company, LLC Estimates
B47: 763.350.4027 | AG47: $ in thousands, except per share data
C50: Client funds/customer | D50: 14021.904 | E50: 16544.28 | F50: 13190.713 | G50: 14375.02 | I50: 14159.115 | J50: 16937.964 | K50: 15365.412 | L50: 16335.76 | N50: 16062.341 | O50: 15104.618 | P50: 13065.174 | Q50: 15057.234 | S50: 13769.827 | T50: #DIV/0! | U50: #DIV/0! | V50: #DIV/0! | X50: #DIV/0! | Y50: #DIV/0! | Z50: #DIV/0! | AA50: #DIV/0! | AC50: #DIV/0! | AD50: #DIV/0! | AE50: #DIV/0! | AF50: #DIV/0! | AH50: #DIV/0! | AI50: #DIV/0! | AJ50: #DIV/0! | AK50: #DIV/0! | AM50: #DIV/0! | AN50: #DIV/0! | AO50: #DIV/0! | AP50: #DIV/0! | AR50: #DIV/0! | AS50: #DIV/0! | AT50: #DIV/0! | AU50: #DIV/0! | AW50: #DIV/0! | AX50: #DIV/0! | AY50: #DIV/0! | AZ50: #DIV/0!
C51: Client funds held / revenue | D51: =D13/IS!D17 -> 54.134019 | E51: =E13/IS!E17 -> 59.543889 | F51: =F13/IS!F17 -> 46.007053 | G51: =G13/IS!G17 -> 46.922129 | I51: =I13/IS!I17 -> 45.207373 | J51: =J13/IS!J17 -> 46.649576 | K51: =K13/IS!K17 -> 41.776064 | L51: =L13/IS!L17 -> 41.954689 | N51: =N13/IS!N17 -> 41.685999 | O51: =O13/IS!O17 -> 37.916146 | P51: =P13/IS!P17 -> 32.829299 | Q51: =Q13/IS!Q17 -> 39.046545 | S51: =S13/IS!S17 -> 36.116406 | T51: =T13/IS!T17 -> 41.033953 | U51: =U13/IS!U17 -> 32.305065 | V51: =V13/IS!V17 -> 28.216601 | X51: =X13/IS!X17 -> 20.553794 | Y51: =Y13/IS!Y17 -> 21.603005 | Z51: =Z13/IS!Z17 -> 18.234508 | AA51: =AA13/IS!AA17 -> 15.695956 | AC51: =AC13/IS!AC17 -> 13.576895 | AD51: =AD13/IS!AD17 -> 13.361415 | AE51: 11.397186 | AF51: 12.066219 | AH51: =AH13/IS!AH17 -> 10.700618 | AI51: =AI13/IS!AI17 -> 11.477213 | AJ51: 11.087667 | AK51: 12.066219 | AM51: =AM13/IS!AM17 -> 10.565409 | AN51: =AN13/IS!AN17 -> 10.38891 | AO51: 11.087667 | AP51: 12.066219 | AR51: =AR13/IS!AR17 -> 10.043624 | AS51: =AS13/IS!AS17 -> 9.7238799 | AT51: #DIV/0! | AU51: #DIV/0! | AW51: =AW13/IS!AW17 -> 10.015583 | AX51: =AX13/IS!AX17 -> 10.273227 | AY51: #DIV/0! | AZ51: #DIV/0!
C53: DSO | E53: =((E9+D9)/2)/IS!E17*91 -> 10.517461 | F53: =((F9+E9)/2)/IS!F17*91 -> 8.7605911 | G53: =((G9+F9)/2)/IS!G17*91 -> 9.1113517 | I53: =((I9+H9)/2)/IS!I17*91 -> 11.55755 | J53: =((J9+I9)/2)/IS!J17*91 -> 14.119733 | K53: =((K9+J9)/2)/IS!K17*91 -> 13.977545 | L53: =((L9+K9)/2)/IS!L17*91 -> 12.065719 | N53: =((N9+M9)/2)/IS!N17*91 -> 10.461065 | O53: =((O9+N9)/2)/IS!O17*91 -> 9.8749364 | P53: =((P9+O9)/2)/IS!P17*91 -> 9.0834465 | Q53: =((Q9+P9)/2)/IS!Q17*91 -> 8.3112325 | S53: =((S9+R9)/2)/IS!S17*91 -> 9.1513991 | T53: =((T9+S9)/2)/IS!T17*91 -> 10.169202 | U53: =((U9+T9)/2)/IS!U17*91 -> 12.659538 | V53: =((V9+U9)/2)/IS!V17*91 -> 16.163594 | X53: =((X9+W9)/2)/IS!X17*91 -> 14.623558 | Y53: =((Y9+X9)/2)/IS!Y17*91 -> 12.866243 | Z53: =((Z9+Y9)/2)/IS!Z17*91 -> 13.982218 | AA53: =((AA9+Z9)/2)/IS!AA17*91 -> 11.567877 | AC53: =((AC9+AB9)/2)/IS!AC17*91 -> 10.509027 | AD53: =((AD9+AC9)/2)/IS!AD17*91 -> 10.555931 | AE53: =((AE9+AD9)/2)/IS!AE17*91 -> 10.905443 | AF53: =((AF9+AE9)/2)/IS!AF17*91 -> 9.5767629 | AH53: =((AH9+AG9)/2)/IS!AH17*91 -> 7.8074381 | AI53: =((AI9+AH9)/2)/IS!AI17*91 -> 7.2503995 | AJ53: =((AJ9+AI9)/2)/IS!AJ17*91 -> 7.9643452 | AK53: =((AK9+AJ9)/2)/IS!AK17*91 -> 7.6710459 | AM53: =((AM9+AL9)/2)/IS!AM17*91 -> 7.6139671 | AN53: =((AN9+AM9)/2)/IS!AN17*91 -> 7.6359591 | AO53: =((AO9+AN9)/2)/IS!AO17*91 -> 7.0588973 | AP53: =((AP9+AO9)/2)/IS!AP17*91 -> 7.003232 | AR53: =((AR9+AQ9)/2)/IS!AR17*91 -> 7.4105463 | AS53: =((AS9+AR9)/2)/IS!AS17*91 -> 8.0402488 | AT53: =((AT9+AS9)/2)/IS!AT17*91 -> 9.4265612 | AU53: =((AU9+AT9)/2)/IS!AU17*91 -> 9.2550385 | AW53: =((AW9+AV9)/2)/IS!AW17*91 -> 9.4529796 | AX53: =((AX9+AW9)/2)/IS!AX17*91 -> 9.3874558 | AY53: =((AY9+AX9)/2)/IS!AY17*91 -> 9.6148453 | AZ53: =((AZ9+AY9)/2)/IS!AZ17*91 -> 9.2240957
C55: Deferred Revs | D55: =D38+D28 -> 3464 | E55: =E38+E28 -> 2809 | F55: =F38+F28 -> 3376.6799 | G55: =G38+G28 -> 5365 | I55: =I38+I28 -> 5696 | J55: =J38+J28 -> 5754 | K55: =K38+K28 -> 5523.3871 | L55: =L38+L28 -> 1446.7353 | N55: =N38+N28 -> 1412.2348 | O55: =O38+O28 -> 1375 | P55: =P38+P28 -> 14045 | Q55: =Q38+Q28 -> 16127 | S55: =S38+S28 -> 4661 | T55: =T38+T28 -> 6712 | U55: =U38+U28 -> 3459 | V55: =V38+V28 -> 25888 | X55: =X38+X28 -> 26372 | Y55: =Y38+Y28 -> 27060 | Z55: =Z38+Z28 -> 29278 | AA55: =AA38+AA28 -> 20803 | AC55: =AC38+AC28 -> 22014 | AD55: =AD38+AD28 -> 28970 | AE55: =AE38+AE28 -> 26058 | AF55: =AF38+AF28 -> 153990 | AH55: =AH38+AH28 -> 155537 | AI55: =AI38+AI28 -> 157288 | AJ55: =AJ38+AJ28 -> 21582 | AK55: =AK38+AK28 -> 574 | AM55: =AM38+AM28 -> 609 | AN55: =AN38+AN28 -> 504 | AO55: =AO38+AO28 -> 3874 | AP55: =AP38+AP28 -> 181586 | AR55: =AR38+AR28 -> 1661 | AS55: =AS38+AS28 -> 1871 | AT55: =AT38+AT28 -> 8057.1815 | AU55: =AU38+AU28 -> 8596.9522 | AW55: =AW38+AW28 -> 8784.5403 | AX55: =AX38+AX28 -> 9103.8056 | AY55: =AY38+AY28 -> 8991.1778 | AZ55: =AZ38+AZ28 -> 9660.2783
C56: % y/y change | I56: =I55/D55-1 -> 0.6443418 | J56: =J55/E55-1 -> 1.0484158 | K56: =K55/F55-1 -> 0.63574493 | L56: =L55/G55-1 -> -0.73033825 | N56: =N55/I55-1 -> -0.75206552 | O56: =O55/J55-1 -> -0.7610358 | P56: =P55/K55-1 -> 1.5428238 | Q56: =Q55/L55-1 -> 10.147167 | S56: =S55/N55-1 -> 2.3004427 | T56: =T55/O55-1 -> 3.8814545 | U56: =U55/P55-1 -> -0.75372019 | V56: =V55/Q55-1 -> 0.60525826 | X56: =X55/S55-1 -> 4.6580133 | Y56: =Y55/T55-1 -> 3.0315852 | Z56: =Z55/U55-1 -> 7.464296 | AA56: =AA55/V55-1 -> -0.19642305 | AC56: =AC55/X55-1 -> -0.16525102 | AD56: =AD55/Y55-1 -> 0.070583888 | AE56: =AE55/Z55-1 -> -0.10998019 | AF56: =AF55/AA55-1 -> 6.4022977 | AH56: =AH55/AC55-1 -> 6.0653675 | AI56: =AI55/AD55-1 -> 4.4293407 | AJ56: =AJ55/AE55-1 -> -0.17177067 | AK56: =AK55/AF55-1 -> -0.99627249 | AM56: =AM55/AH55-1 -> -0.99608453 | AN56: =AN55/AI55-1 -> -0.99679569 | AO56: =AO55/AJ55-1 -> -0.82049856 | AP56: =AP55/AK55-1 -> 315.35192 | AR56: =AR55/AM55-1 -> 1.727422 | AS56: =AS55/AN55-1 -> 2.7123016 | AT56: =AT55/AO55-1 -> 1.0798094 | AU56: =AU55/AP55-1 -> -0.95265631 | AW56: =AW55/AR55-1 -> 4.2887058 | AX56: =AX55/AS55-1 -> 3.8657433 | AY56: =AY55/AT55-1 -> 0.11592097 | AZ56: =AZ55/AU55-1 -> 0.1236864
C57: % q/q change | E57: =E55/D55-1 -> -0.18908776 | F57: =F55/E55-1 -> 0.20209325 | G57: =G55/F55-1 -> 0.58883877 | I57: =I55/G55-1 -> 0.061696179 | J57: =J55/I55-1 -> 0.010182584 | K57: =K55/J55-1 -> -0.040078717 | L57: =L55/K55-1 -> -0.738071 | N57: =N55/L55-1 -> -0.023847134 | O57: =O55/N55-1 -> -0.026365857 | P57: =P55/O55-1 -> 9.2145455 | Q57: =Q55/P55-1 -> 0.14823781 | S57: =S55/Q55-1 -> -0.71098158 | T57: =T55/S55-1 -> 0.44003433 | U57: =U55/T55-1 -> -0.48465435 | V57: =V55/U55-1 -> 6.484244 | X57: =X55/V55-1 -> 0.018695921 | Y57: =Y55/X55-1 -> 0.026088275 | Z57: =Z55/Y55-1 -> 0.081966001 | AA57: =AA55/Z55-1 -> -0.28946649 | AC57: =AC55/AA55-1 -> 0.058212758 | AD57: =AD55/AC55-1 -> 0.31598074 | AE57: =AE55/AD55-1 -> -0.10051778 | AF57: =AF55/AE55-1 -> 4.9095096 | AH57: =AH55/AF55-1 -> 0.010046107 | AI57: =AI55/AH55-1 -> 0.011257771 | AJ57: =AJ55/AI55-1 -> -0.86278674 | AK57: =AK55/AJ55-1 -> -0.97340376 | AM57: =AM55/AK55-1 -> 0.06097561 | AN57: =AN55/AM55-1 -> -0.17241379 | AO57: =AO55/AN55-1 -> 6.6865079 | AP57: =AP55/AO55-1 -> 45.872999 | AR57: =AR55/AP55-1 -> -0.99085282 | AS57: =AS55/AR55-1 -> 0.12642986 | AT57: =AT55/AS55-1 -> 3.3063504 | AU57: =AU55/AT55-1 -> 0.066992492 | AW57: =AW55/AU55-1 -> 0.021820307 | AX57: =AX55/AW55-1 -> 0.036344 | AY57: =AY55/AX55-1 -> -0.012371515 | AZ57: =AZ55/AY55-1 -> 0.074417446
B59: Drivers of Revenue % - Assets
C60: Accounts Receivable | D60: =D9/IS!D17 -> 0.13875078 | E60: =E9/IS!E17 -> 0.1112568 | F60: =F9/IS!F17 -> 0.09387225 | G60: =G9/IS!G17 -> 0.11794464 | I60: =I9/IS!I17 -> 0.15144401 | J60: =J9/IS!J17 -> 0.17970164 | K60: =K9/IS!K17 -> 0.14178128 | L60: =L9/IS!L17 -> 0.13879558 | N60: =N9/IS!N17 -> 0.10490757 | O60: =O9/IS!O17 -> 0.12259468 | P60: =P9/IS!P17 -> 0.083434392 | Q60: =Q9/IS!Q17 -> 0.10097364 | S60: =S9/IS!S17 -> 0.10911294 | T60: =T9/IS!T17 -> 0.13020631 | U60: =U9/IS!U17 -> 0.16043389 | V60: =V9/IS!V17 -> 0.23280058 | X60: =X9/IS!X17 -> 0.16742854 | Y60: =Y9/IS!Y17 -> 0.15614336 | Z60: =Z9/IS!Z17 -> 0.16091809 | AA60: =AA9/IS!AA17 -> 0.1200923 | AC60: =AC9/IS!AC17 -> 0.12638959 | AD60: =AD9/IS!AD17 -> 0.12023184 | AE60: =AE9/IS!AE17 -> 0.12498395 | AF60: =AF9/IS!AF17 -> 0.095387235 | AH60: =AH9/IS!AH17 -> 0.07902028 | AI60: =AI9/IS!AI17 -> 0.083681062 | AJ60: =AJ9/IS!AJ17 -> 0.092533774 | AK60: =AK9/IS!AK17 -> 0.081617273 | AM60: =AM9/IS!AM17 -> 0.089089134 | AN60: =AN9/IS!AN17 -> 0.079742604 | AO60: =AO9/IS!AO17 -> 0.074432537 | AP60: =AP9/IS!AP17 -> 0.084364378 | AR60: =AR9/IS!AR17 -> 0.081146507 | AS60: =AS9/IS!AS17 -> 0.099266648 | AT60: 0.105 | AU60: 0.105 | AW60: 0.105 | AX60: 0.105 | AY60: 0.105 | AZ60: 0.105
C61: Unbilled Revenue | D61: =D11/IS!D17 -> 0.17759794 | E61: =E11/IS!E17 -> 0.16737982 | F61: =F11/IS!F17 -> 0.17008131 | G61: =G11/IS!G17 -> 0.15625999 | I61: =I11/IS!I17 -> 0.15898053 | J61: =J11/IS!J17 -> 0.15115619 | K61: =K11/IS!K17 -> 0.15691145 | L61: =L11/IS!L17 -> 0.15133972 | N61: =N11/IS!N17 -> 0.15394095 | O61: =O11/IS!O17 -> 0.15120266 | P61: =P11/IS!P17 -> 0.14918748 | Q61: =Q11/IS!Q17 -> 0.15552125 | S61: =S11/IS!S17 -> 0.14986258 | T61: =T11/IS!T17 -> 0.13636784 | U61: =U11/IS!U17 -> 0.13165824 | V61: =V11/IS!V17 -> 0.10371392 | X61: =X11/IS!X17 -> 0 | Y61: =Y11/IS!Y17 -> 0 | Z61: =Z11/IS!Z17 -> 0 | AA61: =AA11/IS!AA17 -> 0 | AC61: =AC11/IS!AC17 -> 0 | AD61: =AD11/IS!AD17 -> 0 | AE61: =AE11/IS!AE17 -> 0 | AF61: =AF11/IS!AF17 -> 0 | AH61: =AH11/IS!AH17 -> 0 | AI61: =AI11/IS!AI17 -> 0 | AJ61: =AJ11/IS!AJ17 -> 0 | AK61: =AK11/IS!AK17 -> 0 | AM61: =AM11/IS!AM17 -> 0 | AN61: =AN11/IS!AN17 -> 0 | AO61: =AO11/IS!AO17 -> 0 | AP61: =AP11/IS!AP17 -> 0 | AR61: =AR11/IS!AR17 -> 0 | AS61: =AS11/IS!AS17 -> 0 | AT61: 0 | AU61: 0 | AW61: 0 | AX61: 0 | AY61: 0 | AZ61: 0
C62: Prepaid expenses & other CA | D62: =D12/IS!D17 -> 0.19971453 | E62: =E12/IS!E17 -> 0.30496144 | F62: =F12/IS!F17 -> 0.30443074 | G62: =G12/IS!G17 -> 0.29874111 | I62: =I12/IS!I17 -> 0.31512764 | J62: =J12/IS!J17 -> 0.34455488 | K62: =K12/IS!K17 -> 0.37332669 | L62: =L12/IS!L17 -> 0.38095852 | N62: =N12/IS!N17 -> 0.38814333 | O62: =O12/IS!O17 -> 0.40348004 | P62: =P12/IS!P17 -> 0.60967742 | Q62: =Q12/IS!Q17 -> 0.6359772 | S62: =S12/IS!S17 -> 0.33372287 | T62: =T12/IS!T17 -> 0.34689611 | U62: =U12/IS!U17 -> 0.305802 | V62: =V12/IS!V17 -> 0.75475579 | X62: =X12/IS!X17 -> 0.6045763 | Y62: =Y12/IS!Y17 -> 0.54140518 | Z62: =Z12/IS!Z17 -> 0.55038314 | AA62: =AA12/IS!AA17 -> 0.75545522 | AC62: =AC12/IS!AC17 -> 0.60897949 | AD62: =AD12/IS!AD17 -> 0.68724568 | AE62: =AE12/IS!AE17 -> 0.6241676 | AF62: =AF12/IS!AF17 -> 0.57473233 | AH62: =AH12/IS!AH17 -> 0.63946424 | AI62: =AI12/IS!AI17 -> 0.64279188 | AJ62: =AJ12/IS!AJ17 -> 0.79311701 | AK62: =AK12/IS!AK17 -> 0.86470545 | AM62: =AM12/IS!AM17 -> 0.79161947 | AN62: =AN12/IS!AN17 -> 0.69472961 | AO62: =AO12/IS!AO17 -> 0.67370337 | AP62: =AP12/IS!AP17 -> 0.67410636 | AR62: =AR12/IS!AR17 -> 0.68056128 | AS62: =AS12/IS!AS17 -> 0.67155166 | AT62: 0.65 | AU62: 0.65 | AW62: 0.65 | AX62: 0.65 | AY62: 0.65 | AZ62: 0.65
C63: Funds Held for Customers | D63: =D13/IS!D17 -> 54.134019 | E63: =E13/IS!E17 -> 59.543889 | F63: =F13/IS!F17 -> 46.007053 | G63: =G13/IS!G17 -> 46.922129 | I63: =I13/IS!I17 -> 45.207373 | J63: =J13/IS!J17 -> 46.649576 | K63: =K13/IS!K17 -> 41.776064 | L63: =L13/IS!L17 -> 41.954689 | N63: =N13/IS!N17 -> 41.685999 | O63: =O13/IS!O17 -> 37.916146 | P63: =P13/IS!P17 -> 32.829299 | Q63: =Q13/IS!Q17 -> 39.046545 | S63: =S13/IS!S17 -> 36.116406 | T63: =T13/IS!T17 -> 41.033953 | U63: =U13/IS!U17 -> 32.305065 | V63: =V13/IS!V17 -> 28.216601 | X63: =X13/IS!X17 -> 20.553794 | Y63: =Y13/IS!Y17 -> 21.603005 | Z63: =Z13/IS!Z17 -> 18.234508 | AA63: =AA13/IS!AA17 -> 15.695956 | AC63: =AC13/IS!AC17 -> 13.576895 | AD63: =AD13/IS!AD17 -> 13.361415 | AE63: =AE13/IS!AE17 -> 11.397186 | AF63: =AF13/IS!AF17 -> 11.338182 | AH63: =AH13/IS!AH17 -> 10.700618 | AI63: =AI13/IS!AI17 -> 11.477213 | AJ63: =AJ13/IS!AJ17 -> 10.868773 | AK63: =AK13/IS!AK17 -> 10.780577 | AM63: =AM13/IS!AM17 -> 10.565409 | AN63: =AN13/IS!AN17 -> 10.38891 | AO63: =AO13/IS!AO17 -> 10.209504 | AP63: =AP13/IS!AP17 -> 10.55036 | AR63: =AR13/IS!AR17 -> 10.043624 | AS63: =AS13/IS!AS17 -> 9.7238799 | AT63: =AT13/IS!AT17 -> 10.295788 | AU63: =AU13/IS!AU17 -> 9.8139636 | AW63: =AW13/IS!AW17 -> 10.015583 | AX63: =AX13/IS!AX17 -> 10.273227 | AY63: =AY13/IS!AY17 -> 9.9898524 | AZ63: =AZ13/IS!AZ17 -> 9.8536737
C64: Other Assets | D64: =D19/IS!D17 -> 0.19478422 | E64: =E19/IS!E17 -> 0.18479049 | F64: =F19/IS!F17 -> 0.21587693 | G64: =G19/IS!G17 -> 0.2372467 | I64: =I19/IS!I17 -> 0.24420123 | J64: =J19/IS!J17 -> 0.20105104 | K64: =K19/IS!K17 -> 0.211724 | L64: =L19/IS!L17 -> 0.20959276 | N64: =N19/IS!N17 -> 0.21030697 | O64: =O19/IS!O17 -> 0.16256397 | P64: =P19/IS!P17 -> 0.16538928 | Q64: =Q19/IS!Q17 -> 0.25409641 | S64: =S19/IS!S17 -> 0.37836785 | T64: =T19/IS!T17 -> 0.40645758 | U64: =U19/IS!U17 -> 0.37662794 | V64: =V19/IS!V17 -> 0.67615908 | X64: =X19/IS!X17 -> 0.45814498 | Y64: =Y19/IS!Y17 -> 0.34468104 | Z64: =Z19/IS!Z17 -> 0.32235143 | AA64: =AA19/IS!AA17 -> 0.23838658 | AC64: =AC19/IS!AC17 -> 0.21244846 | AD64: =AD19/IS!AD17 -> 0.19076483 | AE64: =AE19/IS!AE17 -> 0.18234852 | AF64: =AF19/IS!AF17 -> 0.18367947 | AH64: =AH19/IS!AH17 -> 0.15952916 | AI64: =AI19/IS!AI17 -> 0.15318294 | AJ64: =AJ19/IS!AJ17 -> 0.14777666 | AK64: =AK19/IS!AK17 -> 0.11222557 | AM64: =AM19/IS!AM17 -> 0.089415539 | AN64: =AN19/IS!AN17 -> 0.0827987 | AO64: =AO19/IS!AO17 -> 0.087684281 | AP64: =AP19/IS!AP17 -> 0.086547767 | AR64: =AR19/IS!AR17 -> 0.086490912 | AS64: =AS19/IS!AS17 -> 0.079518462 | AT64: 0.24387984 | AU64: 0.22097984 | AW64: 0.24387984 | AX64: 0.24387984 | AY64: 0.24387984 | AZ64: 0.22097984
B66: Drivers of Revenue % - Liabilities
C67: Accounts payable | D67: =D23/IS!D17 -> 0.11196226 | E67: =E23/IS!E17 -> 0.15959778 | F67: =F23/IS!F17 -> 0.077144858 | G67: =G23/IS!G17 -> 0.078561387 | I67: =I23/IS!I17 -> 0.11505463 | J67: =J23/IS!J17 -> 0.14581526 | K67: =K23/IS!K17 -> 0.1654279 | L67: =L23/IS!L17 -> 0.1598048 | N67: =N23/IS!N17 -> 0.16163697 | O67: =O23/IS!O17 -> 0.15399181 | P67: =P23/IS!P17 -> 0.15709435 | Q67: =Q23/IS!Q17 -> 0.082593208 | S67: =S23/IS!S17 -> 0.14209353 | T67: =T23/IS!T17 -> 0.093921732 | U67: =U23/IS!U17 -> 0.072315779 | V67: =V23/IS!V17 -> 0.15208309 | X67: =X23/IS!X17 -> 0.11104445 | Y67: =Y23/IS!Y17 -> 0.075218242 | Z67: =Z23/IS!Z17 -> 0.056515149 | AA67: =AA23/IS!AA17 -> 0.049685098 | AC67: =AC23/IS!AC17 -> 0.050051321 | AD67: =AD23/IS!AD17 -> 0.05485258 | AE67: =AE23/IS!AE17 -> 0.033549192 | AF67: =AF23/IS!AF17 -> 0.028782058 | AH67: =AH23/IS!AH17 -> 0.021283014 | AI67: =AI23/IS!AI17 -> 0.027542034 | AJ67: =AJ23/IS!AJ17 -> 0.021125104 | AK67: =AK23/IS!AK17 -> 0.021669358 | AM67: =AM23/IS!AM17 -> 0.031192635 | AN67: =AN23/IS!AN17 -> 0.015785235 | AO67: =AO23/IS!AO17 -> 0.0259675 | AP67: =AP23/IS!AP17 -> 0.042501741 | AR67: =AR23/IS!AR17 -> 0.01768581 | AS67: =AS23/IS!AS17 -> 0.01216386 | AT67: 0.035 | AU67: 0.035 | AW67: 0.035 | AX67: 0.035 | AY67: 0.035 | AZ67: 0.035
C68: Accrued Compensation and Benefits | D68: =D24/IS!D17 -> 0.17133965 | E68: =E24/IS!E17 -> 0.17311743 | F68: =F24/IS!F17 -> 0.14861644 | G68: =G24/IS!G17 -> 0.17563495 | I68: =I24/IS!I17 -> 0.12807632 | J68: =J24/IS!J17 -> 0.12708352 | K68: =K24/IS!K17 -> 0.12347489 | L68: =L24/IS!L17 -> 0.13677041 | N68: =N24/IS!N17 -> 0.12532708 | O68: =O24/IS!O17 -> 0.16322927 | P68: =P24/IS!P17 -> 0.16306088 | Q68: =Q24/IS!Q17 -> 0.29415816 | S68: =S24/IS!S17 -> 0.16457833 | T68: =T24/IS!T17 -> 0.26466833 | U68: =U24/IS!U17 -> 0.19471693 | V68: =V24/IS!V17 -> 0.2591826 | X68: =X24/IS!X17 -> 0.15357967 | Y68: =Y24/IS!Y17 -> 0.13513721 | Z68: =Z24/IS!Z17 -> 0.11070571 | AA68: =AA24/IS!AA17 -> 0.14485993 | AC68: =AC24/IS!AC17 -> 0.089807937 | AD68: =AD24/IS!AD17 -> 0.11930879 | AE68: =AE24/IS!AE17 -> 0.075724166 | AF68: =AF24/IS!AF17 -> 0.11115841 | AH68: =AH24/IS!AH17 -> 0.07551191 | AI68: =AI24/IS!AI17 -> 0.10432817 | AJ68: =AJ24/IS!AJ17 -> 0.085500328 | AK68: =AK24/IS!AK17 -> 0.099393305 | AM68: =AM24/IS!AM17 -> 0.065016041 | AN68: =AN24/IS!AN17 -> 0.080674879 | AO68: =AO24/IS!AO17 -> 0.092117348 | AP68: =AP24/IS!AP17 -> 0.10325056 | AR68: =AR24/IS!AR17 -> 0.090842243 | AS68: =AS24/IS!AS17 -> 0.079776498 | AT68: 0.085 | AU68: 0.1 | AW68: 0.085 | AX68: 0.1 | AY68: 0.085 | AZ68: 0.1
C69: Other Accrued Liabilities | D69: =D26/IS!D17 -> 0.11532036 | E69: =E26/IS!E17 -> 0.095890569 | F69: =F26/IS!F17 -> 0.10463393 | G69: =G26/IS!G17 -> 0.15389212 | I69: =I26/IS!I17 -> 0.16914815 | J69: =J26/IS!J17 -> 0.25705181 | K69: =K26/IS!K17 -> 0.26420065 | L69: =L26/IS!L17 -> 0.2067542 | N69: =N26/IS!N17 -> 0.21975115 | O69: =O26/IS!O17 -> 0.25261003 | P69: =P26/IS!P17 -> 0.26422508 | Q69: =Q26/IS!Q17 -> 0.20282593 | S69: =S26/IS!S17 -> 0.18037612 | T69: =T26/IS!T17 -> 0.12212046 | U69: =U26/IS!U17 -> 0.15536175 | V69: =V26/IS!V17 -> 0.92013849 | X69: =X26/IS!X17 -> 0.67001834 | Y69: =Y26/IS!Y17 -> 0.55968251 | Z69: =Z26/IS!Z17 -> 0.9293995 | AA69: =AA26/IS!AA17 -> 0.59973729 | AC69: =AC26/IS!AC17 -> 0.61675162 | AD69: =AD26/IS!AD17 -> 0.69825696 | AE69: =AE26/IS!AE17 -> 0.62825485 | AF69: =AF26/IS!AF17 -> 0.65791954 | AH69: =AH26/IS!AH17 -> 0.82932603 | AI69: =AI26/IS!AI17 -> 0.84274164 | AJ69: =AJ26/IS!AJ17 -> 0.81603762 | AK69: =AK26/IS!AK17 -> 0.87150568 | AM69: =AM26/IS!AM17 -> 0.59234761 | AN69: =AN26/IS!AN17 -> 0.7324371 | AO69: =AO26/IS!AO17 -> 0.73397131 | AP69: =AP26/IS!AP17 -> 0.65855135 | AR69: =AR26/IS!AR17 -> 0.77425639 | AS69: =AS26/IS!AS17 -> 0.81755657 | AT69: 0.65 | AU69: 0.65 | AW69: 0.65 | AX69: 0.65 | AY69: 0.65 | AZ69: 0.65
C70: Deferred Revenue, current portion | D70: =D25/IS!D17 -> 0.20263108 | E70: =E25/IS!E17 -> 0.17555756 | F70: =F25/IS!F17 -> 0.16054787 | G70: =G25/IS!G17 -> 0.16804547 | I70: =I25/IS!I17 -> 0.12691685 | J70: =J25/IS!J17 -> 0.1461999 | K70: =K25/IS!K17 -> 0.1182967 | L70: =L25/IS!L17 -> 0.10947294 | N70: =N25/IS!N17 -> 0.105358 | O70: =O25/IS!O17 -> 0.1093654 | P70: =P25/IS!P17 -> 0.14797478 | Q70: =Q25/IS!Q17 -> 0.13989551 | S70: =S25/IS!S17 -> 0.13343721 | T70: =T25/IS!T17 -> 0.099528171 | U70: =U25/IS!U17 -> 0.14012856 | V70: =V25/IS!V17 -> 0.16414345 | X70: =X25/IS!X17 -> 0.18021276 | Y70: =Y25/IS!Y17 -> 0.1948325 | Z70: =Z25/IS!Z17 -> 0.18195326 | AA70: =AA25/IS!AA17 -> 0.15916412 | AC70: =AC25/IS!AC17 -> 0.13222195 | AD70: =AD25/IS!AD17 -> 0.11675884 | AE70: =AE25/IS!AE17 -> 0.10303975 | AF70: =AF25/IS!AF17 -> 0.088951055 | AH70: =AH25/IS!AH17 -> 0.063901503 | AI70: =AI25/IS!AI17 -> 0.054402738 | AJ70: =AJ25/IS!AJ17 -> 0.054320369 | AK70: =AK25/IS!AK17 -> 0.049484236 | AM70: =AM25/IS!AM17 -> 0.060622123 | AN70: =AN25/IS!AN17 -> 0.060060019 | AO70: =AO25/IS!AO17 -> 0.06068947 | AP70: =AP25/IS!AP17 -> 0.058523695 | AR70: =AR25/IS!AR17 -> 0.052514144 | AS70: =AS25/IS!AS17 -> 0.050370052 | AT70: 0.07 | AU70: 0.07 | AW70: 0.07 | AX70: 0.07 | AY70: 0.07 | AZ70: 0.07
C71: Customer Funds Deposits | D71: =D31/IS!D17 -> 54.134019 | E71: =E31/IS!E17 -> 59.543889 | F71: =F31/IS!F17 -> 46.007053 | G71: =G31/IS!G17 -> 46.922122 | I71: =I31/IS!I17 -> 45.207373 | J71: =J31/IS!J17 -> 46.649576 | K71: =K31/IS!K17 -> 41.776064 | L71: =L31/IS!L17 -> 41.954811 | N71: =N31/IS!N17 -> 41.685999 | O71: =O31/IS!O17 -> 38.172032 | P71: =P31/IS!P17 -> 32.829299 | Q71: =Q31/IS!Q17 -> 39.046545 | S71: =S31/IS!S17 -> 36.116406 | T71: =T31/IS!T17 -> 41.033953 | U71: =U31/IS!U17 -> 32.305065 | V71: =V31/IS!V17 -> 28.216601 | X71: =X31/IS!X17 -> 20.553794 | Y71: =Y31/IS!Y17 -> 21.603005 | Z71: =Z31/IS!Z17 -> 18.234508 | AA71: =AA31/IS!AA17 -> 15.695956 | AC71: =AC31/IS!AC17 -> 13.576895 | AD71: =AD31/IS!AD17 -> 13.361415 | AE71: =AE31/IS!AE17 -> 11.398177 | AF71: =AF31/IS!AF17 -> 11.338182 | AH71: =AH31/IS!AH17 -> 10.700618 | AI71: =AI31/IS!AI17 -> 11.477213 | AJ71: =AJ31/IS!AJ17 -> 10.868773 | AK71: =AK31/IS!AK17 -> 10.780577 | AM71: =AM31/IS!AM17 -> 10.565409 | AN71: =AN31/IS!AN17 -> 10.38891 | AO71: =AO31/IS!AO17 -> 10.209504 | AP71: =AP31/IS!AP17 -> 10.55036 | AR71: =AR31/IS!AR17 -> 10.043624 | AS71: =AS31/IS!AS17 -> 9.7238799 | AT71: =AT31/IS!AT17 -> 10.295788 | AU71: =AU31/IS!AU17 -> 9.8139636 | AW71: =AW31/IS!AW17 -> 10.015583 | AX71: =AX31/IS!AX17 -> 10.273227 | AY71: =AY31/IS!AY17 -> 9.9898524 | AZ71: =AZ31/IS!AZ17 -> 9.8536737
C72: Def Rev, Long-Term | D72: =D33/IS!D17 -> 0.13432418 | E72: =E33/IS!E17 -> 0.099847539 | F72: =F33/IS!F17 -> 0.069902465 | G72: =G33/IS!G17 -> 0.099022218 | I72: =I33/IS!I17 -> 0.10029375 | J72: =J33/IS!J17 -> 0.070811369 | K72: =K33/IS!K17 -> 0.075442237 | L72: =L33/IS!L17 -> 0.056354918 | N72: =N33/IS!N17 -> 0.043822185 | O72: =O33/IS!O17 -> 0.053505629 | P72: =P33/IS!P17 -> 0.050885278 | Q72: =Q33/IS!Q17 -> 0.062265495 | S72: =S33/IS!S17 -> 0.060269644 | T72: =T33/IS!T17 -> 0.058580812 | U72: =U33/IS!U17 -> 0.051324115 | V72: =V33/IS!V17 -> 0.047628173 | X72: =X33/IS!X17 -> 0.022306906 | Y72: =Y33/IS!Y17 -> 0.014839147 | Z72: =Z33/IS!Z17 -> 0 | AA72: =AA33/IS!AA17 -> 0.010783085 | AC72: =AC33/IS!AC17 -> 0.010103338 | AD72: =AD33/IS!AD17 -> 0.007742129 | AE72: =AE33/IS!AE17 -> 0.0046119132 | AF72: =AF33/IS!AF17 -> 0.0013852147 | AH72: =AH33/IS!AH17 -> 0.015738479 | AI72: =AI33/IS!AI17 -> 0.013105386 | AJ72: =AJ33/IS!AJ17 -> 0.012865758 | AK72: =AK33/IS!AK17 -> 0.01212518 | AM72: =AM33/IS!AM17 -> 0.00027897894 | AN72: =AN33/IS!AN17 -> 0.00055715838 | AO72: =AO33/IS!AO17 -> 0.00068394297 | AP72: =AP33/IS!AP17 -> 0.00074344788 | AR72: =AR33/IS!AR17 -> 0.00087430921 | AS72: =AS33/IS!AS17 -> 0.0010224974 | AT72: 0.01 | AU72: 0.01 | AW72: 0.01 | AX72: 0.01 | AY72: 0.01 | AZ72: 0.01
C73: Other Long-Term Liabilities | D73: =D38/IS!D17 -> 0.032054635 | E73: =E38/IS!E17 -> 0.025852203 | F73: =F38/IS!F17 -> 0.019574553 | G73: =G38/IS!G17 -> 0.087073913 | I73: =I38/IS!I17 -> 0.062611126 | J73: =J38/IS!J17 -> 0.048233273 | K73: =K38/IS!K17 -> 0.036234191 | L73: =L38/IS!L17 -> 0.045660911 | N73: =N38/IS!N17 -> 0.040143709 | O73: =O38/IS!O17 -> 0.035184237 | P73: =P38/IS!P17 -> 0.28486539 | Q73: =Q38/IS!Q17 -> 0.32835431 | S73: =S38/IS!S17 -> 0.051093943 | T73: =T38/IS!T17 -> 0.081635674 | U73: =U38/IS!U17 -> 0.057902842 | V73: =V38/IS!V17 -> 0.33073985 | X73: =X38/IS!X17 -> 0.22283247 | Y73: =Y38/IS!Y17 -> 0.17293166 | Z73: =Z38/IS!Z17 -> 0.17541085 | AA73: =AA38/IS!AA17 -> 0.10390019 | AC73: =AC38/IS!AC17 -> 0.095744681 | AD73: =AD38/IS!AD17 -> 0.11142051 | AE73: =AE38/IS!AE17 -> 0.095606391 | AF73: =AF38/IS!AF17 -> 0.064003676 | AH73: =AH38/IS!AH17 -> 0.067229536 | AI73: =AI38/IS!AI17 -> 0.069913185 | AJ73: =AJ38/IS!AJ17 -> 0.066811546 | AK73: =AK38/IS!AK17 -> 0.0016702312 | AM73: =AM38/IS!AM17 -> 0.0016989817 | AN73: =AN38/IS!AN17 -> 0.0013901377 | AO73: =AO38/IS!AO17 -> 0.010814674 | AP73: =AP38/IS!AP17 -> 0.0041241793 | AR73: =AR38/IS!AR17 -> 0.0041971896 | AS73: =AS38/IS!AS17 -> 0.0045120107 | AT73: 0.02 | AU73: 0.02 | AW73: 0.02 | AX73: 0.02 | AY73: 0.02 | AZ73: 0.02

Sheet CF
B2: Bill.com, Inc. (BILL) | T2: =T52+S52+Q52+P52 -> -35005
AC3: .
B4: Statement of Cash Flows | D4: 1Q18 | E4: 2Q18 | F4: 3Q18 | G4: 4Q18 | H4: 2018 | I4: 1Q19 | J4: 2Q19 | K4: 3Q19 | L4: 4Q19 | M4: 2019 | N4: 1Q20 | O4: 2Q20 | P4: 3Q20 | Q4: 4Q20 | R4: 2020 | S4: 1Q21 | T4: 2Q21 | U4: 3Q21 | V4: 4Q21 | W4: 2021 | X4: 1Q22 | Y4: 2Q22 | Z4: 3Q22 | AA4: 4Q22 | AB4: 2022 | AC4: 1Q23 | AD4: 2Q23 | AE4: 3Q23 | AF4: 4Q23 | AG4: 2023 | AH4: =IS!AH4 -> 1Q24 | AI4: =IS!AI4 -> 2Q24 | AJ4: =IS!AJ4 -> 3Q24 | AK4: 4Q24 | AL4: =IS!AL4 -> 2024 | AM4: =IS!AM4 -> 1Q25 | AN4: =IS!AN4 -> 2Q25 | AO4: =IS!AO4 -> 3Q25 | AP4: =IS!AP4 -> 4Q25 | AQ4: =IS!AQ4 -> 2025 | AR4: =IS!AR4 -> 1Q26 | AS4: =IS!AS4 -> 2Q26 | ... BA4: =IS!BA4 -> 2027E
B5: Operating Activities
B7: Net Income | D7: =IS!D76 -> -2994.7337 | E7: =IS!E76 -> -1587.3625 | F7: =IS!F76 -> -1190.4828 | G7: =IS!G76 -> -1422.1003 | H7: =IS!H76 -> -7194.6793 | I7: =IS!I76 -> -1063.2963 | J7: =IS!J76 -> 281.17186 | K7: =IS!K76 -> -2032.592 | ... W7: =IS!W76 -> -98801 | X7: -75685 | Y7: =IS!Y76 -> -80440 | Z7: =IS!Z76 -> -86720 | AA7: =IS!AA76 -> -84942 | AB7: =IS!AB76 -> -325841 | AC7: =IS!AC76 -> -81640 | AD7: =IS!AD76 -> -95076 | AE7: =IS!AE76 -> -31138 | AF7: =IS!AF76 -> -15871 | AG7: =SUM(AC7:AF7) -> -223725 | AH7: =IS!AH76 -> -27861 | AI7: =IS!AI76 -> -40421 | AJ7: =IS!AJ76 -> 31809 | AK7: =IS!AK76 -> 7596 | AL7: =SUM(AH7:AK7) -> -28877 | AM7: =IS!AM76 -> 8912 | AN7: =IS!AN76 -> 33548 | AO7: =IS!AO76 -> -11589 | AP7: -7072 | AQ7: =SUM(AM7:AP7) -> 23799 | AR7: =IS!AR76 -> -2962 | AS7: =IS!AS76 -> -2588 | AT7: =IS!AT76 -> -5188.2593 | AU7: =IS!AU76 -> 103.04782 | AV7: =SUM(AR7:AU7) -> -10635.211 | AW7: =IS!AW76 -> 1447.0467 | AX7: =IS!AX76 -> 3379.0605 | AY7: =IS!AY76 -> -5124.5478 | AZ7: =IS!AZ76 -> -2470.6487 | BA7: =SUM(AW7:AZ7) -> -2769.0893
C9: Stock-based compensation expense | D9: 370 | E9: 365 | F9: 369 | G9: 441 | H9: =SUM(D9:G9) -> 1545 | I9: 786 | J9: 415 | K9: 1376 | L9: 1505 | M9: =SUM(I9:L9) -> 4082 | N9: 2276 | O9: 3075 | P9: 5085 | Q9: 7628 | R9: =SUM(N9:Q9) -> 18064 | S9: 9894 | T9: 10689 | U9: 10680 | V9: 37027 | W9: =SUM(S9:V9) -> 68290 | X9: 37887 | Y9: 49684 | Z9: 52810 | AA9: 56776 | AB9: =SUM(X9:AA9) -> 197157 | AC9: 72620 | AD9: 119305 | AE9: 63792 | AF9: 57850 | AG9: =SUM(AC9:AF9) -> 313567 | AH9: 65147 | AI9: 65500 | AJ9: 59389 | AK9: 58339 | AL9: =SUM(AH9:AK9) -> 248375 | AM9: 54657 | AN9: 65884 | AO9: 62230 | AP9: 59761 | AQ9: =SUM(AM9:AP9) -> 242532 | AR9: 58805 | AS9: 64256 | AT9: =IS!AT50 -> 64350 | AU9: =IS!AU50 -> 67000 | AV9: =SUM(AR9:AU9) -> 254411 | AW9: =IS!AW50 -> 67000 | AX9: =IS!AX50 -> 71000 | AY9: =IS!AY50 -> 74000 | AZ9: =IS!AZ50 -> 77000 | BA9: =SUM(AW9:AZ9) -> 289000
C10: Amortization of acquired intangibles | R10: =SUM(N10:Q10) -> 0 | V10: 5659 | W10: =SUM(S10:V10) -> 5659 | X10: 16672 | Y10: 19768 | Z10: 19769 | AA10: 19768 | AB10: =SUM(X10:AA10) -> 75977 | AC10: 19769 | AD10: 19994 | AE10: 20220 | AF10: =IS!AF46 -> 20221 | AG10: =SUM(AC10:AF10) -> 80204 | AH10: 20221 | AI10: 20222 | AJ10: 20220 | AK10: 19293 | AL10: =SUM(AH10:AK10) -> 79956 | AM10: 16938 | AN10: 14657 | AO10: 15165 | AP10: 15165 | AQ10: =SUM(AM10:AP10) -> 61925 | AR10: 15165 | AS10: 15165 | AT10: =IS!AT46 -> 20000 | AU10: =IS!AU46 -> 20000 | AV10: =SUM(AR10:AU10) -> 70330 | AW10: =IS!AW46 -> 20000 | AX10: =IS!AX46 -> 20000 | AY10: =IS!AY46 -> 20000 | AZ10: =IS!AZ46 -> 20000 | BA10: =SUM(AW10:AZ10) -> 80000
C11: Depreciation and amortization | D11: 521 | E11: 513 | F11: 586 | G11: 694 | H11: =SUM(D11:G11) -> 2314 | I11: 765 | J11: 808 | K11: 846 | L11: 735 | M11: =SUM(I11:L11) -> 3154 | N11: 985 | O11: 1120 | P11: 1100 | Q11: 1052 | R11: =SUM(N11:Q11) -> 4257 | S11: 924 | T11: 999 | U11: 1526 | V11: 1901 | W11: =SUM(S11:V11) -> 5350 | X11: 2388 | Y11: 2635 | Z11: 3197 | AA11: 2460 | AB11: =SUM(X11:AA11) -> 10680 | AC11: 2546 | AD11: 2535 | AE11: 2826 | AF11: =IS!AF47 -> 3351 | AG11: =SUM(AC11:AF11) -> 11258 | AH11: 3718 | AI11: 3240 | AJ11: 3209 | AK11: 3671 | AL11: =SUM(AH11:AK11) -> 13838 | AM11: 3169 | AN11: 3510 | AO11: 3171 | AP11: 3160 | AQ11: =SUM(AM11:AP11) -> 13010 | AR11: 3839 | AS11: 7615 | AT11: =IS!AT47 -> 0 | AU11: =IS!AU47 -> 0 | AV11: =SUM(AR11:AU11) -> 11454 | AW11: =IS!AW47 -> 0 | AX11: =IS!AX47 -> 0 | AY11: =IS!AY47 -> 0 | AZ11: =IS!AZ47 -> 0 | BA11: =SUM(AW11:AZ11) -> 0
C12: Amortization of capitalized internal-use software costs | R12: =SUM(N12:Q12) -> 0 | W12: =SUM(S12:V12) -> 0 | AA12: 847 | AB12: =SUM(X12:AA12) -> 847 | AC12: 924 | AD12: 977 | AE12: 1108 | AF12: 1206 | AG12: =SUM(AC12:AF12) -> 4215 | AH12: 1352 | AI12: 2387 | AJ12: 2593 | AK12: 3037 | AL12: =SUM(AH12:AK12) -> 9369 | AM12: 3944 | AN12: 3889 | AO12: 3114 | AP12: 3561 | AQ12: =SUM(AM12:AP12) -> 14508 | AR12: 4507 | AS12: 12610 | AV12: =SUM(AR12:AU12) -> 17117 | BA12: =SUM(AW12:AZ12) -> 0
C13: Amortization of debt discount and issuance costs | R13: =SUM(N13:Q13) -> 0 | T13: 3905 | U13: 11819 | V13: 11807 | W13: =SUM(S13:V13) -> 27531 | X13: 556 | Y13: 1399 | Z13: 1407 | AA13: 1415 | AB13: =SUM(X13:AA13) -> 4777 | AC13: 1712 | AD13: 1771 | AE13: 1734 | AF13: 1747 | AG13: =SUM(AC13:AF13) -> 6964 | AH13: 1761 | AI13: 1762 | AJ13: 1651 | AK13: 1064 | AL13: =SUM(AH13:AK13) -> 6238 | AM13: 895 | AN13: 1001 | AO13: 1384 | AP13: 1459 | AQ13: =SUM(AM13:AP13) -> 4739 | AR13: 1610 | AS13: 1625 | AV13: =SUM(AR13:AU13) -> 3235 | BA13: =SUM(AW13:AZ13) -> 0
C14: Accretion of discount on investment in marketable debt securities | D14: 0 | E14: 0 | F14: 0 | G14: 0 | H14: =SUM(D14:G14) -> 0 | I14: -165 | J14: -296 | K14: -424 | L14: -434 | M14: =SUM(I14:L14) -> -1319 | N14: -730 | O14: -1616 | P14: -509 | Q14: -960 | R14: =SUM(N14:Q14) -> -3815 | S14: 46 | T14: 677 | U14: 1247 | V14: 2722 | W14: =SUM(S14:V14) -> 4692 | X14: 2857 | Y14: 3781 | Z14: 3401 | AA14: 1347 | AB14: =SUM(X14:AA14) -> 11386 | AC14: -2215 | AD14: -8186 | AE14: -13309 | AF14: -13484 | AG14: =SUM(AC14:AF14) -> -37194 | AH14: -13093 | AI14: -11078 | AJ14: -15114 | AK14: -15777 | AL14: =SUM(AH14:AK14) -> -55062 | AM14: =-12241 -> -12241 | AN14: -9431 | AO14: -7738 | AP14: -7590 | AQ14: =SUM(AM14:AP14) -> -37000 | AR14: -7464 | AS14: -6422 | AV14: =SUM(AR14:AU14) -> -13886 | BA14: =SUM(AW14:AZ14) -> 0
C15: Accretion of discount on loans held in investment | R15: =SUM(N15:Q15) -> 0 | W15: =SUM(S15:V15) -> 0 | AB15: =SUM(X15:AA15) -> 0 | AG15: =SUM(AC15:AF15) -> 0 | AJ15: -5531 | AK15: -3678 | AL15: =SUM(AH15:AK15) -> -9209 | AM15: =-4631 -> -4631 | AN15: -5329 | AO15: -5279 | AP15: -5976 | AQ15: =SUM(AM15:AP15) -> -21215 | AR15: -6533 | AS15: -7144 | AV15: =SUM(AR15:AU15) -> -13677 | BA15: =SUM(AW15:AZ15) -> 0
C16: Provisions for loses on acquired card receivables | R16: =SUM(N16:Q16) -> 0 | V16: 741 | W16: =SUM(S16:V16) -> 741 | X16: 4049 | Y16: 5486 | Z16: 6086 | AA16: 4258 | AB16: =SUM(X16:AA16) -> 19879 | AC16: 6611 | AD16: 8431 | AE16: 8643 | AF16: 8504 | AG16: =SUM(AC16:AF16) -> 32189 | AH16: 12401 | AI16: 16288 | AJ16: 18590 | AK16: 12826 | AL16: =SUM(AH16:AK16) -> 60105 | AM16: 20661 | AN16: 21358 | AO16: 14945 | AP16: 15785 | AQ16: =SUM(AM16:AP16) -> 72749 | AR16: 16096 | AS16: 22624 | AV16: =SUM(AR16:AU16) -> 38720 | BA16: =SUM(AW16:AZ16) -> 0
C17: Non-cash operating lease | R17: =SUM(N17:Q17) -> 0 | U17: 958 | V17: 1178 | W17: =SUM(S17:V17) -> 2136 | X17: 1960 | Y17: 2123 | Z17: 2224 | AA17: 2294 | AB17: =SUM(X17:AA17) -> 8601 | AC17: 2342 | AD17: 2376 | AE17: 2396 | AF17: 2379 | AG17: =SUM(AC17:AF17) -> 9493 | AH17: 2388 | AI17: 2164 | AJ17: 2038 | AK17: 2052 | AL17: =SUM(AH17:AK17) -> 8642 | AM17: 2045 | AN17: 2062 | AO17: 2067 | AP17: 1990 | AQ17: =SUM(AM17:AP17) -> 8164 | AR17: 2019 | AS17: 2050 | AV17: =SUM(AR17:AU17) -> 4069 | BA17: =SUM(AW17:AZ17) -> 0
C18: Gain on debt extingishment | R18: =SUM(N18:Q18) -> 0 | W18: =SUM(S18:V18) -> 0 | AB18: =SUM(X18:AA18) -> 0 | AG18: =SUM(AC18:AF18) -> 0 | AJ18: -35715 | AK18: -10939 | AL18: =SUM(AH18:AK18) -> -46654 | AN18: -40472 | AQ18: =SUM(AM18:AP18) -> -40472 | AV18: =SUM(AR18:AU18) -> 0 | BA18: =SUM(AW18:AZ18) -> 0
C19: Revaluation of warrant liabilities | D19: 9 | E19: 1.70236 | F19: 4 | G19: 167.29764 | H19: =SUM(D19:G19) -> 182 | I19: -11 | J19: -294 | K19: 166 | L19: 164 | M19: =SUM(I19:L19) -> 25 | N19: 165 | O19: 552 | P19: 0 | Q19: 0 | R19: =SUM(N19:Q19) -> 717 | S19: 765 | T19: 912 | U19: 0 | V19: 0 | W19: =SUM(S19:V19) -> 1677 | X19: 0 | Y19: 0 | Z19: 0 | AA19: 0 | AB19: =SUM(X19:AA19) -> 0 | AC19: 0 | AD19: 0 | AE19: 0 | AF19: 0 | AG19: =SUM(AC19:AF19) -> 0 | AL19: =SUM(AH19:AK19) -> 0 | AQ19: =SUM(AM19:AP19) -> 0 | AU19: 0 | AV19: =SUM(AR19:AU19) -> 0 | AZ19: 0 | BA19: =SUM(AW19:AZ19) -> 0
C20: Issuance of warrants | D20: 0 | E20: 0 | F20: 0 | G20: 0 | H20: =SUM(D20:G20) -> 0 | I20: 52 | J20: 0 | K20: 87 | L20: 135 | M20: =SUM(I20:L20) -> 274 | N20: 0 | R20: =SUM(N20:Q20) -> 0 | W20: =SUM(S20:V20) -> 0 | AB20: =SUM(X20:AA20) -> 0 | AG20: =SUM(AC20:AF20) -> 0 | AL20: =SUM(AH20:AK20) -> 0 | AQ20: =SUM(AM20:AP20) -> 0 | AV20: =SUM(AR20:AU20) -> 0 | BA20: =SUM(AW20:AZ20) -> 0
C21: Other | R21: =SUM(N21:Q21) -> 0 | W21: =SUM(S21:V21) -> 0 | AA21: -726 | AB21: =SUM(X21:AA21) -> -726 | AC21: 930 | AD21: -414 | AE21: 833 | AF21: -220 | AG21: =SUM(AC21:AF21) -> 1129 | AH21: -562 | AI21: -2052 | AJ21: 4402 | AK21: -32 | AL21: =SUM(AH21:AK21) -> 1756 | AM21: 172 | AN21: 340 | AO21: 319 | AP21: -515 | AQ21: =SUM(AM21:AP21) -> 316 | AR21: 368 | AS21: 468 | AV21: =SUM(AR21:AU21) -> 836 | BA21: =SUM(AW21:AZ21) -> 0
C22: Deferred income taxes | D22: 0 | E22: 0 | F22: 0 | G22: 0 | H22: =SUM(D22:G22) -> 0 | I22: -37 | J22: -7 | K22: -69 | L22: -63 | M22: =SUM(I22:L22) -> -176 | N22: 0 | O22: 0 | P22: 0 | Q22: 0 | R22: =SUM(N22:Q22) -> 0 | S22: 0 | T22: -333 | U22: 0 | V22: -40284 | W22: =SUM(S22:V22) -> -40617 | X22: -3943 | Y22: -399 | Z22: -869 | AA22: 616 | AB22: =SUM(X22:AA22) -> -4595 | AC22: -299 | AD22: -527 | AE22: -343 | AF22: -193 | AG22: =SUM(AC22:AF22) -> -1362 | AH22: -42 | AI22: -74 | AJ22: -10 | AK22: -235 | AL22: =SUM(AH22:AK22) -> -361 | AQ22: =SUM(AM22:AP22) -> 0 | AV22: =SUM(AR22:AU22) -> 0 | BA22: =SUM(AW22:AZ22) -> 0
B23: Net Change in Working Capital
C24: Accounts receivable | D24: 289 | E24: 131 | F24: 82 | G24: -781 | H24: =SUM(D24:G24) -> -279 | I24: -1096 | J24: -1276 | K24: 668 | L24: -394 | M24: =SUM(I24:L24) -> -2098 | N24: 707 | O24: -1100 | P24: 1351 | Q24: -2012 | R24: =SUM(N24:Q24) -> -1054 | S24: -790 | T24: -1995 | U24: -2547 | V24: -1203 | W24: =SUM(S24:V24) -> -6535 | X24: 1198 | Y24: -4618 | Z24: -2426 | AA24: 2814 | AB24: =SUM(X24:AA24) -> -3032 | AC24: -4774 | AD24: -2278 | AE24: -2917 | AF24: 5487 | AG24: =SUM(AC24:AF24) -> -4482 | AH24: 3707 | AI24: -3317 | AJ24: -4185 | AK24: 3864 | AL24: =SUM(AH24:AK24) -> 69 | AM24: -4028 | AN24: 2868 | AO24: 2442 | AP24: -5740 | AQ24: =SUM(AM24:AP24) -> -4458 | AR24: 273 | AS24: -9075 | AT24: =BS!AS9-BS!AT9 -> -1137.2029 | AU24: =BS!AT9-BS!AU9 -> -2833.796 | AV24: =SUM(AR24:AU24) -> -12772.999 | AW24: -4774 | AX24: =BS!AW9-BS!AX9 -> -1676.143 | AY24: =BS!AX9-BS!AY9 -> 591.29633 | AZ24: =BS!AY9-BS!AZ9 -> -3512.7775 | BA24: =SUM(AW24:AZ24) -> -9371.6242
C25: Unbilled revenue | D25: 130 | E25: -211 | F25: -370 | G25: -52 | H25: =SUM(D25:G25) -> -503 | I25: -518 | J25: -365 | K25: -502 | L25: -363 | M25: =SUM(I25:L25) -> -1748 | N25: -621 | O25: -493 | P25: -242 | Q25: 802 | R25: =SUM(N25:Q25) -> -554 | S25: -376 | T25: -445 | U25: -495 | V25: -253 | W25: =SUM(S25:V25) -> -1569 | X25: 0 | Y25: 0 | Z25: 5581 | AA25: 0 | AB25: =SUM(X25:AA25) -> 5581 | AG25: =SUM(AC25:AF25) -> 0 | AL25: =SUM(AH25:AK25) -> 0 | AQ25: =SUM(AM25:AP25) -> 0 | AV25: =SUM(AR25:AU25) -> 0 | BA25: =SUM(AW25:AZ25) -> 0
C26: Prepaid expenses and other current assets | D26: -189 | E26: -2124 | F26: -790 | G26: -374 | H26: =SUM(D26:G26) -> -3477 | I26: -1121 | J26: -1875 | K26: -1345 | L26: -1349 | M26: =SUM(I26:L26) -> -5690 | N26: -1142 | O26: -466 | P26: -9235 | Q26: 409 | R26: =SUM(N26:Q26) -> -10434 | S26: 2314 | T26: -6261 | U26: -886 | V26: 7108 | W26: =SUM(S26:V26) -> 2275 | X26: 6321 | Y26: -14868 | Z26: 131 | AA26: -10004 | AB26: =SUM(X26:AA26) -> -18420 | AC26: -1339 | AD26: -3284 | AE26: -2854 | AF26: -9367 | AG26: =SUM(AC26:AF26) -> -16844 | AH26: -4704 | AI26: 4553 | AJ26: 5564 | AK26: -12238 | AL26: =SUM(AH26:AK26) -> -6825 | AM26: -1143 | AN26: -26164 | AO26: 9101 | AP26: -8780 | AQ26: =SUM(AM26:AP26) -> -26986 | AR26: 5403 | AS26: 7510 | AT26: =BS!AS12-BS!AT12 -> 16614.601 | AU26: =BS!AT12-BS!AU12 -> -17542.547 | AV26: =SUM(AR26:AU26) -> 11985.054 | AW26: =BS!AV12-BS!AW12 -> -6096.6143 | AX26: =BS!AW12-BS!AX12 -> -10376.123 | AY26: =BS!AX12-BS!AY12 -> 3660.4059 | AZ26: =BS!AY12-BS!AZ12 -> -21745.766 | BA26: =SUM(AW26:AZ26) -> -34558.098
C27: Other assets | D27: -753 | E27: -250 | F27: -889 | G27: -936 | H27: =SUM(D27:G27) -> -2828 | I27: -850 | J27: 249 | K27: -203 | L27: -191 | M27: =SUM(I27:L27) -> -995 | N27: -50 | O27: -531 | P27: -466 | Q27: -3881 | R27: =SUM(N27:Q27) -> -4928 | S27: -6784 | T27: -4483 | U27: -532 | V27: -726 | W27: =SUM(S27:V27) -> -12525 | X27: -1385 | Y27: 286 | Z27: -2412 | AA27: 6073 | AB27: =SUM(X27:AA27) -> 2562 | AC27: -1138 | AD27: -742 | AE27: -160 | AF27: 2360 | AG27: =SUM(AC27:AF27) -> 320 | AH27: -1074 | AI27: -166 | AJ27: -828 | AK27: 9596 | AL27: =SUM(AH27:AK27) -> 7528 | AM27: 6910 | AN27: 2004 | AO27: -516 | AP27: 19 | AQ27: =SUM(AM27:AP27) -> 8417 | AR27: -1378 | AS27: 1168 | AT27: =BS!AS19-BS!AT19 -> -65275.206 | AU27: =BS!AT19-BS!AU19 -> 3261.5489 | AV27: =SUM(AR27:AU27) -> -62223.657 | AW27: =BS!AV19-BS!AW19 -> -12130.956 | AX27: =BS!AW19-BS!AX19 -> -3893.1189 | AY27: =BS!AX19-BS!AY19 -> 1373.3834 | AZ27: =BS!AY19-BS!AZ19 -> 2902.0103 | BA27: =SUM(AW27:AZ27) -> -11748.681
C28: Accounts payable | D28: -628 | E28: 953 | F28: -1101 | G28: 213 | H28: =SUM(D28:G28) -> -563 | I28: 1048 | J28: 1211 | K28: 881 | L28: 31 | M28: =SUM(I28:L28) -> 3171 | N28: 508 | O28: 638 | P28: -2621 | Q28: -121 | R28: =SUM(N28:Q28) -> -1596 | S28: 1566 | T28: -200 | U28: -439 | V28: 6490 | W28: =SUM(S28:V28) -> 7417 | X28: -732 | Y28: -1291 | Z28: 24095 | AA28: 664 | AB28: =SUM(X28:AA28) -> 22736 | AC28: 1511 | AD28: 2000 | AE28: -4776 | AF28: -421 | AG28: =SUM(AC28:AF28) -> -1686 | AH28: -2508 | AI28: 2741 | AJ28: -2131 | AK28: 773 | AL28: =SUM(AH28:AK28) -> -1125 | AM28: 3804 | AN28: -5878 | AO28: 3834 | AP28: 6453 | AQ28: =SUM(AM28:AP28) -> 8213 | AR28: -9797 | AS28: -724 | AT28: =BS!AT23-BS!AS23 -> 9056.0676 | AU28: =BS!AU23-BS!AT23 -> 944.59867 | AV28: =SUM(AR28:AU28) -> -520.33368 | AW28: =BS!AW23-BS!AV23 -> 328.27923 | AX28: =BS!AX23-BS!AW23 -> 558.71433 | AY28: =BS!AY23-BS!AX23 -> -197.09878 | AZ28: =BS!AZ23-BS!AY23 -> 1170.9258 | BA28: =SUM(AW28:AZ28) -> 1860.8206
C29: Accrued liabilities | D29: -563 | E29: 351 | F29: 251 | G29: 1603 | H29: =SUM(D29:G29) -> 1642 | I29: 153 | J29: 702 | K29: 927 | L29: 2554 | M29: =SUM(I29:L29) -> 4336 | N29: 1132 | O29: 3419 | P29: 2342 | Q29: 2862 | R29: =SUM(N29:Q29) -> 9755 | S29: -4504 | T29: 4492 | U29: 70 | V29: 22922 | W29: =SUM(S29:V29) -> 22980 | X29: -17930 | Y29: 6500 | Z29: -2639 | AA29: -5205 | AB29: =SUM(X29:AA29) -> -19274 | AC29: 4247 | AD29: 11161 | AE29: -5769 | AF29: 24826 | AG29: =SUM(AC29:AF29) -> 34465 | AH29: -2286 | AI29: 23230 | AJ29: -14132 | AK29: 14180 | AL29: =SUM(AH29:AK29) -> 20992 | AM29: -9791 | AN29: 16926 | AO29: 7246 | AP29: 15841 | AQ29: =SUM(AM29:AP29) -> 30222 | AR29: 20826 | AS29: -1644 | AT29: =(BS!AT26-BS!AS26)+(BS!AT24-BS!AS24) -> -75996.579 | AU29: =(BS!AU26-BS!AT26)+(BS!AU24-BS!AT24) -> 26284.286 | AV29: =SUM(AR29:AU29) -> -30530.293 | AW29: =(BS!AW26-BS!AV26)+(BS!AW24-BS!AV24) -> 446.14977 | AX29: =(BS!AX26-BS!AW26)+(BS!AX24-BS!AW24) -> 18560.855 | AY29: =(BS!AY26-BS!AX26)+(BS!AY24-BS!AX24) -> -10966.929 | AZ29: =(BS!AZ26-BS!AY26)+(BS!AZ24-BS!AY24) -> 31834.652 | BA29: =SUM(AW29:AZ29) -> 39874.728
C30: Operating lease liabilities | R30: =SUM(N30:Q30) -> 0 | S30: 5764 | T30: 1166 | U30: 852 | V30: 613 | W30: =SUM(S30:V30) -> 8395 | X30: -792 | Y30: -2160 | AA30: -2286 | AB30: =SUM(X30:AA30) -> -5238 | AC30: -2386 | AD30: -2408 | AE30: -2917 | AF30: -2592 | AG30: =SUM(AC30:AF30) -> -10303 | AH30: -2423 | AI30: -2494 | AJ30: -2642 | AK30: -2280 | AL30: =SUM(AH30:AK30) -> -9839 | AM30: -2348 | AN30: -2080 | AO30: -2759 | AP30: -2225 | AQ30: =SUM(AM30:AP30) -> -9412 | AR30: -2331 | AS30: -2360 | AT30: =BS!AT34-BS!AS34 -> 0 | AU30: =BS!AU34-BS!AT34 -> 0 | AV30: =SUM(AR30:AU30) -> -4691 | AW30: =BS!AW34-BS!AV34 -> 0 | AX30: =BS!AX34-BS!AW34 -> 0 | AY30: =BS!AY34-BS!AX34 -> 0 | AZ30: =BS!AZ34-BS!AY34 -> 0 | BA30: =SUM(AW30:AZ30) -> 0
C31: Other long-term liabilities | D31: 171 | E31: -28 | F31: -57 | G31: -51 | H31: =SUM(D31:G31) -> 35 | I31: -85 | J31: -24 | K31: -103 | L31: 514 | M31: =SUM(I31:L31) -> 302 | N31: 93 | O31: 94 | P31: 10502 | Q31: 2302 | R31: =SUM(N31:Q31) -> 12991 | S31: 1338 | T31: -765 | U31: 3 | V31: 16 | W31: =SUM(S31:V31) -> 592 | X31: -121 | Y31: -1577 | Z31: 2000 | AA31: -7051 | AB31: =SUM(X31:AA31) -> -6749 | AC31: 34 | AD31: 1 | AE31: -307 | AF31: -2825 | AG31: =SUM(AC31:AF31) -> -3097 | AH31: -32 | AI31: -15 | AJ31: -2570 | AK31: -11963 | AL31: =SUM(AH31:AK31) -> -14580 | AM31: 0 | AN31: -124 | AO31: 2385 | AP31: -2215 | AQ31: =SUM(AM31:AP31) -> 46 | AT31: =BS!AT38-BS!AS38 -> 6186.1815 | AU31: =BS!AU38-BS!AT38 -> 539.77067 | AV31: =SUM(AR31:AU31) -> 6725.9522 | AW31: =BS!AW38-BS!AV38 -> 187.58813 | AX31: =BS!AX38-BS!AW38 -> 319.26533 | AY31: =BS!AY38-BS!AX38 -> -112.62787 | AZ31: =BS!AZ38-BS!AY38 -> 669.10049 | BA31: =SUM(AW31:AZ31) -> 1063.3261
C32: Deferred revenue | D32: -23 | E32: -239 | F32: -236 | G32: 1269 | H32: =SUM(D32:G32) -> 771 | I32: -113 | J32: 547 | K32: -170 | L32: -217 | M32: =SUM(I32:L32) -> 47 | N32: -7 | O32: 1117 | P32: 1834 | Q32: 314 | R32: =SUM(N32:Q32) -> 3258 | S32: 438 | T32: -406 | U32: 2892 | V32: 3930 | W32: =SUM(S32:V32) -> 6854 | X32: 5566 | Y32: 761 | Z32: 810 | AA32: 408 | AB32: =SUM(X32:AA32) -> 7545 | AC32: -1303 | AD32: -406 | AE32: -3031 | AF32: -2603 | AG32: =SUM(AC32:AF32) -> -7343 | AH32: -2449 | AI32: -2788 | AJ32: 202 | AK32: -529 | AL32: =SUM(AH32:AK32) -> -5564 | AM32: 657 | AN32: 147 | AO32: 8 | AP32: 734 | AQ32: =SUM(AM32:AP32) -> 1546 | AR32: -1591 | AS32: 183 | AT32: =(BS!AT33-BS!AS33)+(BS!AT25-BS!AS25) -> 10917.726 | AU32: =(BS!AU33-BS!AT33)+(BS!AU25-BS!AT25) -> 2159.0827 | AV32: =SUM(AR32:AU32) -> 11668.809 | AW32: =(BS!AW33-BS!AV33)+(BS!AW25-BS!AV25) -> 750.35253 | AX32: =(BS!AX33-BS!AW33)+(BS!AX25-BS!AW25) -> 1277.0613 | AY32: =(BS!AY33-BS!AX33)+(BS!AY25-BS!AX25) -> -450.51149 | AZ32: =(BS!AZ33-BS!AY33)+(BS!AZ25-BS!AY25) -> 2676.4019 | BA32: =SUM(AW32:AZ32) -> 4253.3043
B33: Cash Flow from Operating Activites | D33: =SUM(D7:D32) -> -3660.7337 | E33: =SUM(E7:E32) -> -2124.6601 | F33: =SUM(F7:F32) -> -3341.4828 | G33: =SUM(G7:G32) -> 771.19738 | H33: =SUM(H7:H32) -> -8355.6793 | I33: =SUM(I7:I32) -> -2255.2963 | J33: =SUM(J7:J32) -> 76.17186 | K33: =SUM(K7:K32) -> 102.40804 | ... BA33: =SUM(BA7:BA32) -> 357604.69
C34: OCF Margins | D34: -0.27938924 | E34: -0.14012027 | F34: -0.19543459 | G34: 0.039547217 | H34: =H33/IS!H17 -> -0.12881819 | I34: =I33/IS!I17 -> -0.10057453 | J34: =J33/IS!J17 -> 0.002929839 | K34: =K33/IS!K17 -> 0.0036258738 | L34: =L33/IS!L17 -> -0.059117798 | M34: =M33/IS!M17 -> -0.03645404 | N34: =N33/IS!N17 -> -0.067661049 | O34: =O33/IS!O17 -> -0.045266121 | ... BA34: =BA33/IS!BA17 -> 0.19573433
O35: =O33-J33 -> -1845.1719
B36: Investing Activites
C37: Cash paid for acquisition | H37: =SUM(D37:G37) -> 0 | M37: =SUM(I37:L37) -> 0 | R37: =SUM(N37:Q37) -> 0 | V37: -556090 | W37: =SUM(S37:V37) -> -556090 | X37: -144452 | Y37: -89 | AB37: =SUM(X37:AA37) -> -144541 | AD37: -28902 | AG37: =SUM(AC37:AF37) -> -28902 | AL37: =SUM(AH37:AK37) -> 0 | AQ37: =SUM(AM37:AP37) -> 0 | AV37: =SUM(AR37:AU37) -> 0 | BA37: =SUM(AW37:AZ37) -> 0
C38: Purchases of corporate and customer fund short-term investments | D38: -256720 | E38: -152202 | F38: -151413 | G38: -166453 | H38: =SUM(D38:G38) -> -726788 | I38: -191198 | J38: -224128 | K38: -218079 | L38: -197217 | M38: =SUM(I38:L38) -> -830622 | N38: -189204 | O38: -225444 | P38: -416046 | Q38: -257917 | R38: =SUM(N38:Q38) -> -1088611 | S38: -343345 | T38: -358097 | U38: -784583 | V38: -584271 | W38: =SUM(S38:V38) -> -2070296 | X38: -608552 | Y38: -843867 | Z38: -723708 | AA38: -625570 | AB38: =SUM(X38:AA38) -> -2801697 | AC38: -859911 | AD38: -781282 | AE38: -753325 | AF38: -349245 | AG38: =SUM(AC38:AF38) -> -2743763 | AH38: -399588 | AI38: -590652 | AJ38: -1052609 | AK38: -639810 | AL38: =SUM(AH38:AK38) -> -2682659 | AM38: -637992 | AN38: -572575 | AO38: -1104408 | AP38: -532761 | AQ38: =SUM(AM38:AP38) -> -2847736 | AR38: -372347 | AS38: -310786 | AV38: =SUM(AR38:AU38) -> -683133 | BA38: =SUM(AW38:AZ38) -> 0
C39: Proceeds from maturities of corporate and customer fund short-term investments | D39: 0 | E39: 14842 | F39: 122894 | G39: 153092 | H39: =SUM(D39:G39) -> 290828 | I39: 206434 | J39: 176550 | K39: 167830 | L39: 143489 | M39: =SUM(I39:L39) -> 694303 | N39: 255171 | O39: 152065 | P39: 189075 | Q39: 209689 | R39: =SUM(N39:Q39) -> 806000 | S39: 244332 | T39: 256827 | U39: 329774 | V39: 273599 | W39: =SUM(S39:V39) -> 1104532 | X39: 318907 | Y39: 348947 | Z39: 640796 | AA39: 593824 | AB39: =SUM(X39:AA39) -> 1902474 | AC39: 838099 | AD39: 845314 | AE39: 827416 | AF39: 773132 | AG39: =SUM(AC39:AF39) -> 3283961 | AH39: 757169 | AI39: 524336 | AJ39: 575715 | AK39: 654887 | AL39: =SUM(AH39:AK39) -> 2512107 | AM39: 563677 | AN39: 539073 | AO39: 624617 | AP39: 487261 | AQ39: =SUM(AM39:AP39) -> 2214628 | AR39: 328254 | AS39: 453200 | AV39: =SUM(AR39:AU39) -> 781454 | BA39: =SUM(AW39:AZ39) -> 0
C40: Purchases of loans held for investment | H40: =SUM(D40:G40) -> 0 | M40: =SUM(I40:L40) -> 0 | R40: =SUM(N40:Q40) -> 0 | W40: =SUM(S40:V40) -> 0 | AB40: =SUM(X40:AA40) -> 0 | AG40: =SUM(AC40:AF40) -> 0 | AH40: -32756 | AI40: -77357 | AJ40: -108830 | AK40: -140711 | AL40: =SUM(AH40:AK40) -> -359654 | AM40: -181686 | AN40: -198987 | AO40: -196212 | AP40: -222041 | AQ40: =SUM(AM40:AP40) -> -798926 | AR40: -241680 | AS40: -268604 | AV40: =SUM(AR40:AU40) -> -510284 | BA40: =SUM(AW40:AZ40) -> 0
C41: Principal repayments of loans held | H41: =SUM(D41:G41) -> 0 | M41: =SUM(I41:L41) -> 0 | R41: =SUM(N41:Q41) -> 0 | W41: =SUM(S41:V41) -> 0 | AB41: =SUM(X41:AA41) -> 0 | AG41: =SUM(AC41:AF41) -> 0 | AH41: 25330 | AI41: 68970 | AJ41: 97561 | AK41: 134311 | AL41: =SUM(AH41:AK41) -> 326172 | AM41: 171987 | AN41: 197462 | AO41: 194846 | AP41: 223218 | AQ41: =SUM(AM41:AP41) -> 787513 | AR41: 244471 | AS41: 271096 | AV41: =SUM(AR41:AU41) -> 515567 | BA41: =SUM(AW41:AZ41) -> 0
C42: Proceeds from sale of corporate and customer fund short-term investments | D42: 0 | E42: 10003 | F42: 4995 | G42: 1500 | H42: =SUM(D42:G42) -> 16498 | I42: 0 | J42: 29162 | K42: 25553 | L42: 0 | M42: =SUM(I42:L42) -> 54715 | N42: 10761 | O42: 11964 | P42: 2612 | Q42: 20822 | R42: =SUM(N42:Q42) -> 46159 | S42: =33286-1522 -> 31764 | T42: 2000 | U42: 83786 | V42: 23593 | W42: =SUM(S42:V42) -> 141143 | X42: 17234 | Y42: 27510 | Z42: 6000 | AA42: 5000 | AB42: =SUM(X42:AA42) -> 55744 | AD42: 5088 | AE42: 6519 | AF42: 0 | AG42: =SUM(AC42:AF42) -> 11607 | AJ42: 1539 | AL42: =SUM(AH42:AK42) -> 1539 | AQ42: =SUM(AM42:AP42) -> 0 | AV42: =SUM(AR42:AU42) -> 0 | BA42: =SUM(AW42:AZ42) -> 0
C43: Decrease (increase) in restricted cash and cash equivalents and other receivables included in funds held for customers | D43: 198523 | E43: -104891 | F43: 109211 | G43: -116967 | H43: =SUM(D43:G43) -> 85876 | I43: -118000 | J43: -180650 | K43: 57799 | L43: -92497 | M43: =SUM(I43:L43) -> -333348 | N43: -213249 | O43: 39519 | P43: 276228 | Q43: 5642 | R43: =SUM(N43:Q43) -> 108140 | T43: 1541 | U43: -9091 | V43: -1720 | W43: =SUM(S43:V43) -> -9270 | X43: -946 | Y43: -7289 | Z43: -5312 | AA43: 0 | AB43: =SUM(X43:AA43) -> -13547 | AC43: 0 | AE43: 0 | AF43: 0 | AG43: =SUM(AC43:AF43) -> 0 | AJ43: 0 | AL43: =SUM(AH43:AK43) -> 0 | AQ43: =SUM(AM43:AP43) -> 0 | AV43: =SUM(AR43:AU43) -> 0 | BA43: =SUM(AW43:AZ43) -> 0
C44: Increase in card receivable acquired | H44: =SUM(D44:G44) -> 0 | M44: =SUM(I44:L44) -> 0 | R44: =SUM(N44:Q44) -> 0 | V44: -15703 | W44: =SUM(S44:V44) -> -15703 | X44: -31717 | Y44: -37507 | Z44: -20685 | AA44: -40436 | AB44: =SUM(X44:AA44) -> -130345 | AC44: -107443 | AD44: 6090 | AE44: -95936 | AF44: -36011 | AG44: =SUM(AC44:AF44) -> -233300 | AH44: -42333 | AI44: 29991 | AJ44: -127508 | AK44: -45636 | AL44: =SUM(AH44:AK44) -> -185486 | AM44: -47968 | AN44: 54918 | AO44: -153338 | AP44: 16949 | AQ44: =SUM(AM44:AP44) -> -129439 | AR44: -52826 | AS44: 6918 | AV44: =SUM(AR44:AU44) -> -45908 | BA44: =SUM(AW44:AZ44) -> 0
C45: Purchase of property and equipment | D45: -222 | E45: -540 | F45: -44 | G45: -507 | H45: =SUM(D45:G45) -> -1313 | I45: -834 | J45: -737 | K45: -688 | L45: -484 | M45: =SUM(I45:L45) -> -2743 | N45: -1946 | O45: -1026 | P45: -2764 | Q45: -5701 | R45: =SUM(N45:Q45) -> -11437 | S45: -5894 | T45: -7742 | U45: -3426 | V45: -1840 | W45: =SUM(S45:V45) -> -18902 | X45: -1404 | Y45: -1063 | Z45: -1291 | AA45: -1619 | AB45: =SUM(X45:AA45) -> -5377 | AC45: -1376 | AD45: -1785 | AE45: -3338 | AF45: -1090 | AG45: =SUM(AC45:AF45) -> -7589 | AH45: -403 | AI45: -352 | AJ45: -16 | AK45: -205 | AL45: =SUM(AH45:AK45) -> -976 | AM45: -517 | AN45: -2868 | AO45: -1147 | AP45: -2789 | AQ45: =SUM(AM45:AP45) -> -7321 | AR45: -1299 | AS45: -1492 | AT45: -1200 | AU45: -1200 | AV45: =SUM(AR45:AU45) -> -5191 | AW45: -1200 | AX45: -1200 | AY45: -1200 | AZ45: -1200 | BA45: =SUM(AW45:AZ45) -> -4800
C46: Capitalization of internal-use software costs | D46: -261 | E46: -235 | F46: -119.1822 | G46: -117.8178 | H46: =SUM(D46:G46) -> -733 | I46: -421 | J46: -412 | K46: -482 | L46: -241 | M46: =SUM(I46:L46) -> -1556 | N46: -215 | O46: -125 | P46: -149 | Q46: -150 | R46: =SUM(N46:Q46) -> -639 | S46: -314 | T46: -346 | U46: -378 | V46: -1266 | W46: =SUM(S46:V46) -> -2304 | X46: -2942 | Y46: -2081 | Z46: -2386 | AA46: -2850 | AB46: =SUM(X46:AA46) -> -10259 | AC46: -4764 | AD46: -5746 | AE46: -6721 | AF46: -6383 | AG46: =SUM(AC46:AF46) -> -23614 | AH46: -5645 | AI46: -5117 | AJ46: -3833 | AK46: -5322 | AL46: =SUM(AH46:AK46) -> -19917 | AM46: -7039 | AN46: -6720 | AO46: -7460 | AP46: -12548 | AQ46: =SUM(AM46:AP46) -> -33767 | AR46: -13294 | AS46: -12692 | AT46: -6500 | AU46: -6500 | AV46: =SUM(AR46:AU46) -> -38986 | AW46: -6500 | AX46: -6500 | AY46: -6500 | AZ46: -6500 | BA46: =SUM(AW46:AZ46) -> -26000
C47: Proceeds from beneficial interest | H47: =SUM(D47:G47) -> 0 | M47: =SUM(I47:L47) -> 0 | R47: =SUM(N47:Q47) -> 0 | W47: =SUM(S47:V47) -> 0 | AA47: 6699 | AB47: =SUM(X47:AA47) -> 6699 | AC47: 2080 | AG47: =SUM(AC47:AF47) -> 2080 | AL47: =SUM(AH47:AK47) -> 0 | AQ47: =SUM(AM47:AP47) -> 0 | AV47: =SUM(AR47:AU47) -> 0 | BA47: =SUM(AW47:AZ47) -> 0
C48: Other | H48: =SUM(D48:G48) -> 0 | M48: =SUM(I48:L48) -> 0 | R48: =SUM(N48:Q48) -> 0 | W48: =SUM(S48:V48) -> 0 | AB48: =SUM(X48:AA48) -> 0 | AF48: -1194 | AG48: =SUM(AC48:AF48) -> -1194 | AK48: -500 | AL48: =SUM(AH48:AK48) -> -500 | AN48: -461 | AO48: -1003 | AP48: -878 | AQ48: =SUM(AM48:AP48) -> -2342 | AS48: -1066 | AV48: =SUM(AR48:AU48) -> -1066 | BA48: =SUM(AW48:AZ48) -> 0
C49: Net decrease (increase) in restricted cash | D49: 221 | E49: 0 | F49: -10.03819 | G49: 0.03819 | H49: =SUM(D49:G49) -> 211 | I49: -0.00507 | J49: 0 | K49: -550 | L49: 0.00507 | M49: =SUM(I49:L49) -> -550 | N49: 550 | R49: =SUM(N49:Q49) -> 550 | W49: =SUM(S49:V49) -> 0 | AB49: =SUM(X49:AA49) -> 0 | AG49: =SUM(AC49:AF49) -> 0
B50: Cash Used in Investing Activites | D50: =SUM(D38:D49) -> -58459 | E50: =SUM(E38:E49) -> -233023 | F50: =SUM(F38:F49) -> 85513.78 | G50: =SUM(G38:G49) -> -129452.78 | H50: =SUM(H38:H49) -> -335421 | I50: =SUM(I38:I49) -> -104019.01 | J50: =SUM(J38:J49) -> -200215 | K50: =SUM(K38:K49) -> 31383 | ... U50: =SUM(U38:U49) -> -383918 | V50: =SUM(V37:V49) -> -863698 | W50: =SUM(W37:W49) -> -1426890 | X50: =SUM(X37:X49) -> -453872 | Y50: =SUM(Y37:Y49) -> -515439 | Z50: =SUM(Z37:Z49) -> -106586 | AA50: =SUM(AA37:AA49) -> -64952 | AB50: =SUM(AB37:AB49) -> -1140849 | AC50: =SUM(AC37:AC49) -> -133315 | AD50: =SUM(AD37:AD49) -> 38777 | AE50: =SUM(AE38:AE49) -> -25385 | AF50: =SUM(AF37:AF49) -> 379209 | AG50: =SUM(AG37:AG49) -> 259286 | AH50: =SUM(AH37:AH49) -> 301774 | AI50: =SUM(AI37:AI49) -> -50181 | AJ50: =SUM(AJ37:AJ49) -> -617981 | AK50: =SUM(AK37:AK49) -> -42986 | AL50: =SUM(AL37:AL49) -> -409374 | AM50: =SUM(AM37:AM49) -> -139538 | ... BA50: =SUM(BA37:BA49) -> -30800
B52: Free Cash Flow | D52: =D33+D45+D46 -> -4143.7337 | E52: =E33+E45+E46 -> -2899.6601 | F52: =F33+F45+F46 -> -3504.665 | G52: =G33+G45+G46 -> 146.37958 | H52: =SUM(D52:G52) -> -10401.679 | I52: =I33+I45+I46 -> -3510.2963 | J52: =J33+J45+J46 -> -1072.8281 | K52: =K33+K45+K46 -> -1067.592 | L52: =L33+L45+L46 -> -2598.1077 | M52: =SUM(I52:L52) -> -8248.8241 | N52: =N33+N45+N46 -> -4541.2805 | O52: =O33+O45+O46 -> -2920 | P52: =P33+P45+P46 -> -2091 | Q52: =Q33+Q45+Q46 -> -6954 | R52: =SUM(N52:Q52) -> -16506.28 | S52: =S33+S45+S46 -> -8364 | T52: =T33+T45+T46 -> -17596 | U52: =U33+U45+U46 -> -5384 | V52: =V33+V45+V46 -> 14680 | W52: =SUM(S52:V52) -> -16664 | X52: =X33+X45+X46 -> -25480 | Y52: =Y33+Y45+Y46 -> -16074 | Z52: =Z33+Z45+Z46 -> 22768 | AA52: =AA33+AA45+AA46 -> -14943 | AB52: =SUM(X52:AA52) -> -33729 | AC52: =AC33+AC45+AC46 -> 12012 | AD52: =AD33+AD45+AD46 -> 47699 | AE52: =AE33+AE45+AE46 -> 23972 | AF52: =AF33+AF45+AF46 -> 72882 | AG52: =SUM(AC52:AF52) -> 156565 | AH52: =AH33+AH45+AH46 -> 47613 | AI52: =AI33+AI45+AI46 -> 74213 | AJ52: =AJ33+AJ45+AJ46 -> 62960 | AK52: =AK33+AK45+AK46 -> 73093 | AL52: =SUM(AH52:AK52) -> 257879 | AM52: =AM33+AM45+AM46 -> 81026 | AN52: =AN33+AN45+AN46 -> 69128 | AO52: =AO33+AO45+AO46 -> 90923 | AP52: =AP33+AP45+AP46 -> 68478 | AQ52: =SUM(AM52:AP52) -> 309555 | AR52: =AR33+AR45+AR46 -> 82262 | AS52: =AS33+AS45+AS46 -> 91133 | AT52: =AT33+AT45+AT46 -> -28172.672 | AU52: =AU33+AU45+AU46 -> 92215.992 | AV52: =SUM(AR52:AU52) -> 237438.32 | AW52: =AW33+AW45+AW46 -> 59457.846 | AX52: =AX33+AX45+AX46 -> 91449.572 | AY52: =AY33+AY45+AY46 -> 75073.371 | AZ52: =AZ33+AZ45+AZ46 -> 100823.9 | BA52: =SUM(AW52:AZ52) -> 326804.69
C53: FCF Margin | D53: =D52/IS!D17 -> -0.31625207 | E53: =E52/IS!E17 -> -0.19123113 | F53: =F52/IS!F17 -> -0.20497869 | G53: =G52/IS!G17 -> 0.0075063857 | H53: =H52/IS!H17 -> -0.16036105 | I53: =I52/IS!I17 -> -0.15654103 | J53: =J52/IS!J17 -> -0.041264763 | K53: =K52/IS!K17 -> -0.037799315 | ... BA53: =BA52/IS!BA17 -> 0.178876
B55: Financing Activities
C56: Payments for repurchase of convertible senior note | AJ56: -710931 | AK56: -222256 | AL56: =SUM(AH56:AK56) -> -933187 | AN56: -539403 | AQ56: =SUM(AM56:AP56) -> -539403 | AS56: -33463 | AV56: =SUM(AR56:AU56) -> -33463 | BA56: =SUM(AW56:AZ56) -> 0
C57: Customer funds deposit liability | D57: 58197 | E57: 193573 | F57: -116256 | G57: 128157 | H57: =SUM(D57:G57) -> 263671 | I57: 98723 | J57: 199090 | K57: -32916 | L57: 149396 | M57: =SUM(I57:L57) -> 414293 | N57: 137186 | O57: 25271 | P57: -138211 | Q57: 290698 | R57: =SUM(N57:Q57) -> 314944 | S57: 24653 | T57: 548777 | U57: -287840 | V57: 278758 | W57: =SUM(S57:V57) -> 564348 | X57: 223923 | Y57: 947874 | Z57: -336855 | AA57: 149846 | AB57: =SUM(X57:AA57) -> 984788 | AC57: -14549 | AD57: 347210 | AE57: -357689 | AF57: 250482 | AG57: =SUM(AC57:AF57) -> 225454 | AH57: =+-91190-13979 -> -105169 | AI57: 390960 | AJ57: -144394 | AK57: 198588 | AL57: =SUM(AH57:AK57) -> 339985 | AM57: 78512 | AN57: -25781 | AO57: -114587 | AP57: 380539 | AQ57: =SUM(AM57:AP57) -> 318683 | AR57: -68715 | AS57: 51771 | AV57: =SUM(AR57:AU57) -> -16944 | BA57: =SUM(AW57:AZ57) -> 0
C58: Net proceeds from issuance of convertible preferred stock | D58: 53361 | E58: 2448 | F58: 0 | G58: -4 | H58: =SUM(D58:G58) -> 55805 | I58: 0 | J58: 69801 | K58: 18074 | L58: -2715 | M58: =SUM(I58:L58) -> 85160 | N58: 0.274 | R58: =SUM(N58:Q58) -> 0.274 | T58: 1129603 | U58: -224 | W58: =SUM(S58:V58) -> 1129379 | X58: 562704 | Y58: -2629 | AB58: =SUM(X58:AA58) -> 560075 | AG58: =SUM(AC58:AF58) -> 0 | AL58: =SUM(AH58:AK58) -> 0 | AN58: =1400000-23100 -> 1376900 | AO58: -906 | AQ58: =SUM(AM58:AP58) -> 1375994 | AV58: =SUM(AR58:AU58) -> 0 | BA58: =SUM(AW58:AZ58) -> 0
C59: Repurchase of common stock | H59: =SUM(D59:G59) -> 0 | M59: =SUM(I59:L59) -> 0 | R59: =SUM(N59:Q59) -> 0 | W59: =SUM(S59:V59) -> 0 | AB59: =SUM(X59:AA59) -> 0 | AE59: -24001 | AF59: -63614 | AG59: =SUM(AC59:AF59) -> -87615 | AH59: -12061 | AI59: -199841 | AL59: =SUM(AH59:AK59) -> -211902 | AM59: -200002 | AN59: -199999 | AP59: -30001 | AQ59: =SUM(AM59:AP59) -> -430002 | AR59: -83145 | AS59: -132651 | AV59: =SUM(AR59:AU59) -> -215796 | BA59: =SUM(AW59:AZ59) -> 0
C60: Purchase of capped calls | H60: =SUM(D60:G60) -> 0 | M60: =SUM(I60:L60) -> 0 | R60: =SUM(N60:Q60) -> 0 | T60: -87860 | W60: =SUM(S60:V60) -> -87860 | X60: -37893 | AB60: =SUM(X60:AA60) -> -37893 | AG60: =SUM(AC60:AF60) -> 0 | AJ60: 10252 | AK60: 1190 | AL60: =SUM(AH60:AK60) -> 11442 | AN60: -92960 | AQ60: =SUM(AM60:AP60) -> -92960 | AV60: =SUM(AR60:AU60) -> 0 | BA60: =SUM(AW60:AZ60) -> 0
C61: Initial public offering | H61: =SUM(D61:G61) -> 0 | M61: =SUM(I61:L61) -> 0 | O61: 227439 | P61: -1021 | R61: =SUM(N61:Q61) -> 226418 | W61: =SUM(S61:V61) -> 0 | Z61: -30 | AB61: =SUM(X61:AA61) -> -30 | AG61: =SUM(AC61:AF61) -> 0 | AL61: =SUM(AH61:AK61) -> 0 | AQ61: =SUM(AM61:AP61) -> 0 | AV61: =SUM(AR61:AU61) -> 0 | BA61: =SUM(AW61:AZ61) -> 0
C62: Net proceeds from issuance of common stock (including exercise of stock options) | D62: 215 | E62: 81 | F62: 110 | G62: 287 | H62: =SUM(D62:G62) -> 693 | I62: 458.31789 | J62: 491 | K62: 367 | L62: 385.68211 | M62: =SUM(I62:L62) -> 1702 | N62: 294 | O62: 607 | P62: 845 | Q62: 308176 | R62: =SUM(N62:Q62) -> 309922 | S62: =8962+4327 -> 13289 | T62: 8480 | U62: 5592 | W62: =SUM(S62:V62) -> 27361 | X62: 1341597 | Y62: -445 | Z62: 6332 | AA62: 4908 | AB62: =SUM(X62:AA62) -> 1352392 | AG62: =SUM(AC62:AF62) -> 0 | AL62: =SUM(AH62:AK62) -> 0 | AQ62: =SUM(AM62:AP62) -> 0 | AV62: =SUM(AR62:AU62) -> 0 | BA62: =SUM(AW62:AZ62) -> 0
C63: Exercise of stock warrants | H63: =SUM(D63:G63) -> 0 | M63: =SUM(I63:L63) -> 0 | O63: 144 | Q63: 10486 | R63: =SUM(N63:Q63) -> 10630 | U63: 4537 | V63: 5175 | W63: =SUM(S63:V63) -> 9712 | X63: 8336 | AB63: =SUM(X63:AA63) -> 8336 | AC63: 3901 | AD63: 4316 | AE63: 2643 | AF63: 3012 | AG63: =SUM(AC63:AF63) -> 13872 | AH63: 2946 | AI63: 2106 | AJ63: 1473 | AK63: 1589 | AL63: =SUM(AH63:AK63) -> 8114 | AM63: 1017 | AN63: 1235 | AO63: 520 | AP63: 929 | AQ63: =SUM(AM63:AP63) -> 3701 | AR63: 276 | AS63: 558 | AV63: =SUM(AR63:AU63) -> 834 | BA63: =SUM(AW63:AZ63) -> 0
C64: Proceeds from issuance of common stock under ESPP | H64: =SUM(D64:G64) -> 0 | M64: =SUM(I64:L64) -> 0 | R64: =SUM(N64:Q64) -> 0 | W64: =SUM(S64:V64) -> 0 | X64: 5726 | Y64: 14448 | Z64: 7123 | AB64: =SUM(X64:AA64) -> 27297 | AG64: =SUM(AC64:AF64) -> 0 | AJ64: 8649 | AL64: =SUM(AH64:AK64) -> 8649 | AM64: 5302 | AP64: 6251 | AQ64: =SUM(AM64:AP64) -> 11553 | AS64: 4648 | AV64: =SUM(AR64:AU64) -> 4648 | BA64: =SUM(AW64:AZ64) -> 0
C65: Tax withholdings relate to net share settlement | H65: =SUM(D65:G65) -> 0 | M65: =SUM(I65:L65) -> 0 | R65: =SUM(N65:Q65) -> 0 | W65: =SUM(S65:V65) -> 0 | AB65: =SUM(X65:AA65) -> 0 | AG65: =SUM(AC65:AF65) -> 0 | AJ65: -1681 | AK65: -2181 | AL65: =SUM(AH65:AK65) -> -3862 | AM65: -1304 | AN65: -3410 | AO65: -1702 | AP65: -1424 | AQ65: =SUM(AM65:AP65) -> -7840 | AR65: -14080 | AS65: -15397 | AV65: =SUM(AR65:AU65) -> -29477 | BA65: =SUM(AW65:AZ65) -> 0
C66: Proceed from line of credit offerings | H66: =SUM(D66:G66) -> 0 | M66: =SUM(I66:L66) -> 0 | R66: =SUM(N66:Q66) -> 0 | W66: =SUM(S66:V66) -> 0 | AB66: =SUM(X66:AA66) -> 0 | AC66: 8494 | AD66: 37500 | AE66: 9385 | AF66: 0 | AG66: =SUM(AC66:AF66) -> 55379 | AH66: 7846 | AI66: 0 | AJ66: 45000 | AL66: =SUM(AH66:AK66) -> 52846 | AQ66: =SUM(AM66:AP66) -> 0 | AR66: 150000 | AV66: =SUM(AR66:AU66) -> 150000 | BA66: =SUM(AW66:AZ66) -> 0
C67: Increase in prepaid card deposits | H67: =SUM(D67:G67) -> 0 | M67: =SUM(I67:L67) -> 0 | R67: =SUM(N67:Q67) -> 0 | W67: =SUM(S67:V67) -> 0 | AB67: =SUM(X67:AA67) -> 0 | AF67: 5520 | AG67: =SUM(AC67:AF67) -> 5520 | AJ67: -4292 | AK67: 2875 | AL67: =SUM(AH67:AK67) -> -1417 | AM67: 11322 | AN67: 21049 | AO67: 11102 | AP67: -14956 | AQ67: =SUM(AM67:AP67) -> 28517 | AR67: 16764 | AS67: 12330 | AV67: =SUM(AR67:AU67) -> 29094 | BA67: =SUM(AW67:AZ67) -> 0
C68: Payments on LOC and bank bo | H68: =SUM(D68:G68) -> 0 | M68: =SUM(I68:L68) -> 0 | R68: =SUM(N68:Q68) -> 0 | W68: =SUM(S68:V68) -> 0 | AB68: =SUM(X68:AA68) -> 0 | AG68: =SUM(AC68:AF68) -> 0 | AL68: =SUM(AH68:AK68) -> 0 | AQ68: =SUM(AM68:AP68) -> 0 | AV68: =SUM(AR68:AU68) -> 0 | BA68: =SUM(AW68:AZ68) -> 0
C69: Net proceeds from (payments on) bank borrowings | D69: -216 | E69: 6329.4444 | F69: 0 | G69: 0 | H69: =SUM(D69:G69) -> 6113.4444 | I69: 0 | J69: -417 | K69: -416 | L69: -8667 | M69: =SUM(I69:L69) -> -9500 | N69: -874 | P69: 2300 | R69: =SUM(N69:Q69) -> 1426 | S69: -664 | U69: -2300 | W69: =SUM(S69:V69) -> -2964 | AA69: =+-40000+37500 -> -2500 | AB69: =SUM(X69:AA69) -> -2500 | AE69: 22500 | AG69: =SUM(AC69:AF69) -> 22500 | AL69: =SUM(AH69:AK69) -> 0 | AP69: -1721 | AQ69: =SUM(AM69:AP69) -> -1721 | AV69: =SUM(AR69:AU69) -> 0 | BA69: =SUM(AW69:AZ69) -> 0
C70: Payment of deferred offering and debt issuance costs | D70: 0 | E70: 0 | F70: 0 | G70: 0 | H70: =SUM(D70:G70) -> 0 | I70: 0 | J70: 0 | K70: 0 | L70: 0 | M70: =SUM(I70:L70) -> 0 | N70: -151 | Q70: -63 | R70: =SUM(N70:Q70) -> -214 | W70: =SUM(S70:V70) -> 0 | AB70: =SUM(X70:AA70) -> 0 | AG70: =SUM(AC70:AF70) -> 0 | AL70: =SUM(AH70:AK70) -> 0 | AQ70: =SUM(AM70:AP70) -> 0 | AV70: =SUM(AR70:AU70) -> 0 | BA70: =SUM(AW70:AZ70) -> 0
C71: Other | H71: =SUM(D71:G71) -> 0 | M71: =SUM(I71:L71) -> 0 | R71: =SUM(N71:Q71) -> 0 | V71: -393 | W71: =SUM(S71:V71) -> -393 | X71: -282 | Y71: -69 | AB71: =SUM(X71:AA71) -> -351 | AG71: =SUM(AC71:AF71) -> 0 | AH71: -5471 | AI71: -2505 | AJ71: -5291 | AL71: =SUM(AH71:AK71) -> -13267 | AQ71: =SUM(AM71:AP71) -> 0 | AS71: -812 | AV71: =SUM(AR71:AU71) -> -812 | BA71: =SUM(AW71:AZ71) -> 0
B72: Cash used in Financing Activites | D72: =SUM(D57:D70) -> 111557 | E72: =SUM(E57:E70) -> 202431.44 | F72: =SUM(F57:F70) -> -116146 | G72: =SUM(G57:G70) -> 128440 | H72: =SUM(H57:H70) -> 326282.44 | I72: =SUM(I57:I70) -> 99181.318 | J72: =SUM(J57:J70) -> 268965 | K72: =SUM(K57:K70) -> -14891 | ... U72: =SUM(U57:U70) -> -280235 | V72: =SUM(V57:V71) -> 283540 | W72: =SUM(W57:W70) -> 1639976 | X72: =SUM(X57:X71) -> 2104111 | Y72: =SUM(Y57:Y71) -> 959179 | Z72: =SUM(Z57:Z70) -> -323430 | AA72: =SUM(AA57:AA70) -> 152254 | AB72: =SUM(AB57:AB70) -> 2892465 | AC72: =SUM(AC57:AC70) -> -2154 | AD72: =SUM(AD57:AD70) -> 389026 | AE72: =SUM(AE57:AE70) -> -347162 | AF72: =SUM(AF57:AF70) -> 195400 | AG72: =SUM(AG57:AG70) -> 235110 | AH72: =SUM(AH57:AH71) -> -111909 | AI72: =SUM(AI57:AI71) -> 190720 | AJ72: =SUM(AJ56:AJ71) -> -801215 | AK72: =SUM(AK56:AK70) -> -20195 | AL72: =SUM(AL56:AL71) -> -742599 | AM72: =SUM(AM57:AM71) -> -105153 | AN72: =SUM(AN56:AN71) -> 537631 | AO72: =SUM(AO56:AO71) -> -105573 | AP72: =SUM(AP56:AP70) -> 339617 | AQ72: =SUM(AQ56:AQ71) -> 666522 | AR72: =SUM(AR57:AR71) -> 1100 | AS72: =SUM(AS56:AS71) -> -113016 | AT72: =SUM(AT56:AT71) -> 0 | AU72: =SUM(AU56:AU71) -> 0 | AV72: =SUM(AV56:AV71) -> -111916 | AW72: =SUM(AW56:AW71) -> 0 | AX72: =SUM(AX56:AX71) -> 0 | AY72: =SUM(AY56:AY71) -> 0 | AZ72: =SUM(AZ56:AZ71) -> 0 | BA72: =SUM(BA56:BA71) -> 0
B74: Effect of exchange rates | AA74: -149 | AB74: =SUM(X74:AA74) -> -149 | AC74: -277 | AD74: 459 | AE74: -170 | AF74: -51 | AG74: =SUM(AC74:AF74) -> -39 | AH74: -180 | AI74: 173 | AJ74: -390 | AK74: 157 | AL74: =SUM(AH74:AK74) -> -240 | AM74: -127 | AN74: -645 | AO74: 591 | AP74: -109 | AQ74: =SUM(AM74:AP74) -> -290 | AR74: 75 | AS74: -2 | AV74: =SUM(AR74:AU74) -> 73 | BA74: =SUM(AW74:AZ74) -> 0
B76: Net change in cash & cash equivalents | D76: =D33+D50+D72 -> 49437.266 | E76: =E33+E50+E72 -> -32716.216 | F76: =F33+F50+F72 -> -33973.703 | G76: =G33+G50+G72 -> -241.58223 | H76: =H33+H50+H72 -> -17494.235 | I76: =I33+I50+I72 -> -7092.9835 | J76: =J33+J50+J72 -> 68826.172 | K76: =K33+K50+K72 -> 16594.408 | ... W76: =W33+W50+W72 -> 217628 | X76: =X33+X50+X72+X74 -> 1629105 | Y76: =Y33+Y50+Y72+Y74 -> 430810 | Z76: =Z33+Z50+Z72+Z74 -> -403571 | AA76: =AA33+AA50+AA72+AA74 -> 76679 | AB76: =AB33+AB50+AB72+AB74 -> 1735320 | AC76: =AC33+AC50+AC72+AC74 -> -117594 | AD76: =AD33+AD50+AD72+AD74 -> 483492 | AE76: =AE33+AE50+AE72+AE74 -> -338686 | ... BA76: =BA33+BA50+BA72+BA74 -> 326804.69
B78: Beginning cash & cash equivalents | D78: 39896 | E78: =D79 -> 89333.266 | F78: =E79 -> 56617.051 | G78: =F79 -> 22643.347 | H78: =D78 -> 39896 | I78: =G79 -> 22401.765 | J78: =I79 -> 15308.782 | K78: =J79 -> 84134.954 | L78: =K79 -> 100729.36 | M78: =H79 -> 22401.765 | N78: =L79 -> 90305.941 | O78: =N79 -> 86248.935 | P78: =O79 -> 314893.93 | Q78: =P79 -> 228584.93 | R78: =M79 -> 90305.941 | S78: =Q79 -> 1592377 | T78: =S79 -> 1554042 | U78: =T79 -> 3037717 | V78: =U79 -> 2371984 | W78: =R79 -> 1592377 | X78: =V79 -> 1809612 | Y78: =X79 -> 3438717 | Z78: =Y79 -> 3869527 | AA78: =Z79 -> 3465956 | AB78: =W79 -> 1810005 | AC78: =AA79 -> 3542715 | AD78: =AC79 -> 3425121 | AE78: =AD79 -> 3908613 | AF78: =AE79 -> 3569927 | AG78: =AB79 -> 3542715 | AH78: =AF79 -> 4224840 | AI78: =AH79 -> 4468186 | AJ78: =AI79 -> 4688580 | AK78: =AJ79 -> 3335803 | AL78: =AG79 -> 4224840 | AM78: =AK79 -> 3351399 | AN78: =AM79 -> 3195163 | AO78: =AN79 -> 3820707 | AP78: =AO79 -> 3171150 | AQ78: =AL79 -> 3351399 | AR78: =AP79 -> 3550884 | AS78: =AR79 -> 3540193 | AT78: =AS79 -> 3669066 | AU78: =AT79 -> 3640893.3 | AV78: =AQ79 -> 3550884 | AW78: =AU79 -> 3733109.3 | AX78: =AW79 -> 3792567.2 | AY78: =AX79 -> 3884016.7 | AZ78: =AY79 -> 3959090.1 | BA78: =AV79 -> 3733109.3
B79: Ending cash & cash equivalents | D79: =D76+D78 -> 89333.266 | E79: =E76+E78 -> 56617.051 | F79: =F76+F78 -> 22643.347 | G79: =G76+G78 -> 22401.765 | H79: =H76+H78 -> 22401.765 | I79: =I76+I78 -> 15308.782 | J79: =J76+J78 -> 84134.954 | K79: =K76+K78 -> 100729.36 | ... P79: =P76+P78 -> 228584.93 | Q79: 1592377 | R79: 1592377 | S79: =S76+S78 -> 1554042 | T79: =T76+T78 -> 3037717 | U79: =U76+U78 -> 2371984 | V79: =V76+V78 -> 1809612 | W79: =W76+W78 -> 1810005 | X79: =X76+X78 -> 3438717 | Y79: =Y76+Y78 -> 3869527 | Z79: =Z76+Z78 -> 3465956 | AA79: 3542715 | AB79: 3542715 | AC79: =AC76+AC78 -> 3425121 | AD79: =AD76+AD78 -> 3908613 | AE79: =AE76+AE78 -> 3569927 | AF79: =AF76+AF78 -> 4224840 | AG79: =AG76+AG78 -> 4224840 | AH79: =AH76+AH78 -> 4468186 | AI79: =AI76+AI78 -> 4688580 | AJ79: =AJ76+AJ78 -> 3335803 | ... BA79: =BA76+BA78 -> 4059914
B80: Scott Berg, sberg@needhamco.com | AG80: Source: Company Reports and Needham & Company, LLC Estimates
B81: 763.350.4027
C83: Depreciation as a % of PPE | D83: =D11/BS!D$16 -> 0.12202353 | E83: =E11/BS!E$16 -> 0.11319506 | F83: =F11/BS!F$16 -> 0.14261377 | G83: =G11/BS!G$16 -> 0.11667274 | I83: =I11/BS!I$16 -> 0.12114014 | J83: =J11/BS!J$16 -> 0.12527445 | K83: =K11/BS!K$16 -> 0.12722715 | L83: =L11/BS!L$16 -> 0.11210168 | N83: =N11/BS!N$16 -> 0.12947774 | O83: =O11/BS!O$16 -> 0.14911463 | P83: =P11/BS!P$16 -> 0.089307461 | Q83: =Q11/BS!Q$16 -> 0.075869032 | S83: =S11/BS!S$16 -> 0.042562992 | T83: =T11/BS!T$16 -> 0.032676959 | U83: =U11/BS!U$16 -> 0.048078135 | V83: =V11/BS!V$16 -> 0.038873666 | X83: =X11/BS!X$16 -> 0.04669352 | Y83: =Y11/BS!Y$16 -> 0.05000854 | Z83: =Z11/BS!Z$16 -> 0.06000488 | AA83: =AA11/BS!AA$16 -> 0.043169255 | AC83: =AC11/BS!AC$16 -> 0.041047965 | AD83: =AD11/BS!AD$16 -> 0.036536327 | AE83: =AE11/BS!AE$16 -> 0.036480991 | AF83: =AF11/BS!AF$16 -> 0.041084302 | AH83: =AH11/BS!AH$16 -> 0.043590405 | AI83: =AI11/BS!AI$16 -> 0.037423334 | AJ83: =AJ11/BS!AJ$16 -> 0.036758305 | AK83: =AK11/BS!AK$16 -> 0.041699798 | AM83: =AM11/BS!AM$16 -> 0.035204852 | AN83: =AN11/BS!AN$16 -> 0.037155832 | AO83: =AO11/BS!AO$16 -> 0.030246955 | AP83: =AP11/BS!AP$16 -> 0.027098644 | AR83: =AR11/BS!AR$16 -> 0.029769613 | AS83: =AS11/BS!AS$16 -> 0.059947413 | AT83: 0.04 | AU83: 0.04 | AW83: 0.04 | AX83: 0.04 | AY83: 0.04 | AZ83: 0.04

Sheet Revenue Build
B2: Bill.com, Inc. (BILL)
B3: Bill AP/AR | D3: =D$104 -> 1Q18 | E3: =E$104 -> 2Q18 | F3: =F$104 -> 3Q18 | G3: =G$104 -> 4Q18 | H3: =H$104 -> 2018 | I3: =I$104 -> 1Q19 | J3: =J$104 -> 2Q19 | K3: =K$104 -> 3Q19 | ... BA3: =BA$104 -> 2027E
A4: x | B4: Customers | X4: =126800-23600+6200 -> 109400 | Y4: 111400 | Z4: 116700 | AA4: 121800 | AC4: 126900 | AD4: 130400 | AE4: 134100 | AF4: 139400 | AG4: =AF4 -> 139400 | AH4: 143100 | AI4: 143200 | AJ4: 146700 | AK4: 151200 | AL4: =AK4 -> 151200 | AM4: 156100 | AN4: 160600 | AO4: 164800 | AP4: 169500 | AQ4: =AP4 -> 169500 | AR4: 173500 | AS4: 177500 | AT4: =AS4+AT5 -> 181250 | AU4: =AT4+AU5 -> 185000 | AV4: =AU4 -> 185000 | AW4: =AU4+AW5 -> 188750 | AX4: =AW4+AX5 -> 192500 | AY4: =AX4+AY5 -> 196250 | AZ4: =AY4+AZ5 -> 200000 | BA4: =AZ4 -> 200000
C5: Quarterly Adds | Y5: =Y4-X4 -> 2000 | Z5: =Z4-Y4 -> 5300 | AA5: =AA4-Z4 -> 5100 | AC5: =AC4-AA4 -> 5100 | AD5: =AD4-AC4 -> 3500 | AE5: =AE4-AD4 -> 3700 | AF5: =AF4-AE4 -> 5300 | AG5: =SUM(AC5:AF5) -> 17600 | AH5: =AH4-AF4 -> 3700 | AI5: =AI4-AH4 -> 100 | AJ5: =AJ4-AI4 -> 3500 | AK5: =AK4-AJ4 -> 4500 | AL5: =SUM(AH5:AK5) -> 11800 | AM5: =AM4-AK4 -> 4900 | AN5: =AN4-AM4 -> 4500 | AO5: =AO4-AN4 -> 4200 | AP5: =AP4-AO4 -> 4700 | AQ5: =SUM(AM5:AP5) -> 18300 | AR5: =AR4-AP4 -> 4000 | AS5: =AS4-AR4 -> 4000 | AT5: 3750 | AU5: 3750 | AV5: =SUM(AR5:AU5) -> 15500 | AW5: 3750 | AX5: 3750 | AY5: 3750 | AZ5: 3750 | BA5: =SUM(AW5:AZ5) -> 15000
C6: Y/Y Growth | AC6: =AC4/X4-1 -> 0.15996344 | AD6: =AD4/Y4-1 -> 0.17055655 | AE6: =AE4/Z4-1 -> 0.14910026 | AF6: =AF4/AA4-1 -> 0.14449918 | AG6: =AG4/AA4-1 -> 0.14449918 | AH6: =AH4/AC4-1 -> 0.12765957 | AI6: =AI4/AD4-1 -> 0.098159509 | AJ6: =AJ4/AE4-1 -> 0.093959732 | AK6: =AK4/AF4-1 -> 0.084648494 | AL6: =AL4/AG4-1 -> 0.084648494 | AM6: =AM4/AH4-1 -> 0.090845563 | AN6: =AN4/AI4-1 -> 0.12150838 | AO6: =AO4/AJ4-1 -> 0.12338105 | ... BA6: =BA4/AV4-1 -> 0.081081081
C7: Q/Q Growth | Y7: =Y4/X4-1 -> 0.018281536 | Z7: =Z4/Y4-1 -> 0.047576302 | AA7: =AA4/Z4-1 -> 0.043701799 | AC7: =AC4/AA4-1 -> 0.041871921 | AD7: =AD4/AC4-1 -> 0.027580772 | AE7: =AE4/AD4-1 -> 0.028374233 | AF7: =AF4/AE4-1 -> 0.039522744 | AH7: =AH4/AF4-1 -> 0.026542324 | AI7: =AI4/AH4-1 -> 0.00069881202 | AJ7: =AJ4/AI4-1 -> 0.024441341 | AK7: =AK4/AJ4-1 -> 0.030674847 | AM7: =AM4/AK4-1 -> 0.032407407 | AN7: =AN4/AM4-1 -> 0.028827675 | AO7: =AO4/AN4-1 -> 0.02615193 | AP7: =AP4/AO4-1 -> 0.028519417 | AR7: =AR4/AP4-1 -> 0.02359882 | AS7: =AS4/AR4-1 -> 0.023054755 | AT7: =AT4/AS4-1 -> 0.021126761 | AU7: =AU4/AT4-1 -> 0.020689655 | AW7: =AW4/AU4-1 -> 0.02027027 | AX7: =AX4/AW4-1 -> 0.01986755 | AY7: =AY4/AX4-1 -> 0.019480519 | AZ7: =AZ4/AY4-1 -> 0.01910828
B8: Subscription Revenue/Customer | AA8: =AA11/AA4*1000 -> 308.70279 | AC8: =AC11/AC4*1000 -> 317.57289 | AD8: =AD11/AD4*1000 -> 327.45399 | AE8: =AE11/AE4*1000 -> 346.01044 | AF8: =AF11/AF4*1000 -> 342.89813 | AH8: =AH11/AH4*1000 -> 344.51433 | AI8: =AI11/AI4*1000 -> 347.06704 | AJ8: =AJ11/AJ4*1000 -> 345.60327 | AK8: =AK11/AK4*1000 -> 339.28571 | AM8: =AM11/AM4*1000 -> 340.16656 | AN8: =AN11/AN4*1000 -> 339.35243 | AO8: =AO11/AO4*1000 -> 334.95146 | AP8: =AP11/AP4*1000 -> 326.84366 | AR8: =AR11/AR4*1000 -> 323.34294 | AS8: =AS11/AS4*1000 -> 325.07042 | AT8: =AO8*(1+AT9) -> 326.57767 | AU8: =AP8*(1+AU9) -> 326.84366 | AW8: =AR8*(1+AW9) -> 328.19308 | AX8: =AS8*(1+AX9) -> 329.94648 | AY8: =AT8*(1+AY9) -> 331.47633 | AZ8: =AU8*(1+AZ9) -> 331.74631
C9: Y/Y Growth | AF9: =AF8/AA8-1 -> 0.11077109 | AH9: =AH8/AC8-1 -> 0.084835432 | AI9: =AI8/AD8-1 -> 0.059895595 | AJ9: =AJ8/AE8-1 -> -0.0011767506 | AK9: =AK8/AF8-1 -> -0.010534967 | AM9: =AM8/AH8-1 -> -0.012619985 | AN9: =AN8/AI8-1 -> -0.022228013 | AO9: =AO8/AJ8-1 -> -0.030820934 | AP9: =AP8/AK8-1 -> -0.036671324 | AR9: =AR8/AM8-1 -> -0.049457008 | AS9: =AS8/AN8-1 -> -0.042086058 | AT9: -0.025 | AU9: 0 | AW9: 0.015 | AX9: 0.015 | AY9: 0.015 | AZ9: 0.015
C10: Q/Q Growth | AC10: =AC8/AA8-1 -> 0.028733464 | AD10: =AD8/AC8-1 -> 0.031114418 | AE10: =AE8/AD8-1 -> 0.056668885 | AF10: =AF8/AE8-1 -> -0.0089948301 | AH10: =AH8/AF8-1 -> 0.0047133263 | AI10: =AI8/AH8-1 -> 0.0074096003 | AJ10: =AJ8/AI8-1 -> -0.0042175342 | AK10: =AK8/AJ8-1 -> -0.018279797 | AM10: =AM8/AK8-1 -> 0.0025961765 | AN10: =AN8/AM8-1 -> -0.002393332 | AO10: =AO8/AN8-1 -> -0.012968736 | AP10: =AP8/AO8-1 -> -0.024205891 | AR10: =AR8/AP8-1 -> -0.010710682 | AS10: =AS8/AR8-1 -> 0.0053425724 | AT10: =AT8/AS8-1 -> 0.0046366795 | AU10: =AU8/AT8-1 -> 0.00081447061 | AW10: =AW8/AU8-1 -> 0.0041286582 | AX10: =AX8/AW8-1 -> 0.0053425724 | AY10: =AY8/AX8-1 -> 0.0046366795 | AZ10: =AZ8/AY8-1 -> 0.00081447061
A11: x | B11: Subscription Revenue | AA11: 37600 | AC11: 40300 | AD11: 42700 | AE11: 46400 | AF11: 47800 | AG11: =SUM(AC11:AF11) -> 177200 | AH11: 49300 | AI11: 49700 | AJ11: 50700 | AK11: 51300 | AL11: =SUM(AH11:AK11) -> 201000 | AM11: 53100 | AN11: 54500 | AO11: 55200 | AP11: 55400 | AQ11: =SUM(AM11:AP11) -> 218200 | AR11: 56100 | AS11: 57700 | AT11: =AT4*AT8/1000 -> 59192.203 | AU11: =AU4*AU8/1000 -> 60466.077 | AV11: =SUM(AR11:AU11) -> 233458.28 | AW11: =AW4*AW8/1000 -> 61946.445 | AX11: =AX4*AX8/1000 -> 63514.697 | AY11: =AY4*AY8/1000 -> 65052.231 | AZ11: =AZ4*AZ8/1000 -> 66349.263 | BA11: =SUM(AW11:AZ11) -> 256862.63
C12: Y/Y Growth | AF12: =AF11/AA11-1 -> 0.2712766 | AH12: =AH11/AC11-1 -> 0.22332506 | AI12: =AI11/AD11-1 -> 0.16393443 | AJ12: =AJ11/AE11-1 -> 0.092672414 | AK12: =AK11/AF11-1 -> 0.073221757 | AL12: =AL11/AG11-1 -> 0.13431151 | AM12: =AM11/AH11-1 -> 0.077079108 | AN12: =AN11/AI11-1 -> 0.096579477 | AO12: =AO11/AJ11-1 -> 0.088757396 | ... BA12: =BA11/AV11-1 -> 0.1002507
C13: Q/Q Growth | AC13: =AC11/AA11-1 -> 0.071808511 | AD13: =AD11/AC11-1 -> 0.05955335 | AE13: =AE11/AD11-1 -> 0.086651054 | AF13: =AF11/AE11-1 -> 0.030172414 | AH13: =AH11/AF11-1 -> 0.031380753 | AI13: =AI11/AH11-1 -> 0.0081135903 | AJ13: =AJ11/AI11-1 -> 0.020120724 | AK13: =AK11/AJ11-1 -> 0.01183432 | AM13: =AM11/AK11-1 -> 0.035087719 | AN13: =AN11/AM11-1 -> 0.026365348 | AO13: =AO11/AN11-1 -> 0.012844037 | AP13: =AP11/AO11-1 -> 0.0036231884 | AR13: =AR11/AP11-1 -> 0.012635379 | AS13: =AS11/AR11-1 -> 0.028520499 | AT13: =AT11/AS11-1 -> 0.025861398 | AU13: =AU11/AT11-1 -> 0.021520977 | AW13: =AW11/AU11-1 -> 0.024482618 | AX13: =AX11/AW11-1 -> 0.025316266 | AY13: =AY11/AX11-1 -> 0.024207524 | AZ13: =AZ11/AY11-1 -> 0.019938314
A14: x | B14: Transactions (M) | AA14: 9.6 | AC14: 9.9 | AD14: 10 | AE14: 9.9 | AF14: 10.6 | AG14: =SUM(AC14:AF14) -> 40.4 | AH14: 10.6 | AI14: 11 | AJ14: 10.7 | AK14: 11.5 | AL14: =SUM(AH14:AK14) -> 43.8 | AM14: 11.7 | AN14: 12.2 | AO14: 11.5 | AP14: 12.4 | AQ14: =SUM(AM14:AP14) -> 47.8 | AR14: 12.5 | AS14: 12.8 | AT14: =AO14*(1+AT15) -> 12.535 | AU14: =AP14*(1+AU15) -> 13.392 | AV14: =SUM(AR14:AU14) -> 51.227 | AW14: =AR14*(1+AW15) -> 13.375 | AX14: =AS14*(1+AX15) -> 13.696 | AY14: =AT14*(1+AY15) -> 13.41245 | AZ14: =AU14*(1+AZ15) -> 14.32944 | BA14: =SUM(AW14:AZ14) -> 54.81289
C15: Y/Y Growth | AF15: =AF14/AA14-1 -> 0.10416667 | AH15: =AH14/AC14-1 -> 0.070707071 | AI15: =AI14/AD14-1 -> 0.1 | AJ15: =AJ14/AE14-1 -> 0.080808081 | AK15: =AK14/AF14-1 -> 0.08490566 | AL15: =AL14/AG14-1 -> 0.084158416 | AM15: =AM14/AH14-1 -> 0.10377358 | AN15: =AN14/AI14-1 -> 0.10909091 | AO15: =AO14/AJ14-1 -> 0.074766355 | ... AS15: =AS14/AN14-1 -> 0.049180328 | AT15: 0.09 | AU15: 0.08 | AV15: =AV14/AQ14-1 -> 0.071694561 | AW15: 0.07 | AX15: 0.07 | AY15: 0.07 | AZ15: 0.07 | BA15: =BA14/AV14-1 -> 0.07
C16: Q/Q Growth | AC16: =AC14/AA14-1 -> 0.03125 | AD16: =AD14/AC14-1 -> 0.01010101 | AE16: =AE14/AD14-1 -> -0.01 | AF16: =AF14/AE14-1 -> 0.070707071 | AH16: =AH14/AF14-1 -> 0 | AI16: =AI14/AH14-1 -> 0.037735849 | AJ16: =AJ14/AI14-1 -> -0.027272727 | AK16: =AK14/AJ14-1 -> 0.074766355 | AM16: =AM14/AK14-1 -> 0.017391304 | AN16: =AN14/AM14-1 -> 0.042735043 | AO16: =AO14/AN14-1 -> -0.057377049 | AP16: =AP14/AO14-1 -> 0.07826087 | AR16: =AR14/AP14-1 -> 0.0080645161 | AS16: =AS14/AR14-1 -> 0.024 | AT16: =AT14/AS14-1 -> -0.020703125 | AU16: =AU14/AT14-1 -> 0.068368568 | AW16: =AW14/AU14-1 -> -0.0012694146 | AX16: =AX14/AW14-1 -> 0.024 | AY16: =AY14/AX14-1 -> -0.020703125 | AZ16: =AZ14/AY14-1 -> 0.068368568
B17: Average Transaction Size ($) | AA17: =AA20/AA14*1000 -> 5739.5833 | AC17: =AC20/AC14*1000 -> 5626.2626 | AD17: =AD20/AD14*1000 -> 5750 | AE17: =AE20/AE14*1000 -> 5555.5556 | AF17: =AF20/AF14*1000 -> 5632.0755 | AG17: =AG20/AG14*1000 -> 5641.0891 | AH17: =AH20/AH14*1000 -> 5707.5472 | AI17: =AI20/AI14*1000 -> 5872.7273 | AJ17: =AJ20/AJ14*1000 -> 5691.5888 | ... AS17: =AS20/AS14*1000 -> 6242.1875 | AT17: =AO17*(1+AT18) -> 6108.2609 | AU17: =AP17*(1+AU18) -> 6033.871 | AV17: =AV20/AV14*1000 -> 6090.0043 | AW17: =AR17*(1+AW18) -> 6035.76 | AX17: =AS17*(1+AX18) -> 6273.3984 | AY17: =AT17*(1+AY18) -> 6138.8022 | AZ17: =AU17*(1+AZ18) -> 6064.0403 | BA17: =BA20/BA14*1000 -> 6127.7454
C18: Y/Y Growth | AF18: =AF17/AA17-1 -> -0.018730952 | AH18: =AH17/AC17-1 -> 0.014447343 | AI18: =AI17/AD17-1 -> 0.021343874 | AJ18: =AJ17/AE17-1 -> 0.024485981 | AK18: =AK17/AF17-1 -> -0.0056951424 | AL18: =AL17/AG17-1 -> 0.013438162 | AM18: =AM17/AH17-1 -> 0.013802359 | AN18: =AN17/AI17-1 -> 0.0035273816 | AO18: =AO17/AJ17-1 -> 0.022103234 | ... AS18: =AS17/AN17-1 -> 0.05917507 | AT18: 0.05 | AU18: 0.032 | AV18: =AV17/AQ17-1 -> 0.04337708 | AW18: 0.01 | AX18: 0.005 | AY18: 0.005 | AZ18: 0.005 | BA18: =BA17/AV17-1 -> 0.0061972203
C19: Q/Q Growth | AC19: =AC17/AA17-1 -> -0.019743717 | AD19: =AD17/AC17-1 -> 0.021992819 | AE19: =AE17/AD17-1 -> -0.033816425 | AF19: =AF17/AE17-1 -> 0.013773585 | AH19: =AH17/AF17-1 -> 0.013400335 | AI19: =AI17/AH17-1 -> 0.028940646 | AJ19: =AJ17/AI17-1 -> -0.030844015 | AK19: =AK17/AJ17-1 -> -0.016091954 | AM19: =AM17/AK17-1 -> 0.033272283 | AN19: =AN17/AM17-1 -> 0.018512241 | AO19: =AO17/AN17-1 -> -0.012904396 | AP19: =AP17/AO17-1 -> 0.0050508703 | AR19: =AR17/AP17-1 -> 0.022102069 | AS19: =AS17/AR17-1 -> 0.044542754 | AT19: =AT17/AS17-1 -> -0.02145508 | AU19: =AU17/AT17-1 -> -0.012178573 | AW19: =AW17/AU17-1 -> 0.00031307137 | AX19: =AX17/AW17-1 -> 0.039371751 | AY19: =AY17/AX17-1 -> -0.02145508 | AZ19: =AZ17/AY17-1 -> -0.012178573
A20: x | B20: Total Payment Volume (B) | AA20: 55.1 | AC20: 55.7 | AD20: 57.5 | AE20: 55 | AF20: 59.7 | AG20: =SUM(AC20:AF20) -> 227.9 | AH20: 60.5 | AI20: 64.6 | AJ20: 60.9 | AK20: 64.4 | AL20: =SUM(AH20:AK20) -> 250.4 | AM20: 67.7 | AN20: 71.9 | AO20: 66.9 | AP20: 72.5 | AQ20: =SUM(AM20:AP20) -> 279 | AR20: 74.7 | AS20: 79.9 | AT20: =AT14*AT17/1000 -> 76.56705 | AU20: =AU14*AU17/1000 -> 80.8056 | AV20: =SUM(AR20:AU20) -> 311.97265 | AW20: =AW14*AW17/1000 -> 80.72829 | AX20: =AX14*AX17/1000 -> 85.920465 | AY20: =AY14*AY17/1000 -> 82.336377 | AZ20: =AZ14*AZ17/1000 -> 86.894302 | BA20: =SUM(AW20:AZ20) -> 335.87943
C21: Y/Y Growth | AF21: =AF20/AA20-1 -> 0.083484574 | AH21: =AH20/AC20-1 -> 0.086175943 | AI21: =AI20/AD20-1 -> 0.12347826 | AJ21: =AJ20/AE20-1 -> 0.10727273 | AK21: =AK20/AF20-1 -> 0.078726968 | AL21: =AL20/AG20-1 -> 0.098727512 | AM21: =AM20/AH20-1 -> 0.11900826 | AN21: =AN20/AI20-1 -> 0.1130031 | AO21: =AO20/AJ20-1 -> 0.098522167 | ... BA21: =BA20/AV20-1 -> 0.076631026
C22: Q/Q Growth | AC22: =AC20/AA20-1 -> 0.010889292 | AD22: =AD20/AC20-1 -> 0.032315978 | AE22: =AE20/AD20-1 -> -0.043478261 | AF22: =AF20/AE20-1 -> 0.085454545 | AH22: =AH20/AF20-1 -> 0.013400335 | AI22: =AI20/AH20-1 -> 0.067768595 | AJ22: =AJ20/AI20-1 -> -0.057275542 | AK22: =AK20/AJ20-1 -> 0.057471264 | AM22: =AM20/AK20-1 -> 0.051242236 | AN22: =AN20/AM20-1 -> 0.062038405 | AO22: =AO20/AN20-1 -> -0.069541029 | AP22: =AP20/AO20-1 -> 0.083707025 | AR22: =AR20/AP20-1 -> 0.030344828 | AS22: =AS20/AR20-1 -> 0.06961178 | AT22: =AT20/AS20-1 -> -0.041714018 | AU22: =AU20/AT20-1 -> 0.055357363 | AW22: =AW20/AU20-1 -> -0.00095674062 | AX22: =AX20/AW20-1 -> 0.064316673 | AY22: =AY20/AX20-1 -> -0.041714018 | AZ22: =AZ20/AY20-1 -> 0.055357363
B23: Take Rate (BPs) | AA23: =AA26/AA20/100 -> 12.341198 | AC23: =AC26/AC20/100 -> 13.572711 | AD23: =AD26/AD20/100 -> 13.843478 | AE23: =AE26/AE20/100 -> 14.981818 | AF23: =AF26/AF20/100 -> 15.20938 | AG23: =AG26/AG20/100 -> 14.409829 | AH23: =AH26/AH20/100 -> 15.553719 | AI23: =AI26/AI20/100 -> 15.232198 | AJ23: =AJ26/AJ20/100 -> 16.157635 | ... AS23: =AS26/AS20/100 -> 16.036045 | AT23: 16.6 | AU23: 16.9 | AV23: =AV26/AV20/100 -> 16.484995 | AW23: 16.9 | AX23: 16.6 | AY23: 17 | AZ23: 17.1 | BA23: =BA26/BA20/100 -> 16.899513
C24: Y/Y Growth | AF24: =AF23/AA23-1 -> 0.23240713 | AH24: =AH23/AC23-1 -> 0.14595522 | AI24: =AI23/AD23-1 -> 0.10031582 | AJ24: =AJ23/AE23-1 -> 0.07848295 | AK24: =AK23/AF23-1 -> 0.057699674 | AL24: =AL23/AG23-1 -> 0.093336532 | AM24: =AM23/AH23-1 -> 0.036632201 | AN24: =AN23/AI23-1 -> 0.025771623 | AO24: =AO23/AJ23-1 -> 0.0044444293 | ... BA24: =BA23/AV23-1 -> 0.025145139
C25: Q/Q Growth | AC25: =AC23/AA23-1 -> 0.099788784 | AD25: =AD23/AC23-1 -> 0.01994939 | AE25: =AE23/AD23-1 -> 0.082229328 | AF25: =AF23/AE23-1 -> 0.015189215 | AH25: =AH23/AF23-1 -> 0.022639895 | AI25: =AI23/AH23-1 -> -0.020671639 | AJ25: =AJ23/AI23-1 -> 0.060755337 | AK25: =AK23/AJ23-1 -> -0.0043743372 | AM25: =AM23/AK23-1 -> 0.0022707493 | AN25: =AN23/AM23-1 -> -0.030931857 | AO25: =AO23/AN23-1 -> 0.038700784 | AP25: =AP23/AO23-1 -> 0.015684642 | AR25: =AR23/AP23-1 -> -0.0051933042 | AS25: =AS23/AR23-1 -> -0.022096586 | AT25: =AT23/AS23-1 -> 0.035167957 | AU25: =AU23/AT23-1 -> 0.018072289 | AW25: =AW23/AU23-1 -> 0 | AX25: =AX23/AW23-1 -> -0.017751479 | AY25: =AY23/AX23-1 -> 0.024096386 | AZ25: =AZ23/AY23-1 -> 0.0058823529
A26: x | B26: Transaction Revenue | AA26: 68000 | AC26: 75600 | AD26: 79600 | AE26: 82400 | AF26: 90800 | AG26: =SUM(AC26:AF26) -> 328400 | AH26: 94100 | AI26: 98400 | AJ26: 98400 | AK26: 103600 | AL26: =SUM(AH26:AK26) -> 394500 | AM26: =109100+56 -> 109156 | AN26: =112400-84+26 -> 112342 | AO26: =108500+87-12 -> 108575 | AP26: =119400+667782-667673 -> 119509 | AQ26: =SUM(AM26:AP26) -> 449582 | AR26: =122500-4 -> 122496 | AS26: =128200-72 -> 128128 | AT26: =AT20*AT23*100 -> 127101.3 | AU26: =AU20*AU23*100 -> 136561.46 | AV26: =SUM(AR26:AU26) -> 514286.77 | AW26: =AW20*AW23*100 -> 136430.81 | AX26: =AX20*AX23*100 -> 142627.97 | AY26: =AY20*AY23*100 -> 139971.84 | AZ26: =AZ20*AZ23*100 -> 148589.26 | BA26: =SUM(AW26:AZ26) -> 567619.88
C27: Y/Y Growth | AF27: =AF26/AA26-1 -> 0.33529412 | AH27: =AH26/AC26-1 -> 0.24470899 | AI27: =AI26/AD26-1 -> 0.2361809 | AJ27: =AJ26/AE26-1 -> 0.19417476 | AK27: =AK26/AF26-1 -> 0.14096916 | AL27: =AL26/AG26-1 -> 0.20127893 | AM27: =AM26/AH26-1 -> 0.16 | AN27: =AN26/AI26-1 -> 0.14168699 | AO27: =AO26/AJ26-1 -> 0.10340447 | ... BA27: =BA26/AV26-1 -> 0.10370306
C28: Q/Q Growth | AC28: =AC26/AA26-1 -> 0.11176471 | AD28: =AD26/AC26-1 -> 0.052910053 | AE28: =AE26/AD26-1 -> 0.035175879 | AF28: =AF26/AE26-1 -> 0.10194175 | AH28: =AH26/AF26-1 -> 0.036343612 | AI28: =AI26/AH26-1 -> 0.045696068 | AJ28: =AJ26/AI26-1 -> 0 | AK28: =AK26/AJ26-1 -> 0.052845528 | AM28: =AM26/AK26-1 -> 0.053629344 | AN28: =AN26/AM26-1 -> 0.029187585 | AO28: =AO26/AN26-1 -> -0.033531538 | AP28: =AP26/AO26-1 -> 0.10070458 | AR28: =AR26/AP26-1 -> 0.024993934 | AS28: =AS26/AR26-1 -> 0.045977011 | AT28: =AT26/AS26-1 -> -0.0080130573 | AU28: =AU26/AT26-1 -> 0.074430087 | AW28: =AW26/AU26-1 -> -0.00095674062 | AX28: =AX26/AW26-1 -> 0.045423477 | AY28: =AY26/AX26-1 -> -0.018622789 | AZ28: =AZ26/AY26-1 -> 0.061565348
B29: Total Revenue | AA29: =SUM(AA11,AA26) -> 105600 | AC29: =SUM(AC11,AC26) -> 115900 | AD29: =SUM(AD11,AD26) -> 122300 | AE29: =SUM(AE11,AE26) -> 128800 | AF29: =SUM(AF11,AF26) -> 138600 | AG29: =SUM(AC29:AF29) -> 505600 | AH29: =SUM(AH11,AH26) -> 143400 | AI29: =SUM(AI11,AI26) -> 148100 | AJ29: =SUM(AJ11,AJ26) -> 149100 | AK29: =SUM(AK11,AK26) -> 154900 | AL29: =SUM(AH29:AK29) -> 595500 | AM29: =SUM(AM11,AM26) -> 162256 | AN29: =SUM(AN11,AN26) -> 166842 | AO29: =SUM(AO11,AO26) -> 163775 | AP29: =SUM(AP11,AP26) -> 174909 | AQ29: =SUM(AM29:AP29) -> 667782 | AR29: =SUM(AR11,AR26) -> 178596 | AS29: =SUM(AS11,AS26) -> 185828 | AT29: =SUM(AT11,AT26) -> 186293.51 | AU29: =SUM(AU11,AU26) -> 197027.54 | AV29: =SUM(AR29:AU29) -> 747745.05 | AW29: =SUM(AW11,AW26) -> 198377.25 | AX29: =SUM(AX11,AX26) -> 206142.67 | AY29: =SUM(AY11,AY26) -> 205024.07 | AZ29: =SUM(AZ11,AZ26) -> 214938.52 | BA29: =SUM(AW29:AZ29) -> 824482.51
C30: Y/Y Growth | AF30: =AF29/AA29-1 -> 0.3125 | AH30: =AH29/AC29-1 -> 0.23727351 | AI30: =AI29/AD29-1 -> 0.21095666 | AJ30: =AJ29/AE29-1 -> 0.1576087 | AK30: =AK29/AF29-1 -> 0.11760462 | AL30: =AL29/AG29-1 -> 0.17780854 | AM30: =AM29/AH29-1 -> 0.13149233 | AN30: =AN29/AI29-1 -> 0.12654963 | AO30: =AO29/AJ29-1 -> 0.098423877 | ... BA30: =BA29/AV29-1 -> 0.10262518
C31: Q/Q Growth | AC31: =AC29/AA29-1 -> 0.097537879 | AD31: =AD29/AC29-1 -> 0.055220017 | AE31: =AE29/AD29-1 -> 0.053147997 | AF31: =AF29/AE29-1 -> 0.076086957 | AH31: =AH29/AF29-1 -> 0.034632035 | AI31: =AI29/AH29-1 -> 0.032775453 | AJ31: =AJ29/AI29-1 -> 0.0067521945 | AK31: =AK29/AJ29-1 -> 0.038900067 | AM31: =AM29/AK29-1 -> 0.047488702 | AN31: =AN29/AM29-1 -> 0.028263978 | AO31: =AO29/AN29-1 -> -0.018382661 | AP31: =AP29/AO29-1 -> 0.067983514 | AR31: =AR29/AP29-1 -> 0.021079533 | AS31: =AS29/AR29-1 -> 0.040493628 | AT31: =AT29/AS29-1 -> 0.0025050351 | AU31: =AU29/AT29-1 -> 0.057618944 | AW31: =AW29/AU29-1 -> 0.0068503821 | AX31: =AX29/AW29-1 -> 0.039144682 | AY31: =AY29/AX29-1 -> -0.0054263248 | AZ31: =AZ29/AY29-1 -> 0.048357477
B34: Bill Spend & Expense (Divvy) | D34: =D$104 -> 1Q18 | E34: =E$104 -> 2Q18 | F34: =F$104 -> 3Q18 | G34: =G$104 -> 4Q18 | H34: =H$104 -> 2018 | I34: =I$104 -> 1Q19 | J34: =J$104 -> 2Q19 | K34: =K$104 -> 3Q19 | ... BA34: =BA$104 -> 2027E
A35: x | B35: Customers | X35: 13500 | Y35: 15500 | Z35: 18100 | AA35: 20700 | AB35: =AA35 -> 20700 | AC35: 22800 | AD35: 24700 | AE35: 27100 | AF35: 29200 | AG35: =AF35 -> 29200 | AH35: 30700 | AI35: 31600 | AJ35: 33500 | AK35: 34800 | AL35: =AK35 -> 34800 | AM35: 36400 | AN35: 37800 | AO35: 39500 | AP35: 41100 | AQ35: =AP35 -> 41100 | AR35: 42500 | AS35: 44000 | AT35: =AS35+AT36 -> 45250 | AU35: =AT35+AU36 -> 46500 | AV35: =AU35 -> 46500 | AW35: =AU35+AW36 -> 47800 | AX35: =AW35+AX36 -> 49100 | AY35: =AX35+AY36 -> 50400 | AZ35: =AY35+AZ36 -> 51700 | BA35: =AZ35 -> 51700
C36: Quarterly Adds | Y36: =Y35-X35 -> 2000 | Z36: =Z35-Y35 -> 2600 | AA36: =AA35-Z35 -> 2600 | AC36: =AC35-AA35 -> 2100 | AD36: =AD35-AC35 -> 1900 | AE36: =AE35-AD35 -> 2400 | AF36: =AF35-AE35 -> 2100 | AG36: =SUM(AC36:AF36) -> 8500 | AH36: =AH35-AF35 -> 1500 | AI36: =AI35-AH35 -> 900 | AJ36: =AJ35-AI35 -> 1900 | AK36: =AK35-AJ35 -> 1300 | AL36: =SUM(AH36:AK36) -> 5600 | AM36: =AM35-AK35 -> 1600 | AN36: =AN35-AM35 -> 1400 | AO36: =AO35-AN35 -> 1700 | AP36: =AP35-AO35 -> 1600 | AQ36: =SUM(AM36:AP36) -> 6300 | AR36: =AR35-AP35 -> 1400 | AS36: =AS35-AR35 -> 1500 | AT36: 1250 | AU36: 1250 | AV36: =SUM(AR36:AU36) -> 5400 | AW36: 1300 | AX36: 1300 | AY36: 1300 | AZ36: 1300 | BA36: =SUM(AW36:AZ36) -> 5200
C37: Y/Y Growth | AC37: =AC35/X35-1 -> 0.68888889 | AD37: =AD35/Y35-1 -> 0.59354839 | AE37: =AE35/Z35-1 -> 0.49723757 | AF37: =AF35/AA35-1 -> 0.41062802 | AG37: =AG35/AB35-1 -> 0.41062802 | AH37: =AH35/AC35-1 -> 0.34649123 | AI37: =AI35/AD35-1 -> 0.27935223 | AJ37: =AJ35/AE35-1 -> 0.23616236 | ... BA37: =BA35/AV35-1 -> 0.11182796
C38: Q/Q Growth | Y38: =Y35/X35-1 -> 0.14814815 | Z38: =Z35/Y35-1 -> 0.16774194 | AA38: =AA35/Z35-1 -> 0.14364641 | AC38: =AC35/AA35-1 -> 0.10144928 | AD38: =AD35/AC35-1 -> 0.083333333 | AE38: =AE35/AD35-1 -> 0.097165992 | AF38: =AF35/AE35-1 -> 0.077490775 | AH38: =AH35/AF35-1 -> 0.051369863 | AI38: =AI35/AH35-1 -> 0.029315961 | AJ38: =AJ35/AI35-1 -> 0.060126582 | AK38: =AK35/AJ35-1 -> 0.03880597 | AM38: =AM35/AK35-1 -> 0.045977011 | AN38: =AN35/AM35-1 -> 0.038461538 | AO38: =AO35/AN35-1 -> 0.044973545 | AP38: =AP35/AO35-1 -> 0.040506329 | AR38: =AR35/AP35-1 -> 0.03406326 | AS38: =AS35/AR35-1 -> 0.035294118 | AT38: =AT35/AS35-1 -> 0.028409091 | AU38: =AU35/AT35-1 -> 0.027624309 | AW38: =AW35/AU35-1 -> 0.027956989 | AX38: =AX35/AW35-1 -> 0.027196653 | AY38: =AY35/AX35-1 -> 0.026476578 | AZ38: =AZ35/AY35-1 -> 0.025793651
A39: x | B39: Transactions (M) | X39: 4.6 | Y39: 5.3 | Z39: 5.9 | AA39: 7.3 | AB39: =SUM(X39:AA39) -> 23.1 | AC39: 8.5 | AD39: 9.4 | AE39: 10.2 | AF39: 11.4 | AG39: =SUM(AC39:AF39) -> 39.5 | AH39: 12.8 | AI39: 13.2 | AJ39: 13.5 | AK39: 14.8 | AL39: =SUM(AH39:AK39) -> 54.3 | AM39: 15.3 | AN39: 16.1 | AO39: 16.5 | AP39: 18.5 | AQ39: =SUM(AM39:AP39) -> 66.4 | AR39: 18.8 | AS39: 19.8 | AT39: =AO39*(1+AT40) -> 20.0475 | AU39: =AP39*(1+AU40) -> 22.2 | AV39: =SUM(AR39:AU39) -> 80.8475 | AW39: =AR39*(1+AW40) -> 21.996 | AX39: =AS39*(1+AX40) -> 23.166 | AY39: =AT39*(1+AY40) -> 23.2551 | AZ39: =AU39*(1+AZ40) -> 25.752 | BA39: =SUM(AW39:AZ39) -> 94.1691
C40: Y/Y Growth | AC40: =AC39/X39-1 -> 0.84782609 | AD40: =AD39/Y39-1 -> 0.77358491 | AE40: =AE39/Z39-1 -> 0.72881356 | AF40: =AF39/AA39-1 -> 0.56164384 | AG40: =AG39/AB39-1 -> 0.70995671 | AH40: =AH39/AC39-1 -> 0.50588235 | AI40: =AI39/AD39-1 -> 0.40425532 | AJ40: =AJ39/AE39-1 -> 0.32352941 | ... AS40: =AS39/AN39-1 -> 0.22981366 | AT40: 0.215 | AU40: 0.2 | AV40: =AV39/AQ39-1 -> 0.21758283 | AW40: 0.17 | AX40: 0.17 | AY40: 0.16 | AZ40: 0.16 | BA40: =BA39/AV39-1 -> 0.16477442
C41: Q/Q Growth | Y41: =Y39/X39-1 -> 0.15217391 | Z41: =Z39/Y39-1 -> 0.11320755 | AA41: =AA39/Z39-1 -> 0.23728814 | AC41: =AC39/AA39-1 -> 0.16438356 | AD41: =AD39/AC39-1 -> 0.10588235 | AE41: =AE39/AD39-1 -> 0.085106383 | AF41: =AF39/AE39-1 -> 0.11764706 | AH41: =AH39/AF39-1 -> 0.12280702 | AI41: =AI39/AH39-1 -> 0.03125 | AJ41: =AJ39/AI39-1 -> 0.022727273 | AK41: =AK39/AJ39-1 -> 0.096296296 | AM41: =AM39/AK39-1 -> 0.033783784 | AN41: =AN39/AM39-1 -> 0.052287582 | AO41: =AO39/AN39-1 -> 0.02484472 | AP41: =AP39/AO39-1 -> 0.12121212 | AR41: =AR39/AP39-1 -> 0.016216216 | AS41: =AS39/AR39-1 -> 0.053191489 | AT41: =AT39/AS39-1 -> 0.0125 | AU41: =AU39/AT39-1 -> 0.10737 | AW41: =AW39/AU39-1 -> -0.0091891892 | AX41: =AX39/AW39-1 -> 0.053191489 | AY41: =AY39/AX39-1 -> 0.0038461538 | AZ41: =AZ39/AY39-1 -> 0.10737
B42: Average Transaction Size ($) | X42: =X45/X39*1000 -> 324.56522 | Y42: =Y45/Y39*1000 -> 358.49057 | Z42: =Z45/Z39*1000 -> 355.9322 | AA42: =AA45/AA39*1000 -> 369.86301 | AB42: =AB45/AB39*1000 -> 354.67532 | AC42: =AC45/AC39*1000 -> 352.94118 | AD42: =AD45/AD39*1000 -> 351.06383 | AE42: =AE45/AE39*1000 -> 333.33333 | ... AS42: =AS45/AS39*1000 -> 328.28283 | AT42: =AO42*(1+AT43) -> 318.64242 | AU42: =AP42*(1+AU43) -> 318.91892 | AV42: =AV45/AV39*1000 -> 323.67091 | AW42: =AR42*(1+AW43) -> 329.78723 | AX42: =AS42*(1+AX43) -> 328.28283 | AY42: =AT42*(1+AY43) -> 321.82885 | AZ42: =AU42*(1+AZ43) -> 322.10811 | BA42: =BA45/BA39*1000 -> 325.35184
C43: Y/Y Growth | AC43: =AC42/X42-1 -> 0.087427603 | AD43: =AD42/Y42-1 -> -0.020716685 | AE43: =AE42/Z42-1 -> -0.063492063 | AF43: =AF42/AA42-1 -> -0.098765432 | AG43: =AG42/AB42-1 -> -0.036380238 | AH43: =AH42/AC42-1 -> -0.11458333 | AI43: =AI42/AD42-1 -> -0.093663912 | AJ43: =AJ42/AE42-1 -> -0.022222222 | ... AS43: =AS42/AN42-1 -> 0.016414141 | AT43: -0.008 | AU43: 0 | AV43: =AV42/AQ42-1 -> -0.00038379027 | AW43: 0 | AX43: 0 | AY43: 0.01 | AZ43: 0.01 | BA43: =BA42/AV42-1 -> 0.0051933297
C44: Q/Q Growth | Y44: =Y42/X42-1 -> 0.10452552 | Z44: =Z42/Y42-1 -> -0.0071364853 | AA44: =AA42/Z42-1 -> 0.039138943 | AC44: =AC42/AA42-1 -> -0.045751634 | AD44: =AD42/AC42-1 -> -0.0053191489 | AE44: =AE42/AD42-1 -> -0.050505051 | AF44: =AF42/AE42-1 -> 0 | AH44: =AH42/AF42-1 -> -0.0625 | AI44: =AI42/AH42-1 -> 0.018181818 | AJ44: =AJ42/AI42-1 -> 0.024338624 | AK44: =AK42/AJ42-1 -> -0.0049140049 | AM44: =AM42/AK42-1 -> 0.027777778 | AN44: =AN42/AM42-1 -> -0.031055901 | AO44: =AO42/AN42-1 -> -0.0054778555 | AP44: =AP42/AO42-1 -> -0.0071392147 | AR44: =AR42/AP42-1 -> 0.034078615 | AS44: =AS42/AR42-1 -> -0.0045617465 | AT44: =AT42/AS42-1 -> -0.029366154 | AU44: =AU42/AT42-1 -> 0.00086772713 | AW44: =AW42/AU42-1 -> 0.034078615 | AX44: =AX42/AW42-1 -> -0.0045617465 | AY44: =AY42/AX42-1 -> -0.019659815 | AZ44: =AZ42/AY42-1 -> 0.00086772713
A45: x | B45: Total Payment Volume (B) | X45: 1.493 | Y45: 1.9 | Z45: 2.1 | AA45: 2.7 | AB45: =SUM(X45:AA45) -> 8.193 | AC45: 3 | AD45: 3.3 | AE45: 3.4 | AF45: 3.8 | AG45: =SUM(AC45:AF45) -> 13.5 | AH45: 4 | AI45: 4.2 | AJ45: 4.4 | AK45: 4.8 | AL45: =SUM(AH45:AK45) -> 17.4 | AM45: 5.1 | AN45: 5.2 | AO45: 5.3 | AP45: 5.9 | AQ45: =SUM(AM45:AP45) -> 21.5 | AR45: 6.2 | AS45: 6.5 | AT45: =AT39*AT42/1000 -> 6.387984 | AU45: =AU39*AU42/1000 -> 7.08 | AV45: =SUM(AR45:AU45) -> 26.167984 | AW45: =AW39*AW42/1000 -> 7.254 | AX45: =AX39*AX42/1000 -> 7.605 | AY45: =AY39*AY42/1000 -> 7.4841621 | AZ45: =AZ39*AZ42/1000 -> 8.294928 | BA45: =SUM(AW45:AZ45) -> 30.63809
C46: Y/Y Growth | AC46: =AC45/X45-1 -> 1.0093771 | AD46: =AD45/Y45-1 -> 0.73684211 | AE46: =AE45/Z45-1 -> 0.61904762 | AF46: =AF45/AA45-1 -> 0.40740741 | AG46: =AG45/AB45-1 -> 0.64774808 | AH46: =AH45/AC45-1 -> 0.33333333 | AI46: =AI45/AD45-1 -> 0.27272727 | AJ46: =AJ45/AE45-1 -> 0.29411765 | ... BA46: =BA45/AV45-1 -> 0.17082348
C47: Q/Q Growth | Y47: =Y45/X45-1 -> 0.27260549 | Z47: =Z45/Y45-1 -> 0.10526316 | AA47: =AA45/Z45-1 -> 0.28571429 | AC47: =AC45/AA45-1 -> 0.11111111 | AD47: =AD45/AC45-1 -> 0.1 | AE47: =AE45/AD45-1 -> 0.03030303 | AF47: =AF45/AE45-1 -> 0.11764706 | AH47: =AH45/AF45-1 -> 0.052631579 | AI47: =AI45/AH45-1 -> 0.05 | AJ47: =AJ45/AI45-1 -> 0.047619048 | AK47: =AK45/AJ45-1 -> 0.090909091 | AM47: =AM45/AK45-1 -> 0.0625 | AN47: =AN45/AM45-1 -> 0.019607843 | AO47: =AO45/AN45-1 -> 0.019230769 | AP47: =AP45/AO45-1 -> 0.11320755 | AR47: =AR45/AP45-1 -> 0.050847458 | AS47: =AS45/AR45-1 -> 0.048387097 | AT47: =AT45/AS45-1 -> -0.017233231 | AU47: =AU45/AT45-1 -> 0.10833089 | AW47: =AW45/AU45-1 -> 0.024576271 | AX47: =AX45/AW45-1 -> 0.048387097 | AY47: =AY45/AX45-1 -> -0.015889276 | AZ47: =AZ45/AY45-1 -> 0.10833089
B48: Take Rate (BPs) | X48: =X51/X45/100 -> 245.14401 | Y48: =Y51/Y45/100 -> 256.31579 | Z48: =Z51/Z45/100 -> 255.2381 | AA48: =AA51/AA45/100 -> 257.40741 | AB48: =AB51/AB45/100 -> 254.36348 | AC48: =AC51/AC45/100 -> 260 | AD48: =AD51/AD45/100 -> 262.42424 | AE48: =AE51/AE45/100 -> 260.58824 | ... AS48: =AS51/AS45/100 -> 256.15385 | AT48: 252 | AU48: 252 | AV48: =AV51/AV45/100 -> 253.43152 | AW48: 252 | AX48: 252 | AY48: 252 | AZ48: 252 | BA48: =BA51/BA45/100 -> 252
C49: Y/Y Growth | AC49: =AC48/X48-1 -> 0.060601093 | AD49: =AD48/Y48-1 -> 0.023831747 | AE49: =AE48/Z48-1 -> 0.02096137 | AF49: =AF48/AA48-1 -> 0.021317683 | AG49: =AG48/AB48-1 -> 0.028274792 | AH49: =AH48/AC48-1 -> 0.020192308 | AI49: =AI48/AD48-1 -> 0.0034642032 | AJ49: =AJ48/AE48-1 -> -0.003129489 | ... BA49: =BA48/AV48-1 -> -0.0056485487
C50: Q/Q Growth | Y50: =Y48/X48-1 -> 0.045572332 | Z50: =Z48/Y48-1 -> -0.0042045566 | AA50: =AA48/Z48-1 -> 0.0084991708 | AC50: =AC48/AA48-1 -> 0.010071942 | AD50: =AD48/AC48-1 -> 0.0093240093 | AE50: =AE48/AD48-1 -> -0.006996332 | AF50: =AF48/AE48-1 -> 0.0088511346 | AH50: =AH48/AF48-1 -> 0.008958959 | AI50: =AI48/AH48-1 -> -0.0072258875 | AJ50: =AJ48/AI48-1 -> -0.013521289 | AK50: =AK48/AJ48-1 -> 0.01370662 | AM50: =AM48/AK48-1 -> -0.012628444 | AN50: =AN48/AM48-1 -> -0.0099928822 | AO50: =AO48/AN48-1 -> 0.01085491 | AP50: =AP48/AO48-1 -> -0.018689566 | AR50: =AR48/AP48-1 -> -0.0064759803 | AS50: =AS48/AR48-1 -> 0.0097235902 | AT50: =AT48/AS48-1 -> -0.016216216 | AU50: =AU48/AT48-1 -> 0 | AW50: =AW48/AU48-1 -> 0 | AX50: =AX48/AW48-1 -> 0 | AY50: =AY48/AX48-1 -> 0 | AZ50: =AZ48/AY48-1 -> 0
A51: x | B51: Transaction Revenue | X51: 36600 | Y51: 48700 | Z51: 53600 | AA51: 69500 | AB51: =SUM(X51:AA51) -> 208400 | AC51: 78000 | AD51: 86600 | AE51: 88600 | AF51: 99900 | AG51: =SUM(AC51:AF51) -> 353100 | AH51: 106100 | AI51: 110600 | AJ51: 114300 | AK51: 126400 | AL51: =SUM(AH51:AK51) -> 457400 | AM51: 132604 | AN51: 133853 | AO51: =137900+8 -> 137908 | AP51: =150600+51 -> 150651 | AQ51: =SUM(AM51:AP51) -> 555016 | AR51: 157286 | AS51: 166500 | AT51: =AT45*AT48*100 -> 160977.2 | AU51: =AU45*AU48*100 -> 178416 | AV51: =SUM(AR51:AU51) -> 663179.2 | AW51: =AW45*AW48*100 -> 182800.8 | AX51: =AX45*AX48*100 -> 191646 | AY51: =AY45*AY48*100 -> 188600.88 | AZ51: =AZ45*AZ48*100 -> 209032.19 | BA51: =SUM(AW51:AZ51) -> 772079.87
C52: Y/Y Growth | AC52: =AC51/X51-1 -> 1.1311475 | AD52: =AD51/Y51-1 -> 0.77823409 | AE52: =AE51/Z51-1 -> 0.65298507 | AF52: =AF51/AA51-1 -> 0.43741007 | AG52: =AG51/AB51-1 -> 0.69433781 | AH52: =AH51/AC51-1 -> 0.36025641 | AI52: =AI51/AD51-1 -> 0.27713626 | AJ52: =AJ51/AE51-1 -> 0.29006772 | ... BA52: =BA51/AV51-1 -> 0.16421003
C53: Q/Q Growth | Y53: =Y51/X51-1 -> 0.33060109 | Z53: =Z51/Y51-1 -> 0.10061602 | AA53: =AA51/Z51-1 -> 0.29664179 | AC53: =AC51/AA51-1 -> 0.12230216 | AD53: =AD51/AC51-1 -> 0.11025641 | AE53: =AE51/AD51-1 -> 0.023094688 | AF53: =AF51/AE51-1 -> 0.1275395 | AH53: =AH51/AF51-1 -> 0.062062062 | AI53: =AI51/AH51-1 -> 0.042412818 | AJ53: =AJ51/AI51-1 -> 0.033453888 | AK53: =AK51/AJ51-1 -> 0.10586177 | AM53: =AM51/AK51-1 -> 0.049082278 | AN53: =AN51/AM51-1 -> 0.0094190221 | AO53: =AO51/AN51-1 -> 0.030294427 | AP53: =AP51/AO51-1 -> 0.092402181 | AR53: =AR51/AP51-1 -> 0.04404219 | AS53: =AS51/AR51-1 -> 0.058581183 | AT53: =AT51/AS51-1 -> -0.033169989 | AU53: =AU51/AT51-1 -> 0.10833089 | AW53: =AW51/AU51-1 -> 0.024576271 | AX53: =AX51/AW51-1 -> 0.048387097 | AY53: =AY51/AX51-1 -> -0.015889276 | AZ53: =AZ51/AY51-1 -> 0.10833089
A54: x | B54: Rewards Expense | AA54: 34400 | AC54: 39000 | AD54: 44000 | AE54: 43000 | AF54: 48700 | AG54: =SUM(AC54:AF54) -> 174700 | AH54: 51800 | AI54: 53700 | AJ54: 53800 | AK54: 60500 | AL54: =SUM(AH54:AK54) -> 219800 | AM54: 62100 | AN54: 64700 | AO54: 68400 | AP54: 76800 | AQ54: =SUM(AM54:AP54) -> 272000 | AR54: 81300 | AS54: 87000
C55: % of Transaction Revenue | AA55: =AA54/AA51 -> 0.49496403 | AC55: =AC54/AC51 -> 0.5 | AD55: =AD54/AD51 -> 0.50808314 | AE55: =AE54/AE51 -> 0.48532731 | AF55: =AF54/AF51 -> 0.48748749 | AG55: =AG54/AG51 -> 0.49476069 | AH55: =AH54/AH51 -> 0.48821866 | AI55: =AI54/AI51 -> 0.48553345 | AJ55: =AJ54/AJ51 -> 0.47069116 | ... AS55: =AS54/AS51 -> 0.52252252
C56: % of TPV (in BPs) | AA56: =AA55/AA52 -> #DIV/0! | AC56: =AC54/AC45/100 -> 130 | AD56: =AD54/AD45/100 -> 133.33333 | AE56: =AE54/AE45/100 -> 126.47059 | AF56: =AF54/AF45/100 -> 128.15789 | AG56: =AG55/AG52 -> 0.71256481 | AH56: =AH54/AH45/100 -> 129.5 | AI56: =AI54/AI45/100 -> 127.85714 | AJ56: =AJ54/AJ45/100 -> 122.27273 | AK56: =AK54/AK45/100 -> 126.04167 | AL56: =AL55/AL52 -> 1.6268404 | AM56: =AM54/AM45/100 -> 121.76471 | AN56: =AN54/AN45/100 -> 124.42308 | AO56: =AO54/AO45/100 -> 129.0566 | AP56: =AP54/AP45/100 -> 130.16949 | AQ56: =AQ55/AQ52 -> 2.2963525 | AR56: =AR54/AR45/100 -> 131.12903 | AS56: =AS54/AS45/100 -> 133.84615
B59: Embedded & Other Solutions | D59: =D$104 -> 1Q18 | E59: =E$104 -> 2Q18 | F59: =F$104 -> 3Q18 | G59: =G$104 -> 4Q18 | H59: =H$104 -> 2018 | I59: =I$104 -> 1Q19 | J59: =J$104 -> 2Q19 | K59: =K$104 -> 3Q19 | ... BA59: =BA$104 -> 2027E
A60: x | B60: Customers | AA60: 257600 | AC60: 270200 | AD60: 280700 | AE60: 294000 | AF60: 292400 | AG60: =AF60 -> 292400 | AH60: 297400 | AI60: 298700 | AJ60: 284700 | AK60: 288500 | AL60: =AK60 -> 288500 | AM60: 283700 | AN60: 282900 | AO60: 284200 | AP60: 283200 | AQ60: =AP60 -> 283200 | AR60: 282500 | AS60: 277000 | AT60: =AS60+AT61 -> 276000 | AU60: =AT60+AU61 -> 275000 | AV60: =AU60 -> 275000 | AW60: =AU60+AW61 -> 275100 | AX60: =AW60+AX61 -> 275200 | AY60: =AX60+AY61 -> 275300 | AZ60: =AY60+AZ61 -> 275400 | BA60: =AZ60 -> 275400
C61: Quarterly Adds | AC61: =AC60-AA60 -> 12600 | AD61: =AD60-AC60 -> 10500 | AE61: =AE60-AD60 -> 13300 | AF61: =AF60-AE60 -> -1600 | AG61: =SUM(AC61:AF61) -> 34800 | AH61: =AH60-AF60 -> 5000 | AI61: =AI60-AH60 -> 1300 | AJ61: =AJ60-AI60 -> -14000 | AK61: =AK60-AJ60 -> 3800 | AL61: =SUM(AH61:AK61) -> -3900 | AM61: =AM60-AK60 -> -4800 | AN61: =AN60-AM60 -> -800 | AO61: =AO60-AN60 -> 1300 | AP61: =AP60-AO60 -> -1000 | AQ61: =SUM(AM61:AP61) -> -5300 | AR61: =AR60-AP60 -> -700 | AS61: =AS60-AR60 -> -5500 | AT61: -1000 | AU61: -1000 | AV61: =SUM(AR61:AU61) -> -8200 | AW61: 100 | AX61: 100 | AY61: 100 | AZ61: 100 | BA61: =SUM(AW61:AZ61) -> 400
