Workbook
Name blank: #REF!
Name Current_Q: #REF!
Name export: #REF!
Name FY_92: #REF!
Name FY_93: #REF!
Name FY_94: #REF!
Name N_A: #REF!
Name N_M: #REF!
Name Next_Actual_Period_Range: '[1]Income Statement'!$D$3:$BE$6
Name NM_T: #REF!
Name Prior_Q: #REF!
Name Same_Q_Last_Yr: #REF!
Name source: #REF!
Name WIZARD_3YRATCF: #REF!
Name WIZARD_3YREBITDA: #REF!
Name WIZARD_3YRSECGROWTH: #REF!
Name WIZARD_AVGTRADINGVOLUME: #REF!
Name WIZARD_BKVALSHR: #REF!
Name WIZARD_BURNRATE: #REF!
Name WIZARD_CASH: #REF!
Name WIZARD_DIVYIELD: #REF!
Name WIZARD_EARNINGS: #REF!
Name WIZARD_EBITDABYSHROO: #REF!
Name WIZARD_EVBYEBITDAOO: #REF!
Name WIZARD_EVINVCAP: #REF!
Name WIZARD_LTDEBT: #REF!
Name WIZARD_MARKETCAP: #REF!
Name WIZARD_NETDEBTCAP: #REF!
Name WIZARD_OPERMARGIN: #REF!
Name WIZARD_PRICEESTNAV: #REF!
Name WIZARD_REVENUES: #REF!
Name WIZARD_ROAA: #REF!
Name WIZARD_ROAE: #REF!
Name WIZARD_ROE: #REF!
Name WIZARD_ROIC: #REF!
Name WIZARD_SHARESOUT: #REF!
Name WIZARD_STATIONREV: #REF!
Name WIZARD_TICKER: #REF!
Name WIZARD_TOTDEBTCAP: #REF!
Name WIZARD_Y1CAPREVR: [2]AMAT_FC!#REF!
Name WIZARD_Y1CAPREVS2: #REF!
Name WIZARD_Y1CASHCYEPSS1: #REF!
Name WIZARD_Y1CASHCYPES1: #REF!
Name WIZARD_Y1CYE: [2]AMAT_FC!#REF!
Name WIZARD_Y1CYPEE: [2]AMAT_FC!#REF!
Name WIZARD_Y1CYPES1: #REF!
Name WIZARD_Y1CYREVS2: #REF!
Name WIZARD_Y1CYS1: #REF!
Name WIZARD_Y1E: [2]AMAT_FC!#REF!
Name WIZARD_Y1EBITDAYRS2: #REF!
Name WIZARD_Y1EMVBYREV: #REF!
Name WIZARD_Y1EVEBITDAS2: #REF!
Name WIZARD_Y1PEE: [2]AMAT_FC!#REF!
Name WIZARD_Y1PES1: #REF!
Name WIZARD_Y1Q1E: [2]AMAT_FC!#REF!
Name WIZARD_Y1Q1R: [2]AMAT_FC!#REF!
Name WIZARD_Y1Q1S1: #REF!
Name WIZARD_Y1Q1S2: #REF!
Name WIZARD_Y1Q2E: [2]AMAT_FC!#REF!
Name WIZARD_Y1Q2R: [2]AMAT_FC!#REF!

Sheet Comparison
B2: ='Income Statement'!B2 -> Tyler Technologies (TYL) | N2: Guidance / Consensus Estimates
B4: Variance Analysis | D4: ='Income Statement'!CJ4 -> 4Q24 | E4: =K4 -> 4Q25 | F4: % Change | G4: ='Income Statement'!CN4 -> 3Q25 | H4: =K4 -> 4Q25 | I4: % Change | J4: 4Q25E | K4: ='Income Statement'!CO4 -> 4Q25 | L4: % Change | N4: 3Q Cons. | O4: 4Q Guide | P4: 4Q Cons. | Q4: FY21 G Prev | R4: FY21 G New | S4: FY21 Cons.
B5: Software License Revenue | D5: ='Income Statement'!CJ5 -> 6106 | E5: =K5 -> 5300 | F5: =E5/D5-1 -> -0.13200131 | G5: ='Income Statement'!CN5 -> 5100 | H5: =K5 -> 5300 | I5: =H5/G5-1 -> 0.039215686 | J5: 5300 | K5: ='Income Statement'!CO5 -> 5300 | L5: =K5/J5-1 -> 0
B6: Subscription Revenue | D6: ='Income Statement'!CJ8 -> 348836 | E6: =K6 -> 404858.03 | F6: =E6/D6-1 -> 0.16059705 | G6: ='Income Statement'!CN8 -> 401094 | H6: =K6 -> 404858.03 | I6: =H6/G6-1 -> 0.0093844186 | J6: 404858.03 | K6: ='Income Statement'!CO8 -> 404858.03 | L6: =K6/J6-1 -> 0
B7: Software Services Revenue | D7: ='Income Statement'!CJ11 -> 62795 | E7: =K7 -> 64000 | F7: =E7/D7-1 -> 0.019189426 | G7: ='Income Statement'!CN11 -> 64728 | H7: =K7 -> 64000 | I7: =H7/G7-1 -> -0.011247065 | J7: 64000 | K7: ='Income Statement'!CO11 -> 64000 | L7: =K7/J7-1 -> 0
B8: Maintenance Revenue | D8: ='Income Statement'!CJ14 -> 115018 | E8: =K8 -> 109500 | F8: =E8/D8-1 -> -0.0479751 | G8: ='Income Statement'!CN14 -> 111312 | H8: =K8 -> 109500 | I8: =H8/G8-1 -> -0.016278568 | J8: 109500 | K8: ='Income Statement'!CO14 -> 109500 | L8: =K8/J8-1 -> 0
B9: Appraisal Services Revenue | D9: ='Income Statement'!CJ17 -> 0 | E9: =K9 -> 0 | F9: =E9/D9-1 -> #DIV/0! | G9: ='Income Statement'!CN17 -> 0 | H9: =K9 -> 0 | I9: =H9/G9-1 -> #DIV/0! | J9: 0 | K9: ='Income Statement'!CO17 -> 0 | L9: =K9/J9-1 -> #DIV/0!
B10: Hardware & Other Revenue | D10: ='Income Statement'!CJ20 -> 8376 | E10: =K10 -> 6500 | F10: =E10/D10-1 -> -0.22397326 | G10: ='Income Statement'!CN20 -> 13645 | H10: =K10 -> 6500 | I10: =H10/G10-1 -> -0.52363503 | J10: 6500 | K10: ='Income Statement'!CO20 -> 6500 | L10: =K10/J10-1 -> 0
B11: Total Revenue | D11: =SUM(D5:D10) -> 541131 | E11: =K11 -> 590158.03 | F11: =E11/D11-1 -> 0.090601045 | G11: =SUM(G5:G10) -> 595879 | H11: =K11 -> 590158.03 | I11: =H11/G11-1 -> -0.0096008854 | J11: 590158.03 | K11: =SUM(K5:K10) -> 590158.03 | L11: =K11/J11-1 -> 0
B13: Cost of Revenue
B14: Software Licenses | D14: ='Income Statement'!CJ28 -> 1282 | E14: =K14 -> 2588 | F14: =E14/D14-1 -> 1.0187207 | G14: ='Income Statement'!CN28 -> 1669 | H14: =K14 -> 2588 | I14: =H14/G14-1 -> 0.55062912 | J14: 1855 | K14: ='Income Statement'!CO28 -> 2588 | L14: =K14/J14-1 -> 0.39514825
B15: Acquired software | D15: ='Income Statement'!BP30 -> 0 | E15: =K15 -> 0 | G15: ='Income Statement'!BS30 -> 0 | H15: =K15 -> 0 | J15: 0 | K15: ='Income Statement'!BU30 -> 0
B16: Software Services, Maint, & Subscrip. | D16: ='Income Statement'!CJ32 -> 279671 | E16: =K16 -> 285538 | F16: =E16/D16-1 -> 0.020978221 | G16: ='Income Statement'!CN32 -> 285958 | H16: =K16 -> 285538 | I16: =H16/G16-1 -> -0.0014687472 | J16: 286287.23 | K16: ='Income Statement'!CO32 -> 285538 | L16: =K16/J16-1 -> -0.002617046
B17: Appraisal Services | D17: ='Income Statement'!CJ34 -> 0 | E17: =K17 -> 0 | F17: =E17/D17-1 -> #DIV/0! | G17: ='Income Statement'!CN34 -> 0 | H17: =K17 -> 0 | I17: =H17/G17-1 -> #DIV/0! | J17: 0 | K17: ='Income Statement'!CO34 -> 0 | L17: =K17/J17-1 -> #DIV/0!
B18: Hardware & Other | D18: ='Income Statement'!CJ36 -> 5778 | E18: =K18 -> 6407 | F18: =E18/D18-1 -> 0.1088612 | G18: ='Income Statement'!CN36 -> 8117 | H18: =K18 -> 6407 | I18: =H18/G18-1 -> -0.21066897 | J18: 4875 | K18: ='Income Statement'!CO36 -> 6407 | L18: =K18/J18-1 -> 0.31425641
B19: Total Cost of Revenue | D19: =SUM(D14:D18) -> 286731 | E19: =K19 -> 294533 | F19: =E19/D19-1 -> 0.027210173 | G19: =SUM(G14:G18) -> 295744 | H19: =K19 -> 294533 | I19: =H19/G19-1 -> -0.0040947576 | J19: 293017.23 | K19: =SUM(K14:K18) -> 294533 | L19: =K19/J19-1 -> 0.0051729831
AC20: Feature | AD20: Traditional Payment Processor | AE20: Tyler Technologies (PayFac)
B21: Gross Profit | D21: =D11-D19 -> 254400 | E21: =K21 -> 295625.03 | F21: =E21/D21-1 -> 0.16204809 | G21: =G11-G19 -> 300135 | H21: =K21 -> 295625.03 | I21: =H21/G21-1 -> -0.015026458 | J21: 297140.81 | K21: =K11-K19 -> 295625.03 | L21: =K21/J21-1 -> -0.0051011949 | AC21: Merchant ID (MID) | AD21: Every single city or court needs its own unique MID from a bank. | AE21: Tyler has a Master MID. Agencies are "sub-merchants" under Tyler.
B22: Gross Margins | D22: =D21/D11 -> 0.47012646 | E22: =K22 -> 0.5009252 | F22: =E22-D22 -> 0.030798747 | G22: =G21/G11 -> 0.50368447 | H22: =K22 -> 0.5009252 | J22: 0.50349362 | K22: =K21/K11 -> 0.5009252 | AC22: Onboarding | AD22: Slow (2–4 weeks). Requires the city to pass bank credit checks. | AE22: Instant (Minutes/Hours). Tyler performs the "underwriting" itself.
AC23: Contracting | AD23: City must sign with a Bank, a Gateway, and a Software vendor. | AE23: Single Vendor. The city only signs a contract with Tyler.
B24: Operating Expenses | AC24: Risk & Liability | AD24: The bank/processor holds the fraud risk. | AE24: Tyler assumes the risk. If a sub-merchant (city) defaults, Tyler is liable.
B25: SG&A | D25: ='Income Statement'!CJ44+'Income Statement'!CJ46 -> 93194 | E25: =K25 -> 91755 | F25: =E25/D25-1 -> -0.015440908 | G25: ='Income Statement'!CN44+'Income Statement'!CN46 -> 93489 | H25: =K25 -> 91755 | I25: =H25/G25-1 -> -0.018547637 | J25: 98556.392 | K25: ='Income Statement'!CO44+'Income Statement'!CO46 -> 91755 | L25: =K25/J25-1 -> -0.069010153
B26: R&D | D26: ='Income Statement'!CJ48 -> 29435 | E26: =K26 -> 50364 | F26: =E26/D26-1 -> 0.71102429 | G26: ='Income Statement'!CN48 -> 48038 | H26: =K26 -> 50364 | I26: =H26/G26-1 -> 0.048420001 | J26: 50163.433 | K26: ='Income Statement'!CO48 -> 50364 | L26: =K26/J26-1 -> 0.0039982732
B27: Other | D27: ='Income Statement'!BP50 -> 0 | E27: =K27 -> 0 | G27: ='Income Statement'!BS50 -> 0 | H27: =K27 -> 0 | J27: 0 | K27: ='Income Statement'!AU50 -> 0
B28: Total Operating Expenses | D28: =SUM(D25:D27) -> 122629 | E28: =K28 -> 142119 | F28: =E28/D28-1 -> 0.15893467 | G28: =SUM(G25:G27) -> 141527 | H28: =K28 -> 142119 | I28: =H28/G28-1 -> 0.0041829474 | J28: 148719.82 | K28: =SUM(K25:K27) -> 142119 | L28: =K28/J28-1 -> -0.044384295
B30: Non-GAAP Operating Income (Loss) | D30: =D21-D28 -> 131771 | E30: =K30 -> 153506.03 | F30: =E30/D30-1 -> 0.1649455 | G30: =G21-G28 -> 158608 | H30: =K30 -> 153506.03 | I30: =H30/G30-1 -> -0.032167142 | J30: 148420.98 | K30: =K21-K28 -> 153506.03 | L30: =K30/J30-1 -> 0.034261001
B31: Non-GAAP Operating Margins | D31: =D30/D11 -> 0.24351035 | E31: =K31 -> 0.26011005 | F31: =E31-D31 -> 0.016599696 | G31: =G30/G11 -> 0.26617484 | H31: =K31 -> 0.26011005 | J31: 0.25149362 | K31: =K30/K11 -> 0.26011005
B33: GAAP & Non-cash charges | D33: ='Income Statement'!CJ64 -> 60085 | E33: =K33 -> 63552 | F33: =E33/D33-1 -> 0.057701589 | G33: ='Income Statement'!CN64 -> 60676 | H33: =K33 -> 63552 | I33: =H33/G33-1 -> 0.047399301 | J33: 62000 | K33: ='Income Statement'!CO64 -> 63552 | L33: =K33/J33-1 -> 0.025032258
B35: GAAP Operating Income | D35: =D30-D33 -> 71686 | E35: =K35 -> 89954.034 | F35: =E35/D35-1 -> 0.25483405 | G35: =G30-G33 -> 97932 | H35: =K35 -> 89954.034 | I35: =H35/G35-1 -> -0.081464343 | J35: 86420.983 | K35: =K30-K33 -> 89954.034 | L35: =K35/J35-1 -> 0.04088187
B36: GAAP Operating Margins | D36: =D35/D11 -> 0.13247439 | E36: =K36 -> 0.15242364 | G36: =G35/G11 -> 0.1643488 | H36: =K36 -> 0.15242364 | J36: 0.14643702 | K36: =K35/K11 -> 0.15242364
B38: Interest & Other Income (Expense) | D38: ='Income Statement'!CJ71 -> 5081 | E38: =K38 -> 9988 | F38: =E38/D38-1 -> 0.96575477 | G38: ='Income Statement'!CN71 -> 9620 | H38: =K38 -> 9988 | I38: =H38/G38-1 -> 0.038253638 | J38: 5765 | K38: ='Income Statement'!CO71 -> 9988 | L38: =K38/J38-1 -> 0.73252385
E39: =K39 -> 0 | H39: =K39 -> 0
B40: Non-GAAP Income before Taxes | D40: =D30+D38 -> 136852 | E40: =K40 -> 163494.03 | F40: =E40/D40-1 -> 0.19467771 | G40: =G30+G38 -> 168228 | H40: =K40 -> 163494.03 | I40: =H40/G40-1 -> -0.028140179 | J40: 154185.98 | K40: =K30+K38 -> 163494.03 | L40: =K40/J40-1 -> 0.060368986
B41: Income Tax | D41: ='Income Statement'!CJ79 -> 30107 | E41: =K41 -> 33416 | F41: =E41/D41-1 -> 0.10990799 | G41: ='Income Statement'!CN79 -> 37851 | H41: =K41 -> 33416 | I41: =H41/G41-1 -> -0.11716996 | J41: 34691.846 | K41: ='Income Statement'!CO79 -> 33416 | L41: =K41/J41-1 -> -0.036776541
B42: Non-GAAP Net Income | D42: =D40-D41 -> 106745 | E42: =K42 -> 130078.03 | F42: =E42/D42-1 -> 0.21858667 | G42: =G40-G41 -> 130377 | H42: =K42 -> 130078.03 | I42: =H42/G42-1 -> -0.0022930885 | J42: 119494.14 | K42: =K40-K41 -> 130078.03 | L42: =K42/J42-1 -> 0.088572526
B44: GAAP Income before Taxes | D44: =D35+D38 -> 76767 | E44: =K44 -> 99942.034 | F44: =E44/D44-1 -> 0.30188797 | G44: =G35+G38 -> 107552 | H44: =K44 -> 99942.034 | I44: =H44/G44-1 -> -0.070756155 | J44: 92185.983 | K44: =K35+K38 -> 99942.034 | L44: =K44/J44-1 -> 0.084134824
B45: Income Tax | D45: ='Income Statement'!CJ85 -> 11546 | E45: =K45 -> 19432 | F45: =E45/D45-1 -> 0.6830071 | G45: ='Income Statement'!CN85 -> 23159 | H45: =K45 -> 19432 | I45: =H45/G45-1 -> -0.16093096 | J45: 19819.986 | K45: ='Income Statement'!CO85 -> 19432 | L45: =K45/J45-1 -> -0.019575506
B46: GAAP Net Income | D46: =D44-D45 -> 65221 | E46: =K46 -> 80510.034 | F46: =E46/D46-1 -> 0.23441888 | G46: =G44-G45 -> 84393 | H46: =K46 -> 80510.034 | I46: =H46/G46-1 -> -0.046010522 | J46: 72365.996 | K46: =K44-K45 -> 80510.034 | L46: =K46/J46-1 -> 0.11253956
B48: Non-GAAP EPS | D48: =D42/D52 -> 2.4308845 | E48: =K48 -> 2.9873466 | F48: =E48/D48-1 -> 0.22891344 | G48: =G42/G52 -> 2.974335 | H48: =K48 -> 2.9873466 | I48: =H48/G48-1 -> 0.0043746356 | J48: 2.7322938 | K48: =K42/K52 -> 2.9873466 | L48: =K48/J48-1 -> 0.093347515
B49: GAAP EPS | D49: =D46/D52 -> 1.485266 | E49: =K49 -> 1.8489777 | G49: =G46/G52 -> 1.9252863 | H49: =K49 -> 1.8489777 | J49: 1.6546851 | K49: =K46/K52 -> 1.8489777
B51: Basic Shares Outstanding | D51: ='Income Statement'!CJ95 -> 42864 | E51: =K51 -> 43057 | G51: ='Income Statement'!CN95 -> 43135 | H51: =K51 -> 43057 | J51: 43335 | K51: ='Income Statement'!CO95 -> 43057
B52: Diluted Shares Outstanding | D52: ='Income Statement'!CJ96 -> 43912 | E52: =K52 -> 43543 | G52: ='Income Statement'!CN96 -> 43834 | H52: =K52 -> 43543 | J52: 43734 | K52: ='Income Statement'!CO96 -> 43543
B54: Source: Company reports and Needham & Co estimates

Sheet Income Statement
CM1: =(CM8+CM14)/CM23 -> 0.86761156 | CN1: =(CN8+CN14)/CN23 -> 0.85991619 | CO1: =(CO8+CO14)/CO23 -> 0.87155983 | CP1: =(CP8+CP14)/CP23 -> 0.8655628 | CQ1: =(CQ8+CQ14)/CQ23 -> 0.87346491 | CR1: =(CR8+CR14)/CR23 -> 0.87133137 | CS1: =(CS8+CS14)/CS23 -> 0.88022056 | CT1: =(CT8+CT14)/CT23 -> 0.88311691 | CU1: =(CU8+CU14)/CU23 -> 0.87704759
B2: Tyler Technologies (TYL) | CL2: =15000/4 -> 3750 | CO2: =CP60/CP96 -> 3.4528243 | CP2: =(+CP58+CP59)/CP96 -> 2.1421863 | CT2: =CU60/CU96 -> 3.2227133 | CU2: =(+CU58+CU59)/CU96 -> 1.929089 | CW2: 40000 | CX2: =CP8-40000 -> 1546016 | CY2: =CP8+CP11+CP14 -> 2283142
B4: Income Statement | D4: 2007 | E4: 1Q08 | F4: 2Q08 | G4: 3Q08 | H4: 4Q08 | I4: 2008 | J4: 1Q09 | K4: 2Q09 | L4: 3Q09 | M4: 4Q09 | N4: 2009 | O4: 1Q10 | P4: 2Q10 | Q4: 3Q10 | R4: 4Q10 | S4: 2010 | T4: 1Q11 | U4: 2Q11 | V4: 3Q11 | W4: 4Q11 | X4: 2011 | Y4: 1Q12 | Z4: 2Q12 | AA4: 3Q12 | AB4: 4Q12 | AC4: 2012 | AD4: 1Q13 | AE4: 2Q13 | AF4: 3Q13 | AG4: 4Q13 | AH4: 2013 | AI4: 1Q14 | AJ4: 2Q14 | AK4: 3Q14 | AL4: 4Q14 | AM4: 2014 | AN4: 1Q15 | AO4: 2Q15 | AP4: 3Q15 | AQ4: 4Q15 | AR4: 2015 | AS4: 1Q16 | AT4: 2Q16 | AU4: 3Q16 | AV4: 4Q16 | AW4: 2016 | AX4: 1Q17 | AY4: 2Q17 | AZ4: 3Q17 | BA4: 4Q17 | BB4: 2017 | BC4: 1Q18 | BD4: 2Q18 | BE4: 3Q18 | BF4: 4Q18 | BG4: 2018 | BH4: 1Q19 | BI4: 2Q19 | BJ4: 3Q19 | BK4: 4Q19 | BL4: 2019 | BM4: 1Q20 | BN4: 2Q20 | BO4: 3Q20 | BP4: 4Q20 | BQ4: 2020 | BR4: 1Q21 | BS4: 2Q21 | BT4: 3Q21 | BU4: 4Q21 | BV4: 2021 | BW4: 1Q22 | BX4: 2Q22 | BY4: 3Q22 | BZ4: 4Q22 | CA4: 2022 | CB4: 1Q23 | CC4: 2Q23 | CD4: 3Q23 | CE4: 4Q23 | CF4: 2023 | CG4: 1Q24 | CH4: 2Q24 | CI4: 3Q24 | CJ4: 4Q24 | CK4: 2024 | CL4: 1Q25 | CM4: 2Q25 | CN4: 3Q25 | CO4: 4Q25 | CP4: 2025 | CQ4: 1Q26E | CR4: 2Q26E | CS4: 3Q26E | CT4: 4Q26E | CU4: 2026E | CY4: =CP32 -> 1135423
B5: Software License Revenue | D5: 35063 | E5: 8369 | F5: 11905 | G5: 11372 | H5: =I5-G5-F5-E5 -> 9844 | I5: 41490 | J5: 10756 | K5: 9912 | L5: 10167 | M5: =N5-L5-K5-J5 -> 11296 | N5: 42131 | O5: 8449 | P5: 8735 | Q5: 9260 | R5: 8469 | S5: =SUM(O5:R5) -> 34913 | T5: 6822 | U5: 8308 | V5: 7631 | W5: 9833 | X5: =SUM(T5:W5) -> 32594 | Y5: 7563 | Z5: 8422 | AA5: 8973 | AB5: 8970 | AC5: =SUM(Y5:AB5) -> 33928 | AD5: 8830 | AE5: 10090 | AF5: 10495 | AG5: 11426 | AH5: =SUM(AD5:AG5) -> 40841 | AI5: 11232 | AJ5: 12083 | AK5: 13226 | AL5: 12524 | AM5: =SUM(AI5:AL5) -> 49065 | AN5: 14300 | AO5: 14586 | AP5: 15690 | AQ5: 14432 | AR5: =SUM(AN5:AQ5) -> 59008 | AS5: 16850 | AT5: 17551 | AU5: 19930 | AV5: 19975 | AW5: =SUM(AS5:AV5) -> 74306 | AX5: 18223 | AY5: 17107 | AZ5: 19842 | BA5: 20522 | BB5: =SUM(AX5:BA5) -> 75694 | BC5: 22776 | BD5: 22400 | BE5: 22444 | BF5: 25821 | BG5: =SUM(BC5:BF5) -> 93441 | BH5: 21793 | BI5: 20675 | BJ5: 25379 | BK5: =32358 -> 32358 | BL5: =SUM(BH5:BK5) -> 100205 | BM5: 18737 | BN5: =17025 -> 17025 | BO5: 19937 | BP5: 17465 | BQ5: =SUM(BM5:BP5) -> 73164 | BR5: 14933 | BS5: 17604 | BT5: 22673 | BU5: 19242 | BV5: =SUM(BR5:BU5) -> 74452 | BW5: 16506 | BX5: 15009 | BY5: 20269 | BZ5: 7622 | CA5: =SUM(BW5:BZ5) -> 59406 | CB5: 10130 | CC5: 9779 | CD5: 10554 | CE5: 7633 | CF5: =SUM(CB5:CE5) -> 38096 | CG5: 8734 | CH5: 5329 | CI5: 6188 | CJ5: 6106 | CK5: =SUM(CG5:CJ5) -> 26357 | CL5: 6994 | CM5: 3663 | CN5: 5100 | CO5: ='Revenue Build'!AF63 -> 5300 | CP5: =SUM(CL5:CO5) -> 21057 | CQ5: ='Revenue Build'!AH63 -> 3000 | CR5: ='Revenue Build'!AI63 -> 3000 | CS5: ='Revenue Build'!AJ63 -> 4000 | CT5: ='Revenue Build'!AK63 -> 4500 | CU5: =SUM(CQ5:CT5) -> 14500 | CV5: 0
C6: Y/Y Growth | I6: =I5/D5-1 -> 0.18329863 | J6: =J5/E5-1 -> 0.28521926 | K6: =K5/F5-1 -> -0.16740865 | L6: =L5/G5-1 -> -0.10596201 | M6: =M5/H5-1 -> 0.14750102 | N6: =N5/I5-1 -> 0.015449506 | O6: =O5/J5-1 -> -0.21448494 | P6: =P5/K5-1 -> -0.11874496 | ... CU6: =CU5/CP5-1 -> -0.31139289 | CX6: Recrruing, SaaS, Maintenace and Transactions Combined | DA6: Price | DB6: 215
C7: Q/Q Growth | F7: =F5/E5-1 -> 0.42251165 | G7: =G5/F5-1 -> -0.044771105 | H7: =H5/G5-1 -> -0.13436511 | J7: =J5/H5-1 -> 0.092645266 | K7: =K5/J5-1 -> -0.078467832 | L7: =L5/K5-1 -> 0.025726392 | M7: =M5/L5-1 -> 0.11104554 | O7: =O5/M5-1 -> -0.25203612 | P7: =P5/O5-1 -> 0.03385016 | Q7: =Q5/P5-1 -> 0.060103034 | R7: =R5/Q5-1 -> -0.085421166 | T7: =T5/R5-1 -> -0.19447396 | U7: =U5/T5-1 -> 0.21782468 | V7: =V5/U5-1 -> -0.081487723 | W7: =W5/V5-1 -> 0.28855982 | Y7: =Y5/W5-1 -> -0.23085528 | Z7: =Z5/Y5-1 -> 0.11357927 | AA7: =AA5/Z5-1 -> 0.06542389 | AB7: =AB5/AA5-1 -> -0.00033433634 | AD7: =AD5/AB5-1 -> -0.015607581 | AE7: =AE5/AD5-1 -> 0.14269536 | AF7: =AF5/AE5-1 -> 0.040138751 | AG7: =AG5/AF5-1 -> 0.088708909 | AI7: =AI5/AG5-1 -> -0.01697882 | AJ7: =AJ5/AI5-1 -> 0.07576567 | AK7: =AK5/AJ5-1 -> 0.094595713 | AL7: =AL5/AK5-1 -> -0.053077272 | AN7: =AN5/AL5-1 -> 0.14180773 | AO7: =AO5/AN5-1 -> 0.02 | AP7: =AP5/AO5-1 -> 0.075689017 | AQ7: =AQ5/AP5-1 -> -0.080178458 | AS7: =AS5/AQ5-1 -> 0.16754435 | AT7: =AT5/AS5-1 -> 0.041602374 | AU7: =AU5/AT5-1 -> 0.13554783 | AV7: =AV5/AU5-1 -> 0.0022579027 | AX7: =AX5/AV5-1 -> -0.087709637 | AY7: =AY5/AX5-1 -> -0.061241288 | AZ7: =AZ5/AY5-1 -> 0.15987607 | BA7: =BA5/AZ5-1 -> 0.034270739 | BC7: =BC5/BA5-1 -> 0.10983335 | BD7: =BD5/BC5-1 -> -0.016508606 | BE7: =BE5/BD5-1 -> 0.0019642857 | BF7: =BF5/BE5-1 -> 0.15046338 | BH7: =BH5/BF5-1 -> -0.15599706 | BI7: =BI5/BH5-1 -> -0.051300876 | BJ7: =BJ5/BI5-1 -> 0.22752116 | BK7: =BK5/BJ5-1 -> 0.27499113 | BM7: =BM5/BK5-1 -> -0.42094691 | BN7: =BN5/BM5-1 -> -0.091370017 | BO7: =BO5/BN5-1 -> 0.17104258 | BP7: =BP5/BO5-1 -> -0.12399057 | BR7: =BR5/BP5-1 -> -0.14497567 | BS7: =BS5/BR5-1 -> 0.1788656 | BT7: =BT5/BS5-1 -> 0.28794592 | BU7: =BU5/BT5-1 -> -0.15132536 | BW7: =BW5/BV5-1 -> -0.77830011 | BX7: =BX5/BW5-1 -> -0.090694293 | BY7: =BY5/BX5-1 -> 0.35045639 | BZ7: =BZ5/BY5-1 -> -0.62395777 | CB7: =CB5/BZ5-1 -> 0.32904749 | CC7: =CC5/CB5-1 -> -0.034649556 | CD7: =CD5/CC5-1 -> 0.079251457 | CE7: =CE5/CD5-1 -> -0.2767671 | CG7: =CG5/CE5-1 -> 0.14424211 | CH7: =CH5/CG5-1 -> -0.38985574 | CI7: =CI5/CH5-1 -> 0.16119347 | CJ7: =CJ5/CI5-1 -> -0.013251454 | CL7: =CL5/CJ5-1 -> 0.14543072 | CM7: =CM5/CL5-1 -> -0.47626537 | CN7: =CN5/CM5-1 -> 0.39230139 | CO7: =CO5/CN5-1 -> 0.039215686 | CQ7: =CQ5/CO5-1 -> -0.43396226 | CR7: =CR5/CQ5-1 -> 0 | CS7: =CS5/CR5-1 -> 0.33333333 | CT7: =CT5/CS5-1 -> 0.125 | DA7: Shares | DB7: 42200
B8: Subscription Revenue | D8: 10406 | E8: 3265 | F8: 3712 | G8: 3526 | H8: =I8-G8-F8-E8 -> 3871 | I8: 14374 | J8: 3976 | K8: 4160 | L8: 4558 | M8: =N8-L8-K8-J8 -> 4487 | N8: 17181 | O8: 5253 | P8: 5807 | Q8: 6020 | R8: 6218 | S8: =SUM(O8:R8) -> 23298 | T8: 6964 | U8: 7277 | V8: 7989 | W8: 8930 | X8: =SUM(T8:W8) -> 31160 | Y8: 9968 | Z8: 10553 | AA8: 11335 | AB8: 12762 | AC8: =SUM(Y8:AB8) -> 44618 | AD8: 13473 | AE8: 13863 | AF8: 15214 | AG8: 19314 | AH8: =SUM(AD8:AG8) -> 61864 | AI8: 20507 | AJ8: 20934 | AK8: 22694 | AL8: 23713 | AM8: =SUM(AI8:AL8) -> 87848 | AN8: 25288 | AO8: 26949 | AP8: 29036 | AQ8: 30660 | AR8: =SUM(AN8:AQ8) -> 111933 | AS8: 34089 | AT8: 33968 | AU8: 36869 | AV8: 37778 | AW8: =SUM(AS8:AV8) -> 142704 | AX8: 40102 | AY8: 40947 | AZ8: 44840 | BA8: 47621 | BB8: =SUM(AX8:BA8) -> 173510 | BC8: 49028 | BD8: =53009+1551+111 -> 54671 | BE8: =58699+1397+104 -> 60200 | BF8: =59811+952+100 -> 60863 | BG8: =SUM(BC8:BF8) -> 224762 | BH8: 67275 | BI8: 73475 | BJ8: 75272 | BK8: =80330 -> 80330 | BL8: =SUM(BH8:BK8) -> 296352 | BM8: 81723 | BN8: =85638 -> 85638 | BO8: 89290 | BP8: 93997 | BQ8: =SUM(BM8:BP8) -> 350648 | BR8: 102479 | BS8: =199558+1288 -> 200846 | BT8: =252942+751 -> 253693 | BU8: =229456+639 -> 230095 | BV8: =SUM(BR8:BU8) -> 787113 | BW8: 245443 | BX8: 255816 | BY8: 254346 | BZ8: 256699 | CA8: =SUM(BW8:BZ8) -> 1012304 | CB8: 280465 | CC8: 297789 | CD8: 295190 | CE8: 286068 | CF8: =SUM(CB8:CE8) -> 1159512 | CG8: 313243 | CH8: 333682 | CI8: 347170 | CJ8: 348836 | CK8: =SUM(CG8:CJ8) -> 1342931 | CL8: 374989 | CM8: 405075 | CN8: 401094 | CO8: ='Revenue Build'!AF65 -> 404858.03 | CP8: =SUM(CL8:CO8) -> 1586016 | CQ8: ='Revenue Build'!AH65 -> 424526.87 | CR8: ='Revenue Build'!AI65 -> 458453.83 | CS8: ='Revenue Build'!AJ65 -> 456704.14 | CT8: ='Revenue Build'!AK65 -> 461889.01 | CU8: =SUM(CQ8:CT8) -> 1801573.8 | CV8: =2095+2135 -> 4230 | CX8: =CF8+CF14 -> 1626173 | CY8: =CK8+CK14 -> 1806063 | DA8: Mkt | DB8: =DB7*DB6 -> 9073000
C9: Y/Y Growth | I9: =I8/D8-1 -> 0.38131847 | J9: =J8/E8-1 -> 0.21776417 | K9: =K8/F8-1 -> 0.12068966 | L9: =L8/G8-1 -> 0.29268293 | M9: =M8/H8-1 -> 0.15913201 | N9: =N8/I8-1 -> 0.19528315 | O9: =O8/J8-1 -> 0.32117706 | P9: =P8/K8-1 -> 0.39591346 | ... CU9: =CU8/CP8-1 -> 0.1359115 | CV9: =CV8/2 -> 2115 | CY9: =CY8/CX8-1 -> 0.11062169 | DA9: Net cash | DB9: =BS100 -> -1332692
C10: Q/Q Growth | F10: =F8/E8-1 -> 0.13690658 | G10: =G8/F8-1 -> -0.050107759 | H10: =H8/G8-1 -> 0.097844583 | J10: =J8/H8-1 -> 0.027124774 | K10: =K8/J8-1 -> 0.046277666 | L10: =L8/K8-1 -> 0.095673077 | M10: =M8/L8-1 -> -0.015577007 | O10: =O8/M8-1 -> 0.1707154 | P10: =P8/O8-1 -> 0.10546354 | Q10: =Q8/P8-1 -> 0.036679869 | R10: =R8/Q8-1 -> 0.032890365 | T10: =T8/R8-1 -> 0.11997427 | U10: =U8/T8-1 -> 0.044945434 | V10: =V8/U8-1 -> 0.097842518 | W10: =W8/V8-1 -> 0.11778696 | Y10: =Y8/W8-1 -> 0.1162374 | Z10: =Z8/Y8-1 -> 0.058687801 | AA10: =AA8/Z8-1 -> 0.074102151 | AB10: =AB8/AA8-1 -> 0.12589325 | AD10: =AD8/AB8-1 -> 0.055712271 | AE10: =AE8/AD8-1 -> 0.028946782 | AF10: =AF8/AE8-1 -> 0.097453654 | AG10: =AG8/AF8-1 -> 0.26948863 | AI10: =AI8/AG8-1 -> 0.061768665 | AJ10: =AJ8/AI8-1 -> 0.020822158 | AK10: =AK8/AJ8-1 -> 0.084073756 | AL10: =AL8/AK8-1 -> 0.044901736 | AN10: =AN8/AL8-1 -> 0.066419264 | AO10: =AO8/AN8-1 -> 0.065683328 | AP10: =AP8/AO8-1 -> 0.077442577 | AQ10: =AQ8/AP8-1 -> 0.055930569 | AS10: =AS8/AQ8-1 -> 0.11183953 | AT10: =AT8/AS8-1 -> -0.0035495321 | AU10: =AU8/AT8-1 -> 0.08540391 | AV10: =AV8/AU8-1 -> 0.024654859 | AX10: =AX8/AV8-1 -> 0.061517285 | AY10: =AY8/AX8-1 -> 0.021071268 | AZ10: =AZ8/AY8-1 -> 0.09507412 | BA10: =BA8/AZ8-1 -> 0.062020517 | BC10: =BC8/BA8-1 -> 0.029545789 | BD10: =BD8/BC8-1 -> 0.1150975 | BE10: =BE8/BD8-1 -> 0.10113223 | BF10: =BF8/BE8-1 -> 0.011013289 | BH10: =BH8/BF8-1 -> 0.10535136 | BI10: =BI8/BH8-1 -> 0.092159049 | BJ10: =BJ8/BI8-1 -> 0.024457298 | BK10: =BK8/BJ8-1 -> 0.067196301 | BM10: =BM8/BK8-1 -> 0.017340969 | BN10: =BN8/BM8-1 -> 0.04790573 | BO10: =BO8/BN8-1 -> 0.04264462 | BP10: =BP8/BO8-1 -> 0.05271587 | BR10: =BR8/BP8-1 -> 0.090236922 | BS10: =BS8/BR8-1 -> 0.95987471 | BT10: =BT8/BS8-1 -> 0.26312199 | BU10: =BU8/BT8-1 -> -0.093017939 | BW10: =BW8/BV8-1 -> -0.68817311 | BX10: =BX8/BW8-1 -> 0.042262358 | BY10: =BY8/BX8-1 -> -0.0057463177 | BZ10: =BZ8/BY8-1 -> 0.0092511775 | CB10: =CB8/BZ8-1 -> 0.092583142 | CC10: =CC8/CB8-1 -> 0.061768848 | CD10: =CD8/CC8-1 -> -0.0087276562 | CE10: =CE8/CD8-1 -> -0.030902131 | CG10: =CG8/CE8-1 -> 0.094994896 | CH10: =CH8/CG8-1 -> 0.065249662 | CI10: =CI8/CH8-1 -> 0.040421719 | CJ10: =CJ8/CI8-1 -> 0.0047988017 | CL10: =CL8/CJ8-1 -> 0.074972193 | CM10: =CM8/CL8-1 -> 0.080231687 | CN10: =CN8/CM8-1 -> -0.0098278097 | CO10: =CO8/CN8-1 -> 0.0093844186 | CQ10: =CQ8/CO8-1 -> 0.048582057 | CR10: =CR8/CQ8-1 -> 0.079917109 | CS10: =CS8/CR8-1 -> -0.0038165021 | CT10: =CT8/CS8-1 -> 0.011352797 | CX10: =2500+2550 -> 5050 | DA10: EV | DB10: =DB8-DB9 -> 10405692
B11: Software Services Revenue | D11: 60283 | E11: 16525 | F11: 19848 | G11: 18600 | H11: =I11-G11-F11-E11 -> 20024 | I11: 74997 | J11: 19232 | K11: 21330 | L11: 20383 | M11: =N11-L11-K11-J11 -> 19460 | N11: 80405 | O11: 17056 | P11: 18506 | Q11: 16718 | R11: 16060 | S11: =SUM(O11:R11) -> 68340 | T11: 16764 | U11: 17992 | V11: 17644 | W11: 17217 | X11: =SUM(T11:W11) -> 69617 | Y11: 18530 | Z11: 21737 | AA11: 22099 | AB11: 21042 | AC11: =SUM(Y11:AB11) -> 83408 | AD11: 20461 | AE11: 24085 | AF11: 24860 | AG11: 23861 | AH11: =SUM(AD11:AG11) -> 93267 | AI11: 24307 | AJ11: 30128 | AK11: 31159 | AL11: 28227 | AM11: =SUM(AI11:AL11) -> 113821 | AN11: 30804 | AO11: 34563 | AP11: 36398 | AQ11: 38087 | AR11: =SUM(AN11:AQ11) -> 139852 | AS11: 42430 | AT11: 46040 | AU11: 44738 | AV11: 41595 | AW11: =SUM(AS11:AV11) -> 174803 | AX11: 45018 | AY11: 47372 | AZ11: 47479 | BA11: 47280 | BB11: =SUM(AX11:BA11) -> 187149 | BC11: 45939 | BD11: 50674 | BE11: 48199 | BF11: 46457 | BG11: =SUM(BC11:BF11) -> 191269 | BH11: 48443 | BI11: 57401 | BJ11: =54997 -> 54997 | BK11: =52220 -> 52220 | BL11: =SUM(BH11:BK11) -> 213061 | BM11: 52133 | BN11: =43654 -> 43654 | BO11: 47946 | BP11: 42676 | BQ11: =SUM(BM11:BP11) -> 186409 | BR11: 47640 | BS11: =53337 -> 53337 | BT11: 54624 | BU11: 53790 | BV11: =SUM(BR11:BU11) -> 209391 | BW11: 61497 | BX11: 63125 | BY11: 63180 | BZ11: 55315 | CA11: =SUM(BW11:BZ11) -> 243117 | CB11: 60929 | CC11: 66420 | CD11: 61126 | CE11: 61501 | CF11: =SUM(CB11:CE11) -> 249976 | CG11: 64806 | CH11: 71928 | CI11: 64462 | CJ11: =62795 -> 62795 | CK11: =SUM(CG11:CJ11) -> 263991 | CL11: 64050 | CM11: 58612 | CN11: 64728 | CO11: ='Revenue Build'!AF67 -> 64000 | CP11: =SUM(CL11:CO11) -> 251390 | CQ11: ='Revenue Build'!AH67 -> 66000 | CR11: ='Revenue Build'!AI67 -> 66000 | CS11: ='Revenue Build'!AJ67 -> 65500 | CT11: ='Revenue Build'!AK67 -> 64000 | CU11: =SUM(CQ11:CT11) -> 261500 | CX11: =CX10/2 -> 2525 | DA11: NY Rev | DB11: =BL23 -> 1091356
C12: Y/Y Growth | I12: =I11/D11-1 -> 0.24408208 | J12: =J11/E11-1 -> 0.16381241 | K12: =K11/F11-1 -> 0.074667473 | L12: =L11/G11-1 -> 0.095860215 | M12: =M11/H11-1 -> -0.028166201 | N12: =N11/I11-1 -> 0.072109551 | O12: =O11/J11-1 -> -0.11314476 | P12: =P11/K11-1 -> -0.13239569 | ... CU12: =CU11/CP11-1 -> 0.040216397 | CW12: =BL8/BL23 -> 0.27154476 | DA12: EV/REV | DB12: =DB10/DB11 -> 9.534645
C13: Q/Q Growth | F13: =F11/E11-1 -> 0.20108926 | G13: =G11/F11-1 -> -0.062877872 | H13: =H11/G11-1 -> 0.07655914 | J13: =J11/H11-1 -> -0.039552537 | K13: =K11/J11-1 -> 0.10908902 | L13: =L11/K11-1 -> -0.044397562 | M13: =M11/L11-1 -> -0.045282834 | O13: =O11/M11-1 -> -0.12353546 | P13: =P11/O11-1 -> 0.085014071 | Q13: =Q11/P11-1 -> -0.096617313 | R13: =R11/Q11-1 -> -0.039358775 | T13: =T11/R11-1 -> 0.043835616 | U13: =U11/T11-1 -> 0.073252207 | V13: =V11/U11-1 -> -0.01934193 | W13: =W11/V11-1 -> -0.024200861 | Y13: =Y11/W11-1 -> 0.076261834 | Z13: =Z11/Y11-1 -> 0.1730707 | AA13: =AA11/Z11-1 -> 0.016653632 | AB13: =AB11/AA11-1 -> -0.047830219 | AD13: =AD11/AB11-1 -> -0.027611444 | AE13: =AE11/AD11-1 -> 0.17711744 | AF13: =AF11/AE11-1 -> 0.032177704 | AG13: =AG11/AF11-1 -> -0.040185036 | AI13: =AI11/AG11-1 -> 0.018691589 | AJ13: =AJ11/AI11-1 -> 0.23947834 | AK13: =AK11/AJ11-1 -> 0.034220659 | AL13: =AL11/AK11-1 -> -0.094098013 | AN13: =AN11/AL11-1 -> 0.091295568 | AO13: =AO11/AN11-1 -> 0.12202961 | AP13: =AP11/AO11-1 -> 0.053091456 | AQ13: =AQ11/AP11-1 -> 0.046403649 | AS13: =AS11/AQ11-1 -> 0.11402841 | AT13: =AT11/AS11-1 -> 0.08508131 | AU13: =AU11/AT11-1 -> -0.028279757 | AV13: =AV11/AU11-1 -> -0.070253476 | AX13: =AX11/AV11-1 -> 0.082293545 | AY13: =AY11/AX11-1 -> 0.052290195 | AZ13: =AZ11/AY11-1 -> 0.0022587182 | BA13: =BA11/AZ11-1 -> -0.0041913267 | BC13: =BC11/BA11-1 -> -0.028362944 | BD13: =BD11/BC11-1 -> 0.10307146 | BE13: =BE11/BD11-1 -> -0.048841615 | BF13: =BF11/BE11-1 -> -0.036141829 | BH13: =BH11/BF11-1 -> 0.042749209 | BI13: =BI11/BH11-1 -> 0.18491836 | BJ13: =BJ11/BI11-1 -> -0.041880803 | BK13: =BK11/BJ11-1 -> -0.050493663 | BM13: =BM11/BK11-1 -> -0.0016660283 | BN13: =BN11/BM11-1 -> -0.1626417 | BO13: =BO11/BN11-1 -> 0.098318596 | BP13: =BP11/BO11-1 -> -0.10991532 | BR13: =BR11/BP11-1 -> 0.11631831 | BS13: =BS11/BR11-1 -> 0.11958438 | BT13: =BT11/BS11-1 -> 0.024129591 | BU13: =BU11/BT11-1 -> -0.015268014 | BW13: =BW11/BV11-1 -> -0.70630543 | BX13: =BX11/BW11-1 -> 0.026472836 | BY13: =BY11/BX11-1 -> 0.00087128713 | BZ13: =BZ11/BY11-1 -> -0.1244856 | CB13: =CB11/BZ11-1 -> 0.10149146 | CC13: =CC11/CB11-1 -> 0.090121289 | CD13: =CD11/CC11-1 -> -0.079704908 | CE13: =CE11/CD11-1 -> 0.006134869 | CG13: =CG11/CE11-1 -> 0.053738964 | CH13: =CH11/CG11-1 -> 0.10989723 | CI13: =CI11/CH11-1 -> -0.10379824 | CJ13: =CJ11/CI11-1 -> -0.025860197 | CL13: =CL11/CJ11-1 -> 0.019985668 | CM13: =CM11/CL11-1 -> -0.08490242 | CN13: =CN11/CM11-1 -> 0.10434723 | CO13: =CO11/CN11-1 -> -0.011247065 | CQ13: =CQ11/CO11-1 -> 0.03125 | CR13: =CR11/CQ11-1 -> 0 | CS13: =CS11/CR11-1 -> -0.0075757576 | CT13: =CT11/CS11-1 -> -0.022900763 | CW13: =BL14/BL23 -> 0.39881304
B14: Maintenance Revenue | D14: 85411 | E14: 24849 | F14: 25900 | G14: 28353 | H14: =I14-G14-F14-E14 -> 28356 | I14: 107458 | J14: 29138 | K14: 30224 | L14: 32744 | M14: =N14-L14-K14-J14 -> 32406 | N14: 124512 | O14: 33416 | P14: 33212 | Q14: 34729 | R14: 34298 | S14: =SUM(O14:R14) -> 135655 | T14: 35512 | U14: 35056 | V14: 37011 | W14: 38919 | X14: =SUM(T14:W14) -> 146498 | Y14: 39850 | Z14: 42060 | AA14: 44452 | AB14: 45489 | AC14: =SUM(Y14:AB14) -> 171851 | AD14: 46050 | AE14: 46639 | AF14: 49291 | AG14: 49740 | AH14: =SUM(AD14:AG14) -> 191720 | AI14: 50240 | AJ14: 51951 | AK14: 54713 | AL14: 55792 | AM14: =SUM(AI14:AL14) -> 212696 | AN14: 57348 | AO14: 59463 | AP14: 61018 | AQ14: =67708+3186+37 -> 70931 | AR14: =SUM(AN14:AQ14) -> 248760 | AS14: =76032+5584+111 -> 81727 | AT14: =78743+4666+111 -> 83520 | AU14: =83000+3149+111 -> 86260 | AV14: =85194+1664+111 -> 86969 | AW14: =SUM(AS14:AV14) -> 338476 | AX14: =86859+204+111 -> 87174 | AY14: =89412+184+111 -> 89707 | AZ14: =92285+151+111 -> 92547 | BA14: =93013+124+111 -> 93248 | BB14: =SUM(AX14:BA14) -> 362676 | BC14: =93897+100+111 -> 94108 | BD14: 96076 | BE14: 96215 | BF14: 98333 | BG14: =SUM(BC14:BF14) -> 384732 | BH14: =100152+1597+100 -> 101849 | BI14: =106689+2757+100 -> 109546 | BJ14: =109833+1698+89 -> 111620 | BK14: =113644-1495+83 -> 112232 | BL14: =SUM(BH14:BK14) -> 435247 | BM14: =114365+160+79 -> 114604 | BN14: =116760+160+78 -> 116998 | BO14: =117979+113+78 -> 118170 | BP14: =118409+45+78 -> 118532 | BQ14: =SUM(BM14:BP14) -> 468304 | BR14: 119112 | BS14: 119621 | BT14: 117833 | BU14: 117721 | BV14: =SUM(BR14:BU14) -> 474287 | BW14: 117029 | BX14: 116815 | BY14: 117338 | BZ14: 117273 | CA14: =SUM(BW14:BZ14) -> 468455 | CB14: 115130 | CC14: 116539 | CD14: 117484 | CE14: 117508 | CF14: =SUM(CB14:CE14) -> 466661 | CG14: 117218 | CH14: 115309 | CI14: 115587 | CJ14: 115018 | CK14: =SUM(CG14:CJ14) -> 463132 | CL14: 112801 | CM14: 112123 | CN14: 111312 | CO14: ='Revenue Build'!AF69 -> 109500 | CP14: =SUM(CL14:CO14) -> 445736 | CQ14: ='Revenue Build'!AH69 -> 107000 | CR14: ='Revenue Build'!AI69 -> 107000 | CS14: ='Revenue Build'!AJ69 -> 104000 | CT14: ='Revenue Build'!AK69 -> 101000 | CU14: =SUM(CQ14:CT14) -> 419000 | CV14: 900 | DA14: EV/Rev | DB14: 14.5
C15: Y/Y Growth | I15: =I14/D14-1 -> 0.25812834 | J15: =J14/E14-1 -> 0.17260252 | K15: =K14/F14-1 -> 0.16694981 | L15: =L14/G14-1 -> 0.15486897 | M15: =M14/H14-1 -> 0.14282691 | N15: =N14/I14-1 -> 0.15870387 | O15: =O14/J14-1 -> 0.14681859 | P15: =P14/K14-1 -> 0.098861832 | ... CU15: =CU14/CP14-1 -> -0.059981693 | DA15: EV | DB15: =DB14*1800000 -> 26100000
C16: Q/Q Growth | F16: =F14/E14-1 -> 0.042295465 | G16: =G14/F14-1 -> 0.094710425 | H16: =H14/G14-1 -> 0.00010580891 | J16: =J14/H14-1 -> 0.027577938 | K16: =K14/J14-1 -> 0.037270918 | L16: =L14/K14-1 -> 0.083377448 | M16: =M14/L14-1 -> -0.010322502 | O16: =O14/M14-1 -> 0.031167068 | P16: =P14/O14-1 -> -0.0061048599 | Q16: =Q14/P14-1 -> 0.045676262 | R16: =R14/Q14-1 -> -0.012410377 | T16: =T14/R14-1 -> 0.03539565 | U16: =U14/T14-1 -> -0.01284073 | V16: =V14/U14-1 -> 0.055767914 | W16: =W14/V14-1 -> 0.051552241 | Y16: =Y14/W14-1 -> 0.023921478 | Z16: =Z14/Y14-1 -> 0.055457967 | AA16: =AA14/Z14-1 -> 0.056871136 | AB16: =AB14/AA14-1 -> 0.023328534 | AD16: =AD14/AB14-1 -> 0.012332652 | AE16: =AE14/AD14-1 -> 0.012790445 | AF16: =AF14/AE14-1 -> 0.056862283 | AG16: =AG14/AF14-1 -> 0.009109168 | AI16: =AI14/AG14-1 -> 0.010052272 | AJ16: =AJ14/AI14-1 -> 0.034056529 | AK16: =AK14/AJ14-1 -> 0.053165483 | AL16: =AL14/AK14-1 -> 0.01972109 | AN16: =AN14/AL14-1 -> 0.027889303 | AO16: =AO14/AN14-1 -> 0.0368801 | AP16: =AP14/AO14-1 -> 0.026150716 | AQ16: =AQ14/AP14-1 -> 0.16246026 | AS16: =AS14/AQ14-1 -> 0.15220425 | AT16: =AT14/AS14-1 -> 0.021938894 | AU16: =AU14/AT14-1 -> 0.032806513 | AV16: =AV14/AU14-1 -> 0.0082193369 | AX16: =AX14/AV14-1 -> 0.0023571617 | AY16: =AY14/AX14-1 -> 0.029056829 | AZ16: =AZ14/AY14-1 -> 0.031658622 | BA16: =BA14/AZ14-1 -> 0.0075745297 | BC16: =BC14/BA14-1 -> 0.0092227179 | BD16: =BD14/BC14-1 -> 0.020912143 | BE16: =BE14/BD14-1 -> 0.0014467713 | BF16: =BF14/BE14-1 -> 0.0220132 | BH16: =BH14/BF14-1 -> 0.035756053 | BI16: =BI14/BH14-1 -> 0.075572661 | BJ16: =BJ14/BI14-1 -> 0.018932686 | BK16: =BK14/BJ14-1 -> 0.0054828884 | BM16: =BM14/BK14-1 -> 0.021134792 | BN16: =BN14/BM14-1 -> 0.020889323 | BO16: =BO14/BN14-1 -> 0.010017265 | BP16: =BP14/BO14-1 -> 0.0030633833 | BR16: =BR14/BP14-1 -> 0.0048931934 | BS16: =BS14/BR14-1 -> 0.004273289 | BT16: =BT14/BS14-1 -> -0.014947208 | BU16: =BU14/BT14-1 -> -0.00095049774 | BW16: =BW14/BV14-1 -> -0.75325278 | BX16: =BX14/BW14-1 -> -0.0018286066 | BY16: =BY14/BX14-1 -> 0.0044771647 | BZ16: =BZ14/BY14-1 -> -0.00055395524 | CB16: =CB14/BZ14-1 -> -0.018273601 | CC16: =CC14/CB14-1 -> 0.012238339 | CD16: =CD14/CC14-1 -> 0.0081088734 | CE16: =CE14/CD14-1 -> 0.00020428314 | CG16: =CG14/CE14-1 -> -0.0024679171 | CH16: =CH14/CG14-1 -> -0.016285895 | CI16: =CI14/CH14-1 -> 0.0024109133 | CJ16: =CJ14/CI14-1 -> -0.0049226989 | CL16: =CL14/CJ14-1 -> -0.019275244 | CM16: =CM14/CL14-1 -> -0.006010585 | CN16: =CN14/CM14-1 -> -0.0072331279 | CO16: =CO14/CN14-1 -> -0.016278568 | CQ16: =CQ14/CO14-1 -> -0.02283105 | CR16: =CR14/CQ14-1 -> 0 | CS16: =CS14/CR14-1 -> -0.028037383 | CT16: =CT14/CS14-1 -> -0.028846154 | CX16: =0.22*CA23 -> 407044.88 | DA16: Net Cash | DB16: =DB9 -> -1332692
B17: Appraisal Service Revenue | D17: 21318 | E17: 4582 | F17: 4378 | G17: 5289 | H17: =I17-G17-F17-E17 -> 4849 | I17: 19098 | J17: 4892 | K17: 5054 | L17: 4692 | M17: =N17-L17-K17-J17 -> 4102 | N17: 18740 | O17: 4275 | P17: 4925 | Q17: 5612 | R17: 5742 | S17: =SUM(O17:R17) -> 20554 | T17: 6197 | U17: 5987 | V17: 5761 | W17: 5283 | X17: =SUM(T17:W17) -> 23228 | Y17: 5682 | Z17: 5771 | AA17: 5594 | AB17: 5496 | AC17: =SUM(Y17:AB17) -> 22543 | AD17: 5591 | AE17: 5056 | AF17: 5207 | AG17: 4971 | AH17: =SUM(AD17:AG17) -> 20825 | AI17: 4851 | AJ17: 5444 | AK17: 5802 | AL17: 5705 | AM17: =SUM(AI17:AL17) -> 21802 | AN17: 6089 | AO17: 6691 | AP17: 6557 | AQ17: 5728 | AR17: =SUM(AN17:AQ17) -> 25065 | AS17: 6558 | AT17: 6984 | AU17: 6541 | AV17: 6204 | AW17: =SUM(AS17:AV17) -> 26287 | AX17: 6612 | AY17: 6366 | AZ17: 6290 | BA17: 5755 | BB17: =SUM(AX17:BA17) -> 25023 | BC17: 5394 | BD17: 5532 | BE17: 5544 | BF17: 5376 | BG17: =SUM(BC17:BF17) -> 21846 | BH17: 5214 | BI17: 6233 | BJ17: =6008 -> 6008 | BK17: =6024 -> 6024 | BL17: =SUM(BH17:BK17) -> 23479 | BM17: 5763 | BN17: =4696 -> 4696 | BO17: 5394 | BP17: 5274 | BQ17: =SUM(BM17:BP17) -> 21127 | BR17: 6465 | BS17: 6265 | BT17: 7146 | BU17: 7912 | BV17: =SUM(BR17:BU17) -> 27788 | BW17: 8518 | BX17: 8812 | BY17: 8638 | BZ17: 8540 | CA17: =SUM(BW17:BZ17) -> 34508 | CW17: 1952 | CX17: =CW17*1.1 -> 2147.2 | CY17: =CX17*1.1 -> 2361.92 | DA17: Mkt | DB17: =DB16+DB15 -> 24767308
C18: Y/Y Growth | I18: =I17/D17-1 -> -0.10413735 | J18: =J17/E17-1 -> 0.067656045 | K18: =K17/F17-1 -> 0.15440841 | L18: =L17/G17-1 -> -0.11287578 | M18: =M17/H17-1 -> -0.15405238 | N18: =N17/I17-1 -> -0.018745418 | O18: =O17/J17-1 -> -0.12612428 | P18: =P17/K17-1 -> -0.025524337 | ... CA18: =CA17/BV17-1 -> 0.24183101 | DA18: Share | DB18: =DB7 -> 42200
C19: Q/Q Growth | F19: =F17/E17-1 -> -0.044522043 | G19: =G17/F17-1 -> 0.20808588 | H19: =H17/G17-1 -> -0.08319153 | J19: =J17/H17-1 -> 0.0088678078 | K19: =K17/J17-1 -> 0.03311529 | L19: =L17/K17-1 -> -0.071626435 | M19: =M17/L17-1 -> -0.12574595 | O19: =O17/M17-1 -> 0.042174549 | P19: =P17/O17-1 -> 0.15204678 | Q19: =Q17/P17-1 -> 0.13949239 | R19: =R17/Q17-1 -> 0.023164647 | T19: =T17/R17-1 -> 0.079240683 | U19: =U17/T17-1 -> -0.033887365 | V19: =V17/U17-1 -> -0.037748455 | W19: =W17/V17-1 -> -0.082971706 | Y19: =Y17/W17-1 -> 0.07552527 | Z19: =Z17/Y17-1 -> 0.015663499 | AA19: =AA17/Z17-1 -> -0.030670594 | AB19: =AB17/AA17-1 -> -0.01751877 | AD19: =AD17/AB17-1 -> 0.017285298 | AE19: =AE17/AD17-1 -> -0.095689501 | AF19: =AF17/AE17-1 -> 0.029865506 | AG19: =AG17/AF17-1 -> -0.045323603 | AI19: =AI17/AG17-1 -> -0.024140012 | AJ19: =AJ17/AI17-1 -> 0.12224284 | AK19: =AK17/AJ17-1 -> 0.06576047 | AL19: =AL17/AK17-1 -> -0.016718373 | AN19: =AN17/AL17-1 -> 0.067309378 | AO19: =AO17/AN17-1 -> 0.098866809 | AP19: =AP17/AO17-1 -> -0.020026902 | AQ19: =AQ17/AP17-1 -> -0.12642977 | AS19: =AS17/AQ17-1 -> 0.14490223 | AT19: =AT17/AS17-1 -> 0.064958829 | AU19: =AU17/AT17-1 -> -0.063430699 | AV19: =AV17/AU17-1 -> -0.051521174 | AX19: =AX17/AV17-1 -> 0.065764023 | AY19: =AY17/AX17-1 -> -0.037205082 | AZ19: =AZ17/AY17-1 -> -0.011938423 | BA19: =BA17/AZ17-1 -> -0.085055644 | BC19: =BC17/BA17-1 -> -0.062728063 | BD19: =BD17/BC17-1 -> 0.025583982 | BE19: =BE17/BD17-1 -> 0.0021691974 | BF19: =BF17/BE17-1 -> -0.03030303 | BH19: =BH17/BF17-1 -> -0.030133929 | BI19: =BI17/BH17-1 -> 0.19543537 | BJ19: =BJ17/BI17-1 -> -0.036098187 | BK19: =BK17/BJ17-1 -> 0.0026631158 | BM19: =BM17/BK17-1 -> -0.043326693 | BN19: =BN17/BM17-1 -> -0.18514663 | BO19: =BO17/BN17-1 -> 0.14863714 | BP19: =BP17/BO17-1 -> -0.022246941 | BR19: =BR17/BP17-1 -> 0.2258248 | BS19: =BS17/BR17-1 -> -0.030935808 | BT19: =BT17/BS17-1 -> 0.14062251 | BU19: =BU17/BT17-1 -> 0.10719284 | BW19: =BW17/BV17-1 -> -0.6934648 | BX19: =BX17/BW17-1 -> 0.034515144 | BY19: =BY17/BX17-1 -> -0.019745801 | BZ19: =BZ17/BY17-1 -> -0.011345219 | DA19: Price | DB19: =DB17/DB18 -> 586.90303
B20: Hardware & Other Revenue | D20: 7315 | E20: 1761 | F20: 1826 | G20: 1497 | H20: =I20-G20-F20-E20 -> 2600 | I20: 7684 | J20: 1571 | K20: 1492 | L20: 1788 | M20: =N20-L20-K20-J20 -> 2466 | N20: 7317 | O20: 1371 | P20: 1415 | Q20: 1430 | R20: 1652 | S20: =SUM(O20:R20) -> 5868 | T20: 1134 | U20: 2115 | V20: 1148 | W20: 1897 | X20: =SUM(T20:W20) -> 6294 | Y20: =1251-121 -> 1130 | Z20: 2825 | AA20: 1392 | AB20: 1609 | AC20: =SUM(Y20:AB20) -> 6956 | AD20: 1394 | AE20: 3355 | AF20: 1954 | AG20: 1423 | AH20: =SUM(AD20:AG20) -> 8126 | AI20: 1489 | AJ20: 3831 | AK20: 1070 | AL20: 1479 | AM20: =SUM(AI20:AL20) -> 7869 | AN20: 1137 | AO20: 4043 | AP20: 2146 | AQ20: 2301 | AR20: =SUM(AN20:AQ20) -> 9627 | AS20: 3334 | AT20: 5686 | AU20: 3419 | AV20: 2535 | AW20: =SUM(AS20:AV20) -> 14974 | AX20: 2728 | AY20: 7919 | AZ20: 3410 | BA20: 3660 | BB20: =SUM(AX20:BA20) -> 17717 | BC20: 4140 | BD20: 8369 | BE20: 4966 | BF20: 6183 | BG20: =SUM(BC20:BF20) -> 23658 | BH20: 4189 | BI20: 10651 | BJ20: =3911 -> 3911 | BK20: =4261 -> 4261 | BL20: =SUM(BH20:BK20) -> 23012 | BM20: 3820 | BN20: =3318 -> 3318 | BO20: 5200 | BP20: 5464 | BQ20: =SUM(BM20:BP20) -> 17802 | BR20: 4173 | BS20: =7690 -> 7690 | BT20: 4655 | BU20: 5416 | BV20: =SUM(BR20:BU20) -> 21934 | BW20: 7115 | BX20: 9108 | BY20: 9420 | BZ20: 6771 | CA20: =SUM(BW20:BZ20) -> 32414 | CB20: 5199 | CC20: 13752 | CD20: 10330 | CE20: 8225 | CF20: =SUM(CB20:CE20) -> 37506 | CG20: 8358 | CH20: 14728 | CI20: 9930 | CJ20: 8376 | CK20: =SUM(CG20:CJ20) -> 41392 | CL20: 6331 | CM20: 16644 | CN20: 13645 | CO20: ='Revenue Build'!AF73 -> 6500 | CP20: =SUM(CL20:CO20) -> 43120 | CQ20: ='Revenue Build'!AH73 -> 8000 | CR20: ='Revenue Build'!AI73 -> 14500 | CS20: ='Revenue Build'!AJ73 -> 6800 | CT20: ='Revenue Build'!AK73 -> 6000 | CU20: =SUM(CQ20:CT20) -> 35300 | CV20: 38
C21: Y/Y Growth | F21: =F20/E20-1 -> 0.036910846 | G21: =G20/F20-1 -> -0.18017525 | H21: =H20/G20-1 -> 0.73680695 | I21: =I20/D20-1 -> 0.050444293 | J21: =J20/E20-1 -> -0.10789324 | K21: =K20/F20-1 -> -0.18291347 | L21: =L20/G20-1 -> 0.19438878 | M21: =M20/H20-1 -> -0.051538462 | N21: =N20/I20-1 -> -0.047761583 | O21: =O20/J20-1 -> -0.12730745 | P21: =P20/K20-1 -> -0.051608579 | ... CU21: =CU20/CP20-1 -> -0.18135436 | CX21: =CF23 -> 1951751 | CY21: =CF23*1.1^7 -> 3803410.5 | DA21: Upside | DB21: =DB19/DB6-1 -> 1.7297815
C22: Q/Q Growth | J22: =J20/H20-1 -> -0.39576923 | K22: =K20/J20-1 -> -0.050286442 | L22: =L20/K20-1 -> 0.19839142 | M22: =M20/L20-1 -> 0.37919463 | O22: =O20/M20-1 -> -0.44403893 | P22: =P20/O20-1 -> 0.032093363 | Q22: =Q20/P20-1 -> 0.010600707 | R22: =R20/Q20-1 -> 0.15524476 | T22: =T20/R20-1 -> -0.31355932 | U22: =U20/T20-1 -> 0.86507937 | V22: =V20/U20-1 -> -0.4572104 | W22: =W20/V20-1 -> 0.65243902 | Y22: =Y20/W20-1 -> -0.40432261 | Z22: =Z20/Y20-1 -> 1.5 | AA22: =AA20/Z20-1 -> -0.50725664 | AB22: =AB20/AA20-1 -> 0.1558908 | AD22: =AD20/AB20-1 -> -0.13362337 | AE22: =AE20/AD20-1 -> 1.4067432 | AF22: =AF20/AE20-1 -> -0.41758569 | AG22: =AG20/AF20-1 -> -0.27175026 | AI22: =AI20/AG20-1 -> 0.046380885 | AJ22: =AJ20/AI20-1 -> 1.5728677 | AK22: =AK20/AJ20-1 -> -0.72069956 | AL22: =AL20/AK20-1 -> 0.38224299 | AN22: =AN20/AL20-1 -> -0.23123732 | AO22: =AO20/AN20-1 -> 2.5558487 | AP22: =AP20/AO20-1 -> -0.46920604 | AQ22: =AQ20/AP20-1 -> 0.0722274 | AS22: =AS20/AQ20-1 -> 0.44893525 | AT22: =AT20/AS20-1 -> 0.70545891 | AU22: =AU20/AT20-1 -> -0.39869856 | AV22: =AV20/AU20-1 -> -0.25855513 | AX22: =AX20/AV20-1 -> 0.076134122 | AY22: =AY20/AX20-1 -> 1.9028592 | AZ22: =AZ20/AY20-1 -> -0.56939007 | BA22: =BA20/AZ20-1 -> 0.073313783 | BC22: =BC20/BA20-1 -> 0.13114754 | BD22: =BD20/BC20-1 -> 1.0214976 | BE22: =BE20/BD20-1 -> -0.40661967 | BF22: =BF20/BE20-1 -> 0.24506645 | BH22: =BH20/BF20-1 -> -0.32249717 | BI22: =BI20/BH20-1 -> 1.5426116 | BJ22: =BJ20/BI20-1 -> -0.63280443 | BK22: =BK20/BJ20-1 -> 0.089491179 | BM22: =BM20/BK20-1 -> -0.10349683 | BN22: =BN20/BM20-1 -> -0.13141361 | BO22: =BO20/BN20-1 -> 0.56720916 | BP22: =BP20/BO20-1 -> 0.050769231 | BR22: =BR20/BP20-1 -> -0.23627379 | BS22: =BS20/BR20-1 -> 0.84279895 | BT22: =BT20/BS20-1 -> -0.3946684 | BU22: =BU20/BT20-1 -> 0.16348013 | BW22: =BW20/BV20-1 -> -0.67561776 | BX22: =BX20/BW20-1 -> 0.28011244 | BY22: =BY20/BX20-1 -> 0.034255599 | BZ22: =BZ20/BY20-1 -> -0.28121019 | CB22: =CB20/BZ20-1 -> -0.23216659 | CC22: =CC20/CB20-1 -> 1.6451241 | CD22: =CD20/CC20-1 -> -0.24883653 | CE22: =CE20/CD20-1 -> -0.20377541 | CG22: =CG20/CE20-1 -> 0.016170213 | CH22: =CH20/CG20-1 -> 0.76214405 | CI22: =CI20/CH20-1 -> -0.32577404 | CJ22: =CJ20/CI20-1 -> -0.15649547 | CL22: =CL20/CJ20-1 -> -0.24414995 | CM22: =CM20/CL20-1 -> 1.6289686 | CN22: =CN20/CM20-1 -> -0.18018505 | CO22: =CO20/CN20-1 -> -0.52363503 | CQ22: =CQ20/CO20-1 -> 0.23076923 | CR22: =CR20/CQ20-1 -> 0.8125 | CS22: =CS20/CR20-1 -> -0.53103448 | CT22: =CT20/CS20-1 -> -0.11764706 | CX22: =CF54 -> 448071 | CY22: =CY21*0.35 -> 1331193.7
B23: Total Revenues | D23: =SUM(D5,D8,D11,D14,D17,D20) -> 219796 | E23: =SUM(E5,E8,E11,E14,E17,E20) -> 59351 | F23: =SUM(F5,F8,F11,F14,F17,F20) -> 67569 | G23: =SUM(G5,G8,G11,G14,G17,G20) -> 68637 | H23: =SUM(H5,H8,H11,H14,H17,H20) -> 69544 | I23: =SUM(I5,I8,I11,I14,I17,I20) -> 265101 | J23: =SUM(J5,J8,J11,J14,J17,J20) -> 69565 | K23: =SUM(K5,K8,K11,K14,K17,K20) -> 72172 | ... CU23: =SUM(CU5,CU8,CU11,CU14,CU17,CU20) -> 2531873.8 | CV23: =+BV23+460000 -> 2054965 | CW23: =+CV23*0.3 -> 616489.5 | CY23: =CY21*0.3 -> 1141023.2 | DC23: =450*1.15 -> 517.5
C24: Y/Y Growth | I24: =I23/D23-1 -> 0.20612295 | J24: =J23/E23-1 -> 0.17209483 | K24: =K23/F23-1 -> 0.068122956 | L24: =L23/G23-1 -> 0.082972741 | M24: =M23/H23-1 -> 0.067194869 | N24: =N23/I23-1 -> 0.095001528 | O24: =O23/J23-1 -> 0.0036656365 | P24: =P23/K23-1 -> 0.0059302777 | ... CU24: =CU23/CP23-1 -> 0.078623661 | CV24: =CF23*1.093 -> 2133263.8 | CY24: 45000
C25: Q/Q Growth | F25: =F23/E23-1 -> 0.13846439 | G25: =G23/F23-1 -> 0.015806065 | H25: =H23/G23-1 -> 0.013214447 | J25: =J23/H23-1 -> 0.0003019671 | K25: =K23/J23-1 -> 0.037475742 | L25: =L23/K23-1 -> 0.029928504 | M25: =M23/L23-1 -> -0.001547113 | O25: =O23/M23-1 -> -0.059245186 | P25: =P23/O23-1 -> 0.039816671 | Q25: =Q23/P23-1 -> 0.016101928 | R25: =R23/Q23-1 -> -0.018029253 | T25: =T23/R23-1 -> 0.013169701 | U25: =U23/T23-1 -> 0.045535678 | V25: =V23/U23-1 -> 0.0058513064 | W25: =W23/V23-1 -> 0.06341988 | Y25: =Y23/W23-1 -> 0.0078460995 | Z25: =Z23/Y23-1 -> 0.1045054 | AA25: =AA23/Z23-1 -> 0.027110148 | AB25: =AB23/AA23-1 -> 0.016228888 | AD25: =AD23/AB23-1 -> 0.0045193356 | AE25: =AE23/AD23-1 -> 0.076086389 | AF25: =AF23/AE23-1 -> 0.03815187 | AG25: =AG23/AF23-1 -> 0.034703469 | AI25: =AI23/AG23-1 -> 0.017076805 | AJ25: =AJ23/AI23-1 -> 0.1042832 | AK25: =AK23/AJ23-1 -> 0.034517693 | AL25: =AL23/AK23-1 -> -0.0095131505 | AN25: =AN23/AL23-1 -> 0.059055242 | AO25: =AO23/AN23-1 -> 0.083939659 | AP25: =AP23/AO23-1 -> 0.031101541 | AQ25: =AQ23/AP23-1 -> 0.074871557 | AS25: =AS23/AQ23-1 -> 0.1409223 | AT25: =AT23/AS23-1 -> 0.047359829 | AU25: =AU23/AT23-1 -> 0.020686558 | AV25: =AV23/AU23-1 -> -0.013658176 | AX25: =AX23/AV23-1 -> 0.024613444 | AY25: =AY23/AX23-1 -> 0.047839205 | AZ25: =AZ23/AY23-1 -> 0.023827942 | BA25: =BA23/AZ23-1 -> 0.017154211 | BC25: =BC23/BA23-1 -> 0.01512706 | BD25: =BD23/BC23-1 -> 0.073794521 | BE25: =BE23/BD23-1 -> -0.00064781552 | BF25: =BF23/BE23-1 -> 0.02300394 | BH25: =BH23/BF23-1 -> 0.023577045 | BI25: =BI23/BH23-1 -> 0.11745316 | BJ25: =BJ23/BI23-1 -> -0.0028563103 | BK25: =BK23/BJ23-1 -> 0.036935354 | BM25: =BM23/BK23-1 -> -0.037035748 | BN25: =BN23/BM23-1 -> -0.019694342 | BO25: =BO23/BN23-1 -> 0.053838698 | BP25: =BP23/BO23-1 -> -0.0088446056 | BR25: =BR23/BP23-1 -> 0.040203523 | BS25: =BS23/BR23-1 -> 0.37503477 | BT25: =BT23/BS23-1 -> 0.13632473 | BU25: =BU23/BT23-1 -> -0.057417764 | BW25: =BW23/BV23-1 -> -0.7140326 | BX25: =BX23/BW23-1 -> 0.02757461 | BY25: =BY23/BX23-1 -> 0.0096141332 | BZ25: =BZ23/BY23-1 -> -0.044318256 | CB25: =CB23/CA23-1 -> -0.74497245 | CC25: =CC23/CB23-1 -> 0.068720555 | CD25: =CD23/CC23-1 -> -0.019027166 | CE25: =CE23/CD23-1 -> -0.0277935 | CG25: =CG23/CF23-1 -> -0.73748752 | CH25: =CH23/CG23-1 -> 0.055853415 | CI25: =CI23/CH23-1 -> 0.0043643341 | CJ25: =CJ23/CI23-1 -> -0.0040600953 | CL25: =CL23/CK23-1 -> -0.7356328 | CM25: =CM23/CL23-1 -> 0.054766307 | CN25: =CN23/CM23-1 -> -0.00039925048 | CO25: =CO23/CN23-1 -> -0.0096008854 | CQ25: =CQ23/CP23-1 -> -0.74075664 | CR25: =CR23/CQ23-1 -> 0.066434141 | CS25: =CS23/CR23-1 -> -0.018413775 | CT25: =CT23/CS23-1 -> 0.0006041864 | CY25: =CY23/CY24 -> 25.35607
CW26: =BV23 -> 1594965 | CX26: 352 | CY26: =CY25*30 -> 760.68211
B27: Cost of Revenue | CW27: 313000 | CY27: =((CY26/CX26)^0.14)-1 -> 0.11391609
B28: Software Licenses | D28: 7953 | E28: 2203 | F28: 2564 | G28: 2071 | H28: =I28-G28-F28-E28 -> 2386 | I28: 9224 | J28: 1276 | K28: 1433 | L28: 1366 | M28: =N28-L28-K28-J28 -> 1365 | N28: 5440 | O28: 707 | P28: 852 | Q28: 912 | R28: 985 | S28: =SUM(O28:R28) -> 3456 | T28: =795 -> 795 | U28: =989 -> 989 | V28: =536 -> 536 | W28: =714 -> 714 | X28: =SUM(T28:W28) -> 3034 | Y28: 566 | Z28: 484 | AA28: 458 | AB28: 475 | AC28: =SUM(Y28:AB28) -> 1983 | AD28: 426 | AE28: 692 | AF28: 583 | AG28: 676 | AH28: =SUM(AD28:AG28) -> 2377 | AI28: 531 | AJ28: 343 | AK28: 565 | AL28: 461 | AM28: =SUM(AI28:AL28) -> 1900 | AN28: 553 | AO28: 483 | AP28: 147 | AQ28: 449 | AR28: =SUM(AN28:AQ28) -> 1632 | AS28: 638 | AT28: 666 | AU28: 623 | AV28: 1037 | AW28: =SUM(AS28:AV28) -> 2964 | AX28: 731 | AY28: 647 | AZ28: 826 | BA28: 1117 | BB28: =SUM(AX28:BA28) -> 3321 | BC28: 778 | BD28: 1204 | BE28: =957 -> 957 | BF28: =863 -> 863 | BG28: =SUM(BC28:BF28) -> 3802 | BH28: 818 | BI28: =891 -> 891 | BJ28: =971 -> 971 | BK28: =1258 -> 1258 | BL28: =SUM(BH28:BK28) -> 3938 | BM28: 740 | BN28: =1130 -> 1130 | BO28: =1177 -> 1177 | BP28: =292 -> 292 | BQ28: =SUM(BM28:BP28) -> 3339 | BR28: =1236 -> 1236 | BS28: 1368 | BT28: =1547 -> 1547 | BU28: =1726 -> 1726 | BV28: =SUM(BR28:BU28) -> 5877 | BW28: =2609 -> 2609 | BX28: =2869 -> 2869 | BY28: =3162 -> 3162 | BZ28: =1436 -> 1436 | CA28: =SUM(BW28:BZ28) -> 10076 | CB28: =2313 -> 2313 | CC28: 2432 | CD28: =3120 -> 3120 | CE28: =2956 -> 2956 | CF28: =SUM(CB28:CE28) -> 10821 | CG28: 1565 | CH28: 1560 | CI28: =1870 -> 1870 | CJ28: =1282 -> 1282 | CK28: =SUM(CG28:CJ28) -> 6277 | CL28: =1910 -> 1910 | CM28: =1839 -> 1839 | CN28: 1669 | CO28: 2588 | CP28: =SUM(CL28:CO28) -> 8006 | CQ28: =(1-CQ29)*CQ5 -> 1500 | CR28: =(1-CR29)*CR5 -> 1500 | CS28: =(1-CS29)*CS5 -> 2000 | CT28: =(1-CT29)*CT5 -> 2250 | CU28: =SUM(CQ28:CT28) -> 7250 | CW28: =CW27+CW26 -> 1907965
C29: Gross Margins | D29: =(D5-D28)/D5 -> 0.77317971 | E29: =(E5-E28)/E5 -> 0.73676664 | F29: =(F5-F28)/F5 -> 0.78462831 | G29: =(G5-G28)/G5 -> 0.81788604 | H29: =(H5-H28)/H5 -> 0.75761885 | I29: =(I5-I28)/I5 -> 0.77768137 | J29: =(J5-J28)/J5 -> 0.88136854 | K29: =(K5-K28)/K5 -> 0.85542776 | ... CP29: =(CP5-CP28)/CP5 -> 0.61979389 | CQ29: 0.5 | CR29: 0.5 | CS29: 0.5 | CT29: 0.5 | CU29: =(CU5-CU28)/CU5 -> 0.5 | CW29: =1537-1507 -> 30
B30: Acquired Software | D30: 2279 | E30: 436 | F30: 461 | G30: 472 | H30: =I30-G30-F30-E30 -> 430 | I30: 1799 | J30: 315 | K30: 358 | L30: 369 | M30: =N30-L30-K30-J30 -> 369 | N30: 1411 | O30: 398 | P30: 398 | Q30: 398 | R30: 398 | S30: =SUM(O30:R30) -> 1592 | T30: 0 | U30: 0 | V30: 0 | W30: 0 | X30: =SUM(T30:W30) -> 0 | Y30: 0 | Z30: 0 | AA30: 0 | AB30: 0 | AC30: =SUM(Y30:AB30) -> 0 | AD30: 0 | AE30: =523-523 -> 0 | AF30: 0 | AH30: =SUM(AD30:AG30) -> 0 | AJ30: 0 | AK30: 0 | AL30: 0 | AM30: =SUM(AI30:AL30) -> 0 | AO30: 0 | AP30: 0 | AR30: =SUM(AN30:AQ30) -> 0 | AS30: 0 | AT30: 0 | AU30: 0 | AV30: 0 | AW30: =SUM(AS30:AV30) -> 0 | AX30: 0 | AY30: 0 | AZ30: 0 | BA30: 0 | BB30: =SUM(AX30:BA30) -> 0 | BC30: 0 | BD30: 0 | BE30: 0 | BF30: 0 | BG30: =SUM(BC30:BF30) -> 0 | BH30: 0 | BI30: 0 | BJ30: 0 | BK30: 0 | BL30: =SUM(BH30:BK30) -> 0 | BM30: 0 | BN30: 0 | BO30: 0 | BP30: 0 | BQ30: =SUM(BM30:BP30) -> 0 | BS30: 0 | BU30: 0 | BV30: =SUM(BR30:BU30) -> 0 | BW30: 0 | BX30: 0 | BY30: 0 | BZ30: 0 | CA30: =SUM(BW30:BZ30) -> 0 | CB30: 0 | CC30: 0 | CD30: 0 | CE30: 0 | CF30: =SUM(CB30:CE30) -> 0 | CG30: 0 | CH30: 0 | CI30: 0 | CJ30: 0 | CK30: =SUM(CG30:CJ30) -> 0 | CL30: 0 | CM30: 0 | CN30: 0 | CO30: 0 | CP30: =SUM(CL30:CO30) -> 0 | CQ30: 0 | CR30: 0 | CS30: 0 | CT30: 0 | CU30: =SUM(CQ30:CT30) -> 0
C31: Gross Margins
B32: Software Services, Maintenance & Subsc. | D32: 104993 | E32: 30444 | F32: 31123 | G32: 31988 | H32: =I32-G32-F32-E32 -> 32692 | I32: 126247 | J32: 33087 | K32: 34174 | L32: 35259 | M32: =N32-L32-K32-J32 -> 34679 | N32: 137199 | O32: 34881 | P32: 34595 | Q32: 34708 | R32: 33901 | S32: =SUM(O32:R32) -> 138085 | T32: =35180-196 -> 34984 | U32: =35502-214 -> 35288 | V32: =35689-239 -> 35450 | W32: =37405-222 -> 37183 | X32: =SUM(T32:W32) -> 142905 | Y32: =39813-248 -> 39565 | Z32: =43118-257 -> 42861 | AA32: =43485-286 -> 43199 | AB32: =45168-293 -> 44875 | AC32: =SUM(Y32:AB32) -> 170500 | AD32: =46382-336 -> 46046 | AE32: =48833-343 -> 48490 | AF32: =51786-408 -> 51378 | AG32: =52616-422 -> 52194 | AH32: =SUM(AD32:AG32) -> 198108 | AI32: =54999-513 -> 54486 | AJ32: =58274-513 -> 57761 | AK32: =61428-569 -> 60859 | AL32: =61662-582 -> 61080 | AM32: =SUM(AI32:AL32) -> 234186 | AN32: =65377-701 -> 64676 | AO32: =69678-746 -> 68932 | AP32: =72764-902 -> 71862 | AQ32: =77521-1031 -> 76490 | AR32: =SUM(AN32:AQ32) -> 281960 | AS32: =85270-1317 -> 83953 | AT32: =86717-1571 -> 85146 | AU32: =88623-1779 -> 86844 | AV32: =88329-1881 -> 86448 | AW32: =SUM(AS32:AV32) -> 342391 | AX32: =93540-2097 -> 91443 | AY32: =96172-2253 -> 93919 | AZ32: =98036-2524 -> 95512 | BA32: =99886-2541 -> 97345 | BB32: =SUM(AX32:BA32) -> 378219 | BC32: =106085-2776 -> 103309 | BD32: =109487-2955 -> 106532 | BE32: =111508-3909 -> 107599 | BF32: =111843-3948 -> 107895 | BG32: =SUM(BC32:BF32) -> 425335 | BH32: =117160-3798 -> 113362 | BI32: =125759-3756 -> 122003 | BJ32: =128545-3612 -> 124933 | BK32: =130674-3836 -> 126838 | BL32: =SUM(BH32:BK32) -> 487136 | BM32: =131779-4252 -> 127527 | BN32: =124287-4369 -> 119918 | BO32: =125881-4555 -> 121326 | BP32: =128557-4949 -> 123608 | BQ32: =SUM(BM32:BP32) -> 492379 | BR32: =134320-5000 -> 129320 | BS32: =199771-5909 -> 193862 | BT32: =241944-6303 -> 235641 | BU32: =223123-6493 -> 216630 | BV32: =SUM(BR32:BU32) -> 775453 | BW32: =236896-6772 -> 230124 | BX32: =244192-6867 -> 237325 | BY32: =239928-7181 -> 232747 | BZ32: =232880-6667+2514 -> 228727 | CA32: =SUM(BW32:BZ32) -> 928923 | CB32: =252415-6342+2588 -> 248661 | CC32: =255789-6437+2896 -> 252248 | CD32: =247781-6847+3083 -> 244017 | CE32: =245236-6981+4058 -> 242313 | CF32: =SUM(CB32:CE32) -> 987239 | CG32: =268870+4363-7390 -> 265843 | CH32: =277145+4484-7620 -> 274009 | CI32: =283750+4961-7972 -> 280739 | CJ32: =283013+4998-8340 -> 279671 | CK32: =SUM(CG32:CJ32) -> 1100262 | CL32: =278053+5379-8714 -> 274718 | CM32: =292595+5505-8891 -> 289209 | CN32: =289070+6195-9307 -> 285958 | CO32: =289171+5584-9217 -> 285538 | CP32: =SUM(CL32:CO32) -> 1135423 | CQ32: =(1-CQ33)*(CQ8+CQ11+CQ14) -> 286812.9 | CR32: =(1-CR33)*(CR8+CR11+CR14) -> 306255.11 | CS32: =(1-CS33)*(CS8+CS11+CS14) -> 300577.99 | CT32: =(1-CT33)*(CT8+CT11+CT14) -> 297772.28 | CU32: =SUM(CQ32:CT32) -> 1191418.3 | CW32: =1510+15 -> 1525
C33: Gross Margins | D33: =(D11+D14+D8-D32)/(D11+D14+D8) -> 0.3273991 | E33: =(E11+E14+E8-E32)/(E11+E14+E8) -> 0.31799547 | F33: =(F11+F14+F8-F32)/(F11+F14+F8) -> 0.37074404 | G33: =(G11+G14+G8-G32)/(G11+G14+G8) -> 0.36631074 | H33: =(H11+H14+H8-H32)/(H11+H14+H8) -> 0.37432776 | I33: =(I11+I14+I8-I32)/(I11+I14+I8) -> 0.35859553 | J33: =(J11+J14+J8-J32)/(J11+J14+J8) -> 0.36791732 | K33: =(K11+K14+K8-K32)/(K11+K14+K8) -> 0.38661737 | ... CP33: =(CP11+CP14+CP8-CP32)/(CP11+CP14+CP8) -> 0.50269279 | CQ33: 0.52 | CR33: 0.515 | CS33: 0.52 | CT33: 0.525 | CU33: =(CU11+CU14+CU8-CU32)/(CU11+CU14+CU8) -> 0.5199908 | CW33: =1540-1510 -> 30
B34: Appraisal Services | D34: 14467 | E34: 3167 | F34: 3004 | G34: 3098 | H34: =I34-G34-F34-E34 -> 2982 | I34: 12251 | J34: 3363 | K34: 2997 | L34: 2851 | M34: =N34-L34-K34-J34 -> 2307 | N34: 11518 | O34: 2877 | P34: 3131 | Q34: 3434 | R34: 3468 | S34: =SUM(O34:R34) -> 12910 | T34: 3824 | U34: 3702 | V34: 3776 | W34: 3248 | X34: =SUM(T34:W34) -> 14550 | Y34: 3796 | Z34: 3876 | AA34: 3598 | AB34: 3619 | AC34: =SUM(Y34:AB34) -> 14889 | AD34: 3799 | AE34: 3418 | AF34: 3360 | AG34: 3232 | AH34: =SUM(AD34:AG34) -> 13809 | AI34: 3311 | AJ34: 3665 | AK34: 3764 | AL34: 3544 | AM34: =SUM(AI34:AL34) -> 14284 | AN34: 4135 | AO34: 4278 | AP34: 3984 | AQ34: 3525 | AR34: =SUM(AN34:AQ34) -> 15922 | AS34: 3962 | AT34: 4458 | AU34: 4053 | AV34: 3938 | AW34: =SUM(AS34:AV34) -> 16411 | AX34: 4197 | AY34: 4282 | AZ34: 4089 | BA34: 3718 | BB34: =SUM(AX34:BA34) -> 16286 | BC34: 3781 | BD34: 3568 | BE34: =3505 -> 3505 | BF34: =3445 -> 3445 | BG34: =SUM(BC34:BF34) -> 14299 | BH34: 3452 | BI34: =3758 -> 3758 | BJ34: =4096 -> 4096 | BK34: =4031 -> 4031 | BL34: =SUM(BH34:BK34) -> 15337 | BM34: 4385 | BN34: =3976 -> 3976 | BO34: =3434 -> 3434 | BP34: =4150 -> 4150 | BQ34: =SUM(BM34:BP34) -> 15945 | BR34: =4617 -> 4617 | BS34: 4429 | BT34: =4506 -> 4506 | BU34: =5509 -> 5509 | BV34: =SUM(BR34:BU34) -> 19061 | BW34: =5936 -> 5936 | BX34: =5976 -> 5976 | BY34: 5783 | BZ34: =6293 -> 6293 | CA34: =SUM(BW34:BZ34) -> 23988 | CW34: =1510+15 -> 1525 | CY34: =2335+2360 -> 4695
C35: Gross Margins | D35: =(D17-D34)/D17 -> 0.32137161 | E35: =(E17-E34)/E17 -> 0.30881711 | F35: =(F17-F34)/F17 -> 0.31384194 | G35: =(G17-G34)/G17 -> 0.414256 | H35: =(H17-H34)/H17 -> 0.38502784 | I35: =(I17-I34)/I17 -> 0.35851922 | J35: =(J17-J34)/J17 -> 0.3125511 | K35: =(K17-K34)/K17 -> 0.40700435 | ... CA35: =(CA17-CA34)/CA17 -> 0.30485684 | CY35: =CY34/2 -> 2347.5
B36: Hardware and Other | D36: 5679 | E36: 1298 | F36: 1328 | G36: 1058 | H36: =I36-G36-F36-E36 -> 2109 | I36: 5793 | J36: 1232 | K36: 1213 | L36: 1252 | M36: =N36-L36-K36-J36 -> 2258 | N36: 5955 | O36: 938 | P36: 1149 | Q36: 1110 | R36: 1071 | S36: =SUM(O36:R36) -> 4268 | T36: 676 | U36: 2161 | V36: 808 | W36: 1349 | X36: =SUM(T36:W36) -> 4994 | Y36: 719 | Z36: 2709 | AA36: 882 | AB36: 948 | AC36: =SUM(Y36:AB36) -> 5258 | AD36: 798 | AE36: 2580 | AF36: 1230 | AG36: 951 | AH36: =SUM(AD36:AG36) -> 5559 | AI36: 774 | AJ36: 3087 | AK36: 667 | AL36: 797 | AM36: =SUM(AI36:AL36) -> 5325 | AN36: 566 | AO36: 3147 | AP36: 1565 | AQ36: 1223 | AR36: =SUM(AN36:AQ36) -> 6501 | AS36: 1846 | AT36: 4515 | AU36: 2120 | AV36: 1662 | AW36: =SUM(AS36:AV36) -> 10143 | AX36: 1316 | AY36: 6799 | AZ36: 2293 | BA36: 2187 | BB36: =SUM(AX36:BA36) -> 12595 | BC36: 2343 | BD36: 6801 | BE36: =2574 -> 2574 | BF36: =3990 -> 3990 | BG36: =SUM(BC36:BF36) -> 15708 | BH36: 2906 | BI36: =8868 -> 8868 | BJ36: =3096 -> 3096 | BK36: =2602 -> 2602 | BL36: =SUM(BH36:BK36) -> 17472 | BM36: 2479 | BN36: =2489 -> 2489 | BO36: =3780 -> 3780 | BP36: =3653 -> 3653 | BQ36: =SUM(BM36:BP36) -> 12401 | BR36: =2458 -> 2458 | BS36: 4623 | BT36: =2764 -> 2764 | BU36: =3101 -> 3101 | BV36: =SUM(BR36:BU36) -> 12946 | BW36: =5028 -> 5028 | BX36: =8161 -> 8161 | BY36: =6033 -> 6033 | BZ36: =4453 -> 4453 | CA36: =SUM(BW36:BZ36) -> 23675 | CB36: =5780 -> 5780 | CC36: 11061 | CD36: =6505 -> 6505 | CE36: =6577 -> 6577 | CF36: =SUM(CB36:CE36) -> 29923 | CG36: 4656 | CH36: 10731 | CI36: 6052 | CJ36: =5778 -> 5778 | CK36: =SUM(CG36:CJ36) -> 27217 | CL36: =3448 -> 3448 | CM36: =13675 -> 13675 | CN36: =8117 -> 8117 | CO36: =6407 -> 6407 | CP36: =SUM(CL36:CO36) -> 31647 | CQ36: =(1-CQ37)*CQ20 -> 6000 | CR36: =(1-CR37)*CR20 -> 10875 | CS36: =(1-CS37)*CS20 -> 5100 | CT36: =(1-CT37)*CT20 -> 4500 | CU36: =SUM(CQ36:CT36) -> 26475
C37: Gross Margins | D37: =(D20-D36)/D20 -> 0.22365003 | E37: =(E20-E36)/E20 -> 0.2629188 | F37: =(F20-F36)/F20 -> 0.27272727 | G37: =(G20-G36)/G20 -> 0.29325317 | H37: =(H20-H36)/H20 -> 0.18884615 | I37: =(I20-I36)/I20 -> 0.24609578 | J37: =(J20-J36)/J20 -> 0.21578612 | K37: =(K20-K36)/K20 -> 0.18699732 | ... CP37: =(CP20-CP36)/CP20 -> 0.26607143 | CQ37: 0.25 | CR37: 0.25 | CS37: 0.25 | CT37: 0.25 | CU37: =(CU20-CU36)/CU20 -> 0.25 | CX37: =0.05*157 -> 7.85
B38: Total Cost of Revenues | D38: =SUM(D28,D30,D32,D34,D36) -> 135371 | E38: =SUM(E28,E30,E32,E34,E36) -> 37548 | F38: =SUM(F28,F30,F32,F34,F36) -> 38480 | G38: =SUM(G28,G30,G32,G34,G36) -> 38687 | H38: =SUM(H28,H30,H32,H34,H36) -> 40599 | I38: =SUM(I28,I30,I32,I34,I36) -> 155314 | J38: =SUM(J28,J30,J32,J34,J36) -> 39273 | K38: =SUM(K28,K30,K32,K34,K36) -> 40175 | ... CU38: =SUM(CU28,CU30,CU32,CU34,CU36) -> 1225143.3
B40: Gross Profit | D40: =D23-D38 -> 84425 | E40: =E23-E38 -> 21803 | F40: =F23-F38 -> 29089 | G40: =G23-G38 -> 29950 | H40: =H23-H38 -> 28945 | I40: =I23-I38 -> 109787 | J40: =J23-J38 -> 30292 | K40: =K23-K38 -> 31997 | ... CU40: =CU23-CU38 -> 1306730.6 | CV40: less than 50 bps, more improvement at OM line
C41: Gross Margin | D41: =D40/D23 -> 0.38410617 | E41: =E40/E23 -> 0.36735691 | F41: =F40/F23 -> 0.43050807 | G41: =G40/G23 -> 0.43635357 | H41: =H40/H23 -> 0.41621132 | I41: =I40/I23 -> 0.41413273 | J41: =J40/J23 -> 0.43544886 | K41: =K40/K23 -> 0.44334368 | ... CU41: =CU40/CU23 -> 0.51611204
B43: Operating Expenses | CV43: G&A up LSD
B44: Sales & Marketing | BM44: 27100 | BN44: 22234 | BO44: 23463 | BP44: 25668 | BQ44: =SUM(BM44:BP44) -> 98465 | BR44: =25480 -> 25480 | BS44: =29708 -> 29708 | BT44: =30262 -> 30262 | BU44: =33176 -> 33176 | BV44: =SUM(BR44:BU44) -> 118626 | BW44: =33066 -> 33066 | BX44: =34021 -> 34021 | BY44: =33689 -> 33689 | BZ44: =34969-2229 -> 32740 | CA44: =SUM(BW44:BZ44) -> 133516 | CB44: =37103-2393 -> 34710 | CC44: =37103-2367 -> 34736 | CD44: =35898-2628 -> 33270 | CE44: =39666-2730 -> 36936 | CF44: =SUM(CB44:CE44) -> 139652 | CG44: =36427-2983 -> 33444 | CH44: =41565-3141 -> 38424 | CI44: =38203-3259 -> 34944 | CJ44: =41536-3457 -> 38079 | CK44: =SUM(CG44:CJ44) -> 144891 | CL44: =36473-3500 -> 32973 | CM44: =36312-3500 -> 32812 | CN44: =37560-3500 -> 34060 | CO44: =38225-3500 -> 34725 | CP44: =SUM(CL44:CO44) -> 134570 | CQ44: =CQ23*CQ45 -> 34686.032 | CR44: =CR23*CR45 -> 36341.414 | CS44: =CS23*CS45 -> 37583.244 | CT44: =CT23*CT45 -> 38243.341 | CU44: =SUM(CQ44:CT44) -> 146854.03
C45: % of Revenue | BM45: =BM44/BM23 -> 0.097911699 | BN45: =BN44/BN23 -> 0.081944798 | BO45: =BO44/BO23 -> 0.082056537 | BP45: =BP44/BP23 -> 0.090569074 | BQ45: =BQ44/BQ23 -> 0.088115484 | BR45: =BR44/BR23 -> 0.086430893 | BS45: =BS44/BS23 -> 0.073287399 | BT45: =BT44/BT23 -> 0.065697836 | ... CP45: =CP44/CP23 -> 0.057329233 | CQ45: 0.057 | CR45: 0.056 | CS45: 0.059 | CT45: 0.06 | CU45: =CU44/CU23 -> 0.058002112
B46: General & Administrative | D46: 51724 | E46: 14752 | F46: 15418 | G46: 15985 | H46: =I46-G46-F46-E46 -> 16768 | I46: 62923 | J46: 17410 | K46: 17084 | L46: 17114 | M46: =N46-L46-K46-J46 -> 18507 | N46: 70115 | O46: 17561 | P46: 17439 | Q46: 17337 | R46: 17143 | S46: =SUM(O46:R46) -> 69480 | T46: =17288-1450+196 -> 16034 | U46: =18466-1519+214 -> 17161 | V46: =18755-1616+239 -> 17378 | W46: =21141-1668+222 -> 19695 | X46: =SUM(T46:W46) -> 70268 | Y46: =21335-1835+248 -> 19748 | Z46: =21699-1768+257 -> 20188 | AA46: =20909-1903+286 -> 19292 | AB46: =22763-1905+293 -> 21151 | AC46: =SUM(Y46:AB46) -> 80379 | AD46: =22646-2575+336 -> 20407 | AE46: =24971-2903+343 -> 22411 | AF46: =24581-2653-510 -> 21418 | AG46: =26091-3114+422-472 -> 22927 | AH46: =SUM(AD46:AG46) -> 87163 | AI46: =25367-3462-24+513 -> 22394 | AJ46: =27419+513-3539 -> 24393 | AK46: =27344-144-3316 -> 23884 | AL46: =28130-346-3350 -> 24434 | AM46: =SUM(AI46:AL46) -> 95105 | AN46: =28545-3557-76 -> 24912 | AO46: =30396-3857-197 -> 26342 | AP46: =31869-4696-342-60 -> 26771 | AQ46: =42507-5533-1173-5723+1031 -> 31109 | AR46: =SUM(AN46:AQ46) -> 109134 | AS46: =40759-18-6480+1317 -> 35578 | AT46: =42232-174-7212+1571 -> 36417 | AU46: =42007+1779-7656-498 -> 35632 | AV46: =42162-8399-311+1881 -> 35333 | AW46: =SUM(AS46:AV46) -> 142960 | AX46: =43142-383-8676+2097 -> 36180 | AY46: =43451-128-8901+2253 -> 36675 | AZ46: =44656+2524-173-9791 -> 37216 | BA46: =45725+2541-9980-418 -> 37868 | BB46: =SUM(AX46:BA46) -> 147939 | BC46: =47604-10557-320+2776 -> 39503 | BD46: =52262-9978-604 -> 41680 | BE46: =52605-10567-484 -> 41554 | BF46: =55134-10826-4 -> 44304 | BG46: =SUM(BC46:BF46) -> 167041 | BH46: =57766-10618-123-695 -> 46330 | BI46: =65827-11310-308-245 -> 53964 | BJ46: =63888-11275-621-5 -> 51987 | BK46: =70265-11762-693-197 -> 57613 | BL46: =SUM(BH46:BK46) -> 209894 | BM46: =41120-17302+4252-1198-727 -> 26145 | BN46: =41039-18386+4369-1259 -> 25763 | BO46: =44109-18424-134+4555 -> 30106 | BP46: =37821-8304-703-810 -> 28004 | BQ46: =SUM(BM46:BP46) -> 110018 | BR46: =53293-20724-767-813 -> 30989 | BS46: =79215-19266-393-19017 -> 40539 | BT46: =71586-29461-401+6303-2888 -> 45139 | BU46: =67860-1876-777-17873 -> 47334 | BV46: =SUM(BR46:BU46) -> 164001 | BW46: =64829-25279-712-1031+6772 -> 44579 | BX46: =65680-25800-398+6867 -> 46349 | BY46: =69931-26912-86+7181-183-1159 -> 48772 | BZ46: =66883-16098-378-757-1623 -> 48027 | CA46: =SUM(BW46:BZ46) -> 187727 | CB46: =72360-19161-479-22-1545 -> 51153 | CC46: =77681-17224-669-50 -> 59738 | CD46: =78519-17506-3812-183-43 -> 56975 | CE46: =80015-17722-2863-682-154 -> 58594 | CF46: =SUM(CB46:CE46) -> 226460 | CG46: =72710-16493-805-27+326 -> 55711 | CH46: =75420-19646-873-2-167 -> 54732 | CI46: =72460-19956-625-35 -> 51844 | CJ46: =80348-22556-1303-1374 -> 55115 | CK46: =SUM(CG46:CJ46) -> 217402 | CL46: =79452-28946-1064-33-24+3750+3500 -> 56635 | CM46: =76601-22161-1055-24 -> 53361 | CN46: =79971-20112-159-214-57 -> 59429 | CO46: =80423-22178-688-467-60 -> 57030 | CP46: =SUM(CL46:CO46) -> 226455 | CQ46: =CQ23*CQ47 -> 58418.58 | CR46: =CR23*CR47 -> 59703.752 | CS46: =CS23*CS47 -> 61152.397 | CT46: =CT23*CT47 -> 61189.345 | CU46: =SUM(CQ46:CT46) -> 240464.07 | CW46: =24366-6493 -> 17873
C47: % of Revenue | D47: =D46/D23 -> 0.2353273 | E47: =E46/E23 -> 0.24855521 | F47: =F46/F23 -> 0.22818156 | G47: =G46/G23 -> 0.23289188 | H47: =H46/H23 -> 0.24111354 | I47: =I46/I23 -> 0.23735482 | J47: =J46/J23 -> 0.25026953 | K47: =K46/K23 -> 0.2367123 | ... CP47: =CP46/CP23 -> 0.096473891 | CQ47: 0.096 | CR47: 0.092 | CS47: 0.096 | CT47: 0.096 | CU47: =CU46/CU23 -> 0.094974745
B48: Research & Development | D48: 4443 | E48: 1816 | F48: 2253 | G48: 1416 | H48: =I48-G48-F48-E48 -> 1801 | I48: 7286 | J48: 2235 | K48: 2839 | L48: 2973 | M48: =N48-L48-K48-J48 -> 3112 | N48: 11159 | O48: 3516 | P48: 3744 | Q48: 3233 | R48: 3478 | S48: =SUM(O48:R48) -> 13971 | T48: 4549 | U48: 5035 | V48: 4196 | W48: 2634 | X48: =SUM(T48:W48) -> 16414 | Y48: 5094 | Z48: 5408 | AA48: 4273 | AB48: 5365 | AC48: =SUM(Y48:AB48) -> 20140 | AD48: 5598 | AE48: 5594 | AF48: 5982 | AG48: 6095 | AH48: =SUM(AD48:AG48) -> 23269 | AI48: 6172 | AJ48: 6389 | AK48: 6567 | AL48: 6615 | AM48: =SUM(AI48:AL48) -> 25743 | AN48: 7004 | AO48: 7110 | AP48: 7193 | AQ48: 8615 | AR48: =SUM(AN48:AQ48) -> 29922 | AS48: 9956 | AT48: 10336 | AU48: 11070 | AV48: 11793 | AW48: =SUM(AS48:AV48) -> 43155 | AX48: 11599 | AY48: 11874 | AZ48: 11834 | BA48: 12017 | BB48: =SUM(AX48:BA48) -> 47324 | BC48: 13048 | BD48: 15831 | BE48: 17050 | BF48: =17335 -> 17335 | BG48: =SUM(BC48:BF48) -> 63264 | BH48: =18941 -> 18941 | BI48: =20101 -> 20101 | BJ48: =21130 -> 21130 | BK48: =21170 -> 21170 | BL48: =SUM(BH48:BK48) -> 81342 | BM48: 22361 | BN48: =21949 -> 21949 | BO48: =21642 -> 21642 | BP48: =22411 -> 22411 | BQ48: =SUM(BM48:BP48) -> 88363 | BR48: =21813 -> 21813 | BS48: 23428 | BT48: =24002 -> 24002 | BU48: =24238 -> 24238 | BV48: =SUM(BR48:BU48) -> 93481 | BW48: =23941 -> 23941 | BX48: =23386 -> 23386 | BY48: =25190 -> 25190 | BZ48: =32667 -> 32667 | CA48: =SUM(BW48:BZ48) -> 105184 | CB48: =26987 -> 26987 | CC48: =28153 -> 28153 | CD48: =28282 -> 28282 | CE48: =26163 -> 26163 | CF48: =SUM(CB48:CE48) -> 109585 | CG48: 29433 | CH48: =28951 -> 28951 | CI48: =30120 -> 30120 | CJ48: =29435 -> 29435 | CK48: =SUM(CG48:CJ48) -> 117939 | CL48: =47844-3750 -> 44094 | CM48: =50842-3750 -> 47092 | CN48: =51788-3750 -> 48038 | CO48: =54114-3750 -> 50364 | CP48: =SUM(CL48:CO48) -> 189588 | CQ48: =CQ23*CQ49 -> 54767.418 | CR48: =CR23*CR49 -> 58405.845 | CS48: =CS23*CS49 -> 57330.373 | CT48: =CT23*CT49 -> 57365.011 | CU48: =SUM(CQ48:CT48) -> 227868.65 | CV48: =244-16 -> 228
C49: % of Revenue | D49: =D48/D23 -> 0.020214199 | E49: =E48/E23 -> 0.030597631 | F49: =F48/F23 -> 0.033343693 | G49: =G48/G23 -> 0.020630272 | H49: =H48/H23 -> 0.025897274 | I49: =I48/I23 -> 0.027483865 | J49: =J48/J23 -> 0.032128225 | K49: =K48/K23 -> 0.039336585 | ... CP49: =CP48/CP23 -> 0.080767888 | CQ49: 0.09 | CR49: 0.09 | CS49: 0.09 | CT49: 0.09 | CU49: =CU48/CU23 -> 0.09
B50: Other | D50: 1478 | E50: 567 | F50: =591+9045 -> 9636 | G50: 612 | H50: =I50-G50-F50-E50 -> 668 | I50: =2438+9045 -> 11483 | J50: 672 | K50: 677 | L50: 685 | M50: =N50-L50-K50-J50 -> 671 | N50: 2705 | O50: 806 | P50: 807 | Q50: 806 | R50: 806 | S50: =SUM(O50:R50) -> 3225 | T50: 0 | U50: 0 | V50: 0 | W50: 0 | X50: =SUM(T50:W50) -> 0 | Y50: 0 | AA50: 0 | AB50: 0 | AC50: =SUM(Y50:AB50) -> 0 | AD50: 0 | AF50: 0 | AG50: 0 | AH50: =SUM(AD50:AG50) -> 0 | AM50: =SUM(AI50:AL50) -> 0 | AR50: =SUM(AN50:AQ50) -> 0 | AW50: =SUM(AS50:AV50) -> 0 | BB50: =SUM(AX50:BA50) -> 0 | BG50: =SUM(BC50:BF50) -> 0 | BL50: =SUM(BH50:BK50) -> 0 | BQ50: =SUM(BM50:BP50) -> 0 | BS50: 0 | BV50: =SUM(BR50:BU50) -> 0 | CA50: =SUM(BW50:BZ50) -> 0 | CF50: =SUM(CB50:CE50) -> 0 | CK50: =SUM(CG50:CJ50) -> 0 | CP50: =SUM(CL50:CO50) -> 0 | CU50: =SUM(CQ50:CT50) -> 0
C51: % of Revenue | D51: =D50/D23 -> 0.0067244172 | E51: =E50/E23 -> 0.0095533352 | F51: =F50/F23 -> 0.14260978 | G51: =G50/G23 -> 0.0089164736 | H51: =H50/H23 -> 0.0096054297 | I51: =I50/I23 -> 0.043315567 | J51: =J50/J23 -> 0.0096600302 | K51: =K50/K23 -> 0.0093803691 | ... AC51: =AC50/AC23 -> 0 | AD51: 0 | AE51: 0 | AF51: 0 | AG51: 0 | AH51: =AH50/AH23 -> 0 | AI51: 0 | AJ51: 0 | AK51: 0 | AL51: 0 | AM51: =AM50/AM23 -> 0 | AN51: 0 | AO51: 0 | AP51: 0 | AQ51: 0 | AR51: =AR50/AR23 -> 0 | AS51: 0 | AT51: 0 | AU51: 0 | AV51: 0 | AW51: =AW50/AW23 -> 0 | AX51: 0 | AY51: 0 | AZ51: 0 | BA51: 0 | BB51: =BB50/BB23 -> 0 | BC51: 0 | BD51: 0 | BE51: 0 | BF51: 0 | BG51: =BG50/BG23 -> 0 | BH51: =BH50/BH23 -> 0 | BI51: 0 | BJ51: 0 | BK51: 0 | BL51: =BL50/BL23 -> 0 | BM51: =BM50/BM23 -> 0 | BN51: 0 | BO51: 0 | BP51: 0 | BQ51: =BQ50/BQ23 -> 0 | BR51: =BR50/BR23 -> 0 | BS51: =BS50/BS23 -> 0 | BT51: 0 | BU51: 0 | BV51: =BV50/BV23 -> 0 | BW51: 0 | BX51: 0 | BY51: 0 | BZ51: 0 | CA51: =CA50/CA23 -> 0 | CB51: 0 | CC51: 0 | CD51: 0 | CE51: 0 | CF51: =CF50/CF23 -> 0 | CG51: 0 | CH51: 0 | CI51: 0 | CJ51: 0 | CK51: =CK50/CK23 -> 0 | CL51: 0 | CM51: 0 | CN51: 0 | CO51: 0 | CP51: =CP50/CP23 -> 0 | CQ51: 0 | CR51: 0 | CS51: 0 | CT51: 0 | CU51: =CU50/CU23 -> 0
B52: Total Operating Expense | D52: =SUM(D46,D48,D50) -> 57645 | E52: =SUM(E46,E48,E50) -> 17135 | F52: =SUM(F46,F48,F50) -> 27307 | G52: =SUM(G46,G48,G50) -> 18013 | H52: =SUM(H46,H48,H50) -> 19237 | I52: =SUM(I46,I48,I50) -> 81692 | J52: =SUM(J46,J48,J50) -> 20317 | K52: =SUM(K46,K48,K50) -> 20600 | ... AC52: =SUM(AC46,AC48,AC50) -> 100519 | AD52: =AD46+AD48+AD50 -> 26005 | AE52: =AE46+AE48+AE50 -> 28005 | AF52: =AF46+AF48+AF50 -> 27400 | AG52: =AG46+AG48+AG50 -> 29022 | AH52: =AH46+AH48+AH50 -> 110432 | AI52: =AI46+AI48+AI50 -> 28566 | AJ52: =AJ46+AJ48+AJ50 -> 30782 | AK52: =AK46+AK48+AK50 -> 30451 | ... BL52: =BL46+BL48+BL50 -> 291236 | BM52: =BM44+BM46+BM48+BM50 -> 75606 | BN52: =BN44+BN46+BN48+BN50 -> 69946 | BO52: =BO44+BO46+BO48+BO50 -> 75211 | BP52: =BP44+BP46+BP48+BP50 -> 76083 | BQ52: =BQ44+BQ46+BQ48+BQ50 -> 296846 | BR52: =BR44+BR46+BR48+BR50 -> 78282 | BS52: =BS44+BS46+BS48+BS50 -> 93675 | BT52: =BT44+BT46+BT48+BT50 -> 99403 | ... BY52: =BY44+BY46+BY48+BY50 -> 107651 | BZ52: =BZ46+BZ48+BZ50+BZ44 -> 113434 | CA52: =CA44+CA46+CA48+CA50 -> 426427 | CB52: =CB46+CB48+CB50+CB44 -> 112850 | CC52: =CC46+CC48+CC50+CC44 -> 122627 | CD52: =CD46+CD48+CD50+CD44 -> 118527 | CE52: =CE46+CE48+CE50+CE44 -> 121693 | CF52: =CF46+CF48+CF50+CF44 -> 475697 | CG52: =CG46+CG48+CG50+CG44 -> 118588 | CH52: =CH46+CH48+CH50+CH44 -> 122107 | CI52: =CI46+CI48+CI50+CI44 -> 116908 | ... CU52: =CU46+CU48+CU50+CU44 -> 615186.75 | CV52: Half Gross Margin and Half Open
B54: Non-GAAP Operating Income | D54: =D40-D52 -> 26780 | E54: =E40-E52 -> 4668 | F54: =F40-F52 -> 1782 | G54: =G40-G52 -> 11937 | H54: =H40-H52 -> 9708 | I54: =I40-I52 -> 28095 | J54: =J40-J52 -> 9975 | K54: =K40-K52 -> 11397 | ... CU54: =CU40-CU52 -> 691543.83 | CV54: 30 bps | CX54: int Expense 7.5mm
C55: Non-GAAP Operating Margin | D55: =D54/D23 -> 0.12184025 | E55: =E54/E23 -> 0.078650739 | F55: =F54/F23 -> 0.026373041 | G55: =G54/G23 -> 0.17391494 | H55: =H54/H23 -> 0.13959508 | I55: =I54/I23 -> 0.10597848 | J55: =J54/J23 -> 0.14339107 | K55: =K54/K23 -> 0.15791443 | ... CU55: =CU54/CU23 -> 0.27313518
B57: GAAP Adjustments
C58: Amortization of acquired software | T58: 295 | U58: 244 | V58: 243 | W58: 343 | X58: =SUM(T58:W58) -> 1125 | Y58: 410 | Z58: 482 | AA58: 478 | AB58: 518 | AC58: =SUM(Y58:AB58) -> 1888 | AD58: 549 | AE58: 523 | AF58: 513 | AG58: 493 | AH58: =SUM(AD58:AG58) -> 2078 | AI58: 481 | AJ58: 444 | AK58: 448 | AL58: 485 | AM58: =SUM(AI58:AL58) -> 1858 | AN58: 456 | AO58: 456 | AP58: 552 | AQ58: 2976 | AR58: =SUM(AN58:AQ58) -> 4440 | AS58: 5459 | AT58: 5680 | AU58: 5598 | AV58: 5498 | AW58: =SUM(AS58:AV58) -> 22235 | AX58: 5410 | AY58: 5360 | AZ58: 5473 | BA58: 5443 | BB58: =SUM(AX58:BA58) -> 21686 | BC58: 5382 | BD58: 5724 | BE58: 5897 | BF58: 5969 | BG58: =SUM(BC58:BF58) -> 22972 | BH58: =6682 -> 6682 | BI58: 7988 | BJ58: 7975 | BK58: 7997 | BL58: =SUM(BH58:BK58) -> 30642 | BM58: 8027 | BN58: 8006 | BO58: 7965 | BP58: 7964 | BQ58: =SUM(BM58:BP58) -> 31962 | BR58: 7964 | BS58: 11823 | BT58: 12896 | BU58: 12918 | BV58: =SUM(BR58:BU58) -> 45601 | BW58: 14714 | BX58: 14039 | BY58: 13622 | BZ58: 11310 | CA58: =SUM(BW58:BZ58) -> 53685 | CB58: 8920 | CC58: 8924 | CD58: 9035 | CE58: 9183 | CF58: =SUM(CB58:CE58) -> 36062 | CG58: 9239 | CH58: 9240 | CI58: =9244 -> 9244 | CJ58: =9241 -> 9241 | CK58: =SUM(CG58:CJ58) -> 36964 | CL58: 9294 | CM58: 9319 | CN58: 9376 | CO58: 9446 | CP58: =SUM(CL58:CO58) -> 37435 | CQ58: 11000 | CR58: 9000 | CS58: 9000 | CT58: 8000 | CU58: =SUM(CQ58:CT58) -> 37000
C59: Amortization of acquired intangibles | T59: 804 | U59: 803 | V59: 801 | W59: 923 | X59: =SUM(T59:W59) -> 3331 | Y59: 946 | Z59: 1137 | AA59: 1103 | AB59: 1093 | AC59: =SUM(Y59:AB59) -> 4279 | AD59: 1131 | AE59: 1128 | AF59: 1129 | AG59: 1129 | AH59: =SUM(AD59:AG59) -> 4517 | AI59: 1129 | AJ59: 1128 | AK59: 1136 | AL59: 1153 | AM59: =SUM(AI59:AL59) -> 4546 | AN59: 1152 | AO59: 1151 | AP59: 1282 | AQ59: 2320 | AR59: =SUM(AN59:AQ59) -> 5905 | AS59: 3362 | AT59: 3453 | AU59: 3458 | AV59: 3458 | AW59: =SUM(AS59:AV59) -> 13731 | AX59: 3458 | AY59: 3463 | AZ59: 3492 | BA59: 3499 | BB59: =SUM(AX59:BA59) -> 13912 | BC59: 3315 | BD59: 4041 | BE59: 4386 | BF59: 4475 | BG59: =SUM(BC59:BF59) -> 16217 | BH59: =4850 -> 4850 | BI59: 5266 | BJ59: =5646 -> 5646 | BK59: 5683 | BL59: =SUM(BH59:BK59) -> 21445 | BM59: 5392 | BN59: 5392 | BO59: 5392 | BP59: 5486 | BQ59: =SUM(BM59:BP59) -> 21662 | BR59: 5412 | BS59: 11420 | BT59: 14183 | BU59: 13834 | BV59: =SUM(BR59:BU59) -> 44849 | BW59: 13221 | BX59: 13604 | BY59: 14941 | BZ59: 18104 | CA59: =SUM(BW59:BZ59) -> 59870 | CB59: 18407 | CC59: 18366 | CD59: 18526 | CE59: 19333 | CF59: =SUM(CB59:CE59) -> 74632 | CG59: 18118 | CH59: 13845 | CI59: =13850 -> 13850 | CJ59: =13814 -> 13814 | CK59: =SUM(CG59:CJ59) -> 59627 | CL59: 14139 | CM59: 13833 | CN59: 14201 | CO59: 14246 | CP59: =SUM(CL59:CO59) -> 56419 | CQ59: 12000 | CR59: 12000 | CS59: 12000 | CT59: 12000 | CU59: =SUM(CQ59:CT59) -> 48000 | CV59: =54000-BQ59 -> 32338 | CW59: =CV59/3 -> 10779.333
C60: Share-based compensation | T60: 1450 | U60: 1519 | V60: 1616 | W60: 1668 | X60: =SUM(T60:W60) -> 6253 | Y60: 1835 | Z60: 1768 | AA60: 1903 | AB60: 1905 | AC60: =SUM(Y60:AB60) -> 7411 | AD60: 2575 | AE60: 2903 | AF60: =408+2653+510 -> 3571 | AG60: =3114+472 -> 3586 | AH60: =SUM(AD60:AG60) -> 12635 | AI60: =3462+24 -> 3486 | AJ60: 3539 | AK60: =3885+144 -> 4029 | AL60: =3932+346 -> 4278 | AM60: =SUM(AI60:AL60) -> 15332 | AN60: =4258+76 -> 4334 | AO60: =4603+197 -> 4800 | AP60: =5598+60 -> 5658 | AQ60: =5723+1173 -> 6896 | AR60: =SUM(AN60:AQ60) -> 21688 | AS60: =6480+18 -> 6498 | AT60: =7212+174 -> 7386 | AU60: =7656+498 -> 8154 | AV60: =8399+311 -> 8710 | AW60: =SUM(AS60:AV60) -> 30748 | AX60: =8676+383 -> 9059 | AY60: =8901+128 -> 9029 | AZ60: =173+9791 -> 9964 | BA60: =9980+418 -> 10398 | BB60: =SUM(AX60:BA60) -> 38450 | BC60: =10557+320 -> 10877 | BD60: =12933+604 -> 13537 | BE60: =14476+484 -> 14960 | BF60: 14774 | BG60: =SUM(BC60:BF60) -> 54148 | BH60: =14416+123 -> 14539 | BI60: 15066 | BJ60: 14887 | BK60: 15598 | BL60: =SUM(BH60:BK60) -> 60090 | BM60: =17302+1198 -> 18500 | BN60: =18386+1259 -> 19645 | BO60: 18424 | BP60: 13253 | BQ60: =SUM(BM60:BP60) -> 69822 | BR60: 25724 | BS60: 25175 | BT60: 29461 | BU60: 24366 | BV60: =SUM(BR60:BU60) -> 104726 | BW60: 25279 | BX60: 25800 | BY60: 26912 | BZ60: 24994 | CA60: =SUM(BW60:BZ60) -> 102985 | CB60: 27896 | CC60: 26028 | CD60: 26981 | CE60: 27433 | CF60: =SUM(CB60:CE60) -> 108338 | CG60: 26866 | CH60: 30407 | CI60: =31187 -> 31187 | CJ60: 34353 | CK60: =SUM(CG60:CJ60) -> 122813 | CL60: 37660 | CM60: 38302 | CN60: 36669 | CO60: 38645 | CP60: =SUM(CL60:CO60) -> 151276 | CQ60: 35000 | CR60: 35000 | CS60: 35000 | CT60: 37000 | CU60: =SUM(CQ60:CT60) -> 142000
C61: Amortization of debt discount | BW61: 0 | BY61: 0 | CA61: =SUM(BW61:BZ61) -> 0 | CF61: =SUM(CB61:CE61) -> 0 | CK61: =SUM(CG61:CJ61) -> 0 | CL61: 0 | CP61: =SUM(CL61:CO61) -> 0 | CU61: =SUM(CQ61:CT61) -> 0
C62: Deferred revenue write down | BD62: 1551 | BE62: 1397 | BF62: 952 | BG62: =SUM(BC62:BF62) -> 3900 | BH62: =1597 -> 1597 | BI62: 2757 | BJ62: 1698 | BK62: -1495 | BL62: =SUM(BH62:BK62) -> 4557 | BM62: 160 | BN62: 160 | BO62: 113 | BP62: 45 | BQ62: =SUM(BM62:BP62) -> 478 | BS62: 1288 | BT62: 751 | BU62: 639 | BV62: =SUM(BR62:BU62) -> 2678 | BZ62: 0 | CA62: =SUM(BW62:BZ62) -> 0 | CE62: 0 | CF62: =SUM(CB62:CE62) -> 0 | CK62: =SUM(CG62:CJ62) -> 0 | CL62: 0 | CP62: =SUM(CL62:CO62) -> 0 | CT62: 0 | CU62: =SUM(CQ62:CT62) -> 0
C63: Other | AP63: 342 | AQ63: =5533+3186+37 -> 8756 | AR63: =SUM(AN63:AQ63) -> 9098 | AS63: =5584+111 -> 5695 | AT63: =4666+111 -> 4777 | AU63: =3149+111 -> 3260 | AV63: =1664+111 -> 1775 | AW63: =SUM(AS63:AV63) -> 15507 | AX63: =204+111 -> 315 | AY63: =184+111 -> 295 | AZ63: =111+151 -> 262 | BA63: =124+111 -> 235 | BB63: =SUM(AX63:BA63) -> 1107 | BC63: =100+111 -> 211 | BD63: 111 | BE63: 104 | BF63: =100+4 -> 104 | BG63: =SUM(BC63:BF63) -> 530 | BH63: =100+695 -> 795 | BI63: =308+245+100 -> 653 | BJ63: =621+5+89 -> 715 | BK63: =83+693+197 -> 973 | BL63: =SUM(BH63:BK63) -> 3136 | BM63: =79+727 -> 806 | BN63: 78 | BO63: =78+134 -> 212 | BP63: =703+810+78 -> 1591 | BQ63: =SUM(BM63:BP63) -> 2687 | BR63: =767+813 -> 1580 | BS63: =19017+393 -> 19410 | BT63: =2888+401 -> 3289 | BU63: =1876+777 -> 2653 | BV63: =SUM(BR63:BU63) -> 26932 | BW63: =712+1031 -> 1743 | BX63: 398 | BY63: =1159+183+86 -> 1428 | BZ63: =378+757+1623 -> 2758 | CA63: =SUM(BW63:BZ63) -> 6327 | CB63: =479+22+1545 -> 2046 | CC63: =669+50 -> 719 | CD63: =3812+183+43 -> 4038 | CE63: =682+154+2863 -> 3699 | CF63: =SUM(CB63:CE63) -> 10502 | CG63: =805+27-326 -> 506 | CH63: =873+2+167 -> 1042 | CI63: =625+35 -> 660 | CJ63: =1303+1374 -> 2677 | CK63: =SUM(CG63:CJ63) -> 4885 | CL63: =33+24+1064 -> 1121 | CM63: =1055+24 -> 1079 | CN63: =159+214+57 -> 430 | CO63: =688+467+60 -> 1215 | CP63: =SUM(CL63:CO63) -> 3845 | CQ63: 0 | CR63: 0 | CS63: 0 | CT63: 0 | CU63: =SUM(CQ63:CT63) -> 0
B64: Total GAAP and non-cash adjustments | T64: =SUM(T58:T60) -> 2549 | U64: =SUM(U58:U60) -> 2566 | V64: =SUM(V58:V60) -> 2660 | W64: =SUM(W58:W60) -> 2934 | X64: =SUM(X58:X60) -> 10709 | Y64: =SUM(Y58:Y60) -> 3191 | Z64: =SUM(Z58:Z60) -> 3387 | AA64: =SUM(AA58:AA60) -> 3484 | ... AO64: =SUM(AO58:AO60) -> 6407 | AP64: =SUM(AP58:AP63) -> 7834 | AQ64: =SUM(AQ58:AQ63) -> 20948 | AR64: =SUM(AR58:AR63) -> 41131 | AS64: =SUM(AS58:AS63) -> 21014 | AT64: =SUM(AT58:AT63) -> 21296 | AU64: =SUM(AU58:AU63) -> 20470 | AV64: =SUM(AV58:AV63) -> 19441 | AW64: =SUM(AW58:AW63) -> 82221 | ... CU64: =SUM(CU58:CU63) -> 227000
BD65: =24964-BD64 -> 0 | CV65: Interest expense
B66: GAAP Operating Income | T66: =T54-T64 -> 9982 | U66: =U54-U64 -> 9833 | V66: =V54-V64 -> 12380 | W66: =W54-W64 -> 14322 | X66: =X54-X64 -> 46517 | Y66: =Y54-Y64 -> 10044 | Z66: =Z54-Z64 -> 12455 | AA66: =AA54-AA64 -> 18659 | ... CU66: =CU54-CU64 -> 464543.83
C67: GAAP Operating Margin | D67: =D66/D32 -> 0 | E67: =E66/E32 -> 0 | F67: =F66/F32 -> 0 | G67: =G66/G32 -> 0 | H67: =H66/H32 -> 0 | I67: =I66/I32 -> 0 | J67: =J66/J32 -> 0 | K67: =K66/K32 -> 0 | ... S67: =S66/S32 -> 0 | T67: =T66/T23 -> 0.13600752 | U67: =U66/U23 -> 0.12814231 | V67: =V66/V23 -> 0.16039594 | W67: =W66/W23 -> 0.17449043 | X67: =X66/X23 -> 0.1503502 | Y67: =Y66/Y23 -> 0.12141726 | Z67: =Z66/Z23 -> 0.13631687 | AA67: =AA66/AA23 -> 0.19882785 | ... CU67: =CU66/CU23 -> 0.18347827
AO68: =AO66-29596 -> 0
B69: Interest expense | J69: -14 | K69: -48 | L69: -41 | M69: -27 | N69: =SUM(J69:M69) -> -130 | O69: =-131-P69 -> -42 | P69: -89 | Q69: -318 | R69: -436 | S69: =SUM(O69:R69) -> -885 | T69: =-739-U69 -> -344 | U69: -395 | V69: -446 | W69: -707 | X69: =SUM(T69:W69) -> -1892 | Y69: =-1219+641 -> -578 | Z69: -641 | AA69: -535 | AB69: -310 | AC69: =SUM(Y69:AB69) -> -2064 | AD69: -210 | AE69: 0 | AF69: -162 | AG69: 0 | AH69: =SUM(AD69:AG69) -> -372 | AI69: 0 | AJ69: 0 | AK69: 0 | AL69: 0 | AM69: =SUM(AI69:AL69) -> 0 | AN69: 0 | AO69: 0 | AP69: 0 | AQ69: 0 | AR69: =SUM(AN69:AQ69) -> 0 | AS69: 0 | AT69: 0 | AU69: 0 | AV69: 0 | AW69: =SUM(AS69:AV69) -> 0 | AX69: 0 | AY69: 0 | AZ69: 0 | BA69: 0 | BB69: =SUM(AX69:BA69) -> 0 | BC69: 0 | BD69: 0 | BE69: 0 | BF69: 0 | BG69: =SUM(BC69:BF69) -> 0 | BH69: 0 | BI69: 0 | BJ69: 0 | BK69: 0 | BL69: =SUM(BH69:BK69) -> 0 | BM69: 0 | BN69: 0 | BO69: 0 | BP69: 0 | BQ69: =SUM(BM69:BP69) -> 0 | BR69: 0 | BS69: -12199 | BT69: -5396 | BU69: -4987 | BV69: =SUM(BR69:BU69) -> -22582 | BW69: -4804 | BX69: -6214 | BY69: =-9258 -> -9258 | BZ69: -8103 | CA69: =SUM(BW69:BZ69) -> -28379 | CB69: =-7684 -> -7684 | CC69: -6387 | CD69: =-5808 -> -5808 | CE69: -3750 | CF69: =SUM(CB69:CE69) -> -23629 | CG69: -2184 | CH69: -1253 | CI69: -1235 | CJ69: -1259 | CK69: =SUM(CG69:CJ69) -> -5931 | CL69: =-1246 -> -1246 | CM69: -1262 | CN69: -1235 | CO69: -1252 | CP69: =SUM(CL69:CO69) -> -4995 | CQ69: =CO69 -> -1252 | CS69: =CR69 -> 0 | CT69: =CS69 -> 0 | CU69: =SUM(CQ69:CT69) -> -1252
B70: Other Income (Expense) | K70: -15 | L70: -1 | N70: =SUM(J70:M70) -> -16 | P70: -13 | Q70: -250 | R70: -594 | S70: =SUM(O70:R70) -> -857 | T70: -156 | U70: -129 | V70: -116 | W70: -111 | X70: =SUM(T70:W70) -> -512 | Y70: -125 | Z70: -132 | AA70: =-849+535 -> -314 | AB70: =-384+310 -> -74 | AC70: =SUM(Y70:AB70) -> -645 | AD70: =-338+210 -> -128 | AE70: -296 | AF70: =-285+162 -> -123 | AG70: -390 | AH70: =SUM(AD70:AG70) -> -937 | AI70: -259 | AJ70: -216 | AK70: -47 | AL70: 167 | AM70: =SUM(AI70:AL70) -> -355 | AN70: 181 | AO70: 185 | AP70: 255 | AQ70: -240 | AR70: =SUM(AN70:AQ70) -> 381 | AS70: -467 | AT70: -720 | AU70: -526 | AV70: -285 | AW70: =SUM(AS70:AV70) -> -1998 | AX70: -190 | AY70: -101 | AZ70: 75 | BA70: 914 | BB70: =SUM(AX70:BA70) -> 698 | BC70: 599 | BD70: 558 | BE70: 1041 | BF70: 1180 | BG70: =SUM(BC70:BF70) -> 3378 | BH70: 586 | BI70: -247 | BJ70: 499 | BK70: 2633 | BL70: =SUM(BH70:BK70) -> 3471 | BM70: 990 | BN70: 470 | BO70: 280 | BP70: 376 | BQ70: =SUM(BM70:BP70) -> 2116 | BR70: 88 | BT70: 445 | BU70: 295 | BV70: =SUM(BR70:BU70) -> 828 | BW70: 364 | BX70: 216 | BY70: 131 | BZ70: 1012 | CA70: =SUM(BW70:BZ70) -> 1723 | CB70: 1246 | CC70: 643 | CD70: 787 | CE70: 652 | CF70: =SUM(CB70:CE70) -> 3328 | CG70: 1845 | CH70: 1883 | CI70: =4504 -> 4504 | CJ70: 6340 | CK70: =SUM(CG70:CJ70) -> 14572 | CL70: =7363 -> 7363 | CM70: 8179 | CN70: 10855 | CO70: 11240 | CP70: =SUM(CL70:CO70) -> 37637 | CQ70: 5750 | CR70: 7000 | CS70: 7000 | CT70: 7000 | CU70: =SUM(CQ70:CT70) -> 26750
B71: Total GAAP Other Income (Expense) | D71: 1800 | E71: 402 | F71: 244 | G71: 398 | H71: =I71-G71-F71-E71 -> 137 | I71: 1181 | J71: -14 | K71: -63 | L71: -42 | M71: =N71-L71-K71-J71 -> -27 | N71: -146 | O71: -42 | P71: -102 | Q71: -568 | R71: -1030 | S71: =SUM(O71:R71) -> -1742 | T71: =T70+T69 -> -500 | U71: =U70+U69 -> -524 | V71: -562 | W71: -818 | X71: =SUM(T71:W71) -> -2404 | Y71: =Y70+Y69 -> -703 | Z71: =Z70+Z69 -> -773 | AA71: =AA70+AA69 -> -849 | AB71: =AB70+AB69 -> -384 | AC71: =SUM(Y71:AB71) -> -2709 | AD71: =AD70+AD69 -> -338 | AE71: =AE70+AE69 -> -296 | AF71: =AF70+AF69 -> -285 | AG71: =AG70+AG69 -> -390 | AH71: =SUM(AD71:AG71) -> -1309 | AI71: =AI70+AI69 -> -259 | AJ71: =AJ70+AJ69 -> -216 | AK71: =AK70+AK69 -> -47 | AL71: =AL70+AL69 -> 167 | AM71: =SUM(AI71:AL71) -> -355 | AN71: =AN70+AN69 -> 181 | AO71: =AO70+AO69 -> 185 | AP71: =AP70+AP69 -> 255 | AQ71: =AQ70+AQ69 -> -240 | AR71: =SUM(AN71:AQ71) -> 381 | AS71: =AS70+AS69 -> -467 | AT71: =AT70+AT69 -> -720 | AU71: =AU70+AU69 -> -526 | AV71: =AV70+AV69 -> -285 | AW71: =SUM(AS71:AV71) -> -1998 | AX71: =AX70+AX69 -> -190 | AY71: =AY70+AY69 -> -101 | AZ71: =AZ70+AZ69 -> 75 | BA71: =BA70+BA69 -> 914 | BB71: =SUM(AX71:BA71) -> 698 | BC71: =BC70+BC69 -> 599 | BD71: =BD70+BD69 -> 558 | BE71: =BE70+BE69 -> 1041 | BF71: =BF70+BF69 -> 1180 | BG71: =SUM(BC71:BF71) -> 3378 | BH71: =BH70+BH69 -> 586 | BI71: =BI70+BI69 -> -247 | BJ71: =BJ70+BJ69 -> 499 | BK71: =BK70+BK69 -> 2633 | BL71: =SUM(BH71:BK71) -> 3471 | BM71: =BM70+BM69 -> 990 | BN71: =BN70+BN69 -> 470 | BO71: =BO70+BO69 -> 280 | BP71: =BP70+BP69 -> 376 | BQ71: =SUM(BM71:BP71) -> 2116 | BR71: =BR70+BR69 -> 88 | BS71: =BS70+BS69 -> -12199 | BT71: =BT70+BT69 -> -4951 | BU71: =BU70+BU69 -> -4692 | BV71: =BV70+BV69 -> -21754 | BW71: =BW70+BW69 -> -4440 | BX71: =BX69+BX70 -> -5998 | BY71: =BY69+BY70 -> -9127 | BZ71: =BZ69+BZ70 -> -7091 | CA71: =SUM(BW71:BZ71) -> -26656 | CB71: =CB70+CB69 -> -6438 | CC71: =CC70+CC69 -> -5744 | CD71: =CD70+CD69 -> -5021 | CE71: =CE70+CE69 -> -3098 | CF71: =SUM(CB71:CE71) -> -20301 | CG71: =CG70+CG69 -> -339 | CH71: =CH70+CH69 -> 630 | CI71: =CI70+CI69 -> 3269 | CJ71: =CJ70+CJ69 -> 5081 | CK71: =SUM(CG71:CJ71) -> 8641 | CL71: =CL70+CL69 -> 6117 | CM71: =CM70+CM69 -> 6917 | CN71: =CN70+CN69 -> 9620 | CO71: =CO70+CO69 -> 9988 | CP71: =SUM(CL71:CO71) -> 32642 | CQ71: =CQ70+CQ69 -> 4498 | CR71: =CR70+CR69 -> 7000 | CS71: =CS70+CS69 -> 7000 | CT71: =CT70+CT69 -> 7000 | CU71: =SUM(CQ71:CT71) -> 25498
B72: Acquired related cost in other income (expense) | BS72: 6407 | BV72: =SUM(BR72:BU72) -> 6407
B73: Total Non-GAAP Other Income (Expense) | BS73: =SUM(BS71:BS72) -> -5792 | BT73: =SUM(BT71:BT72) -> -4951 | BU73: =SUM(BU71:BU72) -> -4692 | BV73: =SUM(BV71:BV72) -> -15347
B75: Adjusted EBITDA | D75: =D81+'Cash Flows'!D8+'Income Statement'!D79-D69 -> 11211 | E75: =E81+'Cash Flows'!E8+'Income Statement'!E79-E69 -> 2936 | F75: =F81+'Cash Flows'!F8+'Income Statement'!F79-F69 -> 2985 | G75: =G81+'Cash Flows'!G8+'Income Statement'!G79-G69 -> 3068 | H75: =H81+'Cash Flows'!H8+'Income Statement'!H79-H69 -> 3622 | I75: =I81+'Cash Flows'!I8+'Income Statement'!I79-I69 -> 12611 | J75: =J81+'Cash Flows'!J8+'Income Statement'!J79-J69 -> 2346 | K75: =K81+'Cash Flows'!K8+'Income Statement'!K79-K69 -> 2450 | ... S75: =S81+'Cash Flows'!S8+'Income Statement'!S79-S69 -> 11673 | T75: =T87+'Cash Flows'!T8+'Income Statement'!T85-T69+T60 -> 13861 | U75: =U87+'Cash Flows'!U8+'Income Statement'!U85-U69+U60 -> 13857 | V75: =V87+'Cash Flows'!V8+'Income Statement'!V85-V69+V60 -> 16439 | W75: =W87+'Cash Flows'!W8+'Income Statement'!W85-W69+W60 -> 18777 | X75: =X87+'Cash Flows'!X8+'Income Statement'!X85-X69+X60 -> 62934 | Y75: =Y87+'Cash Flows'!Y8+'Income Statement'!Y85-Y69+Y60 -> 14780 | Z75: =Z87+'Cash Flows'!Z8+'Income Statement'!Z85-Z69+Z60 -> 17401 | AA75: =AA87+'Cash Flows'!AA8+'Income Statement'!AA85-AA69+AA60 -> 23528 | ... AT75: =AT87+'Cash Flows'!AT8+'Income Statement'!AT85-AT69+AT60 -> 50255 | AU75: ='Cash Flows'!AU8+AU84-AU69+AU60 -> 57244 | AV75: ='Cash Flows'!AV8+AV84-AV69+AV60 -> 56609 | AW75: ='Cash Flows'!AW8+AW84-AW69+AW60 -> 210356 | AX75: ='Cash Flows'!AX8+AX84-AX69+AX60 -> 58117 | AY75: ='Cash Flows'!AY8+AY84-AY69+AY60 -> 59270 | AZ75: ='Cash Flows'!AZ8+AZ84-AZ69+AZ60 -> 67216 | BA75: ='Cash Flows'!BA8+BA84-BA69+BA60 -> 69400 | BB75: ='Cash Flows'!BB8+BB84-BB69+BB60 -> 254003 | ... BG75: ='Cash Flows'!BG8+BG84-BG69+BG60 -> 271777 | BH75: ='Cash Flows'!BH8+BH84-BH69+BH60-123+BH62+695+464 -> 69557 | BI75: ='Cash Flows'!BI8+BI84-BI69+BI60+BI62+160+245 -> 74083 | BJ75: ='Cash Flows'!BJ8+BJ84-BJ69+BJ60+BJ62+160 -> 77100 | BK75: ='Cash Flows'!BK8+BK84-BK69+BK60+BK62+170 -> 82188 | BL75: =SUM(BH75:BK75) -> 302928 | BM75: ='Cash Flows'!BM8+BM84-BM69+BM62+'Cash Flows'!BM12-44+152+727 -> 72430 | BN75: ='Cash Flows'!BN8+BN84-BN69+BN60+BN62-455 -> 80694 | BO75: ='Cash Flows'!BO8+BO84-BO69+BO60+BO62+110 -> 88306 | BP75: ='Cash Flows'!BP8+BP84-BP69+BP60+BP62 -> 81868 | BQ75: =SUM(BM75:BP75) -> 323298 | BR75: ='Cash Flows'!BR8+BR84-BR69+BR62+'Cash Flows'!BR12-44+152+727 -> 85956 | BS75: ='Cash Flows'!BS8+BS84-BS69+BS60+BS62+160 -> 104789 | BT75: ='Cash Flows'!BT8+BT84-BT69+BT60+BT62+2888-1133-461 -> 125022 | BU75: ='Cash Flows'!BU8+BU84-BU69+BU60+BU62+160 -> 111272 | BV75: =SUM(BR75:BU75) -> 427039 | BW75: ='Cash Flows'!BW8+BW84-BW69+BW60+BW62+160 -> 119820 | BX75: ='Income Statement'!BX87+'Income Statement'!BX59+22681+1139+5066+'Income Statement'!BX85+BX60 -> 119049 | BY75: ='Cash Flows'!BY8+BY84-BY69+BY60+BY62 -> 129039 | BZ75: ='Cash Flows'!BZ8+BZ84-BZ69+BZ60+BZ62 -> 108839 | CA75: =SUM(BW75:BZ75) -> 476747 | CB75: =CB87+CB59+18420+CB85+7673+CB60+22+1545 -> 112505 | CC75: =CC87+CC59+19359+5566+'Income Statement'!CC85+'Income Statement'!CC60+50 -> 125499 | CD75: =CD87+CD59+17420+6640+'Income Statement'!CD85+'Income Statement'!CD60+183+3812 -> 132476 | CE75: 117968 | CF75: =SUM(CB75:CE75) -> 488448 | CG75: 134609 | CH75: =CH87+CH59+'Income Statement'!CH85+'Income Statement'!CH60+2+19620+1253+167 -> 143959 | CI75: 152410 | CJ75: 142765 | CK75: =SUM(CG75:CJ75) -> 573743 | CL75: =SUM(CL87,CL59,20209,-CL69,-CL70,CL85,CL60,CL63) -> 162302 | CM75: =SUM(CM87,CM59,'Cash Flows'!CM9,-CM69,-CM70,CM85,CM60,CM63) -> 169299 | CN75: =SUM(CN87,CN59,'Cash Flows'!CN9,-CN69,-CN70,CN85,CN60,CN63) -> 170019 | CO75: =SUM(CO87,CO59,'Cash Flows'!CO9,-CO69,-CO70,CO85,CO60,CO63) -> 164241.03 | CP75: =SUM(CL75:CO75) -> 665861.03 | CQ75: =SUM(CQ87,CQ59,'Cash Flows'!CQ9,-CQ69,-CQ70,CQ85,CQ60,CQ63) -> 177566.79 | CR75: =SUM(CR87,CR59,'Cash Flows'!CR9,-CR69,-CR70,CR85,CR60,CR63) -> 185454.32 | CS75: =SUM(CS87,CS59,'Cash Flows'!CS9,-CS69,-CS70,CS85,CS60,CS63) -> 181453.54 | CT75: =SUM(CT87,CT59,'Cash Flows'!CT9,-CT69,-CT70,CT85,CT60,CT63) -> 182971.39 | CU75: =SUM(CQ75:CT75) -> 727446.04 | CW75: =82188-BK75 -> 0
C76: EBITDA Margins | D76: =D75/D23 -> 0.051006388 | E76: =E75/E23 -> 0.049468417 | F76: =F75/F23 -> 0.044177063 | G76: =G75/G23 -> 0.044698923 | H76: =H75/H23 -> 0.052082135 | I76: =I75/I23 -> 0.047570549 | J76: =J75/J23 -> 0.033723855 | K76: =K75/K23 -> 0.033946683 | ... CU76: =CU75/CU23 -> 0.28731528
B78: Non-GAAP Pre-Tax Income | T78: =T54+T71 -> 12031 | U78: =U54+U71 -> 11875 | V78: =V54+V71 -> 14478 | W78: =W54+W71 -> 16438 | X78: =X54+X71 -> 54822 | Y78: =Y54+Y71 -> 12532 | Z78: =Z54+Z71 -> 15069 | AA78: =AA54+AA71 -> 21294 | ... BR78: =BR54+BR71 -> 78977 | BS78: =BS54+BS73 -> 101614 | BT78: =BT54+BT73 -> 111812 | BU78: =BU54+BU73 -> 97770 | BV78: =BV54+BV73 -> 390173 | BW78: =BW54+BW71 -> 106385 | BX78: =BX54+BX71 -> 104600 | BY78: =BY54+BY71 -> 108688 | BZ78: =BZ54+BZ71 -> 90786 | CA78: =CA54+CA71 -> 410459 | CB78: =CB54+CB71 -> 95811 | CC78: =CC54+CC71 -> 110167 | CD78: =CD54+CD71 -> 117494 | ... CU78: =CU54+CU71 -> 717041.83
C79: Income Tax | T79: =3754+744 -> 4498 | U79: =3685+761 -> 4446 | V79: =4312+700 -> 5012 | W79: =4805+882 -> 5687 | X79: =SUM(T79:W79) -> 19643 | Y79: =3660+932 -> 4592 | Z79: =4577+1015 -> 5592 | AA79: =6978+1150 -> 8128 | AB79: =5659+1101 -> 6760 | AC79: =SUM(Y79:AB79) -> 25072 | AD79: =5639+1279 -> 6918 | AE79: =6006+1375 -> 7381 | AF79: =6523+1590 -> 8113 | AG79: =8550+1770 -> 10320 | AH79: =SUM(AD79:AG79) -> 32732 | AI79: =7720+1540 -> 9260 | AJ79: =8666+1485 -> 10151 | AK79: =9698+1661 -> 11359 | AL79: =9443+1972 -> 11415 | AM79: =SUM(AI79:AL79) -> 42185 | AN79: =10086+1866 -> 11952 | AO79: =10945+1947 -> 12892 | AP79: =11602+2334 -> 13936 | AQ79: =10922+7171 -> 18093 | AR79: =SUM(AN79:AQ79) -> 56873 | AS79: =10495+6819 -> 17314 | AT79: =11323+6944 -> 18267 | AU79: =14155+6613 -> 20768 | AV79: =3923+15408 -> 19331 | AW79: =SUM(AS79:AV79) -> 75680 | AX79: =3653+15589 -> 19242 | AY79: =5396+14172 -> 19568 | AZ79: =5259+16144 -> 21403 | BA79: =-16625+39287 -> 22662 | BB79: =SUM(AX79:BA79) -> 82875 | BC79: =1612+12601 -> 14213 | BD79: =-1461+16500 -> 15039 | BE79: =-298+15987 -> 15689 | BF79: =BF85+7376 -> 15931 | BG79: =SUM(BC79:BF79) -> 60872 | BH79: =7521+7729 -> 15250 | BI79: =BI85+11935 -> 16355 | BJ79: =BJ85+16992 -> 17154 | BK79: =BK85+17371 -> 18371 | BL79: =SUM(BH79:BK79) -> 67130 | BM79: =-12667+28932 -> 16265 | BN79: =-12081+30103 -> 18022 | BO79: =BO85+9038 -> 19690 | BP79: =BP85+24102 -> 18420 | BQ79: =SUM(BM79:BP79) -> 72397 | BR79: =BR85+17634 -> 18954 | BS79: =BS85+23826 -> 24388 | BT79: =BT85+19772 -> 26835 | BU79: 23465 | BV79: =SUM(BR79:BU79) -> 93642 | BW79: =BW85+14088 -> 25532 | BX79: =BX85+14290 -> 25103 | BY79: =BY85+22737 -> 21290 | BZ79: =BZ85+17884 -> 20427 | CA79: =SUM(BW79:BZ79) -> 92352 | CB79: =CB85+13411 -> 21078 | CC79: =CC85+17237 -> 24237 | CD79: =CD85+13946 -> 25849 | CE79: =CE85+17198 -> 22945 | CF79: =SUM(CB79:CE79) -> 94109 | CG79: =CG85+14232 -> 26701 | CH79: =CH85+18377 -> 29304 | CI79: =CI85+20829 -> 31028 | CJ79: =CJ85+18561 -> 30107 | CK79: =SUM(CG79:CJ79) -> 117140 | CL79: =CL85+21200 -> 35438 | CM79: =CM85+19249 -> 37135 | CN79: =CN85+14692 -> 37851 | CO79: =CO85+13984 -> 33416 | CP79: =SUM(CL79:CO79) -> 143840 | CQ79: =CQ80*CQ78 -> 39293.187 | CR79: =CR80*CR78 -> 42060.724 | CS79: =CS80*CS78 -> 41459.832 | CT79: =CT80*CT78 -> 42105.878 | CU79: =SUM(CQ79:CT79) -> 164919.62
C80: Tax Rate % | T80: =T79/T78 -> 0.37386751 | U80: =U79/U78 -> 0.3744 | V80: =V79/V78 -> 0.34618041 | W80: =W79/W78 -> 0.34596666 | X80: =X79/X78 -> 0.35830506 | Y80: =Y79/Y78 -> 0.36642196 | Z80: =Z79/Z78 -> 0.37109297 | AA80: 0.392 | AB80: 0.392 | AC80: =AC79/AC78 -> 0.37173442 | AD80: 0.392 | AE80: =AE79/AE78 -> 0.37644719 | AF80: =AF79/AF78 -> 0.35606759 | AG80: =AG79/AG78 -> 0.42521632 | AH80: =AH79/AH78 -> 0.38486049 | AI80: =AI79/AI78 -> 0.37491396 | AJ80: =AJ79/AJ78 -> 0.35596311 | AK80: =AK79/AK78 -> 0.3515521 | AL80: =AL79/AL78 -> 0.37211501 | ... BE80: =BE79/BE78 -> 0.24000306 | BF80: 0.24 | BG80: =BG79/BG78 -> 0.23999653 | BH80: =BH79/BH78 -> 0.2400063 | BI80: =BI79/BI78 -> 0.23998885 | BJ80: =BJ79/BJ78 -> 0.24000672 | BK80: =BK79/BK78 -> 0.23999948 | BL80: =BL79/BL78 -> 0.24000029 | BM80: =BM79/BM78 -> 0.24264168 | BN80: =BN79/BN78 -> 0.24242669 | ... CP80: =CP79/CP78 -> 0.21984739 | CQ80: 0.23 | CR80: 0.23 | CS80: 0.23 | CT80: 0.23 | CU80: =CU79/CU78 -> 0.23
B81: Non-GAAP Net Income (Loss) | T81: =T78-T79 -> 7533 | U81: =U78-U79 -> 7429 | V81: =V78-V79 -> 9466 | W81: =W78-W79 -> 10751 | X81: =X78-X79 -> 35179 | Y81: =Y78-Y79 -> 7940 | Z81: =Z78-Z79 -> 9477 | AA81: =AA78-AA79 -> 13166 | ... CU81: =CU78-CU79 -> 552122.21
C82: Non-GAAP Net Margin | D82: =D81/D23 -> 0 | E82: =E81/E23 -> 0 | F82: =F81/F23 -> 0 | G82: =G81/G23 -> 0 | H82: =H81/H23 -> 0 | I82: =I81/I23 -> 0 | J82: =J81/J23 -> 0 | K82: =K81/K23 -> 0 | ... CU82: =CU81/CU23 -> 0.21806861
BS83: =+BS81-77227 -> -1
B84: GAAP Pre-Tax Income | D84: =D54+D71 -> 28580 | E84: =E54+E71 -> 5070 | F84: =F54+F71 -> 2026 | G84: =G54+G71 -> 12335 | H84: =H54+H71 -> 9845 | I84: =I54+I71 -> 29276 | J84: =J54+J71 -> 9961 | K84: =K54+K71 -> 11334 | ... S84: =S54+S71 -> 39899 | T84: =T66+T71 -> 9482 | U84: =U66+U71 -> 9309 | V84: =V66+V71 -> 11818 | W84: =W66+W71 -> 13504 | X84: =X66+X71 -> 44113 | Y84: =Y66+Y71 -> 9341 | Z84: =Z66+Z71 -> 11682 | AA84: =AA66+AA71 -> 17810 | ... CU84: =CU66+CU71 -> 490041.83
C85: Income Tax | D85: 11079 | E85: 1944 | F85: 1780 | G85: 5976 | H85: 4714 | I85: 14414 | J85: 3955 | K85: 4461 | L85: 4946 | M85: =N85-L85-K85-J85 -> 4266 | N85: 17628 | O85: 3222 | P85: 4134 | Q85: 4540 | R85: 2949 | S85: =SUM(O85:R85) -> 14845 | T85: 3754 | U85: 3685 | V85: 4312 | W85: 4805 | X85: =SUM(T85:W85) -> 16556 | Y85: 3660 | Z85: 4577 | AA85: 6978 | AB85: 5659 | AC85: =SUM(Y85:AB85) -> 20874 | AD85: 5639 | AE85: 6006 | AF85: 6523 | AG85: 8550 | AH85: =SUM(AD85:AG85) -> 26718 | AI85: 7720 | AJ85: 8666 | AK85: 9698 | AL85: 9443 | AM85: =SUM(AI85:AL85) -> 35527 | AN85: 10086 | AO85: 10945 | AP85: 11602 | AQ85: 10922 | AR85: =SUM(AN85:AQ85) -> 43555 | AS85: 9350 | AT85: 5188 | AU85: 989 | AV85: 3923 | AW85: =SUM(AS85:AV85) -> 19450 | AX85: 3653 | AY85: 5396 | AZ85: 5259 | BA85: -16625 | BB85: =SUM(AX85:BA85) -> -2317 | BC85: 1612 | BD85: -1461 | BE85: -298 | BF85: =8555 -> 8555 | BG85: =SUM(BC85:BF85) -> 8408 | BH85: 7729 | BI85: 4420 | BJ85: 162 | BK85: 1000 | BL85: =SUM(BH85:BK85) -> 13311 | BM85: -12667 | BN85: =-12081 -> -12081 | BO85: 10652 | BP85: -5682 | BQ85: =SUM(BM85:BP85) -> -19778 | BR85: 1320 | BS85: 562 | BT85: 7063 | BU85: -11422 | BV85: =SUM(BR85:BU85) -> -2477 | BW85: 11444 | BX85: 10813 | BY85: -1447 | BZ85: 2543 | CA85: =SUM(BW85:BZ85) -> 23353 | CB85: 7667 | CC85: 7000 | CD85: 11903 | CE85: 5747 | CF85: =SUM(CB85:CE85) -> 32317 | CG85: 12469 | CH85: 10927 | CI85: =10199 -> 10199 | CJ85: 11546 | CK85: =SUM(CG85:CJ85) -> 45141 | CL85: 14238 | CM85: 17886 | CN85: 23159 | CO85: 19432 | CP85: =SUM(CL85:CO85) -> 74715 | CQ85: =CQ84*CQ86 -> 26517.387 | CR85: =CR84*CR86 -> 29815.087 | CS85: =CS84*CS86 -> 29201.133 | CT85: =CT84*CT86 -> 29626.223 | CU85: =SUM(CQ85:CT85) -> 115159.83
C86: Tax Rate % | D86: =D85/D84 -> 0.38764871 | E86: =E85/E84 -> 0.38343195 | F86: =F85/F84 -> 0.87857848 | G86: =G85/G84 -> 0.48447507 | H86: =H85/H84 -> 0.47882174 | I86: =I85/I84 -> 0.49234868 | J86: =J85/J84 -> 0.39704849 | K86: =K85/K84 -> 0.39359449 | ... Z86: =Z85/Z84 -> 0.39179935 | AA86: 0.392 | AB86: 0.392 | AC86: =AC85/AC84 -> 0.38750278 | AD86: 0.38 | AE86: =AE85/AE84 -> 0.39899023 | AF86: =AF85/AF84 -> 0.37121557 | AG86: =AG85/AG84 -> 0.44853636 | AH86: =AH85/AH84 -> 0.40593142 | AI86: 0.38 | AJ86: =AJ85/AJ84 -> 0.37024695 | AK86: =AK85/AK84 -> 0.36324818 | AL86: =AL85/AL84 -> 0.38138126 | AM86: =AM85/AM84 -> 0.37607842 | AN86: =AN85/AN84 -> 0.36865383 | AO86: =AO85/AO84 -> 0.3675162 | AP86: =AP85/AP84 -> 0.36548639 | AQ86: =AQ85/AQ84 -> 0.55895599 | ... BS86: =BS85/BS84 -> 0.021539995 | BT86: 0.05 | BU86: 0.05 | BV86: =BV85/BV84 -> -0.015580576 | BW86: =BW85/BW84 -> 0.22252469 | BX86: =BX85/BX84 -> 0.21302626 | BY86: =BY85/BY84 -> -0.027942454 | BZ86: =BZ85/BZ84 -> 0.0756395 | CA86: =CA85/CA84 -> 0.12448825 | CB86: =CB85/CB84 -> 0.19892585 | CC86: =CC85/CC84 -> 0.12471049 | ... CP86: =CP85/CP84 -> 0.18434628 | CQ86: 0.235 | CR86: 0.235 | CS86: 0.235 | CT86: 0.235 | CU86: =CU85/CU84 -> 0.235
B87: GAAP Net Income | D87: =D84-D85 -> 17501 | E87: =E84-E85 -> 3126 | F87: =F84-F85 -> 246 | G87: =G84-G85 -> 6359 | H87: =H84-H85 -> 5131 | I87: =I84-I85 -> 14862 | J87: =J84-J85 -> 6006 | K87: =K84-K85 -> 6873 | ... CU87: =CU84-CU85 -> 374882
C88: GAAP Net Margin | D88: =D87/D23 -> 0.079623833 | E88: =E87/E23 -> 0.052669711 | F88: =F87/F23 -> 0.0036407228 | G88: =G87/G23 -> 0.092646823 | H88: =H87/H23 -> 0.073780628 | I88: =I87/I23 -> 0.056061652 | J88: =J87/J23 -> 0.08633652 | K88: =K87/K23 -> 0.095230837 | ... CU88: =CU87/CU23 -> 0.14806504
B90: Non-GAAP EPS | D90: =IF(D81>0,D81/D96,D81/D95) -> 0 | E90: =IF(E81>0,E81/E96,E81/E95) -> 0 | F90: =IF(F81>0,F81/F96,F81/F95) -> 0 | G90: =IF(G81>0,G81/G96,G81/G95) -> 0 | H90: =IF(H81>0,H81/H96,H81/H95) -> 0 | I90: =IF(I81>0,I81/I96,I81/I95) -> 0 | J90: =IF(J81>0,J81/J96,J81/J95) -> 0 | K90: =IF(K81>0,K81/K96,K81/K95) -> 0 | ... CU90: =IF(CU81>0,CU81/CU96,CU81/CU95) -> 12.530504
C91: Y/Y Growth % | J91: =J90/E90-1 -> #DIV/0! | K91: =K90/F90-1 -> #DIV/0! | L91: =L90/G90-1 -> #DIV/0! | M91: =M90/H90-1 -> #DIV/0! | O91: =O90/J90-1 -> #DIV/0! | P91: =P90/K90-1 -> #DIV/0! | Q91: =Q90/L90-1 -> #DIV/0! | R91: =R90/M90-1 -> #DIV/0! | T91: =T90/O90-1 -> #DIV/0! | U91: =U90/P90-1 -> #DIV/0! | V91: =V90/Q90-1 -> #DIV/0! | W91: =W90/R90-1 -> #DIV/0! | Y91: =Y90/T90-1 -> 0.092587022 | Z91: =Z90/U90-1 -> 0.31768119 | AA91: =AA90/V90-1 -> 0.38977629 | AB91: =AB90/W90-1 -> 0.051121295 | AC91: =AC90/X90-1 -> 0.21284789 | AD91: =AD90/Y90-1 -> 0.38412375 | AE91: =AE90/Z90-1 -> 0.23284709 | AF91: =AF90/AA90-1 -> 0.057390443 | ... CU91: =CU90/CP90-1 -> 0.07553904
B92: GAAP EPS | D92: =D87/D96 -> 0.42322016 | E92: =E87/E96 -> 0.079085182 | F92: =F87/F96 -> 0.0062069488 | G92: =G87/G96 -> 0.15889952 | H92: =H87/H96 -> 0.13527551 | I92: =I87/I96 -> 0.37928746 | J92: =J87/J96 -> 0.16344191 | K92: =K87/K96 -> 0.18715791 | ... CU92: =CU87/CU96 -> 8.5080085
C93: Y/Y Growth % | I93: =I92/D92-1 -> -0.10380577 | J93: =J92/E92-1 -> 1.0666566 | K93: =K92/F92-1 -> 29.152966 | L93: =L92/G92-1 -> 0.28928951 | M93: =M92/H92-1 -> 0.34347122 | N93: =N92/I92-1 -> 0.94442108 | O93: =O92/J92-1 -> -0.18677519 | P93: =P92/K92-1 -> -0.077730656 | ... CU93: =CU92/CP92-1 -> 0.12757185
B95: Basic Shares Outstanding | D95: 38735 | E95: 38020 | F95: 38087 | G95: 38474 | H95: =G95-2089 -> 36385 | I95: 37714 | J95: 35497 | K95: 35343 | L95: 35118 | M95: =L95+122 -> 35240 | N95: 35240 | O95: 35101 | P95: 34862 | Q95: 34103 | R95: 32285 | S95: 34075 | T95: 32086 | U95: 32005 | V95: 31097 | W95: 29823 | X95: 31267 | Y95: 30015 | Z95: 30171 | AA95: 30387 | AB95: 30779 | AC95: =AVERAGE(Y95:AB95) -> 30338 | AD95: 31403 | AE95: 31617 | AF95: 32037 | AG95: 32498 | AH95: =AVERAGE(AD95:AG95) -> 31888.75 | AI95: 32916 | AJ95: 32918 | AK95: 32935 | AL95: 33275 | AM95: =AVERAGE(AI95:AL95) -> 33011 | AN95: 33562 | AO95: 33751 | AP95: 33900 | AQ95: 35334 | AR95: =AVERAGE(AN95:AQ95) -> 34136.75 | AS95: 36549 | AT95: 36160 | AU95: 36433 | AV95: 36653 | AW95: =AVERAGE(AS95:AV95) -> 36448.75 | AX95: 36845 | AY95: 37154 | AZ95: 37391 | BA95: 37694 | BB95: =AVERAGE(AX95:BA95) -> 37271 | BC95: 38002 | BD95: 38390 | BE95: 38761 | BF95: 38614 | BG95: =AVERAGE(BC95:BF95) -> 38441.75 | BH95: 38308 | BI95: 38402 | BJ95: 38765 | BK95: =BJ95+400 -> 39165 | BL95: =AVERAGE(BH95:BK95) -> 38660 | BM95: 39500 | BN95: 39963 | BO95: =BN95+100 -> 40063 | BP95: =BO95+100 -> 40163 | BQ95: =AVERAGE(BM95:BP95) -> 39922.25 | BR95: 40611 | BS95: 40765 | BT95: 40888 | BU95: 41126 | BV95: =AVERAGE(BR95:BU95) -> 40847.5 | BW95: 41364 | BX95: 41500 | BY95: 41600 | BZ95: 41707 | CA95: =AVERAGE(BW95:BZ95) -> 41542.75 | CB95: 41832 | CC95: 41980 | CD95: 42087 | CE95: =+CD95+200 -> 42287 | CF95: =AVERAGE(CB95:CE95) -> 42046.5 | CG95: 42332 | CH95: 42527 | CI95: 42714 | CJ95: 42864 | CK95: =AVERAGE(CG95:CJ95) -> 42609.25 | CL95: 43024 | CM95: 43163 | CN95: 43135 | CO95: 43057 | CP95: =AVERAGE(CL95:CO95) -> 43094.75 | CQ95: =+CP95+200 -> 43294.75 | CR95: =+CQ95+200 -> 43494.75 | CS95: =+CR95+200 -> 43694.75 | CT95: =+CS95+200 -> 43894.75 | CU95: =AVERAGE(CQ95:CT95) -> 43594.75
B96: Diluted Shares Outstanding | D96: 41352 | E96: 39527 | F96: 39633 | G96: 40019 | H96: =G96-2089 -> 37930 | I96: 39184 | J96: 36747 | K96: 36723 | L96: 36487 | M96: =L96+137 -> 36624 | N96: 36624 | O96: 36655 | P96: 36203 | Q96: 35410 | R96: 33895 | S96: 35528 | T96: 33720 | U96: 33848 | V96: 32960 | W96: 32031 | X96: 33154 | Y96: 32530 | Z96: 32769 | AA96: 32986 | AB96: 33421 | AC96: =AVERAGE(Y96:AB96) -> 32926.5 | AD96: 33948 | AE96: 34290 | AF96: 34764 | AG96: 35348 | AH96: =AVERAGE(AD96:AG96) -> 34587.5 | AI96: 35500 | AJ96: 35161 | AK96: 35284 | AL96: 35661 | AM96: =AVERAGE(AI96:AL96) -> 35401.5 | AN96: 35895 | AO96: 36097 | AP96: 36349 | AQ96: 37864 | AR96: =AVERAGE(AN96:AQ96) -> 36551.25 | AS96: 39071 | AT96: 38738 | AU96: 39062 | AV96: 38975 | AW96: =AVERAGE(AS96:AV96) -> 38961.5 | AX96: 38932 | AY96: 39201 | AZ96: 39342 | BA96: 39499 | BB96: =AVERAGE(AX96:BA96) -> 39243.5 | BC96: 39836 | BD96: 40224 | BE96: 40528 | BF96: 39891 | BG96: =AVERAGE(BC96:BF96) -> 40119.75 | BH96: 39585 | BI96: 39813 | BJ96: 40280 | BK96: =BJ96+400 -> 40680 | BL96: =AVERAGE(BH96:BK96) -> 40089.5 | BM96: 41144 | BN96: 41416 | BO96: 41606 | BP96: =BO96+680 -> 42286 | BQ96: =AVERAGE(BM96:BP96) -> 41613 | BR96: 42056 | BS96: 42094 | BT96: 42286 | BU96: 42536 | BV96: =AVERAGE(BR96:BU96) -> 42243 | BW96: 42443 | BX96: 42321 | BY96: 42407 | BZ96: 42419 | CA96: =AVERAGE(BW96:BZ96) -> 42397.5 | CB96: 42506 | CC96: 42751 | CD96: 42841 | CE96: =+CD96+200 -> 43041 | CF96: =AVERAGE(CB96:CE96) -> 42784.75 | CG96: 43100 | CH96: 43275 | CI96: 43694 | CJ96: 43912 | CK96: =AVERAGE(CG96:CJ96) -> 43495.25 | CL96: 43943 | CM96: 43929 | CN96: 43834 | CO96: 43543 | CP96: =AVERAGE(CL96:CO96) -> 43812.25 | CQ96: =+CP96+100 -> 43912.25 | CR96: =+CQ96+100 -> 44012.25 | CS96: =+CR96+100 -> 44112.25 | CT96: =+CS96+100 -> 44212.25 | CU96: =AVERAGE(CQ96:CT96) -> 44062.25 | CV96: =41750-BQ96 -> 137
B98: Deferred Revenue | D98: ='Balance Sheet'!D29 -> 73714 | E98: ='Balance Sheet'!E29 -> 83426 | F98: ='Balance Sheet'!F29 -> 92973 | G98: ='Balance Sheet'!G29 -> 91029 | H98: ='Balance Sheet'!H29 -> 95773 | I98: ='Balance Sheet'!I29 -> 95773 | J98: ='Balance Sheet'!J29 -> 87042 | K98: ='Balance Sheet'!K29 -> 92441 | ... AB98: ='Balance Sheet'!AB29 -> 140550 | AD98: ='Balance Sheet'!AD29 -> 125385 | AE98: ='Balance Sheet'!AE29 -> 155903 | AF98: ='Balance Sheet'!AF29 -> 151510 | AG98: ='Balance Sheet'!AG29 -> 156738 | AI98: ='Balance Sheet'!AI29 -> 139298 | AJ98: ='Balance Sheet'!AJ29 -> 184578 | AK98: ='Balance Sheet'!AK29 -> 185844 | AL98: ='Balance Sheet'!AL29 -> 189212 | AN98: ='Balance Sheet'!AN29 -> 164706 | AO98: ='Balance Sheet'!AO29 -> 201549 | AP98: ='Balance Sheet'!AP29 -> 200890 | AQ98: ='Balance Sheet'!AQ29 -> 281627 | AS98: ='Balance Sheet'!AS29 -> 250108 | AT98: ='Balance Sheet'!AT29 -> 296481 | AU98: ='Balance Sheet'!AU29 -> 288316 | AV98: ='Balance Sheet'!AV29 -> 298217 | AX98: ='Balance Sheet'!AX29 -> 270208 | AY98: ='Balance Sheet'!AY29 -> 304128 | AZ98: ='Balance Sheet'!AZ29 -> 297163 | BA98: ='Balance Sheet'!BA29 -> 309461 | BC98: ='Balance Sheet'!BC29 -> 268132 | BD98: ='Balance Sheet'!BD29 -> 316084 | BE98: ='Balance Sheet'!BE29 -> 326421 | BF98: ='Balance Sheet'!BF29 -> 350512 | BH98: ='Balance Sheet'!BH29 -> 319900 | BI98: ='Balance Sheet'!BI29 -> 368488 | BJ98: ='Balance Sheet'!BJ29 -> 391560 | BK98: ='Balance Sheet'!BK29 -> 412495 | BM98: ='Balance Sheet'!BM29 -> 365959 | BN98: ='Balance Sheet'!BN29 -> 423037 | BO98: ='Balance Sheet'!BO29 -> 436504 | BP98: ='Balance Sheet'!BP29 -> 461278 | BR98: ='Balance Sheet'!BR29 -> 420535 | BS98: ='Balance Sheet'!BS29 -> 484482 | BT98: ='Balance Sheet'!BT29 -> 495250 | BU98: ='Balance Sheet'!BU29 -> 510529 | BW98: ='Balance Sheet'!BW29 -> 454678 | BX98: ='Balance Sheet'!BX29 -> 528588 | BY98: ='Balance Sheet'!BY29 -> 529233 | BZ98: ='Balance Sheet'!BZ29 -> 568538 | CB98: ='Balance Sheet'!CB29 -> 497395 | CC98: ='Balance Sheet'!CC29 -> 565840 | CD98: ='Balance Sheet'!CD29 -> 600439 | CE98: ='Balance Sheet'!CE29 -> 632914 | CG98: ='Balance Sheet'!CG29 -> 571871 | CH98: ='Balance Sheet'!CH29 -> 652302 | CI98: ='Balance Sheet'!CI29 -> 682422 | CJ98: ='Balance Sheet'!CJ29 -> 701438 | CL98: ='Balance Sheet'!CL29 -> 642379 | CM98: ='Balance Sheet'!CM29 -> 720497 | CN98: ='Balance Sheet'!CN29 -> 761050 | CO98: ='Balance Sheet'!CO29 -> 780838
B99: Cash Flow-Operating | D99: ='Cash Flows'!D26 -> 27821 | E99: ='Cash Flows'!E26 -> 17578 | F99: ='Cash Flows'!F26 -> 2910 | G99: ='Cash Flows'!G26 -> 24169 | H99: ='Cash Flows'!H26 -> 894 | I99: ='Cash Flows'!I26 -> 45551 | J99: ='Cash Flows'!J26 -> 8532 | K99: ='Cash Flows'!K26 -> -8344 | ... BP99: ='Cash Flows'!BP26 -> 88008 | BR99: ='Cash Flows'!BR26 -> 71704 | BS99: ='Cash Flows'!BS26 -> -20348 | BT99: ='Cash Flows'!BT26 -> 205386 | BU99: ='Cash Flows'!BU26 -> 115010 | BW99: ='Cash Flows'!BW26 -> 53541 | BX99: ='Cash Flows'!BX26 -> 76679 | BY99: ='Cash Flows'!BY26 -> 129377 | BZ99: ='Cash Flows'!BZ26 -> 121857 | CB99: ='Cash Flows'!CB26 -> 74709 | CC99: ='Cash Flows'!CC26 -> -19184 | CD99: ='Cash Flows'!CD26 -> 177496 | CE99: ='Cash Flows'!CE26 -> 147419 | CG99: ='Cash Flows'!CG26 -> 71839 | CH99: ='Cash Flows'!CH26 -> 64304 | CI99: ='Cash Flows'!CI26 -> 263716 | CJ99: ='Cash Flows'!CJ26 -> 224774 | CL99: ='Cash Flows'!CL26 -> 56158 | CM99: ='Cash Flows'!CM26 -> 98312 | CN99: ='Cash Flows'!CN26 -> 255191 | CO99: ='Cash Flows'!CO26 -> 243883
B100: Net Cash | D100: ='Balance Sheet'!D6 -> 55694 | E100: ='Balance Sheet'!E6 -> 40298 | F100: ='Balance Sheet'!F6 -> 38144 | G100: ='Balance Sheet'!G6 -> 29361 | H100: ='Balance Sheet'!H6 -> 7619 | I100: ='Balance Sheet'!I6 -> 7619 | J100: ='Balance Sheet'!J6 -> 7393 | K100: ='Balance Sheet'!K6 -> 9449 | ... AB100: ='Balance Sheet'!AB6 -> 6406 | AD100: ='Balance Sheet'!AD6 -> 4495 | AE100: ='Balance Sheet'!AE6 -> 3068 | AF100: ='Balance Sheet'!AF6 -> 52121 | AG100: ='Balance Sheet'!AG6 -> 78876 | AI100: ='Balance Sheet'!AI6 -> 97145 | AJ100: ='Balance Sheet'!AJ6 -> 88892 | AK100: ='Balance Sheet'!AK6 -> 157431 | AL100: ='Balance Sheet'!AL6 -> 206167 | AN100: ='Balance Sheet'!AN6-'Balance Sheet'!AN28-'Balance Sheet'!AN34-'Balance Sheet'!AN36 -> 194721 | AO100: ='Balance Sheet'!AO6-'Balance Sheet'!AO28-'Balance Sheet'!AO34-'Balance Sheet'!AO36 -> 204103 | AP100: ='Balance Sheet'!AP6-'Balance Sheet'!AP28-'Balance Sheet'!AP34-'Balance Sheet'!AP36 -> 238614 | AQ100: ='Balance Sheet'!AQ6-'Balance Sheet'!AQ28-'Balance Sheet'!AQ34-'Balance Sheet'!AQ36 -> -32913 | AR100: ='Balance Sheet'!AR6-'Balance Sheet'!AR28-'Balance Sheet'!AR34-'Balance Sheet'!AR36 -> -32913 | AS100: ='Balance Sheet'!AS6-'Balance Sheet'!AS28-'Balance Sheet'!AS34-'Balance Sheet'!AS36 -> -104659 | AT100: ='Balance Sheet'!AT6-'Balance Sheet'!AT28-'Balance Sheet'!AT34-'Balance Sheet'!AT36 -> -93673 | AU100: ='Balance Sheet'!AU6-'Balance Sheet'!AU28-'Balance Sheet'!AU34-'Balance Sheet'!AU36 -> -10686 | AV100: ='Balance Sheet'!AV6-'Balance Sheet'!AV28-'Balance Sheet'!AV34-'Balance Sheet'!AV36 -> 26151 | AX100: ='Balance Sheet'!AX6-'Balance Sheet'!AX28-'Balance Sheet'!AX34-'Balance Sheet'!AX36 -> 63731 | AY100: ='Balance Sheet'!AY6-'Balance Sheet'!AY28-'Balance Sheet'!AY34-'Balance Sheet'!AY36 -> 55072 | AZ100: ='Balance Sheet'!AZ6-'Balance Sheet'!AZ28-'Balance Sheet'!AZ34-'Balance Sheet'!AZ36 -> 124603 | BA100: ='Balance Sheet'!BA6-'Balance Sheet'!BA28-'Balance Sheet'!BA34-'Balance Sheet'!BA36 -> 185926 | BC100: ='Balance Sheet'!BC6-'Balance Sheet'!BC28-'Balance Sheet'!BC34-'Balance Sheet'!BC36 -> 210616 | BD100: ='Balance Sheet'!BD6-'Balance Sheet'!BD28-'Balance Sheet'!BD34-'Balance Sheet'!BD36 -> 93247 | BE100: ='Balance Sheet'!BE6-'Balance Sheet'!BE28-'Balance Sheet'!BE34-'Balance Sheet'!BE36 -> 219452 | BF100: ='Balance Sheet'!BF6-'Balance Sheet'!BF28-'Balance Sheet'!BF34-'Balance Sheet'!BF36 -> 134279 | BH100: ='Balance Sheet'!BH6-'Balance Sheet'!BH28-'Balance Sheet'!BH34-'Balance Sheet'!BH36 -> -45563 | BI100: ='Balance Sheet'!BI6-'Balance Sheet'!BI28-'Balance Sheet'!BI34-'Balance Sheet'!BI36 -> -3813 | BJ100: ='Balance Sheet'!BJ6-'Balance Sheet'!BJ28-'Balance Sheet'!BJ34-'Balance Sheet'!BJ36 -> 161438 | BK100: ='Balance Sheet'!BK6-'Balance Sheet'!BK28-'Balance Sheet'!BK34-'Balance Sheet'!BK36 -> 232682 | BM100: ='Balance Sheet'!BM6-'Balance Sheet'!BM28-'Balance Sheet'!BM34-'Balance Sheet'!BM36 -> 301985 | BN100: ='Balance Sheet'!BN6-'Balance Sheet'!BN28-'Balance Sheet'!BN34-'Balance Sheet'!BN36 -> 351336 | BO100: ='Balance Sheet'!BO6-'Balance Sheet'!BO28-'Balance Sheet'!BO34-'Balance Sheet'!BO36 -> 518685 | BP100: ='Balance Sheet'!BP6-'Balance Sheet'!BP28-'Balance Sheet'!BP34-'Balance Sheet'!BP36 -> 603623 | BR100: ='Balance Sheet'!BR6-'Balance Sheet'!BR28-'Balance Sheet'!BR34-'Balance Sheet'!BR36 -> 659269 | BS100: ='Balance Sheet'!BS6-'Balance Sheet'!BS28-'Balance Sheet'!BS34-'Balance Sheet'!BS36 -> -1332692 | BT100: ='Balance Sheet'!BT6-'Balance Sheet'!BT28-'Balance Sheet'!BT34-'Balance Sheet'!BT36 -> -1193742 | BU100: ='Balance Sheet'!BU6-'Balance Sheet'!BU28-'Balance Sheet'!BU34-'Balance Sheet'!BU36 -> -1032105 | BW100: ='Balance Sheet'!BW6-'Balance Sheet'!BW28-'Balance Sheet'!BW34-'Balance Sheet'!BW36 -> -1078920 | BX100: ='Balance Sheet'!BX6-'Balance Sheet'!BX28-'Balance Sheet'!BX34-'Balance Sheet'!BX36 -> -1010026 | BY100: ='Balance Sheet'!BY6-'Balance Sheet'!BY28-'Balance Sheet'!BY34-'Balance Sheet'!BY36 -> -890265 | BZ100: ='Balance Sheet'!BZ6-'Balance Sheet'!BZ28-'Balance Sheet'!BZ34-'Balance Sheet'!BZ36 -> -813532 | CB100: ='Balance Sheet'!CB6-'Balance Sheet'!CB28-'Balance Sheet'!CB34-'Balance Sheet'!CB36 -> -737672 | CC100: ='Balance Sheet'!CC6-'Balance Sheet'!CC28-'Balance Sheet'!CC34-'Balance Sheet'!CC36 -> -750310 | CD100: ='Balance Sheet'!CD6-'Balance Sheet'!CD28-'Balance Sheet'!CD34-'Balance Sheet'!CD36 -> -603684 | CE100: ='Balance Sheet'!CE6-'Balance Sheet'!CE28-'Balance Sheet'!CE34-'Balance Sheet'!CE36 -> -480514 | CG100: ='Balance Sheet'!CG6-'Balance Sheet'!CG28-'Balance Sheet'!CG34-'Balance Sheet'!CG36 -> -408401 | CH100: ='Balance Sheet'!CH6-'Balance Sheet'!CH28-'Balance Sheet'!CH34-'Balance Sheet'!CH36 -> -346347 | CI100: ='Balance Sheet'!CI6-'Balance Sheet'!CI28-'Balance Sheet'!CI34-'Balance Sheet'!CI36 -> -59206 | CJ100: ='Balance Sheet'!CJ6-'Balance Sheet'!CJ28-'Balance Sheet'!CJ34-'Balance Sheet'!CJ36 -> 146787 | CL100: ='Balance Sheet'!CL6-'Balance Sheet'!CL28-'Balance Sheet'!CL34-'Balance Sheet'!CL36 -> 705729 | CM100: ='Balance Sheet'!CM6-'Balance Sheet'!CM28-'Balance Sheet'!CM34-'Balance Sheet'!CM36 -> 787447 | CN100: ='Balance Sheet'!CN6-'Balance Sheet'!CN28-'Balance Sheet'!CN34-'Balance Sheet'!CN36 -> 834101 | CO100: ='Balance Sheet'!CO6-'Balance Sheet'!CO28-'Balance Sheet'!CO34-'Balance Sheet'!CO36 -> 1015400
B101: Cash/Share | D101: =D100/D96 -> 1.3468272 | E101: =E100/E96 -> 1.0195057 | F101: =F100/F96 -> 0.9624303 | G101: =G100/G96 -> 0.7336765 | H101: =H100/H96 -> 0.20087002 | I101: =I100/I96 -> 0.19444161 | J101: =J100/J96 -> 0.20118649 | K101: =K100/K96 -> 0.25730469 | ... AB101: =AB100/AB96 -> 0.19167589 | AD101: =AD100/AD96 -> 0.13240839 | AE101: =AE100/AE96 -> 0.089472149 | AF101: =AF100/AF96 -> 1.4992809 | AG101: =AG100/AG96 -> 2.2314134 | AI101: =AI100/AI96 -> 2.7364789 | AJ101: =AJ100/AJ96 -> 2.528142 | AK101: =AK100/AK96 -> 4.4618241 | AL101: =AL100/AL96 -> 5.7813017 | AN101: =AN100/AN96 -> 5.4247388 | AO101: =AO100/AO96 -> 5.6542926 | AP101: =AP100/AP96 -> 6.5645272 | AQ101: =AQ100/AQ96 -> -0.86924255 | AS101: =AS100/AS96 -> -2.6786875 | AT101: =AT100/AT96 -> -2.4181166 | AU101: =AU100/AU96 -> -0.2735651 | AV101: =AV100/AV96 -> 0.67096857 | AX101: =AX100/AX96 -> 1.6369824 | AY101: =AY100/AY96 -> 1.4048621 | AZ101: =AZ100/AZ96 -> 3.167175 | BA101: =BA100/BA96 -> 4.7071065 | BC101: =BC100/BC96 -> 5.287077 | BD101: =BD100/BD96 -> 2.3181931 | BE101: =BE100/BE96 -> 5.4148243 | BF101: =BF100/BF96 -> 3.3661478 | BH101: =BH100/BH96 -> -1.1510168 | BI101: =BI100/BI96 -> -0.095772738 | BJ101: =BJ100/BJ96 -> 4.0078947 | BK101: =BK100/BK96 -> 5.7198132 | BM101: =BM100/BM96 -> 7.3397093 | BN101: =BN100/BN96 -> 8.4830983 | BO101: =BO100/BO96 -> 12.466591 | BP101: =BP100/BP96 -> 14.274772 | BR101: =BR100/BR96 -> 15.67598 | BS101: =BS100/BS96 -> -31.659904 | BT101: =BT100/BT96 -> -28.230194 | BU101: =BU100/BU96 -> -24.26427 | BW101: =BW100/BW96 -> -25.420446 | BX101: =BX100/BX96 -> -23.865835 | BY101: =BY100/BY96 -> -20.99335 | BZ101: =BZ100/BZ96 -> -19.178481 | CB101: =CB100/CB96 -> -17.354538 | CC101: =CC100/CC96 -> -17.550701 | CD101: =CD100/CD96 -> -14.091268 | CE101: =CE100/CE96 -> -11.164099 | CG101: =CG100/CG96 -> -9.4756613 | CH101: =CH100/CH96 -> -8.0033969 | CI101: =CI100/CI96 -> -1.3550144 | CJ101: =CJ100/CJ96 -> 3.3427537 | CL101: =CL100/CL96 -> 16.060101 | CM101: =CM100/CM96 -> 17.925448 | CN101: =CN100/CN96 -> 19.028631 | CO101: =CO100/CO96 -> 23.319477
B102: Joshua Reilly, CFA, Jreilly@needhamco.com | CU102: Source: Company Reports and Needham & Company, LLC Estimates
B103: 612.386.4640 | CU103: $ in thousands, except per share data
CL104: =CL8+CL14 -> 487790 | CM104: =CM8+CM14 -> 517198 | CN104: =CN8+CN14 -> 512406 | CO104: =CO8+CO14 -> 514358.03 | CP104: =SUM(CL104:CO104) -> 2031752 | CQ104: =CQ8+CQ14 -> 531526.87 | CR104: =CR8+CR14 -> 565453.83 | CS104: =CS8+CS14 -> 560704.14 | CT104: =CT8+CT14 -> 562889.01 | CU104: =SUM(CQ104:CT104) -> 2220573.8
AB105: 27 | AD105: 25 | AE105: 28 | AF105: 34 | AG105: 34 | AH105: 121 | AI105: 25 | AJ105: 28 | AK105: 34 | AL105: 34 | AM105: 121 | AN105: 107.8 | AO105: 127.6 | AP105: 147.4 | AQ105: 167.2 | AR105: 187 | AS105: 107.8 | AT105: 127.6 | AU105: 147.4 | AV105: 167.2 | AW105: 187 | CG105: =119/513 -> 0.23196881 | CK105: =510/2130 -> 0.23943662 | CL105: =119/513 -> 0.23196881
C106: Proforma Adjustments | D106: 2007 | E106: 1Q08 | F106: 2Q08 | G106: 3Q08 | H106: 4Q08 | J106: 1Q09 | K106: 2Q09 | L106: 3Q09 | M106: 4Q09 | O106: 1Q10 | P106: 2Q10 | Q106: 3Q10 | R106: 4Q10 | S106: 2010 | T106: 1Q11 | U106: 2Q11 | V106: 3Q11 | W106: 4Q11 | X106: 2011 | Y106: 1Q12 | Z106: 2Q12 | AA106: 3Q12 | AB106: 4Q12 | AC106: 2012 | AD106: 1Q13 | AE106: 2Q13 | AF106: 3Q13 | AG106: 4Q13 | AH106: 2013 | AI106: 1Q14 | AJ106: 2Q14 | AK106: 3Q14 | AL106: 4Q14 | AM106: 2014 | AN106: 1Q15 | AO106: 2Q15E | AP106: 3Q15E | AQ106: 4Q15E | AR106: 2015E | AS106: 1Q15E | AT106: 2Q15E | AU106: 3Q15E | AV106: 4Q15E | AW106: 2015E
C107: GAAP Operating Income | D107: =D81 -> 0 | E107: =E81 -> 0 | F107: =F81 -> 0 | G107: =G81 -> 0 | H107: =H81 -> 0 | J107: =J81 -> 0 | K107: =K81 -> 0 | L107: =L81 -> 0 | M107: =M81 -> 0 | O107: =O81 -> 0 | P107: =P81 -> 0 | Q107: =Q81 -> 0 | R107: =R81 -> 0 | S107: =S81 -> 0 | T107: =T54 -> 12531 | U107: =U54 -> 12399 | V107: =V54 -> 15040 | W107: =W54 -> 17256 | X107: =X54 -> 57226 | Y107: =Y54 -> 13235 | Z107: =Z54 -> 15842 | AA107: =AA54 -> 22143 | ... AW107: =AW54 -> 213526
C109: Add Back:
C110: Amortization | D110: =D50+D30 -> 3757 | E110: =E50+E30 -> 1003 | F110: =F50+F30 -> 10097 | G110: =G50+G30 -> 1084 | H110: =H50+H30 -> 1098 | J110: =J50+J30 -> 987 | K110: =K50+K30 -> 1035 | L110: =L50+L30 -> 1054 | M110: =M50+M30 -> 1040 | O110: =O50+O30 -> 1204 | P110: =P50+P30 -> 1205 | Q110: =Q50+Q30 -> 1204 | R110: =R50+R30 -> 1204 | S110: =S50+S30 -> 4817 | T110: =T50+T30 -> 0 | U110: =U50+U30 -> 0 | V110: =V50+V30 -> 0 | ... AW110: =AW50+AW30 -> 0
C111: Share-based comp | D111: ='Cash Flows'!D12 -> 2365 | E111: ='Cash Flows'!E12 -> 716 | F111: ='Cash Flows'!F12 -> 905 | G111: ='Cash Flows'!G12 -> 1098 | H111: ='Cash Flows'!H12 -> 1101 | J111: ='Cash Flows'!J12 -> 1127 | K111: ='Cash Flows'!K12 -> 1238 | L111: ='Cash Flows'!L12 -> 1288 | M111: ='Cash Flows'!M12 -> 1392 | O111: ='Cash Flows'!O12 -> 1465 | P111: ='Cash Flows'!P12 -> 1608 | Q111: ='Cash Flows'!Q12 -> 1544 | R111: ='Cash Flows'!R12 -> 1515 | S111: ='Cash Flows'!S12 -> 6132 | T111: ='Cash Flows'!T12 -> 1449 | U111: ='Cash Flows'!U12 -> 1520 | V111: ='Cash Flows'!V12 -> 1616 | ... AA111: ='Cash Flows'!AA12 -> 1903 | AB111: 1905 | AC111: ='Cash Flows'!AC12 -> 7411 | AD111: 2200 | AE111: 2400 | AF111: 2600 | AG111: 2800 | AH111: =SUM(AD111:AG111) -> 10000 | AI111: 3000 | AJ111: 3200 | AK111: 3400 | AL111: 3600 | AM111: =SUM(AI111:AL111) -> 13200 | AN111: 3800 | AO111: 4000 | AP111: 4200 | AQ111: 4400 | AR111: =SUM(AN111:AQ111) -> 16400 | AS111: 3800 | AT111: 4000 | AU111: 4200 | AV111: 4400 | AW111: =SUM(AS111:AV111) -> 16400
...

Sheet Balance Sheet
B2: ='Income Statement'!B2 -> Tyler Technologies (TYL)
B4: Balance Sheet | D4: 2007 | E4: 1Q08 | F4: 2Q08 | G4: 3Q08 | H4: 4Q08 | I4: 2008 | J4: 1Q09 | K4: 2Q09 | L4: 3Q09 | M4: 4Q09 | N4: 2009 | O4: 1Q10 | P4: 2Q10 | Q4: 3Q10 | R4: 4Q10 | S4: 2010 | T4: 1Q11 | U4: 2Q11 | V4: 3Q11 | W4: 4Q11 | X4: 2011 | Y4: 1Q12 | Z4: 2Q12 | AA4: 3Q12 | AB4: 4Q12 | AC4: 2012 | AD4: 1Q13 | AE4: 2Q13 | AF4: 3Q13 | AG4: 4Q13 | AH4: 2013 | AI4: 1Q14 | AJ4: 2Q14 | AK4: 3Q14 | AL4: 4Q14 | AM4: 2014 | AN4: 1Q15 | AO4: 2Q15 | AP4: 3Q15 | AQ4: 4Q15 | AR4: 2015 | AS4: 1Q16 | AT4: 2Q16 | AU4: 3Q16 | AV4: 4Q16 | AW4: 2016 | AX4: 1Q17 | AY4: 2Q17 | AZ4: 3Q17 | BA4: 4Q17 | BB4: 2017 | BC4: 1Q18 | BD4: 2Q18 | BE4: 3Q18 | BF4: 4Q18 | BG4: 2018 | BH4: 1Q19 | BI4: 2Q19 | BJ4: 3Q19 | BK4: 4Q19 | BL4: 2019 | BM4: 1Q20 | BN4: 2Q20 | BO4: 3Q20 | BP4: 4Q20 | BQ4: 2020 | BR4: 1Q21 | BS4: 2Q21 | BT4: 3Q21 | BU4: 4Q21 | BV4: 2021 | BW4: 1Q22 | BX4: 2Q22 | BY4: 3Q22 | BZ4: 4Q22 | CA4: 2022 | CB4: ='Income Statement'!CB4 -> 1Q23 | CC4: ='Income Statement'!CC4 -> 2Q23 | CD4: ='Income Statement'!CD4 -> 3Q23 | CE4: ='Income Statement'!CE4 -> 4Q23 | CF4: ='Income Statement'!CF4 -> 2023 | CG4: ='Income Statement'!CG4 -> 1Q24 | CH4: ='Income Statement'!CH4 -> 2Q24 | CI4: ='Income Statement'!CI4 -> 3Q24 | ... CU4: ='Income Statement'!CU4 -> 2026E
B5: Assets:
C6: Cash & Cash Equivilents | D6: 55694 | E6: 40298 | F6: 38144 | G6: 29361 | H6: 7619 | I6: =H6 -> 7619 | J6: 7393 | K6: 9449 | L6: 7895 | M6: 15746 | N6: =M6 -> 15746 | O6: 9051 | P6: 6217 | Q6: 6449 | R6: 2139 | S6: =R6 -> 2139 | T6: 2248 | U6: 1437 | V6: 5280 | W6: 1351 | X6: =W6 -> 1351 | Y6: 9932 | Z6: =312+50 -> 362 | AA6: 103 | AB6: 6406 | AC6: =AB6 -> 6406 | AD6: 4495 | AE6: 3068 | AF6: 52121 | AG6: 78876 | AH6: =AG6 -> 78876 | AI6: 97145 | AJ6: =88092+800 -> 88892 | AK6: 157431 | AL6: 206167 | AM6: =AL6 -> 206167 | AN6: 194721 | AO6: 204103 | AP6: 238614 | AQ6: 33087 | AR6: =AQ6 -> 33087 | AS6: 35341 | AT6: 41327 | AU6: 23314 | AV6: 36151 | AW6: =AV6 -> 36151 | AX6: 63731 | AY6: 55072 | AZ6: 124603 | BA6: 185926 | BB6: =BA6 -> 185926 | BC6: 210616 | BD6: 93247 | BE6: 219452 | BF6: 134279 | BG6: =BF6 -> 134279 | BH6: 39437 | BI6: 11187 | BJ6: 161438 | BK6: 232682 | BL6: =BK6 -> 232682 | BM6: 301985 | BN6: 351336 | BO6: 518685 | BP6: 603623 | BQ6: =BP6 -> 603623 | BR6: 1250752 | BS6: 216773 | BT6: =234128 -> 234128 | BU6: 309171 | BV6: =BU6 -> 309171 | BW6: 243262 | BX6: 253062 | BY6: 185927 | BZ6: 173857 | CA6: =BZ6 -> 173857 | CB6: 130845 | CC6: 118764 | CD6: 131486 | CE6: 165493 | CF6: =CE6 -> 165493 | CG6: 188237 | CH6: 250722 | CI6: =538296 -> 538296 | CJ6: 744721 | CK6: =CJ6 -> 744721 | CL6: 705729 | CM6: 787447 | CN6: 834101 | CO6: 1015400 | CP6: =CO6 -> 1015400 | CQ6: =CP6+'Cash Flows'!CQ56 -> 989383.92 | CR6: =CQ6+'Cash Flows'!CR56 -> 1217020 | CS6: =CR6+'Cash Flows'!CS56 -> 1455664.2 | CT6: =CS6+'Cash Flows'!CT56 -> 1696790.2 | CU6: =CT6 -> 1696790.2
C7: Accounts Receivable | D7: 63965 | E7: 59271 | F7: 79638 | G7: 66430 | H7: 76989 | I7: =H7 -> 76989 | J7: 65596 | K7: 83183 | L7: 85613 | M7: 81245 | N7: =M7 -> 81245 | O7: 63076 | P7: 89503 | Q7: 77139 | R7: 81860 | S7: =R7 -> 81860 | T7: 66474 | U7: 90486 | V7: 75456 | W7: 90012 | X7: =W7 -> 90012 | Y7: 58888 | Z7: 100460 | AA7: 78218 | AB7: 100327 | AC7: =AB7 -> 100327 | AD7: 76220 | AE7: 121256 | AF7: 90503 | AG7: 106570 | AH7: =AG7 -> 106570 | AI7: 82334 | AJ7: 144234 | AK7: 111803 | AL7: 112660 | AM7: =AL7 -> 112660 | AN7: 105790 | AO7: 152178 | AP7: 129228 | AQ7: 176360 | AR7: =AQ7 -> 176360 | AS7: 137332 | AT7: 209483 | AU7: 188429 | AV7: 200334 | AW7: =AV7 -> 200334 | AX7: 163723 | AY7: 233831 | AZ7: 206444 | BA7: 227127 | BB7: =BA7 -> 227127 | BC7: 216516 | BD7: 299253 | BE7: 281523 | BF7: 298912 | BG7: =BF7 -> 298912 | BH7: 298980 | BI7: 381379 | BJ7: 347982 | BK7: 374089 | BL7: =BK7 -> 374089 | BM7: 318144 | BN7: 405731 | BO7: 362667 | BP7: 382319 | BQ7: =BP7 -> 382319 | BR7: 330824 | BS7: 584156 | BT7: 538119 | BU7: 521059 | BV7: =BU7 -> 521059 | BW7: 501200 | BX7: 597560 | BY7: 561780 | BZ7: 577257 | CA7: =BZ7 -> 577257 | CB7: 508683 | CC7: 638726 | CD7: 623613 | CE7: 619704 | CF7: =CE7 -> 619704 | CG7: 542441 | CH7: 700825 | CI7: 619508 | CJ7: 587634 | CK7: =CJ7 -> 587634 | CL7: 559873 | CM7: 714413 | CN7: 661986 | CO7: 638798 | CP7: =CO7 -> 638798 | CQ7: =CQ55*'Income Statement'!CQ23 -> 699805.9 | CR7: =CR55*'Income Statement'!CR23 -> 746296.9 | CS7: =CS55*'Income Statement'!CS23 -> 700704.55 | CT7: =CT55*'Income Statement'!CT23 -> 688380.13 | CU7: =CT7 -> 688380.13
C8: Short-term investments | BT8: 49355 | BU8: 52300 | BV8: =BU8 -> 52300 | BW8: 44973 | BX8: 34466 | BY8: 39360 | BZ8: 37030 | CA8: =BZ8 -> 37030 | CB8: 28810 | CC8: 19100 | CD8: 11623 | CE8: 10385 | CF8: =CE8 -> 10385 | CG8: 8707 | CH8: 7288 | CI8: 5985 | CJ8: 23257 | CK8: =CJ8 -> 23257 | CL8: 101674 | CM8: 104899 | CN8: 116720 | CO8: 81800 | CP8: =CO8 -> 81800 | CQ8: =CP8 -> 81800 | CR8: =CQ8 -> 81800 | CS8: =CR8 -> 81800 | CT8: =CS8 -> 81800 | CU8: =CT8 -> 81800
C9: Prepaid Expenses | D9: 7726 | E9: 8611 | F9: 8787 | G9: 7693 | H9: 8602 | I9: =H9 -> 8602 | J9: 8597 | K9: 8811 | L9: 7766 | M9: 7921 | N9: =M9 -> 7921 | O9: 7814 | P9: 7470 | Q9: 7642 | R9: 0 | S9: =R9 -> 0 | T9: 7915 | U9: 0 | V9: 0 | W9: 0 | X9: =W9 -> 0 | Y9: 0 | Z9: 0 | AA9: 0 | AB9: 0 | AC9: =AB9 -> 0 | AD9: 0 | AE9: 0 | AF9: 0 | AG9: 0 | AH9: =AG9 -> 0 | AI9: 0 | AJ9: 0 | AK9: 0 | AL9: 0 | AM9: =AL9 -> 0 | AN9: 0 | AO9: 0 | AP9: 0 | AQ9: 0 | AR9: =AQ9 -> 0 | AS9: 0 | AT9: 0 | AU9: 0 | AV9: 0 | AW9: =AV9 -> 0 | AX9: 0 | AY9: 0 | AZ9: 0 | BA9: 0 | BB9: =BA9 -> 0 | BC9: 0 | BD9: 0 | BE9: 0 | BF9: 0 | BG9: =BF9 -> 0 | BH9: 0 | BI9: 0 | BJ9: 0 | BK9: 0 | BL9: =BK9 -> 0 | BM9: 0 | BN9: 0 | BO9: 0 | BP9: 0 | BQ9: =BP9 -> 0 | BS9: 0 | BT9: 53145 | BU9: 63664 | BV9: =BU9 -> 63664 | BW9: 70464 | BX9: 69647 | BY9: 65704 | BZ9: 59098 | CA9: =BZ9 -> 59098 | CB9: 77325 | CC9: 80290 | CD9: 67636 | CE9: 65003 | CF9: =CE9 -> 65003 | CG9: 85036 | CH9: 83497 | CI9: 74775 | CJ9: 73192 | CK9: =CJ9 -> 73192 | CL9: 99662 | CM9: 99332 | CN9: 88277 | CO9: 84142 | CP9: =CO9 -> 84142 | CQ9: ='Income Statement'!CQ23*'Balance Sheet'!CQ57 -> 73023.224 | CR9: ='Income Statement'!CR23*'Balance Sheet'!CR57 -> 77874.46 | CS9: ='Income Statement'!CS23*'Balance Sheet'!CS57 -> 76440.497 | CT9: ='Income Statement'!CT23*'Balance Sheet'!CT57 -> 70112.791 | CU9: =CT9 -> 70112.791
C10: Income tax receivable | AG10: 9721 | AQ10: 21080 | AR10: =AQ10 -> 21080 | AS10: 11798 | AT10: 23994 | AU10: 17680 | AV10: 2895 | AW10: =AV10 -> 2895 | AX10: 0 | AY10: 12206 | AZ10: 3362 | BA10: 11339 | BB10: =BA10 -> 11339 | BC10: 7286 | BD10: 13100 | BE10: 13281 | BF10: 4697 | BG10: =BF10 -> 4697 | BI10: =BH10 -> 0 | BJ10: 4 | BK10: 6482 | BL10: =BK10 -> 6482 | BM10: 16657 | BN10: 27935 | BO10: 20752 | BP10: 21598 | BQ10: =BP10 -> 21598 | BR10: 17066 | BS10: 20404 | BT10: 3509 | BU10: 18137 | BV10: =BU10 -> 18137 | BW10: 0 | BX10: 2552 | BY10: 7379 | BZ10: 0 | CA10: =BZ10 -> 0 | CB10: =CA10 -> 0 | CC10: =CB10 -> 0 | CD10: =CC10 -> 0 | CE10: =CD10 -> 0 | CF10: =CE10 -> 0 | CG10: =CF10 -> 0 | CH10: =CG10 -> 0 | CJ10: 11975 | CK10: =CJ10 -> 11975 | CM10: =CL10 -> 0 | CN10: 36761 | CO10: 23748 | CP10: =CO10 -> 23748 | CQ10: =CP10 -> 23748 | CR10: =CQ10 -> 23748 | CS10: =CR10 -> 23748 | CT10: =CS10 -> 23748 | CU10: =CT10 -> 23748
C11: Other Current | D11: 1324 | E11: 1556 | F11: 3594 | G11: 1771 | H11: 1444 | I11: =H11 -> 1444 | J11: 1551 | K11: 2113 | L11: 1767 | M11: 1437 | N11: =M11 -> 1437 | O11: 1493 | P11: 3886 | Q11: 2019 | R11: 11344 | S11: =R11 -> 11344 | T11: 1896 | U11: 12305 | V11: 10491 | W11: 10634 | X11: =W11 -> 10634 | Y11: 9764 | Z11: 11343 | AA11: 10692 | AB11: 10480 | AC11: =AB11 -> 10480 | AD11: 11290 | AE11: 16716 | AF11: 16629 | AG11: 14309 | AH11: =AG11 -> 14309 | AI11: 20381 | AJ11: 20147 | AK11: 16007 | AL11: 18209 | AM11: =AL11 -> 18209 | AN11: 17590 | AO11: 29569 | AP11: 33989 | AQ11: 37688 | AR11: =AQ11 -> 37688 | AS11: 41065 | AT11: 49147 | AU11: 47904 | AV11: 43580 | AW11: =AV11 -> 43580 | AX11: 44121 | AY11: 51169 | AZ11: 65312 | BA11: 72408 | BB11: =BA11 -> 72408 | BC11: 98218 | BD11: 96388 | BE11: 87438 | BF11: 80970 | BG11: =BF11 -> 80970 | BH11: 63857 | BI11: 61004 | BJ11: 60382 | BK11: 66444 | BL11: =BK11 -> 66444 | BM11: 75434 | BN11: 88940 | BO11: 88495 | BP11: 105530 | BQ11: =BP11 -> 105530 | BR11: 101710 | BS11: 107595 | BV11: =BU11 -> 0 | CA11: =BZ11 -> 0 | CF11: =CE11 -> 0 | CK11: =CJ11 -> 0 | CO11: 0 | CP11: =CO11 -> 0 | CU11: =CT11 -> 0
C12: Deferred Income taxes | D12: 2355 | E12: 1922 | F12: 1922 | G12: 1839 | H12: 2570 | I12: =H12 -> 2570 | J12: 2586 | K12: 2589 | L12: 2555 | M12: 3338 | N12: =M12 -> 3338 | O12: 3279 | P12: 3288 | Q12: 4112 | R12: 3106 | S12: =R12 -> 3106 | T12: 3106 | U12: 3106 | V12: 3106 | W12: 5095 | X12: =W12 -> 5095 | Y12: 5095 | Z12: 5095 | AA12: 5051 | AB12: 5544 | AC12: =AB12 -> 5544 | AD12: 5544 | AE12: 5512 | AF12: 5512 | AG12: 7759 | AH12: =AG12 -> 7759 | AI12: 7759 | AJ12: 7759 | AK12: 7759 | AL12: 9674 | AM12: =AL12 -> 9674 | AN12: 9674 | AO12: 9674 | AP12: =AO12 -> 9674 | AQ12: 0 | AR12: =AQ12 -> 0 | AS12: =AR12 -> 0 | AT12: =AS12 -> 0 | AU12: =AT12 -> 0 | AV12: =AU12 -> 0 | AW12: =AV12 -> 0 | AX12: =AW12 -> 0 | AY12: =AX12 -> 0 | ... CC12: =CB12 -> 0 | CD12: 7633 | CE12: 0 | CF12: =CE12 -> 0 | CG12: =CF12 -> 0 | CH12: =CG12 -> 0 | CI12: =CH12 -> 0 | CK12: =CJ12 -> 0 | CM12: 17601 | CO12: 0 | CP12: =CO12 -> 0 | CQ12: =CP12 -> 0 | CR12: =CQ12 -> 0 | CS12: =CR12 -> 0 | CT12: =CS12 -> 0 | CU12: =CT12 -> 0
B13: Total Current Assets | D13: =SUM(D6:D12) -> 131064 | E13: =SUM(E6:E12) -> 111658 | F13: =SUM(F6:F12) -> 132085 | G13: =SUM(G6:G12) -> 107094 | H13: =SUM(H6:H12) -> 97224 | I13: =SUM(I6:I12) -> 97224 | J13: =SUM(J6:J12) -> 85723 | K13: =SUM(K6:K12) -> 106145 | ... AB13: =SUM(AB6:AB12) -> 122757 | AC13: =AB13 -> 122757 | AD13: =SUM(AD6:AD12) -> 97549 | AE13: =SUM(AE6:AE12) -> 146552 | AF13: =SUM(AF6:AF12) -> 164765 | AG13: =SUM(AG6:AG12) -> 217235 | AH13: =AG13 -> 217235 | AI13: =SUM(AI6:AI12) -> 207619 | AJ13: =SUM(AJ6:AJ12) -> 261032 | AK13: =SUM(AK6:AK12) -> 293000 | AL13: =SUM(AL6:AL12) -> 346710 | AM13: =AL13 -> 346710 | AN13: =SUM(AN6:AN12) -> 327775 | AO13: =SUM(AO6:AO12) -> 395524 | AP13: =SUM(AP6:AP12) -> 411505 | AQ13: =SUM(AQ6:AQ12) -> 268215 | AR13: =AQ13 -> 268215 | AS13: =SUM(AS6:AS12) -> 225536 | AT13: =SUM(AT6:AT12) -> 323951 | AU13: =SUM(AU6:AU12) -> 277327 | AV13: =SUM(AV6:AV12) -> 282960 | AW13: =AV13 -> 282960 | AX13: =SUM(AX6:AX12) -> 271575 | AY13: =SUM(AY6:AY12) -> 352278 | AZ13: =SUM(AZ6:AZ12) -> 399721 | BA13: =SUM(BA6:BA12) -> 496800 | BB13: =BA13 -> 496800 | BC13: =SUM(BC6:BC12) -> 532636 | BD13: =SUM(BD6:BD12) -> 501988 | BE13: =SUM(BE6:BE12) -> 601694 | BF13: =SUM(BF6:BF12) -> 518858 | BG13: =BF13 -> 518858 | BH13: =SUM(BH6:BH12) -> 402274 | BI13: =SUM(BI6:BI12) -> 453570 | BJ13: =SUM(BJ6:BJ12) -> 569806 | BK13: =SUM(BK6:BK12) -> 679697 | BL13: =BK13 -> 679697 | BM13: =SUM(BM6:BM12) -> 712220 | BN13: =SUM(BN6:BN12) -> 873942 | BO13: =SUM(BO6:BO12) -> 990599 | BP13: =SUM(BP6:BP12) -> 1113070 | BQ13: =BP13 -> 1113070 | BR13: =SUM(BR6:BR12) -> 1700352 | BS13: =SUM(BS6:BS12) -> 928928 | BT13: =SUM(BT6:BT12) -> 878256 | BU13: =SUM(BU6:BU12) -> 964331 | BV13: =BU13 -> 964331 | BW13: =SUM(BW6:BW12) -> 859899 | BX13: =SUM(BX6:BX12) -> 957287 | BY13: =SUM(BY6:BY12) -> 860150 | BZ13: =SUM(BZ6:BZ12) -> 847242 | CA13: =BZ13 -> 847242 | CB13: =SUM(CB6:CB12) -> 745663 | CC13: =SUM(CC6:CC12) -> 856880 | CD13: =SUM(CD6:CD12) -> 841991 | CE13: =SUM(CE6:CE12) -> 860585 | CF13: =CE13 -> 860585 | CG13: =SUM(CG6:CG12) -> 824421 | CH13: =SUM(CH6:CH12) -> 1042332 | CI13: =SUM(CI6:CI12) -> 1238564 | CJ13: =SUM(CJ6:CJ12) -> 1440779 | CK13: =CJ13 -> 1440779 | CL13: =SUM(CL6:CL12) -> 1466938 | CM13: =SUM(CM6:CM12) -> 1723692 | CN13: =SUM(CN6:CN12) -> 1737845 | CO13: =SUM(CO6:CO12) -> 1843888 | CP13: =CO13 -> 1843888 | CQ13: =SUM(CQ6:CQ12) -> 1867761 | CR13: =SUM(CR6:CR12) -> 2146739.4 | CS13: =SUM(CS6:CS12) -> 2338357.3 | CT13: =SUM(CT6:CT12) -> 2560831.1 | CU13: =CT13 -> 2560831.1
C14: Accounts Receivable Long-term | D14: 398 | E14: 529 | F14: 460 | G14: 681 | H14: 197 | I14: =H14 -> 197 | J14: 292 | K14: 311 | L14: 483 | M14: 1018 | N14: =M14 -> 1018 | O14: 1109 | P14: 774 | Q14: 1287 | R14: 1231 | S14: =R14 -> 1231 | T14: 1403 | U14: 631 | V14: 1212 | W14: 2095 | X14: =W14 -> 2095 | Y14: 1400 | Z14: 576 | AA14: 681 | AB14: 1187 | AC14: =AB14 -> 1187 | AD14: 1621 | AE14: 800 | AF14: 1098 | AG14: 588 | AH14: =AG14 -> 588 | AI14: 526 | AJ14: 1127 | AK14: 1454 | AL14: 1761 | AM14: =AL14 -> 1761 | AN14: 311 | AO14: 391 | AP14: 1072 | AQ14: 2777 | AR14: =AQ14 -> 2777 | AS14: 3098 | AT14: 2579 | AU14: 2744 | AV14: 2480 | AW14: =AV14 -> 2480 | AX14: 2577 | AY14: 2333 | AZ14: 3867 | BA14: 7536 | BB14: =BA14 -> 7536 | BC14: 11550 | BD14: 12387 | BE14: 12966 | BF14: 16020 | BG14: =BF14 -> 16020 | BH14: 22821 | BI14: 20511 | BJ14: 20437 | BK14: 22432 | BL14: =BK14 -> 22432 | BM14: 21394 | BN14: 21121 | BO14: 24459 | BP14: 21417 | BQ14: =BP14 -> 21417 | BR14: 23802 | BS14: 15744 | BT14: 14917 | BU14: 13937 | BV14: =BU14 -> 13937 | BW14: 14742 | BX14: 12665 | BY14: 9213 | BZ14: 8271 | CA14: =BZ14 -> 8271 | CB14: 9282 | CC14: 8310 | CD14: 10123 | CE14: 8988 | CF14: =CE14 -> 8988 | CG14: 7340 | CH14: 7928 | CI14: 7331 | CJ14: 7153 | CK14: =CJ14 -> 7153 | CL14: 7205 | CM14: 7015 | CN14: 6855 | CO14: 5968 | CP14: =CO14 -> 5968 | CQ14: =CQ59*'Income Statement'!CQ23 -> 36511.612 | CR14: =CR59*'Income Statement'!CR23 -> 19468.615 | CS14: =CS59*'Income Statement'!CS23 -> 19110.124 | CT14: =CT59*'Income Statement'!CT23 -> 19121.67 | CU14: =CT14 -> 19121.67
C15: PP&E | D15: 9826 | E15: 10030 | F15: 13220 | G15: 24773 | H15: 26522 | I15: =H15 -> 26522 | J15: 27874 | K15: 28454 | L15: 31961 | M15: 35750 | N15: =M15 -> 35750 | O15: 36190 | P15: 35695 | Q15: 35321 | R15: 34851 | S15: =R15 -> 34851 | T15: 41386 | U15: 40511 | V15: 40780 | W15: 40915 | X15: =W15 -> 40915 | Y15: 40721 | Z15: 42500 | AA15: 43017 | AB15: 45381 | AC15: =AB15 -> 45381 | AD15: 48170 | AE15: 55378 | AF15: 63145 | AG15: 64844 | AH15: =AG15 -> 64844 | AI15: 66222 | AJ15: 67160 | AK15: 66694 | AL15: 65910 | AM15: =AL15 -> 65910 | AN15: 67301 | AO15: 67908 | AP15: 68092 | AQ15: 101112 | AR15: =AQ15 -> 101112 | AS15: 114291 | AT15: 115886 | AU15: 120963 | AV15: 124268 | AW15: =AV15 -> 124268 | AX15: 142109 | AY15: 147956 | AZ15: 149142 | BA15: 152315 | BB15: =BA15 -> 152315 | BC15: 154254 | BD15: 154464 | BE15: 156498 | BF15: 155177 | BG15: =BF15 -> 155177 | BH15: 164617 | BI15: 170150 | BJ15: 169950 | BK15: 171861 | BL15: =BK15 -> 171861 | BM15: 175460 | BN15: 174967 | BO15: 170833 | BP15: 168004 | BQ15: =BP15 -> 168004 | BR15: 169295 | BS15: 177712 | BT15: 176745 | BU15: 181193 | BV15: =BU15 -> 181193 | BW15: 177508 | BX15: 177907 | BY15: 175196 | BZ15: 172786 | CA15: =BZ15 -> 172786 | CB15: 167683 | CC15: 165721 | CD15: 165737 | CE15: 169720 | CF15: =CE15 -> 169720 | CG15: 167121 | CH15: 167634 | CI15: 165272 | CJ15: 163775 | CK15: =CJ15 -> 163775 | CL15: 160972 | CM15: 161293 | CN15: 160626 | CO15: 160355 | CP15: =CO15 -> 160355 | CQ15: =CP15-'Cash Flows'!CQ33-'Cash Flows'!CQ9+'Cash Flows'!CQ34 -> 136880.15 | CR15: =CQ15-'Cash Flows'!CR33-'Cash Flows'!CR9+'Cash Flows'!CR34 -> 117048.54 | CS15: =CR15-'Cash Flows'!CS33-'Cash Flows'!CS9+'Cash Flows'!CS34 -> 98605.142 | CT15: =CS15-'Cash Flows'!CT33-'Cash Flows'!CT9+'Cash Flows'!CT34 -> 82452.782 | CU15: =CT15 -> 82452.782
C16: Non-current Investments | D16: 0 | E16: 5825 | F16: 5650 | G16: 4893 | H16: 3779 | I16: =H16 -> 3779 | J16: 3733 | K16: 2800 | L16: 2097 | M16: 1976 | N16: =M16 -> 1976 | O16: 2145 | P16: 2094 | Q16: 2149 | R16: 2126 | S16: =R16 -> 2126 | T16: 2126 | U16: 2101 | V16: 2101 | W16: 1953 | X16: =W16 -> 1953 | Y16: 1953 | Z16: 1903 | AA16: 2029 | AB16: 2037 | AC16: =AB16 -> 2037 | AD16: 2012 | AE16: 2103 | AF16: 2078 | AG16: 1288 | AH16: =AG16 -> 1288 | AI16: 1280 | AK16: =AJ16 -> 0 | AL16: =AK16 -> 0 | AM16: =AL16 -> 0 | AN16: =AM16 -> 0 | AO16: =AN16 -> 0 | AP16: =AO16 -> 0 | AQ16: =AP16 -> 0 | AR16: =AQ16 -> 0 | ... AT16: =AS16 -> 0 | AU16: 0 | AV16: 0 | AW16: =AV16 -> 0 | AX16: =AW16 -> 0 | AY16: =AX16 -> 0 | AZ16: =AY16 -> 0 | BA16: =AZ16 -> 0 | BB16: =BA16 -> 0 | BC16: 0 | BD16: =BC16 -> 0 | BE16: =BD16 -> 0 | BF16: =BE16 -> 0 | BG16: =BF16 -> 0 | BH16: =BG16 -> 0 | BI16: =BH16 -> 0 | BJ16: =BI16 -> 0 | BK16: =BJ16 -> 0 | ... BO16: =BN16 -> 0 | BP16: 82640 | BQ16: =BP16 -> 82640 | BR16: 112910 | BS16: 79057 | BT16: 64916 | BU16: 46353 | BV16: =BU16 -> 46353 | BW16: 34342 | BX16: 26464 | BY16: 22627 | BZ16: 18508 | CA16: =BZ16 -> 18508 | CB16: 14544 | CC16: 10116 | CD16: 9553 | CE16: 7046 | CF16: =CE16 -> 7046 | CG16: 5492 | CH16: 3879 | CI16: 3884 | CJ16: 10758 | CK16: =CJ16 -> 10758 | CL16: 3032 | CM16: 2994 | CN16: 22439 | CO16: 60698 | CP16: =CO16 -> 60698 | CQ16: =CP16 -> 60698 | CR16: =CQ16 -> 60698 | CS16: =CR16 -> 60698 | CT16: =CS16 -> 60698 | CU16: =CT16 -> 60698
C17: Intangibles | D17: 100220 | E17: 119406 | F17: 116873 | G17: 126635 | H17: 124039 | I17: =H17 -> 124039 | J17: 123379 | K17: 124056 | L17: 123492 | M17: 122239 | N17: =M17 -> 122239 | O17: 129498 | P17: 128072 | Q17: 128642 | R17: 127375 | S17: =R17 -> 127375 | T17: 125849 | U17: 124577 | V17: 123310 | W17: 141722 | X17: =W17 -> 141722 | Y17: 150010 | Z17: 156740 | AA17: 155069 | AB17: 165756 | AC17: =AB17 -> 165756 | AD17: 165042 | AE17: 163300 | AF17: 161639 | AG17: 159997 | AH17: =AG17 -> 159997 | AI17: 158387 | AJ17: 156815 | AK17: 160376 | AL17: 158864 | AM17: =AL17 -> 158864 | AN17: 157257 | AO17: 163467 | AP17: 161633 | AQ17: 295378 | AR17: =AQ17 -> 295378 | AS17: 286475 | AT17: 285491 | AU17: 276326 | AV17: 267259 | AW17: =AV17 -> 267259 | AX17: 258280 | AY17: 252874 | AZ17: 245520 | BA17: 236444 | BB17: =BA17 -> 236444 | BC17: 221069 | BD17: 293194 | BE17: 282806 | BF17: 276852 | BG17: =BF17 -> 276852 | BH17: 389633 | BI17: 377478 | BJ17: 377580 | BK17: 378914 | BL17: =BK17 -> 378914 | BM17: 366506 | BN17: 354115 | BO17: 341999 | BP17: 331189 | BQ17: =BP17 -> 331189 | BR17: 308614 | BS17: 1045580 | BT17: 1086457 | BU17: 1052493 | BV17: =BU17 -> 1052493 | BW17: 1072479 | BX17: 1032786 | BY17: 1004045 | BZ17: 1002164 | CA17: =BZ17 -> 1002164 | CB17: 976359 | CC17: 948990 | CD17: 938277 | CE17: 928870 | CF17: =CE17 -> 928870 | CG17: 901434 | CH17: 878272 | CI17: 855099 | CJ17: 831966 | CK17: =CJ17 -> 831966 | CL17: 816955 | CM17: 793725 | CN17: 779170 | CO17: 780414 | CP17: =CO17 -> 780414 | CQ17: =CO17-'Income Statement'!CQ59-'Income Statement'!CQ58 -> 757414 | CR17: =CP17-'Income Statement'!CR59-'Income Statement'!CR58 -> 759414 | CS17: =CQ17-'Income Statement'!CS59-'Income Statement'!CS58 -> 736414 | CT17: =CR17-'Income Statement'!CT59-'Income Statement'!CT58 -> 739414 | CU17: =CT17 -> 739414
C18: Other Assets | W18: 1614 | X18: =W18 -> 1614 | Z18: 1467 | AA18: 1234 | AB18: 1197 | AC18: =AB18 -> 1197 | AD18: 980 | AE18: 795 | AF18: 690 | AG18: 536 | AH18: =AG18 -> 536 | AI18: 207 | AJ18: 683 | AK18: 739 | AL18: 737 | AM18: =AL18 -> 737 | AN18: 15738 | AO18: 3744 | AP18: 21080 | AQ18: 20422 | AR18: =AQ18 -> 20422 | AS18: 33442 | AT18: 29752 | AU18: 27881 | AV18: 30741 | AW18: =AV18 -> 30741 | AX18: 30903 | AY18: 31347 | AZ18: 39800 | BA18: 38510 | BB18: =BA18 -> 38510 | BC18: 48388 | BD18: 57580 | BE18: 61156 | BF18: 70338 | BG18: =BF18 -> 70338 | BH18: 75318 | BI18: 71462 | BJ18: 71104 | BK18: 79601 | BL18: =BK18 -> 79601 | BM18: 85776 | BN18: 101764 | BO18: =75278+33646 -> 108924 | BP18: 33792 | BQ18: =BP18 -> 33792 | BR18: =33806+12190 -> 45996 | BS18: 0 | BT18: =BS18 -> 0 | BU18: =BT18 -> 0 | BV18: =BU18 -> 0 | BW18: =BV18 -> 0 | BX18: =BW18 -> 0 | BY18: =BX18 -> 0 | BZ18: =BY18 -> 0 | CA18: =BZ18 -> 0 | ... CG18: =CF18 -> 0 | CK18: =CJ18 -> 0 | CM18: =CL18 -> 0 | CN18: =CM18 -> 0 | CO18: =CN18 -> 0 | CP18: =CO18 -> 0 | CQ18: =CP18 -> 0 | CR18: =CQ18 -> 0 | CS18: =CR18 -> 0 | CT18: =CS18 -> 0 | CU18: =CT18 -> 0
C19: Cost Method Investment | AO19: 15000 | AP19: 15000 | AQ19: 15000 | AR19: =AQ19 -> 15000 | AS19: 0 | AT19: 0 | AU19: 0 | AV19: 0 | AX19: 0 | AY19: 0 | AZ19: 0 | BA19: 0 | BB19: 0 | BC19: =BB19 -> 0 | BD19: 0 | BE19: 0 | BF19: 0 | BG19: 0 | BH19: =BG19 -> 0 | BI19: 0 | BJ19: 0 | BK19: 0 | BL19: 0 | BM19: =BL19 -> 0 | BN19: 0 | BO19: 0 | BP19: 0 | BQ19: 0 | BR19: 0 | BS19: 0 | BT19: 0 | BU19: 0 | BV19: 0 | BW19: 0 | BX19: 0 | BY19: 0 | BZ19: 0 | CA19: 0 | CB19: 0 | CC19: 0 | CD19: 0 | CE19: 0 | CF19: 0 | CG19: 0 | CK19: 0 | CM19: 0 | CN19: 0 | CO19: 0 | CP19: 0 | CQ19: 0 | CR19: 0 | CS19: 0 | CT19: 0 | CU19: 0
C20: Operating lease right-of-use assets | BH20: 20067 | BI20: 20349 | BJ20: 20172 | BK20: 18992 | BL20: =BK20 -> 18992 | BM20: 17992 | BN20: 16659 | BO20: 15321 | BP20: 18734 | BQ20: =BP20 -> 18734 | BR20: 19192 | BS20: 28230 | BT20: 40449 | BU20: 39720 | BV20: =BU20 -> 39720 | BW20: 42369 | BX20: 40577 | BY20: 53202 | BZ20: 50989 | CA20: =BZ20 -> 50989 | CB20: 48627 | CC20: 46824 | CD20: 42513 | CE20: 39039 | CF20: =CE20 -> 39039 | CG20: 37874 | CH20: 36647 | CI20: 34741 | CJ20: 31433 | CK20: =CJ20 -> 31433 | CL20: 33289 | CM20: 34723 | CN20: 36564 | CO20: 35602 | CP20: =CO20 -> 35602 | CQ20: =CP20 -> 35602 | CR20: =CQ20 -> 35602 | CS20: =CR20 -> 35602 | CT20: =CS20 -> 35602 | CU20: =CT20 -> 35602
C21: Goodwill | AQ21: 653666 | AR21: =AQ21 -> 653666 | AS21: 655167 | AT21: 655393 | AU21: 647525 | AV21: 650237 | AW21: =AV21 -> 650237 | AX21: 650237 | AY21: 651721 | AZ21: 655068 | BA21: 657987 | BB21: =BA21 -> 657987 | BC21: 657727 | BD21: 740146 | BE21: 749502 | BF21: 753718 | BG21: =BF21 -> 753718 | BH21: 834572 | BI21: 835911 | BJ21: 826040 | BK21: 840117 | BL21: =BK21 -> 840117 | BM21: 840028 | BN21: 840028 | BO21: 840028 | BP21: 838428 | BQ21: =BP21 -> 838428 | BR21: 851629 | BS21: 2309434 | BT21: 2355144 | BU21: 2359674 | BV21: =BU21 -> 2359674 | BW21: 2440843 | BX21: 2449638 | BY21: 2449405 | BZ21: 2489308 | CA21: =BZ21 -> 2489308 | CB21: 2489084 | CC21: 2489084 | CD21: 2510488 | CE21: 2532109 | CF21: =CE21 -> 2532109 | CG21: 2532125 | CH21: 2531899 | CI21: 2531653 | CJ21: 2531653 | CK21: =CJ21 -> 2531653 | CL21: 2542017 | CM21: 2542019 | CN21: 2554457 | CO21: 2590013 | CP21: =CO21 -> 2590013 | CQ21: =CP21 -> 2590013 | CR21: =CQ21 -> 2590013 | CS21: =CR21 -> 2590013 | CT21: =CS21 -> 2590013 | CU21: =CT21 -> 2590013
C22: Software development costs | BS22: 17179 | BT22: 22570 | BU22: 28489 | BV22: =BU22 -> 28489 | BW22: 36311 | BX22: 43505 | BY22: 51092 | BZ22: 48189 | CB22: 54565 | CC22: 61228 | CD22: 66434 | CE22: 67124 | CF22: =CE22 -> 67124 | CG22: 69795 | CH22: 74069 | CI22: 76580 | CJ22: 76117 | CK22: =CJ22 -> 76117 | CL22: 75837 | CM22: 74719 | CN22: 71777 | CO22: 68371 | CP22: =CO22 -> 68371
C23: Other non-current assets | BS23: 39139 | BT23: 43484 | BU23: 45971 | BW23: 45313 | BX23: 46217 | BY23: 50443 | BZ23: 49960 | CB23: 49828 | CC23: 48396 | CD23: 52313 | CE23: 63182 | CF23: =CE23 -> 63182 | CG23: 63153 | CH23: 76818 | CI23: 83384 | CJ23: 86381 | CK23: =CJ23 -> 86381 | CL23: 85889 | CM23: 85575 | CN23: 87636 | CO23: 93599 | CP23: =CO23 -> 93599
B24: Total Assets | D24: =D13+SUM(D14:D17) -> 241508 | E24: =E13+SUM(E14:E17) -> 247448 | F24: =F13+SUM(F14:F17) -> 268288 | G24: =G13+SUM(G14:G17) -> 264076 | H24: =H13+SUM(H14:H17) -> 251761 | I24: =I13+SUM(I14:I17) -> 251761 | J24: =J13+SUM(J14:J17) -> 241001 | K24: =K13+SUM(K14:K17) -> 261766 | ... V24: =V13+SUM(V14:V17) -> 261736 | W24: =W13+SUM(W14:W18) -> 295391 | X24: =X13+SUM(X14:X18) -> 295391 | Y24: =Y13+SUM(Y14:Y18) -> 277763 | Z24: =Z13+SUM(Z14:Z18) -> 320446 | AA24: =AA13+SUM(AA14:AA18) -> 296094 | AB24: =AB13+SUM(AB14:AB18) -> 338315 | AC24: =AC13+SUM(AC14:AC18) -> 338315 | AD24: =AD13+SUM(AD14:AD18) -> 315374 | ... AN24: =AN13+SUM(AN14:AN18) -> 568382 | AO24: =AO13+SUM(AO14:AO19) -> 646034 | AP24: =AP13+SUM(AP14:AP19) -> 678382 | AQ24: =AQ13+SUM(AQ14:AQ21) -> 1356570 | AR24: =AR13+SUM(AR14:AR21) -> 1356570 | AS24: =AS13+SUM(AS14:AS21) -> 1318009 | AT24: =AT13+SUM(AT14:AT21) -> 1413052 | AU24: =AU13+SUM(AU14:AU21) -> 1352766 | AV24: =AV13+SUM(AV14:AV21) -> 1357945 | AW24: =AW13+SUM(AW14:AW21) -> 1357945 | AX24: =AX13+SUM(AX14:AX21) -> 1355681 | ... BR24: =BR13+SUM(BR14:BR21) -> 3231790 | BS24: =SUM(BS13:BS23) -> 4641003 | BT24: =SUM(BT13:BT23) -> 4682938 | BU24: =SUM(BU13:BU23) -> 4732161 | BV24: =SUM(BV13:BV23) -> 4686190 | BW24: =SUM(BW13:BW23) -> 4723806 | BX24: =SUM(BX13:BX23) -> 4787046 | BY24: =SUM(BY13:BY23) -> 4675373 | BZ24: =SUM(BZ13:BZ23) -> 4687417 | ... CU24: =SUM(CU13:CU23) -> 6088132.6
B26: Liabilities:
C27: Accounts Payable & Accrued Liabilities | D27: 22228 | E27: 20583 | F27: 23948 | G27: 28855 | H27: 25530 | I27: =H27 -> 25530 | J27: 21980 | K27: 23089 | L27: 29309 | M27: 29917 | N27: =M27 -> 29917 | O27: 20436 | P27: 19895 | Q27: 42750 | R27: 22059 | S27: =R27 -> 22059 | T27: 22354 | U27: 22797 | V27: 24938 | W27: 27962 | X27: =W27 -> 27962 | Y27: 17515 | Z27: 24291 | AA27: 24527 | AB27: 29245 | AC27: =AB27 -> 29245 | AD27: 24428 | AE27: 27359 | AF27: 30136 | AG27: 35372 | AH27: =AG27 -> 35372 | AI27: 22084 | AJ27: 31186 | AK27: 35517 | AL27: 43627 | AM27: =AL27 -> 43627 | AN27: 28132 | AO27: 39195 | AP27: 41584 | AQ27: 55945 | AR27: =AQ27 -> 55945 | AS27: 39576 | AT27: 56449 | AU27: 60176 | AV27: 63284 | AW27: =AV27 -> 63284 | AX27: 47356 | AY27: 55454 | AZ27: 62146 | BA27: 72849 | BB27: =BA27 -> 72849 | BC27: 51417 | BD27: 57798 | BE27: 70617 | BF27: 73390 | BG27: =BF27 -> 73390 | BH27: 69835 | BI27: 78956 | BJ27: 78841 | BK27: 90211 | BL27: =BK27 -> 90211 | BM27: 72723 | BN27: 65008 | BO27: 92761 | BP27: 97095 | BQ27: =BP27 -> 97095 | BR27: 98908 | BS27: 241631 | BT27: 280850 | BU27: 278412 | BV27: =BU27 -> 278412 | BW27: 269222 | BX27: 264908 | BY27: 242434 | BZ27: 236754 | CA27: =BZ27 -> 236754 | CB27: 226883 | CC27: 245091 | CD27: 267068 | CE27: 304897 | CF27: =CE27 -> 304897 | CG27: 251614 | CH27: 303476 | CI27: 306075 | CJ27: 354526 | CK27: =CJ27 -> 354526 | CL27: 298741 | CM27: 344192 | CN27: 320953 | CO27: 365346 | CP27: =CO27 -> 365346 | CQ27: =CQ62*'Income Statement'!CQ23 -> 334689.78 | CR27: =CR62*'Income Statement'!CR23 -> 356924.61 | CS27: =CS62*'Income Statement'!CS23 -> 350352.28 | CT27: =CT62*'Income Statement'!CT23 -> 420676.75 | CU27: =CT27 -> 420676.75
C28: Short-Term Revolving Line of Credit | D28: 0 | E28: 0 | F28: 0 | G28: 0 | H28: 8000 | I28: =H28 -> 8000 | J28: 7500 | K28: 15425 | L28: 2101 | M28: 0 | N28: =M28 -> 0 | O28: 0 | P28: 14650 | Q28: 0 | R28: 0 | S28: =R28 -> 0 | T28: 0 | U28: 0 | V28: 0 | W28: 0 | X28: =W28 -> 0 | Y28: 0 | Z28: 0 | AA28: 0 | AB28: 0 | AC28: =AB28 -> 0 | AD28: 0 | AE28: 0 | AF28: 0 | AG28: 0 | AH28: =AG28 -> 0 | AI28: 0 | AJ28: 0 | AK28: 0 | AL28: 0 | AM28: =AL28 -> 0 | AN28: 0 | AO28: 0 | AP28: 0 | AQ28: 0 | AR28: =AQ28 -> 0 | AS28: 0 | AT28: 0 | AU28: 0 | AV28: 0 | AW28: =AV28 -> 0 | AX28: 0 | AY28: 0 | AZ28: 0 | BA28: 0 | BB28: =BA28 -> 0 | BC28: 0 | BD28: 0 | BE28: 0 | BF28: 0 | BG28: =BF28 -> 0 | BH28: 0 | BI28: 0 | BJ28: 0 | BK28: 0 | BL28: =BK28 -> 0 | BM28: 0 | BN28: 0 | BO28: 0 | BP28: 0 | BQ28: =BP28 -> 0 | BR28: 0 | BS28: 30000 | BT28: 30000 | BU28: 30000 | BV28: =BU28 -> 30000 | BW28: 30000 | BX28: 30000 | BY28: 30000 | BZ28: 30000 | CA28: =BZ28 -> 30000 | CB28: 30000 | CC28: 30000 | CD28: 30000 | CE28: 49801 | CF28: =CE28 -> 49801 | CG28: 0 | CK28: =CJ28 -> 0 | CM28: 0 | CN28: 0 | CO28: 0 | CP28: =CO28 -> 0 | CQ28: 0 | CR28: 0 | CS28: 0 | CT28: 0 | CU28: =CT28 -> 0
C29: Deferred Revenue | D29: 73714 | E29: 83426 | F29: 92973 | G29: 91029 | H29: 95773 | I29: =H29 -> 95773 | J29: 87042 | K29: 92441 | L29: 99670 | M29: 99116 | N29: =M29 -> 99116 | O29: 85828 | P29: 97838 | Q29: 98357 | R29: 102590 | S29: =R29 -> 102590 | T29: 91792 | U29: 110455 | V29: 108114 | W29: 123678 | X29: =W29 -> 123678 | Y29: 109381 | Z29: 125721 | AA29: 120127 | AB29: 140550 | AC29: =AB29 -> 140550 | AD29: 125385 | AE29: 155903 | AF29: 151510 | AG29: 156738 | AH29: =AG29 -> 156738 | AI29: 139298 | AJ29: 184578 | AK29: 185844 | AL29: 189212 | AM29: =AL29 -> 189212 | AN29: 164706 | AO29: 201549 | AP29: 200890 | AQ29: 281627 | AR29: =AQ29 -> 281627 | AS29: 250108 | AT29: 296481 | AU29: 288316 | AV29: 298217 | AW29: =AV29 -> 298217 | AX29: 270208 | AY29: 304128 | AZ29: 297163 | BA29: 309461 | BB29: =BA29 -> 309461 | BC29: 268132 | BD29: 316084 | BE29: 326421 | BF29: 350512 | BG29: =BF29 -> 350512 | BH29: 319900 | BI29: 368488 | BJ29: 391560 | BK29: 412495 | BL29: =BK29 -> 412495 | BM29: 365959 | BN29: 423037 | BO29: 436504 | BP29: 461278 | BQ29: =BP29 -> 461278 | BR29: 420535 | BS29: 484482 | BT29: 495250 | BU29: 510529 | BV29: =BU29 -> 510529 | BW29: 454678 | BX29: 528588 | BY29: 529233 | BZ29: 568538 | CA29: =BZ29 -> 568538 | CB29: 497395 | CC29: 565840 | CD29: 600439 | CE29: 632914 | CF29: =CE29 -> 632914 | CG29: 571871 | CH29: 652302 | CI29: 682422 | CJ29: 701438 | CK29: =CJ29 -> 701438 | CL29: 642379 | CM29: 720497 | CN29: 761050 | CO29: 780838 | CP29: =CO29 -> 780838 | CQ29: =CQ63*'Income Statement'!CQ23 -> 730232.24 | CR29: =CR63*'Income Statement'!CR23 -> 811192.29 | CS29: =CS63*'Income Statement'!CS23 -> 859955.59 | CT29: =CT63*'Income Statement'!CT23 -> 866849.05 | CU29: =CT29 -> 866849.05
C30: Income Taxes Payable | D30: 632 | E30: 1233 | F30: 0 | G30: 0 | H30: 166 | I30: =H30 -> 166 | J30: 2755 | K30: 0 | L30: 0 | M30: 220 | N30: =M30 -> 220 | O30: 1384 | P30: 0 | Q30: 0 | R30: 0 | S30: =R30 -> 0 | T30: 1448 | U30: 0 | V30: 0 | W30: 0 | X30: =W30 -> 0 | Y30: 2126 | Z30: 0 | AA30: =Z30 -> 0 | AB30: =AA30 -> 0 | AC30: =AB30 -> 0 | AD30: =AC30 -> 0 | AE30: =AD30 -> 0 | AF30: =AE30 -> 0 | AG30: =AF30 -> 0 | AH30: =AG30 -> 0 | ... AM30: =AL30 -> 0 | AN30: 4816 | AP30: =AO30 -> 0 | AQ30: =AP30 -> 0 | AR30: =AQ30 -> 0 | AS30: =AR30 -> 0 | AT30: =AS30 -> 0 | AU30: =AT30 -> 0 | AV30: =AU30 -> 0 | AW30: =AV30 -> 0 | AX30: 4681 | AY30: 0 | AZ30: =AY30 -> 0 | BA30: =AZ30 -> 0 | BB30: =BA30 -> 0 | BC30: =BB30 -> 0 | BD30: =BC30 -> 0 | BE30: =BD30 -> 0 | BF30: =BE30 -> 0 | BG30: =BF30 -> 0 | BH30: 7868 | BI30: 249 | BK30: =BJ30 -> 0 | BL30: =BK30 -> 0 | BM30: =BL30 -> 0 | BN30: =BM30 -> 0 | BO30: =BN30 -> 0 | BP30: =BO30 -> 0 | BQ30: =BP30 -> 0 | BR30: =BQ30 -> 0 | ... BV30: =BU30 -> 0 | BW30: 1374 | BY30: =BX30 -> 0 | BZ30: 43667 | CA30: =BZ30 -> 43667 | CB30: 69337 | CC30: 1905 | CD30: 0 | CE30: 2466 | CF30: =CE30 -> 2466 | CG30: 38293 | CH30: 20375 | CI30: 22485 | CK30: =CJ30 -> 0 | CL30: 12533 | CN30: =CM30 -> 0 | CO30: =CN30 -> 0 | CP30: =CO30 -> 0 | CQ30: =CP30 -> 0 | CR30: =CQ30 -> 0 | CS30: =CR30 -> 0 | CT30: =CS30 -> 0 | CU30: =CT30 -> 0
C31: Operating lease liabilities | BH31: 5777 | BI31: 6039 | BJ31: 6413 | BK31: 6387 | BL31: =BK31 -> 6387 | BM31: 6373 | BN31: 6217 | BO31: 5780 | BP31: 5904 | BQ31: =BP31 -> 5904 | BR31: 5913 | BS31: 9666 | BT31: 10125 | BU31: 10560 | BV31: =BU31 -> 10560 | BW31: 11186 | BX31: 10363 | BY31: 10581 | BZ31: 10736 | CA31: =BZ31 -> 10736 | CB31: 11413 | CC31: 11381 | CD31: 11527 | CE31: 11060 | CF31: =CE31 -> 11060 | CG31: 11147 | CH31: 11179 | CI31: 10653 | CJ31: 9643 | CK31: =CJ31 -> 9643 | CL31: 9281 | CM31: 8998 | CN31: 9661 | CO31: 9598 | CP31: =CO31 -> 9598 | CQ31: =CP31 -> 9598 | CR31: =CQ31 -> 9598 | CS31: =CR31 -> 9598 | CT31: =CS31 -> 9598 | CU31: =CT31 -> 9598
C32: Short Term Debt | CL32: 598366 | CM32: 598798 | CN32: 599231 | CO32: 599663 | CP32: =CO32 -> 599663 | CQ32: =CP32 -> 599663 | CR32: =CQ32 -> 599663 | CS32: =CR32 -> 599663 | CT32: =CS32 -> 599663 | CU32: =CT32 -> 599663
B33: Total Current Liabilities | D33: =SUM(D27:D30) -> 96574 | E33: =SUM(E27:E30) -> 105242 | F33: =SUM(F27:F30) -> 116921 | G33: =SUM(G27:G30) -> 119884 | H33: =SUM(H27:H30) -> 129469 | I33: =SUM(I27:I30) -> 129469 | J33: =SUM(J27:J30) -> 119277 | K33: =SUM(K27:K30) -> 130955 | ... AB33: =SUM(AB27:AB30) -> 169795 | AC33: =AB33 -> 169795 | AD33: =SUM(AD27:AD30) -> 149813 | AE33: =SUM(AE27:AE30) -> 183262 | AF33: =SUM(AF27:AF30) -> 181646 | AG33: =SUM(AG27:AG30) -> 192110 | AH33: =AG33 -> 192110 | AI33: =SUM(AI27:AI30) -> 161382 | AJ33: =SUM(AJ27:AJ30) -> 215764 | AK33: =SUM(AK27:AK30) -> 221361 | AL33: =SUM(AL27:AL30) -> 232839 | AM33: =AL33 -> 232839 | AN33: =SUM(AN27:AN30) -> 197654 | AO33: =SUM(AO27:AO30) -> 240744 | AP33: =SUM(AP27:AP30) -> 242474 | AQ33: =SUM(AQ27:AQ30) -> 337572 | AR33: =AQ33 -> 337572 | AS33: =SUM(AS27:AS30) -> 289684 | AT33: =SUM(AT27:AT30) -> 352930 | AU33: =SUM(AU27:AU30) -> 348492 | AV33: =SUM(AV27:AV30) -> 361501 | AW33: =AV33 -> 361501 | AX33: =SUM(AX27:AX30) -> 322245 | AY33: =SUM(AY27:AY30) -> 359582 | AZ33: =SUM(AZ27:AZ30) -> 359309 | BA33: =SUM(BA27:BA30) -> 382310 | BB33: =BA33 -> 382310 | BC33: =SUM(BC27:BC30) -> 319549 | BD33: =SUM(BD27:BD30) -> 373882 | BE33: =SUM(BE27:BE30) -> 397038 | BF33: 423902 | BG33: =BF33 -> 423902 | BH33: =SUM(BH27:BH32) -> 403380 | BI33: =SUM(BI27:BI32) -> 453732 | BJ33: =SUM(BJ27:BJ32) -> 476814 | BK33: =SUM(BK27:BK32) -> 509093 | BL33: =BK33 -> 509093 | BM33: =SUM(BM27:BM32) -> 445055 | BN33: =SUM(BN27:BN32) -> 494262 | BO33: =SUM(BO27:BO30) -> 529265 | BP33: =SUM(BP27:BP32) -> 564277 | BQ33: =BP33 -> 564277 | BR33: =SUM(BR27:BR32) -> 525356 | BS33: =SUM(BS27:BS32) -> 765779 | BT33: =SUM(BT27:BT32) -> 816225 | BU33: =SUM(BU27:BU32) -> 829501 | BV33: =BU33 -> 829501 | BW33: =SUM(BW27:BW32) -> 766460 | BX33: =SUM(BX27:BX32) -> 833859 | BY33: =SUM(BY27:BY32) -> 812248 | BZ33: =SUM(BZ27:BZ32) -> 889695 | CA33: =BZ33 -> 889695 | CB33: =SUM(CB27:CB32) -> 835028 | CC33: =SUM(CC27:CC32) -> 854217 | CD33: =SUM(CD27:CD32) -> 909034 | CE33: =SUM(CE27:CE32) -> 1001138 | CF33: =CE33 -> 1001138 | CG33: =SUM(CG27:CG32) -> 872925 | CH33: =SUM(CH27:CH32) -> 987332 | CI33: =SUM(CI27:CI32) -> 1021635 | CJ33: =SUM(CJ27:CJ32) -> 1065607 | CK33: =CJ33 -> 1065607 | CL33: =SUM(CL27:CL32) -> 1561300 | CM33: =SUM(CM27:CM32) -> 1672485 | CN33: =SUM(CN27:CN32) -> 1690895 | CO33: =SUM(CO27:CO32) -> 1755445 | CP33: =CO33 -> 1755445 | CQ33: =SUM(CQ27:CQ32) -> 1674183 | CR33: =SUM(CR27:CR32) -> 1777377.9 | CS33: =SUM(CS27:CS32) -> 1819568.9 | CT33: =SUM(CT27:CT32) -> 1896786.8 | CU33: =CT33 -> 1896786.8
C34: Long Term Debt | AR34: =AQ34 -> 0 | AT34: =AS34 -> 0 | AU34: =AT34 -> 0 | AV34: =AU34 -> 0 | AW34: =AV34 -> 0 | AY34: =AX34 -> 0 | AZ34: =AY34 -> 0 | BA34: =AZ34 -> 0 | BB34: =BA34 -> 0 | BD34: =BC34 -> 0 | BE34: =BD34 -> 0 | BF34: =BE34 -> 0 | BG34: =BF34 -> 0 | BI34: =BH34 -> 0 | BJ34: =BI34 -> 0 | BK34: =BJ34 -> 0 | BL34: =BK34 -> 0 | BN34: =BM34 -> 0 | BO34: =BN34 -> 0 | BP34: =BO34 -> 0 | BQ34: =BP34 -> 0 | BR34: 591483 | BS34: =862559+591906 -> 1454465 | BT34: =805535+592335 -> 1397870 | BU34: =718511+592765 -> 1311276 | BV34: =BU34 -> 1311276 | BW34: =698988+593194 -> 1292182 | BX34: =639464+593624 -> 1233088 | BY34: =452138+594054 -> 1046192 | BZ34: =362905+594484 -> 957389 | CA34: =BZ34 -> 957389 | CB34: =243603+594914 -> 838517 | CC34: =243729+595345 -> 839074 | CD34: =109395+595775 -> 705170 | CE34: 596206 | CF34: =CE34 -> 596206 | CG34: 596638 | CH34: 597069 | CI34: =597502 -> 597502 | CJ34: 597934 | CK34: =CJ34 -> 597934 | CM34: =CL34 -> 0 | CN34: =CM34 -> 0 | CO34: =CN34 -> 0 | CP34: =CO34 -> 0 | CQ34: =CP34 -> 0 | CR34: =CQ34 -> 0 | CS34: =CR34 -> 0 | CT34: =CS34 -> 0 | CU34: =CT34 -> 0
C35: Deferred revenue | AQ35: 3115 | AR35: =AQ35 -> 3115 | AS35: 4561 | AT35: 3704 | AU35: 2924 | AV35: 2140 | AW35: =AV35 -> 2140 | AX35: 1908 | AY35: 1643 | AZ35: 1468 | BA35: 1274 | BB35: =BA35 -> 1274 | BC35: 641 | BD35: 785 | BE35: 493 | BF35: 424 | BG35: =BF35 -> 424 | BH35: 442 | BI35: 551 | BJ35: 241 | BK35: 199 | BL35: =BK35 -> 199 | BM35: 167 | BN35: 167 | BO35: 118 | BP35: 100 | BQ35: =BP35 -> 100 | BR35: 83 | BS35: 68 | BT35: 53 | BU35: 38 | BV35: =BU35 -> 38 | BW35: 0 | BX35: =BW35 -> 0 | BY35: 2473 | BZ35: 2037 | CA35: =BZ35 -> 2037 | CB35: 1600 | CC35: 1164 | CD35: 727 | CE35: 296 | CF35: =CE35 -> 296 | CJ35: 22376 | CK35: =CJ35 -> 22376 | CL35: 22376 | CM35: 22878 | CN35: 22217 | CO35: 20988 | CP35: =CO35 -> 20988 | CQ35: =CP35 -> 20988 | CR35: =CQ35 -> 20988 | CS35: =CR35 -> 20988 | CT35: =CS35 -> 20988 | CU35: =CT35 -> 20988
C36: Revolving Line of Credit | D36: 0 | E36: 0 | F36: 0 | G36: 0 | H36: 0 | I36: 0 | J36: 0 | K36: 0 | L36: 0 | M36: 0 | N36: 0 | O36: 0 | P36: 0 | Q36: 16500 | R36: 26500 | S36: =R36 -> 26500 | T36: 22500 | U36: 31500 | V36: 58000 | W36: 60700 | X36: =W36 -> 60700 | Y36: 56000 | Z36: 65700 | AA36: 28000 | AB36: 18000 | AC36: =AB36 -> 18000 | AD36: 0 | AE36: =AD36 -> 0 | AF36: =AE36 -> 0 | AG36: =AF36 -> 0 | AH36: =AG36 -> 0 | AI36: =AH36 -> 0 | AJ36: =AI36 -> 0 | AK36: =AJ36 -> 0 | AL36: =AK36 -> 0 | ... AP36: =AO36 -> 0 | AQ36: 66000 | AR36: =AQ36 -> 66000 | AS36: 140000 | AT36: 135000 | AU36: 34000 | AV36: 10000 | AW36: =AV36 -> 10000 | AX36: 0 | AY36: =AX36 -> 0 | AZ36: =AY36 -> 0 | BA36: =AZ36 -> 0 | BB36: =BA36 -> 0 | BC36: =BB36 -> 0 | BD36: =BC36 -> 0 | BE36: =BD36 -> 0 | BF36: =BE36 -> 0 | BG36: =BF36 -> 0 | BH36: 85000 | BI36: 15000 | BK36: =BJ36 -> 0 | BL36: =BK36 -> 0 | BM36: =BL36 -> 0 | BN36: =BM36 -> 0 | BO36: =BN36 -> 0 | BP36: =BO36 -> 0 | BQ36: =BP36 -> 0 | BR36: =BQ36 -> 0 | BS36: 65000 | BU36: =BT36 -> 0 | BV36: =BU36 -> 0 | BW36: =BV36 -> 0 | BX36: =BW36 -> 0 | BY36: =BX36 -> 0 | BZ36: =BY36 -> 0 | CA36: =BZ36 -> 0 | CB36: =CA36 -> 0 | ... CG36: =CF36 -> 0 | CK36: =CJ36 -> 0 | CM36: =CL36 -> 0 | CN36: =CM36 -> 0 | CO36: =CN36 -> 0 | CP36: =CO36 -> 0 | CQ36: =CP36 -> 0 | CR36: =CQ36 -> 0 | CS36: =CR36 -> 0 | CT36: =CS36 -> 0 | CU36: =CT36 -> 0
C37: Operating lease liabilities, long-term | BH37: 18956 | BI37: 18769 | BJ37: 18134 | BK37: 16822 | BL37: =BK37 -> 16822 | BM37: 15548 | BN37: 14126 | BO37: 12870 | BP37: 16279 | BQ37: =BP37 -> 16279 | BR37: 16636 | BS37: 22118 | BT37: 37348 | BU37: 36336 | BV37: =BU37 -> 36336 | BW37: 38403 | BX37: 36018 | BY37: 49759 | BZ37: 48049 | CA37: =BZ37 -> 48049 | CB37: 46567 | CC37: 44483 | CD37: 42098 | CE37: 39822 | CF37: =CE37 -> 39822 | CG37: 37631 | CH37: 35624 | CI37: 33674 | CJ37: 30791 | CK37: =CJ37 -> 30791 | CL37: 32455 | CM37: 33922 | CN37: 34556 | CO37: 33347 | CP37: =CO37 -> 33347 | CQ37: =CP37 -> 33347 | CR37: =CQ37 -> 33347 | CS37: =CR37 -> 33347 | CT37: =CS37 -> 33347 | CU37: =CT37 -> 33347
C38: Deferred Income Taxes | D38: 7723 | E38: 9415 | F38: 9069 | G38: 8889 | H38: 8030 | I38: =H38 -> 8030 | J38: 8030 | K38: 8080 | L38: 8092 | M38: 7059 | N38: =M38 -> 7059 | O38: 7059 | P38: 7137 | Q38: 7237 | R38: 5911 | S38: =R38 -> 5911 | T38: 5911 | U38: 5952 | V38: 5972 | W38: 4941 | X38: =W38 -> 4941 | Y38: 4994 | Z38: 5127 | AA38: 5431 | AB38: 5221 | AC38: =AB38 -> 5221 | AD38: 5363 | AE38: 5511 | AF38: 4141 | AG38: 6059 | AH38: =AG38 -> 6059 | AI38: 6155 | AJ38: 4574 | AK38: 4911 | AL38: 4170 | AM38: =AL38 -> 4170 | AN38: 4340 | AO38: 4673 | AP38: 4813 | AQ38: 91062 | AR38: =AQ38 -> 91062 | AS38: 91775 | AT38: 92110 | AU38: 85095 | AV38: 68779 | AW38: =AV38 -> 68779 | AX38: 64691 | AY38: 59682 | AZ38: 54563 | BA38: 38914 | BB38: =BA38 -> 38914 | BC38: 44220 | BD38: 44803 | BE38: 44965 | BF38: 41791 | BG38: =BF38 -> 41791 | BH38: 42779 | BI38: 39749 | BJ38: 40303 | BK38: 48442 | BL38: =BK38 -> 48442 | BM38: 45774 | BN38: 44713 | BO38: 45985 | BP38: 40507 | BQ38: =BP38 -> 40507 | BR38: 37239 | BS38: 220680 | BT38: 227537 | BU38: 228085 | BV38: =BU38 -> 228085 | BW38: 230292 | BX38: 216947 | BY38: 203204 | BZ38: 148891 | CA38: =BZ38 -> 148891 | CB38: 130367 | CC38: 109247 | CD38: 105002 | CE38: 78590 | CF38: =CE38 -> 78590 | CG38: 54274 | CH38: 41584 | CI38: 36660 | CJ38: 47503 | CK38: =CJ38 -> 47503 | CL38: 36448 | CM38: 36437 | CN38: 75829 | CO38: 95063 | CP38: =CO38 -> 95063 | CQ38: =CP38 -> 95063 | CR38: =CQ38 -> 95063 | CS38: =CR38 -> 95063 | CT38: =CS38 -> 95063 | CU38: =CT38 -> 95063
C39: Other long term liabilities | BS39: 4902 | BT39: 3132 | BU39: 2893 | BV39: =BU39 -> 2893 | BW39: 8735 | BX39: 8807 | BY39: 14199 | BZ39: 16967 | CA39: =BZ39 -> 16967 | CB39: 17423 | CC39: 19113 | CD39: 22547 | CE39: 22621 | CF39: =CE39 -> 22621 | CG39: 24152 | CH39: 25762 | CI39: 31925 | CJ39: 27382 | CK39: =CJ39 -> 27382 | CL39: 26851 | CM39: 25366 | CN39: 31105 | CO39: 31276 | CP39: =CO39 -> 31276 | CQ39: =CP39 -> 31276 | CR39: =CQ39 -> 31276 | CS39: =CR39 -> 31276 | CT39: =CS39 -> 31276 | CU39: =CT39 -> 31276
B40: Total Liabilities | D40: =D38+D36+D33 -> 104297 | E40: =E38+E36+E33 -> 114657 | F40: =F38+F36+F33 -> 125990 | G40: =G38+G36+G33 -> 128773 | H40: =H38+H36+H33 -> 137499 | I40: =I38+I36+I33 -> 137499 | J40: =J38+J36+J33 -> 127307 | K40: =K38+K36+K33 -> 139035 | ... AB40: =AB38+AB36+AB33 -> 193016 | AC40: =AB40 -> 193016 | AD40: =AD38+AD36+AD33 -> 155176 | AE40: =AE38+AE36+AE33 -> 188773 | AF40: =AF38+AF36+AF33 -> 185787 | AG40: =AG38+AG36+AG33 -> 198169 | AH40: =AG40 -> 198169 | AI40: =AI38+AI36+AI33 -> 167537 | AJ40: =AJ38+AJ36+AJ33 -> 220338 | AK40: =AK38+AK36+AK33 -> 226272 | AL40: =AL38+AL36+AL33 -> 237009 | AM40: =AL40 -> 237009 | AN40: =AN38+AN36+AN33 -> 201994 | AO40: =AO38+AO36+AO33 -> 245417 | AP40: =AP38+AP36+AP33 -> 247287 | AQ40: =AQ38+AQ36+AQ33+AQ35+AQ34 -> 497749 | AR40: =AQ40 -> 497749 | AS40: =AS38+AS36+AS33+AS34+AS35 -> 526020 | AT40: =AT38+AT36+AT33+AT34+AT35 -> 583744 | AU40: =AU38+AU36+AU33+AU34+AU35 -> 470511 | AV40: =AV38+AV36+AV33+AV34+AV35 -> 442420 | AW40: =AV40 -> 442420 | AX40: =AX38+AX36+AX33+AX34+AX35 -> 388844 | AY40: =AY38+AY36+AY33+AY34+AY35 -> 420907 | AZ40: =AZ38+AZ36+AZ33+AZ34+AZ35 -> 415340 | BA40: =BA38+BA36+BA33+BA34+BA35 -> 422498 | BB40: =BA40 -> 422498 | BC40: =BC38+BC36+BC33+BC34+BC35 -> 364410 | BD40: =BD38+BD36+BD33+BD34+BD35 -> 419470 | BE40: =BE38+BE36+BE33+BE34+BE35 -> 442496 | BF40: =BF38+BF36+BF33+BF34+BF35 -> 466117 | BG40: =BF40 -> 466117 | BH40: =BH38+BH36+BH33+BH34+BH35+BH37 -> 550557 | BI40: =BI38+BI36+BI33+BI34+BI35+BI37 -> 527801 | BJ40: =BJ38+BJ36+BJ33+BJ34+BJ35+BJ37 -> 535492 | BK40: =BK38+BK36+BK33+BK34+BK35+BK37 -> 574556 | BL40: =BK40 -> 574556 | BM40: =BM38+BM36+BM33+BM34+BM35+BM37 -> 506544 | BN40: =BN38+BN36+BN33+BN34+BN35+BN37 -> 553268 | BO40: =BO38+BO36+BO33+BO34+BO35+BO37 -> 588238 | BP40: =BP38+BP36+BP33+BP34+BP35+BP37 -> 621163 | BQ40: =BP40 -> 621163 | BR40: =BR38+BR36+BR33+BR34+BR35+BR37 -> 1170797 | BS40: =SUM(BS33:BS39) -> 2533012 | BT40: =SUM(BT33:BT39) -> 2482165 | BU40: =SUM(BU33:BU39) -> 2408129 | BV40: =BU40 -> 2408129 | BW40: =SUM(BW33:BW39) -> 2336072 | BX40: =SUM(BX33:BX39) -> 2328719 | BY40: =SUM(BY33:BY39) -> 2128075 | BZ40: =SUM(BZ33:BZ39) -> 2063028 | CA40: =BZ40 -> 2063028 | CB40: =SUM(CB33:CB39) -> 1869502 | CC40: =SUM(CC33:CC39) -> 1867298 | CD40: =SUM(CD33:CD39) -> 1784578 | CE40: =SUM(CE33:CE39) -> 1738673 | CF40: =CE40 -> 1738673 | CG40: =SUM(CG33:CG39) -> 1585620 | CH40: =SUM(CH33:CH39) -> 1687371 | CI40: =SUM(CI33:CI39) -> 1721396 | CJ40: =SUM(CJ33:CJ39) -> 1791593 | CK40: =CJ40 -> 1791593 | CL40: =SUM(CL33:CL39) -> 1679430 | CM40: =SUM(CM33:CM39) -> 1791088 | CN40: =SUM(CN33:CN39) -> 1854602 | CO40: =SUM(CO33:CO39) -> 1936119 | CP40: =CO40 -> 1936119 | CQ40: =SUM(CQ33:CQ39) -> 1854857 | CR40: =SUM(CR33:CR39) -> 1958051.9 | CS40: =SUM(CS33:CS39) -> 2000242.9 | CT40: =SUM(CT33:CT39) -> 2077460.8 | CU40: =CT40 -> 2077460.8
B42: Shareholders Equity:
C43: Total Shareholder Equity | D43: 137211 | E43: 132791 | F43: 142298 | G43: 135303 | H43: 114262 | I43: =H43 -> 114262 | J43: 113694 | K43: 122731 | L43: 124457 | M43: 134358 | N43: =M43 -> 134358 | O43: 138948 | P43: 137479 | Q43: 99916 | R43: 106972 | S43: =R43 -> 106972 | T43: 108398 | U43: 104450 | V43: 64712 | W43: 78110 | X43: =W43 -> 78110 | Y43: 87747 | Z43: =Z24-Z40 -> 99607 | AA43: =AA24-AA40 -> 118009 | AB43: =AB24-AB40 -> 145299 | AC43: =AB43 -> 145299 | AD43: =AD24-AD40 -> 160198 | AE43: 180155 | AF43: =AF24-AF40 -> 207628 | AG43: =AG24-AG40 -> 246319 | AH43: =AG43 -> 246319 | AI43: =AI24-AI40 -> 266704 | AJ43: =AJ24-AJ40 -> 266479 | AK43: =AK24-AK40 -> 295991 | AL43: =AL24-AL40 -> 336973 | AM43: =AL43 -> 336973 | AN43: =AN24-AN40 -> 366388 | AO43: =AO24-AO40 -> 400617 | AP43: =AP24-AP40 -> 431095 | AQ43: =AQ24-AQ40 -> 858821 | AR43: =AQ43 -> 858821 | AS43: =AS24-AS40 -> 791989 | AT43: =AT24-AT40 -> 829308 | AU43: =AU24-AU40 -> 882255 | AV43: =AV24-AV40 -> 915525 | AW43: =AV43 -> 915525 | AX43: =AX24-AX40 -> 966837 | AY43: =AY24-AY40 -> 1017602 | AZ43: =AZ24-AZ40 -> 1077778 | BA43: =BA24-BA40 -> 1167094 | BB43: =BA43 -> 1167094 | BC43: =BC24-BC40 -> 1261214 | BD43: =BD24-BD40 -> 1340289 | BE43: =BE24-BE40 -> 1422126 | BF43: =BF24-BF40 -> 1324846 | BG43: =BF43 -> 1324846 | BH43: =BH24-BH40 -> 1358745 | BI43: =BI24-BI40 -> 1421630 | BJ43: =BJ24-BJ40 -> 1519597 | BK43: =BK24-BK40 -> 1617058 | BL43: =BK43 -> 1617058 | BM43: =BM24-BM40 -> 1712832 | BN43: =BN24-BN40 -> 1829328 | BO43: =BO24-BO40 -> 1903925 | BP43: =BP24-BP40 -> 1986111 | BQ43: =BP43 -> 1986111 | BR43: =BR24-BR40 -> 2060993 | BS43: =BS24-BS40 -> 2107991 | BT43: =BT24-BT40 -> 2200773 | BU43: =BU24-BU40 -> 2324032 | BV43: =BU43 -> 2324032 | BW43: =BW24-BW40 -> 2387734 | BX43: =BX24-BX40 -> 2458327 | BY43: =BY24-BY40 -> 2547298 | BZ43: =BZ24-BZ40 -> 2624389 | CA43: =BZ43 -> 2624389 | CB43: =CB24-CB40 -> 2686133 | CC43: =CC24-CC40 -> 2768251 | CD43: =CD24-CD40 -> 2852851 | CE43: =CE24-CE40 -> 2937990 | CF43: =CE43 -> 2937990 | CG43: =CG24-CG40 -> 3023135 | CH43: =CH24-CH40 -> 3132107 | CI43: =CI24-CI40 -> 3275112 | CJ43: =CJ24-CJ40 -> 3388422 | CK43: =CJ43 -> 3388422 | CL43: =CL24-CL40 -> 3512704 | CM43: =CM24-CM40 -> 3634667 | CN43: =CN24-CN40 -> 3602767 | CO43: =CO24-CO40 -> 3702789 | CP43: =CO43 -> 3702789 | CQ43: =CQ24-CQ40 -> 3630022.8 | CR43: =CR24-CR40 -> 3770931.6 | CS43: =CS24-CS40 -> 3878556.7 | CT43: =CT24-CT40 -> 4010671.8 | CU43: =CT43 -> 4010671.8
B44: Total Liabilities & Shareholders Equity | D44: =D40+D43 -> 241508 | E44: =E40+E43 -> 247448 | F44: =F40+F43 -> 268288 | G44: =G40+G43 -> 264076 | H44: =H40+H43 -> 251761 | I44: =I40+I43 -> 251761 | J44: =J40+J43 -> 241001 | K44: =K40+K43 -> 261766 | ... Y44: =Y40+Y43 -> 277763 | Z44: =Z43+Z40 -> 320446 | AA44: =AA43+AA40 -> 296094 | AB44: =AB43+AB40 -> 338315 | AC44: =AB44 -> 338315 | AD44: =AD43+AD40 -> 315374 | AE44: =AE43+AE40 -> 368928 | AF44: =AF43+AF40 -> 393415 | AG44: =AG43+AG40 -> 444488 | AH44: =AG44 -> 444488 | AI44: =AI43+AI40 -> 434241 | AJ44: =AJ43+AJ40 -> 486817 | AK44: =AK43+AK40 -> 522263 | AL44: =AL43+AL40 -> 573982 | AM44: =AL44 -> 573982 | AN44: =AN43+AN40 -> 568382 | AO44: =AO43+AO40 -> 646034 | AP44: =AP43+AP40 -> 678382 | AQ44: =AQ43+AQ40 -> 1356570 | AR44: =AQ44 -> 1356570 | AS44: =AS43+AS40 -> 1318009 | AT44: =AT43+AT40 -> 1413052 | AU44: =AU43+AU40 -> 1352766 | AV44: =AV43+AV40 -> 1357945 | AW44: =AV44 -> 1357945 | AX44: =AX43+AX40 -> 1355681 | AY44: =AY43+AY40 -> 1438509 | AZ44: =AZ43+AZ40 -> 1493118 | BA44: =BA43+BA40 -> 1589592 | BB44: =BA44 -> 1589592 | BC44: =BC43+BC40 -> 1625624 | BD44: =BD43+BD40 -> 1759759 | BE44: =BE43+BE40 -> 1864622 | BF44: =BF43+BF40 -> 1790963 | BG44: =BF44 -> 1790963 | BH44: =BH43+BH40 -> 1909302 | BI44: =BI43+BI40 -> 1949431 | BJ44: =BJ43+BJ40 -> 2055089 | BK44: =BK43+BK40 -> 2191614 | BL44: =BK44 -> 2191614 | BM44: =BM43+BM40 -> 2219376 | BN44: =BN43+BN40 -> 2382596 | BO44: =BO43+BO40 -> 2492163 | BP44: =BP43+BP40 -> 2607274 | BQ44: =BP44 -> 2607274 | BR44: =BR43+BR40 -> 3231790 | BS44: =BS43+BS40 -> 4641003 | BT44: =BT43+BT40 -> 4682938 | BU44: =BU43+BU40 -> 4732161 | BV44: =BU44 -> 4732161 | BW44: =BW43+BW40 -> 4723806 | BX44: =BX43+BX40 -> 4787046 | BY44: =BY43+BY40 -> 4675373 | BZ44: =BZ43+BZ40 -> 4687417 | CA44: =BZ44 -> 4687417 | CB44: =CB43+CB40 -> 4555635 | CC44: =CC43+CC40 -> 4635549 | CD44: =CD43+CD40 -> 4637429 | CE44: =CE43+CE40 -> 4676663 | CF44: =CE44 -> 4676663 | CG44: =CG43+CG40 -> 4608755 | CH44: =CH43+CH40 -> 4819478 | CI44: =CI43+CI40 -> 4996508 | CJ44: =CJ43+CJ40 -> 5180015 | CK44: =CJ44 -> 5180015 | CL44: =CL43+CL40 -> 5192134 | CM44: =CM43+CM40 -> 5425755 | CN44: =CN43+CN40 -> 5457369 | CO44: =CO43+CO40 -> 5638908 | CP44: =CO44 -> 5638908 | CQ44: =CQ43+CQ40 -> 5484879.8 | CR44: =CR43+CR40 -> 5728983.5 | CS44: =CS43+CS40 -> 5878799.5 | CT44: =CT43+CT40 -> 6088132.6 | CU44: =CT44 -> 6088132.6
B45: Joshua Reilly, CFA, Jreilly@needhamco.com | CU45: Source: Company Reports and Needham & Company, LLC Estimates
B46: 612.386.4640 | CU46: $ in thousands, except per share data
C47: check | D47: =D24-D44 -> 0 | E47: =E24-E44 -> 0 | F47: =F24-F44 -> 0 | G47: =G24-G44 -> 0 | H47: =H24-H44 -> 0 | I47: =I24-I44 -> 0 | J47: =J24-J44 -> 0 | K47: =K24-K44 -> 0 | ... BP47: =BP24-BP44 -> 0 | BR47: =BR24-BR44 -> 0 | BS47: =BS24-BS44 -> 0 | BT47: =BT24-BT44 -> 0 | BU47: =BU24-BU44 -> 0 | BW47: =BW24-BW44 -> 0 | BX47: =BX24-BX44 -> 0 | BY47: =BY24-BY44 -> 0 | BZ47: =BZ24-BZ44 -> 0 | CB47: =CB24-CB44 -> 0 | CC47: =CC24-CC44 -> 0 | CD47: =CD24-CD44 -> 0 | CE47: =CE24-CE44 -> 0 | CG47: =CG24-CG44 -> 0 | CH47: =CH24-CH44 -> 0 | CI47: =CI24-CI44 -> 0 | CJ47: =CJ24-CJ44 -> 0 | CL47: =CL24-CL44 -> 0 | CM47: =CM24-CM44 -> 0 | CN47: =CN24-CN44 -> 0 | CO47: =CO24-CO44 -> 0 | CQ47: =CQ24-CQ44 -> 0 | CR47: =CR24-CR44 -> 0 | CS47: =CS24-CS44 -> 0 | CT47: =CT24-CT44 -> 0
C49: DSO | J49: =J7/'Income Statement'!J23*365/4 -> 86.043772 | K49: =K7/'Income Statement'!K23*365/4 -> 105.17166 | L49: =L7/'Income Statement'!L23*365/4 -> 105.09856 | M49: =M7/'Income Statement'!M23*365/4 -> 99.890945 | O49: =O7/'Income Statement'!O23*365/4 -> 82.43605 | P49: =P7/'Income Statement'!P23*365/4 -> 112.49516 | Q49: =Q7/'Income Statement'!Q23*365/4 -> 95.418587 | R49: =R7/'Income Statement'!R23*365/4 -> 103.11745 | T49: =((T7+R7)/2)/'Income Statement'!T23*91 -> 91.959683 | U49: =((U7+T7)/2)/'Income Statement'!U23*91 -> 93.069395 | V49: =((V7+U7)/2)/'Income Statement'!V23*91 -> 97.822878 | W49: =((W7+V7)/2)/'Income Statement'!W23*91 -> 91.726191 | Y49: =((Y7+W7)/2)/'Income Statement'!Y23*91 -> 81.89923 | Z49: =((Z7+Y7)/2)/'Income Statement'!Z23*91 -> 79.3531 | AA49: =((AA7+Z7)/2)/'Income Statement'!AA23*91 -> 86.630604 | AB49: =((AB7+AA7)/2)/'Income Statement'!AB23*91 -> 85.183683 | AD49: =((AD7+AB7)/2)/'Income Statement'!AD23*91 -> 83.851486 | AE49: =((AE7+AD7)/2)/'Income Statement'!AE23*91 -> 87.160077 | AF49: =((AF7+AE7)/2)/'Income Statement'!AF23*91 -> 90.029382 | AG49: =((AG7+AF7)/2)/'Income Statement'!AG23*91 -> 80.975496 | AI49: =((AI7+AG7)/2)/'Income Statement'!AI23*91 -> 76.3157 | AJ49: =((AJ7+AI7)/2)/'Income Statement'!AJ23*91 -> 82.887844 | AK49: =((AK7+AJ7)/2)/'Income Statement'!AK23*91 -> 90.543458 | AL49: =((AL7+AK7)/2)/'Income Statement'!AL23*91 -> 80.140195 | AN49: =((AN7+AL7)/2)/'Income Statement'!AN23*91 -> 73.644288 | AO49: =((AO7+AN7)/2)/'Income Statement'!AO23*91 -> 80.232024 | AP49: =((AP7+AO7)/2)/'Income Statement'!AP23*91 -> 84.881653 | AQ49: =((AQ7+AP7)/2)/'Income Statement'!AQ23*91 -> 85.755148 | AS49: =((AS7+AQ7)/2)/'Income Statement'!AS23*91 -> 77.15628 | AT49: =((AT7+AS7)/2)/'Income Statement'!AT23*91 -> 81.446007 | AU49: =((AU7+AT7)/2)/'Income Statement'!AU23*91 -> 91.551733 | AV49: =((AV7+AU7)/2)/'Income Statement'!AV23*91 -> 90.685324 | AX49: =((AX7+AV7)/2)/'Income Statement'!AX23*91 -> 82.882228 | AY49: =((AY7+AX7)/2)/'Income Statement'!AY23*91 -> 86.376085 | AZ49: =((AZ7+AY7)/2)/'Income Statement'!AZ23*91 -> 93.43174 | BA49: =((BA7+AZ7)/2)/'Income Statement'!BA23*91 -> 90.457345 | BC49: =((BC7+BA7)/2)/'Income Statement'!BC23*91 -> 91.179423 | BD49: =((BD7+BC7)/2)/'Income Statement'!BD23*91 -> 98.718207 | BE49: =((BE7+BD7)/2)/'Income Statement'!BE23*91 -> 111.23261 | BF49: =((BF7+BE7)/2)/'Income Statement'!BF23*91 -> 108.66752 | BH49: =((BH7+BF7)/2)/'Income Statement'!BH23*91 -> 109.35744 | BI49: =((BI7+BH7)/2)/'Income Statement'!BI23*91 -> 111.36133 | BJ49: =((BJ7+BI7)/2)/'Income Statement'!BJ23*91 -> 119.72396 | BK49: =((BK7+BJ7)/2)/'Income Statement'!BK23*91 -> 114.3054 | BM49: =((BM7+BK7)/2)/'Income Statement'!BM23*91 -> 113.79652 | BN49: =((BN7+BM7)/2)/'Income Statement'!BN23*91 -> 121.38884 | BO49: =((BO7+BN7)/2)/'Income Statement'!BO23*91 -> 122.27207 | BP49: =((BP7+BO7)/2)/'Income Statement'!BP23*91 -> 119.60447 | BR49: =((BR7+BP7)/2)/'Income Statement'!BR23*91 -> 110.06712 | BS49: =((BS7+BR7)/2)/'Income Statement'!BS23*91 -> 102.702 | BT49: =((BT7+BS7)/2)/'Income Statement'!BT23*91 -> 110.85726 | BU49: =((BU7+BT7)/2)/'Income Statement'!BU23*91 -> 110.99784 | BW49: =((BW7+BV7)/2)/'Income Statement'!BW23*91 -> 101.97757 | BX49: =((BX7+BW7)/2)/'Income Statement'!BX23*91 -> 106.66776 | BY49: =((BY7+BX7)/2)/'Income Statement'!BY23*91 -> 111.47712 | BZ49: =((BZ7+BY7)/2)/'Income Statement'!BZ23*91 -> 114.60392 | CB49: =((CB7+CA7)/2)/'Income Statement'!CB23*91 -> 104.71539 | CC49: =((CC7+CB7)/2)/'Income Statement'!CC23*91 -> 103.52822 | CD49: =((CD7+CC7)/2)/'Income Statement'!CD23*91 -> 116.1073 | CE49: =((CE7+CD7)/2)/'Income Statement'!CE23*91 -> 117.62696 | CG49: =((CG7+CF7)/2)/'Income Statement'!CG23*91 -> 103.20419 | CH49: =((CH7+CG7)/2)/'Income Statement'!CH23*91 -> 104.56768 | CI49: =((CI7+CH7)/2)/'Income Statement'!CI23*91 -> 110.56702 | CJ49: =((CJ7+CI7)/2)/'Income Statement'!CJ23*91 -> 101.5003 | CL49: =((CL7+CK7)/2)/'Income Statement'!CL23*91 -> 92.382877 | CM49: =((CM7+CL7)/2)/'Income Statement'!CM23*91 -> 97.262807 | CN49: =((CN7+CM7)/2)/'Income Statement'!CN23*91 -> 105.09878 | CO49: =((CO7+CN7)/2)/'Income Statement'!CO23*91 -> 100.28784 | CQ49: =((CQ7+CP7)/2)/'Income Statement'!CQ23*91 -> 100.08839 | CR49: =((CR7+CQ7)/2)/'Income Statement'!CR23*91 -> 101.39038 | CS49: =((CS7+CR7)/2)/'Income Statement'!CS23*91 -> 103.35658 | CT49: =((CT7+CS7)/2)/'Income Statement'!CT23*91 -> 99.159779
C51: Deferred Revs | AC51: =AC35+AC29 -> 140550 | AD51: =AD35+AD29 -> 125385 | AE51: =AE35+AE29 -> 155903 | AF51: =AF35+AF29 -> 151510 | AG51: =AG35+AG29 -> 156738 | AH51: =AH35+AH29 -> 156738 | AI51: =AI35+AI29 -> 139298 | AJ51: =AJ35+AJ29 -> 184578 | ... AL51: =AL35+AL29 -> 189212 | AN51: =AN35+AN29 -> 164706 | AO51: =AO35+AO29 -> 201549 | AP51: =AP35+AP29 -> 200890 | AQ51: =AQ35+AQ29 -> 284742 | AS51: =AS35+AS29 -> 254669 | AT51: =AT35+AT29 -> 300185 | AU51: =AU35+AU29 -> 291240 | AV51: =AV35+AV29 -> 300357 | AX51: =AX35+AX29 -> 272116 | AY51: =AY35+AY29 -> 305771 | AZ51: =AZ35+AZ29 -> 298631 | BA51: =BA35+BA29 -> 310735 | BC51: =BC35+BC29 -> 268773 | BD51: =BD35+BD29 -> 316869 | BE51: =BE35+BE29 -> 326914 | BF51: =BF35+BF29 -> 350936 | BH51: =BH35+BH29 -> 320342 | BI51: =BI35+BI29 -> 369039 | BJ51: =BJ35+BJ29 -> 391801 | BK51: =BK35+BK29 -> 412694 | BM51: =BM35+BM29 -> 366126 | BN51: =BN35+BN29 -> 423204 | BO51: =BO35+BO29 -> 436622 | BP51: =BP35+BP29 -> 461378 | BR51: =BR35+BR29 -> 420618 | BS51: =BS35+BS29 -> 484550 | BT51: =BT35+BT29 -> 495303 | BU51: =BU35+BU29 -> 510567 | BW51: =BW35+BW29 -> 454678 | BX51: =BX35+BX29 -> 528588 | BY51: =BY35+BY29 -> 531706 | BZ51: =BZ35+BZ29 -> 570575 | CB51: =CB35+CB29 -> 498995 | CC51: =CC35+CC29 -> 567004 | CD51: =CD35+CD29 -> 601166 | CE51: =CE35+CE29 -> 633210 | CG51: =CG35+CG29 -> 571871 | CH51: =CH35+CH29 -> 652302 | CI51: =CI35+CI29 -> 682422 | CJ51: =CJ35+CJ29 -> 723814 | CL51: =CL35+CL29 -> 664755 | CM51: =CM35+CM29 -> 743375 | CN51: =CN35+CN29 -> 783267 | CO51: =CO35+CO29 -> 801826 | CQ51: =CQ35+CQ29 -> 751220.24 | CR51: =CR35+CR29 -> 832180.29 | CS51: =CS35+CS29 -> 880943.59 | CT51: =CT35+CT29 -> 887837.05
C52: Deferred Revs | U52: =U29/P29-1 -> 0.12895807 | V52: =V29/Q29-1 -> 0.099199854 | Z52: =Z29/U29-1 -> 0.13821013 | AA52: =AA29/V29-1 -> 0.11111419 | AB52: =AB29/W29-1 -> 0.13641876 | AD52: =AD29/Y29-1 -> 0.14631426 | AE52: =AE29/Z29-1 -> 0.24007127 | AF52: =AF29/AA29-1 -> 0.26124851 | AG52: =AG29/AB29-1 -> 0.11517609 | AI52: =AI51/AD51-1 -> 0.11096224 | AJ52: =AJ51/AE51-1 -> 0.18392847 | AK52: =AK51/AF51-1 -> 0.2266121 | AL52: =AL51/AG51-1 -> 0.20718652 | AN52: =AN51/AI51-1 -> 0.18240032 | AO52: =AO51/AJ51-1 -> 0.091944869 | AP52: =AP51/AK51-1 -> 0.080960375 | AQ52: =AQ51/AL51-1 -> 0.50488341 | AS52: =AS51/AN51-1 -> 0.54620354 | AT52: =AT51/AO51-1 -> 0.48938968 | AU52: =AU51/AP51-1 -> 0.44974862 | AV52: =AV51/AQ51-1 -> 0.054839118 | AX52: =AX51/AS51-1 -> 0.068508535 | AY52: =AY51/AT51-1 -> 0.018608525 | AZ52: =AZ51/AU51-1 -> 0.025377695 | BA52: =BA51/AV51-1 -> 0.034552216 | BC52: =BC51/AX51-1 -> -0.012285202 | BD52: =BD51/AY51-1 -> 0.036295136 | BE52: =BE51/AZ51-1 -> 0.094708855 | BF52: =BF51/BA51-1 -> 0.1293739 | BH52: =BH51/BC51-1 -> 0.19186823 | BI52: =BI51/BD51-1 -> 0.16464217 | BJ52: =BJ51/BE51-1 -> 0.19848339 | BK52: =BK51/BF51-1 -> 0.17598081 | BM52: =BM51/BH51-1 -> 0.14292225 | BN52: =BN51/BI51-1 -> 0.14677311 | BO52: =BO51/BJ51-1 -> 0.11439736 | BP52: =BP51/BK51-1 -> 0.11796634 | BR52: =BR51/BM51-1 -> 0.14883401 | BS52: =BS51/BN51-1 -> 0.1449561 | BT52: =BT51/BO51-1 -> 0.13439772 | BU52: =BU51/BP51-1 -> 0.10661323 | BW52: =BW51/BR51-1 -> 0.080976088 | BX52: =BX51/BS51-1 -> 0.090884326 | BY52: =BY51/BT51-1 -> 0.073496425 | BZ52: =BZ51/BU51-1 -> 0.11753208 | CB52: =CB51/BW51-1 -> 0.097468978 | CC52: =CC51/BX51-1 -> 0.07267664 | CD52: =CD51/BY51-1 -> 0.1306361 | CE52: =CE51/BZ51-1 -> 0.10977523 | CG52: =CG51/CB51-1 -> 0.14604555 | CH52: =CH51/CC51-1 -> 0.15043633 | CI52: =CI51/CD51-1 -> 0.135164 | CJ52: =CJ51/CE51-1 -> 0.14308681 | CL52: =CL51/CG51-1 -> 0.16242125 | CM52: =CM51/CH51-1 -> 0.13961785 | CN52: =CN51/CI51-1 -> 0.14777513 | CO52: =CO51/CJ51-1 -> 0.10777907 | CQ52: =CQ51/CL51-1 -> 0.13007084 | CR52: =CR51/CM51-1 -> 0.1194623 | CS52: =CS51/CN51-1 -> 0.12470408 | CT52: =CT51/CO51-1 -> 0.10726897
O53: =O29/N29-1 -> -0.13406514 | P53: =P29/O29-1 -> 0.13993102 | Q53: =Q29/P29-1 -> 0.0053046873 | R53: =R29/Q29-1 -> 0.0430371 | T53: =T29/S29-1 -> -0.10525392 | U53: =U29/T29-1 -> 0.20331837 | V53: =V29/U29-1 -> -0.021194151 | W53: =W29/V29-1 -> 0.14395915
B54: Drivers of Revenue %
C55: Accounts Receivable | E55: =E7/'Income Statement'!E23 -> 0.99865209 | F55: =F7/'Income Statement'!F23 -> 1.1786174 | G55: =G7/'Income Statement'!G23 -> 0.96784533 | H55: =H7/'Income Statement'!H23 -> 1.1070545 | J55: =J7/'Income Statement'!J23 -> 0.94294545 | K55: =K7/'Income Statement'!K23 -> 1.1525661 | L55: =L7/'Income Statement'!L23 -> 1.1517651 | M55: =M7/'Income Statement'!M23 -> 1.0946953 | O55: =O7/'Income Statement'!O23 -> 0.90340877 | P55: =P7/'Income Statement'!P23 -> 1.2328237 | Q55: =Q7/'Income Statement'!Q23 -> 1.0456831 | R55: =R7/'Income Statement'!R23 -> 1.1300543 | T55: =T7/'Income Statement'!T23 -> 0.9057267 | U55: =U7/'Income Statement'!U23 -> 1.1792011 | V55: =V7/'Income Statement'!V23 -> 0.97761194 | W55: =W7/'Income Statement'!W23 -> 1.0966508 | Y55: =Y7/'Income Statement'!Y23 -> 0.71186973 | Z55: =Z7/'Income Statement'!Z23 -> 1.0995097 | AA55: =AA7/'Income Statement'!AA23 -> 0.83348074 | AB55: =AB7/'Income Statement'!AB23 -> 1.0519986 | AD55: =AD7/'Income Statement'!AD23 -> 0.79562417 | AE55: =AE7/'Income Statement'!AE23 -> 1.1762378 | AF55: =AF7/'Income Statement'!AF23 -> 0.84565646 | AG55: =AG7/'Income Statement'!AG23 -> 0.96238768 | AI55: =AI7/'Income Statement'!AI23 -> 0.73103901 | AJ55: =AJ7/'Income Statement'!AJ23 -> 1.1597076 | AK55: =AK7/'Income Statement'!AK23 -> 0.86895324 | AL55: =AL7/'Income Statement'!AL23 -> 0.88402385 | AN55: =AN7/'Income Statement'!AN23 -> 0.78382704 | AO55: =AO7/'Income Statement'!AO23 -> 1.0402133 | AP55: =AP7/'Income Statement'!AP23 -> 0.85669396 | AQ55: =AQ7/'Income Statement'!AQ23 -> 1.0877087 | AS55: =AS7/'Income Statement'!AS23 -> 0.74238329 | AT55: =AT7/'Income Statement'!AT23 -> 1.0812082 | AU55: =AU7/'Income Statement'!AU23 -> 0.952831 | AV55: =AV7/'Income Statement'!AV23 -> 1.0270589 | AX55: =AX7/'Income Statement'!AX23 -> 0.81920073 | AY55: =AY7/'Income Statement'!AY23 -> 1.1165755 | AZ55: =AZ7/'Income Statement'!AZ23 -> 0.96285586 | BA55: =BA7/'Income Statement'!BA23 -> 1.0414561 | BC55: =BC7/'Income Statement'!BC23 -> 0.97800664 | BD55: =BD7/'Income Statement'!BD23 -> 1.258836 | BE55: =BE7/'Income Statement'!BE23 -> 1.1850207 | BF55: =BF7/'Income Statement'!BF23 -> 1.2299235 | BH55: =BH7/'Income Statement'!BH23 -> 1.2018668 | BI55: =BI7/'Income Statement'!BI23 -> 1.3719607 | BJ55: =BJ7/'Income Statement'!BJ23 -> 1.2554052 | BK55: =BK7/'Income Statement'!BK23 -> 1.3015187 | BM55: =BM7/'Income Statement'!BM23 -> 1.1494472 | BN55: =BN7/'Income Statement'!BN23 -> 1.495347 | BO55: =BO7/'Income Statement'!BO23 -> 1.2683458 | BP55: =BP7/'Income Statement'!BP23 -> 1.3490057 | BR55: =BR7/'Income Statement'!BR23 -> 1.1221905 | BS55: =BS7/'Income Statement'!BS23 -> 1.4410689 | BT55: =BT7/'Income Statement'!BT23 -> 1.1682392 | BU55: =BU7/'Income Statement'!BU23 -> 1.2001101 | BW55: =BW7/'Income Statement'!BW23 -> 1.0988626 | BX55: =BX7/'Income Statement'!BX23 -> 1.2749715 | BY55: =BY7/'Income Statement'!BY23 -> 1.1872162 | BZ55: =BZ7/'Income Statement'!BZ23 -> 1.276496 | CB55: =CB7/'Income Statement'!CB23 -> 1.078054 | CC55: =CC7/'Income Statement'!CC23 -> 1.2666123 | CD55: =CD7/'Income Statement'!CD23 -> 1.260629 | CE55: =CE7/'Income Statement'!CE23 -> 1.28854 | CG55: =CG7/'Income Statement'!CG23 -> 1.0587127 | CH55: =CH7/'Income Statement'!CH23 -> 1.2954826 | CI55: =CI7/'Income Statement'!CI23 -> 1.1401911 | CJ55: =CJ7/'Income Statement'!CJ23 -> 1.0859367 | CL55: =CL7/'Income Statement'!CL23 -> 0.99063636 | CM55: =CM7/'Income Statement'!CM23 -> 1.1984443 | CN55: =CN7/'Income Statement'!CN23 -> 1.1109403 | CO55: =CO7/'Income Statement'!CO23 -> 1.0824185 | CQ55: 1.15 | CR55: 1.15 | CS55: 1.1 | CT55: 1.08
C56: Other Current | E56: =E11/'Income Statement'!E23 -> 0.026216913 | F56: =F11/'Income Statement'!F23 -> 0.053190072 | G56: =G11/'Income Statement'!G23 -> 0.02580241 | H56: =H11/'Income Statement'!H23 -> 0.020763833 | J56: =J11/'Income Statement'!J23 -> 0.022295695 | K56: =K11/'Income Statement'!K23 -> 0.029277282 | L56: =L11/'Income Statement'!L23 -> 0.023771727 | M56: =M11/'Income Statement'!M23 -> 0.019362141 | O56: =O11/'Income Statement'!O23 -> 0.021383558 | P56: =P11/'Income Statement'!P23 -> 0.053526171 | Q56: =Q11/'Income Statement'!Q23 -> 0.02736922 | R56: =R11/'Income Statement'!R23 -> 0.15660073 | T56: =T11/'Income Statement'!T23 -> 0.025833526 | U56: =U11/'Income Statement'!U23 -> 0.16035707 | V56: =V11/'Income Statement'!V23 -> 0.13592195 | W56: =W11/'Income Statement'!W23 -> 0.12955811 | Y56: =Y11/'Income Statement'!Y23 -> 0.11803247 | Z56: =Z11/'Income Statement'!Z23 -> 0.12414631 | AA56: =AA11/'Income Statement'!AA23 -> 0.11393255 | AB56: =AB11/'Income Statement'!AB23 -> 0.10989011 | AD56: =AD11/'Income Statement'!AD23 -> 0.11785092 | AE56: =AE11/'Income Statement'!AE23 -> 0.16215272 | AF56: =AF11/'Income Statement'!AF23 -> 0.15538072 | AG56: =AG11/'Income Statement'!AG23 -> 0.1292184 | AI56: =AI11/'Income Statement'!AI23 -> 0.18096177 | AJ56: =AJ11/'Income Statement'!AJ23 -> 0.16199114 | AK56: =AK11/'Income Statement'!AK23 -> 0.12440931 | AL56: =AL11/'Income Statement'!AL23 -> 0.14288293 | AN56: =AN11/'Income Statement'!AN23 -> 0.13032912 | AO56: =AO11/'Income Statement'!AO23 -> 0.20211901 | AP56: =AP11/'Income Statement'!AP23 -> 0.22532401 | AQ56: =AQ11/'Income Statement'!AQ23 -> 0.23244253 | AS56: =AS11/'Income Statement'!AS23 -> 0.22198737 | AT56: =AT11/'Income Statement'!AT23 -> 0.25366324 | AU56: =AU11/'Income Statement'!AU23 -> 0.24223668 | AV56: =AV11/'Income Statement'!AV23 -> 0.22342302 | AX56: =AX11/'Income Statement'!AX23 -> 0.22076285 | AY56: =AY11/'Income Statement'!AY23 -> 0.24433907 | AZ56: =AZ11/'Income Statement'!AZ23 -> 0.3046155 | BA56: =BA11/'Income Statement'!BA23 -> 0.33201581 | BC56: =BC11/'Income Statement'!BC23 -> 0.44365246 | BD56: =BD11/'Income Statement'!BD23 -> 0.40546521 | BE56: =BE11/'Income Statement'!BE23 -> 0.36805462 | BF56: =BF11/'Income Statement'!BF23 -> 0.33316463 | BH56: =BH11/'Income Statement'!BH23 -> 0.25669814 | BI56: =BI11/'Income Statement'!BI23 -> 0.21945385 | BJ56: =BJ11/'Income Statement'!BJ23 -> 0.2178385 | BK56: =BK11/'Income Statement'!BK23 -> 0.23116987 | BM56: =BM11/'Income Statement'!BM23 -> 0.27254137 | BN56: =BN11/'Income Statement'!BN23 -> 0.32779393 | BO56: =BO11/'Income Statement'!BO23 -> 0.30949125 | BP56: =BP11/'Income Statement'!BP23 -> 0.3723607 | BR56: =BR11/'Income Statement'!BR23 -> 0.34501123 | BS56: =BS11/'Income Statement'!BS23 -> 0.26542876 | BT56: =BT11/'Income Statement'!BT23 -> 0 | BU56: =BU11/'Income Statement'!BU23 -> 0 | BW56: =BW11/'Income Statement'!BW23 -> 0 | BX56: =BX11/'Income Statement'!BX23 -> 0 | BY56: =BY11/'Income Statement'!BY23 -> 0 | BZ56: =BZ11/'Income Statement'!BZ23 -> 0 | CB56: =CB11/'Income Statement'!CB23 -> 0 | CC56: =CC11/'Income Statement'!CC23 -> 0 | CD56: =CD11/'Income Statement'!CD23 -> 0 | CE56: =CE11/'Income Statement'!CE23 -> 0 | CG56: =CG11/'Income Statement'!CG23 -> 0 | CH56: =CH11/'Income Statement'!CH23 -> 0 | CI56: =CI11/'Income Statement'!CI23 -> 0 | CJ56: =CJ11/'Income Statement'!CJ23 -> 0 | CL56: =CL11/'Income Statement'!CL23 -> 0 | CM56: =CM11/'Income Statement'!CM23 -> 0 | CN56: =CN11/'Income Statement'!CN23 -> 0 | CO56: =CO11/'Income Statement'!CO23 -> 0 | CQ56: 0.4 | CR56: 0.4 | CS56: 0.4 | CT56: 0.35
C57: Prepaid expenses | BT57: =BT9/'Income Statement'!BT23 -> 0.1153761 | BU57: =BU9/'Income Statement'!BU23 -> 0.14663178 | CQ57: 0.12 | CR57: 0.12 | CS57: 0.12 | CT57: 0.11
C59: Accounts Receivable Long-term | E59: =E14/'Income Statement'!E23 -> 0.0089130764 | F59: =F14/'Income Statement'!F23 -> 0.0068078557 | G59: =G14/'Income Statement'!G23 -> 0.0099217623 | H59: =H14/'Income Statement'!H23 -> 0.002832739 | J59: =J14/'Income Statement'!J23 -> 0.0041975131 | K59: =K14/'Income Statement'!K23 -> 0.0043091504 | L59: =L14/'Income Statement'!L23 -> 0.0064978744 | M59: =M14/'Income Statement'!M23 -> 0.013716534 | O59: =O14/'Income Statement'!O23 -> 0.015883701 | P59: =P14/'Income Statement'!P23 -> 0.010661157 | Q59: =Q14/'Income Statement'!Q23 -> 0.017446353 | R59: =R14/'Income Statement'!R23 -> 0.016993608 | T59: =T14/'Income Statement'!T23 -> 0.019116264 | U59: =U14/'Income Statement'!U23 -> 0.0082231055 | V59: =V14/'Income Statement'!V23 -> 0.015702736 | W59: =W14/'Income Statement'!W23 -> 0.02552419 | Y59: =Y14/'Income Statement'!Y23 -> 0.016923951 | Z59: =Z14/'Income Statement'!Z23 -> 0.0063041765 | AA59: =AA14/'Income Statement'!AA23 -> 0.0072566466 | AB59: =AB14/'Income Statement'!AB23 -> 0.012446523 | AD59: =AD14/'Income Statement'!AD23 -> 0.016920845 | AE59: =AE14/'Income Statement'!AE23 -> 0.0077603601 | AF59: =AF14/'Income Statement'!AF23 -> 0.010259669 | AG59: =AG14/'Income Statement'!AG23 -> 0.0053099743 | AI59: =AI14/'Income Statement'!AI23 -> 0.0046703248 | AJ59: =AJ14/'Income Statement'!AJ23 -> 0.009061598 | AK59: =AK14/'Income Statement'!AK23 -> 0.011300752 | AL59: =AL14/'Income Statement'!AL23 -> 0.013818267 | AN59: =AN14/'Income Statement'!AN23 -> 0.002304284 | AO59: =AO14/'Income Statement'!AO23 -> 0.0026726819 | AP59: =AP14/'Income Statement'!AP23 -> 0.0071066326 | AQ59: =AQ14/'Income Statement'!AQ23 -> 0.01712728 | AS59: =AS14/'Income Statement'!AS23 -> 0.016747032 | AT59: =AT14/'Income Statement'!AT23 -> 0.013311036 | AU59: =AU14/'Income Statement'!AU23 -> 0.013875615 | AV59: =AV14/'Income Statement'!AV23 -> 0.012714297 | AX59: =AX14/'Income Statement'!AX23 -> 0.012894219 | AY59: =AY14/'Income Statement'!AY23 -> 0.011140399 | AZ59: =AZ14/'Income Statement'!AZ23 -> 0.018035708 | BA59: =BA14/'Income Statement'!BA23 -> 0.034555175 | BC59: =BC14/'Income Statement'!BC23 -> 0.052171556 | BD59: =BD14/'Income Statement'!BD23 -> 0.052107083 | BE59: =BE14/'Income Statement'!BE23 -> 0.054578058 | BF59: =BF14/'Income Statement'!BF23 -> 0.065916974 | BH59: =BH14/'Income Statement'!BH23 -> 0.091737919 | BI59: =BI14/'Income Statement'!BI23 -> 0.073785618 | BJ59: =BJ14/'Income Statement'!BJ23 -> 0.073730009 | BK59: =BK14/'Income Statement'!BK23 -> 0.078044707 | BM59: =BM14/'Income Statement'!BM23 -> 0.077296047 | BN59: =BN14/'Income Statement'!BN23 -> 0.077842767 | BO59: =BO14/'Income Statement'!BO23 -> 0.085539822 | BP59: =BP14/'Income Statement'!BP23 -> 0.075569497 | BR59: =BR14/'Income Statement'!BR23 -> 0.080738937 | BS59: =BS14/'Income Statement'!BS23 -> 0.038839263 | BT59: =BT14/'Income Statement'!BT23 -> 0.032384331 | BU59: =BU14/'Income Statement'!BU23 -> 0.032099886 | BW59: =BW14/'Income Statement'!BW23 -> 0.032321292 | BX59: =BX14/'Income Statement'!BX23 -> 0.027022414 | BY59: =BY14/'Income Statement'!BY23 -> 0.019469939 | BZ59: =BZ14/'Income Statement'!BZ23 -> 0.01828977 | CB59: =CB14/'Income Statement'!CB23 -> 0.019671381 | CC59: =CC14/'Income Statement'!CC23 -> 0.016478973 | CD59: =CD14/'Income Statement'!CD23 -> 0.020463569 | CE59: =CE14/'Income Statement'!CE23 -> 0.018688596 | CG59: =CG14/'Income Statement'!CG23 -> 0.014325893 | CH59: =CH14/'Income Statement'!CH23 -> 0.014654994 | CI59: =CI14/'Income Statement'!CI23 -> 0.013492547 | CJ59: =CJ14/'Income Statement'!CJ23 -> 0.013218611 | CL59: =CL14/'Income Statement'!CL23 -> 0.012748489 | CM59: =CM14/'Income Statement'!CM23 -> 0.011767824 | CN59: =CN14/'Income Statement'!CN23 -> 0.011504013 | CO59: =CO14/'Income Statement'!CO23 -> 0.010112546 | CQ59: 0.06 | CR59: 0.03 | CS59: 0.03 | CT59: 0.03
C60: Non-current Investments | E60: =E16/'Income Statement'!E23 -> 0.098144934 | F60: =F16/'Income Statement'!F23 -> 0.083618227 | G60: =G16/'Income Statement'!G23 -> 0.071288081 | H60: =H16/'Income Statement'!H23 -> 0.054339699 | J60: =J16/'Income Statement'!J23 -> 0.053662043 | K60: =K16/'Income Statement'!K23 -> 0.038796209 | L60: =L16/'Income Statement'!L23 -> 0.028211268 | M60: =M16/'Income Statement'!M23 -> 0.026624628 | O60: =O16/'Income Statement'!O23 -> 0.030721856 | P60: =P16/'Income Statement'!P23 -> 0.028842975 | Q60: =Q16/'Income Statement'!Q23 -> 0.029131478 | R60: =R16/'Income Statement'!R23 -> 0.029348831 | T60: =T16/'Income Statement'!T23 -> 0.02896734 | U60: =U16/'Income Statement'!U23 -> 0.027379944 | V60: =V16/'Income Statement'!V23 -> 0.027220667 | W60: =W16/'Income Statement'!W23 -> 0.02379415 | Y60: =Y16/'Income Statement'!Y23 -> 0.023608912 | Z60: =Z16/'Income Statement'!Z23 -> 0.020827861 | AA60: =AA16/'Income Statement'!AA23 -> 0.021620758 | AB60: =AB16/'Income Statement'!AB23 -> 0.021359366 | AD60: =AD16/'Income Statement'!AD23 -> 0.021002307 | AE60: =AE16/'Income Statement'!AE23 -> 0.020400047 | AF60: =AF16/'Income Statement'!AF23 -> 0.01941675 | AG60: =AG16/'Income Statement'!AG23 -> 0.011631372 | AI60: =AI16/'Income Statement'!AI23 -> 0.011365049 | AJ60: =AJ16/'Income Statement'!AJ23 -> 0 | AK60: =AK16/'Income Statement'!AK23 -> 0 | AL60: =AL16/'Income Statement'!AL23 -> 0 | AN60: =AN16/'Income Statement'!AN23 -> 0 | AO60: =AO16/'Income Statement'!AO23 -> 0 | AP60: =AP16/'Income Statement'!AP23 -> 0 | AQ60: =AQ16/'Income Statement'!AQ23 -> 0 | AS60: =AS16/'Income Statement'!AS23 -> 0 | AT60: =AT16/'Income Statement'!AT23 -> 0 | AU60: =AU16/'Income Statement'!AU23 -> 0 | AV60: =AV16/'Income Statement'!AV23 -> 0 | AX60: =AX16/'Income Statement'!AX23 -> 0 | AY60: =AY16/'Income Statement'!AY23 -> 0 | AZ60: =AZ16/'Income Statement'!AZ23 -> 0 | BA60: =BA16/'Income Statement'!BA23 -> 0 | BC60: =BC16/'Income Statement'!BC23 -> 0 | BD60: =BD16/'Income Statement'!BD23 -> 0 | BE60: =BE16/'Income Statement'!BE23 -> 0 | BF60: =BF16/'Income Statement'!BF23 -> 0 | BH60: =BH16/'Income Statement'!BH23 -> 0 | BI60: =BI16/'Income Statement'!BI23 -> 0 | BJ60: =BJ16/'Income Statement'!BJ23 -> 0 | BK60: =BK16/'Income Statement'!BK23 -> 0 | BM60: =BM16/'Income Statement'!BM23 -> 0 | BN60: =BN16/'Income Statement'!BN23 -> 0 | BO60: =BO16/'Income Statement'!BO23 -> 0 | BP60: =BP16/'Income Statement'!BP23 -> 0.29159374 | BR60: =BR16/'Income Statement'!BR23 -> 0.38300283 | BS60: =BS16/'Income Statement'!BS23 -> 0.19502767 | BT60: =BT16/'Income Statement'!BT23 -> 0.14093056 | BU60: =BU16/'Income Statement'!BU23 -> 0.10676085 | BW60: =BW16/'Income Statement'!BW23 -> 0.075293571 | BX60: =BX16/'Income Statement'!BX23 -> 0.056464363 | BY60: =BY16/'Income Statement'!BY23 -> 0.0478179 | BZ60: =BZ16/'Income Statement'!BZ23 -> 0.040926982 | CB60: =CB16/'Income Statement'!CB23 -> 0.030823159 | CC60: =CC16/'Income Statement'!CC23 -> 0.020060324 | CD60: =CD16/'Income Statement'!CD23 -> 0.019311318 | CE60: =CE16/'Income Statement'!CE23 -> 0.014650628 | CG60: =CG16/'Income Statement'!CG23 -> 0.010719047 | CH60: =CH16/'Income Statement'!CH23 -> 0.0071703735 | CI60: =CI16/'Income Statement'!CI23 -> 0.007148418 | CJ60: =CJ16/'Income Statement'!CJ23 -> 0.019880583 | CL60: =CL16/'Income Statement'!CL23 -> 0.005364805 | CM60: =CM16/'Income Statement'!CM23 -> 0.005022504 | CN60: =CN16/'Income Statement'!CN23 -> 0.037656974 | CO60: =CO16/'Income Statement'!CO23 -> 0.10285042 | CQ60: 0.1 | CR60: 0.1 | CS60: 0.1 | CT60: 0.1
C62: Accounts Payable & Accrued Liabilities | E62: =E27/'Income Statement'!E23 -> 0.34680123 | F62: =F27/'Income Statement'!F23 -> 0.35442289 | G62: =G27/'Income Statement'!G23 -> 0.42040008 | H62: =H27/'Income Statement'!H23 -> 0.36710572 | J62: =J27/'Income Statement'!J23 -> 0.31596349 | K62: =K27/'Income Statement'!K23 -> 0.31991631 | L62: =L27/'Income Statement'!L23 -> 0.39429855 | M62: =M27/'Income Statement'!M23 -> 0.40310172 | O62: =O27/'Income Statement'!O23 -> 0.2926955 | P62: =P27/'Income Statement'!P23 -> 0.27403581 | Q62: =Q27/'Income Statement'!Q23 -> 0.57951172 | R62: =R27/'Income Statement'!R23 -> 0.30451828 | T62: =T27/'Income Statement'!T23 -> 0.30457946 | U62: =U27/'Income Statement'!U23 -> 0.29708738 | V62: =V27/'Income Statement'!V23 -> 0.32309805 | W62: =W27/'Income Statement'!W23 -> 0.34067179 | Y62: =Y27/'Income Statement'!Y23 -> 0.21173072 | Z62: =Z27/'Income Statement'!Z23 -> 0.26585894 | AA62: =AA27/'Income Statement'!AA23 -> 0.26135649 | AB62: =AB27/'Income Statement'!AB23 -> 0.30665422 | AD62: =AD27/'Income Statement'!AD23 -> 0.25499222 | AE62: =AE27/'Income Statement'!AE23 -> 0.26539461 | AF62: =AF27/'Income Statement'!AF23 -> 0.28158959 | AG62: =AG27/'Income Statement'!AG23 -> 0.31942927 | AI62: =AI27/'Income Statement'!AI23 -> 0.19608261 | AJ62: =AJ27/'Income Statement'!AJ23 -> 0.25074977 | AK62: =AK27/'Income Statement'!AK23 -> 0.27604458 | AL62: =AL27/'Income Statement'!AL23 -> 0.34233365 | AN62: =AN27/'Income Statement'!AN23 -> 0.20843768 | AO62: =AO27/'Income Statement'!AO23 -> 0.26791756 | AP62: =AP27/'Income Statement'!AP23 -> 0.2756737 | AQ62: =AQ27/'Income Statement'!AQ23 -> 0.34504345 | AS62: =AS27/'Income Statement'!AS23 -> 0.2139382 | AT62: =AT27/'Income Statement'!AT23 -> 0.29135118 | AU62: =AU27/'Income Statement'!AU23 -> 0.30429264 | AV62: =AV27/'Income Statement'!AV23 -> 0.32444016 | AX62: =AX27/'Income Statement'!AX23 -> 0.23694942 | AY62: =AY27/'Income Statement'!AY23 -> 0.26480054 | AZ62: =AZ27/'Income Statement'!AZ23 -> 0.28984926 | BA62: =BA27/'Income Statement'!BA23 -> 0.33403795 | BC62: =BC27/'Income Statement'!BC23 -> 0.23225151 | BD62: =BD27/'Income Statement'!BD23 -> 0.24313273 | BE62: =BE27/'Income Statement'!BE23 -> 0.29724963 | BF62: =BF27/'Income Statement'!BF23 -> 0.30197545 | BH62: =BH27/'Income Statement'!BH23 -> 0.28072905 | BI62: =BI27/'Income Statement'!BI23 -> 0.2840338 | BJ62: =BJ27/'Income Statement'!BJ23 -> 0.28443253 | BK62: =BK27/'Income Statement'!BK23 -> 0.31385927 | BM62: =BM27/'Income Statement'!BM23 -> 0.26274659 | BN62: =BN27/'Income Statement'!BN23 -> 0.23959105 | BO62: =BO27/'Income Statement'!BO23 -> 0.32441062 | BP62: =BP27/'Income Statement'!BP23 -> 0.34259795 | BR62: =BR27/'Income Statement'!BR23 -> 0.33550654 | BS62: =BS27/'Income Statement'!BS23 -> 0.59608548 | BT62: =BT27/'Income Statement'!BT23 -> 0.60971638 | BU62: =BU27/'Income Statement'!BU23 -> 0.64124226 | BW62: =BW27/'Income Statement'!BW23 -> 0.59025932 | BX62: =BX27/'Income Statement'!BX23 -> 0.56521544 | BY62: =BY27/'Income Statement'!BY23 -> 0.51233857 | BZ62: =BZ27/'Income Statement'!BZ23 -> 0.52353722 | CB62: =CB27/'Income Statement'!CB23 -> 0.48083407 | CC62: =CC27/'Income Statement'!CC23 -> 0.48602262 | CD62: =CD27/'Income Statement'!CD23 -> 0.53987596 | CE62: =CE27/'Income Statement'!CE23 -> 0.63396717 | CG62: =CG27/'Income Statement'!CG23 -> 0.49108926 | CH62: =CH27/'Income Statement'!CH23 -> 0.56097868 | CI62: =CI27/'Income Statement'!CI23 -> 0.56332442 | CJ62: =CJ27/'Income Statement'!CJ23 -> 0.65515744 | CL62: =CL27/'Income Statement'!CL23 -> 0.52859077 | CM62: =CM27/'Income Statement'!CM23 -> 0.57739001 | CN62: =CN27/'Income Statement'!CN23 -> 0.5386211 | CO62: =CO27/'Income Statement'!CO23 -> 0.61906469 | CQ62: 0.55 | CR62: 0.55 | CS62: 0.55 | CT62: 0.66
C63: Deferred Revenue | E63: =E29/'Income Statement'!E23 -> 1.4056376 | F63: =F29/'Income Statement'!F23 -> 1.3759712 | G63: =G29/'Income Statement'!G23 -> 1.326238 | H63: =H29/'Income Statement'!H23 -> 1.3771569 | J63: =J29/'Income Statement'!J23 -> 1.2512327 | K63: =K29/'Income Statement'!K23 -> 1.280843 | L63: =L29/'Income Statement'!L23 -> 1.3408761 | M63: =M29/'Income Statement'!M23 -> 1.3354892 | O63: =O29/'Income Statement'!O23 -> 1.2292753 | P63: =P29/'Income Statement'!P23 -> 1.3476309 | Q63: =Q29/'Income Statement'!Q23 -> 1.3333107 | R63: =R29/'Income Statement'!R23 -> 1.4162261 | T63: =T29/'Income Statement'!T23 -> 1.2506915 | U63: =U29/'Income Statement'!U23 -> 1.4394344 | V63: =V29/'Income Statement'!V23 -> 1.4007307 | W63: =W29/'Income Statement'!W23 -> 1.5068166 | Y63: =Y29/'Income Statement'!Y23 -> 1.3222562 | Z63: =Z29/'Income Statement'!Z23 -> 1.375985 | AA63: =AA29/'Income Statement'!AA23 -> 1.2800575 | AB63: =AB29/'Income Statement'!AB23 -> 1.4737648 | AD63: =AD29/'Income Statement'!AD23 -> 1.3088341 | AE63: =AE29/'Income Statement'!AE23 -> 1.5123293 | AF63: =AF29/'Income Statement'!AF23 -> 1.4157035 | AG63: =AG29/'Income Statement'!AG23 -> 1.4154332 | AI63: =AI29/'Income Statement'!AI23 -> 1.2368192 | AJ63: =AJ29/'Income Statement'!AJ23 -> 1.484092 | AK63: =AK29/'Income Statement'!AK23 -> 1.4444134 | AL63: =AL29/'Income Statement'!AL23 -> 1.4847144 | AN63: =AN29/'Income Statement'!AN23 -> 1.2203518 | AO63: =AO29/'Income Statement'!AO23 -> 1.3776889 | AP63: =AP29/'Income Statement'!AP23 -> 1.3317644 | AQ63: =AQ29/'Income Statement'!AQ23 -> 1.7369479 | AS63: =AS29/'Income Statement'!AS23 -> 1.3520228 | AT63: =AT29/'Income Statement'!AT23 -> 1.5302324 | AU63: =AU29/'Income Statement'!AU23 -> 1.4579307 | AV63: =AV29/'Income Statement'!AV23 -> 1.5288789 | AX63: =AX29/'Income Statement'!AX23 -> 1.3520067 | AY63: =AY29/'Income Statement'!AY23 -> 1.4522534 | AZ63: =AZ29/'Income Statement'!AZ23 -> 1.3859697 | BA63: =BA29/'Income Statement'!BA23 -> 1.4189861 | BC63: =BC29/'Income Statement'!BC23 -> 1.211157 | BD63: =BD29/'Income Statement'!BD23 -> 1.3296371 | BE63: =BE29/'Income Statement'!BE23 -> 1.3740108 | BF63: =BF29/'Income Statement'!BF23 -> 1.4422404 | BH63: =BH29/'Income Statement'!BH23 -> 1.2859629 | BI63: =BI29/'Income Statement'!BI23 -> 1.325587 | BJ63: =BJ29/'Income Statement'!BJ23 -> 1.4126204 | BK63: =BK29/'Income Statement'!BK23 -> 1.4351396 | BM63: =BM29/'Income Statement'!BM23 -> 1.3222017 | BN63: =BN29/'Income Statement'!BN23 -> 1.5591293 | BO63: =BO29/'Income Statement'!BO23 -> 1.526574 | BP63: =BP29/'Income Statement'!BP23 -> 1.6276111 | BR63: =BR29/'Income Statement'!BR23 -> 1.4264998 | BS63: =BS29/'Income Statement'!BS23 -> 1.1951806 | BT63: =BT29/'Income Statement'!BT23 -> 1.0751719 | BU63: =BU29/'Income Statement'!BU23 -> 1.1758573 | BW63: =BW29/'Income Statement'!BW23 -> 0.99686478 | BX63: =BX29/'Income Statement'!BX23 -> 1.1278108 | BY63: =BY29/'Income Statement'!BY23 -> 1.1184342 | BZ63: =BZ29/'Income Statement'!BZ23 -> 1.2572155 | CB63: =CB29/'Income Statement'!CB23 -> 1.0541313 | CC63: =CC29/'Income Statement'!CC23 -> 1.1220773 | CD63: =CD29/'Income Statement'!CD23 -> 1.2137829 | CE63: =CE29/'Income Statement'!CE23 -> 1.3160074 | CG63: =CG29/'Income Statement'!CG23 -> 1.1161529 | CH63: =CH29/'Income Statement'!CH23 -> 1.2057873 | CI63: =CI29/'Income Statement'!CI23 -> 1.2559829 | CJ63: =CJ29/'Income Statement'!CJ23 -> 1.2962443 | CL63: =CL29/'Income Statement'!CL23 -> 1.136622 | CM63: =CM29/'Income Statement'!CM23 -> 1.2086503 | CN63: =CN29/'Income Statement'!CN23 -> 1.2771888 | CO63: =CO29/'Income Statement'!CO23 -> 1.3230998 | CQ63: 1.2 | CR63: 1.25 | CS63: 1.35 | CT63: 1.36

Sheet Cash Flows
B2: ='Income Statement'!B2 -> Tyler Technologies (TYL)
B4: Statement of Cash Flows | D4: 2007 | E4: 1Q08 | F4: 2Q08 | G4: 3Q08 | H4: 4Q08 | I4: 2008 | J4: 1Q09 | K4: 2Q09 | L4: 3Q09 | M4: 4Q09 | N4: 2009 | O4: 1Q10 | P4: 2Q10 | Q4: 3Q10 | R4: 4Q10 | S4: 2010 | T4: 1Q11 | U4: 2Q11 | V4: 3Q11 | W4: 4Q11 | X4: 2011 | Y4: 1Q12 | Z4: 2Q12 | AA4: 3Q12 | AB4: 4Q12 | AC4: 2012 | AD4: 1Q13 | AE4: 2Q13 | AF4: 3Q13 | AG4: 4Q13 | AH4: 2013 | AI4: 1Q14 | AJ4: 2Q14 | AK4: 3Q14 | AL4: 4Q14 | AM4: 2014 | AN4: 1Q15 | AO4: 2Q15 | AP4: 3Q15 | AQ4: 4Q15 | AR4: 2015 | AS4: 1Q16 | AT4: 2Q16 | AU4: 3Q16 | AV4: 4Q16 | AW4: 2016 | AX4: 1Q17 | AY4: 2Q17 | AZ4: 3Q17 | BA4: 4Q17 | BB4: 2017 | BC4: 1Q18 | BD4: 2Q18 | BE4: 3Q18 | BF4: 4Q18 | BG4: 2018 | BH4: 1Q19 | BI4: 2Q19 | BJ4: 3Q19 | BK4: 4Q19 | BL4: 2019 | BM4: 1Q20 | BN4: 2Q20 | BO4: 3Q20 | BP4: 4Q20 | BQ4: 2020 | BR4: 1Q21 | BS4: 2Q21 | BT4: 3Q21 | BU4: 4Q21 | BV4: 2021 | BW4: 1Q22 | BX4: 2Q22 | BY4: 3Q22 | BZ4: 4Q22 | CA4: 2022 | CB4: ='Income Statement'!CB4 -> 1Q23 | CC4: ='Income Statement'!CC4 -> 2Q23 | CD4: ='Income Statement'!CD4 -> 3Q23 | CE4: ='Income Statement'!CE4 -> 4Q23 | CF4: ='Income Statement'!CF4 -> 2023 | CG4: ='Income Statement'!CG4 -> 1Q24 | CH4: ='Income Statement'!CH4 -> 2Q24 | CI4: ='Income Statement'!CI4 -> 3Q24 | ... CU4: ='Income Statement'!CU4 -> 2026E
B5: Operating Activities
