Workbook
Name \P: #REF!
Name \P: #REF!
Name \P: #REF!
Name \P: #REF!
Name \Q: [1]TSFW!#REF!
Name \Q: [1]TSFW!#REF!
Name \Q: [1]TSFW!#REF!
Name \Q: [1]TSFW!#REF!
Name \S: '[2]US$'!#REF!
Name \S: '[2]US$'!#REF!
Name \X: [1]TSFW!#REF!
Name \X: [1]TSFW!#REF!
Name _1997: #REF!
Name _1997: #REF!
Name _1997: #REF!
Name _1997: #REF!
Name _1998: #REF!
Name _1998: #REF!
Name _1998: #REF!
Name _1999: #REF!
Name _1999: #REF!
Name _1999: #REF!
Name _1st_year: '[3]LINKS&INPUTS'!$D$52
Name _2000: #REF!
Name _2000: #REF!
Name _2000: #REF!
Name _2000: #REF!
Name _2000_EPS: #REF!
Name _2000_EPS: #REF!
Name _2000_EPS: #REF!
Name _2000_Rev: #REF!
Name _2000_Rev: #REF!
Name _2000_Rev: #REF!
Name _2001: #REF!
Name _2001_EPS: #REF!
Name _2001_Rev: #REF!
Name _2002: #REF!
Name _2002_EPS: #REF!
Name _2002_Rev: #REF!
Name _2003: #REF!
Name _2003_EPS: #REF!
Name _2003_Rev: #REF!
Name _2004: #REF!
Name _2004_EPS: #REF!
Name _2004_Rev: #REF!
Name _2005: #REF!
Name _2005_cfps: [4]NAV!#REF!
Name _2005_EPS: #REF!
Name _2005_EPS: #REF!
Name _2005_EPS: #REF!
Name _2005_EPS: #REF!
Name _2005_Rev: #REF!
Name _2005_Rev: #REF!
Name _2005_Rev: #REF!
Name _2006: #REF!
Name _2006: #REF!
Name _2006: #REF!
Name _2006_cfps: [4]NAV!#REF!
Name _2006_cfps: [4]NAV!#REF!
Name _2006_cfps: [4]NAV!#REF!

Sheet __FDSCACHE__
B1: This sheet contains FactSet XML data for use with this workbook's =FDS codes. Modifying the worksheet's contents may damage the workbook's =FDS functionality.

Sheet Comparison
B2: =IS!B2 -> CS DISCO (LAW)
B4: Variance Analysis | D4: =IS!AF4 -> 4Q24 | E4: =K4 -> 4Q25 | F4: Y/Y Chg. | G4: =IS!AJ4 -> 3Q25 | H4: =K4 -> 4Q25 | I4: Q/Q Chg. | J4: 4Q25E | K4: =IS!AK4 -> 4Q25 | L4: % Delta
B5: Software Revenue | D5: =IS!AF5 -> 30764 | E5: =K5 -> 35136 | F5: =E5/D5-1 -> 0.14211416 | G5: =IS!AJ5 -> 35233 | H5: =K5 -> 35136 | I5: =H5/G5-1 -> -0.0027531008 | J5: 34240.332 | K5: =IS!AK5 -> 35136 | L5: =K5/J5-1 -> 0.026158274
B6: Services Revenue | D6: =IS!AF8 -> 6235 | E6: =K6 -> 6035 | F6: =E6/D6-1 -> -0.032076985 | G6: =IS!AJ8 -> 5686 | H6: =K6 -> 6035 | I6: =H6/G6-1 -> 0.061378825 | J6: 5511.74 | K6: =IS!AK8 -> 6035 | L6: =K6/J6-1 -> 0.094935538
B7: Total Revenue | D7: =IS!AF11 -> 36999 | E7: =K7 -> 41171 | F7: =E7/D7-1 -> 0.1127598 | G7: =IS!AJ11 -> 40919 | H7: =K7 -> 41171 | I7: =H7/G7-1 -> 0.0061585083 | J7: 39752.072 | K7: =IS!AK11 -> 41171 | L7: =K7/J7-1 -> 0.035694441
B8: Cost of Revenue | D8: =IS!AF14 -> 9092 | E8: =K8 -> 9661 | F8: =E8/D8-1 -> 0.06258249 | G8: =IS!AJ14 -> 9447 | H8: =K8 -> 9661 | I8: =H8/G8-1 -> 0.022652694 | J8: 9540.4973 | K8: =IS!AK14 -> 9661 | L8: =K8/J8-1 -> 0.012630654
B9: Gross Profit | D9: =D7-D8 -> 27907 | E9: =K9 -> 31510 | F9: =E9/D9-1 -> 0.12910739 | G9: =G7-G8 -> 31472 | H9: =K9 -> 31510 | I9: =H9/G9-1 -> 0.0012074225 | J9: 30211.575 | K9: =K7-K8 -> 31510 | L9: =K9/J9-1 -> 0.042977743
B10: Gross Margins | D10: =D9/D7 -> 0.75426363 | E10: =K10 -> 0.76534454 | G10: =G9/G7 -> 0.76912926 | H10: =K10 -> 0.76534454 | J10: 0.76 | K10: =K9/K7 -> 0.76534454
B12: Operating Expenses
B13: S&M | D13: =IS!AF19 -> 13871 | E13: =K13 -> 13891 | F13: =E13/D13-1 -> 0.0014418571 | G13: =IS!AJ19 -> 13612 | H13: =K13 -> 13891 | I13: =H13/G13-1 -> 0.020496621 | J13: 13793.969 | K13: =IS!AK19 -> 13891 | L13: =K13/J13-1 -> 0.0070343072
B14: R&D | D14: =IS!AF21 -> 11934 | E14: =K14 -> 12965 | F14: =E14/D14-1 -> 0.086391822 | G14: =IS!AJ21 -> 11461 | H14: =K14 -> 12965 | I14: =H14/G14-1 -> 0.13122764 | J14: 12323.142 | K14: =IS!AK21 -> 12965 | L14: =K14/J14-1 -> 0.052085553
B15: G&A | D15: =IS!AF23 -> 7294 | E15: =K15 -> 7879 | F15: =E15/D15-1 -> 0.080202906 | G15: =IS!AJ23 -> 7748 | H15: =K15 -> 7879 | I15: =H15/G15-1 -> 0.016907589 | J15: 7473.3895 | K15: =IS!AK23 -> 7879 | L15: =K15/J15-1 -> 0.054273963
B16: Total Operating Expenses | D16: =SUM(D13:D15) -> 33099 | E16: =K16 -> 34735 | F16: =E16/D16-1 -> 0.049427475 | G16: =SUM(G13:G15) -> 32821 | H16: =K16 -> 34735 | I16: =H16/G16-1 -> 0.058316322 | J16: 33590.501 | K16: =SUM(K13:K15) -> 34735 | L16: =K16/J16-1 -> 0.034072108 | N16: =K16-J16 -> 1144.4992
B18: Non-GAAP Operating Income | D18: =D9-D16 -> -5192 | E18: =K18 -> -3225 | F18: =E18/D18-1 -> -0.37885208 | G18: =G9-G16 -> -1349 | H18: =K18 -> -3225 | I18: =H18/G18-1 -> 1.3906597 | J18: -3378.9261 | K18: =K9-K16 -> -3225 | L18: =K18/J18-1 -> -0.045554746
B19: Non-GAAP Operating Margin | D19: =D18/D7 -> -0.14032812 | E19: =K19 -> -0.078331836 | G19: =G18/G7 -> -0.03296757 | H19: =K19 -> -0.078331836 | J19: -0.085 | K19: =K18/K7 -> -0.078331836
B21: GAAP & Non-cash charges | D21: =IS!AF33 -> 20938 | E21: =K21 -> 6017 | F21: =E21/D21-1 -> -0.71262776 | G21: =IS!AJ33 -> 13113 | H21: =K21 -> 6017 | I21: =H21/G21-1 -> -0.54114238 | J21: 6000 | K21: =IS!AK33 -> 6017 | L21: =K21/J21-1 -> 0.0028333333
B23: GAAP Operating Income | D23: =D18-D21 -> -26130 | E23: =K23 -> -9242 | F23: =E23/D23-1 -> -0.64630693 | G23: =G18-G21 -> -14462 | H23: =K23 -> -9242 | I23: =H23/G23-1 -> -0.36094593 | J23: -9378.9261 | K23: =K18-K21 -> -9242 | L23: =K23/J23-1 -> -0.014599339
B24: GAAP Operating Margin | D24: =D23/D7 -> -0.7062353 | E24: =K24 -> -0.22447839 | G24: =G23/G7 -> -0.35342995 | H24: =K24 -> -0.22447839 | J24: -0.23593553 | K24: =K23/K7 -> -0.22447839
B26: Interest & Other Income (Expense) | D26: =IS!AF40 -> 953 | E26: =K26 -> 996 | F26: =E26/D26-1 -> 0.045120672 | G26: =IS!AJ40 -> 937 | H26: =K26 -> 996 | I26: =H26/G26-1 -> 0.062966916 | J26: 850 | K26: =IS!AK40 -> 996 | L26: =K26/J26-1 -> 0.17176471
B28: Adjusted EBITDA | D28: =IS!AF50 -> -4287 | E28: =K28 -> -2159 | F28: =E28/D28-1 -> -0.49638442 | G28: =IS!AJ50 -> -297 | H28: =K28 -> -2159 | I28: =H28/G28-1 -> 6.2693603 | J28: -2455.4761 | K28: =IS!AK50 -> -2159 | L28: =K28/J28-1 -> -0.12074079
B29: EBITDA Margin | D29: =D28/D7 -> -0.115868 | E29: =K29 -> -0.052439824 | G29: =G28/G7 -> -0.0072582419 | H29: =K29 -> -0.052439824 | J29: -0.061769764 | K29: =K28/K7 -> -0.052439824
B31: Non-GAAP Income before Taxes | D31: =D18+D26 -> -4239 | E31: =K31 -> -2229 | F31: =E31/D31-1 -> -0.47416844 | G31: =G18+G26 -> -412 | H31: =K31 -> -2229 | I31: =H31/G31-1 -> 4.4101942 | J31: -2528.9261 | K31: =K18+K26 -> -2229 | L31: =K31/J31-1 -> -0.11859821
B32: Income Tax | D32: =IS!AF54 -> 23 | E32: =K32 -> 256 | F32: =E32/D32-1 -> 10.130435 | G32: =IS!AJ54 -> 140 | H32: =K32 -> 256 | I32: =H32/G32-1 -> 0.82857143 | J32: 100 | K32: =IS!AK54 -> 256 | L32: =K32/J32-1 -> 1.56
B33: Non-GAAP Net Income | D33: =D31-D32 -> -4262 | E33: =K33 -> -2485 | F33: =E33/D33-1 -> -0.4169404 | G33: =G31-G32 -> -552 | H33: =K33 -> -2485 | I33: =H33/G33-1 -> 3.5018116 | J33: -2628.9261 | K33: =K31-K32 -> -2485 | L33: =K33/J33-1 -> -0.054747115
B35: GAAP Income before Taxes | D35: =D23+D26 -> -25177 | E35: =K35 -> -8246 | F35: =E35/D35-1 -> -0.67247885 | G35: =G23+G26 -> -13525 | H35: =K35 -> -8246 | I35: =H35/G35-1 -> -0.39031423 | J35: -8528.9261 | K35: =K23+K26 -> -8246 | L35: =K35/J35-1 -> -0.033172537
B36: Income Tax | D36: =IS!AF60 -> 23 | E36: =K36 -> 256 | F36: =E36/D36-1 -> 10.130435 | G36: =IS!AJ60 -> 140 | H36: =K36 -> 256 | I36: =H36/G36-1 -> 0.82857143 | J36: 100 | K36: =IS!AK60 -> 256 | L36: =K36/J36-1 -> 1.56
B37: GAAP Net Income | D37: =D35-D36 -> -25200 | E37: =K37 -> -8502 | F37: =E37/D37-1 -> -0.66261905 | G37: =G35-G36 -> -13665 | H37: =K37 -> -8502 | I37: =H37/G37-1 -> -0.37782656 | J37: -8628.9261 | K37: =K35-K36 -> -8502 | L37: =K37/J37-1 -> -0.014709376
B39: Non-GAAP EPS | D39: =IS!AF65 -> -0.070912782 | E39: =K39 -> -0.03952412 | F39: =E39/D39-1 -> -0.44263757 | G39: =IS!AJ65 -> -0.0088897478 | H39: =K39 -> -0.03952412 | I39: =H39/G39-1 -> 3.4460339 | J39: -0.041918658 | K39: =IS!AK65 -> -0.03952412 | L39: =K39/J39-1 -> -0.05712344
B40: GAAP EPS | D40: =IS!AF67 -> -0.41928721 | E40: =K40 -> -0.13522498 | G40: =IS!AJ67 -> -0.22006957 | H40: =K40 -> -0.13522498 | J40: -0.13758964 | K40: =IS!AK67 -> -0.13522498
B42: Basic Shares Outstanding | D42: =IS!Z70 -> 60350 | E42: =K42 -> 59815 | G42: =IS!AC70 -> 61188 | H42: =K42 -> 59815 | J42: 59815 | K42: =IS!AD70 -> 59815
B43: Diluted Shares Outstanding | D43: =IS!Z71 -> 60350 | E43: =K43 -> 59815 | G43: =IS!AC71 -> 61188 | H43: =K43 -> 59815 | J43: 59815 | K43: =IS!AD71 -> 59815
B46: Source: Company reports and Needham & Co estimates

Sheet G Chg
C5: FY26 Guidance ($mm) | D5: FY26 Street Estimate | E5: Initial FY26 Guidance | F5: Delta | G5: 3Q26 Guide | H5: =LEFT(G5,4)& " Result" -> 3Q26 Result | I5: =LEFT(G5,4)& " Beat" -> 3Q26 Beat | J5: Rest of Year Raise / (Reduce)
C6: Revenue | D6: 170.4 | E6: =AVERAGE(167,177) -> 172 | F6: =E6-D6 -> 1.6 | G6: 38.5 | H6: =Comparison!K7/1000 -> 41.171 | I6: =H6-G6 -> 2.671 | J6: =F6-I6 -> -1.071
C7: Growth | D7: =D6/(IS!AL11/1000)-1 -> 0.086395195 | E7: =E6/(IS!AL11/1000)-1 -> 0.096596089
C8: Software Revenue | D8: 148.1 | E8: =AVERAGE(145.5,152.5) -> 149 | F8: =E8-D8 -> 0.9 | G8: 33.25 | H8: =Comparison!K5/1000 -> 35.136 | I8: =H8-G8 -> 1.886 | J8: =F8-I8 -> -0.986
C9: Growth | D9: =D8*1000/IS!AL5-1 -> 0.10522388 | E9: =E8*1000/IS!AL5-1 -> 0.1119403
C10: Services Revenue | D10: =D6-D8 -> 22.3 | E10: =E6-E8 -> 23 | F10: =E10-D10 -> 0.7 | G10: =G6-G8 -> 5.25 | H10: =Comparison!K6/1000 -> 6.035 | I10: =H10-G10 -> 0.785 | J10: =F10-I10 -> -0.085
C11: Growth | D11: =D10*1000/IS!AL8-1 -> -0.02402731 | E11: =E10*1000/IS!AL8-1 -> 0.0066086043
C12: Adjusted EBITDA | D12: -2.9 | E12: =AVERAGE(-8.5,-4.5) -> -6.5 | F12: =E12-D12 -> -3.6 | G12: -4 | H12: =Comparison!K28/1000 -> -2.159 | I12: =H12-G12 -> 1.841 | J12: =F12-I12 -> -5.441
C13: Margin | D13: =D12/D6 -> -0.017018779 | E13: =E12/E6 -> -0.037790698
L14: Guidance History | M14: FY22 | N14: FY23 | O14: FY24 | P14: FY25E | Q14: FY26E
H15: Manually update Software/Services Result | L15: Revenue Growth - Initial Guide | M15: 0.3 | N15: 0.036 | O15: 0.079 | P15: =AVERAGE(145500,157500)/IS!AG11-1 -> 0.045974551 | Q15: TBD
L16: Revenue Growth- Actual | M16: =IS!W12 -> 0.1823302 | N16: =IS!AB12 -> 0.021451291 | O16: =IS!AG12 -> 0.048888406 | P16: =IS!AL12 -> 0.082904702
L17: Difference | M17: =M16-M15 -> -0.1176698 | N17: =N16-N15 -> -0.014548709 | O17: =O16-O15 -> -0.030111594 | P17: =P16-P15 -> 0.036930151
L19: Adj. EBITDA Margin - Initial Guide | M19: -0.319 | N19: -0.286 | O19: -0.151 | P19: =-17/AVERAGE(145.5,157.5) -> -0.11221122 | Q19: TBD
L20: Adj. EBITDA Margin - Actual | M20: =IS!W51 -> -0.32934389 | N20: =IS!AB51 -> -0.18751539 | O20: =IS!AG51 -> -0.12923136 | P20: =IS!AL51 -> -0.065241092
L21: Difference | M21: =M20-M19 -> -0.010343886 | N21: =N20-N19 -> 0.098484611 | O21: =O20-O19 -> 0.021768636 | P21: =P20-P19 -> 0.046970129
L23: Needham & Company Research

Sheet IS
B2: CS DISCO (LAW)
B4: Income Statement | D4: 1Q19 | E4: 2Q19 | F4: 3Q19 | G4: 4Q19 | H4: 2019 | I4: 1Q20 | J4: 2Q20 | K4: 3Q20 | L4: 4Q20 | M4: 2020 | N4: 1Q21 | O4: 2Q21 | P4: 3Q21 | Q4: 4Q21 | R4: 2021 | S4: 1Q22 | T4: 2Q22 | U4: 3Q22 | V4: 4Q22 | W4: 2022 | X4: 1Q23 | Y4: 2Q23 | Z4: 3Q23 | AA4: 4Q23 | AB4: 2023 | AC4: 1Q24 | AD4: 2Q24 | AE4: 3Q24 | AF4: 4Q24 | AG4: 2024 | AH4: 1Q25 | AI4: 2Q25 | AJ4: 3Q25 | AK4: 4Q25 | AL4: 2025 | AM4: 1Q26E | AN4: 2Q26E | AO4: 3Q26E | AP4: 4Q26E | AQ4: 2026E
B5: Software Revenue | X5: 27560 | Y5: 27012 | Z5: 28413 | AA5: 29282 | AB5: =SUM(X5:AA5) -> 112267 | AC5: 29909 | AD5: 29278 | AE5: 30181 | AF5: =120132-SUM(AC5:AE5) -> 30764 | AG5: =SUM(AC5:AF5) -> 120132 | AH5: 30887 | AI5: 32744 | AJ5: 35233 | AK5: =134000-SUM(AH5:AJ5) -> 35136 | AL5: =SUM(AH5:AK5) -> 134000 | AM5: =AH5*(1+AM6) -> 34531.666 | AN5: =AI5*(1+AN6) -> 36673.28 | AO5: =AJ5*(1+AO6) -> 38185.026 | AP5: =AK5*(1+AP6) -> 39633.408 | AQ5: =SUM(AM5:AP5) -> 149023.38
C6: Y/Y Growth | X6: - | Y6: - | Z6: - | AA6: - | AB6: - | AC6: =AC5/X5-1 -> 0.085232221 | AD6: =AD5/Y5-1 -> 0.083888642 | AE6: =AE5/Z5-1 -> 0.062225038 | AF6: =AF5/AA5-1 -> 0.050611297 | AG6: =AG5/AB5-1 -> 0.070056205 | AH6: =AH5/AC5-1 -> 0.032699188 | AI6: =AI5/AD5-1 -> 0.1183824 | AJ6: =AJ5/AE5-1 -> 0.16739008 | ... AL6: =AL5/AG5-1 -> 0.11543968 | AM6: 0.118 | AN6: 0.12 | AO6: =1.122*(AJ5-1200)/AJ5-1 -> 0.083785826 | AP6: 0.128 | AQ6: =AQ5/AL5-1 -> 0.11211478
C7: Q/Q Growth | X7: - | Y7: =Y5/X5-1 -> -0.01988389 | Z7: =Z5/Y5-1 -> 0.051865837 | AA7: =AA5/Z5-1 -> 0.030584592 | AC7: =AC5/AA5-1 -> 0.021412472 | AD7: =AD5/AC5-1 -> -0.021097329 | AE7: =AE5/AD5-1 -> 0.030842271 | AF7: =AF5/AE5-1 -> 0.019316789 | AH7: =AH5/AF5-1 -> 0.0039981797 | AI7: =AI5/AH5-1 -> 0.060122382 | AJ7: =AJ5/AI5-1 -> 0.076013926 | AK7: =AK5/AJ5-1 -> -0.0027531008 | AM7: =AM5/AK5-1 -> -0.017199852 | AN7: =AN5/AM5-1 -> 0.062018844 | AO7: =AO5/AN5-1 -> 0.041222001 | AP7: =AP5/AO5-1 -> 0.037930628
B8: Services Revenue | X8: 5569 | Y8: 7264 | Z8: 6530 | AA8: 6460 | AB8: =SUM(X8:AA8) -> 25823 | AC8: =AC11-AC5 -> 5662 | AD8: =AD11-AD5 -> 6727 | AE8: =AE11-AE5 -> 6085 | AF8: =36999-AF5 -> 6235 | AG8: =SUM(AC8:AF8) -> 24709 | AH8: =AH11-AH5 -> 5766 | AI8: =AI11-AI5 -> 5362 | AJ8: =AJ11-AJ5 -> 5686 | AK8: =22849-SUM(AH8:AJ8) -> 6035 | AL8: =SUM(AH8:AK8) -> 22849 | AM8: =AH8*(1+AM9) -> 5218.23 | AN8: =AI8*(1+AN9) -> 5630.1 | AO8: =AJ8*(1+AO9) -> 5856.58 | AP8: =AK8*(1+AP9) -> 6276.4 | AQ8: =SUM(AM8:AP8) -> 22981.31
C9: Y/Y Growth | X9: - | Y9: - | Z9: - | AA9: - | AB9: - | AC9: =AC8/X8-1 -> 0.016699587 | AD9: =AD8/Y8-1 -> -0.073926211 | AE9: =AE8/Z8-1 -> -0.068147014 | AF9: =AF8/AA8-1 -> -0.034829721 | AG9: =AG8/AB8-1 -> -0.043139837 | AH9: =AH8/AC8-1 -> 0.018368068 | AI9: =AI8/AD8-1 -> -0.20291363 | AJ9: =AJ8/AE8-1 -> -0.065571076 | ... AL9: =AL8/AG8-1 -> -0.075276215 | AM9: -0.095 | AN9: 0.05 | AO9: 0.03 | AP9: 0.04 | AQ9: =AQ8/AL8-1 -> 0.0057906254
C10: Q/Q Growth | X10: - | Y10: =Y8/X8-1 -> 0.30436344 | Z10: =Z8/Y8-1 -> -0.10104626 | AA10: =AA8/Z8-1 -> -0.010719755 | AC10: =AC8/AA8-1 -> -0.12352941 | AD10: =AD8/AC8-1 -> 0.18809608 | AE10: =AE8/AD8-1 -> -0.095436301 | AF10: =AF8/AE8-1 -> 0.024650781 | AH10: =AH8/AF8-1 -> -0.075220529 | AI10: =AI8/AH8-1 -> -0.070065904 | AJ10: =AJ8/AI8-1 -> 0.060425214 | AK10: =AK8/AJ8-1 -> 0.061378825 | AM10: =AM8/AK8-1 -> -0.13533886 | AN10: =AN8/AM8-1 -> 0.078929062 | AO10: =AO8/AN8-1 -> 0.040226639 | AP10: =AP8/AO8-1 -> 0.071683474
B11: Total Revenue | D11: =+D116 -> 10378 | E11: =+E116 -> 11305 | F11: =+F116 -> 12652 | G11: =+G116 -> 14221 | H11: =H116 -> 48556 | I11: =+I116 -> 15668 | J11: =+J116 -> 15727 | K11: =+K116 -> 17863 | L11: =+L116 -> 19186 | M11: =M116 -> 68444 | N11: =+N116 -> 21131 | O11: 29547 | P11: 29854 | Q11: 33810 | R11: =SUM(N11:Q11) -> 114342 | S11: 34468 | T11: 33710 | U11: =34475 -> 34475 | V11: 32537 | W11: =SUM(S11:V11) -> 135190 | X11: =+X5+X8 -> 33129 | Y11: =+Y5+Y8 -> 34276 | Z11: =+Z5+Z8 -> 34943 | AA11: =+AA5+AA8 -> 35742 | AB11: =+AB5+AB8 -> 138090 | AC11: 35571 | AD11: 36005 | AE11: =36266 -> 36266 | AF11: =+AF5+AF8 -> 36999 | AG11: =+AG5+AG8 -> 144841 | AH11: 36653 | AI11: 38106 | AJ11: 40919 | AK11: =+AK5+AK8 -> 41171 | AL11: =+AL5+AL8 -> 156849 | AM11: =+AM5+AM8 -> 39749.896 | AN11: =+AN5+AN8 -> 42303.38 | AO11: =+AO5+AO8 -> 44041.606 | AP11: =+AP5+AP8 -> 45909.808 | AQ11: =+AQ5+AQ8 -> 172004.69
C12: Y/Y Growth | I12: =I11/D11-1 -> 0.50973213 | J12: =J11/E11-1 -> 0.39115436 | K12: =K11/F11-1 -> 0.41187164 | L12: =L11/G11-1 -> 0.34913157 | M12: =M11/H11-1 -> 0.40958893 | N12: =N11/I11-1 -> 0.34867245 | O12: =O11/J11-1 -> 0.87874356 | P12: =P11/K11-1 -> 0.67127582 | ... AQ12: =AQ11/AL11-1 -> 0.096625991
C13: Q/Q Growth | E13: =E11/D11-1 -> 0.089323569 | F13: =F11/E11-1 -> 0.11915082 | G13: =G11/F11-1 -> 0.12401201 | I13: =I11/G11-1 -> 0.10175093 | J13: =J11/I11-1 -> 0.003765637 | K13: =K11/J11-1 -> 0.13581738 | L13: =L11/K11-1 -> 0.074063707 | N13: =N11/L11-1 -> 0.101376 | O13: =O11/N11-1 -> 0.39827741 | P13: =P11/O11-1 -> 0.010390226 | Q13: =Q11/P11-1 -> 0.13251156 | S13: =S11/Q11-1 -> 0.019461698 | T13: =T11/S11-1 -> -0.021991412 | U13: =U11/T11-1 -> 0.022693563 | V13: =V11/U11-1 -> -0.056214648 | X13: =X11/V11-1 -> 0.018194671 | Y13: =Y11/X11-1 -> 0.034622234 | Z13: =Z11/Y11-1 -> 0.01945968 | AA13: =AA11/Z11-1 -> 0.02286581 | AC13: =AC11/AA11-1 -> -0.0047842874 | AD13: =AD11/AC11-1 -> 0.01220095 | AE13: =AE11/AD11-1 -> 0.0072489932 | AF13: =AF11/AE11-1 -> 0.020211769 | AH13: =AH11/AF11-1 -> -0.0093516041 | AI13: =AI11/AH11-1 -> 0.039642048 | AJ13: =AJ11/AI11-1 -> 0.073820396 | AK13: =AK11/AJ11-1 -> 0.0061585083 | AM13: =AM11/AK11-1 -> -0.034517112 | AN13: =AN11/AM11-1 -> 0.064238759 | AO13: =AO11/AN11-1 -> 0.04108953 | AP13: =AP11/AO11-1 -> 0.042419025
B14: Cost of Revenue | D14: =D118-D137 -> 2902 | E14: =E118-E137 -> 3304 | F14: =F118-F137 -> 3618 | G14: =G118-G137 -> 4626 | H14: =H118-H137 -> 14450 | I14: =I118-I137 -> 5065 | J14: =J118-J137 -> 4502 | K14: =K118-K137 -> 5515 | ... N14: =N118-N137 -> 5780 | O14: =8695-10 -> 8685 | P14: =7829-10 -> 7819 | Q14: =8786-29 -> 8757 | R14: =SUM(N14:Q14) -> 31041 | S14: =8969-160 -> 8809 | T14: =8489-234 -> 8255 | U14: =8634-274 -> 8360 | V14: =8071-270 -> 7801 | W14: =SUM(S14:V14) -> 33225 | X14: =8277-231 -> 8046 | Y14: =9039-271 -> 8768 | Z14: =8939-270 -> 8669 | AA14: =8693-264 -> 8429 | AB14: =SUM(X14:AA14) -> 33912 | AC14: =8852-385 -> 8467 | AD14: =9288-432 -> 8856 | AE14: =9740-456 -> 9284 | AF14: =9534-442 -> 9092 | AG14: =SUM(AC14:AF14) -> 35699 | AH14: 9004 | AI14: =9683-562 -> 9121 | AJ14: 9447 | AK14: 9661 | AL14: =SUM(AH14:AK14) -> 37233 | AM14: =AM11*(1-AM16) -> 9818.2243 | AN14: =AN11*(1-AN16) -> 10068.204 | AO14: =AO11*(1-AO16) -> 10481.902 | AP14: =AP11*(1-AP16) -> 10834.715 | AQ14: =SUM(AM14:AP14) -> 41203.046
B15: Gross Profit | D15: =D11-D14 -> 7476 | E15: =E11-E14 -> 8001 | F15: =F11-F14 -> 9034 | G15: =G11-G14 -> 9595 | H15: =H11-H14 -> 34106 | I15: =I11-I14 -> 10603 | J15: =J11-J14 -> 11225 | K15: =K11-K14 -> 12348 | ... AQ15: =AQ11-AQ14 -> 130801.64
C16: Gross Margin | D16: =D15/D11 -> 0.72037001 | E16: =E15/E11 -> 0.70773994 | F16: =F15/F11 -> 0.71403731 | G16: =G15/G11 -> 0.67470642 | H16: =H15/H11 -> 0.70240547 | I16: =I15/I11 -> 0.67672964 | J16: =J15/J11 -> 0.7137407 | K16: =K15/K11 -> 0.69126127 | ... AL16: =AL15/AL11 -> 0.76261882 | AM16: 0.753 | AN16: 0.762 | AO16: 0.762 | AP16: 0.764 | AQ16: =AQ15/AQ11 -> 0.76045394
B18: Operating Expenses
C19: Sales & marketing | D19: =D122-D138 -> 5256 | E19: =E122-E138 -> 5821 | F19: =F122-F138 -> 6946 | G19: =G122-G138 -> 7798 | H19: =H122-H138 -> 25821 | I19: =I122-I138 -> 9252 | J19: =J122-J138 -> 7082 | K19: =K122-K138 -> 7093 | ... N19: =N122-N138 -> 7793 | O19: =10832-235 -> 10597 | P19: =13168-245 -> 12923 | Q19: =15169-695 -> 14474 | R19: =SUM(N19:Q19) -> 45787 | S19: =16419-821 -> 15598 | T19: =18931-1380 -> 17551 | U19: =19311-753 -> 18558 | V19: =18178-1232 -> 16946 | W19: =SUM(S19:V19) -> 68653 | X19: =19060-1391-177 -> 17492 | Y19: =18053-1360-471 -> 16222 | Z19: =16708-1277 -> 15431 | AA19: =14311-1338 -> 12973 | AB19: =SUM(X19:AA19) -> 62118 | AC19: =15808-1080 -> 14728 | AD19: =15498-1171 -> 14327 | AE19: =14988-1213 -> 13775 | AF19: 13871 | AG19: =SUM(AC19:AF19) -> 56701 | AH19: 13183 | AI19: 13763 | AJ19: 13612 | AK19: 13891 | AL19: =SUM(AH19:AK19) -> 54449 | AM19: =AM11*AM20 -> 14150.963 | AN19: =AN11*AN20 -> 14002.419 | AO19: =AO11*AO20 -> 14049.272 | AP19: =AP11*AP20 -> 14691.139 | AQ19: =SUM(AM19:AP19) -> 56893.793
C20: % of Revenue | D20: =D19/D11 -> 0.50645596 | E20: =E19/E11 -> 0.51490491 | F20: =F19/F11 -> 0.54900411 | G20: =G19/G11 -> 0.548344 | H20: =H19/H11 -> 0.53177774 | I20: =I19/I11 -> 0.59050294 | J20: =J19/J11 -> 0.45030839 | K20: =K19/K11 -> 0.39707776 | ... AL20: =AL19/AL11 -> 0.34714279 | AM20: 0.356 | AN20: 0.331 | AO20: 0.319 | AP20: 0.32 | AQ20: =AQ19/AQ11 -> 0.33076884
C21: Research & Development | D21: =D123-D139 -> 4761 | E21: =E123-E139 -> 6243 | F21: =F123-F139 -> 6968 | G21: =G123-G139 -> 6653 | H21: =H123-H139 -> 24625 | I21: =I123-I139 -> 7981 | J21: =J123-J139 -> 5998 | K21: =K123-K139 -> 6010 | ... N21: =N123-N139 -> 6061 | O21: =7861-285 -> 7576 | P21: =9652-301 -> 9351 | Q21: =10639-1294 -> 9345 | R21: =SUM(N21:Q21) -> 32333 | S21: =12318-1427 -> 10891 | T21: =15181-2073 -> 13108 | U21: =15694-1916 -> 13778 | V21: =16065-2652 -> 13413 | W21: =SUM(S21:V21) -> 51190 | X21: =15772-2190-509 -> 13073 | Y21: =13258-1729-1001 -> 10528 | Z21: =12065-2001 -> 10064 | AA21: =10528-1847 -> 8681 | AB21: =SUM(X21:AA21) -> 42346 | AC21: =12079-2092 -> 9987 | AD21: =12888-2084 -> 10804 | AE21: =12757-1680 -> 11077 | AF21: 11934 | AG21: =SUM(AC21:AF21) -> 43802 | AH21: 12214 | AI21: 11724 | AJ21: 11461 | AK21: 12965 | AL21: =SUM(AH21:AK21) -> 48364 | AM21: =AM11*AM22 -> 12918.716 | AN21: =AN11*AN22 -> 12648.711 | AO21: =AO11*AO22 -> 12816.107 | AP21: =AP11*AP22 -> 13130.205 | AQ21: =SUM(AM21:AP21) -> 51513.739
C22: % of Revenue | D22: =D21/D11 -> 0.45875891 | E22: =E21/E11 -> 0.55223352 | F22: =F21/F11 -> 0.55074297 | G22: =G21/G11 -> 0.46782927 | H22: =H21/H11 -> 0.50714639 | I22: =I21/I11 -> 0.50938218 | J22: =J21/J11 -> 0.38138234 | K22: =K21/K11 -> 0.33644964 | ... AL22: =AL21/AL11 -> 0.30834752 | AM22: 0.325 | AN22: 0.299 | AO22: 0.291 | AP22: 0.286 | AQ22: =AQ21/AQ11 -> 0.29949032
C23: General & Administrative | D23: =D124-D140 -> 1923 | E23: =E124-E140 -> 2632 | F23: =F124-F140 -> 2454 | G23: =G124-G140 -> 2881 | H23: =H124-H140 -> 9890 | I23: =I124-I140 -> 4068 | J23: =J124-J140 -> 2952 | K23: =K124-K140 -> 2837 | ... N23: =N124-N140 -> 3857 | O23: =5128-436 -> 4692 | P23: =8270-498 -> 7772 | Q23: =8163-1077 -> 7086 | R23: =SUM(N23:Q23) -> 23407 | S23: =8519-798 -> 7721 | T23: =11065-1835-386-798 -> 8046 | U23: =10906-2722-329 -> 7855 | V23: =10248-3190-540 -> 6518 | W23: =SUM(S23:V23) -> 30140 | X23: =12300-3412-330 -> 8558 | Y23: =10917-3508-102 -> 7307 | Z23: =128+6429 -> 6557 | AA23: =9887-1498-500-74 -> 7815 | AB23: =SUM(X23:AA23) -> 30237 | AC23: =11164-2116-199 -> 8849 | AD23: =10715-2371-384 -> 7960 | AE23: =9658-1798-143 -> 7717 | AF23: 7294 | AG23: =SUM(AC23:AF23) -> 31820 | AH23: 8418 | AI23: 7249 | AJ23: 7748 | AK23: 7879 | AL23: =SUM(AH23:AK23) -> 31294 | AM23: =AM11*AM24 -> 8744.9771 | AN23: =AN11*AN24 -> 7699.2152 | AO23: =AO11*AO24 -> 7883.4475 | AP23: =AP11*AP24 -> 8080.1262 | AQ23: =SUM(AM23:AP23) -> 32407.766
C24: % of Revenue | D24: =D23/D11 -> 0.18529582 | E24: =E23/E11 -> 0.23281734 | F24: =F23/F11 -> 0.19396143 | G24: =G23/G11 -> 0.20258772 | H24: =H23/H11 -> 0.20368235 | I24: =I23/I11 -> 0.25963748 | J24: =J23/J11 -> 0.18770268 | K24: =K23/K11 -> 0.15881991 | ... AL24: =AL23/AL11 -> 0.19951673 | AM24: 0.22 | AN24: 0.182 | AO24: 0.179 | AP24: 0.176 | AQ24: =AQ23/AQ11 -> 0.18841211
B25: Total Operating Expense | D25: =D19+D21+D23 -> 11940 | E25: =E19+E21+E23 -> 14696 | F25: =F19+F21+F23 -> 16368 | G25: =G19+G21+G23 -> 17332 | H25: =H19+H21+H23 -> 60336 | I25: =I19+I21+I23 -> 21301 | J25: =J19+J21+J23 -> 16032 | K25: =K19+K21+K23 -> 15940 | ... AQ25: =AQ19+AQ21+AQ23 -> 140815.3
B27: Non-GAAP Operating Income | D27: =D15-D25 -> -4464 | E27: =E15-E25 -> -6695 | F27: =F15-F25 -> -7334 | G27: =G15-G25 -> -7737 | H27: =H15-H25 -> -26230 | I27: =I15-I25 -> -10698 | J27: =J15-J25 -> -4807 | K27: =K15-K25 -> -3592 | ... AQ27: =AQ15-AQ25 -> -10013.654
C28: Non-GAAP Operating Margin | D28: =D27/D11 -> -0.43014068 | E28: =E27/E11 -> -0.59221583 | F28: =F27/F11 -> -0.5796712 | G28: =G27/G11 -> -0.54405457 | H28: =H27/H11 -> -0.54020101 | I28: =I27/I11 -> -0.68279295 | J28: =J27/J11 -> -0.3056527 | K28: =K27/K11 -> -0.20108604 | ... AQ28: =AQ27/AQ11 -> -0.058217328
B30: GAAP Adjustments
C31: Stock base compensation | D31: =D141 -> 2632 | E31: =+E141 -> 534 | F31: =+F141 -> 453 | G31: =+G141 -> 501 | H31: =SUM(D31:G31) -> 4120 | I31: =+I141 -> 488 | J31: =+J141 -> 504 | K31: =+K141 -> 506 | L31: =+L141 -> 495 | M31: =SUM(I31:L31) -> 1993 | N31: =+N141 -> 488 | O31: 966 | P31: 1054 | Q31: 3095 | R31: =SUM(N31:Q31) -> 5603 | S31: 3206 | T31: 5522 | U31: 5665 | V31: 7344 | W31: =SUM(S31:V31) -> 21737 | X31: 7224 | Y31: 6868 | Z31: -2881 | AA31: 4947 | AB31: =SUM(X31:AA31) -> 16158 | AC31: 5673 | AD31: 6058 | AE31: 5147 | AF31: 5391 | AG31: =SUM(AC31:AF31) -> 22269 | AH31: 5879 | AI31: 6478 | AJ31: 6090 | AK31: 6017 | AL31: =SUM(AH31:AK31) -> 24464 | AM31: 6000 | AN31: 6000 | AO31: 6000 | AP31: 6000 | AQ31: =SUM(AM31:AP31) -> 24000
C32: Other | H32: =SUM(D32:G32) -> 0 | K32: -1057 | M32: =SUM(I32:L32) -> -1057 | R32: =SUM(N32:Q32) -> 0 | T32: =386+798 -> 1184 | U32: 329 | V32: 540 | W32: =SUM(S32:V32) -> 2053 | X32: 1016 | Y32: 1574 | Z32: 0 | AA32: =500+74 -> 574 | AB32: =SUM(X32:AA32) -> 3164 | AC32: 199 | AD32: 384 | AE32: 143 | AF32: =303+31+15213 -> 15547 | AG32: =SUM(AC32:AF32) -> 16273 | AH32: 565 | AI32: 1581 | AJ32: 7023 | AK32: 0 | AL32: =SUM(AH32:AK32) -> 9169 | AQ32: =SUM(AM32:AP32) -> 0
B33: GAAP Adjustments | D33: =SUM(D31:D32) -> 2632 | E33: =SUM(E31:E32) -> 534 | F33: =SUM(F31:F32) -> 453 | G33: =SUM(G31:G32) -> 501 | H33: =SUM(H31:H32) -> 4120 | I33: =SUM(I31:I32) -> 488 | J33: =SUM(J31:J32) -> 504 | K33: =SUM(K31:K32) -> -551 | ... AQ33: =SUM(AQ31:AQ32) -> 24000
B35: GAAP Operating Income | D35: =D27-D33 -> -7096 | E35: =E27-E33 -> -7229 | F35: =F27-F33 -> -7787 | G35: =G27-G33 -> -8238 | H35: =H27-H33 -> -30350 | I35: =I27-I33 -> -11186 | J35: =J27-J33 -> -5311 | K35: =K27-K33 -> -3041 | ... AQ35: =AQ27-AQ33 -> -34013.654
C36: GAAP Operating Margin | D36: =D35/D11 -> -0.6837541 | E36: =E35/E11 -> -0.63945157 | F36: =F35/F11 -> -0.61547581 | G36: =G35/G11 -> -0.57928416 | H36: =H35/H11 -> -0.62505149 | I36: =I35/I11 -> -0.71393924 | J36: =J35/J11 -> -0.3376995 | K36: =K35/K11 -> -0.17024016 | ... AQ36: =AQ35/AQ11 -> -0.19774841
B38: Interest and Other Income | D38: =D129 -> 180 | E38: =E129 -> 144 | F38: =F129 -> 215 | G38: =G129 -> 113 | H38: =H129 -> 652 | I38: =I129 -> 63 | J38: =J129 -> 15 | K38: =K129 -> 55 | ... N38: =N129 -> 13 | O38: 21 | P38: 40 | Q38: 32 | R38: =SUM(N38:Q38) -> 106 | S38: 30 | T38: 29 | U38: 364 | V38: 1279 | W38: =SUM(S38:V38) -> 1702 | X38: 1947 | Y38: 2129 | Z38: 2191 | AA38: 2039 | AB38: =SUM(X38:AA38) -> 8306 | AC38: 1986 | AD38: 1735 | AE38: 1652 | AF38: 1464 | AG38: =SUM(AC38:AF38) -> 6837 | AH38: 1354 | AI38: 1208 | AJ38: 937 | AK38: 996 | AL38: =SUM(AH38:AK38) -> 4495 | AM38: =AK38-25 -> 971 | AN38: =AM38-25 -> 946 | AO38: =AN38-30 -> 916 | AP38: =AO38-50 -> 866 | AQ38: =SUM(AM38:AP38) -> 3699
B39: Interest and Other Expense | D39: =+D130 -> -33 | E39: =+E130 -> 36 | F39: =+F130 -> -87 | G39: =+G130 -> -40 | H39: =+H130 -> -124 | I39: =+I130 -> -88 | J39: =+J130 -> -161 | K39: =+K130 -> -170 | ... N39: =+N130 -> -57 | O39: -92 | P39: -169 | Q39: -222 | R39: =SUM(N39:Q39) -> -540 | S39: -93 | T39: -200 | U39: -314 | V39: 134 | W39: =SUM(S39:V39) -> -473 | X39: 8 | Y39: 4 | Z39: -260 | AA39: 80 | AB39: =SUM(X39:AA39) -> -168 | AC39: -150 | AD39: -80 | AE39: 185 | AF39: -511 | AG39: =SUM(AC39:AF39) -> -556 | AL39: =SUM(AH39:AK39) -> 0 | AQ39: =SUM(AM39:AP39) -> 0
B40: Total Other Income (Expense) | D40: =SUM(D38:D39) -> 147 | E40: =SUM(E38:E39) -> 180 | F40: =SUM(F38:F39) -> 128 | G40: =SUM(G38:G39) -> 73 | H40: =SUM(D40:G40) -> 528 | I40: =SUM(I38:I39) -> -25 | J40: =SUM(J38:J39) -> -146 | K40: =SUM(K38:K39) -> -115 | L40: =SUM(L38:L39) -> -15 | M40: =SUM(I40:L40) -> -301 | N40: =SUM(N38:N39) -> -44 | O40: =SUM(O38:O39) -> -71 | P40: =SUM(P38:P39) -> -129 | Q40: =SUM(Q38:Q39) -> -190 | R40: =SUM(N40:Q40) -> -434 | S40: =SUM(S38:S39) -> -63 | T40: =SUM(T38:T39) -> -171 | U40: =SUM(U38:U39) -> 50 | V40: =SUM(V38:V39) -> 1413 | W40: =SUM(S40:V40) -> 1229 | X40: =SUM(X38:X39) -> 1955 | Y40: =SUM(Y38:Y39) -> 2133 | Z40: =SUM(Z38:Z39) -> 1931 | AA40: =SUM(AA38:AA39) -> 2119 | AB40: =SUM(X40:AA40) -> 8138 | AC40: =SUM(AC38:AC39) -> 1836 | AD40: =SUM(AD38:AD39) -> 1655 | AE40: =SUM(AE38:AE39) -> 1837 | AF40: =SUM(AF38:AF39) -> 953 | AG40: =SUM(AC40:AF40) -> 6281 | AH40: =SUM(AH38:AH39) -> 1354 | AI40: =SUM(AI38:AI39) -> 1208 | AJ40: =SUM(AJ38:AJ39) -> 937 | AK40: =SUM(AK38:AK39) -> 996 | AL40: =SUM(AH40:AK40) -> 4495 | AM40: =SUM(AM38:AM39) -> 971 | AN40: =SUM(AN38:AN39) -> 946 | AO40: =SUM(AO38:AO39) -> 916 | AP40: =SUM(AP38:AP39) -> 866 | AQ40: =SUM(AM40:AP40) -> 3699
B42: EBITDA Reconciliation
C43: GAAP Net Loss | D43: =D62 -> -6952 | E43: =E62 -> -7051 | F43: =F62 -> -7661 | G43: =G62 -> -8168 | H43: =SUM(D43:G43) -> -29832 | I43: =I62 -> -11236 | J43: =J62 -> -5477 | K43: =K62 -> -3169 | L43: =L62 -> -2991 | M43: =SUM(I43:L43) -> -22873 | N43: =N62 -> -2928 | O43: =O62 -> -3083 | P43: =P62 -> -9225 | Q43: =Q62 -> -9108 | R43: =SUM(N43:Q43) -> -24344 | S43: =S62 -> -11849 | T43: =T62 -> -20171 | U43: =U62 -> -20058 | V43: =V62 -> -18687 | W43: =SUM(S43:V43) -> -70765 | X43: =X62 -> -20365 | Y43: =Y62 -> -14915 | Z43: =Z62 -> -1030 | AA43: =AA62 -> -5840 | AB43: =SUM(X43:AA43) -> -42150 | AC43: =AC62 -> -10582 | AD43: =AD62 -> -10834 | AE43: =AE62 -> -9158 | AF43: =AF62 -> -25200 | AG43: =SUM(AC43:AF43) -> -55774 | AH43: =AH62 -> -11393 | AI43: =AI62 -> -10812 | AJ43: =AJ62 -> -13665 | AK43: =AK62 -> -8502 | AL43: =SUM(AH43:AK43) -> -44372 | AM43: =AM62 -> -11061.985 | AN43: =AN62 -> -7319.169 | AO43: =AO62 -> -6423.1234 | AP43: =AP62 -> -6160.3765 | AQ43: =SUM(AM43:AP43) -> -30964.654
C44: Dep & Amortization | D44: =D143 -> 120 | E44: =E143 -> 176 | F44: =F143 -> 247 | G44: =G143 -> 260 | H44: =SUM(D44:G44) -> 803 | I44: =I143 -> 378 | J44: =J143 -> 421 | K44: =K143 -> 415 | L44: =L143 -> 410 | M44: =SUM(I44:L44) -> 1624 | N44: =N143 -> 424 | O44: 406 | P44: 424 | Q44: 420 | R44: =SUM(N44:Q44) -> 1674 | S44: =CF!S10 -> 455 | T44: =CF!T10 -> 700 | U44: =CF!U10 -> 924 | V44: =CF!V10 -> 895 | W44: =SUM(S44:V44) -> 2974 | X44: =CF!X10 -> 952 | Y44: =CF!Y10 -> 1005 | Z44: =CF!Z10 -> 1054 | AA44: =CF!AA10 -> 1148 | AB44: =SUM(X44:AA44) -> 4159 | AC44: =CF!AC10 -> 1075 | AD44: =CF!AD10 -> 1028 | AE44: =CF!AE10 -> 989 | AF44: =CF!AF10 -> 834 | AG44: =SUM(AC44:AF44) -> 3926 | AH44: =CF!AH10 -> 927 | AI44: =CF!AI10 -> 902 | AJ44: =CF!AJ10 -> 902 | AK44: =CF!AK10 -> 927 | AL44: =SUM(AH44:AK44) -> 3658 | AM44: =CF!AM10 -> 872.045 | AN44: =CF!AN10 -> 869.50982 | AO44: =CF!AO10 -> 878.7662 | AP44: =CF!AP10 -> 886.95808 | AQ44: =SUM(AM44:AP44) -> 3507.2791
C45: Provision for Income Taxes | D45: =D54 -> 3 | E45: =E54 -> 2 | F45: =F54 -> 2 | G45: =G54 -> 2 | H45: =SUM(D45:G45) -> 9 | I45: =I54 -> 25 | J45: =J54 -> 20 | K45: =K54 -> 13 | L45: =L54 -> 13 | M45: =SUM(I45:L45) -> 71 | N45: =N54 -> 36 | O45: =O54 -> 43 | P45: =P54 -> 31 | Q45: =Q54 -> -29 | R45: =SUM(N45:Q45) -> 81 | S45: =S54 -> 29 | T45: =T54 -> 44 | U45: =U54 -> 38 | V45: =V54 -> 75 | W45: =SUM(S45:V45) -> 186 | X45: =X54 -> 40 | Y45: =Y54 -> 57 | Z45: =Z54 -> 64 | AA45: 282 | AB45: =SUM(X45:AA45) -> 443 | AC45: =AC54 -> 86 | AD45: =AD54 -> 105 | AE45: =AE54 -> 118 | AF45: =AF54 -> 23 | AG45: =SUM(AC45:AF45) -> 332 | AH45: =AH54 -> 137 | AI45: =AI54 -> 210 | AJ45: =AJ54 -> 140 | AK45: =AK54 -> 256 | AL45: =SUM(AH45:AK45) -> 743 | AM45: =AM54 -> 150 | AN45: =AN54 -> 150 | AO45: =AO54 -> 150 | AP45: =AP54 -> 200 | AQ45: =SUM(AM45:AP45) -> 650
C46: Interest and Other, Net | D46: =-D40 -> -147 | E46: =-E40 -> -180 | F46: =-F40 -> -128 | G46: =-G40 -> -73 | H46: =SUM(D46:G46) -> -528 | I46: =-I40 -> 25 | J46: =-J40 -> 146 | K46: =-K40 -> 115 | L46: =-L40 -> 15 | M46: =SUM(I46:L46) -> 301 | N46: =-N40 -> 44 | O46: =-O40 -> 71 | P46: =-P40 -> 129 | Q46: =-Q40 -> 190 | R46: =SUM(N46:Q46) -> 434 | S46: =-S40 -> 63 | T46: =-T40 -> 171 | U46: =-U40 -> -50 | V46: =-V40 -> -1413 | W46: =SUM(S46:V46) -> -1229 | X46: =-X40 -> -1955 | Y46: =-Y40 -> -2133 | Z46: =-Z40 -> -1931 | AA46: =-AA40 -> -2119 | AB46: =SUM(X46:AA46) -> -8138 | AC46: =-AC40 -> -1836 | AD46: =-AD40 -> -1655 | AE46: =-AE40 -> -1837 | AF46: =-AF40 -> -953 | AG46: =SUM(AC46:AF46) -> -6281 | AH46: =-AH40 -> -1354 | AI46: =-AI40 -> -1208 | AJ46: =-AJ40 -> -937 | AK46: =-AK40 -> -996 | AL46: =SUM(AH46:AK46) -> -4495 | AM46: =-AM40 -> -971 | AN46: =-AN40 -> -946 | AO46: =-AO40 -> -916 | AP46: =-AP40 -> -866 | AQ46: =SUM(AM46:AP46) -> -3699
C47: Stock-based Compensation | D47: =D141 -> 2632 | E47: =E141 -> 534 | F47: =F141 -> 453 | G47: =G141 -> 501 | H47: =SUM(D47:G47) -> 4120 | I47: =I141 -> 488 | J47: =J141 -> 504 | K47: =K141 -> 506 | L47: =L141 -> 495 | M47: =SUM(I47:L47) -> 1993 | N47: =N141 -> 488 | O47: =O31 -> 966 | P47: =P31 -> 1054 | Q47: =Q31 -> 3095 | R47: =SUM(N47:Q47) -> 5603 | S47: =S31 -> 3206 | T47: =T31 -> 5522 | U47: =U31 -> 5665 | V47: =V31 -> 7344 | W47: =SUM(S47:V47) -> 21737 | X47: =X31 -> 7224 | Y47: =Y31 -> 6868 | Z47: =Z31 -> -2881 | AA47: =AA31 -> 4947 | AB47: =SUM(X47:AA47) -> 16158 | AC47: =AC31 -> 5673 | AD47: =AD31 -> 6058 | AE47: =AE31 -> 5147 | AF47: =AF31 -> 5391 | AG47: =SUM(AC47:AF47) -> 22269 | AH47: =AH31 -> 5879 | AI47: =AI31 -> 6478 | AJ47: =AJ31 -> 6090 | AK47: =AK31 -> 6017 | AL47: =SUM(AH47:AK47) -> 24464 | AM47: =AM31 -> 6000 | AN47: =AN31 -> 6000 | AO47: =AO31 -> 6000 | AP47: =AP31 -> 6000 | AQ47: =SUM(AM47:AP47) -> 24000
C48: Other | D48: =D125 -> 0 | E48: =E125 -> 0 | F48: =F125 -> 0 | G48: =G125 -> 0 | H48: =SUM(D48:G48) -> 0 | I48: =I125 -> 0 | J48: =J125 -> 0 | K48: =K125 -> -1057 | L48: =L125 -> 0 | M48: =SUM(I48:L48) -> -1057 | N48: =N125 -> 0 | Q48: 160 | R48: =SUM(N48:Q48) -> 160 | S48: 275 | T48: =+T32+135 -> 1319 | U48: =87+329 -> 416 | V48: =23+540 -> 563 | W48: =SUM(S48:V48) -> 2573 | X48: =1016+110 -> 1126 | Y48: =134+1574 -> 1708 | Z48: 175 | AA48: =51+500+74 -> 625 | AB48: =SUM(X48:AA48) -> 3634 | AC48: =193+199 -> 392 | AD48: =178+384 -> 562 | AE48: =95+143 -> 238 | AF48: =71+303+31+15213 -> 15618 | AG48: =SUM(AC48:AF48) -> 16810 | AH48: =150+565 -> 715 | AI48: =161+1581 -> 1742 | AJ48: =150+AJ32 -> 7173 | AK48: 139 | AL48: =SUM(AH48:AK48) -> 9769 | AQ48: =SUM(AM48:AP48) -> 0
B50: Adjusted EBITDA | D50: =SUM(D43:D48) -> -4344 | E50: =SUM(E43:E48) -> -6519 | F50: =SUM(F43:F48) -> -7087 | G50: =SUM(G43:G48) -> -7478 | H50: =SUM(H43:H48) -> -25428 | I50: =SUM(I43:I48) -> -10320 | J50: =SUM(J43:J48) -> -4386 | K50: =SUM(K43:K48) -> -3177 | ... N50: =SUM(N43:N48) -> -1936 | O50: =SUM(O43:O49) -> -1597 | P50: =SUM(P43:P49) -> -7587 | Q50: =SUM(Q43:Q49) -> -5272 | R50: =SUM(R43:R49) -> -16392 | S50: =SUM(S43:S49) -> -7821 | T50: =SUM(T43:T49) -> -12415 | U50: =SUM(U43:U49) -> -13065 | V50: =SUM(V43:V49) -> -11223 | ... AQ50: =SUM(AQ43:AQ49) -> -6506.3744
C51: EBITDA Margins | D51: =D50/D11 -> -0.41857776 | E51: =E50/E11 -> -0.5766475 | F51: =F50/F11 -> -0.56014859 | G51: =G50/G11 -> -0.52584206 | H51: =H50/H11 -> -0.52368399 | I51: =I50/I11 -> -0.65866735 | J51: =J50/J11 -> -0.27888345 | K51: =K50/K11 -> -0.17785366 | ... AQ51: =AQ50/AQ11 -> -0.037826727
B53: Non-GAAP Pre-Tax Income | D53: =D27+D40 -> -4317 | E53: =E27+E40 -> -6515 | F53: =F27+F40 -> -7206 | G53: =G27+G40 -> -7664 | H53: =H27+H40 -> -25702 | I53: =I27+I40 -> -10723 | J53: =J27+J40 -> -4953 | K53: =K27+K40 -> -3707 | ... AQ53: =AQ27+AQ40 -> -6314.6535
C54: Income Tax | D54: =D133 -> 3 | E54: =E133 -> 2 | F54: =F133 -> 2 | G54: =G133 -> 2 | H54: =H133 -> 9 | I54: =+I133 -> 25 | J54: =+J133 -> 20 | K54: =+K133 -> 13 | L54: =+L133 -> 13 | M54: =SUM(I54:L54) -> 71 | N54: =+N133 -> 36 | O54: 43 | P54: 31 | Q54: -29 | R54: =SUM(N54:Q54) -> 81 | S54: 29 | T54: 44 | U54: 38 | V54: 75 | W54: =SUM(S54:V54) -> 186 | X54: =X60 -> 40 | Y54: =Y60 -> 57 | Z54: =Z60 -> 64 | AA54: =AA60 -> 282 | AB54: =SUM(X54:AA54) -> 443 | AC54: 86 | AD54: 105 | AE54: =AE60 -> 118 | AF54: =AF60 -> 23 | AG54: =SUM(AC54:AF54) -> 332 | AH54: =AH60 -> 137 | AI54: =AI60 -> 210 | AJ54: =AJ60 -> 140 | AK54: =AK60 -> 256 | AL54: =SUM(AH54:AK54) -> 743 | AM54: 150 | AN54: 150 | AO54: 150 | AP54: 200 | AQ54: =SUM(AM54:AP54) -> 650
C55: Tax Rate % | D55: =D54/D53 -> -0.00069492703 | E55: =E54/E53 -> -0.00030698388 | F55: =F54/F53 -> -0.00027754649 | G55: =G54/G53 -> -0.00026096033 | H55: =H54/H53 -> -0.0003501673 | I55: =I54/I53 -> -0.0023314371 | J55: =J54/J53 -> -0.0040379568 | K55: =K54/K53 -> -0.0035068789 | ... AQ55: =AQ54/AQ53 -> -0.10293518
B56: Non-GAAP Net Income | D56: =D53-D54 -> -4320 | E56: =E53-E54 -> -6517 | F56: =F53-F54 -> -7208 | G56: =G53-G54 -> -7666 | H56: =H53-H54 -> -25711 | I56: =I53-I54 -> -10748 | J56: =J53-J54 -> -4973 | K56: =K53-K54 -> -3720 | ... AQ56: =AQ53-AQ54 -> -6964.6535
C57: Non-GAAP Net Margin | D57: =D56/D11 -> -0.41626518 | E57: =E56/E11 -> -0.57647059 | F57: =F56/F11 -> -0.5697123 | G57: =G56/G11 -> -0.53906195 | H57: =H56/H11 -> -0.52951232 | I57: =I56/I11 -> -0.68598417 | J57: =J56/J11 -> -0.3162078 | K57: =K56/K11 -> -0.20825169 | ... AQ57: =AQ56/AQ11 -> -0.040491068
B59: GAAP Pre-Tax Income | D59: =D35+D40 -> -6949 | E59: =E35+E40 -> -7049 | F59: =F35+F40 -> -7659 | G59: =G35+G40 -> -8165 | H59: =H35+H40 -> -29822 | I59: =I35+I40 -> -11211 | J59: =J35+J40 -> -5457 | K59: =K35+K40 -> -3156 | ... AQ59: =AQ35+AQ40 -> -30314.654
C60: Income Tax | D60: =D54 -> 3 | E60: =E54 -> 2 | F60: =F54 -> 2 | G60: 3 | H60: =SUM(D60:G60) -> 10 | I60: =I54 -> 25 | J60: =J54 -> 20 | K60: =K54 -> 13 | L60: =L54 -> 13 | M60: =SUM(I60:L60) -> 71 | N60: =N54 -> 36 | O60: 43 | P60: =P54 -> 31 | Q60: =Q54 -> -29 | R60: =SUM(N60:Q60) -> 81 | S60: =S54 -> 29 | T60: =T54 -> 44 | U60: 38 | V60: =V54 -> 75 | W60: =SUM(S60:V60) -> 186 | X60: 40 | Y60: 57 | Z60: 64 | AA60: 282 | AB60: =SUM(X60:AA60) -> 443 | AC60: 86 | AD60: 105 | AE60: 118 | AF60: 23 | AG60: =SUM(AC60:AF60) -> 332 | AH60: 137 | AI60: 210 | AJ60: 140 | AK60: 256 | AL60: =SUM(AH60:AK60) -> 743 | AM60: =AM54 -> 150 | AN60: =AN54 -> 150 | AO60: =AO54 -> 150 | AP60: =AP54 -> 200 | AQ60: =SUM(AM60:AP60) -> 650
C61: Tax Rate % | D61: =D60/D59 -> -0.00043171679 | E61: =E60/E59 -> -0.00028372819 | F61: =F60/F59 -> -0.0002611307 | G61: =G60/G59 -> -0.00036742192 | H61: =H60/H59 -> -0.00033532292 | I61: =I60/I59 -> -0.0022299527 | J61: =J60/J59 -> -0.0036650174 | K61: =K60/K59 -> -0.0041191381 | ... AQ61: =AQ60/AQ59 -> -0.021441776
B62: GAAP Net Income | D62: =D59-D60 -> -6952 | E62: =E59-E60 -> -7051 | F62: =F59-F60 -> -7661 | G62: =G59-G60 -> -8168 | H62: =H59-H60 -> -29832 | I62: =I59-I60 -> -11236 | J62: =J59-J60 -> -5477 | K62: =K59-K60 -> -3169 | ... AQ62: =AQ59-AQ60 -> -30964.654
C63: GAAP Net Margin | D63: =D62/D11 -> -0.66987859 | E63: =E62/E11 -> -0.62370632 | F63: =F62/F11 -> -0.60551691 | G63: =G62/G11 -> -0.57436186 | H63: =H62/H11 -> -0.61438339 | I63: =I62/I11 -> -0.71713046 | J63: =J62/J11 -> -0.34825459 | K63: =K62/K11 -> -0.17740581 | ... AQ63: =AQ62/AQ11 -> -0.18002215
B65: Non-GAAP EPS | H65: =H56/H70 -> -0.39799694 | I65: =IF(I56>0,I56/I71,I56/I70) -> -0.16410162 | J65: =IF(J56>0,J56/J71,J56/J70) -> -0.37901075 | K65: =IF(K56>0,K56/K71,K56/K70) -> -0.282203 | L65: =IF(L56>0,L56/L71,L56/L70) -> -0.18793766 | M65: =+M56/M70 -> -0.33824164 | N65: =IF(N56>0,N56/N71,N56/N70) -> -0.036450553 | O65: =IF(O56>0,O56/O71,O56/O70) -> -0.15525081 | P65: =IF(P56>0,P56/P71,P56/P70) -> -0.17125671 | Q65: =IF(Q56>0,Q56/Q71,Q56/Q70) -> -0.1046631 | R65: =IF(R56>0,R56/R71,R56/R70) -> -0.4035986 | S65: =IF(S56>0,S56/S71,S56/S70) -> -0.14908922 | T65: =IF(T56>0,T56/T71,T56/T70) -> -0.23078637 | U65: =IF(U56>0,U56/U71,U56/U70) -> -0.2398322 | ... AQ65: =IF(AQ56>0,AQ56/AQ71,AQ56/AQ70) -> -0.10804509
C66: Y/Y Growth % | M66: =M65/H65-1 -> -0.15014008 | N66: =N65/I65-1 -> -0.77787817 | O66: =O65/J65-1 -> -0.59037888 | P66: =P65/K65-1 -> -0.39314357 | Q66: =Q65/L65-1 -> -0.44309668 | R66: =R65/M65-1 -> 0.19322563 | S66: =S65/N65-1 -> 3.0901771 | T66: =T65/O65-1 -> 0.48653895 | ... AQ66: =AQ65/AL65-1 -> -0.3792941
B67: GAAP EPS | H67: =+H62/H71 -> -0.46178852 | I67: =I62/I70 -> -0.17155246 | J67: =J62/J70 -> -0.41742245 | K67: =K62/K70 -> -0.24040358 | L67: =L62/L70 -> -0.22520895 | M67: =+M62/M70 -> -0.35267362 | N67: =N62/N70 -> -0.043740663 | O67: =O62/O70 -> -0.2260927 | P67: =P62/P71 -> -0.19334759 | Q67: =Q62/Q71 -> -0.1585351 | R67: =R62/R71 -> -0.52426254 | S67: =S62/S71 -> -0.20439178 | T67: =T62/T71 -> -0.34572535 | U67: =U62/U71 -> -0.34204737 | V67: =V62/V71 -> -0.3162143 | W67: =W62/W71 -> -1.2093842 | ... AQ67: =AQ62/AQ71 -> -0.48036542
C68: Y/Y Growth % | M68: =M67/H67-1 -> -0.2362876 | N68: =N67/I67-1 -> -0.74503039 | O68: =O67/J67-1 -> -0.45836 | P68: =P67/K67-1 -> -0.1957375 | Q68: =Q67/L67-1 -> -0.29605327 | R68: =R67/M67-1 -> 0.48653746 | S68: =S67/N67-1 -> 3.6728092 | T68: =T67/O67-1 -> 0.52913101 | ... AQ68: =AQ67/AL67-1 -> -0.33210619
B70: Basic Shares Outstanding | H70: 64601 | I70: 65496 | J70: 13121 | K70: 13182 | L70: 13281 | M70: 64856 | N70: 66940 | O70: 13636 | P70: 47712 | Q70: 57451 | R70: =AVERAGE(N70:Q70) -> 46434.75 | S70: 57972 | T70: 58344 | U70: 58641 | V70: 59096 | W70: =AVERAGE(S70:V70) -> 58513.25 | X70: 59410 | Y70: 59856 | Z70: 60350 | AA70: 60810 | AB70: =AVERAGE(X70:AA70) -> 60106.5 | AC70: 61188 | AD70: 59815 | AE70: 59675 | AF70: 60102 | AG70: =AVERAGE(AC70:AF70) -> 60195 | AH70: 60565 | AI70: 61245 | AJ70: 62094 | AK70: 62873 | AL70: =AVERAGE(AH70:AK70) -> 61694.25 | AM70: =+AK70*1.01 -> 63501.73 | AN70: =+AM70*1.01 -> 64136.747 | AO70: =+AN70*1.01 -> 64778.115 | AP70: =+AO70*1.01 -> 65425.896 | AQ70: =AVERAGE(AM70:AP70) -> 64460.622
B71: Diluted Shares Outstanding | H71: 64601 | I71: 65496 | J71: 13121 | K71: 13182 | L71: 13281 | M71: 65856 | N71: 66940 | O71: 13636 | P71: 47712 | Q71: 57451 | R71: =AVERAGE(N71:Q71) -> 46434.75 | S71: 57972 | T71: 58344 | U71: 58641 | V71: 59096 | W71: =AVERAGE(S71:V71) -> 58513.25 | X71: 59410 | Y71: 59856 | Z71: 60350 | AA71: 60810 | AB71: =AVERAGE(X71:AA71) -> 60106.5 | AC71: 61188 | AD71: 59815 | AE71: 59675 | AF71: 60102 | AG71: =AVERAGE(AC71:AF71) -> 60195 | AH71: 60565 | AI71: 61245 | AJ71: 62094 | AK71: 62873 | AL71: =AVERAGE(AH71:AK71) -> 61694.25 | AM71: =+AK71*1.01 -> 63501.73 | AN71: =+AM71*1.01 -> 64136.747 | AO71: =+AN71*1.01 -> 64778.115 | AP71: =+AO71*1.01 -> 65425.896 | AQ71: =AVERAGE(AM71:AP71) -> 64460.622
B73: Deferred Revenue | D73: =BS!D45 -> 801 | E73: =BS!E45 -> 681 | F73: =BS!F45 -> 646 | G73: =BS!G45 -> 1418 | I73: =BS!I45 -> 1537 | J73: =BS!J45 -> 1339 | K73: =BS!K45 -> 1101 | L73: =BS!L45 -> 1642 | N73: =BS!N45 -> 2752 | O73: =BS!O45 -> 1489 | P73: =BS!P45 -> 1575 | Q73: =BS!Q45 -> 2175 | S73: =BS!S45 -> 3035 | T73: =BS!T45 -> 2690 | U73: =BS!U45 -> 2741 | V73: =BS!V45 -> 4100 | X73: =BS!X45 -> 4169 | Y73: =BS!Y45 -> 3310 | Z73: =BS!Z45 -> 2966 | AA73: =BS!AA45 -> 4285 | AC73: =BS!AC45 -> 3501 | AD73: =BS!AD45 -> 3518 | AE73: =BS!AE45 -> 3042 | AF73: =BS!AF45 -> 4296 | AH73: =BS!AH45 -> 3905 | AI73: =BS!AI45 -> 3493 | AJ73: =BS!AJ45 -> 4272 | AK73: =BS!AK45 -> 5382
B74: Cash Flow-Operating | D74: =CF!D25 -> -9354 | E74: =CF!E25 -> -2893 | F74: =CF!F25 -> -6152 | G74: =CF!G25 -> -8900 | H74: =CF!H25 -> -27299 | I74: =CF!I25 -> -10114 | J74: =CF!J25 -> -5000 | K74: =CF!K25 -> -2585 | ... AK74: =CF!AK25 -> 762
B75: Gross Cash
B76: Net Cash | D76: =BS!D6 -> 43786 | E76: =BS!E6 -> 40307 | F76: =BS!F6 -> 33348 | G76: =BS!G6 -> 23224 | I76: =BS!I6 -> 29398 | J76: =BS!J6 -> 24022 | K76: =BS!K6 -> 78188 | L76: =BS!L6 -> 58569 | N76: =BS!N6 -> 53632 | O76: =BS!O6 -> 47026 | P76: =BS!P6 -> 258478 | Q76: =BS!Q6 -> 255477 | S76: =BS!S6 -> 238576 | T76: =BS!T6 -> 228187 | U76: =BS!U6 -> 213122 | V76: =BS!V6 -> 203244 | X76: =BS!X6 -> 187635 | Y76: =BS!Y6 -> 178919 | Z76: =BS!Z6 -> 157652 | AA76: =BS!AA6 -> 159551 | AC76: =BS!AC6 -> 148679 | AD76: =BS!AD6 -> 130005 | AE76: =BS!AE6 -> 126794 | AF76: =BS!AF6 -> 129127 | AH76: =BS!AH6 -> 118811 | AI76: =BS!AI6 -> 114344 | AJ76: =BS!AJ6 -> 113486 | AK76: =BS!AK6 -> 114597
B77: Cash/Share | I77: =I76/I70 -> 0.44885184 | N77: =N76/N70 -> 0.8011951 | O77: =O76/O70 -> 3.4486653 | P77: =P76/P70 -> 5.4174631 | Q77: =Q76/Q70 -> 4.4468678 | S77: =S76/S70 -> 4.115366 | T77: =T76/T70 -> 3.911062 | U77: =U76/U70 -> 3.6343514 | V77: =V76/V70 -> 3.4392175 | X77: =X76/X70 -> 3.1583067 | Y77: =Y76/Y70 -> 2.9891573 | Z77: =Z76/Z70 -> 2.6122949 | AA77: =AA76/AA70 -> 2.6237625 | AC77: =AC76/AC70 -> 2.4298719 | AD77: =AD76/AD70 -> 2.1734515 | AE77: =AE76/AE70 -> 2.1247424 | AF77: =AF76/AF70 -> 2.1484643 | AH77: =AH76/AH70 -> 1.9617106 | AI77: =AI76/AI70 -> 1.8669932 | AJ77: =AJ76/AJ70 -> 1.8276484 | AK77: =AK76/AK70 -> 1.8226743
B78: Scott Berg, sberg@needhamco.com | AL78: Source: Company Reports and Needham & Company, LLC Estimates | AQ78: Source: Company Reports and Needham & Company, LLC Estimates
B79: 763.350.4027 | AL79: $ in thousands, except per share data | AQ79: $ in thousands, except per share data
D81: 2019 Billings | I81: 2020 Billings | N81: 2021 Billings | S81: 2022 Billings | X81: =AB4 &" Billings" -> 2023 Billings | AC81: =AG4 &" Billings" -> 2024 Billings | AH81: =AL4 &" Billings" -> 2025 Billings | AM81: =AQ4 &" Billings" -> 2026E Billings
D82: =D4 -> 1Q19 | E82: =E4 -> 2Q19 | F82: =F4 -> 3Q19 | G82: =G4 -> 4Q19 | H82: =H4 -> 2019 | I82: =I4 -> 1Q20 | J82: =J4 -> 2Q20 | K82: =K4 -> 3Q20 | ... AQ82: =AQ4 -> 2026E
C83: Revenue | D83: =D11 -> 10378 | E83: =E11 -> 11305 | F83: =F11 -> 12652 | G83: =G11 -> 14221 | I83: =I11 -> 15668 | J83: =J11 -> 15727 | K83: =K11 -> 17863 | L83: =L11 -> 19186 | N83: =N11 -> 21131 | O83: =O11 -> 29547 | P83: =P11 -> 29854 | Q83: =Q11 -> 33810 | S83: =S11 -> 34468 | T83: =T11 -> 33710 | U83: =U11 -> 34475 | V83: =V11 -> 32537 | X83: =X11 -> 33129 | Y83: =Y11 -> 34276 | Z83: =Z11 -> 34943 | AA83: =AA11 -> 35742 | AC83: =AC11 -> 35571 | AD83: =AD11 -> 36005 | AE83: =AE11 -> 36266 | AF83: =AF11 -> 36999 | AH83: =AH11 -> 36653 | AI83: =AI11 -> 38106 | AJ83: =AJ11 -> 40919 | AK83: =AK11 -> 41171 | AM83: =AM11 -> 39749.896 | AN83: =AN11 -> 42303.38 | AO83: =AO11 -> 44041.606 | AP83: =AP11 -> 45909.808
C84: Change In Deferred Revenue | D84: =+CF!D22 -> -30 | E84: =+CF!E22 -> -120 | F84: =+CF!F22 -> -35 | G84: =+CF!G22 -> 772 | I84: =+CF!I22 -> 119 | J84: =+CF!J22 -> -198 | K84: =+CF!K22 -> -238 | L84: =+CF!L22 -> 541 | N84: =+CF!N22 -> 1110 | O84: =BS!O45-BS!N45 -> -1263 | P84: =BS!P45-BS!O45 -> 86 | Q84: =BS!Q45-BS!P45 -> 600 | S84: =BS!S45-BS!Q45 -> 860 | T84: =BS!T45-BS!S45 -> -345 | U84: =BS!U45-BS!T45 -> 51 | V84: =BS!V45-BS!U45 -> 1359 | X84: =BS!X45-BS!V45 -> 69 | Y84: =BS!Y45-BS!X45 -> -859 | Z84: =BS!Z45-BS!Y45 -> -344 | AA84: =BS!AA45-BS!Z45 -> 1319 | AC84: =BS!AC45-BS!AA45 -> -784 | AD84: =BS!AD45-BS!AC45 -> 17 | AE84: =BS!AE45-BS!AD45 -> -476 | AF84: =BS!AF45-BS!AE45 -> 1254 | AH84: =BS!AH45-BS!AF45 -> -391 | AI84: =BS!AI45-BS!AH45 -> -412 | AJ84: =BS!AJ45-BS!AI45 -> 779 | AK84: =BS!AK45-BS!AJ45 -> 1110 | AM84: =BS!AM45-BS!AK45 -> -1407.0104 | AN84: =BS!AN45-BS!AM45 -> 255.3484 | AO84: =BS!AO45-BS!AN45 -> 173.8226 | AP84: =BS!AP45-BS!AO45 -> 645.91828
C85: Billings | D85: =D84+D83 -> 10348 | E85: =E84+E83 -> 11185 | F85: =F84+F83 -> 12617 | G85: =G84+G83 -> 14993 | H85: =SUM(D85:G85) -> 49143 | I85: =I84+I83 -> 15787 | J85: =J84+J83 -> 15529 | K85: =K84+K83 -> 17625 | L85: =L84+L83 -> 19727 | M85: =SUM(I85:L85) -> 68668 | N85: =N84+N83 -> 22241 | O85: =O84+O83 -> 28284 | P85: =P84+P83 -> 29940 | Q85: =Q84+Q83 -> 34410 | R85: =SUM(N85:Q85) -> 114875 | S85: =S84+S83 -> 35328 | T85: =T84+T83 -> 33365 | U85: =U84+U83 -> 34526 | V85: =V84+V83 -> 33896 | W85: =SUM(S85:V85) -> 137115 | X85: =X84+X83 -> 33198 | Y85: =Y84+Y83 -> 33417 | Z85: =Z84+Z83 -> 34599 | AA85: =AA84+AA83 -> 37061 | AB85: =SUM(X85:AA85) -> 138275 | AC85: =AC84+AC83 -> 34787 | AD85: =AD84+AD83 -> 36022 | AE85: =AE84+AE83 -> 35790 | AF85: =AF84+AF83 -> 38253 | AG85: =SUM(AC85:AF85) -> 144852 | AH85: =AH84+AH83 -> 36262 | AI85: =AI84+AI83 -> 37694 | AJ85: =AJ84+AJ83 -> 41698 | AK85: =AK84+AK83 -> 42281 | AL85: =SUM(AH85:AK85) -> 157935 | AM85: =AM84+AM83 -> 38342.886 | AN85: =AN84+AN83 -> 42558.728 | AO85: =AO84+AO83 -> 44215.429 | AP85: =AP84+AP83 -> 46555.726 | AQ85: =SUM(AM85:AP85) -> 171672.77
C86: % change y/y | I86: =I85/D85-1 -> 0.52560881 | J86: =J85/E85-1 -> 0.38837729 | K86: =K85/F85-1 -> 0.39692478 | L86: =L85/G85-1 -> 0.31574735 | M86: =M85/H85-1 -> 0.39730989 | N86: =N85/I85-1 -> 0.40881738 | O86: =O85/J85-1 -> 0.82136648 | P86: =P85/K85-1 -> 0.6987234 | ... AQ86: =AQ85/AL85-1 -> 0.086983689
C87: % change q/q | E87: =E85/D85-1 -> 0.080885195 | F87: =F85/E85-1 -> 0.12802861 | G87: =G85/F85-1 -> 0.18831735 | I87: =I85/G85-1 -> 0.052958047 | J87: =J85/I85-1 -> -0.01634256 | K87: =K85/J85-1 -> 0.13497328 | L87: =L85/K85-1 -> 0.11926241 | N87: =N85/L85-1 -> 0.12743955 | O87: =O85/N85-1 -> 0.27170541 | P87: =P85/O85-1 -> 0.058549003 | Q87: =Q85/P85-1 -> 0.1492986 | S87: =S85/Q85-1 -> 0.026678291 | T87: =T85/S85-1 -> -0.055564991 | U87: =U85/T85-1 -> 0.034796943 | V87: =V85/U85-1 -> -0.018247118 | X87: =X85/V85-1 -> -0.0205924 | Y87: =Y85/X85-1 -> 0.0065967829 | Z87: =Z85/Y85-1 -> 0.035371218 | AA87: =AA85/Z85-1 -> 0.071158126 | AC87: =AC85/AA85-1 -> -0.061358301 | AD87: =AD85/AC85-1 -> 0.035501768 | AE87: =AE85/AD85-1 -> -0.0064405086 | AF87: =AF85/AE85-1 -> 0.068818106 | AH87: =AH85/AF85-1 -> -0.052048205 | AI87: =AI85/AH85-1 -> 0.039490376 | AJ87: =AJ85/AI85-1 -> 0.1062238 | AK87: =AK85/AJ85-1 -> 0.013981486 | AM87: =AM85/AK85-1 -> -0.093141468 | AN87: =AN85/AM85-1 -> 0.10995111 | AO87: =AO85/AN85-1 -> 0.03892739 | AP87: =AP85/AO85-1 -> 0.052929436
C89: Revenue | D89: =#REF! -> #REF! | E89: =#REF! -> #REF! | F89: =#REF! -> #REF! | G89: =#REF! -> #REF! | I89: =#REF! -> #REF! | J89: =#REF! -> #REF! | K89: =#REF! -> #REF! | L89: =#REF! -> #REF! | N89: =#REF! -> #REF! | O89: =#REF! -> #REF! | P89: =#REF! -> #REF! | Q89: =#REF! -> #REF! | S89: =#REF! -> #REF! | T89: =#REF! -> #REF! | U89: =#REF! -> #REF! | V89: =#REF! -> #REF! | X89: =#REF! -> #REF! | Y89: =#REF! -> #REF! | Z89: =#REF! -> #REF! | AA89: =#REF! -> #REF! | AC89: =#REF! -> #REF! | AD89: =#REF! -> #REF! | AE89: =#REF! -> #REF! | AF89: =#REF! -> #REF! | AH89: =#REF! -> #REF! | AI89: =#REF! -> #REF! | AJ89: =#REF! -> #REF! | AK89: =#REF! -> #REF! | AM89: =#REF! -> #REF! | AN89: =#REF! -> #REF! | AO89: =#REF! -> #REF! | AP89: =#REF! -> #REF!
C90: LTM Revenue | D90: =D89+#REF!+#REF!+#REF! -> #REF! | E90: =E89+D89+#REF!+#REF! -> #REF! | F90: =F89+E89+D89+#REF! -> #REF! | G90: =G89+F89+E89+D89 -> #REF! | I90: =I89+G89+F89+E89 -> #REF! | J90: =J89+I89+G89+F89 -> #REF! | K90: =K89+J89+I89+G89 -> #REF! | L90: =L89+K89+J89+I89 -> #REF! | N90: =N89+L89+K89+J89 -> #REF! | O90: =O89+N89+L89+K89 -> #REF! | P90: =P89+O89+N89+L89 -> #REF! | Q90: =Q89+P89+O89+N89 -> #REF! | S90: =S89+Q89+P89+O89 -> #REF! | T90: =T89+S89+Q89+P89 -> #REF! | U90: =U89+T89+S89+Q89 -> #REF! | V90: =V89+U89+T89+S89 -> #REF! | X90: =X89+V89+U89+T89 -> #REF! | Y90: =Y89+X89+V89+U89 -> #REF! | Z90: =Z89+Y89+X89+V89 -> #REF! | AA90: =AA89+Z89+Y89+X89 -> #REF! | AC90: =AC89+AA89+Z89+Y89 -> #REF! | AD90: =AD89+AC89+AA89+Z89 -> #REF! | AE90: =AE89+AD89+AC89+AA89 -> #REF! | AF90: =AF89+AE89+AD89+AC89 -> #REF! | AH90: =AH89+AF89+AE89+AD89 -> #REF! | AI90: =AI89+AH89+AF89+AE89 -> #REF! | AJ90: =AJ89+AI89+AH89+AF89 -> #REF! | AK90: =AK89+AJ89+AI89+AH89 -> #REF! | AM90: =AM89+AK89+AJ89+AI89 -> #REF! | AN90: =AN89+AM89+AK89+AJ89 -> #REF! | AO90: =AO89+AN89+AM89+AK89 -> #REF! | AP90: =AP89+AO89+AN89+AM89 -> #REF!
C91: Y/Y Change in LTM Revenes | D91: =D90-#REF! -> #REF! | E91: =E90-#REF! -> #REF! | F91: =F90-#REF! -> #REF! | G91: =G90-#REF! -> #REF! | I91: =I90-D90 -> #REF! | J91: =J90-E90 -> #REF! | K91: =K90-F90 -> #REF! | L91: =L90-G90 -> #REF! | N91: =N90-I90 -> #REF! | O91: =O90-J90 -> #REF! | P91: =P90-K90 -> #REF! | Q91: =Q90-L90 -> #REF! | S91: =S90-N90 -> #REF! | T91: =T90-O90 -> #REF! | U91: =U90-P90 -> #REF! | V91: =V90-Q90 -> #REF! | X91: =X90-S90 -> #REF! | Y91: =Y90-T90 -> #REF! | Z91: =Z90-U90 -> #REF! | AA91: =AA90-V90 -> #REF! | AC91: =AC90-X90 -> #REF! | AD91: =AD90-Y90 -> #REF! | AE91: =AE90-Z90 -> #REF! | AF91: =AF90-AA90 -> #REF! | AH91: =AH90-AC90 -> #REF! | AI91: =AI90-AD90 -> #REF! | AJ91: =AJ90-AE90 -> #REF! | AK91: =AK90-AF90 -> #REF! | AM91: =AM90-AH90 -> #REF! | AN91: =AN90-AI90 -> #REF! | AO91: =AO90-AJ90 -> #REF! | AP91: =AP90-AK90 -> #REF!
C92: Retention Rate | X92: 0.83 | Y92: 0.83 | Z92: 0.83 | AA92: 0.83 | AC92: 0.83 | AD92: 0.83 | AE92: 0.83 | AF92: 0.83 | AH92: 0.83 | AI92: 0.83 | AJ92: 0.83 | AK92: 0.83 | AM92: 0.83 | AN92: 0.83 | AO92: 0.83 | AP92: 0.83
C93: NTM Revenue Retention | D93: =D92*D90 -> #REF! | E93: =E92*E90 -> #REF! | F93: =F92*F90 -> #REF! | G93: =G92*G90 -> #REF! | I93: N/A | J93: N/A | K93: N/A | L93: N/A | N93: N/A | O93: N/A | P93: N/A | Q93: N/A | S93: =S92*S90 -> #REF! | T93: =T92*T90 -> #REF! | U93: =U92*U90 -> #REF! | V93: =V92*V90 -> #REF! | X93: =X92*X90 -> #REF! | Y93: =Y92*Y90 -> #REF! | Z93: =Z92*Z90 -> #REF! | AA93: =AA92*AA90 -> #REF! | AC93: =AC92*AC90 -> #REF! | AD93: =AD92*AD90 -> #REF! | AE93: =AE92*AE90 -> #REF! | AF93: =AF92*AF90 -> #REF! | AH93: =AH92*AH90 -> #REF! | AI93: =AI92*AI90 -> #REF! | AJ93: =AJ92*AJ90 -> #REF! | AK93: =AK92*AK90 -> #REF! | AM93: =AM92*AM90 -> #REF! | AN93: =AN92*AN90 -> #REF! | AO93: =AO92*AO90 -> #REF! | AP93: =AP92*AP90 -> #REF!
C94: NTM Gross New Revenue Churn | D94: =D90-D93 -> #REF! | E94: =E90-E93 -> #REF! | F94: =F90-F93 -> #REF! | G94: =G90-G93 -> #REF! | I94: =I90-I93 -> #REF! | J94: =J90-J93 -> #REF! | K94: =K90-K93 -> #REF! | L94: =L90-L93 -> #REF! | N94: =N90-N93 -> #REF! | O94: =O90-O93 -> #REF! | P94: =P90-P93 -> #REF! | Q94: =Q90-Q93 -> #REF! | S94: =S90-S93 -> #REF! | T94: =T90-T93 -> #REF! | U94: =U90-U93 -> #REF! | V94: =V90-V93 -> #REF! | X94: =X90-X93 -> #REF! | Y94: =Y90-Y93 -> #REF! | Z94: =Z90-Z93 -> #REF! | AA94: =AA90-AA93 -> #REF! | AC94: =AC90-AC93 -> #REF! | AD94: =AD90-AD93 -> #REF! | AE94: =AE90-AE93 -> #REF! | AF94: =AF90-AF93 -> #REF! | AH94: =AH90-AH93 -> #REF! | AI94: =AI90-AI93 -> #REF! | AJ94: =AJ90-AJ93 -> #REF! | AK94: =AK90-AK93 -> #REF! | AM94: =AM90-AM93 -> #REF! | AN94: =AN90-AN93 -> #REF! | AO94: =AO90-AO93 -> #REF! | AP94: =AP90-AP93 -> #REF!
C95: LTM Gross New Suscription Revv | D95: =D91+#REF! -> #REF! | E95: =E91+#REF! -> #REF! | F95: =F91+#REF! -> #REF! | G95: =G91+#REF! -> #REF! | I95: =I91+D94 -> #REF! | J95: =J91+E94 -> #REF! | K95: =K91+F94 -> #REF! | L95: =L91+G94 -> #REF! | N95: =N91+I94 -> #REF! | O95: =O91+J94 -> #REF! | P95: =P91+K94 -> #REF! | Q95: =Q91+L94 -> #REF! | S95: =S91+N94 -> #REF! | T95: =T91+O94 -> #REF! | U95: =U91+P94 -> #REF! | V95: =V91+Q94 -> #REF! | X95: =X91+S94 -> #REF! | Y95: =Y91+T94 -> #REF! | Z95: =Z91+U94 -> #REF! | AA95: =AA91+V94 -> #REF! | AC95: =AC91+X94 -> #REF! | AD95: =AD91+Y94 -> #REF! | AE95: =AE91+Z94 -> #REF! | AF95: =AF91+AA94 -> #REF! | AH95: =AH91+AC94 -> #REF! | AI95: =AI91+AD94 -> #REF! | AJ95: =AJ91+AE94 -> #REF! | AK95: =AK91+AF94 -> #REF! | AM95: =AM91+AH94 -> #REF! | AN95: =AN91+AI94 -> #REF! | AO95: =AO91+AJ94 -> #REF! | AP95: =AP91+AK94 -> #REF!
C97: Short Term Deferred Revenue | D97: =BS!D25 -> 801 | E97: =BS!E25 -> 681 | F97: =BS!F25 -> 646 | G97: =BS!G25 -> 1418 | I97: =BS!I25 -> 1537 | J97: =BS!J25 -> 1339 | K97: =BS!K25 -> 1101 | L97: =BS!L25 -> 1642 | N97: =BS!N25 -> 2752 | O97: =BS!#REF! -> #REF! | P97: =BS!#REF! -> #REF! | Q97: =BS!#REF! -> #REF! | S97: =BS!#REF! -> #REF! | T97: =BS!#REF! -> #REF! | U97: =BS!#REF! -> #REF! | V97: =BS!#REF! -> #REF! | X97: =BS!#REF! -> #REF! | Y97: =BS!#REF! -> #REF! | Z97: =BS!#REF! -> #REF! | AA97: =BS!#REF! -> #REF! | AC97: =BS!#REF! -> #REF! | AD97: =BS!#REF! -> #REF! | AE97: =BS!#REF! -> #REF! | AF97: =BS!#REF! -> #REF! | AH97: =BS!#REF! -> #REF! | AI97: =BS!#REF! -> #REF! | AJ97: =BS!#REF! -> #REF! | AK97: =BS!#REF! -> #REF! | AM97: =BS!#REF! -> #REF! | AN97: =BS!#REF! -> #REF! | AO97: =BS!#REF! -> #REF! | AP97: =BS!#REF! -> #REF!
C98: Y/Y Change Short Term Deferred Rev | D98: =D97-#REF! -> #REF! | E98: =E97-#REF! -> #REF! | F98: =F97-#REF! -> #REF! | G98: =G97-#REF! -> #REF! | I98: =I97-D97 -> 736 | J98: =J97-E97 -> 658 | K98: =K97-F97 -> 455 | L98: =L97-G97 -> 224 | N98: =N97-I97 -> 1215 | O98: =O97-J97 -> #REF! | P98: =P97-K97 -> #REF! | Q98: =Q97-L97 -> #REF! | S98: =S97-N97 -> #REF! | T98: =T97-O97 -> #REF! | U98: =U97-P97 -> #REF! | V98: =V97-Q97 -> #REF! | X98: =X97-S97 -> #REF! | Y98: =Y97-T97 -> #REF! | Z98: =Z97-U97 -> #REF! | AA98: =AA97-V97 -> #REF! | AC98: =AC97-X97 -> #REF! | AD98: =AD97-Y97 -> #REF! | AE98: =AE97-Z97 -> #REF! | AF98: =AF97-AA97 -> #REF! | AH98: =AH97-AC97 -> #REF! | AI98: =AI97-AD97 -> #REF! | AJ98: =AJ97-AE97 -> #REF! | AK98: =AK97-AF97 -> #REF! | AM98: =AM97-AH97 -> #REF! | AN98: =AN97-AI97 -> #REF! | AO98: =AO97-AJ97 -> #REF! | AP98: =AP97-AK97 -> #REF!
C99: Change in Y/Y Short Term Deferred | D99: =D98-#REF! -> #REF! | E99: =E98-#REF! -> #REF! | F99: =F98-#REF! -> #REF! | G99: =G98-#REF! -> #REF! | I99: =I98-D98 -> #REF! | J99: =J98-E98 -> #REF! | K99: =K98-F98 -> #REF! | L99: =L98-G98 -> #REF! | N99: =N98-I98 -> 479 | O99: =O98-J98 -> #REF! | P99: =P98-K98 -> #REF! | Q99: =Q98-L98 -> #REF! | S99: =S98-N98 -> #REF! | T99: =T98-O98 -> #REF! | U99: =U98-P98 -> #REF! | V99: =V98-Q98 -> #REF! | X99: =X98-S98 -> #REF! | Y99: =Y98-T98 -> #REF! | Z99: =Z98-U98 -> #REF! | AA99: =AA98-V98 -> #REF! | AC99: =AC98-X98 -> #REF! | AD99: =AD98-Y98 -> #REF! | AE99: =AE98-Z98 -> #REF! | AF99: =AF98-AA98 -> #REF! | AH99: =AH98-AC98 -> #REF! | AI99: =AI98-AD98 -> #REF! | AJ99: =AJ98-AE98 -> #REF! | AK99: =AK98-AF98 -> #REF! | AM99: =AM98-AH98 -> #REF! | AN99: =AN98-AI98 -> #REF! | AO99: =AO98-AJ98 -> #REF! | AP99: =AP98-AK98 -> #REF!
C100: Gross New Billings | D100: =D99+D95 -> #REF! | E100: =E99+E95 -> #REF! | F100: =F99+F95 -> #REF! | G100: =G99+G95 -> #REF! | I100: =I99+I95 -> #REF! | J100: =J99+J95 -> #REF! | K100: =K99+K95 -> #REF! | L100: =L99+L95 -> #REF! | N100: =N99+N95 -> #REF! | O100: =O99+O95 -> #REF! | P100: =P99+P95 -> #REF! | Q100: =Q99+Q95 -> #REF! | S100: =S99+S95 -> #REF! | T100: =T99+T95 -> #REF! | U100: =U99+U95 -> #REF! | V100: =V99+V95 -> #REF! | X100: =X99+X95 -> #REF! | Y100: =Y99+Y95 -> #REF! | Z100: =Z99+Z95 -> #REF! | AA100: =AA99+AA95 -> #REF! | AC100: =AC99+AC95 -> #REF! | AD100: =AD99+AD95 -> #REF! | AE100: =AE99+AE95 -> #REF! | AF100: =AF99+AF95 -> #REF! | AH100: =AH99+AH95 -> #REF! | AI100: =AI99+AI95 -> #REF! | AJ100: =AJ99+AJ95 -> #REF! | AK100: =AK99+AK95 -> #REF! | AM100: =AM99+AM95 -> #REF! | AN100: =AN99+AN95 -> #REF! | AO100: =AO99+AO95 -> #REF! | AP100: =AP99+AP95 -> #REF!
C101: Net New Billings | D101: =D100-#REF! -> #REF! | E101: =E100-#REF! -> #REF! | F101: =F100-#REF! -> #REF! | G101: =G100-#REF! -> #REF! | I101: =I100-D94 -> #REF! | J101: =J100-E94 -> #REF! | K101: =K100-F94 -> #REF! | L101: =L100-G94 -> #REF! | N101: =N100-I94 -> #REF! | O101: =O100-J94 -> #REF! | P101: =P100-K94 -> #REF! | Q101: =Q100-L94 -> #REF! | S101: =S100-N94 -> #REF! | T101: =T100-O94 -> #REF! | U101: =U100-P94 -> #REF! | V101: =V100-Q94 -> #REF! | X101: =X100-S94 -> #REF! | Y101: =Y100-T94 -> #REF! | Z101: =Z100-U94 -> #REF! | AA101: =AA100-V94 -> #REF! | AC101: =AC100-X94 -> #REF! | AD101: =AD100-Y94 -> #REF! | AE101: =AE100-Z94 -> #REF! | AF101: =AF100-AA94 -> #REF! | AH101: =AH100-AC94 -> #REF! | AI101: =AI100-AD94 -> #REF! | AJ101: =AJ100-AE94 -> #REF! | AK101: =AK100-AF94 -> #REF! | AM101: =AM100-AH94 -> #REF! | AN101: =AN100-AI94 -> #REF! | AO101: =AO100-AJ94 -> #REF! | AP101: =AP100-AK94 -> #REF!
C102: Revenue Run Off | D102: =D99+D90 -> #REF! | E102: =E99+E90 -> #REF! | F102: =F99+F90 -> #REF! | G102: =G99+G90 -> #REF! | I102: =I99+I90 -> #REF! | J102: =J99+J90 -> #REF! | K102: =K99+K90 -> #REF! | L102: =L99+L90 -> #REF! | N102: =N99+N90 -> #REF! | O102: =O99+O90 -> #REF! | P102: =P99+P90 -> #REF! | Q102: =Q99+Q90 -> #REF! | S102: =S99+S90 -> #REF! | T102: =T99+T90 -> #REF! | U102: =U99+U90 -> #REF! | V102: =V99+V90 -> #REF! | X102: =X99+X90 -> #REF! | Y102: =Y99+Y90 -> #REF! | Z102: =Z99+Z90 -> #REF! | AA102: =AA99+AA90 -> #REF! | AC102: =AC99+AC90 -> #REF! | AD102: =AD99+AD90 -> #REF! | AE102: =AE99+AE90 -> #REF! | AF102: =AF99+AF90 -> #REF! | AH102: =AH99+AH90 -> #REF! | AI102: =AI99+AI90 -> #REF! | AJ102: =AJ99+AJ90 -> #REF! | AK102: =AK99+AK90 -> #REF! | AM102: =AM99+AM90 -> #REF! | AN102: =AN99+AN90 -> #REF! | AO102: =AO99+AO90 -> #REF! | AP102: =AP99+AP90 -> #REF!
C104: LTM S&M | D104: =D21+#REF!+#REF!+#REF! -> #REF! | E104: =E21+D21+#REF!+#REF! -> #REF! | F104: =F21+E21+D21+#REF! -> #REF! | G104: =G21+F21+E21+D21 -> 24625 | I104: =I21+G21+F21+E21 -> 27845 | J104: =J21+I21+G21+F21 -> 27600 | K104: =K21+J21+I21+G21 -> 26642 | L104: =L21+K21+J21+I21 -> 25735 | N104: =N21+L21+K21+J21 -> 23815 | O104: =O21+N21+L21+K21 -> 25393 | P104: =P21+O21+N21+L21 -> 28734 | Q104: =Q21+P21+O21+N21 -> 32333 | S104: =S21+Q21+P21+O21 -> 37163 | T104: =T21+S21+Q21+P21 -> 42695 | U104: =U21+T21+S21+Q21 -> 47122 | V104: =V21+U21+T21+S21 -> 51190 | X104: =X21+V21+U21+T21 -> 53372 | Y104: =Y21+X21+V21+U21 -> 50792 | Z104: =Z21+Y21+X21+V21 -> 47078 | AA104: =AA21+Z21+Y21+X21 -> 42346 | AC104: =AC21+AA21+Z21+Y21 -> 39260 | AD104: =AD21+AC21+AA21+Z21 -> 39536 | AE104: =AE21+AD21+AC21+AA21 -> 40549 | AF104: =AF21+AE21+AD21+AC21 -> 43802 | AH104: =AH21+AF21+AE21+AD21 -> 46029 | AI104: =AI21+AH21+AF21+AE21 -> 46949 | AJ104: =AJ21+AI21+AH21+AF21 -> 47333 | AK104: =AK21+AJ21+AI21+AH21 -> 48364 | AM104: =AM21+AK21+AJ21+AI21 -> 49068.716 | AN104: =AN21+AM21+AK21+AJ21 -> 49993.427 | AO104: =AO21+AN21+AM21+AK21 -> 51348.534 | AP104: =AP21+AO21+AN21+AM21 -> 51513.739
C106: Billings Ratio | D106: =D104/D100 -> #REF! | E106: =E104/E100 -> #REF! | F106: =F104/F100 -> #REF! | G106: =G104/G100 -> #REF! | I106: =I104/I100 -> #REF! | J106: =J104/J100 -> #REF! | K106: =K104/K100 -> #REF! | L106: =L104/L100 -> #REF! | N106: =N104/N100 -> #REF! | O106: =O104/O100 -> #REF! | P106: =P104/P100 -> #REF! | Q106: =Q104/Q100 -> #REF! | S106: =S104/S100 -> #REF! | T106: =T104/T100 -> #REF! | U106: =U104/U100 -> #REF! | V106: =V104/V100 -> #REF! | X106: =X104/X100 -> #REF! | Y106: =Y104/Y100 -> #REF! | Z106: =Z104/Z100 -> #REF! | AA106: =AA104/AA100 -> #REF! | AC106: =AC104/AC100 -> #REF! | AD106: =AD104/AD100 -> #REF! | AE106: =AE104/AE100 -> #REF! | AF106: =AF104/AF100 -> #REF! | AH106: =AH104/AH100 -> #REF! | AI106: =AI104/AI100 -> #REF! | AJ106: =AJ104/AJ100 -> #REF! | AK106: =AK104/AK100 -> #REF! | AM106: =AM104/AM100 -> #REF! | AN106: =AN104/AN100 -> #REF! | AO106: =AO104/AO100 -> #REF! | AP106: =AP104/AP100 -> #REF!
B108: CAC Ratio | L108: =((L19+K19+J19+I19)/(L11+K11+J11+I11-G11-F11-E11-D11)) -> 1.5449517 | N108: =((N19+M19+L19+K19)/(N11+M11+L11+K11-I11-H11-G11-F11)) -> 1.489318 | O108: =((O19+N19+M19+L19)/(O11+N11+M11+L11-J11-I11-H11-G11)) -> 1.2782083 | P108: =((P19+O19+N19+M19)/(P11+O11+N11+M11-K11-J11-I11-H11)) -> 1.2125992 | Q108: =((Q19+P19+O19+N19)/(Q11+P11+O11+N11-L11-K11-J11-I11)) -> 0.99758159 | S108: =((S19+R19+Q19+P19)/(S11+R11+Q11+P11-N11-M11-L11-K11)) -> 1.0341526 | T108: =((T19+S19+R19+Q19)/(T11+S11+R11+Q11-O11-N11-M11-L11)) -> 1.1972264 | U108: =((U19+T19+S19+R19)/(U11+T11+S11+R11-P11-O11-N11-M11)) -> 1.4333348 | V108: =((V19+U19+T19+S19)/(V11+U11+T11+S11-Q11-P11-O11-N11)) -> 3.2930257 | X108: =((X19+W19+V19+U19)/(X11+W11+V11+U11-S11-R11-Q11-P11)) -> 5.322177 | Y108: =((Y19+X19+W19+V19)/(Y11+X11+W11+V11-T11-S11-R11-Q11)) -> 6.3457611 | Z108: =((Z19+Y19+X19+W19)/(Z11+Y11+X11+W11-U11-T11-S11-R11)) -> 5.734216 | AA108: =((AA19+Z19+Y19+X19)/(AA11+Z11+Y11+X11-V11-U11-T11-S11)) -> 21.42 | AC108: =((AC19+AB19+AA19+Z19)/(AC11+AB11+AA11+Z11-X11-W11-V11-U11)) -> 11.674986 | AD108: =((AD19+AC19+AB19+AA19)/(AD11+AC11+AB11+AA11-Y11-X11-W11-V11)) -> 10.134877 | AE108: =((AE19+AD19+AC19+AB19)/(AE11+AD11+AC11+AB11-Z11-Y11-X11-W11)) -> 12.50274 | AF108: =((AF19+AE19+AD19+AC19)/(AF11+AE11+AD11+AC11-AA11-Z11-Y11-X11)) -> 8.3989039 | AH108: =((AH19+AG19+AF19+AE19)/(AH11+AG11+AF11+AE11-AC11-AB11-AA11-Z11)) -> 9.3661769 | AI108: =((AI19+AH19+AG19+AF19)/(AI11+AH11+AG11+AF11-AD11-AC11-AB11-AA11)) -> 8.7139666 | AJ108: =((AJ19+AI19+AH19+AG19)/(AJ11+AI11+AH11+AG11-AE11-AD11-AC11-AB11)) -> 6.6675122 | AK108: =((AK19+AJ19+AI19+AH19)/(AK11+AJ11+AI11+AH11-AF11-AE11-AD11-AC11)) -> 4.5343937 | AM108: =((AM19+AL19+AK19+AJ19)/(AM11+AL11+AK11+AJ11-AH11-AG11-AF11-AE11)) -> 4.0160209 | AN108: =((AN19+AM19+AL19+AK19)/(AN11+AM11+AL11+AK11-AI11-AH11-AG11-AF11)) -> 4.110601 | AO108: =((AO19+AN19+AM19+AL19)/(AO11+AN11+AM11+AL11-AJ11-AI11-AH11-AG11)) -> 4.3100184 | AP108: =((AP19+AO19+AN19+AM19)/(AP11+AO11+AN11+AM11-AK11-AJ11-AI11-AH11)) -> 3.7539559
B114: GAAP IS
B115: 1000
B116: Revenue | D116: 10378 | E116: 11305 | F116: 12652 | G116: 14221 | H116: =SUM(D116:G116) -> 48556 | I116: 15668 | J116: 15727 | K116: 17863 | L116: 19186 | M116: =SUM(I116:L116) -> 68444 | N116: 21131
B118: Cost of Revenue | D118: 2902 | E118: 3307 | F118: 3620 | G118: 4628 | H118: =SUM(D118:G118) -> 14457 | I118: 5071 | J118: 4509 | K118: 5522 | L118: 5347 | M118: =SUM(I118:L118) -> 20449 | N118: 5788
B120: Gross Profit | D120: =D116-D118 -> 7476 | E120: =E116-E118 -> 7998 | F120: =F116-F118 -> 9032 | G120: =G116-G118 -> 9593 | H120: =SUM(D120:G120) -> 34099 | I120: =I116-I118 -> 10597 | J120: =J116-J118 -> 11218 | K120: =K116-K118 -> 12341 | L120: =L116-L118 -> 13839 | M120: =SUM(I120:L120) -> 47995 | N120: =N116-N118 -> 15343
C122: GAAP Sales & Marketing | D122: 5346 | E122: 5890 | F122: 6998 | G122: 7888 | H122: =SUM(D122:G122) -> 26122 | I122: 9322 | J122: 7170 | K122: 7182 | L122: 7387 | M122: =SUM(I122:L122) -> 31061 | N122: 7876
C123: GAAP Research & Development | D123: 4809 | E123: 6471 | F123: 7190 | G123: 6882 | H123: =SUM(D123:G123) -> 25352 | I123: 8203 | J123: 6215 | K123: 6227 | L123: 5954 | M123: =SUM(I123:L123) -> 26599 | N123: 6262
C124: GAAP General & Administration | D124: 4417 | E124: 2866 | F124: 2631 | G124: 3061 | H124: =SUM(D124:G124) -> 12975 | I124: 4258 | J124: 3144 | K124: 3030 | L124: 3461 | M124: =SUM(I124:L124) -> 13893 | N124: 4053
C125: Refund of Sales and Use Taxes | K125: -1057
B126: GAAP Total Operating Expenses | D126: =SUM(D122:D125) -> 14572 | E126: =SUM(E122:E125) -> 15227 | F126: =SUM(F122:F125) -> 16819 | G126: =SUM(G122:G125) -> 17831 | H126: =SUM(H122:H125) -> 64449 | I126: =SUM(I122:I125) -> 21783 | J126: =SUM(J122:J125) -> 16529 | K126: =SUM(K122:K125) -> 15382 | ... N126: =SUM(N122:N125) -> 18191
B128: Net Interest | D128: =D129+D130 -> 147 | E128: =E129+E130 -> 180 | F128: =F129+F130 -> 128 | G128: =G129+G130 -> 73 | H128: =H129+H130 -> 528 | I128: =I129+I130 -> -25 | J128: =J129+J130 -> -146 | K128: =K129+K130 -> -115 | ... N128: =N129+N130 -> -44
C129: Interest and Other Income | D129: 180 | E129: 144 | F129: 215 | G129: 113 | H129: =SUM(D129:G129) -> 652 | I129: 63 | J129: 15 | K129: 55 | L129: 22 | M129: =SUM(I129:L129) -> 155 | N129: 13
...

Sheet BS
B2: =IS!B2 -> CS DISCO (LAW)
B4: Balance Sheet | D4: 1Q19 | E4: 2Q19 | F4: 3Q19 | G4: 4Q19 | H4: 2019 | I4: 1Q20 | J4: 2Q20 | K4: 3Q20 | L4: 4Q20 | M4: 2020 | N4: 1Q21 | O4: 2Q21 | P4: 3Q21 | Q4: 4Q21 | R4: 2021 | S4: 1Q22 | T4: 2Q22 | U4: 3Q22 | V4: 4Q22 | W4: 2022 | X4: =IS!X4 -> 1Q23 | Y4: =IS!Y4 -> 2Q23 | Z4: =IS!Z4 -> 3Q23 | AA4: =IS!AA4 -> 4Q23 | AB4: =IS!AB4 -> 2023 | AC4: =IS!AC4 -> 1Q24 | AD4: =IS!AD4 -> 2Q24 | AE4: =IS!AE4 -> 3Q24 | ... AQ4: =IS!AQ4 -> 2026E
B5: Assets:
C6: Cash & Cash Equivalents | D6: 43786 | E6: 40307 | F6: 33348 | G6: 23224 | H6: =G6 -> 23224 | I6: 29398 | J6: 24022 | K6: 78188 | L6: 58569 | M6: =L6 -> 58569 | N6: 53632 | O6: 47026 | P6: 258478 | Q6: 255477 | R6: =Q6 -> 255477 | S6: 238576 | T6: 228187 | U6: 213122 | V6: 203244 | W6: =V6 -> 203244 | X6: 187635 | Y6: 178919 | Z6: 157652 | AA6: 159551 | AB6: =AA6 -> 159551 | AC6: 148679 | AD6: 130005 | AE6: =76549+50245 -> 126794 | AF6: =52771+76356 -> 129127 | AG6: =AF6 -> 129127 | AH6: =34533+84278 -> 118811 | AI6: =21672+92672 -> 114344 | AJ6: =28804+84682 -> 113486 | AK6: =19655+94942 -> 114597 | AL6: =AK6 -> 114597 | AM6: =AL6+CF!AM51 -> 100786.59 | AN6: =AM6+CF!AN51 -> 99653.353 | AO6: =AN6+CF!AO51 -> 97358.69 | AP6: =AO6+CF!AP51 -> 97706.938 | AQ6: =AP6 -> 97706.938
C7: Accounts Receivable, Net | D7: 4592 | E7: 4926 | F7: 5026 | G7: 7362 | H7: =G7 -> 7362 | I7: 8114 | J7: 8631 | K7: 9942 | L7: 12912 | M7: =L7 -> 12912 | N7: 14952 | O7: 21195 | P7: 23180 | Q7: 20740 | R7: =Q7 -> 20740 | S7: 24930 | T7: 24309 | U7: 22204 | V7: 22720 | W7: =V7 -> 22720 | X7: 23851 | Y7: 24577 | Z7: 27103 | AA7: 26993 | AB7: =AA7 -> 26993 | AC7: 24501 | AD7: 25334 | AE7: 23988 | AF7: 23117 | AG7: =AF7 -> 23117 | AH7: 22326 | AI7: 23861 | AJ7: 24233 | AK7: 25622 | AL7: =AK7 -> 25622 | AM7: =AM50*IS!AM11 -> 29017.424 | AN7: =AN50*IS!AN11 -> 30881.467 | AO7: =AO50*IS!AO11 -> 32150.372 | AP7: =AP50*IS!AP11 -> 33973.258 | AQ7: =AP7 -> 33973.258
C8: Insurance Recovery Receivable | AJ8: 9240 | AK8: 8039 | AL8: =AK8 -> 8039 | AM8: =AL8 -> 8039 | AN8: =AM8 -> 8039 | AO8: =AN8 -> 8039 | AP8: =AO8 -> 8039 | AQ8: =AP8 -> 8039
C9: Other Current Assets | D9: 1736 | E9: 1354 | F9: 939 | G9: 1341 | H9: =G9 -> 1341 | I9: 1118 | J9: 1030 | K9: 1240 | L9: 1364 | M9: =L9 -> 1364 | N9: 1439 | O9: 4329 | P9: 6558 | Q9: 4634 | R9: =Q9 -> 4634 | S9: 3662 | T9: 2950 | U9: 6437 | V9: 5576 | W9: =V9 -> 5576 | X9: 4880 | Y9: 3717 | Z9: 6292 | AA9: 5795 | AB9: =AA9 -> 5795 | AC9: 5388 | AD9: 4812 | AE9: 6318 | AF9: 4692 | AG9: =AF9 -> 4692 | AH9: 4459 | AI9: 4566 | AJ9: 6103 | AK9: 4736 | AL9: =AK9 -> 4736 | AM9: =AM51*IS!AM$11 -> 5962.4844 | AN9: =AN51*IS!AN$11 -> 5499.4394 | AO9: =AO51*IS!AO$11 -> 7046.657 | AP9: =AP51*IS!AP$11 -> 6886.4712 | AQ9: =AP9 -> 6886.4712
B10: Total Current Assets | D10: =SUM(D6:D9) -> 50114 | E10: =SUM(E6:E9) -> 46587 | F10: =SUM(F6:F9) -> 39313 | G10: =SUM(G6:G9) -> 31927 | H10: =SUM(H6:H9) -> 31927 | I10: =SUM(I6:I9) -> 38630 | J10: =SUM(J6:J9) -> 33683 | K10: =SUM(K6:K9) -> 89370 | ... Q10: =SUM(Q6:Q9) -> 280851 | R10: =Q10 -> 280851 | S10: =SUM(S6:S9) -> 267168 | T10: =SUM(T6:T9) -> 255446 | U10: =SUM(U6:U9) -> 241763 | V10: =SUM(V6:V9) -> 231540 | W10: =V10 -> 231540 | X10: =SUM(X6:X9) -> 216366 | Y10: =SUM(Y6:Y9) -> 207213 | Z10: =SUM(Z6:Z9) -> 191047 | AA10: =SUM(AA6:AA9) -> 192339 | AB10: =AA10 -> 192339 | AC10: =SUM(AC6:AC9) -> 178568 | AD10: =SUM(AD6:AD9) -> 160151 | AE10: =SUM(AE6:AE9) -> 157100 | AF10: =SUM(AF6:AF9) -> 156936 | AG10: =AF10 -> 156936 | AH10: =SUM(AH6:AH9) -> 145596 | AI10: =SUM(AI6:AI9) -> 142771 | AJ10: =SUM(AJ6:AJ9) -> 153062 | AK10: =SUM(AK6:AK9) -> 152994 | AL10: =AK10 -> 152994 | AM10: =SUM(AM6:AM9) -> 143805.5 | AN10: =SUM(AN6:AN9) -> 144073.26 | AO10: =SUM(AO6:AO9) -> 144594.72 | AP10: =SUM(AP6:AP9) -> 146605.67 | AQ10: =AP10 -> 146605.67
C11: Property and Equipment, Net | D11: 1290 | E11: 2106 | F11: 2720 | G11: 3589 | H11: =G11 -> 3589 | I11: 3877 | J11: 3785 | K11: 3763 | L11: 3873 | M11: =L11 -> 3873 | N11: 4022 | O11: 4494 | P11: 4947 | Q11: 5335 | R11: =Q11 -> 5335 | S11: 5848 | T11: 7229 | U11: 7491 | V11: 7507 | W11: =V11 -> 7507 | X11: 7795 | Y11: 8638 | Z11: 9182 | AA11: 9663 | AB11: =AA11 -> 9663 | AC11: 9518 | AD11: 9232 | AE11: 9239 | AF11: 7878 | AG11: =AF11 -> 7878 | AH11: 7538 | AI11: 7665 | AJ11: 8030 | AK11: 7583 | AL11: =AK11 -> 7583 | AM11: =AL11-CF!AM29-CF!AM10 -> 7560.955 | AN11: =AM11-CF!AN29-CF!AN10 -> 7641.4452 | AO11: =AN11-CF!AO29-CF!AO10 -> 7712.679 | AP11: =AO11-CF!AP29-CF!AP10 -> 7775.7209 | AQ11: =AP11 -> 7775.7209
C12: Operating Lease Right-of-Use Assets | D12: 0 | E12: 0 | F12: 0 | G12: 0 | H12: =G12 -> 0 | I12: 2813 | J12: 2468 | K12: 2100 | L12: 1850 | M12: =L12 -> 1850 | N12: 1608 | O12: 1364 | P12: 1115 | Q12: 864 | R12: =Q12 -> 864 | S12: 609 | T12: 10937 | U12: 10293 | V12: 9824 | W12: =V12 -> 9824 | X12: 9606 | Y12: 9124 | Z12: 8637 | AA12: 8143 | AB12: =AA12 -> 8143 | AC12: 7878 | AD12: 7372 | AE12: 6859 | AF12: 8388 | AG12: =AF12 -> 8388 | AH12: 7832 | AI12: 7270 | AJ12: 6700 | AK12: 6121 | AL12: =AK12 -> 6121 | AM12: =AK12-500 -> 5621 | AN12: =AM12-500 -> 5121 | AO12: =AN12-500 -> 4621 | AP12: =AO12-500 -> 4121 | AQ12: =AP12 -> 4121
C13: Primary law intangible asset, net | Z13: 14000 | AA13: 14000 | AB13: =AA13 -> 14000 | AC13: 14000 | AD13: 14000 | AE13: 14000 | AF13: 0 | AG13: =AF13 -> 0 | AK13: 0 | AL13: =AK13 -> 0 | AM13: =AL13 -> 0 | AN13: =AM13 -> 0 | AO13: =AN13 -> 0 | AP13: =AO13 -> 0 | AQ13: =AP13 -> 0
C14: Intangible assets, net | H14: =G14 -> 0 | M14: =L14 -> 0 | R14: =Q14 -> 0 | S14: 1173 | T14: 1101 | U14: 1031 | V14: 962 | W14: =V14 -> 962 | X14: 891 | Y14: 821 | Z14: 751 | AA14: 681 | AB14: =AA14 -> 681 | AC14: 610 | AD14: 540 | AE14: 470 | AF14: 400 | AG14: =AF14 -> 400 | AH14: 341 | AI14: 296 | AJ14: 251 | AK14: 206 | AL14: =AK14 -> 206 | AM14: =AK14-70 -> 136 | AN14: =AL14-70 -> 136 | AO14: =AM14-70 -> 66 | AP14: =AN14-70 -> 66 | AQ14: =AP14 -> 66
C15: Goodwill | H15: =G15 -> 0 | M15: =L15 -> 0 | R15: =Q15 -> 0 | S15: 5898 | T15: 5898 | U15: 5898 | V15: 5898 | W15: =V15 -> 5898 | X15: 5898 | Y15: 5898 | Z15: 5898 | AA15: 5898 | AB15: =AA15 -> 5898 | AC15: 5898 | AD15: 5898 | AE15: 5898 | AF15: 5898 | AG15: =AF15 -> 5898 | AH15: 5898 | AI15: 5898 | AJ15: 5898 | AK15: 5898 | AL15: =AK15 -> 5898 | AM15: =AL15 -> 5898 | AN15: =AM15 -> 5898 | AO15: =AN15 -> 5898 | AP15: =AO15 -> 5898 | AQ15: =AP15 -> 5898
C16: Other Assets | D16: 224 | E16: 291 | F16: 278 | G16: 382 | H16: =G16 -> 382 | I16: 377 | J16: 341 | K16: 326 | L16: 539 | M16: =L16 -> 539 | N16: 535 | O16: 501 | P16: 534 | Q16: 351 | R16: =Q16 -> 351 | S16: 384 | T16: 737 | U16: 736 | V16: 591 | W16: =V16 -> 591 | X16: 721 | Y16: 721 | Z16: 730 | AA16: 823 | AB16: =AA16 -> 823 | AC16: 804 | AD16: 808 | AE16: 816 | AF16: 820 | AG16: =AF16 -> 820 | AH16: 825 | AI16: 827 | AJ16: 820 | AK16: 837 | AL16: =AK16 -> 837 | AM16: 535 | AN16: 535 | AO16: 535 | AP16: 535 | AQ16: =AP16 -> 535
B17: Total Assets | D17: =D10+SUM(D11:D16) -> 51628 | E17: =E10+SUM(E11:E16) -> 48984 | F17: =F10+SUM(F11:F16) -> 42311 | G17: =G10+SUM(G11:G16) -> 35898 | H17: =H10+SUM(H11:H16) -> 35898 | I17: =I10+SUM(I11:I16) -> 45697 | J17: =J10+SUM(J11:J16) -> 40277 | K17: =K10+SUM(K11:K16) -> 95559 | ... Q17: =Q10+SUM(Q11:Q16) -> 287401 | R17: =Q17 -> 287401 | S17: =S10+SUM(S11:S16) -> 281080 | T17: =T10+SUM(T11:T16) -> 281348 | U17: =U10+SUM(U11:U16) -> 267212 | V17: =V10+SUM(V11:V16) -> 256322 | W17: =V17 -> 256322 | X17: =X10+SUM(X11:X16) -> 241277 | Y17: =Y10+SUM(Y11:Y16) -> 232415 | Z17: =Z10+SUM(Z11:Z16) -> 230245 | AA17: =AA10+SUM(AA11:AA16) -> 231547 | AB17: =AA17 -> 231547 | AC17: =AC10+SUM(AC11:AC16) -> 217276 | AD17: =AD10+SUM(AD11:AD16) -> 198001 | AE17: =AE10+SUM(AE11:AE16) -> 194382 | AF17: =AF10+SUM(AF11:AF16) -> 180320 | AG17: =AF17 -> 180320 | AH17: =AH10+SUM(AH11:AH16) -> 168030 | AI17: =AI10+SUM(AI11:AI16) -> 164727 | AJ17: =AJ10+SUM(AJ11:AJ16) -> 174761 | AK17: =AK10+SUM(AK11:AK16) -> 173639 | AL17: =AK17 -> 173639 | AM17: =AM10+SUM(AM11:AM16) -> 163556.46 | AN17: =AN10+SUM(AN11:AN16) -> 163404.71 | AO17: =AO10+SUM(AO11:AO16) -> 163427.4 | AP17: =AP10+SUM(AP11:AP16) -> 165001.39 | AQ17: =AP17 -> 165001.39
B19: Liabilities:
C20: Accounts Payable | D20: 1240 | E20: 2479 | F20: 2432 | G20: 3986 | H20: =G20 -> 3986 | I20: 4170 | J20: 4878 | K20: 5269 | L20: 3588 | M20: =L20 -> 3588 | N20: 4267 | O20: 6144 | P20: 7953 | Q20: 4686 | R20: =Q20 -> 4686 | S20: 7545 | T20: 8565 | U20: 6843 | V20: 8485 | W20: =V20 -> 8485 | X20: 6545 | Y20: 5122 | Z20: 6485 | AA20: 5234 | AB20: =AA20 -> 5234 | AC20: 1995 | AD20: 4040 | AE20: 3410 | AF20: 3994 | AG20: =AF20 -> 3994 | AH20: 5409 | AI20: 3122 | AJ20: 2464 | AK20: 3888 | AL20: =AK20 -> 3888 | AM20: =AM56*IS!AM$11 -> 5564.9854 | AN20: =AN56*IS!AN$11 -> 5922.4732 | AO20: =AO56*IS!AO$11 -> 6165.8248 | AP20: =AP56*IS!AP$11 -> 6427.3731 | AQ20: =AP20 -> 6427.3731
C21: Accrued Expenses | D21: 567 | E21: 713 | F21: 798 | G21: 1080 | H21: =G21 -> 1080 | I21: 1654 | J21: 762 | K21: 660 | L21: 641 | M21: =L21 -> 641 | N21: 771 | O21: 2800 | P21: 3244 | Q21: 2844 | R21: =Q21 -> 2844 | S21: 3816 | T21: 4609 | U21: 4728 | V21: 4705 | W21: =V21 -> 4705 | X21: 3696 | Y21: 4386 | Z21: 4161 | AA21: 5502 | AB21: =AA21 -> 5502 | AC21: 6341 | AD21: 5457 | AE21: 5847 | AF21: 5947 | AG21: =AF21 -> 5947 | AH21: 3901 | AI21: 6187 | AJ21: 5189 | AK21: 6533 | AL21: =AK21 -> 6533 | AM21: =AM57*IS!AM$11 -> 5564.9854 | AN21: =AN57*IS!AN$11 -> 5922.4732 | AO21: =AO57*IS!AO$11 -> 6165.8248 | AP21: =AP57*IS!AP$11 -> 6656.9222 | AQ21: =AP21 -> 6656.9222
C22: Accrued legal loss contingency | AJ22: 15500 | AK22: 11500 | AL22: =AK22 -> 11500 | AM22: =AL22 -> 11500 | AN22: =AM22 -> 11500 | AO22: =AN22 -> 11500 | AP22: =AO22 -> 11500 | AQ22: =AP22 -> 11500
C23: Accrued Salary and Benefits | D23: 1174 | E23: 3549 | F23: 4002 | G23: 2723 | H23: =G23 -> 2723 | I23: 2465 | J23: 2810 | K23: 3959 | L23: 5240 | M23: =L23 -> 5240 | N23: 2945 | O23: 4858 | P23: 6775 | Q23: 7955 | R23: =Q23 -> 7955 | S23: 4503 | T23: 5817 | U23: 6337 | V23: 3536 | W23: =V23 -> 3536 | X23: 3952 | Y23: 5124 | Z23: 5526 | AA23: 6230 | AB23: =AA23 -> 6230 | AC23: 3134 | AD23: 5513 | AE23: 6816 | AF23: 9127 | AG23: =AF23 -> 9127 | AH23: 3692 | AI23: 5809 | AJ23: 7955 | AK23: 10457 | AL23: =AK23 -> 10457 | AM23: =AM58*IS!AM$11 -> 6757.4823 | AN23: =AN58*IS!AN$11 -> 7191.5746 | AO23: =AO58*IS!AO$11 -> 7266.865 | AP23: =AP58*IS!AP$11 -> 7804.6674 | AQ23: =AP23 -> 7804.6674
C24: Current Portion of Revolving Line of Credit | D24: 0 | E24: 0 | F24: 0 | G24: 0 | I24: 0 | J24: 17000 | K24: 17000 | L24: 0 | N24: 0 | O24: 0 | P24: 0 | Q24: 0 | S24: 0 | T24: 0 | U24: 0 | V24: 0 | X24: 0 | Z24: 0 | AA24: 0 | AC24: 0 | AM24: 0 | AN24: 0 | AO24: 0 | AP24: 0
C25: Deferred Revenue | D25: 801 | E25: 681 | F25: 646 | G25: 1418 | H25: =G25 -> 1418 | I25: 1537 | J25: 1339 | K25: 1101 | L25: 1642 | M25: =L25 -> 1642 | N25: 2752 | O25: 1489 | P25: 1575 | Q25: 2175 | R25: =Q25 -> 2175 | S25: 3035 | T25: 2690 | U25: 2741 | V25: 4100 | W25: =V25 -> 4100 | X25: 4169 | Y25: 3310 | Z25: 2966 | AA25: 4285 | AB25: =AA25 -> 4285 | AC25: 3501 | AD25: 3518 | AE25: 3042 | AF25: 4296 | AG25: =AF25 -> 4296 | AH25: 3905 | AI25: 3493 | AJ25: 4272 | AK25: 5382 | AL25: =AK25 -> 5382 | AM25: =AM59*IS!AM$11 -> 3974.9896 | AN25: =AN59*IS!AN$11 -> 4230.338 | AO25: =AO59*IS!AO$11 -> 4404.1606 | AP25: =AP59*IS!AP$11 -> 5050.0789 | AQ25: =AP25 -> 5050.0789
C26: Operating Leases | D26: 0 | E26: 0 | F26: 0 | G26: 0 | I26: 1271 | J26: 1158 | K26: 1016 | L26: 1018 | N26: 1031 | O26: 1045 | P26: 1059 | Q26: 890 | R26: =Q26 -> 890 | S26: 627 | T26: 1229 | U26: 1599 | V26: 1902 | W26: =V26 -> 1902 | X26: 1981 | Y26: 1982 | Z26: 1905 | AA26: 1826 | AB26: =AA26 -> 1826 | AC26: 1983 | AD26: 1905 | AE26: 1823 | AF26: 2288 | AG26: =AF26 -> 2288 | AH26: 2460 | AI26: 2514 | AJ26: 2569 | AK26: 2624 | AL26: =AK26 -> 2624 | AM26: =AK26-80 -> 2544 | AN26: =AM26-80 -> 2464 | AO26: =AN26-80 -> 2384 | AP26: =AO26-80 -> 2304 | AQ26: =AP26 -> 2304
C27: Finance Leases | D27: 0 | E27: 0 | F27: 0 | G27: 0 | H27: =G27 -> 0 | I27: 107 | J27: 109 | K27: 111 | L27: 112 | M27: =L27 -> 112 | N27: 114 | O27: 116 | P27: 117 | Q27: 99 | R27: =Q27 -> 99 | S27: 70 | T27: 39 | U27: 31 | V27: 39 | W27: =V27 -> 39 | X27: 40 | Y27: 40 | Z27: =Y27 -> 40 | AA27: 41 | AB27: =AA27 -> 41 | AC27: 41 | AD27: 41 | AE27: 42 | AF27: 42 | AG27: =AF27 -> 42 | AH27: 43 | AI27: 43 | AJ27: 43 | AK27: 44 | AL27: =AK27 -> 44 | AM27: =AL27 -> 44 | AN27: =AM27 -> 44 | AO27: =AN27 -> 44 | AP27: =AO27 -> 44 | AQ27: =AP27 -> 44
B28: Total Current Liabilities | D28: =SUM(D20:D27) -> 3782 | E28: =SUM(E20:E27) -> 7422 | F28: =SUM(F20:F27) -> 7878 | G28: =SUM(G20:G27) -> 9207 | H28: =SUM(H20:H27) -> 9207 | I28: =SUM(I20:I27) -> 11204 | J28: =SUM(J20:J27) -> 28056 | K28: =SUM(K20:K27) -> 29116 | ... AQ28: =SUM(AQ20:AQ27) -> 39787.042
C29: Long-term Debt | D29: 0 | E29: 0 | F29: 0 | G29: 0 | H29: =G29 -> 0 | I29: 17000 | J29: 0 | K29: 0 | L29: 0 | M29: =L29 -> 0 | N29: 0 | O29: =N29 -> 0 | P29: =O29 -> 0 | Q29: =P29 -> 0 | R29: =Q29 -> 0 | S29: =R29 -> 0 | T29: =S29 -> 0 | U29: =T29 -> 0 | V29: =U29 -> 0 | ... AD29: =AC29 -> 0 | AE29: 0 | AF29: =AE29 -> 0 | AG29: =AF29 -> 0 | AH29: =AG29 -> 0 | AK29: =AJ29 -> 0 | AL29: =AK29 -> 0 | AM29: =AL29 -> 0 | AN29: =AM29 -> 0 | AO29: =AN29 -> 0 | AP29: =AO29 -> 0 | AQ29: =AP29 -> 0
C30: Debt Issuance Costs | D30: 0 | E30: 0 | F30: 0 | G30: 0 | H30: =G30 -> 0 | I30: 0 | J30: 0 | K30: 0 | L30: 0 | M30: =L30 -> 0 | N30: 0 | O30: =N30 -> 0 | P30: =O30 -> 0 | Q30: =P30 -> 0 | R30: =Q30 -> 0 | S30: =R30 -> 0 | T30: =S30 -> 0 | U30: =T30 -> 0 | V30: =U30 -> 0 | ... AD30: =AC30 -> 0 | AE30: 0 | AF30: =AE30 -> 0 | AG30: =AF30 -> 0 | AH30: =AG30 -> 0 | AK30: =AJ30 -> 0 | AL30: =AK30 -> 0 | AM30: =AL30 -> 0 | AN30: =AM30 -> 0 | AO30: =AN30 -> 0 | AP30: =AO30 -> 0 | AQ30: =AP30 -> 0
C31: Operating Lease, Noncurrent | D31: 0 | E31: 0 | F31: 0 | G31: 0 | H31: =G31 -> 0 | I31: 1658 | J31: 1405 | K31: 1149 | L31: 890 | M31: =L31 -> 890 | N31: 627 | O31: 361 | P31: 91 | Q31: 0 | R31: =Q31 -> 0 | S31: 0 | T31: 9711 | U31: 9219 | V31: 8770 | W31: =V31 -> 8770 | X31: 8449 | Y31: 7969 | Z31: 7560 | AA31: 7136 | AB31: =AA31 -> 7136 | AC31: 6702 | AD31: 6262 | AE31: 5817 | AF31: 6855 | AG31: =AF31 -> 6855 | AH31: 6216 | AI31: 5566 | AJ31: 4908 | AK31: 4231 | AL31: =AK31 -> 4231 | AM31: =AK31-440 -> 3791 | AN31: =AM31-440 -> 3351 | AO31: =AN31-440 -> 2911 | AP31: =AO31-440 -> 2471 | AQ31: =AP31 -> 2471
C32: Financing Lease, Noncurrent | D32: 0 | E32: 0 | F32: 0 | G32: 0 | I32: 183 | J32: 156 | K32: 127 | L32: 99 | N32: 70 | O32: 40 | P32: 10 | Q32: 0 | R32: =Q32 -> 0 | S32: =R32 -> 0 | T32: 219 | U32: 209 | V32: 199 | W32: =V32 -> 199 | X32: 189 | Y32: 179 | Z32: 169 | AA32: 158 | AB32: =AA32 -> 158 | AC32: 148 | AD32: 137 | AE32: 127 | AF32: 116 | AG32: =AF32 -> 116 | AH32: 105 | AI32: 94 | AJ32: 83 | AK32: 72 | AL32: =AK32 -> 72 | AM32: =AL32 -> 72 | AN32: =AM32 -> 72 | AO32: =AN32 -> 72 | AP32: =AO32 -> 72 | AQ32: =AP32 -> 72
C33: Other Liabilities | D33: 121 | E33: 336 | F33: 361 | G33: 270 | H33: =G33 -> 270 | I33: 0 | J33: 0 | K33: 1 | L33: 0 | M33: =L33 -> 0 | N33: 0 | O33: =N33 -> 0 | P33: =O33 -> 0 | Q33: 75 | R33: =Q33 -> 75 | S33: 653 | T33: 631 | U33: 723 | V33: 950 | W33: =V33 -> 950 | X33: 458 | Y33: 424 | Z33: 389 | AA33: 800 | AB33: =AA33 -> 800 | AC33: 278 | AD33: 238 | AE33: 199 | AF33: 141 | AG33: =AF33 -> 141 | AH33: 127 | AI33: 149 | AJ33: 148 | AK33: 601 | AL33: =AK33 -> 601 | AM33: =AL33 -> 601 | AN33: =AM33 -> 601 | AO33: =AN33 -> 601 | AP33: =AO33 -> 601 | AQ33: =AP33 -> 601
B34: Total Liabilities | D34: =D28+SUM(D29:D33) -> 3903 | E34: =E28+SUM(E29:E33) -> 7758 | F34: =F28+SUM(F29:F33) -> 8239 | G34: =G28+SUM(G29:G33) -> 9477 | H34: =H28+SUM(H29:H33) -> 9477 | I34: =I28+SUM(I29:I33) -> 30045 | J34: =J28+SUM(J29:J33) -> 29617 | K34: =K28+SUM(K29:K33) -> 30393 | ... AQ34: =AQ28+SUM(AQ29:AQ33) -> 42931.042
B36: Shareholders Equity:
C37: Total Shareholder Equity | D37: =D17-D34 -> 47725 | E37: =E17-E34 -> 41226 | F37: =F17-F34 -> 34072 | G37: =G17-G34 -> 26421 | H37: =G37 -> 26421 | I37: =I17-I34 -> 15652 | J37: =J17-J34 -> 10660 | K37: =K17-K34 -> 65166 | L37: =L17-L34 -> 65877 | M37: =L37 -> 65877 | N37: =N17-N34 -> 63611 | O37: =O17-O34 -> 62056 | P37: =P17-P34 -> 273988 | Q37: =Q17-Q34 -> 268677 | R37: =Q37 -> 268677 | S37: =S17-S34 -> 260831 | T37: =T17-T34 -> 247838 | U37: =U17-U34 -> 234782 | V37: =V17-V34 -> 223636 | W37: =V37 -> 223636 | X37: =X17-X34 -> 211798 | Y37: =Y17-Y34 -> 203879 | Z37: =Z17-Z34 -> 201044 | AA37: =AA17-AA34 -> 200335 | AB37: =AA37 -> 200335 | AC37: =AC17-AC34 -> 193153 | AD37: =AD17-AD34 -> 170890 | AE37: =AE17-AE34 -> 167259 | AF37: =AF17-AF34 -> 147514 | AG37: =AF37 -> 147514 | AH37: =AH17-AH34 -> 142172 | AI37: =AI17-AI34 -> 137750 | AJ37: =AJ17-AJ34 -> 131630 | AK37: =AK17-AK34 -> 128307 | AL37: =AK37 -> 128307 | AM37: =AM17-AM34 -> 123142.02 | AN37: =AN17-AN34 -> 122105.85 | AO37: =AO17-AO34 -> 121912.72 | AP37: =AP17-AP34 -> 122070.35 | AQ37: =AP37 -> 122070.35
B38: Total Liabilities & Shareholders Equity | D38: =D37+D34 -> 51628 | E38: =E37+E34 -> 48984 | F38: =F37+F34 -> 42311 | G38: =G37+G34 -> 35898 | H38: =G38 -> 35898 | I38: =I37+I34 -> 45697 | J38: =J37+J34 -> 40277 | K38: =K37+K34 -> 95559 | L38: =L37+L34 -> 79107 | M38: =L38 -> 79107 | N38: =N37+N34 -> 76188 | O38: =O37+O34 -> 78909 | P38: =P37+P34 -> 294812 | Q38: =Q37+Q34 -> 287401 | R38: =Q38 -> 287401 | S38: =S37+S34 -> 281080 | T38: =T37+T34 -> 281348 | U38: =U37+U34 -> 267212 | V38: =V37+V34 -> 256322 | W38: =V38 -> 256322 | X38: =X37+X34 -> 241277 | Y38: =Y37+Y34 -> 232415 | Z38: =Z37+Z34 -> 230245 | AA38: =AA37+AA34 -> 231547 | AB38: =AA38 -> 231547 | AC38: =AC37+AC34 -> 217276 | AD38: =AD37+AD34 -> 198001 | AE38: =AE37+AE34 -> 194382 | AF38: =AF37+AF34 -> 180320 | AG38: =AF38 -> 180320 | AH38: =AH37+AH34 -> 168030 | AI38: =AI37+AI34 -> 164727 | AJ38: =AJ37+AJ34 -> 174761 | AK38: =AK37+AK34 -> 173639 | AL38: =AK38 -> 173639 | AM38: =AM37+AM34 -> 163556.46 | AN38: =AN37+AN34 -> 163404.71 | AO38: =AO37+AO34 -> 163427.4 | AP38: =AP37+AP34 -> 165001.39 | AQ38: =AP38 -> 165001.39
B39: Scott Berg, sberg@needhamco.com | AB39: Source: Company Reports and Needham & Company, LLC Estimates | AG39: Source: Company Reports and Needham & Company, LLC Estimates | AL39: Source: Company Reports and Needham & Company, LLC Estimates | AQ39: Source: Company Reports and Needham & Company, LLC Estimates
B40: 763.350.4027 | AB40: $ in thousands, except per share data | AG40: $ in thousands, except per share data | AL40: $ in thousands, except per share data | AQ40: $ in thousands, except per share data
C41: check | D41: =D17-D38 -> 0 | E41: =E17-E38 -> 0 | F41: =F17-F38 -> 0 | G41: =G17-G38 -> 0 | H41: =H17-H38 -> 0 | I41: =I17-I38 -> 0 | J41: =J17-J38 -> 0 | K41: =K17-K38 -> 0 | ... AQ41: =AQ17-AQ38 -> 0
C43: DSO | D43: =((D7+#REF!)/2)/IS!D11*91 -> #REF! | E43: =((E7+D7)/2)/IS!E11*91 -> 38.30774 | F43: =((F7+E7)/2)/IS!F11*91 -> 35.790073 | G43: =((G7+F7)/2)/IS!G11*91 -> 39.635328 | I43: =((I7+H7)/2)/IS!I11*91 -> 44.94243 | J43: =((J7+I7)/2)/IS!J11*91 -> 48.44519 | K43: =((K7+J7)/2)/IS!K11*91 -> 47.308487 | L43: =((L7+K7)/2)/IS!L11*91 -> 54.198739 | N43: =((N7+M7)/2)/IS!N11*91 -> 59.997728 | O43: =((O7+N7)/2)/IS!O11*91 -> 55.663468 | P43: =((P7+O7)/2)/IS!P11*91 -> 67.631222 | Q43: =((Q7+P7)/2)/IS!Q11*91 -> 59.10559 | S43: =((S7+R7)/2)/IS!S11*91 -> 60.287368 | T43: =((T7+S7)/2)/IS!T11*91 -> 66.460234 | U43: =((U7+T7)/2)/IS!U11*91 -> 61.387716 | V43: =((V7+U7)/2)/IS!V11*91 -> 62.822079 | X43: =((X7+W7)/2)/IS!X11*91 -> 63.961499 | Y43: =((Y7+X7)/2)/IS!Y11*91 -> 64.286206 | Z43: =((Z7+Y7)/2)/IS!Z11*91 -> 67.293592 | AA43: =((AA7+Z7)/2)/IS!AA11*91 -> 68.864865 | AC43: =((AC7+AB7)/2)/IS!AC11*91 -> 65.867617 | AD43: =((AD7+AC7)/2)/IS!AD11*91 -> 62.977156 | AE43: =((AE7+AD7)/2)/IS!AE11*91 -> 61.880301 | AF43: =((AF7+AE7)/2)/IS!AF11*91 -> 57.927985 | AH43: =((AH7+AG7)/2)/IS!AH11*91 -> 56.411658 | AI43: =((AI7+AH7)/2)/IS!AI11*91 -> 55.149019 | AJ43: =((AJ7+AI7)/2)/IS!AJ11*91 -> 53.478262 | AK43: =((AK7+AJ7)/2)/IS!AK11*91 -> 55.097095 | AM43: =((AM7+AL7)/2)/IS!AM11*91 -> 62.543404 | AN43: =((AN7+AM7)/2)/IS!AN11*91 -> 64.425102 | AO43: =((AO7+AN7)/2)/IS!AO11*91 -> 65.119076 | AP43: =((AP7+AO7)/2)/IS!AP11*91 -> 65.533386
B45: Deferred Revs | D45: =D25 -> 801 | E45: =E25 -> 681 | F45: =F25 -> 646 | G45: =G25 -> 1418 | I45: =I25 -> 1537 | J45: =J25 -> 1339 | K45: =K25 -> 1101 | L45: =L25 -> 1642 | N45: =N25 -> 2752 | O45: =O25 -> 1489 | P45: =P25 -> 1575 | Q45: =Q25 -> 2175 | S45: =S25 -> 3035 | T45: =T25 -> 2690 | U45: =U25 -> 2741 | V45: =V25 -> 4100 | X45: =X25 -> 4169 | Y45: =Y25 -> 3310 | Z45: =Z25 -> 2966 | AA45: =AA25 -> 4285 | AC45: =AC25 -> 3501 | AD45: =AD25 -> 3518 | AE45: =AE25 -> 3042 | AF45: =AF25 -> 4296 | AH45: =AH25 -> 3905 | AI45: =AI25 -> 3493 | AJ45: =AJ25 -> 4272 | AK45: =AK25 -> 5382 | AM45: =AM25 -> 3974.9896 | AN45: =AN25 -> 4230.338 | AO45: =AO25 -> 4404.1606 | AP45: =AP25 -> 5050.0789
C46: % y/y change | I46: =I45/D45-1 -> 0.91885144 | J46: =J45/E45-1 -> 0.96622614 | K46: =K45/F45-1 -> 0.70433437 | L46: =L45/G45-1 -> 0.15796897 | N46: =N45/I45-1 -> 0.79050098 | O46: =O45/J45-1 -> 0.1120239 | P46: =P45/K45-1 -> 0.43051771 | Q46: =Q45/L45-1 -> 0.32460414 | S46: =S45/N45-1 -> 0.1028343 | T46: =T45/O45-1 -> 0.8065816 | U46: =U45/P45-1 -> 0.74031746 | V46: =V45/Q45-1 -> 0.88505747 | X46: =X45/S45-1 -> 0.37364086 | Y46: =Y45/T45-1 -> 0.23048327 | Z46: =Z45/U45-1 -> 0.08208683 | AA46: =AA45/V45-1 -> 0.045121951 | AC46: =AC45/X45-1 -> -0.16023027 | AD46: =AD45/Y45-1 -> 0.062839879 | AE46: =AE45/Z45-1 -> 0.025623736 | AF46: =AF45/AA45-1 -> 0.0025670945 | AH46: =AH45/AC45-1 -> 0.1153956 | AI46: =AI45/AD45-1 -> -0.0071063104 | AJ46: =AJ45/AE45-1 -> 0.40433925 | AK46: =AK45/AF45-1 -> 0.2527933 | AM46: =AM45/AH45-1 -> 0.017923073 | AN46: =AN45/AI45-1 -> 0.21109018 | AO46: =AO45/AJ45-1 -> 0.03093647 | AP46: =AP45/AK45-1 -> -0.061672449
C47: % q/q change | E47: =E45/D45-1 -> -0.14981273 | F47: =F45/E45-1 -> -0.051395007 | G47: =G45/F45-1 -> 1.1950464 | I47: =I45/G45-1 -> 0.083921016 | J47: =J45/I45-1 -> -0.12882238 | K47: =K45/J45-1 -> -0.17774459 | L47: =L45/K45-1 -> 0.49137148 | N47: =N45/L45-1 -> 0.67600487 | O47: =O45/N45-1 -> -0.45893895 | P47: =P45/O45-1 -> 0.057756884 | Q47: =Q45/P45-1 -> 0.38095238 | S47: =S45/Q45-1 -> 0.3954023 | T47: =T45/S45-1 -> -0.11367381 | U47: =U45/T45-1 -> 0.018959108 | V47: =V45/U45-1 -> 0.49580445 | X47: =X45/V45-1 -> 0.016829268 | Y47: =Y45/X45-1 -> -0.20604462 | Z47: =Z45/Y45-1 -> -0.10392749 | AA47: =AA45/Z45-1 -> 0.44470668 | AC47: =AC45/AA45-1 -> -0.18296383 | AD47: =AD45/AC45-1 -> 0.0048557555 | AE47: =AE45/AD45-1 -> -0.13530415 | AF47: =AF45/AE45-1 -> 0.4122288 | AH47: =AH45/AF45-1 -> -0.091014898 | AI47: =AI45/AH45-1 -> -0.10550576 | AJ47: =AJ45/AI45-1 -> 0.22301746 | AK47: =AK45/AJ45-1 -> 0.25983146 | AM47: =AM45/AK45-1 -> -0.26142891 | AN47: =AN45/AM45-1 -> 0.064238759 | AO47: =AO45/AN45-1 -> 0.04108953 | AP47: =AP45/AO45-1 -> 0.14666093
B49: Drivers of Revenue % - Assets
C50: Accounts Receivable | D50: =D7/IS!D$11 -> 0.44247447 | E50: =E7/IS!E$11 -> 0.4357364 | F50: =F7/IS!F$11 -> 0.39724945 | G50: =G7/IS!G$11 -> 0.51768511 | I50: =I7/IS!I$11 -> 0.51787082 | J50: =J7/IS!J$11 -> 0.54880142 | K50: =K7/IS!K$11 -> 0.55656945 | L50: =L7/IS!L$11 -> 0.67299072 | N50: =N7/IS!N$11 -> 0.70758601 | O50: =O7/IS!O$11 -> 0.71733171 | P50: =P7/IS!P$11 -> 0.77644537 | Q50: =Q7/IS!Q$11 -> 0.61342798 | S50: =S7/IS!S$11 -> 0.72327956 | T50: =T7/IS!T$11 -> 0.72112133 | U50: =U7/IS!U$11 -> 0.64406091 | V50: =V7/IS!V$11 -> 0.69828196 | X50: =X7/IS!X$11 -> 0.71994325 | Y50: =Y7/IS!Y$11 -> 0.71703233 | Z50: =Z7/IS!Z$11 -> 0.7756346 | AA50: =AA7/IS!AA$11 -> 0.75521795 | AC50: =AC7/IS!AC$11 -> 0.68879143 | AD50: =AD7/IS!AD$11 -> 0.7036245 | AE50: =AE7/IS!AE$11 -> 0.66144598 | AF50: =AF7/IS!AF$11 -> 0.62480067 | AH50: =AH7/IS!AH$11 -> 0.60911794 | AI50: =AI7/IS!AI$11 -> 0.62617436 | AJ50: =AJ7/IS!AJ$11 -> 0.59221877 | AK50: =AK7/IS!AK$11 -> 0.62233125 | AM50: 0.73 | AN50: 0.73 | AO50: 0.73 | AP50: 0.74
C51: Other Current Assets | D51: =D9/IS!D$11 -> 0.16727693 | E51: =E9/IS!E$11 -> 0.11977001 | F51: =F9/IS!F$11 -> 0.074217515 | G51: =G9/IS!G$11 -> 0.094297166 | I51: =I9/IS!I$11 -> 0.071355629 | J51: =J9/IS!J$11 -> 0.065492465 | K51: =K9/IS!K$11 -> 0.069417231 | L51: =L9/IS!L$11 -> 0.071093506 | N51: =N9/IS!N$11 -> 0.068099001 | O51: =O9/IS!O$11 -> 0.14651234 | P51: =P9/IS!P$11 -> 0.21966906 | Q51: =Q9/IS!Q$11 -> 0.13706004 | S51: =S9/IS!S$11 -> 0.10624347 | T51: =T9/IS!T$11 -> 0.087511124 | U51: =U9/IS!U$11 -> 0.18671501 | V51: =V9/IS!V$11 -> 0.17137413 | X51: =X9/IS!X$11 -> 0.14730297 | Y51: =Y9/IS!Y$11 -> 0.10844323 | Z51: =Z9/IS!Z$11 -> 0.18006468 | AA51: =AA9/IS!AA$11 -> 0.16213418 | AC51: =AC9/IS!AC$11 -> 0.1514717 | AD51: =AD9/IS!AD$11 -> 0.1336481 | AE51: =AE9/IS!AE$11 -> 0.17421276 | AF51: =AF9/IS!AF$11 -> 0.12681424 | AH51: =AH9/IS!AH$11 -> 0.12165443 | AI51: =AI9/IS!AI$11 -> 0.11982365 | AJ51: =AJ9/IS!AJ$11 -> 0.14914832 | AK51: =AK9/IS!AK$11 -> 0.11503243 | AM51: 0.15 | AN51: 0.13 | AO51: 0.16 | AP51: 0.15
C52: Operating Lease Righ to Use Assets | D52: =D12/IS!D$11 -> 0 | I52: =I12/IS!I$11 -> 0.17953791 | J52: =J12/IS!J$11 -> 0.15692758 | K52: =K12/IS!K$11 -> 0.11756144 | L52: =L12/IS!L$11 -> 0.096424476 | N52: =N12/IS!N$11 -> 0.07609673 | O52: =O12/IS!O$11 -> 0.046163739 | P52: =P12/IS!P$11 -> 0.037348429 | Q52: =Q12/IS!Q$11 -> 0.02555457 | S52: =S12/IS!S$11 -> 0.017668562 | T52: =T12/IS!T$11 -> 0.32444379 | U52: =U12/IS!U$11 -> 0.29856418 | V52: =V12/IS!V$11 -> 0.30193318 | X52: =X12/IS!X$11 -> 0.28995744 | Y52: =Y12/IS!Y$11 -> 0.26619209 | Z52: =Z12/IS!Z$11 -> 0.24717397 | AA52: =AA12/IS!AA$11 -> 0.22782721 | AC52: =AC12/IS!AC$11 -> 0.22147255 | AD52: =AD12/IS!AD$11 -> 0.20474934 | AE52: =AE12/IS!AE$11 -> 0.18913031 | AF52: =AF12/IS!AF$11 -> 0.22670883 | AH52: =AH12/IS!AH$11 -> 0.21367964 | AI52: =AI12/IS!AI$11 -> 0.1907836 | AJ52: =AJ12/IS!AJ$11 -> 0.16373812 | AK52: =AK12/IS!AK$11 -> 0.14867261 | AM52: 0.2 | AN52: =AM52 -> 0.2 | AO52: =AN52 -> 0.2 | AP52: =AO52 -> 0.2
C53: Other Assets | D53: =D16/IS!D$11 -> 0.02158412 | E53: =(E17-E10)/IS!E11 -> 0.21203008 | F53: =(F17-F10)/IS!F11 -> 0.23695858 | G53: =(G17-G10)/IS!G11 -> 0.27923493 | I53: =I16/IS!I$11 -> 0.024061782 | J53: =J16/IS!J$11 -> 0.021682457 | K53: =K16/IS!K$11 -> 0.018250014 | L53: =L16/IS!L$11 -> 0.028093401 | N53: =N16/IS!N$11 -> 0.025318253 | O53: =O16/IS!O$11 -> 0.016956036 | P53: =P16/IS!P$11 -> 0.01788705 | Q53: =Q16/IS!Q$11 -> 0.010381544 | S53: =S16/IS!S$11 -> 0.011140768 | T53: =T16/IS!T$11 -> 0.021862949 | U53: =U16/IS!U$11 -> 0.021348803 | V53: =V16/IS!V$11 -> 0.018163936 | X53: =X16/IS!X$11 -> 0.02176341 | Y53: =Y16/IS!Y$11 -> 0.021035127 | Z53: =Z16/IS!Z$11 -> 0.020891166 | AA53: =AA16/IS!AA$11 -> 0.023026132 | AC53: =AC16/IS!AC$11 -> 0.022602682 | AD53: =AD16/IS!AD$11 -> 0.022441328 | AE53: =AE16/IS!AE$11 -> 0.022500414 | AF53: =AF16/IS!AF$11 -> 0.022162761 | AH53: =AH16/IS!AH$11 -> 0.022508389 | AI53: =AI16/IS!AI$11 -> 0.021702619 | AJ53: =AJ16/IS!AJ$11 -> 0.02003959 | AK53: =AK16/IS!AK$11 -> 0.020329844 | AM53: 0.02 | AN53: 0.02 | AO53: 0.02 | AP53: 0.02
B55: Drivers of Revenue % - Liabilities
C56: Accounts Payable | D56: =D20/IS!D$11 -> 0.11948352 | E56: =E20/IS!E$11 -> 0.2192835 | F56: =F20/IS!F$11 -> 0.19222257 | G56: =G20/IS!G$11 -> 0.28028971 | I56: =I20/IS!I$11 -> 0.26614756 | J56: =J20/IS!J$11 -> 0.31016723 | K56: =K20/IS!K$11 -> 0.29496725 | L56: =L20/IS!L$11 -> 0.18701136 | N56: =N20/IS!N$11 -> 0.20193081 | O56: =O20/IS!O$11 -> 0.20793989 | P56: =P20/IS!P$11 -> 0.26639646 | Q56: =Q20/IS!Q$11 -> 0.13859805 | S56: =S20/IS!S$11 -> 0.21889869 | T56: =T20/IS!T$11 -> 0.25407891 | U56: =U20/IS!U$11 -> 0.19849166 | V56: =V20/IS!V$11 -> 0.26078004 | X56: =X20/IS!X$11 -> 0.19756105 | Y56: =Y20/IS!Y$11 -> 0.14943401 | Z56: =Z20/IS!Z$11 -> 0.18558796 | AA56: =AA20/IS!AA$11 -> 0.14643836 | AC56: =AC20/IS!AC$11 -> 0.056085013 | AD56: =AD20/IS!AD$11 -> 0.11220664 | AE56: =AE20/IS!AE$11 -> 0.094027464 | AF56: =AF20/IS!AF$11 -> 0.10794886 | AH56: =AH20/IS!AH$11 -> 0.14757319 | AI56: =AI20/IS!AI$11 -> 0.081929355 | AJ56: =AJ20/IS!AJ$11 -> 0.060216525 | AK56: =AK20/IS!AK$11 -> 0.094435404 | AM56: 0.14 | AN56: 0.14 | AO56: 0.14 | AP56: 0.14
C57: Accrued Expenses | D57: =D21/IS!D$11 -> 0.054634804 | E57: =E21/IS!E$11 -> 0.063069438 | F57: =F21/IS!F$11 -> 0.063073032 | G57: =G21/IS!G$11 -> 0.075944026 | I57: =I21/IS!I$11 -> 0.10556548 | J57: =J21/IS!J$11 -> 0.048451707 | K57: =K21/IS!K$11 -> 0.036947881 | L57: =L21/IS!L$11 -> 0.033409778 | N57: =N21/IS!N$11 -> 0.036486678 | O57: =O21/IS!O$11 -> 0.094764274 | P57: =P21/IS!P$11 -> 0.10866216 | Q57: =Q21/IS!Q$11 -> 0.084117125 | S57: =S21/IS!S$11 -> 0.11071138 | T57: =T21/IS!T$11 -> 0.13672501 | U57: =U21/IS!U$11 -> 0.13714286 | V57: =V21/IS!V$11 -> 0.1446046 | X57: =X21/IS!X$11 -> 0.11156389 | Y57: =Y21/IS!Y$11 -> 0.12796126 | Z57: =Z21/IS!Z$11 -> 0.11907964 | AA57: =AA21/IS!AA$11 -> 0.15393655 | AC57: =AC21/IS!AC$11 -> 0.17826319 | AD57: =AD21/IS!AD$11 -> 0.15156228 | AE57: =AE21/IS!AE$11 -> 0.16122539 | AF57: =AF21/IS!AF$11 -> 0.16073407 | AH57: =AH21/IS!AH$11 -> 0.10643058 | AI57: =AI21/IS!AI$11 -> 0.16236288 | AJ57: =AJ21/IS!AJ$11 -> 0.12681151 | AK57: =AK21/IS!AK$11 -> 0.15867965 | AM57: 0.14 | AN57: 0.14 | AO57: 0.14 | AP57: 0.145
C58: Accrued Salary and Benefits | D58: =D23/IS!D$11 -> 0.11312392 | E58: =E23/IS!E$11 -> 0.31393189 | F58: =F23/IS!F$11 -> 0.31631363 | G58: =G23/IS!G$11 -> 0.19147739 | I58: =I23/IS!I$11 -> 0.15732704 | J58: =J23/IS!J$11 -> 0.17867362 | K58: =K23/IS!K$11 -> 0.2216313 | L58: =L23/IS!L$11 -> 0.27311581 | N58: =N23/IS!N$11 -> 0.1393687 | O58: =O23/IS!O$11 -> 0.16441602 | P58: =P23/IS!P$11 -> 0.22693776 | Q58: =Q23/IS!Q$11 -> 0.23528542 | S58: =S23/IS!S$11 -> 0.13064292 | T58: =T23/IS!T$11 -> 0.17256007 | U58: =U23/IS!U$11 -> 0.18381436 | V58: =V23/IS!V$11 -> 0.10867628 | X58: =X23/IS!X$11 -> 0.11929126 | Y58: =Y23/IS!Y$11 -> 0.14949236 | Z58: =Z23/IS!Z$11 -> 0.15814326 | AA58: =AA23/IS!AA$11 -> 0.17430474 | AC58: =AC23/IS!AC$11 -> 0.088105479 | AD58: =AD23/IS!AD$11 -> 0.15311762 | AE58: =AE23/IS!AE$11 -> 0.18794463 | AF58: =AF23/IS!AF$11 -> 0.24668234 | AH58: =AH23/IS!AH$11 -> 0.10072845 | AI58: =AI23/IS!AI$11 -> 0.15244318 | AJ58: =AJ23/IS!AJ$11 -> 0.19440847 | AK58: =AK23/IS!AK$11 -> 0.25398946 | AM58: 0.17 | AN58: 0.17 | AO58: 0.165 | AP58: 0.17
C59: Deferred Revenue | D59: =D25/IS!D$11 -> 0.077182501 | E59: =E25/IS!E$11 -> 0.060238832 | F59: =F25/IS!F$11 -> 0.051059121 | G59: =G25/IS!G$11 -> 0.099711694 | I59: =I25/IS!I$11 -> 0.098098034 | J59: =J25/IS!J$11 -> 0.085140205 | K59: =K25/IS!K$11 -> 0.061635783 | L59: =L25/IS!L$11 -> 0.085583238 | N59: =N25/IS!N$11 -> 0.1302352 | O59: =O25/IS!O$11 -> 0.050394287 | P59: =P25/IS!P$11 -> 0.05275675 | Q59: =Q25/IS!Q$11 -> 0.06433008 | S59: =S25/IS!S$11 -> 0.088052687 | T59: =T25/IS!T$11 -> 0.079798279 | U59: =U25/IS!U$11 -> 0.079506889 | V59: =V25/IS!V$11 -> 0.12601039 | X59: =X25/IS!X$11 -> 0.12584141 | Y59: =Y25/IS!Y$11 -> 0.096569028 | Z59: =Z25/IS!Z$11 -> 0.084881092 | AA59: =AA25/IS!AA$11 -> 0.11988697 | AC59: =AC25/IS!AC$11 -> 0.098422873 | AD59: =AD25/IS!AD$11 -> 0.097708652 | AE59: =AE25/IS!AE$11 -> 0.083880218 | AF59: =AF25/IS!AF$11 -> 0.11611125 | AH59: =AH25/IS!AH$11 -> 0.10653971 | AI59: =AI25/IS!AI$11 -> 0.091665355 | AJ59: =AJ25/IS!AJ$11 -> 0.10440138 | AK59: =AK25/IS!AK$11 -> 0.13072308 | AM59: 0.1 | AN59: 0.1 | AO59: 0.1 | AP59: 0.11

Sheet CF
B2: =IS!B2 -> CS DISCO (LAW) | T2: =+T25-S25 -> 590 | U2: =U25-P25 -> -5856 | AJ2: =AJ25-AE25 -> 1878 | AK2: =AK25-AF25 -> -1326
B4: Cash Flow Statement | D4: 1Q19 | E4: 2Q19 | F4: 3Q19 | G4: 4Q19 | H4: 2019 | I4: 1Q20 | J4: 2Q20 | K4: 3Q20 | L4: 4Q20 | M4: =IS!M4 -> 2020 | N4: =IS!N4 -> 1Q21 | O4: =IS!O4 -> 2Q21 | P4: =IS!P4 -> 3Q21 | Q4: =IS!Q4 -> 4Q21 | R4: =IS!R4 -> 2021 | S4: =IS!S4 -> 1Q22 | T4: =IS!T4 -> 2Q22 | ... AQ4: =IS!AQ4 -> 2026E
B5: Operating Activities
B7: Net loss | D7: =IS!D62 -> -6952 | E7: =IS!E62 -> -7051 | F7: =IS!F62 -> -7661 | G7: =IS!G62 -> -8168 | H7: =IS!H62 -> -29832 | I7: =IS!I62 -> -11236 | J7: =IS!J62 -> -5477 | K7: =IS!K62 -> -3169 | ... Q7: =IS!Q62 -> -9108 | R7: =SUM(N7:Q7) -> -24344 | S7: =IS!S62 -> -11849 | T7: =+-32020-S7 -> -20171 | U7: =-52077-T7-S7 -> -20057 | V7: =-70765-U7-T7-S7 -> -18688 | W7: =SUM(S7:V7) -> -70765 | X7: -20365 | Y7: =+-35280-X7 -> -14915 | Z7: =+-36310-Y7-X7 -> -1030 | AA7: =+-42150-Z7-Y7-X7 -> -5840 | AB7: =SUM(X7:AA7) -> -42150 | AC7: =IS!AC62 -> -10582 | AD7: =IS!AD62 -> -10834 | AE7: =IS!AE62 -> -9158 | AF7: =IS!AF62 -> -25200 | AG7: -55774 | AH7: =IS!AH62 -> -11393 | AI7: =IS!AI62 -> -10812 | AJ7: =IS!AJ62 -> -13665 | AK7: =IS!AK62 -> -8502 | AL7: =SUM(AH7:AK7) -> -44372 | AM7: =IS!AM62 -> -11061.985 | AN7: =IS!AN62 -> -7319.169 | AO7: =IS!AO62 -> -6423.1234 | AP7: =IS!AP62 -> -6160.3765 | AQ7: =SUM(AM7:AP7) -> -30964.654
R8: =SUM(N8:Q8) -> 0 | W8: =SUM(S8:V8) -> 0 | AB8: =SUM(X8:AA8) -> 0 | AQ8: =SUM(AM8:AP8) -> 0
B9: Adjustments to reconcile net cash
C10: Depreciation & Amortization | D10: 120 | E10: 176 | F10: 247 | G10: 260 | H10: =SUM(D10:G10) -> 803 | I10: 378 | J10: 421 | K10: 415 | L10: 410 | M10: =SUM(I10:L10) -> 1624 | N10: 424 | O10: =830-N10 -> 406 | P10: =1254-O10-N10 -> 424 | Q10: =1674-P10-O10-N10 -> 420 | R10: =SUM(N10:Q10) -> 1674 | S10: 455 | T10: =1155-S10 -> 700 | U10: =2079-T10-S10 -> 924 | V10: =2974-U10-T10-S10 -> 895 | W10: =SUM(S10:V10) -> 2974 | X10: 952 | Y10: =1957-X10 -> 1005 | Z10: =3011-Y10-X10 -> 1054 | AA10: =4159-Z10-Y10-X10 -> 1148 | AB10: =SUM(X10:AA10) -> 4159 | AC10: 1075 | AD10: =2103-AC10 -> 1028 | AE10: 989 | AF10: =AG10-SUM(AC10:AE10) -> 834 | AG10: 3926 | AH10: 927 | AI10: 902 | AJ10: 902 | AK10: =AL10-SUM(AH10:AJ10) -> 927 | AL10: 3658 | AM10: =AM58 -> 872.045 | AN10: =AN58 -> 869.50982 | AO10: =AO58 -> 878.7662 | AP10: =AP58 -> 886.95808 | AQ10: =SUM(AM10:AP10) -> 3507.2791
C11: Stock-based compensation | D11: 2638 | E11: 531 | F11: 456 | G11: 495 | H11: =SUM(D11:G11) -> 4120 | I11: 488 | J11: 500 | K11: 502 | L11: 503 | M11: =SUM(I11:L11) -> 1993 | N11: 488 | O11: =1454-N11 -> 966 | P11: =2508-O11-N11 -> 1054 | Q11: =5603-P11-O11-N11 -> 3095 | R11: =SUM(N11:Q11) -> 5603 | S11: 3206 | T11: =8728-S11 -> 5522 | U11: =14393-T11-S11 -> 5665 | V11: =21737-U11-T11-S11 -> 7344 | W11: =SUM(S11:V11) -> 21737 | X11: 7224 | Y11: =14092-X11 -> 6868 | Z11: =11211-Y11-X11 -> -2881 | AA11: =16158-Z11-Y11-X11 -> 4947 | AB11: =SUM(X11:AA11) -> 16158 | AC11: 5673 | AD11: =11731-AC11 -> 6058 | AE11: 5147 | AF11: =AG11-SUM(AC11:AE11) -> 5391 | AG11: 22269 | AH11: 5879 | AI11: 6478 | AJ11: 6090 | AK11: =AL11-SUM(AH11:AJ11) -> 6017 | AL11: 24464 | AM11: =IS!AM31 -> 6000 | AN11: =IS!AN31 -> 6000 | AO11: =IS!AO31 -> 6000 | AP11: =IS!AP31 -> 6000 | AQ11: =SUM(AM11:AP11) -> 24000
C12: Charge to Allowance for Credit Losses | D12: 89 | E12: 89 | F12: 89 | G12: 89 | H12: =SUM(D12:G12) -> 356 | I12: 135 | J12: 115 | K12: 77 | L12: 124 | M12: =SUM(I12:L12) -> 451 | N12: 130 | O12: =251-N12 -> 121 | P12: =517-O12-N12 -> 266 | Q12: =833-P12-O12-N12 -> 316 | R12: =SUM(N12:Q12) -> 833 | S12: 180 | T12: =367-S12 -> 187 | U12: =853-T12-S12 -> 486 | V12: =1294-U12-T12-S12 -> 441 | W12: =SUM(S12:V12) -> 1294 | X12: 831 | Y12: =1356-X12 -> 525 | Z12: =1801-Y12-X12 -> 445 | AA12: =2432-Z12-Y12-X12 -> 631 | AB12: =SUM(X12:AA12) -> 2432 | AC12: 564 | AD12: =1126-AC12 -> 562 | AE12: 933 | AF12: =AG12-SUM(AC12:AE12) -> 53 | AG12: 2112 | AH12: 534 | AI12: 563 | AJ12: 577 | AK12: =AL12-SUM(AH12:AJ12) -> 213 | AL12: 1887 | AM12: 257 | AN12: 271 | AO12: 288 | AP12: 306 | AQ12: =SUM(AM12:AP12) -> 1122
C13: Loss on Disposal of Long-Lived Assets | D13: 0 | E13: 0 | F13: 0 | G13: 12 | H13: =SUM(D13:G13) -> 12 | I13: 0 | J13: 0 | K13: 0 | L13: 6 | M13: =SUM(I13:L13) -> 6 | N13: 0 | O13: 0 | P13: 0 | Q13: =-1-P13-O13-N13 -> -1 | R13: =SUM(N13:Q13) -> -1 | S13: 0 | T13: -1 | U13: =-1-T13 -> 0 | V13: 0 | W13: =SUM(S13:V13) -> -1 | X13: 0 | Y13: =1-X13 -> 1 | Z13: =1-Y13 -> 0 | AA13: =41-Z13-Y13-X13 -> 40 | AB13: =SUM(X13:AA13) -> 41 | AC13: 0 | AD13: =+-2 -> -2 | AE13: -1 | AF13: =AG13-SUM(AC13:AE13) -> -1 | AG13: -4 | AK13: =AL13-SUM(AH13:AJ13) -> 0 | AM13: 0 | AN13: 0 | AO13: 0 | AP13: 0 | AQ13: =SUM(AM13:AP13) -> 0
C14: Non-Cash Operating Lease Costs | D14: 0 | E14: 0 | F14: 0 | G14: 0 | H14: =SUM(D14:G14) -> 0 | I14: 374 | J14: 346 | K14: 368 | L14: 249 | M14: =SUM(I14:L14) -> 1337 | N14: 242 | O14: =487-N14 -> 245 | P14: =735-O14-N14 -> 248 | Q14: =986-P14-O14-N14 -> 251 | R14: =SUM(N14:Q14) -> 986 | S14: 255 | T14: =513-S14 -> 258 | U14: =983-T14-S14 -> 470 | V14: =1452-U14-T14-S14 -> 469 | W14: =SUM(S14:V14) -> 1452 | X14: 218 | Y14: =699-X14 -> 481 | Z14: =1187-Y14-X14 -> 488 | AA14: =1681-Z14-Y14-X14 -> 494 | AB14: =SUM(X14:AA14) -> 1681 | AC14: 265 | AD14: =771-AC14 -> 506 | AE14: 513 | AF14: =AG14-SUM(AC14:AE14) -> 529 | AG14: 1813 | AH14: 556 | AI14: 562 | AJ14: 570 | AK14: =AL14-SUM(AH14:AJ14) -> 578 | AL14: 2266 | AM14: 262 | AN14: 262 | AO14: 262 | AP14: 262 | AQ14: =SUM(AM14:AP14) -> 1048
C15: Other | D15: 9 | E15: 10 | F15: 10 | G15: 9 | H15: =SUM(D15:G15) -> 38 | I15: 9 | J15: 10 | K15: 9 | L15: 42 | M15: =SUM(I15:L15) -> 70 | N15: 21 | O15: 20 | P15: 22 | Q15: 177 | R15: =SUM(N15:Q15) -> 240 | S15: 0 | T15: 798 | U15: 329 | V15: 540 | W15: =SUM(S15:V15) -> 1667 | X15: 0 | Y15: 0 | Z15: 0 | AA15: 500 | AB15: =SUM(X15:AA15) -> 500 | AC15: 0 | AD15: 0 | AE15: =((-256+9)-0)-0 -> -247 | AF15: =AG15-SUM(AC15:AE15) -> 14706 | AG15: =-1057+15213+303 -> 14459 | AH15: =-828-142 -> -970 | AI15: =(-1707-103)--970 -> -840 | AJ15: =((-2568+93)--840)--970 -> -665 | AK15: =AL15-SUM(AH15:AJ15) -> -1162 | AL15: =-3444-193 -> -3637 | AQ15: =SUM(AM15:AP15) -> 0
B16: Net Change in Working Capital | H16: =SUM(D16:G16) -> 0 | AF16: =AG16-SUM(AC16:AE16) -> 0 | AK16: =AL16-SUM(AH16:AJ16) -> 0
C17: AR | D17: -1528 | E17: -422 | F17: -189 | G17: -2425 | H17: =SUM(D17:G17) -> -4564 | I17: -932 | J17: -631 | K17: -1387 | L17: -3051 | M17: =SUM(I17:L17) -> -6001 | N17: -2171 | O17: =-8534-N17 -> -6363 | P17: =-10786-O17-N17 -> -2252 | Q17: =-8662-P17-O17-N17 -> 2124 | R17: =SUM(N17:Q17) -> -8662 | S17: -4370 | T17: =+-3935-S17 -> 435 | U17: =-2317-T17-S17 -> 1618 | V17: =+-3274-U17-T17-S17 -> -957 | W17: =SUM(S17:V17) -> -3274 | X17: -1963 | Y17: =+-3214-X17 -> -1251 | Z17: =+-6184-Y17-X17 -> -2970 | AA17: =+-6705-Z17-Y17-X17 -> -521 | AB17: =SUM(X17:AA17) -> -6705 | AC17: 1927 | AD17: =533-AC17 -> -1394 | AE17: 413 | AF17: =AG17-SUM(AC17:AE17) -> 818 | AG17: 1764 | AH17: 258 | AI17: -2098 | AJ17: -950 | AK17: =AL17-SUM(AH17:AJ17) -> -1602 | AL17: -4392 | AM17: =BS!AL7-BS!AM7 -> -3395.4241 | AN17: =BS!AM7-BS!AN7 -> -1864.0433 | AO17: =BS!AN7-BS!AO7 -> -1268.905 | AP17: =BS!AO7-BS!AP7 -> -1822.8855 | AQ17: =SUM(AM17:AP17) -> -8351.2579
C18: Other current assets | D18: -613 | E18: 382 | F18: 414 | G18: -401 | H18: =SUM(D18:G18) -> -218 | I18: 223 | J18: 119 | K18: -219 | L18: -147 | M18: =SUM(I18:L18) -> -24 | N18: -75 | O18: =-819-N18 -> -744 | P18: =-4391-O18-N18 -> -3572 | Q18: =-3168-P18-O18-N18 -> 1223 | R18: =SUM(N18:Q18) -> -3168 | S18: 965 | T18: =1671-S18 -> 706 | U18: =-1831-T18-S18 -> -3502 | V18: =+-989-U18-T18-S18 -> 842 | W18: =SUM(S18:V18) -> -989 | X18: 676 | Y18: =1819-X18 -> 1143 | Z18: =+-775-Y18-X18 -> -2594 | AA18: =+-310-Z18-Y18-X18 -> 465 | AB18: =SUM(X18:AA18) -> -310 | AC18: 409 | AD18: =984-AC18 -> 575 | AE18: -1507 | AF18: =AG18-SUM(AC18:AE18) -> 1626 | AG18: 1103 | AH18: 232 | AI18: -107 | AJ18: =((-9240-1413)--107)-232 -> -10778 | AK18: =AL18-SUM(AH18:AJ18) -> 2571 | AL18: =-8039-43 -> -8082 | AM18: =BS!AL9-BS!AM9 -> -1226.4844 | AN18: =BS!AM9-BS!AN9 -> 463.045 | AO18: =BS!AN9-BS!AO9 -> -1547.2176 | AP18: =BS!AO9-BS!AP9 -> 160.18576 | AQ18: =SUM(AM18:AP18) -> -2150.4712
C19: Other Long-Term Assets | D19: -1 | E19: -76 | F19: 2 | G19: -10 | H19: =SUM(D19:G19) -> -85 | I19: -5 | J19: 0 | K19: 17 | L19: 19 | M19: =SUM(I19:L19) -> 31 | N19: 0 | P19: =-40-O19-N19 -> -40 | Q19: =-24-P19-O19-N19 -> 16 | R19: =SUM(N19:Q19) -> -24 | S19: -39 | T19: =+-387-S19 -> -348 | U19: =-387-T19-S19 -> 0 | V19: =+-237-U19-T19-S19 -> 150 | W19: =SUM(S19:V19) -> -237 | X19: -124 | Y19: =+-124-X19 -> 0 | Z19: =+-124-Y19-X19 -> 0 | AA19: =+-226-Z19-Y19-X19 -> -102 | AB19: =SUM(X19:AA19) -> -226 | AC19: 17 | AD19: =14-AC19 -> -3 | AE19: 0 | AF19: =AG19-SUM(AC19:AE19) -> -21 | AG19: -7 | AJ19: 0 | AK19: =AL19-SUM(AH19:AJ19) -> -36 | AL19: -36
C20: AP | D20: -467 | E20: 1238 | F20: -47 | G20: 1554 | H20: =SUM(D20:G20) -> 2278 | I20: 184 | J20: 709 | K20: 391 | L20: -1681 | M20: =SUM(I20:L20) -> -397 | N20: 679 | O20: =1513-N20 -> 834 | P20: =3829-O20-N20 -> 2316 | Q20: =1091-P20-O20-N20 -> -2738 | R20: =SUM(N20:Q20) -> 1091 | S20: 2773 | T20: =2966-S20 -> 193 | U20: =2058-T20-S20 -> -908 | V20: =3186-U20-T20-S20 -> 1128 | W20: =SUM(S20:V20) -> 3186 | X20: -1765 | Y20: =+-3186-X20 -> -1421 | Z20: =+-1928-Y20-X20 -> 1258 | AA20: =+-4091-Z20-Y20-X20 -> -2163 | AB20: =SUM(X20:AA20) -> -4091 | AC20: -2838 | AD20: =+-816-AC20 -> 2022 | AE20: -616 | AF20: =AG20-SUM(AC20:AE20) -> 583 | AG20: -849 | AH20: 1536 | AI20: -2285 | AJ20: 116 | AK20: =AL20-SUM(AH20:AJ20) -> 770 | AL20: 137 | AM20: =BS!AM20-BS!AK20 -> 1676.9854 | AN20: =BS!AN20-BS!AM20 -> 357.48776 | AO20: =BS!AO20-BS!AN20 -> 243.35164 | AP20: =BS!AP20-BS!AO20 -> 261.54828 | AQ20: =SUM(AM20:AP20) -> 2539.3731
C21: Accrued Expenses and Other | D21: -2619 | E21: 2350 | F21: 562 | G21: -1087 | H21: =SUM(D21:G21) -> -794 | I21: 543 | J21: -548 | K21: 1047 | L21: 1221 | M21: =SUM(I21:L21) -> 2263 | N21: -2167 | O21: =1268-N21 -> 3435 | P21: =3578-O21-N21 -> 2310 | Q21: =4615-P21-O21-N21 -> 1037 | R21: =SUM(N21:Q21) -> 4615 | S21: -3253 | T21: =+-1703-S21 -> 1550 | U21: =-1474-T21-S21 -> 229 | V21: =+-4199-U21-T21-S21 -> -2725 | W21: =SUM(S21:V21) -> -4199 | X21: -248 | Y21: =1616-X21 -> 1864 | Z21: =1791-Y21-X21 -> 175 | AA21: =4226-Z21-Y21-X21 -> 2435 | AB21: =SUM(X21:AA21) -> 4226 | AC21: -2738 | AD21: =-1365-AC21 -> 1373 | AE21: 1720 | AF21: =AG21-SUM(AC21:AE21) -> 2130 | AG21: 2485 | AH21: -7159 | AI21: 4443 | AJ21: 1228 | AK21: =AL21-SUM(AH21:AJ21) -> 3773 | AL21: 2285 | AM21: =BS!AM21-BS!AL21+BS!AM23-BS!AL23 -> -4667.5322 | AN21: =BS!AN21-BS!AM21+BS!AN23-BS!AM23 -> 791.58004 | AO21: =BS!AO21-BS!AN21+BS!AO23-BS!AN23 -> 318.64203 | AP21: =BS!AP21-BS!AO21+BS!AP23-BS!AO23 -> 1028.8997 | AQ21: =SUM(AM21:AP21) -> -2528.4105
C22: Deferred Revenue | D22: -30 | E22: -120 | F22: -35 | G22: 772 | H22: =SUM(D22:G22) -> 587 | I22: 119 | J22: -198 | K22: -238 | L22: 541 | M22: =SUM(I22:L22) -> 224 | N22: 1110 | O22: =-153-N22 -> -1263 | P22: =-67-O22-N22 -> 86 | Q22: =533-P22-O22-N22 -> 600 | R22: =SUM(N22:Q22) -> 533 | S22: 556 | T22: =211-S22 -> -345 | U22: =261-T22-S22 -> 50 | V22: =1621-U22-T22-S22 -> 1360 | W22: =SUM(S22:V22) -> 1621 | X22: 69 | Y22: =+-790-X22 -> -859 | Z22: =+-1134-Y22-X22 -> -344 | AA22: =185-Z22-Y22-X22 -> 1319 | AB22: =SUM(X22:AA22) -> 185 | AC22: -784 | AD22: =-767-AC22 -> 17 | AE22: -476 | AF22: =AG22-SUM(AC22:AE22) -> 1254 | AG22: 11 | AH22: -391 | AI22: -412 | AJ22: 779 | AK22: =AL22-SUM(AH22:AJ22) -> 1110 | AL22: 1086 | AM22: =BS!AM25-BS!AL25 -> -1407.0104 | AN22: =BS!AN25-BS!AM25 -> 255.3484 | AO22: =BS!AO25-BS!AN25 -> 173.8226 | AP22: =BS!AP25-BS!AO25 -> 645.91828 | AQ22: =SUM(AM22:AP22) -> -331.92112
C23: Operating Lease Liabilities | D23: 0 | E23: 0 | F23: 0 | G23: 0 | H23: =SUM(D23:G23) -> 0 | I23: -394 | J23: -366 | K23: -398 | L23: -258 | M23: =SUM(I23:L23) -> -1416 | N23: -249 | O23: =-502-N23 -> -253 | P23: =-758-O23-N23 -> -256 | Q23: =-1018-P23-O23-N23 -> -260 | R23: =SUM(N23:Q23) -> -1018 | S23: -263 | T23: =+-525-S23 -> -262 | U23: =-469-T23-S23 -> 56 | V23: =+-614-U23-T23-S23 -> -145 | W23: =SUM(S23:V23) -> -614 | X23: -242 | Y23: =+-722-X23 -> -480 | Z23: =+-1207-Y23-X23 -> -485 | AA23: =+-1710-Z23-Y23-X23 -> -503 | AB23: =SUM(X23:AA23) -> -1710 | AC23: -278 | AD23: =-796-AC23 -> -518 | AE23: -527 | AF23: =AG23-SUM(AC23:AE23) -> -555 | AG23: -1878 | AH23: -466 | AI23: -596 | AJ23: -604 | AK23: =AL23-SUM(AH23:AJ23) -> -622 | AL23: -2288 | AM23: -270 | AN23: -270 | AO23: -270 | AP23: -270 | AQ23: =SUM(AM23:AP23) -> -1080
C24: Other Liabilities | T24: -16 | U24: =149-T24 -> 165 | V24: =134-U24-T24 -> -15 | W24: =SUM(S24:V24) -> 134 | X24: -15 | Y24: =+-30-X24 -> -15 | Z24: =+-46-Y24-X24 -> -16 | AA24: =279-Z24-Y24-X24 -> 325 | AB24: =SUM(X24:AA24) -> 279 | AC24: -40 | AD24: =-80-AC24 -> -40 | AE24: -40 | AF24: =AG24-SUM(AC24:AE24) -> -59 | AG24: -179 | AH24: -41 | AI24: -19 | AJ24: =((15500-139)--19)--41 -> 15421 | AK24: =AL24-SUM(AH24:AJ24) -> -3273 | AL24: =588+11500 -> 12088 | AQ24: =SUM(AM24:AP24) -> 0
B25: Cash Flow from Operating Activites | D25: =SUM(D7:D23) -> -9354 | E25: =SUM(E7:E23) -> -2893 | F25: =SUM(F7:F23) -> -6152 | G25: =SUM(G7:G23) -> -8900 | H25: =SUM(H7:H24) -> -27299 | I25: =SUM(I7:I24) -> -10114 | J25: =SUM(J7:J24) -> -5000 | K25: =SUM(K7:K24) -> -2585 | L25: =SUM(L7:L24) -> -5013 | M25: =SUM(M7:M24) -> -22712 | N25: =SUM(N7:N24) -> -4496 | O25: =SUM(O7:O24) -> -5679 | ... AQ25: =SUM(AQ7:AQ24) -> -13190.062
C26: OCF Margins | D26: =D25/IS!D11 -> -0.90132974 | E26: =E25/IS!E11 -> -0.25590447 | F26: =F25/IS!F11 -> -0.48624723 | G26: =G25/IS!G11 -> -0.62583503 | H26: =H25/IS!H11 -> -0.56221682 | I26: =I25/IS!I11 -> -0.64551953 | J26: =J25/IS!J11 -> -0.31792459 | K26: =K25/IS!K11 -> -0.14471253 | ... AQ26: =AQ25/IS!AQ11 -> -0.076684316
B28: Investing Activites
C29: Purchases of PPE and capitalized internal-use software | D29: -614 | E29: -608 | F29: -859 | G29: -1244 | H29: =SUM(D29:G29) -> -3325 | I29: -663 | J29: -331 | K29: -393 | L29: -517 | M29: =SUM(I29:L29) -> -1904 | N29: -586 | O29: =-1447-N29 -> -861 | P29: =-2335-O29-N29 -> -888 | Q29: =-3107-P29-O29-N29 -> -772 | R29: =SUM(N29:Q29) -> -3107 | S29: -631 | T29: =+-1868-S29 -> -1237 | U29: =-3727-T29-S29 -> -1859 | V29: =-4378-U29-T29-S29 -> -651 | W29: =SUM(S29:V29) -> -4378 | X29: -844 | Y29: =+-2497-X29 -> -1653 | Z29: =+-3587-Y29-X29 -> -1090 | AA29: =+-4859-Z29-Y29-X29 -> -1272 | AB29: =SUM(X29:AA29) -> -4859 | AC29: -688 | AD29: =-1346-AC29 -> -658 | AE29: =-2223-AD29-AC29 -> -877 | AF29: =AG29-SUM(AC29:AE29) -> -558 | AG29: -2781 | AH29: -525 | AI29: =-1490-AH29 -> -965 | AJ29: =-2546-AI29-AH29 -> -1056 | AK29: =AL29-SUM(AH29:AJ29) -> -507 | AL29: -3053 | AM29: -850 | AN29: -950 | AO29: -950 | AP29: -950 | AQ29: =SUM(AM29:AP29) -> -3700
C30: Purchase of primary law intangible asset | Z30: =+-14000 -> -14000 | AA30: =+-14000-Z30 -> 0 | AB30: =SUM(X30:AA30) -> -14000 | AF30: =AG30-SUM(AC30:AE30) -> 0 | AK30: =AL30-SUM(AH30:AJ30) -> 0 | AQ30: =SUM(AM30:AP30) -> 0
C31: Proceeds from disposal of equipment | Y31: =1-X31 -> 1 | Z31: =1-Y31-X31 -> 0 | AA31: =4-Y31 -> 3 | AB31: =SUM(X31:AA31) -> 4 | AD31: 2 | AE31: =3-AD31 -> 1 | AF31: =AG31-SUM(AC31:AE31) -> 1 | AG31: 4 | AH31: 2 | AI31: =4-AH31 -> 2 | AJ31: =6-AI31-AH31 -> 2 | AK31: =AL31-SUM(AH31:AJ31) -> 2 | AL31: 8 | AQ31: =SUM(AM31:AP31) -> 0
C32: Changes in ST investments | AE32: -49937 | AF32: =AG32-SUM(AC32:AE32) -> -25321 | AG32: =-87937+12679 -> -75258 | AH32: =-45436+38303 -> -7133 | AI32: =-91940+77138-AH32 -> -7669 | AJ32: =+-155427+149639-AI32-AH32 -> 9014 | AK32: =AL32-SUM(AH32:AJ32) -> -9363 | AL32: =-206095+190944 -> -15151 | AQ32: =SUM(AM32:AP32) -> 0
C33: Cash paid for acquisitions | H33: =SUM(D33:G33) -> 0 | M33: =SUM(I33:L33) -> 0 | R33: =SUM(N33:Q33) -> 0 | S33: -5310 | T33: =+-5310-S33 -> 0 | U33: =-5310-T33-S33 -> 0 | V33: =-5310-U33-T33-S33 -> 0 | W33: =SUM(S33:V33) -> -5310 | X33: -1180 | Y33: =+-1180-X33 -> 0 | Z33: =+-1180-Y33-X33 -> 0 | AA33: =+-1180-Z33-Y33-X33 -> 0 | AB33: =SUM(X33:AA33) -> -1180 | AF33: =AG33-SUM(AC33:AE33) -> 0 | AK33: =AL33-SUM(AH33:AJ33) -> 0 | AQ33: =SUM(AM33:AP33) -> 0
B34: Cash Used in Investing Activites | D34: =SUM(D29:D29) -> -614 | E34: =SUM(E29:E29) -> -608 | F34: =SUM(F29:F29) -> -859 | G34: =SUM(G29:G29) -> -1244 | H34: =SUM(H29:H33) -> -3325 | I34: =SUM(I29:I33) -> -663 | J34: =SUM(J29:J33) -> -331 | K34: =SUM(K29:K33) -> -393 | L34: =SUM(L29:L33) -> -517 | M34: =SUM(M29:M33) -> -1904 | N34: =SUM(N29:N33) -> -586 | O34: =SUM(O29:O33) -> -861 | ... AQ34: =SUM(AQ29:AQ33) -> -3700
B36: Free Cash Flow | D36: =D25+D29 -> -9968 | E36: =E25+E29 -> -3501 | F36: =F25+F29 -> -7011 | G36: =G25+G29 -> -10144 | H36: =H25+H29 -> -30624 | I36: =I25+I29 -> -10777 | J36: =J25+J29 -> -5331 | K36: =K25+K29 -> -2978 | ... AQ36: =AQ25+AQ29 -> -16890.062
C37: FCF Margin | D37: =D36/IS!D11 -> -0.96049335 | E37: =E36/IS!E11 -> -0.30968598 | F37: =F36/IS!F11 -> -0.55414164 | G37: =G36/IS!G11 -> -0.7133113 | H37: =H36/IS!H11 -> -0.63069446 | I37: =I36/IS!I11 -> -0.68783508 | J37: =J36/IS!J11 -> -0.3389712 | K37: =K36/IS!K11 -> -0.16671332 | ... AQ37: =AQ36/IS!AQ11 -> -0.098195357
B39: Financing Activities
C40: Issuance and Repayment of Debt | D40: -5784 | E40: 0 | F40: 0 | G40: 0 | H40: =SUM(D40:G40) -> -5784 | I40: 17000 | J40: 0 | K40: 0 | L40: -17176 | M40: =SUM(I40:L40) -> -176 | R40: =SUM(N40:Q40) -> 0 | W40: =SUM(S40:V40) -> 0 | AB40: =SUM(X40:AA40) -> 0
C41: Proceeds from Exercise of Stock Options | D41: 28 | E41: 21 | F41: 51 | G41: 23 | H41: =SUM(D41:G41) -> 123 | I41: 8 | J41: 8 | K41: 263 | L41: 168 | M41: =SUM(I41:L41) -> 447 | N41: 222 | O41: =835-N41 -> 613 | P41: =1598-O41-N41 -> 763 | Q41: =2288+146-P41-O41-N41 -> 836 | R41: =SUM(N41:Q41) -> 2434 | S41: 970 | T41: =2656-S41 -> 1686 | U41: =3923-T41-S41 -> 1267 | V41: =4059-U41-T41-S41 -> 136 | W41: =SUM(S41:V41) -> 4059 | X41: 260 | Y41: =283-X41 -> 23 | Z41: =514-Y41-X41 -> 231 | AA41: =543-Z41-Y41-X41 -> 29 | AB41: =SUM(X41:AA41) -> 543 | AC41: 10 | AD41: =18-AC41 -> 8 | AE41: 12 | AF41: =AG41-SUM(AC41:AE41) -> 50 | AG41: 80 | AH41: 6 | AI41: =29-AH41 -> 23 | AJ41: =36-AI41-AH41 -> 7 | AK41: =AL41-SUM(AH41:AJ41) -> 2 | AL41: 38 | AQ41: =SUM(AM41:AP41) -> 0
C42: Issuance of Common Stock under ESPP, Net | X42: 932 | Y42: =932-X42 -> 0 | Z42: =1459-Y42-X42 -> 527 | AA42: =1459-Z42-Y42-X42 -> 0 | AB42: =SUM(X42:AA42) -> 1459 | AC42: 360 | AD42: =360-AC42 -> 0 | AE42: 241 | AF42: =AG42-SUM(AC42:AE42) -> -1 | AG42: 600 | AH42: 240 | AI42: =240-AH42 -> 0 | AJ42: =421-AI42-AH42 -> 181 | AK42: =AL42-SUM(AH42:AJ42) -> 0 | AL42: 421 | AQ42: =SUM(AM42:AP42) -> 0
C43: Issuance of Redeemable Convertible Preferred Stock | D43: 49765 | E43: 0 | F43: 0 | G43: 0 | H43: =SUM(D43:G43) -> 49765 | I43: 0 | J43: 0 | K43: 56936 | L43: 2999 | M43: =SUM(I43:L43) -> 59935 | N43: 0 | R43: =SUM(N43:Q43) -> 0 | W43: =SUM(S43:V43) -> 0 | AB43: =SUM(X43:AA43) -> 0 | AF43: =AG43-SUM(AC43:AE43) -> 0 | AG43: 0 | AK43: =AL43-SUM(AH43:AJ43) -> 0 | AQ43: =SUM(AM43:AP43) -> 0
C44: Repurchase of Common Stock Related to Net Share Settlement | D44: 0 | E44: 0 | F44: 0 | G44: 0 | H44: =SUM(D44:G44) -> 0 | I44: -31 | J44: -27 | K44: -27 | L44: -53 | M44: =SUM(I44:L44) -> -138 | N44: -50 | O44: =-107-N44 -> -57 | P44: =-296-O44-N44 -> -189 | Q44: =-476-P44-O44-N44 -> -180 | R44: =SUM(N44:Q44) -> -476 | S44: -233 | T44: =+-264-S44 -> -31 | U44: =-264-T44-S44 -> 0 | V44: =+-264-U44-T44-S44 -> 0 | W44: =SUM(S44:V44) -> -264 | X44: -15 | Y44: =+-38-X44 -> -23 | Z44: =+-64-Y44-X44 -> -26 | AA44: =+-89-Z44-Y44-X44 -> -25 | AB44: =SUM(X44:AA44) -> -89 | AC44: -39 | AD44: =-71-AC44 -> -32 | AE44: -29 | AF44: =AG44-SUM(AC44:AE44) -> -27 | AG44: -127 | AH44: -24 | AI44: =-44-AH44 -> -20 | AJ44: =-70-AI44-AH44 -> -26 | AK44: =AL44-SUM(AH44:AJ44) -> -35 | AL44: -105 | AQ44: =SUM(AM44:AP44) -> 0
C45: Repurchase of common stock related to share repurchase program | AC45: -2718 | AD45: =-20052-AC45 -> -17334 | AE45: 0 | AF45: =AG45-SUM(AC45:AE45) -> 0 | AG45: -20052 | AK45: =AL45-SUM(AH45:AJ45) -> 0 | AQ45: =SUM(AM45:AP45) -> 0
C46: Cash Paid for Acquisitions | AC46: -457 | AD46: =-457-AC46 -> 0 | AE46: 0 | AF46: =AG46-SUM(AC46:AE46) -> 1 | AG46: -456 | AH46: -296 | AI46: =-296-AH46 -> 0 | AJ46: =-296-AI46-AH46 -> 0 | AK46: =AL46-SUM(AH46:AJ46) -> 0 | AL46: -296 | AQ46: =SUM(AM46:AP46) -> 0
C47: Principal Payments on Finance Lease Obligations | D47: 0 | E47: 0 | F47: 0 | G47: 0 | H47: =SUM(D47:G47) -> 0 | I47: -26 | J47: -26 | K47: -28 | L47: -27 | M47: =SUM(I47:L47) -> -107 | N47: -27 | O47: =-55-N47 -> -28 | P47: =-83-O47-N47 -> -28 | Q47: =-112-P47-O47-N47 -> -29 | R47: =SUM(N47:Q47) -> -112 | S47: -29 | T47: =+-42-S47 -> -13 | U47: =-40-T47-S47 -> 2 | V47: =+-42-U47-T47-S47 -> -2 | W47: =SUM(S47:V47) -> -42 | X47: -10 | Y47: =+-20-X47 -> -10 | Z47: =+-29-Y47-X47 -> -9 | AA47: =+-40-Z47-Y47-X47 -> -11 | AB47: =SUM(X47:AA47) -> -40 | AC47: -10 | AD47: =-20-AC47 -> -10 | AE47: -10 | AF47: =AG47-SUM(AC47:AE47) -> -11 | AG47: -41 | AH47: -10 | AI47: =-21-AH47 -> -11 | AJ47: =-32-AI47-AH47 -> -11 | AK47: =AL47-SUM(AH47:AJ47) -> -10 | AL47: -42 | AQ47: =SUM(AM47:AP47) -> 0
C48: Proceeds from Initial Public Offering, Net | D48: 0 | E48: 0 | F48: 0 | G48: 0 | H48: =SUM(D48:G48) -> 0 | I48: 0 | J48: 0 | K48: 0 | L48: 0 | M48: =SUM(I48:L48) -> 0 | N48: 0 | O48: -594 | P48: =219819-O48-N48 -> 220413 | Q48: =219811-P48-O48-N48 -> -8 | R48: =SUM(N48:Q48) -> 219811 | S48: -284 | T48: =+-284-S48 -> 0 | U48: =-284-T48-S48 -> 0 | V48: =-284-U48-T48-S48 -> 0 | W48: =SUM(S48:V48) -> -284 | Y48: =0-X48 -> 0 | AB48: =SUM(X48:AA48) -> 0 | AD48: =0-AC48 -> 0 | AF48: =AG48-SUM(AC48:AE48) -> 0 | AG48: 0 | AK48: =AL48-SUM(AH48:AJ48) -> 0 | AQ48: =SUM(AM48:AP48) -> 0
B49: Cash used in Financing Activites | D49: =SUM(D40:D48) -> 44009 | E49: =SUM(E40:E48) -> 21 | F49: =SUM(F40:F48) -> 51 | G49: =SUM(G40:G48) -> 23 | H49: =SUM(H40:H48) -> 44104 | I49: =SUM(I40:I48) -> 16951 | J49: =SUM(J40:J48) -> -45 | K49: =SUM(K40:K48) -> 57144 | ... AQ49: =SUM(AQ40:AQ48) -> 0
B51: Net change in cash & cash equivalents | D51: =D25+D34+D49 -> 34041 | E51: =E25+E34+E49 -> -3480 | F51: =F25+F34+F49 -> -6960 | G51: =G25+G34+G49 -> -10121 | H51: =H25+H34+H49 -> 13480 | I51: =I25+I34+I49 -> 6174 | J51: =J25+J34+J49 -> -5376 | K51: =K25+K34+K49 -> 54166 | ... AQ51: =AQ25+AQ34+AQ49 -> -16890.062
B53: Beginning cash & cash equivalents | D53: 9744 | E53: =D54 -> 43785 | F53: =E54 -> 40305 | G53: =F54 -> 33345 | H53: 9744 | I53: =H54 -> 23224 | J53: =I54 -> 29398 | K53: =J54 -> 24022 | L53: =K54 -> 78188 | M53: =H54 -> 23224 | N53: =L54 -> 58569 | O53: =N54 -> 53632 | P53: =O54 -> 47026 | Q53: =P54 -> 258478 | R53: =M54 -> 58569 | S53: 255477 | T53: =S54 -> 238576 | U53: =T54 -> 228187 | V53: =U54 -> 213122 | W53: =R54 -> 255477 | X53: =V54 -> 203244 | Y53: =X54 -> 187635 | Z53: =Y54 -> 178919 | AA53: =Z54 -> 157652 | AB53: =W54 -> 203244 | AC53: =AA54 -> 159551 | AD53: =AC54 -> 148679 | AE53: =AD54 -> 130005 | AF53: =AE54 -> 76549 | AG53: =AB54 -> 159551 | AH53: =AF54 -> 52771 | AI53: =AH54 -> 34533 | AJ53: =AI54 -> 21672 | AK53: =AJ54 -> 28804 | AL53: =AG54 -> 52771 | AM53: =AK54 -> 19655 | AN53: =AM54 -> 5844.5947 | AO53: =AN54 -> 4711.3534 | AP53: =AO54 -> 2416.69 | AQ53: =AL54 -> 19655
B54: Ending cash & cash equivalents | D54: =D53+D51 -> 43785 | E54: =E53+E51 -> 40305 | F54: =F51+F53 -> 33345 | G54: =G51+G53 -> 23224 | H54: =H51+H53 -> 23224 | I54: =I51+I53 -> 29398 | J54: =J51+J53 -> 24022 | K54: =K51+K53 -> 78188 | L54: =L51+L53 -> 58569 | M54: =M51+M53 -> 58569 | ... AQ54: =AQ51+AQ53 -> 2764.938
B55: Scott Berg, sberg@needhamco.com
B56: 763.350.4027 | D56: =D54-BS!D6 -> -1 | E56: =E54-BS!E6 -> -2 | F56: =F54-BS!F6 -> -3 | G56: =G54-BS!G6 -> 0 | H56: =H54-BS!H6 -> 0 | I56: =I54-BS!I6 -> 0 | J56: =J54-BS!J6 -> 0 | K56: =K54-BS!K6 -> 0 | ... AQ56: =AQ54-BS!AQ6 -> -94942
B58: Depreciation & Amortization | D58: =IS!D143 -> 120 | E58: =IS!E143 -> 176 | F58: =IS!F143 -> 247 | G58: =IS!G143 -> 260 | I58: =IS!I143 -> 378 | J58: =IS!J143 -> 421 | K58: =IS!K143 -> 415 | L58: =IS!L143 -> 410 | N58: =IS!N143 -> 424 | O58: =IS!O143 -> 0 | P58: =IS!P143 -> 0 | Q58: =Q59*BS!P11 -> 415.548 | S58: =S59*BS!R11 -> 455 | T58: =T59*BS!S11 -> 700 | U58: =U59*BS!T11 -> 924 | V58: =V59*BS!U11 -> 895 | X58: =X59*BS!W11 -> 952 | Y58: =Y59*BS!X11 -> 1005 | Z58: =Z59*BS!Y11 -> 1054 | AA58: =AA59*BS!Z11 -> 1148 | AC58: =AC59*BS!AB11 -> 1075 | AD58: =AD59*BS!AC11 -> 1028 | AE58: =AE59*BS!AD11 -> 989 | AF58: =AF59*BS!AE11 -> 834 | AH58: =AH59*BS!AG11 -> 927 | AI58: =AI59*BS!AH11 -> 902 | AJ58: =AJ59*BS!AI11 -> 902 | AK58: =AK59*BS!AJ11 -> 927 | AM58: =AM59*BS!AL11 -> 872.045 | AN58: =AN59*BS!AM11 -> 869.50982 | AO58: =AO59*BS!AN11 -> 878.7662 | AP58: =AP59*BS!AO11 -> 886.95808
C59: % Revenue | D59: =D58/BS!C11 -> #VALUE! | E59: =E58/BS!D11 -> 0.13643411 | F59: =F58/BS!E11 -> 0.11728395 | G59: =G58/BS!F11 -> 0.095588235 | I59: =I58/BS!H11 -> 0.10532182 | J59: =J58/BS!I11 -> 0.10858912 | K59: =K58/BS!J11 -> 0.10964333 | L59: =L58/BS!K11 -> 0.10895562 | N59: =N58/BS!M11 -> 0.10947586 | O59: =O58/BS!N11 -> 0 | P59: =P58/BS!O11 -> 0 | Q59: 0.084 | S59: =+S10/BS!R11 -> 0.085285848 | T59: =+T10/BS!S11 -> 0.11969904 | U59: =+U10/BS!T11 -> 0.12781851 | V59: =+V10/BS!U11 -> 0.11947671 | X59: =+X10/BS!W11 -> 0.12681497 | Y59: =+Y10/BS!X11 -> 0.1289288 | Z59: =+Z10/BS!Y11 -> 0.12201899 | AA59: =+AA10/BS!Z11 -> 0.12502723 | AC59: =+AC10/BS!AB11 -> 0.11124909 | AD59: =+AD10/BS!AC11 -> 0.10800588 | AE59: =+AE10/BS!AD11 -> 0.10712738 | AF59: =+AF10/BS!AE11 -> 0.09026951 | AH59: =+AH10/BS!AG11 -> 0.11766946 | AI59: =+AI10/BS!AH11 -> 0.11966039 | AJ59: =+AJ10/BS!AI11 -> 0.11767776 | AK59: =+AK10/BS!AJ11 -> 0.11544209 | AM59: 0.115 | AN59: 0.115 | AO59: 0.115 | AP59: 0.115

Sheet Metrics
B2: =Comparison!B2 -> CS DISCO (LAW)
B4: Metrics | D4: 1Q17 | E4: 2Q17 | F4: 3Q17 | G4: 4Q17 | H4: 2017 | I4: 1Q18 | J4: 2Q18 | K4: 3Q18 | L4: 4Q18 | M4: 2018 | N4: 1Q19 | O4: 2Q19 | P4: 3Q19 | Q4: 4Q19 | R4: 2019 | S4: 1Q20 | T4: 2Q20 | U4: 3Q20 | V4: 4Q20 | W4: =IS!M4 -> 2020 | X4: =IS!N4 -> 1Q21 | Y4: =IS!O4 -> 2Q21 | Z4: =IS!P4 -> 3Q21 | AA4: =IS!Q4 -> 4Q21 | AB4: =IS!R4 -> 2021 | AC4: =IS!S4 -> 1Q22 | AD4: =IS!T4 -> 2Q22 | ... AV4: =IS!AL4 -> 2025
B5: Total Customers | N5: 480 | O5: 509 | P5: 530 | Q5: 635 | R5: =Q5 -> 635 | S5: 713 | T5: 762 | U5: 792 | V5: 825 | W5: =V5 -> 825 | X5: 909 | Z5: =1318/1.26 -> 1046.0317 | AA5: 1126 | AB5: =AA5 -> 1126 | AD5: 1255 | AE5: 1318 | AF5: 1327 | AG5: =AF5 -> 1327 | AH5: 1388 | AI5: 1431 | AJ5: 1449 | AK5: 1463 | AL5: =AK5 -> 1463 | AM5: 1442 | AN5: 1449 | AO5: 1439 | AP5: 1478 | AQ5: =AP5 -> 1478 | AV5: 1549
C6: Y/Y Growth | I6: =I5/D5-1 -> #DIV/0! | J6: =J5/E5-1 -> #DIV/0! | K6: =K5/F5-1 -> #DIV/0! | L6: =L5/G5-1 -> #DIV/0! | S6: =S5/N5-1 -> 0.48541667 | T6: =T5/O5-1 -> 0.49705305 | U6: =U5/P5-1 -> 0.49433962 | V6: =V5/Q5-1 -> 0.2992126 | W6: =W5/R5-1 -> 0.2992126 | X6: =X5/S5-1 -> 0.27489481 | Z6: =Z5/U5-1 -> 0.32074715 | AA6: =AA5/V5-1 -> 0.36484848 | AB6: =AB5/W5-1 -> 0.36484848 | AE6: =AE5/Z5-1 -> 0.26 | AF6: =AF5/AA5-1 -> 0.17850799 | AG6: =AG5/AB5-1 -> 0.17850799 | AI6: =AI5/AD5-1 -> 0.14023904 | AJ6: =AJ5/AE5-1 -> 0.09939302 | AK6: =AK5/AF5-1 -> 0.10248681 | AL6: =AL5/AG5-1 -> 0.10248681 | AM6: =AM5/AH5-1 -> 0.038904899 | AN6: =AN5/AI5-1 -> 0.012578616 | AO6: =AO5/AJ5-1 -> -0.0069013112 | AP6: =AP5/AK5-1 -> 0.010252905 | AQ6: =AQ5/AL5-1 -> 0.010252905 | AV6: =AV5/AQ5-1 -> 0.048037889
B7: Net New Customers | O7: =O5-N5 -> 29 | P7: =P5-O5 -> 21 | Q7: =Q5-P5 -> 105 | S7: =S5-Q5 -> 78 | T7: =T5-S5 -> 49 | U7: =U5-T5 -> 30 | V7: =V5-U5 -> 33 | W7: =SUM(S7:V7) -> 190 | X7: =X5-V5 -> 84 | AA7: =AA5-Z5 -> 79.968254 | AB7: =SUM(X7:AA7) -> 163.96825 | AE7: =AE5-AD5 -> 63 | AF7: =AF5-AE5 -> 9 | AG7: =SUM(AC7:AF7) -> 72 | AH7: =AH5-AF5 -> 61 | AI7: =AI5-AH5 -> 43 | AJ7: =AJ5-AI5 -> 18 | AK7: =AK5-AJ5 -> 14 | AL7: =SUM(AH7:AK7) -> 136 | AM7: =AM5-AK5 -> -21 | AN7: =AN5-AM5 -> 7 | AO7: =AO5-AN5 -> -10 | AP7: =AP5-AO5 -> 39 | AQ7: =SUM(AM7:AP7) -> 15 | AV7: =AV5-AQ5 -> 71
B9: Annualized Revenue Per Customer | N9: =(4*IS!D11/N5)*1000 -> 86483.333 | O9: =(4*IS!E11/O5)*1000 -> 88840.864 | P9: =(4*IS!F11/P5)*1000 -> 95486.792 | Q9: =(4*IS!G11/Q5)*1000 -> 89581.102 | R9: =(4*IS!H11/R5)*1000 -> 305864.57 | S9: =(4*IS!I11/S5)*1000 -> 87899.018 | T9: =(4*IS!J11/T5)*1000 -> 82556.43 | U9: =(4*IS!K11/U5)*1000 -> 90217.172 | ... X9: =(4*IS!N11/X5)*1000 -> 92985.699 | Z9: =(4*IS!P11/Z5)*1000 -> 114160.97 | AA9: =(4*IS!Q11/AA5)*1000 -> 120106.57 | AB9: =(4*IS!R11/AB5)*1000 -> 406188.28 | AD9: =(4*IS!T11/AD5)*1000 -> 107442.23 | AE9: =(4*IS!U11/AE5)*1000 -> 104628.22 | AF9: =(4*IS!V11/AF5)*1000 -> 98076.865 | AG9: =(4*IS!W11/AG5)*1000 -> 407505.65 | AH9: =(4*IS!X11/AH5)*1000 -> 95472.622 | AI9: =(4*IS!Y11/AI5)*1000 -> 95809.923 | AJ9: =(4*IS!Z11/AJ5)*1000 -> 96461.008 | AK9: =(4*IS!AA11/AK5)*1000 -> 97722.488 | ... AQ9: =(4*IS!AG11/AQ5)*1000 -> 391991.88 | AV9: =(4*IS!AL11/AV5)*1000 -> 405032.92
C10: Y/Y Growth | I10: =I9/D9-1 -> #DIV/0! | J10: =J9/E9-1 -> #DIV/0! | K10: =K9/F9-1 -> #DIV/0! | L10: =L9/G9-1 -> #DIV/0! | S10: =S9/N9-1 -> 0.016369453 | T10: =T9/O9-1 -> -0.0707381 | U10: =U9/P9-1 -> -0.055186907 | V10: =V9/Q9-1 -> 0.038422478 | W10: =W9/R9-1 -> 0.084956327 | X10: =X9/S9-1 -> 0.057869592 | Z10: =Z9/U9-1 -> 0.2654018 | AA10: =AA9/V9-1 -> 0.29114878 | AB10: =AB9/W9-1 -> 0.2240128 | AE10: =AE9/Z9-1 -> -0.083502676 | AF10: =AF9/AA9-1 -> -0.183418 | AG10: =AG9/AB9-1 -> 0.0032432614 | AI10: =AI9/AD9-1 -> -0.1082657 | AJ10: =AJ9/AE9-1 -> -0.078059405 | AK10: =AK9/AF9-1 -> -0.0036132585 | AL10: =AL9/AG9-1 -> -0.073502486 | AM10: =AM9/AH9-1 -> 0.033503504 | AN10: =AN9/AI9-1 -> 0.037394472 | AO10: =AO9/AJ9-1 -> 0.045074042 | AP10: =AP9/AK9-1 -> 0.024662937 | AQ10: =AQ9/AL9-1 -> 0.038243395 | AV10: =AV9/AQ9-1 -> 0.033268657
B12: Net Dollar Revenue Retention | S12: 1.3597564 | T12: 1.3009329 | U12: 1.2759943 | V12: 1.2706701 | X12: 1.2241792
I13: =I12/D12-1 -> #DIV/0! | J13: =J12/E12-1 -> #DIV/0! | K13: =K12/F12-1 -> #DIV/0! | L13: =L12/G12-1 -> #DIV/0! | X13: =X12/S12-1 -> -0.09970698 | Y13: =Y12/T12-1 -> -1 | Z13: =Z12/U12-1 -> -1 | AA13: =AA12/V12-1 -> -1 | AB13: =AB12/W12-1 -> #DIV/0! | AC13: =AC12/X12-1 -> -1 | AD13: =AD12/Y12-1 -> #DIV/0! | AE13: =AE12/Z12-1 -> #DIV/0! | ... AV13: =AV12/AQ12-1 -> #DIV/0!
B16: Total Revenue | N16: =IS!D11 -> 10378 | O16: =IS!E11 -> 11305 | P16: =IS!F11 -> 12652 | Q16: =IS!G11 -> 14221 | R16: =IS!R11 -> 114342 | S16: =IS!I11 -> 15668 | T16: =IS!J11 -> 15727 | U16: =IS!K11 -> 17863 | V16: =IS!L11 -> 19186 | W16: =SUM(S16:V16) -> 68444 | X16: =IS!N11 -> 21131 | Y16: =IS!O11 -> 29547 | Z16: =IS!P11 -> 29854 | AA16: =IS!Q11 -> 33810 | AB16: =SUM(X16:AA16) -> 114342 | AC16: =IS!S11 -> 34468 | AD16: =IS!T11 -> 33710 | AE16: =IS!U11 -> 34475 | AF16: =IS!V11 -> 32537 | AG16: =SUM(AC16:AF16) -> 135190 | AH16: =IS!X11 -> 33129 | AI16: =IS!Y11 -> 34276 | AJ16: =IS!Z11 -> 34943 | AK16: =IS!AA11 -> 35742 | AL16: =SUM(AH16:AK16) -> 138090 | AM16: =IS!AC11 -> 35571 | AN16: =IS!AD11 -> 36005 | AO16: =IS!AE11 -> 36266 | AP16: =IS!AF11 -> 36999 | AQ16: =SUM(AM16:AP16) -> 144841 | AR16: =IS!AH11 -> 36653 | AS16: =IS!AI11 -> 38106 | AT16: =IS!AJ11 -> 40919 | AU16: =IS!AK11 -> 41171 | AV16: =SUM(AR16:AU16) -> 156849
C17: Y/Y Growth | S17: =(S16-N16)/N16 -> 0.50973213 | T17: =(T16-O16)/O16 -> 0.39115436 | U17: =(U16-P16)/P16 -> 0.41187164 | V17: =(V16-Q16)/Q16 -> 0.34913157 | W17: =(W16-R16)/R16 -> -0.40140981 | X17: =(X16-S16)/S16 -> 0.34867245 | Y17: =(Y16-T16)/T16 -> 0.87874356 | Z17: =(Z16-U16)/U16 -> 0.67127582 | ... AV17: =(AV16-AQ16)/AQ16 -> 0.082904702
B18: Large Customers (>$100K TTM rev) | M18: 77 | R18: 113 | W18: 141 | AB18: 214 | AG18: 265 | AL18: 289 | AM18: =AR18/(1+AR19) -> 294.44444 | AN18: =AS18/(1+AS19) -> 304.71698 | AO18: =AT18/(1+AT19) -> 307.54717 | AP18: 315 | AQ18: 315 | AR18: 318 | AS18: 323 | AT18: 326 | AU18: 330 | AV18: 330
C19: Y/Y Growth | R19: =R18/M18-1 -> 0.46753247 | W19: =W18/R18-1 -> 0.24778761 | AB19: =AB18/W18-1 -> 0.5177305 | AG19: =AG18/AB18-1 -> 0.23831776 | AL19: =AL18/AG18-1 -> 0.090566038 | AQ19: =AQ18/AL18-1 -> 0.089965398 | AR19: 0.08 | AS19: 0.06 | AT19: 0.06 | AU19: =AU18/AP18-1 -> 0.047619048 | AV19: =AV18/AQ18-1 -> 0.047619048
C20: % of Revenue | W20: 0.74 | AB20: 0.81 | AG20: 0.78 | AL20: 0.75 | AQ20: 0.76 | AR20: 0.76 | AT20: 0.76 | AV20: 0.76
B21: Net New Customers | W21: =W18-R18 -> 28 | AB21: =AB18-W18 -> 73 | AG21: =AG18-AB18 -> 51 | AL21: =AL18-AG18 -> 24 | AN21: =AN18-AM18 -> 10.272537 | AO21: =AO18-AN18 -> 2.8301887 | AP21: =AP18-AO18 -> 7.4528302 | AQ21: =AQ18-AL18 -> 26 | AS21: =AS18-AR18 -> 5 | AT21: =AT18-AS18 -> 3 | AU21: =AU18-AT18 -> 4 | AV21: =AV18-AQ18 -> 15
B22: Over $1M Revenue Customers | W22: 9 | AB22: 20 | AG22: 23 | AL22: 19 | AQ22: 19 | AV22: 20
C23: Y/Y Growth | AB23: =AB22/W22-1 -> 1.2222222 | AG23: =AG22/AB22-1 -> 0.15 | AL23: =AL22/AG22-1 -> -0.17391304 | AQ23: =AQ22/AL22-1 -> 0 | AV23: =AV22/AQ22-1 -> 0.052631579
B24: Net New Customers | AB24: =AB22-W22 -> 11 | AG24: =AG22-AB22 -> 3 | AL24: =AL22-AG22 -> -4 | AQ24: =AQ22-AL22 -> 0 | AV24: =AV22-AQ22 -> 1
B25: Net Revenue Retention | W25: 1.27 | AB25: 1.46 | AG25: 1.06 | AL25: 0.92 | AQ25: 0.96 | AV25: 0.98
B26: Software Net Revenue Retention | W26: 1.27 | AL26: 0.98 | AQ26: 1 | AV26: 1.03
B27: Multi-Product Attach Rate | AG27: 0.11 | AL27: 0.15 | AQ27: 0.17 | AV27: 0.19
L30: Customer Count
L32: $50k+ | M32: 137 | V32: 262
L35: $100k+ | M35: 77 | Q35: 113 | V35: 141 | X35: 157 | AA35: 214 | AF35: 265
AF36: =AF35/AA35-1 -> 0.23831776
L38: $250k | M38: 27 | V38: 63
L41: $500k | M41: 7 | V41: 30
L44: $1m | M44: 0 | V44: 9 | AF44: 23
M52: 2018 | N52: 2020
H53: $1mm+ | M53: 0 | N53: 9
H54: $500k+ | M54: 7 | N54: 30
H55: $250k+ | M55: 27 | N55: 63
H56: $100k+ | M56: 77 | N56: 141
H57: $50k+ | M57: 137 | N57: 262

Sheet V
Y2: Current $50 PT is 18x FY22
B3: Assumptions / Outputs | C3: LAW | E3: Valuation and Price Target
B5: Current Price | C5: =_xll.FDSZ(C3,"P_PRICE(NOW)") -> #NAME? | E5: Financials ($M) | J5: 43830 | O5: =J5+365 -> 44195 | T5: =O5+365 -> 44560 | Y5: =T5+365 -> 44925 | AD5: =Y5+365 -> 45290 | AE5: Target
B6: $ Multiplier | C6: 1000 | E6: Revenue | J6: =IS!H11/V!$C$6 -> 48.556 | O6: =IS!M11/V!$C$6 -> 68.444 | T6: =IS!R11/V!$C$6 -> 114.342 | Y6: =IS!W11/V!$C$6 -> 135.19 | AD6: =IS!AB11/V!$C$6 -> 138.09
B7: Base | C7: 4.5 | E7: Non-GAAP Gross Profit | J7: =IS!H15/V!$C$6 -> 34.106 | O7: =IS!M15/V!$C$6 -> 48.023 | T7: =IS!R15/V!$C$6 -> 83.301 | Y7: =IS!W15/V!$C$6 -> 101.965 | AD7: =IS!AB15/V!$C$6 -> 104.178
B8: Target Price | C8: =AE25 -> 14.609311 | E8: Non-GAAP Op Inc | J8: =IS!H27/V!$C$6 -> -26.23 | O8: =IS!M27/V!$C$6 -> -21.565 | T8: =IS!R27/V!$C$6 -> -18.226 | Y8: =IS!W27/V!$C$6 -> -48.018 | AD8: =IS!AB27/V!$C$6 -> -30.523
B9: Up / Down to Target | C9: =C8/C5-1 -> #NAME? | E9: Adj. EBITDA | J9: =IS!H50/V!$C$6 -> -25.428 | O9: =IS!M50/V!$C$6 -> -19.941 | T9: =IS!R50/V!$C$6 -> -16.392 | Y9: =IS!W50/V!$C$6 -> -44.524 | AD9: =IS!AB50/V!$C$6 -> -25.894
E10: Non-GAAP EPS | J10: =IS!H65 -> -0.39799694 | O10: =IS!M65 -> -0.33824164 | T10: =IS!R65 -> -0.4035986 | Y10: =IS!W65 -> -0.80280962 | AD10: =IS!AB65 -> -0.37979253
E11: Free Cash Flow | J11: =CF!H36/V!$C$6 -> -30.624 | O11: =CF!M36/V!$C$6 -> -24.616 | T11: =CF!R36/V!$C$6 -> -24.749 | Y11: =CF!W36/V!$C$6 -> -50.392 | AD11: =CF!AB36/V!$C$6 -> -30.39
B12: Multiple Scenario | E12: Multiples
B13: Bear | C13: 10 | E13: EV/Revenue | J13: =J24/J6 -> #NAME? | O13: =O24/O6 -> #NAME? | T13: =T24/T6 -> #NAME? | Y13: =Y24/Y6 -> #NAME? | AD13: =AD24/AD6 -> #NAME? | AE13: =C7 -> 4.5
B14: Base | C14: 12 | E14: EV/Gross Profit | J14: =J24/J7 -> #NAME? | O14: =O24/O7 -> #NAME? | T14: =T24/T7 -> #NAME? | Y14: =Y24/Y7 -> #NAME? | AD14: =AD24/AD7 -> #NAME? | AE14: =AE24/Y7 -> 5.966312
B15: Bull | C15: 14 | E15: EV/Non-GAAP Op Inc | J15: =IF(J8>0, J24/J8, "NM ") -> NM | O15: =IF(O8>0, O24/O8, "NM ") -> NM | T15: =IF(T8>0, T24/T8, "NM ") -> NM | Y15: =IF(Y8>0, Y24/Y8, "NM ") -> NM | AD15: =IF(AD8>0, AD24/AD8, "NM ") -> NM | AE15: =IF(Y8>0, AE24/Y8, "NM ") -> NM
E16: EV/Adj. EBITDA | J16: =IF(J9>0, J24/J9, "NM ") -> NM | O16: =IF(O9>0, O24/O9, "NM ") -> NM | T16: =IF(T9>0, T24/T9, "NM ") -> NM | Y16: =IF(Y9>0, Y24/Y9, "NM ") -> NM | AD16: =IF(AD9>0, AD24/AD9, "NM ") -> NM | AE16: =IF(Y9>0, AE24/Y9, "NM ") -> NM
E17: Adj. P/E | J17: =IF(J10>0, $C$5/J10, "NM ") -> NM | O17: =IF(O10>0, $C$5/O10, "NM ") -> NM | T17: =IF(T10>0, $C$5/T10, "NM ") -> NM | Y17: =IF(Y10>0, $C$5/Y10, "NM ") -> NM | AD17: =IF(AD10>0, $C$5/AD10, "NM ") -> NM | AE17: =IF(Y10>0, $C$5/Y10, "NM ") -> NM
E18: EV/FCF | J18: =IF(J11>0, J24/J11, "NM ") -> NM | O18: =IF(O11>0, O24/O11, "NM ") -> NM | T18: =IF(T11>0, T24/T11, "NM ") -> NM | Y18: =IF(Y11>0, Y24/Y11, "NM ") -> NM | AD18: =IF(AD11>0, AD24/AD11, "NM ") -> NM | AE18: =IF(Y11>0, AE24/Y11, "NM ") -> NM
B19: Most Recent Q (Update) | E19: Capitalization
B20: Cash | C20: =BS!S6/V!$C$6 -> 238.576 | E20: Cash | J20: =BS!H6/$C$6 -> 23.224 | O20: =BS!M6/$C$6 -> 58.569 | T20: =BS!R6/$C$6 -> 255.477 | Y20: =BS!W6/$C$6 -> 203.244 | AD20: =BS!AB6/$C$6 -> 159.551 | AE20: =C20 -> 238.576
B21: Debt | C21: =(BS!S24+BS!S29)/V!$C$6 -> 0 | E21: Debt | J21: =(BS!H24+BS!H29)/V!$C$6 -> 0 | O21: =(BS!M24+BS!M29)/V!$C$6 -> 0 | T21: =(BS!R24+BS!R29)/V!$C$6 -> 0 | Y21: =(BS!W24+BS!W29)/V!$C$6 -> 0 | AD21: =(BS!AB24+BS!AB29)/V!$C$6 -> 0 | AE21: =C21 -> 0
B22: Shares Outstanding | C22: =IS!S71/V!$C$6 -> 57.972 | E22: Shares Outstanding | J22: =IS!H71/V!$C$6 -> 64.601 | O22: =IS!M71/V!$C$6 -> 65.856 | T22: =IS!R71/V!$C$6 -> 46.43475 | Y22: =IS!W71/V!$C$6 -> 58.51325 | AD22: =IS!AB71/V!$C$6 -> 60.1065 | AE22: =C22 -> 57.972
B23: Current Market cap | C23: =C22*C5 -> #NAME? | E23: Market Cap | J23: =J22*$C$5 -> #NAME? | O23: =O22*$C$5 -> #NAME? | T23: =T22*$C$5 -> #NAME? | Y23: =Y22*$C$5 -> #NAME? | AD23: =AD22*$C$5 -> #NAME? | AE23: =AE24+AE20-AE21 -> 846.931
B24: Current EV | C24: =C23-C20 -> #NAME? | E24: EV | J24: =J23-J20+J21 -> #NAME? | O24: =O23-O20+O21 -> #NAME? | T24: =T23-T20+T21 -> #NAME? | Y24: =Y23-Y20+Y21 -> #NAME? | AD24: =AD23-AD20+AD21 -> #NAME? | AE24: =AE13*Y6 -> 608.355
E25: Price Target | AE25: =AE23/AE22 -> 14.609311
E28: Revenue | J28: =J6 -> 48.556 | O28: =O6 -> 68.444 | T28: =T6 -> 114.342 | Y28: =Y6 -> 135.19 | AD28: =AD6 -> 138.09
E29: Current EV / Revenue | J29: =$C$24/J28 -> #NAME? | O29: =$C$24/O28 -> #NAME? | T29: =$C$24/T28 -> #NAME? | Y29: =$C$24/Y28 -> #NAME? | AD29: =$C$24/AD28 -> #NAME?
B33: Price Target | C33: 6.22
B34: Shares Outstanding | C34: =IS!AJ71 -> 62094
B35: Market Value | C35: =C33*C34 -> 386224.68
B36: Cash & Equivalents | C36: =BS!AJ6 -> 113486
B37: EV | C37: =C35-C36 -> 272738.68
B38: FY25 Revenue | C38: =IS!AL11 -> 156849
B39: EV/Rev | C39: =C37/C38 -> 1.7388615
B41: FY25 Revenue | C41: =IS!AQ11 -> 172004.69
B42: EV/Rev | C42: =C37/C41 -> 1.5856468

Sheet BM Upload
A1: ALL FISCAL DATA MUST BE ENTERED IN MILLION (INCLUDING NUMBER OF SHARE) | AE1: NULL:FISCAL
A2: ALL PER SHARE DATA MUST BE IN UNIT | AE2: ADJUSTED:FISCAL
A3: DATA MUST BE ENTERED IN THE CURRENCY OF THE COMPANY | AE3: BASIC:FISCAL
A4: Click here to find a list of BlueMatrix Client Codes | AE4: DILUTED:FISCAL
AC5: Strong Buy | AE5: GAAP:FISCAL
AC6: Buy | AE6: INDICATED:FISCAL
AC7: Hold | AE7: MANAGED:FISCAL
AC8: Under Perform | AE8: NON-GAAP:FISCAL
A9: Company name | C9: Disco | AC9: Rating Suspended | AE9: OPERATING:FISCAL
A10: Rating | B10: RATING | C10: Buy | D10: =_xll.BLUEMATRIX2("/servlet/excelData",C10, $C$14,$B10) -> #NAME? | AC10: Restricted | AE10: PRIMARY:FISCAL
A11: Currency | C11: USD | AC11: Under Review | AE11: PROFORMA:FISCAL
AC12: Sell | AE12: RESTATED:FISCAL
A13: 12-Month Price Target | B13: TARGET_PRICE | C13: 10 | D13: =_xll.BLUEMATRIX2("/servlet/excelData",C13, $C$14,$B13) -> #NAME? | AE13: REVENUE:FISCAL
A14: Ticker | C14: LAW | AC14: A | AD14: E | AE14: NULL:CALENDAR
AC15: E | AD15: A | AE15: ADJUSTED:CALENDAR
D16: =$B$17-1 -> 2022 | E16: =$B$17-1 -> 2022 | F16: =$B$17-1 -> 2022 | G16: =$B$17-1 -> 2022 | H16: =$B$17-1 -> 2022 | I16: =$B$17 -> 2023 | J16: =$B$17 -> 2023 | K16: =$B$17 -> 2023 | L16: =$B$17 -> 2023 | M16: =$B$17 -> 2023 | N16: =$B$17+1 -> 2024 | O16: =$B$17+1 -> 2024 | P16: =$B$17+1 -> 2024 | Q16: =$B$17+1 -> 2024 | R16: =$B$17+1 -> 2024 | S16: =N16+1 -> 2025 | T16: =O16+1 -> 2025 | U16: =P16+1 -> 2025 | V16: =Q16+1 -> 2025 | W16: =R16+1 -> 2025 | X16: =S16+1 -> 2026 | Y16: =T16+1 -> 2026 | Z16: =U16+1 -> 2026 | ... AB16: =W16+1 -> 2026 | AE16: BASIC:CALENDAR
A17: Current Year (Matching What Selected From Drop-down Bars - ie. Fiscal or Calendar) | B17: 2023 | D17: =IF(RIGHT(IS!S4)="E","E","A") -> A | E17: =IF(RIGHT(IS!T4)="E","E","A") -> A | F17: =IF(RIGHT(IS!U4)="E","E","A") -> A | G17: =IF(RIGHT(IS!V4)="E","E","A") -> A | H17: =IF(RIGHT(IS!W4)="E","E","A") -> A | I17: =IF(RIGHT(IS!X4)="E","E","A") -> A | J17: =IF(RIGHT(IS!Y4)="E","E","A") -> A | K17: =IF(RIGHT(IS!Z4)="E","E","A") -> A | ... AB17: =IF(RIGHT(IS!AQ4)="E","E","A") -> E | AE17: DILUTED:CALENDAR
A18: Current Base Quarter (NOT one just reported - One After That) | B18: Q2 | D18: =D16&D19 -> 2022Q1 | E18: =E16&E19 -> 2022Q2 | F18: =F16&F19 -> 2022Q3 | G18: =G16&G19 -> 2022Q4 | H18: =H16 -> 2022 | I18: =I16&I19&I17 -> 2023Q1A | J18: =J16&J19&J17 -> 2023Q2A | K18: =K16&K19&K17 -> 2023Q3A | L18: =L16&L19&L17 -> 2023Q4A | M18: =M16&M17 -> 2023A | N18: =N16&N19&N17 -> 2024Q1A | O18: =O16&O19&O17 -> 2024Q2A | P18: =P16&P19&P17 -> 2024Q3A | Q18: =Q16&Q19&Q17 -> 2024Q4A | R18: =R16&R17 -> 2024A | S18: =S16&S19&S17 -> 2025Q1A | T18: =T16&T19&T17 -> 2025Q2A | U18: =U16&U19&U17 -> 2025Q3A | V18: =V16&V19&V17 -> 2025Q4A | W18: =W16&W17 -> 2025A | X18: =X16&X19&X17 -> 2026Q1E | Y18: =Y16&Y19&Y17 -> 2026Q2E | Z18: =Z16&Z19&Z17 -> 2026Q3E | AA18: =AA16&AA19&AA17 -> 2026Q4E | AB18: =AB16&AB17 -> 2026E | AE18: GAAP:CALENDAR
D19: Q1 | E19: Q2 | F19: Q3 | G19: Q4 | H19: AN | I19: Q1 | J19: Q2 | K19: Q3 | L19: Q4 | M19: AN | N19: Q1 | O19: Q2 | P19: Q3 | Q19: Q4 | R19: AN | S19: Q1 | T19: Q2 | U19: Q3 | V19: Q4 | W19: AN | X19: Q1 | Y19: Q2 | Z19: Q3 | AA19: Q4 | AB19: AN | AE19: INDICATED:CALENDAR
A20: BlueMatrix Time Series Grids | D20: =($B$45&"/"&31&"/"&(D16+$D$45)) -> 3/31/2022 | E20: =$B$46&"/"&31&"/"&(E16+$D$46) -> 6/31/2022 | F20: =$B$47&"/"&31&"/"&(F16+$D$47) -> 9/31/2022 | G20: =$B$48&"/"&31&"/"&(G16+$D$48) -> 12/31/2022 | H20: =G20 -> 12/31/2022 | I20: =($B$45&"/"&31&"/"&(I16+$D$45)) -> 3/31/2023 | J20: =$B$46&"/"&31&"/"&(J16+$D$46) -> 6/31/2023 | K20: =$B$47&"/"&31&"/"&(K16+$D$47) -> 9/31/2023 | L20: =$B$48&"/"&31&"/"&(L16+$D$48) -> 12/31/2023 | M20: =L20 -> 12/31/2023 | N20: =($B$45&"/"&31&"/"&(N16+$D$45)) -> 3/31/2024 | O20: =$B$46&"/"&31&"/"&(O16+$D$46) -> 6/31/2024 | P20: =$B$47&"/"&31&"/"&(P16+$D$47) -> 9/31/2024 | Q20: =$B$48&"/"&31&"/"&(Q16+$D$48) -> 12/31/2024 | R20: =Q20 -> 12/31/2024 | S20: =($B$45&"/"&31&"/"&(S16+$D$45)) -> 3/31/2025 | T20: =$B$46&"/"&31&"/"&(T16+$D$46) -> 6/31/2025 | U20: =$B$47&"/"&31&"/"&(U16+$D$47) -> 9/31/2025 | V20: =$B$48&"/"&31&"/"&(V16+$D$48) -> 12/31/2025 | W20: =V20 -> 12/31/2025 | X20: =($B$45&"/"&31&"/"&(X16+$D$45)) -> 3/31/2026 | Y20: =$B$46&"/"&31&"/"&(Y16+$D$46) -> 6/31/2026 | Z20: =$B$47&"/"&31&"/"&(Z16+$D$47) -> 9/31/2026 | AA20: =$B$48&"/"&31&"/"&(AA16+$D$48) -> 12/31/2026 | AB20: =AA20 -> 12/31/2026 | AE20: MANAGED:CALENDAR
A21: Revenue ($M) | B21: REVENUE | D21: =IS!S11/1000 -> 34.468 | E21: =IS!T11/1000 -> 33.71 | F21: =IS!U11/1000 -> 34.475 | G21: =IS!V11/1000 -> 32.537 | H21: =IS!W11/1000 -> 135.19 | I21: =IS!X11/1000 -> 33.129 | J21: =IS!Y11/1000 -> 34.276 | K21: =IS!Z11/1000 -> 34.943 | ... AB21: =IS!AQ11/1000 -> 172.00469 | AE21: NON-GAAP:CALENDAR
B22: NULL:FISCAL | D22: =_xll.BLUEMATRIX2("/servlet/excelData",D21, $C$14,$B21&":"&D$16&D$17&":"&D$19&":"&$B22) -> #NAME? | E22: =_xll.BLUEMATRIX2("/servlet/excelData",E21, $C$14,$B21&":"&E$16&E$17&":"&E$19&":"&$B22) -> #NAME? | F22: =_xll.BLUEMATRIX2("/servlet/excelData",F21, $C$14,$B21&":"&F$16&F$17&":"&F$19&":"&$B22) -> #NAME? | G22: =_xll.BLUEMATRIX2("/servlet/excelData",G21, $C$14,$B21&":"&G$16&G$17&":"&G$19&":"&$B22) -> #NAME? | H22: =_xll.BLUEMATRIX2("/servlet/excelData",H21, $C$14,$B21&":"&H$16&H$17&":"&H$19&":"&$B22) -> #NAME? | I22: =_xll.BLUEMATRIX2("/servlet/excelData",I21, $C$14,$B21&":"&I$16&I$17&":"&I$19&":"&$B22) -> #NAME? | J22: =_xll.BLUEMATRIX2("/servlet/excelData",J21, $C$14,$B21&":"&J$16&J$17&":"&J$19&":"&$B22) -> #NAME? | K22: =_xll.BLUEMATRIX2("/servlet/excelData",K21, $C$14,$B21&":"&K$16&K$17&":"&K$19&":"&$B22) -> #NAME? | ... AB22: =_xll.BLUEMATRIX2("/servlet/excelData",AB21, $C$14,$B21&":"&AB$16&AB$17&":"&AB$19&":"&$B22) -> #NAME? | AE22: OPERATING:CALENDAR
A23: EPS | B23: EPS | D23: =IS!S65 -> -0.14908922 | E23: =IS!T65 -> -0.23078637 | F23: =IS!U65 -> -0.2398322 | G23: =IS!V65 -> -0.18280425 | H23: =IS!W65 -> -0.80280962 | I23: =IS!X65 -> -0.20409022 | J23: =IS!Y65 -> -0.10814288 | K23: =IS!Z65 -> -0.064805302 | ... AB23: =IS!AQ65 -> -0.10804509 | AE23: PRIMARY:CALENDAR
B24: NON-GAAP:FISCAL | D24: =_xll.BLUEMATRIX2("/servlet/excelData",D23, $C$14,$B23&":"&D$16&D$17&":"&D$19&":"&$B24) -> #NAME? | E24: =_xll.BLUEMATRIX2("/servlet/excelData",E23, $C$14,$B23&":"&E$16&E$17&":"&E$19&":"&$B24) -> #NAME? | F24: =_xll.BLUEMATRIX2("/servlet/excelData",F23, $C$14,$B23&":"&F$16&F$17&":"&F$19&":"&$B24) -> #NAME? | G24: =_xll.BLUEMATRIX2("/servlet/excelData",G23, $C$14,$B23&":"&G$16&G$17&":"&G$19&":"&$B24) -> #NAME? | H24: =_xll.BLUEMATRIX2("/servlet/excelData",H23, $C$14,$B23&":"&H$16&H$17&":"&H$19&":"&$B24) -> #NAME? | I24: =_xll.BLUEMATRIX2("/servlet/excelData",I23, $C$14,$B23&":"&I$16&I$17&":"&I$19&":"&$B24) -> #NAME? | J24: =_xll.BLUEMATRIX2("/servlet/excelData",J23, $C$14,$B23&":"&J$16&J$17&":"&J$19&":"&$B24) -> #NAME? | K24: =_xll.BLUEMATRIX2("/servlet/excelData",K23, $C$14,$B23&":"&K$16&K$17&":"&K$19&":"&$B24) -> #NAME? | ... AB24: =_xll.BLUEMATRIX2("/servlet/excelData",AB23, $C$14,$B23&":"&AB$16&AB$17&":"&AB$19&":"&$B24) -> #NAME? | AE24: PROFORMA:CALENDAR
A25: FCF | B25: FCF | AE25: RESTATED:CALENDAR
D26: =_xll.BLUEMATRIX2("/servlet/excelData",D25, $C$14,$B25&":"&D$16&D$17&":"&D$19&":"&$B26) -> #NAME? | E26: =_xll.BLUEMATRIX2("/servlet/excelData",E25, $C$14,$B25&":"&E$16&E$17&":"&E$19&":"&$B26) -> #NAME? | F26: =_xll.BLUEMATRIX2("/servlet/excelData",F25, $C$14,$B25&":"&F$16&F$17&":"&F$19&":"&$B26) -> #NAME? | G26: =_xll.BLUEMATRIX2("/servlet/excelData",G25, $C$14,$B25&":"&G$16&G$17&":"&G$19&":"&$B26) -> #NAME? | H26: =_xll.BLUEMATRIX2("/servlet/excelData",H25, $C$14,$B25&":"&H$16&H$17&":"&H$19&":"&$B26) -> #NAME? | I26: =_xll.BLUEMATRIX2("/servlet/excelData",I25, $C$14,$B25&":"&I$16&I$17&":"&I$19&":"&$B26) -> #NAME? | J26: =_xll.BLUEMATRIX2("/servlet/excelData",J25, $C$14,$B25&":"&J$16&J$17&":"&J$19&":"&$B26) -> #NAME? | K26: =_xll.BLUEMATRIX2("/servlet/excelData",K25, $C$14,$B25&":"&K$16&K$17&":"&K$19&":"&$B26) -> #NAME? | ... AB26: =_xll.BLUEMATRIX2("/servlet/excelData",AB25, $C$14,$B25&":"&AB$16&AB$17&":"&AB$19&":"&$B26) -> #NAME? | AE26: REVENUE:CALENDAR
A27: FFO | B27: FFO
D28: =_xll.BLUEMATRIX2("/servlet/excelData",D27, $C$14,$B27&":"&D$16&D$17&":"&D$19&":"&$B28) -> #NAME? | E28: =_xll.BLUEMATRIX2("/servlet/excelData",E27, $C$14,$B27&":"&E$16&E$17&":"&E$19&":"&$B28) -> #NAME? | F28: =_xll.BLUEMATRIX2("/servlet/excelData",F27, $C$14,$B27&":"&F$16&F$17&":"&F$19&":"&$B28) -> #NAME? | G28: =_xll.BLUEMATRIX2("/servlet/excelData",G27, $C$14,$B27&":"&G$16&G$17&":"&G$19&":"&$B28) -> #NAME? | H28: =_xll.BLUEMATRIX2("/servlet/excelData",H27, $C$14,$B27&":"&H$16&H$17&":"&H$19&":"&$B28) -> #NAME? | I28: =_xll.BLUEMATRIX2("/servlet/excelData",I27, $C$14,$B27&":"&I$16&I$17&":"&I$19&":"&$B28) -> #NAME? | J28: =_xll.BLUEMATRIX2("/servlet/excelData",J27, $C$14,$B27&":"&J$16&J$17&":"&J$19&":"&$B28) -> #NAME? | K28: =_xll.BLUEMATRIX2("/servlet/excelData",K27, $C$14,$B27&":"&K$16&K$17&":"&K$19&":"&$B28) -> #NAME? | ... AB28: =_xll.BLUEMATRIX2("/servlet/excelData",AB27, $C$14,$B27&":"&AB$16&AB$17&":"&AB$19&":"&$B28) -> #NAME?
A29: Net Cash/Debt ($M) | B29: NET_CASH_DEBT
D30: =_xll.BLUEMATRIX2("/servlet/excelData",D29, $C$14,$B29&":"&D$16&D$17&":"&D$19&":"&$B30) -> #NAME? | E30: =_xll.BLUEMATRIX2("/servlet/excelData",E29, $C$14,$B29&":"&E$16&E$17&":"&E$19&":"&$B30) -> #NAME? | F30: =_xll.BLUEMATRIX2("/servlet/excelData",F29, $C$14,$B29&":"&F$16&F$17&":"&F$19&":"&$B30) -> #NAME? | G30: =_xll.BLUEMATRIX2("/servlet/excelData",G29, $C$14,$B29&":"&G$16&G$17&":"&G$19&":"&$B30) -> #NAME? | H30: =_xll.BLUEMATRIX2("/servlet/excelData",H29, $C$14,$B29&":"&H$16&H$17&":"&H$19&":"&$B30) -> #NAME? | I30: =_xll.BLUEMATRIX2("/servlet/excelData",I29, $C$14,$B29&":"&I$16&I$17&":"&I$19&":"&$B30) -> #NAME? | J30: =_xll.BLUEMATRIX2("/servlet/excelData",J29, $C$14,$B29&":"&J$16&J$17&":"&J$19&":"&$B30) -> #NAME? | K30: =_xll.BLUEMATRIX2("/servlet/excelData",K29, $C$14,$B29&":"&K$16&K$17&":"&K$19&":"&$B30) -> #NAME? | ... AB30: =_xll.BLUEMATRIX2("/servlet/excelData",AB29, $C$14,$B29&":"&AB$16&AB$17&":"&AB$19&":"&$B30) -> #NAME?
A31: Operating Margin | B31: OP_MARGIN | D31: =IS!S28 -> -0.24808518 | E31: =IS!T28 -> -0.39305844 | F31: =IS!U28 -> -0.40829587 | G31: =IS!V28 -> -0.37314442 | H31: =IS!W28 -> -0.35518899 | I31: =IS!X28 -> -0.42379788 | J31: =IS!Y28 -> -0.2494165 | K31: =IS!Z28 -> -0.16535501 | ... AB31: =IS!AQ28 -> -0.058217328
B32: NON-GAAP:FISCAL | D32: =_xll.BLUEMATRIX2("/servlet/excelData",D31, $C$14,$B31&":"&D$16&D$17&":"&D$19&":"&$B32) -> #NAME? | E32: =_xll.BLUEMATRIX2("/servlet/excelData",E31, $C$14,$B31&":"&E$16&E$17&":"&E$19&":"&$B32) -> #NAME? | F32: =_xll.BLUEMATRIX2("/servlet/excelData",F31, $C$14,$B31&":"&F$16&F$17&":"&F$19&":"&$B32) -> #NAME? | G32: =_xll.BLUEMATRIX2("/servlet/excelData",G31, $C$14,$B31&":"&G$16&G$17&":"&G$19&":"&$B32) -> #NAME? | H32: =_xll.BLUEMATRIX2("/servlet/excelData",H31, $C$14,$B31&":"&H$16&H$17&":"&H$19&":"&$B32) -> #NAME? | I32: =_xll.BLUEMATRIX2("/servlet/excelData",I31, $C$14,$B31&":"&I$16&I$17&":"&I$19&":"&$B32) -> #NAME? | J32: =_xll.BLUEMATRIX2("/servlet/excelData",J31, $C$14,$B31&":"&J$16&J$17&":"&J$19&":"&$B32) -> #NAME? | K32: =_xll.BLUEMATRIX2("/servlet/excelData",K31, $C$14,$B31&":"&K$16&K$17&":"&K$19&":"&$B32) -> #NAME? | ... AB32: =_xll.BLUEMATRIX2("/servlet/excelData",AB31, $C$14,$B31&":"&AB$16&AB$17&":"&AB$19&":"&$B32) -> #NAME?
A33: Revenue ($M) | B33: REVENUE
D34: =_xll.BLUEMATRIX2("/servlet/excelData",D33, $C$14,$B33&":"&D$16&D$17&":"&D$19&":"&$B34) -> #NAME? | E34: =_xll.BLUEMATRIX2("/servlet/excelData",E33, $C$14,$B33&":"&E$16&E$17&":"&E$19&":"&$B34) -> #NAME? | F34: =_xll.BLUEMATRIX2("/servlet/excelData",F33, $C$14,$B33&":"&F$16&F$17&":"&F$19&":"&$B34) -> #NAME? | G34: =_xll.BLUEMATRIX2("/servlet/excelData",G33, $C$14,$B33&":"&G$16&G$17&":"&G$19&":"&$B34) -> #NAME? | H34: =_xll.BLUEMATRIX2("/servlet/excelData",H33, $C$14,$B33&":"&H$16&H$17&":"&H$19&":"&$B34) -> #NAME? | I34: =_xll.BLUEMATRIX2("/servlet/excelData",I33, $C$14,$B33&":"&I$16&I$17&":"&I$19&":"&$B34) -> #NAME? | J34: =_xll.BLUEMATRIX2("/servlet/excelData",J33, $C$14,$B33&":"&J$16&J$17&":"&J$19&":"&$B34) -> #NAME? | K34: =_xll.BLUEMATRIX2("/servlet/excelData",K33, $C$14,$B33&":"&K$16&K$17&":"&K$19&":"&$B34) -> #NAME? | ... AB34: =_xll.BLUEMATRIX2("/servlet/excelData",AB33, $C$14,$B33&":"&AB$16&AB$17&":"&AB$19&":"&$B34) -> #NAME?
A35: ROIC | B35: ROIC
D36: =_xll.BLUEMATRIX2("/servlet/excelData",D35, $C$14,$B35&":"&D$16&D$17&":"&D$19&":"&$B36) -> #NAME? | E36: =_xll.BLUEMATRIX2("/servlet/excelData",E35, $C$14,$B35&":"&E$16&E$17&":"&E$19&":"&$B36) -> #NAME? | F36: =_xll.BLUEMATRIX2("/servlet/excelData",F35, $C$14,$B35&":"&F$16&F$17&":"&F$19&":"&$B36) -> #NAME? | G36: =_xll.BLUEMATRIX2("/servlet/excelData",G35, $C$14,$B35&":"&G$16&G$17&":"&G$19&":"&$B36) -> #NAME? | H36: =_xll.BLUEMATRIX2("/servlet/excelData",H35, $C$14,$B35&":"&H$16&H$17&":"&H$19&":"&$B36) -> #NAME? | I36: =_xll.BLUEMATRIX2("/servlet/excelData",I35, $C$14,$B35&":"&I$16&I$17&":"&I$19&":"&$B36) -> #NAME? | J36: =_xll.BLUEMATRIX2("/servlet/excelData",J35, $C$14,$B35&":"&J$16&J$17&":"&J$19&":"&$B36) -> #NAME? | K36: =_xll.BLUEMATRIX2("/servlet/excelData",K35, $C$14,$B35&":"&K$16&K$17&":"&K$19&":"&$B36) -> #NAME? | ... AB36: =_xll.BLUEMATRIX2("/servlet/excelData",AB35, $C$14,$B35&":"&AB$16&AB$17&":"&AB$19&":"&$B36) -> #NAME?
D44: Calendar Year = Fiscal Year (If yes =0, if less= -1, if more = 1)
A45: Fiscal 1Q Ending Month Number | B45: 3 | D45: 0
A46: Fiscal 2Q Ending Month Number | B46: 6 | D46: 0
A47: Fiscal 3Q Ending Month Number | B47: 9 | D47: 0
A48: Fiscal 4Q Ending Month Number | B48: 12 | D48: 0

Sheet DCF
A1: ($000s) | B1: 2014E | C1: 2015E | D1: 2016E | E1: 2017E | F1: 2018E | H1: Historical Metrics | I1: 2011 | J1: 2012 | K1: 2013 | L1: 3 Yr
A2: Revenues | B2: =#REF! -> #REF! | C2: =#REF! -> #REF! | D2: =C2*(1+D3) -> #REF! | E2: =D2*(1+E3) -> #REF! | F2: =E2*(1+F3) -> #REF! | H2: Rev growth (yoy) | J2: =#REF! -> #REF! | K2: =#REF! -> #REF!
A3: Rev growth rate | B3: =#REF! -> #REF! | C3: =C2/B2-1 -> #REF! | D3: =B36 -> 0.2 | E3: =D3 -> 0.2 | F3: =E3 -> 0.2 | H3: CF yield | I3: =I11/I10 -> #REF! | J3: =J11/J10 -> #REF! | K3: =K11/K10 -> #REF! | L3: =L11/L10 -> #REF!
A4: CF Ops | B4: =B2*B5 -> #REF! | C4: =C2*C5 -> #REF! | D4: =D2*D5 -> #REF! | E4: =E2*E5 -> #REF! | F4: =F2*F5 -> #REF! | H4: FCF yield | I4: =I12/I10 -> #REF! | J4: =J12/J10 -> #REF! | K4: =K12/K10 -> #REF! | L4: =L12/L10 -> #REF!
A5: CF yield | B5: 0.1 | C5: =B5 -> 0.1 | D5: =C5 -> 0.1 | E5: =D5 -> 0.1 | F5: 0.2 | H5: Op Margin | I5: =I13/I10 -> #REF! | J5: =J13/J10 -> #REF! | K5: =K13/K10 -> #REF! | L5: =L13/L10 -> #REF!
A6: CapEx | B6: =B2*B7 -> #REF! | C6: =C2*C7 -> #REF! | D6: =D2*D7 -> #REF! | E6: =E2*E7 -> #REF! | F6: =F2*F7 -> #REF! | H6: Net Margin | I6: =I14/I10 -> #REF! | J6: =J14/J10 -> #REF! | K6: =K14/K10 -> #REF! | L6: =L14/L10 -> #REF!
A7: CapEx (% sales) | B7: 0.06 | C7: 0.05 | D7: 0.042 | E7: 0.035 | F7: 0.03 | H7: EPS | I7: =I14/I15 -> #REF! | J7: =J14/J15 -> #REF! | K7: =K14/K15 -> #REF! | L7: =L14/L15 -> #REF!
A8: FCF | B8: =B4-B6 -> #REF! | C8: =C4-C6 -> #REF! | D8: =D4-D6 -> #REF! | E8: =E4-E6 -> #REF! | F8: =F4-F6 -> #REF!
H9: Historical Data | I9: 2011 | J9: 2012 | K9: 2013 | L9: 3 Yr
A10: Discount Period | B10: 1 | C10: 2 | D10: 3 | E10: 4 | F10: 5 | H10: Revenues | I10: =#REF! -> #REF! | J10: =#REF! -> #REF! | K10: =#REF! -> #REF! | L10: =SUM(I10:K10) -> #REF!
A11: DCF | B11: =B8/((1+$B$37)^B10) -> #REF! | C11: =C8/((1+$B$37)^C10) -> #REF! | D11: =D8/((1+$B$37)^D10) -> #REF! | E11: =E8/((1+$B$37)^E10) -> #REF! | F11: =F8/((1+$B$37)^F10) -> #REF! | H11: CF Ops | I11: =#REF! -> #REF! | J11: =#REF! -> #REF! | K11: =#REF! -> #REF! | L11: =SUM(I11:K11) -> #REF!
H12: FCF | I12: =#REF! -> #REF! | J12: =#REF! -> #REF! | K12: =#REF! -> #REF! | L12: =SUM(I12:K12) -> #REF!
A13: Op Income | B13: =#REF! -> #REF! | C13: =#REF! -> #REF! | D13: =D14*D2 -> #REF! | E13: =E14*E2 -> #REF! | F13: =F14*F2 -> #REF! | H13: Op Income | I13: =#REF! -> #REF! | J13: =#REF! -> #REF! | K13: =#REF! -> #REF! | L13: =SUM(I13:K13) -> #REF!
A14: Op margin | B14: =B13/B2 -> #REF! | C14: =C13/C2 -> #REF! | D14: 0.05 | E14: 0.1 | F14: 0.1 | H14: Net Income | I14: =#REF! -> #REF! | J14: =#REF! -> #REF! | K14: =#REF! -> #REF! | L14: =SUM(I14:K14) -> #REF!
A15: Net Income | B15: =#REF! -> #REF! | C15: =#REF! -> #REF! | D15: =D16*D2 -> #REF! | E15: =E16*E2 -> #REF! | F15: =F16*F2 -> #REF! | H15: # shares | I15: =#REF! -> #REF! | J15: =#REF! -> #REF! | K15: =#REF! -> #REF! | L15: =K15 -> #REF!
A16: Net Margin | B16: =B15/B2 -> #REF! | C16: =C15/C2 -> #REF! | D16: 0.05 | E16: 0.1 | F16: 0.1
A17: EPS | B17: =#REF! -> #REF! | C17: =#REF! -> #REF! | D17: =D15/D18 -> #REF! | E17: =E15/E18 -> #REF! | F17: =F15/F18 -> #REF!
A18: # Shares | B18: =#REF! -> #REF! | C18: =#REF! -> #REF! | D18: =C18*1.01 -> #REF! | E18: =D18*1.01 -> #REF! | F18: =E18*1.01 -> #REF!
A20: Valuation w/ Discounted Terminal Val | B20: EV/Rev | C20: EV/Earnings | D20: EV/FCF
A21: Sum of FCFs | B21: =SUM(B11:F11) -> #REF! | C21: =B21 -> #REF! | D21: =C21 -> #REF!
A22: Terminal Value (discounted) | B22: =(B26*F2)/((1+B37)^(F10)) -> #REF! | C22: =(C26*F15)/((1+B37)^F10) -> #REF! | D22: =(D26*F8)/((1+B37)^F10) -> #REF!
A23: Cash | B23: =#REF! -> #REF! | C23: =B23 -> #REF! | D23: =B23 -> #REF!
A24: Value (w/ terminal discount) | B24: =SUM(B21:B23) -> #REF! | C24: =SUM(C21:C23) -> #REF! | D24: =SUM(D21:D23) -> #REF!
A25: Share Price | B25: =B24/$B$18 -> #REF! | C25: =C24/$B$18 -> #REF! | D25: =D24/$B$18 -> #REF!
A26: Multiple (w/ discount) | B26: 5.8 | C26: 58 | D26: 35
A28: Valuation w/o TV Discount | B28: EV/Rev | C28: EV/Earnings | D28: EV/FCF
A29: Sum of FCFs | B29: =B21 -> #REF! | C29: =B29 -> #REF! | D29: =C29 -> #REF!
A30: Terminal Value (ex-discount) | B30: =B34*F2 -> #REF! | C30: =C34*F15 -> #REF! | D30: =D34*F8 -> #REF!
A31: Cash | B31: =B23 -> #REF! | C31: =B31 -> #REF! | D31: =C31 -> #REF!
A32: Value | B32: =SUM(B29:B31) -> #REF! | C32: =SUM(C29:C31) -> #REF! | D32: =SUM(D29:D31) -> #REF!
A33: Share Price | B33: =B32/$B$18 -> #REF! | C33: =C32/$B$18 -> #REF! | D33: =D32/$B$18 -> #REF!
A34: Multiple (w/ discount) | B34: 3.4 | C34: 34 | D34: 20
A36: Growth Rate | B36: 0.2
A37: Discount Rate | B37: 0.12

Sheet Summary Metrics
E7: Summary Metrics | F7: =IS!H4 -> 2019 | G7: 2020 | H7: 2021E | I7: 2022E | J7: 2023E
E8: Total Revenue | F8: =IS!H11 -> 48556 | G8: =IS!M11 -> 68444 | H8: =IS!R11 -> 114342 | I8: =IS!W11 -> 135190 | J8: =IS!AB11 -> 138090
E9: Y/Y Growth | F9: NA | G9: =G8/F8-1 -> 0.40958893 | H9: =H8/G8-1 -> 0.67059202 | I9: =I8/H8-1 -> 0.1823302 | J9: =J8/I8-1 -> 0.021451291
E10: Non-GAAP Gross Profit | F10: =IS!H15 -> 34106 | G10: =IS!M15 -> 48023 | H10: =IS!R15 -> 83301 | I10: =IS!W15 -> 101965 | J10: =IS!AB15 -> 104178
E11: Margin | F11: =IS!H16 -> 0.70240547 | G11: =IS!M16 -> 0.7016393 | H11: =IS!R16 -> 0.72852495 | I11: =IS!W16 -> 0.75423478 | J11: =IS!AB16 -> 0.75442103
E12: Total Non-GAAP Operating Expense | F12: =IS!H25 -> 60336 | G12: =IS!M25 -> 69588 | H12: =IS!R25 -> 101527 | I12: =IS!W25 -> 149983 | J12: =IS!AB25 -> 134701
E13: % Revenue | F13: =F12/F8 -> 1.2426065 | G13: =G12/G8 -> 1.0167144 | H13: =H12/H8 -> 0.88792395 | I13: =I12/I8 -> 1.1094238 | J13: =J12/J8 -> 0.97545803
E14: Non-GAAP Operating Income (Loss) | F14: =IS!H27 -> -26230 | G14: =IS!M27 -> -21565 | H14: =IS!R27 -> -18226 | I14: =IS!W27 -> -48018 | J14: =IS!AB27 -> -30523
E15: Margin | F15: =IS!H28 -> -0.54020101 | G15: =IS!M28 -> -0.3150751 | H15: =IS!R28 -> -0.159399 | I15: =IS!W28 -> -0.35518899 | J15: =IS!AB28 -> -0.221037
E16: Adjusted EBITDA | F16: =IS!H50 -> -25428 | G16: =IS!M50 -> -19941 | H16: =IS!R50 -> -16392 | I16: =IS!W50 -> -44524 | J16: =IS!AB50 -> -25894
E17: Margin | F17: =IS!H51 -> -0.52368399 | G17: =IS!M51 -> -0.29134767 | H17: =IS!R51 -> -0.1433594 | I17: =IS!W51 -> -0.32934389 | J17: =IS!AB51 -> -0.18751539
E18: Non-GAAP EPS | F18: =IS!H65 -> -0.39799694 | G18: =IS!M65 -> -0.33824164 | H18: =IS!R65 -> -0.4035986 | I18: =IS!W65 -> -0.80280962 | J18: =IS!AB65 -> -0.37979253
E20: Operating Cash Flow | F20: =CF!H25 -> -27299 | G20: =CF!M25 -> -22712 | H20: =CF!R25 -> -21642 | I20: =CF!W25 -> -46014 | J20: =CF!AB25 -> -25531
E21: Free Cash Flow | F21: =CF!H36 -> -30624 | G21: =CF!M36 -> -24616 | H21: =CF!R36 -> -24749 | I21: =CF!W36 -> -50392 | J21: =CF!AB36 -> -30390
E22: Margin | F22: =CF!H37 -> -0.63069446 | G22: =CF!M37 -> -0.35965169 | H22: =CF!R37 -> -0.21644715 | I22: =CF!W37 -> -0.37274946 | J22: =CF!AB37 -> -0.22007386
E25: Metrics | F25: 1Q19 | G25: 2Q19 | H25: 3Q19 | I25: 4Q19 | J25: 2019 | K25: 1Q20 | L25: 2Q20 | M25: 3Q20 | N25: 4Q20 | O25: 2020 | P25: 1Q21 | Q25: 2Q21 | R25: 3Q21 | S25: 4Q21 | T25: 2021
E26: Total Customers | F26: 480 | G26: 509 | H26: 530 | I26: 635 | K26: 713 | L26: 762 | M26: 792 | N26: 825 | P26: 909 | S26: 1126
E27: Net quartely additions | G27: =G26-F26 -> 29 | H27: =H26-G26 -> 21 | I27: =I26-G26 -> 126 | K27: =K26-I26 -> 78 | L27: =L26-K26 -> 49 | M27: =M26-L26 -> 30 | N27: =N26-M26 -> 33 | P27: =P26-N26 -> 84 | Q27: =Q26-P26 -> -909 | R27: =R26-Q26 -> 0 | S27: =S26-R26 -> 1126 | U27: =U26-S26 -> -1126 | V27: =V26-U26 -> 0 | W27: =W26-V26 -> 0 | X27: =X26-W26 -> 0
E28: q/q growth | G28: =(G26-F26)/F26 -> 0.060416667 | H28: =(H26-G26)/G26 -> 0.041257367 | I28: =(I26-H26)/H26 -> 0.19811321 | K28: =(K26-I26)/I26 -> 0.12283465 | L28: =(L26-K26)/K26 -> 0.068723703 | M28: =(M26-L26)/L26 -> 0.039370079 | N28: =(N26-M26)/M26 -> 0.041666667 | P28: =(P26-N26)/N26 -> 0.10181818 | Q28: =(Q26-P26)/P26 -> -1 | R28: =(R26-Q26)/Q26 -> #DIV/0! | S28: =(S26-R26)/R26 -> #DIV/0! | U28: =(U26-S26)/S26 -> -1 | V28: =(V26-U26)/U26 -> #DIV/0! | W28: =(W26-V26)/V26 -> #DIV/0! | X28: =(X26-W26)/W26 -> #DIV/0!
E29: y/y growth | K29: =(K26-F26)/F26 -> 0.48541667 | L29: =(L26-G26)/G26 -> 0.49705305 | M29: =(M26-H26)/H26 -> 0.49433962 | N29: =(N26-I26)/I26 -> 0.2992126 | P29: =(P26-K26)/K26 -> 0.27489481 | Q29: =(Q26-L26)/L26 -> -1 | R29: =(R26-M26)/M26 -> -1 | S29: =(S26-N26)/N26 -> 0.36484848 | U29: =(U26-P26)/P26 -> -1 | V29: =(V26-Q26)/Q26 -> #DIV/0! | W29: =(W26-R26)/R26 -> #DIV/0! | X29: =(X26-S26)/S26 -> -1
E31: ARPU | F31: =(IS!D11/F26)*4000 -> 86483.333 | G31: =(IS!E11/G26)*4000 -> 88840.864 | H31: =(IS!F11/H26)*4000 -> 95486.792 | I31: =(IS!G11/I26)*4000 -> 89581.102 | K31: =(IS!I11/K26)*4000 -> 87899.018 | L31: =(IS!J11/L26)*4000 -> 82556.43 | M31: =(IS!K11/M26)*4000 -> 90217.172 | N31: =(IS!L11/N26)*4000 -> 93023.03 | P31: =(IS!N11/P26)*4000 -> 92985.699 | S31: =(IS!Q11/S26)*4000 -> 120106.57
E32: Net quarterly increase | G32: =G31-F31 -> 2357.5311 | H32: =H31-G31 -> 6645.928 | I32: =I31-H31 -> -5905.6901 | K32: =K31-I31 -> -1682.0841 | L32: =L31-K31 -> -5342.5878 | M32: =M31-L31 -> 7660.7413 | N32: =N31-M31 -> 2805.8586 | P32: =P31-N31 -> -37.331733 | Q32: =Q31-P31 -> -92985.699 | R32: =R31-Q31 -> 0 | S32: =S31-R31 -> 120106.57 | U32: =U31-T31 -> 0 | V32: =V31-U31 -> 0 | W32: =W31-V31 -> 0 | Y32: =Y31-W31 -> 0
E33: q/q growth | G33: =(G31-F31)/F31 -> 0.027259947 | H33: =(H31-G31)/G31 -> 0.074807107 | I33: =(I31-H31)/H31 -> -0.06184824 | K33: =(K31-I31)/I31 -> -0.018777221 | L33: =(L31-K31)/K31 -> -0.060780972 | M33: =(M31-L31)/L31 -> 0.092793998 | N33: =(N31-M31)/M31 -> 0.031101159 | P33: =(P31-N31)/N31 -> -0.0004013171 | Q33: =(Q31-P31)/P31 -> -1 | R33: =(R31-Q31)/Q31 -> #DIV/0! | S33: =(S31-R31)/R31 -> #DIV/0! | U33: =(U31-T31)/T31 -> #DIV/0! | V33: =(V31-U31)/U31 -> #DIV/0! | W33: =(W31-V31)/V31 -> #DIV/0! | Y33: =(Y31-W31)/W31 -> #DIV/0!
E34: y/y growth | K34: =(K31-F31)/F31 -> 0.016369453 | L34: =(L31-G31)/G31 -> -0.0707381 | M34: =(M31-H31)/H31 -> -0.055186907 | N34: =(N31-I31)/I31 -> 0.038422478 | P34: =(P31-K31)/K31 -> 0.057869592 | Q34: =(Q31-L31)/L31 -> -1 | R34: =(R31-M31)/M31 -> -1 | S34: =(S31-N31)/N31 -> 0.29114878 | U34: =(U31-P31)/P31 -> -1 | V34: =(V31-Q31)/Q31 -> #DIV/0! | W34: =(W31-R31)/R31 -> #DIV/0! | Y34: =(Y31-T31)/T31 -> #DIV/0!
E36: Net Dollar Revenue Retention | K36: 1.36 | L36: 1.3 | M36: 1.28 | N36: 1.27 | P36: 1.22 | S36: 1.46
E37: Net quarterly change | L37: =L36-K36 -> -0.06 | M37: =M36-L36 -> -0.02 | N37: =N36-M36 -> -0.01 | P37: =P36-N36 -> -0.05 | Q37: =Q36-P36 -> -1.22 | R37: =R36-Q36 -> 0 | S37: =S36-R36 -> 1.46 | U37: =U36-S36 -> -1.46 | V37: =V36-U36 -> 0 | W37: =W36-V36 -> 0 | X37: =X36-W36 -> 0
E38: q/q growth | L38: =(L36-K36)/K36 -> -0.044117647 | M38: =(M36-L36)/L36 -> -0.015384615 | N38: =(N36-M36)/M36 -> -0.0078125 | P38: =(P36-N36)/N36 -> -0.039370079 | Q38: =(Q36-P36)/P36 -> -1 | R38: =(R36-Q36)/Q36 -> #DIV/0! | S38: =(S36-R36)/R36 -> #DIV/0! | U38: =(U36-S36)/S36 -> -1 | V38: =(V36-U36)/U36 -> #DIV/0! | W38: =(W36-V36)/V36 -> #DIV/0! | X38: =(X36-W36)/W36 -> #DIV/0!
E39: y/y growth | P39: =(P36-K36)/K36 -> -0.10294118 | Q39: =(Q36-L36)/L36 -> -1 | R39: =(R36-M36)/M36 -> -1 | S39: =(S36-N36)/N36 -> 0.1496063 | U39: =(U36-P36)/P36 -> -1 | V39: =(V36-Q36)/Q36 -> #DIV/0! | W39: =(W36-R36)/R36 -> #DIV/0! | X39: =(X36-S36)/S36 -> -1

Sheet Initiation
A1: Reports Contained
A2: Revenue vs. Operating Margin
A3: CAC Ratio
A4: Long-term Model
A5: Gross margins vs. Q/Q Revenue growth | Z5: Long term model
AA7: FY20 | AB7: FY21E | AC7: Target Model
C8: 2019 | D8: 2020 | E8: 2021E | F8: 2022E | G8: 2023E | J8: CAC Ratio | Z8: Gross Margin | AA8: 0.702 | AB8: 0.71 | AC8: 73-78%
B9: Revenues ($M) | C9: =(IS!H11)/1000 -> 48.556 | D9: =(IS!M11)/1000 -> 68.444 | E9: =IS!R11/1000 -> 114.342 | F9: =IS!W11/1000 -> 135.19 | G9: =IS!AB11/1000 -> 138.09 | J9: 4Q20 | K9: 1Q21 | L9: 2Q21E | M9: 3Q21E | N9: 4Q21E | O9: 1Q22E | P9: 2Q22E | Q9: 3Q22E | R9: 4Q22E | S9: 1Q23E | T9: 2Q23E | U9: 3Q22E | V9: 4Q23E | Z9: Sales and Marketing % | AA9: 0.449 | AB9: 0.448 | AC9: 25-30%
B10: Non-GAAP Operating Margin | C10: =IS!H28 -> -0.54020101 | D10: =IS!M28 -> -0.3150751 | E10: =IS!R28 -> -0.159399 | F10: =IS!W28 -> -0.35518899 | G10: =IS!AB28 -> -0.221037 | J10: =IS!L108 -> 1.5449517 | K10: =IS!N108 -> 1.489318 | L10: =IS!O108 -> 1.2782083 | M10: =IS!P108 -> 1.2125992 | N10: =IS!Q108 -> 0.99758159 | O10: =IS!S108 -> 1.0341526 | P10: =IS!T108 -> 1.1972264 | Q10: =IS!U108 -> 1.4333348 | R10: =IS!V108 -> 3.2930257 | S10: =IS!X108 -> 5.322177 | T10: =IS!Y108 -> 6.3457611 | U10: =IS!Z108 -> 5.734216 | V10: =IS!AA108 -> 21.42 | Z10: Research & Development % | AA10: 0.376 | AB10: 0.316 | AC10: 17-20%
Z11: General & Administrative % | AA11: 0.192 | AB11: 0.232 | AC11: 8-10%
Z12: Adj. EBITDA Margin | AA12: -0.291 | AB12: -0.269 | AC12: 20%+
C35: 2019 | D35: 2020 | E35: 2021E | F35: 2022E | G35: 2023E
B36: Operating Cash Flow | C36: =CF!H25 -> -27299 | D36: =CF!M25 -> -22712 | E36: =CF!R25 -> -21642 | F36: =CF!W25 -> -46014 | G36: =CF!AB25 -> -25531
B37: OCF margins | C37: =CF!H26 -> -0.56221682 | D37: =CF!M26 -> -0.33183332 | E37: =CF!R26 -> -0.18927428 | F37: =CF!W26 -> -0.34036541 | G37: =CF!AB26 -> -0.18488667
B38: Free Cash Flow | C38: =CF!H36 -> -30624 | D38: =CF!M36 -> -24616 | E38: =CF!R36 -> -24749 | F38: =CF!W36 -> -50392 | G38: =CF!AB36 -> -30390
B39: FCF Margins | C39: =CF!H37 -> -0.63069446 | D39: =CF!M37 -> -0.35965169 | E39: =CF!R37 -> -0.21644715 | F39: =CF!W37 -> -0.37274946 | G39: =CF!AB37 -> -0.22007386
B40: Source: Company reports and Needham & Company estimates
C46: 1Q19 | D46: 2Q19 | E46: 3Q19 | F46: 4Q19 | G46: 1Q20 | H46: 2Q20 | I46: 3Q20 | J46: 4Q20 | K46: 1Q21
B47: Q/Q Revenue Growth | D47: 0.089323569 | E47: 0.11915082 | F47: 0.12401201 | G47: 0.10175093 | H47: 0.003765637 | I47: 0.13581738 | J47: 0.074063707 | K47: 0.101376
B48: Gross Margins | C48: 0.72037001 | D48: 0.70773994 | E48: 0.71403731 | F48: 0.67470642 | G48: 0.67672964 | H48: 0.7137407 | I48: 0.69126127 | J48: 0.72172417 | K48: 0.72646822

Sheet CF Metrics
C2: FY20 | D2: FY21E | E2: FY22E | F2: FY23E
B3: Operating Cash Flow | C3: =CF!M25 -> -22712 | D3: =CF!R25 -> -21642 | E3: =CF!W25 -> -46014 | F3: =CF!AB25 -> -25531
B4: OCF Margin | C4: =CF!M26 -> -0.33183332 | D4: =CF!R26 -> -0.18927428 | E4: =CF!W26 -> -0.34036541 | F4: =CF!AB26 -> -0.18488667
B5: Free Cash Flow | C5: =CF!M36 -> -24616 | D5: =CF!R36 -> -24749 | E5: =CF!W36 -> -50392 | F5: =CF!AB36 -> -30390
B6: FCF Margin | C6: =CF!M37 -> -0.35965169 | D6: =CF!R37 -> -0.21644715 | E6: =CF!W37 -> -0.37274946 | F6: =CF!AB37 -> -0.22007386

Sheet V Sensitivity
B2: Share Price and Upside Sensitivity | K2: Base Scenario for table
D4: FY22 / FY23 Revenue Growth
C5: EV / Revenue | D5: =Q32 -> 59.285861 | E5: 0.3 | F5: =E5+0.025 -> 0.325 | G5: =F5+0.025 -> 0.35 | H5: =G5+0.025 -> 0.375 | I5: =H5+0.025 -> 0.4
D6: 20 | E6: 43.009937 | F6: 44.545192 | G6: 46.10969 | H6: 47.70343 | I6: 49.326414
D7: =D6+2.5 -> 22.5 | E7: 47.951995 | F7: 49.679157 | G7: 51.439217 | H7: 53.232176 | I7: 55.058032
D8: =D7+2.5 -> 25 | E8: 52.894054 | F8: 54.813122 | G8: 56.768745 | H8: 58.760921 | I8: 60.78965
D9: =D8+2.5 -> 27.5 | E9: 57.836112 | F9: 59.947088 | G9: 62.098272 | H9: 64.289666 | I9: 66.521268
D10: =D9+2.5 -> 30 | E10: 62.778171 | F10: 65.081053 | G10: 67.4278 | H10: 69.818411 | I10: 72.252886
D13: FY22 / FY23 Revenue Growth
C14: EV / Revenue | E14: =E5 -> 0.3 | F14: =F5 -> 0.325 | G14: =G5 -> 0.35 | H14: =H5 -> 0.375 | I14: =I5 -> 0.4
D15: =D6 -> 20 | E15: =E6/$T$25-1 -> #NAME? | F15: =F6/$T$25-1 -> #NAME? | G15: =G6/$T$25-1 -> #NAME? | H15: =H6/$T$25-1 -> #NAME? | I15: =I6/$T$25-1 -> #NAME?
D16: =D7 -> 22.5 | E16: =E7/$T$25-1 -> #NAME? | F16: =F7/$T$25-1 -> #NAME? | G16: =G7/$T$25-1 -> #NAME? | H16: =H7/$T$25-1 -> #NAME? | I16: =I7/$T$25-1 -> #NAME?
D17: =D8 -> 25 | E17: =E8/$T$25-1 -> #NAME? | F17: =F8/$T$25-1 -> #NAME? | G17: =G8/$T$25-1 -> #NAME? | H17: =H8/$T$25-1 -> #NAME? | I17: =I8/$T$25-1 -> #NAME?
D18: =D9 -> 27.5 | E18: =E9/$T$25-1 -> #NAME? | F18: =F9/$T$25-1 -> #NAME? | G18: =G9/$T$25-1 -> #NAME? | H18: =H9/$T$25-1 -> #NAME? | I18: =I9/$T$25-1 -> #NAME?
D19: =D10 -> 30 | E19: =E10/$T$25-1 -> #NAME? | F19: =F10/$T$25-1 -> #NAME? | G19: =G10/$T$25-1 -> #NAME? | H19: =H10/$T$25-1 -> #NAME? | I19: =I10/$T$25-1 -> #NAME?
B22: Inputs
K24: Base | L24: FY20A | M24: FY21E | N24: FY22E | P24: Base Assumption | S24: Current Valuation
K25: Revenue | L25: =V!O6 -> 68.444 | M25: =L25*(1+M26) -> 96.50604 | N25: =M25*(1+N26) -> 136.07352 | P25: Revenue | Q25: =N25 -> 136.07352 | S25: Current Price | T25: =V!C5 -> #NAME?
K26: Growth | M26: =Q26 -> 0.41 | N26: =M26 -> 0.41 | P26: Growth Rate | Q26: 0.41 | S26: Latest Fully Diluted Shares | T26: =V!C22 -> 57.972
P27: Multiple | Q27: 24 | S27: Latest Cash | T27: =V!C20 -> 238.576
K28: Actual Est. | L28: =V!O6 -> 68.444 | M28: =V!T6 -> 114.342 | N28: =V!Y6 -> 135.19 | P28: EV | Q28: =Q27*N25 -> 3265.7644 | S28: Latest Debt | T28: =V!C21 -> 0
K29: Growth | M29: =M28/L28-1 -> 0.67059202 | N29: =N28/M28-1 -> 0.1823302 | P29: (+) Net Cash | Q29: =(V!Y20-V!Y21) -> 203.244 | S29: Current Mkt. Cap | T29: =T25*T26 -> #NAME?
P30: Mkt. Cap | Q30: =Q28+Q29 -> 3469.0084 | S30: Current EV | T30: =T29-T27 -> #NAME?
P31: Assumed Shares | Q31: =V!Y22 -> 58.51325 | S31: Current EV / 22E Sales | T31: =T30/M28 -> #NAME?
P32: Implied Share Price | Q32: =Q30/Q31 -> 59.285861 | S32: Current EV / 23E Sales | T32: =T30/N28 -> #NAME?

Sheet Sheet1
F5: 2Q25 Adj. EBITDA Loss | G5: =IS!AI50 -> -2688
F6: 60% Revenue Conversion level to reduce Adj. EBITDA Loss to $0 | G6: =-G5/0.6 -> 4480
F8: 2Q Total Revenue | G8: =IS!AI11 -> 38106
F10: Quarterly revenue required to achieve Adj. EBITDA breakeven (2Q total revenue + $4,480k) | G10: =G8+G6 -> 42586
F12: Current 4Q26 5.8% revenue estimate | G12: =IS!AP11 -> 45909.808
