Workbook
Name _15__xlnm.Print_Area: #N/A
Name _1994: #REF!
Name _1994: #REF!
Name _1995: #REF!
Name _1995: #REF!
Name _1996: #REF!
Name _1996: #REF!
Name _1997: #REF!
Name _1997: #REF!
Name _1998: #REF!
Name _1998: #REF!
Name _1999: #REF!
Name _1999: #REF!
Name _1Q94: #REF!
Name _1Q94: #REF!
Name _1Q95: #REF!
Name _1Q95: #REF!
Name _2007: [1]BalanceSheet!#REF!
Name _2007: [1]BalanceSheet!#REF!
Name _2008: [1]BalanceSheet!#REF!
Name _2008: [1]BalanceSheet!#REF!
Name _2Q94: #REF!
Name _2Q94: #REF!
Name _2Q95: #REF!
Name _2Q95: #REF!
Name _3Q94: #REF!
Name _3Q94: #REF!
Name _3Q95: #REF!
Name _3Q95: #REF!
Name _4Q94: #REF!
Name _4Q94: #REF!
Name _4Q95: #REF!
Name _4Q95: #REF!
Name _dcf2: [2]Sheet15!#REF!
Name _Key1: [3]BMY!#REF!
Name _Key1: [3]BMY!#REF!
Name _Order1: 0
Name _Sort: [3]BMY!#REF!
Name _Sort: [3]BMY!#REF!
Name _top4: #REF!
Name a: [4]NOPAT_VDF!$C$90:$AE$90
Name a: [5]NOPAT_VDF!$C$90:$AE$90
Name a: [6]NOPAT_VDF!$C$90:$AE$90
Name abit: 0.000000001
Name Acc_payable: '[7]Invested capital_VDF'!$C$17:$AE$17
Name Acc_payable: '[6]Invested capital_VDF'!$C$17:$AE$17
Name Acc_payable_growth_fore: [4]Forecasts_VDF!$H$150:$K$150
Name Acc_payable_growth_fore: [5]Forecasts_VDF!$H$150:$K$150
Name Acc_payable_growth_fore: [6]Forecasts_VDF!$H$150:$K$150
Name Acc_Rec: '[7]Invested capital_VDF'!$C$7:$AE$7
Name Acc_Rec: '[5]Invested capital_VDF'!$C$7:$AE$7
Name Acc_Rec: '[6]Invested capital_VDF'!$C$7:$AE$7
Name Acc_Rec_growth_fore: [4]Forecasts_VDF!$H$147:$K$147
Name Acc_Rec_growth_fore: [5]Forecasts_VDF!$H$147:$K$147
Name Acc_Rec_growth_fore: [6]Forecasts_VDF!$H$147:$K$147
Name Acc_Rec_turns: '[7]Invested capital_VDF'!$C$95:$Q$95
Name Acc_Rec_turns: '[5]Invested capital_VDF'!$C$95:$Q$95
Name Acc_Rec_turns: '[6]Invested capital_VDF'!$C$95:$Q$95
Name Accel_Ratio: '[7]Summary Page_VDF'!$E$9
Name Accel_Ratio: '[5]Summary Page_VDF'!$E$9

Sheet __FDSCACHE__
B1: This sheet contains FactSet XML data for use with this workbook's =FDS codes. Modifying the worksheet's contents may damage the workbook's =FDS functionality.

Sheet Intro
A1: 46070
C5: NeoGenomics
C6: Nasdaq: NEO
C8: Tycho Peterson
C9: Life Science Tools & Diagnostics
C10: 212.738.5583
C11: tpeterson2@jefferies.com
C13: Matt Stanton
C14: 615.963.8397
C15: mstanton@jefferies.com
C17: Jack Melick
C18: 617.345.8671
C19: jmelick@jefferies.com
... C31: ppatel5@jefferies.com

Sheet IS
EY2: =Intro!C5 -> NeoGenomics
EY3: Historical and Projected Statements of Income
EY4: Dollars in millions, except per share amounts
D5: Historical results | J5: Historical results | P5: Historical results | V5: Historical results | AB5: Historical results | AH5: Historical results | AN5: Historical results | AT5: Historical results | AZ5: Historical results | BF5: Historical results | BL5: Historical results | BR5: Historical results | BX5: Historical results | CD5: Historical results | CJ5: Historical results | CP5: Historical results | CV5: Historical results | DB5: Historical results | DH5: Historical results | DN5: Historical results | DT5: Historical results | DZ5: Historical results | EF5: Historical results | EL5: Historical results | ER5: Historical results | EX5: Historical results | FD5: Projections | FJ5: Projections | FP5: Projections | FV5: Projections | GB5: Projections | GH5: Projections | GN5: Projections | GT5: Projections | GZ5: Projections | HF5: Projections
D6: 2000 | J6: 2001 | P6: 2002 | V6: 2003 | AB6: 2004 | AH6: 2005 | AN6: 2006 | AT6: 2007 | AZ6: 2008 | BF6: 2009 | BL6: 2010 | BR6: 2011 | BX6: 2012 | CD6: 2013 | CJ6: 2014 | CP6: 2015 | CV6: 2016 | DB6: 2017 | DH6: 2018 | DN6: 2019 | DT6: 2020 | DZ6: 2021 | EF6: 2022 | EL6: 2023 | ER6: =EL6+1 -> 2024 | EX6: =ER6+1 -> 2025 | FD6: =EX6+1 -> 2026 | FJ6: =FD6+1 -> 2027 | FP6: =FJ6+1 -> 2028 | FV6: =FP6+1 -> 2029 | GB6: =FV6+1 -> 2030 | GH6: =GB6+1 -> 2031 | GN6: =GH6+1 -> 2032 | GT6: =GN6+1 -> 2033 | GZ6: =GT6+1 -> 2034 | HF6: =GZ6+1 -> 2035
D7: 36616 | E7: 36707 | F7: 36799 | G7: 36891 | H7: Total | J7: 36981 | K7: 37072 | L7: 37164 | M7: 37256 | N7: Total | P7: 37346 | Q7: 37437 | R7: 37529 | S7: 37621 | T7: Total | V7: 37711 | W7: 37802 | X7: 37894 | Y7: 37986 | Z7: Total | AB7: 38077 | AC7: 38168 | AD7: 38260 | AE7: 38352 | AF7: Total | AH7: 38442 | AI7: 38533 | AJ7: 38625 | AK7: 38717 | AL7: Total | AN7: =AH7+365 -> 38807 | AO7: =AI7+365 -> 38898 | AP7: =AJ7+365 -> 38990 | AQ7: =AK7+365 -> 39082 | AR7: Total | AT7: =AN7+365 -> 39172 | AU7: =AO7+365 -> 39263 | AV7: =AP7+365 -> 39355 | AW7: =AQ7+365 -> 39447 | AX7: Total | AZ7: =AT7+365 -> 39537 | BA7: =AU7+365 -> 39628 | BB7: =AV7+365 -> 39720 | BC7: =AW7+365 -> 39812 | BD7: Total | BF7: =AZ7+365 -> 39902 | BG7: =BA7+365 -> 39993 | BH7: =BB7+365 -> 40085 | BI7: =BC7+365 -> 40177 | BJ7: Total | BL7: =BF7+365 -> 40267 | BM7: =BG7+365 -> 40358 | BN7: =BH7+365 -> 40450 | BO7: =BI7+365 -> 40542 | BP7: Total | BR7: =BL7+365 -> 40632 | BS7: =BM7+365 -> 40723 | BT7: =BN7+365 -> 40815 | BU7: =BO7+365 -> 40907 | BV7: Total | BX7: =BR7+365 -> 40997 | BY7: =BS7+365 -> 41088 | BZ7: =BT7+365 -> 41180 | CA7: =BU7+365 -> 41272 | CB7: Total | CD7: =BX7+365 -> 41362 | CE7: =BY7+365 -> 41453 | CF7: =BZ7+365 -> 41545 | CG7: =CA7+365 -> 41637 | CH7: Total | CJ7: =CD7+365 -> 41727 | CK7: =CE7+365 -> 41818 | CL7: =CF7+365 -> 41910 | CM7: =CG7+365 -> 42002 | CN7: Total | CP7: =CJ7+365 -> 42092 | CQ7: =CK7+365 -> 42183 | CR7: =CL7+365 -> 42275 | CS7: =CM7+365 -> 42367 | CT7: Total | CV7: =CP7+365 -> 42457 | CW7: =CQ7+365 -> 42548 | CX7: =CR7+365 -> 42640 | CY7: =CS7+365 -> 42732 | CZ7: Total | DB7: =CV7+365 -> 42822 | DC7: =CW7+365 -> 42913 | DD7: =CX7+365 -> 43005 | DE7: =CY7+365 -> 43097 | DF7: Total | DH7: 43190 | DI7: 43281 | DJ7: 43373 | DK7: 43465 | DL7: Total | DN7: =DH7+365 -> 43555 | DO7: =DI7+365 -> 43646 | DP7: =DJ7+365 -> 43738 | DQ7: =DK7+365 -> 43830 | DR7: Total | DT7: =DN7+365 -> 43920 | DU7: =DO7+365 -> 44011 | DV7: =DP7+365 -> 44103 | DW7: =DQ7+365 -> 44195 | DX7: Total | DZ7: =DT7+365 -> 44285 | EA7: =DU7+365 -> 44376 | EB7: =DV7+365 -> 44468 | EC7: =DW7+365 -> 44560 | ED7: Total | EF7: =DZ7+365 -> 44650 | EG7: =EA7+365 -> 44741 | EH7: =EB7+365 -> 44833 | EI7: =EC7+365 -> 44925 | EJ7: Total | EL7: =EF7+365 -> 45015 | EM7: =EG7+365 -> 45106 | EN7: =EH7+365 -> 45198 | EO7: =EI7+365 -> 45290 | EP7: Total | ER7: =EOMONTH(EL7+365,0) -> 45382 | ES7: =EOMONTH(EM7+365,0) -> 45473 | ET7: =EOMONTH(EN7+365,0) -> 45565 | EU7: =EOMONTH(EO7+365,0) -> 45657 | EV7: Total | EX7: =EOMONTH(ER7+365,0) -> 45747 | EY7: =EOMONTH(ES7+365,0) -> 45838 | EZ7: =EOMONTH(ET7+365,0) -> 45930 | FA7: =EOMONTH(EU7+365,0) -> 46022 | FB7: Total | FD7: =EOMONTH(EX7+365,0) -> 46112 | FE7: =EOMONTH(EY7+365,0) -> 46203 | FF7: =EOMONTH(EZ7+365,0) -> 46295 | FG7: =EOMONTH(FA7+365,0) -> 46387 | FH7: Total | FJ7: =EOMONTH(FD7+365,0) -> 46477 | FK7: =EOMONTH(FE7+365,0) -> 46568 | FL7: =EOMONTH(FF7+365,0) -> 46660 | FM7: =EOMONTH(FG7+365,0) -> 46752 | FN7: Total | FP7: =EOMONTH(FJ7+365,0) -> 46843 | FQ7: =EOMONTH(FK7+365,0) -> 46934 | FR7: =EOMONTH(FL7+365,0) -> 47026 | FS7: =EOMONTH(FM7+365,0) -> 47118 | FT7: Total | FV7: =EOMONTH(FP7+365,0) -> 47208 | FW7: =EOMONTH(FQ7+365,0) -> 47299 | FX7: =EOMONTH(FR7+365,0) -> 47391 | FY7: =EOMONTH(FS7+365,0) -> 47483 | FZ7: Total | GB7: =EOMONTH(FV7+365,0) -> 47573 | GC7: =EOMONTH(FW7+365,0) -> 47664 | GD7: =EOMONTH(FX7+365,0) -> 47756 | GE7: =EOMONTH(FY7+365,0) -> 47848 | GF7: Total | GH7: =EOMONTH(GB7+365,0) -> 47938 | GI7: =EOMONTH(GC7+365,0) -> 48029 | GJ7: =EOMONTH(GD7+365,0) -> 48121 | GK7: =EOMONTH(GE7+365,0) -> 48213 | GL7: Total | GN7: =EOMONTH(GH7+365,0) -> 48304 | GO7: =EOMONTH(GI7+365,0) -> 48395 | GP7: =EOMONTH(GJ7+365,0) -> 48487 | GQ7: =EOMONTH(GK7+365,0) -> 48579 | GR7: Total | GT7: =EOMONTH(GN7+365,0) -> 48669 | GU7: =EOMONTH(GO7+365,0) -> 48760 | GV7: =EOMONTH(GP7+365,0) -> 48852 | GW7: =EOMONTH(GQ7+365,0) -> 48944 | GX7: Total | GZ7: =EOMONTH(GT7+365,0) -> 49034 | HA7: =EOMONTH(GU7+365,0) -> 49125 | HB7: =EOMONTH(GV7+365,0) -> 49217 | HC7: =EOMONTH(GW7+365,0) -> 49309 | HD7: Total | HF7: =EOMONTH(GZ7+365,0) -> 49399 | HG7: =EOMONTH(HA7+365,0) -> 49490 | HH7: =EOMONTH(HB7+365,0) -> 49582 | HI7: =EOMONTH(HC7+365,0) -> 49674 | HJ7: Total
B9: Net sales | DH9: 63.423 | DI9: 67.746 | DJ9: 69.096 | DK9: 76.475 | DL9: =SUM(DH9:DK9) -> 276.74 | DN9: 95.577 | DO9: 101.713 | DP9: 104.672 | DQ9: 106.868 | DR9: =SUM(DN9:DQ9) -> 408.83 | DT9: 106.03 | DU9: 86.977 | DV9: 125.444 | DW9: 125.997 | DX9: =SUM(DT9:DW9) -> 444.448 | DZ9: 115.533 | EA9: 121.724 | EB9: 121.34 | EC9: 125.732 | ED9: =SUM(DZ9:EC9) -> 484.329 | EF9: 117.169 | EG9: 125.072 | EH9: 128.782 | EI9: 138.705 | EJ9: =SUM(EF9:EI9) -> 509.728 | EL9: 137.22 | EM9: 146.917 | EN9: 151.954 | EO9: 155.552 | EP9: =SUM(EL9:EO9) -> 591.643 | ER9: 156.24 | ES9: 164.502 | ET9: 167.824 | EU9: 172 | EV9: =SUM(ER9:EU9) -> 660.566 | EX9: 168.035 | EY9: 181.33 | EZ9: 187.797 | FA9: 190.17 | FB9: =SUM(EX9:FA9) -> 727.332
C10: Cost of products sold | DH10: 36.12 | DI10: 37.216 | DJ10: 36.775 | DK10: 39.364 | DL10: =DL9-DL11 -> 149.475 | DN10: 48.462 | DO10: 52.747 | DP10: 53.84 | DQ10: 56.945 | DR10: =DR9-DR11 -> 211.994 | DT10: 59.661 | DU10: 58.971 | DV10: 71.379 | DW10: 68.544 | DX10: =DX9-DX11 -> 258.555 | DZ10: 73.959 | EA10: 68.734 | EB10: 74.101 | EC10: 80.475 | ED10: =ED9-ED11 -> 297.269 | EF10: 78.937 | EG10: 81.126 | EH10: 79.889 | EI10: 81.88 | EJ10: =EJ9-EJ11 -> 321.832 | EL10: 82.406 | EM10: 87.026 | EN10: 89.643 | EO10: 87.964 | EP10: =EP9-EP11 -> 347.039 | ER10: 90.771 | ES10: 92.008 | ET10: 92.944 | EU10: 94.743 | EV10: =SUM(ER10:EU10) -> 370.466 | EX10: 94.789 | EY10: 104.072 | EZ10: 107.351 | FA10: 106.827 | FB10: =SUM(EX10:FA10) -> 413.039
B11: Gross profit | DH11: =DH9-DH10 -> 27.303 | DI11: =DI9-DI10 -> 30.53 | DJ11: =DJ9-DJ10 -> 32.321 | DK11: =DK9-DK10 -> 37.111 | DL11: =SUM(DH11:DK11) -> 127.265 | DN11: =DN9-DN10 -> 47.115 | DO11: =DO9-DO10 -> 48.966 | DP11: =DP9-DP10 -> 50.832 | DQ11: =DQ9-DQ10 -> 49.923 | DR11: =SUM(DN11:DQ11) -> 196.836 | DT11: =DT9-DT10 -> 46.369 | DU11: =DU9-DU10 -> 28.006 | DV11: =DV9-DV10 -> 54.065 | DW11: =DW9-DW10 -> 57.453 | DX11: =SUM(DT11:DW11) -> 185.893 | DZ11: =DZ9-DZ10 -> 41.574 | EA11: =EA9-EA10 -> 52.99 | EB11: =EB9-EB10 -> 47.239 | EC11: =EC9-EC10 -> 45.257 | ED11: =SUM(DZ11:EC11) -> 187.06 | EF11: =EF9-EF10 -> 38.232 | EG11: =EG9-EG10 -> 43.946 | EH11: =EH9-EH10 -> 48.893 | EI11: =EI9-EI10 -> 56.825 | EJ11: =SUM(EF11:EI11) -> 187.896 | EL11: =EL9-EL10 -> 54.814 | EM11: =EM9-EM10 -> 59.891 | EN11: =EN9-EN10 -> 62.311 | EO11: =EO9-EO10 -> 67.588 | EP11: =SUM(EL11:EO11) -> 244.604 | ER11: =ER9-ER10 -> 65.469 | ES11: =ES9-ES10 -> 72.494 | ET11: =ET9-ET10 -> 74.88 | EU11: =EU9-EU10 -> 77.257 | EV11: =EV9-EV10 -> 290.1 | EX11: =EX9-EX10 -> 73.246 | EY11: =EY9-EY10 -> 77.258 | EZ11: =EZ9-EZ10 -> 80.446 | FA11: =FA9-FA10 -> 83.343 | FB11: =FB9-FB10 -> 314.293
C12: G&A | DH12: 17.067 | DI12: 20.983 | DJ12: 21.055 | DK12: 25.717 | DL12: =SUM(DH12:DK12) -> 84.822 | DN12: 32.142 | DO12: 29.577 | DP12: 33.054 | DQ12: 33.22 | DR12: =SUM(DN12:DQ12) -> 127.993 | DT12: 36.344 | DU12: 34.613 | DV12: 36.128 | DW12: 36.709 | DX12: =SUM(DT12:DW12) -> 143.794 | DZ12: 40.476 | EA12: 54.638 | EB12: 63.839 | EC12: 62.394 | ED12: =SUM(DZ12:EC12) -> 221.347 | EF12: 66.248 | EG12: 57.951 | EH12: 64.282 | EI12: 57.855 | EJ12: =SUM(EF12:EI12) -> 246.336 | EL12: 61.549 | EM12: 60.308 | EN12: 61.486 | EO12: 59.758 | EP12: =SUM(EL12:EO12) -> 243.101 | ER12: 65.797 | ES12: 63.328 | ET12: 66.969 | EU12: 63.643 | EV12: =SUM(ER12:EU12) -> 259.737 | EX12: 68.207 | EY12: 71.747 | EZ12: 69.874 | FA12: 63.509 | FB12: =SUM(EX12:FA12) -> 273.337
C13: Sales and Marketing | DH13: 6.775 | DI13: 7.68 | DJ13: 6.9 | DK13: 8.047 | DL13: =SUM(DH13:DK13) -> 29.402 | DN13: 11.216 | DO13: 12.324 | DP13: 11.508 | DQ13: 12.302 | DR13: =SUM(DN13:DQ13) -> 47.35 | DT13: 13.258 | DU13: 10.195 | DV13: 11.304 | DW13: 13.105 | DX13: =SUM(DT13:DW13) -> 47.862 | DZ13: 13.749 | EA13: 17.224 | EB13: 15.704 | EC13: 15.917 | ED13: =SUM(DZ13:EC13) -> 62.594 | EF13: 16.299 | EG13: 17.071 | EH13: 16.809 | EI13: 17.142 | EJ13: =SUM(EF13:EI13) -> 67.321 | EL13: 16.259 | EM13: 18.901 | EN13: 17.61 | EO13: 18.072 | EP13: =SUM(EL13:EO13) -> 70.842 | ER13: 20.221 | ES13: 21.677 | ET13: 20.415 | EU13: 22.339 | EV13: =SUM(ER13:EU13) -> 84.652 | EX13: 22.683 | EY13: 24.075 | EZ13: 21.806 | FA13: 23.443 | FB13: =SUM(EX13:FA13) -> 92.007
C14: Research & Development | DH14: 0.956 | DI14: 1.073 | DJ14: 0.446 | DK14: 0.526 | DL14: =SUM(DH14:DK14) -> 3.001 | DN14: 1.209 | DO14: 2.587 | DP14: 2.611 | DQ14: 2.08 | DR14: =SUM(DN14:DQ14) -> 8.487 | DT14: 2.06 | DU14: 2.105 | DV14: 1.964 | DW14: 2.1 | DX14: =SUM(DT14:DW14) -> 8.229 | DZ14: 2.456 | EA14: 3.495 | EB14: 7.409 | EC14: 8.513 | ED14: =SUM(DZ14:EC14) -> 21.873 | EF14: 7.713 | EG14: 8.626 | EH14: 7.312 | EI14: 6.675 | EJ14: =SUM(EF14:EI14) -> 30.326 | EL14: 7.395 | EM14: 7.502 | EN14: 5.285 | EO14: 7.127 | EP14: =SUM(EL14:EO14) -> 27.309 | ER14: 7.62 | ES14: 7.886 | ET14: 7.684 | EU14: 7.969 | EV14: =SUM(ER14:EU14) -> 31.159 | EX14: 10.181 | EY14: 9.023 | EZ14: 8.694 | FA14: 9.179 | FB14: =SUM(EX14:FA14) -> 37.077
C15: Other expenses | DH15: 0 | DI15: 0 | DJ15: 0 | DK15: 0 | DL15: =SUM(DH15:DK15) -> 0 | DN15: 0 | DO15: 0 | DP15: 0 | DQ15: 0 | DR15: =SUM(DN15:DQ15) -> 0 | DT15: 0 | DU15: 0 | DV15: 0 | DW15: 0 | DX15: =SUM(DT15:DW15) -> 0 | DZ15: 0 | EA15: 0 | EB15: 0 | EC15: 0 | ED15: =SUM(DZ15:EC15) -> 0 | EF15: 0 | EG15: 0 | EH15: 0 | EI15: 1.536 | EJ15: =SUM(EF15:EI15) -> 1.536 | EL15: 4.684 | EM15: 3.074 | EN15: 2.125 | EO15: 1.205 | EP15: =SUM(EL15:EO15) -> 11.088 | ER15: 2.398 | ES15: 1.544 | ET15: 1.009 | EU15: 1.707 | EV15: =SUM(ER15:EU15) -> 6.658 | EX15: 0 | EY15: 20.041 | EZ15: 7.086 | FA15: 0.626 | FB15: =SUM(EX15:FA15) -> 27.753
B16: Operating income | DH16: =DH11-SUM(DH12:DH15) -> 2.505 | DI16: =DI11-SUM(DI12:DI15) -> 0.794 | DJ16: =DJ11-SUM(DJ12:DJ15) -> 3.92 | DK16: =DK11-SUM(DK12:DK15) -> 2.821 | DL16: =DL11-SUM(DL12:DL15) -> 10.04 | DN16: =DN11-SUM(DN12:DN15) -> 2.548 | DO16: =DO11-SUM(DO12:DO15) -> 4.478 | DP16: =DP11-SUM(DP12:DP15) -> 3.659 | DQ16: =DQ11-SUM(DQ12:DQ15) -> 2.321 | DR16: =DR11-SUM(DR12:DR15) -> 13.006 | DT16: =DT11-SUM(DT12:DT15) -> -5.293 | DU16: =DU11-SUM(DU12:DU15) -> -18.907 | DV16: =DV11-SUM(DV12:DV15) -> 4.669 | DW16: =DW11-SUM(DW12:DW15) -> 5.539 | DX16: =DX11-SUM(DX12:DX15) -> -13.992 | DZ16: =DZ11-SUM(DZ12:DZ15) -> -15.107 | EA16: =EA11-SUM(EA12:EA15) -> -22.367 | EB16: =EB11-SUM(EB12:EB15) -> -39.713 | EC16: =EC11-SUM(EC12:EC15) -> -41.567 | ED16: =ED11-SUM(ED12:ED15) -> -118.754 | EF16: =EF11-SUM(EF12:EF15) -> -52.028 | EG16: =EG11-SUM(EG12:EG15) -> -39.702 | EH16: =EH11-SUM(EH12:EH15) -> -39.51 | EI16: =EI11-SUM(EI12:EI15) -> -26.383 | EJ16: =EJ11-SUM(EJ12:EJ15) -> -157.623 | EL16: =EL11-SUM(EL12:EL15) -> -35.073 | EM16: =EM11-SUM(EM12:EM15) -> -29.894 | EN16: =EN11-SUM(EN12:EN15) -> -24.195 | EO16: =EO11-SUM(EO12:EO15) -> -18.574 | EP16: =EP11-SUM(EP12:EP15) -> -107.736 | ER16: =ER11-SUM(ER12:ER15) -> -30.567 | ES16: =ES11-SUM(ES12:ES15) -> -21.941 | ET16: -21.197 | EU16: -18.401 | EV16: =EV11-SUM(EV12:EV15) -> -92.106 | EX16: =EX11-SUM(EX12:EX15) -> -27.825 | EY16: =EY11-SUM(EY12:EY15) -> -47.628 | EZ16: =EZ11-SUM(EZ12:EZ15) -> -27.014 | FA16: =FA11-SUM(FA12:FA15) -> -13.414 | FB16: =FB11-SUM(FB12:FB15) -> -115.881
C17: Interest expense | DH17: 1.486 | DI17: 1.407 | DJ17: 1.873 | DK17: 1.464 | DL17: =SUM(DH17:DK17) -> 6.23 | DN17: 1.826 | DO17: 1.304 | DP17: 0.203 | DQ17: 0.38 | DR17: =SUM(DN17:DQ17) -> 3.713 | DT17: 0.819 | DU17: 1.548 | DV17: 2.458 | DW17: 2.194 | DX17: =SUM(DT17:DW17) -> 7.019 | DZ17: 1.177 | EA17: 0.902 | EB17: 1.296 | EC17: 1.707 | ED17: =SUM(DZ17:EC17) -> 5.082 | EF17: 1.301 | EG17: 0.926 | EH17: 0.139 | EI17: 0 | EJ17: =SUM(EF17:EI17) -> 2.366 | EL17: 0 | EM17: 0 | EN17: 0 | EO17: 1.681 | EP17: =SUM(EL17:EO17) -> 1.681 | ER17: 1.685 | ES17: 1.666 | ET17: 1.642 | EU17: 1.624 | EV17: =SUM(ER17:EU17) -> 6.617 | EX17: 1.618 | EY17: 0.933 | EZ17: 0.603 | FA17: 0.599 | FB17: =SUM(EX17:FA17) -> 3.753
C18: Interest income | DH18: 0 | DI18: 0 | DJ18: 0 | DK18: 0 | DL18: =SUM(DH18:DK18) -> 0 | DN18: 0 | DO18: 0 | DP18: 0 | DQ18: 0 | DR18: =SUM(DN18:DQ18) -> 0 | DT18: 0 | DU18: 0 | DV18: 0 | DW18: 0 | DX18: =SUM(DT18:DW18) -> 0 | DZ18: 0 | EA18: 0 | EB18: 0 | EC18: 0 | ED18: =SUM(DZ18:EC18) -> 0 | EF18: 0 | EG18: 0 | EH18: 0 | EI18: -0.86 | EJ18: =SUM(EF18:EI18) -> -0.86 | EL18: -1.467 | EM18: -2.524 | EN18: -2.84 | EO18: -4.845 | EP18: =SUM(EL18:EO18) -> -11.676 | ER18: -4.834 | ES18: -4.592 | ET18: -4.673 | EU18: -4.328 | EV18: =SUM(ER18:EU18) -> -18.427 | EX18: -3.721 | EY18: =-2.263 -> -2.263 | EZ18: -1.563 | FA18: -1.523 | FB18: =SUM(EX18:FA18) -> -9.07
C19: Other expense, net | DH19: =-0.063 -> -0.063 | DI19: 0.124 | DJ19: -0.03 | DK19: -0.046 | DL19: =SUM(DH19:DK19) -> -0.015 | DN19: 5.169 | DO19: =1.018-0.01 -> 1.008 | DP19: -0.035 | DQ19: -0.494 | DR19: =SUM(DN19:DQ19) -> 5.648 | DT19: -0.223 | DU19: =-7.405+1.4+3.506 -> -2.499 | DV19: -0.011 | DW19: -4.222 | DX19: =SUM(DT19:DW19) -> -6.955 | DZ19: 4.854 | EA19: =-0.171-96.534 -> -96.705 | EB19: =-17.75-0.089 -> -17.839 | EC19: 0.93 | ED19: =SUM(DZ19:EC19) -> -108.76 | EF19: -0.168 | EG19: 0.405 | EH19: -0.025 | EI19: 0.001 | EJ19: =SUM(EF19:EI19) -> 0.213 | EL19: 0.114 | EM19: -0.73 | EN19: 0.096 | EO19: -0.124 | EP19: =SUM(EL19:EO19) -> -0.644 | ER19: 0.263 | ES19: 0.002 | ET19: -0.317 | EU19: 0.431 | EV19: =SUM(ER19:EU19) -> 0.379 | EX19: -0.065 | EY19: -0.482 | EZ19: 0.335 | FA19: -0.084 | FB19: =SUM(EX19:FA19) -> -0.296
B20: Income before taxes | DH20: =DH16-SUM(DH17:DH19) -> 1.082 | DI20: =DI16-SUM(DI17:DI19) -> -0.737 | DJ20: =DJ16-SUM(DJ17:DJ19) -> 2.077 | DK20: =DK16-SUM(DK17:DK19) -> 1.403 | DL20: =DL16-SUM(DL17:DL19) -> 3.825 | DN20: =DN16-SUM(DN17:DN19) -> -4.447 | DO20: =DO16-SUM(DO17:DO19) -> 2.166 | DP20: =DP16-SUM(DP17:DP19) -> 3.491 | DQ20: =DQ16-SUM(DQ17:DQ19) -> 2.435 | DR20: =DR16-SUM(DR17:DR19) -> 3.645 | DT20: =DT16-SUM(DT17:DT19) -> -5.889 | DU20: =DU16-SUM(DU17:DU19) -> -17.956 | DV20: =DV16-SUM(DV17:DV19) -> 2.222 | DW20: =DW16-SUM(DW17:DW19) -> 7.567 | DX20: =DX16-SUM(DX17:DX19) -> -14.056 | DZ20: =DZ16-SUM(DZ17:DZ19) -> -21.138 | EA20: =EA16-SUM(EA17:EA19) -> 73.436 | EB20: =EB16-SUM(EB17:EB19) -> -23.17 | EC20: =EC16-SUM(EC17:EC19) -> -44.204 | ED20: =ED16-SUM(ED17:ED19) -> -15.076 | EF20: =EF16-SUM(EF17:EF19) -> -53.161 | EG20: =EG16-SUM(EG17:EG19) -> -41.033 | EH20: =EH16-SUM(EH17:EH19) -> -39.624 | EI20: =EI16-SUM(EI17:EI19) -> -25.524 | EJ20: =EJ16-SUM(EJ17:EJ19) -> -159.342 | EL20: =EL16-SUM(EL17:EL19) -> -33.72 | EM20: =EM16-SUM(EM17:EM19) -> -26.64 | EN20: =EN16-SUM(EN17:EN19) -> -21.451 | EO20: =EO16-SUM(EO17:EO19) -> -15.286 | EP20: =EP16-SUM(EP17:EP19) -> -97.097 | ER20: =ER16-SUM(ER17:ER19) -> -27.681 | ES20: =ES16-SUM(ES17:ES19) -> -19.017 | ET20: -17.849 | EU20: -16.128 | EV20: =EV16-SUM(EV17:EV19) -> -80.675 | EX20: =EX16-SUM(EX17:EX19) -> -25.657 | EY20: =EY16-SUM(EY17:EY19) -> -45.816 | EZ20: =EZ16-SUM(EZ17:EZ19) -> -26.389 | FA20: =FA16-SUM(FA17:FA19) -> -12.406 | FB20: =FB16-SUM(FB17:FB19) -> -110.268
C21: Income tax | DH21: 0.438 | DI21: -0.357 | DJ21: 0.054 | DK21: 1.05 | DL21: =SUM(DH21:DK21) -> 1.185 | DN21: -2.023 | DO21: 0.175 | DP21: 1.348 | DQ21: -3.861 | DR21: =SUM(DN21:DQ21) -> -4.361 | DT21: 1.089 | DU21: -11.132 | DV21: -0.335 | DW21: -7.85 | DX21: =SUM(DT21:DW21) -> -18.228 | DZ21: 0.976 | EA21: -2.437 | EB21: -2.822 | EC21: -2.445 | ED21: =SUM(DZ21:EC21) -> -6.728 | EF21: -3.753 | EG21: -5.73 | EH21: -2.772 | EI21: -2.837 | EJ21: =SUM(EF21:EI21) -> -15.092 | EL21: -2.925 | EM21: -2.309 | EN21: -2.935 | EO21: -0.96 | EP21: =SUM(EL21:EO21) -> -9.129 | ER21: -0.62 | ES21: -0.375 | ET21: -0.15 | EU21: -0.804 | EV21: =SUM(ER21:EU21) -> -1.949 | EX21: 0.266 | EY21: -0.724 | EZ21: 0.74 | FA21: -2.525 | FB21: =SUM(EX21:FA21) -> -2.243
B22: GAAP Net income | DH22: =DH20-DH21 -> 0.644 | DI22: =DI20-DI21 -> -0.38 | DJ22: =DJ20-DJ21 -> 2.023 | DK22: =DK20-DK21 -> 0.353 | DL22: =DL20-DL21 -> 2.64 | DN22: =DN20-DN21 -> -2.424 | DO22: =DO20-DO21 -> 1.991 | DP22: =DP20-DP21 -> 2.143 | DQ22: =DQ20-DQ21 -> 6.296 | DR22: =DR20-DR21 -> 8.006 | DT22: =DT20-DT21 -> -6.978 | DU22: =DU20-DU21 -> -6.824 | DV22: =DV20-DV21 -> 2.557 | DW22: =DW20-DW21 -> 15.417 | DX22: =DX20-DX21 -> 4.172 | DZ22: =DZ20-DZ21 -> -22.114 | EA22: =EA20-EA21 -> 75.873 | EB22: =EB20-EB21 -> -20.348 | EC22: =EC20-EC21 -> -41.759 | ED22: =ED20-ED21 -> -8.348 | EF22: =EF20-EF21 -> -49.408 | EG22: =EG20-EG21 -> -35.303 | EH22: =EH20-EH21 -> -36.852 | EI22: =EI20-EI21 -> -22.687 | EJ22: =EJ20-EJ21 -> -144.25 | EL22: =EL20-EL21 -> -30.795 | EM22: =EM20-EM21 -> -24.331 | EN22: =EN20-EN21 -> -18.516 | EO22: =EO20-EO21 -> -14.326 | EP22: =EP20-EP21 -> -87.968 | ER22: =ER20-ER21 -> -27.061 | ES22: =ES20-ES21 -> -18.642 | ET22: -17.699 | EU22: -15.324 | EV22: =EV20-EV21 -> -78.726 | EX22: =EX20-EX21 -> -25.923 | EY22: =EY20-EY21 -> -45.092 | EZ22: =EZ20-EZ21 -> -27.129 | FA22: =FA20-FA21 -> -9.881 | FB22: =FB20-FB21 -> -108.025
B24: Basic average shares | DH24: 80.507 | DI24: 81.017 | DJ24: 87.253 | DK24: 93.27 | DL24: 85.618 | DN24: 94.74 | DO24: 98.297 | DP24: 103.899 | DQ24: 104.393 | DR24: 100.47 | DT24: 104.484 | DU24: 107.887 | DV24: 110.461 | DW24: 111.2 | DX24: 100.47 | DZ24: 116.199 | EA24: 118.287 | EB24: 122.559 | EC24: 123.082 | ED24: 119.962 | EF24: 123.63 | EG24: 124.068 | EH24: 124.425 | EI24: 124.714 | EJ24: 124.217 | EL24: 125.026 | EM24: 125.356 | EN24: 125.687 | EO24: 125.929 | EP24: 124.217 | ER24: 126.111 | ES24: 126.405 | ET24: 126.953 | EU24: 127.16 | EV24: =AVERAGE(ER24:EU24) -> 126.65725 | EX24: 127.376 | EY24: 127.949 | EZ24: 128.415 | FA24: 128.648 | FB24: =AVERAGE(EX24:FA24) -> 128.097
B25: Diluted average shares | DH25: 80.507 | DI25: 90.168 | DJ25: 90.927 | DK25: 96.874 | DL25: 91.568 | DN25: 94.74 | DO25: 102.336 | DP25: 107.88 | DQ25: 107.816 | DR25: 103.615 | DT25: 104.484 | DU25: 107.887 | DV25: 119.191 | DW25: 114.236 | DX25: 103.615 | DZ25: 116.199 | EA25: 131.237 | EB25: 122.559 | EC25: 123.082 | ED25: 119.962 | EF25: 123.63 | EG25: 124.068 | EH25: 124.425 | EI25: 124.714 | EJ25: 124.217 | EL25: 125.026 | EM25: 125.356 | EN25: 125.687 | EO25: 125.929 | EP25: 124.217 | ER25: 126.111 | ES25: 126.405 | ET25: 126.953 | EU25: 127.16 | EV25: =AVERAGE(ER25:EU25) -> 126.65725 | EX25: 127.376 | EY25: 127.949 | EZ25: 128.415 | FA25: 128.648 | FB25: =AVERAGE(EX25:FA25) -> 128.097
B27: COGS Adjustments
B28: Amortization of intangible assets | DZ28: 5.299 | EA28: 0.729 | EB28: 4.824 | EC28: 4.853 | ED28: =SUM(DZ28:EC28) -> 15.705 | EF28: 4.853 | EG28: 4.853 | EH28: 4.853 | EI28: 4.854 | EJ28: =SUM(EF28:EI28) -> 19.413 | EL28: 4.853 | EM28: 4.853 | EN28: 4.853 | EO28: 5.079 | EP28: =SUM(EL28:EO28) -> 19.638 | ER28: 4.9 | ES28: 4.9 | ET28: 4.9 | EU28: 4.9 | EV28: =SUM(ER28:EU28) -> 19.6 | EX28: 4.9 | EY28: 4.8 | EZ28: 4.613 | FA28: 4.615 | FB28: =SUM(EX28:FA28) -> 18.928
B29: SBC | DZ29: 0 | EA29: 0 | EB29: 0 | EC29: 0 | ED29: =SUM(DZ29:EC29) -> 0 | EF29: 0 | EG29: 0 | EH29: 0 | EI29: 0 | EJ29: =SUM(EF29:EI29) -> 0 | EL29: 0 | EM29: 0 | EN29: 0 | EO29: 0 | EP29: =SUM(EL29:EO29) -> 0 | ER29: 0.405 | ES29: 0.367 | ET29: 0.3 | EU29: 0.3 | EV29: =SUM(ER29:EU29) -> 1.372 | EX29: 0.405 | EY29: =5.114-EY28 -> 0.314 | EZ29: 0.337 | FA29: =4.964-FA28 -> 0.349 | FB29: =SUM(EX29:FA29) -> 1.405
B30: Other | DZ30: 0 | EA30: 0 | EB30: 0 | EC30: 0 | ED30: =SUM(DZ30:EC30) -> 0 | EF30: 0 | EG30: 0 | EH30: 0 | EI30: 0 | EJ30: =SUM(EF30:EI30) -> 0 | EL30: 0 | EM30: 0 | EN30: 0 | EO30: 0 | EP30: =SUM(EL30:EO30) -> 0 | ER30: 0 | ES30: 0 | ET30: 0 | EU30: 0 | EV30: =SUM(ER30:EU30) -> 0 | EX30: 0 | EY30: 0 | EZ30: 0 | FA30: 0 | FB30: =SUM(EX30:FA30) -> 0
B32: EBITDA Adjustments
B33: Depreciation | DH33: =CF!DH11 -> 3.633 | DI33: =CF!DI11 -> 3.811 | DJ33: =CF!DJ11 -> 4.033 | DK33: =CF!DK11 -> 4.327 | DL33: =SUM(DH33:DK33) -> 15.804 | DN33: =CF!DN11 -> 5.271 | DO33: =CF!DO11 -> 5.081 | DP33: =CF!DP11 -> 4.848 | DQ33: =CF!DQ11 -> 5.146 | DR33: =SUM(DN33:DQ33) -> 20.346 | DT33: =CF!DT11 -> 6.24 | DU33: =CF!DU11 -> 5.937 | DV33: =CF!DV11 -> 6.528 | DW33: =CF!DW11 -> 7.199 | DX33: =SUM(DT33:DW33) -> 25.904 | DZ33: =CF!DZ11 -> 6.68 | EA33: =CF!EA11 -> 6.949 | EB33: =CF!EB11 -> 8.178 | EC33: =CF!EC11 -> 8.385 | ED33: =SUM(DZ33:EC33) -> 30.192 | EF33: =CF!EF11 -> 8.395 | EG33: =CF!EG11 -> 8.526 | EH33: =CF!EH11 -> 8.973 | EI33: =CF!EI11 -> 9.478 | EJ33: =SUM(EF33:EI33) -> 35.372 | EL33: =CF!EL11 -> 9.048 | EM33: =CF!EM11 -> 9.475 | EN33: =CF!EN11 -> 9.349 | EO33: =CF!EO11 -> 9.578 | EP33: =SUM(EL33:EO33) -> 37.45 | ER33: =CF!ER11 -> 9.905 | ES33: =CF!ES11 -> 9.746 | ET33: =CF!ET11 -> 9.623 | EU33: =CF!EU11 -> 9.827 | EV33: =SUM(ER33:EU33) -> 39.101 | EX33: 9.366 | EY33: 9.14 | EZ33: 8.803 | FA33: 8.763 | FB33: =SUM(EX33:FA33) -> 36.072 | FD33: =CF!FD11 -> 9.835095 | FE33: =CF!FE11 -> 9.7467105 | FF33: =CF!FF11 -> 9.6671644 | FG33: =CF!FG11 -> 9.595573 | FH33: =SUM(FD33:FG33) -> 38.844543 | FJ33: =CF!FJ11 -> 9.6072263 | FK33: =CF!FK11 -> 9.6177143 | FL33: =CF!FL11 -> 9.6271535 | FM33: =CF!FM11 -> 9.6356488 | FN33: =SUM(FJ33:FM33) -> 38.487743 | FP33: =CF!FP11 -> 9.7258474 | FQ33: =CF!FQ11 -> 9.8070262 | FR33: =CF!FR11 -> 9.8800871 | FS33: =CF!FS11 -> 9.9458419 | FT33: =SUM(FP33:FS33) -> 39.358803 | FV33: =CF!FV11 -> 10.094591 | FW33: =CF!FW11 -> 10.228465 | FX33: =CF!FX11 -> 10.348952 | FY33: =CF!FY11 -> 10.457391 | FZ33: =SUM(FV33:FY33) -> 41.1294 | GB33: =CF!GB11 -> 11.096009 | GC33: =CF!GC11 -> 11.232379 | GD33: =CF!GD11 -> 11.354545 | GE33: =CF!GE11 -> 11.463985 | GF33: =SUM(GB33:GE33) -> 45.146917 | GH33: =CF!GH11 -> 11.671862 | GI33: =CF!GI11 -> 11.858085 | GJ33: =CF!GJ11 -> 12.024911 | GK33: =CF!GK11 -> 12.174358 | GL33: =SUM(GH33:GK33) -> 47.729216 | GN33: =CF!GN11 -> 12.967734 | GO33: =CF!GO11 -> 13.145554 | GP33: =CF!GP11 -> 13.304045 | GQ33: =CF!GQ11 -> 13.445309 | GR33: =SUM(GN33:GQ33) -> 52.862641 | GT33: =CF!GT11 -> 13.706143 | GU33: =CF!GU11 -> 13.938626 | GV33: =CF!GV11 -> 14.145839 | GW33: =CF!GW11 -> 14.330529 | GX33: =SUM(GT33:GW33) -> 56.121138 | GZ33: =CF!GZ11 -> 14.641538 | HA33: =CF!HA11 -> 14.918741 | HB33: =CF!HB11 -> 15.165814 | HC33: =CF!HC11 -> 15.386031 | HD33: =SUM(GZ33:HC33) -> 60.112124
B34: Amortization of intangible assets | DH34: =CF!DH12 -> 1.413 | DI34: =CF!DI12 -> 1.421 | DJ34: =CF!DJ12 -> 1.421 | DK34: =CF!DK12 -> 1.673 | DL34: =SUM(DH34:DK34) -> 5.928 | DN34: =CF!DN12 -> 2.559 | DO34: =CF!DO12 -> 2.543 | DP34: =CF!DP12 -> 2.38 | DQ34: =CF!DQ12 -> 2.443 | DR34: =SUM(DN34:DQ34) -> 9.925 | DT34: =CF!DT12 -> 2.452 | DU34: =CF!DU12 -> 2.467 | DV34: =CF!DV12 -> 2.468 | DW34: =CF!DW12 -> 2.43 | DX34: =SUM(DT34:DW34) -> 9.817 | DZ34: =CF!DZ12 -> 2.458 | EA34: =CF!EA12 -> 3.751 | EB34: =CF!EB12 -> 8.474 | EC34: =CF!EC12 -> 8.477 | ED34: =SUM(DZ34:EC34) -> 23.16 | EF34: =CF!EF12 -> 8.49 | EG34: =CF!EG12 -> 8.489 | EH34: =CF!EH12 -> 8.491 | EI34: =CF!EI12 -> 8.588 | EJ34: =SUM(EF34:EI34) -> 34.058 | EL34: =CF!EL12 -> 8.783 | EM34: =CF!EM12 -> 8.783 | EN34: =CF!EN12 -> 8.784 | EO34: =CF!EO12 -> 8.783 | EP34: =SUM(EL34:EO34) -> 35.133 | ER34: =CF!ER12 -> 8.362 | ES34: =CF!ES12 -> 8.361 | ET34: =CF!ET12 -> 8.362 | EU34: =CF!EU12 -> 8.361 | EV34: =SUM(ER34:EU34) -> 33.446 | EX34: 8.362 | EY34: 8.124 | EZ34: 7.634 | FA34: 7.632 | FB34: =SUM(EX34:FA34) -> 31.752 | FD34: =CF!FD12 -> 0 | FE34: =CF!FE12 -> 0 | FF34: =CF!FF12 -> 0 | FG34: =CF!FG12 -> 0 | FH34: =SUM(FD34:FG34) -> 0 | FJ34: =CF!FJ12 -> 0 | FK34: =CF!FK12 -> 0 | FL34: =CF!FL12 -> 0 | FM34: =CF!FM12 -> 0 | FN34: =SUM(FJ34:FM34) -> 0 | FP34: =CF!FP12 -> 0 | FQ34: =CF!FQ12 -> 0 | FR34: =CF!FR12 -> 0 | FS34: =CF!FS12 -> 0 | FT34: =SUM(FP34:FS34) -> 0 | FV34: =CF!FV12 -> 0 | FW34: =CF!FW12 -> 0 | FX34: =CF!FX12 -> 0 | FY34: =CF!FY12 -> 0 | FZ34: =SUM(FV34:FY34) -> 0 | GB34: =CF!GB12 -> 0 | GC34: =CF!GC12 -> 0 | GD34: =CF!GD12 -> 0 | GE34: =CF!GE12 -> 0 | GF34: =SUM(GB34:GE34) -> 0 | GH34: =CF!GH12 -> 0 | GI34: =CF!GI12 -> 0 | GJ34: =CF!GJ12 -> 0 | GK34: =CF!GK12 -> 0 | GL34: =SUM(GH34:GK34) -> 0 | GN34: =CF!GN12 -> 0 | GO34: =CF!GO12 -> 0 | GP34: =CF!GP12 -> 0 | GQ34: =CF!GQ12 -> 0 | GR34: =SUM(GN34:GQ34) -> 0 | GT34: =CF!GT12 -> 0 | GU34: =CF!GU12 -> 0 | GV34: =CF!GV12 -> 0 | GW34: =CF!GW12 -> 0 | GX34: =SUM(GT34:GW34) -> 0 | GZ34: =CF!GZ12 -> 0 | HA34: =CF!HA12 -> 0 | HB34: =CF!HB12 -> 0 | HC34: =CF!HC12 -> 0 | HD34: =SUM(GZ34:HC34) -> 0
B35: SBC | DH35: =CF!DH13 -> 1.624 | DI35: =CF!DI13 -> 2.333 | DJ35: =CF!DJ13 -> 1.191 | DK35: =CF!DK13 -> 1.807 | DL35: =SUM(DH35:DK35) -> 6.955 | DN35: =CF!DN13 -> 2.139 | DO35: =CF!DO13 -> 2.313 | DP35: =CF!DP13 -> 3.275 | DQ35: =CF!DQ13 -> 2.273 | DR35: =SUM(DN35:DQ35) -> 10 | DT35: =CF!DT13 -> 2.186 | DU35: =CF!DU13 -> 2.635 | DV35: =CF!DV13 -> 2.715 | DW35: =CF!DW13 -> 2.676 | DX35: =SUM(DT35:DW35) -> 10.212 | DZ35: =CF!DZ13 -> 2.653 | EA35: =CF!EA13 -> 4.506 | EB35: =CF!EB13 -> 5.237 | EC35: =CF!EC13 -> 10.062 | ED35: =SUM(DZ35:EC35) -> 22.458 | EF35: =CF!EF13 -> 12.103 | EG35: =CF!EG13 -> 3.626 | EH35: =CF!EH13 -> 4.28 | EI35: =CF!EI13 -> 4.663 | EJ35: =SUM(EF35:EI35) -> 24.672 | EL35: =CF!EL13 -> 4.758 | EM35: =CF!EM13 -> 5.705 | EN35: =CF!EN13 -> 7.18 | EO35: =CF!EO13 -> 6.99 | EP35: =SUM(EL35:EO35) -> 24.633 | ER35: =CF!ER13 -> 7.774 | ES35: =CF!ES13 -> 8.841 | ET35: =CF!ET13 -> 8.47 | EU35: =CF!EU13 -> 8.328 | EV35: =SUM(ER35:EU35) -> 33.413 | EX35: 10.754 | EY35: 12.215 | EZ35: 10.305 | FA35: 8.042 | FB35: =SUM(EX35:FA35) -> 41.316 | FD35: =CF!FD13 -> 0 | FE35: =CF!FE13 -> 0 | FF35: =CF!FF13 -> 0 | FG35: =CF!FG13 -> 0 | FH35: =SUM(FD35:FG35) -> 0 | FJ35: =CF!FJ13 -> 0 | FK35: =CF!FK13 -> 0 | FL35: =CF!FL13 -> 0 | FM35: =CF!FM13 -> 0 | FN35: =SUM(FJ35:FM35) -> 0 | FP35: =CF!FP13 -> 0 | FQ35: =CF!FQ13 -> 0 | FR35: =CF!FR13 -> 0 | FS35: =CF!FS13 -> 0 | FT35: =SUM(FP35:FS35) -> 0 | FV35: =CF!FV13 -> 0 | FW35: =CF!FW13 -> 0 | FX35: =CF!FX13 -> 0 | FY35: =CF!FY13 -> 0 | FZ35: =SUM(FV35:FY35) -> 0 | GB35: =CF!GB13 -> 0 | GC35: =CF!GC13 -> 0 | GD35: =CF!GD13 -> 0 | GE35: =CF!GE13 -> 0 | GF35: =SUM(GB35:GE35) -> 0 | GH35: =CF!GH13 -> 0 | GI35: =CF!GI13 -> 0 | GJ35: =CF!GJ13 -> 0 | GK35: =CF!GK13 -> 0 | GL35: =SUM(GH35:GK35) -> 0 | GN35: =CF!GN13 -> 0 | GO35: =CF!GO13 -> 0 | GP35: =CF!GP13 -> 0 | GQ35: =CF!GQ13 -> 0 | GR35: =SUM(GN35:GQ35) -> 0 | GT35: =CF!GT13 -> 0 | GU35: =CF!GU13 -> 0 | GV35: =CF!GV13 -> 0 | GW35: =CF!GW13 -> 0 | GX35: =SUM(GT35:GW35) -> 0 | GZ35: =CF!GZ13 -> 0 | HA35: =CF!HA13 -> 0 | HB35: =CF!HB13 -> 0 | HC35: =CF!HC13 -> 0 | HD35: =SUM(GZ35:HC35) -> 0
B36: Transition/restructuring | DH36: 0 | DI36: 1.822 | DJ36: 0.67 | DK36: 0 | DL36: =SUM(DH36:DK36) -> 2.492 | DN36: 0 | DO36: 0 | DP36: 0 | DQ36: 0 | DR36: =SUM(DN36:DQ36) -> 0 | DT36: 0 | DU36: 0 | DV36: 0 | DW36: 0 | DX36: =SUM(DT36:DW36) -> 0 | DZ36: =6.061+0.46 -> 6.521 | EA36: =0.368 -> 0.368 | EB36: 0.775 | EC36: 0.378 | ED36: =SUM(DZ36:EC36) -> 8.042 | EF36: 0 | EG36: 0 | EH36: 2.792 | EI36: 1.536 | EJ36: =SUM(EF36:EI36) -> 4.328 | EL36: 4.684 | EM36: 3.074 | EN36: 2.125 | EO36: 1.205 | EP36: =SUM(EL36:EO36) -> 11.088 | ER36: 2.398 | ES36: 1.544 | ET36: 1.009 | EU36: 1.707 | EV36: =SUM(ER36:EU36) -> 6.658 | EX36: 0 | EY36: 0.637 | EZ36: =0.319 -> 0.319 | FA36: 0.351 | FB36: =SUM(EX36:FA36) -> 1.307 | FH36: =SUM(FD36:FG36) -> 0 | FN36: =SUM(FJ36:FM36) -> 0 | FT36: =SUM(FP36:FS36) -> 0 | FZ36: =SUM(FV36:FY36) -> 0 | GF36: =SUM(GB36:GE36) -> 0 | GL36: =SUM(GH36:GK36) -> 0 | GR36: =SUM(GN36:GQ36) -> 0 | GX36: =SUM(GT36:GW36) -> 0 | HD36: =SUM(GZ36:HC36) -> 0
B37: Acquisition related charges | DH37: 0 | DI37: 0 | DJ37: 0 | DK37: 2.325 | DL37: =SUM(DH37:DK37) -> 2.325 | DN37: 1.266 | DO37: 0.512 | DP37: 0.334 | DQ37: 1.052 | DR37: =SUM(DN37:DQ37) -> 3.164 | DT37: 1.296 | DU37: 0.11 | DV37: 0.446 | DW37: 0.22 | DX37: =SUM(DT37:DW37) -> 2.072 | DZ37: 0.814 | EA37: 10.998 | EB37: 1.533 | EC37: 2.338 | ED37: =SUM(DZ37:EC37) -> 15.683 | EF37: 1.03 | EG37: 1.252 | EH37: 0.197 | EI37: 0 | EJ37: =SUM(EF37:EI37) -> 2.479 | EL37: 0 | EM37: 0 | EN37: 0 | EO37: 0 | EP37: =SUM(EL37:EO37) -> 0 | ER37: 0 | ES37: 0 | ET37: 0 | EU37: 0 | EV37: =SUM(ER37:EU37) -> 0 | EX37: 0 | EY37: 3.204 | EZ37: 1.8 | FA37: 1.09 | FB37: =SUM(EX37:FA37) -> 6.094 | FH37: =SUM(FD37:FG37) -> 0 | FN37: =SUM(FJ37:FM37) -> 0 | FT37: =SUM(FP37:FS37) -> 0 | FZ37: =SUM(FV37:FY37) -> 0 | GF37: =SUM(GB37:GE37) -> 0 | GL37: =SUM(GH37:GK37) -> 0 | GR37: =SUM(GN37:GQ37) -> 0 | GX37: =SUM(GT37:GW37) -> 0 | HD37: =SUM(GZ37:HC37) -> 0
B38: Other | DH38: 0 | DI38: 0 | DJ38: 0 | DK38: 0 | DL38: =SUM(DH38:DK38) -> 0 | DN38: 5.145 | DO38: 1.018 | DP38: 0.364 | DQ38: -0.134 | DR38: =SUM(DN38:DQ38) -> 6.393 | DT38: -0.03 | DU38: -1.965 | DV38: -0.105 | DW38: -4.026 | DX38: =SUM(DT38:DW38) -> -6.126 | DZ38: 5.021 | EA38: 0.174 | EB38: =10.5+1.814 -> 12.314 | EC38: =0.7+2.372 -> 3.072 | ED38: =SUM(DZ38:EC38) -> 20.581 | EF38: 2.831 | EG38: 1.94 | EH38: 3.195 | EI38: 0.952 | EJ38: =SUM(EF38:EI38) -> 8.918 | EL38: 0.789 | EM38: 0.076 | EN38: 0.158 | EO38: 1.242 | EP38: =SUM(EL38:EO38) -> 2.265 | ER38: 5.883 | ES38: =2.358+1.962 -> 4.32 | ET38: =0.677+6.113 -> 6.79 | EU38: =1.085+1.397 -> 2.482 | EV38: =SUM(ER38:EU38) -> 19.475 | EX38: =2.983+1.172+2.193 -> 6.348 | EY38: =4.46+20.041 -> 24.501 | EZ38: =3.634+7.086 -> 10.72 | FA38: =0.626+0.206 -> 0.832 | FB38: =SUM(EX38:FA38) -> 42.401 | FH38: =SUM(FD38:FG38) -> 0 | FN38: =SUM(FJ38:FM38) -> 0 | FT38: =SUM(FP38:FS38) -> 0 | FZ38: =SUM(FV38:FY38) -> 0 | GF38: =SUM(GB38:GE38) -> 0 | GL38: =SUM(GH38:GK38) -> 0 | GR38: =SUM(GN38:GQ38) -> 0 | GX38: =SUM(GT38:GW38) -> 0 | HD38: =SUM(GZ38:HC38) -> 0
B39: Financing | DH39: 0 | DI39: 0 | DJ39: 0 | DK39: 0 | DL39: =SUM(DH39:DK39) -> 0 | DN39: 0 | DO39: 0 | DP39: 0 | DQ39: 0 | DR39: =SUM(DN39:DQ39) -> 0 | DT39: 0 | DU39: 0 | DV39: 0 | DW39: 0 | DX39: =SUM(DT39:DW39) -> 0 | DZ39: 0 | EA39: -96.534 | EB39: -17.75 | EC39: 0 | ED39: =SUM(DZ39:EC39) -> -114.284 | EF39: 0 | EG39: 0 | EH39: 0 | EI39: 0 | EJ39: =SUM(EF39:EI39) -> 0 | EL39: 0 | EM39: 0 | EN39: 0 | EO39: 0 | EP39: =SUM(EL39:EO39) -> 0 | ER39: 0 | ES39: 0 | ET39: 0 | EU39: 0 | EV39: =SUM(ER39:EU39) -> 0 | EX39: 0 | EY39: 0 | EZ39: 0 | FA39: 0 | FB39: =SUM(EX39:FA39) -> 0
FH40: =SUM(FD40:FG40) -> 0 | FN40: =SUM(FJ40:FM40) -> 0 | FT40: =SUM(FP40:FS40) -> 0 | FZ40: =SUM(FV40:FY40) -> 0 | GF40: =SUM(GB40:GE40) -> 0 | GL40: =SUM(GH40:GK40) -> 0 | GR40: =SUM(GN40:GQ40) -> 0 | GX40: =SUM(GT40:GW40) -> 0 | HD40: =SUM(GZ40:HC40) -> 0
B41: EPS Adjustments
B42: Amortization of intangible assets | DH42: 1.413 | DI42: 1.123 | DJ42: 1.123 | DK42: 1.321 | DL42: =SUM(DH42:DK42) -> 4.98 | DN42: 2.559 | DO42: 2.009 | DP42: 1.88 | DQ42: 1.93 | DR42: =SUM(DN42:DQ42) -> 8.378 | DT42: 1.937 | DU42: 1.949 | DV42: 1.949 | DW42: 1.92 | DX42: =SUM(DT42:DW42) -> 7.755 | DZ42: 2.458 | EA42: 3.751 | EB42: 8.474 | EC42: 8.477 | ED42: =SUM(DZ42:EC42) -> 23.16 | EF42: 8.49 | EG42: 8.49 | EH42: 8.49 | EI42: 8.588 | EJ42: =SUM(EF42:EI42) -> 34.058 | EL42: 8.783 | EM42: 8.783 | EN42: 8.784 | EO42: 8.783 | EP42: =SUM(EL42:EO42) -> 35.133 | ER42: 8.362 | ES42: 8.361 | ET42: 8.362 | EU42: 8.362 | EV42: =SUM(ER42:EU42) -> 33.447 | EX42: 8.362 | EY42: 8.124 | EZ42: 7.634 | FA42: 7.632 | FB42: =SUM(EX42:FA42) -> 31.752
B43: SBC | DH43: 1.624 | DI43: 2.284 | DJ43: 0.941 | DK43: 1.695 | DL43: =SUM(DH43:DK43) -> 6.544 | DN43: 1.959 | DO43: 2.019 | DP43: 2.96 | DQ43: 1.971 | DR43: =SUM(DN43:DQ43) -> 8.909 | DT43: 1.847 | DU43: 2.202 | DV43: 2.185 | DW43: 2.215 | DX43: =SUM(DT43:DW43) -> 8.449 | DZ43: 2.653 | EA43: 4.506 | EB43: 5.237 | EC43: 10.062 | ED43: =SUM(DZ43:EC43) -> 22.458 | EF43: 12.103 | EG43: 3.626 | EH43: 4.28 | EI43: 4.662 | EJ43: =SUM(EF43:EI43) -> 24.671 | EL43: 4.758 | EM43: 5.705 | EN43: 7.18 | EO43: 6.99 | EP43: =SUM(EL43:EO43) -> 24.633 | ER43: 7.774 | ES43: 8.841 | ET43: 8.47 | EU43: 8.328 | EV43: =SUM(ER43:EU43) -> 33.413 | EX43: 10.754 | EY43: 12.215 | EZ43: 10.305 | FA43: 8.042 | FB43: =SUM(EX43:FA43) -> 41.316
B44: Transition/restructuring | DH44: 0 | DI44: 1.439 | DJ44: 0.53 | DK44: 0 | DL44: =SUM(DH44:DK44) -> 1.969 | DN44: 0 | DO44: 0 | DP44: 0 | DQ44: 0 | DR44: =SUM(DN44:DQ44) -> 0 | DT44: 0 | DU44: 0 | DV44: 0 | DW44: 0 | DX44: =SUM(DT44:DW44) -> 0 | DZ44: =0.46+6.061 -> 6.521 | EA44: 0.368 | EB44: 0.775 | EC44: 0.378 | ED44: =SUM(DZ44:EC44) -> 8.042 | EF44: 0 | EG44: 0 | EH44: 2.792 | EI44: 1.536 | EJ44: =SUM(EF44:EI44) -> 4.328 | EL44: 4.684 | EM44: 3.074 | EN44: 2.125 | EO44: 1.205 | EP44: =SUM(EL44:EO44) -> 11.088 | ER44: 2.398 | ES44: 1.544 | ET44: 1.009 | EU44: 1.707 | EV44: =SUM(ER44:EU44) -> 6.658 | EX44: 0 | EY44: 0.637 | EZ44: =0.319+7.086 -> 7.405 | FA44: 0.351 | FB44: =SUM(EX44:FA44) -> 8.393
B45: Acquisition related charges | DH45: 0 | DI45: 0 | DJ45: 0 | DK45: 2.116 | DL45: =SUM(DH45:DK45) -> 2.116 | DN45: 1 | DO45: 0.405 | DP45: 0.264 | DQ45: 0.831 | DR45: =SUM(DN45:DQ45) -> 2.5 | DT45: 1.024 | DU45: 0.087 | DV45: 0.353 | DW45: 0.174 | DX45: =SUM(DT45:DW45) -> 1.638 | DZ45: 0.814 | EA45: 10.998 | EB45: 1.533 | EC45: 2.338 | ED45: =SUM(DZ45:EC45) -> 15.683 | EF45: 1.03 | EG45: 1.252 | EH45: 0.197 | EI45: 0 | EJ45: =SUM(EF45:EI45) -> 2.479 | EL45: 0 | EM45: 0 | EN45: 0 | EO45: 0 | EP45: =SUM(EL45:EO45) -> 0 | ER45: 0 | ES45: 0 | ET45: 0 | EU45: 0 | EV45: =SUM(ER45:EU45) -> 0 | EX45: 0 | EY45: 3.204 | EZ45: 1.8 | FA45: 1.09 | FB45: =SUM(EX45:FA45) -> 6.094
B46: Other | DH46: 0 | DI46: 0 | DJ46: 0 | DK46: 0 | DL46: =SUM(DH46:DK46) -> 0 | DN46: 4.065 | DO46: 0.804 | DP46: 0.288 | DQ46: -0.106 | DR46: =SUM(DN46:DQ46) -> 5.051 | DT46: -0.024 | DU46: -1.553 | DV46: -0.083 | DW46: -3.181 | DX46: =SUM(DT46:DW46) -> -4.841 | DZ46: 5.021 | EA46: 0.174 | EB46: =10.5+1.814 -> 12.314 | EC46: =0.7+2.372 -> 3.072 | ED46: =SUM(DZ46:EC46) -> 20.581 | EF46: 2.831 | EG46: 1.94 | EH46: 3.195 | EI46: 0.952 | EJ46: =SUM(EF46:EI46) -> 8.918 | EL46: 0.798 | EM46: 0.076 | EN46: 0.158 | EO46: 1.242 | EP46: =SUM(EL46:EO46) -> 2.274 | ER46: 5.883 | ES46: =1.962+2.358 -> 4.32 | ET46: =6.113+0.677 -> 6.79 | EU46: =1.397+1.085 -> 2.482 | EV46: =SUM(ER46:EU46) -> 19.475 | EX46: =2.193+2.983+1.172 -> 6.348 | EY46: =4.46+20.041 -> 24.501 | EZ46: 3.634 | FA46: =0.626+0.206 -> 0.832 | FB46: =SUM(EX46:FA46) -> 35.315
B47: Financing (below the line) | DH47: 0 | DI47: 0 | DJ47: 0 | DK47: 0 | DL47: =SUM(DH47:DK47) -> 0 | DN47: 0 | DO47: 0 | DP47: 0 | DQ47: 0 | DR47: =SUM(DN47:DQ47) -> 0 | DT47: 0 | DU47: 0 | DV47: 0 | DW47: 0 | DX47: =SUM(DT47:DW47) -> 0 | DZ47: 0 | EA47: -96.534 | EB47: -17.75 | EC47: 0 | ED47: =SUM(DZ47:EC47) -> -114.284 | EF47: 0 | EG47: 0 | EH47: 0 | EI47: 0 | EJ47: =SUM(EF47:EI47) -> 0 | EL47: 0 | EM47: 0 | EN47: 0 | EO47: 0 | EP47: =SUM(EL47:EO47) -> 0 | ER47: 0 | ES47: 0 | ET47: 0 | EU47: 0 | EV47: =SUM(ER47:EU47) -> 0 | EX47: 0 | EY47: 0 | EZ47: 0 | FA47: 0 | FB47: =SUM(EX47:FA47) -> 0
B49: Net sales | DH49: =DH9 -> 63.423 | DI49: =DI9 -> 67.746 | DJ49: =DJ9 -> 69.096 | DK49: =DK9 -> 76.475 | DL49: =SUM(DH49:DK49) -> 276.74 | DN49: =DN9 -> 95.577 | DO49: =DO9 -> 101.713 | DP49: =DP9 -> 104.672 | DQ49: =DQ9 -> 106.868 | DR49: =SUM(DN49:DQ49) -> 408.83 | DT49: =DT9 -> 106.03 | DU49: =DU9 -> 86.977 | DV49: =DV9 -> 125.444 | DW49: =DW9 -> 125.997 | DX49: =SUM(DT49:DW49) -> 444.448 | DZ49: =DZ9 -> 115.533 | EA49: =EA9 -> 121.724 | EB49: =EB9 -> 121.34 | EC49: =EC9 -> 125.732 | ED49: =SUM(DZ49:EC49) -> 484.329 | EF49: =EF9 -> 117.169 | EG49: =EG9 -> 125.072 | EH49: =EH9 -> 128.782 | EI49: =EI9 -> 138.705 | EJ49: =SUM(EF49:EI49) -> 509.728 | EL49: =EL9 -> 137.22 | EM49: =EM9 -> 146.917 | EN49: =EN9 -> 151.954 | EO49: =EO9 -> 155.552 | EP49: =SUM(EL49:EO49) -> 591.643 | ER49: =ER9 -> 156.24 | ES49: =ES9 -> 164.502 | ET49: =ET9 -> 167.824 | EU49: =EU9 -> 172 | EV49: =SUM(ER49:EU49) -> 660.566 | EX49: =EX9 -> 168.035 | EY49: =EY9 -> 181.33 | EZ49: =EZ9 -> 187.797 | FA49: =FA9 -> 190.17 | FB49: =SUM(EX49:FA49) -> 727.332 | FD49: =Rev!FD90 -> 184.62187 | FE49: =Rev!FE90 -> 196.07045 | FF49: =Rev!FF90 -> 205.58086 | FG49: =Rev!FG90 -> 211.08994 | FH49: =SUM(FD49:FG49) -> 797.36311 | FJ49: =Rev!FJ90 -> 202.63173 | FK49: =Rev!FK90 -> 215.24926 | FL49: =Rev!FL90 -> 225.69169 | FM49: =Rev!FM90 -> 231.75279 | FN49: =SUM(FJ49:FM49) -> 875.32547 | FP49: =Rev!FP90 -> 222.43794 | FQ49: =Rev!FQ90 -> 236.34374 | FR49: =Rev!FR90 -> 247.81137 | FS49: =Rev!FS90 -> 254.48032 | FT49: =SUM(FP49:FS49) -> 961.07336 | FV49: =FP49*(1+FV85) -> 243.11602 | FW49: =FQ49*(1+FW85) -> 258.31452 | FX49: =FR49*(1+FX85) -> 270.8482 | FY49: =FS49*(1+FY85) -> 278.1371 | FZ49: =SUM(FV49:FY49) -> 1050.4158 | GB49: =FV49*(1+GB85) -> 264.50079 | GC49: =FW49*(1+GC85) -> 281.03617 | GD49: =FX49*(1+GD85) -> 294.67232 | GE49: =FY49*(1+GE85) -> 302.60236 | GF49: =SUM(GB49:GE49) -> 1142.8116 | GH49: =GB49*(1+GH85) -> 285.91507 | GI49: =GC49*(1+GI85) -> 303.78918 | GJ49: =GD49*(1+GJ85) -> 318.52933 | GK49: =GE49*(1+GK85) -> 327.10139 | GL49: =SUM(GH49:GK49) -> 1235.335 | GN49: =GH49*(1+GN85) -> 307.63351 | GO49: =GI49*(1+GO85) -> 326.86535 | GP49: =GJ49*(1+GP85) -> 342.72518 | GQ49: =GK49*(1+GQ85) -> 351.94839 | GR49: =SUM(GN49:GQ49) -> 1329.1724 | GT49: =GN49*(1+GT85) -> 329.46354 | GU49: =GO49*(1+GU85) -> 350.06009 | GV49: =GP49*(1+GV85) -> 367.04535 | GW49: =GQ49*(1+GW85) -> 376.92305 | GX49: =SUM(GT49:GW49) -> 1423.492 | GZ49: =GT49*(1+GZ85) -> 351.19533 | HA49: =GU49*(1+HA85) -> 373.15046 | HB49: =GV49*(1+HB85) -> 391.25608 | HC49: =GW49*(1+HC85) -> 401.78533 | HD49: =SUM(GZ49:HC49) -> 1517.3872 | HF49: =GZ49*(1+HF85) -> 372.6046 | HG49: =HA49*(1+HG85) -> 395.89814 | HH49: =HB49*(1+HH85) -> 415.1075 | HI49: =HC49*(1+HI85) -> 426.27862 | HJ49: =SUM(HF49:HI49) -> 1609.8889
C50: Cost of products sold | DH50: =DH10 -> 36.12 | DI50: =DI10 -> 37.216 | DJ50: =DJ10 -> 36.775 | DK50: =DK10 -> 39.364 | DL50: =SUM(DH50:DK50) -> 149.475 | DN50: =DN10 -> 48.462 | DO50: =DO10 -> 52.747 | DP50: =DP10 -> 53.84 | DQ50: =DQ10 -> 56.945 | DR50: =SUM(DN50:DQ50) -> 211.994 | DT50: =DT10 -> 59.661 | DU50: =DU10 -> 58.971 | DV50: =DV10 -> 71.379 | DW50: =DW10 -> 68.544 | DX50: =SUM(DT50:DW50) -> 258.555 | DZ50: =DZ10-SUM(DZ28:DZ30) -> 68.66 | EA50: =EA10-SUM(EA28:EA30) -> 68.005 | EB50: =EB10-SUM(EB28:EB30) -> 69.277 | EC50: =EC10-SUM(EC28:EC30) -> 75.622 | ED50: =SUM(DZ50:EC50) -> 281.564 | EF50: =EF10-SUM(EF28:EF30) -> 74.084 | EG50: =EG10-SUM(EG28:EG30) -> 76.273 | EH50: =EH10-SUM(EH28:EH30) -> 75.036 | EI50: =EI10-SUM(EI28:EI30) -> 77.026 | EJ50: =EJ49-EJ51 -> 302.419 | EL50: =EL10-SUM(EL28:EL30) -> 77.553 | EM50: =EM10-SUM(EM28:EM30) -> 82.173 | EN50: =EN10-SUM(EN28:EN30) -> 84.79 | EO50: =EO10-SUM(EO28:EO30) -> 82.885 | EP50: =EP49-EP51 -> 327.401 | ER50: =ER10-SUM(ER28:ER30) -> 85.466 | ES50: =ES10-SUM(ES28:ES30) -> 86.741 | ET50: =ET10-SUM(ET28:ET30) -> 87.744 | EU50: =EU10-SUM(EU28:EU30) -> 89.543 | EV50: =EV49-EV51 -> 349.494 | EX50: =EX10-SUM(EX28:EX30) -> 89.484 | EY50: =EY10-SUM(EY28:EY30) -> 98.958 | EZ50: =EZ10-SUM(EZ28:EZ30) -> 102.401 | FA50: =FA10-SUM(FA28:FA30) -> 101.863 | FB50: =FB49-FB51 -> 392.706 | FD50: =FD49-FD51 -> 96.470817 | FE50: =FE49-FE51 -> 104.84559 | FF50: =FF49-FF51 -> 110.04228 | FG50: =FG49-FG51 -> 110.9577 | FH50: =FH49-FH51 -> 422.31639 | FJ50: =FJ49-FJ51 -> 104.78923 | FK50: =FK49-FK51 -> 111.31427 | FL50: =FL49-FL51 -> 116.71448 | FM50: =FM49-FM51 -> 119.84893 | FN50: =FN49-FN51 -> 452.6669 | FP50: =FP49-FP51 -> 112.25136 | FQ50: =FQ49-FQ51 -> 119.2688 | FR50: =FR49-FR51 -> 125.05584 | FS50: =FS49-FS51 -> 128.42126 | FT50: =FT49-FT51 -> 484.99725 | FV50: =FV49-FV51 -> 119.64742 | FW50: =FW49-FW51 -> 127.12723 | FX50: =FX49-FX51 -> 133.29557 | FY50: =FY49-FY51 -> 136.88274 | FZ50: =FZ49-FZ51 -> 516.95296 | GB50: =GB49-GB51 -> 126.86549 | GC50: =GC49-GC51 -> 134.79654 | GD50: =GD49-GD51 -> 141.337 | GE50: =GE49-GE51 -> 145.14057 | GF50: =GF49-GF51 -> 548.13959 | GH50: =GH49-GH51 -> 133.56272 | GI50: =GI49-GI51 -> 141.91245 | GJ50: =GJ49-GJ51 -> 148.79818 | GK50: =GK49-GK51 -> 152.80255 | GL50: =GL49-GL51 -> 577.07591 | GN50: =GN49-GN51 -> 139.86288 | GO50: =GO49-GO51 -> 148.60647 | GP50: =GP49-GP51 -> 155.817 | GQ50: =GQ49-GQ51 -> 160.01025 | GR50: =GR49-GR51 -> 604.2966 | GT50: =GT49-GT51 -> 145.66942 | GU50: =GU49-GU51 -> 154.776 | GV50: =GV49-GV51 -> 162.28589 | GW50: =GW49-GW51 -> 166.65323 | GX50: =GX49-GX51 -> 629.38454 | GZ50: =GZ49-GZ51 -> 150.888 | HA50: =HA49-HA51 -> 160.32083 | HB50: =HB49-HB51 -> 168.09975 | HC50: =HC49-HC51 -> 172.62355 | HD50: =HD49-HD51 -> 651.93212 | HF50: =HF49-HF51 -> 155.42875 | HG50: =HG49-HG51 -> 165.14544 | HH50: =HH49-HH51 -> 173.15846 | HI50: =HI49-HI51 -> 177.81839 | HJ50: =HJ49-HJ51 -> 671.55104
B51: Gross profit | DH51: =DH49-DH50 -> 27.303 | DI51: =DI49-DI50 -> 30.53 | DJ51: =DJ49-DJ50 -> 32.321 | DK51: =DK49-DK50 -> 37.111 | DL51: =DL49-DL50 -> 127.265 | DN51: =DN49-DN50 -> 47.115 | DO51: =DO49-DO50 -> 48.966 | DP51: =DP49-DP50 -> 50.832 | DQ51: =DQ49-DQ50 -> 49.923 | DR51: =DR49-DR50 -> 196.836 | DT51: =DT49-DT50 -> 46.369 | DU51: =DU49-DU50 -> 28.006 | DV51: =DV49-DV50 -> 54.065 | DW51: =DW49-DW50 -> 57.453 | DX51: =DX49-DX50 -> 185.893 | DZ51: =DZ49-DZ50 -> 46.873 | EA51: =EA49-EA50 -> 53.719 | EB51: =EB49-EB50 -> 52.063 | EC51: =EC49-EC50 -> 50.11 | ED51: =ED49-ED50 -> 202.765 | EF51: =EF49-EF50 -> 43.085 | EG51: =EG49-EG50 -> 48.799 | EH51: =EH49-EH50 -> 53.746 | EI51: =EI49-EI50 -> 61.679 | EJ51: =SUM(EF51:EI51) -> 207.309 | EL51: =EL49-EL50 -> 59.667 | EM51: =EM49-EM50 -> 64.744 | EN51: =EN49-EN50 -> 67.164 | EO51: =EO49-EO50 -> 72.667 | EP51: =SUM(EL51:EO51) -> 264.242 | ER51: =ER49-ER50 -> 70.774 | ES51: =ES49-ES50 -> 77.761 | ET51: =ET49-ET50 -> 80.08 | EU51: =EU49-EU50 -> 82.457 | EV51: =SUM(ER51:EU51) -> 311.072 | EX51: =EX49-EX50 -> 78.551 | EY51: =EY49-EY50 -> 82.372 | EZ51: =EZ49-EZ50 -> 85.396 | FA51: =FA49-FA50 -> 88.307 | FB51: =SUM(EX51:FA51) -> 334.626 | FD51: =FD49*FD74 -> 88.151049 | FE51: =FE49*FE74 -> 91.224854 | FF51: =FF49*FF74 -> 95.538573 | FG51: =FG49*FG74 -> 100.13225 | FH51: =SUM(FD51:FG51) -> 375.04672 | FJ51: =FJ49*FJ74 -> 97.842507 | FK51: =FK49*FK74 -> 103.93499 | FL51: =FL49*FL74 -> 108.97721 | FM51: =FM49*FM74 -> 111.90387 | FN51: =SUM(FJ51:FM51) -> 422.65857 | FP51: =FP49*FP74 -> 110.18658 | FQ51: =FQ49*FQ74 -> 117.07494 | FR51: =FR49*FR74 -> 122.75553 | FS51: =FS49*FS74 -> 126.05905 | FT51: =SUM(FP51:FS51) -> 476.07611 | FV51: =FV49*FV74 -> 123.4686 | FW51: =FW49*FW74 -> 131.18729 | FX51: =FX49*FX74 -> 137.55263 | FY51: =FY49*FY74 -> 141.25436 | FZ51: =SUM(FV51:FY51) -> 533.46289 | GB51: =GB49*GB74 -> 137.6353 | GC51: =GC49*GC74 -> 146.23963 | GD51: =GD49*GD74 -> 153.33532 | GE51: =GE49*GE74 -> 157.46179 | GF51: =SUM(GB51:GE51) -> 594.67204 | GH51: =GH49*GH74 -> 152.35235 | GI51: =GI49*GI74 -> 161.87672 | GJ51: =GJ49*GJ74 -> 169.73114 | GK51: =GK49*GK74 -> 174.29884 | GL51: =SUM(GH51:GK51) -> 658.25906 | GN51: =GN49*GN74 -> 167.77063 | GO51: =GO49*GO74 -> 178.25888 | GP51: =GP49*GP74 -> 186.90818 | GQ51: =GQ49*GQ74 -> 191.93814 | GR51: =SUM(GN51:GQ51) -> 724.87583 | GT51: =GT49*GT74 -> 183.79412 | GU51: =GU49*GU74 -> 195.28409 | GV51: =GV49*GV74 -> 204.75946 | GW51: =GW49*GW74 -> 210.26983 | GX51: =SUM(GT51:GW51) -> 794.1075 | GZ51: =GZ49*GZ74 -> 200.30733 | HA51: =HA49*HA74 -> 212.82963 | HB51: =HB49*HB74 -> 223.15633 | HC51: =HC49*HC74 -> 229.16178 | HD51: =SUM(GZ51:HC51) -> 865.45508 | HF51: =HF49*HF74 -> 217.17586 | HG51: =HG49*HG74 -> 230.7527 | HH51: =HH49*HH74 -> 241.94904 | HI51: =HI49*HI74 -> 248.46023 | HJ51: =SUM(HF51:HI51) -> 938.33783
C52: G&A | DH52: =DH12-SUM(DH34:DH38) -> 14.03 | DI52: =DI12-SUM(DI34:DI38) -> 15.407 | DJ52: =DJ12-SUM(DJ34:DJ38) -> 17.773 | DK52: =DK12-SUM(DK34:DK38) -> 19.912 | DL52: =SUM(DH52:DK52) -> 67.122 | DN52: =DN12-SUM(DN34:DN38) -> 21.033 | DO52: =DO12-SUM(DO34:DO38) -> 23.191 | DP52: =DP12-SUM(DP34:DP38) -> 26.701 | DQ52: =DQ12-SUM(DQ34:DQ38) -> 27.586 | DR52: =SUM(DN52:DQ52) -> 98.511 | DT52: =DT12-SUM(DT34:DT38) -> 30.44 | DU52: =DU12-SUM(DU34:DU38) -> 31.366 | DV52: =DV12-SUM(DV34:DV38) -> 30.604 | DW52: =DW12-SUM(DW34:DW38) -> 35.409 | DX52: =SUM(DT52:DW52) -> 127.819 | DZ52: =DZ12-SUM(DZ34:DZ38)+SUM(DZ28:DZ30) -> 28.308 | EA52: =EA12-SUM(EA34:EA38)+SUM(EA28:EA30) -> 35.57 | EB52: =EB12-SUM(EB34:EB38)+SUM(EB28:EB30) -> 40.33 | EC52: =EC12-SUM(EC34:EC38)+SUM(EC28:EC30) -> 42.92 | ED52: =SUM(DZ52:EC52) -> 147.128 | EF52: =EF12-SUM(EF34:EF38)+SUM(EF28:EF30) -> 46.647 | EG52: =EG12-SUM(EG34:EG38)+SUM(EG28:EG30) -> 47.497 | EH52: =EH12-SUM(EH34:EH38)+SUM(EH28:EH30) -> 50.18 | EI52: =EI12-SUM(EI34:EI38)+SUM(EI28:EI30)+EI36 -> 48.506 | EJ52: =SUM(EF52:EI52) -> 192.83 | EL52: =EL12-SUM(EL34:EL38)+SUM(EL28:EL30)+EL36 -> 52.072 | EM52: =EM12-SUM(EM34:EM38)+SUM(EM28:EM30)+EM36 -> 50.597 | EN52: =EN12-SUM(EN34:EN38)+SUM(EN28:EN30)+EN36 -> 50.217 | EO52: =EO12-SUM(EO34:EO38)+SUM(EO28:EO30)+EO36 -> 47.822 | EP52: =SUM(EL52:EO52) -> 200.708 | ER52: =ER12-SUM(ER34:ER38)+SUM(ER28:ER30)+ER36 -> 49.083 | ES52: =ES12-SUM(ES34:ES38)+SUM(ES28:ES30)+ES36 -> 47.073 | ET52: =ET12-SUM(ET34:ET38)+SUM(ET28:ET30)+ET36 -> 48.547 | EU52: =EU12-SUM(EU34:EU38)+SUM(EU28:EU30)+EU36 -> 49.672 | EV52: =SUM(ER52:EU52) -> 194.375 | EX52: =EX12-SUM(EX34:EX38)+SUM(EX28:EX30)+EX36 -> 48.048 | EY52: =EY12-SUM(EY34:EY38)+SUM(EY28:EY30)+EY38 -> 52.681 | EZ52: =EZ12-SUM(EZ34:EZ38)+SUM(EZ28:EZ30)+EZ36 -> 44.365 | FA52: =FA12-SUM(FA34:FA38)+SUM(FA28:FA30)+FA36 -> 50.877 | FB52: =SUM(EX52:FA52) -> 195.971 | FD52: =FD$49*FD75 -> 52.790856 | FE52: =FE$49*FE75 -> 53.919372 | FF52: =FF$49*FF75 -> 53.451022 | FG52: =FG$49*FG75 -> 54.883385 | FH52: =SUM(FD52:FG52) -> 215.04464 | FJ52: =FJ$49*FJ75 -> 53.838185 | FK52: =FK$49*FK75 -> 57.190596 | FL52: =FL$49*FL75 -> 59.965094 | FM52: =FM$49*FM75 -> 61.575498 | FN52: =SUM(FJ52:FM52) -> 232.56937 | FP52: =FP$49*FP75 -> 57.9884 | FQ52: =FQ$49*FQ75 -> 61.613569 | FR52: =FR$49*FR75 -> 64.60312 | FS52: =FS$49*FS75 -> 66.34168 | FT52: =SUM(FP52:FS52) -> 250.54677 | FV52: =FV$49*FV75 -> 61.677256 | FW52: =FW$49*FW75 -> 65.533036 | FX52: =FX$49*FX75 -> 68.712763 | FY52: =FY$49*FY75 -> 70.561919 | FZ52: =SUM(FV52:FY52) -> 266.48497 | GB52: =GB$49*GB75 -> 65.779954 | GC52: =GC$49*GC75 -> 69.892216 | GD52: =GD$49*GD75 -> 73.283455 | GE52: =GE$49*GE75 -> 75.255615 | GF52: =SUM(GB52:GE52) -> 284.21124 | GH52: =GH$49*GH75 -> 69.675999 | GI52: =GI$49*GI75 -> 74.031824 | GJ52: =GJ$49*GJ75 -> 77.623921 | GK52: =GK$49*GK75 -> 79.712889 | GL52: =SUM(GH52:GK52) -> 301.04463 | GN52: =GN$49*GN75 -> 73.430501 | GO52: =GO$49*GO75 -> 78.02104 | GP52: =GP$49*GP75 -> 81.806697 | GQ52: =GQ$49*GQ75 -> 84.008229 | GR52: =SUM(GN52:GQ52) -> 317.26647 | GT52: =GT$49*GT75 -> 76.993896 | GU52: =GU$49*GU75 -> 81.807202 | GV52: =GV$49*GV75 -> 85.776568 | GW52: =GW$49*GW75 -> 88.084934 | GX52: =SUM(GT52:GW52) -> 332.6626 | GZ52: =GZ$49*GZ75 -> 79.96533 | HA52: =HA$49*HA75 -> 84.964396 | HB52: =HB$49*HB75 -> 89.086952 | HC52: =HC$49*HC75 -> 91.484406 | HD52: =SUM(GZ52:HC52) -> 345.50108 | HF52: =HF$49*HF75 -> 82.60448 | HG52: =HG$49*HG75 -> 87.768534 | HH52: =HH$49*HH75 -> 92.02715 | HI52: =HI$49*HI75 -> 94.503728 | HJ52: =SUM(HF52:HI52) -> 356.90389
C53: Sales and Marketing | DH53: =DH13 -> 6.775 | DI53: =DI13 -> 7.68 | DJ53: =DJ13 -> 6.9 | DK53: =DK13 -> 8.047 | DL53: =SUM(DH53:DK53) -> 29.402 | DN53: =DN13 -> 11.216 | DO53: =DO13 -> 12.324 | DP53: =DP13 -> 11.508 | DQ53: =DQ13 -> 12.302 | DR53: =SUM(DN53:DQ53) -> 47.35 | DT53: =DT13 -> 13.258 | DU53: =DU13 -> 10.195 | DV53: =DV13 -> 11.304 | DW53: =DW13 -> 13.105 | DX53: =SUM(DT53:DW53) -> 47.862 | DZ53: =DZ13 -> 13.749 | EA53: =EA13 -> 17.224 | EB53: =EB13 -> 15.704 | EC53: =EC13 -> 15.917 | ED53: =SUM(DZ53:EC53) -> 62.594 | EF53: =EF13 -> 16.299 | EG53: =EG13 -> 17.071 | EH53: =EH13 -> 16.809 | EI53: =EI13 -> 17.142 | EJ53: =SUM(EF53:EI53) -> 67.321 | EL53: =EL13 -> 16.259 | EM53: =EM13 -> 18.901 | EN53: =EN13 -> 17.61 | EO53: =EO13 -> 18.072 | EP53: =SUM(EL53:EO53) -> 70.842 | ER53: =ER13 -> 20.221 | ES53: =ES13 -> 21.677 | ET53: =ET13 -> 20.415 | EU53: =EU13 -> 22.339 | EV53: =SUM(ER53:EU53) -> 84.652 | EX53: =EX13 -> 22.683 | EY53: =EY13 -> 24.075 | EZ53: =EZ13 -> 21.806 | FA53: =FA13 -> 23.443 | FB53: =SUM(EX53:FA53) -> 92.007 | FD53: =FD$49*FD76 -> 24.922057 | FE53: =FE$49*FE76 -> 25.489158 | FF53: =FF$49*FF76 -> 25.697607 | FG53: =FG$49*FG76 -> 26.021883 | FH53: =SUM(FD53:FG53) -> 102.1307 | FJ53: =FJ$49*FJ76 -> 25.548937 | FK53: =FK$49*FK76 -> 27.139825 | FL53: =FL$49*FL76 -> 28.456464 | FM53: =FM$49*FM76 -> 29.220682 | FN53: =SUM(FJ53:FM53) -> 110.36591 | FP53: =FP$49*FP76 -> 27.490118 | FQ53: =FQ$49*FQ76 -> 29.208675 | FR53: =FR$49*FR76 -> 30.625908 | FS53: =FS$49*FS76 -> 31.450094 | FT53: =SUM(FP53:FS53) -> 118.77479 | FV53: =FV$49*FV76 -> 29.437841 | FW53: =FW$49*FW76 -> 31.27816 | FX53: =FX$49*FX76 -> 32.795807 | FY53: =FY$49*FY76 -> 33.678388 | FZ53: =SUM(FV53:FY53) -> 127.1902 | GB53: =GB$49*GB76 -> 31.365975 | GC53: =GC$49*GC76 -> 33.326833 | GD53: =GD$49*GD76 -> 34.943883 | GE53: =GE$49*GE76 -> 35.884272 | GF53: =SUM(GB53:GE53) -> 135.52096 | GH53: =GH$49*GH76 -> 33.190613 | GI53: =GI$49*GI76 -> 35.265538 | GJ53: =GJ$49*GJ76 -> 36.976657 | GK53: =GK$49*GK76 -> 37.97175 | GL53: =SUM(GH53:GK53) -> 143.40456 | GN53: =GN$49*GN76 -> 34.942726 | GO53: =GO$49*GO76 -> 37.127186 | GP53: =GP$49*GP76 -> 38.928633 | GQ53: =GQ$49*GQ76 -> 39.976257 | GR53: =SUM(GN53:GQ53) -> 150.9748 | GT53: =GT$49*GT76 -> 37.422302 | GU53: =GU$49*GU76 -> 39.761773 | GV53: =GV$49*GV76 -> 41.691054 | GW53: =GW$49*GW76 -> 42.813018 | GX53: =SUM(GT53:GW53) -> 161.68815 | GZ53: =GZ$49*GZ76 -> 39.89072 | HA53: =HA$49*HA76 -> 42.384506 | HB53: =HB$49*HB76 -> 44.441044 | HC53: =HC$49*HC76 -> 45.637014 | HD53: =SUM(GZ53:HC53) -> 172.35328 | HF53: =HF$49*HF76 -> 42.322505 | HG53: =HG$49*HG76 -> 44.968314 | HH53: =HH$49*HH76 -> 47.150221 | HI53: =HI$49*HI76 -> 48.419099 | HJ53: =SUM(HF53:HI53) -> 182.86014
C54: Research & Development | DH54: =DH14 -> 0.956 | DI54: =DI14 -> 1.073 | DJ54: =DJ14 -> 0.446 | DK54: =DK14 -> 0.526 | DL54: =SUM(DH54:DK54) -> 3.001 | DN54: =DN14 -> 1.209 | DO54: =DO14 -> 2.587 | DP54: =DP14 -> 2.611 | DQ54: =DQ14 -> 2.08 | DR54: =SUM(DN54:DQ54) -> 8.487 | DT54: =DT14 -> 2.06 | DU54: =DU14 -> 2.105 | DV54: =DV14 -> 1.964 | DW54: =DW14 -> 2.1 | DX54: =SUM(DT54:DW54) -> 8.229 | DZ54: =DZ14 -> 2.456 | EA54: =EA14 -> 3.495 | EB54: =EB14 -> 7.409 | EC54: =EC14 -> 8.513 | ED54: =SUM(DZ54:EC54) -> 21.873 | EF54: =EF14 -> 7.713 | EG54: =EG14 -> 8.626 | EH54: =EH14 -> 7.312 | EI54: =EI14 -> 6.675 | EJ54: =SUM(EF54:EI54) -> 30.326 | EL54: =EL14 -> 7.395 | EM54: =EM14 -> 7.502 | EN54: =EN14 -> 5.285 | EO54: =EO14 -> 7.127 | EP54: =SUM(EL54:EO54) -> 27.309 | ER54: =ER14 -> 7.62 | ES54: =ES14 -> 7.886 | ET54: =ET14 -> 7.684 | EU54: =EU14 -> 7.969 | EV54: =SUM(ER54:EU54) -> 31.159 | EX54: =EX14 -> 10.181 | EY54: =EY14 -> 9.023 | EZ54: =EZ14 -> 8.694 | FA54: =FA14 -> 9.179 | FB54: =SUM(EX54:FA54) -> 37.077 | FD54: =FD$49*FD77 -> 11.185974 | FE54: =FE$49*FE77 -> 9.7564861 | FF54: =FF$49*FF77 -> 9.5172977 | FG54: =FG$49*FG77 -> 10.18875 | FH54: =SUM(FD54:FG54) -> 40.648508 | FJ54: =FJ$49*FJ77 -> 10.329896 | FK54: =FK$49*FK77 -> 10.97312 | FL54: =FL$49*FL77 -> 11.505461 | FM54: =FM$49*FM77 -> 11.814448 | FN54: =SUM(FJ54:FM54) -> 44.622926 | FP54: =FP$49*FP77 -> 11.339589 | FQ54: =FQ$49*FQ77 -> 12.048489 | FR54: =FR$49*FR77 -> 12.633093 | FS54: =FS$49*FS77 -> 12.973067 | FT54: =SUM(FP54:FS54) -> 48.994239 | FV54: =FV$49*FV77 -> 12.393731 | FW54: =FW$49*FW77 -> 13.16853 | FX54: =FX$49*FX77 -> 13.80748 | FY54: =FY$49*FY77 -> 14.179059 | FZ54: =SUM(FV54:FY54) -> 53.548799 | GB54: =GB$49*GB77 -> 13.483897 | GC54: =GC$49*GC77 -> 14.326849 | GD54: =GD$49*GD77 -> 15.022002 | GE54: =GE$49*GE77 -> 15.426265 | GF54: =SUM(GB54:GE54) -> 58.259013 | GH54: =GH$49*GH77 -> 14.575569 | GI54: =GI$49*GI77 -> 15.486767 | GJ54: =GJ$49*GJ77 -> 16.2382 | GK54: =GK$49*GK77 -> 16.675193 | GL54: =SUM(GH54:GK54) -> 62.97573 | GN54: =GN$49*GN77 -> 15.682746 | GO54: =GO$49*GO77 -> 16.66316 | GP54: =GP$49*GP77 -> 17.471673 | GQ54: =GQ$49*GQ77 -> 17.94186 | GR54: =SUM(GN54:GQ54) -> 67.759439 | GT54: =GT$49*GT77 -> 16.795612 | GU54: =GU$49*GU77 -> 17.845597 | GV54: =GV$49*GV77 -> 18.711483 | GW54: =GW$49*GW77 -> 19.215035 | GX54: =SUM(GT54:GW54) -> 72.567726 | GZ54: =GZ$49*GZ77 -> 17.90347 | HA54: =HA$49*HA77 -> 19.022713 | HB54: =HB$49*HB77 -> 19.945714 | HC54: =HC$49*HC77 -> 20.48248 | HD54: =SUM(GZ54:HC54) -> 77.354377 | HF54: =HF$49*HF77 -> 18.994886 | HG54: =HG$49*HG77 -> 20.182359 | HH54: =HH$49*HH77 -> 21.161627 | HI54: =HI$49*HI77 -> 21.731116 | HJ54: =SUM(HF54:HI54) -> 82.069988
C55: Other expenses | DH55: =DH15 -> 0 | DI55: =DI15 -> 0 | DJ55: =DJ15 -> 0 | DK55: =DK15 -> 0 | DL55: =SUM(DH55:DK55) -> 0 | DN55: =DN15 -> 0 | DO55: =DO15 -> 0 | DP55: =DP15 -> 0 | DQ55: =DQ15 -> 0 | DR55: =SUM(DN55:DQ55) -> 0 | DT55: =DT15 -> 0 | DU55: =DU15 -> 0 | DV55: =DV15 -> 0 | DW55: =DW15 -> 0 | DX55: =SUM(DT55:DW55) -> 0 | DZ55: =DZ15 -> 0 | EA55: =EA15 -> 0 | EB55: =EB15 -> 0 | EC55: =EC15 -> 0 | ED55: =SUM(DZ55:EC55) -> 0 | EF55: =EF15 -> 0 | EG55: =EG15 -> 0 | EH55: =EH15 -> 0 | EI55: =EI15-EI36 -> 0 | EJ55: =SUM(EF55:EI55) -> 0 | EL55: =EL15-EL36 -> 0 | EM55: =EM15-EM36 -> 0 | EN55: =EN15-EN36 -> 0 | EO55: =EO15-EO36 -> 0 | EP55: =SUM(EL55:EO55) -> 0 | ER55: =ER15-ER36 -> 0 | ES55: =ES15-ES36 -> 0 | ET55: =ET15-ET36 -> 0 | EU55: =EU15-EU36 -> 0 | EV55: =SUM(ER55:EU55) -> 0 | EX55: =EX15-EX36 -> 0 | EY55: =EY15-EY38 -> -4.46 | EZ55: =EZ15-EZ36 -> 6.767 | FA55: =FA15-FA36 -> 0.275 | FB55: =SUM(EX55:FA55) -> 2.582 | FD55: 0 | FE55: 0 | FF55: 0 | FG55: 0 | FH55: =SUM(FD55:FG55) -> 0 | FJ55: =FD55 -> 0 | FK55: =FE55 -> 0 | FL55: =FF55 -> 0 | FM55: =FG55 -> 0 | FN55: =SUM(FJ55:FM55) -> 0 | FP55: =FJ55 -> 0 | FQ55: =FK55 -> 0 | FR55: =FL55 -> 0 | FS55: =FM55 -> 0 | FT55: =SUM(FP55:FS55) -> 0 | FV55: =FP55 -> 0 | FW55: =FQ55 -> 0 | FX55: =FR55 -> 0 | FY55: =FS55 -> 0 | FZ55: =SUM(FV55:FY55) -> 0 | GB55: =FV55 -> 0 | GC55: =FW55 -> 0 | GD55: =FX55 -> 0 | GE55: =FY55 -> 0 | GF55: =SUM(GB55:GE55) -> 0 | GH55: =GB55 -> 0 | GI55: =GC55 -> 0 | GJ55: =GD55 -> 0 | GK55: =GE55 -> 0 | GL55: =SUM(GH55:GK55) -> 0 | GN55: =GH55 -> 0 | GO55: =GI55 -> 0 | GP55: =GJ55 -> 0 | GQ55: =GK55 -> 0 | GR55: =SUM(GN55:GQ55) -> 0 | GT55: =GN55 -> 0 | GU55: =GO55 -> 0 | GV55: =GP55 -> 0 | GW55: =GQ55 -> 0 | GX55: =SUM(GT55:GW55) -> 0 | GZ55: =GT55 -> 0 | HA55: =GU55 -> 0 | HB55: =GV55 -> 0 | HC55: =GW55 -> 0 | HD55: =SUM(GZ55:HC55) -> 0 | HF55: =GZ55 -> 0 | HG55: =HA55 -> 0 | HH55: =HB55 -> 0 | HI55: =HC55 -> 0 | HJ55: =SUM(HF55:HI55) -> 0
B56: Operating income | DH56: =DH51-SUM(DH52:DH55) -> 5.542 | DI56: =DI51-SUM(DI52:DI55) -> 6.37 | DJ56: =DJ51-SUM(DJ52:DJ55) -> 7.202 | DK56: =DK51-SUM(DK52:DK55) -> 8.626 | DL56: =DL51-SUM(DL52:DL55) -> 27.74 | DN56: =DN51-SUM(DN52:DN55) -> 13.657 | DO56: =DO51-SUM(DO52:DO55) -> 10.864 | DP56: =DP51-SUM(DP52:DP55) -> 10.012 | DQ56: =DQ51-SUM(DQ52:DQ55) -> 7.955 | DR56: =DR51-SUM(DR52:DR55) -> 42.488 | DT56: =DT51-SUM(DT52:DT55) -> 0.611 | DU56: =DU51-SUM(DU52:DU55) -> -15.66 | DV56: =DV51-SUM(DV52:DV55) -> 10.193 | DW56: =DW51-SUM(DW52:DW55) -> 6.839 | DX56: =DX51-SUM(DX52:DX55) -> 1.983 | DZ56: =DZ51-SUM(DZ52:DZ55) -> 2.36 | EA56: =EA51-SUM(EA52:EA55) -> -2.57 | EB56: =EB51-SUM(EB52:EB55) -> -11.38 | EC56: =EC51-SUM(EC52:EC55) -> -17.24 | ED56: =ED51-SUM(ED52:ED55) -> -28.83 | EF56: =EF51-SUM(EF52:EF55) -> -27.574 | EG56: =EG51-SUM(EG52:EG55) -> -24.395 | EH56: =EH51-SUM(EH52:EH55) -> -20.555 | EI56: =EI51-SUM(EI52:EI55) -> -10.644 | EJ56: =EJ51-SUM(EJ52:EJ55) -> -83.168 | EL56: =EL51-SUM(EL52:EL55) -> -16.059 | EM56: =EM51-SUM(EM52:EM55) -> -12.256 | EN56: =EN51-SUM(EN52:EN55) -> -5.948 | EO56: =EO51-SUM(EO52:EO55) -> -0.354 | EP56: =EP51-SUM(EP52:EP55) -> -34.617 | ER56: =ER51-SUM(ER52:ER55) -> -6.15 | ES56: =ES51-SUM(ES52:ES55) -> 1.125 | ET56: =ET51-SUM(ET52:ET55) -> 3.434 | EU56: =EU51-SUM(EU52:EU55) -> 2.477 | EV56: =EV51-SUM(EV52:EV55) -> 0.886 | EX56: =EX51-SUM(EX52:EX55) -> -2.361 | EY56: =EY51-SUM(EY52:EY55) -> 1.053 | EZ56: =EZ51-SUM(EZ52:EZ55) -> 3.764 | FA56: =FA51-SUM(FA52:FA55) -> 4.533 | FB56: =FB51-SUM(FB52:FB55) -> 6.989 | FD56: =FD51-SUM(FD52:FD55) -> -0.74783749 | FE56: =FE51-SUM(FE52:FE55) -> 2.0598372 | FF56: =FF51-SUM(FF52:FF55) -> 6.872646 | FG56: =FG51-SUM(FG52:FG55) -> 9.0382281 | FH56: =FH51-SUM(FH52:FH55) -> 17.222874 | FJ56: =FJ51-SUM(FJ52:FJ55) -> 8.1254894 | FK56: =FK51-SUM(FK52:FK55) -> 8.6314496 | FL56: =FL51-SUM(FL52:FL55) -> 9.0501888 | FM56: =FM51-SUM(FM52:FM55) -> 9.2932378 | FN56: =FN51-SUM(FN52:FN55) -> 35.100366 | FP56: =FP51-SUM(FP52:FP55) -> 13.368473 | FQ56: =FQ51-SUM(FQ52:FQ55) -> 14.204209 | FR56: =FR51-SUM(FR52:FR55) -> 14.893411 | FS56: =FS51-SUM(FS52:FS55) -> 15.294213 | FT56: =FT51-SUM(FT52:FT55) -> 57.760305 | FV56: =FV51-SUM(FV52:FV55) -> 19.959774 | FW56: =FW51-SUM(FW52:FW55) -> 21.207568 | FX56: =FX51-SUM(FX52:FX55) -> 22.23658 | FY56: =FY51-SUM(FY52:FY55) -> 22.834997 | FZ56: =FZ51-SUM(FZ52:FZ55) -> 86.238918 | GB56: =GB51-SUM(GB52:GB55) -> 27.005474 | GC56: =GC51-SUM(GC52:GC55) -> 28.693733 | GD56: =GD51-SUM(GD52:GD55) -> 30.085981 | GE56: =GE51-SUM(GE52:GE55) -> 30.895637 | GF56: =GF51-SUM(GF52:GF55) -> 116.68082 | GH56: =GH51-SUM(GH52:GH55) -> 34.91017 | GI56: =GI51-SUM(GI52:GI55) -> 37.092594 | GJ56: =GJ51-SUM(GJ52:GJ55) -> 38.892363 | GK56: =GK51-SUM(GK52:GK55) -> 39.939011 | GL56: =GL51-SUM(GL52:GL55) -> 150.83414 | GN56: =GN51-SUM(GN52:GN55) -> 43.714657 | GO56: =GO51-SUM(GO52:GO55) -> 46.447497 | GP56: =GP51-SUM(GP52:GP55) -> 48.701175 | GQ56: =GQ51-SUM(GQ52:GQ55) -> 50.011792 | GR56: =GR51-SUM(GR52:GR55) -> 188.87512 | GT56: =GT51-SUM(GT52:GT55) -> 52.582311 | GU56: =GU51-SUM(GU52:GU55) -> 55.869516 | GV56: =GV51-SUM(GV52:GV55) -> 58.58036 | GW56: =GW51-SUM(GW52:GW55) -> 60.156839 | GX56: =GX51-SUM(GX52:GX55) -> 227.18903 | GZ56: =GZ51-SUM(GZ52:GZ55) -> 62.547814 | HA56: =HA51-SUM(HA52:HA55) -> 66.458017 | HB56: =HB51-SUM(HB52:HB55) -> 69.682626 | HC56: =HC51-SUM(HC52:HC55) -> 71.557882 | HD56: =HD51-SUM(HD52:HD55) -> 270.24634 | HF56: =HF51-SUM(HF52:HF55) -> 73.253986 | HG56: =HG51-SUM(HG52:HG55) -> 77.83349 | HH56: =HH51-SUM(HH52:HH55) -> 81.610047 | HI56: =HI51-SUM(HI52:HI55) -> 83.806287 | HJ56: =HJ51-SUM(HJ52:HJ55) -> 316.50381
C57: Interest expense | DH57: =DH17 -> 1.486 | DI57: =DI17 -> 1.407 | DJ57: =DJ17 -> 1.873 | DK57: =DK17 -> 1.464 | DL57: =SUM(DH57:DK57) -> 6.23 | DN57: =DN17 -> 1.826 | DO57: =DO17 -> 1.304 | DP57: =DP17 -> 0.203 | DQ57: =DQ17 -> 0.38 | DR57: =SUM(DN57:DQ57) -> 3.713 | DT57: =DT17 -> 0.819 | DU57: =DU17 -> 1.548 | DV57: =DV17 -> 2.458 | DW57: =DW17 -> 2.194 | DX57: =SUM(DT57:DW57) -> 7.019 | DZ57: =DZ17 -> 1.177 | EA57: =EA17 -> 0.902 | EB57: =EB17 -> 1.296 | EC57: =EC17 -> 1.707 | ED57: =SUM(DZ57:EC57) -> 5.082 | EF57: =EF17 -> 1.301 | EG57: =EG17 -> 0.926 | EH57: =EH17 -> 0.139 | EI57: =EI17 -> 0 | EJ57: =SUM(EF57:EI57) -> 2.366 | EL57: =EL17 -> 0 | EM57: =EM17 -> 0 | EN57: =EN17 -> 0 | EO57: =EO17 -> 1.681 | EP57: =SUM(EL57:EO57) -> 1.681 | ER57: =ER17 -> 1.685 | ES57: =ES17 -> 1.666 | ET57: =ET17 -> 1.642 | EU57: =EU17 -> 1.624 | EV57: =SUM(ER57:EU57) -> 6.617 | EX57: =EX17 -> 1.618 | EY57: =EY17 -> 0.933 | EZ57: =EZ17 -> 0.603 | FA57: =FA17 -> 0.599 | FB57: =SUM(EX57:FA57) -> 3.753 | FD57: =+'Other Accts'!FD47 -> 0.615625 | FE57: =+'Other Accts'!FE47 -> 0.615625 | FF57: =+'Other Accts'!FF47 -> 0.615625 | FG57: =+'Other Accts'!FG47 -> 0.615625 | FH57: =SUM(FD57:FG57) -> 2.4625 | FJ57: =+'Other Accts'!FJ47 -> 0.215625 | FK57: =+'Other Accts'!FK47 -> 0.215625 | FL57: =+'Other Accts'!FL47 -> 0.215625 | FM57: =+'Other Accts'!FM47 -> 2.371875 | FN57: =SUM(FJ57:FM57) -> 3.01875 | FP57: =+'Other Accts'!FP47 -> 4.528125 | FQ57: =+'Other Accts'!FQ47 -> 4.528125 | FR57: =+'Other Accts'!FR47 -> 4.528125 | FS57: =+'Other Accts'!FS47 -> 4.528125 | FT57: =SUM(FP57:FS57) -> 18.1125 | FV57: =+'Other Accts'!FV47 -> 4.528125 | FW57: =+'Other Accts'!FW47 -> 4.3125 | FX57: =+'Other Accts'!FX47 -> 4.3125 | FY57: =+'Other Accts'!FY47 -> 4.3125 | FZ57: =SUM(FV57:FY57) -> 17.465625 | GB57: =+'Other Accts'!GB47 -> 4.3125 | GC57: =+'Other Accts'!GC47 -> 4.3125 | GD57: =+'Other Accts'!GD47 -> 4.3125 | GE57: =+'Other Accts'!GE47 -> 4.3125 | GF57: =SUM(GB57:GE57) -> 17.25 | GH57: =+'Other Accts'!GH47 -> 4.3125 | GI57: =+'Other Accts'!GI47 -> 4.3125 | GJ57: =+'Other Accts'!GJ47 -> 4.3125 | GK57: =+'Other Accts'!GK47 -> 2.15625 | GL57: =SUM(GH57:GK57) -> 15.09375 | GN57: =+'Other Accts'!GN47 -> 0 | GO57: =+'Other Accts'!GO47 -> 0 | GP57: =+'Other Accts'!GP47 -> 0 | GQ57: =+'Other Accts'!GQ47 -> 0 | GR57: =SUM(GN57:GQ57) -> 0 | GT57: =+'Other Accts'!GT47 -> 0 | GU57: =+'Other Accts'!GU47 -> 0 | GV57: =+'Other Accts'!GV47 -> 0 | GW57: =+'Other Accts'!GW47 -> 0 | GX57: =SUM(GT57:GW57) -> 0 | GZ57: =+'Other Accts'!GZ47 -> 0 | HA57: =+'Other Accts'!HA47 -> 0 | HB57: =+'Other Accts'!HB47 -> 0 | HC57: =+'Other Accts'!HC47 -> 0 | HD57: =SUM(GZ57:HC57) -> 0 | HF57: =+'Other Accts'!HF47 -> 0 | HG57: =+'Other Accts'!HG47 -> 0 | HH57: =+'Other Accts'!HH47 -> 0 | HI57: =+'Other Accts'!HI47 -> 0 | HJ57: =SUM(HF57:HI57) -> 0
C58: Interest income | DH58: =DH18 -> 0 | DI58: =DI18 -> 0 | DJ58: =DJ18 -> 0 | DK58: =DK18 -> 0 | DL58: =SUM(DH58:DK58) -> 0 | DN58: =DN18 -> 0 | DO58: =DO18 -> 0 | DP58: =DP18 -> 0 | DQ58: =DQ18 -> 0 | DR58: =SUM(DN58:DQ58) -> 0 | DT58: =DT18 -> 0 | DU58: =DU18 -> 0 | DV58: =DV18 -> 0 | DW58: =DW18 -> 0 | DX58: =SUM(DT58:DW58) -> 0 | DZ58: =DZ18 -> 0 | EA58: =EA18 -> 0 | EB58: =EB18 -> 0 | EC58: =EC18 -> 0 | ED58: =SUM(DZ58:EC58) -> 0 | EF58: =EF18 -> 0 | EG58: =EG18 -> 0 | EH58: =EH18 -> 0 | EI58: =EI18 -> -0.86 | EJ58: =SUM(EF58:EI58) -> -0.86 | EL58: =EL18 -> -1.467 | EM58: =EM18 -> -2.524 | EN58: =EN18 -> -2.84 | EO58: =EO18 -> -4.845 | EP58: =SUM(EL58:EO58) -> -11.676 | ER58: =ER18 -> -4.834 | ES58: =ES18 -> -4.592 | ET58: =ET18 -> -4.673 | EU58: =EU18 -> -4.328 | EV58: =SUM(ER58:EU58) -> -18.427 | EX58: =EX18 -> -3.721 | EY58: =EY18 -> -2.263 | EZ58: =EZ18 -> -1.563 | FA58: =FA18 -> -1.523 | FB58: =SUM(EX58:FA58) -> -9.07 | FD58: =-'Other Accts'!FD10 -> -1.2786041 | FE58: =-'Other Accts'!FE10 -> -1.2868019 | FF58: =-'Other Accts'!FF10 -> -1.2851217 | FG58: =-'Other Accts'!FG10 -> -1.3241443 | FH58: =SUM(FD58:FG58) -> -5.174672 | FJ58: =-'Other Accts'!FJ10 -> -1.3866853 | FK58: =-'Other Accts'!FK10 -> -1.4930897 | FL58: =-'Other Accts'!FL10 -> -1.5399455 | FM58: =-'Other Accts'!FM10 -> -1.5920869 | FN58: =SUM(FJ58:FM58) -> -6.0118073 | FP58: =-'Other Accts'!FP10 -> -4.2233975 | FQ58: =-'Other Accts'!FQ10 -> -4.3567345 | FR58: =-'Other Accts'!FR10 -> -4.4287729 | FS58: =-'Other Accts'!FS10 -> -4.5089543 | FT58: =SUM(FP58:FS58) -> -17.517859 | FV58: =-'Other Accts'!FV10 -> -2.0083776 | FW58: =-'Other Accts'!FW10 -> -2.1571163 | FX58: =-'Other Accts'!FX10 -> -2.2315872 | FY58: =-'Other Accts'!FY10 -> -2.3156531 | FZ58: =SUM(FV58:FY58) -> -8.7127343 | GB58: =-'Other Accts'!GB10 -> -2.4097031 | GC58: =-'Other Accts'!GC10 -> -2.6119397 | GD58: =-'Other Accts'!GD10 -> -2.733681 | GE58: =-'Other Accts'!GE10 -> -2.8676782 | GF58: =SUM(GB58:GE58) -> -10.623002 | GH58: =-'Other Accts'!GH10 -> -3.0135753 | GI58: =-'Other Accts'!GI10 -> -3.2717463 | GJ58: =-'Other Accts'!GJ10 -> -3.4444888 | GK58: =-'Other Accts'!GK10 -> -3.6327662 | GL58: =SUM(GH58:GK58) -> -13.362577 | GN58: =-'Other Accts'!GN10 -> -1.2607577 | GO58: =-'Other Accts'!GO10 -> -1.5961103 | GP58: =-'Other Accts'!GP10 -> -1.8416369 | GQ58: =-'Other Accts'!GQ10 -> -2.105972 | GR58: =SUM(GN58:GQ58) -> -6.8044769 | GT58: =-'Other Accts'!GT10 -> -2.3868687 | GU58: =-'Other Accts'!GU10 -> -2.7864577 | GV58: =-'Other Accts'!GV10 -> -3.0922108 | GW58: =-'Other Accts'!GW10 -> -3.420411 | GX58: =SUM(GT58:GW58) -> -11.685948 | GZ58: =-'Other Accts'!GZ10 -> -3.767763 | HA58: =-'Other Accts'!HA10 -> -4.2404839 | HB58: =-'Other Accts'!HB10 -> -4.6158066 | HC58: =-'Other Accts'!HC10 -> -5.017534 | HD58: =SUM(GZ58:HC58) -> -17.641588 | HF58: =-'Other Accts'!HF10 -> -5.4411746 | HG58: =-'Other Accts'!HG10 -> -5.9935891 | HH58: =-'Other Accts'!HH10 -> -6.4454717 | HI58: =-'Other Accts'!HI10 -> -6.9279382 | HJ58: =SUM(HF58:HI58) -> -24.808174
C59: Other expense, net | DH59: =DH19 -> -0.063 | DI59: =DI19 -> 0.124 | DJ59: =DJ19 -> -0.03 | DK59: =DK19 -> -0.046 | DL59: =SUM(DH59:DK59) -> -0.015 | DN59: =DN19 -> 5.169 | DO59: =DO19 -> 1.008 | DP59: =DP19 -> -0.035 | DQ59: =DQ19 -> -0.494 | DR59: =SUM(DN59:DQ59) -> 5.648 | DT59: =DT19 -> -0.223 | DU59: =DU19 -> -2.499 | DV59: =DV19 -> -0.011 | DW59: =DW19 -> -4.222 | DX59: =SUM(DT59:DW59) -> -6.955 | DZ59: =DZ19-DZ39 -> 4.854 | EA59: =EA19-EA39 -> -0.171 | EB59: =EB19-EB39 -> -0.089 | EC59: =EC19-EC39 -> 0.93 | ED59: =SUM(DZ59:EC59) -> 5.524 | EF59: =EF19-EF39 -> -0.168 | EG59: =EG19-EG39 -> 0.405 | EH59: =EH19-EH39 -> -0.025 | EI59: =EI19-EI39 -> 0.001 | EJ59: =SUM(EF59:EI59) -> 0.213 | EL59: =EL19-EL39 -> 0.114 | EM59: =EM19-EM39 -> -0.73 | EN59: =EN19-EN39 -> 0.096 | EO59: =EO19-EO39 -> -0.124 | EP59: =SUM(EL59:EO59) -> -0.644 | ER59: =ER19-ER39 -> 0.263 | ES59: =ES19-ES39 -> 0.002 | ET59: =ET19-ET39 -> -0.317 | EU59: =EU19-EU39 -> 0.431 | EV59: =SUM(ER59:EU59) -> 0.379 | EX59: =EX19-EX39 -> -0.065 | EY59: =EY19-EY39 -> -0.482 | EZ59: =EZ19-EZ39 -> 0.335 | FA59: =FA19-FA39 -> -0.084 | FB59: =SUM(EX59:FA59) -> -0.296 | FD59: 0 | FE59: 0 | FF59: 0 | FG59: 0 | FH59: =SUM(FD59:FG59) -> 0 | FJ59: 0 | FK59: 0 | FL59: 0 | FM59: 0 | FN59: =SUM(FJ59:FM59) -> 0 | FP59: 0 | FQ59: 0 | FR59: 0 | FS59: 0 | FT59: =SUM(FP59:FS59) -> 0 | FV59: 0 | FW59: 0 | FX59: 0 | FY59: 0 | FZ59: =SUM(FV59:FY59) -> 0 | GB59: 0 | GC59: 0 | GD59: 0 | GE59: 0 | GF59: =SUM(GB59:GE59) -> 0 | GH59: 0 | GI59: 0 | GJ59: 0 | GK59: 0 | GL59: =SUM(GH59:GK59) -> 0 | GN59: 0 | GO59: 0 | GP59: 0 | GQ59: 0 | GR59: =SUM(GN59:GQ59) -> 0 | GT59: 0 | GU59: 0 | GV59: 0 | GW59: 0 | GX59: =SUM(GT59:GW59) -> 0 | GZ59: 0 | HA59: 0 | HB59: 0 | HC59: 0 | HD59: =SUM(GZ59:HC59) -> 0 | HF59: 0 | HG59: 0 | HH59: 0 | HI59: 0 | HJ59: =SUM(HF59:HI59) -> 0
B60: Income before taxes | DH60: =DH56-SUM(DH57:DH59) -> 4.119 | DI60: =DI56-SUM(DI57:DI59) -> 4.839 | DJ60: =DJ56-SUM(DJ57:DJ59) -> 5.359 | DK60: =DK56-SUM(DK57:DK59) -> 7.208 | DL60: =DL56-SUM(DL57:DL59) -> 21.525 | DN60: =DN56-SUM(DN57:DN59) -> 6.662 | DO60: =DO56-SUM(DO57:DO59) -> 8.552 | DP60: =DP56-SUM(DP57:DP59) -> 9.844 | DQ60: =DQ56-SUM(DQ57:DQ59) -> 8.069 | DR60: =DR56-SUM(DR57:DR59) -> 33.127 | DT60: =DT56-SUM(DT57:DT59) -> 0.015 | DU60: =DU56-SUM(DU57:DU59) -> -14.709 | DV60: =DV56-SUM(DV57:DV59) -> 7.746 | DW60: =DW56-SUM(DW57:DW59) -> 8.867 | DX60: =DX56-SUM(DX57:DX59) -> 1.919 | DZ60: =DZ56-SUM(DZ57:DZ59) -> -3.671 | EA60: =EA56-SUM(EA57:EA59) -> -3.301 | EB60: =EB56-SUM(EB57:EB59) -> -12.587 | EC60: =EC56-SUM(EC57:EC59) -> -19.877 | ED60: =ED56-SUM(ED57:ED59) -> -39.436 | EF60: =EF56-SUM(EF57:EF59) -> -28.707 | EG60: =EG56-SUM(EG57:EG59) -> -25.726 | EH60: =EH56-SUM(EH57:EH59) -> -20.669 | EI60: =EI56-SUM(EI57:EI59) -> -9.785 | EJ60: =EJ56-SUM(EJ57:EJ59) -> -84.887 | EL60: =EL56-SUM(EL57:EL59) -> -14.706 | EM60: =EM56-SUM(EM57:EM59) -> -9.002 | EN60: =EN56-SUM(EN57:EN59) -> -3.204 | EO60: =EO56-SUM(EO57:EO59) -> 2.934 | EP60: =EP56-SUM(EP57:EP59) -> -23.978 | ER60: =ER56-SUM(ER57:ER59) -> -3.264 | ES60: =ES56-SUM(ES57:ES59) -> 4.049 | ET60: =ET56-SUM(ET57:ET59) -> 6.782 | EU60: =EU56-SUM(EU57:EU59) -> 4.75 | EV60: =EV56-SUM(EV57:EV59) -> 12.317 | EX60: =EX56-SUM(EX57:EX59) -> -0.193 | EY60: =EY56-SUM(EY57:EY59) -> 2.865 | EZ60: =EZ56-SUM(EZ57:EZ59) -> 4.389 | FA60: =FA56-SUM(FA57:FA59) -> 5.541 | FB60: =FB56-SUM(FB57:FB59) -> 12.602 | FD60: =FD56-SUM(FD57:FD59) -> -0.084858345 | FE60: =FE56-SUM(FE57:FE59) -> 2.7310141 | FF60: =FF56-SUM(FF57:FF59) -> 7.5421427 | FG60: =FG56-SUM(FG57:FG59) -> 9.7467474 | FH60: =FH56-SUM(FH57:FH59) -> 19.935046 | FJ60: =FJ56-SUM(FJ57:FJ59) -> 9.2965498 | FK60: =FK56-SUM(FK57:FK59) -> 9.9089143 | FL60: =FL56-SUM(FL57:FL59) -> 10.374509 | FM60: =FM56-SUM(FM57:FM59) -> 8.5134497 | FN60: =FN56-SUM(FN57:FN59) -> 38.093423 | FP60: =FP56-SUM(FP57:FP59) -> 13.063745 | FQ60: =FQ56-SUM(FQ57:FQ59) -> 14.032818 | FR60: =FR56-SUM(FR57:FR59) -> 14.794059 | FS60: =FS56-SUM(FS57:FS59) -> 15.275042 | FT60: =FT56-SUM(FT57:FT59) -> 57.165664 | FV60: =FV56-SUM(FV57:FV59) -> 17.440026 | FW60: =FW56-SUM(FW57:FW59) -> 19.052184 | FX60: =FX56-SUM(FX57:FX59) -> 20.155667 | FY60: =FY56-SUM(FY57:FY59) -> 20.83815 | FZ60: =FZ56-SUM(FZ57:FZ59) -> 77.486027 | GB60: =GB56-SUM(GB57:GB59) -> 25.102677 | GC60: =GC56-SUM(GC57:GC59) -> 26.993173 | GD60: =GD56-SUM(GD57:GD59) -> 28.507162 | GE60: =GE56-SUM(GE57:GE59) -> 29.450815 | GF60: =GF56-SUM(GF57:GF59) -> 110.05383 | GH60: =GH56-SUM(GH57:GH59) -> 33.611245 | GI60: =GI56-SUM(GI57:GI59) -> 36.05184 | GJ60: =GJ56-SUM(GJ57:GJ59) -> 38.024352 | GK60: =GK56-SUM(GK57:GK59) -> 41.415527 | GL60: =GL56-SUM(GL57:GL59) -> 149.10296 | GN60: =GN56-SUM(GN57:GN59) -> 44.975414 | GO60: =GO56-SUM(GO57:GO59) -> 48.043607 | GP60: =GP56-SUM(GP57:GP59) -> 50.542812 | GQ60: =GQ56-SUM(GQ57:GQ59) -> 52.117764 | GR60: =GR56-SUM(GR57:GR59) -> 195.6796 | GT60: =GT56-SUM(GT57:GT59) -> 54.96918 | GU60: =GU56-SUM(GU57:GU59) -> 58.655974 | GV60: =GV56-SUM(GV57:GV59) -> 61.672571 | GW60: =GW56-SUM(GW57:GW59) -> 63.57725 | GX60: =GX56-SUM(GX57:GX59) -> 238.87497 | GZ60: =GZ56-SUM(GZ57:GZ59) -> 66.315577 | HA60: =HA56-SUM(HA57:HA59) -> 70.698501 | HB60: =HB56-SUM(HB57:HB59) -> 74.298432 | HC60: =HC56-SUM(HC57:HC59) -> 76.575416 | HD60: =HD56-SUM(HD57:HD59) -> 287.88793 | HF60: =HF56-SUM(HF57:HF59) -> 78.695161 | HG60: =HG56-SUM(HG57:HG59) -> 83.827079 | HH60: =HH56-SUM(HH57:HH59) -> 88.055519 | HI60: =HI56-SUM(HI57:HI59) -> 90.734225 | HJ60: =HJ56-SUM(HJ57:HJ59) -> 341.31198
C61: Income tax | DH61: =DH21 -> 0.438 | DI61: =DI21+((SUM(DI34:DI38)-SUM(DI42:DI46))) -> 0.373 | DJ61: =DJ21+((SUM(DJ34:DJ38)-SUM(DJ42:DJ46))) -> 0.742 | DK61: =DK21+((SUM(DK34:DK38)-SUM(DK42:DK46))) -> 1.723 | DL61: =SUM(DH61:DK61) -> 3.276 | DN61: =DN21+((SUM(DN34:DN38)-SUM(DN42:DN46))) -> -0.497 | DO61: =DO21+((SUM(DO34:DO38)-SUM(DO42:DO46))) -> 1.324 | DP61: =DP21+((SUM(DP34:DP38)-SUM(DP42:DP46))) -> 2.309 | DQ61: =DQ21+((SUM(DQ34:DQ38)-SUM(DQ42:DQ46))) -> -2.853 | DR61: =SUM(DN61:DQ61) -> 0.283 | DT61: =DT21+((SUM(DT34:DT38)-SUM(DT42:DT46))) -> 2.209 | DU61: =DU21+((SUM(DU34:DU38)-SUM(DU42:DU46))) -> -10.57 | DV61: =DV21+((SUM(DV34:DV38)-SUM(DV42:DV46))) -> 0.785 | DW61: =DW21+((SUM(DW34:DW38)-SUM(DW42:DW46))) -> -7.678 | DX61: =SUM(DT61:DW61) -> -15.254 | DZ61: =DZ21+((SUM(DZ34:DZ39)-SUM(DZ42:DZ47))) -> 0.976 | EA61: =EA21+((SUM(EA34:EA39)-SUM(EA42:EA47))) -> -2.437 | EB61: =EB21+((SUM(EB34:EB39)-SUM(EB42:EB47))) -> -2.822 | EC61: =EC21+((SUM(EC34:EC39)-SUM(EC42:EC47))) -> -2.445 | ED61: =SUM(DZ61:EC61) -> -6.728 | EF61: =EF21+((SUM(EF34:EF39)-SUM(EF42:EF47))) -> -3.753 | EG61: =EG21+((SUM(EG34:EG39)-SUM(EG42:EG47))) -> -5.731 | EH61: =EH21+((SUM(EH34:EH39)-SUM(EH42:EH47))) -> -2.771 | EI61: =EI21+((SUM(EI34:EI39)-SUM(EI42:EI47))) -> -2.836 | EJ61: =SUM(EF61:EI61) -> -15.091 | EL61: =EL21+((SUM(EL34:EL39)-SUM(EL42:EL47))) -> -2.934 | EM61: =EM21+((SUM(EM34:EM39)-SUM(EM42:EM47))) -> -2.309 | EN61: =EN21+((SUM(EN34:EN39)-SUM(EN42:EN47))) -> -2.935 | EO61: =EO21+((SUM(EO34:EO39)-SUM(EO42:EO47))) -> -0.96 | EP61: =SUM(EL61:EO61) -> -9.138 | ER61: =ER21+((SUM(ER34:ER39)-SUM(ER42:ER47))) -> -0.62 | ES61: =ES21+((SUM(ES34:ES39)-SUM(ES42:ES47))) -> -0.375 | ET61: =ET21+((SUM(ET34:ET39)-SUM(ET42:ET47))) -> -0.15 | EU61: =EU21+((SUM(EU34:EU39)-SUM(EU42:EU47))) -> -0.805 | EV61: =SUM(ER61:EU61) -> -1.95 | EX61: =EX21+((SUM(EX34:EX39)-SUM(EX42:EX47))) -> 0.266 | EY61: =EY21+((SUM(EY34:EY39)-SUM(EY42:EY47))) -> -0.724 | EZ61: =EZ21+((SUM(EZ34:EZ39)-SUM(EZ42:EZ47))) -> 0.74 | FA61: =FA21+((SUM(FA34:FA39)-SUM(FA42:FA47))) -> -2.525 | FB61: =SUM(EX61:FA61) -> -2.243 | FD61: =FD60*FD81 -> 0 | FE61: =FE60*FE81 -> 0 | FF61: =FF60*FF81 -> 0 | FG61: =FG60*FG81 -> 0 | FH61: =SUM(FD61:FG61) -> 0 | FJ61: =FJ60*FJ81 -> 0 | FK61: =FK60*FK81 -> 0 | FL61: =FL60*FL81 -> 0 | FM61: =FM60*FM81 -> 0 | FN61: =SUM(FJ61:FM61) -> 0 | FP61: =FP60*FP81 -> 0 | FQ61: =FQ60*FQ81 -> 0 | FR61: =FR60*FR81 -> 0 | FS61: =FS60*FS81 -> 0 | FT61: =SUM(FP61:FS61) -> 0 | FV61: =FV60*FV81 -> 3.4880053 | FW61: =FW60*FW81 -> 3.8104368 | FX61: =FX60*FX81 -> 4.0311334 | FY61: =FY60*FY81 -> 4.16763 | FZ61: =SUM(FV61:FY61) -> 15.497205 | GB61: =GB60*GB81 -> 5.0205355 | GC61: =GC60*GC81 -> 5.3986345 | GD61: =GD60*GD81 -> 5.7014324 | GE61: =GE60*GE81 -> 5.8901629 | GF61: =SUM(GB61:GE61) -> 22.010765 | GH61: =GH60*GH81 -> 6.722249 | GI61: =GI60*GI81 -> 7.2103681 | GJ61: =GJ60*GJ81 -> 7.6048704 | GK61: =GK60*GK81 -> 8.2831054 | GL61: =SUM(GH61:GK61) -> 29.820593 | GN61: =GN60*GN81 -> 8.9950829 | GO61: =GO60*GO81 -> 9.6087215 | GP61: =GP60*GP81 -> 10.108562 | GQ61: =GQ60*GQ81 -> 10.423553 | GR61: =SUM(GN61:GQ61) -> 39.135919 | GT61: =GT60*GT81 -> 10.993836 | GU61: =GU60*GU81 -> 11.731195 | GV61: =GV60*GV81 -> 12.334514 | GW61: =GW60*GW81 -> 12.71545 | GX61: =SUM(GT61:GW61) -> 47.774995 | GZ61: =GZ60*GZ81 -> 13.263115 | HA61: =HA60*HA81 -> 14.1397 | HB61: =HB60*HB81 -> 14.859686 | HC61: =HC60*HC81 -> 15.315083 | HD61: =SUM(GZ61:HC61) -> 57.577585 | HF61: =HF60*HF81 -> 15.739032 | HG61: =HG60*HG81 -> 16.765416 | HH61: =HH60*HH81 -> 17.611104 | HI61: =HI60*HI81 -> 18.146845 | HJ61: =SUM(HF61:HI61) -> 68.262397
B62: Net income | DH62: =DH60-DH61 -> 3.681 | DI62: =DI60-DI61 -> 4.466 | DJ62: =DJ60-DJ61 -> 4.617 | DK62: =DK60-DK61 -> 5.485 | DL62: =DL60-DL61 -> 18.249 | DN62: =DN60-DN61 -> 7.159 | DO62: =DO60-DO61 -> 7.228 | DP62: =DP60-DP61 -> 7.535 | DQ62: =DQ60-DQ61 -> 10.922 | DR62: =DR60-DR61 -> 32.844 | DT62: =DT60-DT61 -> -2.194 | DU62: =DU60-DU61 -> -4.139 | DV62: =DV60-DV61 -> 6.961 | DW62: =DW60-DW61 -> 16.545 | DX62: =DX60-DX61 -> 17.173 | DZ62: =DZ60-DZ61 -> -4.647 | EA62: =EA60-EA61 -> -0.864 | EB62: =EB60-EB61 -> -9.765 | EC62: =EC60-EC61 -> -17.432 | ED62: =ED60-ED61 -> -32.708 | EF62: =EF60-EF61 -> -24.954 | EG62: =EG60-EG61 -> -19.995 | EH62: =EH60-EH61 -> -17.898 | EI62: =EI60-EI61 -> -6.949 | EJ62: =EJ60-EJ61 -> -69.796 | EL62: =EL60-EL61 -> -11.772 | EM62: =EM60-EM61 -> -6.693 | EN62: =EN60-EN61 -> -0.269 | EO62: =EO60-EO61 -> 3.894 | EP62: =EP60-EP61 -> -14.84 | ER62: =ER60-ER61 -> -2.644 | ES62: =ES60-ES61 -> 4.424 | ET62: =ET60-ET61 -> 6.932 | EU62: =EU60-EU61 -> 5.555 | EV62: =EV60-EV61 -> 14.267 | EX62: =EX60-EX61 -> -0.459 | EY62: =EY60-EY61 -> 3.589 | EZ62: =EZ60-EZ61 -> 3.649 | FA62: =FA60-FA61 -> 8.066 | FB62: =FB60-FB61 -> 14.845 | FD62: =FD60-FD61 -> -0.084858345 | FE62: =FE60-FE61 -> 2.7310141 | FF62: =FF60-FF61 -> 7.5421427 | FG62: =FG60-FG61 -> 9.7467474 | FH62: =FH60-FH61 -> 19.935046 | FJ62: =FJ60-FJ61 -> 9.2965498 | FK62: =FK60-FK61 -> 9.9089143 | FL62: =FL60-FL61 -> 10.374509 | FM62: =FM60-FM61 -> 8.5134497 | FN62: =FN60-FN61 -> 38.093423 | FP62: =FP60-FP61 -> 13.063745 | FQ62: =FQ60-FQ61 -> 14.032818 | FR62: =FR60-FR61 -> 14.794059 | FS62: =FS60-FS61 -> 15.275042 | FT62: =FT60-FT61 -> 57.165664 | FV62: =FV60-FV61 -> 13.952021 | FW62: =FW60-FW61 -> 15.241747 | FX62: =FX60-FX61 -> 16.124533 | FY62: =FY60-FY61 -> 16.67052 | FZ62: =FZ60-FZ61 -> 61.988822 | GB62: =GB60-GB61 -> 20.082142 | GC62: =GC60-GC61 -> 21.594538 | GD62: =GD60-GD61 -> 22.80573 | GE62: =GE60-GE61 -> 23.560652 | GF62: =GF60-GF61 -> 88.043061 | GH62: =GH60-GH61 -> 26.888996 | GI62: =GI60-GI61 -> 28.841472 | GJ62: =GJ60-GJ61 -> 30.419481 | GK62: =GK60-GK61 -> 33.132421 | GL62: =GL60-GL61 -> 119.28237 | GN62: =GN60-GN61 -> 35.980332 | GO62: =GO60-GO61 -> 38.434886 | GP62: =GP60-GP61 -> 40.43425 | GQ62: =GQ60-GQ61 -> 41.694211 | GR62: =GR60-GR61 -> 156.54368 | GT62: =GT60-GT61 -> 43.975344 | GU62: =GU60-GU61 -> 46.924779 | GV62: =GV60-GV61 -> 49.338057 | GW62: =GW60-GW61 -> 50.8618 | GX62: =GX60-GX61 -> 191.09998 | GZ62: =GZ60-GZ61 -> 53.052462 | HA62: =HA60-HA61 -> 56.558801 | HB62: =HB60-HB61 -> 59.438746 | HC62: =HC60-HC61 -> 61.260333 | HD62: =HD60-HD61 -> 230.31034 | HF62: =HF60-HF61 -> 62.956128 | HG62: =HG60-HG61 -> 67.061663 | HH62: =HH60-HH61 -> 70.444415 | HI62: =HI60-HI61 -> 72.58738 | HJ62: =HJ60-HJ61 -> 273.04959
B64: Basic average shares | DH64: =DH24 -> 80.507 | DI64: =DI24 -> 81.017 | DJ64: =DJ24 -> 87.253 | DK64: =DK24 -> 93.27 | DL64: =DL24 -> 85.618 | DN64: =DN24 -> 94.74 | DO64: =DO24 -> 98.297 | DP64: =DP24 -> 103.899 | DQ64: =DQ24 -> 104.393 | DR64: =DR24 -> 100.47 | DT64: =DT24 -> 104.484 | DU64: =DU24 -> 107.887 | DV64: =DV24 -> 110.461 | DW64: =DW24 -> 111.2 | DX64: =DX24 -> 100.47 | DZ64: =DZ24 -> 116.199 | EA64: =EA24 -> 118.287 | EB64: =EB24 -> 122.559 | EC64: =EC24 -> 123.082 | ED64: =ED24 -> 119.962 | EF64: =EF24 -> 123.63 | EG64: =EG24 -> 124.068 | EH64: =EH24 -> 124.425 | EI64: =EI24 -> 124.714 | EJ64: =EJ24 -> 124.217 | EL64: =EL24 -> 125.026 | EM64: =EM24 -> 125.356 | EN64: =EN24 -> 125.687 | EO64: =EO24 -> 125.929 | EP64: =EP24 -> 124.217 | ER64: =ER24 -> 126.111 | ES64: =ES24 -> 126.405 | ET64: =ET24 -> 126.953 | EU64: =EU24 -> 127.16 | EV64: =EV65 -> 126.65725 | EX64: =EX24 -> 127.376 | EY64: =EY24 -> 127.949 | EZ64: =EZ24 -> 128.415 | FA64: =FA65 -> 128.881 | FB64: =FB65 -> 128.15525 | FD64: =FD65 -> 129.23387 | FE64: =FE65 -> 129.58675 | FF64: =FF65 -> 129.93962 | FG64: =FG65 -> 130.2925 | FH64: =FH65 -> 129.76319 | FJ64: =FJ65 -> 130.59537 | FK64: =FK65 -> 130.89825 | FL64: =FL65 -> 131.20112 | FM64: =FM65 -> 131.504 | FN64: =FN65 -> 131.04969 | FP64: =FP65 -> 131.75687 | FQ64: =FQ65 -> 132.00975 | FR64: =FR65 -> 132.26262 | FS64: =FS65 -> 132.5155 | FT64: =FT65 -> 132.13619 | FV64: =FV65 -> 132.71837 | FW64: =FW65 -> 132.92125 | FX64: =FX65 -> 133.12412 | FY64: =FY65 -> 133.327 | FZ64: =FZ65 -> 133.02269 | GB64: =GB65 -> 133.47987 | GC64: =GC65 -> 133.63275 | GD64: =GD65 -> 133.78562 | GE64: =GE65 -> 133.9385 | GF64: =GF65 -> 133.70919 | GH64: =GH65 -> 134.04137 | GI64: =GI65 -> 134.14425 | GJ64: =GJ65 -> 134.24712 | GK64: =GK65 -> 134.35 | GL64: =GL65 -> 134.19569 | GN64: =GN65 -> 134.40287 | GO64: =GO65 -> 134.45575 | GP64: =GP65 -> 134.50862 | GQ64: =GQ65 -> 134.5615 | GR64: =GR65 -> 134.48219 | GT64: =GT65 -> 134.5615 | GU64: =GU65 -> 134.5615 | GV64: =GV65 -> 134.5615 | GW64: =GW65 -> 134.5615 | GX64: =GX65 -> 134.5615 | GZ64: =GZ65 -> 134.5615 | HA64: =HA65 -> 134.5615 | HB64: =HB65 -> 134.5615 | HC64: =HC65 -> 134.5615 | HD64: =HD65 -> 134.5615 | HF64: =HF65 -> 134.5615 | HG64: =HG65 -> 134.5615 | HH64: =HH65 -> 134.5615 | HI64: =HI65 -> 134.5615 | HJ64: =HJ65 -> 134.5615
B65: Diluted average shares | DH65: =DH25 -> 80.507 | DI65: =DI25 -> 90.168 | DJ65: =DJ25 -> 90.927 | DK65: =DK25 -> 96.874 | DL65: =DL25 -> 91.568 | DN65: =DN25 -> 94.74 | DO65: =DO25 -> 102.336 | DP65: =DP25 -> 107.88 | DQ65: =DQ25 -> 107.816 | DR65: =DR25 -> 103.615 | DT65: =DT25 -> 104.484 | DU65: =DU25 -> 107.887 | DV65: =DV25 -> 119.191 | DW65: =DW25 -> 114.236 | DX65: =DX25 -> 103.615 | DZ65: =DZ25 -> 116.199 | EA65: =EA25 -> 131.237 | EB65: =EB25 -> 122.559 | EC65: =EC25 -> 123.082 | ED65: =ED25 -> 119.962 | EF65: =EF25 -> 123.63 | EG65: =EG25 -> 124.068 | EH65: =EH25 -> 124.425 | EI65: =EI25 -> 124.714 | EJ65: =EJ25 -> 124.217 | EL65: =EL25 -> 125.026 | EM65: =EM25 -> 125.356 | EN65: =EN25 -> 125.687 | EO65: =EO25 -> 125.929 | EP65: =EP25 -> 124.217 | ER65: =ER25 -> 126.111 | ES65: =ES25 -> 126.405 | ET65: =ET25 -> 126.953 | EU65: =EU25 -> 127.16 | EV65: =AVERAGE(ER65:EU65) -> 126.65725 | EX65: =EX25 -> 127.376 | EY65: =EY25 -> 127.949 | EZ65: =EZ25 -> 128.415 | FA65: =BS!FA72 -> 128.881 | FB65: =AVERAGE(EX65:FA65) -> 128.15525 | FD65: =BS!FD72 -> 129.23387 | FE65: =BS!FE72 -> 129.58675 | FF65: =BS!FF72 -> 129.93962 | FG65: =BS!FG72 -> 130.2925 | FH65: =AVERAGE(FD65:FG65) -> 129.76319 | FJ65: =BS!FJ72 -> 130.59537 | FK65: =BS!FK72 -> 130.89825 | FL65: =BS!FL72 -> 131.20112 | FM65: =BS!FM72 -> 131.504 | FN65: =AVERAGE(FJ65:FM65) -> 131.04969 | FP65: =BS!FP72 -> 131.75687 | FQ65: =BS!FQ72 -> 132.00975 | FR65: =BS!FR72 -> 132.26262 | FS65: =BS!FS72 -> 132.5155 | FT65: =AVERAGE(FP65:FS65) -> 132.13619 | FV65: =BS!FV72 -> 132.71837 | FW65: =BS!FW72 -> 132.92125 | FX65: =BS!FX72 -> 133.12412 | FY65: =BS!FY72 -> 133.327 | FZ65: =AVERAGE(FV65:FY65) -> 133.02269 | GB65: =BS!GB72 -> 133.47987 | GC65: =BS!GC72 -> 133.63275 | GD65: =BS!GD72 -> 133.78562 | GE65: =BS!GE72 -> 133.9385 | GF65: =AVERAGE(GB65:GE65) -> 133.70919 | GH65: =BS!GH72 -> 134.04137 | GI65: =BS!GI72 -> 134.14425 | GJ65: =BS!GJ72 -> 134.24712 | GK65: =BS!GK72 -> 134.35 | GL65: =AVERAGE(GH65:GK65) -> 134.19569 | GN65: =BS!GN72 -> 134.40287 | GO65: =BS!GO72 -> 134.45575 | GP65: =BS!GP72 -> 134.50862 | GQ65: =BS!GQ72 -> 134.5615 | GR65: =AVERAGE(GN65:GQ65) -> 134.48219 | GT65: =BS!GT72 -> 134.5615 | GU65: =BS!GU72 -> 134.5615 | GV65: =BS!GV72 -> 134.5615 | GW65: =BS!GW72 -> 134.5615 | GX65: =AVERAGE(GT65:GW65) -> 134.5615 | GZ65: =BS!GZ72 -> 134.5615 | HA65: =BS!HA72 -> 134.5615 | HB65: =BS!HB72 -> 134.5615 | HC65: =BS!HC72 -> 134.5615 | HD65: =AVERAGE(GZ65:HC65) -> 134.5615 | HF65: =BS!HF72 -> 134.5615 | HG65: =BS!HG72 -> 134.5615 | HH65: =BS!HH72 -> 134.5615 | HI65: =BS!HI72 -> 134.5615 | HJ65: =AVERAGE(HF65:HI65) -> 134.5615
B67: Basic E.P.S. (non GAAP) | DH67: =DH62/DH64 -> 0.045722732 | DI67: =DI62/DI64 -> 0.055124233 | DJ67: =DJ62/DJ64 -> 0.052915086 | DK67: =DK62/DK64 -> 0.058807762 | DL67: =DL62/DL64 -> 0.21314443 | DN67: =DN62/DN64 -> 0.075564703 | DO67: =DO62/DO64 -> 0.073532254 | DP67: =DP62/DP64 -> 0.072522353 | DQ67: =DQ62/DQ64 -> 0.10462387 | DR67: =DR62/DR64 -> 0.32690355 | DT67: =DT62/DT64 -> -0.02099843 | DU67: =DU62/DU64 -> -0.038364214 | DV67: =DV62/DV64 -> 0.063017717 | DW67: =DW62/DW64 -> 0.14878597 | DX67: =DX62/DX64 -> 0.17092664 | DZ67: =DZ62/DZ64 -> -0.039991738 | EA67: =EA62/EA64 -> -0.0073042684 | EB67: =EB62/EB64 -> -0.079675911 | EC67: =EC62/EC64 -> -0.14162916 | ED67: =ED62/ED64 -> -0.27265301 | EF67: =EF62/EF64 -> -0.20184421 | EG67: =EG62/EG64 -> -0.16116162 | EH67: =EH62/EH64 -> -0.14384569 | EI67: =EI62/EI64 -> -0.055719486 | EJ67: =EJ62/EJ64 -> -0.56188766 | EL67: =EL62/EL64 -> -0.094156415 | EM67: =EM62/EM64 -> -0.05339194 | EN67: =EN62/EN64 -> -0.0021402373 | EO67: =EO62/EO64 -> 0.030922186 | EP67: =EP62/EP64 -> -0.11946835 | ER67: =ER62/ER64 -> -0.020965657 | ES67: =ES62/ES64 -> 0.034998616 | ET67: =ET62/ET64 -> 0.054602885 | EU67: =EU62/EU64 -> 0.043685121 | EV67: =EV62/EV64 -> 0.11264258 | EX67: =EX62/EX64 -> -0.0036035046 | EY67: =EY62/EY64 -> 0.028050239 | EZ67: =EZ62/EZ64 -> 0.028415684 | FA67: =FA62/FA64 -> 0.062584865 | FB67: =FB62/FB64 -> 0.11583607 | FD67: =FD62/FD64 -> -0.00065662617 | FE67: =FE62/FE64 -> 0.021074794 | FF67: =FF62/FF64 -> 0.058043439 | FG67: =FG62/FG64 -> 0.074806665 | FH67: =FH62/FH64 -> 0.15362636 | FJ67: =FJ62/FJ64 -> 0.071185903 | FK67: =FK62/FK64 -> 0.075699364 | FL67: =FL62/FL64 -> 0.079073325 | FM67: =FM62/FM64 -> 0.064739093 | FN67: =FN62/FN64 -> 0.29067924 | FP67: =FP62/FP64 -> 0.099150388 | FQ67: =FQ62/FQ64 -> 0.10630138 | FR67: =FR62/FR64 -> 0.11185366 | FS67: =FS62/FS64 -> 0.11526985 | FT67: =FT62/FT64 -> 0.43262686 | FV67: =FV62/FV64 -> 0.10512502 | FW67: =FW62/FW64 -> 0.1146675 | FX67: =FX62/FX64 -> 0.12112405 | FY67: =FY62/FY64 -> 0.12503484 | FZ67: =FZ62/FZ64 -> 0.46600187 | GB67: =GB62/GB64 -> 0.15045071 | GC67: =GC62/GC64 -> 0.16159615 | GD67: =GD62/GD64 -> 0.17046472 | GE67: =GE62/GE64 -> 0.17590649 | GF67: =GF62/GF64 -> 0.6584668 | GH67: =GH62/GH64 -> 0.20060221 | GI67: =GI62/GI64 -> 0.21500342 | GJ67: =GJ62/GJ64 -> 0.22659317 | GK67: =GK62/GK64 -> 0.24661274 | GL67: =GL62/GL64 -> 0.88886889 | GN67: =GN62/GN64 -> 0.26770507 | GO67: =GO62/GO64 -> 0.28585528 | GP67: =GP62/GP64 -> 0.30060711 | GQ67: =GQ62/GQ64 -> 0.30985245 | GR67: =GR62/GR64 -> 1.1640477 | GT67: =GT62/GT64 -> 0.3268048 | GU67: =GU62/GU64 -> 0.34872366 | GV67: =GV62/GV64 -> 0.36665805 | GW67: =GW62/GW64 -> 0.37798182 | GX67: =GX62/GX64 -> 1.4201683 | GZ67: =GZ62/GZ64 -> 0.39426182 | HA67: =HA62/HA64 -> 0.42031934 | HB67: =HB62/HB64 -> 0.44172178 | HC67: =HC62/HC64 -> 0.45525899 | HD67: =HD62/HD64 -> 1.7115619 | HF67: =HF62/HF64 -> 0.46786138 | HG67: =HG62/HG64 -> 0.49837185 | HH67: =HH62/HH64 -> 0.52351092 | HI67: =HI62/HI64 -> 0.53943647 | HJ67: =HJ62/HJ64 -> 2.0291806
B68: Diluted E.P.S. (non GAAP) | DH68: =DH62/DH65 -> 0.045722732 | DI68: =DI62/DI65 -> 0.049529767 | DJ68: =DJ62/DJ65 -> 0.050776997 | DK68: =DK62/DK65 -> 0.056619939 | DL68: =DL62/DL65 -> 0.19929451 | DN68: =DN62/DN65 -> 0.075564703 | DO68: =DO62/DO65 -> 0.070630081 | DP68: =DP62/DP65 -> 0.069846125 | DQ68: =DQ62/DQ65 -> 0.10130222 | DR68: =DR62/DR65 -> 0.31698113 | DT68: =DT62/DT65 -> -0.02099843 | DU68: =DU62/DU65 -> -0.038364214 | DV68: =DV62/DV65 -> 0.058402061 | DW68: =DW62/DW65 -> 0.14483175 | DX68: =DX62/DX65 -> 0.16573855 | DZ68: =DZ62/DZ65 -> -0.039991738 | EA68: =EA62/EA65 -> -0.0065835092 | EB68: =EB62/EB65 -> -0.079675911 | EC68: =EC62/EC65 -> -0.14162916 | ED68: =ED62/ED65 -> -0.27265301 | EF68: =EF62/EF65 -> -0.20184421 | EG68: =EG62/EG65 -> -0.16116162 | EH68: =EH62/EH65 -> -0.14384569 | EI68: =EI62/EI65 -> -0.055719486 | EJ68: =EJ62/EJ65 -> -0.56188766 | EL68: =EL62/EL65 -> -0.094156415 | EM68: =EM62/EM65 -> -0.05339194 | EN68: =EN62/EN65 -> -0.0021402373 | EO68: =EO62/EO65 -> 0.030922186 | EP68: =EP62/EP65 -> -0.11946835 | ER68: =ER62/ER65 -> -0.020965657 | ES68: =ES62/ES65 -> 0.034998616 | ET68: =ET62/ET65 -> 0.054602885 | EU68: =EU62/EU65 -> 0.043685121 | EV68: =EV62/EV65 -> 0.11264258 | EX68: =EX62/EX65 -> -0.0036035046 | EY68: =EY62/EY65 -> 0.028050239 | EZ68: =EZ62/EZ65 -> 0.028415684 | FA68: =FA62/FA65 -> 0.062584865 | FB68: =FB62/FB65 -> 0.11583607 | FD68: =FD62/FD65 -> -0.00065662617 | FE68: =FE62/FE65 -> 0.021074794 | FF68: =FF62/FF65 -> 0.058043439 | FG68: =FG62/FG65 -> 0.074806665 | FH68: =FH62/FH65 -> 0.15362636 | FJ68: =FJ62/FJ65 -> 0.071185903 | FK68: =FK62/FK65 -> 0.075699364 | FL68: =FL62/FL65 -> 0.079073325 | FM68: =FM62/FM65 -> 0.064739093 | FN68: =FN62/FN65 -> 0.29067924 | FP68: =FP62/FP65 -> 0.099150388 | FQ68: =FQ62/FQ65 -> 0.10630138 | FR68: =FR62/FR65 -> 0.11185366 | FS68: =FS62/FS65 -> 0.11526985 | FT68: =FT62/FT65 -> 0.43262686 | FV68: =FV62/FV65 -> 0.10512502 | FW68: =FW62/FW65 -> 0.1146675 | FX68: =FX62/FX65 -> 0.12112405 | FY68: =FY62/FY65 -> 0.12503484 | FZ68: =FZ62/FZ65 -> 0.46600187 | GB68: =GB62/GB65 -> 0.15045071 | GC68: =GC62/GC65 -> 0.16159615 | GD68: =GD62/GD65 -> 0.17046472 | GE68: =GE62/GE65 -> 0.17590649 | GF68: =GF62/GF65 -> 0.6584668 | GH68: =GH62/GH65 -> 0.20060221 | GI68: =GI62/GI65 -> 0.21500342 | GJ68: =GJ62/GJ65 -> 0.22659317 | GK68: =GK62/GK65 -> 0.24661274 | GL68: =GL62/GL65 -> 0.88886889 | GN68: =GN62/GN65 -> 0.26770507 | GO68: =GO62/GO65 -> 0.28585528 | GP68: =GP62/GP65 -> 0.30060711 | GQ68: =GQ62/GQ65 -> 0.30985245 | GR68: =GR62/GR65 -> 1.1640477 | GT68: =GT62/GT65 -> 0.3268048 | GU68: =GU62/GU65 -> 0.34872366 | GV68: =GV62/GV65 -> 0.36665805 | GW68: =GW62/GW65 -> 0.37798182 | GX68: =GX62/GX65 -> 1.4201683 | GZ68: =GZ62/GZ65 -> 0.39426182 | HA68: =HA62/HA65 -> 0.42031934 | HB68: =HB62/HB65 -> 0.44172178 | HC68: =HC62/HC65 -> 0.45525899 | HD68: =HD62/HD65 -> 1.7115619 | HF68: =HF62/HF65 -> 0.46786138 | HG68: =HG62/HG65 -> 0.49837185 | HH68: =HH62/HH65 -> 0.52351092 | HI68: =HI62/HI65 -> 0.53943647 | HJ68: =HJ62/HJ65 -> 2.0291806
B70: Adj. EBITDA | DH70: =DH56+DH33-DH59 -> 9.238 | DI70: =DI56+DI33-DI59 -> 10.057 | DJ70: =DJ56+DJ33-DJ59 -> 11.265 | DK70: =DK56+DK33-DK59 -> 12.999 | DL70: =SUM(DH70:DK70) -> 43.559 | DN70: =DN56+DN33-DN59 -> 13.759 | DO70: =DO56+DO33-DO59 -> 14.937 | DP70: =DP56+DP33-DP59 -> 14.895 | DQ70: =DQ56+DQ33-DQ59 -> 13.595 | DR70: =SUM(DN70:DQ70) -> 57.186 | DT70: =DT56+DT33-DT59 -> 7.074 | DU70: =DU56+DU33-DU59 -> -7.224 | DV70: =DV56+DV33-DV59 -> 16.732 | DW70: =DW56+DW33-DW59 -> 18.26 | DX70: =SUM(DT70:DW70) -> 34.842 | DZ70: =DZ56+DZ33-DZ59 -> 4.186 | EA70: =EA56+EA33-EA59 -> 4.55 | EB70: =EB56+EB33-EB59 -> -3.113 | EC70: =EC56+EC33-EC59 -> -9.785 | ED70: =SUM(DZ70:EC70) -> -4.162 | EF70: =EF56+EF33-EF59 -> -19.011 | EG70: =EG56+EG33-EG59 -> -16.274 | EH70: =EH56+EH33-EH59 -> -11.557 | EI70: =EI56+EI33-EI59 -> -1.167 | EJ70: =SUM(EF70:EI70) -> -48.009 | EL70: =EL56+EL33-EL59 -> -7.125 | EM70: =EM56+EM33-EM59 -> -2.051 | EN70: =EN56+EN33-EN59 -> 3.305 | EO70: =EO56+EO33-EO59 -> 9.348 | EP70: =SUM(EL70:EO70) -> 3.477 | ER70: =ER56+ER33-ER59 -> 3.492 | ES70: =ES56+ES33-ES59 -> 10.869 | ET70: =ET56+ET33-ET59 -> 13.374 | EU70: =EU56+EU33-EU59 -> 11.873 | EV70: =SUM(ER70:EU70) -> 39.608 | EX70: =EX56+EX33-EX59 -> 7.07 | EY70: =EY56+EY33-EY59 -> 10.675 | EZ70: =EZ56+EZ33-EZ59 -> 12.232 | FA70: =FA56+FA33-FA59 -> 13.38 | FB70: =SUM(EX70:FA70) -> 43.357 | FD70: =FD56+FD33 -> 9.0872575 | FE70: =FE56+FE33 -> 11.806548 | FF70: =FF56+FF33 -> 16.53981 | FG70: =FG56+FG33 -> 18.633801 | FH70: =SUM(FD70:FG70) -> 56.067417 | FJ70: =FJ56+FJ33 -> 17.732716 | FK70: =FK56+FK33 -> 18.249164 | FL70: =FL56+FL33 -> 18.677342 | FM70: =FM56+FM33 -> 18.928887 | FN70: =SUM(FJ70:FM70) -> 73.588109 | FP70: =FP56+FP33 -> 23.09432 | FQ70: =FQ56+FQ33 -> 24.011235 | FR70: =FR56+FR33 -> 24.773498 | FS70: =FS56+FS33 -> 25.240055 | FT70: =SUM(FP70:FS70) -> 97.119108 | FV70: =FV56+FV33 -> 30.054365 | FW70: =FW56+FW33 -> 31.436033 | FX70: =FX56+FX33 -> 32.585532 | FY70: =FY56+FY33 -> 33.292387 | FZ70: =SUM(FV70:FY70) -> 127.36832 | GB70: =GB56+GB33 -> 38.101483 | GC70: =GC56+GC33 -> 39.926112 | GD70: =GD56+GD33 -> 41.440526 | GE70: =GE56+GE33 -> 42.359621 | GF70: =SUM(GB70:GE70) -> 161.82774 | GH70: =GH56+GH33 -> 46.582032 | GI70: =GI56+GI33 -> 48.950679 | GJ70: =GJ56+GJ33 -> 50.917274 | GK70: =GK56+GK33 -> 52.113369 | GL70: =SUM(GH70:GK70) -> 198.56335 | GN70: =GN56+GN33 -> 56.682391 | GO70: =GO56+GO33 -> 59.593051 | GP70: =GP56+GP33 -> 62.00522 | GQ70: =GQ56+GQ33 -> 63.4571 | GR70: =SUM(GN70:GQ70) -> 241.73776 | GT70: =GT56+GT33 -> 66.288454 | GU70: =GU56+GU33 -> 69.808143 | GV70: =GV56+GV33 -> 72.726199 | GW70: =GW56+GW33 -> 74.487368 | GX70: =SUM(GT70:GW70) -> 283.31016 | GZ70: =GZ56+GZ33 -> 77.189352 | HA70: =HA56+HA33 -> 81.376759 | HB70: =HB56+HB33 -> 84.848439 | HC70: =HC56+HC33 -> 86.943913 | HD70: =SUM(GZ70:HC70) -> 330.35846 | HF70: =HF56+HF33 -> 73.253986 | HG70: =HG56+HG33 -> 77.83349 | HH70: =HH56+HH33 -> 81.610047 | HI70: =HI56+HI33 -> 83.806287 | HJ70: =SUM(HF70:HI70) -> 316.50381
B73: Margin Analysis
B74: Gross margin | DH74: =DH51/DH49 -> 0.43049052 | DI74: =DI51/DI49 -> 0.45065391 | DJ74: =DJ51/DJ49 -> 0.46776948 | DK74: =DK51/DK49 -> 0.4852697 | DL74: =DL51/DL49 -> 0.45987208 | DN74: =DN51/DN49 -> 0.49295333 | DO74: =DO51/DO49 -> 0.48141339 | DP74: =DP51/DP49 -> 0.48563131 | DQ74: =DQ51/DQ49 -> 0.46714639 | DR74: =DR51/DR49 -> 0.48146173 | DT74: =DT51/DT49 -> 0.43731963 | DU74: =DU51/DU49 -> 0.32199317 | DV74: =DV51/DV49 -> 0.43098913 | DW74: =DW51/DW49 -> 0.45598705 | DX74: =DX51/DX49 -> 0.4182559 | DZ74: =DZ51/DZ49 -> 0.40571092 | EA74: =EA51/EA49 -> 0.44131806 | EB74: =EB51/EB49 -> 0.42906708 | EC74: =EC51/EC49 -> 0.39854611 | ED74: =ED51/ED49 -> 0.41865137 | EF74: =EF51/EF49 -> 0.36771672 | EG74: =EG51/EG49 -> 0.39016726 | EH74: =EH51/EH49 -> 0.41734093 | EI74: =EI51/EI49 -> 0.44467755 | EJ74: =EJ51/EJ49 -> 0.40670514 | EL74: =EL51/EL49 -> 0.43482728 | EM74: =EM51/EM49 -> 0.4406842 | EN74: =EN51/EN49 -> 0.44200218 | EO74: =EO51/EO49 -> 0.46715568 | EP74: =EP51/EP49 -> 0.44662406 | ER74: =ER51/ER49 -> 0.45298259 | ES74: =ES51/ES49 -> 0.4727055 | ET74: =ET51/ET49 -> 0.47716656 | EU74: =EU51/EU49 -> 0.47940116 | EV74: =EV51/EV49 -> 0.47091736 | EX74: =EX51/EX49 -> 0.46746809 | EY74: =EY51/EY49 -> 0.4542657 | EZ74: =EZ51/EZ49 -> 0.45472505 | FA74: =FA51/FA49 -> 0.46435821 | FB74: =FB51/FB49 -> 0.46007325 | FD74: =EX74+0.01 -> 0.47746809 | FE74: =EY74+0.011 -> 0.4652657 | FF74: =EZ74+0.01 -> 0.46472505 | FG74: =FA74+0.01 -> 0.47435821 | FH74: =FH51/FH49 -> 0.47035876 | FJ74: =FN74 -> 0.48285876 | FK74: =FN74 -> 0.48285876 | FL74: =FN74 -> 0.48285876 | FM74: =FN74 -> 0.48285876 | FN74: =FH74+0.0125 -> 0.48285876 | FP74: =FT74 -> 0.49535876 | FQ74: =FT74 -> 0.49535876 | FR74: =FT74 -> 0.49535876 | FS74: =FT74 -> 0.49535876 | FT74: =FN74+0.0125 -> 0.49535876 | FV74: =FZ74 -> 0.50785876 | FW74: =FZ74 -> 0.50785876 | FX74: =FZ74 -> 0.50785876 | FY74: =FZ74 -> 0.50785876 | FZ74: =FT74+0.0125 -> 0.50785876 | GB74: =GF74 -> 0.52035876 | GC74: =GF74 -> 0.52035876 | GD74: =GF74 -> 0.52035876 | GE74: =GF74 -> 0.52035876 | GF74: =FZ74+0.0125 -> 0.52035876 | GH74: =GL74 -> 0.53285876 | GI74: =GL74 -> 0.53285876 | GJ74: =GL74 -> 0.53285876 | GK74: =GL74 -> 0.53285876 | GL74: =GF74+0.0125 -> 0.53285876 | GN74: =GR74 -> 0.54535876 | GO74: =GR74 -> 0.54535876 | GP74: =GR74 -> 0.54535876 | GQ74: =GR74 -> 0.54535876 | GR74: =GL74+0.0125 -> 0.54535876 | GT74: =GX74 -> 0.55785876 | GU74: =GX74 -> 0.55785876 | GV74: =GX74 -> 0.55785876 | GW74: =GX74 -> 0.55785876 | GX74: =GR74+0.0125 -> 0.55785876 | GZ74: =HD74 -> 0.57035876 | HA74: =HD74 -> 0.57035876 | HB74: =HD74 -> 0.57035876 | HC74: =HD74 -> 0.57035876 | HD74: =GX74+0.0125 -> 0.57035876 | HF74: =HJ74 -> 0.58285876 | HG74: =HJ74 -> 0.58285876 | HH74: =HJ74 -> 0.58285876 | HI74: =HJ74 -> 0.58285876 | HJ74: =HD74+0.0125 -> 0.58285876
C75: =C52 -> G&A | DH75: =DH52/DH49 -> 0.22121312 | DI75: =DI52/DI49 -> 0.22742302 | DJ75: =DJ52/DJ49 -> 0.25722184 | DK75: =DK52/DK49 -> 0.26037267 | DL75: =DL52/DL49 -> 0.24254535 | DN75: =DN52/DN49 -> 0.2200634 | DO75: =DO52/DO49 -> 0.22800429 | DP75: =DP52/DP49 -> 0.2550921 | DQ75: =DQ52/DQ49 -> 0.25813153 | DR75: =DR52/DR49 -> 0.24095834 | DT75: =DT52/DT49 -> 0.28708856 | DU75: =DU52/DU49 -> 0.36062407 | DV75: =DV52/DV49 -> 0.24396543 | DW75: =DW52/DW49 -> 0.2810305 | DX75: =DX52/DX49 -> 0.28759045 | DZ75: =DZ52/DZ49 -> 0.2450209 | EA75: =EA52/EA49 -> 0.29221846 | EB75: =EB52/EB49 -> 0.33237185 | EC75: =EC52/EC49 -> 0.34136099 | ED75: =ED52/ED49 -> 0.30377698 | EF75: =EF52/EF49 -> 0.39811725 | EG75: =EG52/EG49 -> 0.37975726 | EH75: =EH52/EH49 -> 0.38965073 | EI75: =EI52/EI49 -> 0.34970621 | EJ75: =EJ52/EJ49 -> 0.3782998 | EL75: =EL52/EL49 -> 0.37947821 | EM75: =EM52/EM49 -> 0.34439173 | EN75: =EN52/EN49 -> 0.33047501 | EO75: =EO52/EO49 -> 0.30743417 | EP75: =EP52/EP49 -> 0.33923836 | ER75: =ER52/ER49 -> 0.31415131 | ES75: =ES52/ES49 -> 0.28615458 | ET75: =ET52/ET49 -> 0.28927329 | EU75: =EU52/EU49 -> 0.2887907 | EV75: =EV52/EV49 -> 0.29425523 | EX75: =EX52/EX49 -> 0.28594043 | EY75: =EY52/EY49 -> 0.29052556 | EZ75: =EZ52/EZ49 -> 0.23623913 | FA75: =FA52/FA49 -> 0.26753431 | FB75: =FB52/FB49 -> 0.26943817 | FD75: =EX75 -> 0.28594043 | FE75: 0.275 | FF75: 0.26 | FG75: 0.26 | FH75: =FH52/FH49 -> 0.26969474 | FJ75: =FN75 -> 0.26569474 | FK75: =FN75 -> 0.26569474 | FL75: =FN75 -> 0.26569474 | FM75: =FN75 -> 0.26569474 | FN75: =FH75-0.004 -> 0.26569474 | FP75: =FT75 -> 0.26069474 | FQ75: =FT75 -> 0.26069474 | FR75: =FT75 -> 0.26069474 | FS75: =FT75 -> 0.26069474 | FT75: =FN75-0.005 -> 0.26069474 | FV75: =FZ75 -> 0.25369474 | FW75: =FZ75 -> 0.25369474 | FX75: =FZ75 -> 0.25369474 | FY75: =FZ75 -> 0.25369474 | FZ75: =FT75-0.007 -> 0.25369474 | GB75: =GF75 -> 0.24869474 | GC75: =GF75 -> 0.24869474 | GD75: =GF75 -> 0.24869474 | GE75: =GF75 -> 0.24869474 | GF75: =FZ75-0.005 -> 0.24869474 | GH75: =GL75 -> 0.24369474 | GI75: =GL75 -> 0.24369474 | GJ75: =GL75 -> 0.24369474 | GK75: =GL75 -> 0.24369474 | GL75: =GF75-0.005 -> 0.24369474 | GN75: =GR75 -> 0.23869474 | GO75: =GR75 -> 0.23869474 | GP75: =GR75 -> 0.23869474 | GQ75: =GR75 -> 0.23869474 | GR75: =GL75-0.005 -> 0.23869474 | GT75: =GX75 -> 0.23369474 | GU75: =GX75 -> 0.23369474 | GV75: =GX75 -> 0.23369474 | GW75: =GX75 -> 0.23369474 | GX75: =GR75-0.005 -> 0.23369474 | GZ75: =HD75 -> 0.22769474 | HA75: =HD75 -> 0.22769474 | HB75: =HD75 -> 0.22769474 | HC75: =HD75 -> 0.22769474 | HD75: =GX75-0.006 -> 0.22769474 | HF75: =HJ75 -> 0.22169474 | HG75: =HJ75 -> 0.22169474 | HH75: =HJ75 -> 0.22169474 | HI75: =HJ75 -> 0.22169474 | HJ75: =HD75-0.006 -> 0.22169474
C76: =C53 -> Sales and Marketing | DH76: =DH53/DH49 -> 0.10682245 | DI76: =DI53/DI49 -> 0.11336463 | DJ76: =DJ53/DJ49 -> 0.099861063 | DK76: =DK53/DK49 -> 0.10522393 | DL76: =DL53/DL49 -> 0.10624413 | DN76: =DN53/DN49 -> 0.11735041 | DO76: =DO53/DO49 -> 0.12116445 | DP76: =DP53/DP49 -> 0.10994344 | DQ76: =DQ53/DQ49 -> 0.11511397 | DR76: =DR53/DR49 -> 0.11581831 | DT76: =DT53/DT49 -> 0.12504008 | DU76: =DU53/DU49 -> 0.1172149 | DV76: =DV53/DV49 -> 0.090111922 | DW76: =DW53/DW49 -> 0.10401041 | DX76: =DX53/DX49 -> 0.10768864 | DZ76: =DZ53/DZ49 -> 0.11900496 | EA76: =EA53/EA49 -> 0.14150044 | EB76: =EB53/EB49 -> 0.12942146 | EC76: =EC53/EC49 -> 0.12659466 | ED76: =ED53/ED49 -> 0.1292386 | EF76: =EF53/EF49 -> 0.13910676 | EG76: =EG53/EG49 -> 0.13648938 | EH76: =EH53/EH49 -> 0.1305229 | EI76: =EI53/EI49 -> 0.12358603 | EJ76: =EJ53/EJ49 -> 0.1320724 | EL76: =EL53/EL49 -> 0.11848856 | EM76: =EM53/EM49 -> 0.12865087 | EN76: =EN53/EN49 -> 0.11589034 | EO76: =EO53/EO49 -> 0.1161798 | EP76: =EP53/EP49 -> 0.11973775 | ER76: =ER53/ER49 -> 0.12942268 | ES76: =ES53/ES49 -> 0.13177347 | ET76: =ET53/ET49 -> 0.1216453 | EU76: =EU53/EU49 -> 0.12987791 | EV76: =EV53/EV49 -> 0.12815071 | EX76: =EX53/EX49 -> 0.13498973 | EY76: =EY53/EY49 -> 0.13276898 | EZ76: =EZ53/EZ49 -> 0.11611474 | FA76: =FA53/FA49 -> 0.12327391 | FB76: =FB53/FB49 -> 0.12649932 | FD76: =EX76 -> 0.13498973 | FE76: 0.13 | FF76: 0.125 | FG76: =FA76 -> 0.12327391 | FH76: =FH53/FH49 -> 0.12808557 | FJ76: =FN76 -> 0.12608557 | FK76: =FN76 -> 0.12608557 | FL76: =FN76 -> 0.12608557 | FM76: =FN76 -> 0.12608557 | FN76: =FH76-0.002 -> 0.12608557 | FP76: =FT76 -> 0.12358557 | FQ76: =FT76 -> 0.12358557 | FR76: =FT76 -> 0.12358557 | FS76: =FT76 -> 0.12358557 | FT76: =FN76-0.0025 -> 0.12358557 | FV76: =FZ76 -> 0.12108557 | FW76: =FZ76 -> 0.12108557 | FX76: =FZ76 -> 0.12108557 | FY76: =FZ76 -> 0.12108557 | FZ76: =FT76-0.0025 -> 0.12108557 | GB76: =GF76 -> 0.11858557 | GC76: =GF76 -> 0.11858557 | GD76: =GF76 -> 0.11858557 | GE76: =GF76 -> 0.11858557 | GF76: =FZ76-0.0025 -> 0.11858557 | GH76: =GL76 -> 0.11608557 | GI76: =GL76 -> 0.11608557 | GJ76: =GL76 -> 0.11608557 | GK76: =GL76 -> 0.11608557 | GL76: =GF76-0.0025 -> 0.11608557 | GN76: =GR76 -> 0.11358557 | GO76: =GR76 -> 0.11358557 | GP76: =GR76 -> 0.11358557 | GQ76: =GR76 -> 0.11358557 | GR76: =GL76-0.0025 -> 0.11358557 | GT76: =GX76 -> 0.11358557 | GU76: =GX76 -> 0.11358557 | GV76: =GX76 -> 0.11358557 | GW76: =GX76 -> 0.11358557 | GX76: =GR76 -> 0.11358557 | GZ76: =HD76 -> 0.11358557 | HA76: =HD76 -> 0.11358557 | HB76: =HD76 -> 0.11358557 | HC76: =HD76 -> 0.11358557 | HD76: =GX76 -> 0.11358557 | HF76: =HJ76 -> 0.11358557 | HG76: =HJ76 -> 0.11358557 | HH76: =HJ76 -> 0.11358557 | HI76: =HJ76 -> 0.11358557 | HJ76: =HD76 -> 0.11358557
C77: =C54 -> Research & Development | DH77: =DH54/DH49 -> 0.015073396 | DI77: =DI54/DI49 -> 0.015838573 | DJ77: =DJ54/DJ49 -> 0.0064547875 | DK77: =DK54/DK49 -> 0.0068780647 | DL77: =DL54/DL49 -> 0.010844114 | DN77: =DN54/DN49 -> 0.012649487 | DO77: =DO54/DO49 -> 0.02543431 | DP77: =DP54/DP49 -> 0.024944589 | DQ77: =DQ54/DQ49 -> 0.019463263 | DR77: =DR54/DR49 -> 0.02075924 | DT77: =DT54/DT49 -> 0.019428464 | DU77: =DU54/DU49 -> 0.0242018 | DV77: =DV54/DV49 -> 0.015656389 | DW77: =DW54/DW49 -> 0.016667064 | DX77: =DX54/DX49 -> 0.018515102 | DZ77: =DZ54/DZ49 -> 0.021257996 | EA77: =EA54/EA49 -> 0.028712497 | EB77: =EB54/EB49 -> 0.061059832 | EC77: =EC54/EC49 -> 0.067707505 | ED77: =ED54/ED49 -> 0.04516145 | EF77: =EF54/EF49 -> 0.065827992 | EG77: =EG54/EG49 -> 0.068968274 | EH77: =EH54/EH49 -> 0.056778121 | EI77: =EI54/EI49 -> 0.048123716 | EJ77: =EJ54/EJ49 -> 0.059494475 | EL77: =EL54/EL49 -> 0.053891561 | EM77: =EM54/EM49 -> 0.051062845 | EN77: =EN54/EN49 -> 0.034780262 | EO77: =EO54/EO49 -> 0.045817476 | EP77: =EP54/EP49 -> 0.046157903 | ER77: =ER54/ER49 -> 0.048771121 | ES77: =ES54/ES49 -> 0.047938627 | ET77: =ET54/ET49 -> 0.045786062 | EU77: =EU54/EU49 -> 0.046331395 | EV77: =EV54/EV49 -> 0.047170154 | EX77: =EX54/EX49 -> 0.060588568 | EY77: =EY54/EY49 -> 0.049760106 | EZ77: =EZ54/EZ49 -> 0.046294669 | FA77: =FA54/FA49 -> 0.04826734 | FB77: =FB54/FB49 -> 0.05097672 | FD77: =EX77 -> 0.060588568 | FE77: =EY77 -> 0.049760106 | FF77: =EZ77 -> 0.046294669 | FG77: =FA77 -> 0.04826734 | FH77: =FH54/FH49 -> 0.050978667 | FJ77: =FN77 -> 0.050978667 | FK77: =FN77 -> 0.050978667 | FL77: =FN77 -> 0.050978667 | FM77: =FN77 -> 0.050978667 | FN77: =FH77 -> 0.050978667 | FP77: =FT77 -> 0.050978667 | FQ77: =FT77 -> 0.050978667 | FR77: =FT77 -> 0.050978667 | FS77: =FT77 -> 0.050978667 | FT77: =FN77 -> 0.050978667 | FV77: =FZ77 -> 0.050978667 | FW77: =FZ77 -> 0.050978667 | FX77: =FZ77 -> 0.050978667 | FY77: =FZ77 -> 0.050978667 | FZ77: =FT77 -> 0.050978667 | GB77: =GF77 -> 0.050978667 | GC77: =GF77 -> 0.050978667 | GD77: =GF77 -> 0.050978667 | GE77: =GF77 -> 0.050978667 | GF77: =FZ77 -> 0.050978667 | GH77: =GL77 -> 0.050978667 | GI77: =GL77 -> 0.050978667 | GJ77: =GL77 -> 0.050978667 | GK77: =GL77 -> 0.050978667 | GL77: =GF77 -> 0.050978667 | GN77: =GR77 -> 0.050978667 | GO77: =GR77 -> 0.050978667 | GP77: =GR77 -> 0.050978667 | GQ77: =GR77 -> 0.050978667 | GR77: =GL77 -> 0.050978667 | GT77: =GX77 -> 0.050978667 | GU77: =GX77 -> 0.050978667 | GV77: =GX77 -> 0.050978667 | GW77: =GX77 -> 0.050978667 | GX77: =GR77 -> 0.050978667 | GZ77: =HD77 -> 0.050978667 | HA77: =HD77 -> 0.050978667 | HB77: =HD77 -> 0.050978667 | HC77: =HD77 -> 0.050978667 | HD77: =GX77 -> 0.050978667 | HF77: =HJ77 -> 0.050978667 | HG77: =HJ77 -> 0.050978667 | HH77: =HJ77 -> 0.050978667 | HI77: =HJ77 -> 0.050978667 | HJ77: =HD77 -> 0.050978667
B78: EBITDA margin | EL78: =EL70/EL49 -> -0.051923918 | EM78: =EM70/EM49 -> -0.013960263 | EN78: =EN70/EN49 -> 0.021750003 | EO78: =EO70/EO49 -> 0.060095659 | EP78: =EP70/EP49 -> 0.0058768548 | ER78: =ER70/ER49 -> 0.02235023 | ES78: =ES70/ES49 -> 0.066072145 | ET78: =ET70/ET49 -> 0.079690628 | EU78: =EU70/EU49 -> 0.06902907 | EV78: =EV70/EV49 -> 0.0599607 | EX78: =EX70/EX49 -> 0.042074568 | EY78: =EY70/EY49 -> 0.058870567 | EZ78: =EZ70/EZ49 -> 0.065134161 | FA78: =FA70/FA49 -> 0.070358101 | FB78: =FB70/FB49 -> 0.059611017 | FD78: =FD70/FD49 -> 0.049220917 | FE78: =FE70/FE49 -> 0.060215846 | FF78: =FF70/FF49 -> 0.080454041 | FG78: =FG70/FG49 -> 0.088274226 | FH78: =FH70/FH49 -> 0.070316041 | FJ78: =FJ70/FJ49 -> 0.087512038 | FK78: =FK70/FK49 -> 0.084781541 | FL78: =FL70/FL49 -> 0.082756004 | FM78: =FM70/FM49 -> 0.081677059 | FN78: =FN70/FN49 -> 0.084069424 | FP78: =FP70/FP49 -> 0.10382366 | FQ78: =FQ70/FQ49 -> 0.10159455 | FR78: =FR70/FR49 -> 0.099969174 | FS78: =FS70/FS49 -> 0.099182739 | FT78: =FT70/FT49 -> 0.10105275 | FV78: =FV70/FV49 -> 0.12362149 | FW78: =FW70/FW49 -> 0.12169673 | FX78: =FX70/FX49 -> 0.12030921 | FY78: =FY70/FY49 -> 0.11969776 | FZ78: =FZ70/FZ49 -> 0.12125514 | GB78: =GB70/GB49 -> 0.14405055 | GC78: =GC70/GC49 -> 0.14206752 | GD78: =GD70/GD49 -> 0.14063257 | GE78: =GE70/GE49 -> 0.13998444 | GF78: =GF70/GF49 -> 0.14160491 | GH78: =GH70/GH49 -> 0.16292262 | GI78: =GI70/GI49 -> 0.16113372 | GJ78: =GJ70/GJ49 -> 0.15985113 | GK78: =GK70/GK49 -> 0.1593187 | GL78: =GL70/GL49 -> 0.16073645 | GN78: =GN70/GN49 -> 0.18425298 | GO78: =GO70/GO49 -> 0.18231682 | GP78: =GP70/GP49 -> 0.18091819 | GQ78: =GQ70/GQ49 -> 0.18030229 | GR78: =GR70/GR49 -> 0.18187088 | GT78: =GT70/GT49 -> 0.20120118 | GU78: =GU70/GU49 -> 0.1994176 | GV78: =GV70/GV49 -> 0.19813955 | GW78: =GW70/GW49 -> 0.19761956 | GX78: =GX70/GX49 -> 0.19902476 | GZ78: =GZ70/GZ49 -> 0.21979037 | HA78: =HA70/HA49 -> 0.21808029 | HB78: =HB70/HB49 -> 0.21686165 | HC78: =HC70/HC49 -> 0.21639395 | HD78: =HD70/HD49 -> 0.21771533 | HF78: =HF70/HF49 -> 0.19659979 | HG78: =HG70/HG49 -> 0.19659979 | HH78: =HH70/HH49 -> 0.19659979 | HI78: =HI70/HI49 -> 0.19659979 | HJ78: =HJ70/HJ49 -> 0.19659979
B79: Operating margin | DH79: =DH56/DH49 -> 0.087381549 | DI79: =DI56/DI49 -> 0.094027692 | DJ79: =DJ56/DJ49 -> 0.10423179 | DK79: =DK56/DK49 -> 0.11279503 | DL79: =DL56/DL49 -> 0.10023849 | DN79: =DN56/DN49 -> 0.14289003 | DO79: =DO56/DO49 -> 0.10681034 | DP79: =DP56/DP49 -> 0.095651177 | DQ79: =DQ56/DQ49 -> 0.074437624 | DR79: =DR56/DR49 -> 0.10392584 | DT79: =DT56/DT49 -> 0.00576252 | DU79: =DU56/DU49 -> -0.1800476 | DV79: =DV56/DV49 -> 0.081255381 | DW79: =DW56/DW49 -> 0.05427907 | DX79: =DX56/DX49 -> 0.0044617143 | DZ79: =DZ56/DZ49 -> 0.020427064 | EA79: =EA56/EA49 -> -0.021113338 | EB79: =EB56/EB49 -> -0.093786056 | EC79: =EC56/EC49 -> -0.13711704 | ED79: =ED56/ED49 -> -0.059525653 | EF79: =EF56/EF49 -> -0.23533528 | EG79: =EG56/EG49 -> -0.19504765 | EH79: =EH56/EH49 -> -0.15961082 | EI79: =EI56/EI49 -> -0.076738402 | EJ79: =EJ56/EJ49 -> -0.16316153 | EL79: =EL56/EL49 -> -0.11703105 | EM79: =EM56/EM49 -> -0.083421251 | EN79: =EN56/EN49 -> -0.039143425 | EO79: =EO56/EO49 -> -0.0022757663 | EP79: =EP56/EP49 -> -0.058509946 | ER79: =ER56/ER49 -> -0.039362519 | ES79: =ES56/ES49 -> 0.0068388226 | ET79: =ET56/ET49 -> 0.020461912 | EU79: =EU56/EU49 -> 0.014401163 | EV79: =EV56/EV49 -> 0.001341274 | EX79: =EX56/EX49 -> -0.014050644 | EY79: =EY56/EY49 -> 0.005807092 | EZ79: =EZ56/EZ49 -> 0.020042919 | FA79: =FA56/FA49 -> 0.023836567 | FB79: =FB56/FB49 -> 0.0096090919 | FD79: =FD56/FD49 -> -0.0040506442 | FE79: =FE56/FE49 -> 0.010505598 | FF79: =FF56/FF49 -> 0.03343038 | FG79: =FG56/FG49 -> 0.042816953 | FH79: =FH56/FH49 -> 0.021599788 | FJ79: =FJ56/FJ49 -> 0.040099788 | FK79: =FK56/FK49 -> 0.040099788 | FL79: =FL56/FL49 -> 0.040099788 | FM79: =FM56/FM49 -> 0.040099788 | FN79: =FN56/FN49 -> 0.040099788 | FP79: =FP56/FP49 -> 0.060099788 | FQ79: =FQ56/FQ49 -> 0.060099788 | FR79: =FR56/FR49 -> 0.060099788 | FS79: =FS56/FS49 -> 0.060099788 | FT79: =FT56/FT49 -> 0.060099788 | FV79: =FV56/FV49 -> 0.082099788 | FW79: =FW56/FW49 -> 0.082099788 | FX79: =FX56/FX49 -> 0.082099788 | FY79: =FY56/FY49 -> 0.082099788 | FZ79: =FZ56/FZ49 -> 0.082099788 | GB79: =GB56/GB49 -> 0.10209979 | GC79: =GC56/GC49 -> 0.10209979 | GD79: =GD56/GD49 -> 0.10209979 | GE79: =GE56/GE49 -> 0.10209979 | GF79: =GF56/GF49 -> 0.10209979 | GH79: =GH56/GH49 -> 0.12209979 | GI79: =GI56/GI49 -> 0.12209979 | GJ79: =GJ56/GJ49 -> 0.12209979 | GK79: =GK56/GK49 -> 0.12209979 | GL79: =GL56/GL49 -> 0.12209979 | GN79: =GN56/GN49 -> 0.14209979 | GO79: =GO56/GO49 -> 0.14209979 | GP79: =GP56/GP49 -> 0.14209979 | GQ79: =GQ56/GQ49 -> 0.14209979 | GR79: =GR56/GR49 -> 0.14209979 | GT79: =GT56/GT49 -> 0.15959979 | GU79: =GU56/GU49 -> 0.15959979 | GV79: =GV56/GV49 -> 0.15959979 | GW79: =GW56/GW49 -> 0.15959979 | GX79: =GX56/GX49 -> 0.15959979 | GZ79: =GZ56/GZ49 -> 0.17809979 | HA79: =HA56/HA49 -> 0.17809979 | HB79: =HB56/HB49 -> 0.17809979 | HC79: =HC56/HC49 -> 0.17809979 | HD79: =HD56/HD49 -> 0.17809979 | HF79: =HF56/HF49 -> 0.19659979 | HG79: =HG56/HG49 -> 0.19659979 | HH79: =HH56/HH49 -> 0.19659979 | HI79: =HI56/HI49 -> 0.19659979 | HJ79: =HJ56/HJ49 -> 0.19659979
B80: =B60 -> Income before taxes | DH80: =DH60/DH$49 -> 0.064944894 | DI80: =DI60/DI$49 -> 0.071428571 | DJ80: =DJ60/DJ$49 -> 0.077558759 | DK80: =DK60/DK$49 -> 0.094253024 | DL80: =DL60/DL$49 -> 0.077780588 | DN80: =DN60/DN$49 -> 0.069702962 | DO80: =DO60/DO$49 -> 0.084079714 | DP80: =DP60/DP$49 -> 0.094046163 | DQ80: =DQ60/DQ$49 -> 0.075504361 | DR80: =DR60/DR$49 -> 0.081028789 | DT80: =DT60/DT$49 -> 0.0001414694 | DU80: =DU60/DU$49 -> -0.16911367 | DV80: =DV60/DV$49 -> 0.061748669 | DW80: =DW60/DW$49 -> 0.070374691 | DX80: =DX60/DX$49 -> 0.0043177155 | DZ80: =DZ60/DZ$49 -> -0.031774471 | EA80: =EA60/EA$49 -> -0.027118728 | EB80: =EB60/EB$49 -> -0.10373331 | EC80: =EC60/EC$49 -> -0.15809022 | ED80: =ED60/ED$49 -> -0.081423991 | EF80: =EF60/EF$49 -> -0.24500508 | EG80: =EG60/EG$49 -> -0.20568952 | EH80: =EH60/EH$49 -> -0.16049603 | EI80: =EI60/EI$49 -> -0.070545402 | EJ80: =EJ60/EJ$49 -> -0.16653392 | EL80: =EL60/EL$49 -> -0.10717097 | EM80: =EM60/EM$49 -> -0.061272691 | EN80: =EN60/EN$49 -> -0.021085328 | EO80: =EO60/EO$49 -> 0.01886186 | EP80: =EP60/EP$49 -> -0.040527818 | ER80: =ER60/ER$49 -> -0.020890937 | ES80: =ES60/ES$49 -> 0.024613683 | ET80: =ET60/ET$49 -> 0.040411383 | EU80: =EU60/EU$49 -> 0.027616279 | EV80: =EV60/EV$49 -> 0.018646131 | EX80: =EX60/EX$49 -> -0.0011485702 | EY80: =EY60/EY$49 -> 0.015799923 | EZ80: =EZ60/EZ$49 -> 0.02337098 | FA80: =FA60/FA$49 -> 0.029137088 | FB80: =FB60/FB$49 -> 0.017326338 | FD80: =FD60/FD$49 -> -0.00045963323 | FE80: =FE60/FE$49 -> 0.013928739 | FF80: =FF60/FF$49 -> 0.03668699 | FG80: =FG60/FG$49 -> 0.046173434 | FH80: =FH60/FH$49 -> 0.025001214 | FJ80: =FJ60/FJ$49 -> 0.045879042 | FK80: =FK60/FK$49 -> 0.046034603 | FL80: =FL60/FL$49 -> 0.045967618 | FM80: =FM60/FM$49 -> 0.036735047 | FN80: =FN60/FN$49 -> 0.043519153 | FP80: =FP60/FP$49 -> 0.058729844 | FQ80: =FQ60/FQ$49 -> 0.059374613 | FR80: =FR60/FR$49 -> 0.059698869 | FS80: =FS60/FS$49 -> 0.060024455 | FT80: =FT60/FT$49 -> 0.059481062 | FV80: =FV60/FV$49 -> 0.071735406 | FW80: =FW60/FW$49 -> 0.073755759 | FX80: =FX60/FX$49 -> 0.074416839 | FY80: =FY60/FY$49 -> 0.074920426 | FZ80: =FZ60/FZ$49 -> 0.073767001 | GB80: =GB60/GB$49 -> 0.09490587 | GC80: =GC60/GC$49 -> 0.096048751 | GD80: =GD60/GD$49 -> 0.096741908 | GE80: =GE60/GE$49 -> 0.097325133 | GF80: =GF60/GF$49 -> 0.096300934 | GH80: =GH60/GH$49 -> 0.11755674 | GI80: =GI60/GI$49 -> 0.11867388 | GJ80: =GJ60/GJ$49 -> 0.11937473 | GK80: =GK60/GK$49 -> 0.12661373 | GL80: =GL60/GL$49 -> 0.12069841 | GN80: =GN60/GN$49 -> 0.14619803 | GO80: =GO60/GO$49 -> 0.14698287 | GP80: =GP60/GP$49 -> 0.1474733 | GQ80: =GQ60/GQ$49 -> 0.14808354 | GR80: =GR60/GR$49 -> 0.14721912 | GT80: =GT60/GT$49 -> 0.1668445 | GU80: =GU60/GU$49 -> 0.16755973 | GV80: =GV60/GV$49 -> 0.16802439 | GW80: =GW60/GW$49 -> 0.16867435 | GX80: =GX60/GX$49 -> 0.16780914 | GZ80: =GZ60/GZ$49 -> 0.18882818 | HA80: =HA60/HA$49 -> 0.18946379 | HB80: =HB60/HB$49 -> 0.18989719 | HC80: =HC60/HC$49 -> 0.19058788 | HD80: =HD60/HD$49 -> 0.18972608 | HF80: =HF60/HF$49 -> 0.21120287 | HG80: =HG60/HG$49 -> 0.21173901 | HH80: =HH60/HH$49 -> 0.21212702 | HI80: =HI60/HI$49 -> 0.21285192 | HJ80: =HJ60/HJ$49 -> 0.21200965
C81: =C61 -> Income tax | DH81: =DH61/DH60 -> 0.10633649 | DI81: =DI61/DI60 -> 0.077082042 | DJ81: =DJ61/DJ60 -> 0.13845867 | DK81: =DK61/DK60 -> 0.23903996 | DL81: =DL61/DL60 -> 0.15219512 | DN81: =DN61/DN60 -> -0.074602222 | DO81: =DO61/DO60 -> 0.15481759 | DP81: =DP61/DP60 -> 0.23455912 | DQ81: =DQ61/DQ60 -> -0.35357541 | DR81: =DR61/DR60 -> 0.0085428804 | DT81: =DT61/DT60 -> 147.26667 | DU81: =DU61/DU60 -> 0.71860766 | DV81: =DV61/DV60 -> 0.10134263 | DW81: =DW61/DW60 -> -0.8659073 | DX81: =DX61/DX60 -> -7.9489317 | DZ81: =DZ61/DZ60 -> -0.26586761 | EA81: =EA61/EA60 -> 0.73826113 | EB81: =EB61/EB60 -> 0.22419957 | EC81: =EC61/EC60 -> 0.12300649 | ED81: =ED61/ED60 -> 0.17060554 | EF81: =EF61/EF60 -> 0.13073466 | EG81: =EG61/EG60 -> 0.22277074 | EH81: =EH61/EH60 -> 0.13406551 | EI81: =EI61/EI60 -> 0.28983137 | EJ81: =EJ61/EJ60 -> 0.17777752 | EL81: =EL61/EL60 -> 0.1995104 | EM81: =EM61/EM60 -> 0.25649856 | EN81: =EN61/EN60 -> 0.91604245 | EO81: =EO61/EO60 -> -0.32719836 | EP81: =EP61/EP60 -> 0.38109934 | ER81: =ER61/ER60 -> 0.18995098 | ES81: =ES61/ES60 -> -0.092615461 | ET81: =ET61/ET60 -> -0.02211737 | EU81: =EU61/EU60 -> -0.16947368 | EV81: =EV61/EV60 -> -0.15831777 | EX81: =EX61/EX60 -> -1.3782383 | EY81: =EY61/EY60 -> -0.25270506 | EZ81: =EZ61/EZ60 -> 0.16860333 | FA81: =FA61/FA60 -> -0.45569392 | FB81: =FB61/FB60 -> -0.17798762 | FD81: =FH81 -> 0 | FE81: =FH81 -> 0 | FF81: =FH81 -> 0 | FG81: =FH81 -> 0 | FH81: 0 | FJ81: =FN81 -> 0 | FK81: =FN81 -> 0 | FL81: =FN81 -> 0 | FM81: =FN81 -> 0 | FN81: =FH81 -> 0 | FP81: =FT81 -> 0 | FQ81: =FT81 -> 0 | FR81: =FT81 -> 0 | FS81: =FT81 -> 0 | FT81: 0 | FV81: =FZ81 -> 0.2 | FW81: =FZ81 -> 0.2 | FX81: =FZ81 -> 0.2 | FY81: =FZ81 -> 0.2 | FZ81: 0.2 | GB81: =GF81 -> 0.2 | GC81: =GF81 -> 0.2 | GD81: =GF81 -> 0.2 | GE81: =GF81 -> 0.2 | GF81: =FZ81 -> 0.2 | GH81: =GL81 -> 0.2 | GI81: =GL81 -> 0.2 | GJ81: =GL81 -> 0.2 | GK81: =GL81 -> 0.2 | GL81: =GF81 -> 0.2 | GN81: =GR81 -> 0.2 | GO81: =GR81 -> 0.2 | GP81: =GR81 -> 0.2 | GQ81: =GR81 -> 0.2 | GR81: =GL81 -> 0.2 | GT81: =GX81 -> 0.2 | GU81: =GX81 -> 0.2 | GV81: =GX81 -> 0.2 | GW81: =GX81 -> 0.2 | GX81: =GR81 -> 0.2 | GZ81: =HD81 -> 0.2 | HA81: =HD81 -> 0.2 | HB81: =HD81 -> 0.2 | HC81: =HD81 -> 0.2 | HD81: =GX81 -> 0.2 | HF81: =HJ81 -> 0.2 | HG81: =HJ81 -> 0.2 | HH81: =HJ81 -> 0.2 | HI81: =HJ81 -> 0.2 | HJ81: =HD81 -> 0.2
B82: Net margin | DH82: =DH62/DH49 -> 0.058038882 | DI82: =DI62/DI49 -> 0.065922711 | DJ82: =DJ62/DJ49 -> 0.066820076 | DK82: =DK62/DK49 -> 0.071722785 | DL82: =DL62/DL49 -> 0.065942762 | DN82: =DN62/DN49 -> 0.074902958 | DO82: =DO62/DO49 -> 0.071062696 | DP82: =DP62/DP49 -> 0.071986778 | DQ82: =DQ62/DQ49 -> 0.10220085 | DR82: =DR62/DR49 -> 0.08033657 | DT82: =DT62/DT49 -> -0.020692257 | DU82: =DU62/DU49 -> -0.047587293 | DV82: =DV62/DV49 -> 0.055490896 | DW82: =DW62/DW49 -> 0.13131265 | DX82: =DX62/DX49 -> 0.038638941 | DZ82: =DZ62/DZ49 -> -0.040222274 | EA82: =EA62/EA49 -> -0.007098025 | EB82: =EB62/EB49 -> -0.080476347 | EC82: =EC62/EC49 -> -0.1386441 | ED82: =ED62/ED49 -> -0.067532607 | EF82: =EF62/EF49 -> -0.21297442 | EG82: =EG62/EG49 -> -0.15986792 | EH82: =EH62/EH49 -> -0.13897905 | EI82: =EI62/EI49 -> -0.050099131 | EJ82: =EJ62/EJ49 -> -0.13692793 | EL82: =EL62/EL49 -> -0.085789244 | EM82: =EM62/EM49 -> -0.045556335 | EN82: =EN62/EN49 -> -0.0017702726 | EO82: =EO62/EO49 -> 0.025033429 | EP82: =EP62/EP49 -> -0.025082693 | ER82: =ER62/ER49 -> -0.016922683 | ES82: =ES62/ES49 -> 0.02689329 | ET82: =ET62/ET49 -> 0.041305177 | EU82: =EU62/EU49 -> 0.032296512 | EV82: =EV62/EV$49 -> 0.021598145 | EX82: =EX62/EX49 -> -0.0027315738 | EY82: =EY62/EY49 -> 0.019792643 | EZ82: =EZ62/EZ49 -> 0.019430555 | FA82: =FA62/FA49 -> 0.042414682 | FB82: =FB62/FB$49 -> 0.020410212 | FD82: =FD62/FD$49 -> -0.00045963323 | FE82: =FE62/FE$49 -> 0.013928739 | FF82: =FF62/FF$49 -> 0.03668699 | FG82: =FG62/FG$49 -> 0.046173434 | FH82: =FH62/FH$49 -> 0.025001214 | FJ82: =FJ62/FJ$49 -> 0.045879042 | FK82: =FK62/FK$49 -> 0.046034603 | FL82: =FL62/FL$49 -> 0.045967618 | FM82: =FM62/FM$49 -> 0.036735047 | FN82: =FN62/FN$49 -> 0.043519153 | FP82: =FP62/FP$49 -> 0.058729844 | FQ82: =FQ62/FQ$49 -> 0.059374613 | FR82: =FR62/FR$49 -> 0.059698869 | FS82: =FS62/FS$49 -> 0.060024455 | FT82: =FT62/FT$49 -> 0.059481062 | FV82: =FV62/FV$49 -> 0.057388324 | FW82: =FW62/FW$49 -> 0.059004608 | FX82: =FX62/FX$49 -> 0.059533471 | FY82: =FY62/FY$49 -> 0.059936341 | FZ82: =FZ62/FZ$49 -> 0.059013601 | GB82: =GB62/GB$49 -> 0.075924696 | GC82: =GC62/GC$49 -> 0.076839 | GD82: =GD62/GD$49 -> 0.077393526 | GE82: =GE62/GE$49 -> 0.077860106 | GF82: =GF62/GF$49 -> 0.077040747 | GH82: =GH62/GH$49 -> 0.094045395 | GI82: =GI62/GI$49 -> 0.094939104 | GJ82: =GJ62/GJ$49 -> 0.095499783 | GK82: =GK62/GK$49 -> 0.10129098 | GL82: =GL62/GL$49 -> 0.096558726 | GN82: =GN62/GN$49 -> 0.11695843 | GO82: =GO62/GO$49 -> 0.1175863 | GP82: =GP62/GP$49 -> 0.11797864 | GQ82: =GQ62/GQ$49 -> 0.11846683 | GR82: =GR62/GR$49 -> 0.1177753 | GT82: =GT62/GT$49 -> 0.1334756 | GU82: =GU62/GU$49 -> 0.13404778 | GV82: =GV62/GV$49 -> 0.13441951 | GW82: =GW62/GW$49 -> 0.13493948 | GX82: =GX62/GX$49 -> 0.13424731 | GZ82: =GZ62/GZ$49 -> 0.15106255 | HA82: =HA62/HA$49 -> 0.15157103 | HB82: =HB62/HB$49 -> 0.15191775 | HC82: =HC62/HC$49 -> 0.15247031 | HD82: =HD62/HD$49 -> 0.15178086 | HF82: =HF62/HF$49 -> 0.16896229 | HG82: =HG62/HG$49 -> 0.16939121 | HH82: =HH62/HH$49 -> 0.16970162 | HI82: =HI62/HI$49 -> 0.17028154 | HJ82: =HJ62/HJ$49 -> 0.16960772
B84: Growth Analysis
B85: =B49 -> Net sales | DN85: =DN49/DH49-1 -> 0.50697696 | DO85: =DO49/DI49-1 -> 0.50138754 | DP85: =DP49/DJ49-1 -> 0.51487785 | DQ85: =DQ49/DK49-1 -> 0.39742399 | DR85: =DR49/DL49-1 -> 0.47730722 | DT85: =DT49/DN49-1 -> 0.10936732 | DU85: =DU49/DO49-1 -> -0.14487824 | DV85: =DV49/DP49-1 -> 0.19844849 | DW85: =DW49/DQ49-1 -> 0.17899652 | DX85: =DX49/DR49-1 -> 0.087121787 | DZ85: =DZ49/DT49-1 -> 0.089625578 | EA85: =EA49/DU49-1 -> 0.39949642 | EB85: =EB49/DV49-1 -> -0.032715794 | EC85: =EC49/DW49-1 -> -0.0021032247 | ED85: =ED49/DX49-1 -> 0.089731532 | EF85: =EF49/DZ49-1 -> 0.014160456 | EG85: =EG49/EA49-1 -> 0.027504847 | EH85: =EH49/EB49-1 -> 0.061331795 | EI85: =EI49/EC49-1 -> 0.10317978 | EJ85: =EJ49/ED49-1 -> 0.052441625 | EL85: =EL49/EF49-1 -> 0.17112888 | EM85: =EM49/EG49-1 -> 0.1746594 | EN85: =EN49/EH49-1 -> 0.17993198 | EO85: =EO49/EI49-1 -> 0.12145921 | EP85: =EP49/EJ49-1 -> 0.16070336 | ER85: =ER49/EL49-1 -> 0.13860953 | ES85: =ES49/EM49-1 -> 0.11969343 | ET85: =ET49/EN49-1 -> 0.1044395 | EU85: =EU49/EO49-1 -> 0.10573956 | EV85: =EV49/EP49-1 -> 0.11649424 | EX85: =EX49/ER49-1 -> 0.075492832 | EY85: =EY49/ES49-1 -> 0.10229663 | EZ85: =EZ49/ET49-1 -> 0.11901158 | FA85: =FA49/EU49-1 -> 0.10563953 | FB85: =FB49/EV49-1 -> 0.10107393 | FD85: =FD49/EX49-1 -> 0.098710781 | FE85: =FE49/EY49-1 -> 0.081290714 | FF85: =FF49/EZ49-1 -> 0.09469723 | FG85: =FG49/FA49-1 -> 0.11000652 | FH85: =FH49/FB49-1 -> 0.096284926 | FJ85: =FJ49/FD49-1 -> 0.097550017 | FK85: =FK49/FE49-1 -> 0.097815935 | FL85: =FL49/FF49-1 -> 0.097824438 | FM85: =FM49/FG49-1 -> 0.097886489 | FN85: =FN49/FH49-1 -> 0.097775234 | FP85: =FP49/FJ49-1 -> 0.097744831 | FQ85: =FQ49/FK49-1 -> 0.098000242 | FR85: =FR49/FL49-1 -> 0.0980084 | FS85: =FS49/FM49-1 -> 0.098067959 | FT85: =FT49/FN49-1 -> 0.097961148 | FV85: =FZ85 -> 0.092961148 | FW85: =FZ85 -> 0.092961148 | FX85: =FZ85 -> 0.092961148 | FY85: =FZ85 -> 0.092961148 | FZ85: =FT85-0.005 -> 0.092961148 | GB85: =GF85 -> 0.087961148 | GC85: =GF85 -> 0.087961148 | GD85: =GF85 -> 0.087961148 | GE85: =GF85 -> 0.087961148 | GF85: =FZ85-0.005 -> 0.087961148 | GH85: =GL85 -> 0.080961148 | GI85: =GL85 -> 0.080961148 | GJ85: =GL85 -> 0.080961148 | GK85: =GL85 -> 0.080961148 | GL85: =GF85-0.007 -> 0.080961148 | GN85: =GR85 -> 0.075961148 | GO85: =GR85 -> 0.075961148 | GP85: =GR85 -> 0.075961148 | GQ85: =GR85 -> 0.075961148 | GR85: =GL85-0.005 -> 0.075961148 | GT85: =GX85 -> 0.070961148 | GU85: =GX85 -> 0.070961148 | GV85: =GX85 -> 0.070961148 | GW85: =GX85 -> 0.070961148 | GX85: =GR85-0.005 -> 0.070961148 | GZ85: =HD85 -> 0.065961148 | HA85: =HD85 -> 0.065961148 | HB85: =HD85 -> 0.065961148 | HC85: =HD85 -> 0.065961148 | HD85: =GX85-0.005 -> 0.065961148 | HF85: =HJ85 -> 0.060961148 | HG85: =HJ85 -> 0.060961148 | HH85: =HJ85 -> 0.060961148 | HI85: =HJ85 -> 0.060961148 | HJ85: =HD85-0.005 -> 0.060961148
C86: =C50 -> Cost of products sold | DN86: =DN50/DH50-1 -> 0.34169435 | DO86: =DO50/DI50-1 -> 0.41732051 | DP86: =DP50/DJ50-1 -> 0.46403807 | DQ86: =DQ50/DK50-1 -> 0.44662636 | DR86: =DR50/DL50-1 -> 0.41825723 | DT86: =DT50/DN50-1 -> 0.23108828 | DU86: =DU50/DO50-1 -> 0.11799723 | DV86: =DV50/DP50-1 -> 0.32576152 | DW86: =DW50/DQ50-1 -> 0.20368777 | DX86: =DX50/DR50-1 -> 0.21963357 | DZ86: =DZ50/DT50-1 -> 0.15083555 | EA86: =EA50/DU50-1 -> 0.15319394 | EB86: =EB50/DV50-1 -> -0.029448437 | EC86: =EC50/DW50-1 -> 0.10326214 | ED86: =ED50/DX50-1 -> 0.088990737 | EF86: =EF50/DZ50-1 -> 0.078997961 | EG86: =EG50/EA50-1 -> 0.1215793 | EH86: =EH50/EB50-1 -> 0.083130043 | EI86: =EI50/EC50-1 -> 0.018566026 | EJ86: =EJ50/ED50-1 -> 0.074068418 | EL86: =EL50/EF50-1 -> 0.046825225 | EM86: =EM50/EG50-1 -> 0.077353716 | EN86: =EN50/EH50-1 -> 0.12999094 | EO86: =EO50/EI50-1 -> 0.076065225 | EP86: =EP50/EJ50-1 -> 0.082607244 | ER86: =ER50/EL50-1 -> 0.10203345 | ES86: =ES50/EM50-1 -> 0.055590036 | ET86: =ET50/EN50-1 -> 0.034839014 | EU86: =EU50/EO50-1 -> 0.080328166 | EV86: =EV50/EP50-1 -> 0.067479941 | EX86: =EX50/ER50-1 -> 0.047012847 | EY86: =EY50/ES50-1 -> 0.14084458 | EZ86: =EZ50/ET50-1 -> 0.16704276 | FA86: =FA50/EU50-1 -> 0.13758753 | FB86: =FB50/EV50-1 -> 0.12364161 | FD86: =FD50/EX50-1 -> 0.078078951 | FE86: =FE50/EY50-1 -> 0.059495863 | FF86: =FF50/EZ50-1 -> 0.074621171 | FG86: =FG50/FA50-1 -> 0.089283599 | FH86: =FH50/FB50-1 -> 0.075400901 | FJ86: =FJ50/FD50-1 -> 0.086227202 | FK86: =FK50/FE50-1 -> 0.061697181 | FL86: =FL50/FF50-1 -> 0.060633029 | FM86: =FM50/FG50-1 -> 0.080131732 | FN86: =FN50/FH50-1 -> 0.071866772 | FP86: =FP50/FJ50-1 -> 0.07121086 | FQ86: =FQ50/FK50-1 -> 0.071460098 | FR86: =FR50/FL50-1 -> 0.071468059 | FS86: =FS50/FM50-1 -> 0.071526178 | FT86: =FT50/FN50-1 -> 0.071421949 | FV86: =FV50/FP50-1 -> 0.065888422 | FW86: =FW50/FQ50-1 -> 0.065888422 | FX86: =FX50/FR50-1 -> 0.065888422 | FY86: =FY50/FS50-1 -> 0.065888422 | FZ86: =FZ50/FT50-1 -> 0.065888422 | GB86: =GB50/FV50-1 -> 0.060327792 | GC86: =GC50/FW50-1 -> 0.060327792 | GD86: =GD50/FX50-1 -> 0.060327792 | GE86: =GE50/FY50-1 -> 0.060327792 | GF86: =GF50/FZ50-1 -> 0.060327792 | GH86: =GH50/GB50-1 -> 0.052790063 | GI86: =GI50/GC50-1 -> 0.052790063 | GJ86: =GJ50/GD50-1 -> 0.052790063 | GK86: =GK50/GE50-1 -> 0.052790063 | GL86: =GL50/GF50-1 -> 0.052790063 | GN86: =GN50/GH50-1 -> 0.047170039 | GO86: =GO50/GI50-1 -> 0.047170039 | GP86: =GP50/GJ50-1 -> 0.047170039 | GQ86: =GQ50/GK50-1 -> 0.047170039 | GR86: =GR50/GL50-1 -> 0.047170039 | GT86: =GT50/GN50-1 -> 0.041515922 | GU86: =GU50/GO50-1 -> 0.041515922 | GV86: =GV50/GP50-1 -> 0.041515922 | GW86: =GW50/GQ50-1 -> 0.041515922 | GX86: =GX50/GR50-1 -> 0.041515922 | GZ86: =GZ50/GT50-1 -> 0.035824818 | HA86: =HA50/GU50-1 -> 0.035824818 | HB86: =HB50/GV50-1 -> 0.035824818 | HC86: =HC50/GW50-1 -> 0.035824818 | HD86: =HD50/GX50-1 -> 0.035824818 | HF86: =HF50/GZ50-1 -> 0.030093501 | HG86: =HG50/HA50-1 -> 0.030093501 | HH86: =HH50/HB50-1 -> 0.030093501 | HI86: =HI50/HC50-1 -> 0.030093501 | HJ86: =HJ50/HD50-1 -> 0.030093501
B87: =B51 -> Gross profit | DN87: =DN51/DH51-1 -> 0.72563455 | DO87: =DO51/DI51-1 -> 0.60386505 | DP87: =DP51/DJ51-1 -> 0.57272362 | DQ87: =DQ51/DK51-1 -> 0.34523457 | DR87: =DR51/DL51-1 -> 0.54666248 | DT87: =DT51/DN51-1 -> -0.015833599 | DU87: =DU51/DO51-1 -> -0.42805212 | DV87: =DV51/DP51-1 -> 0.063601668 | DW87: =DW51/DQ51-1 -> 0.15083228 | DX87: =DX51/DR51-1 -> -0.055594505 | DZ87: =DZ51/DT51-1 -> 0.010869331 | EA87: =EA51/DU51-1 -> 0.91812469 | EB87: =EB51/DV51-1 -> -0.037029502 | EC87: =EC51/DW51-1 -> -0.12780882 | ED87: =ED51/DX51-1 -> 0.09076189 | EF87: =EF51/DZ51-1 -> -0.080814115 | EG87: =EG51/EA51-1 -> -0.091587706 | EH87: =EH51/EB51-1 -> 0.03232622 | EI87: =EI51/EC51-1 -> 0.23087208 | EJ87: =EJ51/ED51-1 -> 0.022410179 | EL87: =EL51/EF51-1 -> 0.38486712 | EM87: =EM51/EG51-1 -> 0.3267485 | EN87: =EN51/EH51-1 -> 0.24965579 | EO87: =EO51/EI51-1 -> 0.17814815 | EP87: =EP51/EJ51-1 -> 0.27462869 | ER87: =ER51/EL51-1 -> 0.1861498 | ES87: =ES51/EM51-1 -> 0.20105338 | ET87: =ET51/EN51-1 -> 0.1923054 | EU87: =EU51/EO51-1 -> 0.13472415 | EV87: =EV51/EP51-1 -> 0.17722391 | EX87: =EX51/ER51-1 -> 0.10988499 | EY87: =EY51/ES51-1 -> 0.059297077 | EZ87: =EZ51/ET51-1 -> 0.066383616 | FA87: =FA51/EU51-1 -> 0.070946069 | FB87: =FB51/EV51-1 -> 0.075718805 | FD87: =FD51/EX51-1 -> 0.12221422 | FE87: =FE51/EY51-1 -> 0.10747406 | FF87: =FF51/EZ51-1 -> 0.11877106 | FG87: =FG51/FA51-1 -> 0.13391063 | FH87: =FH51/FB51-1 -> 0.12079373 | FJ87: =FJ51/FD51-1 -> 0.10994149 | FK87: =FK51/FE51-1 -> 0.13932756 | FL87: =FL51/FF51-1 -> 0.14066187 | FM87: =FM51/FG51-1 -> 0.11756074 | FN87: =FN51/FH51-1 -> 0.12694912 | FP87: =FP51/FJ51-1 -> 0.12616269 | FQ87: =FQ51/FK51-1 -> 0.12642471 | FR87: =FR51/FL51-1 -> 0.12643308 | FS87: =FS51/FM51-1 -> 0.12649418 | FT87: =FT51/FN51-1 -> 0.1263846 | FV87: =FV51/FP51-1 -> 0.12054119 | FW87: =FW51/FQ51-1 -> 0.12054119 | FX87: =FX51/FR51-1 -> 0.12054119 | FY87: =FY51/FS51-1 -> 0.12054119 | FZ87: =FZ51/FT51-1 -> 0.12054119 | GB87: =GB51/FV51-1 -> 0.11473929 | GC87: =GC51/FW51-1 -> 0.11473929 | GD87: =GD51/FX51-1 -> 0.11473929 | GE87: =GE51/FY51-1 -> 0.11473929 | GF87: =GF51/FZ51-1 -> 0.11473929 | GH87: =GH51/GB51-1 -> 0.10692788 | GI87: =GI51/GC51-1 -> 0.10692788 | GJ87: =GJ51/GD51-1 -> 0.10692788 | GK87: =GK51/GE51-1 -> 0.10692788 | GL87: =GL51/GF51-1 -> 0.10692788 | GN87: =GN51/GH51-1 -> 0.10120145 | GO87: =GO51/GI51-1 -> 0.10120145 | GP87: =GP51/GJ51-1 -> 0.10120145 | GQ87: =GQ51/GK51-1 -> 0.10120145 | GR87: =GR51/GL51-1 -> 0.10120145 | GT87: =GT51/GN51-1 -> 0.095508319 | GU87: =GU51/GO51-1 -> 0.095508319 | GV87: =GV51/GP51-1 -> 0.095508319 | GW87: =GW51/GQ51-1 -> 0.095508319 | GX87: =GX51/GR51-1 -> 0.095508319 | GZ87: =GZ51/GT51-1 -> 0.089846252 | HA87: =HA51/GU51-1 -> 0.089846252 | HB87: =HB51/GV51-1 -> 0.089846252 | HC87: =HC51/GW51-1 -> 0.089846252 | HD87: =HD51/GX51-1 -> 0.089846252 | HF87: =HF51/GZ51-1 -> 0.084213205 | HG87: =HG51/HA51-1 -> 0.084213205 | HH87: =HH51/HB51-1 -> 0.084213205 | HI87: =HI51/HC51-1 -> 0.084213205 | HJ87: =HJ51/HD51-1 -> 0.084213205
C88: =C52 -> G&A | DN88: =DN52/DH52-1 -> 0.49914469 | DO88: =DO52/DI52-1 -> 0.5052249 | DP88: =DP52/DJ52-1 -> 0.502335 | DQ88: =DQ52/DK52-1 -> 0.38539574 | DR88: =DR52/DL52-1 -> 0.46764101 | DT88: =DT52/DN52-1 -> 0.44724956 | DU88: =DU52/DO52-1 -> 0.35250744 | DV88: =DV52/DP52-1 -> 0.1461743 | DW88: =DW52/DQ52-1 -> 0.28358588 | DX88: =DX52/DR52-1 -> 0.29750992 | DZ88: =DZ52/DT52-1 -> -0.070039422 | EA88: =EA52/DU52-1 -> 0.13403048 | EB88: =EB52/DV52-1 -> 0.31780159 | EC88: =EC52/DW52-1 -> 0.21212121 | ED88: =ED52/DX52-1 -> 0.15106518 | EF88: =EF52/DZ52-1 -> 0.64783807 | EG88: =EG52/EA52-1 -> 0.33531066 | EH88: =EH52/EB52-1 -> 0.24423506 | EI88: =EI52/EC52-1 -> 0.13014911 | EJ88: =EJ52/ED52-1 -> 0.31062748 | EL88: =EL52/EF52-1 -> 0.11629901 | EM88: =EM52/EG52-1 -> 0.06526728 | EN88: =EN52/EH52-1 -> 0.00073734556 | EO88: =EO52/EI52-1 -> -0.014101348 | EP88: =EP52/EJ52-1 -> 0.040854639 | ER88: =ER52/EL52-1 -> -0.057401291 | ES88: =ES52/EM52-1 -> -0.069648398 | ET88: =ET52/EN52-1 -> -0.03325567 | EU88: =EU52/EO52-1 -> 0.038685124 | EV88: =EV52/EP52-1 -> -0.031553301 | EX88: =EX52/ER52-1 -> -0.021086731 | EY88: =EY52/ES52-1 -> 0.11913411 | EZ88: =EZ52/ET52-1 -> -0.086143325 | FA88: =FA52/EU52-1 -> 0.02425914 | FB88: =FB52/EV52-1 -> 0.0082109325 | FD88: =FD52/EX52-1 -> 0.098710781 | FE88: =FE52/EY52-1 -> 0.023507003 | FF88: =FF52/EZ52-1 -> 0.20480159 | FG88: =FG52/FA52-1 -> 0.078746479 | FH88: =FH52/FB52-1 -> 0.097328866 | FJ88: =FJ52/FD52-1 -> 0.019839223 | FK88: =FK52/FE52-1 -> 0.060668793 | FL88: =FL52/FF52-1 -> 0.12186991 | FM88: =FM52/FG52-1 -> 0.12193332 | FN88: =FN52/FH52-1 -> 0.08149349 | FP88: =FP52/FJ52-1 -> 0.077086822 | FQ88: =FQ52/FK52-1 -> 0.077337427 | FR88: =FR52/FL52-1 -> 0.077345432 | FS88: =FS52/FM52-1 -> 0.077403869 | FT88: =FT52/FN52-1 -> 0.077299069 | FV88: =FV52/FP52-1 -> 0.06361369 | FW88: =FW52/FQ52-1 -> 0.06361369 | FX88: =FX52/FR52-1 -> 0.06361369 | FY88: =FY52/FS52-1 -> 0.06361369 | FZ88: =FZ52/FT52-1 -> 0.06361369 | GB88: =GB52/FV52-1 -> 0.066518821 | GC88: =GC52/FW52-1 -> 0.066518821 | GD88: =GD52/FX52-1 -> 0.066518821 | GE88: =GE52/FY52-1 -> 0.066518821 | GF88: =GF52/FZ52-1 -> 0.066518821 | GH88: =GH52/GB52-1 -> 0.059228458 | GI88: =GI52/GC52-1 -> 0.059228458 | GJ88: =GJ52/GD52-1 -> 0.059228458 | GK88: =GK52/GE52-1 -> 0.059228458 | GL88: =GL52/GF52-1 -> 0.059228458 | GN88: =GN52/GH52-1 -> 0.053885146 | GO88: =GO52/GI52-1 -> 0.053885146 | GP88: =GP52/GJ52-1 -> 0.053885146 | GQ88: =GQ52/GK52-1 -> 0.053885146 | GR88: =GR52/GL52-1 -> 0.053885146 | GT88: =GT52/GN52-1 -> 0.04852745 | GU88: =GU52/GO52-1 -> 0.04852745 | GV88: =GV52/GP52-1 -> 0.04852745 | GW88: =GW52/GQ52-1 -> 0.04852745 | GX88: =GX52/GR52-1 -> 0.04852745 | GZ88: =GZ52/GT52-1 -> 0.038593109 | HA88: =HA52/GU52-1 -> 0.038593109 | HB88: =HB52/GV52-1 -> 0.038593109 | HC88: =HC52/GW52-1 -> 0.038593109 | HD88: =HD52/GX52-1 -> 0.038593109 | HF88: =HF52/GZ52-1 -> 0.033003687 | HG88: =HG52/HA52-1 -> 0.033003687 | HH88: =HH52/HB52-1 -> 0.033003687 | HI88: =HI52/HC52-1 -> 0.033003687 | HJ88: =HJ52/HD52-1 -> 0.033003687
C89: =C54 -> Research & Development | DN89: =DN54/DH54-1 -> 0.26464435 | DO89: =DO54/DI54-1 -> 1.4109972 | DP89: =DP54/DJ54-1 -> 4.8542601 | DQ89: =DQ54/DK54-1 -> 2.9543726 | DR89: =DR54/DL54-1 -> 1.8280573 | DT89: =DT54/DN54-1 -> 0.70388751 | DU89: =DU54/DO54-1 -> -0.1863162 | DV89: =DV54/DP54-1 -> -0.24779778 | DW89: =DW54/DQ54-1 -> 0.0096153846 | DX89: =DX54/DR54-1 -> -0.030399434 | DZ89: =DZ54/DT54-1 -> 0.19223301 | EA89: =EA54/DU54-1 -> 0.66033254 | EB89: =EB54/DV54-1 -> 2.7724033 | EC89: =EC54/DW54-1 -> 3.0538095 | ED89: =ED54/DX54-1 -> 1.6580386 | EF89: =EF54/DZ54-1 -> 2.1404723 | EG89: =EG54/EA54-1 -> 1.4680973 | EH89: =EH54/EB54-1 -> -0.013092185 | EI89: =EI54/EC54-1 -> -0.21590509 | EJ89: =EJ54/ED54-1 -> 0.38645819 | EL89: =EL54/EF54-1 -> -0.041229094 | EM89: =EM54/EG54-1 -> -0.13030373 | EN89: =EN54/EH54-1 -> -0.27721554 | EO89: =EO54/EI54-1 -> 0.067715356 | EP89: =EP54/EJ54-1 -> -0.09948559 | ER89: =ER54/EL54-1 -> 0.030425963 | ES89: =ES54/EM54-1 -> 0.05118635 | ET89: =ET54/EN54-1 -> 0.45392621 | EU89: =EU54/EO54-1 -> 0.11814228 | EV89: =EV54/EP54-1 -> 0.14097916 | EX89: =EX54/ER54-1 -> 0.33608924 | EY89: =EY54/ES54-1 -> 0.14417956 | EZ89: =EZ54/ET54-1 -> 0.13144196 | FA89: =FA54/EU54-1 -> 0.15183837 | FB89: =FB54/EV54-1 -> 0.18992907 | FD89: =FD54/EX54-1 -> 0.098710781 | FE89: =FE54/EY54-1 -> 0.081290714 | FF89: =FF54/EZ54-1 -> 0.09469723 | FG89: =FG54/FA54-1 -> 0.11000652 | FH89: =FH54/FB54-1 -> 0.096326784 | FJ89: =FJ54/FD54-1 -> -0.076531455 | FK89: =FK54/FE54-1 -> 0.12470003 | FL89: =FL54/FF54-1 -> 0.20890001 | FM89: =FM54/FG54-1 -> 0.1595582 | FN89: =FN54/FH54-1 -> 0.097775234 | FP89: =FP54/FJ54-1 -> 0.097744831 | FQ89: =FQ54/FK54-1 -> 0.098000242 | FR89: =FR54/FL54-1 -> 0.0980084 | FS89: =FS54/FM54-1 -> 0.098067959 | FT89: =FT54/FN54-1 -> 0.097961148 | FV89: =FV54/FP54-1 -> 0.092961148 | FW89: =FW54/FQ54-1 -> 0.092961148 | FX89: =FX54/FR54-1 -> 0.092961148 | FY89: =FY54/FS54-1 -> 0.092961148 | FZ89: =FZ54/FT54-1 -> 0.092961148 | GB89: =GB54/FV54-1 -> 0.087961148 | GC89: =GC54/FW54-1 -> 0.087961148 | GD89: =GD54/FX54-1 -> 0.087961148 | GE89: =GE54/FY54-1 -> 0.087961148 | GF89: =GF54/FZ54-1 -> 0.087961148 | GH89: =GH54/GB54-1 -> 0.080961148 | GI89: =GI54/GC54-1 -> 0.080961148 | GJ89: =GJ54/GD54-1 -> 0.080961148 | GK89: =GK54/GE54-1 -> 0.080961148 | GL89: =GL54/GF54-1 -> 0.080961148 | GN89: =GN54/GH54-1 -> 0.075961148 | GO89: =GO54/GI54-1 -> 0.075961148 | GP89: =GP54/GJ54-1 -> 0.075961148 | GQ89: =GQ54/GK54-1 -> 0.075961148 | GR89: =GR54/GL54-1 -> 0.075961148 | GT89: =GT54/GN54-1 -> 0.070961148 | GU89: =GU54/GO54-1 -> 0.070961148 | GV89: =GV54/GP54-1 -> 0.070961148 | GW89: =GW54/GQ54-1 -> 0.070961148 | GX89: =GX54/GR54-1 -> 0.070961148 | GZ89: =GZ54/GT54-1 -> 0.065961148 | HA89: =HA54/GU54-1 -> 0.065961148 | HB89: =HB54/GV54-1 -> 0.065961148 | HC89: =HC54/GW54-1 -> 0.065961148 | HD89: =HD54/GX54-1 -> 0.065961148 | HF89: =HF54/GZ54-1 -> 0.060961148 | HG89: =HG54/HA54-1 -> 0.060961148 | HH89: =HH54/HB54-1 -> 0.060961148 | HI89: =HI54/HC54-1 -> 0.060961148 | HJ89: =HJ54/HD54-1 -> 0.060961148
B90: Adj. EBITDA | ER90: =ER70/EL70-1 -> -1.4901053 | ES90: =ES70/EM70-1 -> -6.2993662 | ET90: =ET70/EN70-1 -> 3.0465961 | EU90: =EU70/EO70-1 -> 0.27011125 | EV90: =EV70/EP70-1 -> 10.391429 | EX90: =EX70/ER70-1 -> 1.0246277 | EY90: =EY70/ES70-1 -> -0.017848928 | EZ90: =EZ70/ET70-1 -> -0.085389562 | FA90: =FA70/EU70-1 -> 0.12692664 | FB90: =FB70/EV70-1 -> 0.094652595 | FD90: =FD70/EX70-1 -> 0.28532638 | FE90: =FE70/EY70-1 -> 0.10599978 | FF90: =FF70/EZ70-1 -> 0.35217548 | FG90: =FG70/FA70-1 -> 0.39266077 | FH90: =FH70/FB70-1 -> 0.2931572 | FJ90: =FJ70/FD70-1 -> 0.95138256 | FK90: =FK70/FE70-1 -> 0.54568163 | FL90: =FL70/FF70-1 -> 0.12923557 | FM90: =FM70/FG70-1 -> 0.015836033 | FN90: =FN70/FH70-1 -> 0.31249329 | FP90: =FP70/FJ70-1 -> 0.30235664 | FQ90: =FQ70/FK70-1 -> 0.31574437 | FR90: =FR70/FL70-1 -> 0.32639309 | FS90: =FS70/FM70-1 -> 0.33341466 | FT90: =FT70/FN70-1 -> 0.31976633 | FV90: =FV70/FP70-1 -> 0.30137474 | FW90: =FW70/FQ70-1 -> 0.30922185 | FX90: =FX70/FR70-1 -> 0.31533836 | FY90: =FY70/FS70-1 -> 0.31902991 | FZ90: =FZ70/FT70-1 -> 0.31146507 | GB90: =GB70/FV70-1 -> 0.26775205 | GC90: =GC70/FW70-1 -> 0.27007476 | GD90: =GD70/FX70-1 -> 0.27174618 | GE90: =GE70/FY70-1 -> 0.27235157 | GF90: =GF70/FZ70-1 -> 0.27054942 | GH90: =GH70/GB70-1 -> 0.22257793 | GI90: =GI70/GC70-1 -> 0.2260317 | GJ90: =GJ70/GD70-1 -> 0.2286831 | GK90: =GK70/GE70-1 -> 0.2302605 | GL90: =GL70/GF70-1 -> 0.22700441 | GN90: =GN70/GH70-1 -> 0.2168295 | GO90: =GO70/GI70-1 -> 0.21741008 | GP90: =GP70/GJ70-1 -> 0.21776395 | GQ90: =GQ70/GK70-1 -> 0.21767412 | GR90: =GR70/GL70-1 -> 0.21743392 | GT90: =GT70/GN70-1 -> 0.16947174 | GU90: =GU70/GO70-1 -> 0.17141415 | GV90: =GV70/GP70-1 -> 0.17290446 | GW90: =GW70/GQ70-1 -> 0.17382244 | GX90: =GX70/GR70-1 -> 0.17197314 | GZ90: =GZ70/GT70-1 -> 0.1644464 | HA90: =HA70/GU70-1 -> 0.16572015 | HB90: =HB70/GV70-1 -> 0.16668326 | HC90: =HC70/GW70-1 -> 0.1672303 | HD90: =HD70/GX70-1 -> 0.1660664 | HF90: =HF70/GZ70-1 -> -0.050983276 | HG90: =HG70/HA70-1 -> -0.043541531 | HH90: =HH70/HB70-1 -> -0.038166786 | HI90: =HI70/HC70-1 -> -0.036087927 | HJ90: =HJ70/HD70-1 -> -0.04193824
B91: =B56 -> Operating income | DN91: =DN56/DH56-1 -> 1.4642728 | DO91: =DO56/DI56-1 -> 0.70549451 | DP91: =DP56/DJ56-1 -> 0.3901694 | DQ91: =DQ56/DK56-1 -> -0.077788083 | DR91: =DR56/DL56-1 -> 0.53165105 | DT91: =DT56/DN56-1 -> -0.95526104 | DU91: =DU56/DO56-1 -> -2.441458 | DV91: =DV56/DP56-1 -> 0.018078306 | DW91: =DW56/DQ56-1 -> -0.14028913 | DX91: =DX56/DR56-1 -> -0.953328 | DZ91: =DZ56/DT56-1 -> 2.8625205 | EA91: =EA56/DU56-1 -> -0.83588761 | EB91: =EB56/DV56-1 -> -2.1164525 | EC91: =EC56/DW56-1 -> -3.5208364 | ED91: =ED56/DX56-1 -> -15.538578 | EF91: =EF56/DZ56-1 -> -12.683898 | EG91: =EG56/EA56-1 -> 8.4922179 | EH91: =EH56/EB56-1 -> 0.80623902 | EI91: =EI56/EC56-1 -> -0.38259861 | EJ91: =EJ56/ED56-1 -> 1.8847728 | EL91: =EL56/EF56-1 -> -0.41760354 | EM91: =EM56/EG56-1 -> -0.49760197 | EN91: =EN56/EH56-1 -> -0.71063002 | EO91: =EO56/EI56-1 -> -0.96674183 | EP91: =EP56/EJ56-1 -> -0.5837702 | ER91: =ER56/EL56-1 -> -0.61703718 | ES91: =ES56/EM56-1 -> -1.0917918 | ET91: =ET56/EN56-1 -> -1.5773369 | EU91: =EU56/EO56-1 -> -7.9971751 | EV91: =EV56/EP56-1 -> -1.0255944 | EX91: =EX56/ER56-1 -> -0.61609756 | EY91: =EY56/ES56-1 -> -0.064 | EZ91: =EZ56/ET56-1 -> 0.096097845 | FA91: =FA56/EU56-1 -> 0.83003633 | FB91: =FB56/EV56-1 -> 6.8882619 | FD91: =FD56/EX56-1 -> -0.68325392 | FE91: =FE56/EY56-1 -> 0.95616067 | FF91: =FF56/EZ56-1 -> 0.82588896 | FG91: =FG56/FA56-1 -> 0.9938734 | FH91: =FH56/FB56-1 -> 1.464283 | FJ91: =FJ56/FD56-1 -> -11.865314 | FK91: =FK56/FE56-1 -> 3.1903553 | FL91: =FL56/FF56-1 -> 0.31684197 | FM91: =FM56/FG56-1 -> 0.028214569 | FN91: =FN56/FH56-1 -> 1.0380086 | FP91: =FP56/FJ56-1 -> 0.64525139 | FQ91: =FQ56/FK56-1 -> 0.64563418 | FR91: =FR56/FL56-1 -> 0.64564641 | FS91: =FS56/FM56-1 -> 0.64573567 | FT91: =FT56/FN56-1 -> 0.64557559 | FV91: =FV56/FP56-1 -> 0.49304817 | FW91: =FW56/FQ56-1 -> 0.49304817 | FX91: =FX56/FR56-1 -> 0.49304817 | FY91: =FY56/FS56-1 -> 0.49304817 | FZ91: =FZ56/FT56-1 -> 0.49304817 | GB91: =GB56/FV56-1 -> 0.352995 | GC91: =GC56/FW56-1 -> 0.352995 | GD91: =GD56/FX56-1 -> 0.352995 | GE91: =GE56/FY56-1 -> 0.352995 | GF91: =GF56/FZ56-1 -> 0.352995 | GH91: =GH56/GB56-1 -> 0.29270716 | GI91: =GI56/GC56-1 -> 0.29270716 | GJ91: =GJ56/GD56-1 -> 0.29270716 | GK91: =GK56/GE56-1 -> 0.29270716 | GL91: =GL56/GF56-1 -> 0.29270716 | GN91: =GN56/GH56-1 -> 0.25220407 | GO91: =GO56/GI56-1 -> 0.25220407 | GP91: =GP56/GJ56-1 -> 0.25220407 | GQ91: =GQ56/GK56-1 -> 0.25220407 | GR91: =GR56/GL56-1 -> 0.25220407 | GT91: =GT56/GN56-1 -> 0.20285311 | GU91: =GU56/GO56-1 -> 0.20285311 | GV91: =GV56/GP56-1 -> 0.20285311 | GW91: =GW56/GQ56-1 -> 0.20285311 | GX91: =GX56/GR56-1 -> 0.20285311 | GZ91: =GZ56/GT56-1 -> 0.18952197 | HA91: =HA56/GU56-1 -> 0.18952197 | HB91: =HB56/GV56-1 -> 0.18952197 | HC91: =HC56/GW56-1 -> 0.18952197 | HD91: =HD56/GX56-1 -> 0.18952197 | HF91: =HF56/GZ56-1 -> 0.1711678 | HG91: =HG56/HA56-1 -> 0.1711678 | HH91: =HH56/HB56-1 -> 0.1711678 | HI91: =HI56/HC56-1 -> 0.1711678 | HJ91: =HJ56/HD56-1 -> 0.1711678
B92: =B62 -> Net income | DN92: =DN62/DH62-1 -> 0.94485194 | DO92: =DO62/DI62-1 -> 0.61845052 | DP92: =DP62/DJ62-1 -> 0.63201213 | DQ92: =DQ62/DK62-1 -> 0.99124886 | DR92: =DR62/DL62-1 -> 0.79976985 | DT92: =DT62/DN62-1 -> -1.3064674 | DU92: =DU62/DO62-1 -> -1.5726342 | DV92: =DV62/DP62-1 -> -0.076177837 | DW92: =DW62/DQ62-1 -> 0.51483245 | DX92: =DX62/DR62-1 -> -0.47713433 | DZ92: =DZ62/DT62-1 -> 1.1180492 | EA92: =EA62/DU62-1 -> -0.79125393 | EB92: =EB62/DV62-1 -> -2.4028157 | EC92: =EC62/DW62-1 -> -2.0536114 | ED92: =ED62/DX62-1 -> -2.9046177 | EF92: =EF62/DZ62-1 -> 4.3699161 | EG92: =EG62/EA62-1 -> 22.142361 | EH92: =EH62/EB62-1 -> 0.8328725 | EI92: =EI62/EC62-1 -> -0.60136531 | EJ92: =EJ62/ED62-1 -> 1.1339122 | EL92: =EL62/EF62-1 -> -0.52825198 | EM92: =EM62/EG62-1 -> -0.66526632 | EN92: =EN62/EH62-1 -> -0.98497039 | EO92: =EO62/EI62-1 -> -1.5603684 | EP92: =EP62/EJ62-1 -> -0.78738037 | ER92: =ER62/EL62-1 -> -0.77539925 | ES92: =ES62/EM62-1 -> -1.6609891 | ET92: =ET62/EN62-1 -> -26.769517 | EU92: =EU62/EO62-1 -> 0.42655367 | EV92: =EV62/EP62-1 -> -1.9613881 | EX92: =EX62/ER62-1 -> -0.82639939 | EY92: =EY62/ES62-1 -> -0.18874322 | EZ92: =EZ62/ET62-1 -> -0.47360069 | FA92: =FA62/EU62-1 -> 0.4520252 | FB92: =FB62/EV62-1 -> 0.040513072 | FD92: =FD62/EX62-1 -> -0.81512343 | FE92: =FE62/EY62-1 -> -0.23905988 | FF92: =FF62/EZ62-1 -> 1.0669067 | FG92: =FG62/FA62-1 -> 0.20837433 | FH92: =FH62/FB62-1 -> 0.34287948 | FJ92: =FJ62/FD62-1 -> -110.55375 | FK92: =FK62/FE62-1 -> 2.6282912 | FL92: =FL62/FF62-1 -> 0.3755387 | FM92: =FM62/FG62-1 -> -0.12653428 | FN92: =FN62/FH62-1 -> 0.91087712 | FP92: =FP62/FJ62-1 -> 0.40522512 | FQ92: =FQ62/FK62-1 -> 0.4161812 | FR92: =FR62/FL62-1 -> 0.42600081 | FS92: =FS62/FM62-1 -> 0.79422477 | FT92: =FT62/FN62-1 -> 0.50067019 | FV92: =FV62/FP62-1 -> 0.067995505 | FW92: =FW62/FQ62-1 -> 0.086150127 | FX92: =FX62/FR62-1 -> 0.089933056 | FY92: =FY62/FS62-1 -> 0.091356706 | FZ92: =FZ62/FT62-1 -> 0.084371581 | GB92: =GB62/FV62-1 -> 0.43937152 | GC92: =GC62/FW62-1 -> 0.41680202 | GD92: =GD62/FX62-1 -> 0.41434974 | GE92: =GE62/FY62-1 -> 0.41331235 | GF92: =GF62/FZ62-1 -> 0.42030545 | GH92: =GH62/GB62-1 -> 0.33895061 | GI92: =GI62/GC62-1 -> 0.33559107 | GJ92: =GJ62/GD62-1 -> 0.33385259 | GK92: =GK62/GE62-1 -> 0.40626082 | GL92: =GL62/GF62-1 -> 0.35481853 | GN92: =GN62/GH62-1 -> 0.33810617 | GO92: =GO62/GI62-1 -> 0.33262566 | GP92: =GP62/GJ62-1 -> 0.32922219 | GQ92: =GQ62/GK62-1 -> 0.25841122 | GR92: =GR62/GL62-1 -> 0.31237899 | GT92: =GT62/GN62-1 -> 0.22220507 | GU92: =GU62/GO62-1 -> 0.2208903 | GV92: =GV62/GP62-1 -> 0.22020458 | GW92: =GW62/GQ62-1 -> 0.21987679 | GX92: =GX62/GR62-1 -> 0.22074543 | GZ92: =GZ62/GT62-1 -> 0.20641381 | HA92: =HA62/GU62-1 -> 0.20530777 | HB92: =HB62/GV62-1 -> 0.20472409 | HC92: =HC62/GW62-1 -> 0.20444681 | HD92: =HD62/GX62-1 -> 0.20518245 | HF92: =HF62/GZ62-1 -> 0.18667685 | HG92: =HG62/HA62-1 -> 0.18569811 | HH92: =HH62/HB62-1 -> 0.18515985 | HI92: =HI62/HC62-1 -> 0.1849002 | HJ92: =HJ62/HD62-1 -> 0.18557241
B93: =B68 -> Diluted E.P.S. (non GAAP) | DN93: =DN68/DH68-1 -> 0.65267253 | DO93: =DO68/DI68-1 -> 0.4260128 | DP93: =DP68/DJ68-1 -> 0.3755466 | DQ93: =DQ68/DK68-1 -> 0.78916155 | DR93: =DR68/DL68-1 -> 0.5905161 | DT93: =DT68/DN68-1 -> -1.2778868 | DU93: =DU68/DO68-1 -> -1.543171 | DV93: =DV68/DP68-1 -> -0.16384681 | DW93: =DW68/DQ68-1 -> 0.4296997 | DX93: =DX68/DR68-1 -> -0.47713433 | DZ93: =DZ68/DT68-1 -> 0.90451084 | EA93: =EA68/DU68-1 -> -0.82839453 | EB93: =EB68/DV68-1 -> -2.3642654 | EC93: =EC68/DW68-1 -> -1.9778875 | ED93: =ED68/DX68-1 -> -2.645079 | EF93: =EF68/DZ68-1 -> 4.0471478 | EG93: =EG68/EA68-1 -> 23.479592 | EH93: =EH68/EB68-1 -> 0.80538494 | EI93: =EI68/EC68-1 -> -0.60658182 | EJ93: =EJ68/ED68-1 -> 1.0608159 | EL93: =EL68/EF68-1 -> -0.53351937 | EM93: =EM68/EG68-1 -> -0.66870562 | EN93: =EN68/EH68-1 -> -0.9851213 | EO93: =EO68/EI68-1 -> -1.5549618 | EP93: =EP68/EJ68-1 -> -0.78738037 | ER93: =ER68/EL68-1 -> -0.77733161 | ES93: =ES68/EM68-1 -> -1.6555037 | ET93: =ET68/EN68-1 -> -26.512538 | EU93: =EU68/EO68-1 -> 0.41274361 | EV93: =EV68/EP68-1 -> -1.9428655 | EX93: =EX68/ER68-1 -> -0.82812346 | EY93: =EY68/ES68-1 -> -0.1985329 | EZ93: =EZ68/ET68-1 -> -0.47959373 | FA93: =FA68/EU68-1 -> 0.43263572 | FB93: =FB68/EV68-1 -> 0.028350569 | FD93: =FD68/EX68-1 -> -0.81778123 | FE93: =FE68/EY68-1 -> -0.24867684 | FF93: =FF68/EZ68-1 -> 1.042655 | FG93: =FG68/FA68-1 -> 0.19528363 | FH93: =FH68/FB68-1 -> 0.32623942 | FJ93: =FJ68/FD68-1 -> -109.41161 | FK93: =FK68/FE68-1 -> 2.5919385 | FL93: =FL68/FF68-1 -> 0.36231289 | FM93: =FM68/FG68-1 -> -0.13458121 | FN93: =FN68/FH68-1 -> 0.89211826 | FP93: =FP68/FJ68-1 -> 0.39283739 | FQ93: =FQ68/FK68-1 -> 0.40425719 | FR93: =FR68/FL68-1 -> 0.41455615 | FS93: =FS68/FM68-1 -> 0.78052933 | FT93: =FT68/FN68-1 -> 0.48833081 | FV93: =FV68/FP68-1 -> 0.060258237 | FW93: =FW68/FQ68-1 -> 0.078701913 | FX93: =FX68/FR68-1 -> 0.082879659 | FY93: =FY68/FS68-1 -> 0.084714121 | FZ93: =FZ68/FT68-1 -> 0.077145029 | GB93: =GB68/FV68-1 -> 0.43115993 | GC93: =GC68/FW68-1 -> 0.40925855 | GD93: =GD68/FX68-1 -> 0.40735652 | GE93: =GE68/FY68-1 -> 0.40685984 | GF93: =GF68/FZ68-1 -> 0.41301321 | GH93: =GH68/GB68-1 -> 0.33334174 | GI93: =GI68/GC68-1 -> 0.33049838 | GJ93: =GJ68/GD68-1 -> 0.32926722 | GK93: =GK68/GE68-1 -> 0.40195359 | GL93: =GL68/GF68-1 -> 0.34990691 | GN93: =GN68/GH68-1 -> 0.3345071 | GO93: =GO68/GI68-1 -> 0.3295383 | GP93: =GP68/GJ68-1 -> 0.32663803 | GQ93: =GQ68/GK68-1 -> 0.25643328 | GR93: =GR68/GL68-1 -> 0.30958311 | GT93: =GT68/GN68-1 -> 0.2207643 | GU93: =GU68/GO68-1 -> 0.21993082 | GV93: =GV68/GP68-1 -> 0.21972511 | GW93: =GW68/GQ68-1 -> 0.21987679 | GX93: =GX68/GR68-1 -> 0.22002591 | GZ93: =GZ68/GT68-1 -> 0.20641381 | HA93: =HA68/GU68-1 -> 0.20530777 | HB93: =HB68/GV68-1 -> 0.20472409 | HC93: =HC68/GW68-1 -> 0.20444681 | HD93: =HD68/GX68-1 -> 0.20518245 | HF93: =HF68/GZ68-1 -> 0.18667685 | HG93: =HG68/HA68-1 -> 0.18569811 | HH93: =HH68/HB68-1 -> 0.18515985 | HI93: =HI68/HC68-1 -> 0.1849002 | HJ93: =HJ68/HD68-1 -> 0.18557241
A95: Source: NeoGenomics and Jefferies LLC estimates.
B98: Incremental operating margins | DL98: =(DL56-DF56)/(DL49-DF49) -> 0.10023849 | DR98: =(DR56-DL56)/(DR49-DL49) -> 0.11165115 | DX98: =(DX56-DR56)/(DX49-DR49) -> -1.1372059 | ED98: =(ED56-DX56)/(ED49-DX49) -> -0.77262356 | EJ98: =(EJ56-ED56)/(EJ49-ED49) -> -2.1393756 | EP98: =(EP56-EJ56)/(EP49-EJ49) -> 0.59269975 | EV98: =(EV56-EP56)/(EV49-EP49) -> 0.51511107 | FB98: =(FB56-EV56)/(FB49-EV49) -> 0.091408801 | FH98: =(FH56-FB56)/(FH49-FB49) -> 0.14613326 | FN98: =(FN56-FH56)/(FN49-FH49) -> 0.22930925 | FT98: =(FT56-FN56)/(FT49-FN49) -> 0.26426236 | FZ98: =(FZ56-FT56)/(FZ49-FT49) -> 0.31875779 | GF98: =(GF56-FZ56)/(GF49-FZ49) -> 0.3294729 | GL98: =(GL56-GF56)/(GL49-GF49) -> 0.36913186 | GR98: =(GR56-GL56)/(GR49-GL49) -> 0.40539228 | GX98: =(GX56-GR56)/(GX49-GR49) -> 0.40621361 | HD98: =(HD56-GX56)/(HD49-GX49) -> 0.45856792 | HJ98: =(HJ56-HD56)/(HJ49-HD49) -> 0.50007176
B100: Operating expenses | DH100: =SUM(DH52:DH54) -> 21.761 | DI100: =SUM(DI52:DI54) -> 24.16 | DJ100: =SUM(DJ52:DJ54) -> 25.119 | DK100: =SUM(DK52:DK54) -> 28.485 | DL100: =SUM(DL52:DL54) -> 99.525 | DN100: =SUM(DN52:DN54) -> 33.458 | DO100: =SUM(DO52:DO54) -> 38.102 | DP100: =SUM(DP52:DP54) -> 40.82 | DQ100: =SUM(DQ52:DQ54) -> 41.968 | DR100: =SUM(DR52:DR54) -> 154.348 | DT100: =SUM(DT52:DT54) -> 45.758 | DU100: =SUM(DU52:DU54) -> 43.666 | DV100: =SUM(DV52:DV54) -> 43.872 | DW100: =SUM(DW52:DW54) -> 50.614 | DX100: =SUM(DX52:DX54) -> 183.91 | DZ100: =SUM(DZ52:DZ54) -> 44.513 | EA100: =SUM(EA52:EA54) -> 56.289 | EB100: =SUM(EB52:EB54) -> 63.443 | EC100: =SUM(EC52:EC54) -> 67.35 | ED100: =SUM(ED52:ED54) -> 231.595 | EF100: =SUM(EF52:EF54) -> 70.659 | EG100: =SUM(EG52:EG54) -> 73.194 | EH100: =SUM(EH52:EH54) -> 74.301 | EI100: =SUM(EI52:EI54) -> 72.323 | EJ100: =SUM(EJ52:EJ54) -> 290.477 | EL100: =SUM(EL52:EL54) -> 75.726 | EM100: =SUM(EM52:EM54) -> 77 | EN100: =SUM(EN52:EN54) -> 73.112 | EO100: =SUM(EO52:EO54) -> 73.021 | EP100: =SUM(EP52:EP54) -> 298.859 | ER100: =SUM(ER52:ER54) -> 76.924 | ES100: =SUM(ES52:ES54) -> 76.636 | ET100: =SUM(ET52:ET54) -> 76.646 | EU100: =SUM(EU52:EU54) -> 79.98 | EV100: =SUM(EV52:EV54) -> 310.186 | EX100: =SUM(EX52:EX54) -> 80.912 | EY100: =SUM(EY52:EY54) -> 85.779 | EZ100: =SUM(EZ52:EZ54) -> 74.865 | FA100: =SUM(FA52:FA54) -> 83.499 | FB100: =SUM(FB52:FB54) -> 325.055 | FD100: =SUM(FD52:FD54) -> 88.898887 | FE100: =SUM(FE52:FE54) -> 89.165016 | FF100: =SUM(FF52:FF54) -> 88.665927 | FG100: =SUM(FG52:FG54) -> 91.094017 | FH100: =SUM(FH52:FH54) -> 357.82385 | FJ100: =SUM(FJ52:FJ54) -> 89.717017 | FK100: =SUM(FK52:FK54) -> 95.303541 | FL100: =SUM(FL52:FL54) -> 99.927019 | FM100: =SUM(FM52:FM54) -> 102.61063 | FN100: =SUM(FN52:FN54) -> 387.55821 | FP100: =SUM(FP52:FP54) -> 96.818107 | FQ100: =SUM(FQ52:FQ54) -> 102.87073 | FR100: =SUM(FR52:FR54) -> 107.86212 | FS100: =SUM(FS52:FS54) -> 110.76484 | FT100: =SUM(FT52:FT54) -> 418.3158 | FV100: =SUM(FV52:FV54) -> 103.50883 | FW100: =SUM(FW52:FW54) -> 109.97973 | FX100: =SUM(FX52:FX54) -> 115.31605 | FY100: =SUM(FY52:FY54) -> 118.41937 | FZ100: =SUM(FZ52:FZ54) -> 447.22397 | GB100: =SUM(GB52:GB54) -> 110.62983 | GC100: =SUM(GC52:GC54) -> 117.5459 | GD100: =SUM(GD52:GD54) -> 123.24934 | GE100: =SUM(GE52:GE54) -> 126.56615 | GF100: =SUM(GF52:GF54) -> 477.99122 | GH100: =SUM(GH52:GH54) -> 117.44218 | GI100: =SUM(GI52:GI54) -> 124.78413 | GJ100: =SUM(GJ52:GJ54) -> 130.83878 | GK100: =SUM(GK52:GK54) -> 134.35983 | GL100: =SUM(GL52:GL54) -> 507.42492 | GN100: =SUM(GN52:GN54) -> 124.05597 | GO100: =SUM(GO52:GO54) -> 131.81139 | GP100: =SUM(GP52:GP54) -> 138.207 | GQ100: =SUM(GQ52:GQ54) -> 141.92635 | GR100: =SUM(GR52:GR54) -> 536.00071 | GT100: =SUM(GT52:GT54) -> 131.21181 | GU100: =SUM(GU52:GU54) -> 139.41457 | GV100: =SUM(GV52:GV54) -> 146.1791 | GW100: =SUM(GW52:GW54) -> 150.11299 | GX100: =SUM(GX52:GX54) -> 566.91847 | GZ100: =SUM(GZ52:GZ54) -> 137.75952 | HA100: =SUM(HA52:HA54) -> 146.37161 | HB100: =SUM(HB52:HB54) -> 153.47371 | HC100: =SUM(HC52:HC54) -> 157.6039 | HD100: =SUM(HD52:HD54) -> 595.20874 | HF100: =SUM(HF52:HF54) -> 143.92187 | HG100: =SUM(HG52:HG54) -> 152.91921 | HH100: =SUM(HH52:HH54) -> 160.339 | HI100: =SUM(HI52:HI54) -> 164.65394 | HJ100: =SUM(HJ52:HJ54) -> 621.83402
C101: Q/Q growth | DI101: =DI100/DH100-1 -> 0.1102431 | DJ101: =DJ100/DI100-1 -> 0.039693709 | DK101: =DK100/DJ100-1 -> 0.13400215 | DN101: =DN100/DK100-1 -> 0.17458311 | DO101: =DO100/DN100-1 -> 0.13880088 | DP101: =DP100/DO100-1 -> 0.071334838 | DQ101: =DQ100/DP100-1 -> 0.028123469 | DT101: =DT100/DQ100-1 -> 0.0903069 | DU101: =DU100/DT100-1 -> -0.045718781 | DV101: =DV100/DU100-1 -> 0.0047176293 | DW101: =DW100/DV100-1 -> 0.15367433 | DZ101: =DZ100/DW100-1 -> -0.12053977 | EA101: =EA100/DZ100-1 -> 0.26455193 | EB101: =EB100/EA100-1 -> 0.1270941 | EC101: =EC100/EB100-1 -> 0.061582838 | EF101: =EF100/EC100-1 -> 0.049131403 | EG101: =EG100/EF100-1 -> 0.035876534 | EH101: =EH100/EG100-1 -> 0.015124191 | EI101: =EI100/EH100-1 -> -0.026621445 | EL101: =EL100/EI100-1 -> 0.047052805 | EM101: =EM100/EL100-1 -> 0.016823812 | EN101: =EN100/EM100-1 -> -0.050493506 | EO101: =EO100/EN100-1 -> -0.0012446657 | ER101: =ER100/EO100-1 -> 0.053450377 | ES101: =ES100/ER100-1 -> -0.0037439551 | ET101: =ET100/ES100-1 -> 0.00013048698 | EU101: =EU100/ET100-1 -> 0.043498682 | EX101: =EX100/EU100-1 -> 0.011652913 | EY101: =EY100/EX100-1 -> 0.06015177 | EZ101: =EZ100/EY100-1 -> -0.12723394 | FA101: =FA100/EZ100-1 -> 0.11532759 | FD101: =FD100/FA100-1 -> 0.064670076 | FE101: =FE100/FD100-1 -> 0.0029936231 | FF101: =FF100/FE100-1 -> -0.0055973665 | FG101: =FG100/FF100-1 -> 0.027384705 | FJ101: =FJ100/FG100-1 -> -0.015116253 | FK101: =FK100/FJ100-1 -> 0.062268268 | FL101: =FL100/FK100-1 -> 0.04851319 | FM101: =FM100/FL100-1 -> 0.026855692 | FP101: =FP100/FM100-1 -> -0.056451473 | FQ101: =FQ100/FP100-1 -> 0.062515425 | FR101: =FR100/FQ100-1 -> 0.04852098 | FS101: =FS100/FR100-1 -> 0.026911391 | FV101: =FV100/FS100-1 -> -0.065508273 | FW101: =FW100/FV100-1 -> 0.062515425 | FX101: =FX100/FW100-1 -> 0.04852098 | FY101: =FY100/FX100-1 -> 0.026911391 | GB101: =GB100/FY100-1 -> -0.065779261 | GC101: =GC100/GB100-1 -> 0.062515425 | GD101: =GD100/GC100-1 -> 0.04852098 | GE101: =GE100/GD100-1 -> 0.026911391 | GH101: =GH100/GE100-1 -> -0.072088542 | GI101: =GI100/GH100-1 -> 0.062515425 | GJ101: =GJ100/GI100-1 -> 0.04852098 | GK101: =GK100/GJ100-1 -> 0.026911391 | GN101: =GN100/GK100-1 -> -0.076688531 | GO101: =GO100/GN100-1 -> 0.062515425 | GP101: =GP100/GO100-1 -> 0.04852098 | GQ101: =GQ100/GP100-1 -> 0.026911391 | GT101: =GT100/GQ100-1 -> -0.075493634 | GU101: =GU100/GT100-1 -> 0.062515425 | GV101: =GV100/GU100-1 -> 0.04852098 | GW101: =GW100/GV100-1 -> 0.026911391 | GZ101: =GZ100/GW100-1 -> -0.08229446 | HA101: =HA100/GZ100-1 -> 0.062515425 | HB101: =HB100/HA100-1 -> 0.04852098 | HC101: =HC100/HB100-1 -> 0.026911391 | HF101: =HF100/HC100-1 -> -0.086812758 | HG101: =HG100/HF100-1 -> 0.062515425 | HH101: =HH100/HG100-1 -> 0.04852098 | HI101: =HI100/HH100-1 -> 0.026911391
C102: y/y growth | DN102: =DN100/DH100-1 -> 0.53752125 | DO102: =DO100/DI100-1 -> 0.57706954 | DP102: =DP100/DJ100-1 -> 0.62506469 | DQ102: =DQ100/DK100-1 -> 0.47333684 | DR102: =DR100/DL100-1 -> 0.55084652 | DT102: =DT100/DN100-1 -> 0.36762508 | DU102: =DU100/DO100-1 -> 0.14602908 | DV102: =DV100/DP100-1 -> 0.074767271 | DW102: =DW100/DQ100-1 -> 0.20601411 | DX102: =DX100/DR100-1 -> 0.19152823 | DZ102: =DZ100/DT100-1 -> -0.027208357 | EA102: =EA100/DU100-1 -> 0.28908075 | EB102: =EB100/DV100-1 -> 0.44609318 | EC102: =EC100/DW100-1 -> 0.3306595 | ED102: =ED100/DX100-1 -> 0.25928443 | EF102: =EF100/DZ100-1 -> 0.58737897 | EG102: =EG100/EA100-1 -> 0.30032511 | EH102: =EH100/EB100-1 -> 0.17114575 | EI102: =EI100/EC100-1 -> 0.073838159 | EJ102: =EJ100/ED100-1 -> 0.25424556 | EL102: =EL100/EF100-1 -> 0.07171061 | EM102: =EM100/EG100-1 -> 0.051998798 | EN102: =EN100/EH100-1 -> -0.016002476 | EO102: =EO100/EI100-1 -> 0.0096511483 | EP102: =EP100/EJ100-1 -> 0.028855985 | ER102: =ER100/EL100-1 -> 0.015820194 | ES102: =ES100/EM100-1 -> -0.0047272727 | ET102: =ET100/EN100-1 -> 0.048336798 | EU102: =EU100/EO100-1 -> 0.095301352 | EV102: =EV100/EP100-1 -> 0.037900816 | EX102: =EX100/ER100-1 -> 0.051843378 | EY102: =EY100/ES100-1 -> 0.11930424 | EZ102: =EZ100/ET100-1 -> -0.023236699 | FA102: =FA100/EU100-1 -> 0.0439985 | FB102: =FB100/EV100-1 -> 0.047935755 | FD102: =FD100/EX100-1 -> 0.098710781 | FE102: =FE100/EY100-1 -> 0.039473723 | FF102: =FF100/EZ100-1 -> 0.18434418 | FG102: =FG100/FA100-1 -> 0.090959382 | FH102: =FH100/FB100-1 -> 0.10081016 | FJ102: =FJ100/FD100-1 -> 0.0092029334 | FK102: =FK100/FE100-1 -> 0.068844535 | FL102: =FL100/FF100-1 -> 0.12700586 | FM102: =FM100/FG100-1 -> 0.12642555 | FN102: =FN100/FH100-1 -> 0.083097753 | FP102: =FP100/FJ100-1 -> 0.079149869 | FQ102: =FQ100/FK100-1 -> 0.079400954 | FR102: =FR100/FL100-1 -> 0.079408974 | FS102: =FS100/FM100-1 -> 0.079467523 | FT102: =FT100/FN100-1 -> 0.079362522 | FV102: =FV100/FP100-1 -> 0.069106084 | FW102: =FW100/FQ100-1 -> 0.069106084 | FX102: =FX100/FR100-1 -> 0.069106084 | FY102: =FY100/FS100-1 -> 0.069106084 | FZ102: =FZ100/FT100-1 -> 0.069106084 | GB102: =GB100/FV100-1 -> 0.068796059 | GC102: =GC100/FW100-1 -> 0.068796059 | GD102: =GD100/FX100-1 -> 0.068796059 | GE102: =GE100/FY100-1 -> 0.068796059 | GF102: =GF100/FZ100-1 -> 0.068796059 | GH102: =GH100/GB100-1 -> 0.061577921 | GI102: =GI100/GC100-1 -> 0.061577921 | GJ102: =GJ100/GD100-1 -> 0.061577921 | GK102: =GK100/GE100-1 -> 0.061577921 | GL102: =GL100/GF100-1 -> 0.061577921 | GN102: =GN100/GH100-1 -> 0.0563153 | GO102: =GO100/GI100-1 -> 0.0563153 | GP102: =GP100/GJ100-1 -> 0.0563153 | GQ102: =GQ100/GK100-1 -> 0.0563153 | GR102: =GR100/GL100-1 -> 0.0563153 | GT102: =GT100/GN100-1 -> 0.057682322 | GU102: =GU100/GO100-1 -> 0.057682322 | GV102: =GV100/GP100-1 -> 0.057682322 | GW102: =GW100/GQ100-1 -> 0.057682322 | GX102: =GX100/GR100-1 -> 0.057682322 | GZ102: =GZ100/GT100-1 -> 0.049901832 | HA102: =HA100/GU100-1 -> 0.049901832 | HB102: =HB100/GV100-1 -> 0.049901832 | HC102: =HC100/GW100-1 -> 0.049901832 | HD102: =HD100/GX100-1 -> 0.049901832 | HF102: =HF100/GZ100-1 -> 0.044732668 | HG102: =HG100/HA100-1 -> 0.044732668 | HH102: =HH100/HB100-1 -> 0.044732668 | HI102: =HI100/HC100-1 -> 0.044732668 | HJ102: =HJ100/HD100-1 -> 0.044732668
B104: EBITDA Phasing | ER104: =ER70/EV70 -> 0.088164007 | ES104: =ES70/EV70 -> 0.27441426 | ET104: =ET70/EV70 -> 0.33765906 | EU104: =EU70/EV70 -> 0.29976267 | EX104: =EX70/FB70 -> 0.16306479 | EY104: =EY70/FB70 -> 0.24621168 | EZ104: =EZ70/FB70 -> 0.28212284 | FA104: =FA70/FB70 -> 0.30860069
B140: Share based compensation
C141: Cost of revenue | DL141: =SUM(DH141:DK141) -> 0 | DR141: =SUM(DN141:DQ141) -> 0 | DX141: =SUM(DT141:DW141) -> 0 | ED141: =SUM(DZ141:EC141) -> 0 | EJ141: =SUM(EF141:EI141) -> 0 | EP141: =SUM(EL141:EO141) -> 0 | ER141: 0.395
C142: General and administrative | DH142: =CF!DH13 -> 1.624 | DI142: =CF!DI13 -> 2.333 | DJ142: =CF!DJ13 -> 1.191 | DK142: =CF!DK13 -> 1.807 | DL142: =SUM(DH142:DK142) -> 6.955 | DN142: =CF!DN13 -> 2.139 | DO142: =CF!DO13 -> 2.313 | DP142: =CF!DP13 -> 3.275 | DQ142: =CF!DQ13 -> 2.273 | DR142: =SUM(DN142:DQ142) -> 10 | DT142: =CF!DT13 -> 2.186 | DU142: =CF!DU13 -> 2.635 | DV142: =CF!DV13 -> 2.715 | DW142: =CF!DW13 -> 2.676 | DX142: =SUM(DT142:DW142) -> 10.212 | DZ142: =CF!DZ13 -> 2.653 | EA142: =CF!EA13 -> 4.506 | EB142: =CF!EB13 -> 5.237 | EC142: =CF!EC13 -> 10.062 | ED142: =SUM(DZ142:EC142) -> 22.458 | EF142: =CF!EF13 -> 12.103 | EG142: =CF!EG13 -> 3.626 | EH142: =CF!EH13 -> 4.28 | EI142: =CF!EI13 -> 4.663 | EJ142: =SUM(EF142:EI142) -> 24.672 | EL142: =CF!EL13 -> 4.758 | EM142: =CF!EM13 -> 5.705 | EN142: =CF!EN13 -> 7.18 | EO142: =CF!EO13 -> 6.99 | EP142: =SUM(EL142:EO142) -> 24.633 | ER142: 6.663
C143: Research and development | DL143: =SUM(DH143:DK143) -> 0 | DR143: =SUM(DN143:DQ143) -> 0 | DX143: =SUM(DT143:DW143) -> 0 | ED143: =SUM(DZ143:EC143) -> 0 | EJ143: =SUM(EF143:EI143) -> 0 | EP143: =SUM(EL143:EO143) -> 0 | ER143: 0.171
C144: Sales and Marketing | DL144: =SUM(DH144:DK144) -> 0 | DR144: =SUM(DN144:DQ144) -> 0 | DX144: =SUM(DT144:DW144) -> 0 | ED144: =SUM(DZ144:EC144) -> 0 | EJ144: =SUM(EF144:EI144) -> 0 | EP144: =SUM(EL144:EO144) -> 0 | ER144: 0.545
C145: Share-based compensation expense, before taxes | DH145: =SUM(DH141:DH144) -> 1.624 | DI145: =SUM(DI141:DI144) -> 2.333 | DJ145: =SUM(DJ141:DJ144) -> 1.191 | DK145: =SUM(DK141:DK144) -> 1.807 | DL145: =SUM(DL141:DL144) -> 6.955 | DN145: =SUM(DN141:DN144) -> 2.139 | DO145: =SUM(DO141:DO144) -> 2.313 | DP145: =SUM(DP141:DP144) -> 3.275 | DQ145: =SUM(DQ141:DQ144) -> 2.273 | DR145: =SUM(DR141:DR144) -> 10 | DT145: =SUM(DT141:DT144) -> 2.186 | DU145: =SUM(DU141:DU144) -> 2.635 | DV145: =SUM(DV141:DV144) -> 2.715 | DW145: =SUM(DW141:DW144) -> 2.676 | DX145: =SUM(DX141:DX144) -> 10.212 | DZ145: =SUM(DZ141:DZ144) -> 2.653 | EA145: =SUM(EA141:EA144) -> 4.506 | EB145: =SUM(EB141:EB144) -> 5.237 | EC145: =SUM(EC141:EC144) -> 10.062 | ED145: =SUM(ED141:ED144) -> 22.458 | EF145: =SUM(EF141:EF144) -> 12.103 | EG145: =SUM(EG141:EG144) -> 3.626 | EH145: =SUM(EH141:EH144) -> 4.28 | EI145: =SUM(EI141:EI144) -> 4.663 | EJ145: =SUM(EJ141:EJ144) -> 24.672 | EL145: =SUM(EL141:EL144) -> 4.758 | EM145: =SUM(EM141:EM144) -> 5.705 | EN145: =SUM(EN141:EN144) -> 7.18 | EO145: =SUM(EO141:EO144) -> 6.99 | EP145: =SUM(EP141:EP144) -> 24.633 | ER145: =SUM(ER141:ER144) -> 7.774 | ES145: =ES147*ES49 -> 6.8490251 | ET145: =ET147*ET49 -> 6.9873363 | EU145: =EU147*EU49 -> 7.1612036 | EV145: =SUM(ER145:EU145) -> 28.771565 | EX145: =EX147*EX49 -> 6.9961212 | EY145: =EY147*EY49 -> 7.5496573 | EZ145: =EZ147*EZ49 -> 7.8189102 | FA145: =FA147*FA49 -> 7.9177099 | FB145: =SUM(EX145:FA145) -> 30.282399 | FD145: =FD147*FD49 -> 7.6867138 | FE145: =FE147*FE49 -> 8.1633743 | FF145: =FF147*FF49 -> 8.5593394 | FG145: =FG147*FG49 -> 8.7887096 | FH145: =SUM(FD145:FG145) -> 33.198137 | FJ145: =FJ147*FJ49 -> 8.4365529 | FK145: =FK147*FK49 -> 8.9618824 | FL145: =FL147*FL49 -> 9.3966519 | FM145: =FM147*FM49 -> 9.6490055 | FN145: =SUM(FJ145:FM145) -> 36.444093 | FP145: =FP147*FP49 -> 9.2611823 | FQ145: =FQ147*FQ49 -> 9.8401491 | FR145: =FR147*FR49 -> 10.317603 | FS145: =FS147*FS49 -> 10.595264 | FT145: =SUM(FP145:FS145) -> 40.014198 | FV145: =FV147*FV49 -> 10.122112 | FW145: =FW147*FW49 -> 10.754901 | FX145: =FX147*FX49 -> 11.276739 | FY145: =FY147*FY49 -> 11.580212 | FZ145: =SUM(FV145:FY145) -> 43.733964 | GB145: =GB147*GB49 -> 11.012465 | GC145: =GC147*GC49 -> 11.700914 | GD145: =GD147*GD49 -> 12.268654 | GE145: =GE147*GE49 -> 12.59882 | GF145: =SUM(GB145:GE145) -> 47.580853 | GH145: =GH147*GH49 -> 11.904047 | GI145: =GI147*GI49 -> 12.648233 | GJ145: =GJ147*GJ49 -> 13.261938 | GK145: =GK147*GK49 -> 13.618835 | GL145: =SUM(GH145:GK145) -> 51.433054 | GN145: =GN147*GN49 -> 12.808292 | GO145: =GO147*GO49 -> 13.609008 | GP145: =GP147*GP49 -> 14.26933 | GQ145: =GQ147*GQ49 -> 14.653338 | GR145: =SUM(GN145:GQ145) -> 55.339968 | GT145: =GT147*GT49 -> 13.717183 | GU145: =GU147*GU49 -> 14.574719 | GV145: =GV147*GV49 -> 15.281898 | GW145: =GW147*GW49 -> 15.693155 | GX145: =SUM(GT145:GW145) -> 59.266955 | GZ145: =GZ147*GZ49 -> 14.621984 | HA145: =HA147*HA49 -> 15.536084 | HB145: =HB147*HB49 -> 16.28991 | HC145: =HC147*HC49 -> 16.728294 | HD145: =SUM(GZ145:HC145) -> 63.176272
C147: % of Revenue | DH147: =DH145/DH49 -> 0.025605853 | DI147: =DI145/DI49 -> 0.034437458 | DJ147: =DJ145/DJ49 -> 0.017236888 | DK147: =DK145/DK49 -> 0.023628637 | DL147: =DL145/DL49 -> 0.025131893 | DN147: =DN145/DN49 -> 0.022379861 | DO147: =DO145/DO49 -> 0.022740456 | DP147: =DP145/DP49 -> 0.031288215 | DQ147: =DQ145/DQ49 -> 0.021269229 | DR147: =DR145/DR49 -> 0.024460045 | DT147: =DT145/DT49 -> 0.020616807 | DU147: =DU145/DU49 -> 0.030295365 | DV147: =DV145/DV49 -> 0.021643124 | DW147: =DW145/DW49 -> 0.021238601 | DX147: =DX145/DX49 -> 0.022976816 | DZ147: =DZ145/DZ49 -> 0.022963136 | EA147: =EA145/EA49 -> 0.037018172 | EB147: =EB145/EB49 -> 0.043159716 | EC147: =EC145/EC49 -> 0.08002736 | ED147: =ED145/ED49 -> 0.046369307 | EF147: =EF145/EF49 -> 0.10329524 | EG147: =EG145/EG49 -> 0.028991301 | EH147: =EH145/EH49 -> 0.033234458 | EI147: =EI145/EI49 -> 0.03361811 | EJ147: =EJ145/EJ49 -> 0.048402285 | EL147: =EL145/EL49 -> 0.034674246 | EM147: =EM145/EM49 -> 0.038831449 | EN147: =EN145/EN49 -> 0.047251142 | EO147: =EO145/EO49 -> 0.044936741 | EP147: =EP145/EP49 -> 0.041634905 | ER147: =ER145/ER49 -> 0.049756784 | ES147: =ET147 -> 0.041634905 | ET147: =EU147 -> 0.041634905 | EU147: =EV147 -> 0.041634905 | EV147: =EP147 -> 0.041634905 | EX147: =EY147 -> 0.041634905 | EY147: =EZ147 -> 0.041634905 | EZ147: =FA147 -> 0.041634905 | FA147: =FB147 -> 0.041634905 | FB147: =EV147 -> 0.041634905 | FD147: =FE147 -> 0.041634905 | FE147: =FF147 -> 0.041634905 | FF147: =FG147 -> 0.041634905 | FG147: =FH147 -> 0.041634905 | FH147: =FB147 -> 0.041634905 | FJ147: =FK147 -> 0.041634905 | FK147: =FL147 -> 0.041634905 | FL147: =FM147 -> 0.041634905 | FM147: =FN147 -> 0.041634905 | FN147: =FH147 -> 0.041634905 | FP147: =FQ147 -> 0.041634905 | FQ147: =FR147 -> 0.041634905 | FR147: =FS147 -> 0.041634905 | FS147: =FT147 -> 0.041634905 | FT147: =FN147 -> 0.041634905 | FV147: =FW147 -> 0.041634905 | FW147: =FX147 -> 0.041634905 | FX147: =FY147 -> 0.041634905 | FY147: =FZ147 -> 0.041634905 | FZ147: =FT147 -> 0.041634905 | GB147: =GC147 -> 0.041634905 | GC147: =GD147 -> 0.041634905 | GD147: =GE147 -> 0.041634905 | GE147: =GF147 -> 0.041634905 | GF147: =FZ147 -> 0.041634905 | GH147: =GI147 -> 0.041634905 | GI147: =GJ147 -> 0.041634905 | GJ147: =GK147 -> 0.041634905 | GK147: =GL147 -> 0.041634905 | GL147: =GF147 -> 0.041634905 | GN147: =GO147 -> 0.041634905 | GO147: =GP147 -> 0.041634905 | GP147: =GQ147 -> 0.041634905 | GQ147: =GR147 -> 0.041634905 | GR147: =GL147 -> 0.041634905 | GT147: =GU147 -> 0.041634905 | GU147: =GV147 -> 0.041634905 | GV147: =GW147 -> 0.041634905 | GW147: =GX147 -> 0.041634905 | GX147: =GR147 -> 0.041634905 | GZ147: =HA147 -> 0.041634905 | HA147: =HB147 -> 0.041634905 | HB147: =HC147 -> 0.041634905 | HC147: =HD147 -> 0.041634905 | HD147: =GX147 -> 0.041634905
B150: Checks
C151: Non-GAAP Net income | DH151: 2.537 | DI151: 4.466 | DJ151: 4.617 | DK151: 5.485 | DL151: 17.937 | DN151: 6.622 | DO151: 7.228 | DP151: 7.535 | DQ151: 10.922 | DR151: 32.308 | DT151: -2.194 | DU151: -4.139 | DV151: 6.961 | DW151: 16.545 | DX151: 17.173 | DZ151: -4.647 | EA151: -0.864 | EB151: -9.765 | EC151: -17.432 | ED151: -32.707 | EF151: -24.954 | EG151: -19.995 | EH151: -17.898 | EI151: -6.949 | EJ151: -69.796 | EL151: -11.772 | EM151: -6.693 | EN151: -0.269 | EO151: 3.894 | EP151: -14.84 | ER151: -2.644
C152: GAAP Net income | DH152: -2.212 | DI152: 5.924 | DJ152: 2.023 | DK152: 0.353 | DL152: 6.088 | DN152: -2.424 | DO152: 1.991 | DP152: 2.143 | DQ152: 6.296 | DR152: 8.006 | DT152: -6.978 | DU152: -6.824 | DV152: 2.557 | DW152: 15.417 | DX152: 4.172 | DZ152: -22.114 | EA152: 75.873 | EB152: -20.348 | EC152: -41.759 | ED152: -8.347 | EF152: -49.408 | EG152: -35.303 | EH152: -36.852 | EI152: -22.687 | EJ152: -144.25 | EL152: -30.795 | EM152: -24.331 | EN152: -18.516 | EO152: -14.326 | EP152: -87.968 | ER152: -27.061
C153: Adjusted EBITDA | DH153: =9.238-#REF! -> #REF! | DI153: =10.056-#REF! -> #REF! | DJ153: 11.266 | DK153: 12.998 | DL153: 43.552 | DN153: 13.759 | DO153: 14.937 | DP153: 14.895 | DQ153: 13.595 | DR153: 57.217 | DT153: 7.074 | DU153: -7.224 | DV153: 16.732 | DW153: 18.259 | DX153: 34.842 | DZ153: 4.186 | EA153: 4.55 | EB153: -3.113 | EC153: -9.785 | ED153: -4.161 | EF153: -19.011 | EG153: -16.273 | EH153: -11.558 | EI153: -1.168 | EJ153: -48.01 | EL153: -7.116 | EM153: -2.051 | EN153: 3.305 | EO153: 9.348 | EP153: 3.486 | ER153: 3.492
C154: Non-GAAP Diluted E.P.S. | DH154: 0.03 | DI154: 0.05 | DJ154: 0.05 | DK154: 0.06 | DL154: 0.2 | DN154: 0.07 | DO154: 0.07 | DP154: 0.07 | DQ154: 0.1 | DR154: 0.31 | DT154: -0.02 | DU154: -0.04 | DV154: 0.06 | DW154: 0.14 | DX154: 0.15 | DZ154: -0.04 | EA154: -0.01 | EB154: -0.08 | EC154: -0.14 | ED154: -0.27 | EF154: -0.2 | EG154: -0.16 | EH154: -0.14 | EI154: -0.06 | EJ154: -0.56 | EL154: -0.09 | EM154: -0.05 | EN154: 0 | EO154: 0.03 | EP154: -0.12 | ER154: -0.02
C157: Non-GAAP Net income | DH157: =DH62-DH151 -> 1.144 | DI157: =DI62-DI151 -> 0 | DJ157: =DJ62-DJ151 -> 0 | DK157: =DK62-DK151 -> 0 | DL157: =DL62-DL151 -> 0.312 | DN157: =DN62-DN151 -> 0.537 | DO157: =DO62-DO151 -> -9.7699626e-15 | DP157: =DP62-DP151 -> 0 | DQ157: =DQ62-DQ151 -> 0 | DR157: =DR62-DR151 -> 0.536 | DT157: =DT62-DT151 -> 0 | DU157: =DU62-DU151 -> 1.1546319e-14 | DV157: =DV62-DV151 -> 0 | DW157: =DW62-DW151 -> 0 | DX157: =DX62-DX151 -> 6.750156e-14 | DZ157: =DZ62-DZ151 -> 0 | EA157: =EA62-EA151 -> 2.0095037e-14 | EB157: =EB62-EB151 -> 0 | EC157: =EC62-EC151 -> 0 | ED157: =ED62-ED151 -> -0.001 | EF157: =EF62-EF151 -> 0 | EG157: =EG62-EG151 -> 0 | EH157: =EH62-EH151 -> 0 | EI157: =EI62-EI151 -> 2.1316282e-14 | EJ157: =EJ62-EJ151 -> 0 | EL157: =EL62-EL151 -> 0 | EM157: =EM62-EM151 -> 0 | EN157: =EN62-EN151 -> -5.5511151e-16 | EO157: =EO62-EO151 -> 0 | EP157: =EP62-EP151 -> -8.5265128e-14 | ER157: =ER62-ER151 -> 8.437695e-15
...

Sheet Rev
B1: =IS!EY2 -> NeoGenomics
B2: Historical and Projected Revenue Statement
B3: =[44]IS!B3 -> Dollars in millions, except per share amounts
ER4: Historical results
D5: Historical results | J5: Historical results | P5: Historical results | V5: Historical results | AB5: Historical results | AH5: Historical results | AN5: Historical results | AT5: Historical results | AZ5: Historical results | BF5: Historical results | BL5: Historical results | BR5: Historical results | BX5: Historical results | CD5: Historical results | CJ5: Historical results | CP5: Historical results | CV5: Historical results | DB5: Historical results | DH5: Historical results | DN5: Historical results | DT5: Historical results | DZ5: Historical results | EF5: Historical results | EL5: Historical results | EX5: Historical results | FD5: Projections | FJ5: Projections | FP5: Projections
D6: 2000 | J6: 2001 | P6: 2002 | V6: 2003 | AB6: 2004 | AH6: 2005 | AN6: 2006 | AT6: 2007 | AZ6: 2008 | BF6: 2009 | BL6: 2010 | BR6: 2011 | BX6: 2012 | CD6: 2013 | CJ6: 2014 | CP6: 2015 | CV6: 2016 | DB6: 2017 | DH6: 2018 | DN6: 2019 | DT6: 2020 | DZ6: 2021 | EF6: =DZ6+1 -> 2022 | EL6: =EF6+1 -> 2023 | ER6: =EL6+1 -> 2024 | EX6: =ER6+1 -> 2025 | FD6: =EX6+1 -> 2026 | FJ6: =FD6+1 -> 2027 | FP6: =FJ6+1 -> 2028
D7: =[44]IS!D7 -> 36616 | E7: =[44]IS!E7 -> 36707 | F7: =[44]IS!F7 -> 36799 | G7: =[44]IS!G7 -> 36891 | H7: Total | J7: =[44]IS!J7 -> 36981 | K7: =[44]IS!K7 -> 37072 | L7: =[44]IS!L7 -> 37164 | M7: =[44]IS!M7 -> 37256 | N7: Total | P7: =[44]IS!P7 -> 37346 | Q7: =[44]IS!Q7 -> 37437 | R7: =[44]IS!R7 -> 37529 | S7: =[44]IS!S7 -> 37621 | T7: Total | V7: =[44]IS!V7 -> 37711 | W7: =[44]IS!W7 -> 37802 | X7: =[44]IS!X7 -> 37894 | Y7: =[44]IS!Y7 -> 37986 | Z7: Total | AB7: =[44]IS!AB7 -> 38077 | AC7: =[44]IS!AC7 -> 38168 | AD7: =[44]IS!AD7 -> 38260 | AE7: =[44]IS!AE7 -> 38352 | AF7: Total | AH7: =[44]IS!AH7 -> 38442 | AI7: =[44]IS!AI7 -> 38533 | AJ7: =[44]IS!AJ7 -> 38625 | AK7: =[44]IS!AK7 -> 38717 | AL7: Total | AN7: =[44]IS!AN7 -> 38807 | AO7: =[44]IS!AO7 -> 38898 | AP7: =[44]IS!AP7 -> 38990 | AQ7: =[44]IS!AQ7 -> 39082 | AR7: Total | AT7: =[44]IS!AT7 -> 39172 | AU7: =[44]IS!AU7 -> 39263 | AV7: =[44]IS!AV7 -> 39355 | AW7: =[44]IS!AW7 -> 39447 | AX7: Total | AZ7: =[44]IS!AZ7 -> 39537 | BA7: =[44]IS!BA7 -> 39628 | BB7: =[44]IS!BB7 -> 39720 | BC7: =[44]IS!BC7 -> 39812 | BD7: Total | BF7: =[44]IS!BF7 -> 39902 | BG7: =[44]IS!BG7 -> 39993 | BH7: =[44]IS!BH7 -> 40085 | BI7: =[44]IS!BI7 -> 40177 | BJ7: Total | BL7: =[44]IS!BL7 -> 40267 | BM7: =[44]IS!BM7 -> 40358 | BN7: =[44]IS!BN7 -> 40450 | BO7: =[44]IS!BO7 -> 40542 | BP7: Total | BR7: =[44]IS!BR7 -> 40632 | BS7: =[44]IS!BS7 -> 40723 | BT7: =[44]IS!BT7 -> 40815 | BU7: =[44]IS!BU7 -> 40907 | BV7: Total | BX7: =[44]IS!BX7 -> 40997 | BY7: =[44]IS!BY7 -> 41088 | BZ7: =[44]IS!BZ7 -> 41180 | CA7: =[44]IS!CA7 -> 41272 | CB7: Total | CD7: =[44]IS!CD7 -> 41362 | CE7: =[44]IS!CE7 -> 41453 | CF7: =[44]IS!CF7 -> 41545 | CG7: =[44]IS!CG7 -> 41637 | CH7: Total | CJ7: =[44]IS!CJ7 -> 41727 | CK7: =[44]IS!CK7 -> 41818 | CL7: =[44]IS!CL7 -> 41910 | CM7: =[44]IS!CM7 -> 42002 | CN7: Total | CP7: =[44]IS!CP7 -> 42092 | CQ7: =[44]IS!CQ7 -> 42183 | CR7: =[44]IS!CR7 -> 42275 | CS7: =[44]IS!CS7 -> 42367 | CT7: Total | CV7: =[44]IS!CV7 -> 42457 | CW7: =[44]IS!CW7 -> 42548 | CX7: =[44]IS!CX7 -> 42640 | CY7: =[44]IS!CY7 -> 42732 | CZ7: Total | DB7: =[44]IS!DB7 -> 42822 | DC7: =[44]IS!DC7 -> 42913 | DD7: =[44]IS!DD7 -> 43005 | DE7: =[44]IS!DE7 -> 43097 | DF7: Total | DH7: =[44]IS!DH7 -> 43187 | DI7: =[44]IS!DI7 -> 43278 | DJ7: =[44]IS!DJ7 -> 43370 | DK7: =[44]IS!DK7 -> 43462 | DL7: Total | DN7: =[44]IS!DN7 -> 43552 | DO7: =[44]IS!DO7 -> 43643 | DP7: =[44]IS!DP7 -> 43735 | DQ7: =[44]IS!DQ7 -> 43827 | DR7: Total | DT7: =[44]IS!DT7 -> 43917 | DU7: =[44]IS!DU7 -> 44008 | DV7: =[44]IS!DV7 -> 44100 | DW7: =[44]IS!DW7 -> 44192 | DX7: Total | DZ7: =IS!DZ7 -> 44285 | EA7: =IS!EA7 -> 44376 | EB7: =IS!EB7 -> 44468 | EC7: =IS!EC7 -> 44560 | ED7: Total | EF7: =IS!EF7 -> 44650 | EG7: =IS!EG7 -> 44741 | EH7: =IS!EH7 -> 44833 | EI7: =IS!EI7 -> 44925 | EJ7: Total | EL7: =IS!EL7 -> 45015 | EM7: =IS!EM7 -> 45106 | EN7: =IS!EN7 -> 45198 | EO7: =IS!EO7 -> 45290 | EP7: Total | ER7: =IS!ER7 -> 45382 | ES7: =IS!ES7 -> 45473 | ET7: =IS!ET7 -> 45565 | EU7: =IS!EU7 -> 45657 | EV7: Total | EX7: =IS!EX7 -> 45747 | EY7: =IS!EY7 -> 45838 | EZ7: =IS!EZ7 -> 45930 | FA7: =IS!FA7 -> 46022 | FB7: Total | FD7: =IS!FD7 -> 46112 | FE7: =IS!FE7 -> 46203 | FF7: =IS!FF7 -> 46295 | FG7: =IS!FG7 -> 46387 | FH7: Total | FJ7: =IS!FJ7 -> 46477 | FK7: =IS!FK7 -> 46568 | FL7: =IS!FL7 -> 46660 | FM7: =IS!FM7 -> 46752 | FN7: Total | FP7: =IS!FP7 -> 46843 | FQ7: =IS!FQ7 -> 46934 | FR7: =IS!FR7 -> 47026 | FS7: =IS!FS7 -> 47118 | FT7: Total
EB8: =EB9/DZ9 -> 1.0423868 | EH8: =EH9/EF9 -> 1.0484381 | EN8: =EN9/EL9 -> 1.0822855
DZ9: =SUM(DZ10:EA10) -> 197.892 | EB9: =SUM(EB10:EC10) -> 206.28 | EF9: =SUM(EF10:EG10) -> 204.426 | EH9: =SUM(EH10:EI10) -> 214.328 | EL9: =SUM(EL10:EM10) -> 238.025 | EN9: =SUM(EN10:EO10) -> 257.611
B10: Clinical Services (ex. Pathline) | DB10: 51.329 | DC10: 53.978 | DD10: 50.74 | DE10: 53.456 | DF10: =SUM(DB10:DE10) -> 209.503 | DH10: 56.971 | DI10: 59.54 | DJ10: 59.449 | DK10: 65.913 | DL10: =SUM(DH10:DK10) -> 241.873 | DN10: 86.21 | DO10: 88.982 | DP10: 92.565 | DQ10: 93.405 | DR10: =SUM(DN10:DQ10) -> 361.162 | DT10: 92.982 | DU10: 73.884 | DV10: 108.733 | DW10: 106.738 | DX10: =SUM(DT10:DW10) -> 382.337 | DZ10: 96.487 | EA10: 101.405 | EB10: 102.227 | EC10: 104.053 | ED10: =SUM(DZ10:EC10) -> 404.172 | EF10: 98.791 | EG10: 105.635 | EH10: 106.162 | EI10: 108.166 | EJ10: =SUM(EF10:EI10) -> 418.754 | EL10: 114.869 | EM10: 123.156 | EN10: 127.553 | EO10: 130.058 | EP10: =SUM(EL10:EO10) -> 495.636 | ER10: 134.535 | ES10: 141.388 | ET10: 145.783 | EU10: =(EU19*EU25)/1000000 -> 149.58074 | EV10: =SUM(ER10:EU10) -> 571.28674 | EX10: =(EX19*EX25)/1000000 -> 149.70882 | EY10: =(EY19*EY25)/1000000 -> 159.49732 | EZ10: =(EZ19*EZ25)/1000000 -> 167.01041 | FA10: =(FA19*FA25)/1000000 -> 169.92266 | FB10: =SUM(EX10:FA10) -> 646.13921 | FD10: =(FD19*FD25)/1000000 -> 164.22309 | FE10: =(FE19*FE25)/1000000 -> 175.44706 | FF10: =(FF19*FF25)/1000000 -> 183.97867 | FG10: =(FG19*FG25)/1000000 -> 189.12392 | FH10: =SUM(FD10:FG10) -> 712.77273 | FJ10: =(FJ19*FJ25)/1000000 -> 180.99026 | FK10: =(FK19*FK25)/1000000 -> 193.3602 | FL10: =(FL19*FL25)/1000000 -> 202.7629 | FM10: =(FM19*FM25)/1000000 -> 208.43347 | FN10: =SUM(FJ10:FM10) -> 785.54683 | FP10: =(FP19*FP25)/1000000 -> 199.46937 | FQ10: =(FQ19*FQ25)/1000000 -> 213.10228 | FR10: =(FR19*FR25)/1000000 -> 223.46499 | FS10: =(FS19*FS25)/1000000 -> 229.71453 | FT10: =SUM(FP10:FS10) -> 865.75116
C11: growth y/y | DH11: =DH10/DB10-1 -> 0.10991837 | DI11: =DI10/DC10-1 -> 0.10304198 | DJ11: =DJ10/DD10-1 -> 0.17163973 | DK11: =DK10/DE10-1 -> 0.23303277 | DL11: =DL10/DF10-1 -> 0.15450853 | DN11: =DN10/DH10-1 -> 0.51322603 | DO11: =DO10/DI10-1 -> 0.4944911 | DP11: =DP10/DJ10-1 -> 0.5570489 | DQ11: =DQ10/DK10-1 -> 0.41709526 | DR11: =DR10/DL10-1 -> 0.49318857 | DT11: =DT10/DN10-1 -> 0.078552372 | DU11: =DU10/DO10-1 -> -0.16967477 | DV11: =DV10/DP10-1 -> 0.17466645 | DW11: =DW10/DQ10-1 -> 0.14274396 | DX11: =DX10/DR10-1 -> 0.058630199 | DZ11: =DZ10/DT10-1 -> 0.037695468 | EA11: =EA10/DU10-1 -> 0.37248931 | EB11: =EB10/DV10-1 -> -0.059834641 | EC11: =EC10/DW10-1 -> -0.025155053 | ED11: =ED10/DX10-1 -> 0.057109304 | EF11: =EF10/DZ10-1 -> 0.023878865 | EG11: =EG10/EA10-1 -> 0.041713919 | EH11: =EH10/EB10-1 -> 0.038492766 | EI11: =EI10/EC10-1 -> 0.039527933 | EJ11: =EJ10/ED10-1 -> 0.036078699 | EL11: =EL10/EF10-1 -> 0.16274762 | EM11: =EM10/EG10-1 -> 0.16586359 | EN11: =EN10/EH10-1 -> 0.20149394 | EO11: =EO10/EI10-1 -> 0.20239262 | EP11: =EP10/EJ10-1 -> 0.18359705 | ER11: =ER10/EL10-1 -> 0.17120372 | ES11: =ES10/EM10-1 -> 0.14803988 | ET11: =ET10/EN10-1 -> 0.14292098 | EU11: =EU10/EO10-1 -> 0.15010791 | EV11: =EV10/EP10-1 -> 0.15263366 | EX11: =EX10/ER10-1 -> 0.11278713 | EY11: =EY10/ES10-1 -> 0.12808248 | EZ11: =EZ10/ET10-1 -> 0.14560967 | FA11: =FA10/EU10-1 -> 0.13599292 | FB11: =FB10/EV10-1 -> 0.13102436 | FD11: =FD10/EX10-1 -> 0.09695 | FE11: =FE10/EY10-1 -> 0.1 | FF11: =FF10/EZ10-1 -> 0.1016 | FG11: =FG10/FA10-1 -> 0.113 | FH11: =FH10/FB10-1 -> 0.10312564 | FJ11: =FJ10/FD10-1 -> 0.1021 | FK11: =FK10/FE10-1 -> 0.1021 | FL11: =FL10/FF10-1 -> 0.1021 | FM11: =FM10/FG10-1 -> 0.1021 | FN11: =FN10/FH10-1 -> 0.1021 | FP11: =FP10/FJ10-1 -> 0.1021 | FQ11: =FQ10/FK10-1 -> 0.1021 | FR11: =FR10/FL10-1 -> 0.1021 | FS11: =FS10/FM10-1 -> 0.1021 | FT11: =FT10/FN10-1 -> 0.1021
C12: growth q/q (%) | DC12: =DC10/DB10-1 -> 0.051608253 | DD12: =DD10/DC10-1 -> -0.059987402 | DE12: =DE10/DD10-1 -> 0.053527789 | DH12: =DH10/DE10-1 -> 0.065755013 | DI12: =DI10/DH10-1 -> 0.045093118 | DJ12: =DJ10/DI10-1 -> -0.0015283843 | DK12: =DK10/DJ10-1 -> 0.10873185 | DN12: =DN10/DK10-1 -> 0.30793622 | DO12: =DO10/DN10-1 -> 0.032154042 | DP12: =DP10/DO10-1 -> 0.040266571 | DQ12: =DQ10/DP10-1 -> 0.0090747043 | DT12: =DT10/DQ10-1 -> -0.0045286655 | DU12: =DU10/DT10-1 -> -0.20539459 | DV12: =DV10/DU10-1 -> 0.47167181 | DW12: =DW10/DV10-1 -> -0.018347696 | DZ12: =DZ10/DW10-1 -> -0.096038899 | EA12: =EA10/DZ10-1 -> 0.050970597 | EB12: =EB10/EA10-1 -> 0.0081061092 | EC12: =EC10/EB10-1 -> 0.017862209 | EF12: =EF10/EC10-1 -> -0.050570382 | EG12: =EG10/EF10-1 -> 0.069277566 | EH12: =EH10/EG10-1 -> 0.0049888768 | EI12: =EI10/EH10-1 -> 0.018876811 | EL12: =EL10/EI10-1 -> 0.061969565 | EM12: =EM10/EL10-1 -> 0.07214305 | EN12: =EN10/EM10-1 -> 0.035702686 | EO12: =EO10/EN10-1 -> 0.019638895 | ER12: =ER10/EO10-1 -> 0.034423104 | ES12: =ES10/ER10-1 -> 0.050938418 | ET12: =ET10/ES10-1 -> 0.031084675 | EU12: =EU10/ET10-1 -> 0.026050603 | EX12: =EX10/EU10-1 -> 0.00085627337 | EY12: =EY10/EX10-1 -> 0.065383644 | EZ12: =EZ10/EY10-1 -> 0.047104803 | FA12: =FA10/EZ10-1 -> 0.017437481
C13: growth q/q ($) | DC13: =DC10-DB10 -> 2.649 | DD13: =DD10-DC10 -> -3.238 | DE13: =DE10-DD10 -> 2.716 | DH13: =DH10-DE10 -> 3.515 | DI13: =DI10-DH10 -> 2.569 | DJ13: =DJ10-DI10 -> -0.091 | DK13: =DK10-DJ10 -> 6.464 | DN13: =DN10-DK10 -> 20.297 | DO13: =DO10-DN10 -> 2.772 | DP13: =DP10-DO10 -> 3.583 | DQ13: =DQ10-DP10 -> 0.84 | DT13: =DT10-DQ10 -> -0.423 | DU13: =DU10-DT10 -> -19.098 | DV13: =DV10-DU10 -> 34.849 | DW13: =DW10-DV10 -> -1.995 | DZ13: =DZ10-DW10 -> -10.251 | EA13: =EA10-DZ10 -> 4.918 | EB13: =EB10-EA10 -> 0.822 | EC13: =EC10-EB10 -> 1.826 | EF13: =EF10-EC10 -> -5.262 | EG13: =EG10-EF10 -> 6.844 | EH13: =EH10-EG10 -> 0.527 | EI13: =EI10-EH10 -> 2.004 | EL13: =EL10-EI10 -> 6.703 | EM13: =EM10-EL10 -> 8.287 | EN13: =EN10-EM10 -> 4.397 | EO13: =EO10-EN10 -> 2.505 | ER13: =ER10-EO10 -> 4.477 | ES13: =ES10-ER10 -> 6.853 | ET13: =ET10-ES10 -> 4.395 | EU13: =EU10-ET10 -> 3.797735 | EX13: =EX10-EU10 -> 0.128082 | EY13: =EY10-EX10 -> 9.788508 | EZ13: =EZ10-EY10 -> 7.51309 | FA13: =FA10-EZ10 -> 2.912241
C14: % of revenue | DB14: =DB10/DB90 -> 0.91905103 | DC14: =DC10/DC90 -> 0.88933191 | DD14: =DD10/DD90 -> 0.86454251 | DE14: =DE10/DE90 -> 0.87030706 | DF14: =DF10/DF90 -> 0.8852601 | DH14: =DH10/DH90 -> 0.89827034 | DI14: =DI10/DI90 -> 0.87887108 | DJ14: =DJ10/DJ90 -> 0.86038266 | DK14: =DK10/DK90 -> 0.86188951 | DL14: =DL10/DL90 -> 0.87400809 | DN14: =DN10/DN90 -> 0.90199525 | DO14: =DO10/DO90 -> 0.87483409 | DP14: =DP10/DP90 -> 0.88433392 | DQ14: =DQ10/DQ90 -> 0.87402216 | DR14: =DR10/DR90 -> 0.88340386 | DT14: =DT10/DT90 -> 0.87694049 | DU14: =DU10/DU90 -> 0.84946595 | DV14: =DV10/DV90 -> 0.86678518 | DW14: =DW10/DW90 -> 0.84714715 | DX14: =DX10/DX90 -> 0.86025137 | DZ14: =DZ10/DZ90 -> 0.83514667 | EA14: =EA10/EA90 -> 0.83307318 | EB14: =EB10/EB90 -> 0.84248393 | EC14: =EC10/EC90 -> 0.8275777 | ED14: =ED10/ED90 -> 0.83449886 | EF14: =EF10/EF90 -> 0.84314964 | EG14: =EG10/EG90 -> 0.84459351 | EH14: =EH10/EH90 -> 0.82435434 | EI14: =EI10/EI90 -> 0.77982769 | EJ14: =EJ10/EJ90 -> 0.82152442 | EL14: =EL10/EL90 -> 0.83711558 | EM14: =EM10/EM90 -> 0.83826923 | EN14: =EN10/EN90 -> 0.83941851 | EO14: =EO10/EO90 -> 0.83610625 | EP14: =EP10/EP90 -> 0.83772816 | ER14: =ER10/ER90 -> 0.86107911 | ES14: =ES10/ES90 -> 0.85949107 | ET14: =ET10/ET90 -> 0.86866598 | EU14: =EU10/EU90 -> 0.86965544 | EX14: =EX10/EX90 -> 0.8909383 | EY14: =EY10/EY90 -> 0.87959701 | EZ14: =EZ10/EZ90 -> 0.88931354 | FA14: =FA10/FA90 -> 0.89353029
C16: Requisitions | DB16: 94528 | DC16: 99247 | DD16: 98031 | DE16: 102714 | DF16: =SUM(DB16:DE16) -> 394520 | DH16: 105229 | DI16: 109986 | DJ16: 108467 | DK16: 115915 | DL16: =SUM(DH16:DK16) -> 439597 | DN16: 137111 | DO16: 144983 | DP16: 143312 | DQ16: 145679 | DR16: =SUM(DN16:DQ16) -> 571085 | DT16: 144319 | DU16: 114413 | DV16: 147518 | DW16: 153170 | DX16: =SUM(DT16:DW16) -> 559420 | DZ16: 151145 | EA16: 163128 | EB16: 159625 | EC16: 159553 | ED16: =SUM(DZ16:EC16) -> 633451
C17: growth y/y | DH17: =DH16/DB16-1 -> 0.11320455 | DI17: =DI16/DC16-1 -> 0.10820478 | DJ17: =DJ16/DD16-1 -> 0.10645612 | DK17: =DK16/DE16-1 -> 0.12852192 | DL17: =DL16/DF16-1 -> 0.11425783 | DN17: =DN16/DH16-1 -> 0.30297732 | DO17: =DO16/DI16-1 -> 0.31819504 | DP17: =DP16/DJ16-1 -> 0.32124978 | DQ17: =DQ16/DK16-1 -> 0.25677436 | DR17: =DR16/DL16-1 -> 0.29911032 | DT17: =DT16/DN16-1 -> 0.052570545 | DU17: =DU16/DO16-1 -> -0.21085231 | DV17: =DV16/DP16-1 -> 0.029348554 | DW17: =DW16/DQ16-1 -> 0.051421276 | DX17: =DX16/DR16-1 -> -0.020426031 | DZ17: =DZ16/DT16-1 -> 0.047298 | EA17: =EA16/DU16-1 -> 0.42578204 | EB17: =EB16/DV16-1 -> 0.08207134 | EC17: =EC16/DW16-1 -> 0.041672651 | ED17: =ED16/DX16-1 -> 0.13233528
C19: Volume | DB19: 155567 | DC19: 163620 | DD19: 163289 | DE19: 174918 | DF19: =SUM(DB19:DE19) -> 657394 | DH19: 178794 | DI19: 187189 | DJ19: 185738 | DK19: 198181 | DL19: =SUM(DH19:DK19) -> 749902 | DN19: 234317 | DO19: 250330 | DP19: 250518 | DQ19: 252374 | DR19: =SUM(DN19:DQ19) -> 987539 | DT19: 250376 | DU19: 204844 | DV19: 255458 | DW19: 265391 | DX19: =SUM(DT19:DW19) -> 976069 | DZ19: 260941 | EA19: 281335 | EB19: 272732 | EC19: 271760 | ED19: =SUM(DZ19:EC19) -> 1086768 | EF19: 266035 | EG19: 272982 | EH19: 270899 | EI19: 278089 | EJ19: =SUM(EF19:EI19) -> 1088005 | EL19: 285476 | EM19: 295116 | EN19: 289637 | EO19: 294850 | EP19: =SUM(EL19:EO19) -> 1165079 | ER19: 300827 | ES19: 311670 | ET19: 314564 | EU19: 321679 | EV19: =SUM(ER19:EU19) -> 1248740 | EX19: 326163 | EY19: 343005 | EZ19: 347215 | FA19: 342586 | FB19: =SUM(EX19:FA19) -> 1358969 | FD19: =EX19*(1+FD20) -> 335947.89 | FE19: =EY19*(1+FE20) -> 343005 | FF19: =EZ19*(1+FF20) -> 354159.3 | FG19: =FA19*(1+FG20) -> 359715.3 | FH19: =SUM(FD19:FG19) -> 1392827.5 | FJ19: =FD19*(1+FJ20) -> 346026.33 | FK19: =FE19*(1+FK20) -> 353295.15 | FL19: =FF19*(1+FL20) -> 364784.08 | FM19: =FG19*(1+FM20) -> 370506.76 | FN19: =SUM(FJ19:FM19) -> 1434612.3 | FP19: =FJ19*(1+FP20) -> 356407.12 | FQ19: =FK19*(1+FQ20) -> 363894 | FR19: =FL19*(1+FR20) -> 375727.6 | FS19: =FM19*(1+FS20) -> 381621.96 | FT19: =SUM(FP19:FS19) -> 1477650.7
C20: growth y/y | DH20: =DH19/DB19-1 -> 0.14930544 | DI20: =DI19/DC19-1 -> 0.14404718 | DJ20: =DJ19/DD19-1 -> 0.13748017 | DK20: =DK19/DE19-1 -> 0.13299375 | DL20: =DL19/DF19-1 -> 0.14071926 | DN20: =DN19/DH19-1 -> 0.31054174 | DO20: =DO19/DI19-1 -> 0.33731149 | DP20: =DP19/DJ19-1 -> 0.34877085 | DQ20: =DQ19/DK19-1 -> 0.27345205 | DR20: =DR19/DL19-1 -> 0.31689074 | DT20: =DT19/DN19-1 -> 0.06853536 | DU20: =DU19/DO19-1 -> -0.18170415 | DV20: =DV19/DP19-1 -> 0.019719142 | DW20: =DW19/DQ19-1 -> 0.051578213 | DX20: =DX19/DR19-1 -> -0.011614731 | DZ20: =DZ19/DT19-1 -> 0.042196536 | EA20: =EA19/DU19-1 -> 0.37341099 | EB20: =EB19/DV19-1 -> 0.067619726 | EC20: =EC19/DW19-1 -> 0.023998553 | ED20: =ED19/DX19-1 -> 0.11341309 | EF20: =EF19/DZ19-1 -> 0.019521654 | EG20: =EG19/EA19-1 -> -0.029690582 | EH20: =EH19/EB19-1 -> -0.0067208835 | EI20: =EI19/EC19-1 -> 0.023288931 | EJ20: =EJ19/ED19-1 -> 0.0011382374 | EL20: =EL19/EF19-1 -> 0.073076851 | EM20: =EM19/EG19-1 -> 0.081082269 | EN20: =EN19/EH19-1 -> 0.069169691 | EO20: =EO19/EI19-1 -> 0.060272071 | EP20: =EP19/EJ19-1 -> 0.070839748 | ER20: =ER19/EL19-1 -> 0.053773347 | ES20: =ES19/EM19-1 -> 0.056093197 | ET20: =ET19/EN19-1 -> 0.086062899 | EU20: =EU19/EO19-1 -> 0.09099203 | EV20: =EV19/EP19-1 -> 0.071807148 | EX20: =EX19/ER19-1 -> 0.084221164 | EY20: =EY19/ES19-1 -> 0.10053903 | EZ20: =EZ19/ET19-1 -> 0.10379764 | FA20: =FA19/EU19-1 -> 0.064993363 | FB20: =FB19/EV19-1 -> 0.088272178 | FD20: 0.03 | FE20: 0 | FF20: 0.02 | FG20: 0.05 | FH20: =FH19/FB19-1 -> 0.024914836 | FJ20: 0.03 | FK20: 0.03 | FL20: 0.03 | FM20: 0.03 | FN20: =FN19/FH19-1 -> 0.03 | FP20: 0.03 | FQ20: 0.03 | FR20: 0.03 | FS20: 0.03 | FT20: =FT19/FN19-1 -> 0.03
C22: Tests per case | DB22: =DB19/DB16 -> 1.645724 | DC22: =DC19/DC16 -> 1.6486141 | DD22: =DD19/DD16 -> 1.6656874 | DE22: =DE19/DE16 -> 1.7029616 | DF22: =DF19/DF16 -> 1.6663135 | DH22: =DH19/DH16 -> 1.6990944 | DI22: =DI19/DI16 -> 1.7019348 | DJ22: =DJ19/DJ16 -> 1.7123918 | DK22: =DK19/DK16 -> 1.7097097 | DL22: =DL19/DL16 -> 1.7058852 | DN22: =DN19/DN16 -> 1.7089584 | DO22: =DO19/DO16 -> 1.7266162 | DP22: =DP19/DP16 -> 1.7480602 | DQ22: =DQ19/DQ16 -> 1.7323979 | DR22: =DR19/DR16 -> 1.729233 | DT22: =DT19/DT16 -> 1.734879 | DU22: =DU19/DU16 -> 1.790391 | DV22: =DV19/DV16 -> 1.7317073 | DW22: =DW19/DW16 -> 1.7326565 | DX22: =DX19/DX16 -> 1.7447875 | DZ22: =DZ19/DZ16 -> 1.7264283 | EA22: =EA19/EA16 -> 1.7246273 | EB22: =EB19/EB16 -> 1.7085795 | EC22: =EC19/EC16 -> 1.7032585 | ED22: =ED19/ED16 -> 1.7156307
C23: growth y/y | DH23: =DH22/DB22-1 -> 0.032429701 | DI23: =DI22/DC22-1 -> 0.032342759 | DJ23: =DJ22/DD22-1 -> 0.028039117 | DK23: =DK22/DE22-1 -> 0.0039625552 | DL23: =DL22/DF22-1 -> 0.023748033 | DN23: =DN22/DH22-1 -> 0.0058054922 | DO23: =DO22/DI22-1 -> 0.014501985 | DP23: =DP22/DJ22-1 -> 0.020829573 | DQ23: =DQ22/DK22-1 -> 0.013270231 | DR23: =DR22/DL22-1 -> 0.013686612 | DT23: =DT22/DN22-1 -> 0.015167454 | DU23: =DU22/DO22-1 -> 0.03693625 | DV23: =DV22/DP22-1 -> -0.0093548606 | DW23: =DW22/DQ22-1 -> 0.00014926248 | DX23: =DX22/DR22-1 -> 0.0089950328 | DZ23: =DZ22/DT22-1 -> -0.0048710712 | EA23: =EA22/DU22-1 -> -0.036731455 | EB23: =EB22/DV22-1 -> -0.01335551 | EC23: =EC22/DW22-1 -> -0.016967037 | ED23: =ED22/DX22-1 -> -0.016710764
C25: ASP/test | DB25: =DB10/DB19*1000000 -> 329.94787 | DC25: =DC10/DC19*1000000 -> 329.89855 | DD25: =DD10/DD19*1000000 -> 310.7374 | DE25: =DE10/DE19*1000000 -> 305.60606 | DF25: =DF10/DF19*1000000 -> 318.68712 | DH25: =DH10/DH19*1000000 -> 318.64045 | DI25: =DI10/DI19*1000000 -> 318.07425 | DJ25: =DJ10/DJ19*1000000 -> 320.06913 | DK25: =DK10/DK19*1000000 -> 332.58991 | DL25: =DL10/DL19*1000000 -> 322.53948 | DN25: =DN10/DN19*1000000 -> 367.92038 | DO25: =DO10/DO19*1000000 -> 355.45879 | DP25: =DP10/DP19*1000000 -> 369.49441 | DQ25: =DQ10/DQ19*1000000 -> 370.10548 | DR25: =DR10/DR19*1000000 -> 365.71923 | DT25: =DT10/DT19*1000000 -> 371.36946 | DU25: =DU10/DU19*1000000 -> 360.68423 | DV25: =DV10/DV19*1000000 -> 425.63944 | DW25: =DW10/DW19*1000000 -> 402.19148 | DX25: =DX10/DX19*1000000 -> 391.71104 | DZ25: =DZ10/DZ19*1000000 -> 369.76558 | EA25: =EA10/EA19*1000000 -> 360.44218 | EB25: =EB10/EB19*1000000 -> 374.82584 | EC25: =EC10/EC19*1000000 -> 382.88563 | ED25: =ED10/ED19*1000000 -> 371.90274 | EF25: =EF10/EF19*1000000 -> 371.34588 | EG25: =EG10/EG19*1000000 -> 386.96691 | EH25: =EH10/EH19*1000000 -> 391.88775 | EI25: =EI10/EI19*1000000 -> 388.96181 | EJ25: =EJ10/EJ19*1000000 -> 384.88242 | EL25: =EL10/EL19*1000000 -> 402.37708 | EM25: =EM10/EM19*1000000 -> 417.31387 | EN25: =EN10/EN19*1000000 -> 440.38918 | EO25: =EO10/EO19*1000000 -> 441.09886 | EP25: =EP10/EP19*1000000 -> 425.40978 | ER25: =ER10/ER19*1000000 -> 447.21717 | ES25: =ES10/ES19*1000000 -> 453.64649 | ET25: =ET10/ET19*1000000 -> 463.44464 | EU25: 465 | EV25: =EV10/EV19*1000000 -> 457.49054 | EX25: 459 | EY25: 465 | EZ25: 481 | FA25: 496 | FB25: =FB10/FB19*1000000 -> 475.46281 | FD25: =EX25*(1+FD26) -> 488.835 | FE25: =EY25*(1+FE26) -> 511.5 | FF25: =EZ25*(1+FF26) -> 519.48 | FG25: =FA25*(1+FG26) -> 525.76 | FH25: =FH10/FH19*1000000 -> 511.74516 | FJ25: =FD25*(1+FJ26) -> 523.05345 | FK25: =FE25*(1+FK26) -> 547.305 | FL25: =FF25*(1+FL26) -> 555.8436 | FM25: =FG25*(1+FM26) -> 562.5632 | FN25: =FN10/FN19*1000000 -> 547.56733 | FP25: =FJ25*(1+FP26) -> 559.66719 | FQ25: =FK25*(1+FQ26) -> 585.61635 | FR25: =FL25*(1+FR26) -> 594.75265 | FS25: =FM25*(1+FS26) -> 601.94262 | FT25: =FT10/FT19*1000000 -> 585.89704
C26: growth y/y | DH26: =DH25/DB25-1 -> -0.034270328 | DI26: =DI25/DC25-1 -> -0.03584223 | DJ26: =DJ25/DD25-1 -> 0.030030905 | DK26: =DK25/DE25-1 -> 0.088296188 | DL26: =DL25/DF25-1 -> 0.012088218 | DN26: =DN25/DH25-1 -> 0.15465687 | DO26: =DO25/DI25-1 -> 0.11753403 | DP26: =DP25/DJ25-1 -> 0.15442063 | DQ26: =DQ25/DK25-1 -> 0.11279829 | DR26: =DR25/DL25-1 -> 0.13387431 | DT26: =DT25/DN25-1 -> 0.0093745254 | DU26: =DU25/DO25-1 -> 0.014700533 | DV26: =DV25/DP25-1 -> 0.15195097 | DW26: =DW25/DQ25-1 -> 0.086694218 | DX26: =DX25/DR25-1 -> 0.071070394 | DZ26: =DZ25/DT25-1 -> -0.0043188289 | EA26: =EA25/DU25-1 -> -0.00067108707 | EB26: =EB25/DV25-1 -> -0.1193818 | EC26: =EC25/DW25-1 -> -0.048001636 | ED26: =ED25/DX25-1 -> -0.050568639 | EF26: =EF25/DZ25-1 -> 0.004273779 | EG26: =EG25/EA25-1 -> 0.073589414 | EH26: =EH25/EB25-1 -> 0.045519581 | EI26: =EI25/EC25-1 -> 0.01586942 | EJ26: =EJ25/ED25-1 -> 0.034900736 | EL26: =EL25/EF25-1 -> 0.083564162 | EM26: =EM25/EG25-1 -> 0.078422633 | EN26: =EN25/EH25-1 -> 0.12376357 | EO26: =EO25/EI25-1 -> 0.13404158 | EP26: =EP25/EJ25-1 -> 0.10529802 | ER26: =ER25/EL25-1 -> 0.11143798 | ES26: =ES25/EM25-1 -> 0.087063043 | ET26: =ET25/EN25-1 -> 0.052352477 | EU26: =EU25/EO25-1 -> 0.05418544 | EV26: =EV25/EP25-1 -> 0.075411429 | EX26: =EX25/ER25-1 -> 0.026346995 | EY26: =EY25/ES25-1 -> 0.02502723 | EZ26: =EZ25/ET25-1 -> 0.037880164 | FA26: =FA25/EU25-1 -> 0.066666667 | FB26: =FB25/EV25-1 -> 0.039284456 | FD26: 0.065 | FE26: 0.1 | FF26: 0.08 | FG26: 0.06 | FH26: =FH25/FB25-1 -> 0.076309565 | FJ26: 0.07 | FK26: 0.07 | FL26: 0.07 | FM26: 0.07 | FN26: =FN25/FH25-1 -> 0.07 | FP26: 0.07 | FQ26: 0.07 | FR26: 0.07 | FS26: 0.07 | FT26: =FT25/FN25-1 -> 0.07
C28: Core ASP | DU28: 351 | DV28: 359 | DW28: 369 | DX28: 363 | DZ28: 355 | EA28: 360
C29: growth y/y | DU29: =DU28/DO25-1 -> -0.012543773 | DV29: =DV28/DP25-1 -> -0.028402074 | DW29: =DW28/DQ25-1 -> -0.0029869279 | DX29: =DX28/DR25-1 -> -0.0074352867 | DZ29: =DZ28/DT25-1 -> -0.044078639 | EA29: =EA28/DU25-1 -> -0.0018970278
C31: COVID revenues | DU31: =((DU25-DU28)*DU19)/1000000 -> 1.983756 | DV31: =((DV25-DV28)*DV19)/1000000 -> 17.023578 | DW31: =((DW25-DW28)*DW19)/1000000 -> 8.808721 | DX31: =((DX25-DX28)*DX19)/1000000 -> 28.023953 | DZ31: =((DZ25-DZ28)*DZ19)/1000000 -> 3.852945 | EA31: =((EA25-EA28)*EA19)/1000000 -> 0.1244
C33: NGS | EF33: =EF10*EF35 -> 18.77029 | EG33: =EG10*EG35 -> 21.127 | EH33: =EH10*EH35 -> 22.29402 | EI33: =EI10*EI35 -> 23.79652 | EJ33: =SUM(EF33:EI33) -> 85.98783 | EL33: =EL10*EL35 -> 26.41987 | EM33: =EM10*EM35 -> 29.55744 | EN33: =EN10*EN35 -> 33.16378 | EO33: =EO10*EO35 -> 33.81508 | EP33: =SUM(EL33:EO33) -> 122.95617 | ER33: =ER10*ER35 -> 39.687825 | ES33: =ES10*ES35 -> 42.4164 | ET33: =ET10*ET35 -> 42.27707 | EU33: =EU10*EU35 -> 41.882606 | EV33: =SUM(ER33:EU33) -> 166.2639 | EX33: =EX10*EX35 -> 46.784005 | EY33: =EY10*EY35 -> 51.756882 | EZ33: =EZ10*EZ35 -> 52.608281 | FA33: =FA10*FA35 -> 51.401603 | FB33: =SUM(EX33:FA33) -> 202.55077 | FD33: =EX33*(1+FD34) -> 58.480007 | FE33: =EY33*(1+FE34) -> 64.696102 | FF33: =EZ33*(1+FF34) -> 65.760351 | FG33: =FA33*(1+FG34) -> 64.252004 | FH33: =SUM(FD33:FG33) -> 253.18846 | FJ33: =FD33*(1+FJ34) -> 76.024009 | FK33: =FE33*(1+FK34) -> 84.104933 | FL33: =FF33*(1+FL34) -> 85.488456 | FM33: =FG33*(1+FM34) -> 83.527606 | FN33: =SUM(FJ33:FM33) -> 329.145 | FP33: =FJ33*(1+FP34) -> 98.831211 | FQ33: =FK33*(1+FQ34) -> 109.33641 | FR33: =FL33*(1+FR34) -> 111.13499 | FS33: =FM33*(1+FS34) -> 108.58589 | FT33: =SUM(FP33:FS33) -> 427.8885
C34: growth y/y | ED34: 0.22 | EL34: =EL33/EF33-1 -> 0.40753659 | EM34: =EM33/EG33-1 -> 0.3990363 | EN34: =EN33/EH33-1 -> 0.48756393 | EO34: =EO33/EI33-1 -> 0.42100946 | EP34: =EP33/EJ33-1 -> 0.42992526 | ER34: =ER33/EL33-1 -> 0.50219607 | ES34: =ES33/EM33-1 -> 0.43504986 | ET34: =ET33/EN33-1 -> 0.27479648 | EU34: =EU33/EO33-1 -> 0.23857775 | EV34: =EV33/EP33-1 -> 0.35222088 | EX34: =EX33/ER33-1 -> 0.17879993 | EY34: =EY33/ES33-1 -> 0.22020921 | EZ34: =EZ33/ET33-1 -> 0.24436913 | FA34: =FA33/EU33-1 -> 0.22727807 | FB34: =FB33/EV33-1 -> 0.21824864 | FD34: 0.25 | FE34: 0.25 | FF34: 0.25 | FG34: 0.25 | FH34: =FH33/FB33-1 -> 0.25 | FJ34: 0.3 | FK34: 0.3 | FL34: 0.3 | FM34: 0.3 | FN34: =FN33/FH33-1 -> 0.3 | FP34: 0.3 | FQ34: 0.3 | FR34: 0.3 | FS34: 0.3 | FT34: =FT33/FN33-1 -> 0.3
C35: % of clinical services | EF35: 0.19 | EG35: 0.2 | EH35: 0.21 | EI35: 0.22 | EJ35: =EJ33/EJ10 -> 0.20534211 | EL35: 0.23 | EM35: 0.24 | EN35: 0.26 | EO35: 0.26 | EP35: =EP33/EP10 -> 0.24807756 | ER35: 0.295 | ES35: 0.3 | ET35: 0.29 | EU35: 0.28 | EV35: =EV33/EV10 -> 0.29103407 | EX35: 0.3125 | EY35: 0.3245 | EZ35: 0.315 | FA35: 0.3025 | FB35: =FB33/FB10 -> 0.31347853 | FD35: =FD33/FD10 -> 0.35610101 | FE35: =FE33/FE10 -> 0.36875 | FF35: =FF33/FF10 -> 0.35743464 | FG35: =FG33/FG10 -> 0.33973495 | FH35: =FH33/FH10 -> 0.35521626 | FJ35: =FJ33/FJ10 -> 0.42004474 | FK35: =FK33/FK10 -> 0.43496507 | FL35: =FL33/FL10 -> 0.42161785 | FM35: =FM33/FM10 -> 0.40073989 | FN35: =FN33/FN10 -> 0.41900112 | FP35: =FP33/FP10 -> 0.49547061 | FQ35: =FQ33/FQ10 -> 0.51307013 | FR35: =FR33/FR10 -> 0.4973262 | FS35: =FS33/FS10 -> 0.47269927 | FT35: =FT33/FT10 -> 0.4942396
C37: Pantracer Tissue | EP37: =EJ33*0.2 -> 17.197566 | EV37: =(EP33*0.15)+EP37 -> 35.640991 | FB37: =(EV33*0.15)+EV37 -> 60.580577
C38: growth y/y | EV38: =EV37/EP37-1 -> 1.0724439 | FB38: =FB37/EV37-1 -> 0.69974443
C40: Pantracer Liquid
C41: Volumes | EZ41: 750 | FA41: 1000 | FB41: =SUM(EZ41:FA41) -> 1750 | FD41: 1250 | FE41: =FD41+500 -> 1750 | FF41: =FE41+750 -> 2500 | FG41: =FF41+1000 -> 3500 | FH41: =SUM(FD41:FG41) -> 9000 | FJ41: =FG41+250 -> 3750 | FK41: =FJ41+250 -> 4000 | FL41: =FK41+500 -> 4500 | FM41: =FL41+500 -> 5000 | FN41: =SUM(FJ41:FM41) -> 17250 | FP41: =FM41+250 -> 5250 | FQ41: =FP41+250 -> 5500 | FR41: =FQ41+500 -> 6000 | FS41: =FR41+500 -> 6500 | FT41: =SUM(FP41:FS41) -> 23250
C42: ASP | EZ42: 1000 | FA42: 1000 | FB42: =(FB43*1000000)/FB41 -> 1000 | FD42: 1500 | FE42: 1750 | FF42: 2000 | FG42: 2250 | FH42: =(FH43*1000000)/FH41 -> 1979.1667 | FJ42: 2500 | FK42: 2500 | FL42: 2500 | FM42: 2500 | FN42: =(FN43*1000000)/FN41 -> 2500 | FP42: 2500 | FQ42: 2500 | FR42: 2500 | FS42: 2500 | FT42: =(FT43*1000000)/FT41 -> 2500
C43: Revenue | EZ43: =(EZ41*EZ42)/1000000 -> 0.75 | FA43: =(FA41*FA42)/1000000 -> 1 | FB43: =SUM(EX43:FA43) -> 1.75 | FD43: =(FD41*FD42)/1000000 -> 1.875 | FE43: =(FE41*FE42)/1000000 -> 3.0625 | FF43: =(FF41*FF42)/1000000 -> 5 | FG43: =(FG41*FG42)/1000000 -> 7.875 | FH43: =SUM(FD43:FG43) -> 17.8125 | FJ43: =(FJ41*FJ42)/1000000 -> 9.375 | FK43: =(FK41*FK42)/1000000 -> 10 | FL43: =(FL41*FL42)/1000000 -> 11.25 | FM43: =(FM41*FM42)/1000000 -> 12.5 | FN43: =SUM(FJ43:FM43) -> 43.125 | FP43: =(FP41*FP42)/1000000 -> 13.125 | FQ43: =(FQ41*FQ42)/1000000 -> 13.75 | FR43: =(FR41*FR42)/1000000 -> 15 | FS43: =(FS41*FS42)/1000000 -> 16.25 | FT43: =SUM(FP43:FS43) -> 58.125
C44: growth y/y | FJ44: =FJ43/FD43-1 -> 4 | FK44: =FK43/FE43-1 -> 2.2653061 | FL44: =FL43/FF43-1 -> 1.25 | FM44: =FM43/FG43-1 -> 0.58730159 | FN44: =FN43/FH43-1 -> 1.4210526 | FP44: =FP43/FJ43-1 -> 0.4 | FQ44: =FQ43/FK43-1 -> 0.375 | FR44: =FR43/FL43-1 -> 0.33333333 | FS44: =FS43/FM43-1 -> 0.3 | FT44: =FT43/FN43-1 -> 0.34782609
C45: contribution to NGS | FB45: =FB43/EV33 -> 0.010525436 | FD45: =(FD43-EX43)/EX33 -> 0.0400778 | FE45: =(FE43-EY43)/EY33 -> 0.059170875 | FF45: =(FF43-EZ43)/EZ33 -> 0.080785761 | FG45: =(FG43-FA43)/FA33 -> 0.13375069 | FH45: =(FH43-FB43)/FB33 -> 0.079301105 | FJ45: =(FJ43-FD43)/FD33 -> 0.12824896 | FK45: =(FK43-FE43)/FE33 -> 0.10723212 | FL45: =(FL43-FF43)/FF33 -> 0.095042072 | FM45: =(FM43-FG43)/FG33 -> 0.07198219 | FN45: =(FN43-FH43)/FH33 -> 0.099974934 | FP45: =(FP43-FJ43)/FJ33 -> 0.049326523 | FQ45: =(FQ43-FK43)/FK33 -> 0.044587159 | FR45: =(FR43-FL43)/FL33 -> 0.043865572 | FS45: =(FS43-FM43)/FM33 -> 0.044895337 | FT45: =(FT43-FN43)/FN33 -> 0.045572619
C46: contribution to clinical | FB46: =FB43/EV65 -> 0.0030632603 | FD46: =(FD43-EX43)/EX65 -> 0.012524312 | FE46: =(FE43-EY43)/EY65 -> 0.018651339 | FF46: =(FF43-EZ43)/EZ65 -> 0.024765397 | FG46: =(FG43-FA43)/FA65 -> 0.039452846 | FH46: =(FH43-FB43)/FB65 -> 0.024345413 | FJ46: =(FJ43-FD43)/FD65 -> 0.044463393 | FK46: =(FK43-FE43)/FE65 -> 0.038512342 | FL46: =(FL43-FF43)/FF65 -> 0.03308477 | FM46: =(FM43-FG43)/FG65 -> 0.023812721 | FN46: =(FN43-FH43)/FH65 -> 0.034582387 | FP46: =(FP43-FJ43)/FJ65 -> 0.020173138 | FQ46: =(FQ43-FK43)/FK65 -> 0.01888986 | FR46: =(FR43-FL43)/FL65 -> 0.018012748 | FS46: =(FS43-FM43)/FM65 -> 0.017519806 | FT46: =(FT43-FN43)/FN65 -> 0.018595672
C48: RaDaR ST Clinical
C49: Volumes | FD49: 500 | FE49: 1500 | FF49: 2000 | FG49: 3000 | FH49: =SUM(FD49:FG49) -> 7000 | FJ49: =FG49 -> 3000 | FK49: =FJ49+250 -> 3250 | FL49: =FK49+250 -> 3500 | FM49: =FL49+250 -> 3750 | FN49: =SUM(FJ49:FM49) -> 13500 | FP49: =FM49 -> 3750 | FQ49: =FP49+250 -> 4000 | FR49: =FQ49+250 -> 4250 | FS49: =FR49+250 -> 4500 | FT49: =SUM(FP49:FS49) -> 16500
C50: ASP | FD50: 700 | FE50: 700 | FF50: 700 | FG50: 700 | FH50: =(FH51*1000000)/FH49 -> 700 | FJ50: 750 | FK50: 750 | FL50: 750 | FM50: 720 | FN50: =(FN51*1000000)/FN49 -> 741.66667 | FP50: 750 | FQ50: 750 | FR50: 750 | FS50: 720 | FT50: =(FT51*1000000)/FT49 -> 741.81818
C51: Revenue | FD51: =(FD49*FD50)/1000000 -> 0.35 | FE51: =(FE49*FE50)/1000000 -> 1.05 | FF51: =(FF49*FF50)/1000000 -> 1.4 | FG51: =(FG49*FG50)/1000000 -> 2.1 | FH51: =SUM(FD51:FG51) -> 4.9 | FJ51: =(FJ49*FJ50)/1000000 -> 2.25 | FK51: =(FK49*FK50)/1000000 -> 2.4375 | FL51: =(FL49*FL50)/1000000 -> 2.625 | FM51: =(FM49*FM50)/1000000 -> 2.7 | FN51: =SUM(FJ51:FM51) -> 10.0125 | FP51: =(FP49*FP50)/1000000 -> 2.8125 | FQ51: =(FQ49*FQ50)/1000000 -> 3 | FR51: =(FR49*FR50)/1000000 -> 3.1875 | FS51: =(FS49*FS50)/1000000 -> 3.24 | FT51: =SUM(FP51:FS51) -> 12.24
C52: growth y/y | FJ52: =FJ51/FD51-1 -> 5.4285714 | FK52: =FK51/FE51-1 -> 1.3214286 | FL52: =FL51/FF51-1 -> 0.875 | FM52: =FM51/FG51-1 -> 0.28571429 | FN52: =FN51/FH51-1 -> 1.0433673 | FP52: =FP51/FJ51-1 -> 0.25 | FQ52: =FQ51/FK51-1 -> 0.23076923 | FR52: =FR51/FL51-1 -> 0.21428571 | FS52: =FS51/FM51-1 -> 0.2 | FT52: =FT51/FN51-1 -> 0.22247191
C53: contribution to NGS | FD53: =(FD51-EX51)/EX33 -> 0.0074811893 | FE53: =(FE51-EY51)/EY33 -> 0.020287157 | FF53: =(FF51-EZ51)/EZ33 -> 0.02661178 | FG53: =(FG51-FA51)/FA33 -> 0.040854757 | FH53: =(FH51-FB51)/FB33 -> 0.024191466 | FJ53: =(FJ51-FD51)/FD33 -> 0.032489736 | FK53: =(FK51-FE51)/FE33 -> 0.021446423 | FL53: =(FL51-FF51)/FF33 -> 0.018628246 | FM53: =(FM51-FG51)/FG33 -> 0.0093382301 | FN53: =(FN51-FH51)/FH33 -> 0.020192468 | FP53: =(FP51-FJ51)/FJ33 -> 0.0073989784 | FQ53: =(FQ51-FK51)/FK33 -> 0.0066880738 | FR53: =(FR51-FL51)/FL33 -> 0.0065798357 | FS53: =(FS51-FM51)/FM33 -> 0.0064649285 | FT53: =(FT51-FN51)/FN33 -> 0.006767534
C54: contribution to clinical | FD54: =(FD51-EX51)/EX65 -> 0.0023378717 | FE54: =(FE51-EY51)/EY65 -> 0.0063947449 | FF54: =(FF51-EZ51)/EZ65 -> 0.008158013 | FG54: =(FG51-FA51)/FA65 -> 0.012051051 | FH54: =(FH51-FB51)/FB65 -> 0.0074267719 | FJ54: =(FJ51-FD51)/FD65 -> 0.011264059 | FK54: =(FK51-FE51)/FE65 -> 0.0077024684 | FL54: =(FL51-FF51)/FF65 -> 0.0064846149 | FM54: =(FM51-FG51)/FG65 -> 0.0030892179 | FN54: =(FN51-FH51)/FH65 -> 0.0069847883 | FP54: =(FP51-FJ51)/FJ65 -> 0.0030259707 | FQ54: =(FQ51-FK51)/FK65 -> 0.002833479 | FR54: =(FR51-FL51)/FL65 -> 0.0027019121 | FS54: =(FS51-FM51)/FM65 -> 0.002522852 | FT54: =(FT51-FN51)/FN65 -> 0.0027614572
C56: Ex-NGS | EF56: =EF10-EF33 -> 80.02071 | EG56: =EG10-EG33 -> 84.508 | EH56: =EH10-EH33 -> 83.86798 | EI56: =EI10-EI33 -> 84.36948 | EJ56: =EJ10-EJ33 -> 332.76617 | EL56: =EL10-EL33 -> 88.44913 | EM56: =EM10-EM33 -> 93.59856 | EN56: =EN10-EN33 -> 94.38922 | EO56: =EO10-EO33 -> 96.24292 | EP56: =EP10-EP33 -> 372.67983 | ER56: =ER10-ER33 -> 94.847175 | ES56: =ES10-ES33 -> 98.9716 | ET56: =ET10-ET33 -> 103.50593 | EU56: =EU10-EU33 -> 107.69813 | EV56: =EV10-EV33 -> 405.02283 | EX56: =EX10-EX33 -> 102.92481 | EY56: =EY10-EY33 -> 107.74044 | EZ56: =EZ10-EZ33 -> 114.40213 | FA56: =FA10-FA33 -> 118.52105 | FB56: =FB10-FB33 -> 443.58844 | FD56: =FD10-FD33 -> 105.74308 | FE56: =FE10-FE33 -> 110.75096 | FF56: =FF10-FF33 -> 118.21832 | FG56: =FG10-FG33 -> 124.87191 | FH56: =FH10-FH33 -> 459.58427 | FJ56: =FJ10-FJ33 -> 104.96626 | FK56: =FK10-FK33 -> 109.25527 | FL56: =FL10-FL33 -> 117.27444 | FM56: =FM10-FM33 -> 124.90586 | FN56: =FN10-FN33 -> 456.40183 | FP56: =FP10-FP33 -> 100.63816 | FQ56: =FQ10-FQ33 -> 103.76587 | FR56: =FR10-FR33 -> 112.32999 | FS56: =FS10-FS33 -> 121.12864 | FT56: =FT10-FT33 -> 437.86266
