Workbook
Name \A: #REF!
Name \B: #REF!
Name \C: #REF!
Name \D: #REF!
Name \E: #REF!
Name \F: #REF!
Name \G: #REF!
Name \H: #REF!
Name \I: #REF!
Name \P: #REF!
Name \S: [1]Model!#REF!
Name \X: [1]Model!#REF!
Name _1A_FUND: [3]Funding!#REF!
Name _2A_FUND: [3]Funding!#REF!
Name _2H_COV: [3]Worksheet!#REF!
Name _4H_COV: [3]Worksheet!#REF!
Name _5MKT_REL: #REF!
Name _6P_COV: [3]Worksheet!#REF!
Name _7MKT_REL: #REF!
Name _9P_COV: [3]Worksheet!#REF!
Name _GRM1: [1]Model!#REF!
Name _GRM2: [1]Model!#REF!
Name _GRM3: [1]Model!#REF!
Name _NM1: [1]Model!#REF!
Name _NM2: [1]Model!#REF!
Name _NM3: [1]Model!#REF!
Name _OM1: [1]Model!#REF!
Name _OM2: [1]Model!#REF!
Name _OM3: [1]Model!#REF!
Name _ROA1: [1]Model!#REF!
Name _ROA2: [1]Model!#REF!
Name _ROA3: [1]Model!#REF!
Name _ROE1: [1]Model!#REF!
Name _ROE2: [1]Model!#REF!
Name _ROE3: [1]Model!#REF!
Name a: [4]Q!#REF!
Name ab: [5]Q!$AB$15
Name ac: [5]Q!$AB$18
Name Acquisition_Y_or_N: [6]IS!#REF!
Name ad: [5]Q!$AB$28
Name ADJ: #REF!
Name ae: [4]Q!#REF!
Name af: [4]Q!#REF!
Name ag: [5]Q!$AB$29
Name ah: [5]Q!$AB$32
Name ai: [5]Q!$AB$42
Name aj: [5]Q!$AB$43
Name ak: [4]Q!#REF!
Name AMV: [1]Model!#REF!
Name AMVL12MOCF: [1]Model!#REF!
Name AMVL12MOPPR: [1]Model!#REF!
Name AMVL12MSAL: [1]Model!#REF!
Name AMVOCF: [1]Model!#REF!
Name AMVOI: [1]Model!#REF!
Name AMVSALES: [1]Model!#REF!
Name ARMINE: #REF!
Name Assets: [7]UNPEARN_IS!#REF!
Name ASSUMPT1: #REF!
Name ASSUMPT2: #REF!
Name Average_Tax_Rate__LTM: [7]UNPEARN_IS!#REF!

Sheet __FDSCACHE__
B1: This sheet contains FactSet XML data for use with this workbook's =FDS codes. Modifying the worksheet's contents may damage the workbook's =FDS functionality.

Sheet Disclaimer
C5: Equity Research
C7: Financial Model
C8: Airfreight & Surface Transportation - Railroads
C9: 46044
C12: CSX Corporation (NYSE: CSX)
C17: Wells Fargo Airfreight & Surface Transportation Team
C19: Christian Wetherbee
C20: Senior Analyst
C21: 212-214-8053
C22: Christian.Wetherbee@wellsfargo.com
C25: Robert Salmon, CFA | E25: Ryan Deveikis | G25: Matthew Hortopan
C26: Research Analyst | E26: Research Analyst | G26: Research Analyst
C27: 212-214-5016 | E27: 212-214-8040 | G27: 212-214-5009
C28: Robert.H.Salmon@wellsfargo.com | E28: Ryan.Deveikis@wellsfargo.com | G28: Matthew.F.Hortopan@wellsfargo.com
C32: Important Disclaimers:
C58: red font = assumption input

Sheet CSX
B1: Wells Fargo Securities, LLC
B2: =Disclaimer!$C$9 -> 46044 | KV2: =KV24*100 -> 60.955208 | KW2: =KW24*100 -> 60.367667 | KX2: =KX24*100 -> 64.427693 | KY2: =KY24*100 -> 64.266304 | LC2: =LC24*100 -> 63.678348 | LD2: =LD24*100 -> 60.875439 | LE2: =LE24*100 -> 62.58635 | LF2: =LF24*100 -> 65.696524 | LJ2: =LJ24*100 -> 69.588081 | LK2: =LK24*100 -> 64.101847 | LL2: =LL24*100 -> 64.148313 | LM2: =LM24*100 -> 66.875713 | LQ2: =LQ24*100 -> 66.217103 | LR2: =LR24*100 -> 62.419645 | LS2: =LS24*100 -> 62.015227 | LT2: =LT24*100 -> 63.843661
GG3: 38807 | JW3: 2019/4f | KA3: 2020/1f | KB3: 2020/2f | KC3: 2020/3f | KD3: 2020/4f | KE3: 2020 | KH3: 2021/1f | KI3: 2021/2f | KJ3: 2021/3f | KK3: 2021/4f | KL3: 2021 | KO3: 2021/1f | KP3: 2021/2f | KQ3: 2022/3f | KR3: 2022/4f | KS3: 2021 | KV3: 2023/1f | KW3: 2023/2f | KX3: 2023/3f | KY3: 2023/4f | KZ3: 2023 | LC3: 2024/1f | LD3: 2024/2f | LE3: 2024/3f | LF3: 2024/4f | LG3: 2024 | LJ3: 2025/1f | LK3: 2025/2f | LL3: 2025/3f | LM3: 2025/4f | LN3: 2025 | LQ3: 2025/1f | LR3: 2025/2f | LS3: 2025/3f | LT3: 2025/4f | LU3: 2026 | LX3: 2025/1f | LY3: 2025/2f | LZ3: 2025/3f | MA3: 2025/4f | MB3: 2027 | ME3: 2025/1f | MF3: 2025/2f | MG3: 2025/3f | MH3: 2025/4f | MI3: 208
B4: CSX - Summary | C4: =D4-1 -> 1978 | D4: =E4-1 -> 1979 | E4: =F4-1 -> 1980 | F4: =G4-1 -> 1981 | G4: =H4-1 -> 1982 | H4: =I4-1 -> 1983 | I4: =J4-1 -> 1984 | J4: =K4-1 -> 1985 | ... L4: =M4-1 -> 1987 | M4: =BV4-1 -> 1988 | N4: =BV4 -> 1989 | O4: =CC4 -> 1990 | P4: =CJ4 -> 1991 | Q4: =CQ4 -> 1992 | R4: =CX4 -> 1993 | S4: =DE4 -> 1994 | T4: =DL4 -> 1995 | U4: =DS4 -> 1996 | V4: =DZ4 -> 1997 | W4: =EG4 -> 1998 | X4: =EN4 -> 1999 | Y4: =EU4 -> 2000 | Z4: =FB4 -> 2001 | AA4: =FI4 -> 2002 | AB4: =FP4 -> 2003 | AC4: =FW4 -> 2004 | AD4: =GD4 -> 2005 | AE4: =GK4 -> 2006 | AF4: =GR4 -> 2007 | AG4: =GY4 -> 2008 | AH4: =HF4 -> 2009 | AI4: =HM4 -> 2010 | AJ4: =HT4 -> 2011 | AK4: =IA4 -> 2012 | AL4: =IH4 -> 2013 | AM4: =IO4 -> 2014 | AN4: =IV4 -> 2015 | AO4: =JC4 -> 2016 | AP4: =JJ4 -> 2017 | AQ4: =JQ4 -> 2018 | AR4: =JX4 -> 2019 | AS4: =KE4 -> 2020 | AT4: =KL4 -> 2021 | AU4: =KS4 -> 2022 | AV4: =KZ4 -> 2023 | AW4: =LG4 -> 2024 | AX4: =LN4 -> 2025 | AY4: =LU4 -> 2026E | AZ4: =MB4 -> 2027E | BA4: =MI4 -> 2028E | BQ4: CSX - Summary | BR4: 1Q89 | BS4: 2Q89 | BT4: 3Q89 | BU4: 4Q89 | BV4: 1989 | BX4: CSX - Summary | BY4: =LEFT(BR4,2)&RIGHT(CC4,2) -> 1Q90 | BZ4: =LEFT(BS4,2)&RIGHT(CC4,2) -> 2Q90 | CA4: =LEFT(BT4,2)&RIGHT(CC4,2) -> 3Q90 | CB4: =LEFT(BU4,2)&RIGHT(CC4,2) -> 4Q90 | CC4: =BV4+1 -> 1990 | CE4: CSX - Summary | CF4: =LEFT(BY4,2)&RIGHT(CJ4,2) -> 1Q91 | CG4: =LEFT(BZ4,2)&RIGHT(CJ4,2) -> 2Q91 | CH4: =LEFT(CA4,2)&RIGHT(CJ4,2) -> 3Q91 | CI4: =LEFT(CB4,2)&RIGHT(CJ4,2) -> 4Q91 | CJ4: =CC4+1 -> 1991 | CL4: CSX - Summary | CM4: =LEFT(CF4,2)&RIGHT(CQ4,2) -> 1Q92 | CN4: =LEFT(CG4,2)&RIGHT(CQ4,2) -> 2Q92 | CO4: =LEFT(CH4,2)&RIGHT(CQ4,2) -> 3Q92 | CP4: =LEFT(CI4,2)&RIGHT(CQ4,2) -> 4Q92 | CQ4: =CJ4+1 -> 1992 | CS4: CSX - Summary | CT4: =LEFT(CM4,2)&RIGHT(CX4,2) -> 1Q93 | CU4: =LEFT(CN4,2)&RIGHT(CX4,2) -> 2Q93 | CV4: =LEFT(CO4,2)&RIGHT(CX4,2) -> 3Q93 | CW4: =LEFT(CP4,2)&RIGHT(CX4,2) -> 4Q93 | CX4: =CQ4+1 -> 1993 | CZ4: CSX - Summary | DA4: =LEFT(CT4,2)&RIGHT(DE4,2) -> 1Q94 | DB4: =LEFT(CU4,2)&RIGHT(DE4,2) -> 2Q94 | DC4: =LEFT(CV4,2)&RIGHT(DE4,2) -> 3Q94 | DD4: =LEFT(CW4,2)&RIGHT(DE4,2) -> 4Q94 | DE4: =CX4+1 -> 1994 | DG4: CSX - Summary | DH4: =LEFT(DA4,2)&RIGHT(DL4,2) -> 1Q95 | DI4: =LEFT(DB4,2)&RIGHT(DL4,2) -> 2Q95 | DJ4: =LEFT(DC4,2)&RIGHT(DL4,2) -> 3Q95 | DK4: =LEFT(DD4,2)&RIGHT(DL4,2) -> 4Q95 | DL4: =DE4+1 -> 1995 | DN4: CSX - Summary | DO4: =LEFT(DH4,2)&RIGHT(DS4,2) -> 1Q96 | DP4: =LEFT(DI4,2)&RIGHT(DS4,2) -> 2Q96 | DQ4: =LEFT(DJ4,2)&RIGHT(DS4,2) -> 3Q96 | DR4: =LEFT(DK4,2)&RIGHT(DS4,2) -> 4Q96 | DS4: =DL4+1 -> 1996 | DU4: CSX - Summary | DV4: =LEFT(DO4,2)&RIGHT(DZ4,2) -> 1Q97 | DW4: =LEFT(DP4,2)&RIGHT(DZ4,2) -> 2Q97 | DX4: =LEFT(DQ4,2)&RIGHT(DZ4,2) -> 3Q97 | DY4: =LEFT(DR4,2)&RIGHT(DZ4,2) -> 4Q97 | DZ4: =DS4+1 -> 1997 | EB4: CSX - Summary | EC4: =LEFT(DV4,2)&RIGHT(EG4,2) -> 1Q98 | ED4: =LEFT(DW4,2)&RIGHT(EG4,2) -> 2Q98 | EE4: =LEFT(DX4,2)&RIGHT(EG4,2) -> 3Q98 | EF4: =LEFT(DY4,2)&RIGHT(EG4,2) -> 4Q98 | EG4: =DZ4+1 -> 1998 | EI4: CSX - Summary | EJ4: =LEFT(EC4,2)&RIGHT(EN4,2) -> 1Q99 | EK4: =LEFT(ED4,2)&RIGHT(EN4,2) -> 2Q99 | EL4: =LEFT(EE4,2)&RIGHT(EN4,2) -> 3Q99 | EM4: =LEFT(EF4,2)&RIGHT(EN4,2) -> 4Q99 | EN4: =EG4+1 -> 1999 | EP4: CSX - Summary | EQ4: =LEFT(EJ4,2)&RIGHT(EU4,2) -> 1Q00 | ER4: =LEFT(EK4,2)&RIGHT(EU4,2) -> 2Q00 | ES4: =LEFT(EL4,2)&RIGHT(EU4,2) -> 3Q00 | ET4: =LEFT(EM4,2)&RIGHT(EU4,2) -> 4Q00 | EU4: =EN4+1 -> 2000 | EW4: CSX - Summary | EX4: =LEFT(EQ4,2)&RIGHT(FB4,2) -> 1Q01 | EY4: =LEFT(ER4,2)&RIGHT(FB4,2) -> 2Q01 | EZ4: =LEFT(ES4,2)&RIGHT(FB4,2) -> 3Q01 | FA4: =LEFT(ET4,2)&RIGHT(FB4,2) -> 4Q01 | FB4: =EU4+1 -> 2001 | FD4: CSX - Summary | FE4: =LEFT(EX4,2)&RIGHT(FI4,2) -> 1Q02 | FF4: =LEFT(EY4,2)&RIGHT(FI4,2) -> 2Q02 | FG4: =LEFT(EZ4,2)&RIGHT(FI4,2) -> 3Q02 | FH4: =LEFT(FA4,2)&RIGHT(FI4,2) -> 4Q02 | FI4: =FB4+1 -> 2002 | FK4: CSX - Summary | FL4: =LEFT(FE4,2)&RIGHT(FP4,2) -> 1Q03 | FM4: =LEFT(FF4,2)&RIGHT(FP4,2) -> 2Q03 | FN4: =LEFT(FG4,2)&RIGHT(FP4,2) -> 3Q03 | FO4: =LEFT(FH4,2)&RIGHT(FP4,2) -> 4Q03 | FP4: =FI4+1 -> 2003 | FR4: CSX - Summary | FS4: =LEFT(FL4,2)&RIGHT(FW4,2) -> 1Q04 | FT4: =LEFT(FM4,2)&RIGHT(FW4,2) -> 2Q04 | FU4: =LEFT(FN4,2)&RIGHT(FW4,2) -> 3Q04 | FV4: =LEFT(FO4,2)&RIGHT(FW4,2) -> 4Q04 | FW4: =FP4+1 -> 2004 | FY4: CSX - Summary | FZ4: =LEFT(FS4,2)&RIGHT(GD4,2) -> 1Q05 | GA4: =LEFT(FT4,2)&RIGHT(GD4,2) -> 2Q05 | GB4: =LEFT(FU4,2)&RIGHT(GD4,2) -> 3Q05 | GC4: =LEFT(FV4,2)&RIGHT(GD4,2) -> 4Q05 | GD4: =FW4+1 -> 2005 | GF4: CSX - Summary | GG4: =LEFT(FZ4,2)&RIGHT(GK4,2) -> 1Q06 | GH4: =LEFT(GA4,2)&RIGHT(GK4,2) -> 2Q06 | GI4: =LEFT(GB4,2)&RIGHT(GK4,2) -> 3Q06 | GJ4: =LEFT(GC4,2)&RIGHT(GK4,2) -> 4Q06 | GK4: =GD4+1 -> 2006 | GM4: CSX - Summary | GN4: =LEFT(GG4,2)&RIGHT(GR4,2) -> 1Q07 | GO4: =LEFT(GH4,2)&RIGHT(GR4,2) -> 2Q07 | GP4: =LEFT(GI4,2)&RIGHT(GR4,2) -> 3Q07 | GQ4: =LEFT(GJ4,2)&RIGHT(GR4,2) -> 4Q07 | GR4: =GK4+1 -> 2007 | GT4: CSX - Summary | GU4: =LEFT(GN4,2)&RIGHT(GY4,2) -> 1Q08 | GV4: =LEFT(GO4,2)&RIGHT(GY4,2) -> 2Q08 | GW4: =LEFT(GP4,2)&RIGHT(GY4,2) -> 3Q08 | GX4: =LEFT(GQ4,2)&RIGHT(GY4,2) -> 4Q08 | GY4: =GR4+1 -> 2008 | HA4: CSX - Summary | HB4: =LEFT(GU4,2)&RIGHT(HF4,2) -> 1Q09 | HC4: =LEFT(GV4,2)&RIGHT(HF4,2) -> 2Q09 | HD4: =LEFT(GW4,2)&RIGHT(HF4,2) -> 3Q09 | HE4: =LEFT(GX4,2)&RIGHT(HF4,2) -> 4Q09 | HF4: =GY4+1 -> 2009 | HH4: CSX - Summary | HI4: =LEFT(HB4,2)&RIGHT(HM4,2) -> 1Q10 | HJ4: =LEFT(HC4,2)&RIGHT(HM4,2) -> 2Q10 | HK4: =LEFT(HD4,2)&RIGHT(HM4,2) -> 3Q10 | HL4: =LEFT(HE4,2)&RIGHT(HM4,2) -> 4Q10 | HM4: =HF4+1 -> 2010 | HO4: CSX - Summary | HP4: =LEFT(HI4,2)&RIGHT(HT4,2) -> 1Q11 | HQ4: =LEFT(HJ4,2)&RIGHT(HT4,2) -> 2Q11 | HR4: =LEFT(HK4,2)&RIGHT(HT4,2) -> 3Q11 | HS4: =LEFT(HL4,2)&RIGHT(HT4,2) -> 4Q11 | HT4: =HM4+1 -> 2011 | HV4: CSX - Summary | HW4: =LEFT(HP4,2)&RIGHT(IA4,2) -> 1Q12 | HX4: =LEFT(HQ4,2)&RIGHT(IA4,2) -> 2Q12 | HY4: =LEFT(HR4,2)&RIGHT(IA4,2) -> 3Q12 | HZ4: =LEFT(HS4,2)&RIGHT(IA4,2) -> 4Q12 | IA4: =HT4+1 -> 2012 | IC4: CSX - Summary | ID4: =LEFT(HW4,2)&RIGHT(IH4,2) -> 1Q13 | IE4: =LEFT(HX4,2)&RIGHT(IH4,2) -> 2Q13 | IF4: =LEFT(HY4,2)&RIGHT(IH4,2) -> 3Q13 | IG4: =LEFT(HZ4,2)&RIGHT(IH4,2) -> 4Q13 | IH4: =IA4+1 -> 2013 | IJ4: CSX - Summary | IK4: =LEFT(ID4,2)&RIGHT(IO4,2) -> 1Q14 | IL4: =LEFT(IE4,2)&RIGHT(IO4,2) -> 2Q14 | IM4: =LEFT(IF4,2)&RIGHT(IO4,2) -> 3Q14 | IN4: =LEFT(IG4,2)&RIGHT(IO4,2) -> 4Q14 | IO4: =IH4+1 -> 2014 | IQ4: CSX - Summary | IR4: =LEFT(IK4,2)&RIGHT(IV4,2) -> 1Q15 | IS4: =LEFT(IL4,2)&RIGHT(IV4,2) -> 2Q15 | IT4: =LEFT(IM4,2)&RIGHT(IV4,2) -> 3Q15 | IU4: =LEFT(IN4,2)&RIGHT(IV4,2) -> 4Q15 | IV4: =IO4+1 -> 2015 | IX4: CSX - Summary | IY4: =LEFT(IR4,2)&RIGHT(JC4,2) -> 1Q16 | IZ4: =LEFT(IS4,2)&RIGHT(JC4,2) -> 2Q16 | JA4: =LEFT(IT4,2)&RIGHT(JC4,2) -> 3Q16 | JB4: =LEFT(IU4,2)&RIGHT(JC4,2) -> 4Q16 | JC4: =IV4+1 -> 2016 | JE4: CSX - Summary | JF4: =LEFT(IY4,2)&RIGHT(JJ4,2) -> 1Q17 | JG4: =LEFT(IZ4,2)&RIGHT(JJ4,2) -> 2Q17 | JH4: =LEFT(JA4,2)&RIGHT(JJ4,2) -> 3Q17 | JI4: =LEFT(JB4,2)&RIGHT(JJ4,2) -> 4Q17 | JJ4: =JC4+1 -> 2017 | JL4: CSX - Summary | JM4: =LEFT(JF4,2)&RIGHT(JQ4,2) -> 1Q18 | JN4: =LEFT(JG4,2)&RIGHT(JQ4,2) -> 2Q18 | JO4: =LEFT(JH4,2)&RIGHT(JQ4,2) -> 3Q18 | JP4: =LEFT(JI4,2)&RIGHT(JQ4,2) -> 4Q18 | JQ4: =JJ4+1 -> 2018 | JS4: CSX - Summary | JT4: =LEFT(JM4,2)&RIGHT(JX4,2) -> 1Q19 | JU4: =LEFT(JN4,2)&RIGHT(JX4,2) -> 2Q19 | JV4: =LEFT(JO4,2)&RIGHT(JX4,2) -> 3Q19 | JW4: =LEFT(JP4,2)&RIGHT(JX4,2) -> 4Q19 | JX4: =JQ4+1 -> 2019 | JZ4: CSX - Summary | KA4: =LEFT(JT4,2)&RIGHT(KE4,2) -> 1Q20 | KB4: =LEFT(JU4,2)&RIGHT(KE4,2) -> 2Q20 | KC4: =LEFT(JV4,2)&RIGHT(KE4,2) -> 3Q20 | KD4: =LEFT(JW4,2)&RIGHT(KE4,2) -> 4Q20 | KE4: =JX4+1 -> 2020 | KG4: CSX - Summary | KH4: =LEFT(KA4,2)&RIGHT(KL4,2) -> 1Q21 | KI4: =LEFT(KB4,2)&RIGHT(KL4,2) -> 2Q21 | KJ4: =LEFT(KC4,2)&RIGHT(KL4,2) -> 3Q21 | KK4: =LEFT(KD4,2)&RIGHT(KL4,2) -> 4Q21 | KL4: =KE4+1 -> 2021 | KN4: CSX - Summary | KO4: =LEFT(KH4,2)&RIGHT(KS4,2) -> 1Q22 | KP4: =LEFT(KI4,2)&RIGHT(KS4,2) -> 2Q22 | KQ4: =LEFT(KJ4,2)&RIGHT(KS4,2) -> 3Q22 | KR4: =LEFT(KK4,2)&RIGHT(KS4,2) -> 4Q22 | KS4: =KL4+1 -> 2022 | KU4: CSX - Summary | KV4: =LEFT(KO4,2)&RIGHT(KZ4,2) -> 1Q23 | KW4: =LEFT(KP4,2)&RIGHT(KZ4,2) -> 2Q23 | KX4: =LEFT(KQ4,2)&RIGHT(KZ4,2) -> 3Q23 | KY4: =LEFT(KR4,2)&RIGHT(KZ4,2) -> 4Q23 | KZ4: =KS4+1 -> 2023 | LB4: CSX - Summary | LC4: =LEFT(KV4,2)&RIGHT($LG$3,2) -> 1Q24 | LD4: =LEFT(KW4,2)&RIGHT($LG$3,2) -> 2Q24 | LE4: =LEFT(KX4,2)&RIGHT($LG$3,2) -> 3Q24 | LF4: =LEFT(KY4,2)&RIGHT($LG$3,2) -> 4Q24 | LG4: =KZ4+1 -> 2024 | LI4: CSX - Summary | LJ4: 1Q25 | LK4: 2Q25 | LL4: 3Q25 | LM4: 4Q25 | LN4: =LG4+1 -> 2025 | LP4: CSX - Summary | LQ4: 1Q26E | LR4: 2Q26E | LS4: 3Q26E | LT4: 4Q26E | LU4: =CONCATENATE(TEXT(LT5,"YYYY"),"E") -> 2026E | LW4: CSX - Summary | LX4: =LEFT(LQ4,2)&RIGHT(MB4,3) -> 1Q27E | LY4: =LEFT(LR4,2)&RIGHT(MB4,3) -> 2Q27E | LZ4: =LEFT(LS4,2)&RIGHT(MB4,3) -> 3Q27E | MA4: =LEFT(LT4,2)&RIGHT(MB4,3) -> 4Q27E | MB4: =CONCATENATE(TEXT(MA5,"YYYY"),"E") -> 2027E | MD4: CSX - Summary | ME4: =LEFT(LX4,2)&RIGHT(MI4,3) -> 1Q28E | MF4: =LEFT(LY4,2)&RIGHT(MI4,3) -> 2Q28E | MG4: =LEFT(LZ4,2)&RIGHT(MI4,3) -> 3Q28E | MH4: =LEFT(MA4,2)&RIGHT(MI4,3) -> 4Q28E | MI4: =CONCATENATE(TEXT(MH5,"YYYY"),"E") -> 2028E
B5: ($ in millions except per share amounts) | C5: FY | D5: FY | E5: FY | F5: FY | G5: FY | H5: FY | I5: FY | J5: FY | K5: FY | L5: FY | M5: FY | N5: =BV5 -> FY | O5: =CC5 -> FY | P5: =CJ5 -> FY | Q5: =CQ5 -> FY | R5: =CX5 -> FY | S5: =DE5 -> FY | T5: =DL5 -> FY | U5: =DS5 -> FY | V5: =DZ5 -> FY | W5: =EG5 -> FY | X5: =EN5 -> FY | Y5: =EU5 -> FY | Z5: =FB5 -> FY | AA5: =FI5 -> FY | AB5: =FP5 -> FY | AC5: =FW5 -> FY | AD5: =GD5 -> FY | AE5: =GK5 -> FY | AF5: =GR5 -> FY | AG5: =GY5 -> FY | AH5: =HF5 -> FY | AI5: =HM5 -> FY | AJ5: =HT5 -> FY | AK5: =IA5 -> FY | AL5: =IH5 -> FY | AM5: =IO5 -> FY | AN5: =IV5 -> FY | AO5: =JC5 -> FY | AP5: =JJ5 -> FY | AQ5: =JQ5 -> FY | AR5: =JX5 -> FY | AS5: =KE5 -> FY | AT5: =KL5 -> FY | AU5: =KS5 -> FY | AV5: =KZ5 -> FY | AW5: =LG5 -> FY | AX5: =LN5 -> FY | AY5: =LU5 -> FY | AZ5: =MB5 -> FY | BA5: =MI5 -> FY | BQ5: ($ in millions except per share amounts) | BR5: 32598 | BS5: =EOMONTH(BR5,3) -> 32689 | BT5: =EOMONTH(BS5,3) -> 32781 | BU5: =EOMONTH(BT5,3) -> 32873 | BV5: FY | BX5: ($ in millions except per share amounts) | BY5: =EOMONTH(BR5,12) -> 32963 | BZ5: =EOMONTH(BY5,3) -> 33054 | CA5: =EOMONTH(BZ5,3) -> 33146 | CB5: =EOMONTH(CA5,3) -> 33238 | CC5: FY | CE5: ($ in millions except per share amounts) | CF5: =EOMONTH(BY5,12) -> 33328 | CG5: =EOMONTH(CF5,3) -> 33419 | CH5: =EOMONTH(CG5,3) -> 33511 | CI5: =EOMONTH(CH5,3) -> 33603 | CJ5: FY | CL5: ($ in millions except per share amounts) | CM5: =EOMONTH(CF5,12) -> 33694 | CN5: =EOMONTH(CM5,3) -> 33785 | CO5: =EOMONTH(CN5,3) -> 33877 | CP5: =EOMONTH(CO5,3) -> 33969 | CQ5: FY | CS5: ($ in millions except per share amounts) | CT5: =EOMONTH(CM5,12) -> 34059 | CU5: =EOMONTH(CT5,3) -> 34150 | CV5: =EOMONTH(CU5,3) -> 34242 | CW5: =EOMONTH(CV5,3) -> 34334 | CX5: FY | CZ5: ($ in millions except per share amounts) | DA5: =EOMONTH(CT5,12) -> 34424 | DB5: =EOMONTH(DA5,3) -> 34515 | DC5: =EOMONTH(DB5,3) -> 34607 | DD5: =EOMONTH(DC5,3) -> 34699 | DE5: FY | DG5: ($ in millions except per share amounts) | DH5: =EOMONTH(DA5,12) -> 34789 | DI5: =EOMONTH(DH5,3) -> 34880 | DJ5: =EOMONTH(DI5,3) -> 34972 | DK5: =EOMONTH(DJ5,3) -> 35064 | DL5: FY | DN5: ($ in millions except per share amounts) | DO5: =EOMONTH(DH5,12) -> 35155 | DP5: =EOMONTH(DO5,3) -> 35246 | DQ5: =EOMONTH(DP5,3) -> 35338 | DR5: =EOMONTH(DQ5,3) -> 35430 | DS5: FY | DU5: ($ in millions except per share amounts) | DV5: =EOMONTH(DO5,12) -> 35520 | DW5: =EOMONTH(DV5,3) -> 35611 | DX5: =EOMONTH(DW5,3) -> 35703 | DY5: =EOMONTH(DX5,3) -> 35795 | DZ5: FY | EB5: ($ in millions except per share amounts) | EC5: =EOMONTH(DV5,12) -> 35885 | ED5: =EOMONTH(EC5,3) -> 35976 | EE5: =EOMONTH(ED5,3) -> 36068 | EF5: =EOMONTH(EE5,3) -> 36160 | EG5: FY | EI5: ($ in millions except per share amounts) | EJ5: =EOMONTH(EC5,12) -> 36250 | EK5: =EOMONTH(EJ5,3) -> 36341 | EL5: =EOMONTH(EK5,3) -> 36433 | EM5: =EOMONTH(EL5,3) -> 36525 | EN5: FY | EP5: ($ in millions except per share amounts) | EQ5: =EOMONTH(EJ5,12) -> 36616 | ER5: =EOMONTH(EQ5,3) -> 36707 | ES5: =EOMONTH(ER5,3) -> 36799 | ET5: =EOMONTH(ES5,3) -> 36891 | EU5: FY | EW5: ($ in millions except per share amounts) | EX5: =EOMONTH(EQ5,12) -> 36981 | EY5: =EOMONTH(EX5,3) -> 37072 | EZ5: =EOMONTH(EY5,3) -> 37164 | FA5: =EOMONTH(EZ5,3) -> 37256 | FB5: FY | FD5: ($ in millions except per share amounts) | FE5: =EOMONTH(EX5,12) -> 37346 | FF5: =EOMONTH(FE5,3) -> 37437 | FG5: =EOMONTH(FF5,3) -> 37529 | FH5: =EOMONTH(FG5,3) -> 37621 | FI5: FY | FK5: ($ in millions except per share amounts) | FL5: =EOMONTH(FE5,12) -> 37711 | FM5: =EOMONTH(FL5,3) -> 37802 | FN5: =EOMONTH(FM5,3) -> 37894 | FO5: =EOMONTH(FN5,3) -> 37986 | FP5: FY | FR5: ($ in millions except per share amounts) | FS5: =EOMONTH(FL5,12) -> 38077 | FT5: =EOMONTH(FS5,3) -> 38168 | FU5: =EOMONTH(FT5,3) -> 38260 | FV5: =EOMONTH(FU5,3) -> 38352 | FW5: FY | FY5: ($ in millions except per share amounts) | FZ5: =EOMONTH(FS5,12) -> 38442 | GA5: =EOMONTH(FZ5,3) -> 38533 | GB5: =EOMONTH(GA5,3) -> 38625 | GC5: =EOMONTH(GB5,3) -> 38717 | GD5: FY | GF5: ($ in millions except per share amounts) | GG5: =EOMONTH(FZ5,12) -> 38807 | GH5: =EOMONTH(GG5,3) -> 38898 | GI5: =EOMONTH(GH5,3) -> 38990 | GJ5: =EOMONTH(GI5,3) -> 39082 | GK5: FY | GM5: ($ in millions except per share amounts) | GN5: =EOMONTH(GG5,12) -> 39172 | GO5: =EOMONTH(GN5,3) -> 39263 | GP5: =EOMONTH(GO5,3) -> 39355 | GQ5: =EOMONTH(GP5,3) -> 39447 | GR5: FY | GT5: ($ in millions except per share amounts) | GU5: =EOMONTH(GN5,12) -> 39538 | GV5: =EOMONTH(GU5,3) -> 39629 | GW5: =EOMONTH(GV5,3) -> 39721 | GX5: =EOMONTH(GW5,3) -> 39813 | GY5: FY | HA5: ($ in millions except per share amounts) | HB5: =EOMONTH(GU5,12) -> 39903 | HC5: =EOMONTH(HB5,3) -> 39994 | HD5: =EOMONTH(HC5,3) -> 40086 | HE5: =EOMONTH(HD5,3) -> 40178 | HF5: FY | HH5: ($ in millions except per share amounts) | HI5: =EOMONTH(HB5,12) -> 40268 | HJ5: =EOMONTH(HI5,3) -> 40359 | HK5: =EOMONTH(HJ5,3) -> 40451 | HL5: =EOMONTH(HK5,3) -> 40543 | HM5: FY | HO5: ($ in millions except per share amounts) | HP5: =EOMONTH(HI5,12) -> 40633 | HQ5: =EOMONTH(HP5,3) -> 40724 | HR5: =EOMONTH(HQ5,3) -> 40816 | HS5: =EOMONTH(HR5,3) -> 40908 | HT5: FY | HV5: ($ in millions except per share amounts) | HW5: =EOMONTH(HP5,12) -> 40999 | HX5: =EOMONTH(HW5,3) -> 41090 | HY5: =EOMONTH(HX5,3) -> 41182 | HZ5: =EOMONTH(HY5,3) -> 41274 | IA5: FY | IC5: ($ in millions except per share amounts) | ID5: =EOMONTH(HW5,12) -> 41364 | IE5: =EOMONTH(ID5,3) -> 41455 | IF5: =EOMONTH(IE5,3) -> 41547 | IG5: =EOMONTH(IF5,3) -> 41639 | IH5: FY | IJ5: ($ in millions except per share amounts) | IK5: =EOMONTH(ID5,12) -> 41729 | IL5: =EOMONTH(IK5,3) -> 41820 | IM5: =EOMONTH(IL5,3) -> 41912 | IN5: =EOMONTH(IM5,3) -> 42004 | IO5: FY | IQ5: ($ in millions except per share amounts) | IR5: =EOMONTH(IK5,12) -> 42094 | IS5: =EOMONTH(IR5,3) -> 42185 | IT5: =EOMONTH(IS5,3) -> 42277 | IU5: =EOMONTH(IT5,3) -> 42369 | IV5: FY | IX5: ($ in millions except per share amounts) | IY5: =EOMONTH(IR5,12) -> 42460 | IZ5: =EOMONTH(IY5,3) -> 42551 | JA5: =EOMONTH(IZ5,3) -> 42643 | JB5: =EOMONTH(JA5,3) -> 42735 | JC5: FY | JE5: ($ in millions except per share amounts) | JF5: =EOMONTH(IY5,12) -> 42825 | JG5: =EOMONTH(JF5,3) -> 42916 | JH5: =EOMONTH(JG5,3) -> 43008 | JI5: =EOMONTH(JH5,3) -> 43100 | JJ5: FY | JL5: ($ in millions except per share amounts) | JM5: =EOMONTH(JF5,12) -> 43190 | JN5: =EOMONTH(JM5,3) -> 43281 | JO5: =EOMONTH(JN5,3) -> 43373 | JP5: =EOMONTH(JO5,3) -> 43465 | JQ5: FY | JS5: ($ in millions except per share amounts) | JT5: =EOMONTH(JM5,12) -> 43555 | JU5: =EOMONTH(JT5,3) -> 43646 | JV5: =EOMONTH(JU5,3) -> 43738 | JW5: =EOMONTH(JV5,3) -> 43830 | JX5: FY | JZ5: ($ in millions except per share amounts) | KA5: =EOMONTH(JT5,12) -> 43921 | KB5: =EOMONTH(KA5,3) -> 44012 | KC5: =EOMONTH(KB5,3) -> 44104 | KD5: =EOMONTH(KC5,3) -> 44196 | KE5: FY | KG5: ($ in millions except per share amounts) | KH5: =EOMONTH(KA5,12) -> 44286 | KI5: =EOMONTH(KH5,3) -> 44377 | KJ5: =EOMONTH(KI5,3) -> 44469 | KK5: =EOMONTH(KJ5,3) -> 44561 | KL5: FY | KN5: ($ in millions except per share amounts) | KO5: =EOMONTH(KH5,12) -> 44651 | KP5: =EOMONTH(KO5,3) -> 44742 | KQ5: =EOMONTH(KP5,3) -> 44834 | KR5: =EOMONTH(KQ5,3) -> 44926 | KS5: FY | KU5: ($ in millions except per share amounts) | KV5: =EOMONTH(KO5,12) -> 45016 | KW5: =EOMONTH(KV5,3) -> 45107 | KX5: =EOMONTH(KW5,3) -> 45199 | KY5: =EOMONTH(KX5,3) -> 45291 | KZ5: FY | LB5: ($ in millions except per share amounts) | LC5: =EOMONTH(KV5,12) -> 45382 | LD5: =EOMONTH(LC5,3) -> 45473 | LE5: =EOMONTH(LD5,3) -> 45565 | LF5: =EOMONTH(LE5,3) -> 45657 | LG5: FY | LI5: ($ in millions except per share amounts) | LJ5: =EOMONTH(LC5,12) -> 45747 | LK5: =EOMONTH(LJ5,3) -> 45838 | LL5: =EOMONTH(LK5,3) -> 45930 | LM5: =EOMONTH(LL5,3) -> 46022 | LN5: FY | LP5: ($ in millions except per share amounts) | LQ5: =EOMONTH(LJ5,12) -> 46112 | LR5: =EOMONTH(LQ5,3) -> 46203 | LS5: =EOMONTH(LR5,3) -> 46295 | LT5: =EOMONTH(LS5,3) -> 46387 | LU5: FY | LW5: ($ in millions except per share amounts) | LX5: =EOMONTH(LQ5,12) -> 46477 | LY5: =EOMONTH(LX5,3) -> 46568 | LZ5: =EOMONTH(LY5,3) -> 46660 | MA5: =EOMONTH(LZ5,3) -> 46752 | MB5: FY | MD5: ($ in millions except per share amounts) | ME5: =EOMONTH(LX5,12) -> 46843 | MF5: =EOMONTH(ME5,3) -> 46934 | MG5: =EOMONTH(MF5,3) -> 47026 | MH5: =EOMONTH(MG5,3) -> 47118 | MI5: FY
B7: Revenue | C7: =+C20 -> 3623.525 | D7: =+D20 -> 4219.9 | E7: =+E20 -> 4723.4 | F7: =+F20 -> 5345.2 | G7: =+G20 -> 4855 | H7: =+H20 -> 4902 | I7: =+I20 -> 5597 | J7: =+J20 -> 5361 | ... M7: =+M20 -> 7592 | N7: =BV7 -> 7745 | O7: =CC7 -> 8205.317 | P7: =CJ7 -> 8636.3 | Q7: =CQ7 -> 8734.1 | R7: =CX7 -> 8940.5 | S7: =DE7 -> 9608 | T7: =DL7 -> 10304 | U7: =DS7 -> 10536 | V7: =DZ7 -> 10963 | W7: =EG7 -> 9861 | X7: =EN7 -> 10811 | Y7: =EU7 -> 8435 | Z7: =FB7 -> 8110 | AA7: =FI7 -> 8152 | AB7: =FP7 -> 7567 | AC7: =FW7 -> 8025 | AD7: =GD7 -> 8601 | AE7: =GK7 -> 9566 | AF7: =GR7 -> 10030 | AG7: =GY7 -> 11255 | AH7: =HF7 -> 9041 | AI7: =HM7 -> 10636 | AJ7: =HT7 -> 11743 | AK7: =IA7 -> 11756 | AL7: =IH7 -> 12058 | AM7: =IO7 -> 12669 | AN7: =IV7 -> 11811 | AO7: =JC7 -> 11069 | AP7: =JJ7 -> 11408 | AQ7: =JQ7 -> 12250 | AR7: =JX7 -> 11937 | AS7: =KE7 -> 10583 | AT7: =KL7 -> 12522 | AU7: =KS7 -> 14853 | AV7: =KZ7 -> 14657 | AW7: =LG7 -> 14540 | AX7: =LN7 -> 14092 | AY7: =LU7 -> 14494.795 | AZ7: =MB7 -> 15180.906 | BA7: =MI7 -> 15848.637 | BQ7: Revenue | BR7: =+BR20 -> 1843.8 | BS7: =+BS20 -> 1974 | BT7: =+BT20 -> 1892.9 | BU7: =+BU20 -> 2034.3 | BV7: =+BV20 -> 7745 | BX7: Revenue | BY7: =+BY20 -> 1907.7 | BZ7: =+BZ20 -> 2046.9 | CA7: =+CA20 -> 2063 | CB7: =+CB20 -> 2187.717 | CC7: =+CC20 -> 8205.317 | CE7: Revenue | CF7: =+CF20 -> 2030.3 | CG7: =+CG20 -> 2125 | CH7: =+CH20 -> 2204.9 | CI7: =+CI20 -> 2276.1 | CJ7: =+CJ20 -> 8636.3 | CL7: Revenue | CM7: =+CM20 -> 2086.4 | CN7: =+CN20 -> 2188.2 | CO7: =+CO20 -> 2214.3 | CP7: =+CP20 -> 2245.2 | CQ7: =+CQ20 -> 8734.1 | CS7: Revenue | CT7: =+CT20 -> 2123.3 | CU7: =+CU20 -> 2263.5 | CV7: =+CV20 -> 2238.7 | CW7: =+CW20 -> 2315 | CX7: =+CX20 -> 8940.5 | CZ7: Revenue | DA7: =+DA20 -> 2227 | DB7: =+DB20 -> 2371 | DC7: =+DC20 -> 2470 | DD7: =+DD20 -> 2540 | DE7: =+DE20 -> 9608 | DG7: Revenue | DH7: =+DH20 -> 2444 | DI7: =+DI20 -> 2549 | DJ7: =+DJ20 -> 2601 | DK7: =+DK20 -> 2710 | DL7: =+DL20 -> 10304 | DN7: Revenue | DO7: =+DO20 -> 2514 | DP7: =+DP20 -> 2672 | DQ7: =+DQ20 -> 2647 | DR7: =+DR20 -> 2703 | DS7: =+DS20 -> 10536 | DU7: Revenue | DV7: =+DV20 -> 2567 | DW7: =+DW20 -> 2678 | DX7: =+DX20 -> 2815 | DY7: =+DY20 -> 2903 | DZ7: =+DZ20 -> 10963 | EB7: Revenue | EC7: =+EC20 -> 2442 | ED7: =+ED20 -> 2490 | EE7: =+EE20 -> 2429 | EF7: =+EF20 -> 2500 | EG7: =+EG20 -> 9861 | EI7: Revenue | EJ7: =+EJ20 -> 2541 | EK7: =+EK20 -> 2616 | EL7: =+EL20 -> 2906 | EM7: =+EM20 -> 2748 | EN7: =+EN20 -> 10811 | EP7: Revenue | EQ7: =+EQ20 -> 2147 | ER7: =+ER20 -> 2202 | ES7: =+ES20 -> 2039 | ET7: =+ET20 -> 2047 | EU7: =+EU20 -> 8435 | EW7: Revenue | EX7: =+EX20 -> 2025 | EY7: =+EY20 -> 2057 | EZ7: =+EZ20 -> 2019 | FA7: =+FA20 -> 2009 | FB7: =+FB20 -> 8110 | FD7: Revenue | FE7: =+FE20 -> 1964 | FF7: =+FF20 -> 2073 | FG7: =+FG20 -> 2055 | FH7: =+FH20 -> 2060 | FI7: =+FI20 -> 8152 | FK7: Revenue | FL7: =+FL20 -> 1960 | FM7: =+FM20 -> 1888 | FN7: =+FN20 -> 1823 | FO7: =+FO20 -> 1896 | FP7: =+FP20 -> 7567 | FR7: Revenue | FS7: =+FS20 -> 1920 | FT7: =+FT20 -> 1995 | FU7: =+FU20 -> 1938 | FV7: =+FV20 -> 2172 | FW7: =+FW20 -> 8025 | FY7: Revenue | FZ7: =+FZ20 -> 2108 | GA7: =+GA20 -> 2149 | GB7: =+GB20 -> 2125 | GC7: =+GC20 -> 2219 | GD7: =+GD20 -> 8601 | GF7: Revenue | GG7: =+GG20 -> 2331 | GH7: =+GH20 -> 2421 | GI7: =+GI20 -> 2418 | GJ7: =+GJ20 -> 2396 | GK7: =+GK20 -> 9566 | GM7: Revenue | GN7: =+GN20 -> 2422 | GO7: =+GO20 -> 2530 | GP7: =+GP20 -> 2501 | GQ7: =+GQ20 -> 2577 | GR7: =+GR20 -> 10030 | GT7: Revenue | GU7: =+GU20 -> 2713 | GV7: =+GV20 -> 2907 | GW7: =+GW20 -> 2961 | GX7: =+GX20 -> 2674 | GY7: =+GY20 -> 11255 | HA7: Revenue | HB7: =+HB20 -> 2247 | HC7: =+HC20 -> 2185 | HD7: =+HD20 -> 2289 | HE7: =+HE20 -> 2320 | HF7: =+HF20 -> 9041 | HH7: Revenue | HI7: =+HI20 -> 2491 | HJ7: =+HJ20 -> 2663 | HK7: =+HK20 -> 2666 | HL7: =+HL20 -> 2816 | HM7: =+HM20 -> 10636 | HO7: Revenue | HP7: =+HP20 -> 2810 | HQ7: =+HQ20 -> 3019 | HR7: =+HR20 -> 2963 | HS7: =+HS20 -> 2951 | HT7: =+HT20 -> 11743 | HV7: Revenue | HW7: =+HW20 -> 2966 | HX7: =+HX20 -> 3012 | HY7: =+HY20 -> 2894 | HZ7: =+HZ20 -> 2884 | IA7: =+IA20 -> 11756 | IC7: Revenue | ID7: =+ID20 -> 2958 | IE7: =+IE20 -> 3069 | IF7: =+IF20 -> 2999 | IG7: =+IG20 -> 3032 | IH7: =+IH20 -> 12058 | IJ7: Revenue | IK7: =+IK20 -> 3012 | IL7: =+IL20 -> 3244 | IM7: =+IM20 -> 3221 | IN7: =+IN20 -> 3192 | IO7: =+IO20 -> 12669 | IQ7: Revenue | IR7: =+IR20 -> 3027 | IS7: =+IS20 -> 3064 | IT7: =+IT20 -> 2939 | IU7: =+IU20 -> 2781 | IV7: =+IV20 -> 11811 | IX7: Revenue | IY7: =+IY20 -> 2618 | IZ7: =+IZ20 -> 2704 | JA7: =+JA20 -> 2710 | JB7: =+JB20 -> 3037 | JC7: =+JC20 -> 11069 | JE7: Revenue | JF7: =+JF20 -> 2869 | JG7: =+JG20 -> 2933 | JH7: =+JH20 -> 2743 | JI7: =+JI20 -> 2863 | JJ7: =+JJ20 -> 11408 | JL7: Revenue | JM7: =+JM20 -> 2876 | JN7: =+JN20 -> 3102 | JO7: =+JO20 -> 3129 | JP7: =+JP20 -> 3143 | JQ7: =+JQ20 -> 12250 | JS7: Revenue | JT7: =+JT20 -> 3013 | JU7: =+JU20 -> 3061 | JV7: =+JV20 -> 2978 | JW7: =+JW20 -> 2885 | JX7: =+JX20 -> 11937 | JZ7: Revenue | KA7: =+KA20 -> 2855 | KB7: =+KB20 -> 2255 | KC7: =+KC20 -> 2648 | KD7: =+KD20 -> 2825 | KE7: =+KE20 -> 10583 | KG7: Revenue | KH7: =+KH20 -> 2813 | KI7: =+KI20 -> 2990 | KJ7: =+KJ20 -> 3292 | KK7: =+KK20 -> 3427 | KL7: =+KL20 -> 12522 | KN7: Revenue | KO7: =+KO20 -> 3413 | KP7: =+KP20 -> 3815 | KQ7: =+KQ20 -> 3895 | KR7: =+KR20 -> 3730 | KS7: =+KS20 -> 14853 | KU7: Revenue | KV7: =+KV20 -> 3706 | KW7: =+KW20 -> 3699 | KX7: =+KX20 -> 3572 | KY7: =+KY20 -> 3680 | KZ7: =+KZ20 -> 14657 | LB7: Revenue | LC7: =+LC20 -> 3681 | LD7: =+LD20 -> 3701 | LE7: =+LE20 -> 3619 | LF7: =+LF20 -> 3539 | LG7: =+LG20 -> 14540 | LI7: Revenue | LJ7: =+LJ20 -> 3423 | LK7: =+LK20 -> 3574 | LL7: =+LL20 -> 3587 | LM7: =+LM20 -> 3508 | LN7: =+LN20 -> 14092 | LP7: Revenue | LQ7: =+LQ20 -> 3460.8174 | LR7: =+LR20 -> 3635.8899 | LS7: =+LS20 -> 3703.9341 | LT7: =+LT20 -> 3694.1538 | LU7: =+LU20 -> 14494.795 | LW7: Revenue | LX7: =+LX20 -> 3628.2348 | LY7: =+LY20 -> 3808.953 | LZ7: =+LZ20 -> 3876.0114 | MA7: =+MA20 -> 3867.7067 | MB7: =+MB20 -> 15180.906 | MD7: Revenue | ME7: =+ME20 -> 3790.9745 | MF7: =+MF20 -> 3977.245 | MG7: =+MG20 -> 4046.1072 | MH7: =+MH20 -> 4034.3107 | MI7: =+MI20 -> 15848.637
B8: Yr/ Yr % | D8: =+D7/C7-1 -> 0.16458421 | E8: =+E7/D7-1 -> 0.11931562 | F8: =+F7/E7-1 -> 0.13164246 | G8: =+G7/F7-1 -> -0.091708449 | H8: =+H7/G7-1 -> 0.0096807415 | I8: =+I7/H7-1 -> 0.14177887 | J8: =+J7/I7-1 -> -0.042165446 | K8: =+K7/J7-1 -> 0.12367096 | ... M8: =+M7/L7-1 -> 0.092374101 | N8: =BV8 -> #DIV/0! | O8: =CC8 -> 0.059434087 | P8: =CJ8 -> 0.052524845 | Q8: =CQ8 -> 0.011324294 | R8: =CX8 -> 0.023631513 | S8: =DE8 -> 0.074660254 | T8: =DL8 -> 0.072439634 | U8: =DS8 -> 0.022515528 | V8: =DZ8 -> 0.040527715 | W8: =EG8 -> -0.10051993 | X8: =EN8 -> 0.096339114 | Y8: =EU8 -> -0.21977615 | Z8: =FB8 -> -0.038529935 | AA8: =FI8 -> 0.0051787916 | AB8: =FP8 -> -0.071761531 | AC8: =FW8 -> 0.060525968 | AD8: =GD8 -> 0.071775701 | AE8: =GK8 -> 0.11219626 | AF8: =GR8 -> 0.048505122 | AG8: =GY8 -> 0.1221336 | AH8: =HF8 -> -0.19671257 | AI8: =HM8 -> 0.17641854 | AJ8: =HT8 -> 0.10408048 | AK8: =IA8 -> 0.0011070425 | AL8: =IH8 -> 0.02568901 | AM8: =IO8 -> 0.050671753 | AN8: =IV8 -> -0.067724367 | AO8: =JC8 -> -0.062822792 | AP8: =JJ8 -> 0.030626073 | AQ8: =JQ8 -> 0.073807854 | AR8: =JX8 -> -0.02555102 | AS8: =KE8 -> -0.11342883 | AT8: =KL8 -> 0.18321837 | AU8: =KS8 -> 0.18615237 | AV8: =KZ8 -> -0.013195987 | AW8: =LG8 -> -0.0079825339 | AX8: =LN8 -> -0.030811554 | AY8: =LU8 -> 0.028583258 | AZ8: =MB8 -> 0.047334962 | BA8: =MI8 -> 0.043984959 | BQ8: Yr/ Yr % | BR8: =+BR7/AV7-1 -> -0.87420345 | BS8: =+BS7/AW7-1 -> -0.86423659 | BT8: =+BT7/AX7-1 -> -0.86567556 | BU8: =+BU7/AY7-1 -> -0.85965307 | BV8: =+BV7/BP7-1 -> #DIV/0! | BX8: Yr/ Yr % | BY8: =+BY7/BR7-1 -> 0.034656687 | BZ8: =+BZ7/BS7-1 -> 0.036930091 | CA8: =+CA7/BT7-1 -> 0.089862116 | CB8: =+CB7/BU7-1 -> 0.075415131 | CC8: =+CC7/BV7-1 -> 0.059434087 | CE8: Yr/ Yr % | CF8: =+CF7/BY7-1 -> 0.06426587 | CG8: =+CG7/BZ7-1 -> 0.038155259 | CH8: =+CH7/CA7-1 -> 0.068783325 | CI8: =+CI7/CB7-1 -> 0.040399649 | CJ8: =+CJ7/CC7-1 -> 0.052524845 | CL8: Yr/ Yr % | CM8: =+CM7/CF7-1 -> 0.027631385 | CN8: =+CN7/CG7-1 -> 0.029741176 | CO8: =+CO7/CH7-1 -> 0.0042632319 | CP8: =+CP7/CI7-1 -> -0.013575853 | CQ8: =+CQ7/CJ7-1 -> 0.011324294 | CS8: Yr/ Yr % | CT8: =+CT7/CM7-1 -> 0.017685966 | CU8: =+CU7/CN7-1 -> 0.034411845 | CV8: =+CV7/CO7-1 -> 0.011019284 | CW8: =+CW7/CP7-1 -> 0.031088544 | CX8: =+CX7/CQ7-1 -> 0.023631513 | CZ8: Yr/ Yr % | DA8: =+DA7/CT7-1 -> 0.048839071 | DB8: =+DB7/CU7-1 -> 0.047492821 | DC8: =+DC7/CV7-1 -> 0.10331889 | DD8: =+DD7/CW7-1 -> 0.097192225 | DE8: =+DE7/CX7-1 -> 0.074660254 | DG8: Yr/ Yr % | DH8: =+DH7/DA7-1 -> 0.097440503 | DI8: =+DI7/DB7-1 -> 0.075073809 | DJ8: =+DJ7/DC7-1 -> 0.053036437 | DK8: =+DK7/DD7-1 -> 0.066929134 | DL8: =+DL7/DE7-1 -> 0.072439634 | DN8: Yr/ Yr % | DO8: =+DO7/DH7-1 -> 0.028641571 | DP8: =+DP7/DI7-1 -> 0.048254217 | DQ8: =+DQ7/DJ7-1 -> 0.017685506 | DR8: =+DR7/DK7-1 -> -0.0025830258 | DS8: =+DS7/DL7-1 -> 0.022515528 | DU8: Yr/ Yr % | DV8: =+DV7/DO7-1 -> 0.021081941 | DW8: =+DW7/DP7-1 -> 0.002245509 | DX8: =+DX7/DQ7-1 -> 0.063468077 | DY8: =+DY7/DR7-1 -> 0.073991861 | DZ8: =+DZ7/DS7-1 -> 0.040527715 | EB8: Yr/ Yr % | EC8: =+EC7/DV7-1 -> -0.048694975 | ED8: =+ED7/DW7-1 -> -0.070201643 | EE8: =+EE7/DX7-1 -> -0.13712256 | EF8: =+EF7/DY7-1 -> -0.13882191 | EG8: =+EG7/DZ7-1 -> -0.10051993 | EI8: Yr/ Yr % | EJ8: =+EJ7/EC7-1 -> 0.040540541 | EK8: =+EK7/ED7-1 -> 0.05060241 | EL8: =+EL7/EE7-1 -> 0.19637711 | EM8: =+EM7/EF7-1 -> 0.0992 | EN8: =+EN7/EG7-1 -> 0.096339114 | EP8: Yr/ Yr % | EQ8: =+EQ7/EJ7-1 -> -0.15505706 | ER8: =+ER7/EK7-1 -> -0.15825688 | ES8: =+ES7/EL7-1 -> -0.29834825 | ET8: =+ET7/EM7-1 -> -0.25509461 | EU8: =+EU7/EN7-1 -> -0.21977615 | EW8: Yr/ Yr % | EX8: =+EX7/EQ7-1 -> -0.056823475 | EY8: =+EY7/ER7-1 -> -0.065849228 | EZ8: =+EZ7/ES7-1 -> -0.0098087298 | FA8: =+FA7/ET7-1 -> -0.018563752 | FB8: =+FB7/EU7-1 -> -0.038529935 | FD8: Yr/ Yr % | FE8: =+FE7/EX7-1 -> -0.030123457 | FF8: =+FF7/EY7-1 -> 0.0077783179 | FG8: =+FG7/EZ7-1 -> 0.017830609 | FH8: =+FH7/FA7-1 -> 0.025385764 | FI8: =+FI7/FB7-1 -> 0.0051787916 | FK8: Yr/ Yr % | FL8: =+FL7/FE7-1 -> -0.0020366599 | FM8: =+FM7/FF7-1 -> -0.089242644 | FN8: =+FN7/FG7-1 -> -0.11289538 | FO8: =+FO7/FH7-1 -> -0.07961165 | FP8: =+FP7/FI7-1 -> -0.071761531 | FR8: Yr/ Yr % | FS8: =+FS7/FL7-1 -> -0.020408163 | FT8: =+FT7/FM7-1 -> 0.056673729 | FU8: =+FU7/FN7-1 -> 0.06308283 | FV8: =+FV7/FO7-1 -> 0.14556962 | FW8: =+FW7/FP7-1 -> 0.060525968 | FY8: Yr/ Yr % | FZ8: =+FZ7/FS7-1 -> 0.097916667 | GA8: =+GA7/FT7-1 -> 0.077192982 | GB8: =+GB7/FU7-1 -> 0.096491228 | GC8: =+GC7/FV7-1 -> 0.021639042 | GD8: =+GD7/FW7-1 -> 0.071775701 | GF8: Yr/ Yr % | GG8: =+GG7/FZ7-1 -> 0.10578748 | GH8: =+GH7/GA7-1 -> 0.1265705 | GI8: =+GI7/GB7-1 -> 0.13788235 | GJ8: =+GJ7/GC7-1 -> 0.07976566 | GK8: =+GK7/GD7-1 -> 0.11219626 | GM8: Yr/ Yr % | GN8: =+GN7/GG7-1 -> 0.039039039 | GO8: =+GO7/GH7-1 -> 0.045022718 | GP8: =+GP7/GI7-1 -> 0.034325889 | GQ8: =+GQ7/GJ7-1 -> 0.075542571 | GR8: =+GR7/GK7-1 -> 0.048505122 | GT8: Yr/ Yr % | GU8: =+GU7/GN7-1 -> 0.12014864 | GV8: =+GV7/GO7-1 -> 0.14901186 | GW8: =+GW7/GP7-1 -> 0.18392643 | GX8: =+GX7/GQ7-1 -> 0.037640667 | GY8: =+GY7/GR7-1 -> 0.1221336 | HA8: Yr/ Yr % | HB8: =+HB7/GU7-1 -> -0.17176557 | HC8: =+HC7/GV7-1 -> -0.24836601 | HD8: =+HD7/GW7-1 -> -0.22695035 | HE8: =+HE7/GX7-1 -> -0.13238594 | HF8: =+HF7/GY7-1 -> -0.19671257 | HH8: Yr/ Yr % | HI8: =+HI7/HB7-1 -> 0.10858923 | HJ8: =+HJ7/HC7-1 -> 0.2187643 | HK8: =+HK7/HD7-1 -> 0.16470074 | HL8: =+HL7/HE7-1 -> 0.2137931 | HM8: =+HM7/HF7-1 -> 0.17641854 | HO8: Yr/ Yr % | HP8: =+HP7/HI7-1 -> 0.12806102 | HQ8: =+HQ7/HJ7-1 -> 0.13368382 | HR8: =+HR7/HK7-1 -> 0.11140285 | HS8: =+HS7/HL7-1 -> 0.047940341 | HT8: =+HT7/HM7-1 -> 0.10408048 | HV8: Yr/ Yr % | HW8: =+HW7/HP7-1 -> 0.055516014 | HX8: =+HX7/HQ7-1 -> -0.0023186486 | HY8: =+HY7/HR7-1 -> -0.023287209 | HZ8: =+HZ7/HS7-1 -> -0.022704168 | IA8: =+IA7/HT7-1 -> 0.0011070425 | IC8: Yr/ Yr % | ID8: =+ID7/HW7-1 -> -0.0026972353 | IE8: =+IE7/HX7-1 -> 0.018924303 | IF8: =+IF7/HY7-1 -> 0.036281963 | IG8: =+IG7/HZ7-1 -> 0.051317614 | IH8: =+IH7/IA7-1 -> 0.02568901 | IJ8: Yr/ Yr % | IK8: =+IK7/ID7-1 -> 0.018255578 | IL8: =+IL7/IE7-1 -> 0.057021831 | IM8: =+IM7/IF7-1 -> 0.074024675 | IN8: =+IN7/IG7-1 -> 0.052770449 | IO8: =+IO7/IH7-1 -> 0.050671753 | IQ8: Yr/ Yr % | IR8: =+IR7/IK7-1 -> 0.0049800797 | IS8: =+IS7/IL7-1 -> -0.055487053 | IT8: =+IT7/IM7-1 -> -0.08755045 | IU8: =+IU7/IN7-1 -> -0.1287594 | IV8: =+IV7/IO7-1 -> -0.067724367 | IX8: Yr/ Yr % | IY8: =+IY7/IR7-1 -> -0.13511728 | IZ8: =+IZ7/IS7-1 -> -0.11749347 | JA8: =+JA7/IT7-1 -> -0.077917659 | JB8: =+JB7/IU7-1 -> 0.092053218 | JC8: =+JC7/IV7-1 -> -0.062822792 | JE8: Yr/ Yr % | JF8: =+JF7/IY7-1 -> 0.095874714 | JG8: =+JG7/IZ7-1 -> 0.084689349 | JH8: =+JH7/JA7-1 -> 0.012177122 | JI8: =+JI7/JB7-1 -> -0.057293382 | JJ8: =+JJ7/JC7-1 -> 0.030626073 | JL8: Yr/ Yr % | JM8: =+JM7/JF7-1 -> 0.0024398745 | JN8: =+JN7/JG7-1 -> 0.057620184 | JO8: =+JO7/JH7-1 -> 0.14072184 | JP8: =+JP7/JI7-1 -> 0.097799511 | JQ8: =+JQ7/JJ7-1 -> 0.073807854 | JS8: Yr/ Yr % | JT8: =+JT7/JM7-1 -> 0.047635605 | JU8: =+JU7/JN7-1 -> -0.013217279 | JV8: =+JV7/JO7-1 -> -0.048258229 | JW8: =+JW7/JP7-1 -> -0.082087178 | JX8: =+JX7/JQ7-1 -> -0.02555102 | JZ8: Yr/ Yr % | KA8: =+KA7/JT7-1 -> -0.052439429 | KB8: =+KB7/JU7-1 -> -0.26331264 | KC8: =+KC7/JV7-1 -> -0.11081263 | KD8: =+KD7/JW7-1 -> -0.020797227 | KE8: =+KE7/JX7-1 -> -0.11342883 | KG8: Yr/ Yr % | KH8: =+KH7/KA7-1 -> -0.014711033 | KI8: =+KI7/KB7-1 -> 0.32594235 | KJ8: =+KJ7/KC7-1 -> 0.24320242 | KK8: =+KK7/KD7-1 -> 0.21309735 | KL8: =+KL7/KE7-1 -> 0.18321837 | KN8: Yr/ Yr % | KO8: =+KO7/KH7-1 -> 0.21329541 | KP8: =+KP7/KI7-1 -> 0.27591973 | KQ8: =+KQ7/KJ7-1 -> 0.18317132 | KR8: =+KR7/KK7-1 -> 0.088415524 | KS8: =+KS7/KL7-1 -> 0.18615237 | KU8: Yr/ Yr % | KV8: =+KV7/KO7-1 -> 0.085848227 | KW8: =+KW7/KP7-1 -> -0.030406291 | KX8: =+KX7/KQ7-1 -> -0.082926829 | KY8: =+KY7/KR7-1 -> -0.013404826 | KZ8: =+KZ7/KS7-1 -> -0.013195987 | LB8: Yr/ Yr % | LC8: =+LC7/KV7-1 -> -0.0067458176 | LD8: =+LD7/KW7-1 -> 0.00054068667 | LE8: =+LE7/KX7-1 -> 0.013157895 | LF8: =+LF7/KY7-1 -> -0.038315217 | LG8: =+LG7/KZ7-1 -> -0.0079825339 | LI8: Yr/ Yr % | LJ8: =+LJ7/LC7-1 -> -0.07008965 | LK8: =+LK7/LD7-1 -> -0.03431505 | LL8: =+LL7/LE7-1 -> -0.0088422216 | LM8: =+LM7/LF7-1 -> -0.0087595366 | LN8: =+LN7/LG7-1 -> -0.030811554 | LP8: Yr/ Yr % | LQ8: =+LQ7/LJ7-1 -> 0.011048035 | LR8: =+LR7/LK7-1 -> 0.017316711 | LS8: =+LS7/LL7-1 -> 0.032599428 | LT8: =+LT7/LM7-1 -> 0.0530655 | LU8: =+LU7/LN7-1 -> 0.028583258 | LW8: Yr/ Yr % | LX8: =+LX7/LQ7-1 -> 0.048375105 | LY8: =+LY7/LR7-1 -> 0.047598534 | LZ8: =+LZ7/LS7-1 -> 0.046457965 | MA8: =+MA7/LT7-1 -> 0.046980423 | MB8: =+MB7/LU7-1 -> 0.047334962 | MD8: Yr/ Yr % | ME8: =+ME7/LX7-1 -> 0.044853677 | MF8: =+MF7/LY7-1 -> 0.044183271 | MG8: =+MG7/LZ7-1 -> 0.04388424 | MH8: =+MH7/MA7-1 -> 0.043075665 | MI8: =+MI7/MB7-1 -> 0.043984959
B10: EPS (Recurring) | C10: =+C62 -> 0.041307607 | D10: =+D62 -> 0.076148068 | E10: =+E62 -> 0.078254736 | F10: =+F62 -> 0.10113868 | G10: =+G62 -> 0.060979194 | H10: =+H62 -> 0.047014456 | I10: =+I62 -> 0.066982961 | J10: =+J62 -> 0.067477122 | ... M10: =+M62 -> 0.085371526 | N10: =BV10 -> 0.11623156 | O10: =CC10 -> 0.11117791 | P10: =CJ10 -> 0.11310847 | Q10: =CQ10 -> 0.12535025 | R10: =CX10 -> 0.12431525 | S10: =DE10 -> 0.1612841 | T10: =DL10 -> 0.19242969 | U10: =DS10 -> 0.21644196 | V10: =DZ10 -> 0.22457436 | W10: =EG10 -> 0.13641276 | X10: =EN10 -> 0.085698428 | Y10: =EU10 -> 0.050115849 | Z10: =FB10 -> 0.088061976 | AA10: =FI10 -> 0.11971524 | AB10: =FP10 -> 0.097850741 | AC10: =FW10 -> 0.11144133 | AD10: =GD10 -> 0.18553469 | AE10: =GK10 -> 0.28476892 | AF10: =GR10 -> 0.30678563 | AG10: =GY10 -> 0.39013514 | AH10: =HF10 -> 0.31030609 | AI10: =HM10 -> 0.4586944 | AJ10: =HT10 -> 0.54882155 | AK10: =IA10 -> 0.58162179 | AL10: =IH10 -> 0.60680406 | AM10: =IO10 -> 0.64105123 | AN10: =IV10 -> 0.66666667 | AO10: =JC10 -> 0.62733826 | AP10: =JJ10 -> 0.76477024 | AQ10: =JQ10 -> 1.2810685 | AR10: =JX10 -> 1.3913952 | AS10: =KE10 -> 1.2000868 | AT10: =KL10 -> 1.558063 | AU10: =KS10 -> 1.9027352 | AV10: =KZ10 -> 1.822156 | AW10: =LG10 -> 1.8283361 | AX10: =LN10 -> 1.6447654 | AY10: =LU10 -> 1.8953327 | AZ10: =MB10 -> 2.2046884 | BA10: =MI10 -> 2.4592512 | BQ10: EPS (Recurring) | BR10: =+BR62 -> 0.019976487 | BS10: =+BS62 -> 0.035563823 | BT10: =+BT62 -> 0.025838288 | BU10: =+BU62 -> 0.035345139 | BV10: =+BV62 -> 0.11623156 | BX10: EPS (Recurring) | BY10: =+BY62 -> 0.016441639 | BZ10: =+BZ62 -> 0.030402705 | CA10: =+CA62 -> 0.028153938 | CB10: =+CB62 -> 0.036120252 | CC10: =+CC62 -> 0.11117791 | CE10: EPS (Recurring) | CF10: =+CF62 -> 0.015905935 | CG10: =+CG62 -> 0.031676201 | CH10: =+CH62 -> 0.029237171 | CI10: =+CI62 -> 0.035971022 | CJ10: =+CJ62 -> 0.11310847 | CL10: EPS (Recurring) | CM10: =+CM62 -> 0.01668723 | CN10: =+CN62 -> 0.03392481 | CO10: =+CO62 -> 0.034182598 | CP10: =+CP62 -> 0.040490138 | CQ10: =+CQ62 -> 0.12535025 | CS10: EPS (Recurring) | CT10: =+CT62 -> 0.013844813 | CU10: =+CU62 -> 0.040601765 | CV10: =+CV62 -> 0.030003775 | CW10: =+CW62 -> 0.039810974 | CX10: =+CX62 -> 0.12431525 | CZ10: EPS (Recurring) | DA10: =+DA62 -> 0.01944321 | DB10: =+DB62 -> 0.042463646 | DC10: =+DC62 -> 0.046383648 | DD10: =+DD62 -> 0.052940504 | DE10: =+DE62 -> 0.1612841 | DG10: EPS (Recurring) | DH10: =+DH62 -> 0.031645305 | DI10: =+DI62 -> 0.048021865 | DJ10: =+DJ62 -> 0.053831268 | DK10: =+DK62 -> 0.058857523 | DL10: =+DL62 -> 0.19242969 | DN10: EPS (Recurring) | DO10: =+DO62 -> 0.037990797 | DP10: =+DP62 -> 0.057399229 | DQ10: =+DQ62 -> 0.056731847 | DR10: =+DR62 -> 0.064073245 | DS10: =+DS62 -> 0.21644196 | DU10: EPS (Recurring) | DV10: =+DV62 -> 0.039463567 | DW10: =+DW62 -> 0.059108403 | DX10: =+DX62 -> 0.060608557 | DY10: =+DY62 -> 0.072172427 | DZ10: =+DZ62 -> 0.22457436 | EB10: EPS (Recurring) | EC10: =+EC62 -> 0.026448158 | ED10: =+ED62 -> 0.044268314 | EE10: =+EE62 -> 0.03273974 | EF10: =+EF62 -> 0.032931683 | EG10: =+EG62 -> 0.13641276 | EI10: EPS (Recurring) | EJ10: =+EJ62 -> 0.017451633 | EK10: =+EK62 -> 0.025020681 | EL10: =+EL62 -> 0.03241773 | EM10: =+EM62 -> 0.010795053 | EN10: =+EN62 -> 0.085698428 | EP10: EPS (Recurring) | EQ10: =+EQ62 -> 0.0059310007 | ER10: =+ER62 -> 0.014466839 | ES10: =+ES62 -> 0.015515814 | ET10: =+ET62 -> 0.014229811 | EU10: =+EU62 -> 0.050115849 | EW10: EPS (Recurring) | EX10: =+EX62 -> 0.0069986833 | EY10: =+EY62 -> 0.028240078 | EZ10: =+EZ62 -> 0.025611394 | FA10: =+FA62 -> 0.027164104 | FB10: =+FB62 -> 0.088061976 | FD10: EPS (Recurring) | FE10: =+FE62 -> 0.017720239 | FF10: =+FF62 -> 0.03327354 | FG10: =+FG62 -> 0.033078535 | FH10: =+FH62 -> 0.035617535 | FI10: =+FI62 -> 0.11971524 | FK10: EPS (Recurring) | FL10: =+FL62 -> 0.0095980443 | FM10: =+FM62 -> 0.030574198 | FN10: =+FN62 -> 0.027718208 | FO10: =+FO62 -> 0.029448156 | FP10: =+FP62 -> 0.097850741 | FR10: EPS (Recurring) | FS10: =+FS62 -> 0.01482272 | FT10: =+FT62 -> 0.032536429 | FU10: =+FU62 -> 0.024845955 | FV10: =+FV62 -> 0.039194284 | FW10: =+FW62 -> 0.11144133 | FY10: EPS (Recurring) | FZ10: =+FZ62 -> 0.037815279 | GA10: =+GA62 -> 0.050435333 | GB10: =+GB62 -> 0.039887013 | GC10: =+GC62 -> 0.057253471 | GD10: =+GD62 -> 0.18553469 | GF10: EPS (Recurring) | GG10: =+GG62 -> 0.058622594 | GH10: =+GH62 -> 0.09381231 | GI10: =+GI62 -> 0.073162632 | GJ10: =+GJ62 -> 0.068904499 | GK10: =+GK62 -> 0.28476892 | GM10: EPS (Recurring) | GN10: =+GN62 -> 0.059732513 | GO10: =+GO62 -> 0.078444532 | GP10: =+GP62 -> 0.074066094 | GQ10: =+GQ62 -> 0.096070405 | GR10: =+GR62 -> 0.30678563 | GT10: EPS (Recurring) | GU10: =+GU62 -> 0.088576242 | GV10: =+GV62 -> 0.098340159 | GW10: =+GW62 -> 0.10390663 | GX10: =+GX62 -> 0.099520406 | GY10: =+GY62 -> 0.39013514 | HA10: EPS (Recurring) | HB10: =+HB62 -> 0.069356086 | HC10: =+HC62 -> 0.078688518 | HD10: =+HD62 -> 0.081020449 | HE10: =+HE62 -> 0.081176676 | HF10: =+HF62 -> 0.31030609 | HH10: EPS (Recurring) | HI10: =+HI62 -> 0.085660089 | HJ10: =+HJ62 -> 0.12021858 | HK10: =+HK62 -> 0.12692868 | HL10: =+HL62 -> 0.12706856 | HM10: =+HM62 -> 0.4586944 | HO10: EPS (Recurring) | HP10: =+HP62 -> 0.1180867 | HQ10: =+HQ62 -> 0.14788097 | HR10: =+HR62 -> 0.14360879 | HS10: =+HS62 -> 0.1395202 | HT10: =+HT62 -> 0.54882155 | HV10: EPS (Recurring) | HW10: =+HW62 -> 0.14267556 | HX10: =+HX62 -> 0.16075423 | HY10: =+HY62 -> 0.14583333 | HZ10: =+HZ62 -> 0.13218547 | IA10: =+IA62 -> 0.58162179 | IC10: EPS (Recurring) | ID10: =+ID62 -> 0.14956012 | IE10: =+IE62 -> 0.16878462 | IF10: =+IF62 -> 0.14800262 | IG10: =+IG62 -> 0.14017769 | IH10: =+IH62 -> 0.60680406 | IJ10: EPS (Recurring) | IK10: =+IK62 -> 0.13161376 | IL10: =+IL62 -> 0.17580592 | IM10: =+IM62 -> 0.1698365 | IN10: =+IN62 -> 0.16448911 | IO10: =+IO62 -> 0.64105123 | IQ10: EPS (Recurring) | IR10: =+IR62 -> 0.14852151 | IS10: =+IS62 -> 0.18638355 | IT10: =+IT62 -> 0.17209776 | IU10: =+IU62 -> 0.15964371 | IV10: =+IV62 -> 0.66666667 | IX10: EPS (Recurring) | IY10: =+IY62 -> 0.12322603 | IZ10: =+IZ62 -> 0.15581232 | JA10: =+JA62 -> 0.16083422 | JB10: =+JB62 -> 0.18828877 | JC10: =+JC62 -> 0.62733826 | JE10: EPS (Recurring) | JF10: =+JF62 -> 0.16864011 | JG10: =+JG62 -> 0.21320346 | JH10: =+JH62 -> 0.17034584 | JI10: =+JI62 -> 0.21316964 | JJ10: =+JJ62 -> 0.76477024 | JL10: EPS (Recurring) | JM10: =+JM62 -> 0.26088589 | JN10: =+JN62 -> 0.33678955 | JO10: =+JO62 -> 0.34894614 | JP10: =+JP62 -> 0.33733493 | JQ10: =+JQ62 -> 1.2810685 | JS10: EPS (Recurring) | JT10: =+JT62 -> 0.34026928 | JU10: =+JU62 -> 0.35935564 | JV10: =+JV62 -> 0.36026936 | JW10: =+JW62 -> 0.33033419 | JX10: =+JX62 -> 1.3913952 | JZ10: EPS (Recurring) | KA10: =+KA62 -> 0.33203967 | KB10: =+KB62 -> 0.21686223 | KC10: =+KC62 -> 0.31986093 | KD10: =+KD62 -> 0.33072237 | KE10: =+KE62 -> 1.2000868 | KG10: EPS (Recurring) | KH10: =+KH62 -> 0.3088364 | KI10: =+KI62 -> 0.39799216 | KJ10: =+KJ62 -> 0.43175736 | KK10: =+KK62 -> 0.42129003 | KL10: =+KL62 -> 1.558063 | KN10: EPS (Recurring) | KO10: =+KO62 -> 0.39170087 | KP10: =+KP62 -> 0.50196768 | KQ10: =+KQ62 -> 0.52257761 | KR10: =+KR62 -> 0.4882494 | KS10: =+KS62 -> 1.9027352 | KU10: EPS (Recurring) | KV10: =+KV62 -> 0.47327502 | KW10: =+KW62 -> 0.48592593 | KX10: =+KX62 -> 0.4142071 | KY10: =+KY62 -> 0.44794312 | KZ10: =+KZ62 -> 1.822156 | LB10: EPS (Recurring) | LC10: =+LC62 -> 0.44852192 | LD10: =+LD62 -> 0.49435318 | LE10: =+LE62 -> 0.46082474 | LF10: =+LF62 -> 0.4242582 | LG10: =+LG62 -> 1.8283361 | LI10: EPS (Recurring) | LJ10: =+LJ62 -> 0.34143763 | LK10: =+LK62 -> 0.4435527 | LL10: =+LL62 -> 0.45257097 | LM10: =+LM62 -> 0.40809853 | LN10: =+LN62 -> 1.6447654 | LP10: EPS (Recurring) | LQ10: =+LQ62 -> 0.4027231 | LR10: =+LR62 -> 0.48784498 | LS10: =+LS62 -> 0.50931281 | LT10: =+LT62 -> 0.49684328 | LU10: =+LU62 -> 1.8953327 | LW10: EPS (Recurring) | LX10: =+LX62 -> 0.47512354 | LY10: =+LY62 -> 0.56740712 | LZ10: =+LZ62 -> 0.59371422 | MA10: =+MA62 -> 0.56994235 | MB10: =+MB62 -> 2.2046884 | MD10: EPS (Recurring) | ME10: =+ME62 -> 0.53775277 | MF10: =+MF62 -> 0.63197805 | MG10: =+MG62 -> 0.65647148 | MH10: =+MH62 -> 0.63467794 | MI10: =+MI62 -> 2.4592512
B11: Yr/ Yr % | D11: =+D10/C10-1 -> 0.84343935 | E11: =+E10/D10-1 -> 0.027665412 | F11: =+F10/E10-1 -> 0.29242883 | G11: =+G10/F10-1 -> -0.39707345 | H11: =+H10/G10-1 -> -0.22900824 | I11: =+I10/H10-1 -> 0.42473116 | J11: =+J10/I10-1 -> 0.007377414 | K11: =+K10/J10-1 -> -0.16388363 | ... M11: =+M10/L10-1 -> 0.28303104 | N11: =BV11 -> #DIV/0! | O11: =CC11 -> -0.043479077 | P11: =CJ11 -> 0.017364515 | Q11: =CQ11 -> 0.10823051 | R11: =CX11 -> -0.0082568601 | S11: =DE11 -> 0.29737986 | T11: =DL11 -> 0.19311008 | U11: =DS11 -> 0.12478462 | V11: =DZ11 -> 0.037573138 | W11: =EG11 -> -0.392572 | X11: =EN11 -> -0.37177116 | Y11: =EU11 -> -0.4152069 | Z11: =FB11 -> 0.75716819 | AA11: =FI11 -> 0.35944308 | AB11: =FP11 -> -0.18263758 | AC11: =FW11 -> 0.13889102 | AD11: =GD11 -> 0.66486427 | AE11: =GK11 -> 0.53485542 | AF11: =GR11 -> 0.077314276 | AG11: =GY11 -> 0.2716865 | AH11: =HF11 -> -0.20461896 | AI11: =HM11 -> 0.47819977 | AJ11: =HT11 -> 0.19648627 | AK11: =IA11 -> 0.059764866 | AL11: =IH11 -> 0.043296626 | AM11: =IO11 -> 0.056438605 | AN11: =IV11 -> 0.039958485 | AO11: =JC11 -> -0.058992616 | AP11: =JJ11 -> 0.21907158 | AQ11: =JQ11 -> 0.67510248 | AR11: =JX11 -> 0.086120787 | AS11: =KE11 -> -0.1374939 | AT11: =KL11 -> 0.29829196 | AU11: =KS11 -> 0.22121837 | AV11: =KZ11 -> -0.042349156 | AW11: =LG11 -> 0.003391661 | AX11: =LN11 -> -0.10040314 | AY11: =LU11 -> 0.15234224 | AZ11: =MB11 -> 0.16321975 | BA11: =MI11 -> 0.11546429 | BQ11: Yr/ Yr % | BR11: =+BR10/AV10-1 -> -0.9890369 | BS11: =+BS10/AW10-1 -> -0.98054853 | BT11: =+BT10/AX10-1 -> -0.98429059 | BU11: =+BU10/AY10-1 -> -0.98135149 | BV11: =+BV10/BP10-1 -> #DIV/0! | BX11: Yr/ Yr % | BY11: =+BY10/BR10-1 -> -0.17695044 | BZ11: =+BZ10/BS10-1 -> -0.1451227 | CA11: =+CA10/BT10-1 -> 0.089620861 | CB11: =+CB10/BU10-1 -> 0.021929822 | CC11: =+CC10/BV10-1 -> -0.043479077 | CE11: Yr/ Yr % | CF11: =+CF10/BY10-1 -> -0.03258217 | CG11: =+CG10/BZ10-1 -> 0.041887578 | CH11: =+CH10/CA10-1 -> 0.038475364 | CI11: =+CI10/CB10-1 -> -0.00413147 | CJ11: =+CJ10/CC10-1 -> 0.017364515 | CL11: Yr/ Yr % | CM11: =+CM10/CF10-1 -> 0.04911974 | CN11: =+CN10/CG10-1 -> 0.070987321 | CO11: =+CO10/CH10-1 -> 0.16914864 | CP11: =+CP10/CI10-1 -> 0.12563212 | CQ11: =+CQ10/CJ10-1 -> 0.10823051 | CS11: Yr/ Yr % | CT11: =+CT10/CM10-1 -> -0.17033486 | CU11: =+CU10/CN10-1 -> 0.19681629 | CV11: =+CV10/CO10-1 -> -0.12225001 | CW11: =+CW10/CP10-1 -> -0.016773562 | CX11: =+CX10/CQ10-1 -> -0.0082568601 | CZ11: Yr/ Yr % | DA11: =+DA10/CT10-1 -> 0.40436778 | DB11: =+DB10/CU10-1 -> 0.045857162 | DC11: =+DC10/CV10-1 -> 0.54592705 | DD11: =+DD10/CW10-1 -> 0.32979675 | DE11: =+DE10/CX10-1 -> 0.29737986 | DG11: Yr/ Yr % | DH11: =+DH10/DA10-1 -> 0.62757618 | DI11: =+DI10/DB10-1 -> 0.13089357 | DJ11: =+DJ10/DC10-1 -> 0.16056565 | DK11: =+DK10/DD10-1 -> 0.11176732 | DL11: =+DL10/DE10-1 -> 0.19311008 | DN11: Yr/ Yr % | DO11: =+DO10/DH10-1 -> 0.20051923 | DP11: =+DP10/DI10-1 -> 0.19527282 | DQ11: =+DQ10/DJ10-1 -> 0.053882784 | DR11: =+DR10/DK10-1 -> 0.088616073 | DS11: =+DS10/DL10-1 -> 0.12478462 | DU11: Yr/ Yr % | DV11: =+DV10/DO10-1 -> 0.038766505 | DW11: =+DW10/DP10-1 -> 0.029776946 | DX11: =+DX10/DQ10-1 -> 0.068333923 | DY11: =+DY10/DR10-1 -> 0.12640505 | DZ11: =+DZ10/DS10-1 -> 0.037573138 | EB11: Yr/ Yr % | EC11: =+EC10/DV10-1 -> -0.32980824 | ED11: =+ED10/DW10-1 -> -0.25106563 | EE11: =+EE10/DX10-1 -> -0.45981654 | EF11: =+EF10/DY10-1 -> -0.54370825 | EG11: =+EG10/DZ10-1 -> -0.392572 | EI11: Yr/ Yr % | EJ11: =+EJ10/EC10-1 -> -0.34015694 | EK11: =+EK10/ED10-1 -> -0.43479481 | EL11: =+EL10/EE10-1 -> -0.0098354341 | EM11: =+EM10/EF10-1 -> -0.67219856 | EN11: =+EN10/EG10-1 -> -0.37177116 | EP11: Yr/ Yr % | EQ11: =+EQ10/EJ10-1 -> -0.66014638 | ER11: =+ER10/EK10-1 -> -0.42180475 | ES11: =+ES10/EL10-1 -> -0.52137876 | ET11: =+ET10/EM10-1 -> 0.31817893 | EU11: =+EU10/EN10-1 -> -0.4152069 | EW11: Yr/ Yr % | EX11: =+EX10/EQ10-1 -> 0.18001728 | EY11: =+EY10/ER10-1 -> 0.95205588 | EZ11: =+EZ10/ES10-1 -> 0.65066387 | FA11: =+FA10/ET10-1 -> 0.90895742 | FB11: =+FB10/EU10-1 -> 0.75716819 | FD11: Yr/ Yr % | FE11: =+FE10/EX10-1 -> 1.531939 | FF11: =+FF10/EY10-1 -> 0.17823823 | FG11: =+FG10/EZ10-1 -> 0.29155545 | FH11: =+FH10/FA10-1 -> 0.3111986 | FI11: =+FI10/FB10-1 -> 0.35944308 | FK11: Yr/ Yr % | FL11: =+FL10/FE10-1 -> -0.45835695 | FM11: =+FM10/FF10-1 -> -0.081125772 | FN11: =+FN10/FG10-1 -> -0.16204851 | FO11: =+FO10/FH10-1 -> -0.17321184 | FP11: =+FP10/FI10-1 -> -0.18263758 | FR11: Yr/ Yr % | FS11: =+FS10/FL10-1 -> 0.54434798 | FT11: =+FT10/FM10-1 -> 0.064179285 | FU11: =+FU10/FN10-1 -> -0.10362332 | FV11: =+FV10/FO10-1 -> 0.33095883 | FW11: =+FW10/FP10-1 -> 0.13889102 | FY11: Yr/ Yr % | FZ11: =+FZ10/FS10-1 -> 1.55117 | GA11: =+GA10/FT10-1 -> 0.55011892 | GB11: =+GB10/FU10-1 -> 0.60537249 | GC11: =+GC10/FV10-1 -> 0.46076074 | GD11: =+GD10/FW10-1 -> 0.66486427 | GF11: Yr/ Yr % | GG11: =+GG10/FZ10-1 -> 0.55023567 | GH11: =+GH10/GA10-1 -> 0.86005135 | GI11: =+GI10/GB10-1 -> 0.83424696 | GJ11: =+GJ10/GC10-1 -> 0.20349906 | GK11: =+GK10/GD10-1 -> 0.53485542 | GM11: Yr/ Yr % | GN11: =+GN10/GG10-1 -> 0.018933306 | GO11: =+GO10/GH10-1 -> -0.16381409 | GP11: =+GP10/GI10-1 -> 0.01234868 | GQ11: =+GQ10/GJ10-1 -> 0.39425446 | GR11: =+GR10/GK10-1 -> 0.077314276 | GT11: Yr/ Yr % | GU11: =+GU10/GN10-1 -> 0.48288155 | GV11: =+GV10/GO10-1 -> 0.25362669 | GW11: =+GW10/GP10-1 -> 0.40289058 | GX11: =+GX10/GQ10-1 -> 0.03591117 | GY11: =+GY10/GR10-1 -> 0.2716865 | HA11: Yr/ Yr % | HB11: =+HB10/GU10-1 -> -0.21698997 | HC11: =+HC10/GV10-1 -> -0.19983333 | HD11: =+HD10/GW10-1 -> -0.22025715 | HE11: =+HE10/GX10-1 -> -0.18432129 | HF11: =+HF10/GY10-1 -> -0.20461896 | HH11: Yr/ Yr % | HI11: =+HI10/HB10-1 -> 0.23507674 | HJ11: =+HJ10/HC10-1 -> 0.5277779 | HK11: =+HK10/HD10-1 -> 0.56662518 | HL11: =+HL10/HE10-1 -> 0.56533334 | HM11: =+HM10/HF10-1 -> 0.47819977 | HO11: Yr/ Yr % | HP11: =+HP10/HI10-1 -> 0.37854978 | HQ11: =+HQ10/HJ10-1 -> 0.23010083 | HR11: =+HR10/HK10-1 -> 0.13141329 | HS11: =+HS10/HL10-1 -> 0.097991543 | HT11: =+HT10/HM10-1 -> 0.19648627 | HV11: Yr/ Yr % | HW11: =+HW10/HP10-1 -> 0.20822724 | HX11: =+HX10/HQ10-1 -> 0.087051501 | HY11: =+HY10/HR10-1 -> 0.015490302 | HZ11: =+HZ10/HS10-1 -> -0.052571087 | IA11: =+IA10/HT10-1 -> 0.059764866 | IC11: Yr/ Yr % | ID11: =+ID10/HW10-1 -> 0.048253205 | IE11: =+IE10/HX10-1 -> 0.049954428 | IF11: =+IF10/HY10-1 -> 0.014875105 | IG11: =+IG10/HZ10-1 -> 0.06046214 | IH11: =+IH10/IA10-1 -> 0.043296626 | IJ11: Yr/ Yr % | IK11: =+IK10/ID10-1 -> -0.11999429 | IL11: =+IL10/IE10-1 -> 0.041599141 | IM11: =+IM10/IF10-1 -> 0.14752363 | IN11: =+IN10/IG10-1 -> 0.17343289 | IO11: =+IO10/IH10-1 -> 0.056438605 | IQ11: Yr/ Yr % | IR11: =+IR10/IK10-1 -> 0.12846491 | IS11: =+IS10/IL10-1 -> 0.060166558 | IT11: =+IT10/IM10-1 -> 0.013314314 | IU11: =+IU10/IN10-1 -> -0.02945726 | IV11: =+IV10/IO10-1 -> 0.039958485 | IX11: Yr/ Yr % | IY11: =+IY10/IR10-1 -> -0.17031524 | IZ11: =+IZ10/IS10-1 -> -0.1640232 | JA11: =+JA10/IT10-1 -> -0.065448514 | JB11: =+JB10/IU10-1 -> 0.17943116 | JC11: =+JC10/IV10-1 -> -0.058992616 | JE11: Yr/ Yr % | JF11: =+JF10/IY10-1 -> 0.36854295 | JG11: =+JG10/IZ10-1 -> 0.36833504 | JH11: =+JH10/JA10-1 -> 0.059139315 | JI11: =+JI10/JB10-1 -> 0.1321421 | JJ11: =+JJ10/JC10-1 -> 0.21907158 | JL11: Yr/ Yr % | JM11: =+JM10/JF10-1 -> 0.5469978 | JN11: =+JN10/JG10-1 -> 0.57966268 | JO11: =+JO10/JH10-1 -> 1.048457 | JP11: =+JP10/JI10-1 -> 0.58247173 | JQ11: =+JQ10/JJ10-1 -> 0.67510248 | JS11: Yr/ Yr % | JT11: =+JT10/JM10-1 -> 0.30428397 | JU11: =+JU10/JN10-1 -> 0.067003514 | JV11: =+JV10/JO10-1 -> 0.032449777 | JW11: =+JW10/JP10-1 -> -0.020753094 | JX11: =+JX10/JQ10-1 -> 0.086120787 | JZ11: Yr/ Yr % | KA11: =+KA10/JT10-1 -> -0.024185567 | KB11: =+KB10/JU10-1 -> -0.39652475 | KC11: =+KC10/JV10-1 -> -0.11216172 | KD11: =+KD10/JW10-1 -> 0.001175104 | KE11: =+KE10/JX10-1 -> -0.1374939 | KG11: Yr/ Yr % | KH11: =+KH10/KA10-1 -> -0.069881038 | KI11: =+KI10/KB10-1 -> 0.83523039 | KJ11: =+KJ10/KC10-1 -> 0.34982838 | KK11: =+KK10/KD10-1 -> 0.27384802 | KL11: =+KL10/KE10-1 -> 0.29829196 | KN11: Yr/ Yr % | KO11: =+KO10/KH10-1 -> 0.26831187 | KP11: =+KP10/KI10-1 -> 0.26125017 | KQ11: =+KQ10/KJ10-1 -> 0.21035021 | KR11: =+KR10/KK10-1 -> 0.15893889 | KS11: =+KS10/KL10-1 -> 0.22121837 | KU11: Yr/ Yr % | KV11: =+KV10/KO10-1 -> 0.20825626 | KW11: =+KW10/KP10-1 -> -0.031957748 | KX11: =+KX10/KQ10-1 -> -0.20737687 | KY11: =+KY10/KR10-1 -> -0.082552651 | KZ11: =+KZ10/KS10-1 -> -0.042349156 | LB11: Yr/ Yr % | LC11: =+LC10/KV10-1 -> -0.052301741 | LD11: =+LD10/KW10-1 -> 0.017342678 | LE11: =+LE10/KX10-1 -> 0.11254669 | LF11: =+LF10/KY10-1 -> -0.052874837 | LG11: =+LG10/KZ10-1 -> 0.003391661 | LI11: Yr/ Yr % | LJ11: =+LJ10/LC10-1 -> -0.23874928 | LK11: =+LK10/LD10-1 -> -0.10276151 | LL11: =+LL10/LE10-1 -> -0.017910872 | LM11: =+LM10/LF10-1 -> -0.038089242 | LN11: =+LN10/LG10-1 -> -0.10040314 | LP11: Yr/ Yr % | LQ11: =+LQ10/LJ10-1 -> 0.17949243 | LR11: =+LR10/LK10-1 -> 0.099857994 | LS11: =+LS10/LL10-1 -> 0.12537668 | LT11: =+LT10/LM10-1 -> 0.21745914 | LU11: =+LU10/LN10-1 -> 0.15234224 | LW11: Yr/ Yr % | LX11: =+LX10/LQ10-1 -> 0.17977722 | LY11: =+LY10/LR10-1 -> 0.16308896 | LZ11: =+LZ10/LS10-1 -> 0.16571623 | MA11: =+MA10/LT10-1 -> 0.14712702 | MB11: =+MB10/LU10-1 -> 0.16321975 | MD11: Yr/ Yr % | ME11: =+ME10/LX10-1 -> 0.13181672 | MF11: =+MF10/LY10-1 -> 0.1138 | MG11: =+MG10/LZ10-1 -> 0.10570282 | MH11: =+MH10/MA10-1 -> 0.1135827 | MI11: =+MI10/MB10-1 -> 0.11546429
B13: Adjusted OR % | C13: =+C24 -> 0.89877647 | D13: =+D24 -> 0.8632432 | E13: =+E24 -> 0.86018546 | F13: =+F24 -> 0.84926663 | G13: =+G24 -> 0.90278064 | H13: =+H24 -> 0.88943288 | I13: =+I24 -> 0.8515276 | J13: =+J24 -> 0.84778959 | ... M13: =+M24 -> 0.8802687 | N13: =BV13 -> 0.88779858 | O13: =CC13 -> 0.8941763 | P13: =CJ13 -> 0.90108032 | Q13: =CQ13 -> 0.88950207 | R13: =CX13 -> 0.8874224 | S13: =DE13 -> 0.87177352 | T13: =DL13 -> 0.86393634 | U13: =DS13 -> 0.85644457 | V13: =DZ13 -> 0.85104442 | W13: =EG13 -> 0.88713112 | X13: =EN13 -> 0.90481917 | Y13: =EU13 -> 0.90361589 | Z13: =FB13 -> 0.87484587 | AA13: =FI13 -> 0.86310108 | AB13: =FP13 -> 0.87960883 | AC13: =FW13 -> 0.86529595 | AD13: =GD13 -> 0.82176491 | AE13: =GK13 -> 0.77796362 | AF13: =GR13 -> 0.77467597 | AG13: =GY13 -> 0.75424256 | AH13: =HF13 -> 0.74825794 | AI13: =HM13 -> 0.70844302 | AJ13: =HT13 -> 0.70893298 | AK13: =IA13 -> 0.70593739 | AL13: =IH13 -> 0.70932161 | AM13: =IO13 -> 0.71481569 | AN13: =IV13 -> 0.69655406 | AO13: =JC13 -> 0.69382961 | AP13: =JJ13 -> 0.66532258 | AQ13: =JQ13 -> 0.60253061 | AR13: =JX13 -> 0.58406635 | AS13: =KE13 -> 0.58782954 | AT13: =KL13 -> 0.5811372 | AU13: =KS13 -> 0.60270652 | AV13: =KZ13 -> 0.6248209 | AW13: =LG13 -> 0.63184319 | AX13: =LN13 -> 0.66136815 | AY13: =LU13 -> 0.63585919 | AZ13: =MB13 -> 0.61438473 | BA13: =MI13 -> 0.60562861 | BQ13: Adjusted OR % | BR13: =+BR24 -> 0.89814514 | BS13: =+BS24 -> 0.88348531 | BT13: =+BT24 -> 0.9070738 | BU13: =+BU24 -> 0.86467089 | BV13: =+BV24 -> 0.88779858 | BX13: Adjusted OR % | BY13: =+BY24 -> 0.9120931 | BZ13: =+BZ24 -> 0.89208071 | CA13: =+CA24 -> 0.88560349 | CB13: =+CB24 -> 0.88859757 | CC13: =+CC24 -> 0.8941763 | CE13: Adjusted OR % | CF13: =+CF24 -> 0.92843422 | CG13: =+CG24 -> 0.90305882 | CH13: =+CH24 -> 0.89074334 | CI13: =+CI24 -> 0.88484689 | CJ13: =+CJ24 -> 0.90108032 | CL13: Adjusted OR % | CM13: =+CM24 -> 0.92455905 | CN13: =+CN24 -> 0.88428846 | CO13: =+CO24 -> 0.8815427 | CP13: =+CP24 -> 0.86985569 | CQ13: =+CQ24 -> 0.88950207 | CS13: Adjusted OR % | CT13: =+CT24 -> 0.92638817 | CU13: =+CU24 -> 0.87740225 | CV13: =+CV24 -> 0.88712199 | CW13: =+CW24 -> 0.86177106 | CX13: =+CX24 -> 0.8874224 | CZ13: Adjusted OR % | DA13: =+DA24 -> 0.91647957 | DB13: =+DB24 -> 0.87178406 | DC13: =+DC24 -> 0.8582996 | DD13: =+DD24 -> 0.84566929 | DE13: =+DE24 -> 0.87177352 | DG13: Adjusted OR % | DH13: =+DH24 -> 0.88707038 | DI13: =+DI24 -> 0.86308356 | DJ13: =+DJ24 -> 0.85390235 | DK13: =+DK24 -> 0.85350554 | DL13: =+DL24 -> 0.86393634 | DN13: Adjusted OR % | DO13: =+DO24 -> 0.88225935 | DP13: =+DP24 -> 0.85086078 | DQ13: =+DQ24 -> 0.85190782 | DR13: =+DR24 -> 0.84239734 | DS13: =+DS24 -> 0.85644457 | DU13: Adjusted OR % | DV13: =+DV24 -> 0.87378263 | DW13: =+DW24 -> 0.83831217 | DX13: =+DX24 -> 0.85719361 | DY13: =+DY24 -> 0.83672063 | DZ13: =+DZ24 -> 0.85104442 | EB13: Adjusted OR % | EC13: =+EC24 -> 0.89434889 | ED13: =+ED24 -> 0.86506024 | EE13: =+EE24 -> 0.89995883 | EF13: =+EF24 -> 0.8896 | EG13: =+EG24 -> 0.88713112 | EI13: Adjusted OR % | EJ13: =+EJ24 -> 0.89728453 | EK13: =+EK24 -> 0.89525994 | EL13: =+EL24 -> 0.89125946 | EM13: =+EM24 -> 0.93522562 | EN13: =+EN24 -> 0.90481917 | EP13: Adjusted OR % | EQ13: =+EQ24 -> 0.92035398 | ER13: =+ER24 -> 0.90917348 | ES13: =+ES24 -> 0.89014223 | ET13: =+ET24 -> 0.89350269 | EU13: =+EU24 -> 0.90361589 | EW13: Adjusted OR % | EX13: =+EX24 -> 0.90666667 | EY13: =+EY24 -> 0.87117161 | EZ13: =+EZ24 -> 0.86131748 | FA13: =+FA24 -> 0.86012942 | FB13: =+FB24 -> 0.87484587 | FD13: Adjusted OR % | FE13: =+FE24 -> 0.89205703 | FF13: =+FF24 -> 0.85045827 | FG13: =+FG24 -> 0.86569343 | FH13: =+FH24 -> 0.84563107 | FI13: =+FI24 -> 0.86310108 | FK13: Adjusted OR % | FL13: =+FL24 -> 0.91734694 | FM13: =+FM24 -> 0.85805085 | FN13: =+FN24 -> 0.87273725 | FO13: =+FO24 -> 0.86867089 | FP13: =+FP24 -> 0.87960883 | FR13: Adjusted OR % | FS13: =+FS24 -> 0.89322917 | FT13: =+FT24 -> 0.84962406 | FU13: =+FU24 -> 0.86635707 | FV13: =+FV24 -> 0.85405157 | FW13: =+FW24 -> 0.86529595 | FY13: Adjusted OR % | FZ13: =+FZ24 -> 0.83206831 | GA13: =+GA24 -> 0.80735226 | GB13: =+GB24 -> 0.83388235 | GC13: =+GC24 -> 0.81433078 | GD13: =+GD24 -> 0.82176491 | GF13: Adjusted OR % | GG13: =+GG24 -> 0.79107679 | GH13: =+GH24 -> 0.73358116 | GI13: =+GI24 -> 0.79776675 | GJ13: =+GJ24 -> 0.79006678 | GK13: =+GK24 -> 0.77796362 | GM13: Adjusted OR % | GN13: =+GN24 -> 0.79975227 | GO13: =+GO24 -> 0.75810277 | GP13: =+GP24 -> 0.77688924 | GQ13: =+GQ24 -> 0.76523089 | GR13: =+GR24 -> 0.77467597 | GT13: Adjusted OR % | GU13: =+GU24 -> 0.76999631 | GV13: =+GV24 -> 0.75335397 | GW13: =+GW24 -> 0.7524485 | GX13: =+GX24 -> 0.74121167 | GY13: =+GY24 -> 0.75424256 | HA13: Adjusted OR % | HB13: =+HB24 -> 0.76769025 | HC13: =+HC24 -> 0.73592677 | HD13: =+HD24 -> 0.74049803 | HE13: =+HE24 -> 0.7487069 | HF13: =+HF24 -> 0.74825794 | HH13: Adjusted OR % | HI13: =+HI24 -> 0.74628663 | HJ13: =+HJ24 -> 0.70033796 | HK13: =+HK24 -> 0.69054764 | HL13: =+HL24 -> 0.69957386 | HM13: =+HM24 -> 0.70844302 | HO13: Adjusted OR % | HP13: =+HP24 -> 0.72491103 | HQ13: =+HQ24 -> 0.69327592 | HR13: =+HR24 -> 0.7036787 | HS13: =+HS24 -> 0.71501186 | HT13: =+HT24 -> 0.70893298 | HV13: Adjusted OR % | HW13: =+HW24 -> 0.71139582 | HX13: =+HX24 -> 0.68691899 | HY13: =+HY24 -> 0.7049067 | HZ13: =+HZ24 -> 0.72122053 | IA13: =+IA24 -> 0.70593739 | IC13: Adjusted OR % | ID13: =+ID24 -> 0.70419202 | IE13: =+IE24 -> 0.68621701 | IF13: =+IF24 -> 0.71523841 | IG13: =+IG24 -> 0.73186016 | IH13: =+IH24 -> 0.70932161 | IJ13: Adjusted OR % | IK13: =+IK24 -> 0.75464807 | IL13: =+IL24 -> 0.69266338 | IM13: =+IM24 -> 0.69698851 | IN13: =+IN24 -> 0.71773183 | IO13: =+IO24 -> 0.71481569 | IQ13: Adjusted OR % | IR13: =+IR24 -> 0.72150644 | IS13: =+IS24 -> 0.66808094 | IT13: =+IT24 -> 0.68254508 | IU13: =+IU24 -> 0.71556994 | IV13: =+IV24 -> 0.69655406 | IX13: Adjusted OR % | IY13: =+IY24 -> 0.73109244 | IZ13: =+IZ24 -> 0.68934911 | JA13: =+JA24 -> 0.6896679 | JB13: =+JB24 -> 0.6694106 | JC13: =+JC24 -> 0.69382961 | JE13: Adjusted OR % | JF13: =+JF24 -> 0.69362147 | JG13: =+JG24 -> 0.63450392 | JH13: =+JH24 -> 0.68319358 | JI13: =+JI24 -> 0.6514146 | JJ13: =+JJ24 -> 0.66532258 | JL13: Adjusted OR % | JM13: =+JM24 -> 0.63699583 | JN13: =+JN24 -> 0.58639587 | JO13: =+JO24 -> 0.58676894 | JP13: =+JP24 -> 0.60260897 | JQ13: =+JQ24 -> 0.60253061 | JS13: Adjusted OR % | JT13: =+JT24 -> 0.59541985 | JU13: =+JU24 -> 0.57366874 | JV13: =+JV24 -> 0.56783076 | JW13: =+JW24 -> 0.6 | JX13: =+JX24 -> 0.58406635 | JZ13: Adjusted OR % | KA13: =+KA24 -> 0.58739054 | KB13: =+KB24 -> 0.63281596 | KC13: =+KC24 -> 0.56910876 | KD13: =+KD24 -> 0.5699115 | KE13: =+KE24 -> 0.58782954 | KG13: Adjusted OR % | KH13: =+KH24 -> 0.60860292 | KI13: =+KI24 -> 0.55117057 | KJ13: =+KJ24 -> 0.56379101 | KK13: =+KK24 -> 0.60140064 | KL13: =+KL24 -> 0.5811372 | KN13: Adjusted OR % | KO13: =+KO24 -> 0.62437738 | KP13: =+KP24 -> 0.58558322 | KQ13: =+KQ24 -> 0.59460847 | KR13: =+KR24 -> 0.60884718 | KS13: =+KS24 -> 0.60270652 | KU13: Adjusted OR % | KV13: =+KV24 -> 0.60955208 | KW13: =+KW24 -> 0.60367667 | KX13: =+KX24 -> 0.64427693 | KY13: =+KY24 -> 0.64266304 | KZ13: =+KZ24 -> 0.6248209 | LB13: Adjusted OR % | LC13: =+LC24 -> 0.63678348 | LD13: =+LD24 -> 0.60875439 | LE13: =+LE24 -> 0.6258635 | LF13: =+LF24 -> 0.65696524 | LG13: =+LG24 -> 0.63184319 | LI13: Adjusted OR % | LJ13: =+LJ24 -> 0.69588081 | LK13: =+LK24 -> 0.64101847 | LL13: =+LL24 -> 0.64148313 | LM13: =+LM24 -> 0.66875713 | LN13: =+LN24 -> 0.66136815 | LP13: Adjusted OR % | LQ13: =+LQ24 -> 0.66217103 | LR13: =+LR24 -> 0.62419645 | LS13: =+LS24 -> 0.62015227 | LT13: =+LT24 -> 0.63843661 | LU13: =+LU24 -> 0.63585919 | LW13: Adjusted OR % | LX13: =+LX24 -> 0.64038082 | LY13: =+LY24 -> 0.60392023 | LZ13: =+LZ24 -> 0.59841679 | MA13: =+MA24 -> 0.61630596 | MB13: =+MB24 -> 0.61438473 | MD13: Adjusted OR % | ME13: =+ME24 -> 0.62865107 | MF13: =+MF24 -> 0.59593166 | MG13: =+MG24 -> 0.59295432 | MH13: =+MH24 -> 0.6062659 | MI13: =+MI24 -> 0.60562861
B14: Yr/ Yr change in bps | D14: =+(D13-C13)*10000 -> -355.33263 | E14: =+(E13-D13)*10000 -> -30.577452 | F14: =+(F13-E13)*10000 -> -109.18828 | G14: =+(G13-F13)*10000 -> 535.14007 | H14: =+(H13-G13)*10000 -> -133.47754 | I14: =+(I13-H13)*10000 -> -379.0528 | J14: =+(J13-I13)*10000 -> -37.380126 | K14: =+(K13-J13)*10000 -> 273.76411 | ... M14: =+(M13-L13)*10000 -> -53.428069 | N14: =BV14 -> 8877.9858 | O14: =CC14 -> 63.777208 | P14: =CJ14 -> 69.040232 | Q14: =CQ14 -> -115.78257 | R14: =CX14 -> -20.796629 | S14: =DE14 -> -156.48882 | T14: =DL14 -> -78.371867 | U14: =DS14 -> -74.917644 | V14: =DZ14 -> -54.001488 | W14: =EG14 -> 360.867 | X14: =EN14 -> 176.88043 | Y14: =EU14 -> -12.032795 | Z14: =FB14 -> -287.70017 | AA14: =FI14 -> -117.4479 | AB14: =FP14 -> 165.07748 | AC14: =FW14 -> -143.12878 | AD14: =GD14 -> -435.31039 | AE14: =GK14 -> -438.0129 | AF14: =GR14 -> -32.876491 | AG14: =GY14 -> -204.33413 | AH14: =HF14 -> -59.846228 | AI14: =HM14 -> -398.14912 | AJ14: =HT14 -> 4.8995766 | AK14: =IA14 -> -29.955877 | AL14: =IH14 -> 33.842185 | AM14: =IO14 -> 54.940796 | AN14: =IV14 -> -182.61632 | AO14: =JC14 -> -27.244455 | AP14: =JJ14 -> -285.07034 | AQ14: =JQ14 -> -627.91968 | AR14: =JX14 -> -184.64264 | AS14: =KE14 -> 37.631896 | AT14: =KL14 -> -66.923394 | AU14: =KS14 -> 215.69325 | AV14: =KZ14 -> 221.14381 | AW14: =LG14 -> 70.222865 | AX14: =LN14 -> 295.24961 | AY14: =LU14 -> -255.08959 | AZ14: =MB14 -> -214.74466 | BA14: =MI14 -> -87.561209 | BQ14: Yr/ Yr change in bps | BR14: =+(BR13-AV13)*10000 -> 2733.2423 | BS14: =+(BS13-AW13)*10000 -> 2516.4212 | BT14: =+(BT13-AX13)*10000 -> 2457.0565 | BU14: =+(BU13-AY13)*10000 -> 2288.117 | BV14: =+(BV13-BP13)*10000 -> 8877.9858 | BX14: Yr/ Yr change in bps | BY14: =+(BY13-BR13)*10000 -> 139.47961 | BZ14: =+(BZ13-BS13)*10000 -> 85.953984 | CA14: =+(CA13-BT13)*10000 -> -214.70312 | CB14: =+(CB13-BU13)*10000 -> 239.26671 | CC14: =+(CC13-BV13)*10000 -> 63.777208 | CE14: Yr/ Yr change in bps | CF14: =+(CF13-BY13)*10000 -> 163.41125 | CG14: =+(CG13-BZ13)*10000 -> 109.78116 | CH14: =+(CH13-CA13)*10000 -> 51.398543 | CI14: =+(CI13-CB13)*10000 -> -37.506782 | CJ14: =+(CJ13-CC13)*10000 -> 69.040232 | CL14: Yr/ Yr change in bps | CM14: =+(CM13-CF13)*10000 -> -38.751725 | CN14: =+(CN13-CG13)*10000 -> -187.70367 | CO14: =+(CO13-CH13)*10000 -> -92.006446 | CP14: =+(CP13-CI13)*10000 -> -149.91195 | CQ14: =+(CQ13-CJ13)*10000 -> -115.78257 | CS14: Yr/ Yr change in bps | CT14: =+(CT13-CM13)*10000 -> 18.291203 | CU14: =+(CU13-CN13)*10000 -> -68.862031 | CV14: =+(CV13-CO13)*10000 -> 55.792907 | CW14: =+(CW13-CP13)*10000 -> -80.846338 | CX14: =+(CX13-CQ13)*10000 -> -20.796629 | CZ14: Yr/ Yr change in bps | DA14: =+(DA13-CT13)*10000 -> -99.086004 | DB14: =+(DB13-CU13)*10000 -> -56.181958 | DC14: =+(DC13-CV13)*10000 -> -288.22395 | DD14: =+(DD13-CW13)*10000 -> -161.01767 | DE14: =+(DE13-CX13)*10000 -> -156.48882 | DG14: Yr/ Yr change in bps | DH14: =+(DH13-DA13)*10000 -> -294.09192 | DI14: =+(DI13-DB13)*10000 -> -87.004952 | DJ14: =+(DJ13-DC13)*10000 -> -43.972499 | DK14: =+(DK13-DD13)*10000 -> 78.362437 | DL14: =+(DL13-DE13)*10000 -> -78.371867 | DN14: Yr/ Yr change in bps | DO14: =+(DO13-DH13)*10000 -> -48.110288 | DP14: =+(DP13-DI13)*10000 -> -122.22784 | DQ14: =+(DQ13-DJ13)*10000 -> -19.945251 | DR14: =+(DR13-DK13)*10000 -> -111.08199 | DS14: =+(DS13-DL13)*10000 -> -74.917644 | DU14: Yr/ Yr change in bps | DV14: =+(DV13-DO13)*10000 -> -84.76722 | DW14: =+(DW13-DP13)*10000 -> -125.48605 | DX14: =+(DX13-DQ13)*10000 -> 52.857855 | DY14: =+(DY13-DR13)*10000 -> -56.767025 | DZ14: =+(DZ13-DS13)*10000 -> -54.001488 | EB14: Yr/ Yr change in bps | EC14: =+(EC13-DV13)*10000 -> 205.66269 | ED14: =+(ED13-DW13)*10000 -> 267.48068 | EE14: =+(EE13-DX13)*10000 -> 427.65225 | EF14: =+(EF13-DY13)*10000 -> 528.79366 | EG14: =+(EG13-DZ13)*10000 -> 360.867 | EI14: Yr/ Yr change in bps | EJ14: =+(EJ13-EC13)*10000 -> 29.356393 | EK14: =+(EK13-ED13)*10000 -> 301.99698 | EL14: =+(EL13-EE13)*10000 -> -86.993676 | EM14: =+(EM13-EF13)*10000 -> 456.25619 | EN14: =+(EN13-EG13)*10000 -> 176.88043 | EP14: Yr/ Yr change in bps | EQ14: =+(EQ13-EJ13)*10000 -> 230.69449 | ER14: =+(ER13-EK13)*10000 -> 139.1354 | ES14: =+(ES13-EL13)*10000 -> -11.172366 | ET14: =+(ET13-EM13)*10000 -> -417.22932 | EU14: =+(EU13-EN13)*10000 -> -12.032795 | EW14: Yr/ Yr change in bps | EX14: =+(EX13-EQ13)*10000 -> -136.87316 | EY14: =+(EY13-ER13)*10000 -> -380.0187 | EZ14: =+(EZ13-ES13)*10000 -> -288.24743 | FA14: =+(FA13-ET13)*10000 -> -333.73269 | FB14: =+(FB13-EU13)*10000 -> -287.70017 | FD14: Yr/ Yr change in bps | FE14: =+(FE13-EX13)*10000 -> -146.0964 | FF14: =+(FF13-EY13)*10000 -> -207.13336 | FG14: =+(FG13-EZ13)*10000 -> 43.759468 | FH14: =+(FH13-FA13)*10000 -> -144.9835 | FI14: =+(FI13-FB13)*10000 -> -117.4479 | FK14: Yr/ Yr change in bps | FL14: =+(FL13-FE13)*10000 -> 252.89912 | FM14: =+(FM13-FF13)*10000 -> 75.925744 | FN14: =+(FN13-FG13)*10000 -> 70.438156 | FO14: =+(FO13-FH13)*10000 -> 230.39818 | FP14: =+(FP13-FI13)*10000 -> 165.07748 | FR14: Yr/ Yr change in bps | FS14: =+(FS13-FL13)*10000 -> -241.17772 | FT14: =+(FT13-FM13)*10000 -> -84.267873 | FU14: =+(FU13-FN13)*10000 -> -63.801772 | FV14: =+(FV13-FO13)*10000 -> -146.19321 | FW14: =+(FW13-FP13)*10000 -> -143.12878 | FY14: Yr/ Yr change in bps | FZ14: =+(FZ13-FS13)*10000 -> -611.60855 | GA14: =+(GA13-FT13)*10000 -> -422.71803 | GB14: =+(GB13-FU13)*10000 -> -324.74716 | GC14: =+(GC13-FV13)*10000 -> -397.20786 | GD14: =+(GD13-FW13)*10000 -> -435.31039 | GF14: Yr/ Yr change in bps | GG14: =+(GG13-FZ13)*10000 -> -409.9152 | GH14: =+(GH13-GA13)*10000 -> -737.71092 | GI14: =+(GI13-GB13)*10000 -> -361.15604 | GJ14: =+(GJ13-GC13)*10000 -> -242.64002 | GK14: =+(GK13-GD13)*10000 -> -438.0129 | GM14: Yr/ Yr change in bps | GN14: =+(GN13-GG13)*10000 -> 86.754798 | GO14: =+(GO13-GH13)*10000 -> 245.21602 | GP14: =+(GP13-GI13)*10000 -> -208.77505 | GQ14: =+(GQ13-GJ13)*10000 -> -248.35889 | GR14: =+(GR13-GK13)*10000 -> -32.876491 | GT14: Yr/ Yr change in bps | GU14: =+(GU13-GN13)*10000 -> -297.55957 | GV14: =+(GV13-GO13)*10000 -> -47.487936 | GW14: =+(GW13-GP13)*10000 -> -244.40747 | GX14: =+(GX13-GQ13)*10000 -> -240.19221 | GY14: =+(GY13-GR13)*10000 -> -204.33413 | HA14: Yr/ Yr change in bps | HB14: =+(HB13-GU13)*10000 -> -23.060604 | HC14: =+(HC13-GV13)*10000 -> -174.272 | HD14: =+(HD13-GW13)*10000 -> -119.50463 | HE14: =+(HE13-GX13)*10000 -> 74.952286 | HF14: =+(HF13-GY13)*10000 -> -59.846228 | HH14: Yr/ Yr change in bps | HI14: =+(HI13-HB13)*10000 -> -214.03622 | HJ14: =+(HJ13-HC13)*10000 -> -355.88809 | HK14: =+(HK13-HD13)*10000 -> -499.50397 | HL14: =+(HL13-HE13)*10000 -> -491.33033 | HM14: =+(HM13-HF13)*10000 -> -398.14912 | HO14: Yr/ Yr change in bps | HP14: =+(HP13-HI13)*10000 -> -213.756 | HQ14: =+(HQ13-HJ13)*10000 -> -70.620455 | HR14: =+(HR13-HK13)*10000 -> 131.31067 | HS14: =+(HS13-HL13)*10000 -> 154.37997 | HT14: =+(HT13-HM13)*10000 -> 4.8995766 | HV14: Yr/ Yr change in bps | HW14: =+(HW13-HP13)*10000 -> -135.15213 | HX14: =+(HX13-HQ13)*10000 -> -63.569285 | HY14: =+(HY13-HR13)*10000 -> 12.279995 | HZ14: =+(HZ13-HS13)*10000 -> 62.086667 | IA14: =+(IA13-HT13)*10000 -> -29.955877 | IC14: Yr/ Yr change in bps | ID14: =+(ID13-HW13)*10000 -> -72.037976 | IE14: =+(IE13-HX13)*10000 -> -7.0198191 | IF14: =+(IF13-HY13)*10000 -> 103.31709 | IG14: =+(IG13-HZ13)*10000 -> 106.39631 | IH14: =+(IH13-IA13)*10000 -> 33.842185 | IJ14: Yr/ Yr change in bps | IK14: =+(IK13-ID13)*10000 -> 504.56053 | IL14: =+(IL13-IE13)*10000 -> 64.463697 | IM14: =+(IM13-IF13)*10000 -> -182.499 | IN14: =+(IN13-IG13)*10000 -> -141.28329 | IO14: =+(IO13-IH13)*10000 -> 54.940796 | IQ14: Yr/ Yr change in bps | IR14: =+(IR13-IK13)*10000 -> -331.41632 | IS14: =+(IS13-IL13)*10000 -> -245.82439 | IT14: =+(IT13-IM13)*10000 -> -144.4343 | IU14: =+(IU13-IN13)*10000 -> -21.618907 | IV14: =+(IV13-IO13)*10000 -> -182.61632 | IX14: Yr/ Yr change in bps | IY14: =+(IY13-IR13)*10000 -> 95.85995 | IZ14: =+(IZ13-IS13)*10000 -> 212.68172 | JA14: =+(JA13-IT13)*10000 -> 71.228133 | JB14: =+(JB13-IU13)*10000 -> -461.59336 | JC14: =+(JC13-IV13)*10000 -> -27.244455 | JE14: Yr/ Yr change in bps | JF14: =+(JF13-IY13)*10000 -> -374.70966 | JG14: =+(JG13-IZ13)*10000 -> -548.45192 | JH14: =+(JH13-JA13)*10000 -> -64.74313 | JI14: =+(JI13-JB13)*10000 -> -179.96002 | JJ14: =+(JJ13-JC13)*10000 -> -285.07034 | JL14: Yr/ Yr change in bps | JM14: =+(JM13-JF13)*10000 -> -566.25643 | JN14: =+(JN13-JG13)*10000 -> -481.08047 | JO14: =+(JO13-JH13)*10000 -> -964.24648 | JP14: =+(JP13-JI13)*10000 -> -488.05628 | JQ14: =+(JQ13-JJ13)*10000 -> -627.91968 | JS14: Yr/ Yr change in bps | JT14: =+(JT13-JM13)*10000 -> -415.7598 | JU14: =+(JU13-JN13)*10000 -> -127.27138 | JV14: =+(JV13-JO13)*10000 -> -189.38177 | JW14: =+(JW13-JP13)*10000 -> -26.089723 | JX14: =+(JX13-JQ13)*10000 -> -184.64264 | JZ14: Yr/ Yr change in bps | KA14: =+(KA13-JT13)*10000 -> -80.293044 | KB14: =+(KB13-JU13)*10000 -> 591.47229 | KC14: =+(KC13-JV13)*10000 -> 12.780024 | KD14: =+(KD13-JW13)*10000 -> -300.88496 | KE14: =+(KE13-JX13)*10000 -> 37.631896 | KG14: Yr/ Yr change in bps | KH14: =+(KH13-KA13)*10000 -> 212.12372 | KI14: =+(KI13-KB13)*10000 -> -816.45396 | KJ14: =+(KJ13-KC13)*10000 -> -53.177528 | KK14: =+(KK13-KD13)*10000 -> 314.89138 | KL14: =+(KL13-KE13)*10000 -> -66.923394 | KN14: Yr/ Yr change in bps | KO14: =+(KO13-KH13)*10000 -> 157.74466 | KP14: =+(KP13-KI13)*10000 -> 344.12656 | KQ14: =+(KQ13-KJ13)*10000 -> 308.17464 | KR14: =+(KR13-KK13)*10000 -> 74.46543 | KS14: =+(KS13-KL13)*10000 -> 215.69325 | KU14: Yr/ Yr change in bps | KV14: =+(KV13-KO13)*10000 -> -148.25303 | KW14: =+(KW13-KP13)*10000 -> 180.93445 | KX14: =+(KX13-KQ13)*10000 -> 496.68459 | KY14: =+(KY13-KR13)*10000 -> 338.15858 | KZ14: =+(KZ13-KS13)*10000 -> 221.14381 | LB14: Yr/ Yr change in bps | LC14: =+(LC13-KV13)*10000 -> 272.31405 | LD14: =+(LD13-KW13)*10000 -> 50.777213 | LE14: =+(LE13-KX13)*10000 -> -184.13433 | LF14: =+(LF13-KY13)*10000 -> 143.02201 | LG14: =+(LG13-KZ13)*10000 -> 70.222865 | LI14: Yr/ Yr change in bps | LJ14: =+(LJ13-LC13)*10000 -> 590.97324 | LK14: =+(LK13-LD13)*10000 -> 322.64076 | LL14: =+(LL13-LE13)*10000 -> 156.19635 | LM14: =+(LM13-LF13)*10000 -> 117.91882 | LN14: =+(LN13-LG13)*10000 -> 295.24961 | LP14: Yr/ Yr change in bps | LQ14: =+(LQ13-LJ13)*10000 -> -337.0978 | LR14: =+(LR13-LK13)*10000 -> -168.22016 | LS14: =+(LS13-LL13)*10000 -> -213.3086 | LT14: =+(LT13-LM13)*10000 -> -303.20512 | LU14: =+(LU13-LN13)*10000 -> -255.08959 | LW14: Yr/ Yr change in bps | LX14: =+(LX13-LQ13)*10000 -> -217.9021 | LY14: =+(LY13-LR13)*10000 -> -202.76219 | LZ14: =+(LZ13-LS13)*10000 -> -217.35481 | MA14: =+(MA13-LT13)*10000 -> -221.30658 | MB14: =+(MB13-LU13)*10000 -> -214.74466 | MD14: Yr/ Yr change in bps | ME14: =+(ME13-LX13)*10000 -> -117.29741 | MF14: =+(MF13-LY13)*10000 -> -79.885695 | MG14: =+(MG13-LZ13)*10000 -> -54.624684 | MH14: =+(MH13-MA13)*10000 -> -100.40059 | MI14: =+(MI13-MB13)*10000 -> -87.561209
B17: CSX Income Statement | C17: =D17-1 -> 1978 | D17: =E17-1 -> 1979 | E17: =F17-1 -> 1980 | F17: =G17-1 -> 1981 | G17: =H17-1 -> 1982 | H17: =I17-1 -> 1983 | I17: =J17-1 -> 1984 | J17: =K17-1 -> 1985 | ... M17: =N17-1 -> 1988 | N17: =BV17 -> 1989 | O17: =CC17 -> 1990 | P17: =CJ17 -> 1991 | Q17: =CQ17 -> 1992 | R17: =CX17 -> 1993 | S17: =DE17 -> 1994 | T17: =DL17 -> 1995 | U17: =DS17 -> 1996 | V17: =DZ17 -> 1997 | W17: =EG17 -> 1998 | X17: =EN17 -> 1999 | Y17: =EU17 -> 2000 | Z17: =FB17 -> 2001 | AA17: =FI17 -> 2002 | AB17: =FP17 -> 2003 | AC17: =FW17 -> 2004 | AD17: =GD17 -> 2005 | AE17: =GK17 -> 2006 | AF17: =GR17 -> 2007 | AG17: =GY17 -> 2008 | AH17: =HF17 -> 2009 | AI17: =HM17 -> 2010 | AJ17: =HT17 -> 2011 | AK17: =IA17 -> 2012 | AL17: =IH17 -> 2013 | AM17: =IO17 -> 2014 | AN17: =IV17 -> 2015 | AO17: =JC17 -> 2016 | AP17: =JJ17 -> 2017 | AQ17: =JQ17 -> 2018 | AR17: =JX17 -> 2019 | AS17: =KE17 -> 2020 | AT17: =KL17 -> 2021 | AU17: =KS17 -> 2022 | AV17: =KZ17 -> 2023 | AW17: =LG17 -> 2024 | AX17: =LN17 -> 2025 | AY17: =LU17 -> 2026E | AZ17: =MB17 -> 2027E | BA17: =MI17 -> 2028E | BQ17: =$B17 -> CSX Income Statement | BR17: =BR4 -> 1Q89 | BS17: =BS4 -> 2Q89 | BT17: =BT4 -> 3Q89 | BU17: =BU4 -> 4Q89 | BV17: =BV4 -> 1989 | BX17: =$B17 -> CSX Income Statement | BY17: =BY4 -> 1Q90 | BZ17: =BZ4 -> 2Q90 | CA17: =CA4 -> 3Q90 | CB17: =CB4 -> 4Q90 | CC17: =CC4 -> 1990 | CE17: =$B17 -> CSX Income Statement | CF17: =CF4 -> 1Q91 | CG17: =CG4 -> 2Q91 | CH17: =CH4 -> 3Q91 | CI17: =CI4 -> 4Q91 | CJ17: =CJ4 -> 1991 | CL17: =$B17 -> CSX Income Statement | CM17: =CM4 -> 1Q92 | CN17: =CN4 -> 2Q92 | CO17: =CO4 -> 3Q92 | CP17: =CP4 -> 4Q92 | CQ17: =CQ4 -> 1992 | CS17: =$B17 -> CSX Income Statement | CT17: =CT4 -> 1Q93 | CU17: =CU4 -> 2Q93 | CV17: =CV4 -> 3Q93 | CW17: =CW4 -> 4Q93 | CX17: =CX4 -> 1993 | CZ17: =$B17 -> CSX Income Statement | DA17: =DA4 -> 1Q94 | DB17: =DB4 -> 2Q94 | DC17: =DC4 -> 3Q94 | DD17: =DD4 -> 4Q94 | DE17: =DE4 -> 1994 | DG17: =$B17 -> CSX Income Statement | DH17: =DH4 -> 1Q95 | DI17: =DI4 -> 2Q95 | DJ17: =DJ4 -> 3Q95 | DK17: =DK4 -> 4Q95 | DL17: =DL4 -> 1995 | DN17: =$B17 -> CSX Income Statement | DO17: =DO4 -> 1Q96 | DP17: =DP4 -> 2Q96 | DQ17: =DQ4 -> 3Q96 | DR17: =DR4 -> 4Q96 | DS17: =DS4 -> 1996 | DU17: =$B17 -> CSX Income Statement | DV17: =DV4 -> 1Q97 | DW17: =DW4 -> 2Q97 | DX17: =DX4 -> 3Q97 | DY17: =DY4 -> 4Q97 | DZ17: =DZ4 -> 1997 | EB17: =$B17 -> CSX Income Statement | EC17: =EC4 -> 1Q98 | ED17: =ED4 -> 2Q98 | EE17: =EE4 -> 3Q98 | EF17: =EF4 -> 4Q98 | EG17: =EG4 -> 1998 | EI17: =$B17 -> CSX Income Statement | EJ17: =EJ4 -> 1Q99 | EK17: =EK4 -> 2Q99 | EL17: =EL4 -> 3Q99 | EM17: =EM4 -> 4Q99 | EN17: =EN4 -> 1999 | EP17: =$B17 -> CSX Income Statement | EQ17: =EQ4 -> 1Q00 | ER17: =ER4 -> 2Q00 | ES17: =ES4 -> 3Q00 | ET17: =ET4 -> 4Q00 | EU17: =EU4 -> 2000 | EW17: =$B17 -> CSX Income Statement | EX17: =EX4 -> 1Q01 | EY17: =EY4 -> 2Q01 | EZ17: =EZ4 -> 3Q01 | FA17: =FA4 -> 4Q01 | FB17: =FB4 -> 2001 | FD17: =$B17 -> CSX Income Statement | FE17: =FE4 -> 1Q02 | FF17: =FF4 -> 2Q02 | FG17: =FG4 -> 3Q02 | FH17: =FH4 -> 4Q02 | FI17: =FI4 -> 2002 | FK17: =$B17 -> CSX Income Statement | FL17: =FL4 -> 1Q03 | FM17: =FM4 -> 2Q03 | FN17: =FN4 -> 3Q03 | FO17: =FO4 -> 4Q03 | FP17: =FP4 -> 2003 | FR17: =$B17 -> CSX Income Statement | FS17: =FS4 -> 1Q04 | FT17: =FT4 -> 2Q04 | FU17: =FU4 -> 3Q04 | FV17: =FV4 -> 4Q04 | FW17: =FW4 -> 2004 | FY17: =$B17 -> CSX Income Statement | FZ17: =FZ4 -> 1Q05 | GA17: =GA4 -> 2Q05 | GB17: =GB4 -> 3Q05 | GC17: =GC4 -> 4Q05 | GD17: =GD4 -> 2005 | GF17: =$B17 -> CSX Income Statement | GG17: =GG4 -> 1Q06 | GH17: =GH4 -> 2Q06 | GI17: =GI4 -> 3Q06 | GJ17: =GJ4 -> 4Q06 | GK17: =GK4 -> 2006 | GM17: =$B17 -> CSX Income Statement | GN17: =GN4 -> 1Q07 | GO17: =GO4 -> 2Q07 | GP17: =GP4 -> 3Q07 | GQ17: =GQ4 -> 4Q07 | GR17: =GR4 -> 2007 | GT17: =$B17 -> CSX Income Statement | GU17: =GU4 -> 1Q08 | GV17: =GV4 -> 2Q08 | GW17: =GW4 -> 3Q08 | GX17: =GX4 -> 4Q08 | GY17: =GY4 -> 2008 | HA17: =$B17 -> CSX Income Statement | HB17: =HB4 -> 1Q09 | HC17: =HC4 -> 2Q09 | HD17: =HD4 -> 3Q09 | HE17: =HE4 -> 4Q09 | HF17: =HF4 -> 2009 | HH17: =$B17 -> CSX Income Statement | HI17: =HI4 -> 1Q10 | HJ17: =HJ4 -> 2Q10 | HK17: =HK4 -> 3Q10 | HL17: =HL4 -> 4Q10 | HM17: =HM4 -> 2010 | HO17: =$B17 -> CSX Income Statement | HP17: =HP4 -> 1Q11 | HQ17: =HQ4 -> 2Q11 | HR17: =HR4 -> 3Q11 | HS17: =HS4 -> 4Q11 | HT17: =HT4 -> 2011 | HV17: =$B17 -> CSX Income Statement | HW17: =HW4 -> 1Q12 | HX17: =HX4 -> 2Q12 | HY17: =HY4 -> 3Q12 | HZ17: =HZ4 -> 4Q12 | IA17: =IA4 -> 2012 | IC17: =$B17 -> CSX Income Statement | ID17: =ID4 -> 1Q13 | IE17: =IE4 -> 2Q13 | IF17: =IF4 -> 3Q13 | IG17: =IG4 -> 4Q13 | IH17: =IH4 -> 2013 | IJ17: =$B17 -> CSX Income Statement | IK17: =IK4 -> 1Q14 | IL17: =IL4 -> 2Q14 | IM17: =IM4 -> 3Q14 | IN17: =IN4 -> 4Q14 | IO17: =IO4 -> 2014 | IQ17: =$B17 -> CSX Income Statement | IR17: =IR4 -> 1Q15 | IS17: =IS4 -> 2Q15 | IT17: =IT4 -> 3Q15 | IU17: =IU4 -> 4Q15 | IV17: =IV4 -> 2015 | IX17: =$B17 -> CSX Income Statement | IY17: =IY4 -> 1Q16 | IZ17: =IZ4 -> 2Q16 | JA17: =JA4 -> 3Q16 | JB17: =JB4 -> 4Q16 | JC17: =JC4 -> 2016 | JE17: =$B17 -> CSX Income Statement | JF17: =JF4 -> 1Q17 | JG17: =JG4 -> 2Q17 | JH17: =JH4 -> 3Q17 | JI17: =JI4 -> 4Q17 | JJ17: =JJ4 -> 2017 | JL17: =$B17 -> CSX Income Statement | JM17: =JM4 -> 1Q18 | JN17: =JN4 -> 2Q18 | JO17: =JO4 -> 3Q18 | JP17: =JP4 -> 4Q18 | JQ17: =JQ4 -> 2018 | JS17: =$B17 -> CSX Income Statement | JT17: =JT4 -> 1Q19 | JU17: =JU4 -> 2Q19 | JV17: =JV4 -> 3Q19 | JW17: =JW4 -> 4Q19 | JX17: =JX4 -> 2019 | JZ17: =$B17 -> CSX Income Statement | KA17: =KA4 -> 1Q20 | KB17: =KB4 -> 2Q20 | KC17: =KC4 -> 3Q20 | KD17: =KD4 -> 4Q20 | KE17: =KE4 -> 2020 | KG17: =$B17 -> CSX Income Statement | KH17: =KH4 -> 1Q21 | KI17: =KI4 -> 2Q21 | KJ17: =KJ4 -> 3Q21 | KK17: =KK4 -> 4Q21 | KL17: =KL4 -> 2021 | KN17: =$B17 -> CSX Income Statement | KO17: =KO4 -> 1Q22 | KP17: =KP4 -> 2Q22 | KQ17: =KQ4 -> 3Q22 | KR17: =KR4 -> 4Q22 | KS17: =KS4 -> 2022 | KU17: =$B17 -> CSX Income Statement | KV17: =KV4 -> 1Q23 | KW17: =KW4 -> 2Q23 | KX17: =KX4 -> 3Q23 | KY17: =KY4 -> 4Q23 | KZ17: =KZ4 -> 2023 | LB17: =$B17 -> CSX Income Statement | LC17: =LC4 -> 1Q24 | LD17: =LD4 -> 2Q24 | LE17: =LE4 -> 3Q24 | LF17: =LF4 -> 4Q24 | LG17: =LG4 -> 2024 | LI17: =$B17 -> CSX Income Statement | LJ17: =LJ4 -> 1Q25 | LK17: =LK4 -> 2Q25 | LL17: =LL4 -> 3Q25 | LM17: =LM4 -> 4Q25 | LN17: =LN4 -> 2025 | LP17: =$B17 -> CSX Income Statement | LQ17: =LQ4 -> 1Q26E | LR17: =LR4 -> 2Q26E | LS17: =LS4 -> 3Q26E | LT17: =LT4 -> 4Q26E | LU17: =LU4 -> 2026E | LW17: =$B17 -> CSX Income Statement | LX17: =LX4 -> 1Q27E | LY17: =LY4 -> 2Q27E | LZ17: =LZ4 -> 3Q27E | MA17: =MA4 -> 4Q27E | MB17: =MB4 -> 2027E | MD17: =$B17 -> CSX Income Statement | ME17: =ME4 -> 1Q28E | MF17: =MF4 -> 2Q28E | MG17: =MG4 -> 3Q28E | MH17: =MH4 -> 4Q28E | MI17: =MI4 -> 2028E
B18: ($ in millions except per share amounts) | C18: =D18 -> FY | D18: =E18 -> FY | E18: =F18 -> FY | F18: =G18 -> FY | G18: =H18 -> FY | H18: =I18 -> FY | I18: =J18 -> FY | J18: =K18 -> FY | ... M18: =N18 -> FY | N18: =BV18 -> FY | O18: =CC18 -> FY | P18: =CJ18 -> FY | Q18: =CQ18 -> FY | R18: =CX18 -> FY | S18: =DE18 -> FY | T18: =DL18 -> FY | U18: =DS18 -> FY | V18: =DZ18 -> FY | W18: =EG18 -> FY | X18: =EN18 -> FY | Y18: =EU18 -> FY | Z18: =FB18 -> FY | AA18: =FI18 -> FY | AB18: =FP18 -> FY | AC18: =FW18 -> FY | AD18: =GD18 -> FY | AE18: =GK18 -> FY | AF18: =GR18 -> FY | AG18: =GY18 -> FY | AH18: =HF18 -> FY | AI18: =HM18 -> FY | AJ18: =HT18 -> FY | AK18: =IA18 -> FY | AL18: =IH18 -> FY | AM18: =IO18 -> FY | AN18: =IV18 -> FY | AO18: =JC18 -> FY | AP18: =JJ18 -> FY | AQ18: =JQ18 -> FY | AR18: =JX18 -> FY | AS18: =KE18 -> FY | AT18: =KL18 -> FY | AU18: =KS18 -> FY | AV18: =KZ18 -> FY | AW18: =LG18 -> FY | AX18: =LN18 -> FY | AY18: =LU18 -> FY | AZ18: =MB18 -> FY | BA18: =MI18 -> FY | BQ18: =$B18 -> ($ in millions except per share amounts) | BR18: =BR5 -> 32598 | BS18: =BS5 -> 32689 | BT18: =BT5 -> 32781 | BU18: =BU5 -> 32873 | BV18: =BV5 -> FY | BX18: =$B18 -> ($ in millions except per share amounts) | BY18: =BY5 -> 32963 | BZ18: =BZ5 -> 33054 | CA18: =CA5 -> 33146 | CB18: =CB5 -> 33238 | CC18: =CC5 -> FY | CE18: =$B18 -> ($ in millions except per share amounts) | CF18: =CF5 -> 33328 | CG18: =CG5 -> 33419 | CH18: =CH5 -> 33511 | CI18: =CI5 -> 33603 | CJ18: =CJ5 -> FY | CL18: =$B18 -> ($ in millions except per share amounts) | CM18: =CM5 -> 33694 | CN18: =CN5 -> 33785 | CO18: =CO5 -> 33877 | CP18: =CP5 -> 33969 | CQ18: =CQ5 -> FY | CS18: =$B18 -> ($ in millions except per share amounts) | CT18: =CT5 -> 34059 | CU18: =CU5 -> 34150 | CV18: =CV5 -> 34242 | CW18: =CW5 -> 34334 | CX18: =CX5 -> FY | CZ18: =$B18 -> ($ in millions except per share amounts) | DA18: =DA5 -> 34424 | DB18: =DB5 -> 34515 | DC18: =DC5 -> 34607 | DD18: =DD5 -> 34699 | DE18: =DE5 -> FY | DG18: =$B18 -> ($ in millions except per share amounts) | DH18: =DH5 -> 34789 | DI18: =DI5 -> 34880 | DJ18: =DJ5 -> 34972 | DK18: =DK5 -> 35064 | DL18: =DL5 -> FY | DN18: =$B18 -> ($ in millions except per share amounts) | DO18: =DO5 -> 35155 | DP18: =DP5 -> 35246 | DQ18: =DQ5 -> 35338 | DR18: =DR5 -> 35430 | DS18: =DS5 -> FY | DU18: =$B18 -> ($ in millions except per share amounts) | DV18: =DV5 -> 35520 | DW18: =DW5 -> 35611 | DX18: =DX5 -> 35703 | DY18: =DY5 -> 35795 | DZ18: =DZ5 -> FY | EB18: =$B18 -> ($ in millions except per share amounts) | EC18: =EC5 -> 35885 | ED18: =ED5 -> 35976 | EE18: =EE5 -> 36068 | EF18: =EF5 -> 36160 | EG18: =EG5 -> FY | EI18: =$B18 -> ($ in millions except per share amounts) | EJ18: =EJ5 -> 36250 | EK18: =EK5 -> 36341 | EL18: =EL5 -> 36433 | EM18: =EM5 -> 36525 | EN18: =EN5 -> FY | EP18: =$B18 -> ($ in millions except per share amounts) | EQ18: =EQ5 -> 36616 | ER18: =ER5 -> 36707 | ES18: =ES5 -> 36799 | ET18: =ET5 -> 36891 | EU18: =EU5 -> FY | EW18: =$B18 -> ($ in millions except per share amounts) | EX18: =EX5 -> 36981 | EY18: =EY5 -> 37072 | EZ18: =EZ5 -> 37164 | FA18: =FA5 -> 37256 | FB18: =FB5 -> FY | FD18: =$B18 -> ($ in millions except per share amounts) | FE18: =FE5 -> 37346 | FF18: =FF5 -> 37437 | FG18: =FG5 -> 37529 | FH18: =FH5 -> 37621 | FI18: =FI5 -> FY | FK18: =$B18 -> ($ in millions except per share amounts) | FL18: =FL5 -> 37711 | FM18: =FM5 -> 37802 | FN18: =FN5 -> 37894 | FO18: =FO5 -> 37986 | FP18: =FP5 -> FY | FR18: =$B18 -> ($ in millions except per share amounts) | FS18: =FS5 -> 38077 | FT18: =FT5 -> 38168 | FU18: =FU5 -> 38260 | FV18: =FV5 -> 38352 | FW18: =FW5 -> FY | FY18: =$B18 -> ($ in millions except per share amounts) | FZ18: =FZ5 -> 38442 | GA18: =GA5 -> 38533 | GB18: =GB5 -> 38625 | GC18: =GC5 -> 38717 | GD18: =GD5 -> FY | GF18: =$B18 -> ($ in millions except per share amounts) | GG18: =GG5 -> 38807 | GH18: =GH5 -> 38898 | GI18: =GI5 -> 38990 | GJ18: =GJ5 -> 39082 | GK18: =GK5 -> FY | GM18: =$B18 -> ($ in millions except per share amounts) | GN18: =GN5 -> 39172 | GO18: =GO5 -> 39263 | GP18: =GP5 -> 39355 | GQ18: =GQ5 -> 39447 | GR18: =GR5 -> FY | GT18: =$B18 -> ($ in millions except per share amounts) | GU18: =GU5 -> 39538 | GV18: =GV5 -> 39629 | GW18: =GW5 -> 39721 | GX18: =GX5 -> 39813 | GY18: =GY5 -> FY | HA18: =$B18 -> ($ in millions except per share amounts) | HB18: =HB5 -> 39903 | HC18: =HC5 -> 39994 | HD18: =HD5 -> 40086 | HE18: =HE5 -> 40178 | HF18: =HF5 -> FY | HH18: =$B18 -> ($ in millions except per share amounts) | HI18: =HI5 -> 40268 | HJ18: =HJ5 -> 40359 | HK18: =HK5 -> 40451 | HL18: =HL5 -> 40543 | HM18: =HM5 -> FY | HO18: =$B18 -> ($ in millions except per share amounts) | HP18: =HP5 -> 40633 | HQ18: =HQ5 -> 40724 | HR18: =HR5 -> 40816 | HS18: =HS5 -> 40908 | HT18: =HT5 -> FY | HV18: =$B18 -> ($ in millions except per share amounts) | HW18: =HW5 -> 40999 | HX18: =HX5 -> 41090 | HY18: =HY5 -> 41182 | HZ18: =HZ5 -> 41274 | IA18: =IA5 -> FY | IC18: =$B18 -> ($ in millions except per share amounts) | ID18: =ID5 -> 41364 | IE18: =IE5 -> 41455 | IF18: =IF5 -> 41547 | IG18: =IG5 -> 41639 | IH18: =IH5 -> FY | IJ18: =$B18 -> ($ in millions except per share amounts) | IK18: =IK5 -> 41729 | IL18: =IL5 -> 41820 | IM18: =IM5 -> 41912 | IN18: =IN5 -> 42004 | IO18: =IO5 -> FY | IQ18: =$B18 -> ($ in millions except per share amounts) | IR18: =IR5 -> 42094 | IS18: =IS5 -> 42185 | IT18: =IT5 -> 42277 | IU18: =IU5 -> 42369 | IV18: =IV5 -> FY | IX18: =$B18 -> ($ in millions except per share amounts) | IY18: =IY5 -> 42460 | IZ18: =IZ5 -> 42551 | JA18: =JA5 -> 42643 | JB18: =JB5 -> 42735 | JC18: =JC5 -> FY | JE18: =$B18 -> ($ in millions except per share amounts) | JF18: =JF5 -> 42825 | JG18: =JG5 -> 42916 | JH18: =JH5 -> 43008 | JI18: =JI5 -> 43100 | JJ18: =JJ5 -> FY | JL18: =$B18 -> ($ in millions except per share amounts) | JM18: =JM5 -> 43190 | JN18: =JN5 -> 43281 | JO18: =JO5 -> 43373 | JP18: =JP5 -> 43465 | JQ18: =JQ5 -> FY | JS18: =$B18 -> ($ in millions except per share amounts) | JT18: =JT5 -> 43555 | JU18: =JU5 -> 43646 | JV18: =JV5 -> 43738 | JW18: =JW5 -> 43830 | JX18: =JX5 -> FY | JZ18: =$B18 -> ($ in millions except per share amounts) | KA18: =KA5 -> 43921 | KB18: =KB5 -> 44012 | KC18: =KC5 -> 44104 | KD18: =KD5 -> 44196 | KE18: =KE5 -> FY | KG18: =$B18 -> ($ in millions except per share amounts) | KH18: =KH5 -> 44286 | KI18: =KI5 -> 44377 | KJ18: =KJ5 -> 44469 | KK18: =KK5 -> 44561 | KL18: =KL5 -> FY | KN18: =$B18 -> ($ in millions except per share amounts) | KO18: =KO5 -> 44651 | KP18: =KP5 -> 44742 | KQ18: =KQ5 -> 44834 | KR18: =KR5 -> 44926 | KS18: =KS5 -> FY | KU18: =$B18 -> ($ in millions except per share amounts) | KV18: =KV5 -> 45016 | KW18: =KW5 -> 45107 | KX18: =KX5 -> 45199 | KY18: =KY5 -> 45291 | KZ18: =KZ5 -> FY | LB18: =$B18 -> ($ in millions except per share amounts) | LC18: =LC5 -> 45382 | LD18: =LD5 -> 45473 | LE18: =LE5 -> 45565 | LF18: =LF5 -> 45657 | LG18: =LG5 -> FY | LI18: =$B18 -> ($ in millions except per share amounts) | LJ18: =LJ5 -> 45747 | LK18: =LK5 -> 45838 | LL18: =LL5 -> 45930 | LM18: =LM5 -> 46022 | LN18: =LN5 -> FY | LP18: =$B18 -> ($ in millions except per share amounts) | LQ18: =LQ5 -> 46112 | LR18: =LR5 -> 46203 | LS18: =LS5 -> 46295 | LT18: =LT5 -> 46387 | LU18: =LU5 -> FY | LW18: =$B18 -> ($ in millions except per share amounts) | LX18: =LX5 -> 46477 | LY18: =LY5 -> 46568 | LZ18: =LZ5 -> 46660 | MA18: =MA5 -> 46752 | MB18: =MB5 -> FY | MD18: =$B18 -> ($ in millions except per share amounts) | ME18: =ME5 -> 46843 | MF18: =MF5 -> 46934 | MG18: =MG5 -> 47026 | MH18: =MH5 -> 47118 | MI18: =MI5 -> FY
B20: Revenue | C20: 3623.525 | D20: 4219.9 | E20: 4723.4 | F20: 5345.2 | G20: 4855 | H20: 4902 | I20: 5597 | J20: 5361 | K20: 6024 | L20: 6950 | M20: 7592 | N20: =BV20 -> 7745 | O20: =CC20 -> 8205.317 | P20: =CJ20 -> 8636.3 | Q20: =CQ20 -> 8734.1 | R20: =CX20 -> 8940.5 | S20: =DE20 -> 9608 | T20: =DL20 -> 10304 | U20: =DS20 -> 10536 | V20: =DZ20 -> 10963 | W20: =EG20 -> 9861 | X20: =EN20 -> 10811 | Y20: =EU20 -> 8435 | Z20: =FB20 -> 8110 | AA20: =FI20 -> 8152 | AB20: =FP20 -> 7567 | AC20: =FW20 -> 8025 | AD20: =GD20 -> 8601 | AE20: =GK20 -> 9566 | AF20: =GR20 -> 10030 | AG20: =GY20 -> 11255 | AH20: =HF20 -> 9041 | AI20: =HM20 -> 10636 | AJ20: =HT20 -> 11743 | AK20: =IA20 -> 11756 | AL20: =IH20 -> 12058 | AM20: =IO20 -> 12669 | AN20: =IV20 -> 11811 | AO20: =JC20 -> 11069 | AP20: =JJ20 -> 11408 | AQ20: =JQ20 -> 12250 | AR20: =JX20 -> 11937 | AS20: =KE20 -> 10583 | AT20: =KL20 -> 12522 | AU20: =KS20 -> 14853 | AV20: =KZ20 -> 14657 | AW20: =LG20 -> 14540 | AX20: =LN20 -> 14092 | AY20: =LU20 -> 14494.795 | AZ20: =MB20 -> 15180.906 | BA20: =MI20 -> 15848.637 | BQ20: Revenue | BR20: =SUM(Revenue!BP37,Revenue!BP384)+Expense!BP69+Expense!BP66+Revenue!BP442+Revenue!BP544 -> 1843.8 | BS20: =SUM(Revenue!BQ37,Revenue!BQ384)+Expense!BQ69+Expense!BQ66+Revenue!BQ442+Revenue!BQ544 -> 1974 | BT20: =SUM(Revenue!BR37,Revenue!BR384)+Expense!BR69+Expense!BR66+Revenue!BR442+Revenue!BR544 -> 1892.9 | BU20: =SUM(Revenue!BS37,Revenue!BS384)+Expense!BS69+Expense!BS66+Revenue!BS442+Revenue!BS544 -> 2034.3 | BV20: =SUM(BR20:BU20) -> 7745 | BX20: Revenue | BY20: =SUM(Revenue!BW37,Revenue!BW384)+Expense!BW69+Expense!BW66+Revenue!BW442+Revenue!BW544 -> 1907.7 | BZ20: =SUM(Revenue!BX37,Revenue!BX384)+Expense!BX69+Expense!BX66+Revenue!BX442+Revenue!BX544 -> 2046.9 | CA20: =SUM(Revenue!BY37,Revenue!BY384)+Expense!BY69+Expense!BY66+Revenue!BY442+Revenue!BY544 -> 2063 | CB20: =SUM(Revenue!BZ37,Revenue!BZ384)+Expense!BZ69+Expense!BZ66+Revenue!BZ442+Revenue!BZ544 -> 2187.717 | CC20: =SUM(BY20:CB20) -> 8205.317 | CE20: Revenue | CF20: =SUM(Revenue!CD37,Revenue!CD384)+Expense!CD69+Expense!CD66+Revenue!CD442+Revenue!CD544 -> 2030.3 | CG20: =SUM(Revenue!CE37,Revenue!CE384)+Expense!CE69+Expense!CE66+Revenue!CE442+Revenue!CE544 -> 2125 | CH20: =SUM(Revenue!CF37,Revenue!CF384)+Expense!CF69+Expense!CF66+Revenue!CF442+Revenue!CF544 -> 2204.9 | CI20: =SUM(Revenue!CG37,Revenue!CG384)+Expense!CG69+Expense!CG66+Revenue!CG442+Revenue!CG544 -> 2276.1 | CJ20: =SUM(CF20:CI20) -> 8636.3 | CL20: Revenue | CM20: =SUM(Revenue!CK37,Revenue!CK384)+Expense!CK69+Expense!CK66+Revenue!CK442+Revenue!CK544 -> 2086.4 | CN20: =SUM(Revenue!CL37,Revenue!CL384)+Expense!CL69+Expense!CL66+Revenue!CL442+Revenue!CL544 -> 2188.2 | CO20: =SUM(Revenue!CM37,Revenue!CM384)+Expense!CM69+Expense!CM66+Revenue!CM442+Revenue!CM544 -> 2214.3 | CP20: =SUM(Revenue!CN37,Revenue!CN384)+Expense!CN69+Expense!CN66+Revenue!CN442+Revenue!CN544 -> 2245.2 | CQ20: =SUM(CM20:CP20) -> 8734.1 | CS20: Revenue | CT20: =SUM(Revenue!CR37,Revenue!CR384)+Expense!CR69+Expense!CR66+Revenue!CR442+Revenue!CR544 -> 2123.3 | CU20: =SUM(Revenue!CS37,Revenue!CS384)+Expense!CS69+Expense!CS66+Revenue!CS442+Revenue!CS544 -> 2263.5 | CV20: =SUM(Revenue!CT37,Revenue!CT384)+Expense!CT69+Expense!CT66+Revenue!CT442+Revenue!CT544 -> 2238.7 | CW20: =SUM(Revenue!CU37,Revenue!CU384)+Expense!CU69+Expense!CU66+Revenue!CU442+Revenue!CU544 -> 2315 | CX20: =SUM(CT20:CW20) -> 8940.5 | CZ20: Revenue | DA20: =SUM(Revenue!CY37,Revenue!CY384)+Expense!CY69+Expense!CY66+Revenue!CY442+Revenue!CY544 -> 2227 | DB20: =SUM(Revenue!CZ37,Revenue!CZ384)+Expense!CZ69+Expense!CZ66+Revenue!CZ442+Revenue!CZ544 -> 2371 | DC20: =SUM(Revenue!DA37,Revenue!DA384)+Expense!DA69+Expense!DA66+Revenue!DA442+Revenue!DA544 -> 2470 | DD20: =SUM(Revenue!DB37,Revenue!DB384)+Expense!DB69+Expense!DB66+Revenue!DB442+Revenue!DB544 -> 2540 | DE20: =SUM(DA20:DD20) -> 9608 | DG20: Revenue | DH20: =SUM(Revenue!DF37,Revenue!DF384)+Expense!DF69+Expense!DF66+Revenue!DF442 -> 2444 | DI20: =SUM(Revenue!DG37,Revenue!DG384)+Expense!DG69+Expense!DG66+Revenue!DG442 -> 2549 | DJ20: =SUM(Revenue!DH37,Revenue!DH384)+Expense!DH69+Expense!DH66+Revenue!DH442 -> 2601 | DK20: =SUM(Revenue!DI37,Revenue!DI384)+Expense!DI69+Expense!DI66+Revenue!DI442 -> 2710 | DL20: =SUM(DH20:DK20) -> 10304 | DN20: Revenue | DO20: =SUM(Revenue!DM37,Revenue!DM384)+Expense!DM69+Expense!DM66+Revenue!DM442 -> 2514 | DP20: =SUM(Revenue!DN37,Revenue!DN384)+Expense!DN69+Expense!DN66+Revenue!DN442 -> 2672 | DQ20: =SUM(Revenue!DO37,Revenue!DO384)+Expense!DO69+Expense!DO66+Revenue!DO442 -> 2647 | DR20: =SUM(Revenue!DP37,Revenue!DP384)+Expense!DP69+Expense!DP66+Revenue!DP442 -> 2703 | DS20: =SUM(DO20:DR20) -> 10536 | DU20: Revenue | DV20: =SUM(Revenue!DT37,Revenue!DT384)+Expense!DT69+Expense!DT66+Revenue!DT442 -> 2567 | DW20: =SUM(Revenue!DU37,Revenue!DU384)+Expense!DU69+Expense!DU66+Revenue!DU442 -> 2678 | DX20: =SUM(Revenue!DV37,Revenue!DV384)+Expense!DV69+Expense!DV66+Revenue!DV442 -> 2815 | DY20: =SUM(Revenue!DW37,Revenue!DW384)+Expense!DW69+Expense!DW66+Revenue!DW442 -> 2903 | DZ20: =SUM(DV20:DY20) -> 10963 | EB20: Revenue | EC20: =SUM(Revenue!EA37,Revenue!EA384)+Expense!EA69+Expense!EA66 -> 2442 | ED20: =SUM(Revenue!EB37,Revenue!EB384)+Expense!EB69+Expense!EB66 -> 2490 | EE20: =SUM(Revenue!EC37,Revenue!EC384)+Expense!EC69+Expense!EC66 -> 2429 | EF20: =SUM(Revenue!ED37,Revenue!ED384)+Expense!ED69+Expense!ED66 -> 2500 | EG20: =SUM(EC20:EF20) -> 9861 | EI20: Revenue | EJ20: =SUM(Revenue!EH37,Revenue!EH384)+Expense!EH69+Expense!EH66 -> 2541 | EK20: =SUM(Revenue!EI37,Revenue!EI384)+Expense!EI69+Expense!EI66 -> 2616 | EL20: =SUM(Revenue!EJ37,Revenue!EJ384)+Expense!EJ69+Expense!EJ66 -> 2906 | EM20: =SUM(Revenue!EK37,Revenue!EK384)+Expense!EK69+Expense!EK66 -> 2748 | EN20: =SUM(EJ20:EM20) -> 10811 | EP20: Revenue | EQ20: =SUM(Revenue!EO37,Revenue!EO384)+Expense!EO69+Expense!EO66 -> 2147 | ER20: =SUM(Revenue!EP37,Revenue!EP384)+Expense!EP69+Expense!EP66 -> 2202 | ES20: =SUM(Revenue!EQ37,Revenue!EQ384)+Expense!EQ69+Expense!EQ66 -> 2039 | ET20: =SUM(Revenue!ER37,Revenue!ER384)+Expense!ER69+Expense!ER66 -> 2047 | EU20: =SUM(EQ20:ET20) -> 8435 | EW20: Revenue | EX20: =SUM(Revenue!EV37,Revenue!EV384)+Expense!EV69 -> 2025 | EY20: =SUM(Revenue!EW37,Revenue!EW384)+Expense!EW69 -> 2057 | EZ20: =SUM(Revenue!EX37,Revenue!EX384)+Expense!EX69 -> 2019 | FA20: =SUM(Revenue!EY37,Revenue!EY384)+Expense!EY69 -> 2009 | FB20: =SUM(EX20:FA20) -> 8110 | FD20: Revenue | FE20: =SUM(Revenue!FC37,Revenue!FC384)+Expense!FC69 -> 1964 | FF20: =SUM(Revenue!FD37,Revenue!FD384)+Expense!FD69 -> 2073 | FG20: =SUM(Revenue!FE37,Revenue!FE384)+Expense!FE69 -> 2055 | FH20: =SUM(Revenue!FF37,Revenue!FF384)+Expense!FF69 -> 2060 | FI20: =SUM(FE20:FH20) -> 8152 | FK20: Revenue | FL20: =SUM(Revenue!FJ37,Revenue!FJ384)+Expense!FJ69 -> 1960 | FM20: =SUM(Revenue!FK37,Revenue!FK384)+Expense!FK69 -> 1888 | FN20: =SUM(Revenue!FL37,Revenue!FL384) -> 1823 | FO20: =SUM(Revenue!FM37,Revenue!FM384) -> 1896 | FP20: =SUM(FL20:FO20) -> 7567 | FR20: Revenue | FS20: =SUM(Revenue!FQ37,Revenue!FQ384) -> 1920 | FT20: =SUM(Revenue!FR37,Revenue!FR384) -> 1995 | FU20: =SUM(Revenue!FS37,Revenue!FS384) -> 1938 | FV20: =SUM(Revenue!FT37,Revenue!FT384) -> 2172 | FW20: =SUM(FS20:FV20) -> 8025 | FY20: Revenue | FZ20: =SUM(Revenue!FX37,Revenue!FX384) -> 2108 | GA20: =SUM(Revenue!FY37,Revenue!FY384) -> 2149 | GB20: =SUM(Revenue!FZ37,Revenue!FZ384) -> 2125 | GC20: =SUM(Revenue!GA37,Revenue!GA384) -> 2219 | GD20: =SUM(FZ20:GC20) -> 8601 | GF20: Revenue | GG20: =SUM(Revenue!GE37,Revenue!GE384) -> 2331 | GH20: =SUM(Revenue!GF37,Revenue!GF384) -> 2421 | GI20: =SUM(Revenue!GG37,Revenue!GG384) -> 2418 | GJ20: =SUM(Revenue!GH37,Revenue!GH384) -> 2396 | GK20: =SUM(GG20:GJ20) -> 9566 | GM20: Revenue | GN20: =SUM(Revenue!GL37,Revenue!GL384) -> 2422 | GO20: =SUM(Revenue!GM37,Revenue!GM384) -> 2530 | GP20: =SUM(Revenue!GN37,Revenue!GN384) -> 2501 | GQ20: =SUM(Revenue!GO37,Revenue!GO384) -> 2577 | GR20: =SUM(GN20:GQ20) -> 10030 | GT20: Revenue | GU20: =SUM(Revenue!GS37,Revenue!GS384) -> 2713 | GV20: =SUM(Revenue!GT37,Revenue!GT384) -> 2907 | GW20: =SUM(Revenue!GU37,Revenue!GU384) -> 2961 | GX20: =SUM(Revenue!GV37,Revenue!GV384) -> 2674 | GY20: =SUM(GU20:GX20) -> 11255 | HA20: Revenue | HB20: =SUM(Revenue!GZ37,Revenue!GZ384) -> 2247 | HC20: =SUM(Revenue!HA37,Revenue!HA384) -> 2185 | HD20: =SUM(Revenue!HB37,Revenue!HB384) -> 2289 | HE20: =SUM(Revenue!HC37,Revenue!HC384) -> 2320 | HF20: =SUM(HB20:HE20) -> 9041 | HH20: Revenue | HI20: =SUM(Revenue!HG37,Revenue!HG384) -> 2491 | HJ20: =SUM(Revenue!HH37,Revenue!HH384) -> 2663 | HK20: =SUM(Revenue!HI37,Revenue!HI384) -> 2666 | HL20: =SUM(Revenue!HJ37,Revenue!HJ384) -> 2816 | HM20: =SUM(HI20:HL20) -> 10636 | HO20: Revenue | HP20: =SUM(Revenue!HN37,Revenue!HN384) -> 2810 | HQ20: =SUM(Revenue!HO37,Revenue!HO384) -> 3019 | HR20: =SUM(Revenue!HP37,Revenue!HP384) -> 2963 | HS20: =SUM(Revenue!HQ37,Revenue!HQ384) -> 2951 | HT20: =SUM(HP20:HS20) -> 11743 | HV20: Revenue | HW20: =SUM(Revenue!HU37,Revenue!HU384) -> 2966 | HX20: =SUM(Revenue!HV37,Revenue!HV384) -> 3012 | HY20: =SUM(Revenue!HW37,Revenue!HW384) -> 2894 | HZ20: =SUM(Revenue!HX37,Revenue!HX384) -> 2884 | IA20: =SUM(HW20:HZ20) -> 11756 | IC20: Revenue | ID20: =SUM(Revenue!IB37,Revenue!IB384) -> 2958 | IE20: =SUM(Revenue!IC37,Revenue!IC384) -> 3069 | IF20: =SUM(Revenue!ID37,Revenue!ID384) -> 2999 | IG20: =SUM(Revenue!IE37,Revenue!IE384) -> 3032 | IH20: =SUM(ID20:IG20) -> 12058 | IJ20: Revenue | IK20: =SUM(Revenue!II37,Revenue!II384) -> 3012 | IL20: =SUM(Revenue!IJ37,Revenue!IJ384) -> 3244 | IM20: =SUM(Revenue!IK37,Revenue!IK384) -> 3221 | IN20: =SUM(Revenue!IL37,Revenue!IL384) -> 3192 | IO20: =SUM(IK20:IN20) -> 12669 | IQ20: Revenue | IR20: 3027 | IS20: 3064 | IT20: 2939 | IU20: 2781 | IV20: =SUM(IR20:IU20) -> 11811 | IX20: Revenue | IY20: 2618 | IZ20: 2704 | JA20: 2710 | JB20: 3037 | JC20: =SUM(IY20:JB20) -> 11069 | JE20: Revenue | JF20: 2869 | JG20: 2933 | JH20: 2743 | JI20: 2863 | JJ20: =SUM(JF20:JI20) -> 11408 | JL20: Revenue | JM20: 2876 | JN20: 3102 | JO20: 3129 | JP20: 3143 | JQ20: =SUM(JM20:JP20) -> 12250 | JS20: Revenue | JT20: 3013 | JU20: =Revenue!JS37 -> 3061 | JV20: 2978 | JW20: 2885 | JX20: =SUM(JT20:JW20) -> 11937 | JZ20: Revenue | KA20: 2855 | KB20: =Revenue!JZ37 -> 2255 | KC20: =Revenue!KA37 -> 2648 | KD20: =Revenue!KB37 -> 2825 | KE20: =SUM(KA20:KD20) -> 10583 | KG20: Revenue | KH20: =Revenue!KF37 -> 2813 | KI20: =Revenue!KG37 -> 2990 | KJ20: =Revenue!KH37 -> 3292 | KK20: =Revenue!KI37 -> 3427 | KL20: =Revenue!KJ37 -> 12522 | KN20: Revenue | KO20: =Revenue!KM37 -> 3413 | KP20: =Revenue!KN37 -> 3815 | KQ20: =Revenue!KO37 -> 3895 | KR20: =Revenue!KP37 -> 3730 | KS20: =Revenue!KQ37 -> 14853 | KU20: Revenue | KV20: =Revenue!KT37 -> 3706 | KW20: =Revenue!KU37 -> 3699 | KX20: =Revenue!KV37 -> 3572 | KY20: =Revenue!KW37 -> 3680 | KZ20: =Revenue!KX37 -> 14657 | LB20: Revenue | LC20: =Revenue!LA37 -> 3681 | LD20: =Revenue!LB37 -> 3701 | LE20: =Revenue!LC37 -> 3619 | LF20: =Revenue!LD37 -> 3539 | LG20: =Revenue!LE37 -> 14540 | LI20: Revenue | LJ20: =Revenue!LH37 -> 3423 | LK20: =Revenue!LI37 -> 3574 | LL20: =Revenue!LJ37 -> 3587 | LM20: =Revenue!LK37 -> 3508 | LN20: =Revenue!LL37 -> 14092 | LP20: Revenue | LQ20: =Revenue!LO37 -> 3460.8174 | LR20: =Revenue!LP37 -> 3635.8899 | LS20: =Revenue!LQ37 -> 3703.9341 | LT20: =Revenue!LR37 -> 3694.1538 | LU20: =Revenue!LS37 -> 14494.795 | LW20: Revenue | LX20: =Revenue!LV37 -> 3628.2348 | LY20: =Revenue!LW37 -> 3808.953 | LZ20: =Revenue!LX37 -> 3876.0114 | MA20: =Revenue!LY37 -> 3867.7067 | MB20: =Revenue!LZ37 -> 15180.906 | MD20: Revenue | ME20: =Revenue!MC37 -> 3790.9745 | MF20: =Revenue!MD37 -> 3977.245 | MG20: =Revenue!ME37 -> 4046.1072 | MH20: =Revenue!MF37 -> 4034.3107 | MI20: =Revenue!MG37 -> 15848.637
B21: Yr/ Yr % | C21: - | D21: =D20/C20-1 -> 0.16458421 | E21: =E20/D20-1 -> 0.11931562 | F21: =F20/E20-1 -> 0.13164246 | G21: =G20/F20-1 -> -0.091708449 | H21: =H20/G20-1 -> 0.0096807415 | I21: =I20/H20-1 -> 0.14177887 | J21: =J20/I20-1 -> -0.042165446 | K21: =K20/J20-1 -> 0.12367096 | ... M21: =M20/L20-1 -> 0.092374101 | N21: =BV21 -> 0.020152792 | O21: =CC21 -> 0.059434087 | P21: =CJ21 -> 0.052524845 | Q21: =CQ21 -> 0.011324294 | R21: =CX21 -> 0.023631513 | S21: =DE21 -> 0.074660254 | T21: =DL21 -> 0.072439634 | U21: =DS21 -> 0.022515528 | V21: =DZ21 -> 0.040527715 | W21: =EG21 -> -0.10051993 | X21: =EN21 -> 0.096339114 | Y21: =EU21 -> -0.21977615 | Z21: =FB21 -> -0.038529935 | AA21: =FI21 -> 0.0051787916 | AB21: =FP21 -> -0.071761531 | AC21: =FW21 -> 0.060525968 | AD21: =GD21 -> 0.071775701 | AE21: =GK21 -> 0.11219626 | AF21: =GR21 -> 0.048505122 | AG21: =GY21 -> 0.1221336 | AH21: =HF21 -> -0.19671257 | AI21: =HM21 -> 0.17641854 | AJ21: =HT21 -> 0.10408048 | AK21: =IA21 -> 0.0011070425 | AL21: =IH21 -> 0.02568901 | AM21: =IO21 -> 0.050671753 | AN21: =IV21 -> -0.067724367 | AO21: =JC21 -> -0.062822792 | AP21: =JJ21 -> 0.030626073 | AQ21: =JQ21 -> 0.073807854 | AR21: =JX21 -> -0.02555102 | AS21: =KE21 -> -0.11342883 | AT21: =KL21 -> 0.18321837 | AU21: =KS21 -> 0.18615237 | AV21: =KZ21 -> -0.013195987 | AW21: =LG21 -> -0.0079825339 | AX21: =LN21 -> -0.030811554 | AY21: =LU21 -> 0.028583258 | AZ21: =MB21 -> 0.047334962 | BA21: =MI21 -> 0.043984959 | BQ21: Yr/ Yr % | BV21: =BV20/M20-1 -> 0.020152792 | BX21: Yr/ Yr % | BY21: =BY20/BR20-1 -> 0.034656687 | BZ21: =BZ20/BS20-1 -> 0.036930091 | CA21: =CA20/BT20-1 -> 0.089862116 | CB21: =CB20/BU20-1 -> 0.075415131 | CC21: =CC20/BV20-1 -> 0.059434087 | CE21: Yr/ Yr % | CF21: =CF20/BY20-1 -> 0.06426587 | CG21: =CG20/BZ20-1 -> 0.038155259 | CH21: =CH20/CA20-1 -> 0.068783325 | CI21: =CI20/CB20-1 -> 0.040399649 | CJ21: =CJ20/CC20-1 -> 0.052524845 | CL21: Yr/ Yr % | CM21: =CM20/CF20-1 -> 0.027631385 | CN21: =CN20/CG20-1 -> 0.029741176 | CO21: =CO20/CH20-1 -> 0.0042632319 | CP21: =CP20/CI20-1 -> -0.013575853 | CQ21: =CQ20/CJ20-1 -> 0.011324294 | CS21: Yr/ Yr % | CT21: =CT20/CM20-1 -> 0.017685966 | CU21: =CU20/CN20-1 -> 0.034411845 | CV21: =CV20/CO20-1 -> 0.011019284 | CW21: =CW20/CP20-1 -> 0.031088544 | CX21: =CX20/CQ20-1 -> 0.023631513 | CZ21: Yr/ Yr % | DA21: =DA20/CT20-1 -> 0.048839071 | DB21: =DB20/CU20-1 -> 0.047492821 | DC21: =DC20/CV20-1 -> 0.10331889 | DD21: =DD20/CW20-1 -> 0.097192225 | DE21: =DE20/CX20-1 -> 0.074660254 | DG21: Yr/ Yr % | DH21: =DH20/DA20-1 -> 0.097440503 | DI21: =DI20/DB20-1 -> 0.075073809 | DJ21: =DJ20/DC20-1 -> 0.053036437 | DK21: =DK20/DD20-1 -> 0.066929134 | DL21: =DL20/DE20-1 -> 0.072439634 | DN21: Yr/ Yr % | DO21: =DO20/DH20-1 -> 0.028641571 | DP21: =DP20/DI20-1 -> 0.048254217 | DQ21: =DQ20/DJ20-1 -> 0.017685506 | DR21: =DR20/DK20-1 -> -0.0025830258 | DS21: =DS20/DL20-1 -> 0.022515528 | DU21: Yr/ Yr % | DV21: =DV20/DO20-1 -> 0.021081941 | DW21: =DW20/DP20-1 -> 0.002245509 | DX21: =DX20/DQ20-1 -> 0.063468077 | DY21: =DY20/DR20-1 -> 0.073991861 | DZ21: =DZ20/DS20-1 -> 0.040527715 | EB21: Yr/ Yr % | EC21: =EC20/DV20-1 -> -0.048694975 | ED21: =ED20/DW20-1 -> -0.070201643 | EE21: =EE20/DX20-1 -> -0.13712256 | EF21: =EF20/DY20-1 -> -0.13882191 | EG21: =EG20/DZ20-1 -> -0.10051993 | EI21: Yr/ Yr % | EJ21: =EJ20/EC20-1 -> 0.040540541 | EK21: =EK20/ED20-1 -> 0.05060241 | EL21: =EL20/EE20-1 -> 0.19637711 | EM21: =EM20/EF20-1 -> 0.0992 | EN21: =EN20/EG20-1 -> 0.096339114 | EP21: Yr/ Yr % | EQ21: =EQ20/EJ20-1 -> -0.15505706 | ER21: =ER20/EK20-1 -> -0.15825688 | ES21: =ES20/EL20-1 -> -0.29834825 | ET21: =ET20/EM20-1 -> -0.25509461 | EU21: =EU20/EN20-1 -> -0.21977615 | EW21: Yr/ Yr % | EX21: =EX20/EQ20-1 -> -0.056823475 | EY21: =EY20/ER20-1 -> -0.065849228 | EZ21: =EZ20/ES20-1 -> -0.0098087298 | FA21: =FA20/ET20-1 -> -0.018563752 | FB21: =FB20/EU20-1 -> -0.038529935 | FD21: Yr/ Yr % | FE21: =FE20/EX20-1 -> -0.030123457 | FF21: =FF20/EY20-1 -> 0.0077783179 | FG21: =FG20/EZ20-1 -> 0.017830609 | FH21: =FH20/FA20-1 -> 0.025385764 | FI21: =FI20/FB20-1 -> 0.0051787916 | FK21: Yr/ Yr % | FL21: =FL20/FE20-1 -> -0.0020366599 | FM21: =FM20/FF20-1 -> -0.089242644 | FN21: =FN20/FG20-1 -> -0.11289538 | FO21: =FO20/FH20-1 -> -0.07961165 | FP21: =FP20/FI20-1 -> -0.071761531 | FR21: Yr/ Yr % | FS21: =FS20/FL20-1 -> -0.020408163 | FT21: =FT20/FM20-1 -> 0.056673729 | FU21: =FU20/FN20-1 -> 0.06308283 | FV21: =FV20/FO20-1 -> 0.14556962 | FW21: =FW20/FP20-1 -> 0.060525968 | FY21: Yr/ Yr % | FZ21: =FZ20/FS20-1 -> 0.097916667 | GA21: =GA20/FT20-1 -> 0.077192982 | GB21: =GB20/FU20-1 -> 0.096491228 | GC21: =GC20/FV20-1 -> 0.021639042 | GD21: =GD20/FW20-1 -> 0.071775701 | GF21: Yr/ Yr % | GG21: =GG20/FZ20-1 -> 0.10578748 | GH21: =GH20/GA20-1 -> 0.1265705 | GI21: =GI20/GB20-1 -> 0.13788235 | GJ21: =GJ20/GC20-1 -> 0.07976566 | GK21: =GK20/GD20-1 -> 0.11219626 | GM21: Yr/ Yr % | GN21: =GN20/GG20-1 -> 0.039039039 | GO21: =GO20/GH20-1 -> 0.045022718 | GP21: =GP20/GI20-1 -> 0.034325889 | GQ21: =GQ20/GJ20-1 -> 0.075542571 | GR21: =GR20/GK20-1 -> 0.048505122 | GT21: Yr/ Yr % | GU21: =GU20/GN20-1 -> 0.12014864 | GV21: =GV20/GO20-1 -> 0.14901186 | GW21: =GW20/GP20-1 -> 0.18392643 | GX21: =GX20/GQ20-1 -> 0.037640667 | GY21: =GY20/GR20-1 -> 0.1221336 | HA21: Yr/ Yr % | HB21: =HB20/GU20-1 -> -0.17176557 | HC21: =HC20/GV20-1 -> -0.24836601 | HD21: =HD20/GW20-1 -> -0.22695035 | HE21: =HE20/GX20-1 -> -0.13238594 | HF21: =HF20/GY20-1 -> -0.19671257 | HH21: Yr/ Yr % | HI21: =HI20/HB20-1 -> 0.10858923 | HJ21: =HJ20/HC20-1 -> 0.2187643 | HK21: =HK20/HD20-1 -> 0.16470074 | HL21: =HL20/HE20-1 -> 0.2137931 | HM21: =HM20/HF20-1 -> 0.17641854 | HO21: Yr/ Yr % | HP21: =HP20/HI20-1 -> 0.12806102 | HQ21: =HQ20/HJ20-1 -> 0.13368382 | HR21: =HR20/HK20-1 -> 0.11140285 | HS21: =HS20/HL20-1 -> 0.047940341 | HT21: =HT20/HM20-1 -> 0.10408048 | HV21: Yr/ Yr % | HW21: =HW20/HP20-1 -> 0.055516014 | HX21: =HX20/HQ20-1 -> -0.0023186486 | HY21: =HY20/HR20-1 -> -0.023287209 | HZ21: =HZ20/HS20-1 -> -0.022704168 | IA21: =IA20/HT20-1 -> 0.0011070425 | IC21: Yr/ Yr % | ID21: =ID20/HW20-1 -> -0.0026972353 | IE21: =IE20/HX20-1 -> 0.018924303 | IF21: =IF20/HY20-1 -> 0.036281963 | IG21: =IG20/HZ20-1 -> 0.051317614 | IH21: =IH20/IA20-1 -> 0.02568901 | IJ21: Yr/ Yr % | IK21: =IK20/ID20-1 -> 0.018255578 | IL21: =IL20/IE20-1 -> 0.057021831 | IM21: =IM20/IF20-1 -> 0.074024675 | IN21: =IN20/IG20-1 -> 0.052770449 | IO21: =IO20/IH20-1 -> 0.050671753 | IQ21: Yr/ Yr % | IR21: =IR20/IK20-1 -> 0.0049800797 | IS21: =IS20/IL20-1 -> -0.055487053 | IT21: =IT20/IM20-1 -> -0.08755045 | IU21: =IU20/IN20-1 -> -0.1287594 | IV21: =IV20/IO20-1 -> -0.067724367 | IX21: Yr/ Yr % | IY21: =IY20/IR20-1 -> -0.13511728 | IZ21: =IZ20/IS20-1 -> -0.11749347 | JA21: =JA20/IT20-1 -> -0.077917659 | JB21: =JB20/IU20-1 -> 0.092053218 | JC21: =JC20/IV20-1 -> -0.062822792 | JE21: Yr/ Yr % | JF21: =JF20/IY20-1 -> 0.095874714 | JG21: =JG20/IZ20-1 -> 0.084689349 | JH21: =JH20/JA20-1 -> 0.012177122 | JI21: =JI20/JB20-1 -> -0.057293382 | JJ21: =JJ20/JC20-1 -> 0.030626073 | JL21: Yr/ Yr % | JM21: =JM20/JF20-1 -> 0.0024398745 | JN21: =JN20/JG20-1 -> 0.057620184 | JO21: =JO20/JH20-1 -> 0.14072184 | JP21: =JP20/JI20-1 -> 0.097799511 | JQ21: =JQ20/JJ20-1 -> 0.073807854 | JS21: Yr/ Yr % | JT21: =JT20/JM20-1 -> 0.047635605 | JU21: =JU20/JN20-1 -> -0.013217279 | JV21: =JV20/JO20-1 -> -0.048258229 | JW21: =JW20/JP20-1 -> -0.082087178 | JX21: =JX20/JQ20-1 -> -0.02555102 | JZ21: Yr/ Yr % | KA21: =KA20/JT20-1 -> -0.052439429 | KB21: =KB20/JU20-1 -> -0.26331264 | KC21: =KC20/JV20-1 -> -0.11081263 | KD21: =KD20/JW20-1 -> -0.020797227 | KE21: =KE20/JX20-1 -> -0.11342883 | KG21: Yr/ Yr % | KH21: =KH20/KA20-1 -> -0.014711033 | KI21: =KI20/KB20-1 -> 0.32594235 | KJ21: =KJ20/KC20-1 -> 0.24320242 | KK21: =KK20/KD20-1 -> 0.21309735 | KL21: =KL20/KE20-1 -> 0.18321837 | KN21: Yr/ Yr % | KO21: =KO20/KH20-1 -> 0.21329541 | KP21: =KP20/KI20-1 -> 0.27591973 | KQ21: =KQ20/KJ20-1 -> 0.18317132 | KR21: =KR20/KK20-1 -> 0.088415524 | KS21: =KS20/KL20-1 -> 0.18615237 | KU21: Yr/ Yr % | KV21: =KV20/KO20-1 -> 0.085848227 | KW21: =KW20/KP20-1 -> -0.030406291 | KX21: =KX20/KQ20-1 -> -0.082926829 | KY21: =KY20/KR20-1 -> -0.013404826 | KZ21: =KZ20/KS20-1 -> -0.013195987 | LB21: Yr/ Yr % | LC21: =LC20/KV20-1 -> -0.0067458176 | LD21: =LD20/KW20-1 -> 0.00054068667 | LE21: =LE20/KX20-1 -> 0.013157895 | LF21: =LF20/KY20-1 -> -0.038315217 | LG21: =LG20/KZ20-1 -> -0.0079825339 | LI21: Yr/ Yr % | LJ21: =LJ20/LC20-1 -> -0.07008965 | LK21: =LK20/LD20-1 -> -0.03431505 | LL21: =LL20/LE20-1 -> -0.0088422216 | LM21: =LM20/LF20-1 -> -0.0087595366 | LN21: =LN20/LG20-1 -> -0.030811554 | LP21: Yr/ Yr % | LQ21: =LQ20/LJ20-1 -> 0.011048035 | LR21: =LR20/LK20-1 -> 0.017316711 | LS21: =LS20/LL20-1 -> 0.032599428 | LT21: =LT20/LM20-1 -> 0.0530655 | LU21: =LU20/LN20-1 -> 0.028583258 | LW21: Yr/ Yr % | LX21: =LX20/LQ20-1 -> 0.048375105 | LY21: =LY20/LR20-1 -> 0.047598534 | LZ21: =LZ20/LS20-1 -> 0.046457965 | MA21: =MA20/LT20-1 -> 0.046980423 | MB21: =MB20/LU20-1 -> 0.047334962 | MD21: Yr/ Yr % | ME21: =ME20/LX20-1 -> 0.044853677 | MF21: =MF20/LY20-1 -> 0.044183271 | MG21: =MG20/LZ20-1 -> 0.04388424 | MH21: =MH20/MA20-1 -> 0.043075665 | MI21: =MI20/MB20-1 -> 0.043984959
B23: Operating expenses | C23: 3256.739 | D23: 3642.8 | E23: 4063 | F23: 4539.5 | G23: 4383 | H23: 4360 | I23: 4766 | J23: 4545 | K23: 5272 | L23: 6155 | M23: 6683 | N23: =BV23 -> 6876 | O23: =CC23 -> 7337 | P23: =CJ23 -> 7782 | Q23: =CQ23 -> 7769 | R23: =CX23 -> 7934 | S23: =DE23 -> 8376 | T23: =DL23 -> 8902 | U23: =DS23 -> 9023.5 | V23: =DZ23 -> 9330 | W23: =EG23 -> 8748 | X23: =EN23 -> 9782 | Y23: =EU23 -> 7622 | Z23: =FB23 -> 7095 | AA23: =FI23 -> 7036 | AB23: =FP23 -> 6656 | AC23: =FW23 -> 6944 | AD23: =GD23 -> 7068 | AE23: =GK23 -> 7442 | AF23: =GR23 -> 7770 | AG23: =GY23 -> 8489 | AH23: =HF23 -> 6765 | AI23: =HM23 -> 7535 | AJ23: =HT23 -> 8325 | AK23: =IA23 -> 8299 | AL23: =IH23 -> 8553 | AM23: =IO23 -> 9056 | AN23: =IV23 -> 8227 | AO23: =JC23 -> 7680 | AP23: =JJ23 -> 7590 | AQ23: =JQ23 -> 7381 | AR23: =JX23 -> 6972 | AS23: =KE23 -> 6221 | AT23: =KL23 -> 7277 | AU23: =KS23 -> 8952 | AV23: =KZ23 -> 9158 | AW23: =LG23 -> 9187 | AX23: =LN23 -> 9320 | AY23: =LU23 -> 9216.6488 | AZ23: =MB23 -> 9326.9167 | BA23: =MI23 -> 9598.3882 | BQ23: Operating expenses | BR23: =SUM(BR27:BR33) -> 1656 | BS23: =SUM(BS27:BS33) -> 1744 | BT23: =SUM(BT27:BT33) -> 1717 | BU23: =SUM(BU27:BU33) -> 1759 | BV23: =SUM(BV27:BV33) -> 6876 | BX23: Operating expenses | BY23: =SUM(BY27:BY33) -> 1740 | BZ23: =SUM(BZ27:BZ33) -> 1826 | CA23: =SUM(CA27:CA33) -> 1827 | CB23: =SUM(CB27:CB33) -> 1944 | CC23: =SUM(CC27:CC33) -> 7337 | CE23: Operating expenses | CF23: =SUM(CF27:CF33) -> 1885 | CG23: =SUM(CG27:CG33) -> 1919 | CH23: =SUM(CH27:CH33) -> 1964 | CI23: =SUM(CI27:CI33) -> 2014 | CJ23: =SUM(CJ27:CJ33) -> 7782 | CL23: Operating expenses | CM23: =SUM(CM27:CM33) -> 1929 | CN23: =SUM(CN27:CN33) -> 1935 | CO23: =SUM(CO27:CO33) -> 1952 | CP23: =SUM(CP27:CP33) -> 1953 | CQ23: =SUM(CQ27:CQ33) -> 7769 | CS23: Operating expenses | CT23: =SUM(CT27:CT33) -> 1967 | CU23: =SUM(CU27:CU33) -> 1986 | CV23: =SUM(CV27:CV33) -> 1986 | CW23: =SUM(CW27:CW33) -> 1995 | CX23: =SUM(CX27:CX33) -> 7934 | CZ23: Operating expenses | DA23: =SUM(DA27:DA33) -> 2041 | DB23: =SUM(DB27:DB33) -> 2067 | DC23: =SUM(DC27:DC33) -> 2120 | DD23: =SUM(DD27:DD33) -> 2148 | DE23: =SUM(DE27:DE33) -> 8376 | DG23: Operating expenses | DH23: =SUM(DH27:DH33) -> 2168 | DI23: =SUM(DI27:DI33) -> 2200 | DJ23: =SUM(DJ27:DJ33) -> 2221 | DK23: =SUM(DK27:DK33) -> 2313 | DL23: =SUM(DL27:DL33) -> 8902 | DN23: Operating expenses | DO23: =SUM(DO27:DO33) -> 2218 | DP23: =SUM(DP27:DP33) -> 2273.5 | DQ23: =SUM(DQ27:DQ33) -> 2255 | DR23: =SUM(DR27:DR33) -> 2277 | DS23: =SUM(DS27:DS33) -> 9023.5 | DU23: Operating expenses | DV23: =SUM(DV27:DV33) -> 2243 | DW23: =SUM(DW27:DW33) -> 2245 | DX23: =SUM(DX27:DX33) -> 2413 | DY23: =SUM(DY27:DY33) -> 2429 | DZ23: =SUM(DZ27:DZ33) -> 9330 | EB23: Operating expenses | EC23: =SUM(EC27:EC33) -> 2184 | ED23: =SUM(ED27:ED33) -> 2154 | EE23: =SUM(EE27:EE33) -> 2186 | EF23: =SUM(EF27:EF33) -> 2224 | EG23: =SUM(EG27:EG33) -> 8748 | EI23: Operating expenses | EJ23: =SUM(EJ27:EJ33) -> 2280 | EK23: =SUM(EK27:EK33) -> 2342 | EL23: =SUM(EL27:EL33) -> 2590 | EM23: =SUM(EM27:EM33) -> 2570 | EN23: =SUM(EN27:EN33) -> 9782 | EP23: Operating expenses | EQ23: =SUM(EQ27:EQ33) -> 1976 | ER23: =SUM(ER27:ER33) -> 2002 | ES23: =SUM(ES27:ES33) -> 1815 | ET23: =SUM(ET27:ET33) -> 1829 | EU23: =SUM(EU27:EU33) -> 7622 | EW23: Operating expenses | EX23: =SUM(EX27:EX33) -> 1836 | EY23: =SUM(EY27:EY33) -> 1792 | EZ23: =SUM(EZ27:EZ33) -> 1739 | FA23: =SUM(FA27:FA33) -> 1728 | FB23: =SUM(FB27:FB33) -> 7095 | FD23: Operating expenses | FE23: =SUM(FE27:FE33) -> 1752 | FF23: =SUM(FF27:FF33) -> 1763 | FG23: =SUM(FG27:FG33) -> 1779 | FH23: =SUM(FH27:FH33) -> 1742 | FI23: =SUM(FI27:FI33) -> 7036 | FK23: Operating expenses | FL23: =SUM(FL27:FL33) -> 1798 | FM23: =SUM(FM27:FM33) -> 1620 | FN23: =SUM(FN27:FN33) -> 1591 | FO23: =SUM(FO27:FO33) -> 1647 | FP23: =SUM(FP27:FP33) -> 6656 | FR23: Operating expenses | FS23: =SUM(FS27:FS33) -> 1715 | FT23: =SUM(FT27:FT33) -> 1695 | FU23: =SUM(FU27:FU33) -> 1679 | FV23: =SUM(FV27:FV33) -> 1855 | FW23: =SUM(FW27:FW33) -> 6944 | FY23: Operating expenses | FZ23: =SUM(FZ27:FZ33) -> 1754 | GA23: =SUM(GA27:GA33) -> 1735 | GB23: =SUM(GB27:GB33) -> 1772 | GC23: =SUM(GC27:GC33) -> 1807 | GD23: =SUM(GD27:GD33) -> 7068 | GF23: Operating expenses | GG23: =SUM(GG27:GG33) -> 1844 | GH23: =SUM(GH27:GH33) -> 1776 | GI23: =SUM(GI27:GI33) -> 1929 | GJ23: =SUM(GJ27:GJ33) -> 1893 | GK23: =SUM(GK27:GK33) -> 7442 | GM23: Operating expenses | GN23: =SUM(GN27:GN33) -> 1937 | GO23: =SUM(GO27:GO33) -> 1918 | GP23: =SUM(GP27:GP33) -> 1943 | GQ23: =SUM(GQ27:GQ33) -> 1972 | GR23: =SUM(GR27:GR33) -> 7770 | GT23: Operating expenses | GU23: =SUM(GU27:GU33) -> 2089 | GV23: =SUM(GV27:GV33) -> 2190 | GW23: =SUM(GW27:GW33) -> 2228 | GX23: =SUM(GX27:GX33) -> 1982 | GY23: =SUM(GY27:GY33) -> 8489 | HA23: Operating expenses | HB23: =SUM(HB27:HB33) -> 1725 | HC23: =SUM(HC27:HC33) -> 1608 | HD23: =SUM(HD27:HD33) -> 1695 | HE23: =SUM(HE27:HE33) -> 1737 | HF23: =SUM(HF27:HF33) -> 6765 | HH23: Operating expenses | HI23: =SUM(HI27:HI33) -> 1859 | HJ23: =SUM(HJ27:HJ33) -> 1865 | HK23: =SUM(HK27:HK33) -> 1841 | HL23: =SUM(HL27:HL33) -> 1970 | HM23: =SUM(HM27:HM33) -> 7535 | HO23: Operating expenses | HP23: =SUM(HP27:HP33) -> 2037 | HQ23: =SUM(HQ27:HQ33) -> 2093 | HR23: =SUM(HR27:HR33) -> 2085 | HS23: =SUM(HS27:HS33) -> 2110 | HT23: =SUM(HT27:HT33) -> 8325 | HV23: Operating expenses | HW23: =SUM(HW27:HW33) -> 2110 | HX23: =SUM(HX27:HX33) -> 2069 | HY23: =SUM(HY27:HY33) -> 2040 | HZ23: =SUM(HZ27:HZ33) -> 2080 | IA23: =SUM(IA27:IA33) -> 8299 | IC23: Operating expenses | ID23: =SUM(ID27:ID33) -> 2083 | IE23: =SUM(IE27:IE33) -> 2106 | IF23: =SUM(IF27:IF33) -> 2145 | IG23: =SUM(IG27:IG33) -> 2219 | IH23: =SUM(IH27:IH33) -> 8553 | IJ23: Operating expenses | IK23: =SUM(IK27:IK33) -> 2273 | IL23: =SUM(IL27:IL33) -> 2247 | IM23: =SUM(IM27:IM33) -> 2245 | IN23: =SUM(IN27:IN33) -> 2291 | IO23: =SUM(IO27:IO33) -> 9056 | IQ23: Operating expenses | IR23: =SUM(IR27:IR33) -> 2184 | IS23: =SUM(IS27:IS33) -> 2047 | IT23: =SUM(IT27:IT33) -> 2006 | IU23: =SUM(IU27:IU33) -> 1990 | IV23: =SUM(IV27:IV33) -> 8227 | IX23: Operating expenses | IY23: =SUM(IY27:IY33) -> 1914 | IZ23: =SUM(IZ27:IZ33) -> 1864 | JA23: =SUM(JA27:JA33) -> 1869 | JB23: =SUM(JB27:JB33) -> 2033 | JC23: =SUM(JC27:JC33) -> 7680 | JE23: Operating expenses | JF23: =SUM(JF27:JF33) -> 1990 | JG23: =SUM(JG27:JG33) -> 1861 | JH23: =SUM(JH27:JH33) -> 1874 | JI23: =SUM(JI27:JI33) -> 1865 | JJ23: =SUM(JJ27:JJ33) -> 7590 | JL23: Operating expenses | JM23: =SUM(JM27:JM33) -> 1832 | JN23: =SUM(JN27:JN33) -> 1819 | JO23: =SUM(JO27:JO33) -> 1836 | JP23: =SUM(JP27:JP33) -> 1894 | JQ23: =SUM(JQ27:JQ33) -> 7381 | JS23: Operating expenses | JT23: =SUM(JT27:JT33) -> 1794 | JU23: =SUM(JU27:JU33) -> 1756 | JV23: =SUM(JV27:JV33) -> 1691 | JW23: =SUM(JW27:JW33) -> 1731 | JX23: =SUM(JX27:JX33) -> 6972 | JZ23: Operating expenses | KA23: =SUM(KA27:KA33) -> 1677 | KB23: =SUM(KB27:KB33) -> 1427 | KC23: =SUM(KC27:KC33) -> 1507 | KD23: =SUM(KD27:KD33) -> 1610 | KE23: =SUM(KE27:KE33) -> 6221 | KG23: Operating expenses | KH23: =SUM(KH27:KH33) -> 1712 | KI23: =SUM(KI27:KI33) -> 1648 | KJ23: =SUM(KJ27:KJ33) -> 1856 | KK23: =SUM(KK27:KK33) -> 2061 | KL23: =SUM(KL27:KL33) -> 7277 | KN23: Operating expenses | KO23: =SUM(KO27:KO33) -> 2131 | KP23: =SUM(KP27:KP33) -> 2234 | KQ23: =SUM(KQ27:KQ33) -> 2316 | KR23: =SUM(KR27:KR33) -> 2271 | KS23: =SUM(KS27:KS33) -> 8952 | KU23: Operating expenses | KV23: =SUM(KV27:KV33) -> 2259 | KW23: =SUM(KW27:KW33) -> 2233 | KX23: =SUM(KX27:KX33) -> 2301 | KY23: =SUM(KY27:KY33) -> 2365 | KZ23: =SUM(KZ27:KZ33) -> 9158 | LB23: Operating expenses | LC23: =SUM(LC27:LC33) -> 2344 | LD23: =SUM(LD27:LD33) -> 2253 | LE23: =SUM(LE27:LE33) -> 2265 | LF23: =SUM(LF27:LF33) -> 2325 | LG23: =SUM(LG27:LG33) -> 9187 | LI23: Operating expenses | LJ23: =SUM(LJ27:LJ33) -> 2382 | LK23: =SUM(LK27:LK33) -> 2291 | LL23: =SUM(LL27:LL33) -> 2301 | LM23: =SUM(LM27:LM33) -> 2346 | LN23: =SUM(LN27:LN33) -> 9320 | LP23: Operating expenses | LQ23: =SUM(LQ27:LQ33) -> 2291.653 | LR23: =SUM(LR27:LR33) -> 2269.5096 | LS23: =SUM(LS27:LS33) -> 2297.0032 | LT23: =SUM(LT27:LT33) -> 2358.483 | LU23: =SUM(LU27:LU33) -> 9216.6488 | LW23: Operating expenses | LX23: =SUM(LX27:LX33) -> 2323.452 | LY23: =SUM(LY27:LY33) -> 2300.3037 | LZ23: =SUM(LZ27:LZ33) -> 2319.4703 | MA23: =SUM(MA27:MA33) -> 2383.6907 | MB23: =SUM(MB27:MB33) -> 9326.9167 | MD23: Operating expenses | ME23: =SUM(ME27:ME33) -> 2383.2002 | MF23: =SUM(MF27:MF33) -> 2370.1662 | MG23: =SUM(MG27:MG33) -> 2399.1568 | MH23: =SUM(MH27:MH33) -> 2445.865 | MI23: =SUM(MI27:MI33) -> 9598.3882
B24: Operating Ratio % | C24: =C23/C20 -> 0.89877647 | D24: =D23/D20 -> 0.8632432 | E24: =E23/E20 -> 0.86018546 | F24: =F23/F20 -> 0.84926663 | G24: =G23/G20 -> 0.90278064 | H24: =H23/H20 -> 0.88943288 | I24: =I23/I20 -> 0.8515276 | J24: =J23/J20 -> 0.84778959 | ... M24: =M23/M20 -> 0.8802687 | N24: =BV24 -> 0.88779858 | O24: =CC24 -> 0.8941763 | P24: =CJ24 -> 0.90108032 | Q24: =CQ24 -> 0.88950207 | R24: =CX24 -> 0.8874224 | S24: =DE24 -> 0.87177352 | T24: =DL24 -> 0.86393634 | U24: =DS24 -> 0.85644457 | V24: =DZ24 -> 0.85104442 | W24: =EG24 -> 0.88713112 | X24: =EN24 -> 0.90481917 | Y24: =EU24 -> 0.90361589 | Z24: =FB24 -> 0.87484587 | AA24: =FI24 -> 0.86310108 | AB24: =FP24 -> 0.87960883 | AC24: =FW24 -> 0.86529595 | AD24: =GD24 -> 0.82176491 | AE24: =GK24 -> 0.77796362 | AF24: =GR24 -> 0.77467597 | AG24: =GY24 -> 0.75424256 | AH24: =HF24 -> 0.74825794 | AI24: =HM24 -> 0.70844302 | AJ24: =HT24 -> 0.70893298 | AK24: =IA24 -> 0.70593739 | AL24: =IH24 -> 0.70932161 | AM24: =IO24 -> 0.71481569 | AN24: =IV24 -> 0.69655406 | AO24: =JC24 -> 0.69382961 | AP24: =JJ24 -> 0.66532258 | AQ24: =JQ24 -> 0.60253061 | AR24: =JX24 -> 0.58406635 | AS24: =KE24 -> 0.58782954 | AT24: =KL24 -> 0.5811372 | AU24: =KS24 -> 0.60270652 | AV24: =KZ24 -> 0.6248209 | AW24: =LG24 -> 0.63184319 | AX24: =LN24 -> 0.66136815 | AY24: =LU24 -> 0.63585919 | AZ24: =MB24 -> 0.61438473 | BA24: =MI24 -> 0.60562861 | BQ24: Operating Ratio % | BR24: =BR23/BR20 -> 0.89814514 | BS24: =BS23/BS20 -> 0.88348531 | BT24: =BT23/BT20 -> 0.9070738 | BU24: =BU23/BU20 -> 0.86467089 | BV24: =BV23/BV20 -> 0.88779858 | BX24: Operating Ratio % | BY24: =BY23/BY20 -> 0.9120931 | BZ24: =BZ23/BZ20 -> 0.89208071 | CA24: =CA23/CA20 -> 0.88560349 | CB24: =CB23/CB20 -> 0.88859757 | CC24: =CC23/CC20 -> 0.8941763 | CE24: Operating Ratio % | CF24: =CF23/CF20 -> 0.92843422 | CG24: =CG23/CG20 -> 0.90305882 | CH24: =CH23/CH20 -> 0.89074334 | CI24: =CI23/CI20 -> 0.88484689 | CJ24: =CJ23/CJ20 -> 0.90108032 | CL24: Operating Ratio % | CM24: =CM23/CM20 -> 0.92455905 | CN24: =CN23/CN20 -> 0.88428846 | CO24: =CO23/CO20 -> 0.8815427 | CP24: =CP23/CP20 -> 0.86985569 | CQ24: =CQ23/CQ20 -> 0.88950207 | CS24: Operating Ratio % | CT24: =CT23/CT20 -> 0.92638817 | CU24: =CU23/CU20 -> 0.87740225 | CV24: =CV23/CV20 -> 0.88712199 | CW24: =CW23/CW20 -> 0.86177106 | CX24: =CX23/CX20 -> 0.8874224 | CZ24: Operating Ratio % | DA24: =DA23/DA20 -> 0.91647957 | DB24: =DB23/DB20 -> 0.87178406 | DC24: =DC23/DC20 -> 0.8582996 | DD24: =DD23/DD20 -> 0.84566929 | DE24: =DE23/DE20 -> 0.87177352 | DG24: Operating Ratio % | DH24: =DH23/DH20 -> 0.88707038 | DI24: =DI23/DI20 -> 0.86308356 | DJ24: =DJ23/DJ20 -> 0.85390235 | DK24: =DK23/DK20 -> 0.85350554 | DL24: =DL23/DL20 -> 0.86393634 | DN24: Operating Ratio % | DO24: =DO23/DO20 -> 0.88225935 | DP24: =DP23/DP20 -> 0.85086078 | DQ24: =DQ23/DQ20 -> 0.85190782 | DR24: =DR23/DR20 -> 0.84239734 | DS24: =DS23/DS20 -> 0.85644457 | DU24: Operating Ratio % | DV24: =DV23/DV20 -> 0.87378263 | DW24: =DW23/DW20 -> 0.83831217 | DX24: =DX23/DX20 -> 0.85719361 | DY24: =DY23/DY20 -> 0.83672063 | DZ24: =DZ23/DZ20 -> 0.85104442 | EB24: Operating Ratio % | EC24: =EC23/EC20 -> 0.89434889 | ED24: =ED23/ED20 -> 0.86506024 | EE24: =EE23/EE20 -> 0.89995883 | EF24: =EF23/EF20 -> 0.8896 | EG24: =EG23/EG20 -> 0.88713112 | EI24: Operating Ratio % | EJ24: =EJ23/EJ20 -> 0.89728453 | EK24: =EK23/EK20 -> 0.89525994 | EL24: =EL23/EL20 -> 0.89125946 | EM24: =EM23/EM20 -> 0.93522562 | EN24: =EN23/EN20 -> 0.90481917 | EP24: Operating Ratio % | EQ24: =EQ23/EQ20 -> 0.92035398 | ER24: =ER23/ER20 -> 0.90917348 | ES24: =ES23/ES20 -> 0.89014223 | ET24: =ET23/ET20 -> 0.89350269 | EU24: =EU23/EU20 -> 0.90361589 | EW24: Operating Ratio % | EX24: =EX23/EX20 -> 0.90666667 | EY24: =EY23/EY20 -> 0.87117161 | EZ24: =EZ23/EZ20 -> 0.86131748 | FA24: =FA23/FA20 -> 0.86012942 | FB24: =FB23/FB20 -> 0.87484587 | FD24: Operating Ratio % | FE24: =FE23/FE20 -> 0.89205703 | FF24: =FF23/FF20 -> 0.85045827 | FG24: =FG23/FG20 -> 0.86569343 | FH24: =FH23/FH20 -> 0.84563107 | FI24: =FI23/FI20 -> 0.86310108 | FK24: Operating Ratio % | FL24: =FL23/FL20 -> 0.91734694 | FM24: =FM23/FM20 -> 0.85805085 | FN24: =FN23/FN20 -> 0.87273725 | FO24: =FO23/FO20 -> 0.86867089 | FP24: =FP23/FP20 -> 0.87960883 | FR24: Operating Ratio % | FS24: =FS23/FS20 -> 0.89322917 | FT24: =FT23/FT20 -> 0.84962406 | FU24: =FU23/FU20 -> 0.86635707 | FV24: =FV23/FV20 -> 0.85405157 | FW24: =FW23/FW20 -> 0.86529595 | FY24: Operating Ratio % | FZ24: =FZ23/FZ20 -> 0.83206831 | GA24: =GA23/GA20 -> 0.80735226 | GB24: =GB23/GB20 -> 0.83388235 | GC24: =GC23/GC20 -> 0.81433078 | GD24: =GD23/GD20 -> 0.82176491 | GF24: Operating Ratio % | GG24: =GG23/GG20 -> 0.79107679 | GH24: =GH23/GH20 -> 0.73358116 | GI24: =GI23/GI20 -> 0.79776675 | GJ24: =GJ23/GJ20 -> 0.79006678 | GK24: =GK23/GK20 -> 0.77796362 | GM24: Operating Ratio % | GN24: =GN23/GN20 -> 0.79975227 | GO24: =GO23/GO20 -> 0.75810277 | GP24: =GP23/GP20 -> 0.77688924 | GQ24: =GQ23/GQ20 -> 0.76523089 | GR24: =GR23/GR20 -> 0.77467597 | GT24: Operating Ratio % | GU24: =GU23/GU20 -> 0.76999631 | GV24: =GV23/GV20 -> 0.75335397 | GW24: =GW23/GW20 -> 0.7524485 | GX24: =GX23/GX20 -> 0.74121167 | GY24: =GY23/GY20 -> 0.75424256 | HA24: Operating Ratio % | HB24: =HB23/HB20 -> 0.76769025 | HC24: =HC23/HC20 -> 0.73592677 | HD24: =HD23/HD20 -> 0.74049803 | HE24: =HE23/HE20 -> 0.7487069 | HF24: =HF23/HF20 -> 0.74825794 | HH24: Operating Ratio % | HI24: =HI23/HI20 -> 0.74628663 | HJ24: =HJ23/HJ20 -> 0.70033796 | HK24: =HK23/HK20 -> 0.69054764 | HL24: =HL23/HL20 -> 0.69957386 | HM24: =HM23/HM20 -> 0.70844302 | HO24: Operating Ratio % | HP24: =HP23/HP20 -> 0.72491103 | HQ24: =HQ23/HQ20 -> 0.69327592 | HR24: =HR23/HR20 -> 0.7036787 | HS24: =HS23/HS20 -> 0.71501186 | HT24: =HT23/HT20 -> 0.70893298 | HV24: Operating Ratio % | HW24: =HW23/HW20 -> 0.71139582 | HX24: =HX23/HX20 -> 0.68691899 | HY24: =HY23/HY20 -> 0.7049067 | HZ24: =HZ23/HZ20 -> 0.72122053 | IA24: =IA23/IA20 -> 0.70593739 | IC24: Operating Ratio % | ID24: =ID23/ID20 -> 0.70419202 | IE24: =IE23/IE20 -> 0.68621701 | IF24: =IF23/IF20 -> 0.71523841 | IG24: =IG23/IG20 -> 0.73186016 | IH24: =IH23/IH20 -> 0.70932161 | IJ24: Operating Ratio % | IK24: =IK23/IK20 -> 0.75464807 | IL24: =IL23/IL20 -> 0.69266338 | IM24: =IM23/IM20 -> 0.69698851 | IN24: =IN23/IN20 -> 0.71773183 | IO24: =IO23/IO20 -> 0.71481569 | IQ24: Operating Ratio % | IR24: =IR23/IR20 -> 0.72150644 | IS24: =IS23/IS20 -> 0.66808094 | IT24: =IT23/IT20 -> 0.68254508 | IU24: =IU23/IU20 -> 0.71556994 | IV24: =IV23/IV20 -> 0.69655406 | IX24: Operating Ratio % | IY24: =IY23/IY20 -> 0.73109244 | IZ24: =IZ23/IZ20 -> 0.68934911 | JA24: =JA23/JA20 -> 0.6896679 | JB24: =JB23/JB20 -> 0.6694106 | JC24: =JC23/JC20 -> 0.69382961 | JE24: Operating Ratio % | JF24: =JF23/JF20 -> 0.69362147 | JG24: =JG23/JG20 -> 0.63450392 | JH24: =JH23/JH20 -> 0.68319358 | JI24: =JI23/JI20 -> 0.6514146 | JJ24: =JJ23/JJ20 -> 0.66532258 | JL24: Operating Ratio % | JM24: =JM23/JM20 -> 0.63699583 | JN24: =JN23/JN20 -> 0.58639587 | JO24: =JO23/JO20 -> 0.58676894 | JP24: =JP23/JP20 -> 0.60260897 | JQ24: =JQ23/JQ20 -> 0.60253061 | JS24: Operating Ratio % | JT24: =JT23/JT20 -> 0.59541985 | JU24: =JU23/JU20 -> 0.57366874 | JV24: =JV23/JV20 -> 0.56783076 | JW24: =JW23/JW20 -> 0.6 | JX24: =JX23/JX20 -> 0.58406635 | JZ24: Operating Ratio % | KA24: =KA23/KA20 -> 0.58739054 | KB24: =KB23/KB20 -> 0.63281596 | KC24: =KC23/KC20 -> 0.56910876 | KD24: =KD23/KD20 -> 0.5699115 | KE24: =KE23/KE20 -> 0.58782954 | KG24: Operating Ratio % | KH24: =KH23/KH20 -> 0.60860292 | KI24: =KI23/KI20 -> 0.55117057 | KJ24: =KJ23/KJ20 -> 0.56379101 | KK24: =KK23/KK20 -> 0.60140064 | KL24: =KL23/KL20 -> 0.5811372 | KN24: Operating Ratio % | KO24: =KO23/KO20 -> 0.62437738 | KP24: =KP23/KP20 -> 0.58558322 | KQ24: =KQ23/KQ20 -> 0.59460847 | KR24: =KR23/KR20 -> 0.60884718 | KS24: =KS23/KS20 -> 0.60270652 | KU24: Operating Ratio % | KV24: =KV23/KV20 -> 0.60955208 | KW24: =KW23/KW20 -> 0.60367667 | KX24: =KX23/KX20+0.0001 -> 0.64427693 | KY24: =KY23/KY20 -> 0.64266304 | KZ24: =KZ23/KZ20 -> 0.6248209 | LB24: Operating Ratio % | LC24: =LC23/LC20 -> 0.63678348 | LD24: =LD23/LD20 -> 0.60875439 | LE24: =LE23/LE20 -> 0.6258635 | LF24: =LF23/LF20 -> 0.65696524 | LG24: =LG23/LG20 -> 0.63184319 | LI24: Operating Ratio % | LJ24: =LJ23/LJ20 -> 0.69588081 | LK24: =LK23/LK20 -> 0.64101847 | LL24: =LL23/LL20 -> 0.64148313 | LM24: =LM23/LM20 -> 0.66875713 | LN24: =LN23/LN20 -> 0.66136815 | LP24: Operating Ratio % | LQ24: =LQ23/LQ20 -> 0.66217103 | LR24: =LR23/LR20 -> 0.62419645 | LS24: =LS23/LS20 -> 0.62015227 | LT24: =LT23/LT20 -> 0.63843661 | LU24: =LU23/LU20 -> 0.63585919 | LW24: Operating Ratio % | LX24: =LX23/LX20 -> 0.64038082 | LY24: =LY23/LY20 -> 0.60392023 | LZ24: =LZ23/LZ20 -> 0.59841679 | MA24: =MA23/MA20 -> 0.61630596 | MB24: =MB23/MB20 -> 0.61438473 | MD24: Operating Ratio % | ME24: =ME23/ME20 -> 0.62865107 | MF24: =MF23/MF20 -> 0.59593166 | MG24: =MG23/MG20 -> 0.59295432 | MH24: =MH23/MH20 -> 0.6062659 | MI24: =MI23/MI20 -> 0.60562861
B25: Yr/ Yr % | D25: =D23/C23-1 -> 0.1185422 | E25: =E23/D23-1 -> 0.11535083 | F25: =F23/E23-1 -> 0.11727787 | G25: =G23/F23-1 -> -0.034475162 | H25: =H23/G23-1 -> -0.0052475473 | I25: =I23/H23-1 -> 0.093119266 | J25: =J23/I23-1 -> -0.046370122 | K25: =K23/J23-1 -> 0.159956 | ... M25: =M23/L23-1 -> 0.085783916 | N25: =BV25 -> 0.028879246 | O25: =CC25 -> 0.067044793 | P25: =CJ25 -> 0.060651492 | Q25: =CQ25 -> -0.0016705217 | R25: =CX25 -> 0.021238255 | S25: =DE25 -> 0.055709604 | T25: =DL25 -> 0.062798472 | U25: =DS25 -> 0.013648618 | V25: =DZ25 -> 0.033966864 | W25: =EG25 -> -0.062379421 | X25: =EN25 -> 0.11819845 | Y25: =EU25 -> -0.22081374 | Z25: =FB25 -> -0.069141957 | AA25: =FI25 -> -0.0083157153 | AB25: =FP25 -> -0.054007959 | AC25: =FW25 -> 0.043269231 | AD25: =GD25 -> 0.017857143 | AE25: =GK25 -> 0.052914544 | AF25: =GR25 -> 0.044074174 | AG25: =GY25 -> 0.092535393 | AH25: =HF25 -> -0.20308635 | AI25: =HM25 -> 0.11382114 | AJ25: =HT25 -> 0.10484406 | AK25: =IA25 -> -0.0031231231 | AL25: =IH25 -> 0.030606097 | AM25: =IO25 -> 0.058809774 | AN25: =IV25 -> -0.091541519 | AO25: =JC25 -> -0.066488392 | AP25: =JJ25 -> -0.01171875 | AQ25: =JQ25 -> -0.027536232 | AR25: =JX25 -> -0.055412546 | AS25: =KE25 -> -0.10771658 | AT25: =KL25 -> 0.16974763 | AU25: =KS25 -> 0.23017727 | AV25: =KZ25 -> 0.023011618 | AW25: =LG25 -> 0.0031666303 | AX25: =LN25 -> 0.014476978 | AY25: =LU25 -> -0.011089182 | AZ25: =MB25 -> 0.011963988 | BA25: =MI25 -> 0.029106239 | BQ25: Yr/ Yr % | BR25: - | BS25: - | BT25: - | BU25: - | BV25: =BV23/M23-1 -> 0.028879246 | BX25: Yr/ Yr % | BY25: =BY23/BR23-1 -> 0.050724638 | BZ25: =BZ23/BS23-1 -> 0.047018349 | CA25: =CA23/BT23-1 -> 0.06406523 | CB25: =CB23/BU23-1 -> 0.10517339 | CC25: =CC23/BV23-1 -> 0.067044793 | CE25: Yr/ Yr % | CF25: =CF23/BY23-1 -> 0.083333333 | CG25: =CG23/BZ23-1 -> 0.050930997 | CH25: =CH23/CA23-1 -> 0.074986316 | CI25: =CI23/CB23-1 -> 0.03600823 | CJ25: =CJ23/CC23-1 -> 0.060651492 | CL25: Yr/ Yr % | CM25: =CM23/CF23-1 -> 0.023342175 | CN25: =CN23/CG23-1 -> 0.0083376759 | CO25: =CO23/CH23-1 -> -0.0061099796 | CP25: =CP23/CI23-1 -> -0.030287984 | CQ25: =CQ23/CJ23-1 -> -0.0016705217 | CS25: Yr/ Yr % | CT25: =CT23/CM23-1 -> 0.019699326 | CU25: =CU23/CN23-1 -> 0.026356589 | CV25: =CV23/CO23-1 -> 0.017418033 | CW25: =CW23/CP23-1 -> 0.021505376 | CX25: =CX23/CQ23-1 -> 0.021238255 | CZ25: Yr/ Yr % | DA25: =DA23/CT23-1 -> 0.037620742 | DB25: =DB23/CU23-1 -> 0.040785498 | DC25: =DC23/CV23-1 -> 0.067472306 | DD25: =DD23/CW23-1 -> 0.076691729 | DE25: =DE23/CX23-1 -> 0.055709604 | DG25: Yr/ Yr % | DH25: =DH23/DA23-1 -> 0.0622244 | DI25: =DI23/DB23-1 -> 0.064344461 | DJ25: =DJ23/DC23-1 -> 0.047641509 | DK25: =DK23/DD23-1 -> 0.076815642 | DL25: =DL23/DE23-1 -> 0.062798472 | DN25: Yr/ Yr % | DO25: =DO23/DH23-1 -> 0.023062731 | DP25: =DP23/DI23-1 -> 0.033409091 | DQ25: =DQ23/DJ23-1 -> 0.01530842 | DR25: =DR23/DK23-1 -> -0.015564202 | DS25: =DS23/DL23-1 -> 0.013648618 | DU25: Yr/ Yr % | DV25: =DV23/DO23-1 -> 0.011271416 | DW25: =DW23/DP23-1 -> -0.012535738 | DX25: =DX23/DQ23-1 -> 0.070066519 | DY25: =DY23/DR23-1 -> 0.066754502 | DZ25: =DZ23/DS23-1 -> 0.033966864 | EB25: Yr/ Yr % | EC25: =EC23/DV23-1 -> -0.026304057 | ED25: =ED23/DW23-1 -> -0.040534521 | EE25: =EE23/DX23-1 -> -0.094073767 | EF25: =EF23/DY23-1 -> -0.084396871 | EG25: =EG23/DZ23-1 -> -0.062379421 | EI25: Yr/ Yr % | EJ25: =EJ23/EC23-1 -> 0.043956044 | EK25: =EK23/ED23-1 -> 0.08727948 | EL25: =EL23/EE23-1 -> 0.18481244 | EM25: =EM23/EF23-1 -> 0.15557554 | EN25: =EN23/EG23-1 -> 0.11819845 | EP25: Yr/ Yr % | EQ25: =EQ23/EJ23-1 -> -0.13333333 | ER25: =ER23/EK23-1 -> -0.14517506 | ES25: =ES23/EL23-1 -> -0.2992278 | ET25: =ET23/EM23-1 -> -0.28832685 | EU25: =EU23/EN23-1 -> -0.22081374 | EW25: Yr/ Yr % | EX25: =EX23/EQ23-1 -> -0.070850202 | EY25: =EY23/ER23-1 -> -0.1048951 | EZ25: =EZ23/ES23-1 -> -0.041873278 | FA25: =FA23/ET23-1 -> -0.055221432 | FB25: =FB23/EU23-1 -> -0.069141957 | FD25: Yr/ Yr % | FE25: =FE23/EX23-1 -> -0.045751634 | FF25: =FF23/EY23-1 -> -0.016183036 | FG25: =FG23/EZ23-1 -> 0.023001725 | FH25: =FH23/FA23-1 -> 0.0081018519 | FI25: =FI23/FB23-1 -> -0.0083157153 | FK25: Yr/ Yr % | FL25: =FL23/FE23-1 -> 0.026255708 | FM25: =FM23/FF23-1 -> -0.081111741 | FN25: =FN23/FG23-1 -> -0.10567735 | FO25: =FO23/FH23-1 -> -0.054535017 | FP25: =FP23/FI23-1 -> -0.054007959 | FR25: Yr/ Yr % | FS25: =FS23/FL23-1 -> -0.046162403 | FT25: =FT23/FM23-1 -> 0.046296296 | FU25: =FU23/FN23-1 -> 0.055311125 | FV25: =FV23/FO23-1 -> 0.12629022 | FW25: =FW23/FP23-1 -> 0.043269231 | FY25: Yr/ Yr % | FZ25: =FZ23/FS23-1 -> 0.022740525 | GA25: =GA23/FT23-1 -> 0.02359882 | GB25: =GB23/FU23-1 -> 0.055390113 | GC25: =GC23/FV23-1 -> -0.025876011 | GD25: =GD23/FW23-1 -> 0.017857143 | GF25: Yr/ Yr % | GG25: =GG23/FZ23-1 -> 0.051311288 | GH25: =GH23/GA23-1 -> 0.023631124 | GI25: =GI23/GB23-1 -> 0.088600451 | GJ25: =GJ23/GC23-1 -> 0.047592695 | GK25: =GK23/GD23-1 -> 0.052914544 | GM25: Yr/ Yr % | GN25: =GN23/GG23-1 -> 0.050433839 | GO25: =GO23/GH23-1 -> 0.079954955 | GP25: =GP23/GI23-1 -> 0.0072576464 | GQ25: =GQ23/GJ23-1 -> 0.041732699 | GR25: =GR23/GK23-1 -> 0.044074174 | GT25: Yr/ Yr % | GU25: =GU23/GN23-1 -> 0.078471864 | GV25: =GV23/GO23-1 -> 0.14181439 | GW25: =GW23/GP23-1 -> 0.14668039 | GX25: =GX23/GQ23-1 -> 0.0050709939 | GY25: =GY23/GR23-1 -> 0.092535393 | HA25: Yr/ Yr % | HB25: =HB23/GU23-1 -> -0.17424605 | HC25: =HC23/GV23-1 -> -0.26575342 | HD25: =HD23/GW23-1 -> -0.23922801 | HE25: =HE23/GX23-1 -> -0.12361251 | HF25: =HF23/GY23-1 -> -0.20308635 | HH25: Yr/ Yr % | HI25: =HI23/HB23-1 -> 0.077681159 | HJ25: =HJ23/HC23-1 -> 0.15982587 | HK25: =HK23/HD23-1 -> 0.086135693 | HL25: =HL23/HE23-1 -> 0.13413932 | HM25: =HM23/HF23-1 -> 0.11382114 | HO25: Yr/ Yr % | HP25: =HP23/HI23-1 -> 0.095750403 | HQ25: =HQ23/HJ23-1 -> 0.12225201 | HR25: =HR23/HK23-1 -> 0.13253666 | HS25: =HS23/HL23-1 -> 0.07106599 | HT25: =HT23/HM23-1 -> 0.10484406 | HV25: Yr/ Yr % | HW25: =HW23/HP23-1 -> 0.035837015 | HX25: =HX23/HQ23-1 -> -0.011466794 | HY25: =HY23/HR23-1 -> -0.021582734 | HZ25: =HZ23/HS23-1 -> -0.014218009 | IA25: =IA23/HT23-1 -> -0.0031231231 | IC25: Yr/ Yr % | ID25: =ID23/HW23-1 -> -0.012796209 | IE25: =IE23/HX23-1 -> 0.017883035 | IF25: =IF23/HY23-1 -> 0.051470588 | IG25: =IG23/HZ23-1 -> 0.066826923 | IH25: =IH23/IA23-1 -> 0.030606097 | IJ25: Yr/ Yr % | IK25: =IK23/ID23-1 -> 0.091214594 | IL25: =IL23/IE23-1 -> 0.066951567 | IM25: =IM23/IF23-1 -> 0.046620047 | IN25: =IN23/IG23-1 -> 0.032447048 | IO25: =IO23/IH23-1 -> 0.058809774 | IQ25: Yr/ Yr % | IR25: =IR23/IK23-1 -> -0.039155301 | IS25: =IS23/IL23-1 -> -0.089007566 | IT25: =IT23/IM23-1 -> -0.1064588 | IU25: =IU23/IN23-1 -> -0.13138368 | IV25: =IV23/IO23-1 -> -0.091541519 | IX25: Yr/ Yr % | IY25: =IY23/IR23-1 -> -0.12362637 | IZ25: =IZ23/IS23-1 -> -0.089399121 | JA25: =JA23/IT23-1 -> -0.068295115 | JB25: =JB23/IU23-1 -> 0.02160804 | JC25: =JC23/IV23-1 -> -0.066488392 | JE25: Yr/ Yr % | JF25: =JF23/IY23-1 -> 0.039707419 | JG25: =JG23/IZ23-1 -> -0.0016094421 | JH25: =JH23/JA23-1 -> 0.0026752274 | JI25: =JI23/JB23-1 -> -0.082636498 | JJ25: =JJ23/JC23-1 -> -0.01171875 | JL25: Yr/ Yr % | JM25: =JM23/JF23-1 -> -0.079396985 | JN25: =JN23/JG23-1 -> -0.022568512 | JO25: =JO23/JH23-1 -> -0.020277481 | JP25: =JP23/JI23-1 -> 0.015549598 | JQ25: =JQ23/JJ23-1 -> -0.027536232 | JS25: Yr/ Yr % | JT25: =JT23/JM23-1 -> -0.020742358 | JU25: =JU23/JN23-1 -> -0.034634415 | JV25: =JV23/JO23-1 -> -0.078976035 | JW25: =JW23/JP23-1 -> -0.086061246 | JX25: =JX23/JQ23-1 -> -0.055412546 | JZ25: Yr/ Yr % | KA25: =KA23/JT23-1 -> -0.065217391 | KB25: =KB23/JU23-1 -> -0.18735763 | KC25: =KC23/JV23-1 -> -0.10881135 | KD25: =KD23/JW23-1 -> -0.069901791 | KE25: =KE23/JX23-1 -> -0.10771658 | KG25: Yr/ Yr % | KH25: =KH23/KA23-1 -> 0.020870602 | KI25: =KI23/KB23-1 -> 0.15487036 | KJ25: =KJ23/KC23-1 -> 0.23158593 | KK25: =KK23/KD23-1 -> 0.28012422 | KL25: =KL23/KE23-1 -> 0.16974763 | KN25: Yr/ Yr % | KO25: =KO23/KH23-1 -> 0.24474299 | KP25: =KP23/KI23-1 -> 0.35558252 | KQ25: =KQ23/KJ23-1 -> 0.24784483 | KR25: =KR23/KK23-1 -> 0.10189229 | KS25: =KS23/KL23-1 -> 0.23017727 | KU25: Yr/ Yr % | KV25: =KV23/KO23-1 -> 0.060065697 | KW25: =KW23/KP23-1 -> -0.00044762757 | KX25: =KX23/KQ23-1 -> -0.0064766839 | KY25: =KY23/KR23-1 -> 0.041391458 | KZ25: =KZ23/KS23-1 -> 0.023011618 | LB25: Yr/ Yr % | LC25: =LC23/KV23-1 -> 0.037627269 | LD25: =LD23/KW23-1 -> 0.0089565607 | LE25: =LE23/KX23-1 -> -0.015645372 | LF25: =LF23/KY23-1 -> -0.016913319 | LG25: =LG23/KZ23-1 -> 0.0031666303 | LI25: Yr/ Yr % | LJ25: =LJ23/LC23-1 -> 0.016211604 | LK25: =LK23/LD23-1 -> 0.0168664 | LL25: =LL23/LE23-1 -> 0.01589404 | LM25: =LM23/LF23-1 -> 0.0090322581 | LN25: =LN23/LG23-1 -> 0.014476978 | LP25: Yr/ Yr % | LQ25: =LQ23/LJ23-1 -> -0.037929041 | LR25: =LR23/LK23-1 -> -0.0093803645 | LS25: =LS23/LL23-1 -> -0.0017369903 | LT25: =LT23/LM23-1 -> 0.0053209838 | LU25: =LU23/LN23-1 -> -0.011089182 | LW25: Yr/ Yr % | LX25: =LX23/LQ23-1 -> 0.01387599 | LY25: =LY23/LR23-1 -> 0.013568642 | LZ25: =LZ23/LS23-1 -> 0.0097810575 | MA25: =MA23/LT23-1 -> 0.010688072 | MB25: =MB23/LU23-1 -> 0.011963988 | MD25: Yr/ Yr % | ME25: =ME23/LX23-1 -> 0.02571528 | MF25: =MF23/LY23-1 -> 0.030370966 | MG25: =MG23/LZ23-1 -> 0.034355456 | MH25: =MH23/MA23-1 -> 0.026083227 | MI25: =MI23/MB23-1 -> 0.029106239
B27: Labor and fringe | C27: =Expense!C32+Expense!C42+Expense!C50+Expense!C59 -> 1769.287 | D27: =Expense!D32+Expense!D42+Expense!D50+Expense!D59 -> 1974.7 | E27: =Expense!E32+Expense!E42+Expense!E50+Expense!E59 -> 2063.1 | F27: =Expense!F32+Expense!F42+Expense!F50+Expense!F59 -> 2304.6 | G27: =Expense!G32+Expense!G42+Expense!G50+Expense!G59 -> 2232 | H27: =Expense!H32+Expense!H42+Expense!H50+Expense!H59 -> 2380 | I27: =Expense!I32+Expense!I42+Expense!I50+Expense!I59 -> 2534 | J27: =Expense!J32+Expense!J42+Expense!J50+Expense!J59 -> 2287 | ... M27: =Expense!M32+Expense!M42+Expense!M50+Expense!M59 -> 2736 | N27: =BV27 -> 2758 | O27: =CC27 -> 2806 | P27: =CJ27 -> 2845 | Q27: =CQ27 -> 2793 | R27: =CX27 -> 2807 | S27: =DE27 -> 2880 | T27: =DL27 -> 2977.5 | U27: =DS27 -> 3034 | V27: =DZ27 -> 3073 | W27: =EG27 -> 2983 | X27: =EN27 -> 3306 | Y27: =EU27 -> 2900 | Z27: =FB27 -> 2931 | AA27: =FI27 -> 2892 | AB27: =FP27 -> 2628 | AC27: =FW27 -> 2760 | AD27: =GD27 -> 2864 | AE27: =GK27 -> 2922 | AF27: =GR27 -> 2986 | AG27: =GY27 -> 2955 | AH27: =HF27 -> 2629 | AI27: =HM27 -> 2957 | AJ27: =HT27 -> 3073 | AK27: =IA27 -> 3020 | AL27: =IH27 -> 3138 | AM27: =IO27 -> 3377 | AN27: =IV27 -> 3290 | AO27: =JC27 -> 3159 | AP27: =JJ27 -> 2946 | AQ27: =JQ27 -> 2738 | AR27: =JX27 -> 2616 | AS27: =KE27 -> 2275 | AT27: =KL27 -> 2550 | AU27: =KS27 -> 2861 | AV27: =KZ27 -> 3052 | AW27: =LG27 -> 3165 | AX27: =LN27 -> 3209 | AY27: =LU27 -> 3180.7282 | AZ27: =MB27 -> 3281.8947 | BA27: =MI27 -> 3394.2564 | BQ27: Labor and fringe | BR27: =Expense!BP32+Expense!BP42+Expense!BP50+Expense!BP59 -> 679 | BS27: =Expense!BQ32+Expense!BQ42+Expense!BQ50+Expense!BQ59 -> 684 | BT27: =Expense!BR32+Expense!BR42+Expense!BR50+Expense!BR59 -> 679 | BU27: =Expense!BS32+Expense!BS42+Expense!BS50+Expense!BS59 -> 716 | BV27: =SUM(BR27:BU27) -> 2758 | BX27: Labor and fringe | BY27: =Expense!BW32+Expense!BW42+Expense!BW50+Expense!BW59 -> 697 | BZ27: =Expense!BX32+Expense!BX42+Expense!BX50+Expense!BX59 -> 707 | CA27: =Expense!BY32+Expense!BY42+Expense!BY50+Expense!BY59 -> 709 | CB27: =Expense!BZ32+Expense!BZ42+Expense!BZ50+Expense!BZ59 -> 693 | CC27: =SUM(BY27:CB27) -> 2806 | CE27: Labor and fringe | CF27: =Expense!CD32+Expense!CD42+Expense!CD50+Expense!CD59 -> 695 | CG27: =Expense!CE32+Expense!CE42+Expense!CE50+Expense!CE59 -> 688 | CH27: =Expense!CF32+Expense!CF42+Expense!CF50+Expense!CF59 -> 713 | CI27: =Expense!CG32+Expense!CG42+Expense!CG50+Expense!CG59 -> 749 | CJ27: =SUM(CF27:CI27) -> 2845 | CL27: Labor and fringe | CM27: =Expense!CK32+Expense!CK42+Expense!CK50+Expense!CK59 -> 722 | CN27: =Expense!CL32+Expense!CL42+Expense!CL50+Expense!CL59 -> 699 | CO27: =Expense!CM32+Expense!CM42+Expense!CM50+Expense!CM59 -> 671 | CP27: =Expense!CN32+Expense!CN42+Expense!CN50+Expense!CN59 -> 701 | CQ27: =SUM(CM27:CP27) -> 2793 | CS27: Labor and fringe | CT27: =Expense!CR32+Expense!CR42+Expense!CR50+Expense!CR59 -> 706 | CU27: =Expense!CS32+Expense!CS42+Expense!CS50+Expense!CS59 -> 684 | CV27: =Expense!CT32+Expense!CT42+Expense!CT50+Expense!CT59 -> 697 | CW27: =Expense!CU32+Expense!CU42+Expense!CU50+Expense!CU59 -> 720 | CX27: =SUM(CT27:CW27) -> 2807 | CZ27: Labor and fringe | DA27: =Expense!CY32+Expense!CY42+Expense!CY50+Expense!CY59 -> 724 | DB27: =Expense!CZ32+Expense!CZ42+Expense!CZ50+Expense!CZ59 -> 706 | DC27: =Expense!DA32+Expense!DA42+Expense!DA50+Expense!DA59 -> 712 | DD27: =Expense!DB32+Expense!DB42+Expense!DB50+Expense!DB59 -> 738 | DE27: =SUM(DA27:DD27) -> 2880 | DG27: Labor and fringe | DH27: =Expense!DF32+Expense!DF42+Expense!DF50+Expense!DF59 -> 743 | DI27: =Expense!DG32+Expense!DG42+Expense!DG50+Expense!DG59 -> 733 | DJ27: =Expense!DH32+Expense!DH42+Expense!DH50+Expense!DH59 -> 742.5 | DK27: =Expense!DI32+Expense!DI42+Expense!DI50+Expense!DI59 -> 759 | DL27: =SUM(DH27:DK27) -> 2977.5 | DN27: Labor and fringe | DO27: =Expense!DM32+Expense!DM42+Expense!DM50+Expense!DM59 -> 765 | DP27: =Expense!DN32+Expense!DN42+Expense!DN50+Expense!DN59 -> 767 | DQ27: =Expense!DO32+Expense!DO42+Expense!DO50+Expense!DO59 -> 757 | DR27: =Expense!DP32+Expense!DP42+Expense!DP50+Expense!DP59 -> 745 | DS27: =SUM(DO27:DR27) -> 3034 | DU27: Labor and fringe | DV27: =Expense!DT32+Expense!DT42+Expense!DT50+Expense!DT59 -> 762 | DW27: =Expense!DU32+Expense!DU42+Expense!DU50+Expense!DU59 -> 755 | DX27: =Expense!DV32+Expense!DV42+Expense!DV50+Expense!DV59 -> 780 | DY27: =Expense!DW32+Expense!DW42+Expense!DW50+Expense!DW59 -> 776 | DZ27: =SUM(DV27:DY27) -> 3073 | EB27: Labor and fringe | EC27: =Expense!EA32+Expense!EA42+Expense!EA50 -> 773 | ED27: =Expense!EB32+Expense!EB42+Expense!EB50 -> 719 | EE27: =Expense!EC32+Expense!EC42+Expense!EC50 -> 748 | EF27: =Expense!ED32+Expense!ED42+Expense!ED50 -> 743 | EG27: =SUM(EC27:EF27) -> 2983 | EI27: Labor and fringe | EJ27: =Expense!EH32+Expense!EH42+Expense!EH50 -> 796 | EK27: =Expense!EI32+Expense!EI42+Expense!EI50 -> 806 | EL27: =Expense!EJ32+Expense!EJ42+Expense!EJ50 -> 873 | EM27: =Expense!EK32+Expense!EK42+Expense!EK50 -> 831 | EN27: =SUM(EJ27:EM27) -> 3306 | EP27: Labor and fringe | EQ27: =Expense!EO32+Expense!EO42+Expense!EO50 -> 727 | ER27: =Expense!EP32+Expense!EP42+Expense!EP50 -> 730 | ES27: =Expense!EQ32+Expense!EQ42+Expense!EQ50 -> 727 | ET27: =Expense!ER32+Expense!ER42+Expense!ER50 -> 716 | EU27: =SUM(EQ27:ET27) -> 2900 | EW27: Labor and fringe | EX27: =Expense!EV32+Expense!EV42+Expense!EV50 -> 753 | EY27: =Expense!EW32+Expense!EW42+Expense!EW50 -> 740 | EZ27: =Expense!EX32+Expense!EX42+Expense!EX50 -> 708 | FA27: =Expense!EY32+Expense!EY42+Expense!EY50 -> 730 | FB27: =SUM(EX27:FA27) -> 2931 | FD27: Labor and fringe | FE27: =Expense!FC32+Expense!FC42+Expense!FC50 -> 729 | FF27: =Expense!FD32+Expense!FD42+Expense!FD50 -> 717 | FG27: =Expense!FE32+Expense!FE42+Expense!FE50 -> 718 | FH27: =Expense!FF32+Expense!FF42+Expense!FF50 -> 728 | FI27: =SUM(FE27:FH27) -> 2892 | FK27: Labor and fringe | FL27: =Expense!FJ32+Expense!FJ42 -> 667 | FM27: =Expense!FK32+Expense!FK42 -> 663 | FN27: =Expense!FL32+Expense!FL42 -> 643 | FO27: =Expense!FM32+Expense!FM42 -> 655 | FP27: =SUM(FL27:FO27) -> 2628 | FR27: Labor and fringe | FS27: =Expense!FQ32+Expense!FQ42 -> 685 | FT27: =Expense!FR32+Expense!FR42 -> 664 | FU27: =Expense!FS32+Expense!FS42 -> 671 | FV27: =Expense!FT32+Expense!FT42 -> 740 | FW27: =SUM(FS27:FV27) -> 2760 | FY27: Labor and fringe | FZ27: =Expense!FX32+Expense!FX42 -> 702 | GA27: =Expense!FY32+Expense!FY42 -> 706 | GB27: =Expense!FZ32+Expense!FZ42 -> 725 | GC27: =Expense!GA32+Expense!GA42 -> 731 | GD27: =SUM(FZ27:GC27) -> 2864 | GF27: Labor and fringe | GG27: =Expense!GE32+Expense!GE42 -> 718 | GH27: =Expense!GF32+Expense!GF42 -> 715 | GI27: =Expense!GG32+Expense!GG42 -> 736 | GJ27: =Expense!GH32+Expense!GH42 -> 753 | GK27: =SUM(GG27:GJ27) -> 2922 | GM27: Labor and fringe | GN27: =Expense!GL32+Expense!GL42 -> 734 | GO27: =Expense!GM32+Expense!GM42 -> 743 | GP27: =Expense!GN32+Expense!GN42 -> 748 | GQ27: =Expense!GO32+Expense!GO42 -> 761 | GR27: =SUM(GN27:GQ27) -> 2986 | GT27: Labor and fringe | GU27: =Expense!GS32+Expense!GS42 -> 745 | GV27: =Expense!GT32+Expense!GT42 -> 733 | GW27: =Expense!GU32+Expense!GU42 -> 754 | GX27: =Expense!GV32+Expense!GV42 -> 723 | GY27: =SUM(GU27:GX27) -> 2955 | HA27: Labor and fringe | HB27: 662 | HC27: 654 | HD27: 653 | HE27: 660 | HF27: =SUM(HB27:HE27) -> 2629 | HH27: Labor and fringe | HI27: 729 | HJ27: 721 | HK27: 731 | HL27: 776 | HM27: =SUM(HI27:HL27) -> 2957 | HO27: Labor and fringe | HP27: 765 | HQ27: 764 | HR27: 765 | HS27: 779 | HT27: =SUM(HP27:HS27) -> 3073 | HV27: Labor and fringe | HW27: 770 | HX27: 744 | HY27: 754 | HZ27: 752 | IA27: =SUM(HW27:HZ27) -> 3020 | IC27: Labor and fringe | ID27: 767 | IE27: 777 | IF27: 791 | IG27: 803 | IH27: =SUM(ID27:IG27) -> 3138 | IJ27: Labor and fringe | IK27: 814 | IL27: 809 | IM27: 845 | IN27: 909 | IO27: =SUM(IK27:IN27) -> 3377 | IQ27: Labor and fringe | IR27: 879 | IS27: 825 | IT27: 787 | IU27: 799 | IV27: =SUM(IR27:IU27) -> 3290 | IX27: Labor and fringe | IY27: 796 | IZ27: 749 | JA27: 762 | JB27: 852 | JC27: =SUM(IY27:JB27) -> 3159 | JE27: Labor and fringe | JF27: 795 | JG27: 751 | JH27: 725 | JI27: 675 | JJ27: =SUM(JF27:JI27) -> 2946 | JL27: Labor and fringe | JM27: 696 | JN27: 669 | JO27: 695 | JP27: 678 | JQ27: =SUM(JM27:JP27) -> 2738 | JS27: Labor and fringe | JT27: 672 | JU27: 648 | JV27: 638 | JW27: 658 | JX27: =SUM(JT27:JW27) -> 2616 | JZ27: Labor and fringe | KA27: 606 | KB27: 507 | KC27: 574 | KD27: 588 | KE27: =SUM(KA27:KD27) -> 2275 | KG27: Labor and fringe | KH27: 620 | KI27: 596 | KJ27: 631 | KK27: 703 | KL27: =SUM(KH27:KK27) -> 2550 | KN27: Labor and fringe | KO27: 692 | KP27: 684 | KQ27: 759 | KR27: 726 | KS27: =SUM(KO27:KR27) -> 2861 | KU27: Labor and fringe | KV27: =723+7 -> 730 | KW27: =741+7 -> 748 | KX27: 761 | KY27: =808+5 -> 813 | KZ27: =SUM(KV27:KY27) -> 3052 | LB27: Labor and fringe | LC27: =Expense!LA7 -> 805 | LD27: =Expense!LB7 -> 766 | LE27: =Expense!LC7 -> 806 | LF27: =Expense!LD7 -> 788 | LG27: =Expense!LE7 -> 3165 | LI27: Labor and fringe | LJ27: =Expense!LH7 -> 821 | LK27: =Expense!LI7 -> 791 | LL27: =Expense!LJ7 -> 793 | LM27: =Expense!LK7 -> 804 | LN27: =Expense!LL7 -> 3209 | LP27: Labor and fringe | LQ27: =Expense!LO7 -> 811.48397 | LR27: =Expense!LP7 -> 777.24666 | LS27: =Expense!LQ7 -> 785.96095 | LT27: =Expense!LR7 -> 806.03666 | LU27: =Expense!LS7 -> 3180.7282 | LW27: Labor and fringe | LX27: =Expense!LV7 -> 835.11462 | LY27: =Expense!LW7 -> 802.15632 | LZ27: =Expense!LX7 -> 811.22337 | MA27: =Expense!LY7 -> 833.40041 | MB27: =Expense!LZ7 -> 3281.8947 | MD27: Labor and fringe | ME27: =Expense!MC7 -> 862.30727 | MF27: =Expense!MD7 -> 829.17262 | MG27: =Expense!ME7 -> 839.45004 | MH27: =Expense!MF7 -> 863.32644 | MI27: =Expense!MG7 -> 3394.2564
B28: Purchased Services and Other | C28: =SUM(Expense!C33,Expense!C43)+Expense!C51+Expense!C60 -> 1073.41 | D28: =SUM(Expense!D33,Expense!D43)+Expense!D51+Expense!D60 -> 1202.9 | E28: =SUM(Expense!E33,Expense!E43)+Expense!E51+Expense!E60 -> 1395.2 | F28: =SUM(Expense!F33,Expense!F43)+Expense!F51+Expense!F60 -> 1533 | G28: =SUM(Expense!G33,Expense!G43)+Expense!G51+Expense!G60 -> 813 | H28: =SUM(Expense!H33,Expense!H43)+Expense!H51+Expense!H60 -> 675 | I28: =SUM(Expense!I33,Expense!I43)+Expense!I51+Expense!I60 -> 848 | J28: =SUM(Expense!J33,Expense!J43)+Expense!J51+Expense!J60 -> 918 | ... M28: =SUM(Expense!M33,Expense!M43)+Expense!M51+Expense!M60 -> 2336 | N28: =BV28 -> 2247 | O28: =CC28 -> 1916 | P28: =CJ28 -> 2058 | Q28: =CQ28 -> 2012 | R28: =CX28 -> 2002 | S28: =DE28 -> 2148 | T28: =DL28 -> 2422.5 | U28: =DS28 -> 2469.5 | V28: =DZ28 -> 2450 | W28: =EG28 -> 2459 | X28: =EN28 -> 2638 | Y28: =EU28 -> 1814 | Z28: =FB28 -> 1657 | AA28: =FI28 -> 1699 | AB28: =FP28 -> 1530 | AC28: =FW28 -> 1724 | AD28: =GD28 -> 1776 | AE28: =GK28 -> 1964 | AF28: =GR28 -> 1924 | AG28: =GY28 -> 2135 | AH28: =HF28 -> 1863 | AI28: =HM28 -> 2075 | AJ28: =HT28 -> 2229 | AK28: =IA28 -> 2156 | AL28: =IH28 -> 2275 | AM28: =IO28 -> 2484 | AN28: =IV28 -> 2336 | AO28: =JC28 -> 2073 | AP28: =JJ28 -> 2114 | AQ28: =JQ28 -> 1967 | AR28: =JX28 -> 1784 | AS28: =KE28 -> 1684 | AT28: =KL28 -> 2132 | AU28: =KS28 -> 2685 | AV28: =KZ28 -> 2792 | AW28: =LG28 -> 2852 | AX28: =LN28 -> 2979 | AY28: =LU28 -> 2934.8989 | AZ28: =MB28 -> 2883.427 | BA28: =MI28 -> 2955.1465 | BQ28: Purchased Services and Other | BR28: =SUM(Expense!BP33,Expense!BP43)+Expense!BP51+Expense!BP60 -> 569 | BS28: =SUM(Expense!BQ33,Expense!BQ43)+Expense!BQ51+Expense!BQ60 -> 630 | BT28: =SUM(Expense!BR33,Expense!BR43)+Expense!BR51+Expense!BR60 -> 624 | BU28: =SUM(Expense!BS33,Expense!BS43)+Expense!BS51+Expense!BS60 -> 424 | BV28: =SUM(BR28:BU28) -> 2247 | BX28: Purchased Services and Other | BY28: =SUM(Expense!BW33,Expense!BW43)+Expense!BW51+Expense!BW60 -> 432 | BZ28: =SUM(Expense!BX33,Expense!BX43)+Expense!BX51+Expense!BX60 -> 478 | CA28: =SUM(Expense!BY33,Expense!BY43)+Expense!BY51+Expense!BY60 -> 477 | CB28: =SUM(Expense!BZ33,Expense!BZ43)+Expense!BZ51+Expense!BZ60 -> 529 | CC28: =SUM(BY28:CB28) -> 1916 | CE28: Purchased Services and Other | CF28: =SUM(Expense!CD33,Expense!CD43)+Expense!CD51+Expense!CD60 -> 485 | CG28: =SUM(Expense!CE33,Expense!CE43)+Expense!CE51+Expense!CE60 -> 531 | CH28: =SUM(Expense!CF33,Expense!CF43)+Expense!CF51+Expense!CF60 -> 531 | CI28: =SUM(Expense!CG33,Expense!CG43)+Expense!CG51+Expense!CG60 -> 511 | CJ28: =SUM(CF28:CI28) -> 2058 | CL28: Purchased Services and Other | CM28: =SUM(Expense!CK33,Expense!CK43)+Expense!CK51+Expense!CK60 -> 482 | CN28: =SUM(Expense!CL33,Expense!CL43)+Expense!CL51+Expense!CL60 -> 503 | CO28: =SUM(Expense!CM33,Expense!CM43)+Expense!CM51+Expense!CM60 -> 528 | CP28: =SUM(Expense!CN33,Expense!CN43)+Expense!CN51+Expense!CN60 -> 499 | CQ28: =SUM(CM28:CP28) -> 2012 | CS28: Purchased Services and Other | CT28: =SUM(Expense!CR33,Expense!CR43)+Expense!CR51+Expense!CR60 -> 494 | CU28: =SUM(Expense!CS33,Expense!CS43)+Expense!CS51+Expense!CS60 -> 507 | CV28: =SUM(Expense!CT33,Expense!CT43)+Expense!CT51+Expense!CT60 -> 509 | CW28: =SUM(Expense!CU33,Expense!CU43)+Expense!CU51+Expense!CU60 -> 492 | CX28: =SUM(CT28:CW28) -> 2002 | CZ28: Purchased Services and Other | DA28: =SUM(Expense!CY33,Expense!CY43)+Expense!CY51+Expense!CY60 -> 519 | DB28: =SUM(Expense!CZ33,Expense!CZ43)+Expense!CZ51+Expense!CZ60 -> 538 | DC28: =SUM(Expense!DA33,Expense!DA43)+Expense!DA51+Expense!DA60 -> 542 | DD28: =SUM(Expense!DB33,Expense!DB43)+Expense!DB51+Expense!DB60 -> 549 | DE28: =SUM(DA28:DD28) -> 2148 | DG28: Purchased Services and Other | DH28: =SUM(Expense!DF33,Expense!DF43)+Expense!DF51+Expense!DF60 -> 565 | DI28: =SUM(Expense!DG33,Expense!DG43)+Expense!DG51+Expense!DG60 -> 609 | DJ28: =SUM(Expense!DH33,Expense!DH43)+Expense!DH51+Expense!DH60 -> 610.5 | DK28: =SUM(Expense!DI33,Expense!DI43)+Expense!DI51+Expense!DI60 -> 638 | DL28: =SUM(DH28:DK28) -> 2422.5 | DN28: Purchased Services and Other | DO28: =SUM(Expense!DM33,Expense!DM43)+Expense!DM51+Expense!DM60 -> 605 | DP28: =SUM(Expense!DN33,Expense!DN43)+Expense!DN51+Expense!DN60 -> 621.5 | DQ28: =SUM(Expense!DO33,Expense!DO43)+Expense!DO51+Expense!DO60 -> 625 | DR28: =SUM(Expense!DP33,Expense!DP43)+Expense!DP51+Expense!DP60 -> 618 | DS28: =SUM(DO28:DR28) -> 2469.5 | DU28: Purchased Services and Other | DV28: =SUM(Expense!DT33,Expense!DT43)+Expense!DT51+Expense!DT60 -> 600 | DW28: =SUM(Expense!DU33,Expense!DU43)+Expense!DU51+Expense!DU60 -> 605 | DX28: =SUM(Expense!DV33,Expense!DV43)+Expense!DV51+Expense!DV60 -> 616 | DY28: =SUM(Expense!DW33,Expense!DW43)+Expense!DW51+Expense!DW60 -> 629 | DZ28: =SUM(DV28:DY28) -> 2450 | EB28: Purchased Services and Other | EC28: =SUM(Expense!EA33,Expense!EA43)+Expense!EA51 -> 580 | ED28: =SUM(Expense!EB33,Expense!EB43)+Expense!EB51 -> 612 | EE28: =SUM(Expense!EC33,Expense!EC43)+Expense!EC51 -> 622 | EF28: =SUM(Expense!ED33,Expense!ED43)+Expense!ED51 -> 645 | EG28: =SUM(EC28:EF28) -> 2459 | EI28: Purchased Services and Other | EJ28: =SUM(Expense!EH33,Expense!EH43)+Expense!EH51 -> 618 | EK28: =SUM(Expense!EI33,Expense!EI43)+Expense!EI51 -> 651 | EL28: =SUM(Expense!EJ33,Expense!EJ43)+Expense!EJ51 -> 691 | EM28: =SUM(Expense!EK33,Expense!EK43)+Expense!EK51 -> 678 | EN28: =SUM(EJ28:EM28) -> 2638 | EP28: Purchased Services and Other | EQ28: =SUM(Expense!EO33,Expense!EO43)+Expense!EO51 -> 470 | ER28: =SUM(Expense!EP33,Expense!EP43)+Expense!EP51 -> 486 | ES28: =SUM(Expense!EQ33,Expense!EQ43)+Expense!EQ51 -> 429 | ET28: =SUM(Expense!ER33,Expense!ER43)+Expense!ER51 -> 429 | EU28: =SUM(EQ28:ET28) -> 1814 | EW28: Purchased Services and Other | EX28: =SUM(Expense!EV33,Expense!EV43)+Expense!EV51 -> 422 | EY28: =SUM(Expense!EW33,Expense!EW43)+Expense!EW51 -> 416 | EZ28: =SUM(Expense!EX33,Expense!EX43)+Expense!EX51 -> 420 | FA28: =SUM(Expense!EY33,Expense!EY43)+Expense!EY51 -> 399 | FB28: =SUM(EX28:FA28) -> 1657 | FD28: Purchased Services and Other | FE28: =SUM(Expense!FC33,Expense!FC43)+Expense!FC51 -> 436 | FF28: =SUM(Expense!FD33,Expense!FD43)+Expense!FD51 -> 439 | FG28: =SUM(Expense!FE33,Expense!FE43)+Expense!FE51 -> 427 | FH28: =SUM(Expense!FF33,Expense!FF43)+Expense!FF51 -> 397 | FI28: =SUM(FE28:FH28) -> 1699 | FK28: Purchased Services and Other | FL28: =SUM(Expense!FJ33,Expense!FJ43) -> 388 | FM28: =SUM(Expense!FK33,Expense!FK43) -> 378 | FN28: =SUM(Expense!FL33,Expense!FL43) -> 366 | FO28: =SUM(Expense!FM33,Expense!FM43) -> 398 | FP28: =SUM(FL28:FO28) -> 1530 | FR28: Purchased Services and Other | FS28: =SUM(Expense!FQ33,Expense!FQ43) -> 416 | FT28: =SUM(Expense!FR33,Expense!FR43) -> 432 | FU28: =SUM(Expense!FS33,Expense!FS43) -> 410 | FV28: =SUM(Expense!FT33,Expense!FT43) -> 466 | FW28: =SUM(FS28:FV28) -> 1724 | FY28: Purchased Services and Other | FZ28: =SUM(Expense!FX33,Expense!FX43) -> 462 | GA28: =SUM(Expense!FY33,Expense!FY43) -> 439 | GB28: =SUM(Expense!FZ33,Expense!FZ43) -> 454 | GC28: =SUM(Expense!GA33,Expense!GA43) -> 421 | GD28: =SUM(FZ28:GC28) -> 1776 | GF28: Purchased Services and Other | GG28: =SUM(Expense!GE33,Expense!GE43) -> 482 | GH28: =SUM(Expense!GF33,Expense!GF43) -> 489 | GI28: =SUM(Expense!GG33,Expense!GG43) -> 497 | GJ28: =SUM(Expense!GH33,Expense!GH43) -> 496 | GK28: =SUM(GG28:GJ28) -> 1964 | GM28: Purchased Services and Other | GN28: =SUM(Expense!GL33,Expense!GL43) -> 539 | GO28: =SUM(Expense!GM33,Expense!GM43) -> 470 | GP28: =SUM(Expense!GN33,Expense!GN43) -> 471 | GQ28: =SUM(Expense!GO33,Expense!GO43) -> 444 | GR28: =SUM(GN28:GQ28) -> 1924 | GT28: Purchased Services and Other | GU28: =SUM(Expense!GS33,Expense!GS43) -> 507 | GV28: =SUM(Expense!GT33,Expense!GT43) -> 513 | GW28: =SUM(Expense!GU33,Expense!GU43) -> 568 | GX28: =SUM(Expense!GV33,Expense!GV43) -> 547 | GY28: =SUM(GU28:GX28) -> 2135 | HA28: Purchased Services and Other | HB28: 477 | HC28: 444 | HD28: 500 | HE28: 442 | HF28: =SUM(HB28:HE28) -> 1863 | HH28: Purchased Services and Other | HI28: 519 | HJ28: 551 | HK28: 509 | HL28: 496 | HM28: =SUM(HI28:HL28) -> 2075 | HO28: Purchased Services and Other | HP28: 530 | HQ28: 557 | HR28: 562 | HS28: 580 | HT28: =SUM(HP28:HS28) -> 2229 | HV28: Purchased Services and Other | HW28: 542 | HX28: 550 | HY28: 525 | HZ28: 539 | IA28: =SUM(HW28:HZ28) -> 2156 | IC28: Purchased Services and Other | ID28: 507 | IE28: 560 | IF28: 576 | IG28: 632 | IH28: =SUM(ID28:IG28) -> 2275 | IJ28: Purchased Services and Other | IK28: 629 | IL28: 621 | IM28: 610 | IN28: 624 | IO28: =SUM(IK28:IN28) -> 2484 | IQ28: Purchased Services and Other | IR28: 627 | IS28: 559 | IT28: 580 | IU28: 570 | IV28: =SUM(IR28:IU28) -> 2336 | IX28: Purchased Services and Other | IY28: 550 | IZ28: 519 | JA28: 507 | JB28: 497 | JC28: =SUM(IY28:JB28) -> 2073 | JE28: Purchased Services and Other | JF28: 571 | JG28: 496 | JH28: 523 | JI28: 524 | JJ28: =SUM(JF28:JI28) -> 2114 | JL28: Purchased Services and Other | JM28: 482 | JN28: 469 | JO28: 474 | JP28: 542 | JQ28: =SUM(JM28:JP28) -> 1967 | JS28: Purchased Services and Other | JT28: 478 | JU28: 455 | JV28: 415 | JW28: 436 | JX28: =SUM(JT28:JW28) -> 1784 | JZ28: Purchased Services and Other | KA28: 454 | KB28: 407 | KC28: 378 | KD28: 445 | KE28: =SUM(KA28:KD28) -> 1684 | KG28: Purchased Services and Other | KH28: 469 | KI28: 441 | KJ28: 577 | KK28: 645 | KL28: =SUM(KH28:KK28) -> 2132 | KN28: Purchased Services and Other | KO28: 675 | KP28: 647 | KQ28: 664 | KR28: 699 | KS28: =SUM(KO28:KR28) -> 2685 | KU28: Purchased Services and Other | KV28: =688+10 -> 698 | KW28: =684+7 -> 691 | KX28: 700 | KY28: 703 | KZ28: =SUM(KV28:KY28) -> 2792 | LB28: Purchased Services and Other | LC28: =Expense!LA8 -> 721 | LD28: =Expense!LB8 -> 699 | LE28: =Expense!LC8 -> 675 | LF28: =Expense!LD8 -> 757 | LG28: =Expense!LE8 -> 2852 | LI28: Purchased Services and Other | LJ28: =Expense!LH8 -> 774 | LK28: =Expense!LI8 -> 710 | LL28: =Expense!LJ8 -> 717 | LM28: =Expense!LK8 -> 778 | LN28: =Expense!LL8 -> 2979 | LP28: Purchased Services and Other | LQ28: =Expense!LO8 -> 709.46757 | LR28: =Expense!LP8 -> 716.27032 | LS28: =Expense!LQ8 -> 737.0829 | LT28: =Expense!LR8 -> 772.07814 | LU28: =Expense!LS8 -> 2934.8989 | LW28: Purchased Services and Other | LX28: =Expense!LV8 -> 707.50579 | LY28: =Expense!LW8 -> 704.6563 | LZ28: =Expense!LX8 -> 717.06211 | MA28: =Expense!LY8 -> 754.2028 | MB28: =Expense!LZ8 -> 2883.427 | MD28: Purchased Services and Other | ME28: =Expense!MC8 -> 720.28516 | MF28: =Expense!MD8 -> 723.85858 | MG28: =Expense!ME8 -> 744.48373 | MH28: =Expense!MF8 -> 766.51904 | MI28: =Expense!MG8 -> 2955.1465
B29: Depreciation | C29: =SUM(Expense!C36,Expense!C46)+Expense!C54+Expense!C62 -> 156.04 | D29: =SUM(Expense!D36,Expense!D46)+Expense!D54+Expense!D62 -> 160.7 | E29: =SUM(Expense!E36,Expense!E46)+Expense!E54+Expense!E62 -> 158 | F29: =SUM(Expense!F36,Expense!F46)+Expense!F54+Expense!F62 -> 169 | G29: =SUM(Expense!G36,Expense!G46)+Expense!G54+Expense!G62 -> 283 | H29: =SUM(Expense!H36,Expense!H46)+Expense!H54+Expense!H62 -> 258 | I29: =SUM(Expense!I36,Expense!I46)+Expense!I54+Expense!I62 -> 295 | J29: =SUM(Expense!J36,Expense!J46)+Expense!J54+Expense!J62 -> 285 | ... M29: =SUM(Expense!M36,Expense!M46)+Expense!M54+Expense!M62 -> 452 | N29: =BV29 -> 433 | O29: =CC29 -> 456 | P29: =CJ29 -> 481 | Q29: =CQ29 -> 483 | R29: =CX29 -> 519 | S29: =DE29 -> 527 | T29: =DL29 -> 552 | U29: =DS29 -> 602 | V29: =DZ29 -> 610 | W29: =EG29 -> 598 | X29: =EN29 -> 600 | Y29: =EU29 -> 572 | Z29: =FB29 -> 613 | AA29: =FI29 -> 631 | AB29: =FP29 -> 611 | AC29: =FW29 -> 702 | AD29: =GD29 -> 818 | AE29: =GK29 -> 856 | AF29: =GR29 -> 883 | AG29: =GY29 -> 904 | AH29: =HF29 -> 905 | AI29: =HM29 -> 947 | AJ29: =HT29 -> 976 | AK29: =IA29 -> 1059 | AL29: =IH29 -> 1104 | AM29: =IO29 -> 1151 | AN29: =IV29 -> 1208 | AO29: =JC29 -> 1301 | AP29: =JJ29 -> 1315 | AQ29: =JQ29 -> 1331 | AR29: =JX29 -> 1349 | AS29: =KE29 -> 1383 | AT29: =KL29 -> 1420 | AU29: =KS29 -> 1500 | AV29: =KZ29 -> 1617 | AW29: =LG29 -> 1658 | AX29: =LN29 -> 1680 | AY29: =LU29 -> 1682 | AZ29: =MB29 -> 1726 | BA29: =MI29 -> 1782 | BQ29: Depreciation | BR29: =SUM(Expense!BP36,Expense!BP46)+Expense!BP54+Expense!BP62 -> 113 | BS29: =SUM(Expense!BQ36,Expense!BQ46)+Expense!BQ54+Expense!BQ62 -> 114 | BT29: =SUM(Expense!BR36,Expense!BR46)+Expense!BR54+Expense!BR62 -> 109 | BU29: =SUM(Expense!BS36,Expense!BS46)+Expense!BS54+Expense!BS62 -> 97 | BV29: =SUM(BR29:BU29) -> 433 | BX29: Depreciation | BY29: =SUM(Expense!BW36,Expense!BW46)+Expense!BW54+Expense!BW62 -> 114 | BZ29: =SUM(Expense!BX36,Expense!BX46)+Expense!BX54+Expense!BX62 -> 112 | CA29: =SUM(Expense!BY36,Expense!BY46)+Expense!BY54+Expense!BY62 -> 110 | CB29: =SUM(Expense!BZ36,Expense!BZ46)+Expense!BZ54+Expense!BZ62 -> 120 | CC29: =SUM(BY29:CB29) -> 456 | CE29: Depreciation | CF29: =SUM(Expense!CD36,Expense!CD46)+Expense!CD54+Expense!CD62 -> 121 | CG29: =SUM(Expense!CE36,Expense!CE46)+Expense!CE54+Expense!CE62 -> 111 | CH29: =SUM(Expense!CF36,Expense!CF46)+Expense!CF54+Expense!CF62 -> 122 | CI29: =SUM(Expense!CG36,Expense!CG46)+Expense!CG54+Expense!CG62 -> 127 | CJ29: =SUM(CF29:CI29) -> 481 | CL29: Depreciation | CM29: =SUM(Expense!CK36,Expense!CK46)+Expense!CK54+Expense!CK62 -> 119 | CN29: =SUM(Expense!CL36,Expense!CL46)+Expense!CL54+Expense!CL62 -> 123 | CO29: =SUM(Expense!CM36,Expense!CM46)+Expense!CM54+Expense!CM62 -> 124 | CP29: =SUM(Expense!CN36,Expense!CN46)+Expense!CN54+Expense!CN62 -> 117 | CQ29: =SUM(CM29:CP29) -> 483 | CS29: Depreciation | CT29: =SUM(Expense!CR36,Expense!CR46)+Expense!CR54+Expense!CR62 -> 129 | CU29: =SUM(Expense!CS36,Expense!CS46)+Expense!CS54+Expense!CS62 -> 131 | CV29: =SUM(Expense!CT36,Expense!CT46)+Expense!CT54+Expense!CT62 -> 130 | CW29: =SUM(Expense!CU36,Expense!CU46)+Expense!CU54+Expense!CU62 -> 129 | CX29: =SUM(CT29:CW29) -> 519 | CZ29: Depreciation | DA29: =SUM(Expense!CY36,Expense!CY46)+Expense!CY54+Expense!CY62 -> 131 | DB29: =SUM(Expense!CZ36,Expense!CZ46)+Expense!CZ54+Expense!CZ62 -> 132 | DC29: =SUM(Expense!DA36,Expense!DA46)+Expense!DA54+Expense!DA62 -> 132 | DD29: =SUM(Expense!DB36,Expense!DB46)+Expense!DB54+Expense!DB62 -> 132 | DE29: =SUM(DA29:DD29) -> 527 | DG29: Depreciation | DH29: =SUM(Expense!DF36,Expense!DF46)+Expense!DF54+Expense!DF62 -> 137 | DI29: =SUM(Expense!DG36,Expense!DG46)+Expense!DG54+Expense!DG62 -> 138 | DJ29: =SUM(Expense!DH36,Expense!DH46)+Expense!DH54+Expense!DH62 -> 137 | DK29: =SUM(Expense!DI36,Expense!DI46)+Expense!DI54+Expense!DI62 -> 140 | DL29: =SUM(DH29:DK29) -> 552 | DN29: Depreciation | DO29: =SUM(Expense!DM36,Expense!DM46)+Expense!DM54+Expense!DM62 -> 151 | DP29: =SUM(Expense!DN36,Expense!DN46)+Expense!DN54+Expense!DN62 -> 152 | DQ29: =SUM(Expense!DO36,Expense!DO46)+Expense!DO54+Expense!DO62 -> 147 | DR29: =SUM(Expense!DP36,Expense!DP46)+Expense!DP54+Expense!DP62 -> 152 | DS29: =SUM(DO29:DR29) -> 602 | DU29: Depreciation | DV29: =SUM(Expense!DT36,Expense!DT46)+Expense!DT54+Expense!DT62 -> 153 | DW29: =SUM(Expense!DU36,Expense!DU46)+Expense!DU54+Expense!DU62 -> 155 | DX29: =SUM(Expense!DV36,Expense!DV46)+Expense!DV54+Expense!DV62 -> 155 | DY29: =SUM(Expense!DW36,Expense!DW46)+Expense!DW54+Expense!DW62 -> 147 | DZ29: =SUM(DV29:DY29) -> 610 | EB29: Depreciation | EC29: =SUM(Expense!EA36,Expense!EA46)+Expense!EA54 -> 150 | ED29: =SUM(Expense!EB36,Expense!EB46)+Expense!EB54 -> 150 | EE29: =SUM(Expense!EC36,Expense!EC46)+Expense!EC54 -> 149 | EF29: =SUM(Expense!ED36,Expense!ED46)+Expense!ED54 -> 149 | EG29: =SUM(EC29:EF29) -> 598 | EI29: Depreciation | EJ29: =SUM(Expense!EH36,Expense!EH46)+Expense!EH54 -> 164 | EK29: =SUM(Expense!EI36,Expense!EI46)+Expense!EI54 -> 156 | EL29: =SUM(Expense!EJ36,Expense!EJ46)+Expense!EJ54 -> 155 | EM29: =SUM(Expense!EK36,Expense!EK46)+Expense!EK54 -> 125 | EN29: =SUM(EJ29:EM29) -> 600 | EP29: Depreciation | EQ29: =SUM(Expense!EO36,Expense!EO46)+Expense!EO54 -> 138 | ER29: =SUM(Expense!EP36,Expense!EP46)+Expense!EP54 -> 140 | ES29: =SUM(Expense!EQ36,Expense!EQ46)+Expense!EQ54 -> 148 | ET29: =SUM(Expense!ER36,Expense!ER46)+Expense!ER54 -> 146 | EU29: =SUM(EQ29:ET29) -> 572 | EW29: Depreciation | EX29: =SUM(Expense!EV36,Expense!EV46)+Expense!EV54 -> 155 | EY29: =SUM(Expense!EW36,Expense!EW46)+Expense!EW54 -> 153 | EZ29: =SUM(Expense!EX36,Expense!EX46)+Expense!EX54 -> 154 | FA29: =SUM(Expense!EY36,Expense!EY46)+Expense!EY54 -> 151 | FB29: =SUM(EX29:FA29) -> 613 | FD29: Depreciation | FE29: =SUM(Expense!FC36,Expense!FC46)+Expense!FC54 -> 151 | FF29: =SUM(Expense!FD36,Expense!FD46)+Expense!FD54 -> 153 | FG29: =SUM(Expense!FE36,Expense!FE46)+Expense!FE54 -> 161 | FH29: =SUM(Expense!FF36,Expense!FF46)+Expense!FF54 -> 166 | FI29: =SUM(FE29:FH29) -> 631 | FK29: Depreciation | FL29: =SUM(Expense!FJ36,Expense!FJ46) -> 153 | FM29: =SUM(Expense!FK36,Expense!FK46) -> 156 | FN29: =SUM(Expense!FL36,Expense!FL46) -> 152 | FO29: =SUM(Expense!FM36,Expense!FM46) -> 150 | FP29: =SUM(FL29:FO29) -> 611 | FR29: Depreciation | FS29: =SUM(Expense!FQ36,Expense!FQ46) -> 160 | FT29: =SUM(Expense!FR36,Expense!FR46) -> 157 | FU29: =SUM(Expense!FS36,Expense!FS46) -> 170 | FV29: =SUM(Expense!FT36,Expense!FT46) -> 215 | FW29: =SUM(FS29:FV29) -> 702 | FY29: Depreciation | FZ29: =SUM(Expense!FX36,Expense!FX46) -> 203 | GA29: =SUM(Expense!FY36,Expense!FY46) -> 203 | GB29: =SUM(Expense!FZ36,Expense!FZ46) -> 204 | GC29: =SUM(Expense!GA36,Expense!GA46) -> 208 | GD29: =SUM(FZ29:GC29) -> 818 | GF29: Depreciation | GG29: =SUM(Expense!GE36,Expense!GE46) -> 211 | GH29: =SUM(Expense!GF36,Expense!GF46) -> 216 | GI29: =SUM(Expense!GG36,Expense!GG46) -> 213 | GJ29: =SUM(Expense!GH36,Expense!GH46) -> 216 | GK29: =SUM(GG29:GJ29) -> 856 | GM29: Depreciation | GN29: =SUM(Expense!GL36,Expense!GL46) -> 221 | GO29: =SUM(Expense!GM36,Expense!GM46) -> 222 | GP29: =SUM(Expense!GN36,Expense!GN46) -> 220 | GQ29: =SUM(Expense!GO36,Expense!GO46) -> 220 | GR29: =SUM(GN29:GQ29) -> 883 | GT29: Depreciation | GU29: =SUM(Expense!GS36,Expense!GS46) -> 222 | GV29: =SUM(Expense!GT36,Expense!GT46) -> 227 | GW29: =SUM(Expense!GU36,Expense!GU46) -> 227 | GX29: =SUM(Expense!GV36,Expense!GV46) -> 228 | GY29: =SUM(GU29:GX29) -> 904 | HA29: Depreciation | HB29: 224 | HC29: 227 | HD29: 227 | HE29: 227 | HF29: =SUM(HB29:HE29) -> 905 | HH29: Depreciation | HI29: 228 | HJ29: 230 | HK29: 232 | HL29: 257 | HM29: =SUM(HI29:HL29) -> 947 | HO29: Depreciation | HP29: 243 | HQ29: 246 | HR29: 251 | HS29: 236 | HT29: =SUM(HP29:HS29) -> 976 | HV29: Depreciation | HW29: 257 | HX29: 263 | HY29: 268 | HZ29: 271 | IA29: =SUM(HW29:HZ29) -> 1059 | IC29: Depreciation | ID29: 270 | IE29: 276 | IF29: 277 | IG29: 281 | IH29: =SUM(ID29:IG29) -> 1104 | IJ29: Depreciation | IK29: 283 | IL29: 287 | IM29: 291 | IN29: 290 | IO29: =SUM(IK29:IN29) -> 1151 | IQ29: Depreciation | IR29: 295 | IS29: 299 | IT29: 302 | IU29: 312 | IV29: =SUM(IR29:IU29) -> 1208 | IX29: Depreciation | IY29: 313 | IZ29: 319 | JA29: 321 | JB29: 348 | JC29: =SUM(IY29:JB29) -> 1301 | JE29: Depreciation | JF29: 320 | JG29: 327 | JH29: 331 | JI29: 337 | JJ29: =SUM(JF29:JI29) -> 1315 | JL29: Depreciation | JM29: 323 | JN29: 329 | JO29: 334 | JP29: 345 | JQ29: =SUM(JM29:JP29) -> 1331 | JS29: Depreciation | JT29: 330 | JU29: 337 | JV29: 338 | JW29: 344 | JX29: =SUM(JT29:JW29) -> 1349 | JZ29: Depreciation | KA29: 344 | KB29: 344 | KC29: 348 | KD29: 347 | KE29: =SUM(KA29:KD29) -> 1383 | KG29: Depreciation | KH29: 345 | KI29: 348 | KJ29: 367 | KK29: 360 | KL29: =SUM(KH29:KK29) -> 1420 | KN29: Depreciation | KO29: 360 | KP29: 369 | KQ29: 378 | KR29: 393 | KS29: =SUM(KO29:KR29) -> 1500 | KU29: Depreciation | KV29: 393 | KW29: =402+2 -> 404 | KX29: 403 | KY29: 417 | KZ29: =SUM(KV29:KY29) -> 1617 | LB29: Depreciation | LC29: =Expense!LA9 -> 410 | LD29: =Expense!LB9 -> 410 | LE29: =Expense!LC9 -> 416 | LF29: =Expense!LD9 -> 422 | LG29: =Expense!LE9 -> 1658 | LI29: Depreciation | LJ29: =Expense!LH9 -> 425 | LK29: =Expense!LI9 -> 427 | LL29: =Expense!LJ9 -> 424 | LM29: =Expense!LK9 -> 404 | LN29: =Expense!LL9 -> 1680 | LP29: Depreciation | LQ29: =Expense!LO9 -> 419 | LR29: =Expense!LP9 -> 420 | LS29: =Expense!LQ9 -> 421 | LT29: =Expense!LR9 -> 422 | LU29: =Expense!LS9 -> 1682 | LW29: Depreciation | LX29: =Expense!LV9 -> 427 | LY29: =Expense!LW9 -> 430 | LZ29: =Expense!LX9 -> 433 | MA29: =Expense!LY9 -> 436 | MB29: =Expense!LZ9 -> 1726 | MD29: Depreciation | ME29: =Expense!MC9 -> 441 | MF29: =Expense!MD9 -> 444 | MG29: =Expense!ME9 -> 447 | MH29: =Expense!MF9 -> 450 | MI29: =Expense!MG9 -> 1782
B30: Fuel | C30: =SUM(Expense!C37,Expense!C47)+Expense!C55+Expense!C63 -> 228.691 | D30: =SUM(Expense!D37,Expense!D47)+Expense!D55+Expense!D63 -> 334 | E30: =SUM(Expense!E37,Expense!E47)+Expense!E55+Expense!E63 -> 462.2 | F30: =SUM(Expense!F37,Expense!F47)+Expense!F55+Expense!F63 -> 554.9 | G30: =SUM(Expense!G37,Expense!G47)+Expense!G55+Expense!G63 -> 446 | H30: =SUM(Expense!H37,Expense!H47)+Expense!H55+Expense!H63 -> 392 | I30: =SUM(Expense!I37,Expense!I47)+Expense!I55+Expense!I63 -> 447 | J30: =SUM(Expense!J37,Expense!J47)+Expense!J55+Expense!J63 -> 405 | ... M30: =SUM(Expense!M37,Expense!M47)+Expense!M55+Expense!M63 -> 351 | N30: =BV30 -> 368 | O30: =CC30 -> 421 | P30: =CJ30 -> 444 | Q30: =CQ30 -> 398 | R30: =CX30 -> 377 | S30: =DE30 -> 384 | T30: =DL30 -> 435 | U30: =DS30 -> 561 | V30: =DZ30 -> 554 | W30: =EG30 -> 393 | X30: =EN30 -> 472 | Y30: =EU30 -> 650 | Z30: =FB30 -> 585 | AA30: =FI30 -> 515 | AB30: =FP30 -> 566 | AC30: =FW30 -> 656 | AD30: =GD30 -> 783 | AE30: =GK30 -> 1112 | AF30: =GR30 -> 1312 | AG30: =GY30 -> 1817 | AH30: =HF30 -> 849 | AI30: =HM30 -> 1212 | AJ30: =HT30 -> 1668 | AK30: =IA30 -> 1672 | AL30: =IH30 -> 1656 | AM30: =IO30 -> 1616 | AN30: =IV30 -> 957 | AO30: =JC30 -> 713 | AP30: =JJ30 -> 864 | AQ30: =JQ30 -> 1046 | AR30: =JX30 -> 906 | AS30: =KE30 -> 541 | AT30: =KL30 -> 913 | AU30: =KS30 -> 1626 | AV30: =KZ30 -> 1377 | AW30: =LG30 -> 1168 | AX30: =LN30 -> 1095 | AY30: =LU30 -> 1058.6546 | AZ30: =MB30 -> 1078.9382 | BA30: =MI30 -> 1102.4666 | BQ30: Fuel | BR30: =SUM(Expense!BP37,Expense!BP47)+Expense!BP55+Expense!BP63 -> 89 | BS30: =SUM(Expense!BQ37,Expense!BQ47)+Expense!BQ55+Expense!BQ63 -> 92 | BT30: =SUM(Expense!BR37,Expense!BR47)+Expense!BR55+Expense!BR63 -> 83 | BU30: =SUM(Expense!BS37,Expense!BS47)+Expense!BS55+Expense!BS63 -> 104 | BV30: =SUM(BR30:BU30) -> 368 | BX30: Fuel | BY30: =SUM(Expense!BW37,Expense!BW47)+Expense!BW55+Expense!BW63 -> 111 | BZ30: =SUM(Expense!BX37,Expense!BX47)+Expense!BX55+Expense!BX63 -> 94 | CA30: =SUM(Expense!BY37,Expense!BY47)+Expense!BY55+Expense!BY63 -> 94 | CB30: =SUM(Expense!BZ37,Expense!BZ47)+Expense!BZ55+Expense!BZ63 -> 122 | CC30: =SUM(BY30:CB30) -> 421 | CE30: Fuel | CF30: =SUM(Expense!CD37,Expense!CD47)+Expense!CD55+Expense!CD63 -> 131 | CG30: =SUM(Expense!CE37,Expense!CE47)+Expense!CE55+Expense!CE63 -> 96 | CH30: =SUM(Expense!CF37,Expense!CF47)+Expense!CF55+Expense!CF63 -> 98 | CI30: =SUM(Expense!CG37,Expense!CG47)+Expense!CG55+Expense!CG63 -> 119 | CJ30: =SUM(CF30:CI30) -> 444 | CL30: Fuel | CM30: =SUM(Expense!CK37,Expense!CK47)+Expense!CK55+Expense!CK63 -> 93 | CN30: =SUM(Expense!CL37,Expense!CL47)+Expense!CL55+Expense!CL63 -> 93 | CO30: =SUM(Expense!CM37,Expense!CM47)+Expense!CM55+Expense!CM63 -> 99 | CP30: =SUM(Expense!CN37,Expense!CN47)+Expense!CN55+Expense!CN63 -> 113 | CQ30: =SUM(CM30:CP30) -> 398 | CS30: Fuel | CT30: =SUM(Expense!CR37,Expense!CR47)+Expense!CR55+Expense!CR63 -> 100 | CU30: =SUM(Expense!CS37,Expense!CS47)+Expense!CS55+Expense!CS63 -> 98 | CV30: =SUM(Expense!CT37,Expense!CT47)+Expense!CT55+Expense!CT63 -> 82 | CW30: =SUM(Expense!CU37,Expense!CU47)+Expense!CU55+Expense!CU63 -> 97 | CX30: =SUM(CT30:CW30) -> 377 | CZ30: Fuel | DA30: =SUM(Expense!CY37,Expense!CY47)+Expense!CY55+Expense!CY63 -> 92 | DB30: =SUM(Expense!CZ37,Expense!CZ47)+Expense!CZ55+Expense!CZ63 -> 91 | DC30: =SUM(Expense!DA37,Expense!DA47)+Expense!DA55+Expense!DA63 -> 98 | DD30: =SUM(Expense!DB37,Expense!DB47)+Expense!DB55+Expense!DB63 -> 103 | DE30: =SUM(DA30:DD30) -> 384 | DG30: Fuel | DH30: =SUM(Expense!DF37,Expense!DF47)+Expense!DF55+Expense!DF63 -> 108 | DI30: =SUM(Expense!DG37,Expense!DG47)+Expense!DG55+Expense!DG63 -> 110 | DJ30: =SUM(Expense!DH37,Expense!DH47)+Expense!DH55+Expense!DH63 -> 106 | DK30: =SUM(Expense!DI37,Expense!DI47)+Expense!DI55+Expense!DI63 -> 111 | DL30: =SUM(DH30:DK30) -> 435 | DN30: Fuel | DO30: =SUM(Expense!DM37,Expense!DM47)+Expense!DM55+Expense!DM63 -> 132 | DP30: =SUM(Expense!DN37,Expense!DN47)+Expense!DN55+Expense!DN63 -> 139 | DQ30: =SUM(Expense!DO37,Expense!DO47)+Expense!DO55+Expense!DO63 -> 125 | DR30: =SUM(Expense!DP37,Expense!DP47)+Expense!DP55+Expense!DP63 -> 165 | DS30: =SUM(DO30:DR30) -> 561 | DU30: Fuel | DV30: =SUM(Expense!DT37,Expense!DT47)+Expense!DT55+Expense!DT63 -> 153 | DW30: =SUM(Expense!DU37,Expense!DU47)+Expense!DU55+Expense!DU63 -> 131 | DX30: =SUM(Expense!DV37,Expense!DV47)+Expense!DV55+Expense!DV63 -> 126 | DY30: =SUM(Expense!DW37,Expense!DW47)+Expense!DW55+Expense!DW63 -> 144 | DZ30: =SUM(DV30:DY30) -> 554 | EB30: Fuel | EC30: =SUM(Expense!EA37,Expense!EA47)+Expense!EA55 -> 109 | ED30: =SUM(Expense!EB37,Expense!EB47)+Expense!EB55 -> 97 | EE30: =SUM(Expense!EC37,Expense!EC47)+Expense!EC55 -> 89 | EF30: =SUM(Expense!ED37,Expense!ED47)+Expense!ED55 -> 98 | EG30: =SUM(EC30:EF30) -> 393 | EI30: Fuel | EJ30: =SUM(Expense!EH37,Expense!EH47)+Expense!EH55 -> 83 | EK30: =SUM(Expense!EI37,Expense!EI47)+Expense!EI55 -> 98 | EL30: =SUM(Expense!EJ37,Expense!EJ47)+Expense!EJ55 -> 127 | EM30: =SUM(Expense!EK37,Expense!EK47)+Expense!EK55 -> 164 | EN30: =SUM(EJ30:EM30) -> 472 | EP30: Fuel | EQ30: =SUM(Expense!EO37,Expense!EO47)+Expense!EO55 -> 156 | ER30: =SUM(Expense!EP37,Expense!EP47)+Expense!EP55 -> 151 | ES30: =SUM(Expense!EQ37,Expense!EQ47)+Expense!EQ55 -> 156 | ET30: =SUM(Expense!ER37,Expense!ER47)+Expense!ER55 -> 187 | EU30: =SUM(EQ30:ET30) -> 650 | EW30: Fuel | EX30: =SUM(Expense!EV37,Expense!EV47)+Expense!EV55 -> 170 | EY30: =SUM(Expense!EW37,Expense!EW47)+Expense!EW55 -> 146 | EZ30: =SUM(Expense!EX37,Expense!EX47)+Expense!EX55 -> 138 | FA30: =SUM(Expense!EY37,Expense!EY47)+Expense!EY55 -> 131 | FB30: =SUM(EX30:FA30) -> 585 | FD30: Fuel | FE30: =SUM(Expense!FC37,Expense!FC47)+Expense!FC55 -> 116 | FF30: =SUM(Expense!FD37,Expense!FD47)+Expense!FD55 -> 128 | FG30: =SUM(Expense!FE37,Expense!FE47)+Expense!FE55 -> 128 | FH30: =SUM(Expense!FF37,Expense!FF47)+Expense!FF55 -> 143 | FI30: =SUM(FE30:FH30) -> 515 | FK30: Fuel | FL30: =SUM(Expense!FJ37,Expense!FJ47) -> 158 | FM30: =SUM(Expense!FK37,Expense!FK47) -> 136 | FN30: =SUM(Expense!FL37,Expense!FL47) -> 132 | FO30: =SUM(Expense!FM37,Expense!FM47) -> 140 | FP30: =SUM(FL30:FO30) -> 566 | FR30: Fuel | FS30: =SUM(Expense!FQ37,Expense!FQ47) -> 154 | FT30: =SUM(Expense!FR37,Expense!FR47) -> 151 | FU30: =SUM(Expense!FS37,Expense!FS47) -> 162 | FV30: =SUM(Expense!FT37,Expense!FT47) -> 189 | FW30: =SUM(FS30:FV30) -> 656 | FY30: Fuel | FZ30: =SUM(Expense!FX37,Expense!FX47) -> 179 | GA30: =SUM(Expense!FY37,Expense!FY47) -> 176 | GB30: =SUM(Expense!FZ37,Expense!FZ47) -> 188 | GC30: =SUM(Expense!GA37,Expense!GA47) -> 240 | GD30: =SUM(FZ30:GC30) -> 783 | GF30: Fuel | GG30: =SUM(Expense!GE37,Expense!GE47) -> 253 | GH30: =SUM(Expense!GF37,Expense!GF47) -> 288 | GI30: =SUM(Expense!GG37,Expense!GG47) -> 300 | GJ30: =SUM(Expense!GH37,Expense!GH47) -> 271 | GK30: =SUM(GG30:GJ30) -> 1112 | GM30: Fuel | GN30: =SUM(Expense!GL37,Expense!GL47) -> 284 | GO30: =SUM(Expense!GM37,Expense!GM47) -> 316 | GP30: =SUM(Expense!GN37,Expense!GN47) -> 330 | GQ30: =SUM(Expense!GO37,Expense!GO47) -> 382 | GR30: =SUM(GN30:GQ30) -> 1312 | GT30: Fuel | GU30: =SUM(Expense!GS37,Expense!GS47) -> 441 | GV30: =SUM(Expense!GT37,Expense!GT47) -> 537 | GW30: =SUM(Expense!GU37,Expense!GU47) -> 508 | GX30: =SUM(Expense!GV37,Expense!GV47) -> 331 | GY30: =SUM(GU30:GX30) -> 1817 | HA30: Fuel | HB30: 191 | HC30: 185 | HD30: 223 | HE30: 250 | HF30: =SUM(HB30:HE30) -> 849 | HH30: Fuel | HI30: 283 | HJ30: 304 | HK30: 279 | HL30: 346 | HM30: =SUM(HI30:HL30) -> 1212 | HO30: Fuel | HP30: 402 | HQ30: 431 | HR30: 412 | HS30: 423 | HT30: =SUM(HP30:HS30) -> 1668 | HV30: Fuel | HW30: 444 | HX30: 410 | HY30: 397 | HZ30: 421 | IA30: =SUM(HW30:HZ30) -> 1672 | IC30: Fuel | ID30: 444 | IE30: 397 | IF30: 407 | IG30: 408 | IH30: =SUM(ID30:IG30) -> 1656 | IJ30: Fuel | IK30: 446 | IL30: 416 | IM30: 393 | IN30: 361 | IO30: =SUM(IK30:IN30) -> 1616 | IQ30: Fuel | IR30: 270 | IS30: 263 | IT30: 223 | IU30: 201 | IV30: =SUM(IR30:IU30) -> 957 | IX30: Fuel | IY30: 150 | IZ30: 172 | JA30: 174 | JB30: 217 | JC30: =SUM(IY30:JB30) -> 713 | JE30: Fuel | JF30: 218 | JG30: 198 | JH30: 205 | JI30: 243 | JJ30: =SUM(JF30:JI30) -> 864 | JL30: Fuel | JM30: 255 | JN30: 270 | JO30: 268 | JP30: 253 | JQ30: =SUM(JM30:JP30) -> 1046 | JS30: Fuel | JT30: 233 | JU30: 234 | JV30: 223 | JW30: 216 | JX30: =SUM(JT30:JW30) -> 906 | JZ30: Fuel | KA30: 192 | KB30: 91 | KC30: 119 | KD30: 139 | KE30: =SUM(KA30:KD30) -> 541 | KG30: Fuel | KH30: 190 | KI30: 194 | KJ30: 247 | KK30: 282 | KL30: =SUM(KH30:KK30) -> 913 | KN30: Fuel | KO30: 331 | KP30: 446 | KQ30: 438 | KR30: 411 | KS30: =SUM(KO30:KR30) -> 1626 | KU30: Fuel | KV30: 364 | KW30: 312 | KX30: 349 | KY30: 352 | KZ30: =SUM(KV30:KY30) -> 1377 | LB30: Fuel | LC30: =Expense!LA10 -> 325 | LD30: =Expense!LB10 -> 301 | LE30: =Expense!LC10 -> 276 | LF30: =Expense!LD10 -> 266 | LG30: =Expense!LE10 -> 1168 | LI30: Fuel | LJ30: =Expense!LH10 -> 275 | LK30: =Expense!LI10 -> 269 | LL30: =Expense!LJ10 -> 281 | LM30: =Expense!LK10 -> 270 | LN30: =Expense!LL10 -> 1095 | LP30: Fuel | LQ30: =Expense!LO10 -> 261.72023 | LR30: =Expense!LP10 -> 270.5492 | LS30: =Expense!LQ10 -> 264.06492 | LT30: =Expense!LR10 -> 262.32023 | LU30: =Expense!LS10 -> 1058.6546 | LW30: Fuel | LX30: =Expense!LV10 -> 266.75393 | LY30: =Expense!LW10 -> 275.88522 | LZ30: =Expense!LX10 -> 269.03657 | MA30: =Expense!LY10 -> 267.26249 | MB30: =Expense!LZ10 -> 1078.9382 | MD30: Fuel | ME30: =Expense!MC10 -> 272.41536 | MF30: =Expense!MD10 -> 281.65835 | MG30: =Expense!ME10 -> 275.16253 | MH30: =Expense!MF10 -> 273.23038 | MI30: =Expense!MG10 -> 1102.4666
B31: Equipment and other rents | C31: =SUM(Expense!C34,Expense!C44)+Expense!C52+Expense!C61 -> 0 | D31: =SUM(Expense!D34,Expense!D44)+Expense!D52+Expense!D61 -> 0 | E31: =SUM(Expense!E34,Expense!E44)+Expense!E52+Expense!E61 -> 0 | F31: =SUM(Expense!F34,Expense!F44)+Expense!F52+Expense!F61 -> 0 | G31: =SUM(Expense!G34,Expense!G44)+Expense!G52+Expense!G61 -> 415 | H31: =SUM(Expense!H34,Expense!H44)+Expense!H52+Expense!H61 -> 497 | I31: =SUM(Expense!I34,Expense!I44)+Expense!I52+Expense!I61 -> 514 | J31: =SUM(Expense!J34,Expense!J44)+Expense!J52+Expense!J61 -> 509 | ... M31: =SUM(Expense!M34,Expense!M44)+Expense!M52+Expense!M61 -> 806 | N31: =BV31 -> 875 | O31: =CC31 -> 914 | P31: =CJ31 -> 1028 | Q31: =CQ31 -> 1029 | R31: =CX31 -> 1011 | S31: =DE31 -> 1060 | T31: =DL31 -> 1101 | U31: =DS31 -> 1103 | V31: =DZ31 -> 1066 | W31: =EG31 -> 1056 | X31: =EN31 -> 1165 | Y31: =EU31 -> 718 | Z31: =FB31 -> 625 | AA31: =FI31 -> 610 | AB31: =FP31 -> 562 | AC31: =FW31 -> 570 | AD31: =GD31 -> 533 | AE31: =GK31 -> 512 | AF31: =GR31 -> 451 | AG31: =GY31 -> 425 | AH31: =HF31 -> 391 | AI31: =HM31 -> 374 | AJ31: =HT31 -> 379 | AK31: =IA31 -> 392 | AL31: =IH31 -> 380 | AM31: =IO31 -> 428 | AN31: =IV31 -> 436 | AO31: =JC31 -> 447 | AP31: =JJ31 -> 429 | AQ31: =JQ31 -> 395 | AR31: =JX31 -> 408 | AS31: =KE31 -> 338 | AT31: =KL31 -> 364 | AU31: =KS31 -> 396 | AV31: =KZ31 -> 354 | AW31: =LG31 -> 355 | AX31: =LN31 -> 357 | AY31: =LU31 -> 360.36708 | AZ31: =MB31 -> 356.65678 | BA31: =MI31 -> 364.51866 | BQ31: Equipment and other rents | BR31: =SUM(Expense!BP34,Expense!BP44)+Expense!BP52+Expense!BP61 -> 204 | BS31: =SUM(Expense!BQ34,Expense!BQ44)+Expense!BQ52+Expense!BQ61 -> 221 | BT31: =SUM(Expense!BR34,Expense!BR44)+Expense!BR52+Expense!BR61 -> 221 | BU31: =SUM(Expense!BS34,Expense!BS44)+Expense!BS52+Expense!BS61 -> 229 | BV31: =SUM(BR31:BU31) -> 875 | BX31: Equipment and other rents | BY31: =SUM(Expense!BW34,Expense!BW44)+Expense!BW52+Expense!BW61 -> 216 | BZ31: =SUM(Expense!BX34,Expense!BX44)+Expense!BX52+Expense!BX61 -> 231 | CA31: =SUM(Expense!BY34,Expense!BY44)+Expense!BY52+Expense!BY61 -> 217 | CB31: =SUM(Expense!BZ34,Expense!BZ44)+Expense!BZ52+Expense!BZ61 -> 250 | CC31: =SUM(BY31:CB31) -> 914 | CE31: Equipment and other rents | CF31: =SUM(Expense!CD34,Expense!CD44)+Expense!CD52+Expense!CD61 -> 248 | CG31: =SUM(Expense!CE34,Expense!CE44)+Expense!CE52+Expense!CE61 -> 257 | CH31: =SUM(Expense!CF34,Expense!CF44)+Expense!CF52+Expense!CF61 -> 256 | CI31: =SUM(Expense!CG34,Expense!CG44)+Expense!CG52+Expense!CG61 -> 267 | CJ31: =SUM(CF31:CI31) -> 1028 | CL31: Equipment and other rents | CM31: =SUM(Expense!CK34,Expense!CK44)+Expense!CK52+Expense!CK61 -> 258 | CN31: =SUM(Expense!CL34,Expense!CL44)+Expense!CL52+Expense!CL61 -> 251 | CO31: =SUM(Expense!CM34,Expense!CM44)+Expense!CM52+Expense!CM61 -> 257 | CP31: =SUM(Expense!CN34,Expense!CN44)+Expense!CN52+Expense!CN61 -> 263 | CQ31: =SUM(CM31:CP31) -> 1029 | CS31: Equipment and other rents | CT31: =SUM(Expense!CR34,Expense!CR44)+Expense!CR52+Expense!CR61 -> 261 | CU31: =SUM(Expense!CS34,Expense!CS44)+Expense!CS52+Expense!CS61 -> 255 | CV31: =SUM(Expense!CT34,Expense!CT44)+Expense!CT52+Expense!CT61 -> 254 | CW31: =SUM(Expense!CU34,Expense!CU44)+Expense!CU52+Expense!CU61 -> 241 | CX31: =SUM(CT31:CW31) -> 1011 | CZ31: Equipment and other rents | DA31: =SUM(Expense!CY34,Expense!CY44)+Expense!CY52+Expense!CY61 -> 263 | DB31: =SUM(Expense!CZ34,Expense!CZ44)+Expense!CZ52+Expense!CZ61 -> 271 | DC31: =SUM(Expense!DA34,Expense!DA44)+Expense!DA52+Expense!DA61 -> 273 | DD31: =SUM(Expense!DB34,Expense!DB44)+Expense!DB52+Expense!DB61 -> 253 | DE31: =SUM(DA31:DD31) -> 1060 | DG31: Equipment and other rents | DH31: =SUM(Expense!DF34,Expense!DF44)+Expense!DF52+Expense!DF61 -> 272 | DI31: =SUM(Expense!DG34,Expense!DG44)+Expense!DG52+Expense!DG61 -> 266 | DJ31: =SUM(Expense!DH34,Expense!DH44)+Expense!DH52+Expense!DH61 -> 270 | DK31: =SUM(Expense!DI34,Expense!DI44)+Expense!DI52+Expense!DI61 -> 293 | DL31: =SUM(DH31:DK31) -> 1101 | DN31: Equipment and other rents | DO31: =SUM(Expense!DM34,Expense!DM44)+Expense!DM52+Expense!DM61 -> 280 | DP31: =SUM(Expense!DN34,Expense!DN44)+Expense!DN52+Expense!DN61 -> 277 | DQ31: =SUM(Expense!DO34,Expense!DO44)+Expense!DO52+Expense!DO61 -> 271 | DR31: =SUM(Expense!DP34,Expense!DP44)+Expense!DP52+Expense!DP61 -> 275 | DS31: =SUM(DO31:DR31) -> 1103 | DU31: Equipment and other rents | DV31: =SUM(Expense!DT34,Expense!DT44)+Expense!DT52+Expense!DT61 -> 274 | DW31: =SUM(Expense!DU34,Expense!DU44)+Expense!DU52+Expense!DU61 -> 263 | DX31: =SUM(Expense!DV34,Expense!DV44)+Expense!DV52+Expense!DV61 -> 264 | DY31: =SUM(Expense!DW34,Expense!DW44)+Expense!DW52+Expense!DW61 -> 265 | DZ31: =SUM(DV31:DY31) -> 1066 | EB31: Equipment and other rents | EC31: =SUM(Expense!EA34,Expense!EA44)+Expense!EA52 -> 254 | ED31: =SUM(Expense!EB34,Expense!EB44)+Expense!EB52 -> 264 | EE31: =SUM(Expense!EC34,Expense!EC44)+Expense!EC52 -> 264 | EF31: =SUM(Expense!ED34,Expense!ED44)+Expense!ED52 -> 274 | EG31: =SUM(EC31:EF31) -> 1056 | EI31: Equipment and other rents | EJ31: =SUM(Expense!EH34,Expense!EH44)+Expense!EH52 -> 294 | EK31: =SUM(Expense!EI34,Expense!EI44)+Expense!EI52 -> 268 | EL31: =SUM(Expense!EJ34,Expense!EJ44)+Expense!EJ52 -> 300 | EM31: =SUM(Expense!EK34,Expense!EK44)+Expense!EK52 -> 303 | EN31: =SUM(EJ31:EM31) -> 1165 | EP31: Equipment and other rents | EQ31: =SUM(Expense!EO34,Expense!EO44)+Expense!EO52 -> 188 | ER31: =SUM(Expense!EP34,Expense!EP44)+Expense!EP52 -> 188 | ES31: =SUM(Expense!EQ34,Expense!EQ44)+Expense!EQ52 -> 176 | ET31: =SUM(Expense!ER34,Expense!ER44)+Expense!ER52 -> 166 | EU31: =SUM(EQ31:ET31) -> 718 | EW31: Equipment and other rents | EX31: =SUM(Expense!EV34,Expense!EV44)+Expense!EV52 -> 163 | EY31: =SUM(Expense!EW34,Expense!EW44)+Expense!EW52 -> 159 | EZ31: =SUM(Expense!EX34,Expense!EX44)+Expense!EX52 -> 155 | FA31: =SUM(Expense!EY34,Expense!EY44)+Expense!EY52 -> 148 | FB31: =SUM(EX31:FA31) -> 625 | FD31: Equipment and other rents | FE31: =SUM(Expense!FC34,Expense!FC44)+Expense!FC52 -> 150 | FF31: =SUM(Expense!FD34,Expense!FD44)+Expense!FD52 -> 155 | FG31: =SUM(Expense!FE34,Expense!FE44)+Expense!FE52 -> 164 | FH31: =SUM(Expense!FF34,Expense!FF44)+Expense!FF52 -> 141 | FI31: =SUM(FE31:FH31) -> 610 | FK31: Equipment and other rents | FL31: =SUM(Expense!FJ34,Expense!FJ44) -> 138 | FM31: =SUM(Expense!FK34,Expense!FK44) -> 131 | FN31: =SUM(Expense!FL34,Expense!FL44) -> 147 | FO31: =SUM(Expense!FM34,Expense!FM44) -> 146 | FP31: =SUM(FL31:FO31) -> 562 | FR31: Equipment and other rents | FS31: =SUM(Expense!FQ34,Expense!FQ44) -> 140 | FT31: =SUM(Expense!FR34,Expense!FR44) -> 144 | FU31: =SUM(Expense!FS34,Expense!FS44) -> 140 | FV31: =SUM(Expense!FT34,Expense!FT44) -> 146 | FW31: =SUM(FS31:FV31) -> 570 | FY31: Equipment and other rents | FZ31: =SUM(Expense!FX34,Expense!FX44) -> 135 | GA31: =SUM(Expense!FY34,Expense!FY44) -> 137 | GB31: =SUM(Expense!FZ34,Expense!FZ44) -> 129 | GC31: =SUM(Expense!GA34,Expense!GA44) -> 132 | GD31: =SUM(FZ31:GC31) -> 533 | GF31: Equipment and other rents | GG31: =SUM(Expense!GE34,Expense!GE44) -> 124 | GH31: =SUM(Expense!GF34,Expense!GF44) -> 132 | GI31: =SUM(Expense!GG34,Expense!GG44) -> 135 | GJ31: =SUM(Expense!GH34,Expense!GH44) -> 121 | GK31: =SUM(GG31:GJ31) -> 512 | GM31: Equipment and other rents | GN31: =SUM(Expense!GL34,Expense!GL44) -> 120 | GO31: =SUM(Expense!GM34,Expense!GM44) -> 107 | GP31: =SUM(Expense!GN34,Expense!GN44) -> 114 | GQ31: =SUM(Expense!GO34,Expense!GO44) -> 110 | GR31: =SUM(GN31:GQ31) -> 451 | GT31: Equipment and other rents | GU31: =SUM(Expense!GS34,Expense!GS44) -> 111 | GV31: =SUM(Expense!GT34,Expense!GT44) -> 112 | GW31: =SUM(Expense!GU34,Expense!GU44) -> 106 | GX31: =SUM(Expense!GV34,Expense!GV44) -> 96 | GY31: =SUM(GU31:GX31) -> 425 | HA31: Equipment and other rents | HB31: 113 | HC31: 98 | HD31: 92 | HE31: 88 | HF31: =SUM(HB31:HE31) -> 391 | HH31: Equipment and other rents | HI31: 100 | HJ31: 89 | HK31: 90 | HL31: 95 | HM31: =SUM(HI31:HL31) -> 374 | HO31: Equipment and other rents | HP31: 97 | HQ31: 95 | HR31: 95 | HS31: 92 | HT31: =SUM(HP31:HS31) -> 379 | HV31: Equipment and other rents | HW31: 97 | HX31: 102 | HY31: 96 | HZ31: 97 | IA31: =SUM(HW31:HZ31) -> 392 | IC31: Equipment and other rents | ID31: 95 | IE31: 96 | IF31: 94 | IG31: 95 | IH31: =SUM(ID31:IG31) -> 380 | IJ31: Equipment and other rents | IK31: 101 | IL31: 114 | IM31: 106 | IN31: 107 | IO31: =SUM(IK31:IN31) -> 428 | IQ31: Equipment and other rents | IR31: 113 | IS31: 101 | IT31: 114 | IU31: 108 | IV31: =SUM(IR31:IU31) -> 436 | IX31: Equipment and other rents | IY31: 105 | IZ31: 105 | JA31: 105 | JB31: 132 | JC31: =SUM(IY31:JB31) -> 447 | JE31: Equipment and other rents | JF31: 99 | JG31: 105 | JH31: 109 | JI31: 116 | JJ31: =SUM(JF31:JI31) -> 429 | JL31: Equipment and other rents | JM31: 101 | JN31: 112 | JO31: 89 | JP31: 93 | JQ31: =SUM(JM31:JP31) -> 395 | JS31: Equipment and other rents | JT31: 100 | JU31: 103 | JV31: 104 | JW31: 101 | JX31: =SUM(JT31:JW31) -> 408 | JZ31: Equipment and other rents | KA31: 81 | KB31: 78 | KC31: 88 | KD31: 91 | KE31: =SUM(KA31:KD31) -> 338 | KG31: Equipment and other rents | KH31: 88 | KI31: 87 | KJ31: 94 | KK31: 95 | KL31: =SUM(KH31:KK31) -> 364 | KN31: Equipment and other rents | KO31: 100 | KP31: 95 | KQ31: 104 | KR31: 97 | KS31: =SUM(KO31:KR31) -> 396 | KU31: Equipment and other rents | KV31: 82 | KW31: 90 | KX31: 94 | KY31: 88 | KZ31: =SUM(KV31:KY31) -> 354 | LB31: Equipment and other rents | LC31: =Expense!LA11 -> 84 | LD31: =Expense!LB11 -> 85 | LE31: =Expense!LC11 -> 91 | LF31: =Expense!LD11 -> 95 | LG31: =Expense!LE11 -> 355 | LI31: Equipment and other rents | LJ31: =Expense!LH11 -> 87 | LK31: =Expense!LI11 -> 94 | LL31: =Expense!LJ11 -> 86 | LM31: =Expense!LK11 -> 90 | LN31: =Expense!LL11 -> 357 | LP31: Equipment and other rents | LQ31: =Expense!LO11 -> 89.981253 | LR31: =Expense!LP11 -> 85.443413 | LS31: =Expense!LQ11 -> 88.89442 | LT31: =Expense!LR11 -> 96.047998 | LU31: =Expense!LS11 -> 360.36708 | LW31: Equipment and other rents | LX31: =Expense!LV11 -> 87.077636 | LY31: =Expense!LW11 -> 87.605918 | LZ31: =Expense!LX11 -> 89.148262 | MA31: =Expense!LY11 -> 92.82496 | MB31: =Expense!LZ11 -> 356.65678 | MD31: Equipment and other rents | ME31: =Expense!MC11 -> 87.192414 | MF31: =Expense!MD11 -> 91.476634 | MG31: =Expense!ME11 -> 93.060466 | MH31: =Expense!MF11 -> 92.789147 | MI31: =Expense!MG11 -> 364.51866
B32: Inland transportation | C32: =SUM(Expense!C45,Expense!C35)+Expense!C53 -> 0 | D32: =SUM(Expense!D45,Expense!D35)+Expense!D53 -> 0 | E32: =SUM(Expense!E45,Expense!E35)+Expense!E53 -> 0 | F32: =SUM(Expense!F45,Expense!F35)+Expense!F53 -> 0 | G32: =SUM(Expense!G45,Expense!G35)+Expense!G53 -> 0 | H32: =SUM(Expense!H45,Expense!H35)+Expense!H53 -> 0 | I32: =SUM(Expense!I45,Expense!I35)+Expense!I53 -> 0 | J32: =SUM(Expense!J45,Expense!J35)+Expense!J53 -> 0 | ... M32: =SUM(Expense!M45,Expense!M35)+Expense!M53 -> 0 | N32: =BV32 -> 189 | O32: =CC32 -> 823 | P32: =CJ32 -> 964 | Q32: =CQ32 -> 1059 | R32: =CX32 -> 1083 | S32: =DE32 -> 1229 | T32: =DL32 -> 1141 | U32: =DS32 -> 954 | V32: =DZ32 -> 955 | W32: =EG32 -> 923 | X32: =EN32 -> 935 | Y32: =EU32 -> 377 | Z32: =FB32 -> 354 | AA32: =FI32 -> 411 | AB32: =FP32 -> 298 | AC32: =FW32 -> 293 | AD32: =GD32 -> 230 | AE32: =GK32 -> 242 | AF32: =GR32 -> 240 | AG32: =GY32 -> 253 | AH32: =HF32 -> 128 | AI32: =HM32 -> 0 | AJ32: =HT32 -> 0 | AK32: =IA32 -> 0 | AL32: =IH32 -> 0 | AM32: =IO32 -> 0 | AN32: =IV32 -> 0 | AO32: =JC32 -> 0 | AP32: =JJ32 -> 0 | AQ32: =JQ32 -> 0 | AR32: =JX32 -> 0 | AS32: =KE32 -> 0 | AT32: =KL32 -> 0 | AU32: =KS32 -> 0 | AV32: =KZ32 -> 0 | AW32: =LG32 -> 0 | AX32: =LN32 -> 0 | AY32: =LU32 -> 0 | AZ32: =MB32 -> 0 | BA32: =MI32 -> 0 | BQ32: Inland transportation | BR32: =SUM(Expense!BP45,Expense!BP35)+Expense!BP53 -> 0 | BS32: =SUM(Expense!BQ45,Expense!BQ35)+Expense!BQ53 -> 0 | BT32: =SUM(Expense!BR45,Expense!BR35)+Expense!BR53 -> 0 | BU32: =SUM(Expense!BS45,Expense!BS35)+Expense!BS53 -> 189 | BV32: =SUM(BR32:BU32) -> 189 | BX32: Inland transportation | BY32: =SUM(Expense!BW45,Expense!BW35)+Expense!BW53 -> 176 | BZ32: =SUM(Expense!BX45,Expense!BX35)+Expense!BX53 -> 199 | CA32: =SUM(Expense!BY45,Expense!BY35)+Expense!BY53 -> 212 | CB32: =SUM(Expense!BZ45,Expense!BZ35)+Expense!BZ53 -> 236 | CC32: =SUM(BY32:CB32) -> 823 | CE32: Inland transportation | CF32: =SUM(Expense!CD45,Expense!CD35)+Expense!CD53 -> 216 | CG32: =SUM(Expense!CE45,Expense!CE35)+Expense!CE53 -> 242 | CH32: =SUM(Expense!CF45,Expense!CF35)+Expense!CF53 -> 244 | CI32: =SUM(Expense!CG45,Expense!CG35)+Expense!CG53 -> 262 | CJ32: =SUM(CF32:CI32) -> 964 | CL32: Inland transportation | CM32: =SUM(Expense!CK45,Expense!CK35)+Expense!CK53 -> 269 | CN32: =SUM(Expense!CL45,Expense!CL35)+Expense!CL53 -> 263 | CO32: =SUM(Expense!CM45,Expense!CM35)+Expense!CM53 -> 269 | CP32: =SUM(Expense!CN45,Expense!CN35)+Expense!CN53 -> 258 | CQ32: =SUM(CM32:CP32) -> 1059 | CS32: Inland transportation | CT32: =SUM(Expense!CR45,Expense!CR35)+Expense!CR53 -> 257 | CU32: =SUM(Expense!CS45,Expense!CS35)+Expense!CS53 -> 264 | CV32: =SUM(Expense!CT45,Expense!CT35)+Expense!CT53 -> 280 | CW32: =SUM(Expense!CU45,Expense!CU35)+Expense!CU53 -> 282 | CX32: =SUM(CT32:CW32) -> 1083 | CZ32: Inland transportation | DA32: =SUM(Expense!CY45,Expense!CY35)+Expense!CY53 -> 283 | DB32: =SUM(Expense!CZ45,Expense!CZ35)+Expense!CZ53 -> 292 | DC32: =SUM(Expense!DA45,Expense!DA35)+Expense!DA53 -> 319 | DD32: =SUM(Expense!DB45,Expense!DB35)+Expense!DB53 -> 335 | DE32: =SUM(DA32:DD32) -> 1229 | DG32: Inland transportation | DH32: =SUM(Expense!DF45,Expense!DF35)+Expense!DF53 -> 276 | DI32: =SUM(Expense!DG45,Expense!DG35)+Expense!DG53 -> 285 | DJ32: =SUM(Expense!DH45,Expense!DH35)+Expense!DH53 -> 284 | DK32: =SUM(Expense!DI45,Expense!DI35)+Expense!DI53 -> 296 | DL32: =SUM(DH32:DK32) -> 1141 | DN32: Inland transportation | DO32: =SUM(Expense!DM45,Expense!DM35)+Expense!DM53 -> 222 | DP32: =SUM(Expense!DN45,Expense!DN35)+Expense!DN53 -> 242 | DQ32: =SUM(Expense!DO45,Expense!DO35)+Expense!DO53 -> 249 | DR32: =SUM(Expense!DP45,Expense!DP35)+Expense!DP53 -> 241 | DS32: =SUM(DO32:DR32) -> 954 | DU32: Inland transportation | DV32: =SUM(Expense!DT45,Expense!DT35)+Expense!DT53 -> 224 | DW32: =SUM(Expense!DU45,Expense!DU35)+Expense!DU53 -> 240 | DX32: =SUM(Expense!DV45,Expense!DV35)+Expense!DV53 -> 251 | DY32: =SUM(Expense!DW45,Expense!DW35)+Expense!DW53 -> 240 | DZ32: =SUM(DV32:DY32) -> 955 | EB32: Inland transportation | EC32: =SUM(Expense!EA45,Expense!EA35)+Expense!EA53 -> 231 | ED32: =SUM(Expense!EB45,Expense!EB35)+Expense!EB53 -> 230 | EE32: =SUM(Expense!EC45,Expense!EC35)+Expense!EC53 -> 236 | EF32: =SUM(Expense!ED45,Expense!ED35)+Expense!ED53 -> 226 | EG32: =SUM(EC32:EF32) -> 923 | EI32: Inland transportation | EJ32: =SUM(Expense!EH45,Expense!EH35)+Expense!EH53 -> 229 | EK32: =SUM(Expense!EI45,Expense!EI35)+Expense!EI53 -> 235 | EL32: =SUM(Expense!EJ45,Expense!EJ35)+Expense!EJ53 -> 243 | EM32: =SUM(Expense!EK45,Expense!EK35)+Expense!EK53 -> 228 | EN32: =SUM(EJ32:EM32) -> 935 | EP32: Inland transportation | EQ32: =SUM(Expense!EO45,Expense!EO35)+Expense!EO53 -> 88 | ER32: =SUM(Expense!EP45,Expense!EP35)+Expense!EP53 -> 95 | ES32: =SUM(Expense!EQ45,Expense!EQ35)+Expense!EQ53 -> 98 | ET32: =SUM(Expense!ER45,Expense!ER35)+Expense!ER53 -> 96 | EU32: =SUM(EQ32:ET32) -> 377 | EW32: Inland transportation | EX32: =SUM(Expense!EV45,Expense!EV35)+Expense!EV53 -> 90 | EY32: =SUM(Expense!EW45,Expense!EW35)+Expense!EW53 -> 87 | EZ32: =SUM(Expense!EX45,Expense!EX35)+Expense!EX53 -> 88 | FA32: =SUM(Expense!EY45,Expense!EY35)+Expense!EY53 -> 89 | FB32: =SUM(EX32:FA32) -> 354 | FD32: Inland transportation | FE32: =SUM(Expense!FC45,Expense!FC35)+Expense!FC53 -> 91 | FF32: =SUM(Expense!FD45,Expense!FD35)+Expense!FD53 -> 99 | FG32: =SUM(Expense!FE45,Expense!FE35)+Expense!FE53 -> 114 | FH32: =SUM(Expense!FF45,Expense!FF35)+Expense!FF53 -> 107 | FI32: =SUM(FE32:FH32) -> 411 | FK32: Inland transportation | FL32: =SUM(Expense!FJ45,Expense!FJ35) -> 74 | FM32: =SUM(Expense!FK45,Expense!FK35) -> 77 | FN32: =SUM(Expense!FL45,Expense!FL35) -> 74 | FO32: =SUM(Expense!FM45,Expense!FM35) -> 73 | FP32: =SUM(FL32:FO32) -> 298 | FR32: Inland transportation | FS32: =SUM(Expense!FQ45,Expense!FQ35) -> 74 | FT32: =SUM(Expense!FR45,Expense!FR35) -> 70 | FU32: =SUM(Expense!FS45,Expense!FS35) -> 72 | FV32: =SUM(Expense!FT45,Expense!FT35) -> 77 | FW32: =SUM(FS32:FV32) -> 293 | FY32: Inland transportation | FZ32: =SUM(Expense!FX45,Expense!FX35) -> 56 | GA32: =SUM(Expense!FY45,Expense!FY35) -> 64 | GB32: =SUM(Expense!FZ45,Expense!FZ35) -> 55 | GC32: =SUM(Expense!GA45,Expense!GA35) -> 55 | GD32: =SUM(FZ32:GC32) -> 230 | GF32: Inland transportation | GG32: =SUM(Expense!GE45,Expense!GE35) -> 56 | GH32: =SUM(Expense!GF45,Expense!GF35) -> 62 | GI32: =SUM(Expense!GG45,Expense!GG35) -> 63 | GJ32: =SUM(Expense!GH45,Expense!GH35) -> 61 | GK32: =SUM(GG32:GJ32) -> 242 | GM32: Inland transportation | GN32: =SUM(Expense!GL45,Expense!GL35) -> 57 | GO32: =SUM(Expense!GM45,Expense!GM35) -> 60 | GP32: =SUM(Expense!GN45,Expense!GN35) -> 60 | GQ32: =SUM(Expense!GO45,Expense!GO35) -> 63 | GR32: =SUM(GN32:GQ32) -> 240 | GT32: Inland transportation | GU32: =SUM(Expense!GS45,Expense!GS35) -> 63 | GV32: =SUM(Expense!GT45,Expense!GT35) -> 68 | GW32: =SUM(Expense!GU45,Expense!GU35) -> 65 | GX32: =SUM(Expense!GV45,Expense!GV35) -> 57 | GY32: =SUM(GU32:GX32) -> 253 | HA32: Inland transportation | HB32: 58 | HC32: 0 | HD32: 0 | HE32: 70 | HF32: =SUM(HB32:HE32) -> 128 | HH32: Inland transportation | HI32: 0 | HJ32: 0 | HK32: 0 | HL32: 0 | HM32: =SUM(HI32:HL32) -> 0 | HO32: Inland transportation | HP32: 0 | HQ32: 0 | HR32: 0 | HS32: 0 | HT32: =SUM(HP32:HS32) -> 0 | HV32: Inland transportation | HW32: 0 | HX32: 0 | HY32: 0 | HZ32: 0 | IA32: =SUM(HW32:HZ32) -> 0 | IC32: Inland transportation | ID32: 0 | IE32: 0 | IF32: 0 | IG32: 0 | IH32: =SUM(ID32:IG32) -> 0 | IJ32: Inland transportation | IK32: 0 | IL32: 0 | IM32: 0 | IN32: 0 | IO32: =SUM(IK32:IN32) -> 0 | IQ32: Inland transportation | IR32: 0 | IS32: 0 | IT32: 0 | IU32: 0 | IV32: =SUM(IR32:IU32) -> 0 | IX32: Inland transportation | IY32: 0 | IZ32: 0 | JA32: 0 | JB32: 0 | JC32: =SUM(IY32:JB32) -> 0 | JE32: Inland transportation | JF32: 0 | JG32: 0 | JH32: 0 | JI32: 0 | JJ32: =SUM(JF32:JI32) -> 0 | JL32: Inland transportation | JM32: 0 | JN32: 0 | JO32: 0 | JP32: 0 | JQ32: =SUM(JM32:JP32) -> 0 | JS32: Inland transportation | JT32: 0 | JU32: 0 | JV32: 0 | JW32: 0 | JX32: =SUM(JT32:JW32) -> 0 | JZ32: Inland transportation | KA32: 0 | KB32: 0 | KC32: 0 | KD32: 0 | KE32: =SUM(KA32:KD32) -> 0 | KG32: Inland transportation | KH32: 0 | KI32: 0 | KJ32: 0 | KK32: 0 | KL32: =SUM(KH32:KK32) -> 0 | KN32: Inland transportation | KO32: 0 | KP32: 0 | KQ32: 0 | KR32: 0 | KS32: =SUM(KO32:KR32) -> 0 | KU32: Inland transportation | KV32: 0 | KW32: 0 | KX32: 0 | KY32: 0 | KZ32: =SUM(KV32:KY32) -> 0 | LB32: Inland transportation | LC32: =Expense!LA12 -> 0 | LD32: =Expense!LB12 -> 0 | LE32: =Expense!LC12 -> 0 | LF32: =Expense!LD12 -> 0 | LG32: =Expense!LE12 -> 0 | LI32: Inland transportation | LJ32: =Expense!LH12 -> 0 | LK32: =Expense!LI12 -> 0 | LL32: =Expense!LJ12 -> 0 | LM32: =Expense!LK12 -> 0 | LN32: =Expense!LL12 -> 0 | LP32: Inland transportation | LQ32: =Expense!LO12 -> 0 | LR32: =Expense!LP12 -> 0 | LS32: =Expense!LQ12 -> 0 | LT32: =Expense!LR12 -> 0 | LU32: =Expense!LS12 -> 0 | LW32: Inland transportation | LX32: =Expense!LV12 -> 0 | LY32: =Expense!LW12 -> 0 | LZ32: =Expense!LX12 -> 0 | MA32: =Expense!LY12 -> 0 | MB32: =Expense!LZ12 -> 0 | MD32: Inland transportation | ME32: =Expense!MC12 -> 0 | MF32: =Expense!MD12 -> 0 | MG32: =Expense!ME12 -> 0 | MH32: =Expense!MF12 -> 0 | MI32: =Expense!MG12 -> 0
