Workbook
Name \0: #REF!
Name \1: #N/A
Name \2: #N/A
Name \3: #N/A
Name \4: #N/A
Name \5: #N/A
Name \6: #N/A
Name \a: #N/A
Name \b: #REF!
Name \c: #REF!
Name \d: #REF!
Name \e: #REF!
Name \f: #REF!
Name \g: #REF!
Name \h: #REF!
Name \i: #REF!
Name \j: #REF!
Name \k: #N/A
Name \l: #REF!
Name \m: #REF!
Name \n: #REF!
Name \o: #REF!
Name \p: #REF!
Name \PRINJV: #REF!
Name \q: #REF!
Name \r: #REF!
Name \s: #REF!
Name \t: #REF!
Name \u: #REF!
Name \v: #N/A
Name \w: #REF!
Name \x: #REF!
Name \y: #REF!
Name \z: #REF!
Name _: #REF!
Name _.4: #REF!
Name _????_3: #REF!
Name _????1_3: #REF!
Name _????8_3: #REF!
Name _??_3: #REF!
Name _??1???_3: #REF!
Name __: #REF!
Name ___: #REF!
Name ____: #REF!
Name _____: #REF!
Name ______: #REF!
Name ________: #REF!
Name __________: #REF!
Name ____________: #REF!
Name _____________: #REF!
Name ______________: #REF!
Name _______________________________________________tax2: #REF!
Name ______________________________________________tax2: #REF!
Name _____________________________________________tax2: #REF!
Name ____________________________________________tax2: #REF!
Name ___________________________________________tax2: #REF!
Name __________________________________________tax2: #REF!
Name _________________________________________tax2: #REF!
Name ________________________________________tax2: #REF!
Name _______________________________________tax2: #REF!

Sheet Disclaimer
C5: Equity Research
C7: Financial Model
C8: Software
C9: 46083
C12: =+'Income Statement'!A1 -> Tenable Holdings, Inc. (TENB)
C17: Wells Fargo Software Team
C19: Richard Poland | E19: David Unger
C20: Analyst | E20: Associate Analyst
C21: (212) 214-5333 | E21: (212) 214-5317
C22: richard.d.poland@wellsfargo.com | E22: David.Unger@wellsfargo.com
C24: Important Disclaimers:

Sheet Income Statement
A1: Tenable Holdings, Inc. (TENB)
A2: Income Statement | B2: 2017/1F | C2: 2017/2F | D2: 2017/3F | E2: 2017/4F | F2: 2018/1F | G2: 2018/2F | H2: 2018/3F | I2: 2018/4F | J2: 2019/1F | K2: 2019/2F | L2: 2019/3F | M2: 2019/4F | N2: 2020/1F | O2: 2020/2F | P2: 2020/3F | Q2: 2020/4F | R2: 2021/1F | S2: 2021/2F | T2: 2021/3F | U2: 2021/4F | V2: 2022/1F | W2: 2022/2F | X2: 2022/3F | Y2: 2022/4F | Z2: 2023/1F | AA2: 2023/2F | AB2: 2023/3F | AC2: 2023/4F | AD2: 2024/1F | AE2: 2024/2F | AF2: 2024/3F | AG2: 2024/4F | AH2: 2025/1F | AI2: 2025/2F | AJ2: 2025/3F | AK2: 2025/4F | AL2: 2026/1F | AM2: 2026/2F | AN2: 2026/3F | AO2: 2026/4F | AP2: 2027/1F | AQ2: 2027/2F | AR2: 2027/3F | AS2: 2027/4F | AU2: 2017 | AV2: 2018 | AW2: 2019 | AX2: 2020 | AY2: 2021 | AZ2: 2022 | BA2: 2023 | BB2: 2024 | BC2: =BB2+1 -> 2025 | BD2: =BC2+1 -> 2026 | BE2: =BD2+1 -> 2027
B3: 2017 | F3: 2018 | J3: 2019 | N3: 2020 | R3: 2021 | V3: 2022 | Z3: 2023 | AD3: 2024 | AH3: =AD3+1 -> 2025 | AL3: =AH3+1 -> 2026 | AP3: =AL3+1 -> 2027
A4: ($ in millions, unless otherwise stated) | B4: 42825 | C4: 42916 | D4: 43008 | E4: 43100 | F4: 43190 | G4: 43281 | H4: 43373 | I4: 43465 | J4: 43555 | K4: 43646 | L4: 43738 | M4: 43830 | N4: 43921 | O4: 44012 | P4: 44104 | Q4: 44196 | R4: 44286 | S4: 44377 | T4: 44469 | U4: 44561 | V4: 44651 | W4: 44742 | X4: 44834 | Y4: 44926 | Z4: 45016 | AA4: 45107 | AB4: 45199 | AC4: 45291 | AD4: 45382 | AE4: 45473 | AF4: Sep-24 | AG4: Dec-24 | AH4: Mar-25 | AI4: Jun-25 | AJ4: Sep-25 | AK4: Dec-25 | AL4: Mar-26E | AM4: Jun-26E | AN4: Sep-26E | AO4: Dec-26E | AP4: Mar-27E | AQ4: Jun-27E | AR4: Sep-27E | AS4: Dec-27E | AU4: 2017 | AV4: 2018 | AW4: 2019 | AX4: 2020 | AY4: CY21 | AZ4: CY22 | BA4: CY23 | BB4: CY24 | BC4: CY25 | BD4: CY26E | BE4: CY27E
A5: Revenue
A6: Subscription | B6: ='Revenue Build'!B13 -> 27.702 | C6: ='Revenue Build'!C13 -> 30.844 | D6: ='Revenue Build'!D13 -> 34.932 | E6: ='Revenue Build'!E13 -> 39.395 | F6: ='Revenue Build'!F13 -> 44.332 | G6: ='Revenue Build'!G13 -> 48.725 | H6: ='Revenue Build'!H13 -> 53.511 | I6: ='Revenue Build'!I13 -> 59.259 | ... AS6: ='Revenue Build'!AS13 -> 275.96222 | AU6: =SUM(B6:E6) -> 132.873 | AV6: =SUM(F6:I6) -> 205.827 | AW6: =SUM(J6:M6) -> 290.549 | AX6: =SUM(N6:Q6) -> 377.354 | AY6: =SUM(R6:U6) -> 476.023 | AZ6: =SUM(V6:Y6) -> 612.51 | BA6: =SUM(Z6:AC6) -> 725.013 | BB6: =SUM(AD6:AG6) -> 824.659 | BC6: =SUM(AH6:AK6) -> 919.573 | BD6: =SUM(AL6:AO6) -> 995.23014 | BE6: =SUM(AP6:AS6) -> 1069.6212
A7: Perpetual Licnese and Maintenance | B7: ='Revenue Build'!B18 -> 11.989 | C7: ='Revenue Build'!C18 -> 12.283 | D7: ='Revenue Build'!D18 -> 12.857 | E7: ='Revenue Build'!E18 -> 13.208 | F7: ='Revenue Build'!F18 -> 13.477 | G7: ='Revenue Build'!G18 -> 13.412 | H7: ='Revenue Build'!H18 -> 13.864 | I7: ='Revenue Build'!I18 -> 13.869 | ... AS7: ='Revenue Build'!AS18 -> 8.5941 | AU7: =SUM(B7:E7) -> 50.337 | AV7: =SUM(F7:I7) -> 54.622 | AW7: =SUM(J7:M7) -> 54.173 | AX7: =SUM(N7:Q7) -> 50.594 | AY7: =SUM(R7:U7) -> 50.333 | AZ7: =SUM(V7:Y7) -> 50.699 | BA7: =SUM(Z7:AC7) -> 48.729 | BB7: =SUM(AD7:AG7) -> 47.774 | BC7: =SUM(AH7:AK7) -> 44.661 | BD7: =SUM(AL7:AO7) -> 40.1949 | BE7: =SUM(AP7:AS7) -> 36.17541
A8: Professional Services and Other | B8: ='Revenue Build'!B23 -> 0.79 | C8: ='Revenue Build'!C23 -> 1.022 | D8: ='Revenue Build'!D23 -> 1.191 | E8: ='Revenue Build'!E23 -> 1.514 | F8: ='Revenue Build'!F23 -> 1.298 | G8: ='Revenue Build'!G23 -> 1.455 | H8: ='Revenue Build'!H23 -> 2.065 | I8: ='Revenue Build'!I23 -> 2.093 | ... AS8: ='Revenue Build'!AS23 -> 11.035 | AU8: =SUM(B8:E8) -> 4.517 | AV8: =SUM(F8:I8) -> 6.911 | AW8: =SUM(J8:M8) -> 9.864 | AX8: =SUM(N8:Q8) -> 12.273 | AY8: =SUM(R8:U8) -> 14.774 | AZ8: =SUM(V8:Y8) -> 19.982 | BA8: =SUM(Z8:AC8) -> 24.968 | BB8: =SUM(AD8:AG8) -> 27.588 | BC8: =SUM(AH8:AK8) -> 35.171 | BD8: =SUM(AL8:AO8) -> 34.8139 | BE8: =SUM(AP8:AS8) -> 34.8139
A9: Total revenue | B9: =+'Revenue Build'!B5 -> 40.481 | C9: =+'Revenue Build'!C5 -> 44.149 | D9: =+'Revenue Build'!D5 -> 48.98 | E9: =+'Revenue Build'!E5 -> 54.117 | F9: =+'Revenue Build'!F5 -> 59.107 | G9: =+'Revenue Build'!G5 -> 63.592 | H9: =+'Revenue Build'!H5 -> 69.44 | I9: =+'Revenue Build'!I5 -> 75.221 | ... AS9: =+'Revenue Build'!AS5 -> 295.59132 | AU9: =SUM(B9:E9) -> 187.727 | AV9: =SUM(F9:I9) -> 267.36 | AW9: =SUM(J9:M9) -> 354.586 | AX9: =SUM(N9:Q9) -> 440.221 | AY9: =SUM(R9:U9) -> 541.13 | AZ9: =SUM(V9:Y9) -> 683.191 | BA9: =SUM(Z9:AC9) -> 798.71 | BB9: =SUM(AD9:AG9) -> 900.021 | BC9: =SUM(AH9:AK9) -> 999.405 | BD9: =SUM(AL9:AO9) -> 1070.2389 | BE9: =SUM(AP9:AS9) -> 1140.6105
A10: Consensus revenue | B10: ='[2]VA Consensus'!C16 -> - | C10: ='[2]VA Consensus'!D16 -> - | D10: ='[2]VA Consensus'!E16 -> - | E10: ='[2]VA Consensus'!F16 -> - | F10: ='[2]VA Consensus'!G16 -> - | G10: ='[2]VA Consensus'!H16 -> - | H10: ='[2]VA Consensus'!I16 -> 66.295101 | I10: ='[2]VA Consensus'!J16 -> 72.829307 | ... AS10: ='[2]VA Consensus'!AT16 -> 296.33303 | AU10: ='[2]VA Consensus'!AV16 -> - | AV10: ='[2]VA Consensus'!AW16 -> 264.96833 | AW10: ='[2]VA Consensus'!AX16 -> 351.79152 | AX10: ='[2]VA Consensus'!AY16 -> 437.03012 | AY10: ='[2]VA Consensus'!AZ16 -> 536.56619 | AZ10: ='[2]VA Consensus'!BA16 -> 680.03864 | BA10: ='[2]VA Consensus'!BB16 -> 791.94039 | BB10: ='[2]VA Consensus'!BC16 -> 895.84654 | ... BE10: ='[2]VA Consensus'!BF16 -> 1145.8385
A11: Management Guidance - Revenue
A12: Low | N12: ='Revenue Build'!N9 -> 100 | O12: ='Revenue Build'!O9 -> 101 | P12: ='Revenue Build'!P9 -> 108 | Q12: ='Revenue Build'!Q9 -> 113 | R12: ='Revenue Build'!R9 -> 118 | S12: ='Revenue Build'!S9 -> 124 | T12: ='Revenue Build'!T9 -> 133 | U12: ='Revenue Build'!U9 -> 143 | ... AB12: ='Revenue Build'!AB9 -> 197 | AC12: 204 | AD12: ='Revenue Build'!AD9 -> 212 | AE12: ='Revenue Build'!AE9 -> 217 | AF12: ='Revenue Build'!AF9 -> 222 | AG12: 229 | AH12: 233 | AI12: ='Revenue Build'!AI9 -> 241 | AJ12: ='Revenue Build'!AJ9 -> 246 | AK12: ='Revenue Build'!AK9 -> 249.1 | AL12: ='Revenue Build'!AL9 -> 257 | AM12: ='Revenue Build'!AM9 | AN12: ='Revenue Build'!AN9 | AO12: ='Revenue Build'!AO9 | AP12: ='Revenue Build'!AP9 | ... AS12: ='Revenue Build'!AS9 | AY12: ='Revenue Build'!AY9 -> 535.1 | AZ12: ='Revenue Build'!AZ9 -> 678.6 | BA12: ='Revenue Build'!BA9 -> 789.4 | BB12: ='Revenue Build'!BB9 -> 893.3 | BC12: ='Revenue Build'!BC9 -> 988 | BD12: ='Revenue Build'!BD9 -> 1065
A13: Mid | N13: ='Revenue Build'!N10 -> 100.5 | O13: ='Revenue Build'!O10 -> 102 | P13: ='Revenue Build'!P10 -> 109 | Q13: ='Revenue Build'!Q10 -> 114 | R13: ='Revenue Build'!R10 -> 119 | S13: ='Revenue Build'!S10 -> 125 | T13: ='Revenue Build'!T10 -> 134 | U13: ='Revenue Build'!U10 -> 144 | ... AS13: ='Revenue Build'!AS10 | AY13: ='Revenue Build'!AY10 -> 536.1 | AZ13: ='Revenue Build'!AZ10 -> 679.6 | BA13: ='Revenue Build'!BA10 -> 791.4 | BB13: ='Revenue Build'!BB10 -> 895.3 | BC13: ='Revenue Build'!BC10 -> 990 | BD13: ='Revenue Build'!BD10 -> 1070
A14: High | N14: ='Revenue Build'!N11 -> 101 | O14: ='Revenue Build'!O11 -> 103 | P14: ='Revenue Build'!P11 -> 110 | Q14: ='Revenue Build'!Q11 -> 115 | R14: ='Revenue Build'!R11 -> 120 | S14: ='Revenue Build'!S11 -> 126 | T14: ='Revenue Build'!T11 -> 135 | U14: ='Revenue Build'!U11 -> 145 | ... AB14: ='Revenue Build'!AB11 -> 199 | AC14: 208 | AD14: ='Revenue Build'!AD11 -> 214 | AE14: ='Revenue Build'!AE11 -> 219 | AF14: ='Revenue Build'!AF11 -> 224 | AG14: 233 | AH14: 235 | AI14: ='Revenue Build'!AI11 -> 243 | AJ14: ='Revenue Build'!AJ11 -> 248 | AK14: ='Revenue Build'!AK11 -> 253.1 | AL14: ='Revenue Build'!AL11 -> 260 | AM14: ='Revenue Build'!AM11 | AN14: ='Revenue Build'!AN11 | AO14: ='Revenue Build'!AO11 | AP14: ='Revenue Build'!AP11 | ... AS14: ='Revenue Build'!AS11 | AY14: ='Revenue Build'!AY11 -> 537.1 | AZ14: ='Revenue Build'!AZ11 -> 680.6 | BA14: ='Revenue Build'!BA11 -> 793.4 | BB14: ='Revenue Build'!BB11 -> 897.3 | BC14: ='Revenue Build'!BC11 -> 992 | BD14: ='Revenue Build'!BD11 -> 1075
A16: Cost of Revenue | B16: =B112-B83-B86 -> 4.233 | C16: =C112-C83-C86 -> 5.147 | D16: =D112-D83-D86 -> 7.21 | E16: =E112-E83-E86 -> 8.114 | F16: =F112-F83-F86 -> 8.5 | G16: =G112-G83-G86 -> 9.614 | H16: =H112-H83-H86 -> 11.318 | I16: =I112-I83-I86 -> 11.425 | ... AK16: =AK112-AK83-AK86 -> 45.064 | AL16: =(1-AL69)*AL9 -> 47.056131 | AM16: =(1-AM69)*AM9 -> 47.980399 | AN16: =(1-AN69)*AN9 -> 47.83697 | AO16: =(1-AO69)*AO9 -> 47.988228 | AP16: =(1-AP69)*AP9 -> 50.43283 | AQ16: =(1-AQ69)*AQ9 -> 51.421835 | AR16: =(1-AR69)*AR9 -> 51.264925 | AS16: =(1-AS69)*AS9 -> 51.43289 | AU16: =SUM(B16:E16) -> 24.704 | AV16: =SUM(F16:I16) -> 40.857 | AW16: =SUM(J16:M16) -> 57.381 | AX16: =SUM(N16:Q16) -> 72.082 | AY16: =SUM(R16:U16) -> 95.503 | AZ16: =SUM(V16:Y16) -> 135.048 | BA16: =SUM(Z16:AC16) -> 158.471 | BB16: =SUM(AD16:AG16) -> 167.534 | BC16: =SUM(AH16:AK16) -> 179.258 | BD16: =SUM(AL16:AO16) -> 190.86173 | BE16: =SUM(AP16:AS16) -> 204.55248
A17: Gross profit | B17: =B9-B16 -> 36.248 | C17: =C9-C16 -> 39.002 | D17: =D9-D16 -> 41.77 | E17: =E9-E16 -> 46.003 | F17: =F9-F16 -> 50.607 | G17: =G9-G16 -> 53.978 | H17: =H9-H16 -> 58.122 | I17: =I9-I16 -> 63.796 | ... AS17: =AS9-AS16 -> 244.15843 | AU17: =SUM(B17:E17) -> 163.023 | AV17: =SUM(F17:I17) -> 226.503 | AW17: =SUM(J17:M17) -> 297.205 | AX17: =SUM(N17:Q17) -> 368.139 | AY17: =SUM(R17:U17) -> 445.627 | AZ17: =SUM(V17:Y17) -> 548.143 | BA17: =SUM(Z17:AC17) -> 640.239 | BB17: =SUM(AD17:AG17) -> 732.487 | BC17: =SUM(AH17:AK17) -> 820.147 | BD17: =SUM(AL17:AO17) -> 879.37722 | BE17: =SUM(AP17:AS17) -> 936.058
A18: Consensus gross profit | B18: ='[2]VA Consensus'!C23 -> - | C18: ='[2]VA Consensus'!D23 -> - | D18: ='[2]VA Consensus'!E23 -> - | E18: ='[2]VA Consensus'!F23 -> - | F18: ='[2]VA Consensus'!G23 -> - | G18: ='[2]VA Consensus'!H23 -> - | H18: ='[2]VA Consensus'!I23 -> 54.516385 | I18: ='[2]VA Consensus'!J23 -> 59.879956 | ... AS18: ='[2]VA Consensus'!AT23 -> 244.19627 | AU18: ='[2]VA Consensus'!AV23 -> - | AV18: ='[2]VA Consensus'!AW23 -> 222.53371 | AW18: ='[2]VA Consensus'!AX23 -> 296.58138 | AX18: ='[2]VA Consensus'!AY23 -> 364.88916 | AY18: ='[2]VA Consensus'!AZ23 -> 442.34027 | AZ18: ='[2]VA Consensus'!BA23 -> 550.00836 | BA18: ='[2]VA Consensus'!BB23 -> 632.37188 | BB18: ='[2]VA Consensus'!BC23 -> 727.79762 | ... BE18: ='[2]VA Consensus'!BF23 -> 941.23666
A20: Operating expenses
A21: Sales and marketing | B21: =B116-B143-B152-B161 -> 25.898 | C21: =C116-C143-C152-C161 -> 27.415 | D21: =D116-D143-D152-D161 -> 29.165 | E21: =E116-E143-E152-E161 -> 32.242 | F21: =F116-F143-F152-F161 -> 38.986 | G21: =G116-G143-G152-G161 -> 41.151 | H21: =H116-H143-H152-H161 -> 41.843 | I21: =I116-I143-I152-I161 -> 44.453 | ... AK21: =AK116-AK143-AK152-AK161 -> 89.425 | AL21: =AL$9*AL71 -> 91.151844 | AM21: =AM$9*AM71 -> 91.598078 | AN21: =AN$9*AN71 -> 84.221809 | AO21: =AO$9*AO71 -> 91.049665 | AP21: =AP$9*AP71 -> 95.780897 | AQ21: =AQ$9*AQ71 -> 96.212651 | AR21: =AR$9*AR71 -> 88.320858 | AS21: =AS$9*AS71 -> 95.546546 | AU21: =SUM(B21:E21) -> 114.72 | AV21: =SUM(F21:I21) -> 166.433 | AW21: =SUM(J21:M21) -> 212.003 | AX21: =SUM(N21:Q21) -> 204.435 | AY21: =SUM(R21:U21) -> 240.629 | AZ21: =SUM(V21:Y21) -> 300.047 | BA21: =SUM(Z21:AC21) -> 332.128 | BB21: =SUM(AD21:AG21) -> 332.658 | BC21: =SUM(AH21:AK21) -> 346.836 | BD21: =SUM(AL21:AO21) -> 358.0214 | BE21: =SUM(AP21:AS21) -> 375.86095
A22: Research and development | B22: =B117-B144-B153-B162 -> 12.064 | C22: =C117-C144-C153-C162 -> 13.261 | D22: =D117-D144-D153-D162 -> 15.359 | E22: =E117-E144-E153-E162 -> 15.207 | F22: =F117-F144-F153-F162 -> 16.658 | G22: =G117-G144-G153-G162 -> 17.151 | H22: =H117-H144-H153-H162 -> 18.126 | I22: =I117-I144-I153-I162 -> 18.959 | ... AK22: =AK117-AK144-AK153-AK162 -> 40.84 | AL22: =AL$9*AL72 -> 42.187116 | AM22: =AM$9*AM72 -> 46.605664 | AN22: =AN$9*AN72 -> 44.809979 | AO22: =AO$9*AO72 -> 43.482209 | AP22: =AP$9*AP72 -> 44.96733 | AQ22: =AQ$9*AQ72 -> 49.673589 | AR22: =AR$9*AR72 -> 47.752748 | AS22: =AS$9*AS72 -> 46.335588 | AU22: =SUM(B22:E22) -> 55.891 | AV22: =SUM(F22:I22) -> 70.894 | AW22: =SUM(J22:M22) -> 78.153 | AX22: =SUM(N22:Q22) -> 86.893 | AY22: =SUM(R22:U22) -> 95.7 | AZ22: =SUM(V22:Y22) -> 112.061 | BA22: =SUM(Z22:AC22) -> 115.938 | BB22: =SUM(AD22:AG22) -> 133.968 | BC22: =SUM(AH22:AK22) -> 165.352 | BD22: =SUM(AL22:AO22) -> 177.08497 | BE22: =SUM(AP22:AS22) -> 188.72925
A23: General and administrative | B23: =B118-B145-B154-B163 -> 5.255 | C23: =C118-C145-C154-C163 -> 5.555 | D23: =D118-D145-D154-D163 -> 6.229 | E23: =E118-E145-E154-E163 -> 7.77 | F23: =F118-F145-F154-F163 -> 7.862 | G23: =G118-G145-G154-G163 -> 8.946 | H23: =H118-H145-H154-H163 -> 10.315 | I23: =I118-I145-I154-I163 -> 11.156 | ... AK23: =AK118-AK145-AK154-AK163 -> 21.511 | AL23: =AL$9*AL73 -> 24.046711 | AM23: =AM$9*AM73 -> 23.632752 | AN23: =AN$9*AN73 -> 23.918485 | AO23: =AO$9*AO73 -> 22.191088 | AP23: =AP$9*AP73 -> 25.080223 | AQ23: =AQ$9*AQ73 -> 24.622399 | AR23: =AR$9*AR73 -> 24.916472 | AS23: =AS$9*AS73 -> 23.056123 | AU23: =SUM(B23:E23) -> 24.809 | AV23: =SUM(F23:I23) -> 38.279 | AW23: =SUM(J23:M23) -> 49.815 | AX23: =SUM(N23:Q23) -> 51.018 | AY23: =SUM(R23:U23) -> 58.313 | AZ23: =SUM(V23:Y23) -> 68.365 | BA23: =SUM(Z23:AC23) -> 71.176 | BB23: =SUM(AD23:AG23) -> 81.743 | BC23: =SUM(AH23:AK23) -> 88.98 | BD23: =SUM(AL23:AO23) -> 93.789036 | BE23: =SUM(AP23:AS23) -> 97.675218
A24: Total operating expenses | B24: =B21+B22+B23 -> 43.217 | C24: =C21+C22+C23 -> 46.231 | D24: =D21+D22+D23 -> 50.753 | E24: =E21+E22+E23 -> 55.219 | F24: =F21+F22+F23 -> 63.506 | G24: =G21+G22+G23 -> 67.248 | H24: =H21+H22+H23 -> 70.284 | I24: =I21+I22+I23 -> 74.568 | ... AS24: =AS21+AS22+AS23 -> 164.93826 | AU24: =SUM(B24:E24) -> 195.42 | AV24: =SUM(F24:I24) -> 275.606 | AW24: =SUM(J24:M24) -> 339.971 | AX24: =SUM(N24:Q24) -> 342.346 | AY24: =SUM(R24:U24) -> 394.642 | AZ24: =SUM(V24:Y24) -> 480.473 | BA24: =SUM(Z24:AC24) -> 519.242 | BB24: =SUM(AD24:AG24) -> 548.369 | BC24: =SUM(AH24:AK24) -> 601.168 | BD24: =SUM(AL24:AO24) -> 628.8954 | BE24: =SUM(AP24:AS24) -> 662.26542
A25: Operating Income | B25: =B17-B24 -> -6.969 | C25: =C17-C24 -> -7.229 | D25: =D17-D24 -> -8.983 | E25: =E17-E24 -> -9.216 | F25: =F17-F24 -> -12.899 | G25: =G17-G24 -> -13.27 | H25: =H17-H24 -> -12.162 | I25: =I17-I24 -> -10.772 | ... AS25: =AS17-AS24 -> 79.220176 | AU25: =SUM(B25:E25) -> -32.397 | AV25: =SUM(F25:I25) -> -49.103 | AW25: =SUM(J25:M25) -> -42.766 | AX25: =SUM(N25:Q25) -> 25.793 | AY25: =SUM(R25:U25) -> 50.985 | AZ25: =SUM(V25:Y25) -> 67.67 | BA25: =SUM(Z25:AC25) -> 120.997 | BB25: =SUM(AD25:AG25) -> 184.118 | BC25: =SUM(AH25:AK25) -> 218.979 | BD25: =SUM(AL25:AO25) -> 250.48182 | BE25: =SUM(AP25:AS25) -> 273.79258
A26: Consensus operating income | B26: ='[2]VA Consensus'!C29 -> - | C26: ='[2]VA Consensus'!D29 -> - | D26: ='[2]VA Consensus'!E29 -> - | E26: ='[2]VA Consensus'!F29 -> - | F26: ='[2]VA Consensus'!G29 -> - | G26: ='[2]VA Consensus'!H29 -> - | H26: ='[2]VA Consensus'!I29 -> -16.934376 | I26: ='[2]VA Consensus'!J29 -> -13.435126 | ... AS26: ='[2]VA Consensus'!AT29 -> 77.324023 | AU26: ='[2]VA Consensus'!AV29 -> - | AV26: ='[2]VA Consensus'!AW29 -> -51.76636 | AW26: ='[2]VA Consensus'!AX29 -> -44.405321 | AX26: ='[2]VA Consensus'!AY29 -> 19.247211 | AY26: ='[2]VA Consensus'!AZ29 -> 46.924672 | AZ26: ='[2]VA Consensus'!BA29 -> 63.35298 | BA26: ='[2]VA Consensus'!BB29 -> 108.76154 | BB26: ='[2]VA Consensus'!BC29 -> 172.68222 | ... BE26: ='[2]VA Consensus'!BF29 -> 280.1123
A27: Management Guidance - Operating Income
A28: Low | N28: -18 | O28: -5.5 | P28: 3 | Q28: 8 | R28: 7 | S28: 7 | T28: 7 | U28: 7 | V28: 10 | W28: 6 | X28: 9 | Y28: 15 | Z28: 9 | AA28: 20 | AB28: 26 | AC28: 23 | AD28: 27 | AE28: 34 | AF28: 42 | AG28: 47 | AH28: 40 | AI28: 43 | AJ28: 52 | AK28: 55.7 | AL28: 53 | AY28: 46.1 | AZ28: 62.7 | BA28: 107.9 | BB28: 171.8 | BC28: 205 | BD28: 245
A29: Mid | N29: =AVERAGE(N28,N30) -> -17.5 | O29: =AVERAGE(O28,O30) -> -4.5 | P29: =AVERAGE(P28,P30) -> 3.5 | Q29: =AVERAGE(Q28,Q30) -> 8.5 | R29: =AVERAGE(R28,R30) -> 8 | S29: =AVERAGE(S28,S30) -> 7.5 | T29: =AVERAGE(T28,T30) -> 7.5 | U29: =AVERAGE(U28,U30) -> 7.5 | ... AC29: =AVERAGE(AC28,AC30) -> 23.5 | AD29: =IFERROR(AVERAGE(AD28,AD30),"") -> 28 | AE29: =IFERROR(AVERAGE(AE28,AE30),"") -> 35 | AF29: =IFERROR(AVERAGE(AF28,AF30),"") -> 43 | AG29: =IFERROR(AVERAGE(AG28,AG30),"") -> 48 | AH29: =IFERROR(AVERAGE(AH28,AH30),"") -> 41 | AI29: =IFERROR(AVERAGE(AI28,AI30),"") -> 44 | AJ29: =IFERROR(AVERAGE(AJ28,AJ30),"") -> 53 | AK29: =IFERROR(AVERAGE(AK28,AK30),"") -> 57.7 | ... AS29: =IFERROR(AVERAGE(AS28,AS30),"") | AY29: =AVERAGE(AY28,AY30) -> 46.6 | AZ29: =AVERAGE(AZ28,AZ30) -> 63.2 | BA29: =AVERAGE(BA28,BA30) -> 108.4 | BB29: =IFERROR(AVERAGE(BB28,BB30),"") -> 172.8 | BC29: =IFERROR(AVERAGE(BC28,BC30),"") -> 210 | BD29: =IFERROR(AVERAGE(BD28,BD30),"") -> 250 | BE29: =IFERROR(AVERAGE(BE28,BE30),"")
A30: High | N30: -17 | O30: -3.5 | P30: 4 | Q30: 9 | R30: 9 | S30: 8 | T30: 8 | U30: 8 | V30: 11 | W30: 7 | X30: 10 | Y30: 16 | Z30: 10 | AA30: 21 | AB30: 27 | AC30: 24 | AD30: 29 | AE30: 36 | AF30: 44 | AG30: 49 | AH30: 42 | AI30: 45 | AJ30: 54 | AK30: 59.7 | AL30: 56 | AY30: 47.1 | AZ30: 63.7 | BA30: 108.9 | BB30: 173.8 | BC30: 215 | BD30: 255
A31: EBITDA | B31: =B25+'Cash Flow'!B8-'Income Statement'!B85 -> -6.084 | C31: =C25+'Cash Flow'!C8-'Income Statement'!C85 -> -6.295 | D31: =D25+'Cash Flow'!D8-'Income Statement'!D85 -> -7.939 | E31: =E25+'Cash Flow'!E8-'Income Statement'!E85 -> -7.99 | F31: =F25+'Cash Flow'!F8-'Income Statement'!F85 -> -11.596 | G31: =G25+'Cash Flow'!G8-'Income Statement'!G85 -> -11.881 | H31: =H25+'Cash Flow'!H8-'Income Statement'!H85 -> -10.727 | I31: =I25+'Cash Flow'!I8-'Income Statement'!I85 -> -9.31 | ... AC31: =AC25+'Cash Flow'!AC8-'Income Statement'!AC85 -> 39.62 | AD31: =AD25+'Cash Flow'!AT8-'Income Statement'!AD85 -> 32.339 | AE31: =AE25+'Cash Flow'!AU8-'Income Statement'!AE85 -> 42.716 | AF31: =AF25+'Cash Flow'!AV8-'Income Statement'!AF85 -> 46.153 | AG31: =AG25+'Cash Flow'!AW8-'Income Statement'!AG85 -> 61.217 | AH31: =AH25+'Cash Flow'!AX8-'Income Statement'!AH85 -> 53.446 | AI31: =AI25+'Cash Flow'!AY8-'Income Statement'!AI85 -> 57.329 | AJ31: =AJ25+'Cash Flow'!AZ8-'Income Statement'!AJ85 -> 74.325 | AK31: =AK25+'Cash Flow'!BA8-'Income Statement'!AK85 -> 84.019 | ... AN31: =AN25+'Cash Flow'!BD8-'Income Statement'!AN85 -> 106.76914 | AO31: =AO25+'Cash Flow'!BF8-'Income Statement'!AO85 -> 65.89541 | AP31: =AP25+'Cash Flow'!BF8-'Income Statement'!AP85 -> 52.563568 | AQ31: =AQ25+'Cash Flow'!BG8-'Income Statement'!AQ85 -> 57.119611 | AR31: =AR25+'Cash Flow'!BH8-'Income Statement'!AR85 -> 74.166226 | AS31: =AS25+'Cash Flow'!BJ8-'Income Statement'!AS85 -> 88.608176 | AU31: =SUM(B31:E31) -> -28.308 | AV31: =SUM(F31:I31) -> -43.514 | AW31: =SUM(J31:M31) -> -36.506 | AX31: =SUM(N31:Q31) -> 34.112 | AY31: =SUM(R31:U31) -> 60.708 | AZ31: =SUM(V31:Y31) -> 78.492 | BA31: =SUM(Z31:AC31) -> 134.246 | BB31: =SUM(AD31:AG31) -> 182.425 | BC31: =SUM(AH31:AK31) -> 269.119 | BD31: =SUM(AL31:AO31) -> 344.10918 | BE31: =SUM(AP31:AS31) -> 272.45758
A33: Interest income | B33: =B123 -> 0 | C33: =C123 -> 0 | D33: =D123 -> 0 | E33: =E123 -> 0 | F33: =F123 -> -0.026 | G33: =G123 -> -0.023 | H33: =H123 -> 0.894 | I33: =I123 -> 1.509 | ... AK33: =AK123 -> 3.395 | AL33: =AK33-0.5 -> 2.895 | AM33: =AL33-0.7 -> 2.195 | AN33: =AM33+0.3 -> 2.495 | AO33: =AN33+0.3 -> 2.795 | AP33: =AO33+0.3 -> 3.095 | AQ33: =AP33+0.3 -> 3.395 | AR33: =AQ33+0.3 -> 3.695 | AS33: =AR33+0.3 -> 3.995 | AU33: =SUM(B33:E33) -> 0 | AV33: =SUM(F33:I33) -> 2.354 | AW33: =SUM(J33:M33) -> 5.83 | AX33: =SUM(N33:Q33) -> 1.74 | AY33: =SUM(R33:U33) -> 0.606 | AZ33: =SUM(V33:Y33) -> 6.284 | BA33: =SUM(Z33:AC33) -> 24.7 | BB33: =SUM(AD33:AG33) -> 23.325 | BC33: =SUM(AH33:AK33) -> 15.992 | BD33: =SUM(AL33:AO33) -> 10.38 | BE33: =SUM(AP33:AS33) -> 14.18
A34: Interest expense | B34: =B124 -> 0 | C34: =C124 -> 0 | D34: =D124 -> 0 | E34: =E124 -> 0 | F34: =F124 -> 0 | G34: =G124 -> 0 | H34: =H124 -> 0 | I34: =I124 -> 0 | ... AK34: =AK124 -> -7.056 | AL34: =AK34+0.7 -> -6.356 | AM34: =AL34-0.025 -> -6.381 | AN34: =AM34-0.025 -> -6.406 | AO34: =AN34-0.025 -> -6.431 | AP34: =AO34-0.025 -> -6.456 | AQ34: =AP34-0.025 -> -6.481 | AR34: =AQ34-0.025 -> -6.506 | AS34: =AR34-0.025 -> -6.531 | AY34: =SUM(R34:U34) -> -7.502 | AZ34: =SUM(V34:Y34) -> -19.001 | BA34: =SUM(Z34:AC34) -> -31.339 | BB34: =SUM(AD34:AG34) -> -31.92 | BC34: =SUM(AH34:AK34) -> -28.419 | BD34: =SUM(AL34:AO34) -> -25.574 | BE34: =SUM(AP34:AS34) -> -25.974
A35: Other income (expense), net | B35: =B125 -> -0.029 | C35: =C125 -> 0.056 | D35: =D125 -> -0.092 | E35: =E125 -> -0.026 | F35: =F125 -> 0.018 | G35: =G125 -> -0.438 | H35: =H125 -> -0.185 | I35: =I125 -> -0.325 | ... AK35: =AK125 -> -1.134 | AL35: =AK35 -> -1.134 | AM35: =AL35 -> -1.134 | AN35: =AM35 -> -1.134 | AO35: =AN35 -> -1.134 | AP35: =AO35 -> -1.134 | AQ35: =AP35 -> -1.134 | AR35: =AQ35 -> -1.134 | AS35: =AR35 -> -1.134 | AU35: =SUM(B35:E35) -> -0.091 | AV35: =SUM(F35:I35) -> -0.93 | AW35: =SUM(J35:M35) -> -0.68 | AX35: =SUM(N35:Q35) -> -1.885 | AY35: =SUM(R35:U35) -> -1.965 | AZ35: =SUM(V35:Y35) -> -4.757 | BA35: =SUM(Z35:AC35) -> -8.602 | BB35: =SUM(AD35:AG35) -> -3.435 | BC35: =SUM(AH35:AK35) -> -1.338 | BD35: =SUM(AL35:AO35) -> -4.536 | BE35: =SUM(AP35:AS35) -> -4.536
A36: Pre-tax income | B36: =B25+SUM(B33:B35) -> -6.998 | C36: =C25+SUM(C33:C35) -> -7.173 | D36: =D25+SUM(D33:D35) -> -9.075 | E36: =E25+SUM(E33:E35) -> -9.242 | F36: =F25+SUM(F33:F35) -> -12.907 | G36: =G25+SUM(G33:G35) -> -13.731 | H36: =H25+SUM(H33:H35) -> -11.453 | I36: =I25+SUM(I33:I35) -> -9.588 | ... AS36: =AS25+SUM(AS33:AS35) -> 75.550176 | AU36: =SUM(B36:E36) -> -32.488 | AV36: =SUM(F36:I36) -> -47.679 | AW36: =SUM(J36:M36) -> -37.616 | AX36: =SUM(N36:Q36) -> 25.152 | AY36: =SUM(R36:U36) -> 42.124 | AZ36: =SUM(V36:Y36) -> 50.196 | BA36: =SUM(Z36:AC36) -> 105.756 | BB36: =SUM(AD36:AG36) -> 172.088 | BC36: =SUM(AH36:AK36) -> 205.214 | BD36: =SUM(AL36:AO36) -> 230.75182 | BE36: =SUM(AP36:AS36) -> 257.46258
A37: Provision for (benefit from) income taxes | B37: =B128-B169-B170-B171 -> 0.061 | C37: =C128-C169-C170-C171 -> 0.053 | D37: =D128-D169-D170-D171 -> 0.072 | E37: =E128-E169-E170-E171 -> 0.039 | F37: =F128-F169-F170-F171 -> 0.454 | G37: =G128-G169-G170-G171 -> 0.269 | H37: =H128-H169-H170-H171 -> 0.572 | I37: =I128-I169-I170-I171 -> 1.287 | ... AK37: =AK128-AK169-AK170-AK171 -> 1.593 | AL37: =AK37+0.075 -> 1.668 | AM37: =AL37+2 -> 3.668 | AN37: =AM37+0.075 -> 3.743 | AO37: =AN37+0.075 -> 3.818 | AP37: =AO37+0.075 -> 3.893 | AQ37: =AP37+0.075 -> 3.968 | AR37: =AQ37+0.075 -> 4.043 | AS37: =AR37+0.075 -> 4.118 | AU37: =SUM(B37:E37) -> 0.225 | AV37: =SUM(F37:I37) -> 2.582 | AW37: =SUM(J37:M37) -> 2.877 | AX37: =SUM(N37:Q37) -> 4.358 | AY37: =SUM(R37:U37) -> 3.183 | AZ37: =SUM(V37:Y37) -> 5.881 | BA37: =SUM(Z37:AC37) -> 8.601 | BB37: =SUM(AD37:AG37) -> 13.499 | BC37: =SUM(AH37:AK37) -> 10.784 | BD37: =SUM(AL37:AO37) -> 12.897 | BE37: =SUM(AP37:AS37) -> 16.022
A38: Adjusted tax rate (non-GAAP) | B38: =+B37/B36 -> -0.0087167762 | C38: =+C37/C36 -> -0.0073888192 | D38: =+D37/D36 -> -0.0079338843 | E38: =+E37/E36 -> -0.0042198658 | F38: =+F37/F36 -> -0.035174711 | G38: =+G37/G36 -> -0.019590707 | H38: =+H37/H36 -> -0.049943246 | I38: =+I37/I36 -> -0.13423029 | ... AS38: =+AS37/AS36 -> 0.054506822 | AU38: =AU37/AU36 -> -0.0069256341 | AV38: =AV37/AV36 -> -0.05415382 | AW38: =AW37/AW36 -> -0.076483411 | AX38: =AX37/AX36 -> 0.17326654 | AY38: =AY37/AY36 -> 0.075562625 | AZ38: =AZ37/AZ36 -> 0.11716073 | BA38: =BA37/BA36 -> 0.081328719 | BB38: =BB37/BB36 -> 0.078442425 | ... BE38: =BE37/BE36 -> 0.062230402
A39: Non-GAAP Net income | B39: =B36-B37 -> -7.059 | C39: =C36-C37 -> -7.226 | D39: =D36-D37 -> -9.147 | E39: =E36-E37 -> -9.281 | F39: =F36-F37 -> -13.361 | G39: =G36-G37 -> -14 | H39: =H36-H37 -> -12.025 | I39: =I36-I37 -> -10.875 | ... AS39: =AS36-AS37 -> 71.432176 | AU39: =SUM(B39:E39) -> -32.713 | AV39: =SUM(F39:I39) -> -50.261 | AW39: =SUM(J39:M39) -> -40.493 | AX39: =SUM(N39:Q39) -> 20.794 | AY39: =SUM(R39:U39) -> 38.941 | AZ39: =SUM(V39:Y39) -> 44.315 | BA39: =SUM(Z39:AC39) -> 97.155 | BB39: =SUM(AD39:AG39) -> 158.589 | BC39: =SUM(AH39:AK39) -> 194.43 | BD39: =SUM(AL39:AO39) -> 217.85482 | BE39: =SUM(AP39:AS39) -> 241.44058
A40: Consensus net income | B40: ='[2]VA Consensus'!C31 -> - | C40: ='[2]VA Consensus'!D31 -> - | D40: ='[2]VA Consensus'!E31 -> - | E40: ='[2]VA Consensus'!F31 -> - | F40: ='[2]VA Consensus'!G31 -> - | G40: ='[2]VA Consensus'!H31 -> - | H40: ='[2]VA Consensus'!I31 -> -16.619108 | I40: ='[2]VA Consensus'!J31 -> -13.023466 | ... AS40: ='[2]VA Consensus'!AT31 -> 68.638046 | AU40: ='[2]VA Consensus'!AV31 -> - | AV40: ='[2]VA Consensus'!AW31 -> -52.415811 | AW40: ='[2]VA Consensus'!AX31 -> -41.748534 | AX40: ='[2]VA Consensus'!AY31 -> 13.487622 | AY40: ='[2]VA Consensus'!AZ31 -> 35.695242 | AZ40: ='[2]VA Consensus'!BA31 -> 38.339587 | BA40: ='[2]VA Consensus'!BB31 -> 83.813788 | BB40: ='[2]VA Consensus'!BC31 -> 151.10782 | ... BE40: ='[2]VA Consensus'!BF31 -> 248.16594
A41: Management Guidance - Non-GAAP Net Income
A42: Low | N42: -19 | O42: -6 | P42: 2 | Q42: 6 | R42: 5 | S42: 5 | T42: 1 | U42: 2 | V42: 5.2 | W42: 1 | X42: 3.2 | Y42: 7.5 | Z42: 3 | AA42: 15 | AB42: 22 | AC42: 16 | AD42: 20 | AE42: 28 | AF42: 35 | AG42: 42 | AH42: 32 | AI42: 36 | AJ42: 44 | AK42: 47.9 | AL42: 46 | AY42: 35 | AZ42: 37.6 | BA42: 83 | BB42: 149.9 | BC42: 185 | BD42: 214
A43: Mid | N43: =AVERAGE(N42,N44) -> -18.5 | O43: =AVERAGE(O42,O44) -> -5 | P43: =AVERAGE(P42,P44) -> 2.5 | Q43: =AVERAGE(Q42,Q44) -> 6.5 | R43: =AVERAGE(R42,R44) -> 6 | S43: =AVERAGE(S42,S44) -> 5.5 | T43: =AVERAGE(T42,T44) -> 2 | U43: =AVERAGE(U42,U44) -> 2.5 | ... AC43: =AVERAGE(AC42,AC44) -> 16.5 | AD43: =IFERROR(AVERAGE(AD42,AD44),"") -> 21 | AE43: =IFERROR(AVERAGE(AE42,AE44),"") -> 29 | AF43: =IFERROR(AVERAGE(AF42,AF44),"") -> 36 | AG43: =IFERROR(AVERAGE(AG42,AG44),"") -> 43 | AH43: =IFERROR(AVERAGE(AH42,AH44),"") -> 33 | AI43: =IFERROR(AVERAGE(AI42,AI44),"") -> 37 | AJ43: =IFERROR(AVERAGE(AJ42,AJ44),"") -> 45 | AK43: =IFERROR(AVERAGE(AK42,AK44),"") -> 49.9 | ... AS43: =IFERROR(AVERAGE(AS42,AS44),"") | AY43: =AVERAGE(AY42,AY44) -> 35.5 | AZ43: =AVERAGE(AZ42,AZ44) -> 38.1 | BA43: =AVERAGE(BA42,BA44) -> 83.5 | BB43: =IFERROR(AVERAGE(BB42,BB44),"") -> 150.9 | BC43: =IFERROR(AVERAGE(BC42,BC44),"") -> 187 | BD43: =IFERROR(AVERAGE(BD42,BD44),"") -> 219 | BE43: =IFERROR(AVERAGE(BE42,BE44),"") | BF43: =IFERROR(AVERAGE(BF42,BF44),"")
A44: High | N44: -18 | O44: -4 | P44: 3 | Q44: 7 | R44: 7 | S44: 6 | T44: 3 | U44: 3 | V44: 6.2 | W44: 2 | X44: 4.2 | Y44: 8.5 | Z44: 4 | AA44: 16 | AB44: 23 | AC44: 17 | AD44: 22 | AE44: 30 | AF44: 37 | AG44: 44 | AH44: 34 | AI44: 38 | AJ44: 46 | AK44: 51.9 | AL44: 49 | AY44: 36 | AZ44: 38.6 | BA44: 84 | BB44: 151.9 | BC44: 189 | BD44: 224
A46: Non-GAAP EPS | B46: -0.33 | C46: =IF(C39<0,C39/C52,C39/C53) -> -0.3275612 | D46: =IF(D39<0,D39/D52,D39/D53) -> -0.40332466 | E46: =IF(E39<0,E39/E52,E39/E53) -> -0.40657993 | F46: =IF(F39<0,F39/F52,F39/F53) -> -0.56867419 | G46: =IF(G39<0,G39/G52,G39/G53) -> -0.58947368 | H46: =IF(H39<0,H39/H52,H39/H53) -> -0.16192887 | I46: =IF(I39<0,I39/I52,I39/I53) -> -0.11796674 | J46: =IF(J39<0,J39/J52,J39/J53) -> -0.1346199 | ... AS46: =IF(AS39<0,AS39/AS52,AS39/AS53) -> 0.59891152 | AU46: =SUM(B46:E46) -> -1.4674658 | AV46: =IF(AV39<0,AV39/AV52,AV39/AV53) -> -0.93649966 | AW46: =IF(AW39<0,AW39/AW52,AW39/AW53) -> -0.42174058 | AX46: =IF(AX39<0,AX39/AX52,AX39/AX53) -> 0.18910169 | AY46: =IF(AY39<0,AY39/AY52,AY39/AY53) -> 0.33913346 | AZ46: =IF(AZ39<0,AZ39/AZ52,AZ39/AZ53) -> 0.37703984 | BA46: =IF(BA39<0,BA39/BA52,BA39/BA53) -> 0.80319276 | BB46: =IF(BB39<0,BB39/BB52,BB39/BB53) -> 1.2855189 | BC46: =IF(BC39<0,BC39/BC52,BC39/BC53) -> 1.5939172 | ... BE46: =IF(BE39<0,BE39/BE52,BE39/BE53) -> 2.0327559
A47: Consensus non-GAAP EPS | B47: ='[2]VA Consensus'!C33 -> - | C47: ='[2]VA Consensus'!D33 -> - | D47: ='[2]VA Consensus'!E33 -> - | E47: ='[2]VA Consensus'!F33 -> - | F47: ='[2]VA Consensus'!G33 -> - | G47: ='[2]VA Consensus'!H33 -> - | H47: ='[2]VA Consensus'!I33 -> -0.18741165 | I47: ='[2]VA Consensus'!J33 -> -0.14205224 | ... AS47: ='[2]VA Consensus'!AT33 -> 0.57140589 | AU47: ='[2]VA Consensus'!AV33 -> - | AV47: ='[2]VA Consensus'!AW33 -> -0.61940889 | AW47: ='[2]VA Consensus'!AX33 -> -0.43477535 | AX47: ='[2]VA Consensus'!AY33 -> 0.1212282 | AY47: ='[2]VA Consensus'!AZ33 -> 0.31047976 | AZ47: ='[2]VA Consensus'!BA33 -> 0.32387049 | BA47: ='[2]VA Consensus'!BB33 -> 0.69225592 | BB47: ='[2]VA Consensus'!BC33 -> 1.2222073 | ... BE47: ='[2]VA Consensus'!BF33 -> 2.0718224
A48: Management Guidance - Non-GAAP EPS
A49: Low | N49: -0.19 | O49: -0.06 | P49: 0.02 | Q49: 0.05 | R49: 0.04 | S49: 0.04 | T49: 0.01 | U49: 0.02 | V49: 0.04 | W49: 0.01 | X49: 0.03 | Y49: 0.06 | Z49: 0.02 | AA49: 0.12 | AB49: 0.18 | AC49: 0.13 | AD49: 0.16 | AE49: 0.22 | AF49: 0.28 | AG49: 0.33 | AH49: 0.26 | AI49: 0.29 | AJ49: 0.36 | AK49: 0.39 | AL49: 0.39 | AY49: 0.3 | AZ49: 0.32 | BA49: 0.68 | BB49: 1.21 | BC49: 1.51 | BD49: 1.81
A50: Mid | N50: =AVERAGE(N49,N51) -> -0.185 | O50: =AVERAGE(O49,O51) -> -0.05 | P50: =AVERAGE(P49,P51) -> 0.025 | Q50: =AVERAGE(Q49,Q51) -> 0.055 | R50: =AVERAGE(R49,R51) -> 0.05 | S50: =AVERAGE(S49,S51) -> 0.045 | T50: =AVERAGE(T49,T51) -> 0.02 | U50: =AVERAGE(U49,U51) -> 0.025 | ... AC50: =AVERAGE(AC49,AC51) -> 0.135 | AD50: =IFERROR(AVERAGE(AD49,AD51),"") -> 0.17 | AE50: =IFERROR(AVERAGE(AE49,AE51),"") -> 0.23 | AF50: =IFERROR(AVERAGE(AF49,AF51),"") -> 0.29 | AG50: =IFERROR(AVERAGE(AG49,AG51),"") -> 0.34 | AH50: =IFERROR(AVERAGE(AH49,AH51),"") -> 0.265 | AI50: =IFERROR(AVERAGE(AI49,AI51),"") -> 0.3 | AJ50: =IFERROR(AVERAGE(AJ49,AJ51),"") -> 0.365 | AK50: =IFERROR(AVERAGE(AK49,AK51),"") -> 0.41 | ... AS50: =IFERROR(AVERAGE(AS49,AS51),"") | AY50: =AVERAGE(AY49,AY51) -> 0.305 | AZ50: =AVERAGE(AZ49,AZ51) -> 0.325 | BA50: =AVERAGE(BA49,BA51) -> 0.685 | BB50: =IFERROR(AVERAGE(BB49,BB51),"") -> 1.22 | BC50: =IFERROR(AVERAGE(BC49,BC51),"") -> 1.525 | BD50: =IFERROR(AVERAGE(BD49,BD51),"") -> 1.855 | BE50: =IFERROR(AVERAGE(BE49,BE51),"")
A51: High | N51: -0.18 | O51: -0.04 | P51: 0.03 | Q51: 0.06 | R51: 0.06 | S51: 0.05 | T51: 0.03 | U51: 0.03 | V51: 0.05 | W51: 0.02 | X51: 0.04 | Y51: 0.07 | Z51: 0.03 | AA51: 0.13 | AB51: 0.19 | AC51: 0.14 | AD51: 0.18 | AE51: 0.24 | AF51: 0.3 | AG51: 0.35 | AH51: 0.27 | AI51: 0.31 | AJ51: 0.37 | AK51: 0.43 | AL51: 0.42 | AY51: 0.31 | AZ51: 0.33 | BA51: 0.69 | BB51: 1.23 | BC51: 1.54 | BD51: 1.9
A52: Basic shares outstanding | C52: =C136 -> 22.06 | D52: =D136 -> 22.679 | E52: =E136 -> 22.827 | F52: =F136 -> 23.495 | G52: =G136 -> 23.75 | H52: =H136 -> 74.261 | I52: =I136 -> 92.187 | J52: =J136 -> 93.738 | ... AH52: =AH136 -> 120.083 | AI52: 120.979 | AJ52: =AJ136 -> 120.483 | AK52: =AK136 -> 118.95 | AL52: =AK52+0.2 -> 119.15 | AM52: =AL52+0.2 -> 119.35 | AN52: =AM52+0.2 -> 119.55 | AO52: =AN52+0.2 -> 119.75 | AP52: =AO52+0.2 -> 119.95 | AQ52: =AP52+0.2 -> 120.15 | AR52: =AQ52+0.2 -> 120.35 | AS52: =AR52+0.2 -> 120.55 | AV52: =AV136 -> 53.669 | AW52: =AW136 -> 96.014 | AX52: =AX136 -> 101.009 | AY52: =AY136 -> 106.387 | AZ52: =AZ136 -> 111.321 | BA52: =+AVERAGE(Z52:AC52) -> 115.399 | BB52: =AVERAGE(AD52:AG52) -> 118.785 | BC52: =AVERAGE(AH52:AK52) -> 120.12375 | BD52: =AVERAGE(AL52:AO52) -> 119.45 | BE52: =AVERAGE(AP52:AS52) -> 120.25
A53: Pro forma Diluted shares outstanding | C53: =C137 -> 77.446 | D53: =D137 -> 78.065 | E53: =E137 -> 78.213 | F53: =F137 -> 78.881 | G53: =G137 -> 79.136 | H53: =H137 -> 88.71 | I53: =I137 -> 92.187 | J53: =J137 -> 93.738 | ... AH53: =AH137 -> 124.152 | AI53: 122.875 | AJ53: =AJ137 -> 121.953 | AK53: =AK137 -> 118.95 | AL53: =AK53-1 -> 117.95 | AM53: =AL53+0 -> 117.95 | AN53: =AM53+0 -> 117.95 | AO53: =AN53+0 -> 117.95 | AP53: =AO53+0.33 -> 118.28 | AQ53: =AP53+0.33 -> 118.61 | AR53: =AQ53+0.33 -> 118.94 | AS53: =AR53+0.33 -> 119.27 | AU53: =AU137 -> 22.211 | AV53: =AV137 -> 84.774 | AW53: =AW137 -> 96.014 | AX53: =AX137 -> 109.962 | AY53: =AY137 -> 114.825 | AZ53: =AZ137 -> 117.534 | BA53: =+AVERAGE(Z53:AC53) -> 120.961 | BB53: =AVERAGE(AD53:AG53) -> 123.36575 | BC53: =AVERAGE(AH53:AK53) -> 121.9825 | BD53: =AVERAGE(AL53:AO53) -> 117.95 | BE53: =AVERAGE(AP53:AS53) -> 118.775
B55: =B3 -> 2017 | F55: =F3 -> 2018 | J55: =J3 -> 2019 | N55: =N3 -> 2020 | R55: =R3 -> 2021 | V55: =V3 -> 2022 | Z55: =Z3 -> 2023 | AD55: =AD3 -> 2024 | AH55: =AH3 -> 2025 | AL55: =AL3 -> 2026 | AP55: =AP3 -> 2027
A56: Y/Y Growth | B56: =B4 -> 42825 | C56: =C4 -> 42916 | D56: =D4 -> 43008 | E56: =E4 -> 43100 | F56: =F4 -> 43190 | G56: =G4 -> 43281 | H56: =H4 -> 43373 | I56: =I4 -> 43465 | ... AS56: =AS4 -> Dec-27E | AU56: =AU4 -> 2017 | AV56: =AV4 -> 2018 | AW56: =AW4 -> 2019 | AX56: =AX4 -> 2020 | AY56: =AY4 -> CY21 | AZ56: =AZ4 -> CY22 | BA56: =BA4 -> CY23 | BB56: =BB4 -> CY24 | ... BE56: =BE4 -> CY27E
A57: Total Revenue | F57: =IF(OR(B9<=0,F9<=0),"NM",(F9-B9)/B9) -> 0.46011709 | G57: =IF(OR(C9<=0,G9<=0),"NM",(G9-C9)/C9) -> 0.44039503 | H57: =IF(OR(D9<=0,H9<=0),"NM",(H9-D9)/D9) -> 0.41772152 | I57: =IF(OR(E9<=0,I9<=0),"NM",(I9-E9)/E9) -> 0.38996988 | J57: =IF(OR(F9<=0,J9<=0),"NM",(J9-F9)/F9) -> 0.35857005 | K57: =IF(OR(G9<=0,K9<=0),"NM",(K9-G9)/G9) -> 0.34268461 | L57: =IF(OR(H9<=0,L9<=0),"NM",(L9-H9)/H9) -> 0.32275346 | M57: =IF(OR(I9<=0,M9<=0),"NM",(M9-I9)/I9) -> 0.29018492 | ... AS57: =IF(OR(AO9<=0,AS9<=0),"NM",(AS9-AO9)/AO9) -> 0.065621742 | AV57: =IF(OR(AU9<=0,AV9<=0),"NM",(AV9-AU9)/AU9) -> 0.42419577 | AW57: =IF(OR(AV9<=0,AW9<=0),"NM",(AW9-AV9)/AV9) -> 0.32624925 | AX57: =IF(OR(AW9<=0,AX9<=0),"NM",(AX9-AW9)/AW9) -> 0.241507 | AY57: =IF(OR(AX9<=0,AY9<=0),"NM",(AY9-AX9)/AX9) -> 0.2292235 | AZ57: =IF(OR(AY9<=0,AZ9<=0),"NM",(AZ9-AY9)/AY9) -> 0.26252656 | BA57: =IF(OR(AZ9<=0,BA9<=0),"NM",(BA9-AZ9)/AZ9) -> 0.16908741 | BB57: =IF(OR(BA9<=0,BB9<=0),"NM",(BB9-BA9)/BA9) -> 0.12684328 | BC57: =IF(OR(BB9<=0,BC9<=0),"NM",(BC9-BB9)/BB9) -> 0.11042409 | ... BE57: =IF(OR(BD9<=0,BE9<=0),"NM",(BE9-BD9)/BD9) -> 0.065753111
A58: Total cost of revenue | F58: =IF(OR(B16<=0,F16<=0),"NM",(F16-B16)/B16) -> 1.0080321 | G58: =IF(OR(C16<=0,G16<=0),"NM",(G16-C16)/C16) -> 0.8678842 | H58: =IF(OR(D16<=0,H16<=0),"NM",(H16-D16)/D16) -> 0.56976422 | I58: =IF(OR(E16<=0,I16<=0),"NM",(I16-E16)/E16) -> 0.40806014 | J58: =IF(OR(F16<=0,J16<=0),"NM",(J16-F16)/F16) -> 0.46152941 | K58: =IF(OR(G16<=0,K16<=0),"NM",(K16-G16)/G16) -> 0.35479509 | L58: =IF(OR(H16<=0,L16<=0),"NM",(L16-H16)/H16) -> 0.27460682 | M58: =IF(OR(I16<=0,M16<=0),"NM",(M16-I16)/I16) -> 0.53234136 | ... AS58: =IF(OR(AO16<=0,AS16<=0),"NM",(AS16-AO16)/AO16) -> 0.071781405 | AV58: =IF(OR(AU16<=0,AV16<=0),"NM",(AV16-AU16)/AU16) -> 0.65386172 | AW58: =IF(OR(AV16<=0,AW16<=0),"NM",(AW16-AV16)/AV16) -> 0.40443498 | AX58: =IF(OR(AW16<=0,AX16<=0),"NM",(AX16-AW16)/AW16) -> 0.25619979 | AY58: =IF(OR(AX16<=0,AY16<=0),"NM",(AY16-AX16)/AX16) -> 0.32492162 | AZ58: =IF(OR(AY16<=0,AZ16<=0),"NM",(AZ16-AY16)/AY16) -> 0.41407076 | BA58: =IF(OR(AZ16<=0,BA16<=0),"NM",(BA16-AZ16)/AZ16) -> 0.17344204 | BB58: =IF(OR(BA16<=0,BB16<=0),"NM",(BB16-BA16)/BA16) -> 0.057190275 | BC58: =IF(OR(BB16<=0,BC16<=0),"NM",(BC16-BB16)/BB16) -> 0.069979825 | ... BE58: =IF(OR(BD16<=0,BE16<=0),"NM",(BE16-BD16)/BD16) -> 0.071731256
A59: Gross profit | F59: =IF(OR(B17<=0,F17<=0),"NM",(F17-B17)/B17) -> 0.3961322 | G59: =IF(OR(C17<=0,G17<=0),"NM",(G17-C17)/C17) -> 0.38398031 | H59: =IF(OR(D17<=0,H17<=0),"NM",(H17-D17)/D17) -> 0.39147714 | I59: =IF(OR(E17<=0,I17<=0),"NM",(I17-E17)/E17) -> 0.38677912 | J59: =IF(OR(F17<=0,J17<=0),"NM",(J17-F17)/F17) -> 0.3412769 | K59: =IF(OR(G17<=0,K17<=0),"NM",(K17-G17)/G17) -> 0.34052762 | L59: =IF(OR(H17<=0,L17<=0),"NM",(L17-H17)/H17) -> 0.33212897 | M59: =IF(OR(I17<=0,M17<=0),"NM",(M17-I17)/I17) -> 0.24681798 | ... AS59: =IF(OR(AO17<=0,AS17<=0),"NM",(AS17-AO17)/AO17) -> 0.064333203 | AV59: =IF(OR(AU17<=0,AV17<=0),"NM",(AV17-AU17)/AU17) -> 0.38939291 | AW59: =IF(OR(AV17<=0,AW17<=0),"NM",(AW17-AV17)/AV17) -> 0.31214598 | AX59: =IF(OR(AW17<=0,AX17<=0),"NM",(AX17-AW17)/AW17) -> 0.23867028 | AY59: =IF(OR(AX17<=0,AY17<=0),"NM",(AY17-AX17)/AX17) -> 0.21048571 | AZ59: =IF(OR(AY17<=0,AZ17<=0),"NM",(AZ17-AY17)/AY17) -> 0.2300489 | BA59: =IF(OR(AZ17<=0,BA17<=0),"NM",(BA17-AZ17)/AZ17) -> 0.16801455 | BB59: =IF(OR(BA17<=0,BB17<=0),"NM",(BB17-BA17)/BA17) -> 0.14408369 | BC59: =IF(OR(BB17<=0,BC17<=0),"NM",(BC17-BB17)/BB17) -> 0.11967448 | ... BE59: =IF(OR(BD17<=0,BE17<=0),"NM",(BE17-BD17)/BD17) -> 0.064455602
A60: Sales and marketing | F60: =IF(OR(B21<=0,F21<=0),"NM",(F21-B21)/B21) -> 0.50536721 | G60: =IF(OR(C21<=0,G21<=0),"NM",(G21-C21)/C21) -> 0.50103958 | H60: =IF(OR(D21<=0,H21<=0),"NM",(H21-D21)/D21) -> 0.43469913 | I60: =IF(OR(E21<=0,I21<=0),"NM",(I21-E21)/E21) -> 0.37872961 | J60: =IF(OR(F21<=0,J21<=0),"NM",(J21-F21)/F21) -> 0.26514646 | K60: =IF(OR(G21<=0,K21<=0),"NM",(K21-G21)/G21) -> 0.25877864 | L60: =IF(OR(H21<=0,L21<=0),"NM",(L21-H21)/H21) -> 0.27089358 | M60: =IF(OR(I21<=0,M21<=0),"NM",(M21-I21)/I21) -> 0.29804513 | ... AS60: =IF(OR(AO21<=0,AS21<=0),"NM",(AS21-AO21)/AO21) -> 0.04938932 | AV60: =IF(OR(AU21<=0,AV21<=0),"NM",(AV21-AU21)/AU21) -> 0.4507758 | AW60: =IF(OR(AV21<=0,AW21<=0),"NM",(AW21-AV21)/AV21) -> 0.27380387 | AX60: =IF(OR(AW21<=0,AX21<=0),"NM",(AX21-AW21)/AW21) -> -0.035697608 | AY60: =IF(OR(AX21<=0,AY21<=0),"NM",(AY21-AX21)/AX21) -> 0.17704405 | AZ60: =IF(OR(AY21<=0,AZ21<=0),"NM",(AZ21-AY21)/AY21) -> 0.24692784 | BA60: =IF(OR(AZ21<=0,BA21<=0),"NM",(BA21-AZ21)/AZ21) -> 0.10691992 | BB60: =IF(OR(BA21<=0,BB21<=0),"NM",(BB21-BA21)/BA21) -> 0.0015957703 | BC60: =IF(OR(BB21<=0,BC21<=0),"NM",(BC21-BB21)/BB21) -> 0.042620349 | ... BE60: =IF(OR(BD21<=0,BE21<=0),"NM",(BE21-BD21)/BD21) -> 0.049828182
A61: Research and development | F61: =IF(OR(B22<=0,F22<=0),"NM",(F22-B22)/B22) -> 0.38080239 | G61: =IF(OR(C22<=0,G22<=0),"NM",(G22-C22)/C22) -> 0.29334138 | H61: =IF(OR(D22<=0,H22<=0),"NM",(H22-D22)/D22) -> 0.18015496 | I61: =IF(OR(E22<=0,I22<=0),"NM",(I22-E22)/E22) -> 0.24672848 | J61: =IF(OR(F22<=0,J22<=0),"NM",(J22-F22)/F22) -> 0.19492136 | K61: =IF(OR(G22<=0,K22<=0),"NM",(K22-G22)/G22) -> 0.12279167 | L61: =IF(OR(H22<=0,L22<=0),"NM",(L22-H22)/H22) -> 0.028301887 | M61: =IF(OR(I22<=0,M22<=0),"NM",(M22-I22)/I22) -> 0.073474339 | ... AS61: =IF(OR(AO22<=0,AS22<=0),"NM",(AS22-AO22)/AO22) -> 0.065621742 | AV61: =IF(OR(AU22<=0,AV22<=0),"NM",(AV22-AU22)/AU22) -> 0.2684332 | AW61: =IF(OR(AV22<=0,AW22<=0),"NM",(AW22-AV22)/AV22) -> 0.1023923 | AX61: =IF(OR(AW22<=0,AX22<=0),"NM",(AX22-AW22)/AW22) -> 0.11183192 | AY61: =IF(OR(AX22<=0,AY22<=0),"NM",(AY22-AX22)/AX22) -> 0.10135454 | AZ61: =IF(OR(AY22<=0,AZ22<=0),"NM",(AZ22-AY22)/AY22) -> 0.17096134 | BA61: =IF(OR(AZ22<=0,BA22<=0),"NM",(BA22-AZ22)/AZ22) -> 0.034597228 | BB61: =IF(OR(BA22<=0,BB22<=0),"NM",(BB22-BA22)/BA22) -> 0.15551415 | BC61: =IF(OR(BB22<=0,BC22<=0),"NM",(BC22-BB22)/BB22) -> 0.2342649 | ... BE61: =IF(OR(BD22<=0,BE22<=0),"NM",(BE22-BD22)/BD22) -> 0.065755363
A62: General and administrative | F62: =IF(OR(B23<=0,F23<=0),"NM",(F23-B23)/B23) -> 0.49609895 | G62: =IF(OR(C23<=0,G23<=0),"NM",(G23-C23)/C23) -> 0.61044104 | H62: =IF(OR(D23<=0,H23<=0),"NM",(H23-D23)/D23) -> 0.65596404 | I62: =IF(OR(E23<=0,I23<=0),"NM",(I23-E23)/E23) -> 0.43577864 | J62: =IF(OR(F23<=0,J23<=0),"NM",(J23-F23)/F23) -> 0.50915798 | K62: =IF(OR(G23<=0,K23<=0),"NM",(K23-G23)/G23) -> 0.342723 | L62: =IF(OR(H23<=0,L23<=0),"NM",(L23-H23)/H23) -> 0.29054775 | M62: =IF(OR(I23<=0,M23<=0),"NM",(M23-I23)/I23) -> 0.13176766 | ... AS62: =IF(OR(AO23<=0,AS23<=0),"NM",(AS23-AO23)/AO23) -> 0.038981199 | AV62: =IF(OR(AU23<=0,AV23<=0),"NM",(AV23-AU23)/AU23) -> 0.54294812 | AW62: =IF(OR(AV23<=0,AW23<=0),"NM",(AW23-AV23)/AV23) -> 0.30136628 | AX62: =IF(OR(AW23<=0,AX23<=0),"NM",(AX23-AW23)/AW23) -> 0.024149353 | AY62: =IF(OR(AX23<=0,AY23<=0),"NM",(AY23-AX23)/AX23) -> 0.14298875 | AZ62: =IF(OR(AY23<=0,AZ23<=0),"NM",(AZ23-AY23)/AY23) -> 0.17238009 | BA62: =IF(OR(AZ23<=0,BA23<=0),"NM",(BA23-AZ23)/AZ23) -> 0.041117531 | BB62: =IF(OR(BA23<=0,BB23<=0),"NM",(BB23-BA23)/BA23) -> 0.14846297 | BC62: =IF(OR(BB23<=0,BC23<=0),"NM",(BC23-BB23)/BB23) -> 0.088533575 | ... BE62: =IF(OR(BD23<=0,BE23<=0),"NM",(BE23-BD23)/BD23) -> 0.041435353
A63: Total operating expenses | F63: =IF(OR(B24<=0,F24<=0),"NM",(F24-B24)/B24) -> 0.46946803 | G63: =IF(OR(C24<=0,G24<=0),"NM",(G24-C24)/C24) -> 0.45460838 | H63: =IF(OR(D24<=0,H24<=0),"NM",(H24-D24)/D24) -> 0.38482454 | I63: =IF(OR(E24<=0,I24<=0),"NM",(I24-E24)/E24) -> 0.35040475 | J63: =IF(OR(F24<=0,J24<=0),"NM",(J24-F24)/F24) -> 0.27693446 | K63: =IF(OR(G24<=0,K24<=0),"NM",(K24-G24)/G24) -> 0.2352635 | L63: =IF(OR(H24<=0,L24<=0),"NM",(L24-H24)/H24) -> 0.2112145 | M63: =IF(OR(I24<=0,M24<=0),"NM",(M24-I24)/I24) -> 0.21607124 | ... AS63: =IF(OR(AO24<=0,AS24<=0),"NM",(AS24-AO24)/AO24) -> 0.052419214 | AV63: =IF(OR(AU24<=0,AV24<=0),"NM",(AV24-AU24)/AU24) -> 0.41032648 | AW63: =IF(OR(AV24<=0,AW24<=0),"NM",(AW24-AV24)/AV24) -> 0.23353991 | AX63: =IF(OR(AW24<=0,AX24<=0),"NM",(AX24-AW24)/AW24) -> 0.00698589 | AY63: =IF(OR(AX24<=0,AY24<=0),"NM",(AY24-AX24)/AX24) -> 0.15275774 | AZ63: =IF(OR(AY24<=0,AZ24<=0),"NM",(AZ24-AY24)/AY24) -> 0.21749079 | BA63: =IF(OR(AZ24<=0,BA24<=0),"NM",(BA24-AZ24)/AZ24) -> 0.080689237 | BB63: =IF(OR(BA24<=0,BB24<=0),"NM",(BB24-BA24)/BA24) -> 0.056095231 | BC63: =IF(OR(BB24<=0,BC24<=0),"NM",(BC24-BB24)/BB24) -> 0.096283707 | ... BE63: =IF(OR(BD24<=0,BE24<=0),"NM",(BE24-BD24)/BD24) -> 0.053061325
A64: Operating income | F64: =IF(OR(B25<=0,F25<=0),"NM",(F25-B25)/B25) -> NM | G64: =IF(OR(C25<=0,G25<=0),"NM",(G25-C25)/C25) -> NM | H64: =IF(OR(D25<=0,H25<=0),"NM",(H25-D25)/D25) -> NM | I64: =IF(OR(E25<=0,I25<=0),"NM",(I25-E25)/E25) -> NM | J64: =IF(OR(F25<=0,J25<=0),"NM",(J25-F25)/F25) -> NM | K64: =IF(OR(G25<=0,K25<=0),"NM",(K25-G25)/G25) -> NM | L64: =IF(OR(H25<=0,L25<=0),"NM",(L25-H25)/H25) -> NM | M64: =IF(OR(I25<=0,M25<=0),"NM",(M25-I25)/I25) -> NM | ... AS64: =IF(OR(AO25<=0,AS25<=0),"NM",(AS25-AO25)/AO25) -> 0.090024757 | AV64: =IF(OR(AU25<=0,AV25<=0),"NM",(AV25-AU25)/AU25) -> NM | AW64: =IF(OR(AV25<=0,AW25<=0),"NM",(AW25-AV25)/AV25) -> NM | AX64: =IF(OR(AW25<=0,AX25<=0),"NM",(AX25-AW25)/AW25) -> NM | AY64: =IF(OR(AX25<=0,AY25<=0),"NM",(AY25-AX25)/AX25) -> 0.9766991 | AZ64: =IF(OR(AY25<=0,AZ25<=0),"NM",(AZ25-AY25)/AY25) -> 0.32725311 | BA64: =IF(OR(AZ25<=0,BA25<=0),"NM",(BA25-AZ25)/AZ25) -> 0.78804492 | BB64: =IF(OR(BA25<=0,BB25<=0),"NM",(BB25-BA25)/BA25) -> 0.52167409 | BC64: =IF(OR(BB25<=0,BC25<=0),"NM",(BC25-BB25)/BB25) -> 0.18934053 | ... BE64: =IF(OR(BD25<=0,BE25<=0),"NM",(BE25-BD25)/BD25) -> 0.093063701
A65: Net income | F65: =IF(OR(B39<=0,F39<=0),"NM",(F39-B39)/B39) -> NM | G65: =IF(OR(C39<=0,G39<=0),"NM",(G39-C39)/C39) -> NM | H65: =IF(OR(D39<=0,H39<=0),"NM",(H39-D39)/D39) -> NM | I65: =IF(OR(E39<=0,I39<=0),"NM",(I39-E39)/E39) -> NM | J65: =IF(OR(F39<=0,J39<=0),"NM",(J39-F39)/F39) -> NM | K65: =IF(OR(G39<=0,K39<=0),"NM",(K39-G39)/G39) -> NM | L65: =IF(OR(H39<=0,L39<=0),"NM",(L39-H39)/H39) -> NM | M65: =IF(OR(I39<=0,M39<=0),"NM",(M39-I39)/I39) -> NM | ... AS65: =IF(OR(AO39<=0,AS39<=0),"NM",(AS39-AO39)/AO39) -> 0.11457066 | AV65: =IF(OR(AU39<=0,AV39<=0),"NM",(AV39-AU39)/AU39) -> NM | AW65: =IF(OR(AV39<=0,AW39<=0),"NM",(AW39-AV39)/AV39) -> NM | AX65: =IF(OR(AW39<=0,AX39<=0),"NM",(AX39-AW39)/AW39) -> NM | AY65: =IF(OR(AX39<=0,AY39<=0),"NM",(AY39-AX39)/AX39) -> 0.87270366 | AZ65: =IF(OR(AY39<=0,AZ39<=0),"NM",(AZ39-AY39)/AY39) -> 0.13800365 | BA65: =IF(OR(AZ39<=0,BA39<=0),"NM",(BA39-AZ39)/AZ39) -> 1.1923728 | BB65: =IF(OR(BA39<=0,BB39<=0),"NM",(BB39-BA39)/BA39) -> 0.63232978 | BC65: =IF(OR(BB39<=0,BC39<=0),"NM",(BC39-BB39)/BB39) -> 0.22599928 | ... BE65: =IF(OR(BD39<=0,BE39<=0),"NM",(BE39-BD39)/BD39) -> 0.10826368
A66: EPS | F66: =IF(OR(B46<=0,F46<=0),"NM",(F46-B46)/B46) -> NM | G66: =IF(OR(C46<=0,G46<=0),"NM",(G46-C46)/C46) -> NM | H66: =IF(OR(D46<=0,H46<=0),"NM",(H46-D46)/D46) -> NM | I66: =IF(OR(E46<=0,I46<=0),"NM",(I46-E46)/E46) -> NM | J66: =IF(OR(F46<=0,J46<=0),"NM",(J46-F46)/F46) -> NM | K66: =IF(OR(G46<=0,K46<=0),"NM",(K46-G46)/G46) -> NM | L66: =IF(OR(H46<=0,L46<=0),"NM",(L46-H46)/H46) -> NM | M66: =IF(OR(I46<=0,M46<=0),"NM",(M46-I46)/I46) -> NM | ... AS66: =IF(OR(AO46<=0,AS46<=0),"NM",(AS46-AO46)/AO46) -> 0.10223535 | AV66: =IF(OR(AU46<=0,AV46<=0),"NM",(AV46-AU46)/AU46) -> NM | AW66: =IF(OR(AV46<=0,AW46<=0),"NM",(AW46-AV46)/AV46) -> NM | AX66: =IF(OR(AW46<=0,AX46<=0),"NM",(AX46-AW46)/AW46) -> NM | AY66: =IF(OR(AX46<=0,AY46<=0),"NM",(AY46-AX46)/AX46) -> 0.79339203 | AZ66: =IF(OR(AY46<=0,AZ46<=0),"NM",(AZ46-AY46)/AY46) -> 0.1117742 | BA66: =IF(OR(AZ46<=0,BA46<=0),"NM",(BA46-AZ46)/AZ46) -> 1.1302597 | BB66: =IF(OR(BA46<=0,BB46<=0),"NM",(BB46-BA46)/BA46) -> 0.60051102 | BC66: =IF(OR(BB46<=0,BC46<=0),"NM",(BC46-BB46)/BB46) -> 0.2399018 | ... BE66: =IF(OR(BD46<=0,BE46<=0),"NM",(BE46-BD46)/BD46) -> 0.10056579
A68: Margin Analysis | B68: =B4 -> 42825 | C68: =C4 -> 42916 | D68: =D4 -> 43008 | E68: =E4 -> 43100 | F68: =F4 -> 43190 | G68: =G4 -> 43281 | H68: =H4 -> 43373 | I68: =I4 -> 43465 | ... AS68: =AS4 -> Dec-27E | AU68: =AU56 -> 2017 | AV68: =AV56 -> 2018 | AW68: =AW56 -> 2019 | AX68: =AX56 -> 2020 | AY68: =AY56 -> CY21 | AZ68: =AZ56 -> CY22 | BA68: =BA56 -> CY23 | BB68: =BB56 -> CY24 | ... BE68: =BE56 -> CY27E
A69: Gross Margin | B69: =+B17/B$9 -> 0.89543243 | C69: =+C17/C$9 -> 0.88341752 | D69: =+D17/D$9 -> 0.85279706 | E69: =+E17/E$9 -> 0.8500656 | F69: =+F17/F$9 -> 0.85619301 | G69: =+G17/G$9 -> 0.84881746 | H69: =+H17/H$9 -> 0.83701037 | I69: =+I17/I$9 -> 0.84811422 | ... AK69: =+AK17/AK$9 -> 0.82703151 | AL69: =AH69-0.001 -> 0.8180117 | AM69: =AI69-0.001 -> 0.81930773 | AN69: 0.822 | AO69: 0.827 | AP69: =AL69-0.001 -> 0.8170117 | AQ69: =AM69-0.001 -> 0.81830773 | AR69: =AN69-0.001 -> 0.821 | AS69: =AO69-0.001 -> 0.826 | AU69: =+AU17/AU$9 -> 0.86840465 | AV69: =+AV17/AV$9 -> 0.84718357 | AW69: =+AW17/AW$9 -> 0.83817466 | AX69: =+AX17/AX$9 -> 0.83625952 | AY69: =+AY17/AY$9 -> 0.82351191 | AZ69: =+AZ17/AZ$9 -> 0.80232761 | BA69: =+BA17/BA$9 -> 0.80159132 | BB69: =+BB17/BB$9 -> 0.81385545 | ... BE69: =+BE17/BE$9 -> 0.82066404
A70: Consensus Gross Margin | H70: =H18/H10 -> 0.82232901 | I70: =I18/I10 -> 0.82219588 | J70: =J18/J10 -> 0.8082627 | K70: =K18/K10 -> 0.82085107 | L70: =L18/L10 -> 0.83078381 | M70: =M18/M10 -> 0.83779344 | N70: =N18/N10 -> 0.81988574 | O70: =O18/O10 -> 0.83072799 | ... AS70: =AS18/AS10 -> 0.82406027 | AX70: =AX18/AX10 -> 0.83492909 | AY70: =AY18/AY10 -> 0.82439087 | AZ70: =AZ18/AZ10 -> 0.80878987 | BA70: =BA18/BA10 -> 0.79850944 | BB70: =BB18/BB10 -> 0.81241327 | BC70: =BC18/BC10 -> 0.81798626 | BD70: =BD18/BD10 -> 0.81979654 | BE70: =BE18/BE10 -> 0.8214392
A71: Sales and Marketing | B71: =+B21/B$9 -> 0.63975692 | C71: =+C21/C$9 -> 0.62096537 | D71: =+D21/D$9 -> 0.59544712 | E71: =+E21/E$9 -> 0.59578321 | F71: =+F21/F$9 -> 0.65958347 | G71: =+G21/G$9 -> 0.6471097 | H71: =+H21/H$9 -> 0.60257776 | I71: =+I21/I$9 -> 0.59096529 | ... AK71: =+AK21/AK$9 -> 0.34323867 | AL71: =+AH71-0.005 -> 0.35252728 | AM71: =+AI71-0.015 -> 0.34495471 | AN71: =+AJ71-0.015 -> 0.31338694 | AO71: =+AK71-0.015 -> 0.32823867 | AP71: =+AL71-0.005 -> 0.34752728 | AQ71: =+AM71-0.005 -> 0.33995471 | AR71: =+AN71-0.005 -> 0.30838694 | AS71: =+AO71-0.005 -> 0.32323867 | AU71: =+AU21/AU$9 -> 0.61110016 | AV71: =+AV21/AV$9 -> 0.62250524 | AW71: =+AW21/AW$9 -> 0.59788881 | AX71: =+AX21/AX$9 -> 0.46439175 | AY71: =+AY21/AY$9 -> 0.44467873 | AZ71: =+AZ21/AZ$9 -> 0.43918465 | BA71: =+BA21/BA$9 -> 0.41583053 | BB71: =+BB21/BB$9 -> 0.36961138 | ... BE71: =+BE21/BE$9 -> 0.32952612
A72: Research and Development | B72: =+B22/B$9 -> 0.29801635 | C72: =+C22/C$9 -> 0.3003692 | D72: =+D22/D$9 -> 0.31357697 | E72: =+E22/E$9 -> 0.28100227 | F72: =+F22/F$9 -> 0.28182787 | G72: =+G22/G$9 -> 0.26970374 | H72: =+H22/H$9 -> 0.26103111 | I72: =+I22/I$9 -> 0.25204398 | ... AK72: =+AK22/AK$9 -> 0.15675557 | AL72: =+AH72 -> 0.16315752 | AM72: =+AI72 -> 0.17551507 | AN72: =+AJ72 -> 0.16673665 | AO72: =+AK72 -> 0.15675557 | AP72: =+AL72 -> 0.16315752 | AQ72: =+AM72 -> 0.17551507 | AR72: =+AN72 -> 0.16673665 | AS72: =+AO72 -> 0.15675557 | AU72: =+AU22/AU$9 -> 0.29772489 | AV72: =+AV22/AV$9 -> 0.26516308 | AW72: =+AW22/AW$9 -> 0.22040633 | AX72: =+AX22/AX$9 -> 0.19738495 | AY72: =+AY22/AY$9 -> 0.17685214 | AZ72: =+AZ22/AZ$9 -> 0.16402587 | BA72: =+BA22/BA$9 -> 0.14515656 | BB72: =+BB22/BB$9 -> 0.14884986 | ... BE72: =+BE22/BE$9 -> 0.16546337
A73: General and administrative | B73: =+B23/B$9 -> 0.12981399 | C73: =+C23/C$9 -> 0.12582391 | D73: =+D23/D$9 -> 0.12717436 | E73: =+E23/E$9 -> 0.1435778 | F73: =+F23/F$9 -> 0.13301301 | G73: =+G23/G$9 -> 0.14067807 | H73: =+H23/H$9 -> 0.14854551 | I73: =+I23/I$9 -> 0.14830965 | ... AK73: =+AK23/AK$9 -> 0.082565356 | AL73: 0.093 | AM73: 0.089 | AN73: 0.089 | AO73: 0.08 | AP73: =+AL73-0.002 -> 0.091 | AQ73: =+AM73-0.002 -> 0.087 | AR73: =+AN73-0.002 -> 0.087 | AS73: =+AO73-0.002 -> 0.078 | AU73: =+AU23/AU$9 -> 0.13215467 | AV73: =+AV23/AV$9 -> 0.143174 | AW73: =+AW23/AW$9 -> 0.14048778 | AX73: =+AX23/AX$9 -> 0.11589179 | AY73: =+AY23/AY$9 -> 0.10776154 | AZ73: =+AZ23/AZ$9 -> 0.10006718 | BA73: =+BA23/BA$9 -> 0.089113696 | BB73: =+BB23/BB$9 -> 0.090823436 | ... BE73: =+BE23/BE$9 -> 0.085634157
A74: Total operating expenses | B74: =+B24/B$9 -> 1.0675873 | C74: =+C24/C$9 -> 1.0471585 | D74: =+D24/D$9 -> 1.0361984 | E74: =+E24/E$9 -> 1.0203633 | F74: =+F24/F$9 -> 1.0744243 | G74: =+G24/G$9 -> 1.0574915 | H74: =+H24/H$9 -> 1.0121544 | I74: =+I24/I$9 -> 0.99131891 | ... AS74: =+AS24/AS$9 -> 0.55799424 | AU74: =+AU24/AU$9 -> 1.0409797 | AV74: =+AV24/AV$9 -> 1.0308423 | AW74: =+AW24/AW$9 -> 0.95878292 | AX74: =+AX24/AX$9 -> 0.77766849 | AY74: =+AY24/AY$9 -> 0.72929241 | AZ74: =+AZ24/AZ$9 -> 0.70327771 | BA74: =+BA24/BA$9 -> 0.65010079 | BB74: =+BB24/BB$9 -> 0.60928467 | ... BE74: =+BE24/BE$9 -> 0.58062365
A75: Operating margin | B75: =+B25/B$9 -> -0.17215484 | C75: =+C25/C$9 -> -0.16374097 | D75: =+D25/D$9 -> -0.18340139 | E75: =+E25/E$9 -> -0.17029769 | F75: =+F25/F$9 -> -0.21823134 | G75: =+G25/G$9 -> -0.20867405 | H75: =+H25/H$9 -> -0.17514401 | I75: =+I25/I$9 -> -0.14320469 | ... AS75: =+AS25/AS$9 -> 0.26800576 | AU75: =+AU25/AU$9 -> -0.17257507 | AV75: =+AV25/AV$9 -> -0.18365874 | AW75: =+AW25/AW$9 -> -0.12060826 | AX75: =+AX25/AX$9 -> 0.058591026 | AY75: =+AY25/AY$9 -> 0.094219504 | AZ75: =+AZ25/AZ$9 -> 0.0990499 | BA75: =+BA25/BA$9 -> 0.15149053 | BB75: =+BB25/BB$9 -> 0.20457078 | ... BE75: =+BE25/BE$9 -> 0.24004039
A76: Consensus Operating margin | H76: =H26/H10 -> -0.25543932 | I76: =I26/I10 -> -0.18447417 | J76: =J26/J10 -> -0.20859379 | K76: =K26/K10 -> -0.17578036 | L76: =L26/L10 -> -0.12977776 | M76: =M26/M10 -> -0.13556189 | N76: =N26/N10 -> -0.17298549 | O76: =O26/O10 -> -0.045755892 | ... AS76: =AS26/AS10 -> 0.26093623 | AX76: =AX26/AX10 -> 0.044040925 | AY76: =AY26/AY10 -> 0.08745365 | AZ76: =AZ26/AZ10 -> 0.093160854 | BA76: =BA26/BA10 -> 0.13733551 | BB76: =BB26/BB10 -> 0.19275871 | BC76: =BC26/BC10 -> 0.21537416 | BD76: =BD26/BD10 -> 0.2343775 | BE76: =BE26/BE10 -> 0.24446054
A77: Net income | B77: =+B39/B$9 -> -0.1743781 | C77: =+C39/C$9 -> -0.16367302 | D77: =+D39/D$9 -> -0.18674969 | E77: =+E39/E$9 -> -0.17149879 | F77: =+F39/F$9 -> -0.22604768 | G77: =+G39/G$9 -> -0.22015348 | H77: =+H39/H$9 -> -0.17317108 | I77: =+I39/I$9 -> -0.14457399 | ... AS77: =+AS39/AS$9 -> 0.24165857 | AU77: =+AU39/AU$9 -> -0.17425836 | AV77: =+AV39/AV$9 -> -0.18798998 | AW77: =+AW39/AW$9 -> -0.11419797 | AX77: =+AX39/AX$9 -> 0.047235366 | AY77: =+AY39/AY$9 -> 0.071962375 | AZ77: =+AZ39/AZ$9 -> 0.06486473 | BA77: =+BA39/BA$9 -> 0.12163989 | BB77: =+BB39/BB$9 -> 0.17620589 | ... BE77: =+BE39/BE$9 -> 0.21167663
A78: Source: Company data, FactSet, Wells Fargo Securities, LLC estimates
A80: Non-GAAP Reconciliation to GAAP Results | B80: =B3 -> 2017 | F80: =F3 -> 2018 | J80: =J3 -> 2019 | N80: =N3 -> 2020 | R80: =R3 -> 2021 | V80: =V3 -> 2022 | Z80: =Z3 -> 2023 | AD80: =AD3 -> 2024 | AH80: =AH3 -> 2025 | AL80: =AL3 -> 2026 | AP80: =AP3 -> 2027
A81: Adjustments | AU81: =AU4 -> 2017 | AV81: =AV4 -> 2018 | AW81: =AW4 -> 2019 | AX81: =AX4 -> 2020 | AY81: =AY4 -> CY21 | AZ81: =AZ4 -> CY22 | BA81: =BA4 -> CY23 | BB81: =BB4 -> CY24 | ... BE81: =BE4 -> CY27E
A82: Share-based compensation | B82: =B83+B84 -> 1.626 | C82: =C83+C84 -> 1.849 | D82: =D83+D84 -> 2.028 | E82: =E83+E84 -> 2.257 | F82: =F83+F84 -> 2.399 | G82: =G83+G84 -> 3.024 | H82: =H83+H84 -> 8.783 | I82: =I83+I84 -> 8.669 | ... AS82: =AS83+AS84 -> 53.206438 | AU82: =SUM(B82:E82) -> 7.76 | AV82: =SUM(F82:I82) -> 22.875 | AW82: =SUM(J82:M82) -> 43.443 | AX82: =SUM(N82:Q82) -> 59.573 | AY82: =SUM(R82:U82) -> 79.405 | AZ82: =SUM(V82:Y82) -> 120.633 | BA82: =SUM(Z82:AC82) -> 145.327 | BB82: =SUM(AD82:AG82) -> 163.515 | BC82: =SUM(AH82:AK82) -> 191.813 | BD82: =SUM(AL82:AO82) -> 200.40001 | BE82: =SUM(AP82:AS82) -> 213.57809
A83: Cost of revenue | B83: =+B142 -> 0.054 | C83: =+C142 -> 0.05 | D83: =+D142 -> 0.063 | E83: =+E142 -> 0.114 | F83: =+F142 -> 0.077 | G83: =+G142 -> 0.114 | H83: =+H142 -> 0.692 | I83: =+I142 -> 0.824 | ... S83: =+S142 -> 1.202 | T83: =T142 -> 1.197 | U83: =U142 -> 1.11 | V83: =V142 -> 1.513 | W83: =W142 -> 2.114 | X83: =X142 -> 2.341 | Y83: =Y142 -> 2.401 | Z83: =Z142 -> 2.625 | AA83: =AA142 -> 2.906 | ... AS83: =AS142 -> 4.1176346 | AU83: =SUM(B83:E83) -> 0.281 | AV83: =SUM(F83:I83) -> 1.707 | AW83: =SUM(J83:M83) -> 2.817 | AX83: =SUM(N83:Q83) -> 3.158 | AY83: =SUM(R83:U83) -> 4.446 | AZ83: =SUM(V83:Y83) -> 8.369 | BA83: =SUM(Z83:AC83) -> 11.247 | BB83: =SUM(AD83:AG83) -> 12.677 | BC83: =SUM(AH83:AK83) -> 13.714 | BD83: =SUM(AL83:AO83) -> 15.508913 | BE83: =SUM(AP83:AS83) -> 16.528762
A84: OpEx | B84: =+B146 -> 1.572 | C84: =+C146 -> 1.799 | D84: =+D146 -> 1.965 | E84: =+E146 -> 2.143 | F84: =+F146 -> 2.322 | G84: =+G146 -> 2.91 | H84: =+H146 -> 8.091 | I84: =+I146 -> 7.845 | ... S84: =+S146 -> 19.267 | T84: =T146 -> 19.715 | U84: =U146 -> 19.962 | V84: =V146 -> 23.885 | W84: =W146 -> 29.799 | X84: =X146 -> 30.302 | Y84: =Y146 -> 28.278 | Z84: =Z146 -> 31.492 | AA84: =AA146 -> 34.954 | ... AS84: =AS146 -> 49.088804 | AU84: =SUM(B84:E84) -> 7.479 | AV84: =SUM(F84:I84) -> 21.168 | AW84: =SUM(J84:M84) -> 40.626 | AX84: =SUM(N84:Q84) -> 56.415 | AY84: =SUM(R84:U84) -> 74.959 | AZ84: =SUM(V84:Y84) -> 112.264 | BA84: =SUM(Z84:AC84) -> 134.08 | BB84: =SUM(AD84:AG84) -> 150.838 | BC84: =SUM(AH84:AK84) -> 178.099 | BD84: =SUM(AL84:AO84) -> 184.8911 | BE84: =SUM(AP84:AS84) -> 197.04933
A85: Amortization of acquired intangible assets | B85: =B86+B87 -> 0.151 | C85: =C86+C87 -> 0.151 | D85: =D86+D87 -> 0.151 | E85: =E86+E87 -> 0.15 | F85: =F86+F87 -> 0.151 | G85: =G86+G87 -> 0.151 | H85: =H86+H87 -> 0.151 | I85: =I86+I87 -> 0.15 | ... AS85: =AS86+AS87 -> 6.782 | AU85: =SUM(B85:E85) -> 0.603 | AV85: =SUM(F85:I85) -> 0.603 | AW85: =SUM(J85:M85) -> 0.62 | AX85: =SUM(N85:Q85) -> 2.314 | AY85: =SUM(R85:U85) -> 6.447 | AZ85: =SUM(V85:Y85) -> 11.372 | BA85: =SUM(Z85:AC85) -> 13.859 | BB85: =SUM(AD85:AG85) -> 19.457 | BC85: =SUM(AH85:AK85) -> 25.965 | BD85: =SUM(AL85:AO85) -> 27.128 | BE85: =SUM(AP85:AS85) -> 27.128
A86: Cost of revenue | B86: =B151 -> 0.151 | C86: =C151 -> 0.151 | D86: =D151 -> 0.151 | E86: =E151 -> 0.15 | F86: =F151 -> 0.151 | G86: =G151 -> 0.151 | H86: =H151 -> 0.151 | I86: =I151 -> 0.15 | ... AS86: =AS151 -> 6.782 | AU86: =SUM(B86:E86) -> 0.603 | AV86: =SUM(F86:I86) -> 0.603 | AW86: =SUM(J86:M86) -> 0.62 | AX86: =SUM(N86:Q86) -> 2.314 | AY86: =SUM(R86:U86) -> 6.447 | AZ86: =SUM(V86:Y86) -> 11.372 | BA86: =SUM(Z86:AC86) -> 13.859 | BB86: =SUM(AD86:AG86) -> 19.457 | BC86: =SUM(AH86:AK86) -> 25.965 | BD86: =SUM(AL86:AO86) -> 27.128 | BE86: =SUM(AP86:AS86) -> 27.128
A87: OpEx | B87: =+B155 -> 0 | C87: =+C155 -> 0 | D87: =+D155 -> 0 | E87: =+E155 -> 0 | F87: =+F155 -> 0 | G87: =+G155 -> 0 | H87: =+H155 -> 0 | I87: =+I155 -> 0 | ... S87: =+S155 -> 0 | T87: =T155 -> 0 | U87: =U155 -> 0 | V87: =V155 -> 0 | W87: =W155 -> 0 | X87: =X155 -> 0 | Y87: =Y155 -> 0 | Z87: =Z155 -> 0 | AA87: =AA155 -> 0 | ... AS87: =AS155 -> 0 | AU87: =SUM(B87:E87) -> 0 | AV87: =SUM(F87:I87) -> 0 | AW87: =SUM(J87:M87) -> 0 | AX87: =SUM(N87:Q87) -> 0 | AY87: =SUM(R87:U87) -> 0 | AZ87: =SUM(V87:Y87) -> 0 | BA87: =SUM(Z87:AC87) -> 0 | BB87: =SUM(AD87:AG87) -> 0 | BC87: =SUM(AH87:AK87) -> 0 | BD87: =SUM(AL87:AO87) -> 0 | BE87: =SUM(AP87:AS87) -> 0
A88: Acquisition related expenses | B88: =B89+B90 -> 0 | C88: =C89+C90 -> 0 | D88: =D89+D90 -> 0 | E88: =E89+E90 -> 0 | F88: =F89+F90 -> 0 | G88: =G89+G90 -> 0 | H88: =H89+H90 -> 0 | I88: =I89+I90 -> 0 | ... AS88: =AS89+AS90 -> 0.441 | AU88: =SUM(B88:E88) -> 0 | AV88: =SUM(F88:I88) -> 0 | AW88: =SUM(J88:M88) -> 3.97 | AX88: =SUM(N88:Q88) -> 0.339 | AY88: =SUM(R88:U88) -> 6.901 | AZ88: =SUM(V88:Y88) -> 3.48 | BA88: =SUM(Z88:AC88) -> 9.472 | BB88: =SUM(AD88:AG88) -> 1.932 | BC88: =SUM(AH88:AK88) -> 7.256 | BD88: =SUM(AL88:AO88) -> 1.764 | BE88: =SUM(AP88:AS88) -> 1.764
A89: Cost of revenue | B89: =B160 -> 0 | C89: =C160 -> 0 | D89: =D160 -> 0 | E89: =E160 -> 0 | F89: =F160 -> 0 | G89: =G160 -> 0 | H89: =H160 -> 0 | I89: =I160 -> 0 | ... AS89: =AS160 -> 0 | AU89: =SUM(B89:E89) -> 0 | AV89: =SUM(F89:I89) -> 0 | AW89: =SUM(J89:M89) -> 0 | AX89: =SUM(N89:Q89) -> 0 | AY89: =SUM(R89:U89) -> 0 | AZ89: =SUM(V89:Y89) -> 0 | BA89: =SUM(Z89:AC89) -> 0 | BB89: =SUM(AD89:AG89) -> 0 | BC89: =SUM(AH89:AK89) -> 0 | BD89: =SUM(AL89:AO89) -> 0 | BE89: =SUM(AP89:AS89) -> 0
A90: OpEx | B90: =+B164 -> 0 | C90: =+C164 -> 0 | D90: =+D164 -> 0 | E90: =+E164 -> 0 | F90: =+F164 -> 0 | G90: =+G164 -> 0 | H90: =+H164 -> 0 | I90: =+I164 -> 0 | ... S90: =+S164 -> 1.542 | T90: =T164 -> 2.27 | U90: =U164 -> 0.931 | V90: =V164 -> 2.179 | W90: =W164 -> 0.713 | X90: =X164 -> 0.322 | Y90: =Y164 -> 0.266 | Z90: =Z164 -> 0.1 | AA90: =AA164 -> 0.03 | ... AS90: =AS164 -> 0.441 | AU90: =SUM(B90:E90) -> 0 | AV90: =SUM(F90:I90) -> 0 | AW90: =SUM(J90:M90) -> 3.97 | AX90: =SUM(N90:Q90) -> 0.339 | AY90: =SUM(R90:U90) -> 6.901 | AZ90: =SUM(V90:Y90) -> 3.48 | BA90: =SUM(Z90:AC90) -> 9.472 | BB90: =SUM(AD90:AG90) -> 1.932 | BC90: =SUM(AH90:AK90) -> 7.256 | BD90: =SUM(AL90:AO90) -> 1.764 | BE90: =SUM(AP90:AS90) -> 1.764
A91: Other items | B91: =SUM(B92:B95) -> 0.177 | C91: =SUM(C92:C95) -> 0.179 | D91: =SUM(D92:D95) -> 0.179 | E91: =SUM(E92:E95) -> 0.174 | F91: =SUM(F92:F95) -> 0.165 | G91: =SUM(G92:G95) -> 0.166 | H91: =SUM(H92:H95) -> -0.035 | I91: =SUM(I92:I95) -> -0.08 | ... AS91: =SUM(AS92:AS95) -> 4.004 | AU91: =SUM(B91:E91) -> 0.709 | AV91: =SUM(F91:I91) -> 0.216 | AW91: =SUM(J91:M91) -> 10.487 | AX91: =SUM(N91:Q91) -> 1.299 | AY91: =SUM(R91:U91) -> -7.135 | AZ91: =SUM(V91:Y91) -> 1.052 | BA91: =SUM(Z91:AC91) -> 2.282 | BB91: =SUM(AD91:AG91) -> 3.916 | BC91: =SUM(AH91:AK91) -> 2.401 | BD91: =SUM(AL91:AO91) -> 13.816 | BE91: =SUM(AP91:AS91) -> 15.416
A92: Taxes impact of stock-based compensation | B92: =B169 -> -0.01 | C92: =C169 -> -0.012 | D92: =D169 -> -0.013 | E92: =E169 -> -0.019 | F92: =F169 -> -0.023 | G92: =G169 -> -0.025 | H92: =H169 -> -0.09 | I92: =I169 -> -0.08 | ... AS92: =AS169 -> 4.163 | AU92: =SUM(B92:E92) -> -0.054 | AV92: =SUM(F92:I92) -> -0.218 | AW92: =SUM(J92:M92) -> -0.095 | AX92: =SUM(N92:Q92) -> 1.299 | AY92: =SUM(R92:U92) -> 0.617 | AZ92: =SUM(V92:Y92) -> 2.103 | BA92: =SUM(Z92:AC92) -> 2.017 | BB92: =SUM(AD92:AG92) -> 2.845 | BC92: =SUM(AH92:AK92) -> 2.723 | BD92: =SUM(AL92:AO92) -> 14.452 | BE92: =SUM(AP92:AS92) -> 16.052
A93: Tax impact of acquistions | B93: =B170 -> 0 | C93: =C170 -> 0 | D93: =D170 -> 0 | E93: =E170 -> 0 | F93: =F170 -> 0 | G93: =G170 -> 0 | H93: =H170 -> 0 | I93: =I170 -> 0 | ... AS93: =AS170 -> -0.159 | AU93: =SUM(B93:E93) -> 0 | AV93: =SUM(F93:I93) -> 0 | AW93: =SUM(J93:M93) -> 10.582 | AX93: =SUM(N93:Q93) -> 0 | AY93: =SUM(R93:U93) -> -10.56 | AZ93: =SUM(V93:Y93) -> -3.703 | BA93: =SUM(Z93:AC93) -> 0.265 | BB93: =SUM(AD93:AG93) -> -0.161 | BC93: =SUM(AH93:AK93) -> -0.322 | BD93: =SUM(AL93:AO93) -> -0.636 | BE93: =SUM(AP93:AS93) -> -0.636
A94: Tax impact from intra-equity asset transfers | B94: =B171 -> 0 | C94: =C171 -> 0 | D94: =D171 -> 0 | E94: =E171 -> 0 | F94: =F171 -> 0 | G94: =G171 -> 0 | H94: =H171 -> 0 | I94: =I171 -> 0 | ... AS94: =AS171 -> 0 | AU94: =SUM(B94:E94) -> 0 | AV94: =SUM(F94:I94) -> 0 | AW94: =SUM(J94:M94) -> 0 | AX94: =SUM(N94:Q94) -> 0 | AY94: =SUM(R94:U94) -> 2.808 | AZ94: =SUM(V94:Y94) -> 2.652 | BA94: =SUM(Z94:AC94) -> 0 | BB94: =SUM(AD94:AG94) -> 1.232 | BC94: =SUM(AH94:AK94) -> 0 | BD94: =SUM(AL94:AO94) -> 0 | BE94: =SUM(AP94:AS94) -> 0
A95: Accretion from convertible preferred stock | B95: =-B130 -> 0.187 | C95: =-C130 -> 0.191 | D95: =-D130 -> 0.192 | E95: =-E130 -> 0.193 | F95: =-F130 -> 0.188 | G95: =-G130 -> 0.191 | H95: =-H130 -> 0.055 | I95: =-I130 -> 0 | ... AS95: =-AS130 -> 0 | AU95: =SUM(B95:E95) -> 0.763 | AV95: =SUM(F95:I95) -> 0.434 | AW95: =SUM(J95:M95) -> 0 | AX95: =SUM(N95:Q95) -> 0 | AY95: =SUM(R95:U95) -> 0 | AZ95: =SUM(V95:Y95) -> 0 | BA95: =SUM(Z95:AC95) -> 0 | BB95: =SUM(AD95:AG95) -> 0 | BC95: =SUM(AH95:AK95) -> 0 | BD95: =SUM(AL95:AO95) -> 0 | BE95: =SUM(AP95:AS95) -> 0
A97: GAAP Gross Profit | B97: =+B17-B83-B86-B89 -> 36.043 | C97: =+C17-C83-C86-C89 -> 38.801 | D97: =+D17-D83-D86-D89 -> 41.556 | E97: =+E17-E83-E86-E89 -> 45.739 | F97: =+F17-F83-F86-F89 -> 50.379 | G97: =+G17-G83-G86-G89 -> 53.713 | H97: =+H17-H83-H86-H89 -> 57.279 | I97: =+I17-I83-I86-I89 -> 62.822 | ... AS97: =+AS17-AS83-AS86-AS89 -> 233.2588 | AU97: =SUM(B97:E97) -> 162.139 | AV97: =SUM(F97:I97) -> 224.193 | AW97: =SUM(J97:M97) -> 293.768 | AX97: =SUM(N97:Q97) -> 362.667 | AY97: =SUM(R97:U97) -> 434.734 | AZ97: =SUM(V97:Y97) -> 528.402 | BA97: =SUM(Z97:AC97) -> 615.133 | BB97: =SUM(AD97:AG97) -> 700.353 | BC97: =SUM(AH97:AK97) -> 780.468 | BD97: =SUM(AL97:AO97) -> 836.7403 | BE97: =SUM(AP97:AS97) -> 892.40124
A98: GAAP Operating Income | B98: =+B25-B82-B85-B88 -> -8.746 | C98: =+C25-C82-C85-C88 -> -9.229 | D98: =+D25-D82-D85-D88 -> -11.162 | E98: =+E25-E82-E85-E88 -> -11.623 | F98: =+F25-F82-F85-F88 -> -15.449 | G98: =+G25-G82-G85-G88 -> -16.445 | H98: =+H25-H82-H85-H88 -> -21.096 | I98: =+I25-I82-I85-I88 -> -19.591 | ... AJ98: =+AJ25-AJ82-AJ85-AJ88 -> 7.136 | AK98: =+AK25-AK82-AK85-AK88-AK168 -> 8.855 | AL98: =+AL25-AL82-AL85-AL88 -> -7.3970412 | AM98: =+AM25-AM82-AM85-AM88 -> 0.70006495 | AN98: =+AN25-AN82-AN85-AN88 -> 12.362317 | AO98: =+AO25-AO82-AO85-AO88 -> 15.524462 | AP98: =+AP25-AP82-AP85-AP88 -> -5.7548697 | AQ98: =+AQ25-AQ82-AQ85-AQ88 -> 2.9197153 | AR98: =+AR25-AR82-AR85-AR88 -> 15.366905 | AS98: =+AS25-AS82-AS85-AS88 -> 18.790738 | AU98: =SUM(B98:E98) -> -40.76 | AV98: =SUM(F98:I98) -> -72.581 | AW98: =SUM(J98:M98) -> -90.799 | AX98: =SUM(N98:Q98) -> -36.433 | AY98: =SUM(R98:U98) -> -41.768 | AZ98: =SUM(V98:Y98) -> -67.815 | BA98: =SUM(Z98:AC98) -> -47.661 | BB98: =SUM(AD98:AG98) -> -0.786 | BC98: =SUM(AH98:AK98) -> -9.168 | BD98: =SUM(AL98:AO98) -> 21.189803 | BE98: =SUM(AP98:AS98) -> 31.322489
A99: GAAP Net income | B99: =+B39-B82-B85-B88-B91 -> -9.013 | C99: =+C39-C82-C85-C88-C91 -> -9.405 | D99: =+D39-D82-D85-D88-D91 -> -11.505 | E99: =+E39-E82-E85-E88-E91 -> -11.862 | F99: =+F39-F82-F85-F88-F91 -> -16.076 | G99: =+G39-G82-G85-G88-G91 -> -17.341 | H99: =+H39-H82-H85-H88-H91 -> -20.924 | I99: =+I39-I82-I85-I88-I91 -> -19.614 | ... AJ99: =+AJ39-AJ82-AJ85-AJ88-AJ91 -> 2.26 | AK99: =+AK39-AK82-AK85-AK88-AK91-AK168 -> -0.737 | AL99: =+AL39-AL82-AL85-AL88-AL91 -> -16.964041 | AM99: =+AM39-AM82-AM85-AM88-AM91 -> -11.691935 | AN99: =+AN39-AN82-AN85-AN88-AN91 -> 0.070317379 | AO99: =+AO39-AO82-AO85-AO88-AO91 -> 3.3324622 | AP99: =+AP39-AP82-AP85-AP88-AP91 -> -17.84687 | AQ99: =+AQ39-AQ82-AQ85-AQ88-AQ91 -> -9.0722847 | AR99: =+AR39-AR82-AR85-AR88-AR91 -> 3.4749053 | AS99: =+AS39-AS82-AS85-AS88-AS91 -> 6.9987383 | AU99: =SUM(B99:E99) -> -41.785 | AV99: =SUM(F99:I99) -> -73.955 | AW99: =SUM(J99:M99) -> -99.013 | AX99: =SUM(N99:Q99) -> -42.731 | AY99: =SUM(R99:U99) -> -46.677 | AZ99: =SUM(V99:Y99) -> -92.222 | BA99: =SUM(Z99:AC99) -> -73.785 | BB99: =SUM(AD99:AG99) -> -30.231 | BC99: =SUM(AH99:AK99) -> -36.118 | BD99: =SUM(AL99:AO99) -> -25.253197 | BE99: =SUM(AP99:AS99) -> -16.445511
A100: GAAP EPS | B100: -0.42671745 | C100: =IF(C99<0,C99/C102,C99/C103) -> -0.42633726 | D100: =IF(D99<0,D99/D102,D99/D103) -> -0.5072975 | E100: =IF(E99<0,E99/E102,E99/E103) -> -0.51964779 | F100: =IF(F99<0,F99/F102,F99/F103) -> -0.68423069 | G100: =IF(G99<0,G99/G102,G99/G103) -> -0.73014737 | H100: =IF(H99<0,H99/H102,H99/H103) -> -0.28176297 | I100: =IF(I99<0,I99/I102,I99/I103) -> -0.21276319 | J100: =IF(J99<0,J99/J102,J99/J103) -> -0.22872261 | ... AS100: =IF(AS99<0,AS99/AS102,AS99/AS103) -> 0.058679788 | AU100: =SUM(B100:E100) -> -1.88 | AV100: =SUM(F100:I100) -> -1.9089042 | AW100: =IF(AW99<0,AW99/AW102,AW99/AW103) -> -1.031235 | AX100: =IF(AX99<0,AX99/AX102,AX99/AX103) -> -0.42304151 | AY100: =IF(AY99<0,AY99/AY102,AY99/AY103) -> -0.43874722 | AZ100: =IF(AZ99<0,AZ99/AZ102,AZ99/AZ103) -> -0.82843309 | BA100: =IF(BA99<0,BA99/BA102,BA99/BA103) -> -0.63939029 | BB100: =IF(BB99<0,BB99/BB102,BB99/BB103) -> -0.25450183 | BC100: =IF(BC99<0,BC99/BC102,BC99/BC103) -> -0.30067326 | BD100: =IF(BD99<0,BD99/BD102,BD99/BD103) -> -0.21141228 | BE100: =IF(BE99<0,BE99/BE102,BE99/BE103) -> -0.136761
A101: Consensus GAAP EPS | B101: ='[2]VA Consensus'!C35 -> - | C101: ='[2]VA Consensus'!D35 -> - | D101: ='[2]VA Consensus'!E35 -> - | E101: ='[2]VA Consensus'!F35 -> - | F101: ='[2]VA Consensus'!G35 -> - | G101: ='[2]VA Consensus'!H35 -> - | H101: ='[2]VA Consensus'!I35 -> -0.25184083 | I101: ='[2]VA Consensus'!J35 -> -0.22992843 | ... AS101: ='[2]VA Consensus'!AT35 -> 0.11878749 | AU101: ='[2]VA Consensus'!AV35 -> - | AV101: ='[2]VA Consensus'!AW35 -> -0.86621 | AW101: ='[2]VA Consensus'!AX35 -> -0.99003801 | AX101: ='[2]VA Consensus'!AY35 -> -0.46178916 | AY101: ='[2]VA Consensus'!AZ35 -> -0.40536131 | AZ101: ='[2]VA Consensus'!BA35 -> -0.70694492 | BA101: ='[2]VA Consensus'!BB35 -> -0.60718521 | BB101: ='[2]VA Consensus'!BC35 -> -0.34700438 | ... BE101: ='[2]VA Consensus'!BF35 -> 0.24425802
A102: Basic shares outstanding | B102: =B52 -> 0 | C102: =C52 -> 22.06 | D102: =D52 -> 22.679 | E102: =E52 -> 22.827 | F102: =F52 -> 23.495 | G102: =G52 -> 23.75 | H102: =H52 -> 74.261 | I102: =I52 -> 92.187 | ... AS102: =AS52 -> 120.55 | AV102: =AV52 -> 53.669 | AW102: =AW52 -> 96.014 | AX102: =AX52 -> 101.009 | AY102: =AY52 -> 106.387 | AZ102: =AZ52 -> 111.321 | BA102: =BA52 -> 115.399 | BB102: =BB52 -> 118.785 | BC102: =BC52 -> 120.12375 | ... BE102: =BE52 -> 120.25
A103: Diluted shares outstanding | B103: =B53 -> 0 | C103: =C53 -> 77.446 | D103: =D53 -> 78.065 | E103: =E53 -> 78.213 | F103: =F53 -> 78.881 | G103: =G53 -> 79.136 | H103: =H53 -> 88.71 | I103: =I53 -> 92.187 | ... AS103: =AS53 -> 119.27 | AV103: =AV53 -> 84.774 | AW103: =AW53 -> 96.014 | AX103: =AX53 -> 109.962 | AY103: =AY53 -> 114.825 | AZ103: =AZ53 -> 117.534 | BA103: =BA53 -> 120.961 | BB103: =BB53 -> 123.36575 | BC103: =BC53 -> 121.9825 | ... BE103: =BE53 -> 118.775
A105: GAAP Inputs | B105: =B3 -> 2017 | F105: =F3 -> 2018 | J105: =J3 -> 2019 | N105: =N3 -> 2020 | R105: =R3 -> 2021 | V105: =V3 -> 2022 | Z105: =Z3 -> 2023 | AD105: =AD3 -> 2024 | AH105: =AH3 -> 2025 | AL105: =AL3 -> 2026 | AP105: =AP3 -> 2027
A106: Revenue | AU106: =AU81 -> 2017 | AV106: =AV81 -> 2018 | AW106: =AW81 -> 2019 | AX106: =AX81 -> 2020 | AY106: =AY81 -> CY21 | AZ106: =AZ81 -> CY22 | BA106: =BA81 -> CY23 | BB106: =BB81 -> CY24 | ... BE106: =BE81 -> CY27E
A107: Subscription | B107: ='Revenue Build'!B13 -> 27.702 | C107: ='Revenue Build'!C13 -> 30.844 | D107: ='Revenue Build'!D13 -> 34.932 | E107: ='Revenue Build'!E13 -> 39.395 | F107: ='Revenue Build'!F13 -> 44.332 | G107: ='Revenue Build'!G13 -> 48.725 | H107: ='Revenue Build'!H13 -> 53.511 | I107: ='Revenue Build'!I13 -> 59.259 | ... AS107: ='Revenue Build'!AS13 -> 275.96222 | AU107: =+SUM(B107:E107) -> 132.873 | AV107: =+SUM(F107:I107) -> 205.827 | AW107: =SUM(J107:M107) -> 290.549 | AX107: =+SUM(N107:Q107) -> 377.354 | AY107: =+SUM(R107:U107) -> 476.023 | AZ107: =+SUM(V107:Y107) -> 612.51 | BA107: =+SUM(Z107:AC107) -> 725.013 | BB107: =SUM(AD107:AG107) -> 824.659 | BC107: =SUM(AH107:AK107) -> 919.573 | BD107: =SUM(AL107:AO107) -> 995.23014 | BE107: =SUM(AP107:AS107) -> 1069.6212
A108: Perpetual Licnese and Maintenance | B108: ='Revenue Build'!B18 -> 11.989 | C108: ='Revenue Build'!C18 -> 12.283 | D108: ='Revenue Build'!D18 -> 12.857 | E108: ='Revenue Build'!E18 -> 13.208 | F108: ='Revenue Build'!F18 -> 13.477 | G108: ='Revenue Build'!G18 -> 13.412 | H108: ='Revenue Build'!H18 -> 13.864 | I108: ='Revenue Build'!I18 -> 13.869 | ... AS108: ='Revenue Build'!AS18 -> 8.5941 | AU108: =+SUM(B108:E108) -> 50.337 | AV108: =+SUM(F108:I108) -> 54.622 | AW108: =SUM(J108:M108) -> 54.173 | AX108: =+SUM(N108:Q108) -> 50.594 | AY108: =+SUM(R108:U108) -> 50.333 | AZ108: =+SUM(V108:Y108) -> 50.699 | BA108: =+SUM(Z108:AC108) -> 48.729 | BB108: =SUM(AD108:AG108) -> 47.774 | BC108: =SUM(AH108:AK108) -> 44.661 | BD108: =SUM(AL108:AO108) -> 40.1949 | BE108: =SUM(AP108:AS108) -> 36.17541
A109: Professional Services and Other | B109: ='Revenue Build'!B23 -> 0.79 | C109: ='Revenue Build'!C23 -> 1.022 | D109: ='Revenue Build'!D23 -> 1.191 | E109: ='Revenue Build'!E23 -> 1.514 | F109: ='Revenue Build'!F23 -> 1.298 | G109: ='Revenue Build'!G23 -> 1.455 | H109: ='Revenue Build'!H23 -> 2.065 | I109: ='Revenue Build'!I23 -> 2.093 | ... AS109: ='Revenue Build'!AS23 -> 11.035 | AU109: =+SUM(B109:E109) -> 4.517 | AV109: =+SUM(F109:I109) -> 6.911 | AW109: =SUM(J109:M109) -> 9.864 | AX109: =+SUM(N109:Q109) -> 12.273 | AY109: =+SUM(R109:U109) -> 14.774 | AZ109: =+SUM(V109:Y109) -> 19.982 | BA109: =+SUM(Z109:AC109) -> 24.968 | BB109: =SUM(AD109:AG109) -> 27.588 | BC109: =SUM(AH109:AK109) -> 35.171 | BD109: =SUM(AL109:AO109) -> 34.8139 | BE109: =SUM(AP109:AS109) -> 34.8139
...

Sheet Revenue Build
A1: =+'Income Statement'!A1 -> Tenable Holdings, Inc. (TENB)
A2: Revenue Build | R2: ='Income Statement'!R2 -> 2021/1F | S2: ='Income Statement'!S2 -> 2021/2F | T2: ='Income Statement'!T2 -> 2021/3F | U2: ='Income Statement'!U2 -> 2021/4F | V2: ='Income Statement'!V2 -> 2022/1F | W2: ='Income Statement'!W2 -> 2022/2F | X2: ='Income Statement'!X2 -> 2022/3F | Y2: ='Income Statement'!Y2 -> 2022/4F | ... AS2: ='Income Statement'!AS2 -> 2027/4F | AX2: ='Income Statement'!AX2 -> 2020 | AY2: ='Income Statement'!AY2 -> 2021 | AZ2: ='Income Statement'!AZ2 -> 2022 | BA2: ='Income Statement'!BA2 -> 2023 | BB2: ='Income Statement'!BB2 -> 2024 | BC2: ='Income Statement'!BC2 -> 2025 | BD2: ='Income Statement'!BD2 -> 2026 | BE2: ='Income Statement'!BE2 -> 2027
B3: ='Income Statement'!B$3 -> 2017 | F3: ='Income Statement'!F$3 -> 2018 | J3: ='Income Statement'!J$3 -> 2019 | N3: ='Income Statement'!N$3 -> 2020 | R3: ='Income Statement'!R$3 -> 2021 | V3: ='Income Statement'!V$3 -> 2022 | Z3: ='Income Statement'!Z$3 -> 2023 | AD3: ='Income Statement'!AD$3 -> 2024 | AH3: ='Income Statement'!AH$3 -> 2025 | AL3: ='Income Statement'!AL$3 -> 2026 | AP3: ='Income Statement'!AP$3 -> 2027
A4: ='Income Statement'!A4 -> ($ in millions, unless otherwise stated) | B4: ='Income Statement'!B$4 -> 42825 | C4: ='Income Statement'!C$4 -> 42916 | D4: ='Income Statement'!D$4 -> 43008 | E4: ='Income Statement'!E$4 -> 43100 | F4: ='Income Statement'!F$4 -> 43190 | G4: ='Income Statement'!G$4 -> 43281 | H4: ='Income Statement'!H$4 -> 43373 | I4: ='Income Statement'!I$4 -> 43465 | ... AS4: ='Income Statement'!AS$4 -> Dec-27E | AU4: ='Income Statement'!AU$4 -> 2017 | AV4: ='Income Statement'!AV$4 -> 2018 | AW4: ='Income Statement'!AW$4 -> 2019 | AX4: ='Income Statement'!AX$4 -> 2020 | AY4: ='Income Statement'!AY$4 -> CY21 | AZ4: ='Income Statement'!AZ$4 -> CY22 | BA4: ='Income Statement'!BA$4 -> CY23 | BB4: ='Income Statement'!BB$4 -> CY24 | ... BE4: ='Income Statement'!BE$4 -> CY27E
A5: Total Revenue | B5: =B13+B18+B23 -> 40.481 | C5: 44.149 | D5: =D13+D18+D23 -> 48.98 | E5: =E13+E18+E23 -> 54.117 | F5: =F13+F18+F23 -> 59.107 | G5: =G13+G18+G23 -> 63.592 | H5: =H13+H18+H23 -> 69.44 | I5: =I13+I18+I23 -> 75.221 | J5: =J13+J18+J23 -> 80.301 | K5: =K13+K18+K23 -> 85.384 | ... AS5: =AS13+AS18+AS23 -> 295.59132 | AU5: =SUM(B5:E5) -> 187.727 | AV5: =SUM(F5:I5) -> 267.36 | AW5: =SUM(J5:M5) -> 354.586 | AX5: =SUM(N5:Q5) -> 440.221 | AY5: =SUM(R5:U5) -> 541.13 | AZ5: =SUM(V5:Y5) -> 683.191 | BA5: =SUM(Z5:AC5) -> 798.71 | BB5: =SUM(AD5:AG5) -> 900.021 | BC5: =SUM(AH5:AK5) -> 999.405 | BD5: =SUM(AL5:AO5) -> 1070.2389 | BE5: =SUM(AP5:AS5) -> 1140.6105
A6: Consensus revenue | B6: ='Income Statement'!B10 -> - | C6: ='Income Statement'!C10 -> - | D6: ='Income Statement'!D10 -> - | E6: ='Income Statement'!E10 -> - | F6: ='Income Statement'!F10 -> - | G6: ='Income Statement'!G10 -> - | H6: ='Income Statement'!H10 -> 66.295101 | I6: ='Income Statement'!I10 -> 72.829307 | ... AD6: ='Income Statement'!AD10 -> 213.54153 | AE6: 218.54245 | AF6: 223.26996 | AG6: ='Income Statement'!AG10 -> 231.55654 | AH6: ='Income Statement'!AH10 -> 233.57912 | AI6: ='Income Statement'!AI10 -> 242.07841 | AJ6: ='Income Statement'!AJ10 -> 247.33865 | AK6: ='Income Statement'!AK10 -> 251.72895 | AL6: ='Income Statement'!AL10 -> 258.87608 | AM6: ='Income Statement'!AM10 -> 264.67593 | AN6: ='Income Statement'!AN10 -> 269.71728 | ... AS6: ='Income Statement'!AS10 -> 296.33303 | AX6: ='Income Statement'!AX10 -> 437.03012 | AY6: ='Income Statement'!AY10 -> 536.56619 | AZ6: ='Income Statement'!AZ10 -> 680.03864 | BA6: ='Income Statement'!BA10 -> 791.94039 | BB6: ='Income Statement'!BB10 -> 895.84654 | BC6: ='Income Statement'!BC10 -> 990.66282 | BD6: ='Income Statement'!BD10 -> 1070.3484 | BE6: ='Income Statement'!BE10 -> 1145.8385
A7: Y/Y Growth | B7: =IF(ISERROR(B5/#REF!-1),"NA",B5/#REF!-1) -> NA | C7: =IF(ISERROR(C5/#REF!-1),"NA",C5/#REF!-1) -> NA | D7: =IF(ISERROR(D5/#REF!-1),"NA",D5/#REF!-1) -> NA | E7: =IF(ISERROR(E5/#REF!-1),"NA",E5/#REF!-1) -> NA | F7: =IF(ISERROR(F5/B5-1),"NA",F5/B5-1) -> 0.46011709 | G7: =IF(ISERROR(G5/C5-1),"NA",G5/C5-1) -> 0.44039503 | H7: =IF(ISERROR(H5/D5-1),"NA",H5/D5-1) -> 0.41772152 | I7: =IF(ISERROR(I5/E5-1),"NA",I5/E5-1) -> 0.38996988 | J7: =IF(ISERROR(J5/F5-1),"NA",J5/F5-1) -> 0.35857005 | K7: =IF(ISERROR(K5/G5-1),"NA",K5/G5-1) -> 0.34268461 | L7: =IF(ISERROR(L5/H5-1),"NA",L5/H5-1) -> 0.32275346 | M7: =IF(ISERROR(M5/I5-1),"NA",M5/I5-1) -> 0.29018492 | ... AS7: =IF(ISERROR(AS5/AO5-1),"NA",AS5/AO5-1) -> 0.065621742 | AU7: =IF(ISERROR(AU5/#REF!-1),"NA",AU5/#REF!-1) -> NA | AV7: =IF(ISERROR(AV5/AU5-1),"NA",AV5/AU5-1) -> 0.42419577 | AW7: =IF(ISERROR(AW5/AV5-1),"NA",AW5/AV5-1) -> 0.32624925 | AX7: =IF(ISERROR(AX5/AW5-1),"NA",AX5/AW5-1) -> 0.241507 | AY7: =IF(ISERROR(AY5/AX5-1),"NA",AY5/AX5-1) -> 0.2292235 | AZ7: =IF(ISERROR(AZ5/AY5-1),"NA",AZ5/AY5-1) -> 0.26252656 | BA7: =IF(ISERROR(BA5/AZ5-1),"NA",BA5/AZ5-1) -> 0.16908741 | BB7: =IF(ISERROR(BB5/BA5-1),"NA",BB5/BA5-1) -> 0.12684328 | BC7: =IF(ISERROR(BC5/BB5-1),"NA",BC5/BB5-1) -> 0.11042409 | ... BE7: =IF(ISERROR(BE5/BD5-1),"NA",BE5/BD5-1) -> 0.065753111
A8: Management Guidance - Revenue
A9: Low | N9: 100 | O9: 101 | P9: 108 | Q9: 113 | R9: 118 | S9: 124 | T9: 133 | U9: 143 | V9: 152 | W9: 162 | X9: 169 | Y9: 180 | Z9: 186 | AA9: 189 | AB9: 197 | AC9: 204 | AD9: 212 | AE9: 217 | AF9: 222 | AG9: 229 | AH9: 233 | AI9: 241 | AJ9: 246 | AK9: 249.1 | AL9: 257 | AY9: 535.1 | AZ9: 678.6 | BA9: 789.4 | BB9: 893.3 | BC9: 988 | BD9: 1065
A10: Mid | N10: =AVERAGE(N9,N11) -> 100.5 | O10: =AVERAGE(O9,O11) -> 102 | P10: =AVERAGE(P9,P11) -> 109 | Q10: =AVERAGE(Q9,Q11) -> 114 | R10: =AVERAGE(R9,R11) -> 119 | S10: =AVERAGE(S9,S11) -> 125 | T10: =AVERAGE(T9,T11) -> 134 | U10: =AVERAGE(U9,U11) -> 144 | ... AB10: =AVERAGE(AB9,AB11) -> 198 | AC10: =IFERROR(AVERAGE(AC9,AC11),"") -> 206 | AD10: =IFERROR(AVERAGE(AD9,AD11),"") -> 213 | AE10: =IFERROR(AVERAGE(AE9,AE11),"") -> 218 | AF10: =IFERROR(AVERAGE(AF9,AF11),"") -> 223 | AG10: =IFERROR(AVERAGE(AG9,AG11),"") -> 231 | AH10: =IFERROR(AVERAGE(AH9,AH11),"") -> 234 | AI10: =IFERROR(AVERAGE(AI9,AI11),"") -> 242 | AJ10: =IFERROR(AVERAGE(AJ9,AJ11),"") -> 247 | ... AS10: =IFERROR(AVERAGE(AS9,AS11),"") | AY10: =AVERAGE(AY9,AY11) -> 536.1 | AZ10: =AVERAGE(AZ9,AZ11) -> 679.6 | BA10: =AVERAGE(BA9,BA11) -> 791.4 | BB10: =IFERROR(AVERAGE(BB9,BB11),"") -> 895.3 | BC10: =IFERROR(AVERAGE(BC9,BC11),"") -> 990 | BD10: =IFERROR(AVERAGE(BD9,BD11),"") -> 1070 | BE10: =IFERROR(AVERAGE(BE9,BE11),"")
A11: High | N11: 101 | O11: 103 | P11: 110 | Q11: 115 | R11: 120 | S11: 126 | T11: 135 | U11: 145 | V11: 154 | W11: 164 | X11: 171 | Y11: 182 | Z11: 188 | AA11: 191 | AB11: 199 | AC11: 208 | AD11: 214 | AE11: 219 | AF11: 224 | AG11: 233 | AH11: 235 | AI11: 243 | AJ11: 248 | AK11: 253.1 | AL11: 260 | AY11: 537.1 | AZ11: 680.6 | BA11: 793.4 | BB11: 897.3 | BC11: 992 | BD11: 1075
A12: Revenue by Type
A13: Subscription | B13: 27.702 | C13: =132.873-B13-D13-E13 -> 30.844 | D13: 34.932 | E13: 39.395 | F13: 44.332 | G13: 48.725 | H13: 53.511 | I13: 59.259 | J13: 64.737 | K13: 69.37 | L13: 75.503 | M13: 80.939 | N13: 86.39 | O13: 92.01 | P13: 96.792 | Q13: 102.162 | R13: 107.402 | S13: 114.167 | T13: 122.156 | U13: 132.298 | V13: 142.687 | W13: 146.806 | X13: 156.764 | Y13: 166.253 | Z13: 171.098 | AA13: 176.767 | AB13: 183.268 | AC13: 193.88 | AD13: 197.635 | AE13: 202.538 | AF13: 208.554 | AG13: 215.932 | AH13: 220.443 | AI13: 228.031 | AJ13: 232.211 | AK13: 238.888 | AL13: =AH13*(1+AL15) -> 241.38509 | AM13: =AI13*(1+AM15) -> 247.41363 | AN13: =AJ13*(1+AN15) -> 249.62682 | AO13: =AK13*(1+AO15) -> 256.8046 | AP13: =AL13*(1+AP15) -> 259.46483 | AQ13: =AM13*(1+AQ15) -> 265.92017 | AR13: =AN13*(1+AR15) -> 268.27395 | AS13: =AO13*(1+AS15) -> 275.96222 | AU13: =SUM(B13:E13) -> 132.873 | AV13: =SUM(F13:I13) -> 205.827 | AW13: =SUM(J13:M13) -> 290.549 | AX13: =SUM(N13:Q13) -> 377.354 | AY13: =SUM(R13:U13) -> 476.023 | AZ13: =SUM(V13:Y13) -> 612.51 | BA13: =SUM(Z13:AC13) -> 725.013 | BB13: =SUM(AD13:AG13) -> 824.659 | BC13: =SUM(AH13:AK13) -> 919.573 | BD13: =SUM(AL13:AO13) -> 995.23014 | BE13: =SUM(AP13:AS13) -> 1069.6212
A14: Consensus subscription revenue | B14: ='[2]VA Consensus'!C18 -> - | C14: ='[2]VA Consensus'!D18 -> - | D14: ='[2]VA Consensus'!E18 -> - | E14: ='[2]VA Consensus'!F18 -> - | F14: ='[2]VA Consensus'!G18 -> - | G14: ='[2]VA Consensus'!H18 -> - | H14: ='[2]VA Consensus'!I18 -> 55.628656 | I14: ='[2]VA Consensus'!J18 -> 61.298786 | ... AS14: ='[2]VA Consensus'!AT18 -> 275.49041 | AU14: ='[2]VA Consensus'!AV18 -> - | AV14: ='[2]VA Consensus'!AW18 -> 219.33527 | AW14: ='[2]VA Consensus'!AX18 -> 290.64225 | AX14: ='[2]VA Consensus'!AY18 -> 374.87473 | AY14: ='[2]VA Consensus'!AZ18 -> 471.94538 | AZ14: ='[2]VA Consensus'!BA18 -> 610.65686 | BA14: ='[2]VA Consensus'!BB18 -> 719.17729 | BB14: ='[2]VA Consensus'!BC18 -> 821.32236 | ... BE14: ='[2]VA Consensus'!BF18 -> 1067.1284
A15: Y/Y Growth | F15: =F13/B13-1 -> 0.60031767 | G15: =G13/C13-1 -> 0.57972377 | H15: =H13/D13-1 -> 0.5318619 | I15: =I13/E13-1 -> 0.50422642 | J15: =J13/F13-1 -> 0.460277 | K15: =K13/G13-1 -> 0.42370446 | L15: =L13/H13-1 -> 0.41098092 | M15: =M13/I13-1 -> 0.3658516 | ... AK15: =AK13/AG13-1 -> 0.10631125 | AL15: 0.095 | AM15: 0.085 | AN15: 0.075 | AO15: 0.075 | AP15: =+AO15-0.0001 -> 0.0749 | AQ15: =+AP15-0.0001 -> 0.0748 | AR15: =+AQ15-0.0001 -> 0.0747 | AS15: =+AR15-0.0001 -> 0.0746 | AU15: =IF(ISERROR(AU13/#REF!-1),"NA",AU13/#REF!-1) -> NA | AV15: =IF(ISERROR(AV13/AU13-1),"NA",AV13/AU13-1) -> 0.5490506 | AW15: =IF(ISERROR(AW13/AV13-1),"NA",AW13/AV13-1) -> 0.41161752 | AX15: =IF(ISERROR(AX13/AW13-1),"NA",AX13/AW13-1) -> 0.298762 | AY15: =IF(ISERROR(AY13/AX13-1),"NA",AY13/AX13-1) -> 0.26147596 | AZ15: =IF(ISERROR(AZ13/AY13-1),"NA",AZ13/AY13-1) -> 0.28672354 | BA15: =IF(ISERROR(BA13/AZ13-1),"NA",BA13/AZ13-1) -> 0.18367537 | BB15: =IF(ISERROR(BB13/BA13-1),"NA",BB13/BA13-1) -> 0.13744029 | BC15: =IF(ISERROR(BC13/BB13-1),"NA",BC13/BB13-1) -> 0.11509485 | ... BE15: =IF(ISERROR(BE13/BD13-1),"NA",BE13/BD13-1) -> 0.074747565
A16: % of total revenue | B16: =B13/B$5 -> 0.68432104 | C16: =C13/C$5 -> 0.69863417 | D16: =D13/D$5 -> 0.71318906 | E16: =E13/E$5 -> 0.72795979 | F16: =F13/F$5 -> 0.75002961 | G16: =G13/G$5 -> 0.76621273 | H16: =H13/H$5 -> 0.77060772 | I16: =I13/I$5 -> 0.78779862 | ... AS16: =AS13/AS$5 -> 0.93359379 | AU16: =AU13/AU$5 -> 0.70779909 | AV16: =AV13/AV$5 -> 0.76984964 | AW16: =AW13/AW$5 -> 0.81940347 | AX16: =AX13/AX$5 -> 0.85719218 | AY16: =AY13/AY$5 -> 0.87968326 | AZ16: =AZ13/AZ$5 -> 0.89654284 | BA16: =BA13/BA$5 -> 0.90772996 | BB16: =BB13/BB$5 -> 0.9162664 | ... BE16: =BE13/BE$5 -> 0.937762
A18: Perpetual License and Maintenance | B18: 11.989 | C18: =50.337-B18-D18-E18 -> 12.283 | D18: 12.857 | E18: 13.208 | F18: 13.477 | G18: 13.412 | H18: 13.864 | I18: 13.869 | J18: 13.527 | K18: 13.553 | L18: 13.797 | M18: 13.296 | N18: 13.419 | O18: 12.179 | P18: 12.448 | Q18: 12.548 | R18: 12.405 | S18: 12.567 | T18: 12.749 | U18: 12.612 | V18: 12.873 | W18: 12.683 | X18: 12.658 | Y18: 12.485 | Z18: 12.181 | AA18: 12.154 | AB18: 12.2 | AC18: 12.194 | AD18: 12.156 | AE18: 12.016 | AF18: 11.769 | AG18: 11.833 | AH18: 11.552 | AI18: 11.411 | AJ18: 11.088 | AK18: 10.61 | AL18: =AH18*(1+AL20) -> 10.3968 | AM18: =AI18*(1+AM20) -> 10.2699 | AN18: =AJ18*(1+AN20) -> 9.9792 | AO18: =AK18*(1+AO20) -> 9.549 | AP18: =AL18*(1+AP20) -> 9.35712 | AQ18: =AM18*(1+AQ20) -> 9.24291 | AR18: =AN18*(1+AR20) -> 8.98128 | AS18: =AO18*(1+AS20) -> 8.5941 | AU18: =SUM(B18:E18) -> 50.337 | AV18: =SUM(F18:I18) -> 54.622 | AW18: =SUM(J18:M18) -> 54.173 | AX18: =SUM(N18:Q18) -> 50.594 | AY18: =SUM(R18:U18) -> 50.333 | AZ18: =SUM(V18:Y18) -> 50.699 | BA18: =SUM(Z18:AC18) -> 48.729 | BB18: =SUM(AD18:AG18) -> 47.774 | BC18: =SUM(AH18:AK18) -> 44.661 | BD18: =SUM(AL18:AO18) -> 40.1949 | BE18: =SUM(AP18:AS18) -> 36.17541
A19: Consensus perpetual license and maintenance revenue | B19: ='[2]VA Consensus'!C19 -> - | C19: ='[2]VA Consensus'!D19 -> - | D19: ='[2]VA Consensus'!E19 -> - | E19: ='[2]VA Consensus'!F19 -> - | F19: ='[2]VA Consensus'!G19 -> - | G19: ='[2]VA Consensus'!H19 -> - | H19: ='[2]VA Consensus'!I19 -> 9.0917194 | I19: ='[2]VA Consensus'!J19 -> 9.7982908 | ... AS19: ='[2]VA Consensus'!AT19 -> 9.5120752 | AU19: ='[2]VA Consensus'!AV19 -> - | AV19: ='[2]VA Consensus'!AW19 -> 37.803338 | AW19: ='[2]VA Consensus'!AX19 -> 51.993046 | AX19: ='[2]VA Consensus'!AY19 -> 50.344036 | AY19: ='[2]VA Consensus'!AZ19 -> 50.28586 | AZ19: ='[2]VA Consensus'!BA19 -> 50.228755 | BA19: ='[2]VA Consensus'!BB19 -> 48.736255 | BB19: ='[2]VA Consensus'!BC19 -> 47.807977 | ... BE19: ='[2]VA Consensus'!BF19 -> 39.682475
A20: Y/Y Growth | F20: =F18/B18-1 -> 0.12411377 | G20: =G18/C18-1 -> 0.091915656 | H20: =H18/D18-1 -> 0.078323092 | I20: =I18/E18-1 -> 0.050045427 | J20: =J18/F18-1 -> 0.0037100245 | K20: =K18/G18-1 -> 0.010512973 | L20: =L18/H18-1 -> -0.0048326601 | M20: =M18/I18-1 -> -0.041315163 | ... AK20: =AK18/AG18-1 -> -0.10335502 | AL20: -0.1 | AM20: =AL20 -> -0.1 | AN20: =AM20 -> -0.1 | AO20: =AN20 -> -0.1 | AP20: =AO20 -> -0.1 | AQ20: =AP20 -> -0.1 | AR20: =AQ20 -> -0.1 | AS20: =AR20 -> -0.1 | AU20: =IF(ISERROR(AU18/#REF!-1),"NA",AU18/#REF!-1) -> NA | AV20: =IF(ISERROR(AV18/AU18-1),"NA",AV18/AU18-1) -> 0.085126249 | AW20: =IF(ISERROR(AW18/AV18-1),"NA",AW18/AV18-1) -> -0.0082201311 | AX20: =IF(ISERROR(AX18/AW18-1),"NA",AX18/AW18-1) -> -0.066066121 | AY20: =IF(ISERROR(AY18/AX18-1),"NA",AY18/AX18-1) -> -0.0051587145 | AZ20: =IF(ISERROR(AZ18/AY18-1),"NA",AZ18/AY18-1) -> 0.0072715713 | BA20: =IF(ISERROR(BA18/AZ18-1),"NA",BA18/AZ18-1) -> -0.038856782 | BB20: =IF(ISERROR(BB18/BA18-1),"NA",BB18/BA18-1) -> -0.019598186 | BC20: =IF(ISERROR(BC18/BB18-1),"NA",BC18/BB18-1) -> -0.065160966 | ... BE20: =IF(ISERROR(BE18/BD18-1),"NA",BE18/BD18-1) -> -0.1
A21: % of total revenue | B21: =B18/B$5 -> 0.29616363 | C21: =C18/C$5 -> 0.27821695 | D21: =D18/D$5 -> 0.2624949 | E21: =E18/E$5 -> 0.24406379 | F21: =F18/F$5 -> 0.22801022 | G21: =G18/G$5 -> 0.21090703 | H21: =H18/H$5 -> 0.19965438 | I21: =I18/I$5 -> 0.1843767 | ... AS21: =AS18/AS$5 -> 0.029074263 | AU21: =AU18/AU$5 -> 0.26813937 | AV21: =AV18/AV$5 -> 0.20430132 | AW21: =AW18/AW$5 -> 0.15277817 | AX21: =AX18/AX$5 -> 0.11492864 | AY21: =AY18/AY$5 -> 0.093014618 | AZ21: =AZ18/AZ$5 -> 0.074209116 | BA21: =BA18/BA$5 -> 0.061009628 | BB21: =BB18/BB$5 -> 0.053080984 | ... BE21: =BE18/BE$5 -> 0.031715832
A23: Professional Services and Other Revenue | B23: 0.79 | C23: =4.517-B23-D23-E23 -> 1.022 | D23: 1.191 | E23: 1.514 | F23: 1.298 | G23: 1.455 | H23: 2.065 | I23: 2.093 | J23: 2.037 | K23: 2.461 | L23: 2.552 | M23: 2.814 | N23: 2.839 | O23: 3.02 | P23: 3.042 | Q23: 3.372 | R23: 3.382 | S23: 3.525 | T23: 3.759 | U23: 4.108 | V23: 3.808 | W23: 4.852 | X23: 5.429 | Y23: 5.893 | Z23: 5.56 | AA23: 6.115 | AB23: 6.061 | AC23: 7.232 | AD23: 6.17 | AE23: 6.687 | AF23: 6.765 | AG23: 7.966 | AH23: 7.142 | AI23: 7.853 | AJ23: 9.141 | AK23: 11.035 | AL23: =AH23*(1+AL25) -> 6.7849 | AM23: =AI23*(1+AM25) -> 7.853 | AN23: =AJ23*(1+AN25) -> 9.141 | AO23: =AK23*(1+AO25) -> 11.035 | AP23: =AL23*(1+AP25) -> 6.7849 | AQ23: =AM23*(1+AQ25) -> 7.853 | AR23: =AN23*(1+AR25) -> 9.141 | AS23: =AO23*(1+AS25) -> 11.035 | AU23: =SUM(B23:E23) -> 4.517 | AV23: =SUM(F23:I23) -> 6.911 | AW23: =SUM(J23:M23) -> 9.864 | AX23: =SUM(N23:Q23) -> 12.273 | AY23: =SUM(R23:U23) -> 14.774 | AZ23: =SUM(V23:Y23) -> 19.982 | BA23: =SUM(Z23:AC23) -> 24.968 | BB23: =SUM(AD23:AG23) -> 27.588 | BC23: =SUM(AH23:AK23) -> 35.171 | BD23: =SUM(AL23:AO23) -> 34.8139 | BE23: =SUM(AP23:AS23) -> 34.8139
A24: Consensus professional services & other revenue | B24: ='[2]VA Consensus'!C20 -> - | C24: ='[2]VA Consensus'!D20 -> - | D24: ='[2]VA Consensus'!E20 -> - | E24: ='[2]VA Consensus'!F20 -> - | F24: ='[2]VA Consensus'!G20 -> - | G24: ='[2]VA Consensus'!H20 -> - | H24: ='[2]VA Consensus'!I20 -> 1.5606257 | I24: ='[2]VA Consensus'!J20 -> 1.8357154 | ... AS24: ='[2]VA Consensus'!AT20 -> 11.236806 | AU24: ='[2]VA Consensus'!AV20 -> - | AV24: ='[2]VA Consensus'!AW20 -> 6.6590402 | AW24: ='[2]VA Consensus'!AX20 -> 9.4087585 | AX24: ='[2]VA Consensus'!AY20 -> 11.959601 | AY24: ='[2]VA Consensus'!AZ20 -> 14.426971 | AZ24: ='[2]VA Consensus'!BA20 -> 19.264648 | BA24: ='[2]VA Consensus'!BB20 -> 24.049979 | BB24: ='[2]VA Consensus'!BC20 -> 26.584014 | ... BE24: ='[2]VA Consensus'!BF20 -> 38.210345
A25: Y/Y Growth | F25: =F23/B23-1 -> 0.64303797 | G25: =G23/C23-1 -> 0.42367906 | H25: =H23/D23-1 -> 0.73383711 | I25: =I23/E23-1 -> 0.38243065 | J25: =J23/F23-1 -> 0.56933744 | K25: =K23/G23-1 -> 0.69140893 | L25: =L23/H23-1 -> 0.23583535 | M25: =M23/I23-1 -> 0.34448161 | ... AK25: =AK23/AG23-1 -> 0.38526237 | AL25: -0.05 | AM25: 0 | AN25: 0 | AO25: 0 | AP25: 0 | AQ25: 0 | AR25: 0 | AS25: 0 | AU25: =IF(ISERROR(AU23/#REF!-1),"NA",AU23/#REF!-1) -> NA | AV25: =IF(ISERROR(AV23/AU23-1),"NA",AV23/AU23-1) -> 0.52999779 | AW25: =IF(ISERROR(AW23/AV23-1),"NA",AW23/AV23-1) -> 0.42728983 | AX25: =IF(ISERROR(AX23/AW23-1),"NA",AX23/AW23-1) -> 0.24422141 | AY25: =IF(ISERROR(AY23/AX23-1),"NA",AY23/AX23-1) -> 0.20378066 | AZ25: =IF(ISERROR(AZ23/AY23-1),"NA",AZ23/AY23-1) -> 0.35251117 | BA25: =IF(ISERROR(BA23/AZ23-1),"NA",BA23/AZ23-1) -> 0.24952457 | BB25: =IF(ISERROR(BB23/BA23-1),"NA",BB23/BA23-1) -> 0.10493432 | BC25: =IF(ISERROR(BC23/BB23-1),"NA",BC23/BB23-1) -> 0.27486588 | ... BE25: =IF(ISERROR(BE23/BD23-1),"NA",BE23/BD23-1) -> 0
A26: % of total revenue | B26: =B23/B$5 -> 0.019515328 | C26: =C23/C$5 -> 0.023148882 | D26: =D23/D$5 -> 0.024316047 | E26: =E23/E$5 -> 0.027976421 | F26: =F23/F$5 -> 0.021960174 | G26: =G23/G$5 -> 0.022880237 | H26: =H23/H$5 -> 0.029737903 | I26: =I23/I$5 -> 0.027824677 | ... AS26: =AS23/AS$5 -> 0.037331948 | AU26: =AU23/AU$5 -> 0.024061536 | AV26: =AV23/AV$5 -> 0.025849042 | AW26: =AW23/AW$5 -> 0.027818357 | AX26: =AX23/AX$5 -> 0.027879179 | AY26: =AY23/AY$5 -> 0.027302127 | AZ26: =AZ23/AZ$5 -> 0.029248043 | BA26: =BA23/BA$5 -> 0.031260407 | BB26: =BB23/BB$5 -> 0.030652618 | ... BE26: =BE23/BE$5 -> 0.030522164
B28: ='Income Statement'!B$3 -> 2017 | F28: ='Income Statement'!F$3 -> 2018 | J28: ='Income Statement'!J$3 -> 2019 | N28: ='Income Statement'!N$3 -> 2020 | R28: ='Income Statement'!R$3 -> 2021 | V28: ='Income Statement'!V$3 -> 2022 | Z28: ='Income Statement'!Z$3 -> 2023 | AD28: ='Income Statement'!AD$3 -> 2024 | AH28: ='Income Statement'!AH$3 -> 2025 | AL28: ='Income Statement'!AL$3 -> 2026 | AP28: ='Income Statement'!AP$3 -> 2027
A29: Billings & Bookings | B29: ='Income Statement'!B$4 -> 42825 | C29: ='Income Statement'!C$4 -> 42916 | D29: ='Income Statement'!D$4 -> 43008 | E29: ='Income Statement'!E$4 -> 43100 | F29: ='Income Statement'!F$4 -> 43190 | G29: ='Income Statement'!G$4 -> 43281 | H29: ='Income Statement'!H$4 -> 43373 | I29: ='Income Statement'!I$4 -> 43465 | ... AS29: ='Income Statement'!AS$4 -> Dec-27E | AU29: ='Income Statement'!AU$4 -> 2017 | AV29: ='Income Statement'!AV$4 -> 2018 | AW29: ='Income Statement'!AW$4 -> 2019 | AX29: ='Income Statement'!AX$4 -> 2020 | AY29: ='Income Statement'!AY$4 -> CY21 | AZ29: ='Income Statement'!AZ$4 -> CY22 | BA29: ='Income Statement'!BA$4 -> CY23 | BB29: ='Income Statement'!BB$4 -> CY24 | ... BE29: ='Income Statement'!BE$4 -> CY27E
A30: Revenue | B30: =B5 -> 40.481 | C30: =C5 -> 44.149 | D30: =D5 -> 48.98 | E30: =E5 -> 54.117 | F30: =F5 -> 59.107 | G30: =G5 -> 63.592 | H30: =H5 -> 69.44 | I30: =I5 -> 75.221 | ... AS30: =AS5 -> 295.59132 | AU30: =SUM(B30:E30) -> 187.727 | AV30: =SUM(F30:I30) -> 267.36 | AW30: =SUM(J30:M30) -> 354.586 | AX30: =SUM(N30:Q30) -> 440.221 | AY30: =SUM(R30:U30) -> 541.13 | AZ30: =SUM(V30:Y30) -> 683.191 | BA30: =SUM(Z30:AC30) -> 798.71 | BB30: =SUM(AD30:AG30) -> 900.021 | BC30: =SUM(AH30:AK30) -> 999.405 | BD30: =SUM(AL30:AO30) -> 1070.2389 | BE30: =SUM(AP30:AS30) -> 1140.6105
A31: Beginning deferred revenue balance | E31: 107.447 | F31: =E32 -> 225.818 | G31: =F32 -> 230.614 | H31: =G32 -> 247.137 | I31: =H32 -> 265.698 | J31: =I32 -> 289.903 | K31: =J32 -> 291.905 | L31: =K32 -> 307.333 | M31: =L32 -> 329.375 | ... AS31: =AR32 -> 942.84624 | AU31: =SUM(B31:E31) -> 107.447 | AV31: =SUM(F31:I31) -> 969.267 | AW31: =SUM(J31:M31) -> 1218.516 | AX31: =SUM(N31:Q31) -> 1476.729 | AY31: =SUM(R31:U31) -> 1785.203 | AZ31: =SUM(V31:Y31) -> 2200.16 | BA31: =SUM(Z31:AC31) -> 2638.322 | BB31: =SUM(AD31:AG31) -> 2946.455 | BC31: =SUM(AH31:AK31) -> 3249.874 | BD31: =SUM(AL31:AO31) -> 3507.4433 | BE31: =SUM(AP31:AS31) -> 3780.9609
A32: Ending deferred revenue balance | E32: ='Balance Sheet'!E25+'Balance Sheet'!E32 -> 225.818 | F32: ='Balance Sheet'!F25+'Balance Sheet'!F32 -> 230.614 | G32: ='Balance Sheet'!G25+'Balance Sheet'!G32 -> 247.137 | H32: ='Balance Sheet'!H25+'Balance Sheet'!H32 -> 265.698 | I32: ='Balance Sheet'!I25+'Balance Sheet'!I32 -> 289.903 | J32: ='Balance Sheet'!J25+'Balance Sheet'!J32 -> 291.905 | K32: ='Balance Sheet'!K25+'Balance Sheet'!K32 -> 307.333 | L32: ='Balance Sheet'!L25+'Balance Sheet'!L32 -> 329.375 | ... AK32: ='Balance Sheet'!AK25+'Balance Sheet'!AK32 -> 899.276 | AL32: =AL31+AL33 -> 872.44803 | AM32: =AM31+AM33 -> 861.10264 | AN32: =AN31+AN33 -> 874.61664 | AO32: =AO31+AO33 -> 969.13296 | AP32: =AP31+AP33 -> 940.53697 | AQ32: =AQ31+AQ33 -> 928.44474 | AR32: =AR31+AR33 -> 942.84624 | AS32: =AS31+AS33 -> 1043.5649 | AU32: =SUM(B32:E32) -> 225.818 | AV32: =SUM(F32:I32) -> 1033.352 | AW32: =SUM(J32:M32) -> 1291.74 | AX32: =SUM(N32:Q32) -> 1548.112 | AY32: =SUM(R32:U32) -> 1881.578 | AZ32: =SUM(V32:Y32) -> 2333.877 | BA32: =SUM(Z32:AC32) -> 2724.217 | BB32: =SUM(AD32:AG32) -> 3029.145 | BC32: =SUM(AH32:AK32) -> 3315.963 | BD32: =SUM(AL32:AO32) -> 3577.3003 | BE32: =SUM(AP32:AS32) -> 3855.3928
A33: Change in deferred revenue | E33: =E32-E31 -> 118.371 | F33: =F32-F31 -> 4.796 | G33: =G32-G31 -> 16.523 | H33: =H32-H31 -> 18.561 | I33: =I32-I31 -> 24.205 | J33: =J32-J31 -> 2.002 | K33: =K32-K31 -> 15.428 | L33: =L32-L31 -> 22.042 | ... AK33: =AK32-AK31 -> 88.773 | AL33: =AL34-AL30 -> -26.827965 | AM33: =AM34-AM30 -> -11.345393 | AN33: =AN34-AN30 -> 13.514002 | AO33: =AO34-AO30 -> 94.516312 | AP33: =AP34-AP30 -> -28.595981 | AQ33: =AQ34-AQ30 -> -12.09223 | AR33: =AR34-AR30 -> 14.401496 | AS33: =AS34-AS30 -> 100.71864 | AU33: =SUM(B33:E33) -> 118.371 | AV33: =SUM(F33:I33) -> 64.085 | AW33: =SUM(J33:M33) -> 73.224 | AX33: =SUM(N33:Q33) -> 71.383 | AY33: =SUM(R33:U33) -> 96.375 | AZ33: =SUM(V33:Y33) -> 133.717 | BA33: =SUM(Z33:AC33) -> 85.895 | BB33: =SUM(AD33:AG33) -> 82.69 | BC33: =SUM(AH33:AK33) -> 66.089 | BD33: =SUM(AL33:AO33) -> 69.856956 | BE33: =SUM(AP33:AS33) -> 74.431922
A34: Total Billings | F34: =F30+F33 -> 63.903 | G34: =G30+G33 -> 80.115 | H34: =H30+H33 -> 88.001 | I34: =I30+I33 -> 99.426 | J34: =J30+J33 -> 82.303 | K34: =K30+K33 -> 100.812 | L34: =L30+L33 -> 113.894 | M34: =M30+M33 -> 130.801 | ... AK34: =AK30+AK33 -> 349.306 | AL34: =AH34*(1+AL35) -> 231.73882 | AM34: =AI34*(1+AM35) -> 254.19114 | AN34: =AJ34*(1+AN35) -> 282.26103 | AO34: =AK34*(1+AO35) -> 371.90491 | AP34: =AL34*(1+AP35) -> 247.01087 | AQ34: =AM34*(1+AQ35) -> 270.92386 | AR34: =AN34*(1+AR35) -> 300.79773 | AS34: =AO34*(1+AS35) -> 396.30996 | AU34: =SUM(B34:E34) -> 0 | AV34: =SUM(F34:I34) -> 331.445 | AW34: =SUM(J34:M34) -> 427.81 | AX34: =SUM(N34:Q34) -> 511.604 | AY34: =SUM(R34:U34) -> 637.505 | AZ34: =SUM(V34:Y34) -> 816.908 | BA34: =SUM(Z34:AC34) -> 884.605 | BB34: =SUM(AD34:AG34) -> 982.711 | BC34: =SUM(AH34:AK34) -> 1065.494 | BD34: =SUM(AL34:AO34) -> 1140.0959 | BE34: =SUM(AP34:AS34) -> 1215.0424
A35: Y/Y Growth | J35: =J34/F34-1 -> 0.2879364 | K35: =K34/G34-1 -> 0.25834113 | L35: =L34/H34-1 -> 0.29423529 | M35: =M34/I34-1 -> 0.31556132 | N35: =N34/J34-1 -> 0.1860078 | O35: =O34/K34-1 -> 0.13505337 | P35: =P34/L34-1 -> 0.20440936 | Q35: =Q34/M34-1 -> 0.24150427 | ... AK35: =AK34/AG34-1 -> 0.086603249 | AL35: =+AL7 -> 0.081249598 | AM35: =+AM7 -> 0.073764269 | AN35: =+AN7 -> 0.064597627 | AO35: =+AO7 -> 0.064696603 | AP35: =+AP7 -> 0.065901979 | AQ35: =+AQ7 -> 0.065827288 | AR35: =+AR7 -> 0.065672183 | AS35: =+AS7 -> 0.065621742 | AV35: =IF(ISERROR(AV34/AU34-1),"NA",AV34/AU34-1) -> NA | AW35: =IF(ISERROR(AW34/AV34-1),"NA",AW34/AV34-1) -> 0.29074205 | AX35: =IF(ISERROR(AX34/AW34-1),"NA",AX34/AW34-1) -> 0.19586732 | AY35: =IF(ISERROR(AY34/AX34-1),"NA",AY34/AX34-1) -> 0.24609073 | AZ35: =IF(ISERROR(AZ34/AY34-1),"NA",AZ34/AY34-1) -> 0.28141426 | BA35: =IF(ISERROR(BA34/AZ34-1),"NA",BA34/AZ34-1) -> 0.082869797 | BB35: =IF(ISERROR(BB34/BA34-1),"NA",BB34/BA34-1) -> 0.11090374 | BC35: =IF(ISERROR(BC34/BB34-1),"NA",BC34/BB34-1) -> 0.084239415 | ... BE35: =IF(ISERROR(BE34/BD34-1),"NA",BE34/BD34-1) -> 0.065737019
A37: Revenue | B37: =B30 -> 40.481 | C37: =C30 -> 44.149 | D37: =D30 -> 48.98 | E37: =E30 -> 54.117 | F37: =F30 -> 59.107 | G37: =G30 -> 63.592 | H37: =H30 -> 69.44 | I37: =I30 -> 75.221 | ... AS37: =AS30 -> 295.59132 | AV37: =SUM(F37:I37) -> 267.36 | AW37: =SUM(J37:M37) -> 354.586 | AX37: =SUM(N37:Q37) -> 440.221 | AY37: =SUM(R37:U37) -> 541.13 | AZ37: =SUM(V37:Y37) -> 683.191 | BA37: =SUM(Z37:AC37) -> 798.71 | BB37: =SUM(AD37:AG37) -> 900.021 | BC37: =SUM(AH37:AK37) -> 999.405 | BD37: =SUM(AL37:AO37) -> 1070.2389 | BE37: =SUM(AP37:AS37) -> 1140.6105
A38: Beginning deferred revenue (current) balance | F38: =E39 -> 154.898 | G38: =F39 -> 160.503 | H38: =G39 -> 174.277 | I38: =H39 -> 191.578 | J38: =I39 -> 213.644 | K38: =J39 -> 214.508 | L38: =K39 -> 227.227 | M38: =L39 -> 245.985 | ... U38: =T39 -> 362.308 | V38: =U39+0.137 -> 407.635 | W38: =V39+0.808 -> 405.594 | X38: =W39 -> 415.378 | Y38: =X39 -> 447.863 | Z38: =Y39 -> 502.115 | AA38: =Z39 -> 490.076 | AB38: =AA39 -> 495.199 | AC38: =AB39+4.1 -> 522.472 | AD38: =AC39 -> 580.779 | AE38: =AD39 -> 562.575 | AF38: =AE39 -> 562.587 | AG38: =AF39 -> 583.94 | AH38: =AG39+6.629 -> 657.001 | AI38: =AH39 -> 633.224 | AJ38: =AI39 -> 624.548 | AK38: =AJ39 -> 639.614 | AL38: =AK39 -> 706.866 | AM38: =AL39 -> 685.77817 | AN38: =AM39 -> 676.86025 | AO38: =AN39 -> 687.48278 | AP38: =AO39 -> 761.77629 | ... AS38: =AR39 -> 741.11391 | AV38: =SUM(F38:I38) -> 681.256 | AW38: =SUM(J38:M38) -> 901.364 | AX38: =SUM(N38:Q38) -> 1116.577 | AY38: =SUM(R38:U38) -> 1350.346 | AZ38: =SUM(V38:Y38) -> 1676.47 | BA38: =SUM(Z38:AC38) -> 2009.862 | BB38: =SUM(AD38:AG38) -> 2289.881 | BC38: =SUM(AH38:AK38) -> 2554.387 | BD38: =SUM(AL38:AO38) -> 2756.9872 | BE38: =SUM(AP38:AS38) -> 2971.9827
A39: Ending deferred revenue (current) balance | E39: ='Balance Sheet'!E25 -> 154.898 | F39: ='Balance Sheet'!F25 -> 160.503 | G39: ='Balance Sheet'!G25 -> 174.277 | H39: ='Balance Sheet'!H25 -> 191.578 | I39: ='Balance Sheet'!I25 -> 213.644 | J39: ='Balance Sheet'!J25 -> 214.508 | K39: ='Balance Sheet'!K25 -> 227.227 | L39: ='Balance Sheet'!L25 -> 245.985 | ... AS39: ='Balance Sheet'!AS25 -> 820.28268 | AV39: =SUM(F39:I39) -> 740.002 | AW39: =SUM(J39:M39) -> 962.068 | AX39: =SUM(N39:Q39) -> 1171.048 | AY39: =SUM(R39:U39) -> 1429.025 | AZ39: =SUM(V39:Y39) -> 1770.142 | BA39: =SUM(Z39:AC39) -> 2084.426 | BB39: =SUM(AD39:AG39) -> 2359.474 | BC39: =SUM(AH39:AK39) -> 2604.252 | BD39: =SUM(AL39:AO39) -> 2811.8975 | BE39: =SUM(AP39:AS39) -> 3030.4891
A40: Change in deferred revenue (current) | F40: =F39-F38 -> 5.605 | G40: =G39-G38 -> 13.774 | H40: =H39-H38 -> 17.301 | I40: =I39-I38 -> 22.066 | J40: =J39-J38 -> 0.864 | K40: =K39-K38 -> 12.719 | L40: =L39-L38 -> 18.758 | M40: =M39-M38 -> 28.363 | ... AS40: =AS39-AS38 -> 79.168775 | AV40: =SUM(F40:I40) -> 58.746 | AW40: =SUM(J40:M40) -> 60.704 | AX40: =SUM(N40:Q40) -> 54.471 | AY40: =SUM(R40:U40) -> 78.679 | AZ40: =SUM(V40:Y40) -> 93.672 | BA40: =SUM(Z40:AC40) -> 74.564 | BB40: =SUM(AD40:AG40) -> 69.593 | BC40: =SUM(AH40:AK40) -> 49.865 | BD40: =SUM(AL40:AO40) -> 54.910291 | BE40: =SUM(AP40:AS40) -> 58.506393
A41: Current Billings | F41: =F37+F40 -> 64.712 | G41: =G37+G40 -> 77.366 | H41: =H37+H40 -> 86.741 | I41: =I37+I40 -> 97.287 | J41: =J37+J40 -> 81.165 | K41: =K37+K40 -> 98.103 | L41: =L37+L40 -> 110.61 | M41: =M37+M40 -> 125.412 | ... AS41: =AS37+AS40 -> 374.7601 | AV41: =SUM(F41:I41) -> 326.106 | AW41: =SUM(J41:M41) -> 415.29 | AX41: =SUM(N41:Q41) -> 494.692 | AY41: =SUM(R41:U41) -> 619.809 | AZ41: =SUM(V41:Y41) -> 776.863 | BA41: =SUM(Z41:AC41) -> 873.274 | BB41: =SUM(AD41:AG41) -> 969.614 | BC41: =SUM(AH41:AK41) -> 1049.27 | BD41: =SUM(AL41:AO41) -> 1125.1492 | BE41: =SUM(AP41:AS41) -> 1199.1169
A42: Consensus Current Billings | B42: ='[2]VA Consensus'!C13 -> - | C42: ='[2]VA Consensus'!D13 -> - | D42: ='[2]VA Consensus'!E13 -> - | E42: ='[2]VA Consensus'!F13 -> - | F42: ='[2]VA Consensus'!G13 -> - | G42: ='[2]VA Consensus'!H13 -> - | H42: ='[2]VA Consensus'!I13 -> 80.923611 | I42: ='[2]VA Consensus'!J13 -> 93.35714 | ... AS42: ='[2]VA Consensus'!AT13 -> 370.09809 | AU42: ='[2]VA Consensus'!AV13 -> - | AV42: ='[2]VA Consensus'!AW13 -> 322.17613 | AW42: ='[2]VA Consensus'!AX13 -> 412.84391 | AX42: ='[2]VA Consensus'!AY13 -> 487.68591 | AY42: ='[2]VA Consensus'!AZ13 -> 604.67528 | AZ42: ='[2]VA Consensus'!BA13 -> 773.56192 | BA42: ='[2]VA Consensus'!BB13 -> 865.96706 | BB42: ='[2]VA Consensus'!BC13 -> 962.40681 | ... BE42: ='[2]VA Consensus'!BF13 -> 1209.507
A43: Y/Y Growth | J43: =J41/F41-1 -> 0.2542496 | K43: =K41/G41-1 -> 0.26803764 | L43: =L41/H41-1 -> 0.27517552 | M43: =M41/I41-1 -> 0.2890931 | N43: =N41/J41-1 -> 0.22239882 | O43: =O41/K41-1 -> 0.13397144 | P43: =P41/L41-1 -> 0.20865202 | Q43: =Q41/M41-1 -> 0.20037158 | ... AS43: =AS41/AO41-1 -> 0.065621742 | AW43: =AW41/AV41-1 -> 0.27348163 | AX43: =AX41/AW41-1 -> 0.19119651 | AY43: =AY41/AX41-1 -> 0.25291899 | AZ43: =AZ41/AY41-1 -> 0.25339096 | BA43: =BA41/AZ41-1 -> 0.12410296 | BB43: =BB41/BA41-1 -> 0.11032047 | BC43: =BC41/BB41-1 -> 0.082152279 | BD43: =BD41/BC41-1 -> 0.072316216 | BE43: =BE41/BD41-1 -> 0.065740294
A44: Management Guidance - Current Billings
A45: Low | Y45: =AZ45-X41-W41-V41 -> 230.02 | AC45: =BA45-AB41-AA41-Z41 -> 260.339 | AG45: =BB45-AF41-AE41-AD41 -> 289.549 | AY45: 602 | AZ45: 768 | BA45: 862 | BB45: 957 | BC45: 1040
A46: Mid | Y46: =AZ46-X41-W41-V41 -> 234.02 | AC46: =BA46-AB41-AA41-Z41 -> 264.339 | AG46: =BB46-AF41-AE41-AD41 -> 294.549 | AY46: =AVERAGE(AY45,AY47) -> 603.5 | AZ46: =AVERAGE(AZ45,AZ47) -> 772 | BA46: =AVERAGE(BA45,BA47) -> 866 | BB46: =AVERAGE(BB45,BB47) -> 962 | BC46: =AVERAGE(BC45,BC47) -> 1044
A47: High | Y47: =AZ47-X41-W41-V41 -> 238.02 | AC47: =BA47-AB41-AA41-Z41 -> 268.339 | AG47: =BB47-AF41-AE41-AD41 -> 299.549 | AY47: 605 | AZ47: 776 | BA47: 870 | BB47: 967 | BC47: 1048
I48: =I41/H41-1 -> 0.12158034 | M48: =M41/L41-1 -> 0.13382154 | Q48: =Q41/P41-1 -> 0.12605375 | U48: =U41/T41-1 -> 0.16385603
A49: RPO | G49: 252 | H49: 267.9 | I49: 293.2 | J49: 295.3 | K49: 313 | L49: 333.4 | M49: 367.3 | N49: 363.9 | O49: 378.2 | P49: 399.7 | Q49: 443.2 | R49: 441.1 | S49: 461.6 | T49: 491.9 | U49: 559 | V49: 555.7 | W49: 567.7 | X49: 612.8 | Y49: 680.4 | Z49: 654.7 | AA49: 662.7 | AB49: 697.184 | AC49: 775.008 | AD49: 742.411 | AE49: 747.541 | AF49: 771.561 | AG49: 867.526 | AH49: 882.245 | AI49: 889.143 | AJ49: 928.864 | AK49: 1061.065 | AV49: =I49 -> 293.2 | AW49: =M49 -> 367.3 | AX49: =Q49 -> 443.2 | AY49: =U49 -> 559 | AZ49: =Y49 -> 680.4 | BA49: =AC49 -> 775.008 | BB49: =AG49 -> 867.526
A50: Y/Y Growth | K50: =K49/G49-1 -> 0.24206349 | L50: =L49/H49-1 -> 0.24449421 | M50: =M49/I49-1 -> 0.25272851 | N50: =N49/J49-1 -> 0.23230613 | O50: =O49/K49-1 -> 0.20830671 | P50: =P49/L49-1 -> 0.19886023 | Q50: =Q49/M49-1 -> 0.20664307 | R50: =R49/N49-1 -> 0.21214619 | ... AK50: =AK49/AG49-1 -> 0.22309303 | AW50: =AW49/AV49-1 -> 0.25272851 | AX50: =AX49/AW49-1 -> 0.20664307 | AY50: =AY49/AX49-1 -> 0.26128159 | AZ50: =AZ49/AY49-1 -> 0.21717352 | BA50: =BA49/AZ49-1 -> 0.13904762 | BB50: =BB49/BA49-1 -> 0.11937683
A51: Current RPO | G51: =G49*G53 -> 178.92 | H51: =H49*H53 -> 192.888 | I51: =I49*I53 -> 214.036 | J51: =J49*J53 -> 215.569 | K51: =K49*K53 -> 231.62 | L51: =L49*L53 -> 246.716 | M51: =M49*M53 -> 275.475 | N51: =N49*N53 -> 272.925 | ... AA51: =AA49*AA53 -> 503.652 | AB51: 528.367 | AC51: 595.053 | AD51: 572.851 | AE51: 572.015 | AF51: 592.351 | AG51: 660.647 | AH51: 647.647 | AI51: 641.918 | AJ51: 669.015 | AK51: 748.616 | AV51: =I51 -> 214.036 | AW51: =M51 -> 275.475 | AX51: =Q51 -> 336.832 | AY51: =U51 -> 424.84 | AZ51: =Y51 -> 510.3 | BA51: =AC51 -> 595.053 | BB51: =AG51 -> 660.647
A52: Y/Y Growth | K52: =K51/G51-1 -> 0.29454505 | L52: =L51/H51-1 -> 0.2790635 | M52: =M51/I51-1 -> 0.28704984 | N52: =N51/J51-1 -> 0.26606794 | O52: =O51/K51-1 -> 0.20830671 | P52: =P51/L51-1 -> 0.23126186 | Q52: =Q51/M51-1 -> 0.22273165 | R52: =R51/N51-1 -> 0.21214619 | ... AK52: =AK51/AG51-1 -> 0.13315583 | AW52: =AW51/AV51-1 -> 0.28704984 | AX52: =AX51/AW51-1 -> 0.22273165 | AY52: =AY51/AX51-1 -> 0.26128159 | AZ52: =AZ51/AY51-1 -> 0.20115808 | BA52: =BA51/AZ51-1 -> 0.16608466 | BB52: =BB51/BA51-1 -> 0.1102322
A53: Current RPO - % of total | G53: 0.71 | H53: 0.72 | I53: 0.73 | J53: 0.73 | K53: 0.74 | L53: 0.74 | M53: 0.75 | N53: 0.75 | O53: 0.74 | P53: 0.76 | Q53: 0.76 | R53: 0.75 | S53: 0.75 | T53: 0.76 | U53: 0.76 | V53: 0.76 | W53: 0.75 | X53: 0.75 | Y53: 0.75 | Z53: 0.76 | AA53: 0.76 | AB53: =AB51/AB49 -> 0.75785876 | AC53: =AC51/AC49 -> 0.7678024 | AD53: =AD51/AD49 -> 0.77160899 | AE53: =AE51/AE49 -> 0.76519549 | AF53: =AF51/AF49 -> 0.76773061 | AG53: =AG51/AG49 -> 0.76152991 | AH53: =AH51/AH49 -> 0.73408974 | AI53: =AI51/AI49 -> 0.72195136 | ... AK53: =AK51/AK49 -> 0.70553265 | AV53: =AV51/AV49 -> 0.73 | AW53: =AW51/AW49 -> 0.75 | AX53: =AX51/AX49 -> 0.76 | AY53: =AY51/AY49 -> 0.76 | AZ53: =AZ51/AZ49 -> 0.75 | BA53: =BA51/BA49 -> 0.7678024 | BB53: =BB51/BB49 -> 0.76152991
A54: Backlog (RPO - Deferred Rev) | G54: =G49-G32 -> 4.863 | H54: =H49-H32 -> 2.202 | I54: =I49-I32 -> 3.297 | J54: =J49-J32 -> 3.395 | K54: =K49-K32 -> 5.667 | L54: =L49-L32 -> 4.025 | M54: =M49-M32 -> 4.173 | N54: =N49-N32 -> 5.809 | ... AK54: =AK49-AK32 -> 161.789 | AV54: =I54 -> 3.297 | AW54: =M54 -> 4.173 | AX54: =Q54 -> 8.69 | AY54: =U54 -> 28.115 | AZ54: =Y54 -> 15.798 | BA54: =AC54 -> 24.511 | BB54: =AG54 -> 34.339
A55: Y/Y Growth | K55: =K54/G54-1 -> 0.16533004 | L55: =L54/H54-1 -> 0.82788374 | M55: =M54/I54-1 -> 0.26569609 | N55: =N54/J54-1 -> 0.71104566 | O55: =O54/K54-1 -> 1.2747485 | P55: =P54/L54-1 -> 1.3597516 | Q55: =Q54/M54-1 -> 1.0824347 | R55: =R54/N54-1 -> 1.1067309 | ... AK55: =AK54/AG54-1 -> 3.7115233 | AW55: =AW54/AV54-1 -> 0.26569609 | AX55: =AX54/AW54-1 -> 1.0824347 | AY55: =AY54/AX54-1 -> 2.235328 | AZ55: =AZ54/AY54-1 -> -0.43809354 | BA55: =BA54/AZ54-1 -> 0.55152551 | BB55: =BB54/BA54-1 -> 0.40096283
A57: Bookings
A58: Total Revenue | H58: =H5 -> 69.44 | I58: =I5 -> 75.221 | J58: =J5 -> 80.301 | K58: =K5 -> 85.384 | L58: =L5 -> 91.852 | M58: =M5 -> 97.049 | N58: =N5 -> 102.648 | O58: =O5 -> 107.209 | ... AK58: =AK5 -> 260.533 | BA58: =SUM(Z58:AC58) -> 798.71 | BB58: =SUM(AD58:AG58) -> 900.021
A59: + change in CRPO | H59: =H51-G51 -> 13.968 | I59: =I51-H51 -> 21.148 | J59: =J51-I51 -> 1.533 | K59: =K51-J51 -> 16.051 | L59: =L51-K51 -> 15.096 | M59: =M51-L51 -> 28.759 | N59: =N51-M51 -> -2.55 | O59: =O51-N51 -> 6.943 | ... AK59: =AK51-AJ51 -> 79.601 | AW59: =SUM(J59:M59) -> 61.439 | AX59: =SUM(N59:Q59) -> 61.357 | AY59: =SUM(R59:U59) -> 88.008 | AZ59: =SUM(V59:Y59) -> 85.46 | BA59: =SUM(Z59:AC59) -> 84.753 | BB59: =SUM(AD59:AG59) -> 65.594
A60: Total CRPO Bookings | H60: =H58+H59 -> 83.408 | I60: =I58+I59 -> 96.369 | J60: =J58+J59 -> 81.834 | K60: =K58+K59 -> 101.435 | L60: =L58+L59 -> 106.948 | M60: =M58+M59 -> 125.808 | N60: =N58+N59 -> 100.098 | O60: =O58+O59 -> 114.152 | ... AK60: =AK58+AK59 -> 340.134 | AW60: =SUM(J60:M60) -> 416.025 | AX60: =SUM(N60:Q60) -> 501.578 | AY60: =SUM(R60:U60) -> 629.138 | AZ60: =SUM(V60:Y60) -> 768.651 | BA60: =SUM(Z60:AC60) -> 883.463 | BB60: =SUM(AD60:AG60) -> 965.615
A61: Y/Y Growth | L61: =L60/H60-1 -> 0.28222712 | M61: =M60/I60-1 -> 0.30548205 | N61: =N60/J60-1 -> 0.22318352 | O61: =O60/K60-1 -> 0.12537093 | P61: =P60/L60-1 -> 0.2733852 | Q61: =Q60/M60-1 -> 0.20137034 | R61: =R60/N60-1 -> 0.17067274 | S61: =S60/O60-1 -> 0.27579017 | ... AK61: =AK60/AG60-1 -> 0.11876248 | AX61: =AX60/AW60-1 -> 0.20564389 | AY61: =AY60/AX60-1 -> 0.25431737 | AZ61: =AZ60/AY60-1 -> 0.22175262 | BA61: =BA60/AZ60-1 -> 0.14936818 | BB61: =BB60/BA60-1 -> 0.092988614
A62: Source: Company data, FactSet, Wells Fargo Securities, LLC estimates
B64: ='Income Statement'!B$3 -> 2017 | F64: ='Income Statement'!F$3 -> 2018 | J64: ='Income Statement'!J$3 -> 2019 | N64: ='Income Statement'!N$3 -> 2020 | R64: ='Income Statement'!R$3 -> 2021 | V64: ='Income Statement'!V$3 -> 2022 | Z64: ='Income Statement'!Z$3 -> 2023 | AD64: ='Income Statement'!AD$3 -> 2024 | AH64: ='Income Statement'!AH$3 -> 2025 | AL64: ='Income Statement'!AL$3 -> 2026 | AP64: ='Income Statement'!AP$3 -> 2027
A65: Customer Metrics | B65: ='Income Statement'!B$4 -> 42825 | C65: ='Income Statement'!C$4 -> 42916 | D65: ='Income Statement'!D$4 -> 43008 | E65: ='Income Statement'!E$4 -> 43100 | F65: ='Income Statement'!F$4 -> 43190 | G65: ='Income Statement'!G$4 -> 43281 | H65: ='Income Statement'!H$4 -> 43373 | I65: ='Income Statement'!I$4 -> 43465 | ... AS65: ='Income Statement'!AS$4 -> Dec-27E | AU65: ='Income Statement'!AU$4 -> 2017 | AV65: ='Income Statement'!AV$4 -> 2018 | AW65: ='Income Statement'!AW$4 -> 2019 | AX65: ='Income Statement'!AX$4 -> 2020 | AY65: ='Income Statement'!AY$4 -> CY21 | AZ65: ='Income Statement'!AZ$4 -> CY22 | BA65: ='Income Statement'!BA$4 -> CY23 | BB65: ='Income Statement'!BB$4 -> CY24 | ... BE65: ='Income Statement'!BE$4 -> CY27E
A66: Total Customers | E66: 24000 | F66: 25000 | I66: 27000 | M66: 30000 | Q66: 30000 | T66: > 35,000 | U66: 40000 | V66: 40000 | Y66: 43000 | Z66: 43000 | AA66: 43000 | AB66: 43000 | AC66: 44000 | AD66: 44000 | AE66: 44000 | AF66: 44000 | AG66: 44000 | AH66: 44000 | AI66: 44000 | AJ66: 44000 | AK66: 44000 | AU66: =E66 -> 24000 | AV66: =I66 -> 27000 | AW66: =M66 -> 30000 | AX66: =Q66 -> 30000 | AY66: =U66 -> 40000 | AZ66: =Y66 -> 43000 | BA66: =AC66 -> 44000 | BB66: =AG66 -> 44000
A67: Y/Y Growth | E67: =E66/21000-1 -> 0.14285714 | I67: =I66/E66-1 -> 0.125 | M67: =M66/I66-1 -> 0.11111111 | U67: =U66/Q66-1 -> 0.33333333 | Y67: =Y66/U66-1 -> 0.075 | Z67: =Z66/V66-1 -> 0.075 | AU67: =AU66/21000-1 -> 0.14285714 | AV67: =AV66/AU66-1 -> 0.125 | AW67: =AW66/AV66-1 -> 0.11111111 | AX67: =AX66/AW66-1 -> 0 | AY67: =AY66/AX66-1 -> 0.33333333 | AZ67: =AZ66/AY66-1 -> 0.075 | BA67: =BA66/AZ66-1 -> 0.023255814 | BB67: =BB66/BA66-1 -> 0
A68: % of Fortune 500 | E68: 0.53 | I68: 0.58 | M68: >50% | Q68: >50% | U68: ~60% | Y68: ~60% | Z68: ~60% | AA68: ~60% | AB68: ~60% | AC68: 0.65 | AD68: 0.65 | AE68: 0.65 | AF68: 0.65 | AG68: 0.65 | AU68: =E68 -> 0.53 | AV68: =I68 -> 0.58 | AW68: =M68 -> >50% | AX68: =Q68 -> >50% | AY68: =U68 -> ~60% | AZ68: =Y68 -> ~60% | BA68: =AC68 -> 0.65 | BB68: =AG68 -> 0.65
A69: % of Global 2000 | E69: 0.29 | I69: 0.32 | M69: >30% | Q69: >30% | U69: ~40% | Y69: ~40% | Z69: ~40% | AA69: ~40% | AB69: ~40% | AC69: 0.5 | AD69: 0.5 | AE69: 0.5 | AF69: 0.5 | AG69: 0.5 | AU69: =E69 -> 0.29 | AV69: =I69 -> 0.32 | AW69: =M69 -> >30% | AX69: =Q69 -> >30% | AY69: =U69 -> ~40% | AZ69: =Y69 -> ~40% | BA69: =AC69 -> 0.5 | BB69: =AG69 -> 0.5
A71: Total Enterprise Platform Customers | E71: 4400 | F71: =E71+F73 -> 4701 | G71: =F71+G73 -> 4983 | H71: =G71+H73 -> 5241 | I71: =H71+I73 -> 5578 | J71: =I71+J73 -> 5889 | K71: =J71+K73 -> 6241 | L71: =K71+L73 -> 6628 | M71: =L71+M73 -> 7089 | ... AK71: =AJ71+AK73 -> 17631 | AU71: =E71 -> 4400 | AV71: =I71 -> 5578 | AW71: =M71 -> 7089 | AX71: =Q71 -> 8544 | AY71: =U71 -> 10426 | AZ71: =Y71 -> 12504 | BA71: =AC71 -> 14292 | BB71: =AG71 -> 15981
A72: Y/Y Growth | E72: =E71/3100-1 -> 0.41935484 | I72: =I71/E71-1 -> 0.26772727 | J72: =J71/F71-1 -> 0.25271219 | K72: =K71/G71-1 -> 0.25245836 | L72: =L71/H71-1 -> 0.26464415 | M72: =M71/I71-1 -> 0.27088562 | N72: =N71/J71-1 -> 0.25793853 | O72: =O71/K71-1 -> 0.24162794 | P72: =P71/L71-1 -> 0.21967411 | ... AK72: =AK71/AG71-1 -> 0.10324761 | AU72: =AU71/3100-1 -> 0.41935484 | AV72: =AV71/AU71-1 -> 0.26772727 | AW72: =AW71/AV71-1 -> 0.27088562 | AX72: =AX71/AW71-1 -> 0.20524757 | AY72: =AY71/AX71-1 -> 0.22027154 | AZ72: =AZ71/AY71-1 -> 0.19930942 | BA72: =BA71/AZ71-1 -> 0.14299424 | BB72: =BB71/BA71-1 -> 0.118178
A73: Net new additions | F73: 301 | G73: 282 | H73: 258 | I73: 337 | J73: 311 | K73: 352 | L73: 387 | M73: 461 | N73: 319 | O73: 341 | P73: 335 | Q73: 460 | R73: 331 | S73: 490 | T73: 499 | U73: 562 | V73: 459 | W73: 540 | X73: 508 | Y73: 571 | Z73: 379 | AA73: 426 | AB73: 386 | AC73: 597 | AD73: 410 | AE73: 408 | AF73: 386 | AG73: 485 | AH73: 361 | AI73: 367 | AJ73: 437 | AK73: 485 | AU73: 1017 | AV73: =AV71-AU71 -> 1178 | AW73: =AW71-AV71 -> 1511 | AX73: =AX71-AW71 -> 1455 | AY73: =AY71-AX71 -> 1882 | AZ73: =AZ71-AY71 -> 2078 | BA73: =BA71-AZ71 -> 1788 | BB73: =BB71-BA71 -> 1689
A74: Y/Y Growth | J74: =J73/F73-1 -> 0.033222591 | K74: =K73/G73-1 -> 0.24822695 | L74: =L73/H73-1 -> 0.5 | M74: =M73/I73-1 -> 0.36795252 | N74: =N73/J73-1 -> 0.025723473 | O74: =O73/K73-1 -> -0.03125 | P74: =P73/L73-1 -> -0.13436693 | Q74: =Q73/M73-1 -> -0.0021691974 | ... AK74: =AK73/AG73-1 -> 0 | AU74: =(AU73/786)-1 -> 0.29389313 | AV74: =AV73/AU73-1 -> 0.15830875 | AW74: =AW73/AV73-1 -> 0.28268251 | AX74: =AX73/AW73-1 -> -0.037061549 | AY74: =AY73/AX73-1 -> 0.29347079 | AZ74: =AZ73/AY73-1 -> 0.10414453 | BA74: =BA73/AZ73-1 -> -0.13955727 | BB74: =BB73/BA73-1 -> -0.055369128
A76: $100K+ Customers | E76: 265 | F76: 307 | G76: 340 | H76: 387 | I76: 453 | J76: 494 | K76: 538 | L76: 589 | M76: 641 | N76: 665 | O76: 715 | P76: 771 | Q76: 837 | R76: 866 | S76: 933 | T76: 995 | U76: 1095 | V76: =U76+17 -> 1112 | W76: =V76+79 -> 1191 | X76: =W76+89 -> 1280 | Y76: =X76+140 -> 1420 | Z76: =Y76+24 -> 1444 | AA76: =Z76+63 -> 1507 | AB76: 1565 | AC76: =AB76+156 -> 1721 | AD76: 1717 | AE76: 1793 | AF76: 1853 | AG76: =AF76+AG78 -> 1988 | AH76: =AG76+AH78 -> 2042 | AI76: 2118 | AJ76: 2156 | AK76: 2161 | AU76: =E76 -> 265 | AV76: =I76 -> 453 | AW76: =M76 -> 641 | AX76: =Q76 -> 837 | AY76: =U76 -> 1095 | AZ76: =Y76 -> 1420 | BA76: =AC76 -> 1721 | BB76: =AG76 -> 1988
A77: Y/Y Growth | E77: =E76/124-1 -> 1.1370968 | I77: =I76/E76-1 -> 0.70943396 | J77: =J76/F76-1 -> 0.60912052 | K77: =K76/G76-1 -> 0.58235294 | L77: =L76/H76-1 -> 0.52196382 | M77: =M76/I76-1 -> 0.41501104 | N77: =N76/J76-1 -> 0.34615385 | O77: =O76/K76-1 -> 0.32899628 | P77: =P76/L76-1 -> 0.3089983 | ... AK77: =AK76/AG76-1 -> 0.087022133 | AU77: =AU76/124-1 -> 1.1370968 | AV77: =AV76/AU76-1 -> 0.70943396 | AW77: =AW76/AV76-1 -> 0.41501104 | AX77: =AX76/AW76-1 -> 0.30577223 | AY77: =AY76/AX76-1 -> 0.30824373 | AZ77: =AZ76/AY76-1 -> 0.29680365 | BA77: =BA76/AZ76-1 -> 0.21197183 | BB77: =BB76/BA76-1 -> 0.15514236
A78: Net new additions | F78: =F76-E76 -> 42 | G78: =G76-F76 -> 33 | H78: =H76-G76 -> 47 | I78: =I76-H76 -> 66 | J78: =J76-I76 -> 41 | K78: =K76-J76 -> 44 | L78: =L76-K76 -> 51 | M78: =M76-L76 -> 52 | ... AF78: =AF76-AE76 -> 60 | AG78: 135 | AH78: 54 | AI78: =AI76-AH76 -> 76 | AJ78: =AJ76-AI76 -> 38 | AK78: =AK76-AJ76 -> 5 | AV78: =AV76-AU76 -> 188 | AW78: =AW76-AV76 -> 188 | AX78: =AX76-AW76 -> 196 | AY78: =AY76-AX76 -> 258 | AZ78: =AZ76-AY76 -> 325 | BA78: =BA76-AZ76 -> 301 | BB78: =AG78 -> 135
A79: Y/Y Growth | J79: =J78/F78-1 -> -0.023809524 | K79: =K78/G78-1 -> 0.33333333 | L79: =L78/H78-1 -> 0.085106383 | M79: =M78/I78-1 -> -0.21212121 | N79: =N78/J78-1 -> -0.41463415 | O79: =O78/K78-1 -> 0.13636364 | P79: =P78/L78-1 -> 0.098039216 | Q79: =Q78/M78-1 -> 0.26923077 | ... AG79: =AG78/AC78-1 -> -0.13461538 | AH79: NM | AI79: =AI78/AE78-1 -> 0 | AJ79: =AJ78/AF78-1 -> -0.36666667 | AK79: =AK78/AG78-1 -> -0.96296296 | AW79: =AW78/AV78-1 -> 0 | AX79: =AX78/AW78-1 -> 0.042553191 | AY79: =AY78/AX78-1 -> 0.31632653 | AZ79: =AZ78/AY78-1 -> 0.25968992 | BA79: =BA78/AZ78-1 -> -0.073846154 | BB79: =BB78/BA78-1 -> -0.55149502
A81: Dollar-Based Net Expansion Rate (TTM ARR) | K81: 1.17 | L81: >110% | M81: >110% | N81: >110% | O81: >110% | P81: 1.1 | Q81: 1.1 | R81: >110% | S81: >110% | T81: 1.13 | U81: 1.17 | V81: >110% | W81: >110% | X81: 1.18 | Y81: 1.17 | Z81: 1.13 | AA81: 1.11 | AB81: 1.11 | AC81: 1.11 | AD81: 1.09 | AE81: 1.09 | AF81: 1.08 | AG81: 1.08 | AH81: 1.08 | AI81: 1.07 | AJ81: 1.06 | AK81: 1.06 | AX81: =Q81 -> 1.1 | AY81: =U81 -> 1.17 | AZ81: =Y81 -> 1.17 | BA81: =AC81 -> 1.11 | BB81: =AG81 -> 1.08
A83: Calculated NRR (Revenue) | X83: =(T30+X84)/T30 -> 1.227889 | Y83: =(U30+Y84)/U30 -> 1.2556738 | Z83: =(V30+Z84)/V30 -> 1.1800863 | AA83: =(W30+AA84)/W30 -> 1.1965426 | AB83: =(X30+AB84)/X30 -> 1.1750061 | AC83: =(Y30+AC84)/Y30 -> 1.185776 | AD83: =(Z30+AD84)/Z30 -> 1.1551586 | AE83: =(AA30+AE84)/AA30 -> 1.1389487 | ... AK83: =(AG30+AK84)/AG30 -> 1.1119921 | AY83: =(AX30+AY84)/AX30 -> 1.2126205 | AZ83: =(AY30+AZ84)/AY30 -> 1.2454124 | BA83: =(AZ30+BA84)/AZ30 -> 1.1842823
A84: Y/Y revenue change from existing customers (10-Q) | X84: 31.6 | Y84: =132.8-94.7 -> 38.1 | Z84: 28.7 | AA84: 32.3 | AB84: 30.6 | AC84: =125.9-AB84-AA84-Z84 -> 34.3 | AD84: 29.3 | AE84: 27.1 | AF84: 25.5 | AG84: =101.1-AF84-AE84-AD84 -> 19.2 | AH84: 23.1 | AI84: =49.2-AH84 -> 26.1 | AJ84: 25.5 | AK84: =101.1-AJ84-AI84-AH84 -> 26.4 | AY84: 93.6 | AZ84: 132.8 | BA84: =SUM(Z84:AC84) -> 125.9
A85: % of total revenue | X85: =X84/(X30-T30) -> 0.87324177 | Y85: =Y84/(Y30-U30) -> 1.069834 | Z85: =Z84/(Z30-V30) -> 0.97383869 | AA85: =AA84/(AA30-W30) -> 1.0522886 | AB85: =AB84/(AB30-X30) -> 1.1470125 | AC85: =AC84/(AC30-Y30) -> 1.1961639 | AD85: =AD84/(AD30-Z30) -> 1.0803038 | AE85: =AE84/(AE30-AA30) -> 1.0341538 | ... AK85: =AK84/(AK30-AG30) -> 1.0644303 | AY85: =AY84/(AY30-AX30) -> 0.9275684 | AZ85: =AZ84/(AZ30-AY30) -> 0.93480969 | BA85: =BA84/(BA30-AZ30) -> 1.089864
A86: Source: Company data, FactSet, Wells Fargo Securities, LLC estimates
B88: ='Income Statement'!B$3 -> 2017 | F88: ='Income Statement'!F$3 -> 2018 | J88: ='Income Statement'!J$3 -> 2019 | N88: ='Income Statement'!N$3 -> 2020 | R88: ='Income Statement'!R$3 -> 2021 | V88: ='Income Statement'!V$3 -> 2022 | Z88: ='Income Statement'!Z$3 -> 2023 | AD88: ='Income Statement'!AD$3 -> 2024 | AH88: ='Income Statement'!AH$3 -> 2025 | AL88: ='Income Statement'!AL$3 -> 2026 | AP88: ='Income Statement'!AP$3 -> 2027
A89: Geographic Mix | B89: ='Income Statement'!B$4 -> 42825 | C89: ='Income Statement'!C$4 -> 42916 | D89: ='Income Statement'!D$4 -> 43008 | E89: ='Income Statement'!E$4 -> 43100 | F89: ='Income Statement'!F$4 -> 43190 | G89: ='Income Statement'!G$4 -> 43281 | H89: ='Income Statement'!H$4 -> 43373 | I89: ='Income Statement'!I$4 -> 43465 | ... AS89: ='Income Statement'!AS$4 -> Dec-27E | AU89: ='Income Statement'!AU$4 -> 2017 | AV89: ='Income Statement'!AV$4 -> 2018 | AW89: ='Income Statement'!AW$4 -> 2019 | AX89: ='Income Statement'!AX$4 -> 2020 | AY89: ='Income Statement'!AY$4 -> CY21 | AZ89: ='Income Statement'!AZ$4 -> CY22 | BA89: ='Income Statement'!BA$4 -> CY23 | BB89: ='Income Statement'!BB$4 -> CY24 | ... BE89: ='Income Statement'!BE$4 -> CY27E
A90: AMERICAS | B90: 30.474 | C90: 33.092 | D90: 36.408 | E90: 39.50541 | F90: 42.762 | G90: 45.715 | H90: 49.391 | I90: 53.336 | J90: 56.091 | K90: 58.888 | L90: 62.413 | M90: 66.224 | N90: 69.314 | O90: 71.946 | P90: 74.569 | Q90: 77.905 | R90: 80.595 | S90: 84.462 | T90: 88.783 | U90: =347.724-SUM(R90:T90) -> 93.884 | V90: 99.5 | W90: 104.979 | X90: 111.227 | Y90: =432.734-SUM(V90:X90) -> 117.028 | Z90: 119.284 | AA90: 122.21 | AB90: 127.016 | AC90: =500.512-SUM(Z90:AB90) -> 132.002 | AD90: 134.483 | AE90: 136.754 | AF90: 140.79456 | AG90: =BB90-SUM(AD90:AF90) -> 146.03644 | AH90: 150.59 | AI90: 152.213 | AJ90: 154.918 | AU90: =SUM(B90:E90) -> 139.47941 | AV90: =SUM(F90:I90) -> 191.204 | AW90: =SUM(J90:M90) -> 243.616 | AX90: =SUM(N90:Q90) -> 293.734 | AY90: =SUM(R90:U90) -> 347.724 | AZ90: =SUM(V90:Y90) -> 432.734 | BA90: =SUM(Z90:AC90) -> 500.512 | BB90: 558.068
A91: Y/Y Growth | F91: =F90/B90-1 -> 0.40322898 | G91: =G90/C90-1 -> 0.38145171 | H91: =H90/D90-1 -> 0.35659745 | I91: =I90/E90-1 -> 0.35009357 | J91: =J90/F90-1 -> 0.31170198 | K91: =K90/G90-1 -> 0.28815487 | L91: =L90/H90-1 -> 0.26365127 | M91: =M90/I90-1 -> 0.24163792 | ... AJ91: =AJ90/AF90-1 -> 0.1003124 | AV91: =AV90/AU90-1 -> 0.37084033 | AW91: =AW90/AV90-1 -> 0.2741156 | AX91: =AX90/AW90-1 -> 0.2057254 | AY91: =AY90/AX90-1 -> 0.18380576 | AZ91: =AZ90/AY90-1 -> 0.2444755 | BA91: =BA90/AZ90-1 -> 0.1566274 | BB91: =BB90/BA90-1 -> 0.11499425
A92: Q/Q Growth | C92: =C90/B90-1 -> 0.0859093 | D92: =D90/C90-1 -> 0.10020549 | E92: =E90/D90-1 -> 0.085074984 | F92: =F90/E90-1 -> 0.082434026 | G92: =G90/F90-1 -> 0.069056639 | H92: =H90/G90-1 -> 0.080411244 | I92: =I90/H90-1 -> 0.079872851 | J92: =J90/I90-1 -> 0.051653667 | ... AJ92: =AJ90/AI90-1 -> 0.01777115
A93: % of total revenue | B93: =B90/B$5 -> 0.75279761 | C93: =C90/C$5 -> 0.74955265 | D93: =D90/D$5 -> 0.74332381 | E93: =E90/E$5 -> 0.73 | F93: =F90/F$5 -> 0.72346761 | G93: =G90/G$5 -> 0.71887973 | H93: =H90/H$5 -> 0.71127592 | I93: =I90/I$5 -> 0.70905731 | ... AE93: =AE90/AE$5 -> 0.61812232 | AF93: 0.62 | AG93: 0.62 | AH93: =AH90/AH$5 -> 0.62972271 | AI93: =AI90/AI$5 -> 0.61551184 | AJ93: 0.62 | AU93: =AU90/AU$5 -> 0.74299067 | AV93: =AV90/AV$5 -> 0.7151556 | AW93: =AW90/AW$5 -> 0.68704348 | AX93: =AX90/AX$5 -> 0.66724214 | AY93: =AY90/AY$5 -> 0.64258866 | AZ93: =AZ90/AZ$5 -> 0.6334012 | BA93: =BA90/BA$5 -> 0.62665047 | BB93: =BB90/BB$5 -> 0.62006109
A94: UNITED STATES | V94: =V5*V97 -> 89.24608 | W94: =W5*W97 -> 93.67437 | X94: =X5*X97 -> 99.66507 | Y94: =Y5*Y97 -> 98.40776 | Z94: =Z5*Z97 -> 105.74984 | AA94: =AA5*AA97 -> 107.2698 | AB94: =AB5*AB97 -> 110.84095 | AC94: =BA94-SUM(Z94:AB94) -> 115.42991 | AD94: =AD5*AD97 -> 116.61894 | AE94: =AE$5*AE97 -> 119.47014 | AF94: =AF$5*AF97 -> 122.62752 | AG94: =BB94-SUM(AD94:AF94) -> 127.29474 | AJ94: =AJ$5*AJ97 -> 136.3176 | AX94: =AX$5*AX97 -> 268.53481 | AY94: =AY$5*AY97 -> 313.8554 | AZ94: =AZ$5*AZ97 -> 382.58696 | BA94: =BA$5*BA97 -> 439.2905 | BB94: =BB$5*BB97 -> 486.01134
A95: Y/Y Growth | V95: NA | W95: NA | X95: NA | Y95: NA | Z95: =Z94/V94-1 -> 0.1849242 | AA95: =AA94/W94-1 -> 0.145135 | AB95: =AB94/X94-1 -> 0.11213437 | AC95: =AC94/Y94-1 -> 0.17297569 | AD95: =AD94/Z94-1 -> 0.10278124 | AE95: =AE94/AA94-1 -> 0.11373509 | AF95: =AF94/AB94-1 -> 0.10633768 | AG95: =AG94/AC94-1 -> 0.10278818 | AJ95: =AJ94/AF94-1 -> 0.11163954 | AX95: NA | AY95: =AY94/AX94-1 -> 0.16876989 | AZ95: =AZ94/AY94-1 -> 0.21899117 | BA95: =BA94/AZ94-1 -> 0.14821085 | BB95: =BB94/BA94-1 -> 0.10635523
A96: Q/Q Growth | V96: NA | W96: =W94/V94-1 -> 0.049618874 | X96: =X94/W94-1 -> 0.063952392 | Y96: =Y94/X94-1 -> -0.012615353 | Z96: =Z94/Y94-1 -> 0.07460875 | AA96: =AA94/Z94-1 -> 0.014373166 | AB96: =AB94/AA94-1 -> 0.03329129 | AC96: =AC94/AB94-1 -> 0.041401305 | AD96: =AD94/AC94-1 -> 0.010300883 | ... AG96: =AG94/AF94-1 -> 0.038060135
A97: % of total revenue | V97: 0.56 | W97: 0.57 | X97: 0.57 | Y97: =((AZ97*AZ5)-(57%*SUM(V5:X5)))/Y5 -> 0.53299695 | Z97: 0.56 | AA97: 0.55 | AB97: 0.55 | AC97: =AC94/AC5 -> 0.54114704 | AD97: 0.54 | AE97: 0.54 | AF97: 0.54 | AG97: =AG94/AG5 -> 0.54 | AJ97: 0.54 | AX97: 0.61 | AY97: 0.58 | AZ97: 0.56 | BA97: 0.55 | BB97: 0.54
A98: EMEA | B98: 7.032 | C98: 7.798 | D98: 8.781 | E98: 10.51 | F98: 11.666 | G98: 12.55 | H98: 14.002 | I98: 15.621 | J98: 17.307 | K98: 18.848 | L98: 19.968 | M98: 21.553 | N98: 23.55 | O98: 24.642 | P98: 26.193 | Q98: 27.77 | R98: 29.266 | S98: 31.947 | T98: 34.923 | U98: =135.176-SUM(R98:T98) -> 39.04 | V98: 43.139 | W98: 41.523 | X98: 44.117 | Y98: =175.767-SUM(V98:X98) -> 46.988 | Z98: 48.259 | AA98: 50.781 | AB98: 51.397 | AC98: =205.851-SUM(Z98:AB98) -> 55.414 | AD98: 57.038 | AE98: 59.32 | AF98: 59.04288 | AG98: =BB98-SUM(AD98:AF98) -> 64.34012 | AH98: 61.248 | AI98: 66.924 | AJ98: 68.261 | AU98: =SUM(B98:E98) -> 34.121 | AV98: =SUM(F98:I98) -> 53.839 | AW98: =SUM(J98:M98) -> 77.676 | AX98: =SUM(N98:Q98) -> 102.155 | AY98: =SUM(R98:U98) -> 135.176 | AZ98: =SUM(V98:Y98) -> 175.767 | BA98: =SUM(Z98:AC98) -> 205.851 | BB98: 239.741
A99: Y/Y Growth | F99: =F98/B98-1 -> 0.65898749 | G99: =G98/C98-1 -> 0.60938702 | H99: =H98/D98-1 -> 0.59457921 | I99: =I98/E98-1 -> 0.48629876 | J99: =J98/F98-1 -> 0.48354192 | K99: =K98/G98-1 -> 0.50183267 | L99: =L98/H98-1 -> 0.42608199 | M99: =M98/I98-1 -> 0.37974521 | ... AJ99: =AJ98/AF98-1 -> 0.15612585 | AV99: =AV98/AU98-1 -> 0.57788459 | AW99: =AW98/AV98-1 -> 0.44274596 | AX99: =AX98/AW98-1 -> 0.31514239 | AY99: =AY98/AX98-1 -> 0.32324409 | AZ99: =AZ98/AY98-1 -> 0.30028259 | BA99: =BA98/AZ98-1 -> 0.17115841 | BB99: =BB98/BA98-1 -> 0.16463364
A100: Q/Q Growth | C100: =C98/B98-1 -> 0.1089306 | D100: =D98/C98-1 -> 0.12605796 | E100: =E98/D98-1 -> 0.1969024 | F100: =F98/E98-1 -> 0.10999049 | G100: =G98/F98-1 -> 0.075775759 | H100: =H98/G98-1 -> 0.11569721 | I100: =I98/H98-1 -> 0.11562634 | J100: =J98/I98-1 -> 0.10793163 | ... AJ100: =AJ98/AI98-1 -> 0.019977885
A101: % of total revenue | B101: =B98/B$5 -> 0.17371112 | C101: =C98/C$5 -> 0.17662914 | D101: =D98/D$5 -> 0.17927726 | E101: =E98/E$5 -> 0.19420884 | F101: =F98/F$5 -> 0.19737087 | G101: =G98/G$5 -> 0.19735187 | H101: =H98/H$5 -> 0.20164171 | I101: =I98/I$5 -> 0.20766807 | ... Z101: =Z98/Z$5 -> 0.25555632 | AA101: 0.26 | AB101: 0.26 | AC101: =AC98/AC$5 -> 0.25978641 | AD101: =AD98/AD$5 -> 0.2641125 | AE101: =AE98/AE$5 -> 0.2681239 | AF101: 0.26 | AG101: 0.26 | AH101: =AH98/AH$5 -> 0.25612097 | AI101: =AI98/AI$5 -> 0.27062415 | AJ101: 0.26 | AU101: =AU98/AU$5 -> 0.18175862 | AV101: =AV98/AV$5 -> 0.20137268 | AW101: =AW98/AW$5 -> 0.2190611 | AX101: =AX98/AX$5 -> 0.2320539 | AY101: =AY98/AY$5 -> 0.24980319 | AZ101: =AZ98/AZ$5 -> 0.25727359 | BA101: =BA98/BA$5 -> 0.25772934 | BB101: =BB98/BB$5 -> 0.26637267
A102: APAC | B102: 2.975 | C102: 3.259 | D102: 3.791 | E102: 4.705 | F102: 4.679 | G102: 5.327 | H102: 6.047 | I102: 6.264 | J102: 6.903 | K102: 7.648 | L102: 9.471 | M102: 9.272 | N102: 9.784 | O102: 10.621 | P102: 11.52 | Q102: 12.407 | R102: 13.328 | S102: 13.85 | T102: 14.958 | U102: =58.23-SUM(R102:T102) -> 16.094 | V102: 16.729 | W102: 17.839 | X102: 19.507 | Y102: =74.69-SUM(V102:X102) -> 20.615 | Z102: 21.296 | AA102: 22.045 | AB102: 23.116 | AC102: =92.347-SUM(Z102:AB102) -> 25.89 | AD102: 24.44 | AE102: 25.167 | AF102: 27.25056 | AG102: =BB102-SUM(AD102:AF102) -> 25.35444 | AH102: 27.299 | AI102: 28.158 | AJ102: 29.261 | AU102: =SUM(B102:E102) -> 14.73 | AV102: =SUM(F102:I102) -> 22.317 | AW102: =SUM(J102:M102) -> 33.294 | AX102: =SUM(N102:Q102) -> 44.332 | AY102: =SUM(R102:U102) -> 58.23 | AZ102: =SUM(V102:Y102) -> 74.69 | BA102: =SUM(Z102:AC102) -> 92.347 | BB102: 102.212
A103: Y/Y Growth | F103: =F102/B102-1 -> 0.57277311 | G103: =G102/C102-1 -> 0.63455048 | H103: =H102/D102-1 -> 0.59509364 | I103: =I102/E102-1 -> 0.33134963 | J103: =J102/F102-1 -> 0.47531524 | K103: =K102/G102-1 -> 0.4357049 | L103: =L102/H102-1 -> 0.56623119 | M103: =M102/I102-1 -> 0.48020434 | ... AJ103: =AJ102/AF102-1 -> 0.073776099 | AV103: =AV102/AU102-1 -> 0.51507128 | AW103: =AW102/AV102-1 -> 0.49186719 | AX103: =AX102/AW102-1 -> 0.33153121 | AY103: =AY102/AX102-1 -> 0.31349815 | AZ103: =AZ102/AY102-1 -> 0.28267216 | BA103: =BA102/AZ102-1 -> 0.2364038 | BB103: =BB102/BA102-1 -> 0.10682534
A104: Q/Q Growth | C104: =C102/B102-1 -> 0.095462185 | D104: =D102/C102-1 -> 0.16324026 | E104: =E102/D102-1 -> 0.24109734 | F104: =F102/E102-1 -> -0.0055260361 | G104: =G102/F102-1 -> 0.13849113 | H104: =H102/G102-1 -> 0.1351605 | I104: =I102/H102-1 -> 0.035885563 | J104: =J102/I102-1 -> 0.10201149 | ... AJ104: =AJ102/AI102-1 -> 0.039171816
A105: % of total revenue | B105: =B102/B$5 -> 0.073491268 | C105: =C102/C$5 -> 0.073818207 | D105: =D102/D$5 -> 0.077398938 | E105: =E102/E$5 -> 0.086941257 | F105: =F102/F$5 -> 0.079161521 | G105: =G102/G$5 -> 0.083768399 | H105: =H102/H$5 -> 0.087082373 | I105: =I102/I$5 -> 0.083274617 | ... AE105: =AE102/AE$5 -> 0.11375378 | AF105: 0.12 | AG105: 0.12 | AH105: =AH102/AH$5 -> 0.11415632 | AI105: =AI102/AI$5 -> 0.11386401 | AJ105: 0.12 | AU105: =AU102/AU$5 -> 0.078465005 | AV105: =AV102/AV$5 -> 0.083471724 | AW105: =AW102/AW$5 -> 0.093895416 | AX105: =AX102/AX$5 -> 0.10070396 | AY105: =AY102/AY$5 -> 0.10760815 | AZ105: =AZ102/AZ$5 -> 0.10932521 | BA105: =BA102/BA$5 -> 0.11562019 | BB105: =BB102/BB$5 -> 0.11356624
A107: Tenable One as a % of New Enterprise Sales | AB107: 0.2 | AC107: 0.22 | AD107: 0.26 | AE107: 0.3 | AF107: 0.3 | AG107: 0.4 | AH107: 0.26
A108: Exposure Management as a % of New Enterprise Sales | AC108: 0.5 | AD108: 0.5 | AE108: 0.5 | AF108: 0.5 | AH108: 0.5
A110: Headcount | E110: 984 | G110: 1152 | H110: 1205 | I110: 1252 | J110: 1298 | K110: 1314 | L110: 1401 | M110: 1477 | N110: 1493 | O110: 1397 | P110: 1373 | Q110: 1367 | U110: 1617 | Y110: 1900 | AC110: 1999 | AG110: 1872 | AU110: =E110 -> 984 | AV110: =I110 -> 1252 | AW110: =M110 -> 1477 | AX110: =Q110 -> 1367 | AY110: =U110 -> 1617 | AZ110: =Y110 -> 1900 | BA110: =AC110 -> 1999 | BB110: =AG110 -> 1872
A111: Y/Y Growth | E111: =E110/751-1 -> 0.310253 | I111: =I110/E110-1 -> 0.27235772 | K111: =K110/G110-1 -> 0.140625 | L111: =L110/H110-1 -> 0.1626556 | M111: =M110/I110-1 -> 0.17971246 | N111: =N110/J110-1 -> 0.15023112 | O111: =O110/K110-1 -> 0.063165906 | P111: =P110/L110-1 -> -0.019985724 | Q111: =Q110/M110-1 -> -0.074475288 | U111: =U110/Q110-1 -> 0.18288222 | Y111: =Y110/U110-1 -> 0.17501546 | AC111: =AC110/Y110-1 -> 0.052105263 | AG111: =AG110/AC110-1 -> -0.063531766 | AU111: =AU110/751-1 -> 0.310253 | AV111: =AV110/AU110-1 -> 0.27235772 | AW111: =AW110/AV110-1 -> 0.17971246 | AX111: =AX110/AW110-1 -> -0.074475288 | AY111: =AY110/AX110-1 -> 0.18288222 | AZ111: =AZ110/AY110-1 -> 0.17501546 | BA111: =BA110/AZ110-1 -> 0.052105263 | BB111: =BB110/BA110-1 -> -0.063531766
A112: U.S.-based | I112: =I110-I114 -> 923 | M112: =M110-M114 -> 1001 | Q112: =Q110-Q114 -> 912 | U112: =U110-U114 -> 982 | Y112: =Y110-Y114 -> 1104 | AC112: =AC110-AC114 -> 1101 | AG112: 854 | AV112: =I112 -> 923 | AW112: =M112 -> 1001 | AX112: =Q112 -> 912 | AY112: =U112 -> 982 | AZ112: =Y112 -> 1104 | BA112: =AC112 -> 1101 | BB112: =AG112 -> 854
A113: Y/Y Growth | AC113: =AC112/Y112-1 -> -0.0027173913 | AG113: =AG112/AC112-1 -> -0.22434151 | AW113: =AW112/AV112-1 -> 0.084507042 | AX113: =AX112/AW112-1 -> -0.088911089 | AY113: =AY112/AX112-1 -> 0.076754386 | AZ113: =AZ112/AY112-1 -> 0.12423625 | BA113: =BA112/AZ112-1 -> -0.0027173913 | BB113: =BB112/BA112-1 -> -0.22434151
...

Sheet Balance Sheet
A1: =+'Income Statement'!A1 -> Tenable Holdings, Inc. (TENB)
A2: Balance Sheet | AU2: =+'Income Statement'!AU2 -> 2017 | AV2: =+'Income Statement'!AV2 -> 2018 | AW2: =+'Income Statement'!AW2 -> 2019 | AX2: =+'Income Statement'!AX2 -> 2020 | AY2: =+'Income Statement'!AY2 -> 2021 | AZ2: =+'Income Statement'!AZ2 -> 2022 | BA2: =+'Income Statement'!BA2 -> 2023 | BB2: =+'Income Statement'!BB2 -> 2024 | ... BE2: =+'Income Statement'!BE2 -> 2027
B3: ='Income Statement'!B$3 -> 2017 | F3: ='Income Statement'!F$3 -> 2018 | J3: ='Income Statement'!J$3 -> 2019 | N3: ='Income Statement'!N$3 -> 2020 | R3: ='Income Statement'!R$3 -> 2021 | V3: ='Income Statement'!V$3 -> 2022 | Z3: ='Income Statement'!Z$3 -> 2023 | AD3: ='Income Statement'!AD$3 -> 2024 | AH3: ='Income Statement'!AH$3 -> 2025 | AL3: ='Income Statement'!AL$3 -> 2026 | AP3: ='Income Statement'!AP$3 -> 2027
A4: ='Income Statement'!A4 -> ($ in millions, unless otherwise stated) | B4: ='Income Statement'!B$4 -> 42825 | C4: ='Income Statement'!C$4 -> 42916 | D4: ='Income Statement'!D$4 -> 43008 | E4: ='Income Statement'!E$4 -> 43100 | F4: ='Income Statement'!F$4 -> 43190 | G4: ='Income Statement'!G$4 -> 43281 | H4: ='Income Statement'!H$4 -> 43373 | I4: ='Income Statement'!I$4 -> 43465 | ... AS4: ='Income Statement'!AS$4 -> Dec-27E | AU4: ='Income Statement'!AU$4 -> 2017 | AV4: ='Income Statement'!AV$4 -> 2018 | AW4: ='Income Statement'!AW$4 -> 2019 | AX4: ='Income Statement'!AX$4 -> 2020 | AY4: ='Income Statement'!AY$4 -> CY21 | AZ4: ='Income Statement'!AZ$4 -> CY22 | BA4: ='Income Statement'!BA$4 -> CY23 | BB4: ='Income Statement'!BB$4 -> CY24 | ... BE4: ='Income Statement'!BE$4 -> CY27E
A5: Current assets
A6: Cash and Cash Equivalents | E6: 27.21 | F6: 26.424 | G6: 23.655 | H6: 253.026 | I6: 165.116 | J6: 167.966 | K6: 185.663 | L6: 171.303 | M6: 74.363 | N6: 107.769 | O6: 136.467 | P6: 141.387 | Q6: 178.223 | R6: 228.386 | S6: 135.927 | T6: 435.854 | U6: 278 | V6: 287.455 | W6: 267.859 | X6: 288.179 | Y6: 300.866 | Z6: 360.434 | AA6: 376.059 | AB6: 445.316 | AC6: 237.132 | AD6: 259.977 | AE6: 233.467 | AF6: 312.207 | AG6: 328.647 | AH6: 233.441 | AI6: 175.025 | AJ6: 171.852 | AK6: 187.762 | AL6: =AK6+'Cash Flow'!AL42 -> 260.82048 | AM6: =AL6+'Cash Flow'!AM42 -> 301.6401 | AN6: =AM6+'Cash Flow'!AN42 -> 354.33571 | AO6: =AN6+'Cash Flow'!AO42 -> 449.41876 | AP6: =AO6+'Cash Flow'!AP42 -> 526.6211 | AQ6: =AP6+'Cash Flow'!AQ42 -> 573.25011 | AR6: =AQ6+'Cash Flow'!AR42 -> 632.09772 | AS6: =AR6+'Cash Flow'!AS42 -> 736.42461 | AU6: =E6 -> 27.21 | AV6: =I6 -> 165.116 | AW6: =M6 -> 74.363 | AX6: =Q6 -> 178.223 | AY6: =U6 -> 278 | AZ6: =Y6 -> 300.866 | BA6: =AC6 -> 237.132 | BB6: =AG6 -> 328.647 | BC6: =AK6 -> 187.762 | BD6: =AO6 -> 449.41876 | BE6: =AS6 -> 736.42461
A7: Short-Term Investments | E7: 0 | F7: 0 | G7: 0 | H7: 34.125 | I7: 118.119 | J7: 131.014 | K7: 111.301 | L7: 125.333 | M7: 137.904 | N7: 118.924 | O7: 105.634 | P7: 127.72 | Q7: 113.623 | R7: 111.945 | S7: 125.111 | T7: 216.041 | U7: 234.292 | V7: 238.645 | W7: 243.047 | X7: 259.832 | Y7: 266.569 | Z7: 256.253 | AA7: 269.487 | AB7: 247.658 | AC7: 236.84 | AD7: 250.794 | AE7: 253.536 | AF7: 236.242 | AG7: 248.547 | AH7: 226.836 | AI7: 211.489 | AJ7: 211.719 | AK7: 214.419 | AL7: =AK7 -> 214.419 | AM7: =AL7 -> 214.419 | AN7: =AM7 -> 214.419 | AO7: =AN7 -> 214.419 | AP7: =AO7 -> 214.419 | AQ7: =AP7 -> 214.419 | AR7: =AQ7 -> 214.419 | AS7: =AR7 -> 214.419 | AU7: =E7 -> 0 | AV7: =I7 -> 118.119 | AW7: =M7 -> 137.904 | AX7: =Q7 -> 113.623 | AY7: =U7 -> 234.292 | AZ7: =Y7 -> 266.569 | BA7: =AC7 -> 236.84 | BB7: =AG7 -> 248.547 | BC7: =AK7 -> 214.419 | BD7: =AO7 -> 214.419 | BE7: =AS7 -> 214.419
A8: Accounts Receivables, net | E8: 50.881 | F8: 43.088 | G8: 49.93 | H8: 59.035 | I8: 68.261 | J8: 56.975 | K8: 68.983 | L8: 81.201 | M8: 94.827 | N8: 74.378 | O8: 81.782 | P8: 87.502 | Q8: 115.342 | R8: 82.822 | S8: 100.483 | T8: 115.421 | U8: 136.601 | V8: 96.381 | W8: 109.354 | X8: 147.944 | Y8: 187.341 | Z8: 123.855 | AA8: 154.436 | AB8: 179.432 | AC8: 220.06 | AD8: 156.804 | AE8: 179.612 | AF8: 192.648 | AG8: 258.734 | AH8: 167.793 | AI8: 181.114 | AJ8: 200.993 | AK8: 279.15 | AL8: =(AL59*AL66)/(365/4) -> 175.7589 | AM8: =(AM59*AM66)/(365/4) -> 188.65376 | AN8: =(AN59*AN66)/(365/4) -> 208.08633 | AO8: =(AO59*AO66)/(365/4) -> 291.13031 | AP8: =(AP59*AP66)/(365/4) -> 181.30106 | AQ8: =(AQ59*AQ66)/(365/4) -> 194.86924 | AR8: =(AR59*AR66)/(365/4) -> 215.47463 | AS8: =(AS59*AS66)/(365/4) -> 303.75607 | AU8: =E8 -> 50.881 | AV8: =I8 -> 68.261 | AW8: =M8 -> 94.827 | AX8: =Q8 -> 115.342 | AY8: =U8 -> 136.601 | AZ8: =Y8 -> 187.341 | BA8: =AC8 -> 220.06 | BB8: =AG8 -> 258.734 | BC8: =AK8 -> 279.15 | BD8: =AO8 -> 291.13031 | BE8: =AS8 -> 303.75607
A9: Deferred Commissions | E9: 17.17 | F9: 18.125 | G9: 19.078 | H9: 20.401 | I9: 23.272 | J9: 23.838 | K9: 24.867 | L9: 26.03 | M9: 28.499 | N9: 28.751 | O9: 29.62 | P9: 30.131 | Q9: 32.143 | R9: 31.936 | S9: 32.686 | T9: 34.248 | U9: 40.311 | V9: 40.335 | W9: 40.67 | X9: 41.283 | Y9: 44.27 | Z9: 44.045 | AA9: 45.036 | AB9: 46.132 | AC9: 49.559 | AD9: 49.168 | AE9: 49.388 | AF9: 49.858 | AG9: 51.791 | AH9: 51.247 | AI9: 50.785 | AJ9: 50.582 | AK9: 52.914 | AL9: =AL59*AL70 -> 52.82513 | AM9: =AM59*AM70 -> 51.875753 | AN9: =AN59*AN70 -> 51.162007 | AO9: =AO59*AO70 -> 53.56347 | AP9: =AP59*AP70 -> 53.550342 | AQ9: =AQ59*AQ70 -> 52.460432 | AR9: =AR59*AR70 -> 51.657965 | AS9: =AS59*AS70 -> 54.122485 | AU9: =E9 -> 17.17 | AV9: =I9 -> 23.272 | AW9: =M9 -> 28.499 | AX9: =Q9 -> 32.143 | AY9: =U9 -> 40.311 | AZ9: =Y9 -> 44.27 | BA9: =AC9 -> 49.559 | BB9: =AG9 -> 51.791 | BC9: =AK9 -> 52.914 | BD9: =AO9 -> 53.56347 | BE9: =AS9 -> 54.122485
A10: Prepaid Expenses & Other Current Assets | E10: 15.994 | F10: 14.795 | G10: 13.324 | H10: 14.718 | I10: 22.02 | J10: 20.636 | K10: 20.316 | L10: 21.126 | M10: 27.369 | N10: 25.632 | O10: 26.298 | P10: 34.236 | Q10: 44.462 | R10: 42.57 | S10: 42.255 | T10: 45.194 | U10: 60.234 | V10: 59.415 | W10: 49.444 | X10: 48.583 | Y10: 58.121 | Z10: 66.466 | AA10: 54.703 | AB10: 52.529 | AC10: 61.882 | AD10: 66.013 | AE10: 58.886 | AF10: 52.575 | AG10: 53.026 | AH10: 67.106 | AI10: 54.079 | AJ10: 44.186 | AK10: 39.339 | AL10: =AL59*AL71 -> 69.972668 | AM10: =AM59*AM71 -> 55.412733 | AN10: =AN59*AN71 -> 44.352841 | AO10: =AO59*AO71 -> 39.110214 | AP10: =AP59*AP71 -> 71.827936 | AQ10: =AQ59*AQ71 -> 56.230242 | AR10: =AR59*AR71 -> 44.401626 | AS10: =AS59*AS71 -> 38.720781 | AU10: =E10 -> 15.994 | AV10: =I10 -> 22.02 | AW10: =M10 -> 27.369 | AX10: =Q10 -> 44.462 | AY10: =U10 -> 60.234 | AZ10: =Y10 -> 58.121 | BA10: =AC10 -> 61.882 | BB10: =AG10 -> 53.026 | BC10: =AK10 -> 39.339 | BD10: =AO10 -> 39.110214 | BE10: =AS10 -> 38.720781
A11: Total current assets | E11: =SUM(E6:E10) -> 111.255 | F11: =SUM(F6:F10) -> 102.432 | G11: =SUM(G6:G10) -> 105.987 | H11: =SUM(H6:H10) -> 381.305 | I11: =SUM(I6:I10) -> 396.788 | J11: =SUM(J6:J10) -> 400.429 | K11: =SUM(K6:K10) -> 411.13 | L11: =SUM(L6:L10) -> 424.993 | ... AS11: =SUM(AS6:AS10) -> 1347.4429 | AU11: =E11 -> 111.255 | AV11: =I11 -> 396.788 | AW11: =M11 -> 362.962 | AX11: =Q11 -> 483.793 | AY11: =U11 -> 749.438 | AZ11: =Y11 -> 857.167 | BA11: =AC11 -> 805.473 | BB11: =AG11 -> 940.745 | BC11: =AK11 -> 773.584 | BD11: =AO11 -> 1047.6418 | BE11: =AS11 -> 1347.4429
A13: Property and Equipment, net | E13: 10.754 | F13: 11.015 | G13: 11.24 | H13: 10.872 | I13: 11.348 | J13: 12.714 | K13: 14.949 | L13: 18.525 | M13: 26.847 | N13: 30.534 | O13: 35.144 | P13: 39.96 | Q13: 38.92 | R13: 38.91 | S13: 37.407 | T13: 36.055 | U13: 36.833 | V13: 39.598 | W13: 43.372 | X13: 45.759 | Y13: 46.726 | Z13: 45.092 | AA13: 44.764 | AB13: 44.076 | AC13: 45.436 | AD13: 45.581 | AE13: 41.448 | AF13: 39.78 | AG13: 39.265 | AH13: 41.343 | AI13: 42.577 | AJ13: 40.471 | AK13: 40.062 | AL13: =AK13+(-'Cash Flow'!AL23-'Cash Flow'!AL24)-'Cash Flow'!AL78 -> 44.502303 | AM13: =AL13+(-'Cash Flow'!AM23-'Cash Flow'!AM24)-'Cash Flow'!AM78 -> 46.667367 | AN13: =AM13+(-'Cash Flow'!AN23-'Cash Flow'!AN24)-'Cash Flow'!AN78 -> 45.346044 | AO13: =AN13+(-'Cash Flow'!AO23-'Cash Flow'!AO24)-'Cash Flow'!AO78 -> 43.39264 | AP13: =AO13+(-'Cash Flow'!AP23-'Cash Flow'!AP24)-'Cash Flow'!AP78 -> 48.238974 | AQ13: =AP13+(-'Cash Flow'!AQ23-'Cash Flow'!AQ24)-'Cash Flow'!AQ78 -> 50.802487 | AR13: =AQ13+(-'Cash Flow'!AR23-'Cash Flow'!AR24)-'Cash Flow'!AR78 -> 49.876687 | AS13: =AR13+(-'Cash Flow'!AS23-'Cash Flow'!AS24)-'Cash Flow'!AS78 -> 48.309257 | AU13: =E13 -> 10.754 | AV13: =I13 -> 11.348 | AW13: =M13 -> 26.847 | AX13: =Q13 -> 38.92 | AY13: =U13 -> 36.833 | AZ13: =Y13 -> 46.726 | BA13: =AC13 -> 45.436 | BB13: =AG13 -> 39.265 | BC13: =AK13 -> 40.062 | BD13: =AO13 -> 43.39264 | BE13: =AS13 -> 48.309257
A14: Deferred Commissions | E14: 33.006 | F14: 32.326 | G14: 31.727 | H14: 32.483 | I14: 36.162 | J14: 35.973 | K14: 36.999 | L14: 38.493 | M14: 43.766 | N14: 41.991 | O14: 42.148 | P14: 41.753 | Q14: 46.733 | R14: 45.364 | S14: 45.811 | T14: 46.99 | U14: 59.638 | V14: 58.928 | W14: 59.33 | X14: 59.993 | Y14: 67.238 | Z14: 64.335 | AA14: 64.546 | AB14: 65.412 | AC14: 72.394 | AD14: 68.447 | AE14: 66.141 | AF14: 64.405 | AG14: 67.914 | AH14: 65.582 | AI14: 64.274 | AJ14: 64.518 | AK14: 71.715 | AL14: =AL59*AL72 -> 68.324843 | AM14: =AM59*AM72 -> 66.359759 | AN14: =AN59*AN72 -> 65.998239 | AO14: =AO59*AO72 -> 73.580831 | AP14: =AP59*AP72 -> 70.071517 | AQ14: =AQ59*AQ72 -> 67.897881 | AR14: =AR59*AR72 -> 67.468526 | AS14: =AS59*AS72 -> 75.45342 | AU14: =E14 -> 33.006 | AV14: =I14 -> 36.162 | AW14: =M14 -> 43.766 | AX14: =Q14 -> 46.733 | AY14: =U14 -> 59.638 | AZ14: =Y14 -> 67.238 | BA14: =AC14 -> 72.394 | BB14: =AG14 -> 67.914 | BC14: =AK14 -> 71.715 | BD14: =AO14 -> 73.580831 | BE14: =AS14 -> 75.45342
A15: Operating Lease Right-of-use-Assets | E15: 5.774 | F15: 3.595 | G15: 12.253 | H15: 23.546 | I15: 8.504 | J15: 9.829 | K15: 9.201 | L15: 40.346 | M15: 42.847 | N15: 41.283 | O15: 40.476 | P15: 41.43 | Q15: 39.426 | R15: 38.364 | S15: 37.299 | T15: 38.694 | U15: 38.53 | V15: 37.521 | W15: 36.906 | X15: 39.594 | Y15: 38.495 | Z15: 37.377 | AA15: 37.124 | AB15: 35.989 | AC15: 34.835 | AD15: 33.694 | AE15: 33.315 | AF15: 32.127 | AG15: 45.139 | AH15: 40.951 | AI15: 36.88 | AJ15: 35.488 | AK15: 35.558 | AL15: =AK15 -> 35.558 | AM15: =AL15 -> 35.558 | AN15: =AM15 -> 35.558 | AO15: =AN15 -> 35.558 | AP15: =AO15 -> 35.558 | AQ15: =AP15 -> 35.558 | AR15: =AQ15 -> 35.558 | AS15: =AR15 -> 35.558 | AU15: =E15 -> 5.774 | AV15: =I15 -> 8.504 | AW15: =M15 -> 42.847 | AX15: =Q15 -> 39.426 | AY15: =U15 -> 38.53 | AZ15: =Y15 -> 38.495 | BA15: =AC15 -> 34.835 | BB15: =AG15 -> 45.139 | BC15: =AK15 -> 35.558 | BD15: =AO15 -> 35.558 | BE15: =AS15 -> 35.558
A16: Intangible Assets | E16: 1.031 | F16: 0.88 | G16: 0.729 | H16: 0.578 | I16: 0 | J16: 0 | K16: 0 | L16: 0 | M16: 15.508 | N16: 14.929 | O16: 14.35 | P16: 13.771 | Q16: 13.193 | R16: 12.614 | S16: 42.61 | T16: 40.889 | U16: 71.536 | V16: 73.221 | W16: 81.536 | X16: 78.456 | Y16: 75.376 | Z16: 72.296 | AA16: 69.224 | AB16: 66.169 | AC16: 107.017 | AD16: 102.349 | AE16: 104.488 | AF16: 99.474 | AG16: 94.461 | AH16: 128.597 | AI16: 128.86 | AJ16: 122.078 | AK16: 115.296 | AL16: =AK16-'Cash Flow'!AL77 -> 108.514 | AM16: =AL16-'Cash Flow'!AM77 -> 101.732 | AN16: =AM16-'Cash Flow'!AN77 -> 94.95 | AO16: =AN16-'Cash Flow'!AO77 -> 88.168 | AP16: =AO16-'Cash Flow'!AP77 -> 81.386 | AQ16: =AP16-'Cash Flow'!AQ77 -> 74.604 | AR16: =AQ16-'Cash Flow'!AR77 -> 67.822 | AS16: =AR16-'Cash Flow'!AS77 -> 61.04 | AU16: =E16 -> 1.031 | AV16: =I16 -> 0 | AW16: =M16 -> 15.508 | AX16: =Q16 -> 13.193 | AY16: =U16 -> 71.536 | AZ16: =Y16 -> 75.376 | BA16: =AC16 -> 107.017 | BB16: =AG16 -> 94.461 | BC16: =AK16 -> 115.296 | BD16: =AO16 -> 88.168 | BE16: =AS16 -> 61.04
A17: Goodwill | E17: 0.265 | F17: 0.265 | G17: 0.265 | H17: 0.265 | I17: 0 | J17: 0 | K17: 0 | L17: 0 | M17: 54.138 | N17: 54.138 | O17: 54.138 | P17: 54.138 | Q17: 54.414 | R17: 54.414 | S17: 126.705 | T17: 126.705 | U17: 261.614 | V17: 280.574 | W17: 316.787 | X17: 316.787 | Y17: 316.52 | Z17: 316.52 | AA17: 316.52 | AB17: 316.52 | AC17: 518.539 | AD17: 518.539 | AE17: 541.292 | AF17: 541.292 | AG17: 541.292 | AH17: 656.481 | AI17: 697.769 | AJ17: 697.886 | AK17: 697.886 | AL17: =AK17 -> 697.886 | AM17: =AL17 -> 697.886 | AN17: =AM17 -> 697.886 | AO17: =AN17 -> 697.886 | AP17: =AO17 -> 697.886 | AQ17: =AP17 -> 697.886 | AR17: =AQ17 -> 697.886 | AS17: =AR17 -> 697.886 | AU17: =E17 -> 0.265 | AV17: =I17 -> 0 | AW17: =M17 -> 54.138 | AX17: =Q17 -> 54.414 | AY17: =U17 -> 261.614 | AZ17: =Y17 -> 316.52 | BA17: =AC17 -> 518.539 | BB17: =AG17 -> 541.292 | BC17: =AK17 -> 697.886 | BD17: =AO17 -> 697.886 | BE17: =AS17 -> 697.886
A18: Other Assets | E18: 2.252 | F18: 5.132 | G18: 7.157 | H18: 5.149 | I18: 7.81 | J18: 7.446 | K18: 8.49 | L18: 9.855 | M18: 12.544 | N18: 11.245 | O18: 9.779 | P18: 11.807 | Q18: 14.11 | R18: 13.522 | S18: 18.473 | T18: 22.399 | U18: 31.23 | V18: 25.802 | W18: 26.737 | X18: 23.327 | Y18: 38.008 | Z18: 36.604 | AA18: 33.94 | AB18: 25.213 | AC18: 23.177 | AD18: 15.656 | AE18: 14.776 | AF18: 13.811 | AG18: 13.303 | AH18: 14.2 | AI18: 13.72 | AJ18: 12.849 | AK18: 13.566 | AL18: =AL59*AL73 -> 15.353744 | AM18: =AM59*AM73 -> 14.732046 | AN18: =AN59*AN73 -> 13.679015 | AO18: =AO59*AO73 -> 14.443674 | AP18: =AP59*AP73 -> 16.365586 | AQ18: =AQ59*AQ73 -> 15.701816 | AR18: =AR59*AR73 -> 14.577346 | AS18: =AS59*AS73 -> 15.391493 | AU18: =E18 -> 2.252 | AV18: =I18 -> 7.81 | AW18: =M18 -> 12.544 | AX18: =Q18 -> 14.11 | AY18: =U18 -> 31.23 | AZ18: =Y18 -> 38.008 | BA18: =AC18 -> 23.177 | BB18: =AG18 -> 13.303 | BC18: =AK18 -> 13.566 | BD18: =AO18 -> 14.443674 | BE18: =AS18 -> 15.391493
A19: Total assets | E19: =SUM(E11:E18) -> 164.337 | F19: =SUM(F11:F18) -> 155.645 | G19: =SUM(G11:G18) -> 169.358 | H19: =SUM(H11:H18) -> 454.198 | I19: =SUM(I11:I18) -> 460.612 | J19: =SUM(J11:J18) -> 466.391 | K19: =SUM(K11:K18) -> 480.769 | L19: =SUM(L11:L18) -> 532.212 | ... AS19: =SUM(AS11:AS18) -> 2281.0811 | AU19: =E19 -> 164.337 | AV19: =I19 -> 460.612 | AW19: =M19 -> 558.612 | AX19: =Q19 -> 690.589 | AY19: =U19 -> 1248.819 | AZ19: =Y19 -> 1439.53 | BA19: =AC19 -> 1606.871 | BB19: =AG19 -> 1742.119 | BC19: =AK19 -> 1747.667 | BD19: =AO19 -> 2000.6709 | BE19: =AS19 -> 2281.0811
A21: Current liabilities
A22: Accounts Payable | E22: 0.338 | F22: 1.639 | G22: 1.457 | H22: 0.538 | I22: 0.171 | J22: 1.287 | K22: 2.207 | L22: 0.795 | M22: 1.732 | N22: 4.404 | O22: 0.429 | P22: 6.248 | Q22: 5.731 | R22: 9.555 | S22: 11.992 | T22: 16.011 | U22: 16.254 | V22: 17.057 | W22: 16.882 | X22: 26.237 | Y22: 18.722 | Z22: 21.872 | AA22: 24.855 | AB22: 26.88 | AC22: 16.941 | AD22: 17.667 | AE22: 19.543 | AF22: 17.833 | AG22: 19.981 | AH22: 17.684 | AI22: 18.828 | AJ22: 20.089 | AK22: 21.889 | AL22: =(AL60*AL67)/(365/4) -> 20.257832 | AM22: =(AM60*AM67)/(365/4) -> 21.380967 | AN22: =(AN60*AN67)/(365/4) -> 21.725754 | AO22: =(AO60*AO67)/(365/4) -> 24.361186 | AP22: =(AP60*AP67)/(365/4) -> 22.81689 | AQ22: =(AQ60*AQ67)/(365/4) -> 24.041589 | AR22: =(AR60*AR67)/(365/4) -> 24.406217 | AS22: =(AS60*AS67)/(365/4) -> 27.237162 | AU22: =E22 -> 0.338 | AV22: =I22 -> 0.171 | AW22: =M22 -> 1.732 | AX22: =Q22 -> 5.731 | AY22: =U22 -> 16.254 | AZ22: =Y22 -> 18.722 | BA22: =AC22 -> 16.941 | BB22: =AG22 -> 19.981 | BC22: =AK22 -> 21.889 | BD22: =AO22 -> 24.361186 | BE22: =AS22 -> 27.237162
A23: Accrued Expenses | E23: 4.878 | F23: 6.273 | G23: 7.462 | H23: 6.57 | I23: 5.554 | J23: 7.994 | K23: 9.77 | L23: 9.474 | M23: 8.436 | N23: 14.536 | O23: 7.909 | P23: 0 | Q23: 0 | R23: 0 | S23: 0 | T23: 0 | U23: 0 | V23: 0 | W23: 0 | X23: 0 | Y23: 0 | Z23: 0 | AA23: 0 | AB23: 0 | AC23: 0 | AD23: 0 | AE23: 0 | AF23: 0 | AG23: 0 | AH23: 0 | AI23: 0 | AJ23: 0 | AK23: 0 | AL23: 0 | AM23: 0 | AN23: 0 | AO23: 0 | AP23: 0 | AQ23: 0 | AR23: 0 | AS23: 0 | AU23: =E23 -> 4.878 | AV23: =I23 -> 5.554 | AW23: =M23 -> 8.436 | AX23: =Q23 -> 0 | AY23: =U23 -> 0 | AZ23: =Y23 -> 0 | BA23: =AC23 -> 0 | BB23: =AG23 -> 0 | BC23: =AK23 -> 0 | BD23: =AO23 -> 0 | BE23: =AS23 -> 0
A24: Accrued Payroll & Benefits | E24: 18.482 | F24: 14.178 | G24: 15.862 | H24: 19.734 | I24: 29.594 | J24: 22.36 | K24: 26.502 | L24: 24.244 | M24: 36.634 | N24: 23.357 | O24: 31.36 | P24: 28.244 | Q24: 35.509 | R24: 26.787 | S24: 35.901 | T24: 33.299 | U24: 54.051 | V24: 35.236 | W24: 41.199 | X24: 37.154 | Y24: 52.62 | Z24: 36.786 | AA24: 45.22 | AB24: 44.85 | AC24: 66.492 | AD24: 43.547 | AE24: 44.119 | AF24: 43.04 | AG24: 55.784 | AH24: 51.432 | AI24: 55.574 | AJ24: 48.429 | AK24: 69.166 | AL24: =AL59*AL75 -> 55.610829 | AM24: =AM59*AM75 -> 59.673376 | AN24: =AN59*AN75 -> 51.557398 | AO24: =AO59*AO75 -> 73.640805 | AP24: =AP59*AP75 -> 59.275693 | AQ24: =AQ59*AQ75 -> 63.601512 | AR24: =AR59*AR75 -> 54.943285 | AS24: =AS59*AS75 -> 78.473243 | AU24: =E24 -> 18.482 | AV24: =I24 -> 29.594 | AW24: =M24 -> 36.634 | AX24: =Q24 -> 35.509 | AY24: =U24 -> 54.051 | AZ24: =Y24 -> 52.62 | BA24: =AC24 -> 66.492 | BB24: =AG24 -> 55.784 | BC24: =AK24 -> 69.166 | BD24: =AO24 -> 73.640805 | BE24: =AS24 -> 78.473243
A25: Deferred Revenues | E25: 154.898 | F25: 160.503 | G25: 174.277 | H25: 191.578 | I25: 213.644 | J25: 214.508 | K25: 227.227 | L25: 245.985 | M25: 274.348 | N25: 270.916 | O25: 274.953 | P25: 296.36 | Q25: 328.819 | R25: 325.113 | S25: 334.106 | T25: 362.308 | U25: 407.498 | V25: 404.786 | W25: 415.378 | X25: 447.863 | Y25: 502.115 | Z25: 490.076 | AA25: 495.199 | AB25: 518.372 | AC25: 580.779 | AD25: 562.575 | AE25: 562.587 | AF25: 583.94 | AG25: 650.372 | AH25: 633.224 | AI25: 624.548 | AJ25: 639.614 | AK25: 706.866 | AL25: =AL86*AL88 -> 685.77817 | AM25: =AM86*AM88 -> 676.86025 | AN25: =AN86*AN88 -> 687.48278 | AO25: =AO86*AO88 -> 761.77629 | AP25: =AP86*AP88 -> 739.29873 | AQ25: =AQ86*AQ88 -> 729.79377 | AR25: =AR86*AR88 -> 741.11391 | AS25: =AS86*AS88 -> 820.28268 | AU25: =E25 -> 154.898 | AV25: =I25 -> 213.644 | AW25: =M25 -> 274.348 | AX25: =Q25 -> 328.819 | AY25: =U25 -> 407.498 | AZ25: =Y25 -> 502.115 | BA25: =AC25 -> 580.779 | BB25: =AG25 -> 650.372 | BC25: =AK25 -> 706.866 | BD25: =AO25 -> 761.77629 | BE25: =AS25 -> 820.28268
A26: Operating Leases | E26: 1.75 | F26: 1.822 | G26: 1.932 | H26: 1.897 | I26: 4.262 | J26: 3.981 | K26: 3.961 | L26: 3.97 | M26: 5.209 | N26: 4.866 | O26: 5.347 | P26: 6.312 | Q26: 3.815 | R26: 4.298 | S26: 5.355 | T26: 6.857 | U26: 2.32 | V26: 3.564 | W26: 5.014 | X26: 5.576 | Y26: 5.821 | Z26: 5.958 | AA26: 5.62 | AB26: 5.655 | AC26: 5.971 | AD26: 5.985 | AE26: 6.161 | AF26: 6.099 | AG26: 6.801 | AH26: 6.305 | AI26: 7.138 | AJ26: 8.327 | AK26: 9.596 | AL26: =AK26 -> 9.596 | AM26: =AL26 -> 9.596 | AN26: =AM26 -> 9.596 | AO26: =AN26 -> 9.596 | AP26: =AO26 -> 9.596 | AQ26: =AP26 -> 9.596 | AR26: =AQ26 -> 9.596 | AS26: =AR26 -> 9.596 | AU26: =E26 -> 1.75 | AV26: =I26 -> 4.262 | AW26: =M26 -> 5.209 | AX26: =Q26 -> 3.815 | AY26: =U26 -> 2.32 | AZ26: =Y26 -> 5.821 | BA26: =AC26 -> 5.971 | BB26: =AG26 -> 6.801 | BC26: =AK26 -> 9.596 | BD26: =AO26 -> 9.596 | BE26: =AS26 -> 9.596
A27: Other Current Liabilities | E27: 0 | F27: 0 | G27: 0 | H27: 0 | I27: 1.079 | J27: 0.653 | K27: 0.538 | L27: 0.701 | M27: 1.284 | N27: 0.75 | O27: 0.783 | P27: 1.126 | Q27: 1.028 | R27: 1.097 | S27: 0.274 | T27: 1.883 | U27: 3.759 | V27: 3.162 | W27: 4.592 | X27: 4.114 | Y27: 4.882 | Z27: 5.259 | AA27: 6.177 | AB27: 4.986 | AC27: 5.655 | AD27: 5.069 | AE27: 5.832 | AF27: 6.205 | AG27: 5.154 | AH27: 6.346 | AI27: 7.179 | AJ27: 3.852 | AK27: 5.432 | AL27: =AL59*AL76 -> 6.8616099 | AM27: =AM59*AM76 -> 7.7085537 | AN27: =AN59*AN76 -> 4.1008301 | AO27: =AO59*AO76 -> 5.7834319 | AP27: =AP59*AP76 -> 7.3138036 | AQ27: =AQ59*AQ76 -> 8.2159869 | AR27: =AR59*AR76 -> 4.3701405 | AS27: =AS59*AS76 -> 6.1629508 | AU27: =E27 -> 0 | AV27: =I27 -> 1.079 | AW27: =M27 -> 1.284 | AX27: =Q27 -> 1.028 | AY27: =U27 -> 3.759 | AZ27: =Y27 -> 4.882 | BA27: =AC27 -> 5.655 | BB27: =AG27 -> 5.154 | BC27: =AK27 -> 5.432 | BD27: =AO27 -> 5.7834319 | BE27: =AS27 -> 6.1629508
A28: Current Portion of Long-term Debt | E28: 0 | F28: 0 | G28: 0 | H28: 0 | I28: 0 | J28: 0 | K28: 0 | L28: 0 | M28: 0 | N28: 0 | O28: 0 | P28: 0 | Q28: 0 | R28: 0 | S28: 0 | T28: 0 | U28: 0 | V28: 0 | W28: 0 | X28: 0 | Y28: 0 | Z28: =Y28 -> 0 | AA28: 0 | AB28: 0 | AC28: 0 | AD28: 0 | AE28: 0 | AF28: 0 | AG28: 0 | AH28: 0 | AI28: =AH28 -> 0 | AJ28: =AI28 -> 0 | AK28: 0 | AL28: =AK28 -> 0 | AM28: =AL28 -> 0 | AN28: =AM28 -> 0 | AO28: =AN28 -> 0 | AP28: =AO28 -> 0 | AQ28: =AP28 -> 0 | AR28: =AQ28 -> 0 | AS28: =AR28 -> 0 | AU28: =E28 -> 0 | AV28: =I28 -> 0 | AW28: =M28 -> 0 | AX28: =Q28 -> 0 | AY28: =U28 -> 0 | AZ28: =Y28 -> 0 | BA28: =AC28 -> 0 | BB28: =AG28 -> 0 | BC28: =AK28 -> 0 | BD28: =AO28 -> 0 | BE28: =AS28 -> 0
A29: Total current liabilities | E29: =SUM(E22:E28) -> 180.346 | F29: =SUM(F22:F28) -> 184.415 | G29: =SUM(G22:G28) -> 200.99 | H29: =SUM(H22:H28) -> 220.317 | I29: =SUM(I22:I28) -> 254.304 | J29: =SUM(J22:J28) -> 250.783 | K29: =SUM(K22:K28) -> 270.205 | L29: =SUM(L22:L28) -> 285.169 | ... AS29: =SUM(AS22:AS28) -> 941.75204 | AU29: =E29 -> 180.346 | AV29: =I29 -> 254.304 | AW29: =M29 -> 327.643 | AX29: =Q29 -> 374.902 | AY29: =U29 -> 483.882 | AZ29: =Y29 -> 584.16 | BA29: =AC29 -> 675.838 | BB29: =AG29 -> 738.092 | BC29: =AK29 -> 812.949 | BD29: =AO29 -> 875.15771 | BE29: =AS29 -> 941.75204
A31: Long term liabilities
A32: Deferred Revenues | E32: 70.92 | F32: 70.111 | G32: 72.86 | H32: 74.12 | I32: 76.259 | J32: 77.397 | K32: 80.106 | L32: 83.39 | M32: 88.779 | N32: 87.175 | O32: 90.356 | P32: 93.842 | Q32: 105.691 | R32: 103.749 | S32: 110.768 | T32: 114.649 | U32: 123.387 | V32: 122.722 | W32: 132.677 | X32: 145.849 | Y32: 162.487 | Z32: 151.992 | AA32: 154.995 | AB32: 163.086 | AC32: 169.718 | AD32: 160.133 | AE32: 163.211 | AF32: 163.512 | AG32: 182.815 | AH32: 175.151 | AI32: 173.261 | AJ32: 170.889 | AK32: 192.41 | AL32: =AL86*AL89 -> 186.66986 | AM32: =AM86*AM89 -> 184.24239 | AN32: =AN86*AN89 -> 187.13386 | AO32: =AO86*AO89 -> 207.35666 | AP32: =AP86*AP89 -> 201.23824 | AQ32: =AQ86*AQ89 -> 198.65097 | AR32: =AR86*AR89 -> 201.73233 | AS32: =AS86*AS89 -> 223.28219 | AU32: =E32 -> 70.92 | AV32: =I32 -> 76.259 | AW32: =M32 -> 88.779 | AX32: =Q32 -> 105.691 | AY32: =U32 -> 123.387 | AZ32: =Y32 -> 162.487 | BA32: =AC32 -> 169.718 | BB32: =AG32 -> 182.815 | BC32: =AK32 -> 192.41 | BD32: =AO32 -> 207.35666 | BE32: =AS32 -> 223.28219
A33: Long-term Debt | E33: 0 | F33: 0 | G33: 0 | H33: 0 | I33: 0 | J33: 0 | K33: 0 | L33: 0 | M33: 0 | N33: 0 | O33: 0 | P33: 0 | Q33: 0 | R33: 0 | S33: 0 | T33: 365.387 | U33: 364.728 | V33: 364.063 | W33: 363.404 | X33: 362.679 | Y33: 361.97 | Z33: 361.287 | AA33: 360.609 | AB33: 359.941 | AC33: 359.281 | AD33: 358.622 | AE33: 357.969 | AF33: 357.334 | AG33: 356.705 | AH33: 356.068 | AI33: 355.439 | AJ33: 354.82 | AK33: 354.209 | AL33: =AK33+'Cash Flow'!AL32 -> 354.209 | AM33: =AL33+'Cash Flow'!AM32 -> 354.209 | AN33: =AM33+'Cash Flow'!AN32 -> 354.209 | AO33: =AN33+'Cash Flow'!AO32 -> 354.209 | AP33: =AO33+'Cash Flow'!AP32 -> 354.209 | AQ33: =AP33+'Cash Flow'!AQ32 -> 354.209 | AR33: =AQ33+'Cash Flow'!AR32 -> 354.209 | AS33: =AR33+'Cash Flow'!AS32 -> 354.209 | AU33: =E33 -> 0 | AV33: =I33 -> 0 | AW33: =M33 -> 0 | AX33: =Q33 -> 0 | AY33: =U33 -> 364.728 | AZ33: =Y33 -> 361.97 | BA33: =AC33 -> 359.281 | BB33: =AG33 -> 356.705 | BC33: =AK33 -> 354.209 | BD33: =AO33 -> 354.209 | BE33: =AS33 -> 354.209
A34: Operating Leases | E34: 0 | F34: 0 | G34: 0 | H34: 0 | I34: 6.055 | J34: 7.466 | K34: 6.559 | L34: 37.788 | M34: 40.663 | N34: 40.301 | O34: 48.678 | P34: 55.645 | Q34: 54.529 | R34: 53.201 | S34: 52.028 | T34: 52.881 | U34: 55.046 | V34: 53.685 | W34: 52.158 | X34: 53.746 | Y34: 52.611 | Z34: 51.088 | AA34: 51.005 | AB34: 49.382 | AC34: 48.058 | AD34: 46.317 | AE34: 45.315 | AF34: 43.706 | AG34: 56.224 | AH34: 54.621 | AI34: 54.059 | AJ34: 52.053 | AK34: 50.877 | AL34: =AK34 -> 50.877 | AM34: =AL34 -> 50.877 | AN34: =AM34 -> 50.877 | AO34: =AN34 -> 50.877 | AP34: =AO34 -> 50.877 | AQ34: =AP34 -> 50.877 | AR34: =AQ34 -> 50.877 | AS34: =AR34 -> 50.877 | AU34: =E34 -> 0 | AV34: =I34 -> 6.055 | AW34: =M34 -> 40.663 | AX34: =Q34 -> 54.529 | AY34: =U34 -> 55.046 | AZ34: =Y34 -> 52.611 | BA34: =AC34 -> 48.058 | BB34: =AG34 -> 56.224 | BC34: =AK34 -> 50.877 | BD34: =AO34 -> 50.877 | BE34: =AS34 -> 50.877
A35: Other Liabilities | E35: =5.199+1.802 -> 7.001 | F35: =4.914+3.145 -> 8.059 | G35: =4.315+11.803 -> 16.118 | H35: =4.104+23.096 -> 27.2 | I35: 2.231 | J35: 2.536 | K35: 2.94 | L35: 2.677 | M35: 2.622 | N35: 2.893 | O35: 4.853 | P35: 4.931 | Q35: 4.802 | R35: 5.108 | S35: 8.888 | T35: 7.158 | U35: 6.463 | V35: 6.632 | W35: 6.213 | X35: 6.664 | Y35: 7.436 | Z35: 7.28 | AA35: 7.598 | AB35: 7.621 | AC35: 7.632 | AD35: 8.159 | AE35: 8.051 | AF35: 8.195 | AG35: 8.329 | AH35: 9.585 | AI35: 9.847 | AJ35: 10.173 | AK35: 10.846 | AL35: =AL59*AL77 -> 10.363777 | AM35: =AM59*AM77 -> 10.573357 | AN35: =AN59*AN77 -> 10.830152 | AO35: =AO59*AO77 -> 11.547699 | AP35: =AP59*AP77 -> 11.046771 | AQ35: =AQ59*AQ77 -> 11.269372 | AR35: =AR59*AR77 -> 11.541391 | AS35: =AS59*AS77 -> 12.30548 | AU35: =E35 -> 7.001 | AV35: =I35 -> 2.231 | AW35: =M35 -> 2.622 | AX35: =Q35 -> 4.802 | AY35: =U35 -> 6.463 | AZ35: =Y35 -> 7.436 | BA35: =AC35 -> 7.632 | BB35: =AG35 -> 8.329 | BC35: =AK35 -> 10.846 | BD35: =AO35 -> 11.547699 | BE35: =AS35 -> 12.30548
A36: Total liabilities | E36: =SUM(E29:E35) -> 258.267 | F36: =SUM(F29:F35) -> 262.585 | G36: =SUM(G29:G35) -> 289.968 | H36: =SUM(H29:H35) -> 321.637 | I36: =SUM(I29:I35) -> 338.849 | J36: =SUM(J29:J35) -> 338.182 | K36: =SUM(K29:K35) -> 359.81 | L36: =SUM(L29:L35) -> 409.024 | ... AS36: =SUM(AS29:AS35) -> 1582.4257 | AU36: =E36 -> 258.267 | AV36: =I36 -> 338.849 | AW36: =M36 -> 459.707 | AX36: =Q36 -> 539.924 | AY36: =U36 -> 1033.506 | AZ36: =Y36 -> 1168.664 | BA36: =AC36 -> 1260.527 | BB36: =AG36 -> 1342.165 | BC36: =AK36 -> 1421.291 | BD36: =AO36 -> 1499.1481 | BE36: =AS36 -> 1582.4257
A38: Stockholders' equity
A39: Convertible Preferred Stock | E39: =49.935+227.8 -> 277.735 | F39: =49.94+227.983 -> 277.923 | G39: =49.946+228.168 -> 278.114 | H39: 0 | I39: 0 | J39: 0 | K39: 0 | L39: 0 | M39: 0 | N39: 0 | O39: 0 | P39: 0 | Q39: 0 | R39: 0 | S39: 0 | T39: 0 | U39: 0 | V39: 0 | W39: 0 | X39: 0 | Y39: 0 | Z39: 0 | AA39: 0 | AB39: 0 | AC39: 0 | AD39: 0 | AE39: 0 | AF39: 0 | AG39: 0 | AH39: 0 | AI39: 0 | AJ39: 0 | AK39: 0 | AL39: 0 | AM39: 0 | AN39: 0 | AO39: 0 | AP39: 0 | AQ39: 0 | AR39: 0 | AS39: 0 | AU39: =E39 -> 277.735 | AV39: =I39 -> 0 | AW39: =M39 -> 0 | AX39: =Q39 -> 0 | AY39: =U39 -> 0 | AZ39: =Y39 -> 0 | BA39: =AC39 -> 0 | BB39: =AG39 -> 0 | BC39: =AK39 -> 0 | BD39: =AO39 -> 0 | BE39: =AS39 -> 0
A40: Common Stock | E40: 0.246 | F40: 0.249 | G40: 0.25 | H40: 0.93 | I40: 0.931 | J40: 0.962 | K40: 0.968 | L40: 0.98 | M40: 0.986 | N40: 1 | O40: 1.011 | P40: 1.028 | Q40: 1.037 | R40: 1.055 | S40: 1.065 | T40: 1.074 | U40: 1.089 | V40: 1.103 | W40: 1.116 | X40: 1.124 | Y40: 1.131 | Z40: 1.147 | AA40: 1.156 | AB40: 1.165 | AC40: 1.175 | AD40: 1.196 | AE40: 1.205 | AF40: 1.213 | AG40: 1.224 | AH40: 1.245 | AI40: 1.274 | AJ40: 1.283 | AK40: 1.29 | AL40: =AK40 -> 1.29 | AM40: =AL40 -> 1.29 | AN40: =AM40 -> 1.29 | AO40: =AN40 -> 1.29 | AP40: =AO40 -> 1.29 | AQ40: =AP40 -> 1.29 | AR40: =AQ40 -> 1.29 | AS40: =AR40 -> 1.29 | AU40: =E40 -> 0.246 | AV40: =I40 -> 0.931 | AW40: =M40 -> 0.986 | AX40: =Q40 -> 1.037 | AY40: =U40 -> 1.089 | AZ40: =Y40 -> 1.131 | BA40: =AC40 -> 1.175 | BB40: =AG40 -> 1.224 | BC40: =AK40 -> 1.29 | BD40: =AO40 -> 1.29 | BE40: =AS40 -> 1.29
A41: Additional Paid-In-Capital | E41: =20.676 -> 20.676 | F41: =23.363 -> 23.363 | G41: =26.651 -> 26.651 | H41: 578.125 | I41: 586.94 | J41: 614.774 | K41: 629.087 | L41: 648.964 | M41: 662.99 | N41: 687.311 | O41: 710.066 | P41: 735.961 | Q41: 757.47 | R41: 786.476 | S41: 811.644 | T41: 840.482 | U41: 869.059 | V41: 906.263 | W41: 944.799 | X41: 985.864 | Y41: 1017.837 | Z41: 1063.051 | AA41: 1101.928 | AB41: 1146.435 | AC41: =1185.1-14.934 -> 1170.166 | AD41: =1237.283-39.925 -> 1197.358 | AE41: =1281.545-64.925 -> 1216.62 | AF41: =1330.517-64.925 -> 1265.592 | AG41: =1374.659-114.911 -> 1259.748 | AH41: =1440.77-174.911 -> 1265.859 | AI41: =1489.379-241.239 -> 1248.14 | AJ41: =1540.611-301.208 -> 1239.403 | AK41: =1586.727-364.574 -> 1222.153 | AL41: =AK41+'Cash Flow'!AL9+'Cash Flow'!AL35+'Cash Flow'!AL36+'Cash Flow'!AL37 -> 1276.452 | AM41: =AL41+'Cash Flow'!AM9+'Cash Flow'!AM35+'Cash Flow'!AM36+'Cash Flow'!AM37 -> 1324.2486 | AN41: =AM41+'Cash Flow'!AN9+'Cash Flow'!AN35+'Cash Flow'!AN36+'Cash Flow'!AN37 -> 1372.6231 | AO41: =AN41+'Cash Flow'!AO9+'Cash Flow'!AO35+'Cash Flow'!AO36+'Cash Flow'!AO37 -> 1422.553 | AP41: =AO41+'Cash Flow'!AP9+'Cash Flow'!AP35+'Cash Flow'!AP36+'Cash Flow'!AP37 -> 1480.4305 | AQ41: =AP41+'Cash Flow'!AQ9+'Cash Flow'!AQ35+'Cash Flow'!AQ36+'Cash Flow'!AQ37 -> 1531.3733 | AR41: =AQ41+'Cash Flow'!AR9+'Cash Flow'!AR35+'Cash Flow'!AR36+'Cash Flow'!AR37 -> 1582.9247 | AS41: =AR41+'Cash Flow'!AS9+'Cash Flow'!AS35+'Cash Flow'!AS36+'Cash Flow'!AS37 -> 1636.1311 | AU41: =E41 -> 20.676 | AV41: =I41 -> 586.94 | AW41: =M41 -> 662.99 | AX41: =Q41 -> 757.47 | AY41: =U41 -> 869.059 | AZ41: =Y41 -> 1017.837 | BA41: =AC41 -> 1170.166 | BB41: =AG41 -> 1259.748 | BC41: =AK41 -> 1222.153 | BD41: =AO41 -> 1422.553 | BE41: =AS41 -> 1636.1311
A42: Accumulated Other Comprehensive Income | E42: 0 | F42: 0 | G42: 0 | H42: 0 | I42: 0 | J42: 0.021 | K42: 0.08 | L42: 0.06 | M42: 0.05 | N42: 0.163 | O42: 0.149 | P42: 0.054 | Q42: 0.01 | R42: 0.008 | S42: -0.016 | T42: -0.015 | U42: -0.306 | V42: -1.363 | W42: -1.856 | X42: -1.869 | Y42: -1.351 | Z42: -0.671 | AA42: -0.701 | AB42: -0.54 | AC42: 0.038 | AD42: -0.185 | AE42: -0.271 | AF42: 0.954 | AG42: 0.318 | AH42: 0.328 | AI42: 0.262 | AJ42: 0.407 | AK42: 0.387 | AL42: =AK42+'Cash Flow'!AL41 -> 0.387 | AM42: =AL42+'Cash Flow'!AM41 -> 0.387 | AN42: =AM42+'Cash Flow'!AN41 -> 0.387 | AO42: =AN42+'Cash Flow'!AO41 -> 0.387 | AP42: =AO42+'Cash Flow'!AP41 -> 0.387 | AQ42: =AP42+'Cash Flow'!AQ41 -> 0.387 | AR42: =AQ42+'Cash Flow'!AR41 -> 0.387 | AS42: =AR42+'Cash Flow'!AS41 -> 0.387 | AU42: =E42 -> 0 | AV42: =I42 -> 0 | AW42: =M42 -> 0.05 | AX42: =Q42 -> 0.01 | AY42: =U42 -> -0.306 | AZ42: =Y42 -> -1.351 | BA42: =AC42 -> 0.038 | BB42: =AG42 -> 0.318 | BC42: =AK42 -> 0.387 | BD42: =AO42 -> 0.387 | BE42: =AS42 -> 0.387
A43: Accumulated Deficit | E43: -392.587 | F43: -408.475 | G43: -425.625 | H43: -446.494 | I43: -466.108 | J43: -487.548 | K43: -509.176 | L43: -526.816 | M43: -565.121 | N43: -588.098 | O43: -600.058 | P43: -605.916 | Q43: -607.852 | R43: -615.6 | S43: -627.238 | T43: -643.484 | U43: -654.529 | V43: -679.035 | W43: -706.534 | X43: -725.264 | Y43: -746.751 | Z43: -771.848 | AA43: -787.822 | AB43: -803.387 | AC43: -825.035 | AD43: -839.421 | AE43: -853.993 | AF43: -863.204 | AG43: -861.336 | AH43: -884.271 | AI43: -898.977 | AJ43: -896.717 | AK43: -897.454 | AL43: =AK43+'Income Statement'!AL99 -> -914.41804 | AM43: =AL43+'Income Statement'!AM99 -> -926.10998 | AN43: =AM43+'Income Statement'!AN99 -> -926.03966 | AO43: =AN43+'Income Statement'!AO99 -> -922.7072 | AP43: =AO43+'Income Statement'!AP99 -> -940.55407 | AQ43: =AP43+'Income Statement'!AQ99 -> -949.62635 | AR43: =AQ43+'Income Statement'!AR99 -> -946.15145 | AS43: =AR43+'Income Statement'!AS99 -> -939.15271 | AU43: =E43 -> -392.587 | AV43: =I43 -> -466.108 | AW43: =M43 -> -565.121 | AX43: =Q43 -> -607.852 | AY43: =U43 -> -654.529 | AZ43: =Y43 -> -746.751 | BA43: =AC43 -> -825.035 | BB43: =AG43 -> -861.336 | BC43: =AK43 -> -897.454 | BD43: =AO43 -> -922.7072 | BE43: =AS43 -> -939.15271
A44: Total stockholders' equity | E44: =SUM(E39:E43) -> -93.93 | F44: =SUM(F39:F43) -> -106.94 | G44: =SUM(G39:G43) -> -120.61 | H44: =SUM(H39:H43) -> 132.561 | I44: =SUM(I39:I43) -> 121.763 | J44: =SUM(J39:J43) -> 128.209 | K44: =SUM(K39:K43) -> 120.959 | L44: =SUM(L39:L43) -> 123.188 | ... T44: =SUM(T39:T43) -> 198.057 | U44: 215.313 | V44: =SUM(V39:V43) -> 226.968 | W44: =SUM(W39:W43) -> 237.525 | X44: =SUM(X39:X43) -> 259.855 | Y44: =SUM(Y39:Y43) -> 270.866 | Z44: =SUM(Z39:Z43) -> 291.679 | AA44: =SUM(AA39:AA43) -> 314.561 | AB44: =SUM(AB39:AB43) -> 343.673 | AC44: =SUM(AC39:AC43) -> 346.344 | ... AS44: =SUM(AS39:AS43) -> 698.6554 | AU44: =E44 -> -93.93 | AV44: =I44 -> 121.763 | AW44: =M44 -> 98.905 | AX44: =Q44 -> 150.665 | AY44: =U44 -> 215.313 | AZ44: =Y44 -> 270.866 | BA44: =AC44 -> 346.344 | BB44: =AG44 -> 399.954 | BC44: =AK44 -> 326.376 | BD44: =AO44 -> 501.52282 | BE44: =AS44 -> 698.6554
A45: Total liabilities and shareholders' equity | E45: =E44+E36 -> 164.337 | F45: =F44+F36 -> 155.645 | G45: =G44+G36 -> 169.358 | H45: =H44+H36 -> 454.198 | I45: =I44+I36 -> 460.612 | J45: =J44+J36 -> 466.391 | K45: =K44+K36 -> 480.769 | L45: =L44+L36 -> 532.212 | ... AS45: =AS44+AS36 -> 2281.0811 | AU45: =E45 -> 164.337 | AV45: =I45 -> 460.612 | AW45: =M45 -> 558.612 | AX45: =Q45 -> 690.589 | AY45: =U45 -> 1248.819 | AZ45: =Y45 -> 1439.53 | BA45: =AC45 -> 1606.871 | BB45: =AG45 -> 1742.119 | BC45: =AK45 -> 1747.667 | BD45: =AO45 -> 2000.6709 | BE45: =AS45 -> 2281.0811
A47: Net cash | E47: =E6+E7-E33-E28 -> 27.21 | F47: =F6+F7-F33-F28 -> 26.424 | G47: =G6+G7-G33-G28 -> 23.655 | H47: =H6+H7-H33-H28 -> 287.151 | I47: =I6+I7-I33-I28 -> 283.235 | J47: =J6+J7-J33-J28 -> 298.98 | K47: =K6+K7-K33-K28 -> 296.964 | L47: =L6+L7-L33-L28 -> 296.636 | ... AS47: =AS6+AS7-AS33-AS28 -> 596.63461 | AU47: =AU6+AU7-AU33-AU28 -> 27.21 | AV47: =AV6+AV7-AV33-AV28 -> 283.235 | AW47: =AW6+AW7-AW33-AW28 -> 212.267 | AX47: =AX6+AX7-AX33-AX28 -> 291.846 | AY47: =AY6+AY7-AY33-AY28 -> 147.564 | AZ47: =AZ6+AZ7-AZ33-AZ28 -> 205.465 | BA47: =BA6+BA7-BA33-BA28 -> 114.691 | BB47: =BB6+BB7-BB33-BB28 -> 220.489 | BC47: =BC6+BC7-BC33-BC28 -> 47.972 | BD47: =AO47 -> 309.62876 | BE47: =AS47 -> 596.63461
A48: Y/Y Growth | I48: =I47/E47-1 -> 9.4092245 | J48: =J47/F47-1 -> 10.314714 | K48: =K47/G47-1 -> 11.553963 | L48: =L47/H47-1 -> 0.033031402 | M48: =M47/I47-1 -> -0.25056225 | N48: =N47/J47-1 -> -0.24177871 | O48: =O47/K47-1 -> -0.1847463 | P48: =P47/L47-1 -> -0.092803975 | ... AS48: =AS47/AO47-1 -> 0.92693536 | AU48: =IF(ISERROR(AU47/AT47-1),"NA",AU47/AT47-1) -> NA | AV48: =IF(ISERROR(AV47/AU47-1),"NA",AV47/AU47-1) -> 9.4092245 | AW48: =IF(ISERROR(AW47/AV47-1),"NA",AW47/AV47-1) -> -0.25056225 | AX48: =IF(ISERROR(AX47/AW47-1),"NA",AX47/AW47-1) -> 0.37490048 | AY48: =IF(ISERROR(AY47/AX47-1),"NA",AY47/AX47-1) -> -0.49437717 | AZ48: =IF(ISERROR(AZ47/AY47-1),"NA",AZ47/AY47-1) -> 0.3923789 | BA48: =IF(ISERROR(BA47/AZ47-1),"NA",BA47/AZ47-1) -> -0.44179787 | BB48: =IF(ISERROR(BB47/BA47-1),"NA",BB47/BA47-1) -> 0.92246122 | ... BE48: =IF(ISERROR(BE47/BD47-1),"NA",BE47/BD47-1) -> 0.92693536
A50: Net cash per diluted share | E50: =E47/'Income Statement'!E53 -> 0.34789613 | F50: =F47/'Income Statement'!F53 -> 0.33498561 | G50: =G47/'Income Statement'!G53 -> 0.29891579 | H50: =H47/'Income Statement'!H53 -> 3.2369631 | I50: =I47/'Income Statement'!I53 -> 3.0723963 | J50: =J47/'Income Statement'!J53 -> 3.1895283 | K50: =K47/'Income Statement'!K53 -> 3.099186 | L50: =L47/'Income Statement'!L53 -> 3.067305 | ... AS50: =AS47/'Income Statement'!AS53 -> 5.0023862 | AU50: NA | AV50: NA | AW50: =M50 -> 2.171796 | AX50: =Q50 -> 2.5897898 | AY50: =+U50 -> 1.2670135 | AZ50: =+Y50 -> 1.747954 | BA50: =AC50 -> 0.93991297 | BB50: =AG50 -> 1.7802476 | BC50: =AK50 -> 0.4032955 | BD50: =AO50 -> 2.6250849 | BE50: =AS50 -> 5.0023862
A51: Y/Y Growth | I51: =I50/E50-1 -> 7.831361 | J51: =J50/F50-1 -> 8.5213888 | K51: =K50/G50-1 -> 9.3680905 | L51: =L50/H50-1 -> -0.052412747 | M51: =M50/I50-1 -> -0.29312634 | N51: =N50/J50-1 -> -0.28102628 | O51: =O50/K50-1 -> -0.28059888 | P51: =P50/L50-1 -> -0.21119524 | ... AS51: =AS50/AO50-1 -> 0.90560934 | AU51: =IF(ISERROR(AU50/AT50-1),"NA",AU50/AT50-1) -> NA | AV51: =IF(ISERROR(AV50/AU50-1),"NA",AV50/AU50-1) -> NA | AW51: =IF(ISERROR(AW50/AV50-1),"NA",AW50/AV50-1) -> NA | AX51: =IF(ISERROR(AX50/AW50-1),"NA",AX50/AW50-1) -> 0.19246455 | AY51: =IF(ISERROR(AY50/AX50-1),"NA",AY50/AX50-1) -> -0.51076587 | AZ51: =IF(ISERROR(AZ50/AY50-1),"NA",AZ50/AY50-1) -> 0.37958587 | BA51: =IF(ISERROR(BA50/AZ50-1),"NA",BA50/AZ50-1) -> -0.4622782 | BB51: =IF(ISERROR(BB50/BA50-1),"NA",BB50/BA50-1) -> 0.89405574 | ... BE51: =IF(ISERROR(BE50/BD50-1),"NA",BE50/BD50-1) -> 0.90560934
A52: Source: Company data, Wells Fargo Securities, LLC estimates
A54: Check | E54: =IF((E19=E45)*AND(E19>0),"—","X") -> — | F54: =IF((F19=F45)*AND(F19>0),"—","X") -> — | G54: =IF((G19=G45)*AND(G19>0),"—","X") -> — | H54: =IF((H19=H45)*AND(H19>0),"—","X") -> — | I54: =IF((I19=I45)*AND(I19>0),"—","X") -> — | J54: =IF((J19=J45)*AND(J19>0),"—","X") -> — | K54: =IF((K19=K45)*AND(K19>0),"—","X") -> — | L54: =IF((L19=L45)*AND(L19>0),"—","X") -> — | ... AS54: =IF((AS19=AS45)*AND(AS19>0),"—","X") -> — | AV54: =IF((AV19=AV45)*AND(AV19>0),"—","X") -> — | AW54: =IF((AW19=AW45)*AND(AW19>0),"—","X") -> — | AX54: =IF((AX19=AX45)*AND(AX19>0),"—","X") -> — | AY54: =IF((AY19=AY45)*AND(AY19>0),"—","X") -> — | AZ54: =IF((AZ19=AZ45)*AND(AZ19>0),"—","X") -> — | BA54: =IF((BA19=BA45)*AND(BA19>0),"—","X") -> — | BB54: =IF((BB19=BB45)*AND(BB19>0),"—","X") -> — | BC54: =IF((BC19=BC45)*AND(BC19>0),"—","X") -> — | ... BE54: =IF((BE19=BE45)*AND(BE19>0),"—","X") -> —
E55: =+E19-E45 -> 0 | F55: =+F19-F45 -> 0 | G55: =+G19-G45 -> 0 | H55: =+H19-H45 -> 0 | I55: =+I19-I45 -> 0 | J55: =+J19-J45 -> 0 | K55: =+K19-K45 -> 0 | L55: =+L19-L45 -> 0 | ... AS55: =+AS19-AS45 -> 0
B57: ='Income Statement'!B$3 -> 2017 | F57: ='Income Statement'!F$3 -> 2018 | J57: ='Income Statement'!J$3 -> 2019 | N57: ='Income Statement'!N$3 -> 2020 | R57: ='Income Statement'!R$3 -> 2021 | V57: ='Income Statement'!V$3 -> 2022 | Z57: ='Income Statement'!Z$3 -> 2023 | AD57: ='Income Statement'!AD$3 -> 2024 | AH57: ='Income Statement'!AH$3 -> 2025 | AL57: ='Income Statement'!AL$3 -> 2026 | AP57: ='Income Statement'!AP$3 -> 2027
A58: Income Statement | B58: =B4 -> 42825 | C58: =C4 -> 42916 | D58: =D4 -> 43008 | E58: =E4 -> 43100 | F58: =F4 -> 43190 | G58: =G4 -> 43281 | H58: =H4 -> 43373 | I58: =I4 -> 43465 | ... AS58: =AS4 -> Dec-27E | AU58: ='Income Statement'!AU$4 -> 2017 | AV58: ='Income Statement'!AV$4 -> 2018 | AW58: ='Income Statement'!AW$4 -> 2019 | AX58: ='Income Statement'!AX$4 -> 2020 | AY58: ='Income Statement'!AY$4 -> CY21 | AZ58: ='Income Statement'!AZ$4 -> CY22 | BA58: ='Income Statement'!BA$4 -> CY23 | BB58: ='Income Statement'!BB$4 -> CY24 | ... BE58: ='Income Statement'!BE$4 -> CY27E
A59: Revenue | B59: =+'Income Statement'!B9 -> 40.481 | C59: =+'Income Statement'!C9 -> 44.149 | D59: =+'Income Statement'!D9 -> 48.98 | E59: =+'Income Statement'!E9 -> 54.117 | F59: =+'Income Statement'!F9 -> 59.107 | G59: =+'Income Statement'!G9 -> 63.592 | H59: =+'Income Statement'!H9 -> 69.44 | I59: =+'Income Statement'!I9 -> 75.221 | ... AS59: =+'Income Statement'!AS9 -> 295.59132
A60: COGS | B60: =+'Income Statement'!B16 -> 4.233 | C60: =+'Income Statement'!C16 -> 5.147 | D60: =+'Income Statement'!D16 -> 7.21 | E60: =+'Income Statement'!E16 -> 8.114 | F60: =+'Income Statement'!F16 -> 8.5 | G60: =+'Income Statement'!G16 -> 9.614 | H60: =+'Income Statement'!H16 -> 11.318 | I60: =+'Income Statement'!I16 -> 11.425 | ... AS60: =+'Income Statement'!AS16 -> 51.43289
A61: R&D | B61: =+'Income Statement'!B22 -> 12.064 | C61: =+'Income Statement'!C22 -> 13.261 | D61: =+'Income Statement'!D22 -> 15.359 | E61: =+'Income Statement'!E22 -> 15.207 | F61: =+'Income Statement'!F22 -> 16.658 | G61: =+'Income Statement'!G22 -> 17.151 | H61: =+'Income Statement'!H22 -> 18.126 | I61: =+'Income Statement'!I22 -> 18.959 | ... AS61: =+'Income Statement'!AS22 -> 46.335588
A62: EBIT | B62: =+'Income Statement'!B25 -> -6.969 | C62: =+'Income Statement'!C25 -> -7.229 | D62: =+'Income Statement'!D25 -> -8.983 | E62: =+'Income Statement'!E25 -> -9.216 | F62: =+'Income Statement'!F25 -> -12.899 | G62: =+'Income Statement'!G25 -> -13.27 | H62: =+'Income Statement'!H25 -> -12.162 | I62: =+'Income Statement'!I25 -> -10.772 | ... AS62: =+'Income Statement'!AS25 -> 79.220176
A63: Net Income | B63: =+'Income Statement'!B39 -> -7.059 | C63: =+'Income Statement'!C39 -> -7.226 | D63: =+'Income Statement'!D39 -> -9.147 | E63: =+'Income Statement'!E39 -> -9.281 | F63: =+'Income Statement'!F39 -> -13.361 | G63: =+'Income Statement'!G39 -> -14 | H63: =+'Income Statement'!H39 -> -12.025 | I63: =+'Income Statement'!I39 -> -10.875 | ... AS63: =+'Income Statement'!AS39 -> 71.432176
A65: Working Capital Ratios
A66: Days Sales Outstanding (DSO) | E66: =+(E8/E59)*(365/4) -> 85.793581 | F66: =+(F8/F59)*(365/4) -> 66.519702 | G66: =+(G8/G59)*(365/4) -> 71.646001 | H66: =+(H8/H59)*(365/4) -> 77.576955 | I66: =+(I8/I59)*(365/4) -> 82.806879 | J66: =+(J8/J59)*(365/4) -> 64.743512 | K66: =+(K8/K59)*(365/4) -> 73.722228 | L66: =+(L8/L59)*(365/4) -> 80.668807 | ... AK66: =+(AK8/AK59)*(365/4) -> 97.770484 | AL66: =+AH66-2 -> 62.026526 | AM66: =+AI66-2 -> 64.829707 | AN66: =+AJ66-2 -> 70.653348 | AO66: =+AK66-2 -> 95.770484 | AP66: =+AL66-2 -> 60.026526 | AQ66: =+AM66-2 -> 62.829707 | AR66: =+AN66-2 -> 68.653348 | AS66: =+AO66-2 -> 93.770484
A67: Days Payable Outstanding (DPO) | E67: =+(E22/E60)*(365/4) -> 3.8011462 | F67: =+(F22/F60)*(365/4) -> 17.595147 | G67: =+(G22/G60)*(365/4) -> 13.828921 | H67: =+(H22/H60)*(365/4) -> 4.3375596 | I67: =+(I22/I60)*(365/4) -> 1.3657549 | J67: =+(J22/J60)*(365/4) -> 9.4533325 | K67: =+(K22/K60)*(365/4) -> 15.461708 | L67: =+(L22/L60)*(365/4) -> 5.0286809 | ... AK67: =+(AK22/AK60)*(365/4) -> 44.322991 | AL67: =+AH67+2 -> 39.28345 | AM67: =+AI67+2 -> 40.662714 | AN67: =+AJ67+2 -> 41.44232 | AO67: =+AK67+2 -> 46.322991 | AP67: =+AL67+2 -> 41.28345 | AQ67: =+AM67+2 -> 42.662714 | AR67: =+AN67+2 -> 43.44232 | AS67: =+AO67+2 -> 48.322991
A69: Current assets & liabilities
A70: =A9 -> Deferred Commissions | E70: =E9/E59 -> 0.31727553 | F70: =F9/F59 -> 0.30664727 | G70: =G9/G59 -> 0.30000629 | H70: =H9/H59 -> 0.2937932 | I70: =I9/I59 -> 0.30938169 | J70: =J9/J59 -> 0.29685807 | K70: =K9/K59 -> 0.29123723 | L70: =L9/L59 -> 0.28339067 | ... AK70: =AK9/AK59 -> 0.20309903 | AL70: =+AH70-1% -> 0.20429975 | AM70: =+AI70-1% -> 0.19536202 | AN70: =+AJ70-1% -> 0.19037237 | AO70: =+AK70-1% -> 0.19309903 | AP70: =+AL70-1% -> 0.19429975 | AQ70: =+AM70-1% -> 0.18536202 | AR70: =+AN70-1% -> 0.18037237 | AS70: =+AO70-1% -> 0.18309903
A71: =A10 -> Prepaid Expenses & Other Current Assets | E71: =E10/E59 -> 0.29554484 | F71: =F10/F59 -> 0.25030876 | G71: =G10/G59 -> 0.20952321 | H71: =H10/H59 -> 0.21195276 | I71: =I10/I59 -> 0.2927374 | J71: =J10/J59 -> 0.2569831 | K71: =K10/K59 -> 0.23793685 | L71: =L10/L59 -> 0.23000044 | ... AK71: =AK10/AK59 -> 0.15099431 | AL71: =+AH71-1% -> 0.27061739 | AM71: =+AI71-1% -> 0.20868214 | AN71: =+AJ71-1% -> 0.16503565 | AO71: =+AK71-1% -> 0.14099431 | AP71: =+AL71-1% -> 0.26061739 | AQ71: =+AM71-1% -> 0.19868214 | AR71: =+AN71-1% -> 0.15503565 | AS71: =+AO71-1% -> 0.13099431
A72: Deferred Commissions (long-term) | E72: =E14/E59 -> 0.60990077 | F72: =F14/F59 -> 0.54690646 | G72: =G14/G59 -> 0.49891496 | H72: =H14/H59 -> 0.46778514 | I72: =I14/I59 -> 0.48074341 | J72: =J14/J59 -> 0.44797699 | K72: =K14/K59 -> 0.43332474 | L72: =L14/L59 -> 0.41907634 | ... AK72: =AK14/AK59 -> 0.27526263 | AL72: =+AH72-1% -> 0.26424447 | AM72: =+AI72-1% -> 0.24990821 | AN72: =+AJ72-1% -> 0.24557756 | AO72: =+AK72-1% -> 0.26526263 | AP72: =+AL72-1% -> 0.25424447 | AQ72: =+AM72-1% -> 0.23990821 | AR72: =+AN72-1% -> 0.23557756 | AS72: =+AO72-1% -> 0.25526263
A73: Other Long-Term Assets | E73: =E18/E59 -> 0.041613541 | F73: =F18/F59 -> 0.086825587 | G73: =G18/G59 -> 0.1125456 | H73: =H18/H59 -> 0.074150346 | I73: =I18/I59 -> 0.10382739 | J73: =J18/J59 -> 0.092726118 | K73: =K18/K59 -> 0.099433149 | L73: =L18/L59 -> 0.10729217 | ... AK73: =AK18/AK59 -> 0.052070179 | AL73: =+AH73 -> 0.059380188 | AM73: =+AI73 -> 0.055480297 | AN73: =+AJ73 -> 0.050899224 | AO73: =+AK73 -> 0.052070179 | AP73: =+AL73 -> 0.059380188 | AQ73: =+AM73 -> 0.055480297 | AR73: =+AN73 -> 0.050899224 | AS73: =+AO73 -> 0.052070179
A75: =A24 -> Accrued Payroll & Benefits | E75: =+E24/E59 -> 0.3415193 | F75: =+F24/F59 -> 0.23987007 | G75: =+G24/G59 -> 0.24943389 | H75: =+H24/H59 -> 0.28418779 | I75: =+I24/I59 -> 0.39342737 | J75: =+J24/J59 -> 0.27845232 | K75: =+K24/K59 -> 0.31038602 | L75: =+L24/L59 -> 0.26394635 | ... AK75: =+AK24/AK59 -> 0.26547885 | AL75: =+AH75 -> 0.21507337 | AM75: =+AI75 -> 0.22472755 | AN75: =+AJ75 -> 0.19184361 | AO75: =+AK75 -> 0.26547885 | AP75: =+AL75 -> 0.21507337 | AQ75: =+AM75 -> 0.22472755 | AR75: =+AN75 -> 0.19184361 | AS75: =+AO75 -> 0.26547885
A76: =A27 -> Other Current Liabilities | E76: =+E27/E59 -> 0 | F76: =+F27/F59 -> 0 | G76: =+G27/G59 -> 0 | H76: =+H27/H59 -> 0 | I76: =+I27/I59 -> 0.014344399 | J76: =+J27/J59 -> 0.0081319037 | K76: =+K27/K59 -> 0.0063009463 | L76: =+L27/L59 -> 0.0076318425 | ... AK76: =+AK27/AK59 -> 0.020849566 | AL76: =+AH76 -> 0.02653709 | AM76: =+AI76 -> 0.029030106 | AN76: =+AJ76 -> 0.015259071 | AO76: =+AK76 -> 0.020849566 | AP76: =+AL76 -> 0.02653709 | AQ76: =+AM76 -> 0.029030106 | AR76: =+AN76 -> 0.015259071 | AS76: =+AO76 -> 0.020849566
A77: Other Liabilities (long-term) | E77: =+E35/E59 -> 0.12936785 | F77: =+F35/F59 -> 0.13634595 | G77: =+G35/G59 -> 0.25345955 | H77: =+H35/H59 -> 0.39170507 | I77: =+I35/I59 -> 0.029659271 | J77: =+J35/J59 -> 0.031581176 | K77: =+K35/K59 -> 0.034432681 | L77: =+L35/L59 -> 0.029144711 | ... AK77: =+AK35/AK59 -> 0.041630043 | AL77: =+AH77 -> 0.040081627 | AM77: =+AI77 -> 0.03981884 | AN77: =+AJ77 -> 0.040298685 | AO77: =+AK77 -> 0.041630043 | AP77: =+AL77 -> 0.040081627 | AQ77: =+AM77 -> 0.03981884 | AR77: =+AN77 -> 0.040298685 | AS77: =+AO77 -> 0.041630043
A79: CFFO | B79: ='Cash Flow'!B20 -> 1.187 | C79: ='Cash Flow'!C20 -> -1.019 | D79: ='Cash Flow'!D20 -> -0.982 | E79: ='Cash Flow'!E20 -> -5.452 | F79: ='Cash Flow'!F20 -> 0.504 | G79: ='Cash Flow'!G20 -> 0.242 | H79: ='Cash Flow'!H20 -> -1.751 | I79: ='Cash Flow'!I20 -> -1.554 | ... AS79: ='Cash Flow'!AS20 -> 107.85889 | AU79: ='Cash Flow'!AU20 -> -6.266 | AV79: ='Cash Flow'!AV20 -> -2.559 | AW79: ='Cash Flow'!AW20 -> -10.744 | AX79: ='Cash Flow'!AX20 -> 64.232 | AY79: ='Cash Flow'!AY20 -> 96.765 | AZ79: ='Cash Flow'!AZ20 -> 131.151 | BA79: ='Cash Flow'!BA20 -> 149.855 | BB79: ='Cash Flow'!BB20 -> 217.476 | ... BE79: ='Cash Flow'!BE20 -> 311.59985
A80: Unlevered Free Cash Flow | B80: ='Cash Flow'!#REF! -> #REF! | C80: ='Cash Flow'!#REF! -> #REF! | D80: ='Cash Flow'!#REF! -> #REF! | E80: ='Cash Flow'!#REF! -> #REF! | F80: ='Cash Flow'!#REF! -> #REF! | G80: ='Cash Flow'!#REF! -> #REF! | H80: ='Cash Flow'!#REF! -> #REF! | I80: ='Cash Flow'!#REF! -> #REF! | ... Q80: ='Cash Flow'!#REF! -> #REF! | R80: ='Cash Flow'!R50 -> 37.635 | S80: ='Cash Flow'!S50 -> 15.08 | T80: ='Cash Flow'!T50 -> 20.073 | U80: ='Cash Flow'!U50 -> 22.394 | V80: ='Cash Flow'!V50 -> 32.102 | W80: ='Cash Flow'!W50 -> 29.081 | X80: ='Cash Flow'!X50 -> 34.759 | Y80: ='Cash Flow'!Y50 -> 32.108 | ... AS80: ='Cash Flow'!AS50 -> 111.84089 | AU80: ='Cash Flow'!AU48 -> -9.021 | AV80: ='Cash Flow'!AV48 -> -8.292 | AW80: ='Cash Flow'!AW48 -> -31.418 | AX80: ='Cash Flow'!AX48 -> 43.955 | AY80: ='Cash Flow'!AY50 -> 95.182 | AZ80: ='Cash Flow'!AZ50 -> 128.05 | BA80: ='Cash Flow'!BA50 -> 175.742 | BB80: ='Cash Flow'!BB50 -> 238.41 | BC80: ='Cash Flow'!BC50 -> 276.85 | BD80: ='Cash Flow'!BD50 -> 289.07276 | BE80: ='Cash Flow'!BE50 -> 316.34185
A81: Consensus Unlevered FCF | J81: ='Cash Flow'!#REF! -> #REF! | K81: ='Cash Flow'!#REF! -> #REF! | L81: ='Cash Flow'!#REF! -> #REF! | M81: ='Cash Flow'!#REF! -> #REF! | N81: ='Cash Flow'!#REF! -> #REF! | O81: ='Cash Flow'!#REF! -> #REF! | P81: ='Cash Flow'!#REF! -> #REF! | Q81: ='Cash Flow'!#REF! -> #REF! | U81: ='Cash Flow'!U52 -> 13.964752 | V81: ='Cash Flow'!V52 -> 23.61851 | W81: ='Cash Flow'!W52 -> 13.37735 | X81: ='Cash Flow'!X52 -> 19.743008 | Y81: ='Cash Flow'!Y52 -> 22.264984 | Z81: ='Cash Flow'!Z52 -> 40.164961 | AA81: ='Cash Flow'!AA52 -> 28.457831 | AB81: ='Cash Flow'!AB52 -> 43.781652 | ... AS81: ='Cash Flow'!AS52 -> 101.43385 | AY81: ='Cash Flow'!AY52 -> 84.987115 | AZ81: ='Cash Flow'!AZ52 -> 107.59353 | BA81: ='Cash Flow'!BA52 -> 139.36409 | BB81: ='Cash Flow'!BB52 -> 230.99967 | BC81: ='Cash Flow'!BC52 -> 270.6455 | BD81: ='Cash Flow'!BD52 -> 291.07501 | BE81: ='Cash Flow'!BE52 -> 327.54771
A82: uFCF Margin | R82: ='Cash Flow'!R53 -> 0.30550617 | S82: ='Cash Flow'!S53 -> 0.11576935 | T82: ='Cash Flow'!T53 -> 0.14476 | U82: ='Cash Flow'!U53 -> 0.15027715 | V82: ='Cash Flow'!V53 -> 0.20143316 | W82: ='Cash Flow'!W53 -> 0.17695523 | X82: ='Cash Flow'!X53 -> 0.19879211 | Y82: ='Cash Flow'!Y53 -> 0.17390362 | ... AS82: ='Cash Flow'!AS53 -> 0.37836324 | AU82: ='Cash Flow'!AU53 -> 0 | AV82: ='Cash Flow'!AV53 -> 0 | AW82: ='Cash Flow'!AW53 -> 0 | AX82: ='Cash Flow'!AX53 -> 0 | AY82: ='Cash Flow'!AY53 -> 0.17589489 | AZ82: ='Cash Flow'!AZ53 -> 0.18742928 | BA82: ='Cash Flow'!BA53 -> 0.2200323 | BB82: ='Cash Flow'!BB53 -> 0.26489382 | ... BE82: ='Cash Flow'!BE53 -> 0.27734433
A84: Billings | B84: ='Revenue Build'!B34 -> 0 | C84: ='Revenue Build'!C34 -> 0 | D84: ='Revenue Build'!D34 -> 0 | E84: ='Revenue Build'!E34 -> 0 | F84: ='Revenue Build'!F34 -> 63.903 | G84: ='Revenue Build'!G34 -> 80.115 | H84: ='Revenue Build'!H34 -> 88.001 | I84: ='Revenue Build'!I34 -> 99.426 | ... AS84: ='Revenue Build'!AS34 -> 396.30996
A85: Change in deferred | B85: ='Revenue Build'!B33 -> 0 | C85: ='Revenue Build'!C33 -> 0 | D85: ='Revenue Build'!D33 -> 0 | E85: ='Revenue Build'!E33 -> 118.371 | F85: ='Revenue Build'!F33 -> 4.796 | G85: ='Revenue Build'!G33 -> 16.523 | H85: ='Revenue Build'!H33 -> 18.561 | I85: ='Revenue Build'!I33 -> 24.205 | ... AS85: ='Revenue Build'!AS33 -> 100.71864
A86: Ending deferred balance, total deferred revenue | B86: ='Revenue Build'!B32 -> 0 | C86: ='Revenue Build'!C32 -> 0 | D86: ='Revenue Build'!D32 -> 0 | E86: ='Revenue Build'!E32 -> 225.818 | F86: ='Revenue Build'!F32 -> 230.614 | G86: ='Revenue Build'!G32 -> 247.137 | H86: ='Revenue Build'!H32 -> 265.698 | I86: ='Revenue Build'!I32 -> 289.903 | ... AS86: ='Revenue Build'!AS32 -> 1043.5649
A88: Short term deferred as % of deferred mix | E88: =E25/E86 -> 0.68594178 | F88: =F25/F86 -> 0.69598116 | G88: =G25/G86 -> 0.70518376 | H88: =H25/H86 -> 0.72103667 | I88: =I25/I86 -> 0.73694995 | J88: =J25/J86 -> 0.73485552 | K88: =K25/K86 -> 0.73935113 | L88: =L25/L86 -> 0.74682353 | ... AK88: =AK25/AK86 -> 0.78603899 | AL88: =AK88 -> 0.78603899 | AM88: =AL88 -> 0.78603899 | AN88: =AM88 -> 0.78603899 | AO88: =AN88 -> 0.78603899 | AP88: =AO88 -> 0.78603899 | AQ88: =AP88 -> 0.78603899 | AR88: =AQ88 -> 0.78603899 | AS88: =AR88 -> 0.78603899
A89: Long term deferred as % of deferred mix | E89: =E32/E86 -> 0.31405822 | F89: =F32/F86 -> 0.30401884 | G89: =G32/G86 -> 0.29481624 | H89: =H32/H86 -> 0.27896333 | I89: =I32/I86 -> 0.26305005 | J89: =J32/J86 -> 0.26514448 | K89: =K32/K86 -> 0.26064887 | L89: =L32/L86 -> 0.25317647 | ... AK89: =AK32/AK86 -> 0.21396101 | AL89: =1-AL88 -> 0.21396101 | AM89: =1-AM88 -> 0.21396101 | AN89: =1-AN88 -> 0.21396101 | AO89: =1-AO88 -> 0.21396101 | AP89: =1-AP88 -> 0.21396101 | AQ89: =1-AQ88 -> 0.21396101 | AR89: =1-AR88 -> 0.21396101 | AS89: =1-AS88 -> 0.21396101
A90: Source: Company data, Wells Fargo Securities, LLC estimates

Sheet Cash Flow
A1: =+'Income Statement'!A1 -> Tenable Holdings, Inc. (TENB)
A2: Statement of Cash Flows | N2: ='Income Statement'!N2 -> 2020/1F | O2: ='Income Statement'!O2 -> 2020/2F | P2: ='Income Statement'!P2 -> 2020/3F | Q2: ='Income Statement'!Q2 -> 2020/4F | R2: ='Income Statement'!R2 -> 2021/1F | S2: ='Income Statement'!S2 -> 2021/2F | T2: ='Income Statement'!T2 -> 2021/3F | U2: ='Income Statement'!U2 -> 2021/4F | ... AS2: ='Income Statement'!AS2 -> 2027/4F | AU2: =+'Income Statement'!AU2 -> 2017 | AV2: =+'Income Statement'!AV2 -> 2018 | AW2: =+'Income Statement'!AW2 -> 2019 | AX2: ='Income Statement'!AX2 -> 2020 | AY2: ='Income Statement'!AY2 -> 2021 | AZ2: ='Income Statement'!AZ2 -> 2022 | BA2: ='Income Statement'!BA2 -> 2023 | BB2: ='Income Statement'!BB2 -> 2024 | BC2: ='Income Statement'!BC2 -> 2025 | BD2: ='Income Statement'!BD2 -> 2026 | BE2: ='Income Statement'!BE2 -> 2027 | BG2: INPUTS
B3: ='Income Statement'!B3 -> 2017 | F3: ='Income Statement'!F3 -> 2018 | J3: ='Income Statement'!J3 -> 2019 | N3: ='Income Statement'!N3 -> 2020 | R3: ='Income Statement'!R3 -> 2021 | V3: ='Income Statement'!V3 -> 2022 | Z3: ='Income Statement'!Z3 -> 2023 | AD3: ='Income Statement'!AD3 -> 2024 | AH3: ='Income Statement'!AH3 -> 2025 | AL3: ='Income Statement'!AL3 -> 2026 | AP3: ='Income Statement'!AP3 -> 2027 | BG3: =R3 -> 2021 | BK3: =V3 -> 2022 | BO3: =Z3 -> 2023 | BS3: =AD3 -> 2024 | BW3: =AH3 -> 2025
A4: ='Income Statement'!A4 -> ($ in millions, unless otherwise stated) | B4: ='Income Statement'!B4 -> 42825 | C4: ='Income Statement'!C4 -> 42916 | D4: ='Income Statement'!D4 -> 43008 | E4: ='Income Statement'!E4 -> 43100 | F4: ='Income Statement'!F4 -> 43190 | G4: ='Income Statement'!G4 -> 43281 | H4: ='Income Statement'!H4 -> 43373 | ... AS4: ='Income Statement'!AS4 -> Dec-27E | AU4: ='Income Statement'!AU4 -> 2017 | AV4: ='Income Statement'!AV4 -> 2018 | AW4: ='Income Statement'!AW4 -> 2019 | AX4: ='Income Statement'!AX4 -> 2020 | AY4: ='Income Statement'!AY4 -> CY21 | AZ4: ='Income Statement'!AZ4 -> CY22 | BA4: ='Income Statement'!BA4 -> CY23 | BB4: ='Income Statement'!BB4 -> CY24 | ... BE4: ='Income Statement'!BE4 -> CY27E | BG4: =R4 -> 44286 | BH4: =S4 -> 44377 | BI4: =T4 -> 44469 | BJ4: =U4 -> 44561 | BK4: =V4 -> 44651 | BL4: =W4 -> 44742 | BM4: =X4 -> 44834 | BN4: =Y4 -> 44926 | ... BZ4: =AK4 -> Dec-25
A5: CASH FLOWS FROM OPERATING ACTIVITIES:
A6: Net income (loss) | B6: -8.826 | C6: =-18.04-B6 -> -9.214 | D6: =-29.353-C6-B6 -> -11.313 | E6: =-41.022-D6-C6-B6 -> -11.669 | F6: -15.888 | G6: =-33.038-F6 -> -17.15 | H6: =-53.907-SUM(F6:G6) -> -20.869 | I6: =-73.521-H6-G6-F6 -> -19.614 | J6: -21.44 | K6: =-43.068-J6 -> -21.628 | L6: =-60.708-SUM(J6:K6) -> -17.64 | M6: =-99.013-SUM(J6:L6) -> -38.305 | N6: -22.977 | O6: =-34.937-N6 -> -11.96 | P6: =-40.795-O6-N6 -> -5.858 | Q6: =-42.731-SUM(N6:P6) -> -1.936 | R6: =BG6 -> -7.748 | S6: =BH6-BG6 -> -11.638 | T6: =BI6-BH6 -> -16.246 | U6: =BJ6-BI6 -> -11.045 | V6: =BK6 -> -24.506 | W6: =BL6-BK6 -> -27.499 | X6: =BM6-BL6 -> -18.73 | Y6: =BN6-BM6 -> -21.487 | Z6: =BO6 -> -25.097 | AA6: =BP6-BO6 -> -15.974 | AB6: =BQ6-BP6 -> -15.565 | AC6: =BR6-BQ6 -> -21.648 | AD6: =BS6 -> -14.386 | AE6: =BT6-BS6 -> -14.572 | AF6: =BU6-BT6 -> -9.211 | AG6: =BV6-BU6 -> 1.868 | AH6: =BW6 -> -22.935 | AI6: =BX6-BW6 -> -14.706 | AJ6: =BY6-BX6 -> 2.26 | AK6: =BZ6-BY6 -> -0.737 | AL6: ='Income Statement'!AL99 -> -16.964041 | AM6: ='Income Statement'!AM99 -> -11.691935 | AN6: ='Income Statement'!AN99 -> 0.070317379 | AO6: ='Income Statement'!AO99 -> 3.3324622 | AP6: ='Income Statement'!AP99 -> -17.84687 | AQ6: ='Income Statement'!AQ99 -> -9.0722847 | AR6: ='Income Statement'!AR99 -> 3.4749053 | AS6: ='Income Statement'!AS99 -> 6.9987383 | AU6: =SUM(B6:E6) -> -41.022 | AV6: =SUM(F6:I6) -> -73.521 | AW6: =SUM(J6:M6) -> -99.013 | AX6: =SUM(N6:Q6) -> -42.731 | AY6: =SUM(R6:U6) -> -46.677 | AZ6: =SUM(V6:Y6) -> -92.222 | BA6: =SUM(Z6:AC6) -> -78.284 | BB6: =SUM(AD6:AG6) -> -36.301 | BC6: =SUM(AH6:AK6) -> -36.118 | BD6: =SUM(AL6:AO6) -> -25.253197 | BE6: =SUM(AP6:AS6) -> -16.445511 | BG6: -7.748 | BH6: -19.386 | BI6: -35.632 | BJ6: -46.677 | BK6: -24.506 | BL6: -52.005 | BM6: -70.735 | BN6: -92.222 | BO6: -25.097 | BP6: -41.071 | BQ6: -56.636 | BR6: -78.284 | BS6: -14.386 | BT6: -28.958 | BU6: -38.169 | BV6: =-36.301 -> -36.301 | BW6: -22.935 | BX6: -37.641 | BY6: -35.381 | BZ6: -36.118
A7: Deferred income taxes | B7: 0.096 | C7: =0.318-B7 -> 0.222 | D7: =0.486-C7-B7 -> 0.168 | E7: =-0.873-D7-C7-B7 -> -1.359 | F7: 0 | G7: 0 | H7: 0 | I7: 0 | J7: 0 | K7: 0 | L7: 0 | M7: 0 | N7: 0.041 | O7: =0-N7 -> -0.041 | P7: =0-O7-N7 -> 0 | Q7: =0.161-SUM(N7:P7) -> 0.161 | R7: =BG7 -> 0 | S7: =BH7-BG7 -> 0 | T7: =BI7-BH7 -> 0 | U7: =BJ7-BI7 -> -10.468 | V7: =BK7 -> 0 | W7: =BL7-BK7 -> 0 | X7: =BM7-BL7 -> 0 | Y7: =BN7-BM7 -> -2.781 | Z7: =BO7 -> 0 | AA7: =BP7-BO7 -> 0 | AB7: =BQ7-BP7 -> 0 | AC7: =BR7-BQ7 -> 0.265 | AD7: =BS7 -> 0 | AE7: =BT7-BS7 -> 0 | AF7: =BU7-BT7 -> 0 | AG7: =BV7-BU7 -> 0 | AH7: =BW7 -> 0 | AI7: =BX7-BW7 -> 0 | AJ7: =BY7-BX7 -> 0 | AK7: =BZ7-BY7 -> 0 | AL7: 0 | AM7: 0 | AN7: 0 | AO7: 0 | AP7: 0 | AQ7: 0 | AR7: 0 | AS7: 0 | AU7: =SUM(B7:E7) -> -0.873 | AV7: =SUM(F7:I7) -> 0 | AW7: =SUM(J7:M7) -> 0 | AX7: =SUM(N7:Q7) -> 0.161 | AY7: =SUM(R7:U7) -> -10.468 | AZ7: =SUM(V7:Y7) -> -2.781 | BA7: =SUM(Z7:AC7) -> 0.265 | BB7: =SUM(AD7:AG7) -> 0 | BC7: =SUM(AH7:AK7) -> 0 | BD7: =SUM(AL7:AO7) -> 0 | BE7: =SUM(AP7:AS7) -> 0 | BG7: 0 | BH7: 0 | BI7: 0 | BJ7: -10.468 | BK7: 0 | BL7: 0 | BM7: 0 | BN7: -2.781 | BO7: 0 | BP7: 0 | BQ7: 0 | BR7: 0.265 | BS7: 0 | BT7: 0 | BU7: 0 | BV7: 0 | BW7: 0 | BX7: 0 | BY7: 0 | BZ7: 0
A8: Depreciation and amortization | B8: 1.036 | C8: =2.121-B8 -> 1.085 | D8: =3.316-C8-B8 -> 1.195 | E8: =4.692-D8-C8-B8 -> 1.376 | F8: 1.454 | G8: =2.994-F8 -> 1.54 | H8: =4.58-SUM(F8:G8) -> 1.586 | I8: =6.192-H8-G8-F8 -> 1.612 | J8: 1.622 | K8: =3.089-J8 -> 1.467 | L8: =4.604-K8-J8 -> 1.515 | M8: =6.88-SUM(J8:L8) -> 2.276 | N8: 2.678 | O8: =5.268-N8 -> 2.59 | P8: =7.98-O8-N8 -> 2.712 | Q8: =10.633-SUM(N8:P8) -> 2.653 | R8: =BG8 -> 2.816 | S8: =BH8-BG8 -> 3.991 | T8: =BI8-BH8 -> 4.316 | U8: =BJ8-BI8 -> 5.047 | V8: =BK8 -> 4.896 | W8: =BL8-BK8 -> 5.245 | X8: =BM8-BL8 -> 5.77 | Y8: =BN8-BM8 -> 6.283 | Z8: =BO8 -> 6.365 | AA8: =BP8-BO8 -> 6.259 | AB8: =BQ8-BP8 -> 6.276 | AC8: =BR8-BQ8 -> 8.208 | AD8: =BS8 -> 8.232 | AE8: =BT8-BS8 -> 7.632 | AF8: =BU8-BT8 -> 8.57 | AG8: =BV8-BU8 -> 8.775 | AH8: =BW8 -> 9.854 | AI8: =BX8-BW8 -> 10.826 | AJ8: =BY8-BX8 -> 11.137 | AK8: =BZ8-BY8 -> 10.138 | AL8: =AL76 -> 11.242697 | AM8: =AM76 -> 11.362936 | AN8: =AN76 -> 11.418323 | AO8: =AO76 -> 11.567404 | AP8: =AP76 -> 11.536666 | AQ8: =AQ76 -> 11.664487 | AR8: =AR76 -> 11.7228 | AS8: =AS76 -> 11.88143 | AU8: =SUM(B8:E8) -> 4.692 | AV8: =SUM(F8:I8) -> 6.192 | AW8: =SUM(J8:M8) -> 6.88 | AX8: =SUM(N8:Q8) -> 10.633 | AY8: =SUM(R8:U8) -> 16.17 | AZ8: =SUM(V8:Y8) -> 22.194 | BA8: =SUM(Z8:AC8) -> 27.108 | BB8: =SUM(AD8:AG8) -> 33.209 | BC8: =SUM(AH8:AK8) -> 41.955 | BD8: =SUM(AL8:AO8) -> 45.59136 | BE8: =SUM(AP8:AS8) -> 46.805383 | BG8: 2.816 | BH8: 6.807 | BI8: 11.123 | BJ8: 16.17 | BK8: 4.896 | BL8: 10.141 | BM8: 15.911 | BN8: 22.194 | BO8: 6.365 | BP8: 12.624 | BQ8: 18.9 | BR8: 27.108 | BS8: 8.232 | BT8: 15.864 | BU8: 24.434 | BV8: 33.209 | BW8: 9.854 | BX8: 20.68 | BY8: 31.817 | BZ8: 41.955
A9: Stock based compensation | B9: 1.626 | C9: =3.475-B9 -> 1.849 | D9: =5.503-C9-B9 -> 2.028 | E9: =7.76-D9-C9-B9 -> 2.257 | F9: 2.399 | G9: =5.423-F9 -> 3.024 | H9: =14.206-G9-F9 -> 8.783 | I9: =22.875-H9-G9-F9 -> 8.669 | J9: 9.319 | K9: =20.692-J9 -> 11.373 | L9: =31.191-K9-J9 -> 10.499 | M9: =41.61-SUM(J9:L9) -> 10.419 | N9: 13.035 | O9: =28.701-N9 -> 15.666 | P9: =44.001-O9-N9 -> 15.3 | Q9: =59.573-SUM(N9:P9) -> 15.572 | R9: =BG9 -> 16.952 | S9: =BH9-BG9 -> 20.469 | T9: =BI9-BH9 -> 20.912 | U9: =BJ9-BI9 -> 21.072 | V9: =BK9 -> 25.398 | W9: =BL9-BK9 -> 31.913 | X9: =BM9-BL9 -> 32.643 | Y9: =BN9-BM9 -> 30.679 | Z9: =BO9 -> 34.117 | AA9: =BP9-BO9 -> 37.86 | AB9: =BQ9-BP9 -> 36.835 | AC9: =BR9-BQ9 -> 36.515 | AD9: =BS9 -> 39.719 | AE9: =BT9-BS9 -> 41.398 | AF9: =BU9-BT9 -> 41.684 | AG9: =BV9-BU9 -> 40.714 | AH9: =BW9 -> 55.903 | AI9: =BX9-BW9 -> 46.526 | AJ9: =BY9-BX9 -> 44.882 | AK9: =BZ9-BY9 -> 44.502 | AL9: ='Income Statement'!AL82 -> 54.299025 | AM9: ='Income Statement'!AM82 -> 47.796576 | AN9: ='Income Statement'!AN82 -> 48.374465 | AO9: ='Income Statement'!AO82 -> 49.929948 | AP9: ='Income Statement'!AP82 -> 57.877438 | AQ9: ='Income Statement'!AQ82 -> 50.942895 | AR9: ='Income Statement'!AR82 -> 51.551321 | AS9: ='Income Statement'!AS82 -> 53.206438 | AU9: =SUM(B9:E9) -> 7.76 | AV9: =SUM(F9:I9) -> 22.875 | AW9: =SUM(J9:M9) -> 41.61 | AX9: =SUM(N9:Q9) -> 59.573 | AY9: =SUM(R9:U9) -> 79.405 | AZ9: =SUM(V9:Y9) -> 120.633 | BA9: =SUM(Z9:AC9) -> 145.327 | BB9: =SUM(AD9:AG9) -> 163.515 | BC9: =SUM(AH9:AK9) -> 191.813 | BD9: =SUM(AL9:AO9) -> 200.40001 | BE9: =SUM(AP9:AS9) -> 213.57809 | BG9: 16.952 | BH9: 37.421 | BI9: 58.333 | BJ9: 79.405 | BK9: 25.398 | BL9: 57.311 | BM9: 89.954 | BN9: 120.633 | BO9: 34.117 | BP9: 71.977 | BQ9: 108.812 | BR9: 145.327 | BS9: 39.719 | BT9: 81.117 | BU9: 122.801 | BV9: 163.515 | BW9: 55.903 | BX9: 102.429 | BY9: 147.311 | BZ9: 191.813
A10: Other | B10: -0.01 | C10: =-0.039-B10 -> -0.029 | D10: =0.023-C10-B10 -> 0.062 | E10: =0.125-D10-C10-B10 -> 0.102 | F10: 0.08 | G10: =0.664-F10 -> 0.584 | H10: =0.771-G10-F10 -> 0.107 | I10: =0.533-H10-G10-F10 -> -0.238 | J10: -0.284 | K10: =-1.022-J10 -> -0.738 | L10: =-0.787-K10-J10 -> 0.235 | M10: =3.459-SUM(J10:L10) -> 4.246 | N10: 0.474 | O10: =0.606-N10 -> 0.132 | P10: =1.009-O10-N10 -> 0.403 | Q10: =1.071-SUM(N10:P10) -> 0.062 | R10: =BG10 -> 0.313 | S10: =BH10-BG10 -> -0.581 | T10: =BI10-BH10 -> 1.1 | U10: =BJ10-BI10 -> 3.083 | V10: =BK10 -> 1.323 | W10: =BL10-BK10 -> -0.658 | X10: =BM10-BL10 -> 1.437 | Y10: =BN10-BM10 -> 3.402 | Z10: =BO10 -> -1.556 | AA10: =BP10-BO10 -> -1.239 | AB10: =BQ10-BP10 -> 4.633 | AC10: =BR10-BQ10 -> -1.363 | AD10: =BS10 -> -0.344 | AE10: =BT10-BS10 -> 3.34 | AF10: =BU10-BT10 -> -0.93 | AG10: =BV10-BU10 -> 1.275 | AH10: =BW10 -> 0.148 | AI10: =BX10-BW10 -> 0.08 | AJ10: =BY10-BX10 -> 1.0678 | AK10: =BZ10-BY10 -> 0.8892 | AL10: 0 | AM10: 0 | AN10: 0 | AO10: 0 | AP10: 0 | AQ10: 0 | AR10: 0 | AS10: 0 | AU10: =SUM(B10:E10) -> 0.125 | AV10: =SUM(F10:I10) -> 0.533 | AW10: =SUM(J10:M10) -> 3.459 | AX10: =SUM(N10:Q10) -> 1.071 | AY10: =SUM(R10:U10) -> 3.915 | AZ10: =SUM(V10:Y10) -> 5.504 | BA10: =SUM(Z10:AC10) -> 0.475 | BB10: =SUM(AD10:AG10) -> 3.341 | BC10: =SUM(AH10:AK10) -> 2.185 | BD10: =SUM(AL10:AO10) -> 0 | BE10: =SUM(AP10:AS10) -> 0 | BG10: 0.313 | BH10: -0.268 | BI10: 0.832 | BJ10: 3.915 | BK10: 1.323 | BL10: 0.665 | BM10: 2.102 | BN10: 5.504 | BO10: -1.556 | BP10: -2.795 | BQ10: 1.838 | BR10: =-8.323+5.617+1.267+1.914 -> 0.475 | BS10: =-2.284+0.329+1.611 -> -0.344 | BT10: =-4.378+0.662+4.528+2.184 -> 2.996 | BU10: =-6.141+1.003-1.452+4.528+4.128 -> 2.066 | BV10: =-7.595+1.353-1.452+4.528+6.507 -> 3.341 | BW10: 0.148 | BX10: =-1.975+0.707+1.496 -> 0.228 | BY10: =-2.568+1.071+0.0018+0+2.791 -> 1.2958 | BZ10: =-3.131+1.442+0.018+3.856 -> 2.185
A11: Changes to assets and liabilities
A12: Accounts receivable | B12: 5.198 | C12: =-1.205-B12 -> -6.403 | D12: =-8.435-C12-B12 -> -7.23 | E12: =-14.769-D12-C12-B12 -> -6.334 | F12: 7.792 | G12: =0.85-F12 -> -6.942 | H12: =-8.19-G12-F12 -> -9.04 | I12: =-17.408-H12-G12-F12 -> -9.218 | J12: 11.104 | K12: =-0.658-J12 -> -11.762 | L12: =-13.309-K12-J12 -> -12.651 | M12: =+-25.941-SUM(J12:L12) -> -12.632 | N12: 20.813 | O12: =13.512-N12 -> -7.301 | P12: =7.774-O12-N12 -> -5.738 | Q12: =-20.012-SUM(N12:P12) -> -27.786 | R12: =BG12 -> 32.455 | S12: =BH12-BG12 -> -13.47 | T12: =BI12-BH12 -> -14.992 | U12: =BJ12-BI12 -> -21.221 | V12: =BK12 -> 40.341 | W12: =BL12-BK12 -> -12.677 | X12: =BM12-BL12 -> -38.391 | Y12: =BN12-BM12 -> -40.529 | Z12: =BO12 -> 64.439 | AA12: =BP12-BO12 -> -30.442 | AB12: =BQ12-BP12 -> -24.913 | AC12: =BR12-BQ12 -> -39.126 | AD12: =BS12 -> 63.437 | AE12: =BT12-BS12 -> -22.975 | AF12: =BU12-BT12 -> -13.551 | AG12: =BV12-BU12 -> -65.641 | AH12: =BW12 -> 92.968 | AI12: =BX12-BW12 -> -13.202 | AJ12: =BY12-BX12 -> -20.033 | AK12: =BZ12-BY12 -> -77.969 | AL12: ='Balance Sheet'!AK8-'Balance Sheet'!AL8 -> 103.3911 | AM12: ='Balance Sheet'!AL8-'Balance Sheet'!AM8 -> -12.894867 | AN12: ='Balance Sheet'!AM8-'Balance Sheet'!AN8 -> -19.432562 | AO12: ='Balance Sheet'!AN8-'Balance Sheet'!AO8 -> -83.043981 | AP12: ='Balance Sheet'!AO8-'Balance Sheet'!AP8 -> 109.82925 | AQ12: ='Balance Sheet'!AP8-'Balance Sheet'!AQ8 -> -13.568179 | AR12: ='Balance Sheet'!AQ8-'Balance Sheet'!AR8 -> -20.605394 | AS12: ='Balance Sheet'!AR8-'Balance Sheet'!AS8 -> -88.28144 | AU12: =SUM(B12:E12) -> -14.769 | AV12: =SUM(F12:I12) -> -17.408 | AW12: =SUM(J12:M12) -> -25.941 | AX12: =SUM(N12:Q12) -> -20.012 | AY12: =SUM(R12:U12) -> -17.228 | AZ12: =SUM(V12:Y12) -> -51.256 | BA12: =SUM(Z12:AC12) -> -30.042 | BB12: =SUM(AD12:AG12) -> -38.73 | BC12: =SUM(AH12:AK12) -> -18.236 | BD12: =SUM(AL12:AO12) -> -11.980307 | BE12: =SUM(AP12:AS12) -> -12.625764 | BG12: 32.455 | BH12: 18.985 | BI12: 3.993 | BJ12: -17.228 | BK12: 40.341 | BL12: 27.664 | BM12: -10.727 | BN12: -51.256 | BO12: 64.439 | BP12: 33.997 | BQ12: 9.084 | BR12: -30.042 | BS12: 63.437 | BT12: 40.462 | BU12: 26.911 | BV12: -38.73 | BW12: 92.968 | BX12: 79.766 | BY12: 59.733 | BZ12: -18.236
A13: Prepaid expenses and other current assets | B13: 0.691 | C13: =-0.205-B13 -> -0.896 | D13: =-0.54-C13-B13 -> -0.335 | E13: =-8.345-D13-C13-B13 -> -7.805 | F13: 1.196 | G13: =2.625-F13 -> 1.429 | H13: =1.228-G13-F13 -> -1.397 | I13: =-6.105-H13-G13-F13 -> -7.333 | J13: 1.374 | K13: =1.673-J13 -> 0.299 | L13: =0.82-K13-J13 -> -0.853 | M13: =-5.188-SUM(J13:L13) -> -6.008 | N13: 1.663 | O13: =1.058-N13 -> -0.605 | P13: =-6.69-O13-N13 -> -7.748 | Q13: =-19.372-SUM(N13:P13) -> -12.682 | R13: =BG13 -> 5.427 | S13: =BH13-BG13 -> -0.35 | T13: =BI13-BH13 -> -10.361 | U13: =BJ13-BI13 -> -40.923 | V13: =BK13 -> 8.463 | W13: =BL13-BK13 -> 8.302 | X13: =BM13-BL13 -> 3.59 | Y13: =BN13-BM13 -> -23.284 | Z13: =BO13 -> -2.776 | AA13: =BP13-BO13 -> 15.425 | AB13: =BQ13-BP13 -> 4.875 | AC13: =BR13-BQ13 -> -15.835 | AD13: =BS13 -> 5.216 | AE13: =BT13-BS13 -> 12.889 | AF13: =BU13-BT13 -> 11.763 | AG13: =BV13-BU13 -> -3.698 | AH13: =BW13 -> -9.875 | AI13: =BX13-BW13 -> 14.967 | AJ13: =BY13-BX13 -> 11.785 | AK13: =BZ13-BY13 -> -4.11 | AL13: =('Balance Sheet'!AK10-'Balance Sheet'!AL10) -> -30.633668 | AM13: =('Balance Sheet'!AL10-'Balance Sheet'!AM10) -> 14.559935 | AN13: =('Balance Sheet'!AM10-'Balance Sheet'!AN10) -> 11.059892 | AO13: =('Balance Sheet'!AN10-'Balance Sheet'!AO10) -> 5.2426268 | AP13: =('Balance Sheet'!AO10-'Balance Sheet'!AP10) -> -32.717723 | AQ13: =('Balance Sheet'!AP10-'Balance Sheet'!AQ10) -> 15.597695 | AR13: =('Balance Sheet'!AQ10-'Balance Sheet'!AR10) -> 11.828616 | AS13: =('Balance Sheet'!AR10-'Balance Sheet'!AS10) -> 5.6808453 | AU13: =SUM(B13:E13) -> -8.345 | AV13: =SUM(F13:I13) -> -6.105 | AW13: =SUM(J13:M13) -> -5.188 | AX13: =SUM(N13:Q13) -> -19.372 | AY13: =SUM(R13:U13) -> -46.207 | AZ13: =SUM(V13:Y13) -> -2.929 | BA13: =SUM(Z13:AC13) -> 1.689 | BB13: =SUM(AD13:AG13) -> 26.17 | BC13: =SUM(AH13:AK13) -> 12.767 | BD13: =SUM(AL13:AO13) -> 0.22878635 | BE13: =SUM(AP13:AS13) -> 0.38943288 | BG13: 5.427 | BH13: 5.077 | BI13: -5.284 | BJ13: -46.207 | BK13: 8.463 | BL13: 16.765 | BM13: 20.355 | BN13: -2.929 | BO13: -2.776 | BP13: 12.649 | BQ13: 17.524 | BR13: 1.689 | BS13: 5.216 | BT13: 18.105 | BU13: 29.868 | BV13: 26.17 | BW13: -9.875 | BX13: 5.092 | BY13: 16.877 | BZ13: 12.767
A14: Deferred commissions | B14: -1.788 | C14: =-6.134-B14 -> -4.346 | D14: =-11.275-C14-B14 -> -5.141 | E14: =-20.058-D14-C14-B14 -> -8.783 | F14: -0.276 | G14: =-0.629-F14 -> -0.353 | H14: =-2.708-G14-F14 -> -2.079 | I14: =-9.258-H14-G14-F14 -> -6.55 | J14: -0.377 | K14: =-2.432-J14 -> -2.055 | L14: =-5.089-K14-J14 -> -2.657 | M14: =-12.831-SUM(J14:L14) -> -7.742 | N14: 1.523 | O14: =0.497-N14 -> -1.026 | P14: =0.381-O14-N14 -> -0.116 | Q14: =0-SUM(N14:P14) -> -0.381 | R14: =BG14 -> 0 | S14: =BH14-BG14 -> 0 | T14: =BI14-BH14 -> 0 | U14: =BJ14-BI14 -> 0 | V14: =BK14 -> 0 | W14: =BL14-BK14 -> 0 | X14: =BM14-BL14 -> 0 | Y14: =BN14-BM14 -> 0 | Z14: =BO14 -> 0 | AA14: =BP14-BO14 -> 0 | AB14: =BQ14-BP14 -> 0 | AC14: =BR14-BQ14 -> 0 | AD14: =BS14 -> 0 | AE14: =BT14-BS14 -> 0 | AF14: =BU14-BT14 -> 0 | AG14: =BV14-BU14 -> 0 | AH14: =BW14 -> 0 | AI14: =BX14-BW14 -> 0 | AJ14: =BY14-BX14 -> 0 | AK14: =BZ14-BY14 -> 0 | AL14: =('Balance Sheet'!AK9-'Balance Sheet'!AL9)+('Balance Sheet'!AK14-'Balance Sheet'!AL14) -> 3.4790265 | AM14: =('Balance Sheet'!AL9-'Balance Sheet'!AM9)+('Balance Sheet'!AL14-'Balance Sheet'!AM14) -> 2.9144612 | AN14: =('Balance Sheet'!AM9-'Balance Sheet'!AN9)+('Balance Sheet'!AM14-'Balance Sheet'!AN14) -> 1.075266 | AO14: =('Balance Sheet'!AN9-'Balance Sheet'!AO9)+('Balance Sheet'!AN14-'Balance Sheet'!AO14) -> -9.9840545 | AP14: =('Balance Sheet'!AO9-'Balance Sheet'!AP9)+('Balance Sheet'!AO14-'Balance Sheet'!AP14) -> 3.5224413 | AQ14: =('Balance Sheet'!AP9-'Balance Sheet'!AQ9)+('Balance Sheet'!AP14-'Balance Sheet'!AQ14) -> 3.2635458 | AR14: =('Balance Sheet'!AQ9-'Balance Sheet'!AR9)+('Balance Sheet'!AQ14-'Balance Sheet'!AR14) -> 1.2318228 | AS14: =('Balance Sheet'!AR9-'Balance Sheet'!AS9)+('Balance Sheet'!AR14-'Balance Sheet'!AS14) -> -10.449414 | AU14: =SUM(B14:E14) -> -20.058 | AV14: =SUM(F14:I14) -> -9.258 | AW14: =SUM(J14:M14) -> -12.831 | AX14: =SUM(N14:Q14) -> 0 | AY14: =SUM(R14:U14) -> 0 | AZ14: =SUM(V14:Y14) -> 0 | BA14: =SUM(Z14:AC14) -> 0 | BB14: =SUM(AD14:AG14) -> 0 | BC14: =SUM(AH14:AK14) -> 0 | BD14: =SUM(AL14:AO14) -> -2.5153009 | BE14: =SUM(AP14:AS14) -> -2.4316041 | BG14: 0 | BH14: 0 | BI14: 0 | BJ14: 0 | BK14: 0 | BL14: 0 | BM14: 0 | BN14: 0 | BW14: 0
