Workbook
Name ___eps95: #REF!
Name ___eps95: #REF!
Name ___eps95: #REF!
Name ___eps95: #REF!
Name ___eps95: #REF!
Name ___eps95: #REF!
Name ___eps95: #REF!
Name ___eps96: #REF!
Name ___eps96: #REF!
Name ___eps96: #REF!
Name ___eps96: #REF!
Name ___eps96: #REF!
Name ___eps96: #REF!
Name ___eps96: #REF!
Name ___eps97: #REF!
Name ___eps97: #REF!
Name ___eps97: #REF!
Name ___eps97: #REF!
Name ___eps97: #REF!
Name ___eps97: #REF!
Name ___eps97: #REF!
Name ___eps98: #REF!
Name ___eps98: #REF!
Name ___eps98: #REF!
Name ___eps98: #REF!
Name ___fcc97: #REF!
Name ___fcc97: #REF!
Name ___fcc97: #REF!
Name ___fcc97: #REF!
Name ___grm98: #REF!
Name ___grm98: #REF!
Name ___grm98: #REF!
Name ___grm98: #REF!
Name ___grm99: #REF!
Name ___grm99: #REF!
Name ___grm99: #REF!
Name ___grm99: #REF!
Name ___net96: #REF!
Name ___net96: #REF!
Name ___net96: #REF!
Name ___net96: #REF!
Name ___net97: #REF!
Name ___net97: #REF!
Name ___net97: #REF!
Name ___net97: #REF!
Name ___net98: #REF!
Name ___net98: #REF!
Name ___net98: #REF!
Name ___net98: #REF!
Name ___net99: #REF!
Name ___net99: #REF!
Name ___net99: #REF!
Name ___net99: #REF!
Name ___opm98: #REF!
Name ___opm98: #REF!
Name ___opm98: #REF!
Name ___opm98: #REF!
Name ___opm99: #REF!
Name ___opm99: #REF!
Name ___opm99: #REF!

Sheet __FDSCACHE__
B1: This sheet contains FactSet XML data for use with this workbook's =FDS codes. Modifying the worksheet's contents may damage the workbook's =FDS functionality.

Sheet BM Upload
A1: ALL FISCAL DATA MUST BE ENTERED IN MILLION (INCLUDING NUMBER OF SHARE) | CD1: NULL:FISCAL
A2: ALL PER SHARE DATA MUST BE IN UNIT | CD2: ADJUSTED:FISCAL
A3: DATA MUST BE ENTERED IN THE CURRENCY OF THE COMPANY | CD3: BASIC:FISCAL
A4: Click here to find a list of BlueMatrix Client Codes | CD4: DILUTED:FISCAL
CB5: Strong Buy | CD5: GAAP:FISCAL
CB6: Buy | CD6: INDICATED:FISCAL
CB7: Hold | CD7: MANAGED:FISCAL
CB8: Under Perform | CD8: NON-GAAP:FISCAL
A9: Company name | C9: Qualys | CB9: Rating Suspended | CD9: OPERATING:FISCAL
A10: Rating | B10: RATING | C10: Hold | D10: =_xll.BLUEMATRIX2("/servlet/excelData",C10, $C$14,$B10) -> #NAME? | CB10: Restricted | CD10: PRIMARY:FISCAL
A11: Currency | C11: USD | CB11: Under Review | CD11: PROFORMA:FISCAL
CB12: Sell | CD12: RESTATED:FISCAL
A13: 12-Month Price Target | B13: TARGET_PRICE | C13: NA | D13: =_xll.BLUEMATRIX2("/servlet/excelData",C13, $C$14,$B13) -> #NAME? | CD13: REVENUE:FISCAL
A14: Ticker | C14: QLYS | AB14: E | CB14: A | CC14: E | CD14: NULL:CALENDAR
CB15: E | CC15: A | CD15: ADJUSTED:CALENDAR
D16: =$B$17-3 -> 2013 | E16: =$B$17-3 -> 2013 | F16: =$B$17-3 -> 2013 | G16: =$B$17-3 -> 2013 | H16: =$B$17-3 -> 2013 | I16: =$B$17-2 -> 2014 | J16: =$B$17-2 -> 2014 | K16: =$B$17-2 -> 2014 | L16: =$B$17-2 -> 2014 | M16: =$B$17-2 -> 2014 | N16: =$B$17-1 -> 2015 | O16: =$B$17-1 -> 2015 | P16: =$B$17-1 -> 2015 | Q16: =$B$17-1 -> 2015 | R16: =$B$17-1 -> 2015 | S16: =$B$17-0 -> 2016 | T16: =$B$17-0 -> 2016 | U16: =$B$17-0 -> 2016 | V16: =$B$17-0 -> 2016 | W16: =$B$17-0 -> 2016 | X16: =$B$17+1 -> 2017 | Y16: =$B$17+1 -> 2017 | Z16: =$B$17+1 -> 2017 | AA16: =$B$17+1 -> 2017 | AB16: =$B$17+1 -> 2017 | AC16: =$B$17+2 -> 2018 | AD16: =$B$17+2 -> 2018 | AE16: =$B$17+2 -> 2018 | AF16: =$B$17+2 -> 2018 | AG16: =$B$17+2 -> 2018 | AH16: =$B$17+3 -> 2019 | AI16: =$B$17+3 -> 2019 | AJ16: =$B$17+3 -> 2019 | AK16: =$B$17+3 -> 2019 | AL16: =$B$17+3 -> 2019 | AM16: =$B$17+4 -> 2020 | AN16: =$B$17+4 -> 2020 | AO16: =$B$17+4 -> 2020 | AP16: =$B$17+4 -> 2020 | AQ16: =$B$17+4 -> 2020 | AR16: =$B$17+5 -> 2021 | AS16: =$B$17+5 -> 2021 | AT16: =$B$17+5 -> 2021 | AU16: =$B$17+5 -> 2021 | AV16: =$B$17+5 -> 2021 | AW16: =$B$17+6 -> 2022 | AX16: =$B$17+6 -> 2022 | AY16: =$B$17+6 -> 2022 | AZ16: =$B$17+6 -> 2022 | BA16: =$B$17+6 -> 2022 | BB16: =$B$17+7 -> 2023 | BC16: =$B$17+7 -> 2023 | BD16: =$B$17+7 -> 2023 | BE16: =$B$17+7 -> 2023 | BF16: =$B$17+7 -> 2023 | BG16: 2024 | BH16: 2024 | BI16: 2024 | BJ16: 2024 | BK16: 2024 | BL16: =BG16+1 -> 2025 | BM16: =BH16+1 -> 2025 | BN16: =BI16+1 -> 2025 | BO16: =BJ16+1 -> 2025 | BP16: =BK16+1 -> 2025 | BQ16: =BL16+1 -> 2026 | BR16: =BM16+1 -> 2026 | BS16: =BN16+1 -> 2026 | ... BZ16: =BU16+1 -> 2027
A17: Current Year (Matching What Selected From Drop-down Bars - ie. Fiscal or Calendar) | B17: 2016 | D17: A | E17: A | F17: A | G17: A | H17: A | I17: A | J17: A | K17: A | L17: A | M17: A | N17: A | O17: A | P17: A | Q17: A | R17: A | S17: A | T17: A | U17: A | V17: A | W17: A | X17: A | Y17: A | Z17: A | AA17: A | AB17: A | AC17: A | AD17: A | AE17: A | AF17: A | AG17: A | AH17: A | AI17: A | AJ17: A | AK17: A | AL17: =+AK17 -> A | AM17: A | AN17: A | AO17: A | AP17: A | AQ17: =+AP17 -> A | AR17: A | AS17: A | AT17: A | AU17: A | AV17: =+AU17 -> A | AW17: A | AX17: A | AY17: A | AZ17: A | BA17: =+AZ17 -> A | BB17: A | BC17: A | BD17: A | BE17: A | BF17: =+BE17 -> A | BG17: =+BF17 -> A | BH17: A | BI17: A | BJ17: A | BK17: =+BJ17 -> A | BL17: A | BM17: A | BN17: A | BO17: A | BP17: =+BO17 -> A | BQ17: E | BR17: E | BS17: E | BT17: E | BU17: =+BT17 -> E | BV17: E | BW17: E | BX17: E | BY17: E | BZ17: =+BY17 -> E
A18: Current Base Quarter (NOT one just reported - One After That) | B18: Q2 | D18: =D16&D19 -> 2013Q1 | E18: =E16&E19 -> 2013Q2 | F18: =F16&F19 -> 2013Q3 | G18: =G16&G19 -> 2013Q4 | H18: =H16 -> 2013 | I18: =I16&I19&I17 -> 2014Q1A | J18: =J16&J19&J17 -> 2014Q2A | K18: =K16&K19&K17 -> 2014Q3A | L18: =L16&L19&L17 -> 2014Q4A | M18: =M16&M17 -> 2014A | N18: =N16&N19&N17 -> 2015Q1A | O18: =O16&O19&O17 -> 2015Q2A | P18: =P16&P19&P17 -> 2015Q3A | Q18: =Q16&Q19&Q17 -> 2015Q4A | R18: =R16&R17 -> 2015A | S18: =S16&S19&S17 -> 2016Q1A | T18: =T16&T19&T17 -> 2016Q2A | U18: =U16&U19&U17 -> 2016Q3A | V18: =V16&V19&V17 -> 2016Q4A | W18: =W16&W17 -> 2016A | X18: =X16&X19&X17 -> 2017Q1A | Y18: =Y16&Y19&Y17 -> 2017Q2A | Z18: =Z16&Z19&Z17 -> 2017Q3A | AA18: =AA16&AA19&AA17 -> 2017Q4A | AB18: =AB16&AB17 -> 2017A | AC18: =AC16&AC19&AC17 -> 2018Q1A | AD18: =AD16&AD19&AD17 -> 2018Q2A | AE18: =AE16&AE19&AE17 -> 2018Q3A | AF18: =AF16&AF19&AF17 -> 2018Q4A | AG18: =AG16&AG17 -> 2018A | AH18: =AH16&AH19&AH17 -> 2019Q1A | AI18: =AI16&AI19&AI17 -> 2019Q2A | AJ18: =AJ16&AJ19&AJ17 -> 2019Q3A | AK18: =AK16&AK19&AK17 -> 2019Q4A | AL18: =AL16&AL17 -> 2019A | AM18: =AM16&AM19&AM17 -> 2020Q1A | AN18: =AN16&AN19&AN17 -> 2020Q2A | AO18: =AO16&AO19&AO17 -> 2020Q3A | AP18: =AP16&AP19&AP17 -> 2020Q4A | AQ18: =AQ16&AQ17 -> 2020A | AR18: =AR16&AR19&AR17 -> 2021Q1A | AS18: =AS16&AS19&AS17 -> 2021Q2A | AT18: =AT16&AT19&AT17 -> 2021Q3A | AU18: =AU16&AU19&AU17 -> 2021Q4A | AV18: =AV16&AV17 -> 2021A | AW18: =AW16&AW19&AW17 -> 2022Q1A | AX18: =AX16&AX19&AX17 -> 2022Q2A | AY18: =AY16&AY19&AY17 -> 2022Q3A | AZ18: =AZ16&AZ19&AZ17 -> 2022Q4A | BA18: =BA16&BA17 -> 2022A | BB18: =BB16&BB19&BB17 -> 2023Q1A | BC18: =BC16&BC19&BC17 -> 2023Q2A | BD18: =BD16&BD19&BD17 -> 2023Q3A | BE18: =BE16&BE19&BE17 -> 2023Q4A | BF18: =BF16&BF17 -> 2023A | BG18: =BG16&BG19&BG17 -> 2024Q1A | BH18: =BH16&BH19&BH17 -> 2024Q2A | BI18: =BI16&BI19&BI17 -> 2024Q3A | BJ18: =BJ16&BJ19&BJ17 -> 2024Q4A | BK18: =BK16&BK17 -> 2024A | BL18: =BL16&BL19&BL17 -> 2025Q1A | BM18: =BM16&BM19&BM17 -> 2025Q2A | BN18: =BN16&BN19&BN17 -> 2025Q3A | BO18: =BO16&BO19&BO17 -> 2025Q4A | BP18: =BP16&BP17 -> 2025A | BQ18: =BQ16&BQ19&BQ17 -> 2026Q1E | BR18: =BR16&BR19&BR17 -> 2026Q2E | BS18: =BS16&BS19&BS17 -> 2026Q3E | BT18: =BT16&BT19&BT17 -> 2026Q4E | BU18: =BU16&BU17 -> 2026E | BV18: =BV16&BV19&BV17 -> 2027Q1E | BW18: =BW16&BW19&BW17 -> 2027Q2E | BX18: =BX16&BX19&BX17 -> 2027Q3E | BY18: =BY16&BY19&BY17 -> 2027Q4E | BZ18: =BZ16&BZ17 -> 2027E
D19: Q1 | E19: Q2 | F19: Q3 | G19: Q4 | H19: AN | I19: Q1 | J19: Q2 | K19: Q3 | L19: Q4 | M19: AN | N19: Q1 | O19: Q2 | P19: Q3 | Q19: Q4 | R19: AN | S19: Q1 | T19: Q2 | U19: Q3 | V19: Q4 | W19: AN | X19: Q1 | Y19: Q2 | Z19: Q3 | AA19: Q4 | AB19: AN | AC19: Q1 | AD19: Q2 | AE19: Q3 | AF19: Q4 | AG19: AN | AH19: Q1 | AI19: Q2 | AJ19: Q3 | AK19: Q4 | AL19: AN | AM19: Q1 | AN19: Q2 | AO19: Q3 | AP19: Q4 | AQ19: AN | AR19: Q1 | AS19: Q2 | AT19: Q3 | AU19: Q4 | AV19: AN | AW19: Q1 | AX19: Q2 | AY19: Q3 | AZ19: Q4 | BA19: AN | BB19: Q1 | BC19: Q2 | BD19: Q3 | BE19: Q4 | BF19: AN | BG19: Q1 | BH19: Q2 | BI19: Q3 | BJ19: Q4 | BK19: AN | BL19: Q1 | BM19: Q2 | BN19: Q3 | BO19: Q4 | BP19: AN | BQ19: Q1 | BR19: Q2 | BS19: Q3 | BT19: Q4 | BU19: AN | BV19: Q1 | BW19: Q2 | BX19: Q3 | BY19: Q4 | BZ19: AN
A20: BlueMatrix Time Series Grids | D20: =($B$45&"/"&31&"/"&(D16+$D$45)) -> 3/31/2013 | E20: =$B$46&"/"&31&"/"&(E16+$D$46) -> 6/31/2013 | F20: =$B$47&"/"&31&"/"&(F16+$D$47) -> 9/31/2013 | G20: =$B$48&"/"&31&"/"&(G16+$D$48) -> 12/31/2013 | H20: =G20 -> 12/31/2013 | I20: =($B$45&"/"&31&"/"&(I16+$D$45)) -> 3/31/2014 | J20: =$B$46&"/"&31&"/"&(J16+$D$46) -> 6/31/2014 | K20: =$B$47&"/"&31&"/"&(K16+$D$47) -> 9/31/2014 | L20: =$B$48&"/"&31&"/"&(L16+$D$48) -> 12/31/2014 | M20: =L20 -> 12/31/2014 | N20: =($B$45&"/"&31&"/"&(N16+$D$45)) -> 3/31/2015 | O20: =$B$46&"/"&31&"/"&(O16+$D$46) -> 6/31/2015 | P20: =$B$47&"/"&31&"/"&(P16+$D$47) -> 9/31/2015 | Q20: =$B$48&"/"&31&"/"&(Q16+$D$48) -> 12/31/2015 | R20: =Q20 -> 12/31/2015 | S20: =($B$45&"/"&31&"/"&(S16+$D$45)) -> 3/31/2016 | T20: =$B$46&"/"&31&"/"&(T16+$D$46) -> 6/31/2016 | U20: =$B$47&"/"&31&"/"&(U16+$D$47) -> 9/31/2016 | V20: =$B$48&"/"&31&"/"&(V16+$D$48) -> 12/31/2016 | W20: =V20 -> 12/31/2016 | X20: =($B$45&"/"&31&"/"&(X16+$D$45)) -> 3/31/2017 | Y20: =$B$46&"/"&31&"/"&(Y16+$D$46) -> 6/31/2017 | Z20: =$B$47&"/"&31&"/"&(Z16+$D$47) -> 9/31/2017 | AA20: =$B$48&"/"&31&"/"&(AA16+$D$48) -> 12/31/2017 | AB20: =AA20 -> 12/31/2017 | AC20: =($B$45&"/"&31&"/"&(AC16+$D$45)) -> 3/31/2018 | AD20: =$B$46&"/"&31&"/"&(AD16+$D$46) -> 6/31/2018 | AE20: =$B$47&"/"&31&"/"&(AE16+$D$47) -> 9/31/2018 | AF20: =$B$48&"/"&31&"/"&(AF16+$D$48) -> 12/31/2018 | AG20: =AF20 -> 12/31/2018 | AH20: =($B$45&"/"&31&"/"&(AH16+$D$45)) -> 3/31/2019 | AI20: =$B$46&"/"&31&"/"&(AI16+$D$46) -> 6/31/2019 | AJ20: =$B$47&"/"&31&"/"&(AJ16+$D$47) -> 9/31/2019 | AK20: =$B$48&"/"&31&"/"&(AK16+$D$48) -> 12/31/2019 | AL20: =AK20 -> 12/31/2019 | AM20: =($B$45&"/"&31&"/"&(AM16+$D$45)) -> 3/31/2020 | AN20: =$B$46&"/"&31&"/"&(AN16+$D$46) -> 6/31/2020 | AO20: =$B$47&"/"&31&"/"&(AO16+$D$47) -> 9/31/2020 | AP20: =$B$48&"/"&31&"/"&(AP16+$D$48) -> 12/31/2020 | AQ20: =AP20 -> 12/31/2020 | AR20: =($B$45&"/"&31&"/"&(AR16+$D$45)) -> 3/31/2021 | AS20: =$B$46&"/"&31&"/"&(AS16+$D$46) -> 6/31/2021 | AT20: =$B$47&"/"&31&"/"&(AT16+$D$47) -> 9/31/2021 | AU20: =$B$48&"/"&31&"/"&(AU16+$D$48) -> 12/31/2021 | AV20: =AU20 -> 12/31/2021 | AW20: =($B$45&"/"&31&"/"&(AW16+$D$45)) -> 3/31/2022 | AX20: =$B$46&"/"&31&"/"&(AX16+$D$46) -> 6/31/2022 | AY20: =$B$47&"/"&31&"/"&(AY16+$D$47) -> 9/31/2022 | AZ20: =$B$48&"/"&31&"/"&(AZ16+$D$48) -> 12/31/2022 | BA20: =AZ20 -> 12/31/2022 | BB20: =($B$45&"/"&31&"/"&(BB16+$D$45)) -> 3/31/2023 | BC20: =$B$46&"/"&31&"/"&(BC16+$D$46) -> 6/31/2023 | BD20: =$B$47&"/"&31&"/"&(BD16+$D$47) -> 9/31/2023 | BE20: =$B$48&"/"&31&"/"&(BE16+$D$48) -> 12/31/2023 | BF20: =BE20 -> 12/31/2023 | BG20: =($B$45&"/"&31&"/"&(BG16+$D$45)) -> 3/31/2024 | BH20: =$B$46&"/"&31&"/"&(BH16+$D$46) -> 6/31/2024 | BI20: =$B$47&"/"&31&"/"&(BI16+$D$47) -> 9/31/2024 | BJ20: =$B$48&"/"&31&"/"&(BJ16+$D$48) -> 12/31/2024 | BK20: =BJ20 -> 12/31/2024 | BL20: =($B$45&"/"&31&"/"&(BL16+$D$45)) -> 3/31/2025 | BM20: =$B$46&"/"&31&"/"&(BM16+$D$46) -> 6/31/2025 | BN20: =$B$47&"/"&31&"/"&(BN16+$D$47) -> 9/31/2025 | BO20: =$B$48&"/"&31&"/"&(BO16+$D$48) -> 12/31/2025 | BP20: =BO20 -> 12/31/2025 | BQ20: =($B$45&"/"&31&"/"&(BQ16+$D$45)) -> 3/31/2026 | BR20: =$B$46&"/"&31&"/"&(BR16+$D$46) -> 6/31/2026 | BS20: =$B$47&"/"&31&"/"&(BS16+$D$47) -> 9/31/2026 | BT20: =$B$48&"/"&31&"/"&(BT16+$D$48) -> 12/31/2026 | BU20: =BT20 -> 12/31/2026 | BV20: =($B$45&"/"&31&"/"&(BV16+$D$45)) -> 3/31/2027 | BW20: =$B$46&"/"&31&"/"&(BW16+$D$46) -> 6/31/2027 | BX20: =$B$47&"/"&31&"/"&(BX16+$D$47) -> 9/31/2027 | BY20: =$B$48&"/"&31&"/"&(BY16+$D$48) -> 12/31/2027 | BZ20: =BY20 -> 12/31/2027
A21: Revenue ($M) | B21: REVENUE | D21: =+IS!I9/1000 -> 24.883 | E21: =+IS!J9/1000 -> 26.291 | F21: =+IS!K9/1000 -> 27.749 | G21: =+IS!L9/1000 -> 29.039 | H21: =+IS!M9/1000 -> 107.962 | I21: =+IS!N9/1000 -> 30.356 | J21: =+IS!O9/1000 -> 32.302 | K21: =+IS!P9/1000 -> 34.348 | ... BZ21: =+IS!CE9/1000 -> 769.34508
B22: NON-GAAP:CALENDAR | D22: =_xll.BLUEMATRIX2("/servlet/excelData",D21, $C$14,$B21&":"&D$16&D$17&":"&D$19&":"&$B22) -> #NAME? | E22: =_xll.BLUEMATRIX2("/servlet/excelData",E21, $C$14,$B21&":"&E$16&E$17&":"&E$19&":"&$B22) -> #NAME? | F22: =_xll.BLUEMATRIX2("/servlet/excelData",F21, $C$14,$B21&":"&F$16&F$17&":"&F$19&":"&$B22) -> #NAME? | G22: =_xll.BLUEMATRIX2("/servlet/excelData",G21, $C$14,$B21&":"&G$16&G$17&":"&G$19&":"&$B22) -> #NAME? | H22: =_xll.BLUEMATRIX2("/servlet/excelData",H21, $C$14,$B21&":"&H$16&H$17&":"&H$19&":"&$B22) -> #NAME? | I22: =_xll.BLUEMATRIX2("/servlet/excelData",I21, $C$14,$B21&":"&I$16&I$17&":"&I$19&":"&$B22) -> #NAME? | J22: =_xll.BLUEMATRIX2("/servlet/excelData",J21, $C$14,$B21&":"&J$16&J$17&":"&J$19&":"&$B22) -> #NAME? | K22: =_xll.BLUEMATRIX2("/servlet/excelData",K21, $C$14,$B21&":"&K$16&K$17&":"&K$19&":"&$B22) -> #NAME? | ... BZ22: =_xll.BLUEMATRIX2("/servlet/excelData",BZ21, $C$14,$B21&":"&BZ$16&BZ$17&":"&BZ$19&":"&$B22) -> #NAME?
A23: EPS | B23: EPS | D23: =IS!I59 -> 0.0097969816 | E23: =IS!J59 -> 0.059644562 | F23: =IS!K59 -> 0.080834276 | G23: =IS!L59 -> 0.047521675 | H23: =IS!M59 -> 0.19855885 | I23: =IS!N59 -> 0.045466803 | J23: =IS!O59 -> 0.11362958 | K23: =IS!P59 -> 0.15377562 | ... BZ23: =IS!CE59 -> 8.0972876
B24: NON-GAAP:CALENDAR | D24: =_xll.BLUEMATRIX2("/servlet/excelData",D23, $C$14,$B23&":"&D$16&D$17&":"&D$19&":"&$B24) -> #NAME? | E24: =_xll.BLUEMATRIX2("/servlet/excelData",E23, $C$14,$B23&":"&E$16&E$17&":"&E$19&":"&$B24) -> #NAME? | F24: =_xll.BLUEMATRIX2("/servlet/excelData",F23, $C$14,$B23&":"&F$16&F$17&":"&F$19&":"&$B24) -> #NAME? | G24: =_xll.BLUEMATRIX2("/servlet/excelData",G23, $C$14,$B23&":"&G$16&G$17&":"&G$19&":"&$B24) -> #NAME? | H24: =_xll.BLUEMATRIX2("/servlet/excelData",H23, $C$14,$B23&":"&H$16&H$17&":"&H$19&":"&$B24) -> #NAME? | I24: =_xll.BLUEMATRIX2("/servlet/excelData",I23, $C$14,$B23&":"&I$16&I$17&":"&I$19&":"&$B24) -> #NAME? | J24: =_xll.BLUEMATRIX2("/servlet/excelData",J23, $C$14,$B23&":"&J$16&J$17&":"&J$19&":"&$B24) -> #NAME? | K24: =_xll.BLUEMATRIX2("/servlet/excelData",K23, $C$14,$B23&":"&K$16&K$17&":"&K$19&":"&$B24) -> #NAME? | ... BZ24: =_xll.BLUEMATRIX2("/servlet/excelData",BZ23, $C$14,$B23&":"&BZ$16&BZ$17&":"&BZ$19&":"&$B24) -> #NAME?
A25: FCF | B25: FCF | BI25: RESTATED:CALENDAR
D26: =_xll.BLUEMATRIX2("/servlet/excelData",D25, $C$14,$B25&":"&D$16&D$17&":"&D$19&":"&$B26) -> #NAME? | E26: =_xll.BLUEMATRIX2("/servlet/excelData",E25, $C$14,$B25&":"&E$16&E$17&":"&E$19&":"&$B26) -> #NAME? | F26: =_xll.BLUEMATRIX2("/servlet/excelData",F25, $C$14,$B25&":"&F$16&F$17&":"&F$19&":"&$B26) -> #NAME? | G26: =_xll.BLUEMATRIX2("/servlet/excelData",G25, $C$14,$B25&":"&G$16&G$17&":"&G$19&":"&$B26) -> #NAME? | H26: =_xll.BLUEMATRIX2("/servlet/excelData",H25, $C$14,$B25&":"&H$16&H$17&":"&H$19&":"&$B26) -> #NAME? | I26: =_xll.BLUEMATRIX2("/servlet/excelData",I25, $C$14,$B25&":"&I$16&I$17&":"&I$19&":"&$B26) -> #NAME? | J26: =_xll.BLUEMATRIX2("/servlet/excelData",J25, $C$14,$B25&":"&J$16&J$17&":"&J$19&":"&$B26) -> #NAME? | K26: =_xll.BLUEMATRIX2("/servlet/excelData",K25, $C$14,$B25&":"&K$16&K$17&":"&K$19&":"&$B26) -> #NAME? | ... W26: =_xll.BLUEMATRIX2("/servlet/excelData",W25, $C$14,$B25&":"&W$16&W$17&":"&W$19&":"&$B26) -> #NAME? | BI26: REVENUE:CALENDAR
A27: FFO | B27: FFO
D28: =_xll.BLUEMATRIX2("/servlet/excelData",D27, $C$14,$B27&":"&D$16&D$17&":"&D$19&":"&$B28) -> #NAME? | E28: =_xll.BLUEMATRIX2("/servlet/excelData",E27, $C$14,$B27&":"&E$16&E$17&":"&E$19&":"&$B28) -> #NAME? | F28: =_xll.BLUEMATRIX2("/servlet/excelData",F27, $C$14,$B27&":"&F$16&F$17&":"&F$19&":"&$B28) -> #NAME? | G28: =_xll.BLUEMATRIX2("/servlet/excelData",G27, $C$14,$B27&":"&G$16&G$17&":"&G$19&":"&$B28) -> #NAME? | H28: =_xll.BLUEMATRIX2("/servlet/excelData",H27, $C$14,$B27&":"&H$16&H$17&":"&H$19&":"&$B28) -> #NAME? | I28: =_xll.BLUEMATRIX2("/servlet/excelData",I27, $C$14,$B27&":"&I$16&I$17&":"&I$19&":"&$B28) -> #NAME? | J28: =_xll.BLUEMATRIX2("/servlet/excelData",J27, $C$14,$B27&":"&J$16&J$17&":"&J$19&":"&$B28) -> #NAME? | K28: =_xll.BLUEMATRIX2("/servlet/excelData",K27, $C$14,$B27&":"&K$16&K$17&":"&K$19&":"&$B28) -> #NAME? | ... W28: =_xll.BLUEMATRIX2("/servlet/excelData",W27, $C$14,$B27&":"&W$16&W$17&":"&W$19&":"&$B28) -> #NAME?
A29: Net Cash/Debt ($M) | B29: NET_CASH_DEBT
D30: =_xll.BLUEMATRIX2("/servlet/excelData",D29, $C$14,$B29&":"&D$16&D$17&":"&D$19&":"&$B30) -> #NAME? | E30: =_xll.BLUEMATRIX2("/servlet/excelData",E29, $C$14,$B29&":"&E$16&E$17&":"&E$19&":"&$B30) -> #NAME? | F30: =_xll.BLUEMATRIX2("/servlet/excelData",F29, $C$14,$B29&":"&F$16&F$17&":"&F$19&":"&$B30) -> #NAME? | G30: =_xll.BLUEMATRIX2("/servlet/excelData",G29, $C$14,$B29&":"&G$16&G$17&":"&G$19&":"&$B30) -> #NAME? | H30: =_xll.BLUEMATRIX2("/servlet/excelData",H29, $C$14,$B29&":"&H$16&H$17&":"&H$19&":"&$B30) -> #NAME? | I30: =_xll.BLUEMATRIX2("/servlet/excelData",I29, $C$14,$B29&":"&I$16&I$17&":"&I$19&":"&$B30) -> #NAME? | J30: =_xll.BLUEMATRIX2("/servlet/excelData",J29, $C$14,$B29&":"&J$16&J$17&":"&J$19&":"&$B30) -> #NAME? | K30: =_xll.BLUEMATRIX2("/servlet/excelData",K29, $C$14,$B29&":"&K$16&K$17&":"&K$19&":"&$B30) -> #NAME? | ... W30: =_xll.BLUEMATRIX2("/servlet/excelData",W29, $C$14,$B29&":"&W$16&W$17&":"&W$19&":"&$B30) -> #NAME?
A31: Operating Margin | B31: OP_MARGIN
D32: =_xll.BLUEMATRIX2("/servlet/excelData",D31, $C$14,$B31&":"&D$16&D$17&":"&D$19&":"&$B32) -> #NAME? | E32: =_xll.BLUEMATRIX2("/servlet/excelData",E31, $C$14,$B31&":"&E$16&E$17&":"&E$19&":"&$B32) -> #NAME? | F32: =_xll.BLUEMATRIX2("/servlet/excelData",F31, $C$14,$B31&":"&F$16&F$17&":"&F$19&":"&$B32) -> #NAME? | G32: =_xll.BLUEMATRIX2("/servlet/excelData",G31, $C$14,$B31&":"&G$16&G$17&":"&G$19&":"&$B32) -> #NAME? | H32: =_xll.BLUEMATRIX2("/servlet/excelData",H31, $C$14,$B31&":"&H$16&H$17&":"&H$19&":"&$B32) -> #NAME? | I32: =_xll.BLUEMATRIX2("/servlet/excelData",I31, $C$14,$B31&":"&I$16&I$17&":"&I$19&":"&$B32) -> #NAME? | J32: =_xll.BLUEMATRIX2("/servlet/excelData",J31, $C$14,$B31&":"&J$16&J$17&":"&J$19&":"&$B32) -> #NAME? | K32: =_xll.BLUEMATRIX2("/servlet/excelData",K31, $C$14,$B31&":"&K$16&K$17&":"&K$19&":"&$B32) -> #NAME? | ... W32: =_xll.BLUEMATRIX2("/servlet/excelData",W31, $C$14,$B31&":"&W$16&W$17&":"&W$19&":"&$B32) -> #NAME?
A33: Revenue ($M) | B33: REVENUE
D34: =_xll.BLUEMATRIX2("/servlet/excelData",D33, $C$14,$B33&":"&D$16&D$17&":"&D$19&":"&$B34) -> #NAME? | E34: =_xll.BLUEMATRIX2("/servlet/excelData",E33, $C$14,$B33&":"&E$16&E$17&":"&E$19&":"&$B34) -> #NAME? | F34: =_xll.BLUEMATRIX2("/servlet/excelData",F33, $C$14,$B33&":"&F$16&F$17&":"&F$19&":"&$B34) -> #NAME? | G34: =_xll.BLUEMATRIX2("/servlet/excelData",G33, $C$14,$B33&":"&G$16&G$17&":"&G$19&":"&$B34) -> #NAME? | H34: =_xll.BLUEMATRIX2("/servlet/excelData",H33, $C$14,$B33&":"&H$16&H$17&":"&H$19&":"&$B34) -> #NAME? | I34: =_xll.BLUEMATRIX2("/servlet/excelData",I33, $C$14,$B33&":"&I$16&I$17&":"&I$19&":"&$B34) -> #NAME? | J34: =_xll.BLUEMATRIX2("/servlet/excelData",J33, $C$14,$B33&":"&J$16&J$17&":"&J$19&":"&$B34) -> #NAME? | K34: =_xll.BLUEMATRIX2("/servlet/excelData",K33, $C$14,$B33&":"&K$16&K$17&":"&K$19&":"&$B34) -> #NAME? | ... W34: =_xll.BLUEMATRIX2("/servlet/excelData",W33, $C$14,$B33&":"&W$16&W$17&":"&W$19&":"&$B34) -> #NAME?
A35: ROIC | B35: ROIC
D36: =_xll.BLUEMATRIX2("/servlet/excelData",D35, $C$14,$B35&":"&D$16&D$17&":"&D$19&":"&$B36) -> #NAME? | E36: =_xll.BLUEMATRIX2("/servlet/excelData",E35, $C$14,$B35&":"&E$16&E$17&":"&E$19&":"&$B36) -> #NAME? | F36: =_xll.BLUEMATRIX2("/servlet/excelData",F35, $C$14,$B35&":"&F$16&F$17&":"&F$19&":"&$B36) -> #NAME? | G36: =_xll.BLUEMATRIX2("/servlet/excelData",G35, $C$14,$B35&":"&G$16&G$17&":"&G$19&":"&$B36) -> #NAME? | H36: =_xll.BLUEMATRIX2("/servlet/excelData",H35, $C$14,$B35&":"&H$16&H$17&":"&H$19&":"&$B36) -> #NAME? | I36: =_xll.BLUEMATRIX2("/servlet/excelData",I35, $C$14,$B35&":"&I$16&I$17&":"&I$19&":"&$B36) -> #NAME? | J36: =_xll.BLUEMATRIX2("/servlet/excelData",J35, $C$14,$B35&":"&J$16&J$17&":"&J$19&":"&$B36) -> #NAME? | K36: =_xll.BLUEMATRIX2("/servlet/excelData",K35, $C$14,$B35&":"&K$16&K$17&":"&K$19&":"&$B36) -> #NAME? | ... W36: =_xll.BLUEMATRIX2("/servlet/excelData",W35, $C$14,$B35&":"&W$16&W$17&":"&W$19&":"&$B36) -> #NAME?
D44: Calendar Year = Fiscal Year (If yes =0, if less= -1, if more = 1)
A45: Fiscal 1Q Ending Month Number | B45: 3 | D45: 0
A46: Fiscal 2Q Ending Month Number | B46: 6 | D46: 0
A47: Fiscal 3Q Ending Month Number | B47: 9 | D47: 0
A48: Fiscal 4Q Ending Month Number | B48: 12 | D48: 0

Sheet Variance
B3: Qualys, Inc. Quarterly Variance Analysis
B4: (Thousands Of Dollars, Except Per-Share Data) | T4: Guidance
D5: Actual | E5: Actual | F5: NH-Ests. | G5: Actual | I5: Variance | L5: Yr-Yr | O5: Q-Q | T5: Quarter | U5: Low Band | V5: High Band | W5: Midpoint
D6: =IS!BO6 -> 4Q-Dec 24A | E6: 3Q-Sep 25A | F6: 4Q-Dec 25E | G6: =IS!BT6 -> 4Q-Dec 25A | I6: % | J6: Absolute | L6: % | M6: Absolute | O6: % | P6: Absolute | T6: Revs | U6: 154500 | V6: 157500 | W6: =AVERAGE(V6,U6) -> 156000
T7: EPS | U7: 5.81 | V7: 5.91 | W7: =AVERAGE(V7,U7) -> 5.86
B8: Calculated Current Billings | D8: =+IS!BO7 -> 192827 | E8: 186387 | F8: 205709.83 | G8: =+IS!BT7 -> 204933 | I8: =+G8/F8-1 -> -0.0037763533 | J8: =+G8-F8 -> -776.833 | L8: =+G8/D8-1 -> 0.062781664 | M8: =+G8-D8 -> 12106 | O8: =+G8/E8-1 -> 0.099502648 | P8: =+G8-E8 -> 18546
B10: Revenues | D10: =+IS!BO9 -> 159191 | E10: 169882 | F10: 173040.62 | G10: =+IS!BT9 -> 175282 | I10: =+G10/F10-1 -> 0.01295293 | J10: =+G10-F10 -> 2241.383 | L10: =+G10/D10-1 -> 0.10107983 | M10: =+G10-D10 -> 16091 | O10: =+G10/E10-1 -> 0.03178677 | P10: =+G10-E10 -> 5400 | T10: New Year | U10: Low Band | V10: High Band | W10: Midpoint | X10: $∆ | Y10: %∆
B11: Street Estimate | C11: Guide: $172.0-$174.0M | F11: 173160 | I11: =+G10/F11-1 -> 0.012254562 | J11: =+G10-F11 -> 2122 | T11: Revs | W11: =+AVERAGE(U11:V11) -> #DIV/0! | X11: =+W11-W18 -> #DIV/0! | Y11: =+W11/W18-1 -> #DIV/0!
B12: Cost of Goods Sold (Non GAAP) | D12: =+IS!BO14 -> 26236 | E12: 24987 | F12: 26821.296 | G12: =+IS!BT14 -> 26241 | I12: =+G12/F12-1 -> -0.02163563 | J12: =+G12-F12 -> -580.29564 | L12: =+G12/D12-1 -> 0.00019057783 | M12: =+G12-D12 -> 5 | O12: =+G12/E12-1 -> 0.050186097 | P12: =+G12-E12 -> 1254 | T12: EPS | W12: =+AVERAGE(U12:V12) -> #DIV/0! | X12: =+W12-W19 -> #DIV/0! | Y12: =+W12/W19-1 -> #DIV/0!
D13: ______ | E13: ______ | F13: ______ | G13: ______ | I13: ______ | J13: ______ | L13: ______ | M13: ______ | O13: ______ | P13: ______
B14: Gross Profit | D14: =+D10-D12 -> 132955 | E14: 144895 | F14: 146219.32 | G14: =+G10-G12 -> 149041 | I14: =+G14/F14-1 -> 0.019297577 | J14: =+G14-F14 -> 2821.6786 | L14: =+G14/D14-1 -> 0.1209883 | M14: =+G14-D14 -> 16086 | O14: =+G14/E14-1 -> 0.028613824 | P14: =+G14-E14 -> 4146
B15: Gross Margin | D15: =+D14/D10 -> 0.83519169 | E15: 0.85291555 | F15: 0.845 | G15: =+G14/G10 -> 0.85029267 | I15: =+G15/F15-1 -> 0.0062635163 | J15: =+(G15-F15)*10000 -> 52.926712 | K15: BPs | L15: =+G15/D15-1 -> 0.018080859 | M15: =+(G15-D15)*10000 -> 151.00983 | N15: BPs | O15: =+G15/E15-1 -> -0.0030751953 | P15: =+(G15-E15)*10000 -> -26.228819 | Q15: BPs
B17: Operating Expenses | T17: Old Year | U17: Low Band | V17: High Band | W17: Midpoint
B18: Research and Development | D18: =+IS!BO21 -> 23025 | E18: 23720 | F18: 23245.6 | G18: =+IS!BT21 -> 24167 | I18: =+G18/F18-1 -> 0.039637609 | J18: =+G18-F18 -> 921.4 | L18: =+G18/D18-1 -> 0.049598263 | M18: =+G18-D18 -> 1142 | O18: =+G18/E18-1 -> 0.018844857 | P18: =+G18-E18 -> 447 | T18: Revs
B19: % of Revenue | D19: =+D18/D10 -> 0.14463757 | E19: 0.13962633 | F19: 0.13433609 | G19: =+G18/G10 -> 0.13787497 | J19: =+(G19-F19)*10000 -> 35.388766 | K19: BPs | M19: =+(G19-D19)*10000 -> -67.626065 | N19: BPs | P19: =+(G19-E19)*10000 -> -17.513617 | Q19: BPs | T19: EPS
B20: Sales and Marketing | D20: =+IS!BO26 -> 30393 | E20: 31790 | F20: 32425.8 | G20: =+IS!BT26 -> 35721 | I20: =+G20/F20-1 -> 0.10162278 | J20: =+G20-F20 -> 3295.2 | L20: =+G20/D20-1 -> 0.17530352 | M20: =+G20-D20 -> 5328 | O20: =+G20/E20-1 -> 0.12365524 | P20: =+G20-E20 -> 3931
B21: % of Revenue | D21: =+D20/D10 -> 0.1909216 | E21: 0.18712989 | F21: 0.18738837 | G21: =+G20/G10 -> 0.2037916 | J21: =+(G21-F21)*10000 -> 164.0323 | K21: BPs | M21: =+(G21-D21)*10000 -> 128.70007 | N21: BPs | P21: =+(G21-E21)*10000 -> 166.61714 | Q21: BPs
B22: General and Administrative | D22: =+IS!BO31 -> 8806 | E22: 9344 | F22: 9157.12 | G22: =+IS!BT31 -> 9026 | I22: =+G22/F22-1 -> -0.014318912 | J22: =+G22-F22 -> -131.12 | L22: =+G22/D22-1 -> 0.024982966 | M22: =+G22-D22 -> 220 | O22: =+G22/E22-1 -> -0.034032534 | P22: =+G22-E22 -> -318
B23: % of Revenue | D23: =+D22/D10 -> 0.055317198 | E23: 0.055002884 | F23: 0.052918905 | G23: =+G22/G10 -> 0.051494164 | J23: =+(G23-F23)*10000 -> -14.247415 | K23: BPs | M23: =+(G23-D23)*10000 -> -38.230339 | N23: BPs | P23: =+(G23-E23)*10000 -> -35.087207 | Q23: BPs
D24: ______ | E24: ______ | F24: ______ | G24: ______ | I24: ______ | J24: ______ | L24: ______ | M24: ______ | O24: ______ | P24: ______
B25: Total Operating Expenses | D25: =D18+D22+D20 -> 62224 | E25: 64854 | F25: 64828.52 | G25: =G18+G22+G20 -> 68914 | I25: =+G25/F25-1 -> 0.063019794 | J25: =+G25-F25 -> 4085.48 | L25: =+G25/D25-1 -> 0.10751479 | M25: =+G25-D25 -> 6690 | O25: =+G25/E25-1 -> 0.062602153 | P25: =+G25-E25 -> 4060
B26: % of Revenue | D26: =D25/D$10 -> 0.39087637 | E26: 0.3817591 | F26: 0.37464337 | G26: =G25/G$10 -> 0.39316074 | J26: =+(G26-F26)*10000 -> 185.17365 | K26: BPs | M26: =+(G26-D26)*10000 -> 22.843666 | N26: BPs | P26: =+(G26-E26)*10000 -> 114.01632 | Q26: BPs
D27: ______ | E27: ______ | F27: ______ | G27: ______ | I27: ______ | J27: ______ | L27: ______ | M27: ______ | O27: ______ | P27: ______
B28: Operating Income | D28: =D14-D25 -> 70731 | E28: 80041 | F28: 81390.801 | G28: =G14-G25 -> 80127 | I28: =+G28/F28-1 -> -0.01552757 | J28: =+G28-F28 -> -1263.8014 | L28: =+G28/D28-1 -> 0.13284133 | M28: =+G28-D28 -> 9396 | O28: =+G28/E28-1 -> 0.0010744493 | P28: =+G28-E28 -> 86
B29: Operating Margin | D29: =D28/D$10 -> 0.44431532 | E29: 0.47115645 | F29: 0.47035663 | G29: =G28/G$10 -> 0.45713194 | I29: =+G29/F29-1 -> -0.028116311 | J29: =+(G29-F29)*10000 -> -132.24693 | K29: BPs | L29: =+G29/D29-1 -> 0.028845768 | M29: =+(G29-D29)*10000 -> 128.16617 | N29: BPs | O29: =+G29/E29-1 -> -0.029766151 | P29: =+(G29-E29)*10000 -> -140.24514 | Q29: BPs
B32: Interest expense | D32: =+IS!BO45 -> 0 | E32: 0 | F32: 0 | G32: =+IS!BT45 -> 0
B33: Interest income | D33: =+IS!BO46 -> 6194 | E33: 6264 | F33: 500 | G33: =+IS!BT46 -> 6345 | I33: =+G33/F33-1 -> 11.69 | J33: =+G33-F33 -> 5845 | L33: =+G33/D33-1 -> 0.024378431 | M33: =+G33-D33 -> 151 | O33: =+G33/E33-1 -> 0.012931034 | P33: =+G33-E33 -> 81
B34: Other expense, net | D34: =+IS!BO47 -> -1777 | E34: -937 | F34: 0 | G34: =+IS!BT47 -> -754 | I34: NA | J34: =+G34-F34 -> -754 | L34: =+G34/D34-1 -> -0.57568936 | M34: =+G34-D34 -> 1023 | O34: =+G34/E34-1 -> -0.19530416 | P34: =+G34-E34 -> 183
B35: Interest and Other Income, net | D35: =SUM(IS!BO45:BO47) -> 4417 | E35: 5327 | F35: 500 | G35: =SUM(IS!BT45:BT47) -> 5591 | I35: =+G35/F35-1 -> 10.182 | J35: =+G35-F35 -> 5091 | L35: =+G35/D35-1 -> 0.26579126 | M35: =+G35-D35 -> 1174 | O35: =+G35/E35-1 -> 0.049558851 | P35: =+G35-E35 -> 264
D36: ______ | E36: ______ | F36: ______ | G36: ______ | I36: ______ | J36: ______ | L36: ______ | M36: ______ | O36: ______ | P36: ______
B37: Pretax Income | D37: =+D34+D28+D33+D32 -> 75148 | E37: 85368 | F37: 81890.801 | G37: =+G34+G28+G33+G32 -> 85718 | I37: =+G37/F37-1 -> 0.046735391 | J37: =+G37-F37 -> 3827.1986 | L37: =+G37/D37-1 -> 0.14065577 | M37: =+G37-D37 -> 10570 | O37: =+G37/E37-1 -> 0.0040998969 | P37: =+G37-E37 -> 350
B38: Pretax Margin | D38: =+D37/D10 -> 0.47206186 | E38: 0.50251351 | F38: 0.47324612 | G38: =+G37/G10 -> 0.48902911 | I38: =+G38/F38-1 -> 0.033350475 | J38: =+(G38-F38)*10000 -> 157.82983 | K38: BPs | L38: =+G38/D38-1 -> 0.035942841 | M38: =+(G38-D38)*10000 -> 169.67245 | N38: BPs | O38: =+G38/E38-1 -> -0.026833909 | P38: =+(G38-E38)*10000 -> -134.84402 | Q38: BPs
B41: Income Tax Expense (Income) | D41: =+IS!BO53 -> 15781 | E41: 17927 | F41: 17197.068 | G41: =+IS!BT53 -> 18003 | I41: =+G41/F41-1 -> 0.046864483 | J41: =+G41-F41 -> 805.93171 | L41: =+G41/D41-1 -> 0.14080223 | M41: =+G41-D41 -> 2222 | O41: =+G41/E41-1 -> 0.0042394154 | P41: =+G41-E41 -> 76
B42: Tax Rate | D42: =+D41/D37 -> 0.20999894 | E42: 0.20999672 | F42: 0.21 | G42: =+G41/G37 -> 0.2100259 | I42: =+G42/F42-1 -> 0.00012332799 | J42: =+(G42-F42)*10000 -> 0.25898878 | K42: BPs | L42: =+G42/D42-1 -> 0.000128398 | M42: =+(G42-D42)*10000 -> 0.26963444 | N42: BPs | O42: =+G42/E42-1 -> 0.00013894881 | P42: =+(G42-E42)*10000 -> 0.29178795 | Q42: BPs
D43: ______ | E43: ______ | F43: ______ | G43: ______ | I43: ______ | J43: ______ | L43: ______ | M43: ______ | O43: ______ | P43: ______
B44: NG-Net Income | D44: =+D37-D41 -> 59367 | E44: 67441 | F44: 64693.733 | G44: =+G37-G41 -> 67715 | I44: =+G44/F44-1 -> 0.046701076 | J44: =+J37-J41 -> 3021.2669 | L44: =+G44/D44-1 -> 0.14061684 | M44: =+G44-D44 -> 8348 | O44: =+G44/E44-1 -> 0.0040628105 | P44: =+G44-E44 -> 274
B47: NG--Earnings Per Share | D47: =+IS!BO59 -> 1.6045135 | E47: 1.8582371 | F47: 1.7960103 | G47: =+IS!BT59 -> 1.8736857 | I47: =+G47/F47-1 -> 0.04324883 | J47: =+G47-F47 -> 0.077675345 | L47: =+G47/D47-1 -> 0.16775936 | M47: =+G47-D47 -> 0.26917215 | O47: =+G47/E47-1 -> 0.0083135468 | P47: =+G47-E47 -> 0.015448541
B48: Street Estimate | C48: Guide: $1.73-$1.80 | F48: 1.78 | I48: =+G47/F48-1 -> 0.052632397 | J48: =+G47-F48 -> 0.093685667
B50: Shares Outstanding | D50: =+IS!BK62 -> 37575 | E50: 37136 | F50: 37136 | G50: =+IS!BN62 -> 37136 | I50: =+G50/F50-1 -> 0 | J50: =+G50-F50 -> 0 | L50: =+G50/D50-1 -> -0.0116833 | M50: =+G50-D50 -> -439 | O50: =+G50/E50-1 -> 0 | P50: =+G50-E50 -> 0
B52: Source: Qualys, Inc. Financial Statements, FactSet Estimates

Sheet BS
B3: Qualys, Inc.—Balance Sheet
B4: (Thousands Of Dollars, Except Per-Share Data) | D4: March | E4: June | F4: Sept | G4: Dec | H4: Dec | I4: March | J4: June | K4: Sept | L4: Dec | M4: Dec | N4: March | O4: June | P4: Sept | Q4: Dec | R4: Dec | S4: March | T4: June | U4: Sept | V4: Dec | W4: Dec | X4: March | Y4: June | Z4: Sept | AA4: Dec | AB4: Dec | AC4: March | AD4: June | AE4: Sept | AF4: Dec | AG4: Dec | AH4: March | AI4: June | AJ4: Sept | AK4: Dec | AL4: Dec | AM4: March | AN4: June | AO4: Sept | AP4: Dec | AQ4: Dec | AR4: March | AS4: June | AT4: Sept | AU4: Dec | AV4: Dec | AW4: March | AX4: June | AY4: Sept | AZ4: Dec | BA4: Dec | BB4: March | BC4: June | BD4: Sept | BE4: Dec | BF4: Dec | BG4: March | BH4: June | BI4: Sept | BJ4: Dec | BK4: Dec | BL4: March | BM4: June | BN4: Sept | BO4: Dec | BP4: Dec | BQ4: March | BR4: June | BS4: Sept | BT4: Dec | BU4: Dec | BV4: March | BW4: June | BX4: Sept | BY4: Dec | BZ4: Dec | CA4: March | CB4: June | CC4: Sept | CD4: Dec | CE4: Dec
D5: 2012A | E5: 2012A | F5: 2012A | G5: 2012A | H5: 2012A | I5: 2013A | J5: 2013A | K5: 2013A | L5: 2013A | M5: 2013A | N5: 2014A | O5: 2014A | P5: 2014A | Q5: 2014A | R5: 2014A | S5: 2015A | T5: 2015A | U5: 2015A | V5: 2015A | W5: 2015A | X5: 2016A | Y5: 2016A | Z5: 2016A | AA5: 2016A | AB5: 2016A | AC5: 2017A | AD5: 2017A | AE5: 2017A | AF5: 2017A | AG5: 2017A | AH5: 2018A | AI5: 2018A | AJ5: 2018A | AK5: 2018A | AL5: 2018A | AM5: 2019A | AN5: 2019A | AO5: 2019A | AP5: 2019A | AQ5: =+AP5 -> 2019A | AR5: 2020A | AS5: 2020A | AT5: 2020A | AU5: 2020A | AV5: =+AU5 -> 2020A | AW5: 2021A | AX5: 2021A | AY5: 2021A | AZ5: 2021A | BA5: =+AZ5 -> 2021A | BB5: 2022A | BC5: 2022A | BD5: 2022A | BE5: 2022A | BF5: =+BE5 -> 2022A | BG5: 2023A | BH5: 2023A | BI5: 2023A | BJ5: 2023A | BK5: =+BJ5 -> 2023A | BL5: 2024A | BM5: 2024A | BN5: 2024A | BO5: 2024A | BP5: =+BO5 -> 2024A | BQ5: 2025A | BR5: 2025A | BS5: 2025A | BT5: 2025A | BU5: =+BT5 -> 2025A | BV5: 2026E | BW5: 2026E | BX5: 2026E | BY5: 2026E | BZ5: =+BY5 -> 2026E | CA5: 2027E | CB5: 2027E | CC5: 2027E | CD5: 2027E | CE5: =+CD5 -> 2027E
B6: Current Assets
B7: Cash and Cash Equivalents | G7: 34885 | H7: =+G7 -> 34885 | L7: 42369 | M7: =+L7 -> 42369 | N7: 48296 | O7: 41672 | P7: 88285 | Q7: 76504 | R7: =+Q7 -> 76504 | S7: 78018 | T7: 84058 | U7: 94763 | V7: 91698 | W7: =+V7 -> 91698 | X7: 112471 | Y7: 118194 | Z7: 98299 | AA7: 86737 | AB7: =+AA7 -> 86737 | AC7: 109651 | AD7: 130572 | AE7: 90517 | AF7: 86591 | AG7: =+AF7 -> 86591 | AH7: 93174 | AI7: 86779 | AJ7: 97964 | AK7: 41026 | AL7: =+AK7 -> 41026 | AM7: 93127 | AN7: 91381 | AO7: 75615 | AP7: =87559 -> 87559 | AQ7: =+AP7 -> 87559 | AR7: 147565 | AS7: 113909 | AT7: =93027 -> 93027 | AU7: =74132 -> 74132 | AV7: =AU7 -> 74132 | AW7: =108753 -> 108753 | AX7: =97278 -> 97278 | AY7: =145740 -> 145740 | AZ7: =137328 -> 137328 | BA7: =+AZ7 -> 137328 | BB7: =166287 -> 166287 | BC7: =120965 -> 120965 | BD7: =193902 -> 193902 | BE7: =173719 -> 173719 | BF7: =+BE7 -> 173719 | BG7: =193854 -> 193854 | BH7: =186145 -> 186145 | BI7: =208724 -> 208724 | BJ7: =203665 -> 203665 | BK7: =+BJ7 -> 203665 | BL7: =273783 -> 273783 | BM7: =281205 -> 281205 | BN7: =235430 -> 235430 | BO7: =232182 -> 232182 | BP7: =+BO7 -> 232182 | BQ7: =290671 -> 290671 | BR7: =193983 -> 193983 | BS7: =225253 -> 225253 | BT7: =250258 -> 250258 | BU7: =+BT7 -> 250258 | BV7: =+CF!BV61 -> 359729.96 | BW7: =+CF!BW61 -> 400997.09 | BX7: =+CF!BX61 -> 487609.74 | BY7: =+CF!BY61 -> 549144.83 | BZ7: =+BY7 -> 549144.83 | CA7: =+CF!CA61 -> 666827.82 | CB7: =+CF!CB61 -> 699696.94 | CC7: =+CF!CC61 -> 807758.35 | CD7: =+CF!CD61 -> 874317.89 | CE7: =+CD7 -> 874317.89
B8: Short-Term Investments | G8: 83547 | H8: =+G8 -> 83547 | L8: 54827 | M8: =+L8 -> 54827 | N8: 57312 | O8: 67673 | P8: 25133 | Q8: 50714 | R8: =+Q8 -> 50714 | S8: 64932 | T8: 74052 | U8: 79382 | V8: 87268 | W8: =+V8 -> 87268 | X8: 93238 | Y8: 96186 | Z8: 111678 | AA8: 157119 | AB8: =+AA8 -> 157119 | AC8: 135128 | AD8: 148290 | AE8: 212210 | AF8: 201823 | AG8: =+AF8 -> 201823 | AH8: 235353 | AI8: 235740 | AJ8: 228542 | AK8: 248140 | AL8: =+AK8 -> 248140 | AM8: 205009 | AN8: 207626 | AO8: 222421 | AP8: =211331 -> 211331 | AQ8: =+AP8 -> 211331 | AR8: 184387 | AS8: 233922 | AT8: =225734 -> 225734 | AU8: =281892 -> 281892 | AV8: =AU8 -> 281892 | AW8: =247982 -> 247982 | AX8: =262941 -> 262941 | AY8: =199947 -> 199947 | AZ8: =267960 -> 267960 | BA8: =+AZ8 -> 267960 | BB8: =290851 -> 290851 | BC8: =298124 -> 298124 | BD8: =191378 -> 191378 | BE8: =147608 -> 147608 | BF8: =+BE8 -> 147608 | BG8: =139925 -> 139925 | BH8: =163107 -> 163107 | BI8: =218690 -> 218690 | BJ8: =221893 -> 221893 | BK8: =+BJ8 -> 221893 | BL8: =179887 -> 179887 | BM8: =112004 -> 112004 | BN8: =150913 -> 150913 | BO8: =149241 -> 149241 | BP8: =+BO8 -> 149241 | BQ8: =150206 -> 150206 | BR8: =176048 -> 176048 | BS8: =193321 -> 193321 | BT8: =195681 -> 195681 | BU8: =+BT8 -> 195681 | BV8: =+BT8 -> 195681 | BW8: =+BV8 -> 195681 | BX8: =+BW8 -> 195681 | BY8: =+BX8 -> 195681 | BZ8: =+BY8 -> 195681 | CA8: =+BY8 -> 195681 | CB8: =+CA8 -> 195681 | CC8: =+CB8 -> 195681 | CD8: =+CC8 -> 195681 | CE8: =+CD8 -> 195681
B9: Accounts Receivable, net | G9: 24545 | H9: =+G9 -> 24545 | L9: 28581 | M9: =+L9 -> 28581 | N9: 21887 | O9: 28062 | P9: 30278 | Q9: 32993 | R9: =+Q9 -> 32993 | S9: 38732 | T9: 34552 | U9: 37876 | V9: 42325 | W9: =+V9 -> 42325 | X9: 42414 | Y9: 40387 | Z9: 41910 | AA9: 47024 | AB9: =+AA9 -> 47024 | AC9: 41639 | AD9: 46359 | AE9: 46354 | AF9: 64412 | AG9: =+AF9 -> 64412 | AH9: 49874 | AI9: 52535 | AJ9: 58612 | AK9: 75825 | AL9: =+AK9 -> 75825 | AM9: 67863 | AN9: 63184 | AO9: 61314 | AP9: =78034 -> 78034 | AQ9: =+AP9 -> 78034 | AR9: 72696 | AS9: 75938 | AT9: =64291 -> 64291 | AU9: =100179 -> 100179 | AV9: =AU9 -> 100179 | AW9: =85222 -> 85222 | AX9: =86044 -> 86044 | AY9: =84267 -> 84267 | AZ9: =108998 -> 108998 | BA9: =+AZ9 -> 108998 | BB9: =89294 -> 89294 | BC9: =97692 -> 97692 | BD9: =98717 -> 98717 | BE9: =121795 -> 121795 | BF9: =+BE9 -> 121795 | BG9: =101786 -> 101786 | BH9: =124912 -> 124912 | BI9: =103428 -> 103428 | BJ9: =146226 -> 146226 | BK9: =+BJ9 -> 146226 | BL9: =115629 -> 115629 | BM9: =109584 -> 109584 | BN9: =114967 -> 114967 | BO9: =164551 -> 164551 | BP9: =+BO9 -> 164551 | BQ9: =121563 -> 121563 | BR9: =128675 -> 128675 | BS9: =128418 -> 128418 | BT9: =170991 -> 170991 | BU9: =+BT9 -> 170991 | BV9: =+BV58*BV74/90 -> 131081.65 | BW9: =+BW58*BW74/90 -> 141749.57 | BX9: =+BX58*BX74/90 -> 131894.5 | BY9: =+BY58*BY74/90 -> 191719.56 | BZ9: =+BY9 -> 191719.56 | CA9: =+CA58*CA74/90 -> 143650.06 | CB9: =+CB58*CB74/90 -> 149565.48 | CC9: =+CC58*CC74/90 -> 141959.06 | CD9: =+CD58*CD74/90 -> 198804.84 | CE9: =+CD9 -> 198804.84
B10: Prepaid Expenses & Other Current Assets | G10: 4377 | H10: =+G10 -> 4377 | L10: 4679 | M10: =+L10 -> 4679 | N10: 4389 | O10: 5502 | P10: 5901 | Q10: 6528 | R10: =+Q10 -> 6528 | S10: 14167 | T10: 12851 | U10: 13300 | V10: 7945 | W10: =+V10 -> 7945 | X10: 7448 | Y10: 7635 | Z10: 9072 | AA10: 9808 | AB10: =+AA10 -> 9808 | AC10: 9043 | AD10: 19055 | AE10: 18299 | AF10: 16524 | AG10: =+AF10 -> 16524 | AH10: 15488 | AI10: 15815 | AJ10: 16623 | AK10: 13974 | AL10: =+AK10 -> 13974 | AM10: 16539 | AN10: 19395 | AO10: 20459 | AP10: =18692 -> 18692 | AQ10: =+AP10 -> 18692 | AR10: 20490 | AS10: 24338 | AT10: =22480 -> 22480 | AU10: =19142 -> 19142 | AV10: =AU10 -> 19142 | AW10: =22099 -> 22099 | AX10: =21979 -> 21979 | AY10: =22899 -> 22899 | AZ10: =32112 -> 32112 | BA10: =+AZ10 -> 32112 | BB10: =26752 -> 26752 | BC10: =34959 -> 34959 | BD10: =38736 -> 38736 | BE10: =30216 -> 30216 | BF10: =+BE10 -> 30216 | BG10: =29183 -> 29183 | BH10: 34017 | BI10: =29836 -> 29836 | BJ10: =26714 -> 26714 | BK10: =+BJ10 -> 26714 | BL10: =36112 -> 36112 | BM10: =31266 -> 31266 | BN10: =35307 -> 35307 | BO10: =39717 -> 39717 | BP10: =+BO10 -> 39717 | BQ10: =39506 -> 39506 | BR10: =44266 -> 44266 | BS10: =49720 -> 49720 | BT10: =40686 -> 40686 | BU10: =+BT10 -> 40686 | BV10: =+(BV59+BV60)*BV78 -> 39379.063 | BW10: =+(BW59+BW60)*BW78 -> 41192.585 | BX10: =+(BX59+BX60)*BX78 -> 53083.714 | BY10: =+(BY59+BY60)*BY78 -> 38888.569 | BZ10: =+BY10 -> 38888.569 | CA10: =+(CA59+CA60)*CA78 -> 38069.306 | CB10: =+(CB59+CB60)*CB78 -> 43709.559 | CC10: =+(CC59+CC60)*CC78 -> 43967.653 | CD10: =+(CD59+CD60)*CD78 -> 43267.735 | CE10: =+CD10 -> 43267.735
D11: ______ | E11: ______ | F11: ______ | G11: ______ | H11: ______ | I11: ______ | J11: ______ | K11: ______ | L11: ______ | M11: ______ | N11: ______ | O11: ______ | P11: ______ | Q11: ______ | R11: ______ | S11: ______ | T11: ______ | U11: ______ | V11: ______ | W11: ______ | X11: ______ | Y11: ______ | Z11: ______ | AA11: ______ | AB11: ______ | AC11: ______ | AD11: ______ | AE11: ______ | AF11: ______ | AG11: ______ | AH11: ______ | AI11: ______ | AJ11: ______ | AK11: ______ | AL11: ______ | AM11: ______ | AN11: ______ | AO11: ______ | AP11: ______ | AQ11: ______ | AR11: ______ | AS11: ______ | AT11: ______ | AU11: ______ | AV11: ______ | AW11: ______ | AX11: ______ | AY11: ______ | AZ11: ______ | BA11: ______ | BB11: ______ | BC11: ______ | BD11: ______ | BE11: ______ | BF11: ______ | BG11: ______ | BH11: ______ | BI11: ______ | BJ11: ______ | BK11: ______ | BL11: ______ | BM11: ______ | BN11: ______ | BO11: ______ | BP11: ______ | BQ11: ______ | BR11: ______ | BS11: ______ | BT11: ______ | BU11: ______ | BV11: ______ | BW11: ______ | BX11: ______ | BY11: ______ | BZ11: ______ | CA11: ______ | CB11: ______ | CC11: ______ | CD11: ______ | CE11: ______
B12: Total Current Assets | D12: =SUM(D7:D10) -> 0 | E12: =SUM(E7:E10) -> 0 | F12: =SUM(F7:F10) -> 0 | G12: =SUM(G7:G10) -> 147354 | H12: =SUM(H7:H10) -> 147354 | I12: =SUM(I7:I10) -> 0 | J12: =SUM(J7:J10) -> 0 | K12: =SUM(K7:K10) -> 0 | ... CE12: =SUM(CE7:CE10) -> 1312071.5
B14: Long-Term Investments | G14: 0 | H14: =+G14 -> 0 | L14: 35608 | M14: =+L14 -> 35608 | N14: 39387 | O14: 34415 | P14: 37896 | Q14: 39448 | R14: =+Q14 -> 39448 | S14: 30891 | T14: 29031 | U14: 25732 | V14: 43277 | W14: =+V14 -> 43277 | X14: 34614 | Y14: 46534 | Z14: 64930 | AA14: 45725 | AB14: =+AA14 -> 45725 | AC14: 63684 | AD14: 45003 | AE14: 40358 | AF14: 67224 | AG14: =+AF14 -> 67224 | AH14: 65363 | AI14: =64215+2500 -> 66715 | AJ14: =64103+2500 -> 66603 | AK14: =76710+2500 -> 79210 | AL14: =+AK14 -> 79210 | AM14: 96322 | AN14: 111521 | AO14: 100951 | AP14: =119508 -> 119508 | AQ14: =+AP14 -> 119508 | AR14: 102777 | AS14: 97483 | AT14: =133260 -> 133260 | AU14: =98458 -> 98458 | AV14: =AU14 -> 98458 | AW14: =101474 -> 101474 | AX14: =110890 -> 110890 | AY14: =136124 -> 136124 | AZ14: =111198 -> 111198 | BA14: =+AZ14 -> 111198 | BB14: =82360 -> 82360 | BC14: =80122 -> 80122 | BD14: =70997 -> 70997 | BE14: =59206 -> 59206 | BF14: =+BE14 -> 59206 | BG14: =44587 -> 44587 | BH14: =38838 -> 38838 | BI14: =33648 -> 33648 | BJ14: =56644 -> 56644 | BK14: =+BJ14 -> 56644 | BL14: =89693 -> 89693 | BM14: =162058 -> 162058 | BN14: =186680 -> 186680 | BO14: =193887 -> 193887 | BP14: =+BO14 -> 193887 | BQ14: =198990 -> 198990 | BR14: =251179 -> 251179 | BS14: =244984 -> 244984 | BT14: =250868 -> 250868 | BU14: =+BT14 -> 250868 | BV14: =+BT14 -> 250868 | BW14: =+BV14 -> 250868 | BX14: =+BW14 -> 250868 | BY14: =+BX14 -> 250868 | BZ14: =+BY14 -> 250868 | CA14: =+BY14 -> 250868 | CB14: =+CA14 -> 250868 | CC14: =+CB14 -> 250868 | CD14: =+CC14 -> 250868 | CE14: =+CD14 -> 250868
B15: Property, Plant, And Equipment, net | G15: 18148 | H15: =+G15 -> 18148 | L15: 23075 | M15: =+L15 -> 23075 | N15: 24169 | O15: 24012 | P15: 24776 | Q15: 26618 | R15: =+Q15 -> 26618 | S15: 28279 | T15: 29238 | U15: 29965 | V15: 31329 | W15: =+V15 -> 31329 | X15: 31786 | Y15: 40025 | Z15: 40670 | AA15: 39401 | AB15: =+AA15 -> 39401 | AC15: 40823 | AD15: 42768 | AE15: 51281 | AF15: 58557 | AG15: =+AF15 -> 58557 | AH15: 60696 | AI15: 64973 | AJ15: 64503 | AK15: 61442 | AL15: =+AK15 -> 61442 | AM15: 60486 | AN15: 59359 | AO15: 58705 | AP15: =60579 -> 60579 | AQ15: =+AP15 -> 60579 | AR15: 61665 | AS15: 63098 | AT15: =67574 -> 67574 | AU15: =64850 -> 64850 | AV15: =AU15 -> 64850 | AW15: =64143 -> 64143 | AX15: =65959 -> 65959 | AY15: =63257 -> 63257 | AZ15: =61854 -> 61854 | BA15: =+AZ15 -> 61854 | BB15: =63377 -> 63377 | BC15: =57830 -> 57830 | BD15: =53935 -> 53935 | BE15: =47428 -> 47428 | BF15: =+BE15 -> 47428 | BG15: =45161 -> 45161 | BH15: =40350 -> 40350 | BI15: =36160 -> 36160 | BJ15: =32599 -> 32599 | BK15: =+BJ15 -> 32599 | BL15: =30191 -> 30191 | BM15: =27758 -> 27758 | BN15: =27343 -> 27343 | BO15: =30349 -> 30349 | BP15: =+BO15 -> 30349 | BQ15: =28250 -> 28250 | BR15: =26162 -> 26162 | BS15: =24792 -> 24792 | BT15: =23166 -> 23166 | BU15: =+BT15 -> 23166 | BV15: =+BV90 -> 21599.495 | BW15: =+BW90 -> 21017.375 | BX15: =+BX90 -> 21654.985 | BY15: =+BY90 -> 22302.762 | BZ15: =+BY15 -> 22302.762 | CA15: =+CA90 -> 20831.044 | CB15: =+CB90 -> 19602.288 | CC15: =+CC90 -> 19185.819 | CD15: =+CD90 -> 18871.569 | CE15: =+CD15 -> 18871.569
B16: Operating Lease ROU Asset | AM16: =29604 -> 29604 | AN16: 28101 | AO16: 27043 | AP16: =40551 -> 40551 | AQ16: =+AP16 -> 40551 | AR16: 38760 | AS16: 42930 | AT16: =47985 -> 47985 | AU16: =44838 -> 44838 | AV16: =AU16 -> 44838 | AW16: =42113 -> 42113 | AX16: =40403 -> 40403 | AY16: =37795 -> 37795 | AZ16: =37016 -> 37016 | BA16: =+AZ16 -> 37016 | BB16: =34569 -> 34569 | BC16: =33451 -> 33451 | BD16: =31454 -> 31454 | BE16: =33752 -> 33752 | BF16: =+BE16 -> 33752 | BG16: =30737 -> 30737 | BH16: =27992 -> 27992 | BI16: =25211 -> 25211 | BJ16: =22391 -> 22391 | BK16: =+BJ16 -> 22391 | BL16: =31371 -> 31371 | BM16: =44100 -> 44100 | BN16: =41294 -> 41294 | BO16: =40968 -> 40968 | BP16: =+BO16 -> 40968 | BQ16: =41329 -> 41329 | BR16: =48678 -> 48678 | BS16: =47959 -> 47959 | BT16: =46001 -> 46001 | BU16: =+BT16 -> 46001 | BV16: =+BU16-1500 -> 44501 | BW16: =+BV16-1500 -> 43001 | BX16: =+BW16-1500 -> 41501 | BY16: =+BX16-1500 -> 40001 | BZ16: =+BY16 -> 40001 | CA16: =+BZ16-1500 -> 38501 | CB16: =+CA16-1500 -> 37001 | CC16: =+CB16-1500 -> 35501 | CD16: =+CC16-1500 -> 34001 | CE16: =+CD16 -> 34001
B17: Deferred Tax Assets, net | G17: 0 | H17: =+G17 -> 0 | L17: 72 | M17: =+L17 -> 72 | N17: 0 | O17: 0 | P17: 0 | Q17: 22639 | R17: =+Q17 -> 22639 | S17: 14415 | T17: 14035 | U17: 13180 | V17: 16079 | W17: =+V17 -> 16079 | X17: 17165 | Y17: 16123 | Z17: 15141 | AA17: 16590 | AB17: =+AA17 -> 16590 | AC17: 37279 | AD17: 35622 | AE17: 32359 | AF17: 25066 | AG17: =+AF17 -> 25066 | AH17: 24085 | AI17: 23570 | AJ17: 28248 | AK17: 26387 | AL17: =+AK17 -> 26387 | AM17: 24653 | AN17: 22976 | AO17: 18302 | AP17: =18830 -> 18830 | AQ17: =+AP17 -> 18830 | AR17: 16930 | AS17: 16971 | AT17: =13581 -> 13581 | AU17: =15811 -> 15811 | AV17: =AU17 -> 15811 | AW17: =20786 -> 20786 | AX17: =16469 -> 16469 | AY17: =31367 -> 31367 | AZ17: =25087 -> 25087 | BA17: =+AZ17 -> 25087 | BB17: =29986 -> 29986 | BC17: =35426 -> 35426 | BD17: =39802 -> 39802 | BE17: =45412 -> 45412 | BF17: =+BE17 -> 45412 | BG17: =49865 -> 49865 | BH17: =54891 -> 54891 | BI17: =57171 -> 57171 | BJ17: =62761 -> 62761 | BK17: =+BJ17 -> 62761 | BL17: =66565 -> 66565 | BM17: =70433 -> 70433 | BN17: =77730 -> 77730 | BO17: =81307 -> 81307 | BP17: =+BO17 -> 81307 | BQ17: =86059 -> 86059 | BR17: =91551 -> 91551 | BS17: =76258 -> 76258 | BT17: =74518 -> 74518 | BU17: =+BT17 -> 74518 | BV17: =+BT17 -> 74518 | BW17: =+BV17 -> 74518 | BX17: =+BW17 -> 74518 | BY17: =+BX17 -> 74518 | BZ17: =+BY17 -> 74518 | CA17: =+BY17 -> 74518 | CB17: =+CA17 -> 74518 | CC17: =+CB17 -> 74518 | CD17: =+CC17 -> 74518 | CE17: =+CD17 -> 74518
B18: Intangible Assets, net | G18: 2811 | H18: =+G18 -> 2811 | L18: 2394 | M18: =+L18 -> 2394 | N18: 2296 | O18: 2198 | P18: 2099 | Q18: 2001 | R18: =+Q18 -> 2001 | S18: 1903 | T18: 1805 | U18: 1708 | V18: 1360 | W18: =+V18 -> 1360 | X18: 1267 | Y18: 1174 | Z18: 1080 | AA18: 987 | AB18: =+AA18 -> 987 | AC18: 894 | AD18: 801 | AE18: 5801 | AF18: 12401 | AG18: =+AF18 -> 12401 | AH18: 11769 | AI18: 14605 | AJ18: 13741 | AK18: 21976 | AL18: =+AK18 -> 21976 | AM18: 21356 | AN18: 19836 | AO18: 18316 | AP18: =16795 -> 16795 | AQ18: =+AP18 -> 16795 | AR18: 15275 | AS18: 13755 | AT18: =13651 -> 13651 | AU18: =12006 -> 12006 | AV18: =AU18 -> 12006 | AW18: =10361 -> 10361 | AX18: =8715 -> 8715 | AY18: =8250 -> 8250 | AZ18: =6545 -> 6545 | BA18: =+AZ18 -> 6545 | BB18: =4839 -> 4839 | BC18: =3365 -> 3365 | BD18: =2019 -> 2019 | BE18: =12801 -> 12801 | BF18: =+BE18 -> 12801 | BG18: =12030 -> 12030 | BH18: =11258 -> 11258 | BI18: =10486 -> 10486 | BJ18: =9715 -> 9715 | BK18: =+BJ18 -> 9715 | BL18: =8943 -> 8943 | BM18: =8172 -> 8172 | BN18: =7451 -> 7451 | BO18: =6812 -> 6812 | BP18: =+BO18 -> 6812 | BQ18: =6172 -> 6172 | BR18: =5533 -> 5533 | BS18: =4894 -> 4894 | BT18: =4255 -> 4255 | BU18: =+BT18 -> 4255 | BV18: =+BV100 -> 3616.75 | BW18: =+BW100 -> 3074.2375 | BX18: =+BX100 -> 2613.1019 | BY18: =+BY100 -> 2221.1366 | BZ18: =+BY18 -> 2221.1366 | CA18: =+CA100 -> 1776.9093 | CB18: =+CB100 -> 1421.5274 | CC18: =+CC100 -> 1137.2219 | CD18: =+CD100 -> 909.77755 | CE18: =+CD18 -> 909.77755
B19: Goodwill | G19: 317 | H19: =+G19 -> 317 | L19: 317 | M19: =+L19 -> 317 | N19: 317 | O19: 317 | P19: 317 | Q19: 317 | R19: =+Q19 -> 317 | S19: 317 | T19: 317 | U19: 317 | V19: 317 | W19: =+V19 -> 317 | X19: 317 | Y19: 317 | Z19: 317 | AA19: 317 | AB19: =+AA19 -> 317 | AC19: 317 | AD19: 317 | AE19: 900 | AF19: 1549 | AG19: =+AF19 -> 1549 | AH19: 1549 | AI19: 1849 | AJ19: 1849 | AK19: 7225 | AL19: =+AK19 -> 7225 | AM19: 7325 | AN19: 7325 | AO19: 7447 | AP19: =7447 -> 7447 | AQ19: =+AP19 -> 7447 | AR19: 7447 | AS19: 7447 | AT19: =7447 -> 7447 | AU19: =7447 -> 7447 | AV19: =AU19 -> 7447 | AW19: =7447 -> 7447 | AX19: =7447 -> 7447 | AY19: =7447 -> 7447 | AZ19: =7447 -> 7447 | BA19: =+AZ19 -> 7447 | BB19: =7447 -> 7447 | BC19: =7447 -> 7447 | BD19: =7447 -> 7447 | BE19: =7447 -> 7447 | BF19: =+BE19 -> 7447 | BG19: =7447 -> 7447 | BH19: =7447 -> 7447 | BI19: =7447 -> 7447 | BJ19: =7447 -> 7447 | BK19: =+BJ19 -> 7447 | BL19: =7447 -> 7447 | BM19: =7447 -> 7447 | BN19: =7447 -> 7447 | BO19: =7447 -> 7447 | BP19: =+BO19 -> 7447 | BQ19: =7447 -> 7447 | BR19: =7447 -> 7447 | BS19: =7447 -> 7447 | BT19: =7447 -> 7447 | BU19: =+BT19 -> 7447 | BV19: =+BT19 -> 7447 | BW19: =+BV19 -> 7447 | BX19: =+BW19 -> 7447 | BY19: =+BX19 -> 7447 | BZ19: =+BY19 -> 7447 | CA19: =+BY19 -> 7447 | CB19: =+CA19 -> 7447 | CC19: =+CB19 -> 7447 | CD19: =+CC19 -> 7447 | CE19: =+CD19 -> 7447
B20: Restricted Cash | G20: 114 | H20: =+G20 -> 114 | L20: 0 | M20: =+L20 -> 0 | N20: 0 | O20: 0 | P20: 0 | Q20: 0 | R20: =+Q20 -> 0 | S20: 0 | T20: 0 | U20: 0 | V20: 0 | W20: =+V20 -> 0 | X20: 0 | Y20: 0 | Z20: 0 | AA20: 1200 | AB20: =+AA20 -> 1200 | AC20: 1200 | AD20: 1200 | AE20: 1200 | AF20: 1200 | AG20: =+AF20 -> 1200 | AH20: 1200 | AI20: 1200 | AJ20: 1200 | AK20: 1200 | AL20: =+AK20 -> 1200 | AM20: 1200 | AN20: 1200 | AO20: 1200 | AP20: =1200 -> 1200 | AQ20: =+AP20 -> 1200 | AR20: 1200 | AS20: 1200 | AT20: =1200 -> 1200 | AU20: =1200 -> 1200 | AV20: =AU20 -> 1200 | AW20: =1200 -> 1200 | AX20: =1200 -> 1200 | AY20: =1200 -> 1200 | AZ20: =1200 -> 1200 | BA20: =+AZ20 -> 1200 | BB20: =1200 -> 1200 | BC20: =1200 -> 1200 | BD20: =1200 -> 1200 | BE20: =2700 -> 2700 | BF20: =+BE20 -> 2700 | BG20: =2700 -> 2700 | BH20: =2700 -> 2700 | BI20: =1200+1500 -> 2700 | BJ20: =1200+1500 -> 2700 | BK20: =+BJ20 -> 2700 | BL20: =1200 -> 1200 | BM20: =1200 -> 1200 | BN20: =1200 -> 1200 | BO20: =1200 -> 1200 | BP20: =+BO20 -> 1200 | BQ20: =1200 -> 1200 | BR20: =1200 -> 1200 | BS20: =1200 -> 1200 | BT20: =1200 -> 1200 | BU20: =+BT20 -> 1200 | BV20: =+BT20 -> 1200 | BW20: =+BV20 -> 1200 | BX20: =+BW20 -> 1200 | BY20: =+BX20 -> 1200 | BZ20: =+BY20 -> 1200 | CA20: =+BY20 -> 1200 | CB20: =+CA20 -> 1200 | CC20: =+CB20 -> 1200 | CD20: =+CC20 -> 1200 | CE20: =+CD20 -> 1200
B21: Other Noncurrent Assets | G21: 1574 | H21: =+G21 -> 1574 | L21: 681 | M21: =+L21 -> 681 | N21: 784 | O21: 721 | P21: 726 | Q21: 2262 | R21: =+Q21 -> 2262 | S21: 2254 | T21: 2106 | U21: 2065 | V21: 1916 | W21: =+V21 -> 1916 | X21: 1942 | Y21: 2276 | Z21: 1939 | AA21: 2096 | AB21: =+AA21 -> 2096 | AC21: 1863 | AD21: 1959 | AE21: 2048 | AF21: 2178 | AG21: =+AF21 -> 2178 | AH21: 7061 | AI21: 7134 | AJ21: 8115 | AK21: 9275 | AL21: =+AK21 -> 9275 | AM21: =2500+10158 -> 12658 | AN21: =13708 -> 13708 | AO21: 14151 | AP21: =15082 -> 15082 | AQ21: =+AP21 -> 15082 | AR21: 15300 | AS21: 16024 | AT21: =16854 -> 16854 | AU21: =16864 -> 16864 | AV21: =AU21 -> 16864 | AW21: =18362 -> 18362 | AX21: =17980 -> 17980 | AY21: =17887 -> 17887 | AZ21: =17814 -> 17814 | BA21: =+AZ21 -> 17814 | BB21: =17588 -> 17588 | BC21: =18430 -> 18430 | BD21: =18044 -> 18044 | BE21: =18857 -> 18857 | BF21: =+BE21 -> 18857 | BG21: =18478 -> 18478 | BH21: =17927 -> 17927 | BI21: =18360 -> 18360 | BJ21: =19863 -> 19863 | BK21: =+BJ21 -> 19863 | BL21: =20961 -> 20961 | BM21: =21373 -> 21373 | BN21: =22561 -> 22561 | BO21: =25876 -> 25876 | BP21: =+BO21 -> 25876 | BQ21: =25078 -> 25078 | BR21: =24783 -> 24783 | BS21: =27743 -> 27743 | BT21: =30010 -> 30010 | BU21: =+BT21 -> 30010 | BV21: =+BT21 -> 30010 | BW21: =+BV21 -> 30010 | BX21: =+BW21 -> 30010 | BY21: =+BX21 -> 30010 | BZ21: =+BY21 -> 30010 | CA21: =+BY21 -> 30010 | CB21: =+CA21 -> 30010 | CC21: =+CB21 -> 30010 | CD21: =+CC21 -> 30010 | CE21: =+CD21 -> 30010
D22: ______ | E22: ______ | F22: ______ | G22: ______ | H22: ______ | I22: ______ | J22: ______ | K22: ______ | L22: ______ | M22: ______ | N22: ______ | O22: ______ | P22: ______ | Q22: ______ | R22: ______ | S22: ______ | T22: ______ | U22: ______ | V22: ______ | W22: ______ | X22: ______ | Y22: ______ | Z22: ______ | AA22: ______ | AB22: ______ | AC22: ______ | AD22: ______ | AE22: ______ | AF22: ______ | AG22: ______ | AH22: ______ | AI22: ______ | AJ22: ______ | AK22: ______ | AL22: ______ | AM22: ______ | AN22: ______ | AO22: ______ | AP22: ______ | AQ22: ______ | AR22: ______ | AS22: ______ | AT22: ______ | AU22: ______ | AV22: ______ | AW22: ______ | AX22: ______ | AY22: ______ | AZ22: ______ | BA22: ______ | BB22: ______ | BC22: ______ | BD22: ______ | BE22: ______ | BF22: ______ | BG22: ______ | BH22: ______ | BI22: ______ | BJ22: ______ | BK22: ______ | BL22: ______ | BM22: ______ | BN22: ______ | BO22: ______ | BP22: ______ | BQ22: ______ | BR22: ______ | BS22: ______ | BT22: ______ | BU22: ______ | BV22: ______ | BW22: ______ | BX22: ______ | BY22: ______ | BZ22: ______ | CA22: ______ | CB22: ______ | CC22: ______ | CD22: ______ | CE22: ______
B23: Total Assets | D23: =SUM(D14:D21)+D12 -> 0 | E23: =SUM(E14:E21)+E12 -> 0 | F23: =SUM(F14:F21)+F12 -> 0 | G23: =SUM(G14:G21)+G12 -> 170318 | H23: =SUM(H14:H21)+H12 -> 170318 | I23: =SUM(I14:I21)+I12 -> 0 | J23: =SUM(J14:J21)+J12 -> 0 | K23: =SUM(K14:K21)+K12 -> 0 | ... CE23: =SUM(CE14:CE21)+CE12 -> 1729896.8
B25: Liabilities and Stock Holders' Equity
B26: Current Liabilities
B27: Accounts Payable | G27: 2031 | H27: =+G27 -> 2031 | L27: 1930 | M27: =+L27 -> 1930 | N27: 2018 | O27: 1735 | P27: 1898 | Q27: 5661 | R27: =+Q27 -> 5661 | S27: 2052 | T27: 1042 | U27: 2055 | V27: 2368 | W27: =+V27 -> 2368 | X27: 4393 | Y27: 5853 | Z27: 1491 | AA27: 2051 | AB27: =+AA27 -> 2051 | AC27: 4338 | AD27: 1924 | AE27: 1398 | AF27: 1144 | AG27: =+AF27 -> 1144 | AH27: 1310 | AI27: 1024 | AJ27: 4723 | AK27: 5588 | AL27: =+AK27 -> 5588 | AM27: 566 | AN27: 963 | AO27: 909 | AP27: =848 -> 848 | AQ27: =+AP27 -> 848 | AR27: 653 | AS27: 1395 | AT27: =2223 -> 2223 | AU27: =731 -> 731 | AV27: =AU27 -> 731 | AW27: =1164 -> 1164 | AX27: =1597 -> 1597 | AY27: =1099 -> 1099 | AZ27: =1296 -> 1296 | BA27: =+AZ27 -> 1296 | BB27: =2477 -> 2477 | BC27: =2132 -> 2132 | BD27: =1308 -> 1308 | BE27: =2808 -> 2808 | BF27: =+BE27 -> 2808 | BG27: =1740 -> 1740 | BH27: =2160 -> 2160 | BI27: =1165 -> 1165 | BJ27: =988 -> 988 | BK27: =+BJ27 -> 988 | BL27: =645 -> 645 | BM27: =1277 -> 1277 | BN27: =1422 -> 1422 | BO27: =1270 -> 1270 | BP27: =+BO27 -> 1270 | BQ27: =1292 -> 1292 | BR27: =1977 -> 1977 | BS27: =1823 -> 1823 | BT27: =1202 -> 1202 | BU27: =+BT27 -> 1202 | BV27: =+BV59*BV108/90 -> 1542.137 | BW27: =+BW59*BW108/90 -> 1889.9942 | BX27: =+BX59*BX108/90 -> 1911.4556 | BY27: =+BY59*BY108/90 -> 1938.0346 | BZ27: =+BY27 -> 1938.0346 | CA27: =+CA59*CA108/90 -> 1644.6891 | CB27: =+CB59*CB108/90 -> 1971.7365 | CC27: =+CC59*CC108/90 -> 2000.3322 | CD27: =+CD59*CD108/90 -> 1988.0484 | CE27: =+CD27 -> 1988.0484
B28: Accrued Liabilities | G28: 7803 | H28: =+G28 -> 7803 | L28: 9037 | M28: =+L28 -> 9037 | N28: 8444 | O28: 8389 | P28: 9101 | Q28: 10353 | R28: =+Q28 -> 10353 | S28: 10547 | T28: 10598 | U28: 11358 | V28: 11786 | W28: =+V28 -> 11786 | X28: 11513 | Y28: 16851 | Z28: 16324 | AA28: 13317 | AB28: =+AA28 -> 13317 | AC28: 13338 | AD28: 13836 | AE28: 14679 | AF28: 21444 | AG28: =+AF28 -> 21444 | AH28: 22181 | AI28: 27454 | AJ28: 23208 | AK28: 25130 | AL28: =+AK28 -> 25130 | AM28: 32017 | AN28: 24315 | AO28: 25595 | AP28: =22784 -> 22784 | AQ28: =+AP28 -> 22784 | AR28: 23753 | AS28: 24810 | AT28: =24772 -> 24772 | AU28: =29833 -> 29833 | AV28: =AU28 -> 29833 | AW28: =27836 -> 27836 | AX28: =30685 -> 30685 | AY28: =33878 -> 33878 | AZ28: =32504 -> 32504 | BA28: =+AZ28 -> 32504 | BB28: =37083 -> 37083 | BC28: =37987 -> 37987 | BD28: =42816 -> 42816 | BE28: =42592 -> 42592 | BF28: =+BE28 -> 42592 | BG28: =41777 -> 41777 | BH28: =52637 -> 52637 | BI28: =49838 -> 49838 | BJ28: =43096 -> 43096 | BK28: =+BJ28 -> 43096 | BL28: =48246 -> 48246 | BM28: =36095 -> 36095 | BN28: =39960 -> 39960 | BO28: =45942 -> 45942 | BP28: =+BO28 -> 45942 | BQ28: =52921 -> 52921 | BR28: =52768 -> 52768 | BS28: =51136 -> 51136 | BT28: =57694 -> 57694 | BU28: =+BT28 -> 57694 | BV28: =+(BV59+BV60)*BV112 -> 59068.594 | BW28: =+(BW59+BW60)*BW112 -> 56639.805 | BX28: =+(BX59+BX60)*BX112 -> 58392.086 | BY28: =+(BY59+BY60)*BY112 -> 66666.118 | BZ28: =+BY28 -> 66666.118 | CA28: =+(CA59+CA60)*CA112 -> 70700.14 | CB28: =+(CB59+CB60)*CB112 -> 54636.948 | CC28: =+(CC59+CC60)*CC112 -> 60455.522 | CD28: =+(CD59+CD60)*CD112 -> 72112.892 | CE28: =+CD28 -> 72112.892
B29: Deferred Revenues, Current | G29: 56497 | H29: =+G29 -> 56497 | L29: 67505 | M29: =+L29 -> 67505 | N29: 71410 | O29: 71853 | P29: 74337 | Q29: 81147 | R29: =+Q29 -> 81147 | S29: 87929 | T29: 87411 | U29: 91939 | V29: 98025 | W29: =+V29 -> 98025 | X29: 101557 | Y29: 103753 | Z29: 109026 | AA29: 114964 | AB29: =+AA29 -> 114964 | AC29: 120044 | AD29: 124738 | AE29: 132167 | AF29: 143186 | AG29: =+AF29 -> 143186 | AH29: 147656 | AI29: 151419 | AJ29: 155115 | AK29: 164624 | AL29: =+AK29 -> 164624 | AM29: 174452 | AN29: 176609 | AO29: 180304 | AP29: =192172 -> 192172 | AQ29: =+AP29 -> 192172 | AR29: 201861 | AS29: 199732 | AT29: =200283 -> 200283 | AU29: =213494 -> 213494 | AV29: =AU29 -> 213494 | AW29: =218898 -> 218898 | AX29: =228180 -> 228180 | AY29: =237539 -> 237539 | AZ29: =257872 -> 257872 | BA29: =+AZ29 -> 257872 | BB29: =266934 -> 266934 | BC29: =275725 -> 275725 | BD29: =278947 -> 278947 | BE29: =293728 -> 293728 | BF29: =+BE29 -> 293728 | BG29: =296516 -> 296516 | BH29: =302446 -> 302446 | BI29: =307179 -> 307179 | BJ29: =333267 -> 333267 | BK29: =+BJ29 -> 333267 | BL29: =332128 -> 332128 | BM29: =324334 -> 324334 | BN29: =337821 -> 337821 | BO29: =371457 -> 371457 | BP29: =+BO29 -> 371457 | BQ29: =366824 -> 366824 | BR29: =354971 -> 354971 | BS29: =371476 -> 371476 | BT29: =401127 -> 401127 | BU29: =+BT29 -> 401127 | BV29: =+BQ29*(1+BV118) -> 396169.92 | BW29: =+BR29*(1+BW118) -> 383368.68 | BX29: =+BS29*(1+BX118) -> 401194.08 | BY29: =+BT29*(1+BY118) -> 431211.52 | BZ29: =+BY29 -> 431211.52 | CA29: =+BV29*(1+CA118) -> 423901.81 | CB29: =+BW29*(1+CB118) -> 410204.49 | CC29: =+BX29*(1+CC118) -> 429277.67 | CD29: =+BY29*(1+CD118) -> 461396.33 | CE29: =+CD29 -> 461396.33
B30: Operating Lease Liabiliy, Current | G30: 1183 | H30: =+G30 -> 1183 | L30: 805 | M30: =+L30 -> 805 | N30: 538 | O30: 270 | P30: 0 | Q30: 0 | R30: =+Q30 -> 0 | S30: 0 | T30: 0 | U30: 0 | V30: 0 | W30: =+V30 -> 0 | X30: 0 | Y30: 0 | Z30: 0 | AA30: 0 | AB30: =+AA30 -> 0 | AC30: 0 | AD30: 0 | AE30: =+AD30 -> 0 | AF30: =+AE30 -> 0 | AG30: =+AF30 -> 0 | AH30: 0 | AI30: 0 | AJ30: 0 | AK30: 1565 | AL30: =+AK30 -> 1565 | AM30: 1153 | AN30: 6826 | AO30: 6937 | AP30: =7663 -> 7663 | AQ30: =+AP30 -> 7663 | AR30: 7968 | AS30: 9161 | AT30: =11777 -> 11777 | AU30: =11672 -> 11672 | AV30: =AU30 -> 11672 | AW30: =11846 -> 11846 | AX30: =12246 -> 12246 | AY30: =12176 -> 12176 | AZ30: =12608 -> 12608 | BA30: =+AZ30 -> 12608 | BB30: =12044 -> 12044 | BC30: =11545 -> 11545 | BD30: =10959 -> 10959 | BE30: =13060 -> 13060 | BF30: =+BE30 -> 13060 | BG30: =12925 -> 12925 | BH30: =11877 -> 11877 | BI30: =12309 -> 12309 | BJ30: =11857 -> 11857 | BK30: =+BJ30 -> 11857 | BL30: =10046 -> 10046 | BM30: =10123 -> 10123 | BN30: =9333 -> 9333 | BO30: =9721 -> 9721 | BP30: =+BO30 -> 9721 | BQ30: =10991 -> 10991 | BR30: =7099 -> 7099 | BS30: =7345 -> 7345 | BT30: =7315 -> 7315 | BU30: =+BT30 -> 7315 | BV30: =+BT30 -> 7315 | BW30: =+BV30 -> 7315 | BX30: =+BW30 -> 7315 | BY30: =+BX30 -> 7315 | BZ30: =+BY30 -> 7315 | CA30: =+BY30 -> 7315 | CB30: =+CA30 -> 7315 | CC30: =+CB30 -> 7315 | CD30: =+CC30 -> 7315 | CE30: =+CD30 -> 7315
D31: ______ | E31: ______ | F31: ______ | G31: ______ | H31: ______ | I31: ______ | J31: ______ | K31: ______ | L31: ______ | M31: ______ | N31: ______ | O31: ______ | P31: ______ | Q31: ______ | R31: ______ | S31: ______ | T31: ______ | U31: ______ | V31: ______ | W31: ______ | X31: ______ | Y31: ______ | Z31: ______ | AA31: ______ | AB31: ______ | AC31: ______ | AD31: ______ | AE31: ______ | AF31: ______ | AG31: ______ | AH31: ______ | AI31: ______ | AJ31: ______ | AK31: ______ | AL31: ______ | AM31: ______ | AN31: ______ | AO31: ______ | AP31: ______ | AQ31: ______ | AR31: ______ | AS31: ______ | AT31: ______ | AU31: ______ | AV31: ______ | AW31: ______ | AX31: ______ | AY31: ______ | AZ31: ______ | BA31: ______ | BB31: ______ | BC31: ______ | BD31: ______ | BE31: ______ | BF31: ______ | BG31: ______ | BH31: ______ | BI31: ______ | BJ31: ______ | BK31: ______ | BL31: ______ | BM31: ______ | BN31: ______ | BO31: ______ | BP31: ______ | BQ31: ______ | BR31: ______ | BS31: ______ | BT31: ______ | BU31: ______ | BV31: ______ | BW31: ______ | BX31: ______ | BY31: ______ | BZ31: ______ | CA31: ______ | CB31: ______ | CC31: ______ | CD31: ______ | CE31: ______
B32: Total Current Liabilities | D32: =SUM(D27:D30) -> 0 | E32: =SUM(E27:E30) -> 0 | F32: =SUM(F27:F30) -> 0 | G32: =SUM(G27:G30) -> 67514 | H32: =SUM(H27:H30) -> 67514 | I32: =SUM(I27:I30) -> 0 | J32: =SUM(J27:J30) -> 0 | K32: =SUM(K27:K30) -> 0 | ... CE32: =SUM(CE27:CE30) -> 542812.27
B35: Deferred Revenue, Net of Current Portion | G35: 8616 | H35: =+G35 -> 8616 | L35: 8889 | M35: =+L35 -> 8889 | N35: 8908 | O35: 8781 | P35: 8965 | Q35: 10064 | R35: =+Q35 -> 10064 | S35: 10064 | T35: 9711 | U35: 9884 | V35: 14564 | W35: =+V35 -> 14564 | X35: 13092 | Y35: 13073 | Z35: 14416 | AA35: 15528 | AB35: =+AA35 -> 15528 | AC35: 18461 | AD35: 16701 | AE35: 16041 | AF35: 17136 | AG35: =+AF35 -> 17136 | AH35: 14995 | AI35: 13327 | AJ35: 17558 | AK35: 20423 | AL35: =+AK35 -> 20423 | AM35: 20450 | AN35: 20835 | AO35: 20156 | AP35: =20935 -> 20935 | AQ35: =+AP35 -> 20935 | AR35: 21823 | AS35: =+AR35*(1+AS125) -> 21823 | AT35: =19157 -> 19157 | AU35: =30540 -> 30540 | AV35: =AU35 -> 30540 | AW35: =29010 -> 29010 | AX35: =28681 -> 28681 | AY35: =27528 -> 27528 | AZ35: =32753 -> 32753 | BA35: =+AZ35 -> 32753 | BB35: =31117 -> 31117 | BC35: =28358 -> 28358 | BD35: =24182 -> 24182 | BE35: =23490 -> 23490 | BF35: =+BE35 -> 23490 | BG35: =21931 -> 21931 | BH35: =34774 -> 34774 | BI35: =32287 -> 32287 | BJ35: =31671 -> 31671 | BK35: =+BJ35 -> 31671 | BL35: =31311 -> 31311 | BM35: =28812 -> 28812 | BN35: =23116 -> 23116 | BO35: =24265 -> 24265 | BP35: =+BO35 -> 24265 | BQ35: =22073 -> 22073 | BR35: =19229 -> 19229 | BS35: =16336 -> 16336 | BT35: =16285 -> 16285 | BU35: =+BT35 -> 16285 | BV35: =+BT35*(1+BV125) -> 16447.85 | BW35: =+BV35*(1+BW125) -> 16612.328 | BX35: =+BW35*(1+BX125) -> 16778.452 | BY35: =+BX35*(1+BY125) -> 16946.236 | BZ35: =+BY35 -> 16946.236 | CA35: =+BY35*(1+CA125) -> 16776.774 | CB35: =+CA35*(1+CB125) -> 16944.542 | CC35: =+CB35*(1+CC125) -> 17113.987 | CD35: =+CC35*(1+CD125) -> 17285.127 | CE35: =+CD35 -> 17285.127
B36: Income Taxes Payable, Noncurrent | G36: 594 | H36: =+G36 -> 594 | L36: 0 | M36: =+L36 -> 0 | N36: 0 | O36: 0 | P36: 0 | Q36: 0 | R36: =+Q36 -> 0 | S36: 0 | T36: 0 | U36: 0 | V36: 0 | W36: =+V36 -> 0 | X36: 0 | Y36: 0 | Z36: 0 | AA36: 0 | AB36: =+AA36 -> 0 | AC36: 0 | AD36: 0 | AE36: 0 | AF36: 0 | AG36: =+AF36 -> 0 | AH36: 0 | AI36: 0 | AJ36: 0 | AK36: 0 | AL36: =+AK36 -> 0 | AM36: 0 | AO36: =+AN36 -> 0 | AP36: =0 -> 0 | AQ36: =+AP36 -> 0 | AR36: 0 | AS36: =+AR36 -> 0 | AT36: =0 -> 0 | AU36: =0 -> 0 | AV36: =AU36 -> 0 | AW36: =0 -> 0 | BA36: =+AZ36 -> 0 | BE36: =+BD36 -> 0 | BF36: =+BE36 -> 0 | BI36: =+BH36 -> 0 | BK36: =+BJ36 -> 0 | BP36: =+BO36 -> 0 | BQ36: =+BO36 -> 0 | BR36: =+BQ36 -> 0 | BS36: =+BR36 -> 0 | BU36: =+BT36 -> 0 | BV36: =+BT36 -> 0 | BW36: =+BV36 -> 0 | BX36: =+BW36 -> 0 | BY36: =+BX36 -> 0 | BZ36: =+BY36 -> 0 | CA36: =+BY36 -> 0 | CB36: =+CA36 -> 0 | CC36: =+CB36 -> 0 | CD36: =+CC36 -> 0 | CE36: =+CD36 -> 0
B37: Operating Lease Liabiliy, Noncurrent | G37: 808 | H37: =+G37 -> 808 | L37: 0 | M37: =+L37 -> 0 | N37: 0 | O37: 0 | P37: 0 | Q37: 0 | R37: =+Q37 -> 0 | S37: 0 | T37: 0 | U37: 0 | V37: 0 | W37: =+V37 -> 0 | X37: 0 | Y37: 0 | Z37: 0 | AA37: 0 | AB37: =+AA37 -> 0 | AC37: 0 | AD37: 0 | AE37: 0 | AF37: 0 | AG37: =+AF37 -> 0 | AH37: 0 | AI37: 0 | AJ37: 0 | AK37: 0 | AL37: =+AK37 -> 0 | AM37: =33589 -> 33589 | AN37: =31987 -> 31987 | AO37: 30696 | AP37: =44015 -> 44015 | AQ37: =+AP37 -> 44015 | AR37: 41486 | AS37: =+AR37 -> 41486 | AT37: =48392 -> 48392 | AU37: =45700 -> 45700 | AV37: =AU37 -> 45700 | AW37: =42692 -> 42692 | AX37: =40422 -> 40422 | AY37: =37320 -> 37320 | AZ37: =35914 -> 35914 | BA37: =+AZ37 -> 35914 | BB37: =33284 -> 33284 | BC37: =31335 -> 31335 | BD37: =28911 -> 28911 | BE37: =29121 -> 29121 | BF37: =+BE37 -> 29121 | BG37: =25913 -> 25913 | BH37: =22872 -> 22872 | BI37: =19655 -> 19655 | BJ37: =16885 -> 16885 | BK37: =+BJ37 -> 16885 | BL37: =27784 -> 27784 | BM37: =40437 -> 40437 | BN37: =38266 -> 38266 | BO37: =37500 -> 37500 | BP37: =+BO37 -> 37500 | BQ37: =37652 -> 37652 | BR37: =48248 -> 48248 | BS37: =47264 -> 47264 | BT37: =44959 -> 44959 | BU37: =+BT37 -> 44959 | BV37: =+BT37 -> 44959 | BW37: =+BV37 -> 44959 | BX37: =+BW37 -> 44959 | BY37: =+BX37 -> 44959 | BZ37: =+BY37 -> 44959 | CA37: =+BY37 -> 44959 | CB37: =+CA37 -> 44959 | CC37: =+CB37 -> 44959 | CD37: =+CC37 -> 44959 | CE37: =+CD37 -> 44959
B38: Convertible Debt
B39: Other Long Term Liabilities | G39: 1231 | H39: =+G39 -> 1231 | L39: 1320 | M39: =+L39 -> 1320 | N39: 1392 | O39: 1423 | P39: 1417 | Q39: 972 | R39: =+Q39 -> 972 | S39: 1042 | T39: 1115 | U39: 1154 | V39: 1205 | W39: =+V39 -> 1205 | X39: 1611 | Y39: 1884 | Z39: 2386 | AA39: 2731 | AB39: =+AA39 -> 2731 | AC39: 872 | AD39: 8685 | AE39: 9401 | AF39: 11071 | AG39: =+AF39 -> 11071 | AH39: 13151 | AI39: 12452 | AJ39: 11256 | AK39: 10361 | AL39: =+AK39 -> 10361 | AM39: 511 | AN39: 479 | AO39: 304 | AP39: =388 -> 388 | AQ39: =+AP39 -> 388 | AR39: 218 | AS39: =+AR39 -> 218 | AT39: =181 -> 181 | AU39: =367 -> 367 | AV39: =AU39 -> 367 | AW39: =1388 -> 1388 | AX39: =2499 -> 2499 | AY39: =3654 -> 3654 | AZ39: =4898 -> 4898 | BA39: =+AZ39 -> 4898 | BB39: =4976 -> 4976 | BC39: =5091 -> 5091 | BD39: =5322 -> 5322 | BE39: =7013 -> 7013 | BF39: =+BE39 -> 7013 | BG39: =7129 -> 7129 | BH39: 5800 | BI39: =6511 -> 6511 | BJ39: =6680 -> 6680 | BK39: =+BJ39 -> 6680 | BL39: =7420 -> 7420 | BM39: =7727 -> 7727 | BN39: =8810 -> 8810 | BO39: =6266 -> 6266 | BP39: =+BO39 -> 6266 | BQ39: =6683 -> 6683 | BR39: =7046 -> 7046 | BS39: =7206 -> 7206 | BT39: =5346 -> 5346 | BU39: =+BT39 -> 5346 | BV39: =+BT39 -> 5346 | BW39: =+BV39 -> 5346 | BX39: =+BW39 -> 5346 | BY39: =+BX39 -> 5346 | BZ39: =+BY39 -> 5346 | CA39: =+BY39 -> 5346 | CB39: =+CA39 -> 5346 | CC39: =+CB39 -> 5346 | CD39: =+CC39 -> 5346 | CE39: =+CD39 -> 5346
D40: ______ | E40: ______ | F40: ______ | G40: ______ | H40: ______ | I40: ______ | J40: ______ | K40: ______ | L40: ______ | M40: ______ | N40: ______ | O40: ______ | P40: ______ | Q40: ______ | R40: ______ | S40: ______ | T40: ______ | U40: ______ | V40: ______ | W40: ______ | X40: ______ | Y40: ______ | Z40: ______ | AA40: ______ | AB40: ______ | AC40: ______ | AD40: ______ | AE40: ______ | AF40: ______ | AG40: ______ | AH40: ______ | AI40: ______ | AJ40: ______ | AK40: ______ | AL40: ______ | AM40: ______ | AN40: ______ | AO40: ______ | AP40: ______ | AQ40: ______ | AR40: ______ | AS40: ______ | AT40: ______ | AU40: ______ | AV40: ______ | AW40: ______ | AX40: ______ | AY40: ______ | AZ40: ______ | BA40: ______ | BB40: ______ | BC40: ______ | BD40: ______ | BE40: ______ | BF40: ______ | BG40: ______ | BH40: ______ | BI40: ______ | BJ40: ______ | BK40: ______ | BL40: ______ | BM40: ______ | BN40: ______ | BO40: ______ | BP40: ______ | BQ40: ______ | BR40: ______ | BS40: ______ | BT40: ______ | BU40: ______ | BV40: ______ | BW40: ______ | BX40: ______ | BY40: ______ | BZ40: ______ | CA40: ______ | CB40: ______ | CC40: ______ | CD40: ______ | CE40: ______
B41: Total Liabilities | D41: =SUM(D32:D39) -> 0 | E41: =SUM(E32:E39) -> 0 | F41: =SUM(F32:F39) -> 0 | G41: =SUM(G32:G39) -> 78763 | H41: =SUM(H32:H39) -> 78763 | I41: =SUM(I32:I39) -> 0 | J41: =SUM(J32:J39) -> 0 | K41: =SUM(K32:K39) -> 0 | ... CE41: =SUM(CE32:CE39) -> 610402.4
B43: Stockholders' Equity | G43: 91555 | H43: =+G43 -> 91555 | L43: 103117 | M43: =+L43 -> 103117 | N43: 106127 | O43: 112121 | P43: 119693 | Q43: 151827 | R43: =+Q43 -> 151827 | S43: 162274 | T43: 172168 | U43: 181898 | V43: 195566 | W43: =+V43 -> 195566 | X43: 210496 | Y43: 227437 | Z43: 241393 | AA43: 258413 | AB43: =+AA43 -> 258413 | AC43: 284468 | AD43: 306062 | AE43: 327641 | AF43: 343544 | AG43: =+AF43 -> 343544 | AH43: 366319 | AI43: 365239 | AJ43: 374140 | AK43: 357989 | AL43: =+AK43 -> 357989 | AM43: 373404 | AN43: 383598 | AO43: 361023 | AP43: =386803 -> 386803 | AQ43: =+AP43 -> 386803 | AR43: 386730 | AS43: =+AS23-AS41 -> 408390 | AT43: =400299 -> 400299 | AU43: =404482 -> 404482 | AV43: =AU43 -> 404482 | AW43: =397108 -> 397108 | AX43: =392995 -> 392995 | AY43: =402986 -> 402986 | AZ43: =+AZ23-AZ41 -> 436714 | BA43: =+AZ43 -> 436714 | BB43: =426635 -> 426635 | BC43: =396838 -> 396838 | BD43: =355186 -> 355186 | BE43: =+BE23-BE41 -> 289129 | BF43: =+BE43 -> 289129 | BG43: =267822 -> 267822 | BH43: =277018 -> 277018 | BI43: =+BI23-BI41 -> 322917 | BJ43: =+BJ23-BJ41 -> 368174 | BK43: =+BJ43 -> 368174 | BL43: =+BL23-BL41 -> 404202 | BM43: =+BM23-BM41 -> 427795 | BN43: =449595 -> 449595 | BO43: =477116 -> 477116 | BP43: =+BO43 -> 477116 | BQ43: =498035 -> 498035 | BR43: =508167 -> 508167 | BS43: =529403 -> 529403 | BT43: =561153 -> 561153 | BU43: =+BT43 -> 561153 | BV43: =+BV23-BV41 -> 628783.42 | BW43: =+BW23-BW41 -> 694625.05 | BX43: =+BX23-BX41 -> 762184.97 | BY43: =+BY23-BY41 -> 829619.94 | BZ43: =+BY43 -> 829619.94 | CA43: =+CA23-CA41 -> 898736.72 | CB43: =+CB23-CB41 -> 969343.08 | CC43: =+CC23-CC41 -> 1042765.6 | CD43: =+CD23-CD41 -> 1119494.4 | CE43: =+CD43 -> 1119494.4
D44: ______ | E44: ______ | F44: ______ | G44: ______ | H44: ______ | I44: ______ | J44: ______ | K44: ______ | L44: ______ | M44: ______ | N44: ______ | O44: ______ | P44: ______ | Q44: ______ | R44: ______ | S44: ______ | T44: ______ | U44: ______ | V44: ______ | W44: ______ | X44: ______ | Y44: ______ | Z44: ______ | AA44: ______ | AB44: ______ | AC44: ______ | AD44: ______ | AE44: ______ | AF44: ______ | AG44: ______ | AH44: ______ | AI44: ______ | AJ44: ______ | AK44: ______ | AL44: ______ | AM44: ______ | AN44: ______ | AO44: ______ | AP44: ______ | AQ44: ______ | AR44: ______ | AS44: ______ | AT44: ______ | AU44: ______ | AV44: ______ | AW44: ______ | AX44: ______ | AY44: ______ | AZ44: ______ | BA44: ______ | BB44: ______ | BC44: ______ | BD44: ______ | BE44: ______ | BF44: ______ | BG44: ______ | BH44: ______ | BI44: ______ | BJ44: ______ | BK44: ______ | BL44: ______ | BM44: ______ | BN44: ______ | BO44: ______ | BP44: ______ | BQ44: ______ | BR44: ______ | BS44: ______ | BT44: ______ | BU44: ______ | BV44: ______ | BW44: ______ | BX44: ______ | BY44: ______ | BZ44: ______ | CA44: ______ | CB44: ______ | CC44: ______ | CD44: ______ | CE44: ______
B45: Total Liabilities and Equity | D45: =+D43+D41 -> 0 | E45: =+E43+E41 -> 0 | F45: =+F43+F41 -> 0 | G45: =+G43+G41 -> 170318 | H45: =+H43+H41 -> 170318 | I45: =+I43+I41 -> 0 | J45: =+J43+J41 -> 0 | K45: =+K43+K41 -> 0 | ... CE45: =+CE43+CE41 -> 1729896.8
B47: Cash and Equivalent Per Share | D47: =+(D7+D8)/D61 -> 0 | E47: =+(E7+E8)/E61 -> 0 | F47: =+(F7+F8)/F61 -> 0 | G47: =+(G7+G8)/G61 -> 3.3775953 | H47: =+(H7+H8)/H61 -> 4.201765 | I47: =+(I7+I8)/I61 -> 0 | J47: =+(J7+J8)/J61 -> 0 | K47: =+(K7+K8)/K61 -> 0 | ... CE47: =+(CE7+CE8)/CE61 -> 30.837121
B48: Debt | D48: =+D30+D37 -> 0 | E48: =+E30+E37 -> 0 | F48: =+F30+F37 -> 0 | G48: =+G30+G37 -> 1991 | H48: =+H30+H37 -> 1991 | I48: =+I30+I37 -> 0 | J48: =+J30+J37 -> 0 | K48: =+K30+K37 -> 0 | ... M48: =+M30+M37 -> 805 | N48: =+N38 -> 0 | O48: =+O38 -> 0 | P48: =+P38 -> 0 | Q48: =+Q38 -> 0 | R48: =+R38 -> 0 | S48: =+S38 -> 0 | T48: =+T38 -> 0 | U48: =+U38 -> 0 | ... CE48: =+CE38 -> 0
B49: Net Cash | D49: =+(D47*D61)-D48 -> 0 | E49: =+(E47*E61)-E48 -> 0 | F49: =+(F47*F61)-F48 -> 0 | G49: =+(G47*G61)-G48 -> 116441 | H49: =+(H47*H61)-H48 -> 116441 | I49: =+(I47*I61)-I48 -> 0 | J49: =+(J47*J61)-J48 -> 0 | K49: =+(K47*K61)-K48 -> 0 | ... CE49: =+(CE47*CE61)-CE48 -> 1069998.9
B50: Net Cash Per Share | D50: =+D49/D61 -> 0 | E50: =+E49/E61 -> 0 | F50: =+F49/F61 -> 0 | G50: =+G49/G61 -> 3.3208134 | H50: =+H49/H61 -> 4.1311278 | I50: =+I49/I61 -> 0 | J50: =+J49/J61 -> 0 | K50: =+K49/K61 -> 0 | ... CE50: =+CE49/CE61 -> 30.837121
B51: Book Value Per Share | D51: =+D43/D61 -> 0 | E51: =+E43/E61 -> 0 | F51: =+F43/F61 -> 0 | G51: =+G43/G61 -> 2.6110826 | H51: =+H43/H61 -> 3.248215 | I51: =+I43/I61 -> 0 | J51: =+J43/J61 -> 0 | K51: =+K43/K61 -> 0 | ... CE51: =+CE43/CE61 -> 32.263571
B52: DSO | L52: =+L9/L58*90 -> 88.58053 | M52: =+((M9+H9)/2)/M58*360 -> 88.574498 | N52: =+N9/N58*90 -> 64.890961 | O52: =+O9/O58*90 -> 78.18649 | P52: =+P9/P58*90 -> 79.335624 | Q52: =+Q9/Q58*90 -> 81.190222 | R52: =+((R9+M9)/2)/R58*360 -> 82.972024 | S52: =+S9/S58*90 -> 92.974155 | T52: =+T9/T58*90 -> 77.981794 | U52: =+U9/U58*90 -> 80.266547 | V52: =+V9/V58*90 -> 85.707054 | W52: =+((W9+R9)/2)/W58*360 -> 82.523192 | X52: =+X9/X58*90 -> 82.538921 | Y52: =+Y9/Y58*90 -> 74.997524 | Z52: =+Z9/Z58*90 -> 73.977681 | AA52: =+AA9/AA58*90 -> 81.038603 | AB52: =+((AB9+W9)/2)/AB58*360 -> 81.257143 | AC52: =+AC9/AC58*90 -> 70.546676 | AD52: =+AD9/AD58*90 -> 75.445915 | AE52: =+AE9/AE58*90 -> 70.12708 | AF52: =+AF9/AF58*90 -> 92.141461 | AG52: =+((AG9+AB9)/2)/AG58*360 -> 86.89795 | AH52: =+AH9/AH58*90 -> 69.186165 | AI52: =+AI9/AI58*90 -> 69.375523 | AJ52: =+AJ9/AJ58*90 -> 73.61467 | AK52: =+AK9/AK58*90 -> 91.971024 | AL52: =+((AL9+AG9)/2)/AL58*360 -> 90.511494 | AM52: =+AM9/AM58*90 -> 81.064863 | AN52: =+AN9/AN58*90 -> 72.046523 | AO52: =+AO9/AO58*90 -> 66.749646 | AP52: =+AP9/AP58*90 -> 82.95214 | AQ52: =+((AQ9+AL9)/2)/AQ58*360 -> 86.113238 | AR52: =+AR9/AR58*90 -> 75.845264 | AS52: =+AS9/AS58*90 -> 76.938197 | AT52: =+AT9/AT58*90 -> 62.17097 | AU52: =+AU9/AU58*90 -> 95.105642 | AV52: =+((AV9+AQ9)/2)/AV58*360 -> 88.379091 | AW52: =+AW9/AW58*90 -> 79.271363 | AX52: =+AX9/AX58*90 -> 77.67106 | AY52: =+AY9/AY58*90 -> 72.274287 | AZ52: =+AZ9/AZ58*90 -> 89.3589 | BA52: =+((BA9+AV9)/2)/BA58*360 -> 91.572043 | BB52: =+BB9/BB58*90 -> 70.855757 | BC52: =+BC9/BC58*90 -> 73.33439 | BD52: =+BD9/BD58*90 -> 70.758675 | BE52: =+BE9/BE58*90 -> 83.772516 | BF52: =+((BF9+BA9)/2)/BF58*360 -> 84.829056 | BG52: =+BG9/BG58*90 -> 70.098942 | BH52: =+BH9/BH58*90 -> 81.933984 | BI52: =+BI9/BI58*90 -> 65.554804 | BJ52: =+BJ9/BJ58*90 -> 91.030919 | BK52: =+((BK9+BF9)/2)/BK58*360 -> 87.010702 | BL52: =+BL9/BL58*90 -> 71.373478 | BM52: =+BM9/BM58*90 -> 66.32165 | BN52: =+BN9/BN58*90 -> 67.246583 | BO52: =+BO9/BO58*90 -> 93.030322 | BP52: =+((BP9+BK9)/2)/BP58*360 -> 92.071313 | BQ52: =+BQ9/BQ58*90 -> 68.422379 | BR52: =+BR9/BR58*90 -> 70.587644 | BS52: =+BS9/BS58*90 -> 68.033223 | BT52: =+BT9/BT58*90 -> 87.79675 | BU52: =+((BU9+BP9)/2)/BU58*360 -> 90.263493 | BV52: =+BV9/BV58*90 -> 68 | BW52: =+BW9/BW58*90 -> 72 | BX52: =+BX9/BX58*90 -> 65 | BY52: =+BY9/BY58*90 -> 92 | BZ52: =+((BZ9+BU9)/2)/BZ58*360 -> 90.570431 | CA52: =+CA9/CA58*90 -> 69 | CB52: =+CB9/CB58*90 -> 71 | CC52: =+CC9/CC58*90 -> 66 | CD52: =+CD9/CD58*90 -> 90 | CE52: =+((CE9+BZ9)/2)/CE58*360 -> 91.369132
B53: Days Payable | L53: =+L27/L59*90 -> 27.136385 | M53: =+((M27+H27)/2)/M59*360 -> 29.427935 | N53: =+N27/N59*90 -> 27.119606 | O53: =+O27/O59*90 -> 22.2531 | P53: =+P27/P59*90 -> 23.574386 | Q53: =+Q27/Q59*90 -> 70.313276 | R53: =+((R27+M27)/2)/R59*360 -> 48.442884 | S53: =+S27/S59*90 -> 24.185437 | T53: =+T27/T59*90 -> 12.003072 | U53: =+U27/U59*90 -> 21.942105 | V53: =+V27/V59*90 -> 24.337102 | W53: =+((W27+R27)/2)/W59*360 -> 44.284357 | X53: =+X27/X59*90 -> 43.750138 | Y53: =+Y27/Y59*90 -> 54.480298 | Z53: =+Z27/Z59*90 -> 12.457297 | AA53: =+AA27/AA59*90 -> 16.574481 | AB53: =+((AB27+W27)/2)/AB59*360 -> 19.58439 | AC53: =+AC27/AC59*90 -> 33.10608 | AD53: =+AD27/AD59*90 -> 14.905742 | AE53: =+AE27/AE59*90 -> 10.389761 | AF53: =+AF27/AF59*90 -> 7.6601443 | AG53: =+((AG27+AB27)/2)/AG59*360 -> 11.746084 | AH53: =+AH27/AH59*90 -> 8.0538288 | AI53: =+AI27/AI59*90 -> 6.227027 | AJ53: =+AJ27/AJ59*90 -> 28.249485 | AK53: =+AK27/AK59*90 -> 32.26949 | AL53: =+((AL27+AG27)/2)/AL59*360 -> 20.17213 | AM53: =+AM27/AM59*90 -> 3.2510052 | AN53: =+AN27/AN59*90 -> 5.5963066 | AO53: =+AO27/AO59*90 -> 5.4409417 | AP53: =+AP27/AP59*90 -> 5.061008 | AQ53: =+((AQ27+AL27)/2)/AQ59*360 -> 18.907168 | AR53: =+AR27/AR59*90 -> 3.5865983 | AS53: =+AS27/AS59*90 -> 7.4674359 | AT53: =+AT27/AT59*90 -> 10.950739 | AU53: =+AU27/AU59*90 -> 3.4994681 | AV53: =+((AV27+AQ27)/2)/AV59*360 -> 4.0447423 | AW53: =+AW27/AW59*90 -> 5.460516 | AX53: =+AX27/AX59*90 -> 7.5290728 | AY53: =+AY27/AY59*90 -> 4.9771046 | AZ53: =+AZ27/AZ59*90 -> 5.5468899 | BA53: =+((BA27+AV27)/2)/BA59*360 -> 4.6082146 | BB53: =+BB27/BB59*90 -> 10.465706 | BC53: =+BC27/BC59*90 -> 8.5721944 | BD53: =+BD27/BD59*90 -> 5.0421896 | BE53: =+BE27/BE59*90 -> 10.066521 | BF53: =+((BF27+BA27)/2)/BF59*360 -> 8.0176259 | BG53: =+BG27/BG59*90 -> 6.3619744 | BH53: =+BH27/BH59*90 -> 8.0337218 | BI53: =+BI27/BI59*90 -> 4.3603926 | BJ53: =+BJ27/BJ59*90 -> 3.6533958 | BK53: =+((BK27+BF27)/2)/BK59*360 -> 7.0297743 | BL53: =+BL27/BL59*90 -> 2.3760796 | BM53: =+BM27/BM59*90 -> 4.828383 | BN53: =+BN27/BN59*90 -> 4.9136144 | BO53: =+BO27/BO59*90 -> 4.3566092 | BP53: =+((BP27+BK27)/2)/BP59*360 -> 4.0435354 | BQ53: =+BQ27/BQ59*90 -> 4.4388456 | BR53: =+BR27/BR59*90 -> 6.7762206 | BS53: =+BS27/BS59*90 -> 6.5662144 | BT53: =+BT27/BT59*90 -> 4.1225563 | BU53: =+((BU27+BP27)/2)/BU59*360 -> 4.2915839 | BV53: =+BV27/BV59*90 -> 5 | BW53: =+BW27/BW59*90 -> 6 | BX53: =+BX27/BX59*90 -> 6 | BY53: =+BY27/BY59*90 -> 6 | BZ53: =+((BZ27+BU27)/2)/BZ59*360 -> 4.9644496 | CA53: =+CA27/CA59*90 -> 5 | CB53: =+CB27/CB59*90 -> 6 | CC53: =+CC27/CC59*90 -> 6 | CD53: =+CD27/CD59*90 -> 6 | CE53: =+((CE27+BZ27)/2)/CE59*360 -> 5.9383056
AB54: =IF(AB45=AB23,"","CHECK") | AC54: =IF(AC45=AC23,"","CHECK") | AD54: =IF(AD45=AD23,"","CHECK") | AE54: =IF(AE45=AE23,"","CHECK") | AF54: =IF(AF45=AF23,"","CHECK") | AG54: =IF(AG45=AG23,"","CHECK") | AH54: =IF(AH45=AH23,"","CHECK") | AI54: =IF(AI45=AI23,"","CHECK") | ... BC54: =IF(BC45=BC23,"","CHECK") | BE54: =IF(BE45=BE23,"","CHECK") | BF54: =IF(BF45=BF23,"","CHECK") | BG54: =IF(BG45=BG23,"","CHECK") | BH54: =IF(BH45=BH23,"","CHECK") | BI54: =IF(BI45=BI23,"","CHECK") | BJ54: =IF(BJ45=BJ23,"","CHECK") | BK54: =IF(BK45=BK23,"","CHECK") | BL54: =IF(BL45=BL23,"","CHECK") | ... CE54: =IF(CE45=CE23,"","CHECK")
B56: Source: Qualys, Inc. Financial Statements,Needham & Co. LLC estimates
B58: Revenues | D58: =+IS!D9 -> 21191 | E58: =+IS!E9 -> 22190 | F58: =+IS!F9 -> 23382 | G58: =+IS!G9 -> 24657 | H58: =+IS!H9 -> 91420 | I58: =+IS!I9 -> 24883 | J58: =+IS!J9 -> 26291 | K58: =+IS!K9 -> 27749 | ... CE58: =+IS!CE9 -> 769345.08
B59: COGS | D59: =+IS!E14 -> 4556 | E59: =+IS!F14 -> 4566 | F59: =+IS!G14 -> 4900 | G59: =+IS!G14 -> 4900 | H59: =+IS!H14 -> 18128 | I59: =+IS!I14 -> 5702 | J59: =+IS!J14 -> 5813 | K59: =+IS!K14 -> 6312 | L59: =+IS!L14 -> 6401 | M59: =+IS!M14 -> 24228 | N59: =+IS!N14 -> 6697 | ... CE59: =+IS!CE14 -> 119006.16
B60: OPEX | D60: =+IS!D37 -> 16539 | E60: =+IS!E37 -> 16968 | F60: =+IS!F37 -> 16068 | G60: =+IS!G37 -> 17260 | H60: =+IS!H37 -> 66835 | I60: =+IS!I37 -> 18505 | J60: =+IS!J37 -> 18377 | K60: =+IS!K37 -> 18321 | ... CE60: =+IS!CE37 -> 319899.22
B61: Shares Outstanding | D61: =+IS!E62 -> 25996 | E61: =+IS!F62 -> 26545 | F61: =+IS!G62 -> 35064 | G61: =+IS!G62 -> 35064 | H61: =+IS!H62 -> 28186.25 | I61: =+IS!I62 -> 35317 | J61: =+IS!J62 -> 35393 | K61: =+IS!K62 -> 36247 | L61: =+IS!L62 -> 36678 | M61: =+IS!M62 -> 35908.75 | N61: =+IS!N62 -> 37082 | ... CE61: =+IS!CE62 -> 34698.404
B63: Operating Cash Flow | H63: =+CF!H27 -> 21952 | M63: =+CF!M27 -> 25146 | N63: =+CF!N27 -> 15075 | O63: =+CF!O27 -> 100 | P63: =+CF!P27 -> 9910 | Q63: =+CF!Q27 -> 16338 | R63: =+CF!R27 -> 41423 | S63: =+CF!S27 -> 10026 | T63: =+CF!T27 -> 15524 | ... CE63: =+CF!CE27 -> 332866.52
AJ64: =+CF!#REF! -> #REF! | AK64: =+CF!#REF! -> #REF! | AL64: =+CF!#REF! -> #REF! | AM64: =+CF!#REF! -> #REF! | AN64: =+CF!#REF! -> #REF! | AO64: =+CF!#REF! -> #REF! | AP64: =+CF!#REF! -> #REF! | AQ64: =+CF!#REF! -> #REF! | AV64: =+CF!#REF! -> #REF! | BA64: =+CF!#REF! -> #REF! | BF64: =+CF!#REF! -> #REF! | BK64: =+CF!#REF! -> #REF! | BP64: =+CF!#REF! -> #REF! | BU64: =+CF!#REF! -> #REF! | BZ64: =+CF!#REF! -> #REF! | CE64: =+CF!#REF! -> #REF!
B65: Free Cash Flow | H65: =+CF!H68 -> 8363 | M65: =+CF!M68 -> 10297 | N65: =+CF!N68 -> 11030 | O65: =+CF!O68 -> -2886 | P65: =+CF!P68 -> 5884 | Q65: =+CF!Q68 -> 12676 | R65: =+CF!R68 -> 26704 | S65: =+CF!S68 -> 3878 | T65: =+CF!T68 -> 11265 | ... CE65: =+CF!CE68 -> 325173.07
AJ66: =+CF!#REF! -> #REF! | AK66: =+CF!#REF! -> #REF! | AL66: =+CF!#REF! -> #REF! | AM66: =+CF!#REF! -> #REF! | AN66: =+CF!#REF! -> #REF! | AO66: =+CF!#REF! -> #REF! | AP66: =+CF!#REF! -> #REF! | AQ66: =+CF!#REF! -> #REF! | AV66: =+CF!#REF! -> #REF! | BA66: =+CF!#REF! -> #REF! | BF66: =+CF!#REF! -> #REF! | BK66: =+CF!#REF! -> #REF! | BP66: =+CF!#REF! -> #REF! | BU66: =+CF!#REF! -> #REF! | BZ66: =+CF!#REF! -> #REF! | CE66: =+CF!#REF! -> #REF!
B68: Drivers
B69: Accounts Receivable | G69: =+G9 -> 24545 | H69: =+H9 -> 24545 | L69: =+L9 -> 28581 | M69: =+M9 -> 28581 | N69: =+N9 -> 21887 | O69: =+O9 -> 28062 | P69: =+P9 -> 30278 | Q69: =+Q9 -> 32993 | R69: =+R9 -> 32993 | S69: =+S9 -> 38732 | ... CE69: =+CE9 -> 198804.84
AV70: =_xll.FDS(+IS!$B$1,"FE_ESTIMATE(RECEIV_NET,MEAN,ANNUAL,"&IS!AV$74&",NOW,,,'')")*1000 -> #NAME? | BA70: =_xll.FDS(+IS!$B$1,"FE_ESTIMATE(RECEIV_NET,MEAN,ANNUAL,"&IS!BA$74&",NOW,,,'')")*1000 -> #NAME? | BF70: =_xll.FDS(+IS!$B$1,"FE_ESTIMATE(RECEIV_NET,MEAN,ANNUAL,"&IS!BF$74&",NOW,,,'')")*1000 -> #NAME? | BI70: =_xll.FDS(+IS!$B$1,"FE_ESTIMATE(RECEIV_NET,MEAN,QUARTERLY,"&IS!BI$74&",NOW,,,'')")*1000 -> #NAME? | BJ70: =_xll.FDS(+IS!$B$1,"FE_ESTIMATE(RECEIV_NET,MEAN,QUARTERLY,"&IS!BJ$74&",NOW,,,'')")*1000 -> #NAME? | BK70: =_xll.FDS(+IS!$B$1,"FE_ESTIMATE(RECEIV_NET,MEAN,ANNUAL,"&IS!BK$74&",NOW,,,'')")*1000 -> #NAME? | BL70: =_xll.FDS(+IS!$B$1,"FE_ESTIMATE(RECEIV_NET,MEAN,QUARTERLY,"&IS!BL$74&",NOW,,,'')")*1000 -> #NAME? | BM70: =_xll.FDS(+IS!$B$1,"FE_ESTIMATE(RECEIV_NET,MEAN,QUARTERLY,"&IS!BM$74&",NOW,,,'')")*1000 -> #NAME? | BN70: =_xll.FDS(+IS!$B$1,"FE_ESTIMATE(RECEIV_NET,MEAN,QUARTERLY,"&IS!BN$74&",NOW,,,'')")*1000 -> #NAME? | BO70: =_xll.FDS(+IS!$B$1,"FE_ESTIMATE(RECEIV_NET,MEAN,QUARTERLY,"&IS!BO$74&",NOW,,,'')")*1000 -> #NAME? | BP70: =_xll.FDS(+IS!$B$1,"FE_ESTIMATE(RECEIV_NET,MEAN,ANNUAL,"&IS!BP$74&",NOW,,,'')")*1000 -> #NAME? | BQ70: =_xll.FDS(+IS!$B$1,"FE_ESTIMATE(RECEIV_NET,MEAN,QUARTERLY,"&IS!BQ$74&",NOW,,,'')")*1000 -> #NAME? | BR70: =_xll.FDS(+IS!$B$1,"FE_ESTIMATE(RECEIV_NET,MEAN,QUARTERLY,"&IS!BR$74&",NOW,,,'')")*1000 -> #NAME? | BS70: =_xll.FDS(+IS!$B$1,"FE_ESTIMATE(RECEIV_NET,MEAN,QUARTERLY,"&IS!BS$74&",NOW,,,'')")*1000 -> #NAME? | BT70: =_xll.FDS(+IS!$B$1,"FE_ESTIMATE(RECEIV_NET,MEAN,QUARTERLY,"&IS!BT$74&",NOW,,,'')")*1000 -> #NAME? | BU70: =_xll.FDS(+IS!$B$1,"FE_ESTIMATE(RECEIV_NET,MEAN,ANNUAL,"&IS!BU$74&",NOW,,,'')")*1000 -> #NAME? | BV70: =_xll.FDS(+IS!$B$1,"FE_ESTIMATE(RECEIV_NET,MEAN,QUARTERLY,"&IS!BV$74&",NOW,,,'')")*1000 -> #NAME? | BW70: =_xll.FDS(+IS!$B$1,"FE_ESTIMATE(RECEIV_NET,MEAN,QUARTERLY,"&IS!BW$74&",NOW,,,'')")*1000 -> #NAME? | BX70: =_xll.FDS(+IS!$B$1,"FE_ESTIMATE(RECEIV_NET,MEAN,QUARTERLY,"&IS!BX$74&",NOW,,,'')")*1000 -> #NAME? | BY70: =_xll.FDS(+IS!$B$1,"FE_ESTIMATE(RECEIV_NET,MEAN,QUARTERLY,"&IS!BY$74&",NOW,,,'')")*1000 -> #NAME? | BZ70: =_xll.FDS(+IS!$B$1,"FE_ESTIMATE(RECEIV_NET,MEAN,ANNUAL,"&IS!BZ$74&",NOW,,,'')")*1000 -> #NAME? | CA70: =_xll.FDS(+IS!$B$1,"FE_ESTIMATE(RECEIV_NET,MEAN,QUARTERLY,"&IS!CA$74&",NOW,,,'')")*1000 -> #NAME? | CB70: =_xll.FDS(+IS!$B$1,"FE_ESTIMATE(RECEIV_NET,MEAN,QUARTERLY,"&IS!CB$74&",NOW,,,'')")*1000 -> #NAME? | CC70: =_xll.FDS(+IS!$B$1,"FE_ESTIMATE(RECEIV_NET,MEAN,QUARTERLY,"&IS!CC$74&",NOW,,,'')")*1000 -> #NAME? | CD70: =_xll.FDS(+IS!$B$1,"FE_ESTIMATE(RECEIV_NET,MEAN,QUARTERLY,"&IS!CD$74&",NOW,,,'')")*1000 -> #NAME? | CE70: =_xll.FDS(+IS!$B$1,"FE_ESTIMATE(RECEIV_NET,MEAN,ANNUAL,"&IS!CE$74&",NOW,,,'')")*1000 -> #NAME?
B71: % of Sales | G71: =+G69/G$58 -> 0.99545768 | H71: =+H69/H$58 -> 0.26848611 | L71: =+L69/L$58 -> 0.98422811 | M71: =+M69/M$58 -> 0.26473204 | N71: =+N69/N$58 -> 0.72101067 | O71: =+O69/O$58 -> 0.86873878 | P71: =+P69/P$58 -> 0.88150693 | Q71: =+Q69/Q$58 -> 0.90211358 | R71: =+R69/R$58 -> 0.24699242 | S71: =+S69/S$58 -> 1.0330462 | ... CE71: =+CE69/CE$58 -> 0.2584079
B72: Yr-Yr Growth | L72: =+L69/G69-1 -> 0.16443267 | M72: =+M69/H69-1 -> 0.16443267 | Q72: =+Q69/L69-1 -> 0.15436829 | R72: =+R69/M69-1 -> 0.15436829 | S72: =+S69/N69-1 -> 0.76963494 | T72: =+T69/O69-1 -> 0.23127361 | U72: =+U69/P69-1 -> 0.25094128 | V72: =+V69/Q69-1 -> 0.28284788 | W72: =+W69/R69-1 -> 0.28284788 | X72: =+X69/S69-1 -> 0.095063513 | ... CE72: =+CE69/BZ69-1 -> 0.036956522
B73: Q-Q Growth | N73: =+N69/L69-1 -> -0.23421154 | O73: =+O69/N69-1 -> 0.28213095 | P73: =+P69/O69-1 -> 0.078967999 | Q73: =+Q69/P69-1 -> 0.089669067 | S73: =+S69/Q69-1 -> 0.17394599 | T73: =+T69/S69-1 -> -0.1079211 | U73: =+U69/T69-1 -> 0.096202825 | V73: =+V69/U69-1 -> 0.11746225 | X73: =+X69/V69-1 -> 0.0021027761 | Y73: =+Y69/X69-1 -> -0.047790824 | Z73: =+Z69/Y69-1 -> 0.037710154 | AA73: =+AA69/Z69-1 -> 0.12202338 | AC73: =+AC69/AA69-1 -> -0.11451599 | AD73: =+AD69/AC69-1 -> 0.11335527 | AE73: =+AE69/AD69-1 -> -0.00010785392 | AF73: =+AF69/AE69-1 -> 0.38956724 | AH73: =+AH69/AF69-1 -> -0.22570329 | AI73: =+AI69/AH69-1 -> 0.053354453 | AJ73: =+AJ69/AI69-1 -> 0.11567526 | AK73: =+AK69/AJ69-1 -> 0.29367706 | AM73: =+AM69/AK69-1 -> -0.10500495 | AN73: =+AN69/AM69-1 -> -0.068947733 | AO73: =+AO69/AN69-1 -> -0.0295961 | AP73: =+AP69/AO69-1 -> 0.27269465 | AR73: =+AR69/AP69-1 -> -0.068406079 | AS73: =+AS69/AR69-1 -> 0.044596677 | AT73: =+AT69/AS69-1 -> -0.15337512 | AU73: =+AU69/AT69-1 -> 0.55821188 | AW73: =+AW69/AU69-1 -> -0.14930275 | AX73: =+AX69/AW69-1 -> 0.0096453967 | AY73: =+AY69/AX69-1 -> -0.020652224 | AZ73: =+AZ69/AY69-1 -> 0.29348381 | BB73: =+BB69/AZ69-1 -> -0.18077396 | BC73: =+BC69/BB69-1 -> 0.094048872 | BD73: =+BD69/BC69-1 -> 0.010492159 | BE73: =+BE69/BD69-1 -> 0.23377939 | BG73: =+BG69/BE69-1 -> -0.16428425 | BH73: =+BH69/BG69-1 -> 0.22720217 | BI73: =+BI69/BH69-1 -> -0.17199308 | BJ73: =+BJ69/BI69-1 -> 0.4137951 | BL73: =+BL69/BJ69-1 -> -0.20924459 | BM73: =+BM69/BL69-1 -> -0.052279273 | BN73: =+BN69/BM69-1 -> 0.049122135 | BO73: =+BO69/BN69-1 -> 0.43128898 | BQ73: =+BQ69/BO69-1 -> -0.26124423 | BR73: =+BR69/BQ69-1 -> 0.058504644 | BS73: =+BS69/BR69-1 -> -0.00199728 | BT73: =+BT69/BS69-1 -> 0.33151895 | BV73: =+BV69/BT69-1 -> -0.23340031 | BW73: =+BW69/BV69-1 -> 0.081383789 | BX73: =+BX69/BW69-1 -> -0.069524521 | BY73: =+BY69/BX69-1 -> 0.45358268 | CA73: =+CA69/BY69-1 -> -0.25072817 | CB73: =+CB69/CA69-1 -> 0.041179363 | CC73: =+CC69/CB69-1 -> -0.050856786 | CD73: =+CD69/CC69-1 -> 0.40043786
B74: DSO | G74: =+G52 -> 0 | H74: =+H52 -> 0 | L74: =+L52 -> 88.58053 | M74: =+M52 -> 88.574498 | N74: =+N52 -> 64.890961 | O74: =+O52 -> 78.18649 | P74: =+P52 -> 79.335624 | Q74: =+Q52 -> 81.190222 | R74: =+R52 -> 82.972024 | S74: =+S52 -> 92.974155 | ... BU74: =+BU52 -> 90.263493 | BV74: 68 | BW74: 72 | BX74: 65 | BY74: 92 | BZ74: =+BZ52 -> 90.570431 | CA74: 69 | CB74: 71 | CC74: 66 | CD74: 90 | CE74: =+CE52 -> 91.369132
B76: Prepaid Expenses & Other Current Assets | G76: =+G10 -> 4377 | H76: =+H10 -> 4377 | L76: =+L10 -> 4679 | M76: =+M10 -> 4679 | N76: =+N10 -> 4389 | O76: =+O10 -> 5502 | P76: =+P10 -> 5901 | Q76: =+Q10 -> 6528 | R76: =+R10 -> 6528 | S76: =+S10 -> 14167 | ... CE76: =+CE10 -> 43267.735
B78: % COGS + OPEX | G78: =+G76/(G$59+G$60) -> 0.19751805 | H78: =+H76/(H$59+H$60) -> 0.051516542 | L78: =+L76/(L$59+L$60) -> 0.17254859 | M78: =+M76/(M$59+M$60) -> 0.04672132 | N78: =+N76/(N$59+N$60) -> 0.15404865 | O78: =+O76/(O$59+O$60) -> 0.19627568 | P78: =+P76/(P$59+P$60) -> 0.20817018 | Q78: =+Q76/(Q$59+Q$60) -> 0.22578079 | R78: =+R76/(R$59+R$60) -> 0.057372367 | S78: =+S76/(S$59+S$60) -> 0.49365809 | ... BJ78: =+BJ76/(BJ$59+BJ$60) -> 0.31874098 | BL78: =+BL76/(BL$59+BL$60) -> 0.44450462 | BM78: =+BM76/(BM$59+BM$60) -> 0.37768624 | BN78: =+BN76/(BN$59+BN$60) -> 0.40187809 | BO78: =+BO76/(BO$59+BO$60) -> 0.44898259 | BP78: =+BP76/(BP$59+BP$60) -> 0.11669835 | BQ78: =+BQ76/(BQ$59+BQ$60) -> 0.44546931 | BR78: =+BR76/(BR$59+BR$60) -> 0.47106523 | BS78: =+BS76/(BS$59+BS$60) -> 0.55342216 | ... BU78: =+BU76/(BU$59+BU$60) -> 0.11066503 | BV78: 0.4 | BW78: 0.4 | BX78: 0.5 | BY78: 0.35 | BZ78: =+BZ76/(BZ$59+BZ$60) -> 0.092877818 | CA78: 0.35 | CB78: 0.4 | CC78: 0.4 | CD78: 0.39 | CE78: =+CE76/(CE$59+CE$60) -> 0.098581008
B79: Yr-Yr Growth | L79: =+L76/G76-1 -> 0.06899703 | M79: =+M76/H76-1 -> 0.06899703 | Q79: =+Q76/L76-1 -> 0.39516991 | R79: =+R76/M76-1 -> 0.39516991 | S79: =+S76/N76-1 -> 2.2278423 | T79: =+T76/O76-1 -> 1.3356961 | U79: =+U76/P76-1 -> 1.2538553 | V79: =+V76/Q76-1 -> 0.21706495 | W79: =+W76/R76-1 -> 0.21706495 | X79: =+X76/S76-1 -> -0.47427119 | ... BJ79: =+BJ76/BE76-1 -> -0.11589886 | BL79: =+BL76/BG76-1 -> 0.23743275 | BM79: =+BM76/BH76-1 -> -0.080871329 | BN79: =+BN76/BI76-1 -> 0.18336908 | BO79: =+BO76/BJ76-1 -> 0.48674852 | BP79: =+BP76/BK76-1 -> 0.48674852 | BQ79: =+BQ76/BL76-1 -> 0.093985379 | BR79: =+BR76/BM76-1 -> 0.41578712 | BS79: =+BS76/BN76-1 -> 0.40821933 | ... CE79: =+CE76/BZ76-1 -> 0.11260806
B80: Q-Q Growth | N80: =+N76/L76-1 -> -0.061979055 | O80: =+O76/N76-1 -> 0.25358852 | P80: =+P76/O76-1 -> 0.072519084 | Q80: =+Q76/P76-1 -> 0.10625318 | S80: =+S76/Q76-1 -> 1.17019 | T80: =+T76/S76-1 -> -0.092891932 | U80: =+U76/T76-1 -> 0.034938915 | V80: =+V76/U76-1 -> -0.40263158 | X80: =+X76/V76-1 -> -0.062555066 | Y80: =+Y76/X76-1 -> 0.025107411 | Z80: =+Z76/Y76-1 -> 0.18821218 | AA80: =+AA76/Z76-1 -> 0.081128748 | AC80: =+AC76/AA76-1 -> -0.077997553 | AD80: =+AD76/AC76-1 -> 1.1071547 | AE80: =+AE76/AD76-1 -> -0.039674626 | AF80: =+AF76/AE76-1 -> -0.096999836 | AH80: =+AH76/AF76-1 -> -0.062696684 | AI80: =+AI76/AH76-1 -> 0.02111312 | AJ80: =+AJ76/AI76-1 -> 0.051090737 | AK80: =+AK76/AJ76-1 -> -0.15935752 | AM80: =+AM76/AK76-1 -> 0.18355517 | AN80: =+AN76/AM76-1 -> 0.17268275 | AO80: =+AO76/AN76-1 -> 0.0548595 | AP80: =+AP76/AO76-1 -> -0.086367858 | AR80: =+AR76/AP76-1 -> 0.096190884 | AS80: =+AS76/AR76-1 -> 0.18779893 | AT80: =+AT76/AS76-1 -> -0.076341524 | AU80: =+AU76/AT76-1 -> -0.14848754 | AW80: =+AW76/AU76-1 -> 0.15447707 | AX80: =+AX76/AW76-1 -> -0.00543011 | AY80: =+AY76/AX76-1 -> 0.041858137 | AZ80: =+AZ76/AY76-1 -> 0.40233198 | BB80: =+BB76/AZ76-1 -> -0.16691579 | BC80: =+BC76/BB76-1 -> 0.3067808 | BD80: =+BD76/BC76-1 -> 0.10804085 | BE80: =+BE76/BD76-1 -> -0.21995043 | BG80: =+BG76/BE76-1 -> -0.034187186 | BH80: =+BH76/BG76-1 -> 0.16564438 | BI80: =+BI76/BH76-1 -> -0.12290913 | BJ80: =+BJ76/BI76-1 -> -0.10463869 | BL80: =+BL76/BJ76-1 -> 0.35180055 | BM80: =+BM76/BL76-1 -> -0.13419362 | BN80: =+BN76/BM76-1 -> 0.12924583 | BO80: =+BO76/BN76-1 -> 0.12490441 | BQ80: =+BQ76/BO76-1 -> -0.0053125865 | BR80: =+BR76/BQ76-1 -> 0.12048803 | BS80: =+BS76/BR76-1 -> 0.12320969 | BT80: =+BT76/BS76-1 -> -0.18169751 | BV80: =+BV76/BT76-1 -> -0.032122535 | BW80: =+BW76/BV76-1 -> 0.046052973 | BX80: =+BX76/BW76-1 -> 0.28867159 | BY80: =+BY76/BX76-1 -> -0.26741055 | CA80: =+CA76/BY76-1 -> -0.021066933 | CB80: =+CB76/CA76-1 -> 0.14815749 | CC80: =+CC76/CB76-1 -> 0.0059047481 | CD80: =+CD76/CC76-1 -> -0.01591892
B82: Beginning PP&E | G82: 16896 | H82: 13861 | I82: =+G15 -> 18148 | J82: =+I90 -> 19787 | K82: =+J90 -> 0 | L82: =+K90 -> 0 | M82: =+H15 -> 18148 | N82: =+L15 -> 23075 | O82: =+N15 -> 24169 | P82: =+O15 -> 24012 | Q82: =+P15 -> 24776 | R82: =+M15 -> 23075 | S82: =+Q15 -> 26618 | T82: =+S15 -> 28279 | U82: =+T15 -> 29238 | V82: =+U15 -> 29965 | W82: =+R15 -> 26618 | X82: =+V15 -> 31329 | Y82: =+X15 -> 31786 | Z82: =+Y15 -> 40025 | AA82: =+Z15 -> 40670 | AB82: =+W15 -> 31329 | AC82: =+AA15 -> 39401 | AD82: =+AC15 -> 40823 | AE82: =+AD15 -> 42768 | AF82: =+AE15 -> 51281 | AG82: =+AB15 -> 39401 | AH82: =+AF15 -> 58557 | AI82: =+AH15 -> 60696 | AJ82: =+AI15 -> 64973 | AK82: =+AJ15 -> 64503 | AL82: =+AG15 -> 58557 | AM82: =+AK15 -> 61442 | AN82: =+AM15 -> 60486 | AO82: =+AN15 -> 59359 | AP82: =+AO15 -> 58705 | AQ82: =+AL15 -> 61442 | AR82: =+AP15 -> 60579 | AS82: =+AR15 -> 61665 | AT82: =+AS15 -> 63098 | AU82: =+AT15 -> 67574 | AV82: =+AQ15 -> 60579 | AW82: =+AU15 -> 64850 | AX82: =+AV15 -> 64850 | AY82: =+AW15 -> 64143 | AZ82: =+AX15 -> 65959 | BA82: =+AV15 -> 64850 | BB82: =+AZ15 -> 61854 | BC82: =+BA15 -> 61854 | BD82: =+BB15 -> 63377 | BE82: =+BC15 -> 57830 | BF82: =+BA15 -> 61854 | BG82: =+BE15 -> 47428 | BH82: =+BF15 -> 47428 | BI82: =+BH15 -> 40350 | BJ82: =+BI15 -> 36160 | BK82: =+BF15 -> 47428 | BL82: =+BJ15 -> 32599 | BM82: =+BL15 -> 30191 | BN82: =+BM15 -> 27758 | BO82: =+BN15 -> 27343 | BP82: =+BK15 -> 32599 | BQ82: =+BO15 -> 30349 | BR82: =+BQ15 -> 28250 | BS82: =+BR15 -> 26162 | BT82: =+BS15 -> 24792 | BU82: =+BP15 -> 30349 | BV82: =+BT15 -> 23166 | BW82: =+BV15 -> 21599.495 | BX82: =+BW15 -> 21017.375 | BY82: =+BX15 -> 21654.985 | BZ82: =+BU15 -> 23166 | CA82: =+BY15 -> 22302.762 | CB82: =+CA15 -> 20831.044 | CC82: =+CB15 -> 19602.288 | CD82: =+CC15 -> 19185.819 | CE82: =+BZ15 -> 22302.762
B83: CapEx | D83: 2927 | E83: =5989-D83 -> 3062 | F83: 8104 | G83: =+H83-SUM(D83:F83) -> -2905 | H83: =+CF!H32*-1 -> 11188 | I83: 3650 | J83: =6238-I83 -> 2588 | L83: =+CF!L32*-1 -> 0 | M83: =+CF!M32*-1 -> 13663 | N83: =+CF!N32*-1 -> 3778 | O83: =+CF!O32*-1 -> 2717 | P83: =+CF!P32*-1 -> 3757 | Q83: =+CF!Q32*-1 -> 3662 | R83: =+CF!R32*-1 -> 13914 | S83: =+CF!S32*-1 -> 6148 | ... AU83: =+CF!AU32*-1 -> 7295 | AV83: =+SUM(AR83:AU83) -> 30037 | AW83: =+CF!AW32*-1 -> 6259 | AX83: =+CF!AX32*-1 -> 6652 | AY83: =+CF!AY32*-1 -> 7178 | AZ83: =+CF!AZ32*-1 -> 4335 | BA83: =+SUM(AW83:AZ83) -> 24424 | BB83: =+CF!BB32*-1 -> 7639 | BC83: =+CF!BC32*-1 -> 3511 | BD83: =+CF!BD32*-1 -> 1241 | BE83: =+CF!BE32*-1 -> 2970 | BF83: =+SUM(BB83:BE83) -> 15361 | BG83: =+CF!BG32*-1 -> 4037 | BH83: =+CF!BH32*-1 -> 1418 | BI83: =+CF!BI32*-1 -> 1808 | BJ83: =+CF!BJ32*-1 -> 1523 | BK83: =+SUM(BG83:BJ83) -> 8786 | BL83: =+CF!BL32*-1 -> 2051 | BM83: =+CF!BM32*-1 -> 1026 | BN83: =+CF!BN32*-1 -> 3420 | BO83: =+CF!BO32*-1 -> 5837 | BP83: =+SUM(BL83:BO83) -> 12334 | BQ83: =+CF!BQ32*-1 -> 2038 | BR83: =+CF!BR32*-1 -> 1327 | BS83: =+CF!BS32*-1 -> 901 | BT83: =+CF!BT32*-1 -> 724 | BU83: =+SUM(BQ83:BT83) -> 4990 | BV83: =+BV85*BV$58 -> 1908.3946 | BW83: =+BW85*BW$58 -> 2657.8044 | BX83: =+BX85*BX$58 -> 2739.3472 | BY83: =+BY85*BY$58 -> 2813.2761 | BZ83: =+SUM(BV83:BY83) -> 10118.822 | CA83: =+CA85*CA$58 -> 1873.6965 | CB83: =+CB85*CB$58 -> 1895.9005 | CC83: =+CC85*CC$58 -> 1935.8054 | CD83: =+CD85*CD$58 -> 1988.0484 | CE83: =+SUM(CA83:CD83) -> 7693.4508
AV84: =_xll.FDS(+IS!$B$1,"FE_ESTIMATE(CAPEX,MEAN,ANNUAL,"&IS!AV$74&",NOW,,,'')")*1000*-1 -> #NAME?
B85: CapEx (as a % of Sales) | G85: =+G83/G$58 -> -0.11781644 | H85: =+H83/H$58 -> 0.12238022 | I85: =+I83/I$58 -> 0.14668649 | J85: =+J83/J$58 -> 0.098436727 | L85: =+L83/L$58 -> 0 | M85: =+M83/M$58 -> 0.12655379 | N85: =+N83/N$58 -> 0.12445645 | O85: =+O83/O$58 -> 0.084112439 | P85: =+P83/P$58 -> 0.10938046 | Q85: =+Q83/Q$58 -> 0.10012851 | R85: =+R83/R$58 -> 0.10416308 | S85: =+S83/S$58 -> 0.16397728 | ... BU85: =+BU83/BU$58 -> 0.0074575005 | BV85: 0.011 | BW85: 0.015 | BX85: 0.015 | BY85: 0.015 | BZ85: =+BZ83/BZ$58 -> 0.014037304 | CA85: 0.01 | CB85: 0.01 | CC85: 0.01 | CD85: 0.01 | CE85: =+CE83/CE$58 -> 0.01
B86: Depreciation and Amortization of PP&E | D86: 1600 | G86: =+'Billings & Recs'!G78 -> 1829 | H86: =+'Billings & Recs'!H78 -> 6895 | I86: 2119 | J86: 2000 | K86: =+'Billings & Recs'!K78 -> -24 | L86: =+'Billings & Recs'!L78 -> 4940 | M86: =+'Billings & Recs'!M78 -> 9195 | N86: =+'Billings & Recs'!N78 -> 2707 | O86: =+'Billings & Recs'!O78 -> 2879 | P86: =+'Billings & Recs'!P78 -> 2946 | Q86: =+'Billings & Recs'!Q78 -> 2972 | R86: =+'Billings & Recs'!R78 -> 11504 | ... AU86: =+'Billings & Recs'!AU78 -> 7225 | AV86: =+SUM(AR86:AU86) -> 26526 | AW86: =+'Billings & Recs'!AW78 -> 7433 | AX86: =+'Billings & Recs'!AX78 -> 7145 | AY86: =+'Billings & Recs'!AY78 -> 7218 | AZ86: =+'Billings & Recs'!AZ78 -> 7440 | BA86: =+SUM(AW86:AZ86) -> 29236 | BB86: =+'Billings & Recs'!BB78 -> 7276 | BC86: =+'Billings & Recs'!BC78 -> 7097 | BD86: =+'Billings & Recs'!BD78 -> 6875 | BE86: =+'Billings & Recs'!BE78 -> 7688 | BF86: =+SUM(BB86:BE86) -> 28936 | BG86: =+'Billings & Recs'!BG78 -> 6672 | BH86: =+'Billings & Recs'!BH78 -> 6230 | BI86: =+'Billings & Recs'!BI78 -> 5922 | BJ86: =+'Billings & Recs'!BJ78 -> 5080 | BK86: =+SUM(BG86:BJ86) -> 23904 | BL86: =+'Billings & Recs'!BL78 -> 4467 | BM86: =+'Billings & Recs'!BM78 -> 4009 | BN86: =+'Billings & Recs'!BN78 -> 3670 | BO86: =+'Billings & Recs'!BO78 -> 3464 | BP86: =+SUM(BL86:BO86) -> 15610 | BQ86: =+'Billings & Recs'!BQ78 -> 3537 | BR86: =+'Billings & Recs'!BR78 -> 3339 | BS86: =+'Billings & Recs'!BS78 -> 2559 | BT86: =+'Billings & Recs'!BT78 -> 2499 | BU86: =+SUM(BQ86:BT86) -> 11934 | BV86: =+BV87*BV82 -> 3474.9 | BW86: =+BW87*BW82 -> 3239.9242 | BX86: =+BX87*BX82 -> 2101.7375 | BY86: =+BY87*BY82 -> 2165.4985 | BZ86: =+SUM(BV86:BY86) -> 10982.06 | CA86: =+CA87*CA82 -> 3345.4143 | CB86: =+CB87*CB82 -> 3124.6567 | CC86: =+CC87*CC82 -> 2352.2746 | CD86: =+CD87*CD82 -> 2302.2983 | CE86: =+SUM(CA86:CD86) -> 11124.644
B87: Depreciation and Amortization of PP&E (as a % of PP&E) | G87: =+G86/G82 -> 0.10825047 | H87: =+H86/H82 -> 0.49743886 | I87: =+I86/I82 -> 0.11676218 | J87: =+J86/J82 -> 0.10107646 | K87: =+K86/K82 -> #DIV/0! | L87: =+L86/L82 -> #DIV/0! | M87: =+M86/M82 -> 0.5066674 | N87: =+N86/N82 -> 0.11731311 | ... BU87: =+BU86/BU82 -> 0.39322548 | BV87: 0.15 | BW87: 0.15 | BX87: 0.1 | BY87: 0.1 | BZ87: =+BZ86/BZ82 -> 0.4740594 | CA87: 0.15 | CB87: 0.15 | CC87: 0.12 | CD87: 0.12 | CE87: =+CE86/CE82 -> 0.49880117
B88: Acquisitions/(Write-offs) | G88: =+(G82+G83-G86-G90)*-1 -> 5986 | H88: =+(H82+H83-H86-H90)*-1 -> -6 | I88: =+(I82+I83-I86-I90)*-1 -> 108 | J88: =+(J82+J83-J86-J90)*-1 -> -20375 | K88: =+(K82+K83-K86-K90)*-1 -> -24 | L88: =+(L82+L83-L86-L90)*-1 -> 28015 | M88: =+(M82+M83-M86-M90)*-1 -> 459 | N88: =+(N82+N83-N86-N90)*-1 -> 23 | ... CE88: =+(CE82+CE83-CE86-CE90)*-1 -> 0
D89: ______ | E89: ______ | F89: ______ | G89: ______ | H89: ______ | I89: ______ | J89: ______ | K89: ______ | L89: ______ | M89: ______ | N89: ______ | O89: ______ | P89: ______ | Q89: ______ | R89: ______ | S89: ______ | T89: ______ | U89: ______ | V89: ______ | W89: ______ | X89: ______ | Y89: ______ | Z89: ______ | AA89: ______ | AB89: ______ | AC89: ______ | AD89: ______ | AE89: ______ | AF89: ______ | AG89: ______ | AH89: ______ | AI89: ______ | AJ89: ______ | AK89: ______ | AL89: ______ | AM89: ______ | AN89: ______ | AO89: ______ | AP89: ______ | AQ89: ______ | AR89: ______ | AS89: ______ | AT89: ______ | AU89: ______ | AV89: ______ | AW89: ______ | AX89: ______ | AY89: ______ | AZ89: ______ | BA89: ______ | BB89: ______ | BC89: ______ | BD89: ______ | BE89: ______ | BF89: ______ | BG89: ______ | BH89: ______ | BI89: ______ | BJ89: ______ | BK89: ______ | BL89: ______ | BM89: ______ | BN89: ______ | BO89: ______ | BP89: ______ | BQ89: ______ | BR89: ______ | BS89: ______ | BT89: ______ | BU89: ______ | BV89: ______ | BW89: ______ | BX89: ______ | BY89: ______ | BZ89: ______ | CA89: ______ | CB89: ______ | CC89: ______ | CD89: ______ | CE89: ______
B90: Ending PP&E | G90: =+G15 -> 18148 | H90: =+H15 -> 18148 | I90: 19787 | J90: =+J15 -> 0 | K90: =+K15 -> 0 | L90: =+L15 -> 23075 | M90: =+M15 -> 23075 | N90: =+N15 -> 24169 | O90: =+O15 -> 24012 | P90: =+P15 -> 24776 | Q90: =+Q15 -> 26618 | ... AU90: =+AU15 -> 64850 | AV90: =+AV82+AV83-AV86 -> 64090 | AW90: =+AW82+AW83-AW86 -> 63676 | AX90: =+AX82+AX83-AX86 -> 64357 | AY90: =+AY82+AY83-AY86 -> 64103 | AZ90: =+AZ82+AZ83-AZ86 -> 62854 | BA90: =+BA82+BA83-BA86 -> 60038 | BB90: =+BB82+BB83-BB86 -> 62217 | BC90: =+BC82+BC83-BC86 -> 58268 | ... CE90: =+CE82+CE83-CE86 -> 18871.569
B93: Beginning Intangibles | J93: 2704 | L93: =+K18 -> 0 | M93: =+H18 -> 2811 | N93: =+L18 -> 2394 | O93: =+N18 -> 2296 | P93: =+O18 -> 2198 | Q93: =+P18 -> 2099 | R93: =+M18 -> 2394 | S93: =+Q18 -> 2001 | T93: =+S18 -> 1903 | U93: =+T18 -> 1805 | V93: =+U18 -> 1708 | W93: =+R18 -> 2001 | X93: =+V18 -> 1360 | Y93: =+X18 -> 1267 | Z93: =+Y18 -> 1174 | AA93: =+Z18 -> 1080 | AB93: =+W18 -> 1360 | AC93: =+AA18 -> 987 | AD93: =+AC18 -> 894 | AE93: =+AD18 -> 801 | AF93: =+AE18 -> 5801 | AG93: =+AB18 -> 987 | AH93: =+AF18 -> 12401 | AI93: =+AH18 -> 11769 | AJ93: =+AI18 -> 14605 | AK93: =+AJ18 -> 13741 | AL93: =+AG18 -> 12401 | AM93: =+AK18 -> 21976 | AN93: =+AM18 -> 21356 | AO93: =+AN18 -> 19836 | AP93: =+AO18 -> 18316 | AQ93: =+AL18 -> 21976 | AR93: =+AP18 -> 16795 | AS93: =+AR18 -> 15275 | AT93: =+AS18 -> 13755 | AU93: =+AT18 -> 13651 | AV93: =+AQ18 -> 16795 | AW93: =+AU18 -> 12006 | AX93: =+AV18 -> 12006 | AY93: =+AX18 -> 8715 | AZ93: =+AY18 -> 8250 | BA93: =+AV18 -> 12006 | BB93: =+AZ18 -> 6545 | BC93: =+BA18 -> 6545 | BD93: =+BB18 -> 4839 | BE93: =+BD18 -> 2019 | BF93: =+BA18 -> 6545 | BG93: =+BE18 -> 12801 | BH93: =+BF18 -> 12801 | BI93: =+BH18 -> 11258 | BJ93: =+BI18 -> 10486 | BK93: =+BF18 -> 12801 | BL93: =+BJ18 -> 9715 | BM93: =+BL18 -> 8943 | BN93: =+BM18 -> 8172 | BO93: =+BN18 -> 7451 | BP93: =+BK18 -> 9715 | BQ93: =+BO18 -> 6812 | BR93: =+BQ18 -> 6172 | BS93: =+BR18 -> 5533 | BT93: =+BS18 -> 4894 | BU93: =+BP18 -> 6812 | BV93: =+BT18 -> 4255 | BW93: =+BV18 -> 3616.75 | BX93: =+BW18 -> 3074.2375 | BY93: =+BX18 -> 2613.1019 | BZ93: =+BU18 -> 4255 | CA93: =+BY18 -> 2221.1366 | CB93: =+CA18 -> 1776.9093 | CC93: =+CB18 -> 1421.5274 | CD93: =+CC18 -> 1137.2219 | CE93: =+BZ18 -> 2221.1366
B94: Purchases of Intangibles | G94: =+CF!G35*-1 -> 0 | H94: =+CF!H35*-1 -> 49 | K94: =+CF!K35*-1 -> 0 | L94: =+CF!L35*-1 -> 0 | M94: =+CF!M35*-1 -> 0 | N94: =+CF!N35*-1 -> 0 | O94: =+CF!O35*-1 -> 0 | P94: =+CF!P35*-1 -> 0 | Q94: =+CF!Q35*-1 -> 0 | R94: =+CF!R35*-1 -> 0 | ... AU94: =+CF!AU35*-1 -> -419 | AV94: =+SUM(AR94:AU94) -> -419 | AW94: =+CF!AW35*-1 -> 0 | AX94: =+CF!AX35*-1 -> -6 | AY94: =+CF!AY35*-1 -> 0 | AZ94: =+CF!AZ35*-1 -> 1236 | BA94: =+SUM(AW94:AZ94) -> 1230 | BB94: =+CF!BB35*-1 -> 0 | BC94: =+CF!BC35*-1 -> 0 | BD94: =+CF!BD35*-1 -> 120 | BE94: =+CF!BE35*-1 -> 8500 | BF94: =+SUM(BB94:BE94) -> 8620 | BG94: =+CF!BG35*-1 -> 0 | BH94: =+CF!BH35*-1 -> 0 | BI94: =+CF!BI35*-1 -> 0 | BJ94: =+CF!BJ35*-1 -> 0 | BK94: =+SUM(BG94:BJ94) -> 0 | BL94: =+CF!BL35*-1 -> 0 | BM94: =+CF!BM35*-1 -> 0 | BN94: =+CF!BN35*-1 -> 0 | BO94: =+CF!BO35*-1 -> 0 | BP94: =+SUM(BL94:BO94) -> 0 | BQ94: =+CF!BQ35*-1 -> 0 | BR94: =+CF!BR35*-1 -> 0 | BS94: =+CF!BS35*-1 -> 0 | BT94: =+CF!BT35*-1 -> 0 | BU94: =+SUM(BQ94:BT94) -> 0 | BV94: =+BV95*BV$58 -> 0 | BW94: =+BW95*BW$58 -> 0 | BX94: =+BX95*BX$58 -> 0 | BY94: =+BY95*BY$58 -> 0 | BZ94: =+SUM(BV94:BY94) -> 0 | CA94: =+CA95*CA$58 -> 0 | CB94: =+CB95*CB$58 -> 0 | CC94: =+CC95*CC$58 -> 0 | CD94: =+CD95*CD$58 -> 0 | CE94: =+SUM(CA94:CD94) -> 0
B95: Purchases of Intangibles (as a % of Sales) | G95: =+G94/G$58 -> 0 | H95: =+H94/H$58 -> 0.00053598775 | K95: =+K94/K$58 -> 0 | L95: =+L94/L$58 -> 0 | M95: =+M94/M$58 -> 0 | N95: =+N94/N$58 -> 0 | O95: =+O94/O$58 -> 0 | P95: =+P94/P$58 -> 0 | Q95: =+Q94/Q$58 -> 0 | R95: =+R94/R$58 -> 0 | ... BU95: =+BU94/BU$58 -> 0 | BV95: 0 | BW95: 0 | BX95: 0 | BY95: 0 | BZ95: =+BZ94/BZ$58 -> 0 | CA95: 0 | CB95: 0 | CC95: 0 | CD95: 0 | CE95: =+CE94/CE$58 -> 0
B96: Amortization of Intangibles | G96: =+'Billings & Recs'!G79 -> 115 | H96: =+'Billings & Recs'!H79 -> 446 | K96: =+'Billings & Recs'!K79 -> 210 | L96: =+'Billings & Recs'!L79 -> -7 | M96: =+'Billings & Recs'!M79 -> 417 | N96: =+'Billings & Recs'!N79 -> 98 | O96: =+'Billings & Recs'!O79 -> 98 | P96: =+'Billings & Recs'!P79 -> 98 | Q96: =+'Billings & Recs'!Q79 -> 99 | R96: =+'Billings & Recs'!R79 -> 393 | ... AU96: =+'Billings & Recs'!AU79 -> 1645 | AV96: =+SUM(AR96:AU96) -> 6289 | AW96: =+'Billings & Recs'!AW79 -> 1645 | AX96: =+'Billings & Recs'!AX79 -> 1646 | AY96: =+'Billings & Recs'!AY79 -> 1665 | AZ96: =+'Billings & Recs'!AZ79 -> 1705 | BA96: =+SUM(AW96:AZ96) -> 6661 | BB96: =+'Billings & Recs'!BB79 -> 1706 | BC96: =+'Billings & Recs'!BC79 -> 1474 | BD96: =+'Billings & Recs'!BD79 -> 1346 | BE96: =+'Billings & Recs'!BE79 -> 1161 | BF96: =+SUM(BB96:BE96) -> 5687 | BG96: =+'Billings & Recs'!BG79 -> 772 | BH96: =+'Billings & Recs'!BH79 -> 772 | BI96: =+'Billings & Recs'!BI79 -> 772 | BJ96: =+'Billings & Recs'!BJ79 -> 771 | BK96: =+SUM(BG96:BJ96) -> 3087 | BL96: =+'Billings & Recs'!BL79 -> 772 | BM96: =+'Billings & Recs'!BM79 -> 771 | BN96: =+'Billings & Recs'!BN79 -> 721 | BO96: =+'Billings & Recs'!BO79 -> 639 | BP96: =+SUM(BL96:BO96) -> 2903 | BQ96: =+'Billings & Recs'!BQ79 -> 640 | BR96: =+'Billings & Recs'!BR79 -> 639 | BS96: =+'Billings & Recs'!BS79 -> 639 | BT96: =+'Billings & Recs'!BT79 -> 639 | BU96: =+SUM(BQ96:BT96) -> 2557 | BV96: =BV93*BV97 -> 638.25 | BW96: =BW93*BW97 -> 542.5125 | BX96: =BX93*BX97 -> 461.13563 | BY96: =BY93*BY97 -> 391.96528 | BZ96: =+SUM(BV96:BY96) -> 2033.8634 | CA96: =CA93*CA97 -> 444.22732 | CB96: =CB93*CB97 -> 355.38186 | CC96: =CC93*CC97 -> 284.30548 | CD96: =CD93*CD97 -> 227.44439 | CE96: =+SUM(CA96:CD96) -> 1311.359
B97: Amortization (as a % of Intangibles) | G97: =+G96/G93 -> #DIV/0! | H97: =+H96/H93 -> #DIV/0! | K97: =+K96/K93 -> #DIV/0! | L97: =+L96/L93 -> #DIV/0! | M97: =+M96/M93 -> 0.14834578 | N97: =+N96/N93 -> 0.040935673 | O97: =+O96/O93 -> 0.042682927 | P97: =+P96/P93 -> 0.044585987 | Q97: =+Q96/Q93 -> 0.047165317 | R97: =+R96/R93 -> 0.1641604 | ... BU97: =+BU96/BU93 -> 0.375367 | BV97: 0.15 | BW97: 0.15 | BX97: 0.15 | BY97: 0.15 | BZ97: =+BZ96/BZ93 -> 0.47799375 | CA97: 0.2 | CB97: 0.2 | CC97: 0.2 | CD97: 0.2 | CE97: =+CE96/CE93 -> 0.5904
B98: Acquisitions/(Write-offs) | G98: =+(G93+G94-G96-G100)*-1 -> 2926 | H98: =+(H93+H94-H96-H100)*-1 -> 3208 | K98: =+(K93+K94-K96-K100)*-1 -> 210 | L98: =+(L93+L94-L96-L100)*-1 -> 2387 | M98: =+(M93+M94-M96-M100)*-1 -> 0 | N98: =+(N93+N94-N96-N100)*-1 -> 0 | O98: =+(O93+O94-O96-O100)*-1 -> 0 | P98: =+(P93+P94-P96-P100)*-1 -> -1 | Q98: =+(Q93+Q94-Q96-Q100)*-1 -> 1 | R98: =+(R93+R94-R96-R100)*-1 -> 0 | ... CE98: =+(CE93+CE94-CE96-CE100)*-1 -> 0
D99: ______ | E99: ______ | F99: ______ | G99: ______ | H99: ______ | I99: ______ | J99: ______ | K99: ______ | L99: ______ | M99: ______ | N99: ______ | O99: ______ | P99: ______ | Q99: ______ | R99: ______ | S99: ______ | T99: ______ | U99: ______ | V99: ______ | W99: ______ | X99: ______ | Y99: ______ | Z99: ______ | AA99: ______ | AB99: ______ | AC99: ______ | AD99: ______ | AE99: ______ | AF99: ______ | AG99: ______ | AH99: ______ | AI99: ______ | AJ99: ______ | AK99: ______ | AL99: ______ | AM99: ______ | AN99: ______ | AO99: ______ | AP99: ______ | AQ99: ______ | AR99: ______ | AS99: ______ | AT99: ______ | AU99: ______ | AV99: ______ | AW99: ______ | AX99: ______ | AY99: ______ | AZ99: ______ | BA99: ______ | BB99: ______ | BC99: ______ | BD99: ______ | BE99: ______ | BF99: ______ | BG99: ______ | BH99: ______ | BI99: ______ | BJ99: ______ | BK99: ______ | BL99: ______ | BM99: ______ | BN99: ______ | BO99: ______ | BP99: ______ | BQ99: ______ | BR99: ______ | BS99: ______ | BT99: ______ | BU99: ______ | BV99: ______ | BW99: ______ | BX99: ______ | BY99: ______ | BZ99: ______ | CA99: ______ | CB99: ______ | CC99: ______ | CD99: ______ | CE99: ______
B100: Ending Intangbiles | G100: =+G18 -> 2811 | H100: =+H18 -> 2811 | K100: =+K18 -> 0 | L100: =+L18 -> 2394 | M100: =+M18 -> 2394 | N100: =+N18 -> 2296 | O100: =+O18 -> 2198 | P100: =+P18 -> 2099 | Q100: =+Q18 -> 2001 | R100: =+R18 -> 2001 | ... AU100: =+AU18 -> 12006 | AV100: =+AV93+AV94-AV96 -> 10087 | AW100: =+AW18 -> 10361 | AX100: =+AX18 -> 8715 | AY100: =+AY93+AY94-AY96 -> 7050 | AZ100: =+AZ93+AZ94-AZ96 -> 7781 | BA100: =+BA93+BA94-BA96 -> 6575 | BB100: =+BB18 -> 4839 | BC100: =+BC18 -> 3365 | BD100: =+BD18 -> 2019 | BE100: =+BE93+BE94-BE96 -> 9358 | BF100: =+BF93+BF94-BF96 -> 9478 | BG100: =+BG18 -> 12030 | BH100: =+BH18 -> 11258 | BI100: =+BI93+BI94-BI96 -> 10486 | BJ100: =+BJ93+BJ94-BJ96 -> 9715 | BK100: =+BK93+BK94-BK96 -> 9714 | BL100: =+BL93+BL94-BL96 -> 8943 | BM100: =+BM93+BM94-BM96 -> 8172 | BN100: =+BN93+BN94-BN96 -> 7451 | BO100: =+BO93+BO94-BO96 -> 6812 | BP100: =+BP93+BP94-BP96 -> 6812 | ... CE100: =+CE93+CE94-CE96 -> 909.77755
AV101: =_xll.FDS(+IS!$B$1,"FE_ESTIMATE(GW_TOT,MEAN,ANNUAL,"&IS!AV$74&",NOW,,,'')")*1000 -> #NAME? | BA101: =_xll.FDS(+IS!$B$1,"FE_ESTIMATE(GW_TOT,MEAN,ANNUAL,"&IS!BA$74&",NOW,,,'')")*1000 -> #NAME? | BF101: =_xll.FDS(+IS!$B$1,"FE_ESTIMATE(GW_TOT,MEAN,ANNUAL,"&IS!BF$74&",NOW,,,'')")*1000 -> #NAME? | BK101: =_xll.FDS(+IS!$B$1,"FE_ESTIMATE(GW_TOT,MEAN,ANNUAL,"&IS!BK$74&",NOW,,,'')")*1000 -> #NAME? | BP101: =_xll.FDS(+IS!$B$1,"FE_ESTIMATE(GW_TOT,MEAN,ANNUAL,"&IS!BP$74&",NOW,,,'')")*1000 -> #NAME? | BU101: =_xll.FDS(+IS!$B$1,"FE_ESTIMATE(GW_TOT,MEAN,ANNUAL,"&IS!BU$74&",NOW,,,'')")*1000 -> #NAME? | BZ101: =_xll.FDS(+IS!$B$1,"FE_ESTIMATE(GW_TOT,MEAN,ANNUAL,"&IS!BZ$74&",NOW,,,'')")*1000 -> #NAME? | CE101: =_xll.FDS(+IS!$B$1,"FE_ESTIMATE(GW_TOT,MEAN,ANNUAL,"&IS!CE$74&",NOW,,,'')")*1000 -> #NAME?
B103: Accounts Payable | G103: =+G27 -> 2031 | H103: =+H27 -> 2031 | K103: =+K27 -> 0 | L103: =+L27 -> 1930 | M103: =+M27 -> 1930 | N103: =+N27 -> 2018 | O103: =+O27 -> 1735 | P103: =+P27 -> 1898 | Q103: =+Q27 -> 5661 | R103: =+R27 -> 5661 | ... CE103: =+CE27 -> 1988.0484
AV104: =_xll.FDS(+IS!$B$1,"FE_ESTIMATE(PAY_ACCT,MEAN,ANNUAL,"&IS!AV$74&",NOW,,,'')")*1000 -> #NAME? | BA104: =_xll.FDS(+IS!$B$1,"FE_ESTIMATE(PAY_ACCT,MEAN,ANNUAL,"&IS!BA$74&",NOW,,,'')")*1000 -> #NAME? | BF104: =_xll.FDS(+IS!$B$1,"FE_ESTIMATE(PAY_ACCT,MEAN,ANNUAL,"&IS!BF$74&",NOW,,,'')")*1000 -> #NAME? | BI104: =_xll.FDS(+IS!$B$1,"FE_ESTIMATE(PAY_ACCT,MEAN,QUARTERLY,"&IS!BI$74&",NOW,,,'')")*1000 -> #NAME? | BJ104: =_xll.FDS(+IS!$B$1,"FE_ESTIMATE(PAY_ACCT,MEAN,QUARTERLY,"&IS!BJ$74&",NOW,,,'')")*1000 -> #NAME? | BK104: =_xll.FDS(+IS!$B$1,"FE_ESTIMATE(PAY_ACCT,MEAN,ANNUAL,"&IS!BK$74&",NOW,,,'')")*1000 -> #NAME? | BL104: =_xll.FDS(+IS!$B$1,"FE_ESTIMATE(PAY_ACCT,MEAN,QUARTERLY,"&IS!BL$74&",NOW,,,'')")*1000 -> #NAME? | BM104: =_xll.FDS(+IS!$B$1,"FE_ESTIMATE(PAY_ACCT,MEAN,QUARTERLY,"&IS!BM$74&",NOW,,,'')")*1000 -> #NAME? | BN104: =_xll.FDS(+IS!$B$1,"FE_ESTIMATE(PAY_ACCT,MEAN,QUARTERLY,"&IS!BN$74&",NOW,,,'')")*1000 -> #NAME? | BO104: =_xll.FDS(+IS!$B$1,"FE_ESTIMATE(PAY_ACCT,MEAN,QUARTERLY,"&IS!BO$74&",NOW,,,'')")*1000 -> #NAME? | BP104: =_xll.FDS(+IS!$B$1,"FE_ESTIMATE(PAY_ACCT,MEAN,ANNUAL,"&IS!BP$74&",NOW,,,'')")*1000 -> #NAME? | BQ104: =_xll.FDS(+IS!$B$1,"FE_ESTIMATE(PAY_ACCT,MEAN,QUARTERLY,"&IS!BQ$74&",NOW,,,'')")*1000 -> #NAME? | BR104: =_xll.FDS(+IS!$B$1,"FE_ESTIMATE(PAY_ACCT,MEAN,QUARTERLY,"&IS!BR$74&",NOW,,,'')")*1000 -> #NAME? | BS104: =_xll.FDS(+IS!$B$1,"FE_ESTIMATE(PAY_ACCT,MEAN,QUARTERLY,"&IS!BS$74&",NOW,,,'')")*1000 -> #NAME? | BT104: =_xll.FDS(+IS!$B$1,"FE_ESTIMATE(PAY_ACCT,MEAN,QUARTERLY,"&IS!BT$74&",NOW,,,'')")*1000 -> #NAME? | BU104: =_xll.FDS(+IS!$B$1,"FE_ESTIMATE(PAY_ACCT,MEAN,ANNUAL,"&IS!BU$74&",NOW,,,'')")*1000 -> #NAME? | BV104: =_xll.FDS(+IS!$B$1,"FE_ESTIMATE(PAY_ACCT,MEAN,QUARTERLY,"&IS!BV$74&",NOW,,,'')")*1000 -> #NAME? | BW104: =_xll.FDS(+IS!$B$1,"FE_ESTIMATE(PAY_ACCT,MEAN,QUARTERLY,"&IS!BW$74&",NOW,,,'')")*1000 -> #NAME? | BX104: =_xll.FDS(+IS!$B$1,"FE_ESTIMATE(PAY_ACCT,MEAN,QUARTERLY,"&IS!BX$74&",NOW,,,'')")*1000 -> #NAME? | BY104: =_xll.FDS(+IS!$B$1,"FE_ESTIMATE(PAY_ACCT,MEAN,QUARTERLY,"&IS!BY$74&",NOW,,,'')")*1000 -> #NAME? | BZ104: =_xll.FDS(+IS!$B$1,"FE_ESTIMATE(PAY_ACCT,MEAN,ANNUAL,"&IS!BZ$74&",NOW,,,'')")*1000 -> #NAME? | CA104: =_xll.FDS(+IS!$B$1,"FE_ESTIMATE(PAY_ACCT,MEAN,QUARTERLY,"&IS!CA$74&",NOW,,,'')")*1000 -> #NAME? | CB104: =_xll.FDS(+IS!$B$1,"FE_ESTIMATE(PAY_ACCT,MEAN,QUARTERLY,"&IS!CB$74&",NOW,,,'')")*1000 -> #NAME? | CC104: =_xll.FDS(+IS!$B$1,"FE_ESTIMATE(PAY_ACCT,MEAN,QUARTERLY,"&IS!CC$74&",NOW,,,'')")*1000 -> #NAME? | CD104: =_xll.FDS(+IS!$B$1,"FE_ESTIMATE(PAY_ACCT,MEAN,QUARTERLY,"&IS!CD$74&",NOW,,,'')")*1000 -> #NAME? | CE104: =_xll.FDS(+IS!$B$1,"FE_ESTIMATE(PAY_ACCT,MEAN,ANNUAL,"&IS!CE$74&",NOW,,,'')")*1000 -> #NAME?
B105: % of COGS | G105: =+G103/G$59 -> 0.4144898 | H105: =+H103/H$59 -> 0.11203663 | K105: =+K103/K$59 -> 0 | L105: =+L103/L$59 -> 0.30151539 | M105: =+M103/M$59 -> 0.079659898 | N105: =+N103/N$59 -> 0.30132895 | O105: =+O103/O$59 -> 0.24725666 | P105: =+P103/P$59 -> 0.26193762 | Q105: =+Q103/Q$59 -> 0.78125863 | R105: =+R103/R$59 -> 0.20070198 | ... CE105: =+CE103/CE$59 -> 0.016705424
B106: Yr-Yr Growth | L106: =+L103/G103-1 -> -0.049729197 | M106: =+M103/H103-1 -> -0.049729197 | Q106: =+Q103/L103-1 -> 1.9331606 | R106: =+R103/M103-1 -> 1.9331606 | S106: =+S103/N103-1 -> 0.016848365 | T106: =+T103/O103-1 -> -0.39942363 | U106: =+U103/P103-1 -> 0.082718651 | V106: =+V103/Q103-1 -> -0.58169935 | W106: =+W103/R103-1 -> -0.58169935 | X106: =+X103/S103-1 -> 1.1408382 | ... CE106: =+CE103/BZ103-1 -> 0.025806452
B107: Q-Q Growth | N107: =+N103/L103-1 -> 0.045595855 | O107: =+O103/N103-1 -> -0.14023786 | P107: =+P103/O103-1 -> 0.093948127 | Q107: =+Q103/P103-1 -> 1.9826133 | S107: =+S103/Q103-1 -> -0.63751987 | T107: =+T103/S103-1 -> -0.49220273 | U107: =+U103/T103-1 -> 0.97216891 | V107: =+V103/U103-1 -> 0.15231144 | X107: =+X103/V103-1 -> 0.85515203 | Y107: =+Y103/X103-1 -> 0.33234692 | Z107: =+Z103/Y103-1 -> -0.74525884 | AA107: =+AA103/Z103-1 -> 0.37558685 | AC107: =+AC103/AA103-1 -> 1.1150658 | AD107: =+AD103/AC103-1 -> -0.55647764 | AE107: =+AE103/AD103-1 -> -0.27338877 | AF107: =+AF103/AE103-1 -> -0.18168813 | AH107: =+AH103/AF103-1 -> 0.1451049 | AI107: =+AI103/AH103-1 -> -0.21832061 | AJ107: =+AJ103/AI103-1 -> 3.6123047 | AK107: =+AK103/AJ103-1 -> 0.18314631 | AM107: =+AM103/AK103-1 -> -0.89871152 | AN107: =+AN103/AM103-1 -> 0.70141343 | AO107: =+AO103/AN103-1 -> -0.056074766 | AP107: =+AP103/AO103-1 -> -0.067106711 | AR107: =+AR103/AP103-1 -> -0.22995283 | AS107: =+AS103/AR103-1 -> 1.136294 | AT107: =+AT103/AS103-1 -> 0.59354839 | AU107: =+AU103/AT103-1 -> -0.67116509 | AW107: =+AW103/AU103-1 -> 0.59233926 | AX107: =+AX103/AW103-1 -> 0.37199313 | AY107: =+AY103/AX103-1 -> -0.31183469 | AZ107: =+AZ103/AY103-1 -> 0.17925387 | BB107: =+BB103/AZ103-1 -> 0.91126543 | BC107: =+BC103/BB103-1 -> -0.13928139 | BD107: =+BD103/BC103-1 -> -0.38649156 | BE107: =+BE103/BD103-1 -> 1.146789 | BG107: =+BG103/BE103-1 -> -0.38034188 | BH107: =+BH103/BG103-1 -> 0.24137931 | BI107: =+BI103/BH103-1 -> -0.46064815 | BJ107: =+BJ103/BI103-1 -> -0.15193133 | BL107: =+BL103/BJ103-1 -> -0.34716599 | BM107: =+BM103/BL103-1 -> 0.97984496 | BN107: =+BN103/BM103-1 -> 0.11354738 | BO107: =+BO103/BN103-1 -> -0.1068917 | BQ107: =+BQ103/BO103-1 -> 0.017322835 | BR107: =+BR103/BQ103-1 -> 0.53018576 | BS107: =+BS103/BR103-1 -> -0.077895802 | BT107: =+BT103/BS103-1 -> -0.34064728 | BV107: =+BV103/BT103-1 -> 0.28297589 | BW107: =+BW103/BV103-1 -> 0.22556829 | BX107: =+BX103/BW103-1 -> 0.011355271 | BY107: =+BY103/BX103-1 -> 0.013905115 | CA107: =+CA103/BY103-1 -> -0.15136237 | CB107: =+CB103/CA103-1 -> 0.19885056 | CC107: =+CC103/CB103-1 -> 0.014502823 | CD107: =+CD103/CC103-1 -> -0.0061408761
B108: Days Payable | G108: =+G53 -> 0 | H108: =+H53 -> 0 | L108: =+L53 -> 27.136385 | M108: =+M53 -> 29.427935 | N108: =+N53 -> 27.119606 | O108: =+O53 -> 22.2531 | P108: =+P53 -> 23.574386 | Q108: =+Q53 -> 70.313276 | R108: =+R53 -> 48.442884 | S108: =+S53 -> 24.185437 | ... BU108: =+BU53 -> 4.2915839 | BV108: 5 | BW108: 6 | BX108: 6 | BY108: 6 | BZ108: =+BZ53 -> 4.9644496 | CA108: 5 | CB108: 6 | CC108: 6 | CD108: 6 | CE108: =+CE53 -> 5.9383056
B110: Accrued Liabilities | G110: =+G28 -> 7803 | H110: =+H28 -> 7803 | L110: =+L28 -> 9037 | M110: =+M28 -> 9037 | N110: =+N28 -> 8444 | O110: =+O28 -> 8389 | P110: =+P28 -> 9101 | Q110: =+Q28 -> 10353 | R110: =+R28 -> 10353 | S110: =+S28 -> 10547 | ... CE110: =+CE28 -> 72112.892
B112: % COGS + OPEX | G112: =+G110/(G$59+G$60) -> 0.35212094 | H112: =+H110/(H$59+H$60) -> 0.091839977 | L112: =+L110/(L$59+L$60) -> 0.33325958 | M112: =+M110/(M$59+M$60) -> 0.090237351 | N112: =+N110/(N$59+N$60) -> 0.29637429 | O112: =+O110/(O$59+O$60) -> 0.29926513 | P112: =+P110/(P$59+P$60) -> 0.3210569 | Q112: =+Q110/(Q$59+Q$60) -> 0.35807422 | R112: =+R110/(R$59+R$60) -> 0.090988988 | S112: =+S110/(S$59+S$60) -> 0.3675169 | ... BU112: =+BU110/(BU$59+BU$60) -> 0.15692642 | BV112: 0.6 | BW112: 0.55 | BX112: 0.55 | BY112: 0.6 | BZ112: =+BZ110/(BZ$59+BZ$60) -> 0.15921912 | CA112: 0.65 | CB112: 0.5 | CC112: 0.55 | CD112: 0.65 | CE112: =+CE110/(CE$59+CE$60) -> 0.16430168
B113: Yr-Yr Growth | L113: =+L110/G110-1 -> 0.1581443 | M113: =+M110/H110-1 -> 0.1581443 | Q113: =+Q110/L110-1 -> 0.14562355 | R113: =+R110/M110-1 -> 0.14562355 | S113: =+S110/N110-1 -> 0.24905258 | T113: =+T110/O110-1 -> 0.26332102 | U113: =+U110/P110-1 -> 0.24799473 | V113: =+V110/Q110-1 -> 0.13841399 | W113: =+W110/R110-1 -> 0.13841399 | X113: =+X110/S110-1 -> 0.091590026 | ... CE113: =+CE110/BZ110-1 -> 0.081702279
B114: Q-Q Growth | N114: =+N110/L110-1 -> -0.065619121 | O114: =+O110/N110-1 -> -0.0065135007 | P114: =+P110/O110-1 -> 0.084873048 | Q114: =+Q110/P110-1 -> 0.1375673 | S114: =+S110/Q110-1 -> 0.01873853 | T114: =+T110/S110-1 -> 0.0048354982 | U114: =+U110/T110-1 -> 0.071711644 | V114: =+V110/U110-1 -> 0.037682691 | X114: =+X110/V110-1 -> -0.023163075 | Y114: =+Y110/X110-1 -> 0.46364979 | Z114: =+Z110/Y110-1 -> -0.031274108 | AA114: =+AA110/Z110-1 -> -0.1842073 | AC114: =+AC110/AA110-1 -> 0.0015769317 | AD114: =+AD110/AC110-1 -> 0.037336932 | AE114: =+AE110/AD110-1 -> 0.060928014 | AF114: =+AF110/AE110-1 -> 0.46086246 | AH114: =+AH110/AF110-1 -> 0.034368588 | AI114: =+AI110/AH110-1 -> 0.23772598 | AJ114: =+AJ110/AI110-1 -> -0.1546587 | AK114: =+AK110/AJ110-1 -> 0.08281627 | AM114: =+AM110/AK110-1 -> 0.27405491 | AN114: =+AN110/AM110-1 -> -0.2405597 | AO114: =+AO110/AN110-1 -> 0.052642402 | AP114: =+AP110/AO110-1 -> -0.10982614 | AR114: =+AR110/AP110-1 -> 0.042529846 | AS114: =+AS110/AR110-1 -> 0.044499642 | AT114: =+AT110/AS110-1 -> -0.0015316405 | AU114: =+AU110/AT110-1 -> 0.20430325 | AW114: =+AW110/AU110-1 -> -0.066939295 | AX114: =+AX110/AW110-1 -> 0.10234948 | AY114: =+AY110/AX110-1 -> 0.10405736 | AZ114: =+AZ110/AY110-1 -> -0.040557294 | BB114: =+BB110/AZ110-1 -> 0.14087497 | BC114: =+BC110/BB110-1 -> 0.024377747 | BD114: =+BD110/BC110-1 -> 0.12712244 | BE114: =+BE110/BD110-1 -> -0.0052316891 | BG114: =+BG110/BE110-1 -> -0.019135049 | BH114: =+BH110/BG110-1 -> 0.25995165 | BI114: =+BI110/BH110-1 -> -0.053175523 | BJ114: =+BJ110/BI110-1 -> -0.1352783 | BL114: =+BL110/BJ110-1 -> 0.11950065 | BM114: =+BM110/BL110-1 -> -0.25185508 | BN114: =+BN110/BM110-1 -> 0.10707854 | BO114: =+BO110/BN110-1 -> 0.1496997 | BQ114: =+BQ110/BO110-1 -> 0.15190893 | BR114: =+BR110/BQ110-1 -> -0.0028911018 | BS114: =+BS110/BR110-1 -> -0.030927835 | BT114: =+BT110/BS110-1 -> 0.12824625 | BV114: =+BV110/BT110-1 -> 0.023825594 | BW114: =+BW110/BV110-1 -> -0.041118108 | BX114: =+BX110/BW110-1 -> 0.030937269 | BY114: =+BY110/BX110-1 -> 0.14169784 | CA114: =+CA110/BY110-1 -> 0.060510823 | CB114: =+CB110/CA110-1 -> -0.22720169 | CC114: =+CC110/CB110-1 -> 0.10649522 | CD114: =+CD110/CC110-1 -> 0.19282555
B116: ST Deferred Revenue | G116: =+G29 -> 56497 | H116: =+H29 -> 56497 | L116: =+L29 -> 67505 | M116: =+M29 -> 67505 | N116: =+N29 -> 71410 | O116: =+O29 -> 71853 | P116: =+P29 -> 74337 | Q116: =+Q29 -> 81147 | R116: =+R29 -> 81147 | S116: =+S29 -> 87929 | ... CE116: =+CE29 -> 461396.33
AV117: =_xll.FDS(+IS!$B$1,"FE_ESTIMATE(DEFREVENUE_ST,MEAN,ANNUAL,"&IS!AV$74&",NOW,,,'')")*1000 -> #NAME? | BA117: =_xll.FDS(+IS!$B$1,"FE_ESTIMATE(DEFREVENUE_ST,MEAN,ANNUAL,"&IS!BA$74&",NOW,,,'')")*1000 -> #NAME? | BF117: =_xll.FDS(+IS!$B$1,"FE_ESTIMATE(DEFREVENUE_ST,MEAN,ANNUAL,"&IS!BF$74&",NOW,,,'')")*1000 -> #NAME? | BK117: =_xll.FDS(+IS!$B$1,"FE_ESTIMATE(DEFREVENUE_ST,MEAN,ANNUAL,"&IS!BK$74&",NOW,,,'')")*1000 -> #NAME? | BL117: =_xll.FDS(+IS!$B$1,"FE_ESTIMATE(DEFREVENUE_ST,MEAN,QUARTERLY,"&IS!BL$74&",NOW,,,'')")*1000 -> #NAME? | BM117: =_xll.FDS(+IS!$B$1,"FE_ESTIMATE(DEFREVENUE_ST,MEAN,QUARTERLY,"&IS!BM$74&",NOW,,,'')")*1000 -> #NAME? | BN117: =_xll.FDS(+IS!$B$1,"FE_ESTIMATE(DEFREVENUE_ST,MEAN,QUARTERLY,"&IS!BN$74&",NOW,,,'')")*1000 -> #NAME? | BO117: =_xll.FDS(+IS!$B$1,"FE_ESTIMATE(DEFREVENUE_ST,MEAN,QUARTERLY,"&IS!BO$74&",NOW,,,'')")*1000 -> #NAME? | BP117: =_xll.FDS(+IS!$B$1,"FE_ESTIMATE(DEFREVENUE_ST,MEAN,ANNUAL,"&IS!BP$74&",NOW,,,'')")*1000 -> #NAME? | BQ117: =_xll.FDS(+IS!$B$1,"FE_ESTIMATE(DEFREVENUE_ST,MEAN,QUARTERLY,"&IS!BQ$74&",NOW,,,'')")*1000 -> #NAME? | BR117: =_xll.FDS(+IS!$B$1,"FE_ESTIMATE(DEFREVENUE_ST,MEAN,QUARTERLY,"&IS!BR$74&",NOW,,,'')")*1000 -> #NAME? | BS117: =_xll.FDS(+IS!$B$1,"FE_ESTIMATE(DEFREVENUE_ST,MEAN,QUARTERLY,"&IS!BS$74&",NOW,,,'')")*1000 -> #NAME? | BU117: =_xll.FDS(+IS!$B$1,"FE_ESTIMATE(DEFREVENUE_ST,MEAN,ANNUAL,"&IS!BU$74&",NOW,,,'')")*1000 -> #NAME? | BV117: =_xll.FDS(+IS!$B$1,"FE_ESTIMATE(DEFREVENUE_ST,MEAN,QUARTERLY,"&IS!BV$74&",NOW,,,'')")*1000 -> #NAME? | BW117: =_xll.FDS(+IS!$B$1,"FE_ESTIMATE(DEFREVENUE_ST,MEAN,QUARTERLY,"&IS!BW$74&",NOW,,,'')")*1000 -> #NAME? | BZ117: =_xll.FDS(+IS!$B$1,"FE_ESTIMATE(DEFREVENUE_ST,MEAN,ANNUAL,"&IS!BZ$74&",NOW,,,'')")*1000 -> #NAME? | CA117: =_xll.FDS(+IS!$B$1,"FE_ESTIMATE(DEFREVENUE_ST,MEAN,QUARTERLY,"&IS!CA$74&",NOW,,,'')")*1000 -> #NAME? | CB117: =_xll.FDS(+IS!$B$1,"FE_ESTIMATE(DEFREVENUE_ST,MEAN,QUARTERLY,"&IS!CB$74&",NOW,,,'')")*1000 -> #NAME? | CE117: =_xll.FDS(+IS!$B$1,"FE_ESTIMATE(DEFREVENUE_ST,MEAN,ANNUAL,"&IS!CE$74&",NOW,,,'')")*1000 -> #NAME?
B118: Growth Rate Input | BV118: 0.08 | BW118: 0.08 | BX118: 0.08 | BY118: 0.075 | CA118: 0.07 | CB118: 0.07 | CC118: 0.07 | CD118: 0.07
B119: Yr-Yr Growth (Deferred Revenue) | L119: =+L116/G116-1 -> 0.1948422 | M119: =+M116/H116-1 -> 0.1948422 | Q119: =+Q116/L116-1 -> 0.20208873 | R119: =+R116/M116-1 -> 0.20208873 | S119: =+S116/N116-1 -> 0.23132614 | T119: =+T116/O116-1 -> 0.21652541 | U119: =+U116/P116-1 -> 0.23678653 | V119: =+V116/Q116-1 -> 0.2079929 | W119: =+W116/R116-1 -> 0.2079929 | X119: =+X116/S116-1 -> 0.15498868 | ... CE119: =+CE116/BZ116-1 -> 0.07
B120: Yr-Yr Growth (Revenue) | G120: =+IS!G137 -> 0 | H120: =+IS!H137 -> 0 | L120: =+IS!L137 -> 0.1777183 | M120: =+IS!M137 -> 0.18094509 | Q120: =+IS!Q137 -> 0.2594442 | R120: =+IS!R137 -> 0.23727793 | S120: =+IS!S137 -> 0.23511003 | T120: =+IS!T137 -> 0.2345056 | U120: =+IS!U137 -> 0.23643298 | V120: =+IS!V137 -> 0.21524075 | W120: =+IS!W137 -> 0.22986398 | X120: =+IS!X137 -> 0.23351026 | ... CE120: =+IS!CE137 -> 0.067271501
B121: Delta | G121: =+G119-G120 -> 0 | H121: =+H119-H120 -> 0 | L121: =+L119-L120 -> 0.017123909 | M121: =+M119-M120 -> 0.013897115 | Q121: =+Q119-Q120 -> -0.057355462 | R121: =+R119-R120 -> -0.035189197 | S121: =+S119-S120 -> -0.0037838829 | T121: =+T119-T120 -> -0.017980197 | U121: =+U119-U120 -> 0.00035354614 | V121: =+V119-V120 -> -0.0072478496 | W121: =+W119-W120 -> -0.021871074 | X121: =+X119-X120 -> -0.078521571 | ... CE121: =+CE119-CE120 -> 0.0027284991
...

Sheet CF
B3: Qualys, Inc.—Cash Flow
B4: (Thousands Of Dollars, Except Per-Share Data) | D4: Mar | E4: June | F4: Sept | G4: Dec | H4: Dec | I4: Mar | J4: June | K4: Sept | L4: Dec | M4: Dec | N4: Mar | O4: June | P4: Sept | Q4: Dec | R4: Dec | S4: Mar | T4: June | U4: Sept | V4: Dec | W4: Dec | X4: Mar | Y4: June | Z4: Sept | AA4: Dec | AB4: Dec | AC4: Mar | AD4: June | AE4: Sept | AF4: Dec | AG4: Dec | AH4: Mar | AI4: June | AJ4: Sept | AK4: Dec | AL4: Dec | AM4: Mar | AN4: June | AO4: Sept | AP4: Dec | AQ4: Dec | AR4: Mar | AS4: June | AT4: Sept | AU4: Dec | AV4: Dec | AW4: Mar | AX4: June | AY4: Sept | AZ4: Dec | BA4: Dec | BB4: Mar | BC4: June | BD4: Sept | BE4: Dec | BF4: Dec | BG4: Mar | BH4: June | BI4: Sept | BJ4: Dec | BK4: Dec | BL4: Mar | BM4: June | BN4: Sept | BO4: Dec | BP4: Dec | BQ4: Mar | BR4: June | BS4: Sept | BT4: Dec | BU4: Dec | BV4: Mar | BW4: June | BX4: Sept | BY4: Dec | BZ4: Dec | CA4: Mar | CB4: June | CC4: Sept | CD4: Dec | CE4: Dec
D5: =+BS!D5 -> 2012A | E5: =+BS!E5 -> 2012A | F5: =+BS!F5 -> 2012A | G5: =+BS!G5 -> 2012A | H5: =+BS!H5 -> 2012A | I5: =+BS!I5 -> 2013A | J5: =+BS!J5 -> 2013A | K5: =+BS!K5 -> 2013A | ... CE5: =+BS!CE5 -> 2027E
B6: Cash from Operating Activities
A7: x | B7: Net Income / Loss | H7: 2280 | M7: 1624 | N7: -440 | O7: 1706 | P7: 3208 | Q7: 25770 | R7: 30244 | S7: 3002 | T7: 3316 | U7: 4123 | V7: 5424 | W7: 15865 | X7: 4783 | Y7: 3538 | Z7: 4996 | AA7: 5907 | AB7: 19224 | AC7: 21930 | AD7: =29132-AC7 -> 7202 | AE7: =37584-AD7-AC7 -> 8452 | AF7: =+AG7-SUM(AC7:AE7) -> 2856 | AG7: 40440 | AH7: 9142 | AI7: =19435-AH7 -> 10293 | AJ7: =42904-AI7-AH7 -> 23469 | AK7: =+AL7-SUM(AH7:AJ7) -> 14400 | AL7: 57304 | AM7: 13266 | AN7: 16232 | AO7: 19174 | AP7: 20664 | AQ7: =+SUM(AM7:AP7) -> 69336 | AR7: 18694 | AS7: 26319 | AT7: 22743 | AU7: =91572-AR7-AS7-AT7 -> 23816 | AV7: =+SUM(AR7:AU7) -> 91572 | AW7: =228 -> 228 | AX7: =21370-AW7 -> 21142 | AY7: =49139-AW7-AX7 -> 27769 | AZ7: =BA7-AY7-AX7-AW7 -> 21821 | BA7: =70960 -> 70960 | BB7: =25410 -> 25410 | BC7: =52006-BB7 -> 26596 | BD7: =79666-BB7-BC7 -> 27660 | BE7: =BF7-SUM(BB7:BD7) -> 28326 | BF7: =107992 -> 107992 | BG7: =29105 -> 29105 | BH7: =64487-BG7 -> 35382 | BI7: =111002-BH7-BG7 -> 46515 | BJ7: =BK7-BI7-BH7-BG7 -> 40593 | BK7: =151595 -> 151595 | BL7: =39731 -> 39731 | BM7: =83503-BL7 -> 43772 | BN7: =129715-BM7-BL7 -> 46212 | BO7: =BP7-BN7-BM7-BL7 -> 43965 | BP7: =173680 -> 173680 | BQ7: =+'Billings & Recs'!BQ77 -> 47534 | BR7: =+'Billings & Recs'!BR77 -> 47290 | BS7: =+'Billings & Recs'!BS77 -> 50346 | BT7: =+'Billings & Recs'!BT77 -> 53150 | BU7: =+'Billings & Recs'!BU77 -> 198320 | BV7: =+'Billings & Recs'!BV77 -> 48846.472 | BW7: =+'Billings & Recs'!BW77 -> 47851.065 | BX7: =+'Billings & Recs'!BX77 -> 49884.489 | ... CE7: =+'Billings & Recs'!CE77 -> 219934
A8: x | B8: Depreciation and Amortization Expense | H8: 7341 | M8: 9612 | N8: 2805 | O8: 2977 | P8: 3044 | Q8: 3071 | R8: 11897 | S8: 3182 | T8: 3404 | U8: 3838 | V8: 3936 | W8: 14360 | X8: 3834 | Y8: 3994 | Z8: 4536 | AA8: 4630 | AB8: 16994 | AC8: 4820 | AD8: =9783-AC8 -> 4963 | AE8: =15054-AD8-AC8 -> 5271 | AF8: =+AG8-SUM(AC8:AE8) -> 5582 | AG8: 20636 | AH8: 7043 | AI8: =14249-AH8 -> 7206 | AJ8: =21224-AI8-AH8 -> 6975 | AK8: =+AL8-SUM(AH8:AJ8) -> 7681 | AL8: 28905 | AM8: 7935 | AN8: 7874 | AO8: 7677 | AP8: 7715 | AQ8: =+SUM(AM8:AP8) -> 31201 | AR8: 7747 | AS8: 7886 | AT8: 8342 | AU8: =32845-AR8-AS8-AT8 -> 8870 | AV8: =+SUM(AR8:AU8) -> 32845 | AW8: =9078 -> 9078 | AX8: =17869-AW8 -> 8791 | AY8: =26752-AW8-AX8 -> 8883 | AZ8: =BA8-AY8-AX8-AW8 -> 9145 | BA8: =35897 -> 35897 | BB8: =8982 -> 8982 | BC8: =17552-BB8 -> 8570 | BD8: =25773-BC8-BB8 -> 8221 | BE8: =BF8-SUM(BB8:BD8) -> 8849 | BF8: =34622 -> 34622 | BG8: =7444 -> 7444 | BH8: =14446-BG8 -> 7002 | BI8: =21140-BH8-BG8 -> 6694 | BJ8: =BK8-BI8-BH8-BG8 -> 5851 | BK8: =26991 -> 26991 | BL8: =5239 -> 5239 | BM8: =10019-BL8 -> 4780 | BN8: =14410-BM8-BL8 -> 4391 | BO8: =BP8-BN8-BM8-BL8 -> 4103 | BP8: =18513 -> 18513 | BQ8: =4177 -> 4177 | BR8: =8155-BQ8 -> 3978 | BS8: =11353-SUM(BQ8:BR8) -> 3198 | BT8: =14491-BS8-BR8-BQ8 -> 3138 | BU8: =+SUM(BQ8:BT8) -> 14491 | BV8: =+'Billings & Recs'!BV81 -> 4113.15 | BW8: =+'Billings & Recs'!BW81 -> 3782.4367 | BX8: =+'Billings & Recs'!BX81 -> 2562.8731 | BY8: =+'Billings & Recs'!BY81 -> 2557.4637 | BZ8: =+'Billings & Recs'!BZ81 -> 13015.924 | CA8: =+'Billings & Recs'!CA81 -> 3789.6416 | CB8: =+'Billings & Recs'!CB81 -> 3480.0385 | CC8: =+'Billings & Recs'!CC81 -> 2636.5801 | ... CE8: =+'Billings & Recs'!CE81 -> 12436.003
B9: Bad Debt Expense | H9: 218 | M9: 307 | N9: 14 | O9: 139 | P9: 193 | Q9: 124 | R9: 470 | S9: 175 | T9: 158 | U9: 296 | V9: 222 | W9: 851 | X9: 80 | Y9: 26 | Z9: 46 | AA9: 47 | AB9: 199 | AC9: 10 | AD9: =296-AC9 -> 286 | AE9: =353-AD9-AC9 -> 57 | AF9: =+AG9-SUM(AC9:AE9) -> 304 | AG9: 657 | AH9: 0 | AI9: 0 | AJ9: 0 | AK9: =+AL9-SUM(AH9:AJ9) -> 86 | AL9: 86 | AM9: 0 | AN9: 86 | AO9: 70 | AP9: 91 | AQ9: =+SUM(AM9:AP9) -> 247 | AR9: 148 | AS9: 151 | AT9: 93 | AU9: =486-AR9-AS9-AT9 -> 94 | AV9: =+SUM(AR9:AU9) -> 486 | AW9: =138 -> 138 | AX9: =152-AW9 -> 14 | AY9: =247-AW9-AX9 -> 95 | AZ9: =BA9-AY9-AX9-AW9 -> 155 | BA9: =402 -> 402 | BB9: =141 -> 141 | BC9: =297-BB9 -> 156 | BD9: =493-BC9-BB9 -> 196 | BE9: =BF9-SUM(BB9:BD9) -> 97 | BF9: =590 -> 590 | BG9: =119 -> 119 | BH9: =160-BG9 -> 41 | BI9: =230-BH9-BG9 -> 70 | BJ9: =BK9-BI9-BH9-BG9 -> 317 | BK9: =547 -> 547 | BL9: =193 -> 193 | BM9: =277-BL9 -> 84 | BN9: =411-BM9-BL9 -> 134 | BO9: =BP9-BN9-BM9-BL9 -> 353 | BP9: =764 -> 764 | BQ9: =206 -> 206 | BR9: =850-BQ9 -> 644 | BS9: =1110-SUM(BQ9:BR9) -> 260 | BT9: =1226-BS9-BR9-BQ9 -> 116 | BU9: =+SUM(BQ9:BT9) -> 1226 | BV9: =0 -> 0 | BW9: =0 -> 0 | BX9: =0 -> 0 | BY9: =0 -> 0 | BZ9: =+SUM(BV9:BY9) -> 0 | CA9: =0 -> 0 | CB9: =0 -> 0 | CC9: =0 -> 0 | CD9: =0 -> 0 | CE9: =+SUM(CA9:CD9) -> 0
B10: Loss on Disposal of Property and Equipment | H10: 10 | M10: 12 | N10: 0 | O10: 1 | P10: 0 | Q10: 323 | R10: 324 | S10: 4 | T10: 0 | U10: 5 | V10: -4 | W10: 5 | X10: 0 | Y10: 39 | Z10: 0 | AA10: 16 | AB10: 55 | AC10: 2 | AD10: =2-AC10 -> 0 | AE10: =3-AD10-AC10 -> 1 | AF10: =+AG10-SUM(AC10:AE10) -> 158 | AG10: 161 | AH10: 7 | AI10: =9-AH10 -> 2 | AJ10: =31-AI10-AH10 -> 22 | AK10: =+AL10-SUM(AH10:AJ10) -> 0 | AL10: 31 | AM10: 105 | AN10: 78 | AO10: 13 | AP10: 6 | AQ10: =+SUM(AM10:AP10) -> 202 | AR10: 0 | AS10: 0 | AT10: 9 | AU10: =106-AR10-AS10-AT10 -> 97 | AV10: =+SUM(AR10:AU10) -> 106 | AW10: =0 -> 0 | AX10: =12-AW10 -> 12 | AY10: =12-AW10-AX10 -> 0 | AZ10: =BA10-AY10-AX10-AW10 -> 625 | BA10: =625+12 -> 637 | BB10: =5 -> 5 | BC10: =5-BB10 -> 0 | BD10: =5-BC10-BB10 -> 0 | BE10: =BF10-SUM(BB10:BD10) -> 1 | BF10: 6 | BG10: 0 | BH10: 0 | BI10: 0 | BJ10: =BK10-BI10-BH10-BG10 -> 0 | BK10: =0 -> 0 | BL10: =0 -> 0 | BM10: =0 -> 0 | BN10: =0 -> 0 | BO10: =BP10-BN10-BM10-BL10 -> 0 | BP10: =0 -> 0 | BQ10: =0 -> 0 | BR10: =0 -> 0 | BS10: =0 -> 0 | BT10: =0-BS10-BR10-BQ10 -> 0 | BU10: =+SUM(BQ10:BT10) -> 0 | BV10: =0 -> 0 | BW10: =0 -> 0 | BX10: =0 -> 0 | BY10: =0 -> 0 | BZ10: =+SUM(BV10:BY10) -> 0 | CA10: =0 -> 0 | CB10: =0 -> 0 | CC10: =0 -> 0 | CD10: =0 -> 0 | CE10: =+SUM(CA10:CD10) -> 0
A11: x | B11: Stock-Based Compensation | H11: 3452 | M11: 5506 | N11: 2126 | O11: 2480 | P11: 2494 | Q11: 3449 | R11: 10549 | S11: 3875 | T11: 4382 | U11: 4421 | V11: 4816 | W11: 17494 | X11: 4697 | Y11: 5322 | Z11: 5103 | AA11: 5027 | AB11: 20149 | AC11: 4332 | AD11: =10779-AC11 -> 6447 | AE11: =18522-AD11-AC11 -> 7743 | AF11: =+AG11-SUM(AC11:AE11) -> 8439 | AG11: 26961 | AH11: 8891 | AI11: =15914-AH11 -> 7023 | AJ11: =22672-AI11-AH11 -> 6758 | AK11: =+AL11-SUM(AH11:AJ11) -> 7418 | AL11: 30090 | AM11: 8445 | AN11: 8335 | AO11: 8383 | AP11: 9729 | AQ11: =+SUM(AM11:AP11) -> 34892 | AR11: 9997 | AS11: 9444 | AT11: 10489 | AU11: =40035-AR11-AS11-AT11 -> 10105 | AV11: =+SUM(AR11:AU11) -> 40035 | AW11: =38202 -> 38202 | AX11: =46755-AW11 -> 8553 | AY11: =56218-AW11-AX11 -> 9463 | AZ11: =BA11-AY11-AX11-AW11 -> 11361 | BA11: =67579 -> 67579 | BB11: =11745 -> 11745 | BC11: =24565-BB11 -> 12820 | BD11: =37856-BC11-BB11 -> 13291 | BE11: =BF11-SUM(BB11:BD11) -> 15552 | BF11: 53408 | BG11: =16033 -> 16033 | BH11: =32038-BG11 -> 16005 | BI11: =50560-BH11-BG11 -> 18522 | BJ11: =BK11-BI11-BH11-BG11 -> 18519 | BK11: =69079 -> 69079 | BL11: =19031 -> 19031 | BM11: =36117-BL11 -> 17086 | BN11: =56454-BM11-BL11 -> 20337 | BO11: =BP11-BN11-BM11-BL11 -> 20679 | BP11: =77133 -> 77133 | BQ11: =18820 -> 18820 | BR11: =36866-BQ11 -> 18046 | BS11: =56313-SUM(BQ11:BR11) -> 19447 | BT11: =76966-BS11-BR11-BQ11 -> 20653 | BU11: =+SUM(BQ11:BT11) -> 76966 | BV11: =+'Billings & Recs'!BV113 -> 19083.946 | BW11: =+'Billings & Recs'!BW113 -> 19490.566 | BX11: =+'Billings & Recs'!BX113 -> 19175.431 | BY11: =+'Billings & Recs'!BY113 -> 18755.174 | BZ11: =+'Billings & Recs'!BZ113 -> 76505.116 | CA11: =+'Billings & Recs'!CA113 -> 18736.965 | CB11: =+'Billings & Recs'!CB113 -> 18959.005 | CC11: =+'Billings & Recs'!CC113 -> 19358.054 | ... CE11: =+'Billings & Recs'!CE113 -> 75940.484
B12: Non-Cash Interest Expense | H12: 24 | M12: 0 | N12: 0 | O12: 0 | P12: 0 | Q12: 0 | R12: 0 | S12: 0 | T12: 0 | U12: 0 | V12: 0 | W12: 0 | X12: 0 | Y12: 0 | Z12: 0 | AA12: 0 | AB12: 0 | AC12: 0 | AD12: =0-AC12 -> 0 | AE12: =0-AD12-AC12 -> 0 | AF12: =+AG12-SUM(AC12:AE12) -> 0 | AG12: 0 | AH12: 0 | AI12: 0 | AJ12: 0 | AK12: =+AL12-SUM(AH12:AJ12) -> 0 | AL12: 0 | AN12: 0 | AO12: 0 | AP12: 0 | AQ12: =+SUM(AM12:AP12) -> 0 | AV12: =+SUM(AR12:AU12) -> 0 | AZ12: 0 | BA12: =+SUM(AW12:AZ12) -> 0 | BE12: =BF12-SUM(BB12:BD12) -> 0 | BJ12: =BK12-BI12-BH12-BG12 -> 0 | BO12: =BP12-BN12-BM12-BL12 -> 0 | BT12: =0-BS12-BR12-BQ12 -> 0 | BU12: =+SUM(BQ12:BT12) -> 0 | BZ12: =+SUM(BV12:BY12) -> 0 | CE12: =+SUM(CA12:CD12) -> 0
B13: Amortization of Premiums and Accretion of Discounts on Investments | H13: 7 | M13: 282 | N13: 136 | O13: 189 | P13: 102 | Q13: 138 | R13: 565 | S13: 168 | T13: 156 | U13: 105 | V13: 165 | W13: 594 | X13: 208 | Y13: 182 | Z13: 227 | AA13: 383 | AB13: 1000 | AC13: 426 | AD13: =850-AC13 -> 424 | AE13: =1155-AD13-AC13 -> 305 | AF13: =+AG13-SUM(AC13:AE13) -> 169 | AG13: 1324 | AH13: 36 | AI13: =+-169-AH13 -> -205 | AJ13: =+-586-AI13-AH13 -> -417 | AK13: =+AL13-SUM(AH13:AJ13) -> -550 | AL13: -1136 | AM13: -580 | AN13: -480 | AO13: -342 | AP13: -195 | AQ13: =+SUM(AM13:AP13) -> -1597 | AR13: -64 | AS13: 43 | AT13: 184 | AU13: =826-AR13-AS13-AT13 -> 663 | AV13: =+SUM(AR13:AU13) -> 826 | AW13: =967 -> 967 | AX13: =2029-AW13 -> 1062 | AY13: =2985-AW13-AX13 -> 956 | AZ13: =BA13-AY13-AX13-AW13 -> 884 | BA13: =3869 -> 3869 | BB13: =762 -> 762 | BC13: =1158-BB13 -> 396 | BD13: =1127-BC13-BB13 -> -31 | BE13: =BF13-SUM(BB13:BD13) -> -294 | BF13: 833 | BG13: =-259 -> -259 | BH13: =-1412-BG13 -> -1153 | BI13: =-3502-BH13-BG13 -> -2090 | BJ13: =BK13-BI13-BH13-BG13 -> -2210 | BK13: =-5712 -> -5712 | BL13: =-1915 -> -1915 | BM13: =-3520-BL13 -> -1605 | BN13: =-5231-BM13-BL13 -> -1711 | BO13: =BP13-BN13-BM13-BL13 -> -1504 | BP13: =-6735 -> -6735 | BQ13: =-1107 -> -1107 | BR13: =-2008-BQ13 -> -901 | BS13: =-2799-SUM(BQ13:BR13) -> -791 | BT13: =-3440-BS13-BR13-BQ13 -> -641 | BU13: =+SUM(BQ13:BT13) -> -3440 | BV13: =0 -> 0 | BW13: =0 -> 0 | BX13: =0 -> 0 | BY13: =0 -> 0 | BZ13: =+SUM(BV13:BY13) -> 0 | CA13: =0 -> 0 | CB13: =0 -> 0 | CC13: =0 -> 0 | CD13: =0 -> 0 | CE13: =+SUM(CA13:CD13) -> 0
B14: Excess Tax Benefits Included in Deferred Tax Assets | H14: 0 | M14: 0 | N14: 0 | O14: -54 | P14: -77 | Q14: -128 | R14: -259 | S14: -91 | T14: -100 | U14: -124 | V14: -172 | W14: -487 | X14: -3095 | Y14: -618 | Z14: -1119 | AA14: -3868 | AB14: -8700 | AC14: 8368 | AD14: =8368-AC14 -> 0 | AE14: =7880-AD14-AC14 -> -488 | AF14: =+AG14-SUM(AC14:AE14) -> -7880 | AG14: 0 | AH14: 0 | AI14: 0 | AJ14: 0 | AK14: =+AL14-SUM(AH14:AJ14) -> 0 | AL14: 0 | AM14: 0 | AN14: 0 | AO14: 0 | AP14: 0 | AQ14: =+SUM(AM14:AP14) -> 0 | AV14: =+SUM(AR14:AU14) -> 0 | BA14: =+SUM(AW14:AZ14) -> 0 | BE14: =BF14-SUM(BB14:BD14) -> 0 | BJ14: =BK14-BI14-BH14-BG14 -> 0 | BO14: =BP14-BN14-BM14-BL14 -> 0 | BT14: =0-BS14-BR14-BQ14 -> 0 | BU14: =+SUM(BQ14:BT14) -> 0 | BZ14: =+SUM(BV14:BY14) -> 0 | CE14: =+SUM(CA14:CD14) -> 0
B15: Impairment of Intangible Assets | H15: 0 | M15: 0 | N15: 0 | O15: 0 | P15: 0 | Q15: 0 | R15: 0 | S15: 0 | T15: 0 | U15: 0 | V15: 255 | W15: 255 | X15: 0 | Y15: 0 | Z15: 0 | AA15: 0 | AB15: 0 | AC15: 0 | AD15: =0-AC15 -> 0 | AE15: =0-AD15-AC15 -> 0 | AF15: =+AG15-SUM(AC15:AE15) -> 0 | AG15: 0 | AH15: 0 | AI15: 0 | AJ15: 0 | AK15: =+AL15-SUM(AH15:AJ15) -> 0 | AL15: 0 | AM15: 0 | AN15: 0 | AO15: 0 | AP15: 0 | AQ15: =+SUM(AM15:AP15) -> 0 | AV15: =+SUM(AR15:AU15) -> 0 | BA15: =+SUM(AW15:AZ15) -> 0 | BE15: =BF15-SUM(BB15:BD15) -> 0 | BJ15: =BK15-BI15-BH15-BG15 -> 0 | BO15: =BP15-BN15-BM15-BL15 -> 0 | BT15: =0-BS15-BR15-BQ15 -> 0 | BU15: =+SUM(BQ15:BT15) -> 0 | BZ15: =+SUM(BV15:BY15) -> 0 | CE15: =+SUM(CA15:CD15) -> 0
B16: Excess Tax Benefits from Stock-Based Compensation | H16: 0 | M16: 0 | N16: 0 | O16: 0 | P16: 0 | Q16: 0 | R16: 0 | S16: 0 | T16: 0 | U16: 0 | V16: 0 | W16: 0 | X16: 0 | Y16: 0 | Z16: 0 | AA16: 0 | AB16: 0 | AC16: 0 | AD16: =0-AC16 -> 0 | AE16: =0-AD16-AC16 -> 0 | AF16: =+AG16-SUM(AC16:AE16) -> 7696 | AG16: 7696 | AH16: 0 | AI16: 0 | AJ16: 0 | AK16: =+AL16-SUM(AH16:AJ16) -> 0 | AL16: 0 | AM16: 0 | AN16: 0 | AO16: 0 | AP16: 0 | AQ16: =+SUM(AM16:AP16) -> 0 | AU16: =0-AR16-AS16-AT16 -> 0 | AV16: =+SUM(AR16:AU16) -> 0 | AW16: =0 -> 0 | BA16: =+SUM(AW16:AZ16) -> 0 | BE16: =BF16-SUM(BB16:BD16) -> 0 | BJ16: =BK16-BI16-BH16-BG16 -> 0 | BO16: =BP16-BN16-BM16-BL16 -> 0 | BT16: =0-BS16-BR16-BQ16 -> 0 | BU16: =+SUM(BQ16:BT16) -> 0 | BZ16: =+SUM(BV16:BY16) -> 0 | CE16: =+SUM(CA16:CD16) -> 0
B17: Deferred Income Taxes | H17: 0 | M17: 0 | N17: 0 | O17: 0 | P17: 0 | Q17: -22599 | R17: -22599 | S17: 1362 | T17: 1702 | U17: 2041 | V17: 1459 | W17: 6564 | X17: -1086 | Y17: 1001 | Z17: 1016 | AA17: -1371 | AB17: -440 | AC17: -22559 | AD17: =-20897-AC17 -> 1662 | AE17: =+-17631-AD17-AC17 -> 3266 | AF17: =+AG17-SUM(AC17:AE17) -> 7217 | AG17: -10414 | AH17: 140 | AI17: =681-AH17 -> 541 | AJ17: =+-4024-AI17-AH17 -> -4705 | AK17: =+AL17-SUM(AH17:AJ17) -> -120 | AL17: -4144 | AM17: 1643 | AN17: 1404 | AO17: 4249 | AP17: -201 | AQ17: =+SUM(AM17:AP17) -> 7095 | AR17: 1784 | AS17: -515 | AT17: 3792 | AU17: =3512-AR17-AS17-AT17 -> -1549 | AV17: =+SUM(AR17:AU17) -> 3512 | AW17: =-5162 -> -5162 | AX17: =-722-AW17 -> 4440 | AY17: =-15962-AW17-AX17 -> -15240 | AZ17: =BA17-AY17-AX17-AW17 -> 6240 | BA17: =-9722 -> -9722 | BB17: =-5095 -> -5095 | BC17: =-10861-BB17 -> -5766 | BD17: =-15599-BC17-BB17 -> -4738 | BE17: =BF17-SUM(BB17:BD17) -> -4652 | BF17: -20251 | BG17: =-4241 -> -4241 | BH17: =-9122-BG17 -> -4881 | BI17: =-11561-BH17-BG17 -> -2439 | BJ17: =BK17-BI17-BH17-BG17 -> -5075 | BK17: =-16636 -> -16636 | BL17: =-4111 -> -4111 | BM17: =-8165-BL17 -> -4054 | BN17: =-15374-BM17-BL17 -> -7209 | BO17: =BP17-BN17-BM17-BL17 -> -4091 | BP17: =-19465 -> -19465 | BQ17: =-4360 -> -4360 | BR17: =-8605-BQ17 -> -4245 | BS17: =6724-SUM(BQ17:BR17) -> 15329 | BT17: =8412-BS17-BR17-BQ17 -> 1688 | BU17: =+SUM(BQ17:BT17) -> 8412 | BV17: =+-(BS!BV17-BS!BT17) -> 0 | BW17: =+-(BS!BW17-BS!BV17) -> 0 | BX17: =+-(BS!BX17-BS!BW17) -> 0 | BY17: =+-(BS!BY17-BS!BX17) -> 0 | BZ17: =+SUM(BV17:BY17) -> 0 | CA17: =+-(BS!CA17-BS!BY17) -> 0 | CB17: =+-(BS!CB17-BS!CA17) -> 0 | CC17: =+-(BS!CC17-BS!CB17) -> 0 | CD17: =+-(BS!CD17-BS!CC17) -> 0 | CE17: =+SUM(CA17:CD17) -> 0
B18: Accounts Receivable | H18: -4014 | M18: -4343 | N18: 6680 | O18: -6313 | P18: -2409 | Q18: -2840 | R18: -4882 | S18: -5914 | T18: 4022 | U18: -3620 | V18: -4671 | W18: -10183 | X18: -169 | Y18: 2002 | Z18: -1570 | AA18: -5161 | AB18: -4898 | AC18: 5375 | AD18: =369-AC18 -> -5006 | AE18: =317-AD18-AC18 -> -52 | AF18: =+AG18-SUM(AC18:AE18) -> -18283 | AG18: -17966 | AH18: 14538 | AI18: =11876-AH18 -> -2662 | AJ18: =5800-AI18-AH18 -> -6076 | AK18: =+AL18-SUM(AH18:AJ18) -> -17298 | AL18: -11498 | AM18: 7962 | AN18: 4593 | AO18: 1800 | AP18: -16811 | AQ18: =+SUM(AM18:AP18) -> -2456 | AR18: 5190 | AS18: -3393 | AT18: 11554 | AU18: =-22631-AR18-AS18-AT18 -> -35982 | AV18: =+SUM(AR18:AU18) -> -22631 | AW18: =14819 -> 14819 | AX18: =13983-AW18 -> -836 | AY18: =15665-AW18-AX18 -> 1682 | AZ18: =BA18-AY18-AX18-AW18 -> -24886 | BA18: =-9221 -> -9221 | BB18: =19563 -> 19563 | BC18: =11009-BB18 -> -8554 | BD18: =9788-BC18-BB18 -> -1221 | BE18: =BF18-SUM(BB18:BD18) -> -23175 | BF18: -13387 | BG18: =19890 -> 19890 | BH18: =-3277-BG18 -> -23167 | BI18: =18137-BH18-BG18 -> 21414 | BJ18: =BK18-BI18-BH18-BG18 -> -43115 | BK18: =-24978 -> -24978 | BL18: =30404 -> 30404 | BM18: =36365-BL18 -> 5961 | BN18: =30848-BM18-BL18 -> -5517 | BO18: =BP18-BN18-BM18-BL18 -> -49937 | BP18: =-19089 -> -19089 | BQ18: =42782 -> 42782 | BR18: =35026-BQ18 -> -7756 | BS18: =35023-SUM(BQ18:BR18) -> -3 | BT18: =-7666-BS18-BR18-BQ18 -> -42689 | BU18: =+SUM(BQ18:BT18) -> -7666 | BV18: =+-(BS!BV9-BS!BT9) -> 39909.353 | BW18: =+-(BS!BW9-BS!BV9) -> -10667.921 | BX18: =+-(BS!BX9-BS!BW9) -> 9855.0708 | BY18: =+-(BS!BY9-BS!BX9) -> -59825.059 | BZ18: =+SUM(BV18:BY18) -> -20728.556 | CA18: =+-(BS!CA9-BS!BY9) -> 48069.493 | CB18: =+-(BS!CB9-BS!CA9) -> -5915.4181 | CC18: =+-(BS!CC9-BS!CB9) -> 7606.4197 | CD18: =+-(BS!CD9-BS!CC9) -> -56845.782 | CE18: =+SUM(CA18:CD18) -> -7085.288
B19: Prepaid Expenses and Other Assets | H19: 91 | M19: 510 | N19: 272 | O19: -1059 | P19: -451 | Q19: -2218 | R19: -3456 | S19: -670 | T19: 136 | U19: -1609 | V19: 1132 | W19: -1011 | X19: 573 | Y19: -656 | Z19: -1113 | AA19: -911 | AB19: -2107 | AC19: 981 | AD19: =+-1067-AC19 -> -2048 | AE19: =+-405-AD19-AC19 -> 662 | AF19: =+AG19-SUM(AC19:AE19) -> 352 | AG19: -53 | AH19: -2341 | AI19: =+-4073-AH19 -> -1732 | AJ19: =+-5733-AI19-AH19 -> -1660 | AK19: =+AL19-SUM(AH19:AJ19) -> -100 | AL19: -5833 | AM19: -3192 | AN19: -3671 | AO19: 378 | AP19: 556 | AQ19: =+SUM(AM19:AP19) -> -5929 | AR19: -1629 | AS19: -5096 | AT19: 654 | AU19: =-2329-AR19-AS19-AT19 -> 3742 | AV19: =+SUM(AR19:AU19) -> -2329 | AW19: =-6083 -> -6083 | AX19: =-6014-AW19 -> 69 | AY19: =-5460-AW19-AX19 -> 554 | AZ19: =BA19-AY19-AX19-AW19 -> -10206 | BA19: =-15666 -> -15666 | BB19: =6067 -> 6067 | BC19: =-1085-BB19 -> -7152 | BD19: =-1412-BC19-BB19 -> -327 | BE19: =BF19-SUM(BB19:BD19) -> 5290 | BF19: =3878 -> 3878 | BG19: =-1289 -> -1289 | BH19: =-7450-BG19 -> -6161 | BI19: =-4804-BH19-BG19 -> 2646 | BJ19: =BK19-BI19-BH19-BG19 -> 1397 | BK19: =-3407 -> -3407 | BL19: =-10126 -> -10126 | BM19: =-4489-BL19 -> 5637 | BN19: =-9900-BM19-BL19 -> -5411 | BO19: =BP19-BN19-BM19-BL19 -> -4755 | BP19: =-14655 -> -14655 | BQ19: =162 -> 162 | BR19: =-4609-BQ19 -> -4771 | BS19: =-13402-SUM(BQ19:BR19) -> -8793 | BT19: =-7821-BS19-BR19-BQ19 -> 5581 | BU19: =+SUM(BQ19:BT19) -> -7821 | BV19: =+-((BS!BV10-BS!BT10)+(BS!BV21-BS!BT21)) -> 1306.9374 | BW19: =+-((BS!BW10-BS!BV10)+(BS!BW21-BS!BV21)) -> -1813.5229 | BX19: =+-((BS!BX10-BS!BW10)+(BS!BX21-BS!BW21)) -> -11891.129 | BY19: =+-((BS!BY10-BS!BX10)+(BS!BY21-BS!BX21)) -> 14195.146 | BZ19: =+SUM(BV19:BY19) -> 1797.4311 | CA19: =+-((BS!CA10-BS!BY10)+(BS!CA21-BS!BY21)) -> 819.26287 | CB19: =+-((BS!CB10-BS!CA10)+(BS!CB21-BS!CA21)) -> -5640.2527 | CC19: =+-((BS!CC10-BS!CB10)+(BS!CC21-BS!CB21)) -> -258.09393 | CD19: =+-((BS!CD10-BS!CC10)+(BS!CD21-BS!CC21)) -> 699.91757 | CE19: =+SUM(CA19:CD19) -> -4379.1662
B20: Restricted Cash | H20: 0 | M20: 0 | N20: 0 | O20: 0 | P20: 0 | Q20: 0 | R20: 0 | S20: 0 | T20: 0 | U20: 0 | V20: 0 | W20: 0 | X20: 0 | Y20: 0 | Z20: 0 | AA20: -1200 | AB20: -1200 | AC20: 0 | AD20: =0-AC20 -> 0 | AE20: =0-AD20-AC20 -> 0 | AF20: =+AG20-SUM(AC20:AE20) -> 0 | AG20: 0 | AH20: 0 | AI20: 0 | AJ20: 0 | AK20: =+AL20-SUM(AH20:AJ20) -> 0 | AL20: 0 | AM20: 0 | AN20: 0 | AO20: 0 | AP20: 0 | AQ20: =+SUM(AM20:AP20) -> 0 | AR20: 0 | AS20: 0 | AT20: 0 | AU20: =0 -> 0 | AV20: =+SUM(AR20:AU20) -> 0 | BA20: =+SUM(AW20:AZ20) -> 0 | BE20: =BF20-SUM(BB20:BD20) -> 0 | BI20: =+-(BS!BI20-BS!BH20) -> 0 | BJ20: =BK20-BI20-BH20-BG20 -> 0 | BO20: =BP20-BN20-BM20-BL20 -> 0 | BQ20: =0 -> 0 | BR20: =+-(BS!BR20-BS!BQ20) -> 0 | BS20: =+-(BS!BS20-BS!BR20) -> 0 | BT20: =0-BS20-BR20-BQ20 -> 0 | BU20: =+SUM(BQ20:BT20) -> 0 | BV20: =+-(BS!BV20-BS!BT20) -> 0 | BW20: =+-(BS!BW20-BS!BV20) -> 0 | BX20: =+-(BS!BX20-BS!BW20) -> 0 | BY20: =+-(BS!BY20-BS!BX20) -> 0 | BZ20: =+SUM(BV20:BY20) -> 0 | CA20: =+-(BS!CA20-BS!BY20) -> 0 | CB20: =+-(BS!CB20-BS!CA20) -> 0 | CC20: =+-(BS!CC20-BS!CB20) -> 0 | CD20: =+-(BS!CD20-BS!CC20) -> 0 | CE20: =+SUM(CA20:CD20) -> 0
B21: Accounts Payable | H21: -242 | M21: -112 | N21: 80 | O21: -287 | P21: 159 | Q21: 2380 | R21: 2332 | S21: -3609 | T21: -1010 | U21: 1013 | V21: 313 | W21: -3293 | X21: 2026 | Y21: -2028 | Z21: -875 | AA21: -343 | AB21: -1220 | AC21: 255 | AD21: =+-206-AC21 -> -461 | AE21: =+-706-AD21-AC21 -> -500 | AF21: =+AG21-SUM(AC21:AE21) -> 252 | AG21: -454 | AH21: -302 | AI21: =+-331-AH21 -> -29 | AJ21: =182-AI21-AH21 -> 513 | AK21: =+AL21-SUM(AH21:AJ21) -> 474 | AL21: 656 | AM21: -1374 | AN21: 185 | AO21: -147 | AP21: 260 | AQ21: =+SUM(AM21:AP21) -> -1076 | AR21: -262 | AS21: 482 | AT21: 106 | AU21: =-389-AR21-AS21-AT21 -> -715 | AV21: =+SUM(AR21:AU21) -> -389 | AW21: =107 -> 107 | AX21: =947-AW21 -> 840 | AY21: =200-AW21-AX21 -> -747 | AZ21: =BA21-AY21-AX21-AW21 -> -232 | BA21: =-32 -> -32 | BB21: =599 -> 599 | BC21: =917-BB21 -> 318 | BD21: =841-BC21-BB21 -> -76 | BE21: =BF21-SUM(BB21:BD21) -> 1266 | BF21: =2107 -> 2107 | BG21: =-1215 -> -1215 | BH21: =-813-BG21 -> 402 | BI21: =-1428-BH21-BG21 -> -615 | BJ21: =BK21-BI21-BH21-BG21 -> -150 | BK21: =-1578 -> -1578 | BL21: =-335 -> -335 | BM21: =229-BL21 -> 564 | BN21: =391-BM21-BL21 -> 162 | BO21: =BP21-BN21-BM21-BL21 -> -172 | BP21: =219 -> 219 | BQ21: =-66 -> -66 | BR21: =699-BQ21 -> 765 | BS21: =591-SUM(BQ21:BR21) -> -108 | BT21: =27-BS21-BR21-BQ21 -> -564 | BU21: =+SUM(BQ21:BT21) -> 27 | BV21: =+(BS!BV27-BS!BT27) -> 340.13702 | BW21: =+(BS!BW27-BS!BV27) -> 347.85722 | BX21: =+(BS!BX27-BS!BW27) -> 21.461397 | BY21: =+(BS!BY27-BS!BX27) -> 26.57901 | BZ21: =+SUM(BV21:BY21) -> 736.03465 | CA21: =+(BS!CA27-BS!BY27) -> -293.34551 | CB21: =+(BS!CB27-BS!CA27) -> 327.04736 | CC21: =+(BS!CC27-BS!CB27) -> 28.595745 | CD21: =+(BS!CD27-BS!CC27) -> -12.283792 | CE21: =+SUM(CA21:CD21) -> 50.013797
B22: Accrued Liabilities | H22: -1163 | M22: 303 | N22: -593 | O22: -25 | P22: 982 | Q22: 1258 | R22: 1622 | S22: 1690 | T22: 156 | U22: 889 | V22: 604 | W22: 3339 | X22: 2822 | Y22: 2064 | Z22: 1877 | AA22: 2933 | AB22: 9696 | AC22: 463 | AD22: =109-AC22 -> -354 | AE22: =747-AD22-AC22 -> 638 | AF22: =+AG22-SUM(AC22:AE22) -> 738 | AG22: 1485 | AH22: 4577 | AI22: =6238-AH22 -> 1661 | AJ22: =5803-AI22-AH22 -> -435 | AK22: =+AL22-SUM(AH22:AJ22) -> 4719 | AL22: 10522 | AM22: 314 | AN22: -435 | AO22: 1396 | AP22: -803 | AQ22: =+SUM(AM22:AP22) -> 472 | AR22: 253 | AS22: -1225 | AT22: 1044 | AU22: =5126-AR22-AS22-AT22 -> 5054 | AV22: =+SUM(AR22:AU22) -> 5126 | AW22: =1686 -> 1686 | AX22: =3032-AW22 -> 1346 | AY22: =9912-AW22-AX22 -> 6880 | AZ22: =BA22-AY22-AX22-AW22 -> -590 | BA22: =9322 -> 9322 | BB22: =3435 -> 3435 | BC22: =3830-BB22 -> 395 | BD22: =3968-BC22-BB22 -> 138 | BE22: =BF22-SUM(BB22:BD22) -> -101 | BF22: =3867 -> 3867 | BG22: =-2 -> -2 | BH22: =8736-BG22 -> 8738 | BI22: =8211-BH22-BG22 -> -525 | BJ22: =BK22-BI22-BH22-BG22 -> -7760 | BK22: =451 -> 451 | BL22: =8892 -> 8892 | BM22: =-3215-BL22 -> -12107 | BN22: =-1351-BM22-BL22 -> 1864 | BO22: =BP22-BN22-BM22-BL22 -> 4296 | BP22: =2945 -> 2945 | BQ22: =8265 -> 8265 | BR22: =3683-BQ22 -> -4582 | BS22: =1568-SUM(BQ22:BR22) -> -2115 | BT22: =7195-BS22-BR22-BQ22 -> 5627 | BU22: =+SUM(BQ22:BT22) -> 7195 | BV22: =+(BS!BV28-BS!BT28) -> 1374.5938 | BW22: =+(BS!BW28-BS!BV28) -> -2428.7888 | BX22: =+(BS!BX28-BS!BW28) -> 1752.2809 | BY22: =+(BS!BY28-BS!BX28) -> 8274.0323 | BZ22: =+SUM(BV22:BY22) -> 8972.1182 | CA22: =+(BS!CA28-BS!BY28) -> 4034.0217 | CB22: =+(BS!CB28-BS!CA28) -> -16063.191 | CC22: =+(BS!CC28-BS!CB28) -> 5818.574 | CD22: =+(BS!CD28-BS!CC28) -> 11657.369 | CE22: =+SUM(CA22:CD22) -> 5446.7738
B23: Deferred Revenues | H23: 13683 | M23: 11281 | N23: 3924 | O23: 316 | P23: 2667 | Q23: 7910 | R23: 14817 | S23: 6782 | T23: -871 | U23: 4701 | V23: 10766 | W23: 21378 | X23: 2059 | Y23: 2178 | Z23: 6616 | AA23: 7050 | AB23: 17903 | AC23: 8012 | AD23: =10947-AC23 -> 2935 | AE23: =17716-AD23-AC23 -> 6769 | AF23: =+AG23-SUM(AC23:AE23) -> 12114 | AG23: 29830 | AH23: 2330 | AI23: =4424-AH23 -> 2094 | AJ23: =12351-AI23-AH23 -> 7927 | AK23: =+AL23-SUM(AH23:AJ23) -> 12374 | AL23: 24725 | AM23: 9855 | AN23: 2542 | AO23: 3016 | AP23: 12647 | AQ23: =+SUM(AM23:AP23) -> 28060 | AR23: 10577 | AS23: -4882 | AT23: 638 | AU23: =30927-AR23-AS23-AT23 -> 24594 | AV23: =+SUM(AR23:AU23) -> 30927 | AW23: =3874 -> 3874 | AX23: =12827-AW23 -> 8953 | AY23: =21033-AW23-AX23 -> 8206 | AZ23: =BA23-AY23-AX23-AW23 -> 25558 | BA23: =46591 -> 46591 | BB23: =7426 -> 7426 | BC23: =13458-BB23 -> 6032 | BD23: =12504-BC23-BB23 -> -954 | BE23: =BF23-SUM(BB23:BD23) -> 12685 | BF23: =25189 -> 25189 | BG23: =1228 -> 1228 | BH23: =20002-BG23 -> 18774 | BI23: =22248-BH23-BG23 -> 2246 | BJ23: =BK23-BI23-BH23-BG23 -> 25472 | BK23: =47720 -> 47720 | BL23: =-1498 -> -1498 | BM23: =-11792-BL23 -> -10294 | BN23: =-4001-BM23-BL23 -> 7791 | BO23: =BP23-BN23-BM23-BL23 -> 34785 | BP23: =30784 -> 30784 | BQ23: =-6825 -> -6825 | BR23: =-21522-BQ23 -> -14697 | BS23: =-7910-SUM(BQ23:BR23) -> 13612 | BT23: =21690-BS23-BR23-BQ23 -> 29600 | BU23: =+SUM(BQ23:BT23) -> 21690 | BV23: =+(BS!BV29-BS!BT29)+(BS!BV35-BS!BT35) -> -4794.23 | BW23: =+(BS!BW29-BS!BV29)+(BS!BW35-BS!BV35) -> -12636.761 | BX23: =+(BS!BX29-BS!BW29)+(BS!BX35-BS!BW35) -> 17991.523 | BY23: =+(BS!BY29-BS!BX29)+(BS!BY35-BS!BX35) -> 30185.23 | BZ23: =+SUM(BV23:BY23) -> 30745.761 | CA23: =+(BS!CA29-BS!BY29)+(BS!CA35-BS!BY35) -> -7479.173 | CB23: =+(BS!CB29-BS!CA29)+(BS!CB35-BS!CA35) -> -13529.559 | CC23: =+(BS!CC29-BS!CB29)+(BS!CC35-BS!CB35) -> 19242.623 | CD23: =+(BS!CD29-BS!CC29)+(BS!CD35-BS!CC35) -> 32289.806 | CE23: =+SUM(CA23:CD23) -> 30523.697
B24: Income Taxes Payable | H24: 181 | M24: 0 | N24: 0 | O24: 0 | P24: 0 | Q24: 0 | R24: 0 | S24: 0 | T24: 0 | U24: 0 | V24: 0 | W24: 0 | X24: 0 | Y24: 0 | Z24: 0 | AA24: 0 | AB24: 0 | AC24: 0 | AD24: =0-AC24 -> 0 | AE24: =0-AD24-AC24 -> 0 | AF24: =+AG24-SUM(AC24:AE24) -> 0 | AG24: 0 | AH24: 0 | AI24: 0 | AJ24: 0 | AK24: =+AL24-SUM(AH24:AJ24) -> 0 | AL24: 0 | AM24: 0 | AN24: 0 | AO24: 0 | AP24: 0 | AQ24: =+SUM(AM24:AP24) -> 0 | AR24: 0 | AS24: 0 | AT24: 0 | AU24: =0 -> 0 | AV24: =+SUM(AR24:AU24) -> 0 | AW24: =+(BS!AW36-BS!AU36) -> 0 | BA24: =+SUM(AW24:AZ24) -> 0 | BB24: =+(BS!BB36-BS!AZ36) -> 0 | BE24: =BF24-SUM(BB24:BD24) -> 0 | BI24: =+(BS!BI36-BS!BH36) -> 0 | BJ24: =BK24-BI24-BH24-BG24 -> 0 | BO24: =BP24-BN24-BM24-BL24 -> 0 | BQ24: =+(BS!BQ36-BS!BO36) -> 0 | BR24: =+(BS!BR36-BS!BQ36) -> 0 | BS24: =+(BS!BS36-BS!BR36) -> 0 | BT24: =0-BS24-BR24-BQ24 -> 0 | BU24: =+SUM(BQ24:BT24) -> 0 | BV24: =+(BS!BV36-BS!BT36) -> 0 | BW24: =+(BS!BW36-BS!BV36) -> 0 | BX24: =+(BS!BX36-BS!BW36) -> 0 | BY24: =+(BS!BY36-BS!BX36) -> 0 | BZ24: =+SUM(BV24:BY24) -> 0 | CA24: =+(BS!CA36-BS!BY36) -> 0 | CB24: =+(BS!CB36-BS!CA36) -> 0 | CC24: =+(BS!CC36-BS!CB36) -> 0 | CD24: =+(BS!CD36-BS!CC36) -> 0 | CE24: =+SUM(CA24:CD24) -> 0
B25: Other Noncurrent Liabilities | H25: 84 | M25: 164 | N25: 71 | O25: 30 | P25: -2 | Q25: -300 | R25: -201 | S25: 70 | T25: 73 | U25: 39 | V25: 47 | W25: 229 | X25: 406 | Y25: 279 | Z25: 503 | AA25: 267 | AB25: 1455 | AC25: 10 | AD25: =477-AC25 -> 467 | AE25: =1190-AD25-AC25 -> 713 | AF25: =+AG25-SUM(AC25:AE25) -> 6153 | AG25: 7343 | AH25: -1072 | AI25: =+-1026-AH25 -> 46 | AJ25: =+-1804-AI25-AH25 -> -778 | AK25: =+AL25-SUM(AH25:AJ25) -> -102 | AL25: -1906 | AM25: -32 | AN25: 185 | AO25: 7 | AP25: 0 | AQ25: =+SUM(AM25:AP25) -> 160 | AR25: 0 | AS25: 0 | AT25: 0 | AU25: =0 -> 0 | AV25: =+SUM(AR25:AU25) -> 0 | AW25: =0 -> 0 | AX25: =0-AW25 -> 0 | AY25: =0-AW25-AX25 -> 0 | AZ25: 0 | BA25: 0 | BE25: =BF25-SUM(BB25:BD25) -> 0 | BF25: =0 -> 0 | BH25: =533-BG25 -> 533 | BI25: =533-BH25-BG25 -> 0 | BJ25: =BK25-BI25-BH25-BG25 -> 0 | BK25: =533 -> 533 | BL25: 0 | BM25: =0 -> 0 | BN25: =0 -> 0 | BO25: =BP25-BN25-BM25-BL25 -> 0 | BQ25: =0 -> 0 | BR25: =0-BQ25 -> 0 | BS25: =0 -> 0 | BT25: =0 -> 0 | BU25: =+SUM(BQ25:BT25) -> 0 | BV25: =+(BS!BV39-BS!BT39) -> 0 | BW25: =+(BS!BW39-BS!BV39) -> 0 | BX25: =+(BS!BX39-BS!BW39) -> 0 | BY25: =+(BS!BY39-BS!BX39) -> 0 | BZ25: =+SUM(BV25:BY25) -> 0 | CA25: =+(BS!CA39-BS!BY39) -> 0 | CB25: =+(BS!CB39-BS!CA39) -> 0 | CC25: =+(BS!CC39-BS!CB39) -> 0 | CD25: =+(BS!CD39-BS!CC39) -> 0 | CE25: =+SUM(CA25:CD25) -> 0
D26: ______ | E26: ______ | F26: ______ | G26: ______ | H26: ______ | I26: ______ | J26: ______ | K26: ______ | L26: ______ | M26: ______ | N26: ______ | O26: ______ | P26: ______ | Q26: ______ | R26: ______ | S26: ______ | T26: ______ | U26: ______ | V26: ______ | W26: ______ | X26: ______ | Y26: ______ | Z26: ______ | AA26: ______ | AB26: ______ | AC26: ______ | AD26: ______ | AE26: ______ | AF26: ______ | AG26: ______ | AH26: ______ | AI26: ______ | AJ26: ______ | AK26: ______ | AL26: ______ | AM26: ______ | AN26: ______ | AO26: ______ | AP26: ______ | AQ26: ______ | AR26: ______ | AS26: ______ | AT26: ______ | AU26: ______ | AV26: ______ | AW26: ______ | AX26: ______ | AY26: ______ | AZ26: ______ | BA26: ______ | BB26: ______ | BC26: ______ | BD26: ______ | BE26: ______ | BF26: ______ | BG26: ______ | BH26: ______ | BI26: ______ | BJ26: ______ | BK26: ______ | BL26: ______ | BM26: ______ | BN26: ______ | BO26: ______ | BP26: ______ | BQ26: ______ | BR26: ______ | BS26: ______ | BT26: ______ | BU26: ______ | BV26: ______ | BW26: ______ | BX26: ______ | BY26: ______ | BZ26: ______ | CA26: ______ | CB26: ______ | CC26: ______ | CD26: ______ | CE26: ______
B27: Net Cash from Operating Activity | D27: =SUM(D7:D25) -> 0 | E27: =SUM(E7:E25) -> 0 | F27: =SUM(F7:F25) -> 0 | G27: =SUM(G7:G25) -> 0 | H27: =SUM(H7:H25) -> 21952 | I27: =SUM(I7:I25) -> 0 | J27: =SUM(J7:J25) -> 0 | K27: =SUM(K7:K25) -> 0 | ... AZ27: =SUM(AZ7:AZ25) -> 39875 | BA27: =200616 -> 200616 | BB27: =SUM(BB7:BB25) -> 79040 | BC27: =SUM(BC7:BC25) -> 33811 | BD27: =SUM(BD7:BD25) -> 42159 | BE27: =SUM(BE7:BE25) -> 43844 | BF27: =SUM(BF7:BF25) -> 198854 | BG27: =SUM(BG7:BG25) -> 66813 | BH27: =SUM(BH7:BH25) -> 51515 | BI27: =SUM(BI7:BI25) -> 92438 | ... CE27: =SUM(CE7:CE25) -> 332866.52
B29: Cash from Investing Activity
B30: Purchases of Investments | H30: -83547 | M30: -145263 | N30: -47451 | O30: -29456 | P30: -40372 | Q30: -40381 | R30: -157660 | S30: -31781 | T30: -29661 | U30: -27252 | V30: -58013 | W30: -146707 | X30: -49450 | Y30: -37914 | Z30: -92797 | AA30: -42792 | AB30: -222953 | AC30: -60201 | AD30: =+-102665-AC30 -> -42464 | AE30: =+-198866-AD30-AC30 -> -96201 | AF30: =+AG30-SUM(AC30:AE30) -> -101025 | AG30: -299891 | AH30: -72176 | AI30: =+-151825-AH30 -> -79649 | AJ30: =+-242056-AI30-AH30 -> -90231 | AK30: =+AL30-SUM(AH30:AJ30) -> -97806 | AL30: -339862 | AM30: -66224 | AN30: -118605 | AO30: -74457 | AP30: -71845 | AQ30: =+SUM(AM30:AP30) -> -331131 | AR30: -85567 | AS30: -77345 | AT30: -127622 | AU30: =-391693-AR30-AS30-AT30 -> -101159 | AV30: =+SUM(AR30:AU30) -> -391693 | AW30: =-115610 -> -115610 | AX30: =-201411-AW30 -> -85801 | AY30: =-255051-AW30-AX30 -> -53640 | AZ30: =BA30-AY30-AX30-AW30 -> -113399 | BA30: =-368450 -> -368450 | BB30: =-81800 -> -81800 | BC30: =-177171-BB30 -> -95371 | BD30: =-178788-BC30-BB30 -> -1617 | BE30: =BF30-SUM(BB30:BD30) -> 0 | BF30: =-178788 -> -178788 | BG30: =-46010 -> -46010 | BH30: =-159392-BG30 -> -113382 | BI30: =-252438-BH30-BG30 -> -93046 | BJ30: =BK30-BI30-BH30-BG30 -> -54374 | BK30: =-306812 -> -306812 | BL30: =-61340 -> -61340 | BM30: =-191812-BL30 -> -130472 | BN30: =-305952-BM30-BL30 -> -114140 | BO30: =BP30-BN30-BM30-BL30 -> -62325 | BP30: =-368277 -> -368277 | BQ30: =-55525 -> -55525 | BR30: =-183545-BQ30 -> -128020 | BS30: =-275379-SUM(BQ30:BR30) -> -91834 | BT30: =-349150-BS30-BR30-BQ30 -> -73771 | BU30: =+SUM(BQ30:BT30) -> -349150 | BV30: =0 -> 0 | BW30: =0 -> 0 | BX30: =0 -> 0 | BY30: =0 -> 0 | BZ30: =+SUM(BV30:BY30) -> 0 | CA30: =0 -> 0 | CB30: =0 -> 0 | CC30: =0 -> 0 | CD30: =0 -> 0 | CE30: =+SUM(CA30:CD30) -> 0
B31: Sales and Maturities of Investments | H31: 0 | M31: 138124 | N31: 41062 | O31: 23898 | P31: 79258 | Q31: 13121 | R31: 157339 | S31: 25977 | T31: 22237 | U31: 25126 | V31: 32169 | W31: 105509 | X31: 52176 | Y31: 22980 | Z31: 58552 | AA31: 16000 | AB31: 149708 | AC31: 63738 | AD31: =111288-AC31 -> 47550 | AE31: =148025-AD31-AC31 -> 36737 | AF31: =+AG31-SUM(AC31:AE31) -> 83971 | AG31: 231996 | AH31: 40080 | AI31: =120838-AH31 -> 80758 | AJ31: =218865-AI31-AH31 -> 98027 | AK31: =+AL31-SUM(AH31:AJ31) -> 66358 | AL31: 285223 | AM31: 91046 | AN31: 102224 | AO31: 70604 | AP31: 64476 | AQ31: =+SUM(AM31:AP31) -> 328350 | AR31: 129651 | AS31: 34458 | AT31: 99187 | AU31: =341879-AR31-AS31-AT31 -> 78583 | AV31: =+SUM(AR31:AU31) -> 341879 | AW31: =145044 -> 145044 | AX31: =205143-AW31 -> 60099 | AY31: =295336-AW31-AX31 -> 90193 | AZ31: =BA31-AY31-AX31-AW31 -> 69230 | BA31: =363941+625 -> 364566 | BB31: =84915 -> 84915 | BC31: =173922-BB31 -> 89007 | BD31: =290949-BC31-BB31 -> 117027 | BE31: =BF31-SUM(BB31:BD31) -> 56888 | BF31: =347837 -> 347837 | BG31: =69709 -> 69709 | BH31: =167120-BG31 -> 97411 | BI31: =212202-BH31-BG31 -> 45082 | BJ31: =BK31-BI31-BH31-BG31 -> 30230 | BK31: =242432 -> 242432 | BL31: =71463 -> 71463 | BM31: =198250-BL31 -> 126787 | BN31: =252940-BM31-BL31 -> 54690 | BO31: =BP31-BN31-BM31-BL31 -> 56244 | BP31: =309184 -> 309184 | BQ31: =50532 -> 50532 | BR31: =100770-BQ31 -> 50238 | BS31: =182322-SUM(BQ31:BR31) -> 81552 | BT31: =248216-BS31-BR31-BQ31 -> 65894 | BU31: =+SUM(BQ31:BT31) -> 248216 | BV31: =0 -> 0 | BW31: =0 -> 0 | BX31: =0 -> 0 | BY31: =0 -> 0 | BZ31: =+SUM(BV31:BY31) -> 0 | CA31: =0 -> 0 | CB31: =0 -> 0 | CC31: =0 -> 0 | CD31: =0 -> 0 | CE31: =+SUM(CA31:CD31) -> 0
A32: x | B32: Purchases of Property and Equipment | H32: -11188 | M32: -13663 | N32: -3778 | O32: -2717 | P32: -3757 | Q32: -3662 | R32: -13914 | S32: -6148 | T32: -4259 | U32: -4458 | V32: -5186 | W32: -20051 | X32: -4181 | Y32: -4785 | Z32: -9843 | AA32: -4436 | AB32: -23245 | AC32: -4543 | AD32: =+-13179-AC32 -> -8636 | AE32: =+-26612-AD32-AC32 -> -13433 | AF32: =+AG32-SUM(AC32:AE32) -> -11206 | AG32: -37818 | AH32: -5985 | AI32: =+-13240-AH32 -> -7255 | AJ32: =+-19496-AI32-AH32 -> -6256 | AK32: =+AL32-SUM(AH32:AJ32) -> -5616 | AL32: -25112 | AM32: -8608 | AN32: -5530 | AO32: -5335 | AP32: -8100 | AQ32: =+SUM(AM32:AP32) -> -27573 | AR32: -7271 | AS32: -4297 | AT32: -11174 | AU32: =-30037-AR32-AS32-AT32 -> -7295 | AV32: =+SUM(AR32:AU32) -> -30037 | AW32: =-6259 -> -6259 | AX32: =-12911-AW32 -> -6652 | AY32: =-20089-AW32-AX32 -> -7178 | AZ32: =BA32-AY32-AX32-AW32 -> -4335 | BA32: =-24424 -> -24424 | BB32: =-7639 -> -7639 | BC32: =-11150-BB32 -> -3511 | BD32: =-12391-BC32-BB32 -> -1241 | BE32: =BF32-SUM(BB32:BD32) -> -2970 | BF32: =-15361 -> -15361 | BG32: =-4037 -> -4037 | BH32: =-5455-BG32 -> -1418 | BI32: =-7263-BH32-BG32 -> -1808 | BJ32: =BK32-BI32-BH32-BG32 -> -1523 | BK32: =-8786 -> -8786 | BL32: =-2051 -> -2051 | BM32: =-3077-BL32 -> -1026 | BN32: =-6497-BM32-BL32 -> -3420 | BO32: =BP32-BN32-BM32-BL32 -> -5837 | BP32: =-12334 -> -12334 | BQ32: =-2038 -> -2038 | BR32: =-3365-BQ32 -> -1327 | BS32: =-4266-SUM(BQ32:BR32) -> -901 | BT32: =-4990-BS32-BR32-BQ32 -> -724 | BU32: =+BS!BU83*-1 -> -4990 | BV32: =+BS!BV83*-1 -> -1908.3946 | BW32: =+BS!BW83*-1 -> -2657.8044 | BX32: =+BS!BX83*-1 -> -2739.3472 | BY32: =+BS!BY83*-1 -> -2813.2761 | BZ32: =+BS!BZ83*-1 -> -10118.822 | CA32: =+BS!CA83*-1 -> -1873.6965 | CB32: =+BS!CB83*-1 -> -1895.9005 | ... CE32: =+BS!CE83*-1 -> -7693.4508
B33: Capitalized Software Development Costs | H33: 0 | M33: 0 | N33: 0 | O33: 0 | P33: 0 | Q33: -98 | R33: -98 | S33: -99 | T33: 0 | U33: 0 | V33: 0 | W33: -99 | X33: -118 | Y33: 118 | Z33: 0 | AA33: 0 | AB33: 0 | AC33: 0 | AD33: =0-AC33 -> 0 | AE33: =0-AD33-AC33 -> 0 | AF33: =+AG33-SUM(AC33:AE33) -> 0 | AG33: 0 | AH33: 0 | AI33: 0 | AJ33: 0 | AK33: =+AL33-SUM(AH33:AJ33) -> 0 | AL33: 0 | AM33: 0 | AN33: 0 | AO33: 0 | AP33: 0 | AQ33: =+SUM(AM33:AP33) -> 0 | AV33: =+SUM(AR33:AU33) -> 0 | AZ33: 0 | BA33: =+SUM(AW33:AZ33) -> 0 | BE33: =BF33-SUM(BB33:BD33) -> 0 | BJ33: =BK33-BI33-BH33-BG33 -> 0 | BU33: =+SUM(BQ33:BT33) -> 0 | BZ33: =+SUM(BV33:BY33) -> 0 | CE33: =+SUM(CA33:CD33) -> 0
B34: Release of Restricted Cash | H34: 0 | M34: 114 | N34: 0 | O34: 0 | P34: 0 | Q34: 0 | R34: 0 | S34: 0 | T34: 0 | U34: 0 | V34: 0 | W34: 0 | X34: 0 | Y34: 0 | Z34: 0 | AA34: 0 | AB34: 0 | AC34: 0 | AD34: =0-AC34 -> 0 | AE34: =0-AD34-AC34 -> 0 | AF34: =+AG34-SUM(AC34:AE34) -> 0 | AG34: 0 | AH34: 0 | AI34: 0 | AJ34: 0 | AK34: =+AL34-SUM(AH34:AJ34) -> 0 | AL34: 0 | AM34: 0 | AN34: 0 | AO34: 0 | AP34: 0 | AQ34: =+SUM(AM34:AP34) -> 0 | AV34: =+SUM(AR34:AU34) -> 0 | AZ34: 0 | BA34: =+SUM(AW34:AZ34) -> 0 | BE34: =BF34-SUM(BB34:BD34) -> 0 | BJ34: =BK34-BI34-BH34-BG34 -> 0 | BU34: =+SUM(BQ34:BT34) -> 0 | BZ34: =+SUM(BV34:BY34) -> 0 | CE34: =+SUM(CA34:CD34) -> 0
A35: x | B35: Purchases of Intangible Assets & Other | H35: -49 | M35: 0 | N35: 0 | O35: 0 | P35: 0 | Q35: 0 | R35: 0 | S35: 0 | T35: 0 | U35: 0 | V35: 0 | W35: 0 | X35: 0 | Y35: 0 | Z35: 0 | AA35: 0 | AB35: 0 | AC35: 0 | AD35: =0-AC35 -> 0 | AE35: =0-AD35-AC35 -> 0 | AF35: =+AG35-SUM(AC35:AE35) -> 0 | AG35: 0 | AH35: 0 | AI35: 0 | AJ35: 0 | AK35: =+AL35-SUM(AH35:AJ35) -> 0 | AL35: 0 | AM35: 0 | AN35: 0 | AO35: -625 | AP35: 0 | AQ35: =+SUM(AM35:AP35) -> -625 | AR35: 0 | AS35: 0 | AT35: 0 | AU35: =419-AR35-AS35-AT35 -> 419 | AV35: =+SUM(AR35:AU35) -> 419 | AW35: =0 -> 0 | AX35: =6-AW35 -> 6 | AY35: =6-AW35-AX35 -> 0 | AZ35: =BA35-AY35-AX35-AW35 -> -1236 | BA35: =-1230 -> -1230 | BB35: 0 | BC35: 0 | BD35: =-120-BC35-BB35 -> -120 | BE35: =BF35-SUM(BB35:BD35) -> -8500 | BF35: =-8620 -> -8620 | BJ35: =BK35-BI35-BH35-BG35 -> 0 | BK35: =0 -> 0 | BL35: =0 -> 0 | BM35: =0 -> 0 | BN35: =0 -> 0 | BO35: =0 -> 0 | BP35: =0 -> 0 | BQ35: =0 -> 0 | BR35: =0 -> 0 | BS35: =0 -> 0 | BT35: =0-BS35-BR35-BQ35 -> 0 | BU35: =+BS!BU94*-1 -> 0 | BV35: =+BS!BV94*-1 -> 0 | BW35: =+BS!BW94*-1 -> 0 | BX35: =+BS!BX94*-1 -> 0 | BY35: =+BS!BY94*-1 -> 0 | BZ35: =+BS!BZ94*-1 -> 0 | CA35: =+BS!CA94*-1 -> 0 | CB35: =+BS!CB94*-1 -> 0 | ... CE35: =+BS!CE94*-1 -> 0
B36: Acquisition of Business, Net | H36: 0 | M36: 0 | N36: 0 | O36: 0 | P36: 0 | Q36: 0 | R36: 0 | S36: 0 | T36: 0 | U36: 0 | V36: 0 | W36: 0 | X36: 0 | Y36: 0 | Z36: 0 | AA36: 0 | AB36: 0 | AC36: 0 | AD36: =0-AC36 -> 0 | AE36: =+-5753-AD36-AC36 -> -5753 | AF36: =+AG36-SUM(AC36:AE36) -> -6729 | AG36: -12482 | AH36: 0 | AI36: =+-3359-2500-AH36 -> -5859 | AJ36: =+-3359-2500-AI36-AH36 -> 0 | AK36: =+AL36-SUM(AH36:AJ36) -> -10274 | AL36: =+-13633-2500 -> -16133 | AM36: -850 | AN36: -1000 | AO36: 0 | AP36: -2200 | AQ36: =+SUM(AM36:AP36) -> -4050 | AR36: =0 -> 0 | AS36: =0-AR36 -> 0 | AT36: -1500 | AU36: =-1500-AR36-AS36-AT36 -> 0 | AV36: =+SUM(AR36:AU36) -> -1500 | AW36: =0 -> 0 | AX36: =0-AW36 -> 0 | AY36: =-1080-AW36-AX36 -> -1080 | AZ36: 0 | BA36: 0 | BB36: 0 | BC36: 0 | BD36: 0 | BE36: =BF36-SUM(BB36:BD36) -> 0 | BF36: =0 -> 0 | BJ36: =BK36-BI36-BH36-BG36 -> 0 | BK36: =0 -> 0 | BL36: =0 -> 0 | BM36: =0 -> 0 | BN36: =0 -> 0 | BO36: =0 -> 0 | BP36: =0 -> 0 | BQ36: =0 -> 0 | BR36: =0 -> 0 | BS36: =0 -> 0 | BT36: =0-BS36-BR36-BQ36 -> 0 | BU36: =+SUM(BQ36:BT36) -> 0 | BV36: =0 -> 0 | BW36: =0 -> 0 | BX36: =0 -> 0 | BY36: =0 -> 0 | BZ36: =+SUM(BV36:BY36) -> 0 | CA36: =0 -> 0 | CB36: =0 -> 0 | CC36: =0 -> 0 | CD36: =0 -> 0 | CE36: =+SUM(CA36:CD36) -> 0
D37: ______ | E37: ______ | F37: ______ | G37: ______ | H37: ______ | I37: ______ | J37: ______ | K37: ______ | L37: ______ | M37: ______ | N37: ______ | O37: ______ | P37: ______ | Q37: ______ | R37: ______ | S37: ______ | T37: ______ | U37: ______ | V37: ______ | W37: ______ | X37: ______ | Y37: ______ | Z37: ______ | AA37: ______ | AB37: ______ | AC37: ______ | AD37: ______ | AE37: ______ | AF37: ______ | AG37: ______ | AH37: ______ | AI37: ______ | AJ37: ______ | AK37: ______ | AL37: ______ | AM37: ______ | AN37: ______ | AO37: ______ | AP37: ______ | AQ37: ______ | AR37: ______ | AS37: ______ | AT37: ______ | AU37: ______ | AV37: ______ | AW37: ______ | AX37: ______ | AY37: ______ | AZ37: ______ | BA37: ______ | BB37: ______ | BC37: ______ | BD37: ______ | BE37: ______ | BF37: ______ | BG37: ______ | BH37: ______ | BI37: ______ | BJ37: ______ | BK37: ______ | BL37: ______ | BM37: ______ | BN37: ______ | BO37: ______ | BP37: ______ | BQ37: ______ | BR37: ______ | BS37: ______ | BT37: ______ | BU37: ______ | BV37: ______ | BW37: ______ | BX37: ______ | BY37: ______ | BZ37: ______ | CA37: ______ | CB37: ______ | CC37: ______ | CD37: ______ | CE37: ______
B38: Net Cash from Investing Activity | D38: =+SUM(D30:D36) -> 0 | E38: =+SUM(E30:E36) -> 0 | F38: =+SUM(F30:F36) -> 0 | G38: =+SUM(G30:G36) -> 0 | H38: =+SUM(H30:H36) -> -94784 | I38: =+SUM(I30:I36) -> 0 | J38: =+SUM(J30:J36) -> 0 | K38: =+SUM(K30:K36) -> 0 | ... AY38: =+SUM(AY30:AY36) -> 28295 | AZ38: =BA38-AY38-AX38-AW38 -> -48654 | BA38: =-29532 -> -29532 | BB38: =+SUM(BB30:BB36) -> -4524 | BC38: =+SUM(BC30:BC36) -> -9875 | BD38: =+SUM(BD30:BD36) -> 114049 | BE38: =+SUM(BE30:BE36) -> 45418 | BF38: =+SUM(BF30:BF36) -> 145068 | BG38: =+SUM(BG30:BG36) -> 19662 | BH38: =+SUM(BH30:BH36) -> -17389 | BI38: =+SUM(BI30:BI36) -> -49772 | ... CE38: =+SUM(CE30:CE36) -> -7693.4508
B40: Cash Flows from Financing Activity
B41: Proceeds from Initial Public Offering, net of Offering Costs | H41: 84534 | M41: 0 | N41: 0 | O41: 0 | P41: 0 | Q41: 0 | R41: 0 | S41: 0 | T41: 0 | U41: 0 | V41: 0 | W41: 0 | X41: 0 | Y41: 0 | Z41: 0 | AA41: 0 | AB41: 0 | AC41: 0 | AD41: =0-AC41 -> 0 | AE41: =0-AD41-AC41 -> 0 | AF41: =+AG41-SUM(AC41:AE41) -> 0 | AG41: 0 | AH41: 0 | AI41: 0 | AJ41: 0 | AK41: =+AL41-SUM(AH41:AJ41) -> 0 | AL41: 0 | AM41: 0 | AN41: 0 | AO41: 0 | AP41: 0 | AQ41: =+SUM(AM41:AP41) -> 0 | AU41: =0-AR41-AS41-AT41 -> 0 | AV41: =+SUM(AR41:AU41) -> 0 | BA41: =+SUM(AW41:AZ41) -> 0 | BF41: =+SUM(BB41:BE41) -> 0 | BK41: =+SUM(BG41:BJ41) -> 0 | BP41: =+SUM(BL41:BO41) -> 0 | BU41: =+SUM(BQ41:BT41) -> 0 | BZ41: =+SUM(BV41:BY41) -> 0 | CE41: =+SUM(CA41:CD41) -> 0
B42: Proceeds from Exercise of Stock Options | H42: 1685 | M42: 4073 | N42: 1256 | O42: 1826 | P42: 1964 | Q42: 2593 | R42: 7639 | S42: 3448 | T42: 2099 | U42: 1047 | V42: 3501 | W42: 10095 | X42: 2113 | Y42: 7383 | Z42: 3033 | AA42: 2628 | AB42: 15157 | AC42: 5602 | AD42: =14603-AC42 -> 9001 | AE42: =22778-AD42-AC42 -> 8175 | AF42: =+AG42-SUM(AC42:AE42) -> 8549 | AG42: 31327 | AH42: 7933 | AI42: =12174-AH42 -> 4241 | AJ42: =20896-AI42-AH42 -> 8722 | AK42: =+AL42-SUM(AH42:AJ42) -> 3157 | AL42: 24053 | AM42: 4047 | AN42: 4944 | AO42: 2023 | AP42: 13817 | AQ42: =+SUM(AM42:AP42) -> 24831 | AR42: 4714 | AS42: 15716 | AT42: 3532 | AU42: =34461-AR42-AS42-AT42 -> 10499 | AV42: =+SUM(AR42:AU42) -> 34461 | AW42: =2264 -> 2264 | AX42: =4438-AW42 -> 2174 | AY42: =10948-AW42-AX42 -> 6510 | AZ42: =BA42-AY42-AX42-AW42 -> 39046 | BA42: =49994 -> 49994 | BB42: =2569 -> 2569 | BC42: =9073-BB42 -> 6504 | BD42: =23161-BC42-BB42+4445 -> 18533 | BE42: =BF42-SUM(BB42:BD42) -> -3123 | BF42: 24483 | BG42: =2328 -> 2328 | BH42: =7148-BG42 -> 4820 | BI42: =28384-BH42-BG42 -> 21236 | BJ42: =BK42-BI42-BH42-BG42 -> 17192 | BK42: =45576 -> 45576 | BL42: =2770 -> 2770 | BM42: =5970-BL42 -> 3200 | BN42: =8311-BM42-BL42 -> 2341 | BO42: =BP42-BN42-BM42-BL42 -> 8958 | BP42: =17269 -> 17269 | BQ42: =2599 -> 2599 | BR42: =5577-BQ42 -> 2978 | BS42: =8856-SUM(BQ42:BR42) -> 3279 | BT42: =16294-BS42-BR42-BQ42 -> 7438 | BU42: =+SUM(BQ42:BT42) -> 16294 | BV42: =0 -> 0 | BW42: =0 -> 0 | BX42: =0 -> 0 | BY42: =0 -> 0 | BZ42: =+SUM(BV42:BY42) -> 0 | CA42: =0 -> 0 | CB42: =0 -> 0 | CC42: =0 -> 0 | CD42: =0 -> 0 | CE42: =+SUM(CA42:CD42) -> 0
B43: Proceeds from Early Exercise of Stock Options | H43: 384 | M43: 40 | N43: 0 | O43: 0 | P43: 0 | Q43: 0 | R43: 0 | S43: 0 | T43: 0 | U43: 0 | V43: 0 | W43: 0 | X43: 0 | Y43: 0 | Z43: 0 | AA43: 0 | AB43: 0 | AC43: 0 | AD43: =0-AC43 -> 0 | AE43: =0-AD43-AC43 -> 0 | AF43: =+AG43-SUM(AC43:AE43) -> 0 | AG43: 0 | AH43: 0 | AI43: 0 | AJ43: 0 | AK43: =+AL43-SUM(AH43:AJ43) -> 0 | AL43: 0 | AM43: 0 | AN43: 0 | AO43: 0 | AP43: 0 | AQ43: =+SUM(AM43:AP43) -> 0 | AU43: =0-AR43-AS43-AT43 -> 0 | AV43: =+SUM(AR43:AU43) -> 0 | BA43: =+SUM(AW43:AZ43) -> 0 | BE43: =BF43-SUM(BB43:BD43) -> 0 | BJ43: =BK43-BI43-BH43-BG43 -> 0 | BO43: =BP43-BN43-BM43-BL43 -> 0 | BR43: =0 -> 0 | BS43: =0 -> 0 | BU43: =+SUM(BQ43:BT43) -> 0 | BV43: =0 -> 0 | BW43: =0 -> 0 | BX43: =0 -> 0 | BY43: =0 -> 0 | BZ43: =+SUM(BV43:BY43) -> 0 | CA43: =0 -> 0 | CB43: =0 -> 0 | CC43: =0 -> 0 | CD43: =0 -> 0 | CE43: =+SUM(CA43:CD43) -> 0
B44: Excess Tax Benefits from Stock-Based Compensation | H44: 0 | M44: 150 | N44: 17 | O44: 37 | P44: 77 | Q44: 128 | R44: 259 | S44: 91 | T44: 100 | U44: 124 | V44: 172 | W44: 487 | X44: 3095 | Y44: 618 | Z44: 1119 | AA44: 3868 | AB44: 8700 | AC44: 0 | AD44: =0-AC44 -> 0 | AE44: =0-AD44-AC44 -> 0 | AF44: =+AG44-SUM(AC44:AE44) -> 0 | AG44: 0 | AH44: 0 | AI44: 0 | AJ44: 0 | AK44: =+AL44-SUM(AH44:AJ44) -> 0 | AL44: 0 | AM44: 0 | AN44: 0 | AO44: 0 | AP44: 0 | AQ44: =+SUM(AM44:AP44) -> 0 | AU44: =0-AR44-AS44-AT44 -> 0 | AV44: =+SUM(AR44:AU44) -> 0 | BA44: =+SUM(AW44:AZ44) -> 0 | BE44: =BF44-SUM(BB44:BD44) -> 0 | BJ44: =BK44-BI44-BH44-BG44 -> 0 | BO44: =BP44-BN44-BM44-BL44 -> 0 | BR44: =0 -> 0 | BS44: =0 -> 0 | BU44: =+SUM(BQ44:BT44) -> 0 | BV44: =0 -> 0 | BW44: =0 -> 0 | BX44: =0 -> 0 | BY44: =0 -> 0 | BZ44: =+SUM(BV44:BY44) -> 0 | CA44: =0 -> 0 | CB44: =0 -> 0 | CC44: =0 -> 0 | CD44: =0 -> 0 | CE44: =+SUM(CA44:CD44) -> 0
B45: Proceeds from Issuance of Series C Preferred Stock | H45: 0 | M45: 0 | N45: 0 | O45: 0 | P45: 0 | Q45: 0 | R45: 0 | S45: 0 | T45: 0 | U45: 0 | V45: 0 | W45: 0 | X45: 0 | Y45: 0 | Z45: 0 | AA45: 0 | AB45: 0 | AC45: 0 | AD45: =0-AC45 -> 0 | AE45: =0-AD45-AC45 -> 0 | AF45: =+AG45-SUM(AC45:AE45) -> 0 | AG45: 0 | AH45: 0 | AI45: 0 | AJ45: 0 | AK45: =+AL45-SUM(AH45:AJ45) -> 0 | AL45: 0 | AM45: 0 | AN45: 0 | AO45: 0 | AP45: 0 | AQ45: =+SUM(AM45:AP45) -> 0 | AU45: =0-AR45-AS45-AT45 -> 0 | AV45: =+SUM(AR45:AU45) -> 0 | BA45: =+SUM(AW45:AZ45) -> 0 | BE45: =BF45-SUM(BB45:BD45) -> 0 | BJ45: =BK45-BI45-BH45-BG45 -> 0 | BO45: =BP45-BN45-BM45-BL45 -> 0 | BR45: =0 -> 0 | BS45: =0 -> 0 | BU45: =+SUM(BQ45:BT45) -> 0 | BV45: =0 -> 0 | BW45: =0 -> 0 | BX45: =0 -> 0 | BY45: =0 -> 0 | BZ45: =+SUM(BV45:BY45) -> 0 | CA45: =0 -> 0 | CB45: =0 -> 0 | CC45: =0 -> 0 | CD45: =0 -> 0 | CE45: =+SUM(CA45:CD45) -> 0
B46: Payments for Taxes Related to Net Share Settlement of Equity Awards | H46: 0 | M46: 0 | N46: 0 | O46: 0 | P46: 0 | Q46: 0 | R46: 0 | S46: 0 | T46: 0 | U46: 0 | V46: 0 | W46: 0 | X46: 0 | Y46: 0 | Z46: -202 | AA46: -236 | AB46: -438 | AC46: -14107 | AD46: =+-15154-AC46 -> -1047 | AE46: =+-17571-AD46-AC46 -> -2417 | AF46: =+AG46-SUM(AC46:AE46) -> -3353 | AG46: -20924 | AH46: -4030 | AI46: =+-8935-AH46 -> -4905 | AJ46: =+-12010-AI46-AH46 -> -3075 | AK46: =+AL46-SUM(AH46:AJ46) -> -2869 | AL46: -14879 | AM46: -3367 | AN46: -4044 | AO46: -3453 | AP46: -4879 | AQ46: =+SUM(AM46:AP46) -> -15743 | AR46: -5000 | AS46: -6115 | AT46: -5223 | AU46: =-20199-AR46-AS46-AT46 -> -3861 | AV46: =+SUM(AR46:AU46) -> -20199 | AW46: =-17643 -> -17643 | AX46: =-21017-AW46 -> -3374 | AY46: =-24194-AW46-AX46 -> -3177 | AZ46: =BA46-AY46-AX46-AW46 -> -3621 | BA46: =-27815 -> -27815 | BB46: =-3631 -> -3631 | BC46: =-8161-BB46 -> -4530 | BD46: =-12853-BC46-BB46 -> -4692 | BE46: =BF46-SUM(BB46:BD46) -> -4762 | BF46: =-17615 -> -17615 | BG46: =-5105 -> -5105 | BH46: =-9494-BG46 -> -4389 | BI46: =-14998-BH46-BG46 -> -5504 | BJ46: =BK46-BI46-BH46-BG46 -> -7348 | BK46: =-22346 -> -22346 | BL46: =-11808 -> -11808 | BM46: =-17711-BL46 -> -5903 | BN46: =-23093-BM46-BL46 -> -5382 | BO46: =BP46-BN46-BM46-BL46 -> -5323 | BP46: =-28416 -> -28416 | BQ46: =-10831 -> -10831 | BR46: =-15267-BQ46 -> -4436 | BS46: =-20200-SUM(BQ46:BR46) -> -4933 | BT46: =-25020-BS46-BR46-BQ46 -> -4820 | BU46: =+SUM(BQ46:BT46) -> -25020 | BV46: =0 -> 0 | BW46: =0 -> 0 | BX46: =0 -> 0 | BY46: =0 -> 0 | BZ46: =+SUM(BV46:BY46) -> 0 | CA46: =0 -> 0 | CB46: =0 -> 0 | CC46: =0 -> 0 | CD46: =0 -> 0 | CE46: =+SUM(CA46:CD46) -> 0
B47: Principal Payments Under Capital Lease Obligations | H47: -2401 | M47: -1186 | N47: -267 | O47: -269 | P47: -269 | Q47: 0 | R47: -805 | S47: 0 | T47: 0 | U47: 0 | V47: 0 | W47: 0 | X47: 0 | Y47: 0 | Z47: 0 | AA47: 0 | AB47: 0 | AC47: 0 | AD47: =0-AC47 -> 0 | AE47: =0-AD47-AC47 -> 0 | AF47: =+AG47-SUM(AC47:AE47) -> 0 | AG47: 0 | AH47: -747 | AI47: =+-794-AH47 -> -47 | AJ47: =+-1203-AI47-AH47 -> -409 | AK47: =+AL47-SUM(AH47:AJ47) -> -414 | AL47: -1617 | AM47: -419 | AN47: -417 | AO47: -437 | AP47: -436 | AQ47: =+SUM(AM47:AP47) -> -1709 | AR47: -30 | AS47: -31 | AT47: -31 | AU47: =-114-AR47-AS47-AT47 -> -22 | AV47: =+SUM(AR47:AU47) -> -114 | AW47: =0 -> 0 | AX47: =-90-AW47 -> -90 | AY47: =-90-AW47-AX47 -> 0 | AZ47: =BA47-AY47-AX47-AW47 -> 0 | BA47: =-90 -> -90 | BB47: 0 | BC47: 0 | BD47: 0 | BE47: =BF47-SUM(BB47:BD47) -> 0 | BF47: =0 -> 0 | BJ47: =BK47-BI47-BH47-BG47 -> 0 | BK47: =0 -> 0 | BL47: =0 -> 0 | BM47: =0 -> 0 | BN47: =0 -> 0 | BO47: =0 -> 0 | BP47: =0 -> 0 | BQ47: =0 -> 0 | BR47: =0 -> 0 | ... BT47: =0 -> 0 | BU47: =+SUM(BQ47:BT47) -> 0 | BV47: =0 -> 0 | BW47: =0 -> 0 | BX47: =0 -> 0 | BY47: =0 -> 0 | BZ47: =+SUM(BV47:BY47) -> 0 | CA47: =0 -> 0 | CB47: =0 -> 0 | CC47: =0 -> 0 | CD47: =0 -> 0 | CE47: =+SUM(CA47:CD47) -> 0
B48: Non-Contingent Payment Related to Acquisition | H48: -1000 | M48: 0 | N48: 0 | O48: 0 | P48: 0 | Q48: 0 | R48: 0 | S48: 0 | T48: 0 | U48: 0 | V48: 0 | W48: 0 | X48: 0 | Y48: 0 | Z48: 0 | AA48: 0 | AB48: 0 | AC48: 0 | AD48: =0-AC48 -> 0 | AE48: =0-AD48-AC48 -> 0 | AF48: =+AG48-SUM(AC48:AE48) -> 0 | AG48: 0 | AH48: 0 | AI48: 0 | AJ48: 0 | AK48: =+AL48-SUM(AH48:AJ48) -> 0 | AL48: 0 | AM48: 0 | AN48: 0 | AO48: 0 | AP48: 0 | AQ48: =+SUM(AM48:AP48) -> 0 | AU48: =0-AR48-AS48-AT48 -> 0 | AV48: =+SUM(AR48:AU48) -> 0 | BA48: =+SUM(AW48:AZ48) -> 0 | BE48: =BF48-SUM(BB48:BD48) -> 0 | BF48: =0 -> 0 | BJ48: =BK48-BI48-BH48-BG48 -> 0 | BK48: =0 -> 0 | BL48: =-1500 -> -1500 | BM48: =-1500-BL48 -> 0 | BN48: =-1500-BM48-BL48 -> 0 | BO48: =BP48-BN48-BM48-BL48 -> 0 | BP48: =-1500 -> -1500 | BQ48: =0 -> 0 | BR48: =0 -> 0 | BS48: =0 -> 0 | BU48: =+SUM(BQ48:BT48) -> 0 | BV48: =0 -> 0 | BW48: =0 -> 0 | BX48: =0 -> 0 | BY48: =0 -> 0 | BZ48: =+SUM(BV48:BY48) -> 0 | CA48: =0 -> 0 | CB48: =0 -> 0 | CC48: =0 -> 0 | CD48: =0 -> 0 | CE48: =+SUM(CA48:CD48) -> 0
B49: Current Portion of Long Term Debt | H49: 0 | M49: 0 | N49: 0 | O49: 0 | P49: 0 | Q49: 0 | R49: 0 | S49: 0 | T49: 0 | U49: 0 | V49: 0 | W49: 0 | X49: 0 | Y49: 0 | Z49: 0 | AA49: 0 | AB49: 0 | AC49: 0 | AD49: 0 | AE49: 0 | AF49: =+AG49-SUM(AC49:AE49) -> 0 | AG49: 0 | AH49: 0 | AI49: 0 | AJ49: 0 | AK49: =+AL49-SUM(AH49:AJ49) -> 0 | AL49: 0 | AM49: 0 | AN49: 0 | AO49: 0 | AP49: 0 | AQ49: =+SUM(AM49:AP49) -> 0 | AU49: =0-AR49-AS49-AT49 -> 0 | AV49: =+SUM(AR49:AU49) -> 0 | BA49: =+SUM(AW49:AZ49) -> 0 | BE49: =BF49-SUM(BB49:BD49) -> 0 | BF49: =0 -> 0 | BJ49: =BK49-BI49-BH49-BG49 -> 0 | BK49: =0 -> 0 | BL49: =0 -> 0 | BM49: =0 -> 0 | BN49: =0 -> 0 | BO49: =0 -> 0 | BP49: =0 -> 0 | BQ49: =0 -> 0 | BR49: =0 -> 0 | BS49: =0 -> 0 | BU49: =+SUM(BQ49:BT49) -> 0 | BV49: =0 -> 0 | BW49: =0 -> 0 | BX49: =0 -> 0 | BY49: =0 -> 0 | BZ49: =+SUM(BV49:BY49) -> 0 | CA49: =0 -> 0 | CB49: =0 -> 0 | CC49: =0 -> 0 | CD49: =0 -> 0 | CE49: =+SUM(CA49:CD49) -> 0
B50: Deferred Income Taxes | H50: 0 | M50: 0 | N50: 0 | O50: 0 | P50: 0 | Q50: 0 | R50: 0 | S50: 0 | T50: 0 | U50: 0 | V50: 0 | W50: 0 | X50: 0 | Y50: 0 | Z50: 0 | AA50: 0 | AB50: 0 | AC50: 0 | AD50: 0 | AE50: 0 | AF50: =+AG50-SUM(AC50:AE50) -> 0 | AG50: 0 | AH50: 0 | AI50: 0 | AJ50: 0 | AK50: =+AL50-SUM(AH50:AJ50) -> 0 | AL50: 0 | AM50: 0 | AN50: 0 | AO50: 0 | AP50: 0 | AQ50: =+SUM(AM50:AP50) -> 0 | AU50: =0-AR50-AS50-AT50 -> 0 | AV50: =+SUM(AR50:AU50) -> 0 | BA50: =+SUM(AW50:AZ50) -> 0 | BE50: =BF50-SUM(BB50:BD50) -> 0 | BF50: =0 -> 0 | BJ50: =BK50-BI50-BH50-BG50 -> 0 | BK50: =0 -> 0 | BL50: =0 -> 0 | BM50: =0 -> 0 | BN50: =0 -> 0 | BO50: =0 -> 0 | BP50: =0 -> 0 | BQ50: =0 -> 0 | BR50: =0 -> 0 | BS50: =0 -> 0 | BU50: =+SUM(BQ50:BT50) -> 0 | BV50: =0 -> 0 | BW50: =0 -> 0 | BX50: =0 -> 0 | BY50: =0 -> 0 | BZ50: =+SUM(BV50:BY50) -> 0 | CA50: =0 -> 0 | CB50: =0 -> 0 | CC50: =0 -> 0 | CD50: =0 -> 0 | CE50: =+SUM(CA50:CD50) -> 0
B51: Repurchase of Common Stock | H51: 0 | M51: 0 | N51: 0 | O51: 0 | P51: 0 | Q51: 0 | R51: 0 | S51: 0 | T51: 0 | U51: 0 | V51: 0 | W51: 0 | X51: 0 | Y51: 0 | Z51: 0 | AA51: 0 | AB51: 0 | AC51: 0 | AD51: 0 | AE51: 0 | AF51: =+AG51-SUM(AC51:AE51) -> 0 | AG51: 0 | AH51: -1481 | AI51: =+-19356-AH51 -> -17875 | AJ51: =+-46542-AI51-AH51 -> -27186 | AK51: =+AL51-SUM(AH51:AJ51) -> -38498 | AL51: -85040 | AM51: -7871 | AN51: -16246 | AO51: -49760 | AP51: -12547 | AQ51: =+SUM(AM51:AP51) -> -86424 | AR51: -28926 | AS51: -25255 | AT51: -37700 | AU51: =-126729-AR51-AS51-AT51 -> -34848 | AV51: =+SUM(AR51:AU51) -> -126729 | AW51: =-31029 -> -31029 | AX51: =-63252-AW51 -> -32223 | AY51: =-94919-AW51-AX51 -> -31667 | AZ51: =BA51-AY51-AX51-AW51 -> -35058 | BA51: =-129977 -> -129977 | BB51: =-46581+2086 -> -44495 | BC51: =-117813+2086-BB51 -> -71232 | BD51: =-212839-BC51-BB51 -> -97112 | BE51: =BF51-SUM(BB51:BD51) -> -100060 | BF51: =-317344+4445 -> -312899 | BG51: =-66551+2988 -> -63563 | BH51: =-108817+2988-BG51 -> -42266 | BI51: =-147725+6077-BH51-BG51 -> -35819 | BJ51: =BK51-BI51-BH51-BG51 -> -23075 | BK51: =-170800+6077 -> -164723 | BL51: =-18029+3608 -> -14421 | BM51: =-53017+3608-BL51 -> -34988 | BN51: =-97188+6872-BM51-BL51 -> -40907 | BO51: =BP51-BN51-BM51-BL51 -> -42687 | BP51: =-139875+6872 -> -133003 | BQ51: =-39653+3817 -> -35836 | BR51: =-89545+3817-BQ51 -> -49892 | BS51: =-138754+6751-SUM(BQ51:BR51) -> -46275 | BT51: =-183425+6751-BS51-BR51-BQ51 -> -44671 | BU51: =+SUM(BQ51:BT51) -> -176674 | BV51: 0 | BW51: 0 | BX51: 0 | BY51: 0 | BZ51: =+SUM(BV51:BY51) -> 0 | CA51: 0 | CB51: 0 | CC51: 0 | CD51: 0 | CE51: =+SUM(CA51:CD51) -> 0
B52: Restructuring Accrual | H52: 0 | M52: 0 | N52: 0 | O52: 0 | P52: 0 | Q52: 0 | R52: 0 | S52: 0 | T52: 0 | U52: 0 | V52: 0 | W52: 0 | X52: 0 | Y52: 0 | Z52: 0 | AA52: 0 | AB52: 0 | AC52: 0 | AD52: 0 | AE52: 0 | AF52: =+AG52-SUM(AC52:AE52) -> 0 | AG52: 0 | AH52: 0 | AI52: 0 | AJ52: 0 | AK52: =+AL52-SUM(AH52:AJ52) -> 0 | AL52: 0 | AM52: 0 | AN52: 0 | AO52: 0 | AP52: 0 | AQ52: =+SUM(AM52:AP52) -> 0 | AV52: =+SUM(AR52:AU52) -> 0 | BA52: =+SUM(AW52:AZ52) -> 0 | BF52: =+SUM(BB52:BE52) -> 0 | BK52: =+SUM(BG52:BJ52) -> 0 | BP52: =+SUM(BL52:BO52) -> 0 | BU52: =+SUM(BQ52:BT52) -> 0 | BZ52: =+SUM(BV52:BY52) -> 0 | CE52: =+SUM(CA52:CD52) -> 0
D53: ______ | E53: ______ | F53: ______ | G53: ______ | H53: ______ | I53: ______ | J53: ______ | K53: ______ | L53: ______ | M53: ______ | N53: ______ | O53: ______ | P53: ______ | Q53: ______ | R53: ______ | S53: ______ | T53: ______ | U53: ______ | V53: ______ | W53: ______ | X53: ______ | Y53: ______ | Z53: ______ | AA53: ______ | AB53: ______ | AC53: ______ | AD53: ______ | AE53: ______ | AF53: ______ | AG53: ______ | AH53: ______ | AI53: ______ | AJ53: ______ | AK53: ______ | AL53: ______ | AM53: ______ | AN53: ______ | AO53: ______ | AP53: ______ | AQ53: ______ | AR53: ______ | AS53: ______ | AT53: ______ | AU53: ______ | AV53: ______ | AW53: ______ | AX53: ______ | AY53: ______ | AZ53: ______ | BA53: ______ | BB53: ______ | BC53: ______ | BD53: ______ | BE53: ______ | BF53: ______ | BG53: ______ | BH53: ______ | BI53: ______ | BJ53: ______ | BK53: ______ | BL53: ______ | BM53: ______ | BN53: ______ | BO53: ______ | BP53: ______ | BQ53: ______ | BR53: ______ | BS53: ______ | BT53: ______ | BU53: ______ | BV53: ______ | BW53: ______ | BX53: ______ | BY53: ______ | BZ53: ______ | CA53: ______ | CB53: ______ | CC53: ______ | CD53: ______ | CE53: ______
B54: Net Cash from Financing Activity | D54: =SUM(D41:D52) -> 0 | E54: =SUM(E41:E52) -> 0 | F54: =SUM(F41:F52) -> 0 | G54: =SUM(G41:G52) -> 0 | H54: =SUM(H41:H52) -> 83202 | I54: =SUM(I41:I52) -> 0 | J54: =SUM(J41:J52) -> 0 | K54: =SUM(K41:K52) -> 0 | ... AY54: =SUM(AY41:AY52) -> -28334 | AZ54: 367 | BA54: =SUM(AW54:AZ54) -> -107888 | BB54: =SUM(BB41:BB52) -> -45557 | BC54: =SUM(BC41:BC52) -> -69258 | BD54: =SUM(BD41:BD52) -> -83271 | BE54: =SUM(BE41:BE52) -> -107945 | BF54: =SUM(BF41:BF52) -> -306031 | BG54: =SUM(BG41:BG52) -> -66340 | BH54: =SUM(BH41:BH52) -> -41835 | BI54: =SUM(BI41:BI52) -> -20087 | ... CE54: =SUM(CE41:CE52) -> 0
B56: Effect of Foreign Exchange Rates on Cash | H56: -33 | M56: -51 | N56: 13 | O56: -43 | P56: -198 | Q56: 180 | R56: -48 | S56: 0 | T56: 0 | U56: 0 | V56: 0 | W56: 0 | X56: 0 | Y56: 0 | Z56: 0 | AA56: 0 | AB56: 0 | AC56: 0 | AD56: =0-AC56 -> 0 | AE56: =0-AD56-AC56 -> 0 | AF56: =+AG56-SUM(AC56:AE56) -> 0 | AG56: 0 | AH56: 0 | AI56: =+-42-AH56 -> -42 | AJ56: =+-42-AI56-AH56 -> 0 | AK56: =+AL56-SUM(AH56:AJ56) -> 42 | AL56: 0 | AM56: 0 | AN56: 0 | AO56: 0 | AP56: 0 | AQ56: =+SUM(AM56:AP56) -> 0 | AR56: 0 | AV56: =+SUM(AR56:AU56) -> 0 | AW56: 0 | BA56: =+SUM(AW56:AZ56) -> 0 | BB56: 0 | BF56: =+SUM(BB56:BE56) -> 0 | BG56: 0 | BK56: =+SUM(BG56:BJ56) -> 0 | BL56: 0 | BP56: =+SUM(BL56:BO56) -> 0 | BQ56: 0 | BU56: =+SUM(BQ56:BT56) -> 0 | BV56: 0 | BZ56: =+SUM(BV56:BY56) -> 0 | CA56: 0 | CE56: =+SUM(CA56:CD56) -> 0
D57: ______ | E57: ______ | F57: ______ | G57: ______ | H57: ______ | I57: ______ | J57: ______ | K57: ______ | L57: ______ | M57: ______ | N57: ______ | O57: ______ | P57: ______ | Q57: ______ | R57: ______ | S57: ______ | T57: ______ | U57: ______ | V57: ______ | W57: ______ | X57: ______ | Y57: ______ | Z57: ______ | AA57: ______ | AB57: ______ | AC57: ______ | AD57: ______ | AE57: ______ | AF57: ______ | AG57: ______ | AH57: ______ | AI57: ______ | AJ57: ______ | AK57: ______ | AL57: ______ | AM57: ______ | AN57: ______ | AO57: ______ | AP57: ______ | AQ57: ______ | AR57: ______ | AS57: ______ | AT57: ______ | AU57: ______ | AV57: ______ | AW57: ______ | AX57: ______ | AY57: ______ | AZ57: ______ | BA57: ______ | BB57: ______ | BC57: ______ | BD57: ______ | BE57: ______ | BF57: ______ | BG57: ______ | BH57: ______ | BI57: ______ | BJ57: ______ | BK57: ______ | BL57: ______ | BM57: ______ | BN57: ______ | BO57: ______ | BP57: ______ | BQ57: ______ | BR57: ______ | BS57: ______ | BT57: ______ | BU57: ______ | BV57: ______ | BW57: ______ | BX57: ______ | BY57: ______ | BZ57: ______ | CA57: ______ | CB57: ______ | CC57: ______ | CD57: ______ | CE57: ______
B58: Net Increase (Decrease) in Cash & Equivalents | D58: =SUM(D54:D56)+D38+D27 -> 0 | E58: =SUM(E54:E56)+E38+E27 -> 0 | F58: =SUM(F54:F56)+F38+F27 -> 0 | G58: =SUM(G54:G56)+G38+G27 -> 0 | H58: =SUM(H54:H56)+H38+H27 -> 10337 | I58: =SUM(I54:I56)+I38+I27 -> 0 | J58: =SUM(J54:J56)+J38+J27 -> 0 | K58: =SUM(K54:K56)+K38+K27 -> 0 | ... AZ58: =SUM(AZ54:AZ56)+AZ38+AZ27 -> -8412 | BA58: =63196 -> 63196 | BB58: =SUM(BB54:BB56)+BB38+BB27 -> 28959 | BC58: =SUM(BC54:BC56)+BC38+BC27 -> -45322 | BD58: =SUM(BD54:BD56)+BD38+BD27 -> 72937 | BE58: =SUM(BE54:BE56)+BE38+BE27 -> -18683 | BF58: =SUM(BF54:BF56)+BF38+BF27 -> 37891 | BG58: =SUM(BG54:BG56)+BG38+BG27 -> 20135 | BH58: =SUM(BH54:BH56)+BH38+BH27 -> -7709 | BI58: =SUM(BI54:BI56)+BI38+BI27 -> 22579 | ... CE58: =SUM(CE54:CE56)+CE38+CE27 -> 325173.07
B60: Cash and Equivalents at Beginning of Period | H60: 24548 | M60: =+H61 -> 34885 | N60: =+M61 -> 42369 | O60: =+N61 -> 48296 | P60: =+O61 -> 41672 | Q60: =+P61 -> 88285 | R60: =+M61 -> 42369 | S60: =+Q61 -> 76504 | T60: =+S61 -> 78018 | U60: =+T61 -> 84058 | V60: =+U61 -> 94763 | W60: =+R61 -> 76504 | X60: =+V61 -> 91698 | Y60: =+X61 -> 112471 | Z60: =+Y61 -> 118194 | AA60: =+Z61 -> 98299 | AB60: =+W61 -> 91698 | AC60: =+AA61 -> 86737 | AD60: =+AC61 -> 109651 | AE60: =+AD61 -> 130572 | AF60: =+AE61 -> 90517 | AG60: 87937 | AH60: =+AF61 -> 87791 | AI60: =+AH61 -> 94374 | AJ60: =+AI61 -> 87979 | AK60: =+AJ61 -> 99164 | AL60: =+AG61 -> 87791 | AM60: =+AK61 -> 42226 | AN60: =+AM61 -> 94327 | AO60: =+AN61 -> 92581 | AP60: =+AO61 -> 76815 | AQ60: =+AL61 -> 42226 | AR60: =+AP61 -> 88759 | AS60: =+AR61 -> 148765 | AT60: =+AS61 -> 115110 | AU60: =+AT61 -> 94227 | AV60: =+AQ61 -> 88759 | AW60: =+AU61 -> 75332 | AX60: =+AW61 -> 109953 | AY60: =+AX61 -> 98478 | AZ60: =+AY61 -> 146940 | BA60: =+AV61 -> 75332 | BB60: =+AZ61 -> 138528 | BC60: =+BB61 -> 167487 | BD60: =+BC61 -> 122165 | BE60: =+BD61 -> 195102 | BF60: =+BA61 -> 138528 | BG60: =+BE61 -> 176419 | BH60: =+BG61 -> 196554 | BI60: =+BH61 -> 188845 | BJ60: =+BI61 -> 211424 | BK60: =+BF61 -> 176419 | BL60: =+BJ61 -> 206365 | BM60: =+BL61 -> 274983 | BN60: =+BM61 -> 282405 | BO60: =+BN61 -> 236630 | BP60: =+BK61 -> 206365 | BQ60: =+BO61 -> 233382 | BR60: =+BQ61 -> 291871 | BS60: =+BR61 -> 195183 | BT60: =+BS61 -> 226453 | BU60: =+BP61 -> 233382 | BV60: =+BT61 -> 251458 | BW60: =+BV61 -> 359729.96 | BX60: =+BW61 -> 400997.09 | BY60: =+BX61 -> 487609.74 | BZ60: =+BU61 -> 251458 | CA60: =+BY61 -> 549144.83 | CB60: =+CA61 -> 666827.82 | CC60: =+CB61 -> 699696.94 | CD60: =+CC61 -> 807758.35 | CE60: =+BZ61 -> 549144.83
B61: Cash and Equivalents at End of Period | H61: =+H60+H58 -> 34885 | M61: =+M60+M58 -> 42369 | N61: =+N60+N58 -> 48296 | O61: =+O60+O58 -> 41672 | P61: =+P60+P58 -> 88285 | Q61: =+Q60+Q58 -> 76504 | R61: =+R60+R58 -> 76504 | S61: =+S60+S58 -> 78018 | T61: =+T60+T58 -> 84058 | ... AE61: =+AE60+AE58 -> 90517 | AF61: 87791 | AG61: =+AG60+AG58 -> 87791 | AH61: =+AH60+AH58 -> 94374 | AI61: =+AI60+AI58 -> 87979 | AJ61: =+AJ60+AJ58 -> 99164 | AK61: =+AK60+AK58 -> 42226 | AL61: =+AL60+AL58 -> 42226 | AM61: =+AM60+AM58 -> 94327 | AN61: =+AN60+AN58 -> 92581 | ... CE61: =+CE60+CE58 -> 874317.89
B63: Free Cash Flow
B64: Cash from Operations | H64: =+H27 -> 21952 | M64: =+M27 -> 25146 | N64: =+N27 -> 15075 | O64: =+O27 -> 100 | P64: =+P27 -> 9910 | Q64: =+Q27 -> 16338 | R64: =+R27 -> 41423 | S64: =+S27 -> 10026 | T64: =+T27 -> 15524 | ... CE64: =+CE27 -> 332866.52
B65: Capital Expenditures | H65: =+H32 -> -11188 | M65: =+M32 -> -13663 | N65: =+N32 -> -3778 | O65: =+O32 -> -2717 | P65: =+P32 -> -3757 | Q65: =+Q32 -> -3662 | R65: =+R32 -> -13914 | S65: =+S32 -> -6148 | T65: =+T32 -> -4259 | ... CE65: =+CE32 -> -7693.4508
B66: Principal Payments Under Capital Lease Obligations | H66: =+H47 -> -2401 | M66: =+M47 -> -1186 | N66: =+N47 -> -267 | O66: =+O47 -> -269 | P66: =+P47 -> -269 | Q66: =+Q47 -> 0 | R66: =+R47 -> -805 | S66: =+S47 -> 0 | T66: =+T47 -> 0 | ... CE66: =+CE47 -> 0
D67: ______ | E67: ______ | F67: ______ | G67: ______ | H67: ______ | I67: ______ | J67: ______ | K67: ______ | L67: ______ | M67: ______ | N67: ______ | O67: ______ | P67: ______ | Q67: ______ | R67: ______ | S67: ______ | T67: ______ | U67: ______ | V67: ______ | W67: ______ | X67: ______ | Y67: ______ | Z67: ______ | AA67: ______ | AB67: ______ | AC67: ______ | AD67: ______ | AE67: ______ | AF67: ______ | AG67: ______ | AH67: ______ | AI67: ______ | AJ67: ______ | AK67: ______ | AL67: ______ | AM67: ______ | AN67: ______ | AO67: ______ | AP67: ______ | AQ67: ______ | AR67: ______ | AS67: ______ | AT67: ______ | AU67: ______ | AV67: ______ | AW67: ______ | AX67: ______ | AY67: ______ | AZ67: ______ | BA67: ______ | BB67: ______ | BC67: ______ | BD67: ______ | BE67: ______ | BF67: ______ | BG67: ______ | BH67: ______ | BI67: ______ | BJ67: ______ | BK67: ______ | BL67: ______ | BM67: ______ | BN67: ______ | BO67: ______ | BP67: ______ | BQ67: ______ | BR67: ______ | BS67: ______ | BT67: ______ | BU67: ______ | BV67: ______ | BW67: ______ | BX67: ______ | BY67: ______ | BZ67: ______ | CA67: ______ | CB67: ______ | CC67: ______ | CD67: ______ | CE67: ______
B68: Free Cash Flow | D68: =D64+D65+D66 -> 0 | E68: =E64+E65+E66 -> 0 | F68: =F64+F65+F66 -> 0 | G68: =G64+G65+G66 -> 0 | H68: =H64+H65+H66 -> 8363 | I68: =I64+I65+I66 -> 0 | J68: =J64+J65+J66 -> 0 | K68: =K64+K65+K66 -> 0 | ... CE68: =CE64+CE65+CE66 -> 325173.07
B69: Yr-Yr Growth | M69: =+M68/H68-1 -> 0.23125673 | R69: =+R68/M68-1 -> 1.5933767 | S69: =+S68/N68-1 -> -0.64841342 | T69: =+T68/O68-1 -> -4.9033264 | U69: =+U68/P68-1 -> 0.98164514 | V69: =+V68/Q68-1 -> 0.50725781 | W69: =+W68/R68-1 -> 0.71918065 | X69: =+X68/S68-1 -> 2.3411552 | Y69: =+Y68/T68-1 -> 0.11300488 | ... CE69: =+CE68/BZ68-1 -> 0.092332732
B70: Q-Q Growth | O70: =+O68/N68-1 -> -1.26165 | P70: =+P68/O68-1 -> -3.038808 | Q70: =+Q68/P68-1 -> 1.1543168 | S70: =+S68/Q68-1 -> -0.69406753 | T70: =+T68/S68-1 -> 1.9048479 | U70: =+U68/T68-1 -> 0.035064359 | V70: =+V68/U68-1 -> 0.63859348 | X70: =+X68/V68-1 -> -0.32183607 | Y70: =+Y68/X68-1 -> -0.032337732 | Z70: =+Z68/Y68-1 -> -0.17052161 | AA70: =+AA68/Z68-1 -> -0.1375 | AC70: =+AC68/AA68-1 -> 2.1083612 | AD70: =+AD68/AC68-1 -> -0.71734452 | AE70: =+AE68/AD68-1 -> 1.4621241 | AF70: =+AF68/AE68-1 -> -0.24443414 | AH70: =+AH68/AF68-1 -> 1.4730237 | AI70: =+AI68/AH68-1 -> -0.5328902 | AJ70: =+AJ68/AI68-1 -> 0.47189419 | AK70: =+AK68/AJ68-1 -> -0.079268293 | AM70: =+AM68/AK68-1 -> 0.53886372 | AN70: =+AN68/AM68-1 -> -0.12284824 | AO70: =+AO68/AN68-1 -> 0.28795068 | AP70: =+AP68/AO68-1 -> -0.3704075 | AR70: =+AR68/AP68-1 -> 0.79659263 | AS70: =+AS68/AR68-1 -> -0.44861967 | AT70: =+AT68/AS68-1 -> 0.94659648 | AU70: =+AU68/AT68-1 -> -0.35032925 | AW70: =+AW68/AU68-1 -> 0.63939375 | AX70: =+AX68/AW68-1 -> -0.076577188 | AY70: =+AY68/AX68-1 -> -0.13267148 | AZ70: =+AZ68/AY68-1 -> -0.13994628 | BB70: =+BB68/AZ68-1 -> 1.0090321 | BC70: =+BC68/BB68-1 -> -0.5756362 | BD70: =+BD68/BC68-1 -> 0.35042904 | BE70: =+BE68/BD68-1 -> -0.0010753214 | BG70: =+BG68/BE68-1 -> 0.53584186 | BH70: =+BH68/BG68-1 -> -0.20197209 | BI70: =+BI68/BH68-1 -> 0.80909036 | BJ70: =+BJ68/BI68-1 -> -0.64342933 | BL70: =+BL68/BJ68-1 -> 1.5824359 | BM70: =+BM68/BL68-1 -> -0.41527069 | BN70: =+BN68/BM68-1 -> 0.18084758 | BO70: =+BO68/BN68-1 -> -0.27312011 | BQ70: =+BQ68/BO68-1 -> 1.567745 | BR70: =+BR68/BQ68-1 -> -0.69833566 | BS70: =+BS68/BR68-1 -> 1.7580138 | BT70: =+BT68/BS68-1 -> -0.16255965 | BV70: =+BV68/BT68-1 -> 0.44487843 | BW70: =+BW68/BV68-1 -> -0.61885677 | BX70: =+BX68/BW68-1 -> 1.0988293 | BY70: =+BY68/BX68-1 -> -0.28953703 | CA70: =+CA68/BY68-1 -> 0.91245356 | CB70: =+CB68/CA68-1 -> -0.72069775 | CC70: =+CC68/CB68-1 -> 2.2876267 | CD70: =+CD68/CC68-1 -> -0.38405816
B71: Free Cash Flow Margin | H71: =+H68/H77 -> 0.091478889 | M71: =+M68/M77 -> 0.095376151 | N71: =+N68/N77 -> 0.36335486 | O71: =+O68/O77 -> -0.089344313 | P71: =+P68/P77 -> 0.17130546 | Q71: =+Q68/Q77 -> 0.34659448 | R71: =+R68/R77 -> 0.19991166 | S71: =+S68/S77 -> 0.10343264 | T71: =+T68/T77 -> 0.28249367 | ... CE71: =+CE68/CE77 -> 0.42266218
B72: Rule of 40 | BB72: =BB71+BB78 -> 0.80175447 | BC72: =BC71+BC78 -> 0.45523884 | BD72: =BD71+BD78 -> 0.52245262 | BE72: =BE71+BE78 -> 0.50429554 | BF72: =BF71+BF78 -> 0.56572903 | BG72: =BG71+BG78 -> 0.63257272 | BH72: =BH71+BH78 -> 0.50954332 | BI72: =BI71+BI78 -> 0.76914997 | ... CE72: =CE71+CE78 -> 0.48993368
B73: Source: Qualys, Inc. Financial Statements, Needham & Co. LLC estimates
B76: I/S
B77: Revenue | D77: =+IS!D9 -> 21191 | E77: =+IS!E9 -> 22190 | F77: =+IS!F9 -> 23382 | G77: =+IS!G9 -> 24657 | H77: =+IS!H9 -> 91420 | I77: =+IS!I9 -> 24883 | J77: =+IS!J9 -> 26291 | K77: =+IS!K9 -> 27749 | ... CE77: =+IS!CE9 -> 769345.08
B78: Yr-Yr Growth | I78: =+I77/D77-1 -> 0.17422491 | J78: =+J77/E77-1 -> 0.18481298 | K78: =+K77/F77-1 -> 0.1867676 | L78: =+L77/G77-1 -> 0.1777183 | M78: =+M77/H77-1 -> 0.18094509 | N78: =+N77/I77-1 -> 0.21994936 | O78: =+O77/J77-1 -> 0.22863337 | P78: =+P77/K77-1 -> 0.23781037 | ... CE78: =+CE77/BZ77-1 -> 0.067271501
B79: Q-Q Growth | E79: =+E77/D77-1 -> 0.047142655 | F79: =+F77/E77-1 -> 0.053717891 | G79: =+G77/F77-1 -> 0.054529125 | I79: =+I77/G77-1 -> 0.0091657541 | J79: =+J77/I77-1 -> 0.056584817 | K79: =+K77/J77-1 -> 0.05545624 | L79: =+L77/K77-1 -> 0.046488162 | N79: =+N77/L77-1 -> 0.045352801 | O79: =+O77/N77-1 -> 0.064105943 | P79: =+P77/O77-1 -> 0.063339731 | Q79: =+Q77/P77-1 -> 0.064778153 | S79: =+S77/Q77-1 -> 0.025155169 | T79: =+T77/S77-1 -> 0.063585203 | U79: =+U77/T77-1 -> 0.064999875 | V79: =+V77/U77-1 -> 0.046528056 | X79: =+X77/V77-1 -> 0.040566993 | Y79: =+Y77/X77-1 -> 0.047958831 | Z79: =+Z77/Y77-1 -> 0.052015846 | AA79: =+AA77/Z77-1 -> 0.024261086 | AC79: =+AC77/AA77-1 -> 0.017176011 | AD79: =+AD77/AC77-1 -> 0.041057209 | AE79: =+AE77/AD77-1 -> 0.07572963 | AF79: =+AF77/AE77-1 -> 0.057572701 | AH79: =+AH77/AF77-1 -> 0.031200827 | AI79: =+AI77/AH77-1 -> 0.050479361 | AJ79: =+AJ77/AI77-1 -> 0.051428404 | AK79: =+AK77/AJ77-1 -> 0.035474057 | AM79: =+AM77/AK77-1 -> 0.015404313 | AN79: =+AN77/AM77-1 -> 0.047595663 | AO79: =+AO77/AN77-1 -> 0.047409697 | AP79: =+AP77/AO77-1 -> 0.024107607 | AR79: =+AR77/AP77-1 -> 0.018886422 | AS79: =+AS77/AR77-1 -> 0.029757834 | AT79: =+AT77/AS77-1 -> 0.047720365 | AU79: =+AU77/AT77-1 -> 0.018609849 | AW79: =+AW77/AU77-1 -> 0.020622145 | AX79: =+AX77/AW77-1 -> 0.030447724 | AY79: =+AY77/AX77-1 -> 0.05247638 | AZ79: =+AZ77/AY77-1 -> 0.046181409 | BB79: =+BB77/AZ77-1 -> 0.033157224 | BC79: =+BC77/BB77-1 -> 0.057071063 | BD79: =+BD77/BC77-1 -> 0.047275487 | BE79: =+BE77/BD77-1 -> 0.042114988 | BG79: =+BG77/BE77-1 -> -0.0012686379 | BH79: =+BH77/BG77-1 -> 0.049937635 | BI79: =+BI77/BH77-1 -> 0.034888382 | BJ79: =+BJ77/BI77-1 -> 0.018127271 | BL79: =+BL77/BJ77-1 -> 0.0085425745 | BM79: =+BM77/BL77-1 -> 0.019910154 | BN79: =+BN77/BM77-1 -> 0.034692148 | BO79: =+BO77/BN77-1 -> 0.034601312 | BQ79: =+BQ77/BO77-1 -> 0.0044474876 | BR79: =+BR77/BQ77-1 -> 0.026035185 | BS79: =+BS77/BR77-1 -> 0.035474394 | BT79: =+BT77/BS77-1 -> 0.03178677 | BV79: =+BV77/BT77-1 -> -0.010221158 | BW79: =+BW77/BV77-1 -> 0.021306912 | BX79: =+BX77/BW77-1 -> 0.030680531 | BY79: =+BY77/BX77-1 -> 0.026987761 | CA79: =+CA77/BY77-1 -> -0.00097088835 | CB79: =+CB77/CA77-1 -> 0.011850366 | CC79: =+CC77/CB77-1 -> 0.021048003 | CD79: =+CD77/CC77-1 -> 0.026987761
B81: Adjusted EBITDA | D81: =+'Billings & Recs'!D94 -> 2296 | E81: =+'Billings & Recs'!E94 -> 2462 | F81: =+'Billings & Recs'!F94 -> 4599 | G81: =+'Billings & Recs'!G94 -> 4441 | H81: =+'Billings & Recs'!H94 -> 13798 | I81: =+'Billings & Recs'!I94 -> 2795 | J81: =+'Billings & Recs'!J94 -> 4475 | K81: =+'Billings & Recs'!K94 -> 3302 | ... CE81: =+'Billings & Recs'!CE94 -> 341564.34
B82: Yr-Yr Growth | I82: =+I81/D81-1 -> 0.21733449 | J82: =+J81/E81-1 -> 0.81762794 | K82: =+K81/F81-1 -> -0.28201783 | L82: =+L81/G81-1 -> 0.54357127 | M82: =+M81/H81-1 -> 0.26300913 | N82: =+N81/I81-1 -> 0.67084079 | O82: =+O81/J81-1 -> 0.61944134 | P82: =+P81/K81-1 -> 1.7392489 | ... CE82: =+CE81/BZ81-1 -> 0.090815246
B83: Q-Q Growth | E83: =+E81/D81-1 -> 0.072299652 | F83: =+F81/E81-1 -> 0.8679935 | G83: =+G81/F81-1 -> -0.034355295 | I83: =+I81/G81-1 -> -0.37063724 | J83: =+J81/I81-1 -> 0.60107335 | K83: =+K81/J81-1 -> -0.26212291 | L83: =+L81/K81-1 -> 1.0760145 | N83: =+N81/L81-1 -> -0.31874544 | O83: =+O81/N81-1 -> 0.55182013 | P83: =+P81/O81-1 -> 0.24810266 | Q83: =+Q81/P81-1 -> 0.18640133 | S83: =+S81/Q81-1 -> 0.1161122 | T83: =+T81/S81-1 -> 0.093596059 | U83: =+U81/T81-1 -> 0.15567262 | V83: =+V81/U81-1 -> 0.086608971 | X83: =+X81/V81-1 -> -0.019455253 | Y83: =+Y81/X81-1 -> -0.023809524 | Z83: =+Z81/Y81-1 -> 0.1195376 | AA83: =+AA81/Z81-1 -> 0.047770339 | AC83: =+AC81/AA81-1 -> -0.089885207 | AD83: =+AD81/AC81-1 -> 0.21483817 | AE83: =+AE81/AD81-1 -> 0.16866644 | AF83: =+AF81/AE81-1 -> -0.00088002347 | AH83: =+AH81/AF81-1 -> 0.032547605 | AI83: =+AI81/AH81-1 -> 0.085953367 | AJ83: =+AJ81/AI81-1 -> 0.19278821 | AK83: =+AK81/AJ81-1 -> -0.086145258 | AM83: =+AM81/AK81-1 -> 0.050924814 | AN83: =+AN81/AM81-1 -> 0.089828571 | AO83: =+AO81/AN81-1 -> 0.15678931 | AP83: =+AP81/AO81-1 -> -0.026807221 | AR83: =+AR81/AP81-1 -> 0.015995103 | AS83: =+AS81/AR81-1 -> 0.122148 | AT83: =+AT81/AS81-1 -> 0.053597273 | AU83: =+AU81/AT81-1 -> -0.038729118 | AW83: =+AW81/AU81-1 -> 0.027405154 | AX83: =+AX81/AW81-1 -> 0.047807067 | AY83: =+AY81/AX81-1 -> 0.07744187 | AZ83: =+AZ81/AY81-1 -> -0.015261411 | BB83: =+BB81/AZ81-1 -> 0.09498537 | BC83: =+BC81/BB81-1 -> 0.0022483506 | BD83: =+BD81/BC81-1 -> 0.0087157988 | BE83: =+BE81/BD81-1 -> 0.0039374385 | BG83: =+BG81/BE81-1 -> 0.065021607 | BH83: =+BH81/BG81-1 -> 0.12239366 | BI83: =+BI81/BH81-1 -> 0.045219795 | BJ83: =+BJ81/BI81-1 -> -0.043190769 | BL83: =+BL81/BJ81-1 -> 0.048481903 | BM83: =+BM81/BL81-1 -> 0.01308108 | BN83: =+BN81/BM81-1 -> -0.0036033975 | BO83: =+BO81/BN81-1 -> 0.06476565 | BQ83: =+BQ81/BO81-1 -> 0.0075072444 | BR83: =+BR81/BQ81-1 -> -0.017671768 | BS83: =+BS81/BR81-1 -> 0.12486552 | BT83: =+BT81/BS81-1 -> 0.00031476998 | BV83: =+BV81/BT81-1 -> -0.049722138 | BW83: =+BW81/BV81-1 -> -0.013656012 | BX83: =+BX81/BW81-1 -> 0.014358991 | BY83: =+BY81/BX81-1 -> 0.00063116816 | CA83: =+CA81/BY81-1 -> 0.042471706 | CB83: =+CB81/CA81-1 -> 0.018246128 | CC83: =+CC81/CB81-1 -> 0.030834732 | CD83: =+CD81/CC81-1 -> 0.048254535
B85: FCF Variance vs EBITDA | BB85: =BB68-BB81 -> 17139 | BC85: =BC68-BC81 -> -24084 | BD85: =BD68-BD81 -> -13940 | BE85: =BE68-BE81 -> -14200 | BF85: =BF68-BF81 -> -35084 | BG85: =BG68-BG81 -> 4121 | BH85: =BH68-BH81 -> -15737 | BI85: =BI68-BI81 -> 21819 | ... CE85: =CE68-CE81 -> -16391.272
B87: EBITDA Margin | BB87: =IS!BB66 -> 0.47841651 | BC87: =IS!BC66 -> 0.45360446 | BD87: =IS!BD66 -> 0.43690318 | BE87: =IS!BE66 -> 0.42089737 | BF87: =IS!BF66 -> 0.44632782 | BG87: =IS!BG66 -> 0.4488342 | BH87: =IS!BH66 -> 0.47980818 | BI87: =IS!BI66 -> 0.48459816 | ... CE87: =IS!CE66 -> 0.44396766
B88: Variance vs FCF | BB88: =BB71-BB87 -> 0.15111092 | BC88: =BC71-BC87 -> -0.20087912 | BD88: =BD71-BD87 -> -0.11102173 | BE88: =BE71-BE87 -> -0.10852204 | BF88: =BF71-BF87 -> -0.071640499 | BG88: =BG71-BG87 -> 0.031534324 | BH88: =BH71-BH87 -> -0.11469364 | BI88: =BI71-BI87 -> 0.15365926 | ... CE88: =CE71-CE87 -> -0.021305487
B90: Operating Income | BB90: =IS!BB41 -> 46986 | BC90: =IS!BC41 -> 47287 | BD90: =IS!BD41 -> 47983 | BE90: =IS!BE41 -> 47385 | BF90: =IS!BF41 -> 189641 | BG90: =IS!BG41 -> 51983 | BH90: =IS!BH41 -> 59604 | BI90: =IS!BI41 -> 62889 | ... CE90: =IS!CE41 -> 330439.69
B91: Variance vs FCF | BB91: =BB68-BB90 -> 24415 | BC91: =BC68-BC90 -> -16987 | BD91: =BD68-BD90 -> -7065 | BE91: =BE68-BE90 -> -6511 | BF91: =BF68-BF90 -> -6148 | BG91: =BG68-BG90 -> 10793 | BH91: =BH68-BH90 -> -9507 | BI91: =BI68-BI90 -> 27741 | ... CE91: =CE68-CE90 -> -5266.6279
B93: Operating Margin | BB93: =IS!BB42 -> 0.41426556 | BC93: =IS!BC42 -> 0.39441002 | BD93: =IS!BD42 -> 0.38214892 | BE93: =IS!BE42 -> 0.36213498 | BF93: =IS!BF42 -> 0.38724136 | BG93: =IS!BG42 -> 0.39777936 | BH93: =IS!BH42 -> 0.43440299 | BI93: =IS!BI42 -> 0.44289276 | ... CE93: =IS!CE42 -> 0.42950778
B94: Variance vs FCF | BB94: =BB71-BB93 -> 0.21526186 | BC94: =BC71-BC93 -> -0.14168467 | BD94: =BD71-BD93 -> -0.056267472 | BE94: =BE71-BE93 -> -0.049759647 | BF94: =BF71-BF93 -> -0.012554036 | BG94: =BG71-BG93 -> 0.082589166 | BH94: =BH71-BH93 -> -0.069288458 | BI94: =BI71-BI93 -> 0.19536466 | ... CE94: =CE71-CE93 -> -0.006845599

Sheet IS
B3: Qualys, Inc.—Quarterly Income Statement
B4: (Thousands Of Dollars, Except Per-Share Data)
D5: 2012A | H5: Year | I5: 2013A | M5: Year | N5: 2014A | R5: Year | S5: 2015A | W5: Year | X5: 2016A | AB5: Year | AC5: 2017A | AG5: Year | AH5: 2018A | AL5: Year | AM5: 2019A | AQ5: Year | AR5: 2020A | AV5: Year | AW5: 2021A | BA5: Year | BB5: 2022A | BF5: Year | BG5: 2023A | BK5: Year | BL5: 2024A | BP5: Year | BQ5: 2025A | BU5: Year | BV5: 2026E | BZ5: Year | CA5: 2027E | CE5: Year
D6: 1Q-Mar 12A | E6: 2Q-Jun 12A | F6: 3Q-Sep 12A | G6: 4Q-Dec 12A | H6: 2012A | I6: 1Q-Mar 13A | J6: 2Q-Jun 13A | K6: 3Q-Sep 13A | L6: 4Q-Dec 13A | M6: 2013A | N6: 1Q-Mar 14A | O6: 2Q-Jun 14A | P6: 3Q-Sep 14A | Q6: 4Q-Dec 14A | R6: 2014A | S6: 1Q-Mar 15A | T6: 2Q-Jun 15A | U6: 3Q-Sep 15A | V6: 4Q-Dec 15A | W6: 2015A | X6: 1Q-Mar 16A | Y6: 2Q-Jun 16A | Z6: 3Q-Sep 16A | AA6: 4Q-Dec 16A | AB6: 2016A | AC6: 1Q-Mar 17A | AD6: 2Q-Jun 17A | AE6: 3Q-Sep 17A | AF6: 4Q-Dec 17A | AG6: 2017A | AH6: 1Q-Mar 18A | AI6: 2Q-Jun 18A | AJ6: 3Q-Sep 18A | AK6: 4Q-Dec 18A | AL6: 2018A | AM6: 1Q-Mar 19A | AN6: 2Q-Jun 19A | AO6: 3Q-Sep 19A | AP6: 4Q-Dec 19A | AQ6: 2019A | AR6: 1Q-Mar 20A | AS6: 2Q-Jun 20A | AT6: 3Q-Sep 20A | AU6: 4Q-Dec 20A | AV6: 2020A | AW6: 1Q-Mar 21A | AX6: 2Q-Jun 21A | AY6: 3Q-Sep 21A | AZ6: 4Q-Dec 21A | BA6: 2021A | BB6: 1Q-Mar 22A | BC6: 2Q-Jun 22A | BD6: 3Q-Sep 22A | BE6: 4Q-Dec 22A | BF6: 2022A | BG6: 1Q-Mar 23A | BH6: 2Q-Jun 23A | BI6: 3Q-Sep 23A | BJ6: 4Q-Dec 23A | BK6: 2023A | BL6: 1Q-Mar 24A | BM6: 2Q-Jun 24A | BN6: 3Q-Sep 24A | BO6: 4Q-Dec 24A | BP6: 2024A | BQ6: 1Q-Mar 25A | BR6: 2Q-Jun 25A | BS6: 3Q-Sep 25A | BT6: 4Q-Dec 25A | BU6: 2025A | BV6: 1Q-Mar 26E | BW6: 2Q-Jun 26E | BX6: 3Q-Sep 26E | BY6: 4Q-Dec 26E | BZ6: 2026E | CA6: 1Q-Mar 27E | CB6: 2Q-Jun 27E | CC6: 3Q-Sep 27E | CD6: 4Q-Dec 27E | CE6: 2027E
